{
  "type": "Feature",
  "properties": {
    "gn:admin1_code": "30.0",
    "gn:asciiname": "Danzhukeng",
    "gn:country_code": "CN",
    "gn:dem": 529,
    "gn:feature_class": "P",
    "gn:feature_code": "PPL",
    "gn:name": "Danzhukeng",
    "gn:population": 0,
    "gn:timezone": "Asia/Shanghai",
    "iso:country": "CN",
    "name:zho_x_preferred": [
      "丹竹坑"
    ],
    "wof:name": "Danzhukeng",
    "wof:placetype": "locality"
  },
  "geometry": {
    "coordinates": [
      116.22861,
      24.11552
    ],
    "type": "Point"
  }
}