{
  "type": "Feature",
  "properties": {
    "gn:admin1_code": "1.0",
    "gn:asciiname": "Zhouloucun",
    "gn:country_code": "CN",
    "gn:dem": 16,
    "gn:feature_class": "P",
    "gn:feature_code": "PPL",
    "gn:name": "Zhouloucun",
    "gn:population": 0,
    "gn:timezone": "Asia/Shanghai",
    "iso:country": "CN",
    "name:zho_x_preferred": [
      "周楼村"
    ],
    "wof:name": "Zhouloucun",
    "wof:placetype": "locality"
  },
  "geometry": {
    "coordinates": [
      116.9245,
      31.56891
    ],
    "type": "Point"
  }
}