{
  "type": "Feature",
  "properties": {
    "gn:admin1_code": "29.0",
    "gn:asciiname": "Shitouzhai",
    "gn:country_code": "CN",
    "gn:dem": 1722,
    "gn:feature_class": "P",
    "gn:feature_code": "PPL",
    "gn:name": "Shitouzhai",
    "gn:population": 0,
    "gn:timezone": "Asia/Shanghai",
    "iso:country": "CN",
    "name:zho_x_preferred": [
      "石头寨"
    ],
    "wof:name": "Shitouzhai",
    "wof:placetype": "locality"
  },
  "geometry": {
    "coordinates": [
      99.112,
      24.651
    ],
    "type": "Point"
  }
}