{
  "type": "Feature",
  "properties": {
    "gn:admin1_code": "5.0",
    "gn:asciiname": "Shuili",
    "gn:country_code": "CN",
    "gn:dem": 109,
    "gn:feature_class": "P",
    "gn:feature_code": "PPL",
    "gn:name": "Shuili",
    "gn:population": 0,
    "gn:timezone": "Asia/Shanghai",
    "iso:country": "CN",
    "name:deu_x_preferred": [
      "Shuili"
    ],
    "name:hak_x_preferred": [
      "Súi-lî-hiông"
    ],
    "name:jpn_x_preferred": [
      "水里郷"
    ],
    "name:kor_x_preferred": [
      "수이리향"
    ],
    "name:pol_x_preferred": [
      "Shuili"
    ],
    "name:und_x_variant": [
      "水礼"
    ],
    "name:vie_x_preferred": [
      "Thủy Lý"
    ],
    "name:zho_x_preferred": [
      "水里鄉"
    ],
    "wof:name": "Shuili",
    "wof:placetype": "locality"
  },
  "geometry": {
    "coordinates": [
      129.73391999999998,
      43.01214
    ],
    "type": "Point"
  }
}