{
  "type": "Feature",
  "properties": {
    "gn:admin1_code": "1.0",
    "gn:asciiname": "Yucun",
    "gn:country_code": "CN",
    "gn:dem": 160,
    "gn:feature_class": "P",
    "gn:feature_code": "PPL",
    "gn:name": "Yucun",
    "gn:population": 0,
    "gn:timezone": "Asia/Shanghai",
    "iso:country": "CN",
    "name:und_x_variant": [
      "Yü-ts’un",
      "Yucun",
      "Yucun Xiang",
      "榆村乡"
    ],
    "name:zho_x_preferred": [
      "榆村"
    ],
    "wof:name": "Yucun",
    "wof:placetype": "locality"
  },
  "geometry": {
    "coordinates": [
      118.35658,
      29.66054
    ],
    "type": "Point"
  }
}