{
  "type": "Feature",
  "properties": {
    "gn:admin1_code": "26.0",
    "gn:asciiname": "Majiayao",
    "gn:country_code": "CN",
    "gn:dem": 1092,
    "gn:feature_class": "P",
    "gn:feature_code": "PPL",
    "gn:name": "Majiayao",
    "gn:population": 0,
    "gn:timezone": "Asia/Shanghai",
    "iso:country": "CN",
    "name:zho_x_preferred": [
      "马家窑"
    ],
    "wof:name": "Majiayao",
    "wof:placetype": "locality"
  },
  "geometry": {
    "coordinates": [
      110.213,
      36.6714
    ],
    "type": "Point"
  }
}