{
  "type": "Feature",
  "properties": {
    "gn:admin1_code": "1.0",
    "gn:asciiname": "Yuanping",
    "gn:country_code": "CN",
    "gn:dem": 237,
    "gn:feature_class": "P",
    "gn:feature_code": "PPL",
    "gn:name": "Yuanping",
    "gn:population": 0,
    "gn:timezone": "Asia/Shanghai",
    "iso:country": "CN",
    "name:ara_x_preferred": [
      "مدينة يوانبينج"
    ],
    "name:ceb_x_preferred": [
      "Yuanping"
    ],
    "name:deu_x_preferred": [
      "Yuanping"
    ],
    "name:fra_x_preferred": [
      "Yuanping"
    ],
    "name:ita_x_preferred": [
      "Yuanping"
    ],
    "name:jpn_x_preferred": [
      "原平市"
    ],
    "name:kik_x_preferred": [
      "Yuanping City"
    ],
    "name:kor_x_preferred": [
      "위안핑시"
    ],
    "name:nld_x_preferred": [
      "Yuanping"
    ],
    "name:nor_x_preferred": [
      "Yuanping"
    ],
    "name:rus_x_preferred": [
      "Юаньпин"
    ],
    "name:swe_x_preferred": [
      "Yuanping"
    ],
    "name:urd_x_preferred": [
      "یوآنپنگ سٹی"
    ],
    "name:vie_x_preferred": [
      "Nguyên Bình"
    ],
    "name:zho_x_preferred": [
      "原坪"
    ],
    "name:zho_x_variant": [
      "原平市"
    ],
    "wof:name": "Yuanping",
    "wof:placetype": "locality"
  },
  "geometry": {
    "coordinates": [
      118.83326,
      30.60962
    ],
    "type": "Point"
  }
}