{
  "type": "Feature",
  "properties": {
    "gn:admin1_code": "11.0",
    "gn:asciiname": "Qijia",
    "gn:country_code": "CN",
    "gn:dem": 257,
    "gn:feature_class": "P",
    "gn:feature_code": "PPL",
    "gn:name": "Qijia",
    "gn:population": 0,
    "gn:timezone": "Asia/Shanghai",
    "iso:country": "CN",
    "name:zho_x_preferred": [
      "祁家"
    ],
    "wof:name": "Qijia",
    "wof:placetype": "locality"
  },
  "geometry": {
    "coordinates": [
      109.93211,
      27.36467
    ],
    "type": "Point"
  }
}