{
  "type": "Feature",
  "properties": {
    "gn:admin1_code": "12.0",
    "gn:asciiname": "Zhangcheng",
    "gn:country_code": "CN",
    "gn:dem": 13,
    "gn:feature_class": "P",
    "gn:feature_code": "PPL",
    "gn:name": "Zhangcheng",
    "gn:population": 0,
    "gn:timezone": "Asia/Shanghai",
    "iso:country": "CN",
    "name:zho_x_preferred": [
      "张城"
    ],
    "wof:name": "Zhangcheng",
    "wof:placetype": "locality"
  },
  "geometry": {
    "coordinates": [
      115.90185,
      29.98256
    ],
    "type": "Point"
  }
}