{
  "type": "Feature",
  "properties": {
    "gn:admin1_code": "14.0",
    "gn:asciiname": "Qingdu",
    "gn:country_code": "CN",
    "gn:dem": 4844,
    "gn:feature_class": "P",
    "gn:feature_code": "PPLF",
    "gn:name": "Qingdu",
    "gn:population": 0,
    "gn:timezone": "Asia/Urumqi",
    "iso:country": "CN",
    "name:bod_x_preferred": [
      "Qingtü"
    ],
    "name:msa_x_preferred": [
      "Qingtü"
    ],
    "name:zho_x_preferred": [
      "Qingdu"
    ],
    "name:zho_x_variant": [
      "青都",
      "Naqiang",
      "那强",
      "青都乡"
    ],
    "wof:name": "Qingdu",
    "wof:placetype": "locality"
  },
  "geometry": {
    "coordinates": [
      88.38333,
      30.03333
    ],
    "type": "Point"
  }
}