{
  "type": "Feature",
  "properties": {
    "gn:admin1_code": "14.0",
    "gn:asciiname": "Yarzhong",
    "gn:country_code": "CN",
    "gn:dem": 3925,
    "gn:feature_class": "P",
    "gn:feature_code": "PPL",
    "gn:name": "Yarzhong",
    "gn:population": 0,
    "gn:timezone": "Asia/Urumqi",
    "iso:country": "CN",
    "name:ara_x_preferred": [
      "ياروجونغ"
    ],
    "name:bod_x_preferred": [
      "Yarzhong"
    ],
    "name:fas_x_preferred": [
      "یارژونگ"
    ],
    "name:msa_x_preferred": [
      "Yarzhong"
    ],
    "name:urd_x_preferred": [
      "یارزھونگ"
    ],
    "name:zho_x_preferred": [
      "Yazhong"
    ],
    "name:zho_x_variant": [
      "亚中",
      "Wari Gongshe",
      "瓦日公社"
    ],
    "wof:name": "Yarzhong",
    "wof:placetype": "locality"
  },
  "geometry": {
    "coordinates": [
      96.302,
      31.802
    ],
    "type": "Point"
  }
}