{
  "type": "Feature",
  "properties": {
    "gn:admin1_code": "15.0",
    "gn:asciiname": "Wan'an",
    "gn:country_code": "CN",
    "gn:dem": 1667,
    "gn:feature_class": "P",
    "gn:feature_code": "PPL",
    "gn:name": "Wan’an",
    "gn:population": 0,
    "gn:timezone": "Asia/Shanghai",
    "iso:country": "CN",
    "name:ceb_x_preferred": [
      "Wan’an"
    ],
    "name:deu_x_preferred": [
      "Wan’an"
    ],
    "name:swe_x_preferred": [
      "Wan’an"
    ],
    "name:zho_x_preferred": [
      "万安"
    ],
    "wof:name": "Wan'an",
    "wof:placetype": "locality"
  },
  "geometry": {
    "coordinates": [
      106.081,
      34.8361
    ],
    "type": "Point"
  }
}