{
  "type": "Feature",
  "properties": {
    "gn:admin1_code": "11",
    "gn:asciiname": "Dahetang",
    "gn:country_code": "CN",
    "gn:dem": 302,
    "gn:feature_class": "P",
    "gn:feature_code": "PPL",
    "gn:name": "Dahetang",
    "gn:population": 0,
    "gn:timezone": "Asia/Shanghai",
    "iso:country": "CN",
    "name:zho_x_preferred": [
      "大和塘"
    ],
    "name:zho_x_variant": [
      "大禾塘街道"
    ],
    "wof:name": "Dahetang",
    "wof:placetype": "locality"
  },
  "geometry": {
    "coordinates": [
      111.34925,
      27.00888
    ],
    "type": "Point"
  }
}