{
  "type": "Feature",
  "properties": {
    "gn:admin1_code": "32.0",
    "gn:asciiname": "Xujiaba",
    "gn:country_code": "CN",
    "gn:dem": 394,
    "gn:feature_class": "P",
    "gn:feature_code": "PPL",
    "gn:name": "Xujiaba",
    "gn:population": 0,
    "gn:timezone": "Asia/Shanghai",
    "iso:country": "CN",
    "name:zho_x_preferred": [
      "徐家坝"
    ],
    "wof:name": "Xujiaba",
    "wof:placetype": "locality"
  },
  "geometry": {
    "coordinates": [
      104.16669,
      29.5624
    ],
    "type": "Point"
  }
}