{
  "type": "Feature",
  "properties": {
    "gn:admin1_code": "26",
    "gn:asciiname": "Chongning",
    "gn:country_code": "CN",
    "gn:dem": 673,
    "gn:feature_class": "P",
    "gn:feature_code": "PPLA4",
    "gn:name": "Chongning",
    "gn:population": 0,
    "gn:timezone": "Asia/Shanghai",
    "iso:country": "CN",
    "name:und_x_variant": [
      "Ch’ung-ning-chen",
      "Ch’ung-ning",
      "Chongning",
      "Chongning Zhen"
    ],
    "name:zho_x_preferred": [
      "崇凝"
    ],
    "wof:name": "Chongning",
    "wof:placetype": "locality"
  },
  "geometry": {
    "coordinates": [
      109.58623,
      34.38226
    ],
    "type": "Point"
  }
}