{
  "type": "Feature",
  "properties": {
    "gn:admin1_code": "24.0",
    "gn:asciiname": "An'ergou",
    "gn:country_code": "CN",
    "gn:dem": 1501,
    "gn:feature_class": "P",
    "gn:feature_code": "PPL",
    "gn:name": "An’ergou",
    "gn:population": 0,
    "gn:timezone": "Asia/Shanghai",
    "iso:country": "CN",
    "name:zho_x_preferred": [
      "An’ergou"
    ],
    "name:zho_x_variant": [
      "安儿沟"
    ],
    "wof:name": "An'ergou",
    "wof:placetype": "locality"
  },
  "geometry": {
    "coordinates": [
      112.71718,
      39.80049
    ],
    "type": "Point"
  }
}