{
  "type": "Feature",
  "properties": {
    "gn:admin1_code": "25",
    "gn:asciiname": "Haidong",
    "gn:country_code": "CN",
    "gn:dem": 13,
    "gn:feature_class": "P",
    "gn:feature_code": "PPL",
    "gn:name": "Haidong",
    "gn:population": 0,
    "gn:timezone": "Asia/Shanghai",
    "iso:country": "CN",
    "name:ara_x_preferred": [
      "هايدونغ"
    ],
    "name:cat_x_preferred": [
      "Haidong"
    ],
    "name:cdo_x_preferred": [
      "Hāi-dĕ̤ng"
    ],
    "name:ces_x_preferred": [
      "Chaj-tung"
    ],
    "name:dan_x_preferred": [
      "Haidong"
    ],
    "name:deu_x_preferred": [
      "Haidong"
    ],
    "name:est_x_preferred": [
      "Haidongi ringkond"
    ],
    "name:eus_x_preferred": [
      "Haidong Prefektura"
    ],
    "name:fas_x_preferred": [
      "هایدونگ"
    ],
    "name:fin_x_preferred": [
      "Haidong"
    ],
    "name:fra_x_preferred": [
      "Haidong"
    ],
    "name:jpn_x_preferred": [
      "海東市"
    ],
    "name:kik_x_preferred": [
      "Haidong"
    ],
    "name:kor_x_preferred": [
      "하이둥시"
    ],
    "name:mon_x_preferred": [
      "Хайдун хот"
    ],
    "name:nld_x_preferred": [
      "Prefectuur Haidong"
    ],
    "name:nor_x_preferred": [
      "Haidong"
    ],
    "name:pol_x_preferred": [
      "Haidong"
    ],
    "name:rus_x_preferred": [
      "Хайдун"
    ],
    "name:spa_x_preferred": [
      "Haidong"
    ],
    "name:swe_x_preferred": [
      "Haidong"
    ],
    "name:tur_x_preferred": [
      "Haidong"
    ],
    "name:ukr_x_preferred": [
      "Хайдун"
    ],
    "name:urd_x_preferred": [
      "ہائیدونگ"
    ],
    "name:vie_x_preferred": [
      "Hải Đông"
    ],
    "name:zho_x_preferred": [
      "海东"
    ],
    "name:zho_x_variant": [
      "海东市"
    ],
    "wof:name": "Haidong",
    "wof:placetype": "locality"
  },
  "geometry": {
    "coordinates": [
      118.37995,
      37.59577
    ],
    "type": "Point"
  }
}