{
  "type": "Feature",
  "properties": {
    "gn:country": "CN",
    "gn:fcode": "PPL",
    "gn:population": 1450,
    "iso:country": "CN",
    "name:ceb_x_preferred": [
      "Qianshan Qu"
    ],
    "name:deu_x_preferred": [
      "Qianshan"
    ],
    "name:jpn_x_preferred": [
      "千山区"
    ],
    "name:kor_x_preferred": [
      "첸산구"
    ],
    "name:nor_x_preferred": [
      "Qianshan"
    ],
    "name:rus_x_preferred": [
      "Цяньшань"
    ],
    "name:swe_x_preferred": [
      "Qianshan"
    ],
    "name:und_x_variant": [
      "T’ang-chia-fang"
    ],
    "name:vie_x_preferred": [
      "Thiên Sơn"
    ],
    "name:zho_x_preferred": [
      "千山区"
    ],
    "qs:name": "Tangjiafang",
    "qs:photos_9r": 0,
    "qs:photos_sr": 0,
    "qs:pop_sr": "3",
    "wd:wordcount": 114,
    "wof:name": "Tangjiafang",
    "wof:placetype": "locality",
    "wof:population": 1450
  },
  "geometry": {
    "coordinates": [
      110.36472,
      26.84
    ],
    "type": "Point"
  }
}