{
  "type": "Feature",
  "properties": {
    "gn:admin1_code": "26",
    "gn:asciiname": "Miaoliangshang",
    "gn:country_code": "CN",
    "gn:dem": 685,
    "gn:feature_class": "P",
    "gn:feature_code": "PPL",
    "gn:name": "Miaoliangshang",
    "gn:population": 0,
    "gn:timezone": "Asia/Shanghai",
    "iso:country": "CN",
    "name:zho_x_preferred": [
      "庙梁上"
    ],
    "wof:name": "Miaoliangshang",
    "wof:placetype": "locality"
  },
  "geometry": {
    "coordinates": [
      108.18155,
      32.27954
    ],
    "type": "Point"
  }
}