{
  "type": "Feature",
  "properties": {
    "gn:admin1_code": "2.0",
    "gn:asciiname": "Zhangsi",
    "gn:country_code": "CN",
    "gn:dem": 474,
    "gn:feature_class": "P",
    "gn:feature_code": "PPL",
    "gn:name": "Zhangsi",
    "gn:population": 0,
    "gn:timezone": "Asia/Shanghai",
    "iso:country": "CN",
    "name:zho_x_preferred": [
      "张斯"
    ],
    "wof:name": "Zhangsi",
    "wof:placetype": "locality"
  },
  "geometry": {
    "coordinates": [
      120.7554,
      29.26844
    ],
    "type": "Point"
  }
}