{
  "type": "Feature",
  "properties": {
    "gn:admin1_code": "11",
    "gn:asciiname": "Moshi",
    "gn:country_code": "CN",
    "gn:dem": 416,
    "gn:feature_class": "P",
    "gn:feature_code": "PPL",
    "gn:name": "Moshi",
    "gn:population": 0,
    "gn:timezone": "Asia/Shanghai",
    "iso:country": "CN",
    "name:ceb_x_preferred": [
      "Moshi"
    ],
    "name:swa_x_preferred": [
      "Moshi"
    ],
    "name:swe_x_preferred": [
      "Moshi"
    ],
    "name:ukr_x_preferred": [
      "Моші"
    ],
    "name:zho_x_preferred": [
      "磨石"
    ],
    "wof:name": "Moshi",
    "wof:placetype": "locality"
  },
  "geometry": {
    "coordinates": [
      109.78011,
      26.53558
    ],
    "type": "Point"
  }
}