{
  "type": "Feature",
  "properties": {
    "gn:admin1_code": "3.0",
    "gn:asciiname": "Ruichang",
    "gn:country_code": "CN",
    "gn:dem": 38,
    "gn:feature_class": "P",
    "gn:feature_code": "PPL",
    "gn:name": "Ruichang",
    "gn:population": 0,
    "gn:timezone": "Asia/Shanghai",
    "iso:country": "CN",
    "name:deu_x_preferred": [
      "Ruichang"
    ],
    "name:fas_x_preferred": [
      "رایچانگ"
    ],
    "name:fra_x_preferred": [
      "Ruichang"
    ],
    "name:ita_x_preferred": [
      "Ruichang"
    ],
    "name:jpn_x_preferred": [
      "瑞昌市"
    ],
    "name:kik_x_preferred": [
      "Ruichang"
    ],
    "name:kor_x_preferred": [
      "뤼창시"
    ],
    "name:mlg_x_preferred": [
      "Ruichang"
    ],
    "name:nld_x_preferred": [
      "Ruichang"
    ],
    "name:nor_x_preferred": [
      "Ruichang"
    ],
    "name:swe_x_preferred": [
      "Ruichang"
    ],
    "name:und_x_variant": [
      "Ruichangshi"
    ],
    "name:vie_x_preferred": [
      "Thụy Xương"
    ],
    "name:war_x_preferred": [
      "Ruichang"
    ],
    "name:zho_x_preferred": [
      "瑞昌市"
    ],
    "wof:name": "Ruichang",
    "wof:placetype": "locality"
  },
  "geometry": {
    "coordinates": [
      115.65671,
      29.67965
    ],
    "type": "Point"
  }
}