{
  "type": "Feature",
  "properties": {
    "gn:admin1_code": "7.0",
    "gn:asciiname": "Shanfang",
    "gn:country_code": "CN",
    "gn:dem": 771,
    "gn:feature_class": "P",
    "gn:feature_code": "PPL",
    "gn:name": "Shanfang",
    "gn:population": 0,
    "gn:timezone": "Asia/Shanghai",
    "iso:country": "CN",
    "name:und_x_variant": [
      "山坊"
    ],
    "wof:name": "Shanfang",
    "wof:placetype": "locality"
  },
  "geometry": {
    "coordinates": [
      116.89236,
      26.64953
    ],
    "type": "Point"
  }
}