{
  "type": "Feature",
  "properties": {
    "gn:admin1_code": "8.0",
    "gn:asciiname": "Zhaoxianzhutun",
    "gn:country_code": "CN",
    "gn:dem": 182,
    "gn:feature_class": "P",
    "gn:feature_code": "PPL",
    "gn:name": "Zhaoxianzhutun",
    "gn:population": 0,
    "gn:timezone": "Asia/Shanghai",
    "iso:country": "CN",
    "name:zho_x_preferred": [
      "赵显珠屯"
    ],
    "wof:name": "Zhaoxianzhutun",
    "wof:placetype": "locality"
  },
  "geometry": {
    "coordinates": [
      128.33285,
      45.53027
    ],
    "type": "Point"
  }
}