{
  "type": "Feature",
  "properties": {
    "gn:admin1_code": "7.0",
    "gn:asciiname": "Yongwu",
    "gn:country_code": "CN",
    "gn:dem": 276,
    "gn:feature_class": "P",
    "gn:feature_code": "PPL",
    "gn:name": "Yongwu",
    "gn:population": 0,
    "gn:timezone": "Asia/Shanghai",
    "iso:country": "CN",
    "name:zho_x_preferred": [
      "永巫"
    ],
    "wof:name": "Yongwu",
    "wof:placetype": "locality"
  },
  "geometry": {
    "coordinates": [
      116.35036,
      25.55935
    ],
    "type": "Point"
  }
}