{
  "type": "Feature",
  "properties": {
    "gn:admin1_code": "26.0",
    "gn:asciiname": "Lianghekou",
    "gn:country_code": "CN",
    "gn:dem": 748,
    "gn:feature_class": "P",
    "gn:feature_code": "PPL",
    "gn:name": "Lianghekou",
    "gn:population": 0,
    "gn:timezone": "Asia/Shanghai",
    "iso:country": "CN",
    "name:und_x_variant": [
      "两河口"
    ],
    "wof:name": "Lianghekou",
    "wof:placetype": "locality"
  },
  "geometry": {
    "coordinates": [
      106.63353,
      32.98517
    ],
    "type": "Point"
  }
}