{
  "type": "Feature",
  "properties": {
    "gn:admin1_code": "11",
    "gn:asciiname": "Sheshiqiao",
    "gn:country_code": "CN",
    "gn:dem": 63,
    "gn:feature_class": "P",
    "gn:feature_code": "PPLA4",
    "gn:name": "Sheshiqiao",
    "gn:population": 0,
    "gn:timezone": "Asia/Shanghai",
    "iso:country": "CN",
    "name:und_x_variant": [
      "Yü-shih-ch’iao",
      "She-shih-ch’iao",
      "Sheshiqiao",
      "佘市桥",
      "Sheshiqiao Zhen",
      "佘市桥镇"
    ],
    "wof:name": "Sheshiqiao",
    "wof:placetype": "locality"
  },
  "geometry": {
    "coordinates": [
      111.51816,
      29.44305
    ],
    "type": "Point"
  }
}