{
  "type": "Feature",
  "properties": {
    "gn:admin1_code": "32.0",
    "gn:asciiname": "Zengjia",
    "gn:country_code": "CN",
    "gn:dem": 3184,
    "gn:feature_class": "P",
    "gn:feature_code": "PPL",
    "gn:name": "Zengjia",
    "gn:population": 0,
    "gn:timezone": "Asia/Shanghai",
    "iso:country": "CN",
    "name:zho_x_preferred": [
      "曾家"
    ],
    "wof:name": "Zengjia",
    "wof:placetype": "locality"
  },
  "geometry": {
    "coordinates": [
      101.76815,
      30.88278
    ],
    "type": "Point"
  }
}