{
  "type": "Feature",
  "properties": {
    "gn:admin1_code": "8.0",
    "gn:asciiname": "Lukuantun",
    "gn:country_code": "CN",
    "gn:dem": 221,
    "gn:feature_class": "P",
    "gn:feature_code": "PPL",
    "gn:name": "Lükuantun",
    "gn:population": 0,
    "gn:timezone": "Asia/Shanghai",
    "iso:country": "CN",
    "name:und_x_variant": [
      "Lükuantun"
    ],
    "name:zho_x_preferred": [
      "吕宽屯"
    ],
    "wof:name": "Lukuantun",
    "wof:placetype": "locality"
  },
  "geometry": {
    "coordinates": [
      125.73138,
      47.19929000000001
    ],
    "type": "Point"
  }
}