{
  "type": "Feature",
  "properties": {
    "gn:admin1_code": "21.0",
    "gn:asciiname": "Liwan",
    "gn:country_code": "CN",
    "gn:dem": 1586,
    "gn:feature_class": "P",
    "gn:feature_code": "PPL",
    "gn:name": "Liwan",
    "gn:population": 0,
    "gn:timezone": "Asia/Shanghai",
    "iso:country": "CN",
    "name:ara_x_preferred": [
      "ليوان"
    ],
    "name:heb_x_preferred": [
      "ליוואן"
    ],
    "name:ita_x_preferred": [
      "Līwān"
    ],
    "name:spa_x_preferred": [
      "Liwan"
    ],
    "name:urd_x_preferred": [
      "لیوان"
    ],
    "name:zho_x_preferred": [
      "里湾"
    ],
    "wof:name": "Liwan",
    "wof:placetype": "locality"
  },
  "geometry": {
    "coordinates": [
      106.92035,
      36.09206
    ],
    "type": "Point"
  }
}