{
  "type": "Feature",
  "properties": {
    "gn:admin1_code": "4.0",
    "gn:asciiname": "Bashang",
    "gn:country_code": "CN",
    "gn:dem": 7,
    "gn:feature_class": "P",
    "gn:feature_code": "PPL",
    "gn:name": "Bashang",
    "gn:population": 0,
    "gn:timezone": "Asia/Shanghai",
    "iso:country": "CN",
    "name:zho_x_preferred": [
      "坝上"
    ],
    "wof:name": "Bashang",
    "wof:placetype": "locality"
  },
  "geometry": {
    "coordinates": [
      119.80921,
      31.85069
    ],
    "type": "Point"
  }
}