{
  "type": "Feature",
  "properties": {
    "gn:admin1_code": "3.0",
    "gn:asciiname": "Xinfang",
    "gn:country_code": "CN",
    "gn:dem": 324,
    "gn:feature_class": "P",
    "gn:feature_code": "PPL",
    "gn:name": "Xinfang",
    "gn:population": 0,
    "gn:timezone": "Asia/Shanghai",
    "iso:country": "CN",
    "name:und_x_variant": [
      "新坊"
    ],
    "wof:name": "Xinfang",
    "wof:placetype": "locality"
  },
  "geometry": {
    "coordinates": [
      116.30445,
      26.52665
    ],
    "type": "Point"
  }
}