{
  "type": "Feature",
  "properties": {
    "gn:admin1_code": "18",
    "gn:asciiname": "Zhongba",
    "gn:country_code": "CN",
    "gn:dem": 951,
    "gn:feature_class": "P",
    "gn:feature_code": "PPL",
    "gn:name": "Zhongba",
    "gn:population": 0,
    "gn:timezone": "Asia/Shanghai",
    "iso:country": "CN",
    "name:ceb_x_preferred": [
      "Zhongba"
    ],
    "name:deu_x_preferred": [
      "Zhongba"
    ],
    "name:zho_x_preferred": [
      "中坝"
    ],
    "wof:name": "Zhongba",
    "wof:placetype": "locality"
  },
  "geometry": {
    "coordinates": [
      107.553,
      28.22
    ],
    "type": "Point"
  }
}