{
  "type": "Feature",
  "properties": {
    "gn:admin1_code": "16.0",
    "gn:asciiname": "Nale",
    "gn:country_code": "CN",
    "gn:dem": 861,
    "gn:feature_class": "P",
    "gn:feature_code": "PPL",
    "gn:name": "Nale",
    "gn:population": 0,
    "gn:timezone": "Asia/Shanghai",
    "iso:country": "CN",
    "name:zho_x_preferred": [
      "那乐"
    ],
    "wof:name": "Nale",
    "wof:placetype": "locality"
  },
  "geometry": {
    "coordinates": [
      106.613,
      24.6019
    ],
    "type": "Point"
  }
}