{
  "type": "Feature",
  "properties": {
    "gn:admin1_code": "3",
    "gn:asciiname": "Pinghu",
    "gn:country_code": "CN",
    "gn:dem": 59,
    "gn:feature_class": "P",
    "gn:feature_code": "PPL",
    "gn:name": "Pinghu",
    "gn:population": 0,
    "gn:timezone": "Asia/Shanghai",
    "iso:country": "CN",
    "name:ara_x_preferred": [
      "بنغهو"
    ],
    "name:deu_x_preferred": [
      "Pinghu"
    ],
    "name:fra_x_preferred": [
      "Pinghu"
    ],
    "name:ita_x_preferred": [
      "Pinghu"
    ],
    "name:jpn_x_preferred": [
      "平湖市"
    ],
    "name:kik_x_preferred": [
      "Pinghu"
    ],
    "name:kor_x_preferred": [
      "핑후시"
    ],
    "name:mlg_x_preferred": [
      "Pinghu"
    ],
    "name:nor_x_preferred": [
      "Pinghu"
    ],
    "name:swe_x_preferred": [
      "Pinghu"
    ],
    "name:tgl_x_preferred": [
      "Pinghu"
    ],
    "name:urd_x_preferred": [
      "پنگہو"
    ],
    "name:vie_x_preferred": [
      "Bình Hồ"
    ],
    "name:war_x_preferred": [
      "Pinghu"
    ],
    "name:wuu_x_preferred": [
      "平湖市"
    ],
    "name:zho_x_preferred": [
      "平湖市"
    ],
    "wof:name": "Pinghu",
    "wof:placetype": "locality"
  },
  "geometry": {
    "coordinates": [
      115.04694,
      27.10861
    ],
    "type": "Point"
  }
}