{
  "type": "Feature",
  "properties": {
    "gn:admin1_code": "33.0",
    "gn:asciiname": "Xiangbei",
    "gn:country_code": "CN",
    "gn:dem": 429,
    "gn:feature_class": "P",
    "gn:feature_code": "PPL",
    "gn:name": "Xiangbei",
    "gn:population": 0,
    "gn:timezone": "Asia/Shanghai",
    "iso:country": "CN",
    "name:zho_x_preferred": [
      "向北"
    ],
    "wof:name": "Xiangbei",
    "wof:placetype": "locality"
  },
  "geometry": {
    "coordinates": [
      106.64796,
      29.91474
    ],
    "type": "Point"
  }
}