{
  "type": "Feature",
  "properties": {
    "gn:admin1_code": "9.0",
    "gn:asciiname": "Xiyingzi",
    "gn:country_code": "CN",
    "gn:dem": 53,
    "gn:feature_class": "P",
    "gn:feature_code": "PPL",
    "gn:name": "Xiyingzi",
    "gn:population": 0,
    "gn:timezone": "Asia/Shanghai",
    "iso:country": "CN",
    "name:zho_x_preferred": [
      "西营子"
    ],
    "wof:name": "Xiyingzi",
    "wof:placetype": "locality"
  },
  "geometry": {
    "coordinates": [
      114.39509,
      33.6165
    ],
    "type": "Point"
  }
}