{
  "type": "Feature",
  "properties": {
    "gn:admin1_code": "26.0",
    "gn:asciiname": "Sungaowan",
    "gn:country_code": "CN",
    "gn:dem": 1623,
    "gn:feature_class": "P",
    "gn:feature_code": "PPL",
    "gn:name": "Sungaowan",
    "gn:population": 0,
    "gn:timezone": "Asia/Shanghai",
    "iso:country": "CN",
    "name:zho_x_preferred": [
      "孙高湾"
    ],
    "wof:name": "Sungaowan",
    "wof:placetype": "locality"
  },
  "geometry": {
    "coordinates": [
      107.89864,
      37.14711
    ],
    "type": "Point"
  }
}