{
  "type": "Feature",
  "properties": {
    "gn:admin1_code": "12.0",
    "gn:asciiname": "Youzhahe",
    "gn:country_code": "CN",
    "gn:dem": 25,
    "gn:feature_class": "P",
    "gn:feature_code": "PPL",
    "gn:name": "Youzhahe",
    "gn:population": 0,
    "gn:timezone": "Asia/Shanghai",
    "iso:country": "CN",
    "name:zho_x_preferred": [
      "油榨河"
    ],
    "wof:name": "Youzhahe",
    "wof:placetype": "locality"
  },
  "geometry": {
    "coordinates": [
      113.4891,
      29.94478
    ],
    "type": "Point"
  }
}