{
  "type": "Feature",
  "properties": {
    "gn:admin1_code": "15.0",
    "gn:asciiname": "Nianzigou",
    "gn:country_code": "CN",
    "gn:dem": 1329,
    "gn:feature_class": "P",
    "gn:feature_code": "PPL",
    "gn:name": "Nianzigou",
    "gn:population": 0,
    "gn:timezone": "Asia/Shanghai",
    "iso:country": "CN",
    "name:und_x_variant": [
      "碾子沟"
    ],
    "wof:name": "Nianzigou",
    "wof:placetype": "locality"
  },
  "geometry": {
    "coordinates": [
      105.76328999999998,
      33.46876
    ],
    "type": "Point"
  }
}