{
  "type": "Feature",
  "properties": {
    "gn:admin1_code": "29.0",
    "gn:asciiname": "Ali",
    "gn:country_code": "CN",
    "gn:dem": 1101,
    "gn:feature_class": "P",
    "gn:feature_code": "PPL",
    "gn:name": "Ali",
    "gn:population": 0,
    "gn:timezone": "Asia/Shanghai",
    "iso:country": "CN",
    "name:afr_x_preferred": [
      "Ali"
    ],
    "name:ang_x_preferred": [
      "Alī"
    ],
    "name:arg_x_preferred": [
      "Alí"
    ],
    "name:aze_x_preferred": [
      "Əli"
    ],
    "name:ces_x_preferred": [
      "Alí"
    ],
    "name:dan_x_preferred": [
      "Ali"
    ],
    "name:diq_x_preferred": [
      "Eli"
    ],
    "name:div_x_preferred": [
      "ޢަލީގެފާނު"
    ],
    "name:hau_x_preferred": [
      "Ali"
    ],
    "name:hrv_x_preferred": [
      "Ali"
    ],
    "name:hun_x_preferred": [
      "Ali kalifa"
    ],
    "name:jpn_x_preferred": [
      "アリー・イブン・アビー・ターリブ"
    ],
    "name:kur_x_preferred": [
      "Elî"
    ],
    "name:lfn_x_preferred": [
      "Ali"
    ],
    "name:lit_x_preferred": [
      "Ali"
    ],
    "name:mzn_x_preferred": [
      "علی"
    ],
    "name:pan_x_preferred": [
      "ਅਲੀ"
    ],
    "name:pnb_x_preferred": [
      "علی"
    ],
    "name:por_x_preferred": [
      "Ali"
    ],
    "name:ron_x_preferred": [
      "Ali"
    ],
    "name:sco_x_preferred": [
      "Ali"
    ],
    "name:slk_x_preferred": [
      "Alí"
    ],
    "name:slv_x_preferred": [
      "Ali"
    ],
    "name:snd_x_preferred": [
      "علي"
    ],
    "name:som_x_preferred": [
      "Cali"
    ],
    "name:sqi_x_preferred": [
      "Aliu"
    ],
    "name:srp_x_preferred": [
      "Алија"
    ],
    "name:tam_x_preferred": [
      "அலீ"
    ],
    "name:tur_x_preferred": [
      "Ali"
    ],
    "name:uzb_x_preferred": [
      "Ali"
    ],
    "name:war_x_preferred": [
      "Ali"
    ],
    "name:wln_x_preferred": [
      "Ali"
    ],
    "name:wuu_x_preferred": [
      "阿里·本·阿比·塔利卜"
    ],
    "name:zho_x_preferred": [
      "阿里"
    ],
    "name:zho_x_variant": [
      "阿里·本·阿比·塔利卜"
    ],
    "wof:name": "Ali",
    "wof:placetype": "locality"
  },
  "geometry": {
    "coordinates": [
      99.6678,
      22.1339
    ],
    "type": "Point"
  }
}