{
  "type": "Feature",
  "properties": {
    "gn:admin1_code": "10.0",
    "gn:asciiname": "Qianliulaitang",
    "gn:country_code": "CN",
    "gn:dem": 10,
    "gn:feature_class": "P",
    "gn:feature_code": "PPL",
    "gn:name": "Qianliulaitang",
    "gn:population": 0,
    "gn:timezone": "Asia/Shanghai",
    "iso:country": "CN",
    "name:zho_x_preferred": [
      "前流来堂"
    ],
    "wof:name": "Qianliulaitang",
    "wof:placetype": "locality"
  },
  "geometry": {
    "coordinates": [
      116.745,
      38.3869
    ],
    "type": "Point"
  }
}