{
  "type": "Feature",
  "properties": {
    "gn:admin1_code": "03",
    "gn:asciiname": "Quangang",
    "gn:country_code": "CN",
    "gn:dem": 33,
    "gn:feature_class": "P",
    "gn:feature_code": "PPLA4",
    "gn:name": "Quangang",
    "gn:population": 0,
    "gn:timezone": "Asia/Shanghai",
    "iso:country": "CN",
    "name:und_x_variant": [
      "Ch’üan-chiang-chieh",
      "Ch’üan-chiang",
      "Quangang",
      "泉港",
      "Quangang Zhen",
      "泉港镇"
    ],
    "wof:name": "Quangang",
    "wof:placetype": "locality"
  },
  "geometry": {
    "coordinates": [
      115.59658,
      28.15594
    ],
    "type": "Point"
  }
}