{
  "type": "Feature",
  "properties": {
    "gn:admin1_code": "16.0",
    "gn:asciiname": "Renyi",
    "gn:country_code": "CN",
    "gn:dem": 338,
    "gn:feature_class": "P",
    "gn:feature_code": "PPL",
    "gn:name": "Renyi",
    "gn:population": 0,
    "gn:timezone": "Asia/Shanghai",
    "iso:country": "CN",
    "name:ceb_x_preferred": [
      "Renyi"
    ],
    "name:deu_x_preferred": [
      "Renyi"
    ],
    "name:rus_x_preferred": [
      "Реньи"
    ],
    "name:swe_x_preferred": [
      "Renyi"
    ],
    "name:zho_x_preferred": [
      "仁义"
    ],
    "wof:name": "Renyi",
    "wof:placetype": "locality"
  },
  "geometry": {
    "coordinates": [
      108.487,
      25.2142
    ],
    "type": "Point"
  }
}