{
  "type": "Feature",
  "properties": {
    "gn:admin1_code": "30",
    "gn:asciiname": "Yongpingxu",
    "gn:country_code": "CN",
    "gn:dem": 13,
    "gn:feature_class": "P",
    "gn:feature_code": "PPL",
    "gn:name": "Yongpingxu",
    "gn:population": 0,
    "gn:timezone": "Asia/Shanghai",
    "iso:country": "CN",
    "name:zho_x_preferred": [
      "永平圩"
    ],
    "wof:name": "Yongpingxu",
    "wof:placetype": "locality"
  },
  "geometry": {
    "coordinates": [
      112.93582,
      23.42446
    ],
    "type": "Point"
  }
}