{
  "type": "Feature",
  "properties": {
    "gn:admin1_code": "3.0",
    "gn:asciiname": "Dingxi",
    "gn:country_code": "CN",
    "gn:dem": 35,
    "gn:feature_class": "P",
    "gn:feature_code": "PPL",
    "gn:name": "Dingxi",
    "gn:population": 0,
    "gn:timezone": "Asia/Shanghai",
    "iso:country": "CN",
    "name:ara_x_preferred": [
      "ديغنشي"
    ],
    "name:cdo_x_preferred": [
      "Dêng-să̤"
    ],
    "name:ceb_x_preferred": [
      "Dingxi Shi"
    ],
    "name:ces_x_preferred": [
      "Ting-si"
    ],
    "name:dan_x_preferred": [
      "Dingxi"
    ],
    "name:deu_x_preferred": [
      "Dingxi"
    ],
    "name:eus_x_preferred": [
      "Dingxi"
    ],
    "name:fas_x_preferred": [
      "دینگسی"
    ],
    "name:fin_x_preferred": [
      "Dingxi"
    ],
    "name:fra_x_preferred": [
      "Dingxi"
    ],
    "name:hye_x_preferred": [
      "Դինսի"
    ],
    "name:ind_x_preferred": [
      "Dingxi"
    ],
    "name:ita_x_preferred": [
      "Dingxi"
    ],
    "name:jpn_x_preferred": [
      "定西市"
    ],
    "name:kik_x_preferred": [
      "Dingxi"
    ],
    "name:kor_x_preferred": [
      "딩시시"
    ],
    "name:msa_x_preferred": [
      "Dingxi"
    ],
    "name:nld_x_preferred": [
      "Dingxi"
    ],
    "name:nno_x_preferred": [
      "Dingxi"
    ],
    "name:nor_x_preferred": [
      "Dingxi"
    ],
    "name:pam_x_preferred": [
      "Dingxi"
    ],
    "name:pnb_x_preferred": [
      "ڈنگسی"
    ],
    "name:pol_x_preferred": [
      "Dingxi"
    ],
    "name:rus_x_preferred": [
      "Динси"
    ],
    "name:sin_x_preferred": [
      "ඩිංසයි"
    ],
    "name:spa_x_preferred": [
      "Dingxi"
    ],
    "name:swe_x_preferred": [
      "Dingxi"
    ],
    "name:tur_x_preferred": [
      "Dingxi"
    ],
    "name:ukr_x_preferred": [
      "Дінсі"
    ],
    "name:und_x_variant": [
      "丁溪"
    ],
    "name:urd_x_preferred": [
      "ڈنگشی"
    ],
    "name:vie_x_preferred": [
      "Định Tây"
    ],
    "name:wuu_x_preferred": [
      "定西市"
    ],
    "name:zho_x_preferred": [
      "定西市"
    ],
    "wof:name": "Dingxi",
    "wof:placetype": "locality"
  },
  "geometry": {
    "coordinates": [
      116.42512,
      28.37932
    ],
    "type": "Point"
  }
}