{
  "type": "Feature",
  "properties": {
    "gn:admin1_code": "19.0",
    "gn:asciiname": "Luanshi",
    "gn:country_code": "CN",
    "gn:dem": 54,
    "gn:feature_class": "P",
    "gn:feature_code": "PPL",
    "gn:name": "Luanshi",
    "gn:population": 0,
    "gn:timezone": "Asia/Shanghai",
    "iso:country": "CN",
    "name:zho_x_preferred": [
      "乱石"
    ],
    "wof:name": "Luanshi",
    "wof:placetype": "locality"
  },
  "geometry": {
    "coordinates": [
      122.14542,
      41.90124
    ],
    "type": "Point"
  }
}