{
  "type": "Feature",
  "properties": {
    "gn:admin1_code": "08",
    "gn:asciiname": "Wudaogou",
    "gn:cc2": "CN",
    "gn:country_code": "CN",
    "gn:dem": 454,
    "gn:feature_class": "P",
    "gn:feature_code": "PPL",
    "gn:name": "Wudaogou",
    "gn:population": 0,
    "gn:timezone": "Asia/Shanghai",
    "iso:country": "CN",
    "name:eng_x_preferred": [
      "Wudaogou"
    ],
    "name:rus_x_preferred": [
      "Удаогоу"
    ],
    "name:rus_x_variant": [
      "Людаогоу",
      "Сыдаогоу"
    ],
    "name:und_x_variant": [
      "Wu-tao-kou"
    ],
    "wof:name": "Wudaogou",
    "wof:placetype": "locality"
  },
  "geometry": {
    "coordinates": [
      126.45,
      50.25
    ],
    "type": "Point"
  }
}