{
  "type": "Feature",
  "properties": {
    "gn:admin1_code": "2.0",
    "gn:asciiname": "Yongchang",
    "gn:country_code": "CN",
    "gn:dem": 11,
    "gn:feature_class": "P",
    "gn:feature_code": "PPL",
    "gn:name": "Yongchang",
    "gn:population": 0,
    "gn:timezone": "Asia/Shanghai",
    "iso:country": "CN",
    "name:ceb_x_preferred": [
      "Yongchang"
    ],
    "name:deu_x_preferred": [
      "Yongchang"
    ],
    "name:zho_x_preferred": [
      "永昌"
    ],
    "wof:name": "Yongchang",
    "wof:placetype": "locality"
  },
  "geometry": {
    "coordinates": [
      121.85839,
      30.02908
    ],
    "type": "Point"
  }
}