{
  "type": "Feature",
  "properties": {
    "gn:admin1_code": "9.0",
    "gn:asciiname": "Junchen",
    "gn:country_code": "CN",
    "gn:dem": 58,
    "gn:feature_class": "P",
    "gn:feature_code": "PPL",
    "gn:name": "Junchen",
    "gn:population": 0,
    "gn:timezone": "Asia/Shanghai",
    "iso:country": "CN",
    "name:aze_x_preferred": [
      "Günçen"
    ],
    "name:bul_x_preferred": [
      "Дзюнчън"
    ],
    "name:jpn_x_preferred": [
      "軍臣単于"
    ],
    "name:kaz_x_preferred": [
      "Гюньчень"
    ],
    "name:kor_x_preferred": [
      "군신선우"
    ],
    "name:mon_x_preferred": [
      "Жюнчэн шаньюй"
    ],
    "name:rus_x_preferred": [
      "Цзюньчэнь"
    ],
    "name:tuk_x_preferred": [
      "Kuniçen"
    ],
    "name:zho_x_preferred": [
      "君陈"
    ],
    "name:zho_x_variant": [
      "军臣单于"
    ],
    "wof:name": "Junchen",
    "wof:placetype": "locality"
  },
  "geometry": {
    "coordinates": [
      114.2978,
      33.42469000000001
    ],
    "type": "Point"
  }
}