{
  "type": "Feature",
  "properties": {
    "gn:admin1_code": "16.0",
    "gn:asciiname": "Botou",
    "gn:country_code": "CN",
    "gn:dem": 124,
    "gn:feature_class": "P",
    "gn:feature_code": "PPL",
    "gn:name": "Botou",
    "gn:population": 0,
    "gn:timezone": "Asia/Shanghai",
    "iso:country": "CN",
    "name:ara_x_preferred": [
      "بوتوو"
    ],
    "name:ceb_x_preferred": [
      "Botou Shi"
    ],
    "name:deu_x_preferred": [
      "Botou"
    ],
    "name:fra_x_preferred": [
      "Botou"
    ],
    "name:ita_x_preferred": [
      "Botou"
    ],
    "name:jpn_x_preferred": [
      "泊頭市"
    ],
    "name:kik_x_preferred": [
      "Botou"
    ],
    "name:kor_x_preferred": [
      "보터우시"
    ],
    "name:mlg_x_preferred": [
      "Botou"
    ],
    "name:nor_x_preferred": [
      "Botou"
    ],
    "name:pam_x_preferred": [
      "Botou"
    ],
    "name:rus_x_preferred": [
      "Ботоу"
    ],
    "name:swe_x_preferred": [
      "Botou"
    ],
    "name:urd_x_preferred": [
      "بوتوو"
    ],
    "name:vie_x_preferred": [
      "Bạc Đầu"
    ],
    "name:zho_x_preferred": [
      "波头"
    ],
    "name:zho_x_variant": [
      "泊头市"
    ],
    "wof:name": "Botou",
    "wof:placetype": "locality"
  },
  "geometry": {
    "coordinates": [
      110.178,
      23.707
    ],
    "type": "Point"
  }
}