{
  "type": "Feature",
  "properties": {
    "gn:admin1_code": "16.0",
    "gn:asciiname": "Gan'ai",
    "gn:country_code": "CN",
    "gn:dem": 211,
    "gn:feature_class": "P",
    "gn:feature_code": "PPL",
    "gn:name": "Gan’ai",
    "gn:population": 0,
    "gn:timezone": "Asia/Shanghai",
    "iso:country": "CN",
    "name:und_x_variant": [
      "Gan’ai"
    ],
    "name:zho_x_preferred": [
      "敢暧"
    ],
    "wof:name": "Gan'ai",
    "wof:placetype": "locality"
  },
  "geometry": {
    "coordinates": [
      108.119,
      23.9913
    ],
    "type": "Point"
  }
}