{
  "type": "Feature",
  "properties": {
    "gn:admin1_code": "16.0",
    "gn:asciiname": "Gushi",
    "gn:country_code": "CN",
    "gn:dem": 1066,
    "gn:feature_class": "P",
    "gn:feature_code": "PPL",
    "gn:name": "Gushi",
    "gn:population": 0,
    "gn:timezone": "Asia/Shanghai",
    "iso:country": "CN",
    "name:ceb_x_preferred": [
      "Gushi"
    ],
    "name:nld_x_preferred": [
      "Gushi"
    ],
    "name:zho_x_preferred": [
      "古石"
    ],
    "wof:name": "Gushi",
    "wof:placetype": "locality"
  },
  "geometry": {
    "coordinates": [
      106.528,
      24.5584
    ],
    "type": "Point"
  }
}