{
  "type": "Feature",
  "properties": {
    "gn:admin1_code": "20",
    "gn:asciiname": "Salqin",
    "gn:cc2": "CN",
    "gn:country_code": "CN",
    "gn:dem": 1067,
    "gn:feature_class": "P",
    "gn:feature_code": "PPL",
    "gn:name": "Salqin",
    "gn:population": 0,
    "gn:timezone": "Asia/Shanghai",
    "iso:country": "CN",
    "name:ara_x_preferred": [
      "سلقين"
    ],
    "name:ceb_x_preferred": [
      "Salqīn"
    ],
    "name:deu_x_preferred": [
      "Salqin"
    ],
    "name:fas_x_preferred": [
      "سلقین"
    ],
    "name:hye_x_preferred": [
      "Սալկին"
    ],
    "name:nno_x_preferred": [
      "Salqin"
    ],
    "name:pol_x_preferred": [
      "Salkin"
    ],
    "name:por_x_preferred": [
      "Salqin"
    ],
    "name:rus_x_preferred": [
      "Салькин"
    ],
    "name:swe_x_preferred": [
      "Salqīn"
    ],
    "name:und_x_variant": [
      "Sharqin"
    ],
    "name:urd_x_preferred": [
      "سلقین"
    ],
    "name:vie_x_preferred": [
      "Salqin"
    ],
    "name:zho_x_preferred": [
      "沙勒钦"
    ],
    "wof:name": "Salqin",
    "wof:placetype": "locality"
  },
  "geometry": {
    "coordinates": [
      111.73139,
      40.55833
    ],
    "type": "Point"
  }
}