{
  "type": "Feature",
  "properties": {
    "gn:admin1_code": "16.0",
    "gn:asciiname": "Andong",
    "gn:country_code": "CN",
    "gn:dem": 127,
    "gn:feature_class": "P",
    "gn:feature_code": "PPL",
    "gn:name": "Andong",
    "gn:population": 0,
    "gn:timezone": "Asia/Shanghai",
    "iso:country": "CN",
    "name:ara_x_preferred": [
      "آندونغ"
    ],
    "name:cat_x_preferred": [
      "Andong"
    ],
    "name:ceb_x_preferred": [
      "Andong"
    ],
    "name:ces_x_preferred": [
      "Andong"
    ],
    "name:deu_x_preferred": [
      "Andong"
    ],
    "name:epo_x_preferred": [
      "Andon"
    ],
    "name:est_x_preferred": [
      "Andong"
    ],
    "name:fas_x_preferred": [
      "آندونگ"
    ],
    "name:fin_x_preferred": [
      "Andong"
    ],
    "name:fra_x_preferred": [
      "Andong"
    ],
    "name:hun_x_preferred": [
      "Andong"
    ],
    "name:hye_x_preferred": [
      "Անդոնգ"
    ],
    "name:ind_x_preferred": [
      "Andong"
    ],
    "name:ita_x_preferred": [
      "Andong"
    ],
    "name:jpn_x_preferred": [
      "安東市"
    ],
    "name:kat_x_preferred": [
      "ანდონი"
    ],
    "name:kor_x_preferred": [
      "안동시"
    ],
    "name:lit_x_preferred": [
      "Andongas"
    ],
    "name:lmo_x_preferred": [
      "Andong"
    ],
    "name:mon_x_preferred": [
      "Аньдун"
    ],
    "name:msa_x_preferred": [
      "Andong"
    ],
    "name:nld_x_preferred": [
      "Andong"
    ],
    "name:nor_x_preferred": [
      "Andong"
    ],
    "name:pol_x_preferred": [
      "Andong"
    ],
    "name:por_x_preferred": [
      "Andong"
    ],
    "name:ron_x_preferred": [
      "Andong"
    ],
    "name:rus_x_preferred": [
      "Андон"
    ],
    "name:spa_x_preferred": [
      "Andong"
    ],
    "name:swe_x_preferred": [
      "Andong"
    ],
    "name:tgl_x_preferred": [
      "Andong"
    ],
    "name:tha_x_preferred": [
      "อันดง"
    ],
    "name:tur_x_preferred": [
      "Andong"
    ],
    "name:ukr_x_preferred": [
      "Андон"
    ],
    "name:urd_x_preferred": [
      "انڈونگ"
    ],
    "name:vie_x_preferred": [
      "Andong"
    ],
    "name:war_x_preferred": [
      "Andong"
    ],
    "name:wuu_x_preferred": [
      "安东市"
    ],
    "name:zho_x_preferred": [
      "安东"
    ],
    "name:zho_x_variant": [
      "安东市"
    ],
    "wof:name": "Andong",
    "wof:placetype": "locality"
  },
  "geometry": {
    "coordinates": [
      109.854,
      22.666
    ],
    "type": "Point"
  }
}