{
  "type": "Feature",
  "properties": {
    "gn:admin1_code": "26.0",
    "gn:asciiname": "Ma'anlingcun",
    "gn:country_code": "CN",
    "gn:dem": 1377,
    "gn:feature_class": "P",
    "gn:feature_code": "PPL",
    "gn:name": "Ma’anlingcun",
    "gn:population": 0,
    "gn:timezone": "Asia/Shanghai",
    "iso:country": "CN",
    "name:und_x_variant": [
      "Ma’anlingcun"
    ],
    "name:zho_x_preferred": [
      "马鞍岭村"
    ],
    "wof:name": "Ma'anlingcun",
    "wof:placetype": "locality"
  },
  "geometry": {
    "coordinates": [
      109.57013,
      33.74275
    ],
    "type": "Point"
  }
}