{
  "type": "Feature",
  "properties": {
    "gn:admin1_code": "7",
    "gn:asciiname": "Wuyuan",
    "gn:country_code": "CN",
    "gn:dem": 36,
    "gn:feature_class": "P",
    "gn:feature_code": "PPL",
    "gn:name": "Wuyuan",
    "gn:population": 0,
    "gn:timezone": "Asia/Shanghai",
    "iso:country": "CN",
    "name:ceb_x_preferred": [
      "Wuyuan"
    ],
    "name:deu_x_preferred": [
      "Wuyuan"
    ],
    "name:fra_x_preferred": [
      "Wuyuan"
    ],
    "name:kor_x_preferred": [
      "우위안"
    ],
    "name:kor_x_variant": [
      "우위안현"
    ],
    "name:nld_x_preferred": [
      "Wuyuan"
    ],
    "name:nor_x_preferred": [
      "Wuyuan"
    ],
    "name:pol_x_preferred": [
      "Wuyuan"
    ],
    "name:por_x_preferred": [
      "Wuyuan"
    ],
    "name:rus_x_preferred": [
      "Уюань"
    ],
    "name:swe_x_preferred": [
      "Wuyuan"
    ],
    "name:tur_x_preferred": [
      "Wuyuan"
    ],
    "name:ukr_x_preferred": [
      "Фуюань"
    ],
    "name:urd_x_preferred": [
      "وویان"
    ],
    "name:vie_x_preferred": [
      "Vụ Nguyên"
    ],
    "name:zho_cn_x_preferred": [
      "婺源"
    ],
    "name:zho_tw_x_preferred": [
      "婺源"
    ],
    "name:zho_x_preferred": [
      "梧园"
    ],
    "wof:name": "Wuyuan",
    "wof:placetype": "locality"
  },
  "geometry": {
    "coordinates": [
      118.43175,
      24.85711
    ],
    "type": "Point"
  }
}