{
  "type": "Feature",
  "properties": {
    "gn:admin1_code": "30",
    "gn:asciiname": "Houhai",
    "gn:country_code": "CN",
    "gn:dem": 7,
    "gn:feature_class": "P",
    "gn:feature_code": "PPL",
    "gn:name": "Houhai",
    "gn:population": 0,
    "gn:timezone": "Asia/Urumqi",
    "iso:country": "CN",
    "name:chv_x_preferred": [
      "Хоухай"
    ],
    "name:deu_x_preferred": [
      "Houhai"
    ],
    "name:fin_x_preferred": [
      "Houhai"
    ],
    "name:ita_x_preferred": [
      "Houhai"
    ],
    "name:nor_x_preferred": [
      "Houhai"
    ],
    "name:rus_x_preferred": [
      "Хоухай"
    ],
    "name:swe_x_preferred": [
      "Houhai"
    ],
    "name:und_x_variant": [
      "Houhaicun",
      "后海村"
    ],
    "name:zho_x_preferred": [
      "后海"
    ],
    "wof:name": "Houhai",
    "wof:placetype": "locality"
  },
  "geometry": {
    "coordinates": [
      110.46497,
      20.64064
    ],
    "type": "Point"
  }
}