{
  "type": "Feature",
  "properties": {
    "gn:admin1_code": "11.0",
    "gn:asciiname": "Yiwan",
    "gn:country_code": "CN",
    "gn:dem": 83,
    "gn:feature_class": "P",
    "gn:feature_code": "PPLA4",
    "gn:name": "Yiwan",
    "gn:population": 0,
    "gn:timezone": "Asia/Shanghai",
    "iso:country": "CN",
    "name:und_x_variant": [
      "宜万",
      "Caijiapo",
      "蔡家坡"
    ],
    "name:zho_x_preferred": [
      "Yiwan Xiang"
    ],
    "name:zho_x_variant": [
      "宜万乡"
    ],
    "wof:name": "Yiwan",
    "wof:placetype": "locality"
  },
  "geometry": {
    "coordinates": [
      111.6814,
      29.86735
    ],
    "type": "Point"
  }
}