{
  "type": "Feature",
  "properties": {
    "gn:admin1_code": "30.0",
    "gn:asciiname": "Fo'ao",
    "gn:country_code": "CN",
    "gn:dem": 16,
    "gn:feature_class": "P",
    "gn:feature_code": "PPL",
    "gn:name": "Fo’ao",
    "gn:population": 0,
    "gn:timezone": "Asia/Shanghai",
    "iso:country": "CN",
    "name:und_x_variant": [
      "Fo’ao"
    ],
    "name:zho_x_preferred": [
      "佛凹"
    ],
    "wof:name": "Fo'ao",
    "wof:placetype": "locality"
  },
  "geometry": {
    "coordinates": [
      112.67422,
      22.29351
    ],
    "type": "Point"
  }
}