{
  "type": "Feature",
  "properties": {
    "gn:admin1_code": "29.0",
    "gn:asciiname": "Xiaomengpo",
    "gn:country_code": "CN",
    "gn:dem": 1540,
    "gn:feature_class": "P",
    "gn:feature_code": "PPL",
    "gn:name": "Xiaomengpo",
    "gn:population": 0,
    "gn:timezone": "Asia/Shanghai",
    "iso:country": "CN",
    "name:zho_x_preferred": [
      "小勐颇"
    ],
    "wof:name": "Xiaomengpo",
    "wof:placetype": "locality"
  },
  "geometry": {
    "coordinates": [
      99.6134,
      23.9043
    ],
    "type": "Point"
  }
}