{
  "type": "Feature",
  "properties": {
    "gn:admin1_code": "18.0",
    "gn:asciiname": "Xiangyangling",
    "gn:country_code": "CN",
    "gn:dem": 897,
    "gn:feature_class": "P",
    "gn:feature_code": "PPL",
    "gn:name": "Xiangyangling",
    "gn:population": 0,
    "gn:timezone": "Asia/Shanghai",
    "iso:country": "CN",
    "name:zho_x_preferred": [
      "向阳领"
    ],
    "wof:name": "Xiangyangling",
    "wof:placetype": "locality"
  },
  "geometry": {
    "coordinates": [
      108.257,
      26.2341
    ],
    "type": "Point"
  }
}