{
  "type": "Feature",
  "properties": {
    "gn:admin1_code": "11.0",
    "gn:asciiname": "Wuchong",
    "gn:country_code": "CN",
    "gn:dem": 456,
    "gn:feature_class": "P",
    "gn:feature_code": "PPL",
    "gn:name": "Wuchong",
    "gn:population": 0,
    "gn:timezone": "Asia/Shanghai",
    "iso:country": "CN",
    "name:zho_x_preferred": [
      "屋冲"
    ],
    "wof:name": "Wuchong",
    "wof:placetype": "locality"
  },
  "geometry": {
    "coordinates": [
      110.9159,
      28.62093
    ],
    "type": "Point"
  }
}