{
  "type": "Feature",
  "properties": {
    "gn:admin1_code": "26.0",
    "gn:asciiname": "Huangtutucun",
    "gn:country_code": "CN",
    "gn:dem": 736,
    "gn:feature_class": "P",
    "gn:feature_code": "PPL",
    "gn:name": "Huangtutucun",
    "gn:population": 0,
    "gn:timezone": "Asia/Shanghai",
    "iso:country": "CN",
    "name:zho_x_preferred": [
      "黄土凸村"
    ],
    "wof:name": "Huangtutucun",
    "wof:placetype": "locality"
  },
  "geometry": {
    "coordinates": [
      110.10493999999998,
      33.47854
    ],
    "type": "Point"
  }
}