{
  "type": "Feature",
  "properties": {
    "gn:admin1_code": "3",
    "gn:asciiname": "Dali",
    "gn:country_code": "CN",
    "gn:dem": 53,
    "gn:feature_class": "P",
    "gn:feature_code": "PPL",
    "gn:name": "Dali",
    "gn:population": 0,
    "gn:timezone": "Asia/Shanghai",
    "iso:country": "CN",
    "name:bul_x_preferred": [
      "Дали"
    ],
    "name:cat_x_preferred": [
      "Dali"
    ],
    "name:ceb_x_preferred": [
      "Dali"
    ],
    "name:dan_x_preferred": [
      "Dali"
    ],
    "name:deu_x_preferred": [
      "Dali"
    ],
    "name:fin_x_preferred": [
      "Dali"
    ],
    "name:fra_x_preferred": [
      "Dali"
    ],
    "name:heb_x_preferred": [
      "דאלי"
    ],
    "name:ita_x_preferred": [
      "Dali"
    ],
    "name:kat_x_preferred": [
      "დალი"
    ],
    "name:lit_x_preferred": [
      "Dali"
    ],
    "name:mlg_x_preferred": [
      "Dali"
    ],
    "name:nld_x_preferred": [
      "Dali"
    ],
    "name:nor_x_preferred": [
      "Dali"
    ],
    "name:pol_x_preferred": [
      "Dali"
    ],
    "name:por_x_preferred": [
      "Dali"
    ],
    "name:rus_x_preferred": [
      "река Дали"
    ],
    "name:rus_x_variant": [
      "Дали"
    ],
    "name:spa_x_preferred": [
      "Dali"
    ],
    "name:swe_x_preferred": [
      "Dali"
    ],
    "name:tat_x_preferred": [
      "Дали"
    ],
    "name:tgl_x_preferred": [
      "Dali"
    ],
    "name:tur_x_preferred": [
      "Dali"
    ],
    "name:ukr_x_preferred": [
      "Далі"
    ],
    "name:urd_x_preferred": [
      "ڈالی"
    ],
    "name:vie_x_preferred": [
      "Sông Dali"
    ],
    "name:zho_cn_x_preferred": [
      "大里溪"
    ],
    "name:zho_tw_x_preferred": [
      "大理河"
    ],
    "wof:name": "Dali",
    "wof:placetype": "locality"
  },
  "geometry": {
    "coordinates": [
      115.22861,
      27.81583
    ],
    "type": "Point"
  }
}