{
  "type": "Feature",
  "properties": {
    "gn:admin1_code": "5.0",
    "gn:asciiname": "Fangma Gouli",
    "gn:country_code": "CN",
    "gn:dem": 413,
    "gn:feature_class": "P",
    "gn:feature_code": "PPL",
    "gn:name": "Fangma Gouli",
    "gn:population": 0,
    "gn:timezone": "Asia/Shanghai",
    "iso:country": "CN",
    "name:zho_x_preferred": [
      "放马沟里"
    ],
    "wof:name": "Fangma Gouli",
    "wof:placetype": "locality"
  },
  "geometry": {
    "coordinates": [
      126.61034,
      43.62397
    ],
    "type": "Point"
  }
}