{
  "type": "Feature",
  "properties": {
    "gn:admin1_code": "26.0",
    "gn:asciiname": "Xiaqumu",
    "gn:country_code": "CN",
    "gn:dem": 840,
    "gn:feature_class": "P",
    "gn:feature_code": "PPL",
    "gn:name": "Xiaqumu",
    "gn:population": 0,
    "gn:timezone": "Asia/Shanghai",
    "iso:country": "CN",
    "name:zho_x_preferred": [
      "下曲木"
    ],
    "wof:name": "Xiaqumu",
    "wof:placetype": "locality"
  },
  "geometry": {
    "coordinates": [
      110.38141,
      36.2986
    ],
    "type": "Point"
  }
}