{
  "type": "Feature",
  "properties": {
    "gn:admin1_code": "01",
    "gn:asciiname": "Dingcheng",
    "gn:country_code": "CN",
    "gn:dem": 68,
    "gn:feature_class": "P",
    "gn:feature_code": "PPLA3",
    "gn:name": "Dingcheng",
    "gn:population": 0,
    "gn:timezone": "Asia/Shanghai",
    "iso:country": "CN",
    "name:ceb_x_preferred": [
      "Dingcheng"
    ],
    "name:und_x_variant": [
      "Dingyuan"
    ],
    "name:zho_x_preferred": [
      "Yüan-t’ing"
    ],
    "name:zho_x_variant": [
      "Ting-ch’eng-chen",
      "定城",
      "Ting-yüan-hsien",
      "Ting-yüan"
    ],
    "wof:name": "Dingcheng",
    "wof:placetype": "locality"
  },
  "geometry": {
    "coordinates": [
      117.65952,
      32.51609000000001
    ],
    "type": "Point"
  }
}