{
  "type": "Feature",
  "properties": {
    "gn:admin1_code": "32.0",
    "gn:asciiname": "Qinggang",
    "gn:country_code": "CN",
    "gn:dem": 412,
    "gn:feature_class": "P",
    "gn:feature_code": "PPL",
    "gn:name": "Qinggang",
    "gn:population": 0,
    "gn:timezone": "Asia/Shanghai",
    "iso:country": "CN",
    "name:ara_x_preferred": [
      "تشينكانغ"
    ],
    "name:ben_x_preferred": [
      "কুইংগ্যাং"
    ],
    "name:deu_x_preferred": [
      "Qinggang"
    ],
    "name:ell_x_preferred": [
      "Κινγκγκάνγκ"
    ],
    "name:eng_x_preferred": [
      "Qinggang"
    ],
    "name:fas_x_preferred": [
      "چینگگانگ"
    ],
    "name:fra_x_preferred": [
      "Qinggang"
    ],
    "name:heb_x_preferred": [
      "קווינגאנג"
    ],
    "name:hin_x_preferred": [
      "किंगैंग"
    ],
    "name:hun_x_preferred": [
      "Qinggang"
    ],
    "name:ind_x_preferred": [
      "Qinggang"
    ],
    "name:ita_x_preferred": [
      "Qinggang"
    ],
    "name:jpn_x_preferred": [
      "青岡鎮"
    ],
    "name:kor_x_preferred": [
      "칭강"
    ],
    "name:nld_x_preferred": [
      "Qinggang"
    ],
    "name:pol_x_preferred": [
      "Qinggang"
    ],
    "name:por_x_preferred": [
      "Qinggang"
    ],
    "name:rus_x_preferred": [
      "Цинган"
    ],
    "name:spa_x_preferred": [
      "Qinggang"
    ],
    "name:tur_x_preferred": [
      "Qinggang"
    ],
    "name:ukr_x_preferred": [
      "Цинган"
    ],
    "name:urd_x_preferred": [
      "قنگانگ"
    ],
    "name:vie_x_preferred": [
      "Thanh Cương"
    ],
    "name:zho_x_preferred": [
      "青岗"
    ],
    "wof:name": "Qinggang",
    "wof:placetype": "locality"
  },
  "geometry": {
    "coordinates": [
      104.25667,
      30.00839
    ],
    "type": "Point"
  }
}