{
  "type": "Feature",
  "properties": {
    "gn:admin1_code": "24",
    "gn:asciiname": "Sishilizhuang",
    "gn:country_code": "CN",
    "gn:dem": 1374,
    "gn:feature_class": "P",
    "gn:feature_code": "PPL",
    "gn:name": "Sishilizhuang",
    "gn:population": 0,
    "gn:timezone": "Asia/Shanghai",
    "iso:country": "CN",
    "name:und_x_variant": [
      "Ssu-shih-li-chuang",
      "Sishilizhuang",
      "四十里庄"
    ],
    "wof:name": "Sishilizhuang",
    "wof:placetype": "locality"
  },
  "geometry": {
    "coordinates": [
      112.82621,
      39.83627
    ],
    "type": "Point"
  }
}