{
  "type": "Feature",
  "properties": {
    "gn:admin1_code": "3",
    "gn:asciiname": "Huxu",
    "gn:country_code": "CN",
    "gn:dem": 48,
    "gn:feature_class": "P",
    "gn:feature_code": "PPLA4",
    "gn:name": "Huxu",
    "gn:population": 0,
    "gn:timezone": "Asia/Shanghai",
    "iso:country": "CN",
    "name:und_x_variant": [
      "虎圩",
      "Huxu Xiang",
      "虎圩乡"
    ],
    "wof:name": "Huxu",
    "wof:placetype": "locality"
  },
  "geometry": {
    "coordinates": [
      116.57448,
      28.17702
    ],
    "type": "Point"
  }
}