{
  "type": "Feature",
  "properties": {
    "gn:admin1_code": "19.0",
    "gn:asciiname": "Shangpozicun",
    "gn:country_code": "CN",
    "gn:dem": 32,
    "gn:feature_class": "P",
    "gn:feature_code": "PPL",
    "gn:name": "Shangpozicun",
    "gn:population": 0,
    "gn:timezone": "Asia/Shanghai",
    "iso:country": "CN",
    "name:zho_x_preferred": [
      "上坡子村"
    ],
    "wof:name": "Shangpozicun",
    "wof:placetype": "locality"
  },
  "geometry": {
    "coordinates": [
      120.84258,
      40.79102
    ],
    "type": "Point"
  }
}