{
  "type": "Feature",
  "properties": {
    "gn:admin1_code": "7",
    "gn:asciiname": "Puyang",
    "gn:country_code": "CN",
    "gn:dem": 604,
    "gn:feature_class": "P",
    "gn:feature_code": "PPL",
    "gn:name": "Puyang",
    "gn:population": 0,
    "gn:timezone": "Asia/Shanghai",
    "iso:country": "CN",
    "name:afr_x_preferred": [
      "Puyang"
    ],
    "name:ara_x_preferred": [
      "بويانغ"
    ],
    "name:bul_x_preferred": [
      "Пуян"
    ],
    "name:cdo_x_preferred": [
      "Bŭk-iòng"
    ],
    "name:ces_x_preferred": [
      "Pchu-jang"
    ],
    "name:dan_x_preferred": [
      "Puyang"
    ],
    "name:deu_x_preferred": [
      "Puyang"
    ],
    "name:epo_x_preferred": [
      "Pujang"
    ],
    "name:eus_x_preferred": [
      "Puyang"
    ],
    "name:fas_x_preferred": [
      "پویانگ"
    ],
    "name:fin_x_preferred": [
      "Puyang"
    ],
    "name:fra_x_preferred": [
      "Puyang"
    ],
    "name:heb_x_preferred": [
      "פויאנג"
    ],
    "name:hun_x_preferred": [
      "Puyang"
    ],
    "name:ita_x_preferred": [
      "Puyang"
    ],
    "name:jpn_x_preferred": [
      "濮陽市"
    ],
    "name:kik_x_preferred": [
      "Puyang"
    ],
    "name:kor_x_preferred": [
      "푸양시"
    ],
    "name:mlg_x_preferred": [
      "Puyang"
    ],
    "name:nld_x_preferred": [
      "Puyang"
    ],
    "name:nno_x_preferred": [
      "Puyang"
    ],
    "name:nor_x_preferred": [
      "Puyang"
    ],
    "name:pam_x_preferred": [
      "Puyang"
    ],
    "name:pol_x_preferred": [
      "Puyang"
    ],
    "name:por_x_preferred": [
      "Puyang"
    ],
    "name:rus_x_preferred": [
      "Пуян"
    ],
    "name:spa_x_preferred": [
      "Puyang"
    ],
    "name:srp_x_preferred": [
      "Пујанг"
    ],
    "name:swe_x_preferred": [
      "Puyang"
    ],
    "name:tur_x_preferred": [
      "Puyang"
    ],
    "name:ukr_x_preferred": [
      "Пуян"
    ],
    "name:und_x_variant": [
      "蒲洋"
    ],
    "name:urd_x_preferred": [
      "پویانگ"
    ],
    "name:vie_x_preferred": [
      "Bộc Dương"
    ],
    "name:war_x_preferred": [
      "Puyang"
    ],
    "name:zho_x_preferred": [
      "濮阳市"
    ],
    "wof:name": "Puyang",
    "wof:placetype": "locality"
  },
  "geometry": {
    "coordinates": [
      119.7525,
      27.17688
    ],
    "type": "Point"
  }
}