{
  "type": "Feature",
  "properties": {
    "gn:admin1_code": "25",
    "gn:asciiname": "Guojiaxiakou",
    "gn:country_code": "CN",
    "gn:dem": 8,
    "gn:feature_class": "P",
    "gn:feature_code": "PPL",
    "gn:name": "Guojiaxiakou",
    "gn:population": 0,
    "gn:timezone": "Asia/Shanghai",
    "iso:country": "CN",
    "name:zho_x_preferred": [
      "郭家下口"
    ],
    "wof:name": "Guojiaxiakou",
    "wof:placetype": "locality"
  },
  "geometry": {
    "coordinates": [
      118.905,
      36.991
    ],
    "type": "Point"
  }
}