{
  "type": "Feature",
  "properties": {
    "gn:admin1_code": "12.0",
    "gn:asciiname": "Laoyayu",
    "gn:country_code": "CN",
    "gn:dem": 655,
    "gn:feature_class": "P",
    "gn:feature_code": "PPL",
    "gn:name": "Laoyayu",
    "gn:population": 0,
    "gn:timezone": "Asia/Shanghai",
    "iso:country": "CN",
    "name:zho_x_preferred": [
      "老鸦峪"
    ],
    "wof:name": "Laoyayu",
    "wof:placetype": "locality"
  },
  "geometry": {
    "coordinates": [
      111.1172,
      32.19409
    ],
    "type": "Point"
  }
}