{
  "type": "Feature",
  "properties": {
    "gn:admin1_code": "19",
    "gn:asciiname": "Hepingcun",
    "gn:country_code": "CN",
    "gn:dem": 220,
    "gn:feature_class": "P",
    "gn:feature_code": "PPL",
    "gn:name": "Hepingcun",
    "gn:population": 0,
    "gn:timezone": "Asia/Shanghai",
    "iso:country": "CN",
    "name:zho_x_preferred": [
      "和平村"
    ],
    "wof:name": "Hepingcun",
    "wof:placetype": "locality"
  },
  "geometry": {
    "coordinates": [
      125.31745,
      41.13088
    ],
    "type": "Point"
  }
}