{
  "type": "Feature",
  "properties": {
    "gn:admin1_code": "16.0",
    "gn:asciiname": "Xinfeng",
    "gn:country_code": "CN",
    "gn:dem": 261,
    "gn:feature_class": "P",
    "gn:feature_code": "PPL",
    "gn:name": "Xinfeng",
    "gn:population": 0,
    "gn:timezone": "Asia/Shanghai",
    "iso:country": "CN",
    "name:ceb_x_preferred": [
      "Xinfeng"
    ],
    "name:deu_x_preferred": [
      "Xinfeng"
    ],
    "name:fra_x_preferred": [
      "Xinfeng"
    ],
    "name:kor_x_preferred": [
      "신펑현"
    ],
    "name:nor_x_preferred": [
      "Xinfeng"
    ],
    "name:swe_x_preferred": [
      "Xinfeng"
    ],
    "name:zho_x_preferred": [
      "新风"
    ],
    "wof:name": "Xinfeng",
    "wof:placetype": "locality"
  },
  "geometry": {
    "coordinates": [
      107.947,
      23.425
    ],
    "type": "Point"
  }
}