{
  "type": "Feature",
  "properties": {
    "gn:admin1_code": "30",
    "gn:asciiname": "Jiang'an",
    "gn:country_code": "CN",
    "gn:dem": 17,
    "gn:feature_class": "P",
    "gn:feature_code": "PPL",
    "gn:name": "Jiang’an",
    "gn:population": 0,
    "gn:timezone": "Asia/Urumqi",
    "iso:country": "CN",
    "name:deu_x_preferred": [
      "Jiang’an"
    ],
    "name:fra_x_preferred": [
      "Jiang'an"
    ],
    "name:nor_x_preferred": [
      "Jiang'an"
    ],
    "name:rus_x_preferred": [
      "Цзянъань"
    ],
    "name:swe_x_preferred": [
      "Jiang'an"
    ],
    "name:zho_x_preferred": [
      "江岸"
    ],
    "name:zho_x_variant": [
      "Jiang’an"
    ],
    "wof:name": "Jiang'an",
    "wof:placetype": "locality"
  },
  "geometry": {
    "coordinates": [
      110.67314,
      21.63244
    ],
    "type": "Point"
  }
}