{
  "type": "Feature",
  "properties": {
    "gn:admin1_code": "32.0",
    "gn:asciiname": "Ruo'erzhai",
    "gn:country_code": "CN",
    "gn:dem": 3416,
    "gn:feature_class": "P",
    "gn:feature_code": "PPL",
    "gn:name": "Ruo’erzhai",
    "gn:population": 0,
    "gn:timezone": "Asia/Shanghai",
    "iso:country": "CN",
    "name:und_x_variant": [
      "Ruo’erzhai"
    ],
    "name:zho_x_preferred": [
      "若尔寨"
    ],
    "wof:name": "Ruo'erzhai",
    "wof:placetype": "locality"
  },
  "geometry": {
    "coordinates": [
      103.753,
      32.3861
    ],
    "type": "Point"
  }
}