{
  "type": "Feature",
  "properties": {
    "gn:admin1_code": "30",
    "gn:asciiname": "Rongxiapo",
    "gn:country_code": "CN",
    "gn:dem": 45,
    "gn:feature_class": "P",
    "gn:feature_code": "PPL",
    "gn:name": "Rongxiapo",
    "gn:population": 0,
    "gn:timezone": "Asia/Urumqi",
    "iso:country": "CN",
    "name:zho_x_preferred": [
      "荣下坡"
    ],
    "wof:name": "Rongxiapo",
    "wof:placetype": "locality"
  },
  "geometry": {
    "coordinates": [
      111.05255,
      21.74999
    ],
    "type": "Point"
  }
}