{
  "type": "Feature",
  "properties": {
    "gn:admin1_code": "15.0",
    "gn:asciiname": "Duanjiazhuang",
    "gn:country_code": "CN",
    "gn:dem": 2409,
    "gn:feature_class": "P",
    "gn:feature_code": "PPL",
    "gn:name": "Duanjiazhuang",
    "gn:population": 0,
    "gn:timezone": "Asia/Shanghai",
    "iso:country": "CN",
    "name:zho_x_preferred": [
      "段家庄"
    ],
    "wof:name": "Duanjiazhuang",
    "wof:placetype": "locality"
  },
  "geometry": {
    "coordinates": [
      103.72,
      37.4025
    ],
    "type": "Point"
  }
}