{
  "type": "Feature",
  "properties": {
    "gn:admin1_code": "5.0",
    "gn:asciiname": "Wudaoyangcha",
    "gn:country_code": "CN",
    "gn:dem": 719,
    "gn:feature_class": "P",
    "gn:feature_code": "PPL",
    "gn:name": "Wudaoyangcha",
    "gn:population": 0,
    "gn:timezone": "Asia/Shanghai",
    "iso:country": "CN",
    "name:und_x_variant": [
      "五道羊岔"
    ],
    "wof:name": "Wudaoyangcha",
    "wof:placetype": "locality"
  },
  "geometry": {
    "coordinates": [
      126.91469,
      41.8792
    ],
    "type": "Point"
  }
}