{
  "type": "Feature",
  "properties": {
    "gn:admin1_code": "32.0",
    "gn:asciiname": "Xikou",
    "gn:country_code": "CN",
    "gn:dem": 295,
    "gn:feature_class": "P",
    "gn:feature_code": "PPL",
    "gn:name": "Xikou",
    "gn:population": 0,
    "gn:timezone": "Asia/Shanghai",
    "iso:country": "CN",
    "name:fas_x_preferred": [
      "شیکو"
    ],
    "name:ita_x_preferred": [
      "Xikou"
    ],
    "name:nor_x_preferred": [
      "Xikou"
    ],
    "name:swe_x_preferred": [
      "Xikou"
    ],
    "name:und_x_variant": [
      "Hsi-k’ou"
    ],
    "name:zho_x_preferred": [
      "溪口"
    ],
    "name:zho_x_variant": [
      "溪口镇"
    ],
    "wof:name": "Xikou",
    "wof:placetype": "locality"
  },
  "geometry": {
    "coordinates": [
      106.69028,
      30.17078
    ],
    "type": "Point"
  }
}