{
  "type": "Feature",
  "properties": {
    "gn:admin1_code": "26.0",
    "gn:asciiname": "Baguamiao",
    "gn:country_code": "CN",
    "gn:dem": 1594,
    "gn:feature_class": "P",
    "gn:feature_code": "PPL",
    "gn:name": "Baguamiao",
    "gn:population": 0,
    "gn:timezone": "Asia/Shanghai",
    "iso:country": "CN",
    "name:zho_x_preferred": [
      "八卦庙"
    ],
    "wof:name": "Baguamiao",
    "wof:placetype": "locality"
  },
  "geometry": {
    "coordinates": [
      106.88648,
      34.18997
    ],
    "type": "Point"
  }
}