{
  "type": "Feature",
  "properties": {
    "gn:admin1_code": "7",
    "gn:asciiname": "Bolu",
    "gn:country_code": "CN",
    "gn:dem": 432,
    "gn:feature_class": "P",
    "gn:feature_code": "PPL",
    "gn:name": "Bolu",
    "gn:population": 0,
    "gn:timezone": "Asia/Shanghai",
    "iso:country": "CN",
    "name:ara_x_preferred": [
      "بولو"
    ],
    "name:ast_x_preferred": [
      "Bolu"
    ],
    "name:aze_x_preferred": [
      "Bolu"
    ],
    "name:bel_x_preferred": [
      "Балу"
    ],
    "name:bul_x_preferred": [
      "Болу"
    ],
    "name:cat_x_preferred": [
      "Bolu"
    ],
    "name:ceb_x_preferred": [
      "Bolu"
    ],
    "name:ces_x_preferred": [
      "Bolu"
    ],
    "name:deu_x_preferred": [
      "Bolu"
    ],
    "name:diq_x_preferred": [
      "Bolu"
    ],
    "name:ell_x_preferred": [
      "Μπολού"
    ],
    "name:epo_x_preferred": [
      "Bolu"
    ],
    "name:fas_x_preferred": [
      "بولو"
    ],
    "name:fra_x_preferred": [
      "Bolu"
    ],
    "name:gag_x_preferred": [
      "Bolu"
    ],
    "name:heb_x_preferred": [
      "בולו"
    ],
    "name:hye_x_preferred": [
      "Բոլու"
    ],
    "name:ita_x_preferred": [
      "Bolu"
    ],
    "name:jpn_x_preferred": [
      "ボル"
    ],
    "name:kat_x_preferred": [
      "ბოლუ"
    ],
    "name:kin_x_preferred": [
      "Bolu"
    ],
    "name:lit_x_preferred": [
      "Bolu"
    ],
    "name:lrc_x_preferred": [
      "بولی"
    ],
    "name:min_x_preferred": [
      "Bolu"
    ],
    "name:mrj_x_preferred": [
      "Болу"
    ],
    "name:msa_x_preferred": [
      "Bolu"
    ],
    "name:nld_x_preferred": [
      "Bolu"
    ],
    "name:nno_x_preferred": [
      "Bolu"
    ],
    "name:nor_x_preferred": [
      "Bolu"
    ],
    "name:pnb_x_preferred": [
      "بولو"
    ],
    "name:pol_x_preferred": [
      "Bolu"
    ],
    "name:por_x_preferred": [
      "Bolu"
    ],
    "name:ron_x_preferred": [
      "Bolu"
    ],
    "name:rus_x_preferred": [
      "Болу"
    ],
    "name:sco_x_preferred": [
      "Bolu"
    ],
    "name:spa_x_preferred": [
      "Bolu"
    ],
    "name:srp_x_preferred": [
      "Болу"
    ],
    "name:swa_x_preferred": [
      "Bolu"
    ],
    "name:swe_x_preferred": [
      "Bolu"
    ],
    "name:tur_x_preferred": [
      "Bolu"
    ],
    "name:udm_x_preferred": [
      "Болу"
    ],
    "name:ukr_x_preferred": [
      "Болу"
    ],
    "name:urd_x_preferred": [
      "بولو"
    ],
    "name:vie_x_preferred": [
      "Bolu"
    ],
    "name:vol_x_preferred": [
      "Bolu"
    ],
    "name:war_x_preferred": [
      "Bolu"
    ],
    "name:zho_x_preferred": [
      "拨炉"
    ],
    "name:zho_x_variant": [
      "博盧"
    ],
    "wof:name": "Bolu",
    "wof:placetype": "locality"
  },
  "geometry": {
    "coordinates": [
      117.4875,
      24.96
    ],
    "type": "Point"
  }
}