{
  "type": "Feature",
  "properties": {
    "gn:admin1_code": "10",
    "gn:asciiname": "Feicheng",
    "gn:country_code": "CN",
    "gn:dem": 22,
    "gn:feature_class": "P",
    "gn:feature_code": "PPL",
    "gn:name": "Feicheng",
    "gn:population": 0,
    "gn:timezone": "Asia/Shanghai",
    "iso:country": "CN",
    "name:deu_x_preferred": [
      "Feicheng"
    ],
    "name:ell_x_preferred": [
      "Φέιτσενγκ"
    ],
    "name:fas_x_preferred": [
      "فیچنگ"
    ],
    "name:fra_x_preferred": [
      "Feicheng"
    ],
    "name:hak_x_preferred": [
      "Phì-sàng"
    ],
    "name:ita_x_preferred": [
      "Feicheng"
    ],
    "name:jpn_x_preferred": [
      "肥城市"
    ],
    "name:kik_x_preferred": [
      "Feicheng"
    ],
    "name:kor_x_preferred": [
      "페이청시"
    ],
    "name:mlg_x_preferred": [
      "Feicheng"
    ],
    "name:nor_x_preferred": [
      "Feicheng"
    ],
    "name:rus_x_preferred": [
      "Фэйчэн"
    ],
    "name:swe_x_preferred": [
      "Feicheng"
    ],
    "name:vie_x_preferred": [
      "Phì Thành"
    ],
    "name:zho_x_preferred": [
      "肥城"
    ],
    "name:zho_x_variant": [
      "肥城市"
    ],
    "wof:name": "Feicheng",
    "wof:placetype": "locality"
  },
  "geometry": {
    "coordinates": [
      116.31307,
      37.62473
    ],
    "type": "Point"
  }
}