{
  "type": "Feature",
  "properties": {
    "gn:admin1_code": "29.0",
    "gn:asciiname": "Dashiban",
    "gn:country_code": "CN",
    "gn:dem": 1914,
    "gn:feature_class": "P",
    "gn:feature_code": "PPL",
    "gn:name": "Dashiban",
    "gn:population": 0,
    "gn:timezone": "Asia/Shanghai",
    "iso:country": "CN",
    "name:zho_x_preferred": [
      "大石板"
    ],
    "wof:name": "Dashiban",
    "wof:placetype": "locality"
  },
  "geometry": {
    "coordinates": [
      103.588,
      23.4526
    ],
    "type": "Point"
  }
}