{
  "type": "Feature",
  "properties": {
    "iso:country": "CN",
    "name:ara_x_preferred": [
      "جينشى"
    ],
    "name:ben_x_preferred": [
      "জিনশি"
    ],
    "name:ell_x_preferred": [
      "Τζίνξι"
    ],
    "name:eng_x_preferred": [
      "Jinxi"
    ],
    "name:fas_x_preferred": [
      "جینکسی"
    ],
    "name:heb_x_preferred": [
      "ג'ינקסי"
    ],
    "name:hin_x_preferred": [
      "जिंक्सी"
    ],
    "name:hun_x_preferred": [
      "Csinhszi"
    ],
    "name:ind_x_preferred": [
      "Jinxi"
    ],
    "name:ita_x_preferred": [
      "Jinxi"
    ],
    "name:jpn_x_preferred": [
      "錦渓鎮"
    ],
    "name:kor_x_preferred": [
      "진시"
    ],
    "name:nld_x_preferred": [
      "Jinxi"
    ],
    "name:pol_x_preferred": [
      "Jinxi"
    ],
    "name:rus_x_preferred": [
      "Цзиньси"
    ],
    "name:swe_x_preferred": [
      "Jinxi"
    ],
    "name:tur_x_preferred": [
      "Jinxi"
    ],
    "name:ukr_x_preferred": [
      "Цзиньсі"
    ],
    "name:urd_x_preferred": [
      "جنزی"
    ],
    "name:vie_x_preferred": [
      "Kim Khê"
    ],
    "name:zho_cn_x_preferred": [
      "锦溪"
    ],
    "name:zho_tw_x_preferred": [
      "錦溪"
    ],
    "name:zho_x_preferred": [
      "锦西市"
    ],
    "qs:name": "锦西市",
    "qs:name_adm0": "中國",
    "qs:name_adm1": "辽宁省",
    "qs:photos": 40,
    "qs:photos_1k": 8,
    "qs:photos_9k": 1,
    "qs:photos_9r": 2,
    "qs:photos_all": 40,
    "qs:photos_sr": 2,
    "qs:placetype": "Town",
    "qs:pop_sr": "0",
    "wof:name": "Jinxi",
    "wof:placetype": "locality"
  },
  "geometry": {
    "coordinates": [
      120.852355,
      40.741014
    ],
    "type": "Point"
  }
}