{
  "type": "Feature",
  "properties": {
    "gn:admin1_code": "12.0",
    "gn:asciiname": "Jieshou",
    "gn:country_code": "CN",
    "gn:dem": 444,
    "gn:feature_class": "P",
    "gn:feature_code": "PPL",
    "gn:name": "Jieshou",
    "gn:population": 0,
    "gn:timezone": "Asia/Shanghai",
    "iso:country": "CN",
    "name:ara_x_preferred": [
      "جيشو"
    ],
    "name:ceb_x_preferred": [
      "Jieshou"
    ],
    "name:deu_x_preferred": [
      "Jieshou"
    ],
    "name:fas_x_preferred": [
      "ژایشو"
    ],
    "name:fra_x_preferred": [
      "Jieshou"
    ],
    "name:heb_x_preferred": [
      "ג'יאנשואו"
    ],
    "name:hun_x_preferred": [
      "Jieshou"
    ],
    "name:ita_x_preferred": [
      "Jieshou"
    ],
    "name:jpn_x_preferred": [
      "界首市"
    ],
    "name:kik_x_preferred": [
      "Jieshou"
    ],
    "name:kor_x_preferred": [
      "제서우시"
    ],
    "name:mlg_x_preferred": [
      "Jieshou"
    ],
    "name:msa_x_preferred": [
      "Jieshou"
    ],
    "name:mwl_x_preferred": [
      "Jieshou"
    ],
    "name:nld_x_preferred": [
      "Jieshou"
    ],
    "name:nor_x_preferred": [
      "Jieshou"
    ],
    "name:pam_x_preferred": [
      "Jieshou"
    ],
    "name:pnb_x_preferred": [
      "جیشوؤ"
    ],
    "name:pol_x_preferred": [
      "Jieshou"
    ],
    "name:por_x_preferred": [
      "Jieshou"
    ],
    "name:spa_x_preferred": [
      "Jièshŏu Shì"
    ],
    "name:swe_x_preferred": [
      "Jieshou"
    ],
    "name:urd_x_preferred": [
      "جئیشوو"
    ],
    "name:vie_x_preferred": [
      "Giới Thủ"
    ],
    "name:war_x_preferred": [
      "Jieshou"
    ],
    "name:zho_x_preferred": [
      "Jieshou"
    ],
    "name:zho_x_variant": [
      "界首",
      "界首市"
    ],
    "wof:name": "Jieshou",
    "wof:placetype": "locality"
  },
  "geometry": {
    "coordinates": [
      114.91604,
      29.66
    ],
    "type": "Point"
  }
}