{
  "type": "Feature",
  "properties": {
    "gn:admin1_code": "9.0",
    "gn:asciiname": "Lixiao'an",
    "gn:country_code": "CN",
    "gn:dem": 82,
    "gn:feature_class": "P",
    "gn:feature_code": "PPL",
    "gn:name": "Lixiao’an",
    "gn:population": 0,
    "gn:timezone": "Asia/Shanghai",
    "iso:country": "CN",
    "name:und_x_variant": [
      "Lixiao’an"
    ],
    "name:zho_x_preferred": [
      "李小安"
    ],
    "wof:name": "Lixiao'an",
    "wof:placetype": "locality"
  },
  "geometry": {
    "coordinates": [
      113.98343,
      34.78534000000001
    ],
    "type": "Point"
  }
}