{
  "type": "Feature",
  "properties": {
    "gn:admin1_code": "16.0",
    "gn:asciiname": "Luzhi",
    "gn:country_code": "CN",
    "gn:dem": 134,
    "gn:feature_class": "P",
    "gn:feature_code": "PPL",
    "gn:name": "Luzhi",
    "gn:population": 0,
    "gn:timezone": "Asia/Shanghai",
    "iso:country": "CN",
    "name:fra_x_preferred": [
      "Luzhi"
    ],
    "name:jpn_x_preferred": [
      "ロク直鎮"
    ],
    "name:wuu_x_preferred": [
      "甪直镇"
    ],
    "name:zho_x_preferred": [
      "渌治"
    ],
    "name:zho_x_variant": [
      "甪直镇"
    ],
    "wof:name": "Luzhi",
    "wof:placetype": "locality"
  },
  "geometry": {
    "coordinates": [
      107.621,
      23.3236
    ],
    "type": "Point"
  }
}