{
  "type": "Feature",
  "properties": {
    "gn:admin1_code": "5.0",
    "gn:asciiname": "Xinxing",
    "gn:country_code": "CN",
    "gn:dem": 146,
    "gn:feature_class": "P",
    "gn:feature_code": "PPL",
    "gn:name": "Xinxing",
    "gn:population": 0,
    "gn:timezone": "Asia/Shanghai",
    "iso:country": "CN",
    "name:ceb_x_preferred": [
      "Xinxing"
    ],
    "name:deu_x_preferred": [
      "Xinxing"
    ],
    "name:eus_x_preferred": [
      "Xinxing"
    ],
    "name:fra_x_preferred": [
      "Xinxing"
    ],
    "name:nor_x_preferred": [
      "Xinxing"
    ],
    "name:rus_x_preferred": [
      "Синьсин"
    ],
    "name:swe_x_preferred": [
      "Xinxing"
    ],
    "name:zho_x_preferred": [
      "新兴"
    ],
    "wof:name": "Xinxing",
    "wof:placetype": "locality"
  },
  "geometry": {
    "coordinates": [
      122.89244,
      45.07305
    ],
    "type": "Point"
  }
}