{
  "type": "Feature",
  "properties": {
    "gn:admin1_code": "8.0",
    "gn:asciiname": "Xianwaimao Luchang",
    "gn:country_code": "CN",
    "gn:dem": 255,
    "gn:feature_class": "P",
    "gn:feature_code": "PPLF",
    "gn:name": "Xianwaimao Luchang",
    "gn:population": 0,
    "gn:timezone": "Asia/Shanghai",
    "iso:country": "CN",
    "name:zho_x_preferred": [
      "县外贸鹿场"
    ],
    "wof:name": "Xianwaimao Luchang",
    "wof:placetype": "locality"
  },
  "geometry": {
    "coordinates": [
      127.9663,
      49.43056
    ],
    "type": "Point"
  }
}