{
  "type": "Feature",
  "properties": {
    "gn:admin1_code": "16.0",
    "gn:asciiname": "Liushou",
    "gn:country_code": "CN",
    "gn:dem": 377,
    "gn:feature_class": "P",
    "gn:feature_code": "PPL",
    "gn:name": "Liushou",
    "gn:population": 0,
    "gn:timezone": "Asia/Shanghai",
    "iso:country": "CN",
    "name:zho_x_preferred": [
      "六守"
    ],
    "wof:name": "Liushou",
    "wof:placetype": "locality"
  },
  "geometry": {
    "coordinates": [
      107.482,
      23.8708
    ],
    "type": "Point"
  }
}