{
  "type": "Feature",
  "properties": {
    "gn:admin1_code": "11.0",
    "gn:asciiname": "Sifangli",
    "gn:country_code": "CN",
    "gn:dem": 179,
    "gn:feature_class": "P",
    "gn:feature_code": "PPL",
    "gn:name": "Sifangli",
    "gn:population": 0,
    "gn:timezone": "Asia/Shanghai",
    "iso:country": "CN",
    "name:zho_x_preferred": [
      "四房里"
    ],
    "wof:name": "Sifangli",
    "wof:placetype": "locality"
  },
  "geometry": {
    "coordinates": [
      111.04166,
      28.36126
    ],
    "type": "Point"
  }
}