{
  "type": "Feature",
  "properties": {
    "gn:admin1_code": "19.0",
    "gn:asciiname": "Wuwei",
    "gn:country_code": "CN",
    "gn:dem": 160,
    "gn:feature_class": "P",
    "gn:feature_code": "PPL",
    "gn:name": "Wuwei",
    "gn:population": 0,
    "gn:timezone": "Asia/Shanghai",
    "iso:country": "CN",
    "name:ceb_x_preferred": [
      "Wuwei"
    ],
    "name:ces_x_preferred": [
      "Wu-wej"
    ],
    "name:deu_x_preferred": [
      "Wuwei"
    ],
    "name:fra_x_preferred": [
      "Wuwei"
    ],
    "name:heb_x_preferred": [
      "וווויי"
    ],
    "name:hun_x_preferred": [
      "Wuwei"
    ],
    "name:jpn_x_preferred": [
      "ウーウェイ"
    ],
    "name:kor_x_preferred": [
      "우웨이"
    ],
    "name:mlg_x_preferred": [
      "Wuwei"
    ],
    "name:nor_x_preferred": [
      "Wuwei"
    ],
    "name:pol_x_preferred": [
      "Wuwei"
    ],
    "name:swe_x_preferred": [
      "Wuwei"
    ],
    "name:und_x_variant": [
      "五味"
    ],
    "wof:name": "Wuwei",
    "wof:placetype": "locality"
  },
  "geometry": {
    "coordinates": [
      124.08362,
      41.8103
    ],
    "type": "Point"
  }
}