{
  "type": "Feature",
  "properties": {
    "gn:admin1_code": "3.0",
    "gn:asciiname": "Yuekou",
    "gn:country_code": "CN",
    "gn:dem": 74,
    "gn:feature_class": "P",
    "gn:feature_code": "PPL",
    "gn:name": "Yuekou",
    "gn:population": 0,
    "gn:timezone": "Asia/Shanghai",
    "iso:country": "CN",
    "name:und_x_variant": [
      "Yüeh-k’ou",
      "Yuekou",
      "岳口",
      "Yuekouxiang",
      "岳口乡"
    ],
    "wof:name": "Yuekou",
    "wof:placetype": "locality"
  },
  "geometry": {
    "coordinates": [
      116.56857,
      27.66338
    ],
    "type": "Point"
  }
}