{
  "type": "Feature",
  "properties": {
    "gn:admin1_code": "19.0",
    "gn:asciiname": "Dadongliang",
    "gn:country_code": "CN",
    "gn:dem": 392,
    "gn:feature_class": "P",
    "gn:feature_code": "PPL",
    "gn:name": "Dadongliang",
    "gn:population": 0,
    "gn:timezone": "Asia/Shanghai",
    "iso:country": "CN",
    "name:zho_x_preferred": [
      "大东梁"
    ],
    "wof:name": "Dadongliang",
    "wof:placetype": "locality"
  },
  "geometry": {
    "coordinates": [
      119.8678,
      41.37916
    ],
    "type": "Point"
  }
}