{
  "type": "Feature",
  "properties": {
    "gn:admin1_code": "12.0",
    "gn:asciiname": "Sunjiagang",
    "gn:country_code": "CN",
    "gn:dem": 73,
    "gn:feature_class": "P",
    "gn:feature_code": "PPL",
    "gn:name": "Sunjiagang",
    "gn:population": 0,
    "gn:timezone": "Asia/Shanghai",
    "iso:country": "CN",
    "name:zho_x_preferred": [
      "孙家岗"
    ],
    "wof:name": "Sunjiagang",
    "wof:placetype": "locality"
  },
  "geometry": {
    "coordinates": [
      112.20997,
      31.60543
    ],
    "type": "Point"
  }
}