{
  "type": "Feature",
  "properties": {
    "gn:admin1_code": "7.0",
    "gn:asciiname": "Jushuhou",
    "gn:country_code": "CN",
    "gn:dem": 98,
    "gn:feature_class": "P",
    "gn:feature_code": "PPL",
    "gn:name": "Jushuhou",
    "gn:population": 0,
    "gn:timezone": "Asia/Shanghai",
    "iso:country": "CN",
    "name:zho_x_preferred": [
      "桔树后"
    ],
    "wof:name": "Jushuhou",
    "wof:placetype": "locality"
  },
  "geometry": {
    "coordinates": [
      118.31324,
      26.5549
    ],
    "type": "Point"
  }
}