{
  "type": "Feature",
  "properties": {
    "gn:admin1_code": "10",
    "gn:asciiname": "Xiaobaizhuang",
    "gn:country_code": "CN",
    "gn:dem": 15,
    "gn:feature_class": "P",
    "gn:feature_code": "PPL",
    "gn:name": "Xiaobaizhuang",
    "gn:population": 0,
    "gn:timezone": "Asia/Shanghai",
    "iso:country": "CN",
    "name:zho_x_preferred": [
      "小白庄"
    ],
    "wof:name": "Xiaobaizhuang",
    "wof:placetype": "locality"
  },
  "geometry": {
    "coordinates": [
      116.3958,
      37.95381
    ],
    "type": "Point"
  }
}