{
  "type": "Feature",
  "properties": {
    "gn:admin1_code": "26.0",
    "gn:asciiname": "Wanghugoucun",
    "gn:country_code": "CN",
    "gn:dem": 1078,
    "gn:feature_class": "P",
    "gn:feature_code": "PPL",
    "gn:name": "Wanghugoucun",
    "gn:population": 0,
    "gn:timezone": "Asia/Shanghai",
    "iso:country": "CN",
    "name:zho_x_preferred": [
      "王虎沟村"
    ],
    "wof:name": "Wanghugoucun",
    "wof:placetype": "locality"
  },
  "geometry": {
    "coordinates": [
      110.34603,
      33.98551
    ],
    "type": "Point"
  }
}