{
  "type": "Feature",
  "properties": {
    "gn:admin1_code": "19.0",
    "gn:asciiname": "Houchengzi",
    "gn:country_code": "CN",
    "gn:dem": 170,
    "gn:feature_class": "P",
    "gn:feature_code": "PPL",
    "gn:name": "Houchengzi",
    "gn:population": 0,
    "gn:timezone": "Asia/Shanghai",
    "iso:country": "CN",
    "name:zho_x_preferred": [
      "后城子"
    ],
    "wof:name": "Houchengzi",
    "wof:placetype": "locality"
  },
  "geometry": {
    "coordinates": [
      120.1225,
      40.84705
    ],
    "type": "Point"
  }
}