{
  "type": "Feature",
  "properties": {
    "gn:admin1_code": "9.0",
    "gn:asciiname": "Xiaoligang",
    "gn:country_code": "CN",
    "gn:dem": 129,
    "gn:feature_class": "P",
    "gn:feature_code": "PPL",
    "gn:name": "Xiaoligang",
    "gn:population": 0,
    "gn:timezone": "Asia/Shanghai",
    "iso:country": "CN",
    "name:zho_x_preferred": [
      "小李岗"
    ],
    "wof:name": "Xiaoligang",
    "wof:placetype": "locality"
  },
  "geometry": {
    "coordinates": [
      112.88756,
      32.53058
    ],
    "type": "Point"
  }
}