{
  "type": "Feature",
  "properties": {
    "gn:admin1_code": "10.0",
    "gn:asciiname": "Anju Dongli",
    "gn:country_code": "CN",
    "gn:dem": 3,
    "gn:feature_class": "P",
    "gn:feature_code": "PPL",
    "gn:name": "Anju Dongli",
    "gn:population": 0,
    "gn:timezone": "Asia/Shanghai",
    "iso:country": "CN",
    "name:zho_x_preferred": [
      "安居东里"
    ],
    "wof:name": "Anju Dongli",
    "wof:placetype": "locality"
  },
  "geometry": {
    "coordinates": [
      119.62458,
      39.93182
    ],
    "type": "Point"
  }
}