{
  "type": "Feature",
  "properties": {
    "gn:country": "CN",
    "gn:fcode": "PPL",
    "gn:population": 87961,
    "iso:country": "CN",
    "name:und_x_variant": [
      "Yü"
    ],
    "name:zho_x_preferred": [
      "颍川"
    ],
    "qs:name": "峪州",
    "qs:name_adm0": "中國",
    "qs:name_adm1": "河南省",
    "qs:photos_9k": 1,
    "qs:photos_9r": 1,
    "qs:photos_all": 1,
    "qs:photos_sr": 0,
    "qs:placetype": "Town",
    "qs:pop_sr": "8",
    "wof:name": "峪州",
    "wof:placetype": "locality",
    "wof:population": 87961
  },
  "geometry": {
    "coordinates": [
      113.46389,
      34.16278
    ],
    "type": "Point"
  }
}