{
  "type": "Feature",
  "properties": {
    "gn:admin1_code": "16.0",
    "gn:asciiname": "Poxin",
    "gn:country_code": "CN",
    "gn:dem": 72,
    "gn:feature_class": "P",
    "gn:feature_code": "PPL",
    "gn:name": "Poxin",
    "gn:population": 0,
    "gn:timezone": "Asia/Shanghai",
    "iso:country": "CN",
    "name:zho_x_preferred": [
      "坡心"
    ],
    "wof:name": "Poxin",
    "wof:placetype": "locality"
  },
  "geometry": {
    "coordinates": [
      110.115,
      22.5318
    ],
    "type": "Point"
  }
}