{
  "type": "Feature",
  "properties": {
    "gn:admin1_code": "14.0",
    "gn:asciiname": "Bazhong",
    "gn:country_code": "CN",
    "gn:dem": 3509,
    "gn:feature_class": "P",
    "gn:feature_code": "PPL",
    "gn:name": "Bazhong",
    "gn:population": 0,
    "gn:timezone": "Asia/Urumqi",
    "iso:country": "CN",
    "name:ara_x_preferred": [
      "باتشونغ"
    ],
    "name:cdo_x_preferred": [
      "Bă-dṳ̆ng"
    ],
    "name:ceb_x_preferred": [
      "Bazhong Shi"
    ],
    "name:ces_x_preferred": [
      "Pa-čung"
    ],
    "name:dan_x_preferred": [
      "Bazhong"
    ],
    "name:deu_x_preferred": [
      "Bazhong"
    ],
    "name:eus_x_preferred": [
      "Bazhong"
    ],
    "name:fas_x_preferred": [
      "باژانگ"
    ],
    "name:fin_x_preferred": [
      "Bazhong"
    ],
    "name:fra_x_preferred": [
      "Bazhong"
    ],
    "name:hak_x_preferred": [
      "Pâ-chûng-sṳ"
    ],
    "name:ita_x_preferred": [
      "Bazhong"
    ],
    "name:jpn_x_preferred": [
      "巴中市"
    ],
    "name:kaz_x_preferred": [
      "Бачжун"
    ],
    "name:kik_x_preferred": [
      "Bazhong"
    ],
    "name:kor_x_preferred": [
      "바중시"
    ],
    "name:nld_x_preferred": [
      "Bazhong"
    ],
    "name:nno_x_preferred": [
      "Bazhong"
    ],
    "name:nor_x_preferred": [
      "Bazhong"
    ],
    "name:pol_x_preferred": [
      "Bazhong"
    ],
    "name:rus_x_preferred": [
      "Бачжун"
    ],
    "name:spa_x_preferred": [
      "Bazhong"
    ],
    "name:swe_x_preferred": [
      "Bazhong"
    ],
    "name:tur_x_preferred": [
      "Bazhong"
    ],
    "name:urd_x_preferred": [
      "باژونگ"
    ],
    "name:vie_x_preferred": [
      "Ba Trung"
    ],
    "name:wuu_x_preferred": [
      "巴中市"
    ],
    "name:zho_x_preferred": [
      "巴中"
    ],
    "name:zho_x_variant": [
      "巴中市"
    ],
    "wof:name": "Bazhong",
    "wof:placetype": "locality"
  },
  "geometry": {
    "coordinates": [
      98.72986,
      29.89386
    ],
    "type": "Point"
  }
}