{
  "type": "Feature",
  "properties": {
    "gn:admin1_code": "5.0",
    "gn:asciiname": "Qingchaguan",
    "gn:country_code": "CN",
    "gn:dem": 498,
    "gn:feature_class": "P",
    "gn:feature_code": "PPL",
    "gn:name": "Qingchaguan",
    "gn:population": 0,
    "gn:timezone": "Asia/Shanghai",
    "iso:country": "CN",
    "name:und_x_variant": [
      "清茶馆"
    ],
    "wof:name": "Qingchaguan",
    "wof:placetype": "locality"
  },
  "geometry": {
    "coordinates": [
      129.55245,
      42.96373
    ],
    "type": "Point"
  }
}