{
  "type": "Feature",
  "properties": {
    "gn:admin1_code": "26.0",
    "gn:asciiname": "Sandaomao",
    "gn:country_code": "CN",
    "gn:dem": 1165,
    "gn:feature_class": "P",
    "gn:feature_code": "PPL",
    "gn:name": "Sandaomao",
    "gn:population": 0,
    "gn:timezone": "Asia/Shanghai",
    "iso:country": "CN",
    "name:zho_x_preferred": [
      "三道峁"
    ],
    "wof:name": "Sandaomao",
    "wof:placetype": "locality"
  },
  "geometry": {
    "coordinates": [
      110.23462,
      38.73535
    ],
    "type": "Point"
  }
}