{
  "type": "Feature",
  "properties": {
    "gn:admin1_code": "3.0",
    "gn:asciiname": "Chifeng",
    "gn:country_code": "CN",
    "gn:dem": 176,
    "gn:feature_class": "P",
    "gn:feature_code": "PPL",
    "gn:name": "Chifeng",
    "gn:population": 0,
    "gn:timezone": "Asia/Shanghai",
    "iso:country": "CN",
    "name:afr_x_preferred": [
      "Chifeng"
    ],
    "name:ara_x_preferred": [
      "تشيفنغ"
    ],
    "name:cdo_x_preferred": [
      "Chiáh-hŭng"
    ],
    "name:ceb_x_preferred": [
      "Chifeng"
    ],
    "name:ces_x_preferred": [
      "Čch’-feng"
    ],
    "name:dan_x_preferred": [
      "Chifeng"
    ],
    "name:deu_x_preferred": [
      "Chifeng"
    ],
    "name:est_x_preferred": [
      "Chifeng"
    ],
    "name:eus_x_preferred": [
      "Chifeng"
    ],
    "name:fas_x_preferred": [
      "چیفنگ"
    ],
    "name:fin_x_preferred": [
      "Chifeng"
    ],
    "name:fra_x_preferred": [
      "Chifeng"
    ],
    "name:hak_x_preferred": [
      "Chhak-fûng-sṳ"
    ],
    "name:heb_x_preferred": [
      "צ'יפנג"
    ],
    "name:ita_x_preferred": [
      "Chifeng"
    ],
    "name:jpn_x_preferred": [
      "赤峰市"
    ],
    "name:kik_x_preferred": [
      "Chifeng"
    ],
    "name:kor_x_preferred": [
      "츠펑시"
    ],
    "name:mlg_x_preferred": [
      "Chifeng"
    ],
    "name:mon_x_preferred": [
      "Улаанхад"
    ],
    "name:nld_x_preferred": [
      "Chifeng"
    ],
    "name:nor_x_preferred": [
      "Chifeng"
    ],
    "name:pol_x_preferred": [
      "Chifeng"
    ],
    "name:por_x_preferred": [
      "Chifeng"
    ],
    "name:rus_x_preferred": [
      "Чифэн"
    ],
    "name:spa_x_preferred": [
      "Ulanhad"
    ],
    "name:srp_x_preferred": [
      "Чифенг"
    ],
    "name:swe_x_preferred": [
      "Chifeng"
    ],
    "name:tur_x_preferred": [
      "Chifeng"
    ],
    "name:und_x_variant": [
      "池丰"
    ],
    "name:urd_x_preferred": [
      "چیفینگ"
    ],
    "name:vie_x_preferred": [
      "Xích Phong"
    ],
    "name:war_x_preferred": [
      "Chifeng"
    ],
    "name:wuu_x_preferred": [
      "赤峰市"
    ],
    "name:zho_x_preferred": [
      "赤峰市"
    ],
    "wof:name": "Chifeng",
    "wof:placetype": "locality"
  },
  "geometry": {
    "coordinates": [
      116.4181,
      27.15954
    ],
    "type": "Point"
  }
}