{
  "type": "Feature",
  "properties": {
    "gn:admin1_code": "4.0",
    "gn:asciiname": "Shang'anziqiao",
    "gn:country_code": "CN",
    "gn:dem": 48,
    "gn:feature_class": "P",
    "gn:feature_code": "PPL",
    "gn:name": "Shang’anziqiao",
    "gn:population": 0,
    "gn:timezone": "Asia/Shanghai",
    "iso:country": "CN",
    "name:und_x_variant": [
      "Shang’anziqiao"
    ],
    "name:zho_x_preferred": [
      "上案子桥"
    ],
    "wof:name": "Shang'anziqiao",
    "wof:placetype": "locality"
  },
  "geometry": {
    "coordinates": [
      119.03104,
      32.02547
    ],
    "type": "Point"
  }
}