{
  "type": "Feature",
  "properties": {
    "gn:admin1_code": "24.0",
    "gn:asciiname": "Shenwan",
    "gn:country_code": "CN",
    "gn:dem": 1294,
    "gn:feature_class": "P",
    "gn:feature_code": "PPL",
    "gn:name": "Shenwan",
    "gn:population": 0,
    "gn:timezone": "Asia/Shanghai",
    "iso:country": "CN",
    "name:fas_x_preferred": [
      "شنوان"
    ],
    "name:swe_x_preferred": [
      "Shenwan"
    ],
    "name:zho_x_preferred": [
      "神湾"
    ],
    "name:zho_x_variant": [
      "神湾镇"
    ],
    "wof:name": "Shenwan",
    "wof:placetype": "locality"
  },
  "geometry": {
    "coordinates": [
      111.9683,
      36.93337
    ],
    "type": "Point"
  }
}