{
  "type": "Feature",
  "properties": {
    "gn:admin1_code": "16.0",
    "gn:asciiname": "Fujiang",
    "gn:country_code": "CN",
    "gn:dem": 182,
    "gn:feature_class": "P",
    "gn:feature_code": "PPL",
    "gn:name": "Fujiang",
    "gn:population": 0,
    "gn:timezone": "Asia/Shanghai",
    "iso:country": "CN",
    "name:zho_x_preferred": [
      "福江"
    ],
    "wof:name": "Fujiang",
    "wof:placetype": "locality"
  },
  "geometry": {
    "coordinates": [
      108.32,
      23.4794
    ],
    "type": "Point"
  }
}