{
  "type": "Feature",
  "properties": {
    "gn:admin1_code": "29.0",
    "gn:asciiname": "Maisebaizu",
    "gn:country_code": "CN",
    "gn:dem": 1859,
    "gn:feature_class": "P",
    "gn:feature_code": "PPL",
    "gn:name": "Maisebaizu",
    "gn:population": 0,
    "gn:timezone": "Asia/Shanghai",
    "iso:country": "CN",
    "name:zho_x_preferred": [
      "麦色白租"
    ],
    "wof:name": "Maisebaizu",
    "wof:placetype": "locality"
  },
  "geometry": {
    "coordinates": [
      104.088,
      23.9589
    ],
    "type": "Point"
  }
}