{
  "type": "Feature",
  "properties": {
    "gn:admin1_code": "8.0",
    "gn:asciiname": "Yumajia",
    "gn:country_code": "CN",
    "gn:dem": 211,
    "gn:feature_class": "P",
    "gn:feature_code": "PPL",
    "gn:name": "Yumajia",
    "gn:population": 0,
    "gn:timezone": "Asia/Shanghai",
    "iso:country": "CN",
    "name:zho_x_preferred": [
      "于马架"
    ],
    "wof:name": "Yumajia",
    "wof:placetype": "locality"
  },
  "geometry": {
    "coordinates": [
      123.26425,
      47.83969
    ],
    "type": "Point"
  }
}