{
  "type": "Feature",
  "properties": {
    "gn:admin1_code": "32.0",
    "gn:asciiname": "Gegang",
    "gn:country_code": "CN",
    "gn:dem": 2504,
    "gn:feature_class": "P",
    "gn:feature_code": "PPL",
    "gn:name": "Gegang",
    "gn:population": 0,
    "gn:timezone": "Asia/Shanghai",
    "iso:country": "CN",
    "name:zho_x_preferred": [
      "各岗"
    ],
    "wof:name": "Gegang",
    "wof:placetype": "locality"
  },
  "geometry": {
    "coordinates": [
      102.005,
      30.9572
    ],
    "type": "Point"
  }
}