{
  "type": "Feature",
  "properties": {
    "gn:admin1_code": "1.0",
    "gn:asciiname": "Zhuduncun",
    "gn:country_code": "CN",
    "gn:dem": 54,
    "gn:feature_class": "P",
    "gn:feature_code": "PPL",
    "gn:name": "Zhuduncun",
    "gn:population": 0,
    "gn:timezone": "Asia/Shanghai",
    "iso:country": "CN",
    "name:zho_x_preferred": [
      "祝墩村"
    ],
    "wof:name": "Zhuduncun",
    "wof:placetype": "locality"
  },
  "geometry": {
    "coordinates": [
      116.6376,
      31.67389
    ],
    "type": "Point"
  }
}