{
  "type": "Feature",
  "properties": {
    "gn:admin1_code": "15.0",
    "gn:asciiname": "Sanbawan",
    "gn:country_code": "CN",
    "gn:dem": 1431,
    "gn:feature_class": "P",
    "gn:feature_code": "PPL",
    "gn:name": "Sanbawan",
    "gn:population": 0,
    "gn:timezone": "Asia/Shanghai",
    "iso:country": "CN",
    "name:zho_x_preferred": [
      "三坝湾"
    ],
    "wof:name": "Sanbawan",
    "wof:placetype": "locality"
  },
  "geometry": {
    "coordinates": [
      100.181,
      39.1868
    ],
    "type": "Point"
  }
}