{
  "type": "Feature",
  "properties": {
    "gn:admin1_code": "8.0",
    "gn:asciiname": "Yongxingcun",
    "gn:country_code": "CN",
    "gn:dem": 124,
    "gn:feature_class": "P",
    "gn:feature_code": "PPL",
    "gn:name": "Yongxingcun",
    "gn:population": 0,
    "gn:timezone": "Asia/Shanghai",
    "iso:country": "CN",
    "name:zho_x_preferred": [
      "永兴村"
    ],
    "wof:name": "Yongxingcun",
    "wof:placetype": "locality"
  },
  "geometry": {
    "coordinates": [
      131.7673,
      46.50993
    ],
    "type": "Point"
  }
}