{
  "type": "Feature",
  "properties": {
    "gn:admin1_code": "11.0",
    "gn:asciiname": "Yangwugang",
    "gn:country_code": "CN",
    "gn:dem": 29,
    "gn:feature_class": "P",
    "gn:feature_code": "PPL",
    "gn:name": "Yangwugang",
    "gn:population": 0,
    "gn:timezone": "Asia/Shanghai",
    "iso:country": "CN",
    "name:zho_x_preferred": [
      "Yangwugang"
    ],
    "name:zho_x_variant": [
      "杨伍岗"
    ],
    "wof:name": "Yangwugang",
    "wof:placetype": "locality"
  },
  "geometry": {
    "coordinates": [
      111.7862,
      29.07912
    ],
    "type": "Point"
  }
}