{
  "type": "Feature",
  "properties": {
    "gn:admin1_code": "02",
    "gn:asciiname": "Meishan",
    "gn:country_code": "CN",
    "gn:dem": 22,
    "gn:feature_class": "P",
    "gn:feature_code": "PPL",
    "gn:name": "Meishan",
    "gn:population": 0,
    "gn:timezone": "Asia/Shanghai",
    "iso:country": "CN",
    "name:ara_x_preferred": [
      "ميشان"
    ],
    "name:cdo_x_preferred": [
      "Mì-săng"
    ],
    "name:ceb_x_preferred": [
      "Meishan Shi"
    ],
    "name:ces_x_preferred": [
      "Mej-šan"
    ],
    "name:dan_x_preferred": [
      "Meishan"
    ],
    "name:deu_x_preferred": [
      "Meishan"
    ],
    "name:eus_x_preferred": [
      "Meishan"
    ],
    "name:fas_x_preferred": [
      "مایشان"
    ],
    "name:fin_x_preferred": [
      "Meishan"
    ],
    "name:fra_x_preferred": [
      "Meishan"
    ],
    "name:ita_x_preferred": [
      "Meishan"
    ],
    "name:jpn_x_preferred": [
      "眉山市"
    ],
    "name:kik_x_preferred": [
      "Meishan"
    ],
    "name:kor_x_preferred": [
      "메이산시"
    ],
    "name:nld_x_preferred": [
      "Meishan"
    ],
    "name:nno_x_preferred": [
      "Meishan"
    ],
    "name:nor_x_preferred": [
      "Meishan"
    ],
    "name:pol_x_preferred": [
      "Meishan"
    ],
    "name:rus_x_preferred": [
      "Мэйшань"
    ],
    "name:spa_x_preferred": [
      "Meishán"
    ],
    "name:swe_x_preferred": [
      "Meishan"
    ],
    "name:tur_x_preferred": [
      "Meishan"
    ],
    "name:urd_x_preferred": [
      "میئشان"
    ],
    "name:vie_x_preferred": [
      "Mi Sơn"
    ],
    "name:zho_x_preferred": [
      "眉山市"
    ],
    "wof:name": "Meishan",
    "wof:placetype": "locality"
  },
  "geometry": {
    "coordinates": [
      122.01583,
      29.81694
    ],
    "type": "Point"
  }
}