{
  "type": "Feature",
  "properties": {
    "gn:admin1_code": "15.0",
    "gn:asciiname": "Touba",
    "gn:country_code": "CN",
    "gn:dem": 1342,
    "gn:feature_class": "P",
    "gn:feature_code": "PPL",
    "gn:name": "Touba",
    "gn:population": 0,
    "gn:timezone": "Asia/Shanghai",
    "iso:country": "CN",
    "name:afr_x_preferred": [
      "Touba"
    ],
    "name:bel_x_preferred": [
      "Туба"
    ],
    "name:cat_x_preferred": [
      "Touba"
    ],
    "name:ceb_x_preferred": [
      "Touba"
    ],
    "name:deu_x_preferred": [
      "Touba"
    ],
    "name:epo_x_preferred": [
      "Tuba"
    ],
    "name:eus_x_preferred": [
      "Touba"
    ],
    "name:fas_x_preferred": [
      "توبا"
    ],
    "name:fas_x_variant": [
      "طوبی"
    ],
    "name:fra_x_preferred": [
      "Touba"
    ],
    "name:heb_x_preferred": [
      "טובה"
    ],
    "name:hin_x_preferred": [
      "तोऊबा"
    ],
    "name:hun_x_preferred": [
      "Touba"
    ],
    "name:ind_x_preferred": [
      "Touba"
    ],
    "name:ita_x_preferred": [
      "Touba"
    ],
    "name:jpn_x_preferred": [
      "トゥーバ"
    ],
    "name:kor_x_preferred": [
      "투바"
    ],
    "name:lit_x_preferred": [
      "Tuba"
    ],
    "name:msa_x_preferred": [
      "Touba"
    ],
    "name:nld_x_preferred": [
      "Touba"
    ],
    "name:pol_x_preferred": [
      "Touba"
    ],
    "name:por_x_preferred": [
      "Touba"
    ],
    "name:ron_x_preferred": [
      "Touba"
    ],
    "name:rus_x_preferred": [
      "Туба"
    ],
    "name:sna_x_preferred": [
      "Touba"
    ],
    "name:spa_x_preferred": [
      "Touba"
    ],
    "name:swe_x_preferred": [
      "Touba"
    ],
    "name:tur_x_preferred": [
      "Touba"
    ],
    "name:ukr_x_preferred": [
      "Туба"
    ],
    "name:urd_x_preferred": [
      "توبا"
    ],
    "name:vep_x_preferred": [
      "Tub"
    ],
    "name:vie_x_preferred": [
      "Touba"
    ],
    "name:wol_x_preferred": [
      "Tuubaa"
    ],
    "name:zho_x_preferred": [
      "头坝"
    ],
    "name:zho_x_variant": [
      "圖巴"
    ],
    "wof:name": "Touba",
    "wof:placetype": "locality"
  },
  "geometry": {
    "coordinates": [
      103.25,
      38.8225
    ],
    "type": "Point"
  }
}