{
  "type": "Feature",
  "properties": {
    "gn:admin1_code": "7.0",
    "gn:asciiname": "Changhua",
    "gn:country_code": "CN",
    "gn:dem": 222,
    "gn:feature_class": "P",
    "gn:feature_code": "PPL",
    "gn:name": "Changhua",
    "gn:population": 0,
    "gn:timezone": "Asia/Shanghai",
    "iso:country": "CN",
    "name:ara_x_preferred": [
      "تشانغهوا"
    ],
    "name:ben_x_preferred": [
      "চাঙ্ঘুয়া"
    ],
    "name:ces_x_preferred": [
      "Čang-chua"
    ],
    "name:deu_x_preferred": [
      "Changhua"
    ],
    "name:ell_x_preferred": [
      "Τσάνγκουα"
    ],
    "name:fas_x_preferred": [
      "جانگوآ"
    ],
    "name:fin_x_preferred": [
      "Changhua"
    ],
    "name:fra_x_preferred": [
      "Changhua"
    ],
    "name:hak_x_preferred": [
      "Chông-fa-sṳ"
    ],
    "name:heb_x_preferred": [
      "צ'אנג'ואה"
    ],
    "name:hin_x_preferred": [
      "चांगुआ"
    ],
    "name:hun_x_preferred": [
      "Changhua"
    ],
    "name:ind_x_preferred": [
      "Changhua"
    ],
    "name:ita_x_preferred": [
      "Changhua"
    ],
    "name:jpn_x_preferred": [
      "彰化市"
    ],
    "name:kor_x_preferred": [
      "장화시"
    ],
    "name:lit_x_preferred": [
      "Džanghua"
    ],
    "name:nld_x_preferred": [
      "Changhua"
    ],
    "name:pol_x_preferred": [
      "Zhanghua"
    ],
    "name:por_x_preferred": [
      "Changhua"
    ],
    "name:rus_x_preferred": [
      "Чжанхуа"
    ],
    "name:spa_x_preferred": [
      "Changhua"
    ],
    "name:swe_x_preferred": [
      "Changhua"
    ],
    "name:tha_x_preferred": [
      "จังฮว่า"
    ],
    "name:tur_x_preferred": [
      "Changhua"
    ],
    "name:ukr_x_preferred": [
      "Чжанхуа"
    ],
    "name:und_x_variant": [
      "长华"
    ],
    "name:urd_x_preferred": [
      "چانگہوا شہر"
    ],
    "name:vie_x_preferred": [
      "Chương Hóa"
    ],
    "name:war_x_preferred": [
      "Changhua"
    ],
    "name:zho_x_preferred": [
      "彰化市"
    ],
    "wof:name": "Changhua",
    "wof:placetype": "locality"
  },
  "geometry": {
    "coordinates": [
      118.37796,
      26.1779
    ],
    "type": "Point"
  }
}