{
  "type": "Feature",
  "properties": {
    "gn:admin1_code": "12",
    "gn:asciiname": "Sandian",
    "gn:country_code": "CN",
    "gn:dem": 31,
    "gn:feature_class": "P",
    "gn:feature_code": "PPLA4",
    "gn:name": "Sandian",
    "gn:population": 0,
    "gn:timezone": "Asia/Shanghai",
    "iso:country": "CN",
    "name:ceb_x_preferred": [
      "Sandīān"
    ],
    "name:fas_x_preferred": [
      "سندیان"
    ],
    "name:msa_x_preferred": [
      "Sandian"
    ],
    "name:swe_x_preferred": [
      "Sandīān"
    ],
    "name:ukr_x_preferred": [
      "Сандіан"
    ],
    "name:und_x_variant": [
      "San-tien-shih",
      "San-tien-chieh",
      "San-tien",
      "三店",
      "Sandian Jiedao",
      "三店街道"
    ],
    "wof:name": "Sandian",
    "wof:placetype": "locality"
  },
  "geometry": {
    "coordinates": [
      114.7919,
      30.93093
    ],
    "type": "Point"
  }
}