{
  "type": "Feature",
  "properties": {
    "gn:admin1_code": "11",
    "gn:asciiname": "Shaping",
    "gn:country_code": "CN",
    "gn:dem": 562,
    "gn:feature_class": "P",
    "gn:feature_code": "PPL",
    "gn:name": "Shaping",
    "gn:population": 0,
    "gn:timezone": "Asia/Shanghai",
    "iso:country": "CN",
    "name:ceb_x_preferred": [
      "Shaping"
    ],
    "name:deu_x_preferred": [
      "Shaping"
    ],
    "name:mlg_x_preferred": [
      "Shaping"
    ],
    "name:rus_x_preferred": [
      "Шейпинг"
    ],
    "name:zho_x_preferred": [
      "沙坪"
    ],
    "wof:name": "Shaping",
    "wof:placetype": "locality"
  },
  "geometry": {
    "coordinates": [
      112.10846,
      26.05883
    ],
    "type": "Point"
  }
}