{
  "type": "Feature",
  "properties": {
    "gn:admin1_code": "30.0",
    "gn:asciiname": "Shayao",
    "gn:country_code": "CN",
    "gn:dem": 8,
    "gn:feature_class": "P",
    "gn:feature_code": "PPL",
    "gn:name": "Shayao",
    "gn:population": 0,
    "gn:timezone": "Asia/Shanghai",
    "iso:country": "CN",
    "name:zho_x_preferred": [
      "沙腰"
    ],
    "wof:name": "Shayao",
    "wof:placetype": "locality"
  },
  "geometry": {
    "coordinates": [
      113.7731,
      23.12094
    ],
    "type": "Point"
  }
}