{
  "type": "Feature",
  "properties": {
    "gn:admin1_code": "06",
    "gn:asciiname": "Zhiqing Songduo",
    "gn:country_code": "CN",
    "gn:dem": 3778,
    "gn:feature_class": "P",
    "gn:feature_code": "PPLA3",
    "gn:name": "Zhiqing Songduo",
    "gn:population": 0,
    "gn:timezone": "Asia/Shanghai",
    "iso:country": "CN",
    "name:und_x_variant": [
      "Chiu-chih",
      "Jigzhi",
      "Chih-ch’ing-sung-to",
      "Chugqênsumdo",
      "Zhiqing Songduo",
      "Zhiqing Songduo Zhen",
      "Jiuzhi",
      "Jiuzhi Xian"
    ],
    "name:zho_x_preferred": [
      "智青松多"
    ],
    "name:zho_x_variant": [
      "智青松多镇",
      "久治",
      "久治县"
    ],
    "wof:name": "Zhiqing Songduo",
    "wof:placetype": "locality"
  },
  "geometry": {
    "coordinates": [
      101.43333,
      33.43333
    ],
    "type": "Point"
  }
}