{
  "type": "Feature",
  "properties": {
    "gn:admin1_code": "7.0",
    "gn:asciiname": "Lidi",
    "gn:country_code": "CN",
    "gn:dem": 576,
    "gn:feature_class": "P",
    "gn:feature_code": "PPL",
    "gn:name": "Lidi",
    "gn:population": 0,
    "gn:timezone": "Asia/Shanghai",
    "iso:country": "CN",
    "name:zho_x_preferred": [
      "李地"
    ],
    "wof:name": "Lidi",
    "wof:placetype": "locality"
  },
  "geometry": {
    "coordinates": [
      116.65654,
      26.18116
    ],
    "type": "Point"
  }
}