{
  "type": "Feature",
  "properties": {
    "gn:admin1_code": "11.0",
    "gn:asciiname": "Yu'ershan",
    "gn:country_code": "CN",
    "gn:dem": 205,
    "gn:feature_class": "P",
    "gn:feature_code": "PPL",
    "gn:name": "Yu’ershan",
    "gn:population": 0,
    "gn:timezone": "Asia/Shanghai",
    "iso:country": "CN",
    "name:und_x_variant": [
      "Yu’ershan"
    ],
    "name:zho_x_preferred": [
      "鱼儿山"
    ],
    "wof:name": "Yu'ershan",
    "wof:placetype": "locality"
  },
  "geometry": {
    "coordinates": [
      110.86418,
      28.52452000000001
    ],
    "type": "Point"
  }
}