{
  "type": "Feature",
  "properties": {
    "gn:admin1_code": "10",
    "gn:asciiname": "Xiaoliangqian",
    "gn:country_code": "CN",
    "gn:dem": 579,
    "gn:feature_class": "P",
    "gn:feature_code": "PPL",
    "gn:name": "Xiaoliangqian",
    "gn:population": 0,
    "gn:timezone": "Asia/Shanghai",
    "iso:country": "CN",
    "name:zho_x_preferred": [
      "小梁前"
    ],
    "wof:name": "Xiaoliangqian",
    "wof:placetype": "locality"
  },
  "geometry": {
    "coordinates": [
      118.47023,
      40.98398
    ],
    "type": "Point"
  }
}