{
  "type": "Feature",
  "properties": {
    "gn:admin1_code": "11",
    "gn:asciiname": "Langtang",
    "gn:cc2": "CN",
    "gn:country_code": "CN",
    "gn:dem": 199,
    "gn:feature_class": "P",
    "gn:feature_code": "PPL",
    "gn:name": "Langtang",
    "gn:population": 0,
    "gn:timezone": "Asia/Shanghai",
    "iso:country": "CN",
    "name:cat_x_preferred": [
      "Langtang"
    ],
    "name:deu_x_preferred": [
      "Langtang"
    ],
    "name:heb_x_preferred": [
      "לנגטאנג"
    ],
    "name:hin_x_preferred": [
      "लांगटांग"
    ],
    "name:jpn_x_preferred": [
      "ランタン谷"
    ],
    "name:kat_x_preferred": [
      "ლანგტანგი"
    ],
    "name:lit_x_preferred": [
      "Langtangas"
    ],
    "name:nep_x_preferred": [
      "लाङटाङ"
    ],
    "name:new_x_preferred": [
      "लाङटाङ"
    ],
    "name:nld_x_preferred": [
      "Langtang"
    ],
    "name:por_x_preferred": [
      "Langtang"
    ],
    "name:rus_x_preferred": [
      "Лангтанг"
    ],
    "name:spa_x_preferred": [
      "Langtang"
    ],
    "name:ukr_x_preferred": [
      "Лангтанг"
    ],
    "name:und_x_variant": [
      "Tuanjieshan"
    ],
    "name:vie_x_preferred": [
      "Langtang"
    ],
    "wof:name": "Langtang",
    "wof:placetype": "locality"
  },
  "geometry": {
    "coordinates": [
      111.10611000000002,
      27.99222
    ],
    "type": "Point"
  }
}