{
  "type": "Feature",
  "properties": {
    "gn:admin1_code": "08",
    "gn:asciiname": "Wumahe",
    "gn:country_code": "CN",
    "gn:dem": 244,
    "gn:feature_class": "P",
    "gn:feature_code": "PPLA3",
    "gn:name": "Wumahe",
    "gn:population": 0,
    "gn:timezone": "Asia/Shanghai",
    "iso:country": "CN",
    "name:und_x_variant": [
      "Wumahe Jiedao",
      "Wumahe Qu"
    ],
    "name:zho_x_preferred": [
      "乌马河"
    ],
    "name:zho_x_variant": [
      "乌马河街道",
      "乌马河区"
    ],
    "wof:name": "Wumahe",
    "wof:placetype": "locality"
  },
  "geometry": {
    "coordinates": [
      128.79277,
      47.72348
    ],
    "type": "Point"
  }
}