{
  "type": "Feature",
  "properties": {
    "gn:admin1_code": "13.0",
    "gn:asciiname": "Alashankou",
    "gn:country_code": "CN",
    "gn:dem": 307,
    "gn:feature_class": "P",
    "gn:feature_code": "PPL",
    "gn:name": "Alashankou",
    "gn:population": 0,
    "gn:timezone": "Asia/Urumqi",
    "iso:country": "CN",
    "name:deu_x_preferred": [
      "Alashankou"
    ],
    "name:eng_x_preferred": [
      "Alashankou"
    ],
    "name:fas_x_preferred": [
      "گردنه آلاتاو"
    ],
    "name:ita_x_preferred": [
      "Alashankou"
    ],
    "name:jpn_x_preferred": [
      "阿拉山口市"
    ],
    "name:kik_x_preferred": [
      "Alashankou"
    ],
    "name:kor_x_preferred": [
      "아라산커우시"
    ],
    "name:rus_x_preferred": [
      "Алашанькоу"
    ],
    "name:tur_x_preferred": [
      "Alashankou"
    ],
    "name:uig_x_preferred": [
      "ئالاتاۋ ئېغىزى"
    ],
    "name:urd_x_preferred": [
      "الاشانکوو"
    ],
    "name:zho_x_preferred": [
      "阿拉山口"
    ],
    "name:zho_x_variant": [
      "Ālāshānkǒu",
      "阿拉山口市"
    ],
    "wof:name": "Alashankou",
    "wof:placetype": "locality"
  },
  "geometry": {
    "coordinates": [
      82.56981,
      45.17018
    ],
    "type": "Point"
  }
}