{
  "type": "Feature",
  "properties": {
    "gn:admin1_code": "19.0",
    "gn:asciiname": "Hanchengcun",
    "gn:country_code": "CN",
    "gn:dem": 40,
    "gn:feature_class": "P",
    "gn:feature_code": "PPL",
    "gn:name": "Hanchengcun",
    "gn:population": 0,
    "gn:timezone": "Asia/Shanghai",
    "iso:country": "CN",
    "name:und_x_variant": [
      "Hanchengbao",
      "Hanchengbu"
    ],
    "name:zho_x_preferred": [
      "韩城村"
    ],
    "name:zho_x_variant": [
      "韩成堡"
    ],
    "wof:name": "Hanchengcun",
    "wof:placetype": "locality"
  },
  "geometry": {
    "coordinates": [
      123.364,
      41.6182
    ],
    "type": "Point"
  }
}