{
  "type": "Feature",
  "properties": {
    "gn:admin1_code": "11.0",
    "gn:asciiname": "Shangnanwan",
    "gn:country_code": "CN",
    "gn:dem": 673,
    "gn:feature_class": "P",
    "gn:feature_code": "PPL",
    "gn:name": "Shangnanwan",
    "gn:population": 0,
    "gn:timezone": "Asia/Shanghai",
    "iso:country": "CN",
    "name:zho_x_preferred": [
      "上南湾"
    ],
    "wof:name": "Shangnanwan",
    "wof:placetype": "locality"
  },
  "geometry": {
    "coordinates": [
      113.27425,
      25.72274
    ],
    "type": "Point"
  }
}