{
  "type": "Feature",
  "properties": {
    "gn:admin1_code": "30",
    "gn:asciiname": "Dali",
    "gn:country_code": "CN",
    "gn:dem": 0,
    "gn:feature_class": "P",
    "gn:feature_code": "PPLA4",
    "gn:name": "Dali",
    "gn:population": 0,
    "gn:timezone": "Asia/Shanghai",
    "iso:country": "CN",
    "name:ara_x_preferred": [
      "دالي"
    ],
    "name:ben_x_preferred": [
      "দালি"
    ],
    "name:deu_x_preferred": [
      "Dali"
    ],
    "name:ell_x_preferred": [
      "Νταλί"
    ],
    "name:eng_x_preferred": [
      "Dali"
    ],
    "name:fas_x_preferred": [
      "دالی"
    ],
    "name:fra_x_preferred": [
      "Dali"
    ],
    "name:heb_x_preferred": [
      "דאלי"
    ],
    "name:hin_x_preferred": [
      "डैली"
    ],
    "name:hun_x_preferred": [
      "Dali"
    ],
    "name:ind_x_preferred": [
      "Dali"
    ],
    "name:ita_x_preferred": [
      "Dali"
    ],
    "name:jpn_x_preferred": [
      "大理川"
    ],
    "name:kor_x_preferred": [
      "달리"
    ],
    "name:nld_x_preferred": [
      "Dali"
    ],
    "name:nor_x_preferred": [
      "Dali"
    ],
    "name:pol_x_preferred": [
      "Dali"
    ],
    "name:por_x_preferred": [
      "Dali"
    ],
    "name:rus_x_preferred": [
      "река Дали"
    ],
    "name:spa_x_preferred": [
      "Dali"
    ],
    "name:swe_x_preferred": [
      "Dali"
    ],
    "name:tur_x_preferred": [
      "Dali"
    ],
    "name:ukr_x_preferred": [
      "Далі"
    ],
    "name:und_x_variant": [
      "Dalijieban"
    ],
    "name:urd_x_preferred": [
      "ڈالی"
    ],
    "name:vie_x_preferred": [
      "Sông Dali"
    ],
    "name:zho_cn_x_preferred": [
      "大里溪"
    ],
    "name:zho_tw_x_preferred": [
      "大理河"
    ],
    "name:zho_x_preferred": [
      "大沥"
    ],
    "name:zho_x_variant": [
      "大沥镇"
    ],
    "wof:name": "Dali",
    "wof:placetype": "locality"
  },
  "geometry": {
    "coordinates": [
      113.11673,
      23.11974
    ],
    "type": "Point"
  }
}