{
  "type": "Feature",
  "properties": {
    "gn:admin1_code": "10.0",
    "gn:asciiname": "Shengao",
    "gn:country_code": "CN",
    "gn:dem": 19,
    "gn:feature_class": "P",
    "gn:feature_code": "PPL",
    "gn:name": "Shengao",
    "gn:population": 0,
    "gn:timezone": "Asia/Shanghai",
    "iso:country": "CN",
    "name:fas_x_preferred": [
      "شنگائو"
    ],
    "name:zho_x_preferred": [
      "申高"
    ],
    "name:zho_x_variant": [
      "沈高镇"
    ],
    "wof:name": "Shengao",
    "wof:placetype": "locality"
  },
  "geometry": {
    "coordinates": [
      116.1512,
      37.73766
    ],
    "type": "Point"
  }
}