{
  "type": "Feature",
  "properties": {
    "gn:admin1_code": "26.0",
    "gn:asciiname": "Niujiagoucun",
    "gn:country_code": "CN",
    "gn:dem": 1637,
    "gn:feature_class": "P",
    "gn:feature_code": "PPL",
    "gn:name": "Niujiagoucun",
    "gn:population": 0,
    "gn:timezone": "Asia/Shanghai",
    "iso:country": "CN",
    "name:und_x_variant": [
      "牛家沟村"
    ],
    "wof:name": "Niujiagoucun",
    "wof:placetype": "locality"
  },
  "geometry": {
    "coordinates": [
      107.32913,
      34.09009
    ],
    "type": "Point"
  }
}