{
  "type": "Feature",
  "properties": {
    "gn:admin1_code": "10.0",
    "gn:asciiname": "Maquan",
    "gn:country_code": "CN",
    "gn:dem": 1166,
    "gn:feature_class": "P",
    "gn:feature_code": "PPL",
    "gn:name": "Maquan",
    "gn:population": 0,
    "gn:timezone": "Asia/Shanghai",
    "iso:country": "CN",
    "name:ara_x_preferred": [
      "ماكان"
    ],
    "name:ben_x_preferred": [
      "মাকুয়ান"
    ],
    "name:deu_x_preferred": [
      "Maquan"
    ],
    "name:ell_x_preferred": [
      "Μακουάν"
    ],
    "name:fas_x_preferred": [
      "ماکوان"
    ],
    "name:fra_x_preferred": [
      "Maquan"
    ],
    "name:heb_x_preferred": [
      "אגם צ'יקיטה"
    ],
    "name:hin_x_preferred": [
      "माक्वान"
    ],
    "name:hun_x_preferred": [
      "Maquan"
    ],
    "name:ind_x_preferred": [
      "Maquan"
    ],
    "name:ita_x_preferred": [
      "Maquan"
    ],
    "name:jpn_x_preferred": [
      "マクアン川"
    ],
    "name:kor_x_preferred": [
      "마쿠안"
    ],
    "name:nld_x_preferred": [
      "Maquan"
    ],
    "name:pol_x_preferred": [
      "Maquan"
    ],
    "name:por_x_preferred": [
      "Maquan"
    ],
    "name:rus_x_preferred": [
      "река Макуан"
    ],
    "name:spa_x_preferred": [
      "Río Maquan"
    ],
    "name:swe_x_preferred": [
      "Maquan"
    ],
    "name:tur_x_preferred": [
      "Maquan"
    ],
    "name:ukr_x_preferred": [
      "Макван"
    ],
    "name:urd_x_preferred": [
      "میکوان"
    ],
    "name:vie_x_preferred": [
      "Sông Mã Tuyền"
    ],
    "name:zho_cn_x_preferred": [
      "马泉河"
    ],
    "name:zho_tw_x_preferred": [
      "馬匡河"
    ],
    "name:zho_x_preferred": [
      "马圈"
    ],
    "wof:name": "Maquan",
    "wof:placetype": "locality"
  },
  "geometry": {
    "coordinates": [
      115.09117,
      40.0877
    ],
    "type": "Point"
  }
}