{
  "type": "Feature",
  "properties": {
    "gn:admin1_code": "5.0",
    "gn:asciiname": "Dataipingzhuang",
    "gn:country_code": "CN",
    "gn:dem": 162,
    "gn:feature_class": "P",
    "gn:feature_code": "PPL",
    "gn:name": "Dataipingzhuang",
    "gn:population": 0,
    "gn:timezone": "Asia/Shanghai",
    "iso:country": "CN",
    "name:zho_x_preferred": [
      "大太平庄"
    ],
    "wof:name": "Dataipingzhuang",
    "wof:placetype": "locality"
  },
  "geometry": {
    "coordinates": [
      125.36527,
      44.49255
    ],
    "type": "Point"
  }
}