{
  "type": "Feature",
  "properties": {
    "gn:admin1_code": "15.0",
    "gn:asciiname": "Huangping",
    "gn:country_code": "CN",
    "gn:dem": 2460,
    "gn:feature_class": "P",
    "gn:feature_code": "PPL",
    "gn:name": "Huangping",
    "gn:population": 0,
    "gn:timezone": "Asia/Shanghai",
    "iso:country": "CN",
    "name:zho_x_preferred": [
      "黄坪"
    ],
    "wof:name": "Huangping",
    "wof:placetype": "locality"
  },
  "geometry": {
    "coordinates": [
      104.123,
      35.6743
    ],
    "type": "Point"
  }
}