{
  "type": "Feature",
  "properties": {
    "gn:admin1_code": "05",
    "gn:asciiname": "Sanjiazi",
    "gn:country_code": "CN",
    "gn:dem": 34,
    "gn:feature_class": "P",
    "gn:feature_code": "PPLA4",
    "gn:name": "Sanjiazi",
    "gn:population": 0,
    "gn:timezone": "Asia/Shanghai",
    "iso:country": "CN",
    "name:und_x_variant": [
      "San-chia-tzu",
      "Sanjiazi",
      "三家子",
      "Sanjiazi Manzu Xiang",
      "三家子满族乡"
    ],
    "name:zho_x_preferred": [
      "三家子村"
    ],
    "wof:name": "Sanjiazi",
    "wof:placetype": "locality"
  },
  "geometry": {
    "coordinates": [
      130.30556,
      42.84
    ],
    "type": "Point"
  }
}