{
  "type": "Feature",
  "properties": {
    "gn:admin1_code": "18.0",
    "gn:asciiname": "Zongping",
    "gn:country_code": "CN",
    "gn:dem": 754,
    "gn:feature_class": "P",
    "gn:feature_code": "PPLA4",
    "gn:name": "Zongping",
    "gn:population": 0,
    "gn:timezone": "Asia/Shanghai",
    "iso:country": "CN",
    "name:und_x_variant": [
      "Zongping Xiang"
    ],
    "name:zho_x_preferred": [
      "棕坪"
    ],
    "name:zho_x_variant": [
      "棕平乡"
    ],
    "wof:name": "Zongping",
    "wof:placetype": "locality"
  },
  "geometry": {
    "coordinates": [
      107.65373999999998,
      28.67295
    ],
    "type": "Point"
  }
}