{
  "type": "Feature",
  "properties": {
    "gn:admin1_code": "14.0",
    "gn:asciiname": "Nana",
    "gn:country_code": "CN",
    "gn:dem": 4986,
    "gn:feature_class": "P",
    "gn:feature_code": "PPL",
    "gn:name": "Nana",
    "gn:population": 0,
    "gn:timezone": "Asia/Urumqi",
    "iso:country": "CN",
    "name:ara_x_preferred": [
      "نانا"
    ],
    "name:bos_x_preferred": [
      "Nana"
    ],
    "name:bre_x_preferred": [
      "Nana"
    ],
    "name:cat_x_preferred": [
      "Nana"
    ],
    "name:ceb_x_preferred": [
      "Nana"
    ],
    "name:ces_x_preferred": [
      "Nana"
    ],
    "name:dan_x_preferred": [
      "Nana"
    ],
    "name:deu_x_preferred": [
      "Nana"
    ],
    "name:fas_x_preferred": [
      "نانا"
    ],
    "name:fin_x_preferred": [
      "Nana"
    ],
    "name:fra_x_preferred": [
      "Nana"
    ],
    "name:heb_x_preferred": [
      "נענע"
    ],
    "name:hrv_x_preferred": [
      "Nana"
    ],
    "name:hun_x_preferred": [
      "Nana"
    ],
    "name:ita_x_preferred": [
      "Nana"
    ],
    "name:msa_x_preferred": [
      "Nana"
    ],
    "name:nld_x_preferred": [
      "Nana"
    ],
    "name:nor_x_preferred": [
      "Nana"
    ],
    "name:pol_x_preferred": [
      "Nana"
    ],
    "name:por_x_preferred": [
      "Nana"
    ],
    "name:ron_x_preferred": [
      "Nana"
    ],
    "name:rus_x_preferred": [
      "Нана"
    ],
    "name:spa_x_preferred": [
      "Nana"
    ],
    "name:srp_x_preferred": [
      "Нана"
    ],
    "name:swe_x_preferred": [
      "Nana"
    ],
    "name:tha_x_preferred": [
      "นานา"
    ],
    "name:ukr_x_preferred": [
      "Нана"
    ],
    "name:vie_x_preferred": [
      "Nana"
    ],
    "name:zho_x_preferred": [
      "纳那"
    ],
    "name:zho_x_variant": [
      "Nana"
    ],
    "wof:name": "Nana",
    "wof:placetype": "locality"
  },
  "geometry": {
    "coordinates": [
      86.0197,
      30.2488
    ],
    "type": "Point"
  }
}