{
  "type": "Feature",
  "properties": {
    "gn:admin1_code": "15.0",
    "gn:asciiname": "Yuzhong Chengguanzhen",
    "gn:country_code": "CN",
    "gn:dem": 1981,
    "gn:feature_class": "P",
    "gn:feature_code": "PPLA3",
    "gn:name": "Yuzhong Chengguanzhen",
    "gn:population": 0,
    "gn:timezone": "Asia/Shanghai",
    "iso:country": "CN",
    "name:und_x_variant": [
      "Chin",
      "Yü-chung-hsien",
      "Chin-ch’eng",
      "Yü-chung",
      "Yuzhong",
      "Yuzhong Chengguanzhen",
      "Yuzhong Xian"
    ],
    "name:zho_x_preferred": [
      "榆中城关镇"
    ],
    "name:zho_x_variant": [
      "榆中县"
    ],
    "wof:name": "Yuzhong Chengguanzhen",
    "wof:placetype": "locality"
  },
  "geometry": {
    "coordinates": [
      104.1125,
      35.84278
    ],
    "type": "Point"
  }
}