{
  "type": "Feature",
  "properties": {
    "gn:admin1_code": "29.0",
    "gn:asciiname": "Budai",
    "gn:country_code": "CN",
    "gn:dem": 1543,
    "gn:feature_class": "P",
    "gn:feature_code": "PPL",
    "gn:name": "Budai",
    "gn:population": 0,
    "gn:timezone": "Asia/Shanghai",
    "iso:country": "CN",
    "name:asm_x_preferred": [
      "বুদাই"
    ],
    "name:ast_x_preferred": [
      "Hotei"
    ],
    "name:ben_x_preferred": [
      "বুদাই"
    ],
    "name:bre_x_preferred": [
      "Hotei"
    ],
    "name:ces_x_preferred": [
      "Hotei"
    ],
    "name:deu_x_preferred": [
      "Budai"
    ],
    "name:fas_x_preferred": [
      "بودای"
    ],
    "name:fin_x_preferred": [
      "Budai"
    ],
    "name:fra_x_preferred": [
      "Budai"
    ],
    "name:glg_x_preferred": [
      "Hotei"
    ],
    "name:heb_x_preferred": [
      "בודאי"
    ],
    "name:hun_x_preferred": [
      "Pu-taj"
    ],
    "name:ind_x_preferred": [
      "Budai"
    ],
    "name:ita_x_preferred": [
      "Budai"
    ],
    "name:mal_x_preferred": [
      "ബുദായ്"
    ],
    "name:nor_x_preferred": [
      "Budai"
    ],
    "name:pan_x_preferred": [
      "ਬੂਦਾਈ"
    ],
    "name:ron_x_preferred": [
      "Budai"
    ],
    "name:rus_x_preferred": [
      "Хотэй"
    ],
    "name:spa_x_preferred": [
      "Hotei"
    ],
    "name:srp_x_preferred": [
      "Будаи"
    ],
    "name:swe_x_preferred": [
      "Budai"
    ],
    "name:tur_x_preferred": [
      "Gülen Buda"
    ],
    "name:vie_x_preferred": [
      "Bố Đại"
    ],
    "name:zho_x_preferred": [
      "补歹"
    ],
    "name:zho_x_variant": [
      "布袋和尚"
    ],
    "wof:name": "Budai",
    "wof:placetype": "locality"
  },
  "geometry": {
    "coordinates": [
      104.275,
      24.7662
    ],
    "type": "Point"
  }
}