{
  "type": "Feature",
  "properties": {
    "gn:admin1_code": "10",
    "gn:asciiname": "Sanqigan",
    "gn:country_code": "CN",
    "gn:dem": 465,
    "gn:feature_class": "P",
    "gn:feature_code": "PPL",
    "gn:name": "Sanqigan",
    "gn:population": 0,
    "gn:timezone": "Asia/Shanghai",
    "iso:country": "CN",
    "name:zho_x_preferred": [
      "三旗杆"
    ],
    "wof:name": "Sanqigan",
    "wof:placetype": "locality"
  },
  "geometry": {
    "coordinates": [
      118.89281,
      40.63666
    ],
    "type": "Point"
  }
}