{
  "type": "Feature",
  "properties": {
    "gn:admin1_code": "05",
    "gn:asciiname": "Tuanjiecun",
    "gn:country_code": "CN",
    "gn:dem": 167,
    "gn:feature_class": "P",
    "gn:feature_code": "PPL",
    "gn:name": "Tuanjiecun",
    "gn:population": 0,
    "gn:timezone": "Asia/Shanghai",
    "iso:country": "CN",
    "name:und_x_variant": [
      "T’uan-chieh-t’un",
      "Tuanjie",
      "Tuanjiecun"
    ],
    "name:zho_x_preferred": [
      "团结村"
    ],
    "wof:name": "Tuanjiecun",
    "wof:placetype": "locality"
  },
  "geometry": {
    "coordinates": [
      122.37973999999998,
      44.59425
    ],
    "type": "Point"
  }
}