{
  "type": "Feature",
  "properties": {
    "gn:admin1_code": "16",
    "gn:asciiname": "Naju",
    "gn:country_code": "CN",
    "gn:dem": 52,
    "gn:feature_class": "P",
    "gn:feature_code": "PPL",
    "gn:name": "Naju",
    "gn:population": 0,
    "gn:timezone": "Asia/Shanghai",
    "iso:country": "CN",
    "name:ara_x_preferred": [
      "ناجو"
    ],
    "name:ceb_x_preferred": [
      "Naju"
    ],
    "name:ces_x_preferred": [
      "Nadžu"
    ],
    "name:deu_x_preferred": [
      "Naju"
    ],
    "name:epo_x_preferred": [
      "Naĝu"
    ],
    "name:fra_x_preferred": [
      "Naju"
    ],
    "name:ita_x_preferred": [
      "Naju"
    ],
    "name:jpn_x_preferred": [
      "羅州市"
    ],
    "name:kor_x_preferred": [
      "나주시"
    ],
    "name:lmo_x_preferred": [
      "Naju"
    ],
    "name:mon_x_preferred": [
      "Нажү"
    ],
    "name:nld_x_preferred": [
      "Naju"
    ],
    "name:nor_x_preferred": [
      "Naju"
    ],
    "name:pol_x_preferred": [
      "Naju"
    ],
    "name:por_x_preferred": [
      "Naju"
    ],
    "name:rus_x_preferred": [
      "Наджу"
    ],
    "name:spa_x_preferred": [
      "Naju"
    ],
    "name:swe_x_preferred": [
      "Naju"
    ],
    "name:tgl_x_preferred": [
      "Naju"
    ],
    "name:tur_x_preferred": [
      "Naju"
    ],
    "name:urd_x_preferred": [
      "ناجو"
    ],
    "name:vie_x_preferred": [
      "Naju"
    ],
    "name:war_x_preferred": [
      "Naju"
    ],
    "name:zho_x_preferred": [
      "那蒟"
    ],
    "name:zho_x_variant": [
      "羅州市"
    ],
    "wof:name": "Naju",
    "wof:placetype": "locality"
  },
  "geometry": {
    "coordinates": [
      108.877,
      22.0692
    ],
    "type": "Point"
  }
}