{
  "type": "Feature",
  "properties": {
    "gn:admin1_code": "26.0",
    "gn:asciiname": "Bianshang",
    "gn:country_code": "CN",
    "gn:dem": 1235,
    "gn:feature_class": "P",
    "gn:feature_code": "PPL",
    "gn:name": "Bianshang",
    "gn:population": 0,
    "gn:timezone": "Asia/Shanghai",
    "iso:country": "CN",
    "name:zho_x_preferred": [
      "砭上"
    ],
    "wof:name": "Bianshang",
    "wof:placetype": "locality"
  },
  "geometry": {
    "coordinates": [
      108.76656,
      35.8644
    ],
    "type": "Point"
  }
}