{
  "type": "Feature",
  "properties": {
    "gn:admin1_code": "11.0",
    "gn:asciiname": "Songjia'ao",
    "gn:country_code": "CN",
    "gn:dem": 289,
    "gn:feature_class": "P",
    "gn:feature_code": "PPL",
    "gn:name": "Songjia’ao",
    "gn:population": 0,
    "gn:timezone": "Asia/Shanghai",
    "iso:country": "CN",
    "name:und_x_variant": [
      "Songjia’ao"
    ],
    "name:zho_x_preferred": [
      "宋家坳"
    ],
    "wof:name": "Songjia'ao",
    "wof:placetype": "locality"
  },
  "geometry": {
    "coordinates": [
      109.71993,
      27.43478
    ],
    "type": "Point"
  }
}