{
  "type": "Feature",
  "properties": {
    "gn:admin1_code": "7",
    "gn:asciiname": "Jixiayang",
    "gn:country_code": "CN",
    "gn:dem": 532,
    "gn:feature_class": "P",
    "gn:feature_code": "PPL",
    "gn:name": "Jixiayang",
    "gn:population": 0,
    "gn:timezone": "Asia/Shanghai",
    "iso:country": "CN",
    "name:und_x_variant": [
      "漈下洋"
    ],
    "wof:name": "Jixiayang",
    "wof:placetype": "locality"
  },
  "geometry": {
    "coordinates": [
      118.49083,
      26.17972
    ],
    "type": "Point"
  }
}