{
  "type": "Feature",
  "properties": {
    "gn:admin1_code": "2.0",
    "gn:asciiname": "Xucun",
    "gn:country_code": "CN",
    "gn:dem": 6,
    "gn:feature_class": "P",
    "gn:feature_code": "PPL",
    "gn:name": "Xucun",
    "gn:population": 0,
    "gn:timezone": "Asia/Shanghai",
    "iso:country": "CN",
    "name:zho_x_preferred": [
      "许村"
    ],
    "wof:name": "Xucun",
    "wof:placetype": "locality"
  },
  "geometry": {
    "coordinates": [
      120.88405,
      30.80393
    ],
    "type": "Point"
  }
}