{
  "type": "Feature",
  "properties": {
    "gn:admin1_code": "11.0",
    "gn:asciiname": "Xinwulong",
    "gn:country_code": "CN",
    "gn:dem": 85,
    "gn:feature_class": "P",
    "gn:feature_code": "PPL",
    "gn:name": "Xinwulong",
    "gn:population": 0,
    "gn:timezone": "Asia/Shanghai",
    "iso:country": "CN",
    "name:zho_x_preferred": [
      "新屋垅"
    ],
    "wof:name": "Xinwulong",
    "wof:placetype": "locality"
  },
  "geometry": {
    "coordinates": [
      112.13535,
      28.71757
    ],
    "type": "Point"
  }
}