{
  "type": "Feature",
  "properties": {
    "gn:admin1_code": "24.0",
    "gn:asciiname": "Songzhuang",
    "gn:country_code": "CN",
    "gn:dem": 904,
    "gn:feature_class": "P",
    "gn:feature_code": "PPL",
    "gn:name": "Songzhuang",
    "gn:population": 0,
    "gn:timezone": "Asia/Shanghai",
    "iso:country": "CN",
    "name:zho_x_preferred": [
      "宋庄"
    ],
    "wof:name": "Songzhuang",
    "wof:placetype": "locality"
  },
  "geometry": {
    "coordinates": [
      113.18212,
      38.34003
    ],
    "type": "Point"
  }
}