{
  "type": "Feature",
  "properties": {
    "gn:admin1_code": "32.0",
    "gn:asciiname": "Panzhihua",
    "gn:country_code": "CN",
    "gn:dem": 1101,
    "gn:feature_class": "P",
    "gn:feature_code": "PPLA3",
    "gn:name": "Panzhihua",
    "gn:population": 0,
    "gn:timezone": "Asia/Shanghai",
    "iso:country": "CN",
    "name:ara_x_preferred": [
      "بانتشيهوا"
    ],
    "name:bul_x_preferred": [
      "Панджихуа"
    ],
    "name:cdo_x_preferred": [
      "Păng-ciĕ-huă"
    ],
    "name:ces_x_preferred": [
      "Pchan-č’-chua"
    ],
    "name:dan_x_preferred": [
      "Panzhihua"
    ],
    "name:deu_x_preferred": [
      "Panzhihua"
    ],
    "name:est_x_preferred": [
      "Panzhihua Shi"
    ],
    "name:eus_x_preferred": [
      "Panzhihua"
    ],
    "name:fas_x_preferred": [
      "پنژیهوا"
    ],
    "name:fin_x_preferred": [
      "Panzhihua"
    ],
    "name:fra_x_preferred": [
      "Panzhihua"
    ],
    "name:hak_x_preferred": [
      "Pân-kî-fâ-sṳ"
    ],
    "name:heb_x_preferred": [
      "פנצ'יהואה"
    ],
    "name:hun_x_preferred": [
      "Panzhihua"
    ],
    "name:ita_x_preferred": [
      "Panzhihua"
    ],
    "name:jpn_x_preferred": [
      "攀枝花市"
    ],
    "name:kik_x_preferred": [
      "Panzhihua"
    ],
    "name:kor_x_preferred": [
      "판즈화시"
    ],
    "name:nld_x_preferred": [
      "Panzhihua"
    ],
    "name:nno_x_preferred": [
      "Panzhihua"
    ],
    "name:nor_x_preferred": [
      "Panzhihua"
    ],
    "name:pol_x_preferred": [
      "Panzhihua"
    ],
    "name:rus_x_preferred": [
      "Паньчжихуа"
    ],
    "name:spa_x_preferred": [
      "Panzhihua"
    ],
    "name:srp_x_preferred": [
      "Панџихуа"
    ],
    "name:swe_x_preferred": [
      "Panzhihua"
    ],
    "name:tur_x_preferred": [
      "Panzhihua"
    ],
    "name:urd_x_preferred": [
      "پانژیہوا"
    ],
    "name:war_x_preferred": [
      "Panzhihua"
    ],
    "name:wuu_x_preferred": [
      "攀枝花市"
    ],
    "name:zho_x_preferred": [
      "攀枝花"
    ],
    "name:zho_x_variant": [
      "攀枝花市"
    ],
    "wof:name": "Panzhihua",
    "wof:placetype": "locality"
  },
  "geometry": {
    "coordinates": [
      101.71276,
      26.58509
    ],
    "type": "Point"
  }
}