{
  "type": "Feature",
  "properties": {
    "gn:admin1_code": "06",
    "gn:asciiname": "Gabasumdo",
    "gn:country_code": "CN",
    "gn:dem": 3113,
    "gn:feature_class": "P",
    "gn:feature_code": "PPLA3",
    "gn:name": "Gabasumdo",
    "gn:population": 0,
    "gn:timezone": "Asia/Shanghai",
    "iso:country": "CN",
    "name:bod_x_preferred": [
      "Gabasumdo"
    ],
    "name:und_x_variant": [
      "Ya-pa-sung-tu",
      "Tongde",
      "T’ung-te",
      "Lo-pa-sung-tu",
      "Ka-pa-sung-tu",
      "Gabasongduo",
      "尕巴松多",
      "Gabasongduo Zhen",
      "Tongde Xian"
    ],
    "name:zho_x_preferred": [
      "尕巴松多镇"
    ],
    "name:zho_x_variant": [
      "同德",
      "同德县"
    ],
    "wof:name": "Gabasumdo",
    "wof:placetype": "locality"
  },
  "geometry": {
    "coordinates": [
      100.54994,
      35.2589
    ],
    "type": "Point"
  }
}