{
  "type": "Feature",
  "properties": {
    "gn:admin1_code": "30.0",
    "gn:asciiname": "Da'ao",
    "gn:country_code": "CN",
    "gn:dem": 3,
    "gn:feature_class": "P",
    "gn:feature_code": "PPL",
    "gn:name": "Da’ao",
    "gn:population": 0,
    "gn:timezone": "Asia/Shanghai",
    "iso:country": "CN",
    "name:zho_x_preferred": [
      "大坳"
    ],
    "name:zho_x_variant": [
      "Da’ao"
    ],
    "wof:name": "Da'ao",
    "wof:placetype": "locality"
  },
  "geometry": {
    "coordinates": [
      113.25141,
      22.73236
    ],
    "type": "Point"
  }
}