{
  "type": "Feature",
  "properties": {
    "gn:admin1_code": "11.0",
    "gn:asciiname": "Maowuli",
    "gn:country_code": "CN",
    "gn:dem": 257,
    "gn:feature_class": "P",
    "gn:feature_code": "PPL",
    "gn:name": "Maowuli",
    "gn:population": 0,
    "gn:timezone": "Asia/Shanghai",
    "iso:country": "CN",
    "name:zho_x_preferred": [
      "茅屋里"
    ],
    "name:zho_x_variant": [
      "毛屋里"
    ],
    "wof:name": "Maowuli",
    "wof:placetype": "locality"
  },
  "geometry": {
    "coordinates": [
      113.53455,
      26.91355
    ],
    "type": "Point"
  }
}