{
  "type": "Feature",
  "properties": {
    "gn:admin1_code": "26.0",
    "gn:asciiname": "Zhongzhuangcun",
    "gn:country_code": "CN",
    "gn:dem": 1133,
    "gn:feature_class": "P",
    "gn:feature_code": "PPL",
    "gn:name": "Zhongzhuangcun",
    "gn:population": 0,
    "gn:timezone": "Asia/Shanghai",
    "iso:country": "CN",
    "name:zho_x_preferred": [
      "中庄村"
    ],
    "wof:name": "Zhongzhuangcun",
    "wof:placetype": "locality"
  },
  "geometry": {
    "coordinates": [
      109.41889,
      36.53303
    ],
    "type": "Point"
  }
}