{
  "type": "Feature",
  "properties": {
    "gn:admin1_code": "26.0",
    "gn:asciiname": "Shanqiaocun",
    "gn:country_code": "CN",
    "gn:dem": 969,
    "gn:feature_class": "P",
    "gn:feature_code": "PPL",
    "gn:name": "Shanqiaocun",
    "gn:population": 0,
    "gn:timezone": "Asia/Shanghai",
    "iso:country": "CN",
    "name:zho_x_preferred": [
      "山桥村"
    ],
    "wof:name": "Shanqiaocun",
    "wof:placetype": "locality"
  },
  "geometry": {
    "coordinates": [
      109.2578,
      35.04985
    ],
    "type": "Point"
  }
}