{
  "type": "Feature",
  "properties": {
    "gn:admin1_code": "16.0",
    "gn:asciiname": "Qinshan",
    "gn:country_code": "CN",
    "gn:dem": 51,
    "gn:feature_class": "P",
    "gn:feature_code": "PPL",
    "gn:name": "Qinshan",
    "gn:population": 0,
    "gn:timezone": "Asia/Shanghai",
    "iso:country": "CN",
    "name:zho_x_preferred": [
      "覃山"
    ],
    "wof:name": "Qinshan",
    "wof:placetype": "locality"
  },
  "geometry": {
    "coordinates": [
      109.778,
      23.247
    ],
    "type": "Point"
  }
}