{
  "type": "Feature",
  "properties": {
    "gn:country": "CN",
    "gn:fcode": "PPL",
    "gn:population": 60444,
    "iso:country": "CN",
    "name:ara_x_preferred": [
      "لونغ كوه"
    ],
    "name:ben_x_preferred": [
      "লংকু"
    ],
    "name:dan_x_preferred": [
      "Longkou"
    ],
    "name:deu_x_preferred": [
      "Longkou"
    ],
    "name:ell_x_preferred": [
      "Λόνγκου"
    ],
    "name:eng_x_preferred": [
      "Longkou"
    ],
    "name:epo_x_preferred": [
      "Longkou"
    ],
    "name:fin_x_preferred": [
      "Longkou"
    ],
    "name:fra_x_preferred": [
      "Longkou"
    ],
    "name:gan_x_preferred": [
      "龙口市"
    ],
    "name:guj_x_preferred": [
      "લોંગકોઉ"
    ],
    "name:hin_x_preferred": [
      "लांगकू"
    ],
    "name:ind_x_preferred": [
      "Longkou"
    ],
    "name:ita_x_preferred": [
      "Longkou"
    ],
    "name:jpn_x_preferred": [
      "竜口市"
    ],
    "name:kan_x_preferred": [
      "ಲಾಂಗ್ಕೌ"
    ],
    "name:kik_x_preferred": [
      "Longkou"
    ],
    "name:kor_x_preferred": [
      "룽커우시"
    ],
    "name:lav_x_preferred": [
      "Longkou"
    ],
    "name:lit_x_preferred": [
      "Longkou"
    ],
    "name:mar_x_preferred": [
      "लॉंगकाऊ"
    ],
    "name:msa_x_preferred": [
      "Longkou"
    ],
    "name:nan_x_preferred": [
      "Liông-kháu-chhī"
    ],
    "name:nld_x_preferred": [
      "Longkou"
    ],
    "name:nob_x_preferred": [
      "Longkou"
    ],
    "name:pol_x_preferred": [
      "Longkou"
    ],
    "name:rus_x_preferred": [
      "Лункоу"
    ],
    "name:sin_x_preferred": [
      "ලෝන්ග්කෝ"
    ],
    "name:swe_x_preferred": [
      "Longkou"
    ],
    "name:tam_x_preferred": [
      "லோங்கோவு"
    ],
    "name:tel_x_preferred": [
      "లాంగ్ కూ"
    ],
    "name:tha_x_preferred": [
      "หลงโข่ว"
    ],
    "name:tur_x_preferred": [
      "Longkou"
    ],
    "name:ukr_x_preferred": [
      "Лоукоу"
    ],
    "name:und_x_variant": [
      "Lung-kou-shih"
    ],
    "name:urd_x_preferred": [
      "لونگکوو"
    ],
    "name:vie_x_preferred": [
      "Long Khẩu"
    ],
    "name:war_x_preferred": [
      "Longkou"
    ],
    "name:wuu_x_preferred": [
      "龙口市"
    ],
    "name:yue_x_preferred": [
      "龍口"
    ],
    "name:zho_x_preferred": [
      "龙港"
    ],
    "name:zho_x_variant": [
      "龙港街道",
      "龙口市"
    ],
    "qs:name": "Longkou",
    "qs:photos_9r": 0,
    "qs:photos_sr": 0,
    "qs:pop_sr": "8",
    "wd:wordcount": 384,
    "wof:name": "Longkou",
    "wof:placetype": "locality",
    "wof:population": 60444
  },
  "geometry": {
    "coordinates": [
      120.32861,
      37.65083
    ],
    "type": "Point"
  }
}