{
  "type": "Feature",
  "properties": {
    "gn:admin1_code": "30",
    "gn:asciiname": "Pushaohe",
    "gn:country_code": "CN",
    "gn:dem": 403,
    "gn:feature_class": "P",
    "gn:feature_code": "PPL",
    "gn:name": "Pushaohe",
    "gn:population": 0,
    "gn:timezone": "Asia/Shanghai",
    "iso:country": "CN",
    "name:zho_x_preferred": [
      "葡杓柯"
    ],
    "wof:name": "Pushaohe",
    "wof:placetype": "locality"
  },
  "geometry": {
    "coordinates": [
      116.03217,
      23.67119
    ],
    "type": "Point"
  }
}