{
  "type": "Feature",
  "properties": {
    "gn:admin1_code": "12.0",
    "gn:asciiname": "Guandian",
    "gn:country_code": "CN",
    "gn:dem": 158,
    "gn:feature_class": "P",
    "gn:feature_code": "PPL",
    "gn:name": "Guandian",
    "gn:population": 0,
    "gn:timezone": "Asia/Shanghai",
    "iso:country": "CN",
    "name:zho_x_preferred": [
      "关店"
    ],
    "wof:name": "Guandian",
    "wof:placetype": "locality"
  },
  "geometry": {
    "coordinates": [
      113.72365,
      31.83725
    ],
    "type": "Point"
  }
}