{
  "type": "Feature",
  "properties": {
    "gn:admin1_code": "30.0",
    "gn:asciiname": "Dongzhou",
    "gn:country_code": "CN",
    "gn:dem": 3,
    "gn:feature_class": "P",
    "gn:feature_code": "PPL",
    "gn:name": "Dongzhou",
    "gn:population": 0,
    "gn:timezone": "Asia/Shanghai",
    "iso:country": "CN",
    "name:zho_x_preferred": [
      "东洲"
    ],
    "wof:name": "Dongzhou",
    "wof:placetype": "locality"
  },
  "geometry": {
    "coordinates": [
      113.58758,
      23.1015
    ],
    "type": "Point"
  }
}