{
  "type": "Feature",
  "properties": {
    "gn:admin1_code": "3.0",
    "gn:asciiname": "Fenjia",
    "gn:country_code": "CN",
    "gn:dem": 86,
    "gn:feature_class": "P",
    "gn:feature_code": "PPL",
    "gn:name": "Fenjia",
    "gn:population": 0,
    "gn:timezone": "Asia/Shanghai",
    "iso:country": "CN",
    "name:zho_x_preferred": [
      "芬家"
    ],
    "wof:name": "Fenjia",
    "wof:placetype": "locality"
  },
  "geometry": {
    "coordinates": [
      117.52505,
      28.68464
    ],
    "type": "Point"
  }
}