{
  "type": "Feature",
  "properties": {
    "gn:admin1_code": "5.0",
    "gn:asciiname": "Baiyinhecun",
    "gn:country_code": "CN",
    "gn:dem": 138,
    "gn:feature_class": "P",
    "gn:feature_code": "PPL",
    "gn:name": "Baiyinhecun",
    "gn:population": 0,
    "gn:timezone": "Asia/Shanghai",
    "iso:country": "CN",
    "name:zho_x_preferred": [
      "白音河村"
    ],
    "wof:name": "Baiyinhecun",
    "wof:placetype": "locality"
  },
  "geometry": {
    "coordinates": [
      123.24366,
      46.08025
    ],
    "type": "Point"
  }
}