{
  "type": "Feature",
  "properties": {
    "gn:admin1_code": "3.0",
    "gn:asciiname": "Fanshang Huangjia",
    "gn:country_code": "CN",
    "gn:dem": 134,
    "gn:feature_class": "P",
    "gn:feature_code": "PPL",
    "gn:name": "Fanshang Huangjia",
    "gn:population": 0,
    "gn:timezone": "Asia/Shanghai",
    "iso:country": "CN",
    "name:zho_x_preferred": [
      "畈上黄家"
    ],
    "wof:name": "Fanshang Huangjia",
    "wof:placetype": "locality"
  },
  "geometry": {
    "coordinates": [
      117.3576,
      28.03974
    ],
    "type": "Point"
  }
}