{
  "type": "Feature",
  "properties": {
    "gn:admin1_code": "3",
    "gn:asciiname": "Jingzhou",
    "gn:country_code": "CN",
    "gn:dem": 148,
    "gn:feature_class": "P",
    "gn:feature_code": "PPL",
    "gn:name": "Jingzhou",
    "gn:population": 0,
    "gn:timezone": "Asia/Shanghai",
    "iso:country": "CN",
    "name:afr_x_preferred": [
      "Jingzhou"
    ],
    "name:ara_x_preferred": [
      "جينغتشو"
    ],
    "name:bul_x_preferred": [
      "Дзинджоу"
    ],
    "name:cat_x_preferred": [
      "Jingzhou"
    ],
    "name:cdo_x_preferred": [
      "Gĭng-ciŭ"
    ],
    "name:ces_x_preferred": [
      "Ťing-čou"
    ],
    "name:dan_x_preferred": [
      "Jingzhou"
    ],
    "name:deu_x_preferred": [
      "Jingzhou"
    ],
    "name:eus_x_preferred": [
      "Jingzhou"
    ],
    "name:fas_x_preferred": [
      "جیانگژو"
    ],
    "name:fin_x_preferred": [
      "Jingzhou"
    ],
    "name:fra_x_preferred": [
      "Jingzhou"
    ],
    "name:heb_x_preferred": [
      "ג'ינגז'ואו"
    ],
    "name:hrv_x_preferred": [
      "Jingzhou"
    ],
    "name:hun_x_preferred": [
      "Jingzhou"
    ],
    "name:ind_x_preferred": [
      "Jingzhou"
    ],
    "name:ita_x_preferred": [
      "Jingzhou"
    ],
    "name:jpn_x_preferred": [
      "荊州市"
    ],
    "name:kik_x_preferred": [
      "Jingzhou"
    ],
    "name:kor_x_preferred": [
      "징저우시"
    ],
    "name:mlg_x_preferred": [
      "Jingzhou"
    ],
    "name:nld_x_preferred": [
      "Jingzhou"
    ],
    "name:nno_x_preferred": [
      "Jingzhou"
    ],
    "name:nor_x_preferred": [
      "Jingzhou"
    ],
    "name:pam_x_preferred": [
      "Jingzhou"
    ],
    "name:pol_x_preferred": [
      "Jingzhou"
    ],
    "name:por_x_preferred": [
      "Jingzhou"
    ],
    "name:rus_x_preferred": [
      "Цзинчжоу"
    ],
    "name:spa_x_preferred": [
      "Jingzhou"
    ],
    "name:swe_x_preferred": [
      "Jingzhou"
    ],
    "name:tgl_x_preferred": [
      "Jingzhou"
    ],
    "name:tur_x_preferred": [
      "Jingzhou"
    ],
    "name:ukr_x_preferred": [
      "Цзінчжоу"
    ],
    "name:urd_x_preferred": [
      "جنگژوو"
    ],
    "name:vie_x_preferred": [
      "Kinh Châu"
    ],
    "name:war_x_preferred": [
      "Jingzhou"
    ],
    "name:wuu_x_preferred": [
      "荆州市"
    ],
    "name:zho_x_preferred": [
      "京州"
    ],
    "name:zho_x_variant": [
      "荆州市"
    ],
    "wof:name": "Jingzhou",
    "wof:placetype": "locality"
  },
  "geometry": {
    "coordinates": [
      114.596,
      25.5236
    ],
    "type": "Point"
  }
}