{
  "type": "Feature",
  "properties": {
    "gn:admin1_code": "16.0",
    "gn:asciiname": "Sinian",
    "gn:country_code": "CN",
    "gn:dem": 122,
    "gn:feature_class": "P",
    "gn:feature_code": "PPL",
    "gn:name": "Sinian",
    "gn:population": 0,
    "gn:timezone": "Asia/Shanghai",
    "iso:country": "CN",
    "name:zho_x_preferred": [
      "四念"
    ],
    "wof:name": "Sinian",
    "wof:placetype": "locality"
  },
  "geometry": {
    "coordinates": [
      110.448,
      23.6211
    ],
    "type": "Point"
  }
}