{
  "type": "Feature",
  "properties": {
    "gn:admin1_code": "3.0",
    "gn:asciiname": "Le'an Xian Damatou Zonghe Kenzhichang",
    "gn:country_code": "CN",
    "gn:dem": 131,
    "gn:feature_class": "P",
    "gn:feature_code": "PPLF",
    "gn:name": "Le’an Xian Damatou Zonghe Kenzhichang",
    "gn:population": 0,
    "gn:timezone": "Asia/Shanghai",
    "iso:country": "CN",
    "name:und_x_variant": [
      "Le’an Xian Damatou Zonghe Kenzhichang",
      "乐安县大马头综合垦殖场"
    ],
    "wof:name": "Le'an Xian Damatou Zonghe Kenzhichang",
    "wof:placetype": "locality"
  },
  "geometry": {
    "coordinates": [
      115.74179,
      27.40234
    ],
    "type": "Point"
  }
}