{
  "type": "Feature",
  "properties": {
    "gn:admin1_code": "10.0",
    "gn:asciiname": "Xianzhuang",
    "gn:country_code": "CN",
    "gn:dem": 8,
    "gn:feature_class": "P",
    "gn:feature_code": "PPL",
    "gn:name": "Xianzhuang",
    "gn:population": 0,
    "gn:timezone": "Asia/Shanghai",
    "iso:country": "CN",
    "name:zho_x_preferred": [
      "线庄"
    ],
    "wof:name": "Xianzhuang",
    "wof:placetype": "locality"
  },
  "geometry": {
    "coordinates": [
      116.5231,
      38.98608
    ],
    "type": "Point"
  }
}