{
  "type": "Feature",
  "properties": {
    "gn:admin1_code": "18.0",
    "gn:asciiname": "Xiyangdian",
    "gn:country_code": "CN",
    "gn:dem": 783,
    "gn:feature_class": "P",
    "gn:feature_code": "PPL",
    "gn:name": "Xiyangdian",
    "gn:population": 0,
    "gn:timezone": "Asia/Shanghai",
    "iso:country": "CN",
    "name:zho_x_preferred": [
      "西洋店"
    ],
    "wof:name": "Xiyangdian",
    "wof:placetype": "locality"
  },
  "geometry": {
    "coordinates": [
      109.029,
      26.4656
    ],
    "type": "Point"
  }
}