{
  "type": "Feature",
  "properties": {
    "gn:admin1_code": "15.0",
    "gn:asciiname": "Yaojing",
    "gn:country_code": "CN",
    "gn:dem": 1384,
    "gn:feature_class": "P",
    "gn:feature_code": "PPL",
    "gn:name": "Yaojing",
    "gn:population": 0,
    "gn:timezone": "Asia/Shanghai",
    "iso:country": "CN",
    "name:zho_x_preferred": [
      "腰井"
    ],
    "wof:name": "Yaojing",
    "wof:placetype": "locality"
  },
  "geometry": {
    "coordinates": [
      102.737,
      38.5327
    ],
    "type": "Point"
  }
}