{
  "type": "Feature",
  "properties": {
    "gn:admin1_code": "11",
    "gn:asciiname": "Yanbei",
    "gn:country_code": "CN",
    "gn:dem": 1276,
    "gn:feature_class": "P",
    "gn:feature_code": "PPL",
    "gn:name": "Yanbei",
    "gn:population": 0,
    "gn:timezone": "Asia/Shanghai",
    "iso:country": "CN",
    "name:zho_x_preferred": [
      "岩背"
    ],
    "wof:name": "Yanbei",
    "wof:placetype": "locality"
  },
  "geometry": {
    "coordinates": [
      110.69361,
      27.48944
    ],
    "type": "Point"
  }
}