{
  "type": "Feature",
  "properties": {
    "gn:admin1_code": "1.0",
    "gn:asciiname": "Beifenlu Huizucun",
    "gn:country_code": "CN",
    "gn:dem": 65,
    "gn:feature_class": "P",
    "gn:feature_code": "PPL",
    "gn:name": "Beifenlu Huizucun",
    "gn:population": 0,
    "gn:timezone": "Asia/Shanghai",
    "iso:country": "CN",
    "name:zho_x_preferred": [
      "北分路回族村"
    ],
    "wof:name": "Beifenlu Huizucun",
    "wof:placetype": "locality"
  },
  "geometry": {
    "coordinates": [
      116.9859,
      31.88049
    ],
    "type": "Point"
  }
}