{
  "type": "Feature",
  "properties": {
    "gn:admin1_code": "30.0",
    "gn:asciiname": "Yangnei Juweihui",
    "gn:country_code": "CN",
    "gn:dem": 6,
    "gn:feature_class": "P",
    "gn:feature_code": "PPL",
    "gn:name": "Yangnei Juweihui",
    "gn:population": 0,
    "gn:timezone": "Asia/Shanghai",
    "iso:country": "CN",
    "name:zho_x_preferred": [
      "洋內居委会"
    ],
    "wof:name": "Yangnei Juweihui",
    "wof:placetype": "locality"
  },
  "geometry": {
    "coordinates": [
      116.3156,
      23.30134
    ],
    "type": "Point"
  }
}