{
  "type": "Feature",
  "properties": {
    "gn:admin1_code": "25.0",
    "gn:asciiname": "Yancheng",
    "gn:country_code": "CN",
    "gn:dem": 27,
    "gn:feature_class": "P",
    "gn:feature_code": "PPLA3",
    "gn:name": "Yancheng",
    "gn:population": 0,
    "gn:timezone": "Asia/Shanghai",
    "iso:country": "CN",
    "name:deu_x_preferred": [
      "Qihe"
    ],
    "name:fas_x_preferred": [
      "شهرستان چیهه"
    ],
    "name:heb_x_preferred": [
      "יאנצ'נג"
    ],
    "name:hun_x_preferred": [
      "Yancheng"
    ],
    "name:jpn_x_preferred": [
      "斉河県"
    ],
    "name:kor_x_preferred": [
      "치허현"
    ],
    "name:nor_x_preferred": [
      "Qihe"
    ],
    "name:rus_x_preferred": [
      "Цихэ"
    ],
    "name:swe_x_preferred": [
      "Qihe"
    ],
    "name:und_x_variant": [
      "Ch’i-ho",
      "Yen-ch’eng-chen",
      "Yen-ch’eng",
      "Yancheng",
      "Yancheng Jiedao"
    ],
    "name:vie_x_preferred": [
      "Tề Hà"
    ],
    "name:zho_x_preferred": [
      "晏城"
    ],
    "name:zho_x_variant": [
      "晏城街道",
      "齐河县"
    ],
    "wof:name": "Yancheng",
    "wof:placetype": "locality"
  },
  "geometry": {
    "coordinates": [
      116.74389,
      36.79944
    ],
    "type": "Point"
  }
}