{
  "type": "Feature",
  "properties": {
    "gn:admin1_code": "4.0",
    "gn:asciiname": "Ertang",
    "gn:country_code": "CN",
    "gn:dem": 9,
    "gn:feature_class": "P",
    "gn:feature_code": "PPL",
    "gn:name": "Ertang",
    "gn:population": 0,
    "gn:timezone": "Asia/Shanghai",
    "iso:country": "CN",
    "name:deu_x_preferred": [
      "Ertang"
    ],
    "name:zho_x_preferred": [
      "珥塘"
    ],
    "wof:name": "Ertang",
    "wof:placetype": "locality"
  },
  "geometry": {
    "coordinates": [
      119.68121,
      31.81231
    ],
    "type": "Point"
  }
}