{
  "type": "Feature",
  "properties": {
    "gn:admin1_code": "26.0",
    "gn:asciiname": "Liangjiazhuang",
    "gn:country_code": "CN",
    "gn:dem": 1336,
    "gn:feature_class": "P",
    "gn:feature_code": "PPL",
    "gn:name": "Liangjiazhuang",
    "gn:population": 0,
    "gn:timezone": "Asia/Shanghai",
    "iso:country": "CN",
    "name:zho_x_preferred": [
      "梁家庄"
    ],
    "wof:name": "Liangjiazhuang",
    "wof:placetype": "locality"
  },
  "geometry": {
    "coordinates": [
      109.06176,
      36.12372
    ],
    "type": "Point"
  }
}