{
  "type": "Feature",
  "properties": {
    "gn:admin1_code": "3.0",
    "gn:asciiname": "Houtang",
    "gn:country_code": "CN",
    "gn:dem": 157,
    "gn:feature_class": "P",
    "gn:feature_code": "PPL",
    "gn:name": "Houtang",
    "gn:population": 0,
    "gn:timezone": "Asia/Shanghai",
    "iso:country": "CN",
    "name:und_x_variant": [
      "厚塘"
    ],
    "wof:name": "Houtang",
    "wof:placetype": "locality"
  },
  "geometry": {
    "coordinates": [
      115.29734,
      26.40063
    ],
    "type": "Point"
  }
}