{
  "type": "Feature",
  "properties": {
    "gn:admin1_code": "19.0",
    "gn:asciiname": "Santiandi",
    "gn:country_code": "CN",
    "gn:dem": 246,
    "gn:feature_class": "P",
    "gn:feature_code": "PPL",
    "gn:name": "Santiandi",
    "gn:population": 0,
    "gn:timezone": "Asia/Shanghai",
    "iso:country": "CN",
    "name:und_x_variant": [
      "三天地"
    ],
    "wof:name": "Santiandi",
    "wof:placetype": "locality"
  },
  "geometry": {
    "coordinates": [
      123.03288,
      40.24695
    ],
    "type": "Point"
  }
}