{
  "type": "Feature",
  "properties": {
    "gn:admin1_code": "1.0",
    "gn:asciiname": "Wushangang",
    "gn:country_code": "CN",
    "gn:dem": 48,
    "gn:feature_class": "P",
    "gn:feature_code": "PPL",
    "gn:name": "Wushangang",
    "gn:population": 0,
    "gn:timezone": "Asia/Shanghai",
    "iso:country": "CN",
    "name:zho_x_preferred": [
      "Wushangang"
    ],
    "name:zho_x_variant": [
      "武山岗"
    ],
    "wof:name": "Wushangang",
    "wof:placetype": "locality"
  },
  "geometry": {
    "coordinates": [
      118.98008,
      30.77505
    ],
    "type": "Point"
  }
}