{
  "type": "Feature",
  "properties": {
    "gn:admin1_code": "30",
    "gn:asciiname": "Jingmen",
    "gn:country_code": "CN",
    "gn:dem": 99,
    "gn:feature_class": "P",
    "gn:feature_code": "PPLA4",
    "gn:name": "Jingmen",
    "gn:population": 0,
    "gn:timezone": "Asia/Shanghai",
    "iso:country": "CN",
    "name:ara_x_preferred": [
      "مدينة جينغمن"
    ],
    "name:cdo_x_preferred": [
      "Gĭng-muòng"
    ],
    "name:ceb_x_preferred": [
      "Jingmen Shi"
    ],
    "name:ces_x_preferred": [
      "Ťing-men"
    ],
    "name:dan_x_preferred": [
      "Jingmen"
    ],
    "name:deu_x_preferred": [
      "Jingmen"
    ],
    "name:eus_x_preferred": [
      "Jingmen"
    ],
    "name:fas_x_preferred": [
      "جینگمن"
    ],
    "name:fin_x_preferred": [
      "Jingmen"
    ],
    "name:fra_x_preferred": [
      "Jingmen"
    ],
    "name:heb_x_preferred": [
      "ג'ינגמן"
    ],
    "name:hun_x_preferred": [
      "Jingmen"
    ],
    "name:ita_x_preferred": [
      "Jingmen"
    ],
    "name:jpn_x_preferred": [
      "荊門市"
    ],
    "name:kik_x_preferred": [
      "Jingmen"
    ],
    "name:kor_x_preferred": [
      "징먼시"
    ],
    "name:mlg_x_preferred": [
      "Jingmen"
    ],
    "name:nld_x_preferred": [
      "Jingmen"
    ],
    "name:nno_x_preferred": [
      "Jingmen"
    ],
    "name:nor_x_preferred": [
      "Jingmen"
    ],
    "name:pam_x_preferred": [
      "Jingmen"
    ],
    "name:pol_x_preferred": [
      "Jingmen"
    ],
    "name:por_x_preferred": [
      "Jingmen"
    ],
    "name:rus_x_preferred": [
      "Цзинмэнь"
    ],
    "name:spa_x_preferred": [
      "Jingmen"
    ],
    "name:swe_x_preferred": [
      "Jingmen"
    ],
    "name:tgl_x_preferred": [
      "Jingmen"
    ],
    "name:tur_x_preferred": [
      "Jingmen"
    ],
    "name:und_x_variant": [
      "Jingmen Zhen"
    ],
    "name:urd_x_preferred": [
      "جنگمین"
    ],
    "name:vie_x_preferred": [
      "Kinh Môn"
    ],
    "name:war_x_preferred": [
      "Jingmen"
    ],
    "name:zho_x_preferred": [
      "径门"
    ],
    "name:zho_x_variant": [
      "径门镇",
      "荆门市"
    ],
    "wof:name": "Jingmen",
    "wof:placetype": "locality"
  },
  "geometry": {
    "coordinates": [
      116.35972,
      24.07083
    ],
    "type": "Point"
  }
}