{
  "type": "Feature",
  "properties": {
    "gn:country": "CN",
    "gn:fcode": "PPL",
    "gn:population": 0,
    "iso:country": "CN",
    "name:und_x_variant": [
      "Pingsha"
    ],
    "name:zho_x_preferred": [
      "平沙"
    ],
    "qs:name": "平沙华侨林场",
    "qs:name_adm0": "中國",
    "qs:name_adm1": "广东省",
    "qs:photos": 110,
    "qs:photos_1k": 22,
    "qs:photos_9k": 1,
    "qs:photos_9r": 3,
    "qs:photos_all": 110,
    "qs:photos_sr": 3,
    "qs:placetype": "Town",
    "qs:pop_sr": "0",
    "wof:name": "平沙华侨林场",
    "wof:placetype": "locality",
    "wof:population": 0
  },
  "geometry": {
    "coordinates": [
      112.78077,
      22.50462
    ],
    "type": "Point"
  }
}