{
  "type": "Feature",
  "properties": {
    "gn:admin1_code": "7.0",
    "gn:asciiname": "Shenhui",
    "gn:country_code": "CN",
    "gn:dem": 122,
    "gn:feature_class": "P",
    "gn:feature_code": "PPL",
    "gn:name": "Shenhui",
    "gn:population": 0,
    "gn:timezone": "Asia/Shanghai",
    "iso:country": "CN",
    "name:fra_x_preferred": [
      "Shenhui"
    ],
    "name:jpn_x_preferred": [
      "荷沢神会"
    ],
    "name:pol_x_preferred": [
      "Heze Shenhui"
    ],
    "name:zho_x_preferred": [
      "深辉"
    ],
    "name:zho_x_variant": [
      "菏泽神会"
    ],
    "wof:name": "Shenhui",
    "wof:placetype": "locality"
  },
  "geometry": {
    "coordinates": [
      118.28544,
      25.13972
    ],
    "type": "Point"
  }
}