{
  "type": "Feature",
  "properties": {
    "gn:admin1_code": "11.0",
    "gn:asciiname": "Nitou'ao",
    "gn:country_code": "CN",
    "gn:dem": 521,
    "gn:feature_class": "P",
    "gn:feature_code": "PPL",
    "gn:name": "Nitou’ao",
    "gn:population": 0,
    "gn:timezone": "Asia/Shanghai",
    "iso:country": "CN",
    "name:und_x_variant": [
      "Nitou’ao"
    ],
    "name:zho_x_preferred": [
      "泥头坳"
    ],
    "wof:name": "Nitou'ao",
    "wof:placetype": "locality"
  },
  "geometry": {
    "coordinates": [
      110.52963,
      28.22037000000001
    ],
    "type": "Point"
  }
}