{
  "type": "Feature",
  "properties": {
    "gn:admin1_code": "8.0",
    "gn:asciiname": "Laozuojiatun",
    "gn:country_code": "CN",
    "gn:dem": 322,
    "gn:feature_class": "P",
    "gn:feature_code": "PPL",
    "gn:name": "Laozuojiatun",
    "gn:population": 0,
    "gn:timezone": "Asia/Shanghai",
    "iso:country": "CN",
    "name:zho_x_preferred": [
      "老左家屯"
    ],
    "wof:name": "Laozuojiatun",
    "wof:placetype": "locality"
  },
  "geometry": {
    "coordinates": [
      125.10308,
      48.86975
    ],
    "type": "Point"
  }
}