{
  "type": "Feature",
  "properties": {
    "gn:admin1_code": "1.0",
    "gn:asciiname": "Tonghua",
    "gn:country_code": "CN",
    "gn:dem": 81,
    "gn:feature_class": "P",
    "gn:feature_code": "PPL",
    "gn:name": "Tonghua",
    "gn:population": 0,
    "gn:timezone": "Asia/Shanghai",
    "iso:country": "CN",
    "name:ara_x_preferred": [
      "تونغهوا"
    ],
    "name:ast_x_preferred": [
      "Tonghua"
    ],
    "name:cdo_x_preferred": [
      "Tŭng-huá"
    ],
    "name:ces_x_preferred": [
      "Tchung-chua"
    ],
    "name:dan_x_preferred": [
      "Tonghua"
    ],
    "name:deu_x_preferred": [
      "Tonghua"
    ],
    "name:epo_x_preferred": [
      "Tonghua"
    ],
    "name:eus_x_preferred": [
      "Tonghua"
    ],
    "name:fas_x_preferred": [
      "تانگهوا"
    ],
    "name:fin_x_preferred": [
      "Tonghua"
    ],
    "name:fra_x_preferred": [
      "Tonghua"
    ],
    "name:heb_x_preferred": [
      "טונגואה"
    ],
    "name:hun_x_preferred": [
      "Tonghua"
    ],
    "name:ita_x_preferred": [
      "Tonghua"
    ],
    "name:jpn_x_preferred": [
      "通化市"
    ],
    "name:kik_x_preferred": [
      "Tonghua"
    ],
    "name:kor_x_preferred": [
      "퉁화시"
    ],
    "name:mlg_x_preferred": [
      "Tonghua"
    ],
    "name:nld_x_preferred": [
      "Tonghua"
    ],
    "name:nno_x_preferred": [
      "Tonghua"
    ],
    "name:nor_x_preferred": [
      "Tonghua"
    ],
    "name:pol_x_preferred": [
      "Tonghua"
    ],
    "name:por_x_preferred": [
      "Tonghua"
    ],
    "name:rus_x_preferred": [
      "Тунхуа"
    ],
    "name:spa_x_preferred": [
      "Tonghua"
    ],
    "name:swe_x_preferred": [
      "Tonghua"
    ],
    "name:tur_x_preferred": [
      "Tonghua"
    ],
    "name:urd_x_preferred": [
      "تونگہوا"
    ],
    "name:vie_x_preferred": [
      "Thông Hóa"
    ],
    "name:war_x_preferred": [
      "Tonghua"
    ],
    "name:wuu_x_preferred": [
      "通化市"
    ],
    "name:zho_x_preferred": [
      "桐花"
    ],
    "name:zho_x_variant": [
      "通化市"
    ],
    "wof:name": "Tonghua",
    "wof:placetype": "locality"
  },
  "geometry": {
    "coordinates": [
      119.17047,
      30.70868
    ],
    "type": "Point"
  }
}