{
  "type": "Feature",
  "properties": {
    "gn:admin1_code": "11.0",
    "gn:asciiname": "Xianiujiang",
    "gn:country_code": "CN",
    "gn:dem": 1019,
    "gn:feature_class": "P",
    "gn:feature_code": "PPL",
    "gn:name": "Xianiujiang",
    "gn:population": 0,
    "gn:timezone": "Asia/Shanghai",
    "iso:country": "CN",
    "name:zho_x_preferred": [
      "下牛江"
    ],
    "wof:name": "Xianiujiang",
    "wof:placetype": "locality"
  },
  "geometry": {
    "coordinates": [
      113.83088,
      25.94126
    ],
    "type": "Point"
  }
}