{
  "type": "Feature",
  "properties": {
    "gn:admin1_code": "16",
    "gn:asciiname": "Huayuan",
    "gn:country_code": "CN",
    "gn:dem": 202,
    "gn:feature_class": "P",
    "gn:feature_code": "PPL",
    "gn:name": "Huayuan",
    "gn:population": 0,
    "gn:timezone": "Asia/Shanghai",
    "iso:country": "CN",
    "name:ceb_x_preferred": [
      "Huayuan"
    ],
    "name:deu_x_preferred": [
      "Huayuan"
    ],
    "name:kor_x_preferred": [
      "화위안"
    ],
    "name:zho_x_preferred": [
      "花园"
    ],
    "wof:name": "Huayuan",
    "wof:placetype": "locality"
  },
  "geometry": {
    "coordinates": [
      110.909,
      25.1721
    ],
    "type": "Point"
  }
}