{
  "type": "Feature",
  "properties": {
    "gn:admin1_code": "25.0",
    "gn:asciiname": "Xiematingcun",
    "gn:country_code": "CN",
    "gn:dem": 116,
    "gn:feature_class": "P",
    "gn:feature_code": "PPL",
    "gn:name": "Xiematingcun",
    "gn:population": 0,
    "gn:timezone": "Asia/Shanghai",
    "iso:country": "CN",
    "name:und_x_variant": [
      "Hsieh-ma-t’ing",
      "Xiemating",
      "Xiematingcun"
    ],
    "name:zho_x_preferred": [
      "歇马亭"
    ],
    "name:zho_x_variant": [
      "歇马亭村"
    ],
    "wof:name": "Xiematingcun",
    "wof:placetype": "locality"
  },
  "geometry": {
    "coordinates": [
      117.06245,
      35.78154
    ],
    "type": "Point"
  }
}