{
  "type": "Feature",
  "properties": {
    "gn:admin1_code": "16.0",
    "gn:asciiname": "Guyuan",
    "gn:country_code": "CN",
    "gn:dem": 178,
    "gn:feature_class": "P",
    "gn:feature_code": "PPL",
    "gn:name": "Guyuan",
    "gn:population": 0,
    "gn:timezone": "Asia/Shanghai",
    "iso:country": "CN",
    "name:ara_x_preferred": [
      "جويوان"
    ],
    "name:cdo_x_preferred": [
      "Gó-nguòng"
    ],
    "name:ces_x_preferred": [
      "Ku-jüan"
    ],
    "name:dan_x_preferred": [
      "Guyuan"
    ],
    "name:deu_x_preferred": [
      "Guyuan"
    ],
    "name:eus_x_preferred": [
      "Guyuan"
    ],
    "name:fas_x_preferred": [
      "گویوان"
    ],
    "name:fin_x_preferred": [
      "Guyuan"
    ],
    "name:fra_x_preferred": [
      "Guyuan"
    ],
    "name:ita_x_preferred": [
      "Guyuan"
    ],
    "name:jpn_x_preferred": [
      "固原市"
    ],
    "name:kik_x_preferred": [
      "Guyuan"
    ],
    "name:kor_x_preferred": [
      "구위안시"
    ],
    "name:nld_x_preferred": [
      "Guyuan"
    ],
    "name:nno_x_preferred": [
      "Guyuan"
    ],
    "name:nor_x_preferred": [
      "Guyuan"
    ],
    "name:pol_x_preferred": [
      "Guyuan"
    ],
    "name:rus_x_preferred": [
      "Гуюань"
    ],
    "name:spa_x_preferred": [
      "Guyuan"
    ],
    "name:swe_x_preferred": [
      "Guyuan"
    ],
    "name:tur_x_preferred": [
      "Guyuan"
    ],
    "name:urd_x_preferred": [
      "گویوان"
    ],
    "name:vie_x_preferred": [
      "Cố Nguyên"
    ],
    "name:zho_x_preferred": [
      "古远"
    ],
    "name:zho_x_variant": [
      "固原市"
    ],
    "wof:name": "Guyuan",
    "wof:placetype": "locality"
  },
  "geometry": {
    "coordinates": [
      109.761,
      23.7021
    ],
    "type": "Point"
  }
}