{
  "type": "Feature",
  "properties": {
    "gn:admin1_code": "25",
    "gn:asciiname": "Zhangwang Yicun",
    "gn:country_code": "CN",
    "gn:dem": 10,
    "gn:feature_class": "P",
    "gn:feature_code": "PPL",
    "gn:name": "Zhangwang Yicun",
    "gn:population": 0,
    "gn:timezone": "Asia/Shanghai",
    "iso:country": "CN",
    "name:zho_x_preferred": [
      "张旺一村"
    ],
    "wof:name": "Zhangwang Yicun",
    "wof:placetype": "locality"
  },
  "geometry": {
    "coordinates": [
      118.39255,
      37.79103
    ],
    "type": "Point"
  }
}