{
  "type": "Feature",
  "properties": {
    "gn:admin1_code": "4.0",
    "gn:asciiname": "Lianxin Yizu",
    "gn:country_code": "CN",
    "gn:dem": 3,
    "gn:feature_class": "P",
    "gn:feature_code": "PPLF",
    "gn:name": "Lianxin Yizu",
    "gn:population": 0,
    "gn:timezone": "Asia/Shanghai",
    "iso:country": "CN",
    "name:zho_x_preferred": [
      "联心一组"
    ],
    "wof:name": "Lianxin Yizu",
    "wof:placetype": "locality"
  },
  "geometry": {
    "coordinates": [
      120.37425,
      32.58868
    ],
    "type": "Point"
  }
}