{
  "type": "Feature",
  "properties": {
    "gn:admin1_code": "07",
    "gn:asciiname": "Hushi",
    "gn:country_code": "CN",
    "gn:dem": 11,
    "gn:feature_class": "P",
    "gn:feature_code": "PPLA4",
    "gn:name": "Hushi",
    "gn:population": 0,
    "gn:timezone": "Asia/Shanghai",
    "iso:country": "CN",
    "name:heb_x_preferred": [
      "חושי"
    ],
    "name:und_x_variant": [
      "Hu-shih",
      "Hushi",
      "Hushi Zhen"
    ],
    "name:zho_x_preferred": [
      "笏石"
    ],
    "name:zho_x_variant": [
      "笏石镇"
    ],
    "wof:name": "Hushi",
    "wof:placetype": "locality"
  },
  "geometry": {
    "coordinates": [
      119.08842,
      25.31778
    ],
    "type": "Point"
  }
}