{
  "type": "Feature",
  "properties": {
    "gn:admin1_code": "9.0",
    "gn:asciiname": "Zhucheng",
    "gn:country_code": "CN",
    "gn:dem": 531,
    "gn:feature_class": "P",
    "gn:feature_code": "PPL",
    "gn:name": "Zhucheng",
    "gn:population": 0,
    "gn:timezone": "Asia/Shanghai",
    "iso:country": "CN",
    "name:deu_x_preferred": [
      "Zhucheng"
    ],
    "name:fas_x_preferred": [
      "ژو چنگ"
    ],
    "name:fra_x_preferred": [
      "Zhucheng"
    ],
    "name:hun_x_preferred": [
      "Zhucheng"
    ],
    "name:ita_x_preferred": [
      "Zhucheng"
    ],
    "name:jpn_x_preferred": [
      "諸城市"
    ],
    "name:kat_x_preferred": [
      "ჯუჩენი"
    ],
    "name:kik_x_preferred": [
      "Zhucheng"
    ],
    "name:kor_x_preferred": [
      "주청시"
    ],
    "name:nor_x_preferred": [
      "Zhucheng"
    ],
    "name:pol_x_preferred": [
      "Zhucheng"
    ],
    "name:rus_x_preferred": [
      "Чжучэн"
    ],
    "name:spa_x_preferred": [
      "Zhucheng"
    ],
    "name:swe_x_preferred": [
      "Zhucheng"
    ],
    "name:urd_x_preferred": [
      "ژوچینگ"
    ],
    "name:vie_x_preferred": [
      "Chư Thành"
    ],
    "name:war_x_preferred": [
      "Zhucheng"
    ],
    "name:zho_x_preferred": [
      "朱城"
    ],
    "name:zho_x_variant": [
      "诸城市"
    ],
    "wof:name": "Zhucheng",
    "wof:placetype": "locality"
  },
  "geometry": {
    "coordinates": [
      111.68346,
      34.7632
    ],
    "type": "Point"
  }
}