{
  "type": "Feature",
  "properties": {
    "gn:admin1_code": "12.0",
    "gn:asciiname": "Xishicun",
    "gn:country_code": "CN",
    "gn:dem": 50,
    "gn:feature_class": "P",
    "gn:feature_code": "PPL",
    "gn:name": "Xishicun",
    "gn:population": 0,
    "gn:timezone": "Asia/Shanghai",
    "iso:country": "CN",
    "name:zho_x_preferred": [
      "西十村"
    ],
    "wof:name": "Xishicun",
    "wof:placetype": "locality"
  },
  "geometry": {
    "coordinates": [
      113.51303,
      30.94602
    ],
    "type": "Point"
  }
}