{
  "type": "Feature",
  "properties": {
    "gn:admin1_code": "12.0",
    "gn:asciiname": "Heigou",
    "gn:country_code": "CN",
    "gn:dem": 1142,
    "gn:feature_class": "P",
    "gn:feature_code": "PPL",
    "gn:name": "Heigou",
    "gn:population": 0,
    "gn:timezone": "Asia/Shanghai",
    "iso:country": "CN",
    "name:zho_x_preferred": [
      "黑沟"
    ],
    "wof:name": "Heigou",
    "wof:placetype": "locality"
  },
  "geometry": {
    "coordinates": [
      111.07034,
      32.21934
    ],
    "type": "Point"
  }
}