{
  "type": "Feature",
  "properties": {
    "gn:admin1_code": "19.0",
    "gn:asciiname": "Qiandujia Wobu",
    "gn:country_code": "CN",
    "gn:dem": 27,
    "gn:feature_class": "P",
    "gn:feature_code": "PPL",
    "gn:name": "Qiandujia Wobu",
    "gn:population": 0,
    "gn:timezone": "Asia/Shanghai",
    "iso:country": "CN",
    "name:und_x_variant": [
      "Qiandujiawobao",
      "Qiandujia Wobu"
    ],
    "name:zho_x_preferred": [
      "前杜家窝堡"
    ],
    "wof:name": "Qiandujia Wobu",
    "wof:placetype": "locality"
  },
  "geometry": {
    "coordinates": [
      122.56,
      41.8445
    ],
    "type": "Point"
  }
}