{
  "type": "Feature",
  "properties": {
    "gn:admin1_code": "9.0",
    "gn:asciiname": "Tudiya",
    "gn:country_code": "CN",
    "gn:dem": 1348,
    "gn:feature_class": "P",
    "gn:feature_code": "PPL",
    "gn:name": "Tudiya",
    "gn:population": 0,
    "gn:timezone": "Asia/Shanghai",
    "iso:country": "CN",
    "name:afr_x_preferred": [
      "Tudia"
    ],
    "name:amh_x_preferred": [
      "ቱዲያ"
    ],
    "name:ara_x_preferred": [
      "توديا"
    ],
    "name:bul_x_preferred": [
      "Тудия"
    ],
    "name:cat_x_preferred": [
      "Tudiya"
    ],
    "name:deu_x_preferred": [
      "Tūdīja"
    ],
    "name:ell_x_preferred": [
      "Τουντίγια"
    ],
    "name:fin_x_preferred": [
      "Tudiya"
    ],
    "name:ind_x_preferred": [
      "Tudiya"
    ],
    "name:nld_x_preferred": [
      "Tudiya"
    ],
    "name:ron_x_preferred": [
      "Tudia"
    ],
    "name:spa_x_preferred": [
      "Tudia"
    ],
    "name:srp_x_preferred": [
      "Тудија"
    ],
    "name:tur_x_preferred": [
      "Tudiya"
    ],
    "name:zho_x_preferred": [
      "土地垭"
    ],
    "name:zho_x_variant": [
      "图迪亚"
    ],
    "wof:name": "Tudiya",
    "wof:placetype": "locality"
  },
  "geometry": {
    "coordinates": [
      112.26031,
      33.72734000000001
    ],
    "type": "Point"
  }
}