{
  "type": "Feature",
  "properties": {
    "gn:admin1_code": "8.0",
    "gn:asciiname": "Yikeshucun",
    "gn:country_code": "CN",
    "gn:dem": 133,
    "gn:feature_class": "P",
    "gn:feature_code": "PPL",
    "gn:name": "Yikeshucun",
    "gn:population": 0,
    "gn:timezone": "Asia/Shanghai",
    "iso:country": "CN",
    "name:zho_x_preferred": [
      "一棵树村"
    ],
    "wof:name": "Yikeshucun",
    "wof:placetype": "locality"
  },
  "geometry": {
    "coordinates": [
      124.10044,
      45.92811
    ],
    "type": "Point"
  }
}