{
  "type": "Feature",
  "properties": {
    "gn:admin1_code": "18",
    "gn:asciiname": "Aozizhai",
    "gn:country_code": "CN",
    "gn:dem": 1135,
    "gn:feature_class": "P",
    "gn:feature_code": "PPL",
    "gn:name": "Aozizhai",
    "gn:population": 0,
    "gn:timezone": "Asia/Shanghai",
    "iso:country": "CN",
    "name:zho_x_preferred": [
      "凹子寨"
    ],
    "wof:name": "Aozizhai",
    "wof:placetype": "locality"
  },
  "geometry": {
    "coordinates": [
      105.631,
      26.0345
    ],
    "type": "Point"
  }
}