{
  "type": "Feature",
  "properties": {
    "gn:admin1_code": "04",
    "gn:asciiname": "Guanlin",
    "gn:country_code": "CN",
    "gn:dem": 9,
    "gn:feature_class": "P",
    "gn:feature_code": "PPLA4",
    "gn:name": "Guanlin",
    "gn:population": 0,
    "gn:timezone": "Asia/Shanghai",
    "iso:country": "CN",
    "name:und_x_variant": [
      "Kuan-lin-chen",
      "Kuan-lin",
      "Kuan-ts’un",
      "Kuan-ts’un-chen",
      "Guanlin",
      "Guanlin Zhen"
    ],
    "name:zho_x_preferred": [
      "官林"
    ],
    "name:zho_x_variant": [
      "官林镇"
    ],
    "wof:name": "Guanlin",
    "wof:placetype": "locality"
  },
  "geometry": {
    "coordinates": [
      119.71164,
      31.50404
    ],
    "type": "Point"
  }
}