{
  "type": "Feature",
  "properties": {
    "gn:admin1_code": "29.0",
    "gn:asciiname": "Yangge",
    "gn:country_code": "CN",
    "gn:dem": 1355,
    "gn:feature_class": "P",
    "gn:feature_code": "PPL",
    "gn:name": "Yangge",
    "gn:population": 0,
    "gn:timezone": "Asia/Shanghai",
    "iso:country": "CN",
    "name:ind_x_preferred": [
      "Yangge"
    ],
    "name:jpn_x_preferred": [
      "ヤンガー"
    ],
    "name:nor_x_preferred": [
      "Yangge"
    ],
    "name:zho_x_preferred": [
      "秧革"
    ],
    "name:zho_x_variant": [
      "秧歌舞"
    ],
    "wof:name": "Yangge",
    "wof:placetype": "locality"
  },
  "geometry": {
    "coordinates": [
      104.09,
      24.3039
    ],
    "type": "Point"
  }
}