{
  "type": "Feature",
  "properties": {
    "gn:admin1_code": "30.0",
    "gn:asciiname": "Linhai",
    "gn:country_code": "CN",
    "gn:dem": 2,
    "gn:feature_class": "P",
    "gn:feature_code": "PPL",
    "gn:name": "Linhai",
    "gn:population": 0,
    "gn:timezone": "Asia/Shanghai",
    "iso:country": "CN",
    "name:ara_x_preferred": [
      "لينهاي"
    ],
    "name:deu_x_preferred": [
      "Linhai"
    ],
    "name:ell_x_preferred": [
      "Λινχάι"
    ],
    "name:est_x_preferred": [
      "Linhai"
    ],
    "name:fas_x_preferred": [
      "لینهای"
    ],
    "name:fra_x_preferred": [
      "Linhai"
    ],
    "name:heb_x_preferred": [
      "לינחאי"
    ],
    "name:hin_x_preferred": [
      "लिंहाइ"
    ],
    "name:hun_x_preferred": [
      "Linhai"
    ],
    "name:ita_x_preferred": [
      "Linhai"
    ],
    "name:jpn_x_preferred": [
      "臨海市"
    ],
    "name:kik_x_preferred": [
      "Linhai"
    ],
    "name:kor_x_preferred": [
      "린하이시"
    ],
    "name:mlg_x_preferred": [
      "Linhai"
    ],
    "name:nor_x_preferred": [
      "Linhai"
    ],
    "name:swe_x_preferred": [
      "Linhai"
    ],
    "name:tgl_x_preferred": [
      "Linhai"
    ],
    "name:tur_x_preferred": [
      "Linhai"
    ],
    "name:ukr_x_preferred": [
      "Ліньхай"
    ],
    "name:urd_x_preferred": [
      "لینائی"
    ],
    "name:vie_x_preferred": [
      "Lâm Hải"
    ],
    "name:war_x_preferred": [
      "Linhai"
    ],
    "name:wuu_x_preferred": [
      "临海市"
    ],
    "name:zho_x_preferred": [
      "淋海"
    ],
    "name:zho_x_variant": [
      "临海市"
    ],
    "wof:name": "Linhai",
    "wof:placetype": "locality"
  },
  "geometry": {
    "coordinates": [
      113.15549,
      22.72379
    ],
    "type": "Point"
  }
}