{
  "type": "Feature",
  "properties": {
    "gn:admin1_code": "4.0",
    "gn:asciiname": "Xuzhuang",
    "gn:country_code": "CN",
    "gn:dem": 9,
    "gn:feature_class": "P",
    "gn:feature_code": "PPL",
    "gn:name": "Xuzhuang",
    "gn:population": 0,
    "gn:timezone": "Asia/Shanghai",
    "iso:country": "CN",
    "name:zho_x_preferred": [
      "徐庄"
    ],
    "wof:name": "Xuzhuang",
    "wof:placetype": "locality"
  },
  "geometry": {
    "coordinates": [
      119.16289,
      32.16819
    ],
    "type": "Point"
  }
}