{
  "type": "Feature",
  "properties": {
    "gn:admin1_code": "9.0",
    "gn:asciiname": "Yichang",
    "gn:country_code": "CN",
    "gn:dem": 189,
    "gn:feature_class": "P",
    "gn:feature_code": "PPL",
    "gn:name": "Yichang",
    "gn:population": 0,
    "gn:timezone": "Asia/Shanghai",
    "iso:country": "CN",
    "name:afr_x_preferred": [
      "Yichang"
    ],
    "name:ara_x_preferred": [
      "ييتشانغ"
    ],
    "name:bul_x_preferred": [
      "Ичан"
    ],
    "name:cdo_x_preferred": [
      "Ngì-chiŏng"
    ],
    "name:ceb_x_preferred": [
      "Yichang"
    ],
    "name:ces_x_preferred": [
      "I-čchang"
    ],
    "name:cym_x_preferred": [
      "Yichang"
    ],
    "name:dan_x_preferred": [
      "Yichang"
    ],
    "name:deu_x_preferred": [
      "Yichang"
    ],
    "name:epo_x_preferred": [
      "Jiĉang"
    ],
    "name:eus_x_preferred": [
      "Yichang"
    ],
    "name:fas_x_preferred": [
      "ایچانگ"
    ],
    "name:fin_x_preferred": [
      "Yichang"
    ],
    "name:fra_x_preferred": [
      "Yichang"
    ],
    "name:heb_x_preferred": [
      "ייצ'אנג"
    ],
    "name:ind_x_preferred": [
      "Yichang"
    ],
    "name:ita_x_preferred": [
      "Yichang"
    ],
    "name:jpn_x_preferred": [
      "宜昌市"
    ],
    "name:kik_x_preferred": [
      "Yichang"
    ],
    "name:kor_x_preferred": [
      "이창시"
    ],
    "name:mlg_x_preferred": [
      "Yichang"
    ],
    "name:nld_x_preferred": [
      "Yichang"
    ],
    "name:nno_x_preferred": [
      "Yichang"
    ],
    "name:nor_x_preferred": [
      "Yichang"
    ],
    "name:pam_x_preferred": [
      "Yichang"
    ],
    "name:pol_x_preferred": [
      "Yichang"
    ],
    "name:por_x_preferred": [
      "Yichang"
    ],
    "name:rus_x_preferred": [
      "Ичан"
    ],
    "name:spa_x_preferred": [
      "Yichang"
    ],
    "name:srp_x_preferred": [
      "Јичанг"
    ],
    "name:swe_x_preferred": [
      "Yichang"
    ],
    "name:tgl_x_preferred": [
      "Yichang"
    ],
    "name:tur_x_preferred": [
      "Yichang"
    ],
    "name:ukr_x_preferred": [
      "Ічан"
    ],
    "name:urd_x_preferred": [
      "یچنگ"
    ],
    "name:vep_x_preferred": [
      "Ičan"
    ],
    "name:vie_x_preferred": [
      "Nghi Xương"
    ],
    "name:war_x_preferred": [
      "Yichang"
    ],
    "name:wuu_x_preferred": [
      "宜昌市"
    ],
    "name:zho_x_preferred": [
      "一场"
    ],
    "name:zho_x_variant": [
      "宜昌市"
    ],
    "wof:name": "Yichang",
    "wof:placetype": "locality"
  },
  "geometry": {
    "coordinates": [
      112.90914,
      34.13735
    ],
    "type": "Point"
  }
}