{
  "type": "Feature",
  "properties": {
    "gn:admin1_code": "15.0",
    "gn:asciiname": "Jinchang",
    "gn:country_code": "CN",
    "gn:dem": 2178,
    "gn:feature_class": "P",
    "gn:feature_code": "PPLA4",
    "gn:name": "Jinchang",
    "gn:population": 0,
    "gn:timezone": "Asia/Shanghai",
    "iso:country": "CN",
    "name:ara_x_preferred": [
      "جينشانغ"
    ],
    "name:cdo_x_preferred": [
      "Gĭng-chiŏng"
    ],
    "name:ceb_x_preferred": [
      "Jinchang"
    ],
    "name:ces_x_preferred": [
      "Ťin-čchang"
    ],
    "name:dan_x_preferred": [
      "Jinchang"
    ],
    "name:deu_x_preferred": [
      "Jinchang"
    ],
    "name:eus_x_preferred": [
      "Jinchang"
    ],
    "name:fas_x_preferred": [
      "جینچانگ"
    ],
    "name:fin_x_preferred": [
      "Jinchang"
    ],
    "name:fra_x_preferred": [
      "Jinchang"
    ],
    "name:heb_x_preferred": [
      "ג'יאנצ'אנג"
    ],
    "name:hun_x_preferred": [
      "Jinchang"
    ],
    "name:hye_x_preferred": [
      "Ցզինչան"
    ],
    "name:ind_x_preferred": [
      "Jinchang"
    ],
    "name:ita_x_preferred": [
      "Jinchang"
    ],
    "name:jpn_x_preferred": [
      "金昌市"
    ],
    "name:kik_x_preferred": [
      "Jinchang"
    ],
    "name:kor_x_preferred": [
      "진창시"
    ],
    "name:mlg_x_preferred": [
      "Jinchang"
    ],
    "name:nld_x_preferred": [
      "Jinchang"
    ],
    "name:nno_x_preferred": [
      "Jinchang"
    ],
    "name:nor_x_preferred": [
      "Jinchang"
    ],
    "name:pam_x_preferred": [
      "Jinchang"
    ],
    "name:pnb_x_preferred": [
      "جنچانگ"
    ],
    "name:pol_x_preferred": [
      "Jinchang"
    ],
    "name:por_x_preferred": [
      "Jinchang"
    ],
    "name:rus_x_preferred": [
      "Цзиньчан"
    ],
    "name:spa_x_preferred": [
      "Jinchang"
    ],
    "name:swe_x_preferred": [
      "Jinchang"
    ],
    "name:tgl_x_preferred": [
      "Jinchang"
    ],
    "name:tur_x_preferred": [
      "Jinchang"
    ],
    "name:urd_x_preferred": [
      "جنچانگ"
    ],
    "name:vie_x_preferred": [
      "Kim Xương"
    ],
    "name:war_x_preferred": [
      "Jinchang"
    ],
    "name:wuu_x_preferred": [
      "金昌市"
    ],
    "name:zho_x_preferred": [
      "金厂"
    ],
    "name:zho_x_variant": [
      "金昌市"
    ],
    "wof:name": "Jinchang",
    "wof:placetype": "locality"
  },
  "geometry": {
    "coordinates": [
      104.89633,
      33.61681
    ],
    "type": "Point"
  }
}