{
  "type": "Feature",
  "properties": {
    "gn:admin1_code": "22.0",
    "gn:asciiname": "Baiyangshihucun",
    "gn:country_code": "CN",
    "gn:dem": 944,
    "gn:feature_class": "P",
    "gn:feature_code": "PPL",
    "gn:name": "Baiyangshihucun",
    "gn:population": 0,
    "gn:timezone": "Asia/Shanghai",
    "iso:country": "CN",
    "name:zho_x_preferred": [
      "白羊石虎村"
    ],
    "wof:name": "Baiyangshihucun",
    "wof:placetype": "locality"
  },
  "geometry": {
    "coordinates": [
      115.6121,
      40.10975
    ],
    "type": "Point"
  }
}