{
  "type": "Feature",
  "properties": {
    "gn:admin1_code": "29",
    "gn:asciiname": "Mafang",
    "gn:country_code": "CN",
    "gn:dem": 1821,
    "gn:feature_class": "P",
    "gn:feature_code": "PPL",
    "gn:name": "Mafang",
    "gn:population": 0,
    "gn:timezone": "Asia/Shanghai",
    "iso:country": "CN",
    "name:zho_x_preferred": [
      "马房"
    ],
    "wof:name": "Mafang",
    "wof:placetype": "locality"
  },
  "geometry": {
    "coordinates": [
      101.518,
      25.1171
    ],
    "type": "Point"
  }
}