{
  "type": "Feature",
  "properties": {
    "gn:admin1_code": "29.0",
    "gn:asciiname": "Xin'an",
    "gn:country_code": "CN",
    "gn:dem": 1409,
    "gn:feature_class": "P",
    "gn:feature_code": "PPL",
    "gn:name": "Xin’an",
    "gn:population": 0,
    "gn:timezone": "Asia/Shanghai",
    "iso:country": "CN",
    "name:und_x_variant": [
      "Xin’an"
    ],
    "name:zho_x_preferred": [
      "新安"
    ],
    "wof:name": "Xin'an",
    "wof:placetype": "locality"
  },
  "geometry": {
    "coordinates": [
      104.472,
      24.3146
    ],
    "type": "Point"
  }
}