{
  "type": "Feature",
  "properties": {
    "gn:admin1_code": "03",
    "gn:asciiname": "Tanxi",
    "gn:country_code": "CN",
    "gn:dem": 34,
    "gn:feature_class": "P",
    "gn:feature_code": "PPLA4",
    "gn:name": "Tanxi",
    "gn:population": 0,
    "gn:timezone": "Asia/Shanghai",
    "iso:country": "CN",
    "name:und_x_variant": [
      "T’an-ch’i",
      "T’an-hsi",
      "Tanxi",
      "滩溪",
      "Tanxi Zhen",
      "滩溪镇"
    ],
    "wof:name": "Tanxi",
    "wof:placetype": "locality"
  },
  "geometry": {
    "coordinates": [
      115.63477,
      28.98396
    ],
    "type": "Point"
  }
}