{
  "type": "Feature",
  "properties": {
    "gn:admin1_code": "02",
    "gn:asciiname": "Laotongtian",
    "gn:country_code": "CN",
    "gn:dem": 246,
    "gn:feature_class": "P",
    "gn:feature_code": "PPL",
    "gn:name": "Laotongtian",
    "gn:population": 0,
    "gn:timezone": "Asia/Shanghai",
    "iso:country": "CN",
    "name:zho_x_preferred": [
      "老同田"
    ],
    "wof:name": "Laotongtian",
    "wof:placetype": "locality"
  },
  "geometry": {
    "coordinates": [
      120.51543999999998,
      27.661
    ],
    "type": "Point"
  }
}