{
  "type": "Feature",
  "properties": {
    "gn:country": "CN",
    "gn:fcode": "PPLA3",
    "gn:population": 113609,
    "iso:country": "CN",
    "name:ara_x_preferred": [
      "مابا"
    ],
    "name:ben_x_preferred": [
      "মাবা"
    ],
    "name:dan_x_preferred": [
      "Maba"
    ],
    "name:ell_x_preferred": [
      "Μάμπα"
    ],
    "name:eng_x_preferred": [
      "Maba"
    ],
    "name:fin_x_preferred": [
      "Maba"
    ],
    "name:fra_x_preferred": [
      "Maba"
    ],
    "name:gan_x_preferred": [
      "马坝镇"
    ],
    "name:guj_x_preferred": [
      "માબા"
    ],
    "name:hin_x_preferred": [
      "माबा"
    ],
    "name:ind_x_preferred": [
      "Maba"
    ],
    "name:ita_x_preferred": [
      "Maba"
    ],
    "name:kan_x_preferred": [
      "ಮಾಬ"
    ],
    "name:kor_x_preferred": [
      "마바"
    ],
    "name:lav_x_preferred": [
      "Maba"
    ],
    "name:lit_x_preferred": [
      "Maba"
    ],
    "name:mar_x_preferred": [
      "माबा"
    ],
    "name:msa_x_preferred": [
      "Maba"
    ],
    "name:nld_x_preferred": [
      "Maba"
    ],
    "name:nob_x_preferred": [
      "Maba"
    ],
    "name:pol_x_preferred": [
      "Maba"
    ],
    "name:por_x_preferred": [
      "Maba"
    ],
    "name:rus_x_preferred": [
      "Маба"
    ],
    "name:sin_x_preferred": [
      "මබා"
    ],
    "name:spa_x_preferred": [
      "Maba"
    ],
    "name:swe_x_preferred": [
      "Maba"
    ],
    "name:tam_x_preferred": [
      "மாபா"
    ],
    "name:tel_x_preferred": [
      "మాబా"
    ],
    "name:tha_x_preferred": [
      "มาแบงค์"
    ],
    "name:tur_x_preferred": [
      "Maba"
    ],
    "name:ukr_x_preferred": [
      "Маба"
    ],
    "name:und_x_variant": [
      "Ch’ü-chiang"
    ],
    "name:urd_x_preferred": [
      "مابا"
    ],
    "name:vie_x_preferred": [
      "Maba"
    ],
    "name:wuu_x_preferred": [
      "马坝镇"
    ],
    "name:zho_x_preferred": [
      "马坝镇"
    ],
    "qs:name": "Maba",
    "qs:photos_9r": 0,
    "qs:photos_sr": 0,
    "qs:pop_sr": "9",
    "wof:name": "Maba",
    "wof:placetype": "locality",
    "wof:population": 113609
  },
  "geometry": {
    "coordinates": [
      113.59839,
      24.68412
    ],
    "type": "Point"
  }
}