{
  "type": "Feature",
  "properties": {
    "gn:admin1_code": "26.0",
    "gn:asciiname": "Jiajiagou",
    "gn:country_code": "CN",
    "gn:dem": 889,
    "gn:feature_class": "P",
    "gn:feature_code": "PPL",
    "gn:name": "Jiajiagou",
    "gn:population": 0,
    "gn:timezone": "Asia/Shanghai",
    "iso:country": "CN",
    "name:zho_x_preferred": [
      "贾家沟"
    ],
    "wof:name": "Jiajiagou",
    "wof:placetype": "locality"
  },
  "geometry": {
    "coordinates": [
      108.37186,
      33.08053
    ],
    "type": "Point"
  }
}