{
  "type": "Feature",
  "properties": {
    "gn:admin1_code": "30",
    "gn:asciiname": "Hengshan",
    "gn:country_code": "CN",
    "gn:dem": 35,
    "gn:feature_class": "P",
    "gn:feature_code": "PPLA4",
    "gn:name": "Hengshan",
    "gn:population": 0,
    "gn:timezone": "Asia/Urumqi",
    "iso:country": "CN",
    "name:ceb_x_preferred": [
      "Hengshan"
    ],
    "name:deu_x_preferred": [
      "Hengshan"
    ],
    "name:fra_x_preferred": [
      "Hengshan"
    ],
    "name:nor_x_preferred": [
      "Hengshan"
    ],
    "name:pol_x_preferred": [
      "Heng Shan"
    ],
    "name:rus_x_preferred": [
      "Хэншань"
    ],
    "name:swe_x_preferred": [
      "Hengshan"
    ],
    "name:und_x_variant": [
      "Hang-shan-hsu",
      "Heng-shan-hsü",
      "Hengshan Zhen",
      "横山镇"
    ],
    "name:zho_x_preferred": [
      "横山"
    ],
    "wof:name": "Hengshan",
    "wof:placetype": "locality"
  },
  "geometry": {
    "coordinates": [
      110.06422,
      21.4748
    ],
    "type": "Point"
  }
}