{
  "type": "Feature",
  "properties": {
    "gn:admin1_code": "16.0",
    "gn:asciiname": "Fushan",
    "gn:country_code": "CN",
    "gn:dem": 58,
    "gn:feature_class": "P",
    "gn:feature_code": "PPL",
    "gn:name": "Fushan",
    "gn:population": 0,
    "gn:timezone": "Asia/Shanghai",
    "iso:country": "CN",
    "name:ceb_x_preferred": [
      "Fushan"
    ],
    "name:deu_x_preferred": [
      "Fushan"
    ],
    "name:fra_x_preferred": [
      "Fushan"
    ],
    "name:nor_x_preferred": [
      "Fushan"
    ],
    "name:rus_x_preferred": [
      "Фушань"
    ],
    "name:swe_x_preferred": [
      "Fushan"
    ],
    "name:zho_x_preferred": [
      "福善"
    ],
    "wof:name": "Fushan",
    "wof:placetype": "locality"
  },
  "geometry": {
    "coordinates": [
      110.952,
      23.3228
    ],
    "type": "Point"
  }
}