{
  "type": "Feature",
  "properties": {
    "gn:admin1_code": "02",
    "gn:asciiname": "Hushang'aocun",
    "gn:country_code": "CN",
    "gn:dem": 14,
    "gn:feature_class": "P",
    "gn:feature_code": "PPL",
    "gn:name": "Hushang’aocun",
    "gn:population": 0,
    "gn:timezone": "Asia/Shanghai",
    "iso:country": "CN",
    "name:und_x_variant": [
      "Hushang’aocun"
    ],
    "name:zho_x_preferred": [
      "Hushang’ao"
    ],
    "name:zho_x_variant": [
      "湖上岙村"
    ],
    "wof:name": "Hushang'aocun",
    "wof:placetype": "locality"
  },
  "geometry": {
    "coordinates": [
      120.9419,
      28.11432000000001
    ],
    "type": "Point"
  }
}