{
  "type": "Feature",
  "properties": {
    "gn:admin1_code": "2.0",
    "gn:asciiname": "Puxi",
    "gn:country_code": "CN",
    "gn:dem": 21,
    "gn:feature_class": "P",
    "gn:feature_code": "PPL",
    "gn:name": "Puxi",
    "gn:population": 0,
    "gn:timezone": "Asia/Shanghai",
    "iso:country": "CN",
    "name:ces_x_preferred": [
      "Pchu-si"
    ],
    "name:deu_x_preferred": [
      "Puxi"
    ],
    "name:eus_x_preferred": [
      "Puxi"
    ],
    "name:fra_x_preferred": [
      "Puxi"
    ],
    "name:kor_x_preferred": [
      "푸시"
    ],
    "name:lit_x_preferred": [
      "Pusi"
    ],
    "name:nld_x_preferred": [
      "Puxi"
    ],
    "name:nor_x_preferred": [
      "Puxi"
    ],
    "name:por_x_preferred": [
      "Puxi"
    ],
    "name:rus_x_preferred": [
      "Пуси"
    ],
    "name:spa_x_preferred": [
      "Puxi"
    ],
    "name:ukr_x_preferred": [
      "Пусі"
    ],
    "name:zho_x_preferred": [
      "普溪"
    ],
    "wof:name": "Puxi",
    "wof:placetype": "locality"
  },
  "geometry": {
    "coordinates": [
      121.0921,
      28.72822
    ],
    "type": "Point"
  }
}