{
  "type": "Feature",
  "properties": {
    "gn:admin1_code": "16.0",
    "gn:asciiname": "Hemu",
    "gn:country_code": "CN",
    "gn:dem": 73,
    "gn:feature_class": "P",
    "gn:feature_code": "PPL",
    "gn:name": "Hemu",
    "gn:population": 0,
    "gn:timezone": "Asia/Shanghai",
    "iso:country": "CN",
    "name:ara_x_preferred": [
      "هيمو البقال"
    ],
    "name:deu_x_preferred": [
      "Hemu"
    ],
    "name:epo_x_preferred": [
      "Hemu"
    ],
    "name:hin_x_preferred": [
      "हेमचन्द्र विक्रमादित्य"
    ],
    "name:ita_x_preferred": [
      "Hemu"
    ],
    "name:jpn_x_preferred": [
      "ヘームー"
    ],
    "name:kat_x_preferred": [
      "ჰემუ"
    ],
    "name:mar_x_preferred": [
      "हेमचंद्र विक्रमादित्य"
    ],
    "name:nld_x_preferred": [
      "Hemu"
    ],
    "name:pan_x_preferred": [
      "ਹੇਮੂ"
    ],
    "name:pnb_x_preferred": [
      "ہیمو بقال"
    ],
    "name:rus_x_preferred": [
      "Хему"
    ],
    "name:tam_x_preferred": [
      "ஹெமு"
    ],
    "name:ukr_x_preferred": [
      "Хему Вікрамадітья"
    ],
    "name:zho_x_preferred": [
      "和睦"
    ],
    "wof:name": "Hemu",
    "wof:placetype": "locality"
  },
  "geometry": {
    "coordinates": [
      109.949,
      22.3111
    ],
    "type": "Point"
  }
}