{
  "type": "Feature",
  "properties": {
    "gn:admin1_code": "7",
    "gn:asciiname": "Xiabaisha",
    "gn:country_code": "CN",
    "gn:dem": 10,
    "gn:feature_class": "P",
    "gn:feature_code": "PPL",
    "gn:name": "Xiabaisha",
    "gn:population": 0,
    "gn:timezone": "Asia/Shanghai",
    "iso:country": "CN",
    "name:und_x_variant": [
      "下白沙",
      "Xiabaisha"
    ],
    "wof:name": "Xiabaisha",
    "wof:placetype": "locality"
  },
  "geometry": {
    "coordinates": [
      118.01885,
      24.34147
    ],
    "type": "Point"
  }
}