{
  "type": "Feature",
  "properties": {
    "gn:admin1_code": "10",
    "gn:asciiname": "Shichang",
    "gn:country_code": "CN",
    "gn:dem": 175,
    "gn:feature_class": "P",
    "gn:feature_code": "PPL",
    "gn:name": "Shichang",
    "gn:population": 0,
    "gn:timezone": "Asia/Shanghai",
    "iso:country": "CN",
    "name:zho_x_preferred": [
      "石场"
    ],
    "wof:name": "Shichang",
    "wof:placetype": "locality"
  },
  "geometry": {
    "coordinates": [
      114.088,
      36.3412
    ],
    "type": "Point"
  }
}