{
  "type": "Feature",
  "properties": {
    "gn:admin1_code": "9.0",
    "gn:asciiname": "Dashiqiao",
    "gn:country_code": "CN",
    "gn:dem": 292,
    "gn:feature_class": "P",
    "gn:feature_code": "PPL",
    "gn:name": "Dashiqiao",
    "gn:population": 0,
    "gn:timezone": "Asia/Shanghai",
    "iso:country": "CN",
    "name:ara_x_preferred": [
      "داشيتشياو"
    ],
    "name:ceb_x_preferred": [
      "Dashiqiao City"
    ],
    "name:deu_x_preferred": [
      "Dashiqiao"
    ],
    "name:fra_x_preferred": [
      "Dashiqiao"
    ],
    "name:ita_x_preferred": [
      "Dashiqiao"
    ],
    "name:jpn_x_preferred": [
      "大石橋市"
    ],
    "name:kik_x_preferred": [
      "Dashiqiao"
    ],
    "name:kor_x_preferred": [
      "다스차오시"
    ],
    "name:mlg_x_preferred": [
      "Dashiqiao"
    ],
    "name:nld_x_preferred": [
      "Dashiqiao"
    ],
    "name:nor_x_preferred": [
      "Dashiqiao"
    ],
    "name:rus_x_preferred": [
      "Дашицяо"
    ],
    "name:swe_x_preferred": [
      "Dashiqiao"
    ],
    "name:urd_x_preferred": [
      "داشیچیاو"
    ],
    "name:zho_x_preferred": [
      "大石桥"
    ],
    "name:zho_x_variant": [
      "大石桥市"
    ],
    "wof:name": "Dashiqiao",
    "wof:placetype": "locality"
  },
  "geometry": {
    "coordinates": [
      112.21435,
      34.25223
    ],
    "type": "Point"
  }
}