{
  "type": "Feature",
  "properties": {
    "gn:admin1_code": "10.0",
    "gn:asciiname": "Xuanzhuang",
    "gn:country_code": "CN",
    "gn:dem": 11,
    "gn:feature_class": "P",
    "gn:feature_code": "PPL",
    "gn:name": "Xuanzhuang",
    "gn:population": 0,
    "gn:timezone": "Asia/Shanghai",
    "iso:country": "CN",
    "name:zho_x_preferred": [
      "宣庄"
    ],
    "wof:name": "Xuanzhuang",
    "wof:placetype": "locality"
  },
  "geometry": {
    "coordinates": [
      117.109,
      38.0034
    ],
    "type": "Point"
  }
}