{
  "type": "Feature",
  "properties": {
    "gn:admin1_code": "2.0",
    "gn:asciiname": "Yafan",
    "gn:country_code": "CN",
    "gn:dem": 49,
    "gn:feature_class": "P",
    "gn:feature_code": "PPLA4",
    "gn:name": "Yafan",
    "gn:population": 0,
    "gn:timezone": "Asia/Shanghai",
    "iso:country": "CN",
    "name:und_x_variant": [
      "雅畈",
      "Yafan Zhen"
    ],
    "name:zho_x_preferred": [
      "雅畈镇"
    ],
    "wof:name": "Yafan",
    "wof:placetype": "locality"
  },
  "geometry": {
    "coordinates": [
      119.67535,
      29.03657
    ],
    "type": "Point"
  }
}