{
  "type": "Feature",
  "properties": {
    "gn:admin1_code": "3.0",
    "gn:asciiname": "Gaobeizhen",
    "gn:country_code": "CN",
    "gn:dem": 48,
    "gn:feature_class": "P",
    "gn:feature_code": "PPL",
    "gn:name": "Gaobeizhen",
    "gn:population": 0,
    "gn:timezone": "Asia/Shanghai",
    "iso:country": "CN",
    "name:und_x_variant": [
      "高陂圳"
    ],
    "wof:name": "Gaobeizhen",
    "wof:placetype": "locality"
  },
  "geometry": {
    "coordinates": [
      115.82219,
      29.46203
    ],
    "type": "Point"
  }
}