{
  "type": "Feature",
  "properties": {
    "gn:admin1_code": "30.0",
    "gn:asciiname": "Shagang",
    "gn:country_code": "CN",
    "gn:dem": 5,
    "gn:feature_class": "P",
    "gn:feature_code": "PPL",
    "gn:name": "Shagang",
    "gn:population": 0,
    "gn:timezone": "Asia/Shanghai",
    "iso:country": "CN",
    "name:zho_x_preferred": [
      "沙岡"
    ],
    "wof:name": "Shagang",
    "wof:placetype": "locality"
  },
  "geometry": {
    "coordinates": [
      112.91788,
      22.05658
    ],
    "type": "Point"
  }
}