{
  "type": "Feature",
  "properties": {
    "gn:admin1_code": "15.0",
    "gn:asciiname": "Tanglubu",
    "gn:country_code": "CN",
    "gn:dem": 1499,
    "gn:feature_class": "P",
    "gn:feature_code": "PPL",
    "gn:name": "Tanglübu",
    "gn:population": 0,
    "gn:timezone": "Asia/Shanghai",
    "iso:country": "CN",
    "name:und_x_variant": [
      "Tanglübu"
    ],
    "name:zho_x_preferred": [
      "汤吕堡"
    ],
    "wof:name": "Tanglubu",
    "wof:placetype": "locality"
  },
  "geometry": {
    "coordinates": [
      102.576,
      38.2118
    ],
    "type": "Point"
  }
}