{
  "type": "Feature",
  "properties": {
    "gn:admin1_code": "8.0",
    "gn:asciiname": "Ji'ergele Teguoleng",
    "gn:country_code": "CN",
    "gn:dem": 502,
    "gn:feature_class": "P",
    "gn:feature_code": "PPLA4",
    "gn:name": "Ji’ergele Teguoleng",
    "gn:population": 0,
    "gn:timezone": "Asia/Urumqi",
    "iso:country": "CN",
    "name:und_x_variant": [
      "Ji’ergele Teguoleng",
      "Ji’ergele Teguoleng Xiang",
      "Ji’ergele Teguoleng Mengguzu Xiang"
    ],
    "name:zho_x_preferred": [
      "吉尔格勒特郭楞"
    ],
    "name:zho_x_variant": [
      "吉尔格勒特郭楞乡",
      "吉尔格勒特郭楞蒙古族乡"
    ],
    "wof:name": "Ji'ergele Teguoleng",
    "wof:placetype": "locality"
  },
  "geometry": {
    "coordinates": [
      84.17916,
      44.35542
    ],
    "type": "Point"
  }
}