{
  "type": "Feature",
  "properties": {
    "gn:admin1_code": "26.0",
    "gn:asciiname": "Xiaoxue",
    "gn:country_code": "CN",
    "gn:dem": 1125,
    "gn:feature_class": "P",
    "gn:feature_code": "PPL",
    "gn:name": "Xiaoxue",
    "gn:population": 0,
    "gn:timezone": "Asia/Shanghai",
    "iso:country": "CN",
    "name:afr_x_preferred": [
      "Xiaoxue"
    ],
    "name:cdo_x_preferred": [
      "Siēu-siók"
    ],
    "name:hak_x_preferred": [
      "Séu-siet"
    ],
    "name:kor_x_preferred": [
      "소설"
    ],
    "name:swe_x_preferred": [
      "Xiaoxue"
    ],
    "name:vie_x_preferred": [
      "Tiểu tuyết"
    ],
    "name:zha_x_preferred": [
      "Siujsiet"
    ],
    "name:zho_x_preferred": [
      "小雪"
    ],
    "wof:name": "Xiaoxue",
    "wof:placetype": "locality"
  },
  "geometry": {
    "coordinates": [
      110.26813,
      36.38281
    ],
    "type": "Point"
  }
}