{
  "type": "Feature",
  "properties": {
    "gn:admin1_code": "25",
    "gn:asciiname": "Maoyu",
    "gn:country_code": "CN",
    "gn:dem": 247,
    "gn:feature_class": "P",
    "gn:feature_code": "PPL",
    "gn:name": "Maoyu",
    "gn:population": 0,
    "gn:timezone": "Asia/Shanghai",
    "iso:country": "CN",
    "name:jpn_x_preferred": [
      "まおゆう魔王勇者"
    ],
    "name:tgl_x_preferred": [
      "Maoyu"
    ],
    "name:zho_x_preferred": [
      "毛峪"
    ],
    "name:zho_x_variant": [
      "魔王勇者"
    ],
    "wof:name": "Maoyu",
    "wof:placetype": "locality"
  },
  "geometry": {
    "coordinates": [
      117.958,
      35.2018
    ],
    "type": "Point"
  }
}