{
  "type": "Feature",
  "properties": {
    "gn:country": "CN",
    "gn:fcode": "PPL",
    "gn:population": 3120,
    "iso:country": "CN",
    "name:eng_x_historical": [
      "Feloon"
    ],
    "name:eng_x_preferred": [
      "Feloon"
    ],
    "name:eng_x_variant": [
      "Feiluan"
    ],
    "name:gan_x_preferred": [
      "飞鸾镇"
    ],
    "name:jpn_x_preferred": [
      "飛鸞鎮"
    ],
    "name:wuu_x_preferred": [
      "飞鸾镇"
    ],
    "name:zho_x_preferred": [
      "飞鸾镇"
    ],
    "qs:name": "Feiluan",
    "qs:photos_9r": 0,
    "qs:photos_sr": 0,
    "qs:pop_sr": "4",
    "wd:wordcount": 268,
    "wof:name": "Feiluan",
    "wof:placetype": "locality",
    "wof:population": 3120
  },
  "geometry": {
    "coordinates": [
      119.5975,
      26.5625
    ],
    "type": "Point"
  }
}