{
  "type": "Feature",
  "properties": {
    "gn:admin1_code": "15.0",
    "gn:asciiname": "Maquangou",
    "gn:country_code": "CN",
    "gn:dem": 1757,
    "gn:feature_class": "P",
    "gn:feature_code": "PPL",
    "gn:name": "Maquangou",
    "gn:population": 0,
    "gn:timezone": "Asia/Shanghai",
    "iso:country": "CN",
    "name:und_x_variant": [
      "马泉沟"
    ],
    "wof:name": "Maquangou",
    "wof:placetype": "locality"
  },
  "geometry": {
    "coordinates": [
      106.82925,
      36.64255
    ],
    "type": "Point"
  }
}