{
  "type": "Feature",
  "properties": {
    "gn:admin1_code": "4.0",
    "gn:asciiname": "Xuguan",
    "gn:country_code": "CN",
    "gn:dem": 6,
    "gn:feature_class": "P",
    "gn:feature_code": "PPL",
    "gn:name": "Xuguan",
    "gn:population": 0,
    "gn:timezone": "Asia/Shanghai",
    "iso:country": "CN",
    "name:und_x_variant": [
      "Xuxu"
    ],
    "name:zho_x_preferred": [
      "徐官"
    ],
    "name:zho_x_variant": [
      "徐圩"
    ],
    "wof:name": "Xuguan",
    "wof:placetype": "locality"
  },
  "geometry": {
    "coordinates": [
      119.70831,
      32.96314
    ],
    "type": "Point"
  }
}