{
  "type": "Feature",
  "properties": {
    "gn:admin1_code": "1.0",
    "gn:asciiname": "Tuanshan Erzhongdui",
    "gn:country_code": "CN",
    "gn:dem": 41,
    "gn:feature_class": "P",
    "gn:feature_code": "PPLF",
    "gn:name": "Tuanshan Erzhongdui",
    "gn:population": 0,
    "gn:timezone": "Asia/Shanghai",
    "iso:country": "CN",
    "name:zho_x_preferred": [
      "Tuanshan Erzhongdui"
    ],
    "name:zho_x_variant": [
      "团山二中队"
    ],
    "wof:name": "Tuanshan Erzhongdui",
    "wof:placetype": "locality"
  },
  "geometry": {
    "coordinates": [
      119.35067,
      30.95317
    ],
    "type": "Point"
  }
}