{
  "type": "Feature",
  "properties": {
    "gn:admin1_code": "30",
    "gn:asciiname": "Nankou",
    "gn:country_code": "CN",
    "gn:dem": 111,
    "gn:feature_class": "P",
    "gn:feature_code": "PPLA4",
    "gn:name": "Nankou",
    "gn:population": 0,
    "gn:timezone": "Asia/Shanghai",
    "iso:country": "CN",
    "name:und_x_variant": [
      "Nankou Zhen",
      "南口镇"
    ],
    "name:zho_x_preferred": [
      "Nan-k’ou-hsü"
    ],
    "name:zho_x_variant": [
      "南口"
    ],
    "wof:name": "Nankou",
    "wof:placetype": "locality"
  },
  "geometry": {
    "coordinates": [
      115.98753,
      24.27437
    ],
    "type": "Point"
  }
}