{
  "type": "Feature",
  "properties": {
    "gn:admin1_code": "1.0",
    "gn:asciiname": "Lijicun",
    "gn:country_code": "CN",
    "gn:dem": 30,
    "gn:feature_class": "P",
    "gn:feature_code": "PPL",
    "gn:name": "Lijicun",
    "gn:population": 0,
    "gn:timezone": "Asia/Shanghai",
    "iso:country": "CN",
    "name:und_x_variant": [
      "Liji"
    ],
    "name:zho_x_preferred": [
      "李集村"
    ],
    "wof:name": "Lijicun",
    "wof:placetype": "locality"
  },
  "geometry": {
    "coordinates": [
      115.92134,
      32.5297
    ],
    "type": "Point"
  }
}