{
  "type": "Feature",
  "properties": {
    "gn:admin1_code": "11.0",
    "gn:asciiname": "Baomudong",
    "gn:country_code": "CN",
    "gn:dem": 136,
    "gn:feature_class": "P",
    "gn:feature_code": "PPL",
    "gn:name": "Baomudong",
    "gn:population": 0,
    "gn:timezone": "Asia/Shanghai",
    "iso:country": "CN",
    "name:zho_x_preferred": [
      "报木洞"
    ],
    "wof:name": "Baomudong",
    "wof:placetype": "locality"
  },
  "geometry": {
    "coordinates": [
      110.14003,
      27.93325
    ],
    "type": "Point"
  }
}