{
  "type": "Feature",
  "properties": {
    "gn:admin1_code": "7.0",
    "gn:asciiname": "Dongshanzhai",
    "gn:country_code": "CN",
    "gn:dem": 190,
    "gn:feature_class": "P",
    "gn:feature_code": "PPL",
    "gn:name": "Dongshanzhai",
    "gn:population": 0,
    "gn:timezone": "Asia/Shanghai",
    "iso:country": "CN",
    "name:zho_x_preferred": [
      "东山寨"
    ],
    "wof:name": "Dongshanzhai",
    "wof:placetype": "locality"
  },
  "geometry": {
    "coordinates": [
      118.33214,
      26.39129
    ],
    "type": "Point"
  }
}