{
  "type": "Feature",
  "properties": {
    "gn:admin1_code": "19.0",
    "gn:asciiname": "Tianjiacun",
    "gn:country_code": "CN",
    "gn:dem": 234,
    "gn:feature_class": "P",
    "gn:feature_code": "PPL",
    "gn:name": "Tianjiacun",
    "gn:population": 0,
    "gn:timezone": "Asia/Shanghai",
    "iso:country": "CN",
    "name:zho_x_preferred": [
      "田家村"
    ],
    "wof:name": "Tianjiacun",
    "wof:placetype": "locality"
  },
  "geometry": {
    "coordinates": [
      124.34457,
      42.934
    ],
    "type": "Point"
  }
}