{
  "type": "Feature",
  "properties": {
    "gn:admin1_code": "14",
    "gn:asciiname": "Gyixong",
    "gn:country_code": "CN",
    "gn:dem": 3570,
    "gn:feature_class": "P",
    "gn:feature_code": "PPL",
    "gn:name": "Gyixong",
    "gn:population": 0,
    "gn:timezone": "Asia/Urumqi",
    "iso:country": "CN",
    "name:bod_x_preferred": [
      "སྐྱིད་གཤོངས"
    ],
    "name:und_x_variant": [
      "Jixiong"
    ],
    "name:zho_x_preferred": [
      "吉雄"
    ],
    "wof:name": "Gyixong",
    "wof:placetype": "locality"
  },
  "geometry": {
    "coordinates": [
      90.9819,
      29.29299
    ],
    "type": "Point"
  }
}