{
  "type": "Feature",
  "properties": {
    "gn:admin1_code": "2.0",
    "gn:asciiname": "Huangjian Lingxia",
    "gn:country_code": "CN",
    "gn:dem": 172,
    "gn:feature_class": "P",
    "gn:feature_code": "PPL",
    "gn:name": "Huangjian Lingxia",
    "gn:population": 0,
    "gn:timezone": "Asia/Shanghai",
    "iso:country": "CN",
    "name:zho_x_preferred": [
      "黄尖岭下"
    ],
    "wof:name": "Huangjian Lingxia",
    "wof:placetype": "locality"
  },
  "geometry": {
    "coordinates": [
      120.62222,
      29.68711
    ],
    "type": "Point"
  }
}