{
  "type": "Feature",
  "properties": {
    "gn:admin1_code": "8.0",
    "gn:asciiname": "Lixincun",
    "gn:country_code": "CN",
    "gn:dem": 206,
    "gn:feature_class": "P",
    "gn:feature_code": "PPL",
    "gn:name": "Lixincun",
    "gn:population": 0,
    "gn:timezone": "Asia/Shanghai",
    "iso:country": "CN",
    "name:zho_x_preferred": [
      "立新村"
    ],
    "wof:name": "Lixincun",
    "wof:placetype": "locality"
  },
  "geometry": {
    "coordinates": [
      131.24109,
      46.56041
    ],
    "type": "Point"
  }
}