{
  "type": "Feature",
  "properties": {
    "gn:admin1_code": "2.0",
    "gn:asciiname": "Anling",
    "gn:country_code": "CN",
    "gn:dem": 447,
    "gn:feature_class": "P",
    "gn:feature_code": "PPLA4",
    "gn:name": "Anling",
    "gn:population": 0,
    "gn:timezone": "Asia/Shanghai",
    "iso:country": "CN",
    "name:und_x_variant": [
      "Anling Xiang",
      "Shangmenlou"
    ],
    "name:zho_x_preferred": [
      "安岭"
    ],
    "name:zho_x_variant": [
      "安岭乡",
      "上门楼"
    ],
    "wof:name": "Anling",
    "wof:placetype": "locality"
  },
  "geometry": {
    "coordinates": [
      120.34763999999998,
      28.56463
    ],
    "type": "Point"
  }
}