{
  "type": "Feature",
  "properties": {
    "gn:admin1_code": "13.0",
    "gn:asciiname": "Tuogemanbashi",
    "gn:country_code": "CN",
    "gn:dem": 2691,
    "gn:feature_class": "P",
    "gn:feature_code": "PPL",
    "gn:name": "Tuogemanbashi",
    "gn:population": 0,
    "gn:timezone": "Asia/Shanghai",
    "iso:country": "CN",
    "name:zho_x_preferred": [
      "托格曼巴什"
    ],
    "wof:name": "Tuogemanbashi",
    "wof:placetype": "locality"
  },
  "geometry": {
    "coordinates": [
      81.95721,
      36.41296
    ],
    "type": "Point"
  }
}