{
  "type": "Feature",
  "properties": {
    "gn:admin1_code": "30",
    "gn:asciiname": "Caogangwu Nongchang",
    "gn:country_code": "CN",
    "gn:dem": 457,
    "gn:feature_class": "P",
    "gn:feature_code": "PPLF",
    "gn:name": "Caogangwu Nongchang",
    "gn:population": 0,
    "gn:timezone": "Asia/Shanghai",
    "iso:country": "CN",
    "name:zho_x_preferred": [
      "草岗武农场"
    ],
    "wof:name": "Caogangwu Nongchang",
    "wof:placetype": "locality"
  },
  "geometry": {
    "coordinates": [
      116.75055,
      23.76162
    ],
    "type": "Point"
  }
}