{
  "type": "Feature",
  "properties": {
    "gn:admin1_code": "25.0",
    "gn:asciiname": "Yangqilingcun",
    "gn:country_code": "CN",
    "gn:dem": 125,
    "gn:feature_class": "P",
    "gn:feature_code": "PPL",
    "gn:name": "Yangqilingcun",
    "gn:population": 0,
    "gn:timezone": "Asia/Shanghai",
    "iso:country": "CN",
    "name:zho_x_preferred": [
      "杨七岭村"
    ],
    "wof:name": "Yangqilingcun",
    "wof:placetype": "locality"
  },
  "geometry": {
    "coordinates": [
      120.11271,
      35.9568
    ],
    "type": "Point"
  }
}