{
  "type": "Feature",
  "properties": {
    "gn:admin1_code": "16.0",
    "gn:asciiname": "Dongsa",
    "gn:country_code": "CN",
    "gn:dem": 529,
    "gn:feature_class": "P",
    "gn:feature_code": "PPL",
    "gn:name": "Dongsa",
    "gn:population": 0,
    "gn:timezone": "Asia/Ho_Chi_Minh",
    "iso:country": "CN",
    "name:zho_x_preferred": [
      "洞洒"
    ],
    "wof:name": "Dongsa",
    "wof:placetype": "locality"
  },
  "geometry": {
    "coordinates": [
      105.577,
      23.0747
    ],
    "type": "Point"
  }
}