{
  "type": "Feature",
  "properties": {
    "gn:admin1_code": "30.0",
    "gn:asciiname": "Zengcuoliao",
    "gn:country_code": "CN",
    "gn:dem": 17,
    "gn:feature_class": "P",
    "gn:feature_code": "PPL",
    "gn:name": "Zengcuoliao",
    "gn:population": 0,
    "gn:timezone": "Asia/Shanghai",
    "iso:country": "CN",
    "name:zho_x_preferred": [
      "曾厝寮"
    ],
    "wof:name": "Zengcuoliao",
    "wof:placetype": "locality"
  },
  "geometry": {
    "coordinates": [
      115.85562,
      22.86586
    ],
    "type": "Point"
  }
}