{
  "type": "Feature",
  "properties": {
    "gn:admin1_code": "11",
    "gn:asciiname": "Silihe",
    "gn:country_code": "CN",
    "gn:dem": 117,
    "gn:feature_class": "P",
    "gn:feature_code": "PPLA4",
    "gn:name": "Silihe",
    "gn:population": 0,
    "gn:timezone": "Asia/Shanghai",
    "iso:country": "CN",
    "name:und_x_variant": [
      "Silihe Xiang"
    ],
    "name:zho_x_preferred": [
      "泗里河"
    ],
    "name:zho_x_variant": [
      "泗里河乡"
    ],
    "wof:name": "Silihe",
    "wof:placetype": "locality"
  },
  "geometry": {
    "coordinates": [
      111.82278,
      28.41194
    ],
    "type": "Point"
  }
}