{
  "type": "Feature",
  "properties": {
    "gn:admin1_code": "10",
    "gn:asciiname": "Xigoukou",
    "gn:country_code": "CN",
    "gn:dem": 1202,
    "gn:feature_class": "P",
    "gn:feature_code": "PPL",
    "gn:name": "Xigoukou",
    "gn:population": 0,
    "gn:timezone": "Asia/Shanghai",
    "iso:country": "CN",
    "name:zho_x_preferred": [
      "西沟口"
    ],
    "wof:name": "Xigoukou",
    "wof:placetype": "locality"
  },
  "geometry": {
    "coordinates": [
      116.53963,
      41.87639
    ],
    "type": "Point"
  }
}