{
  "type": "Feature",
  "properties": {
    "gn:admin1_code": "2.0",
    "gn:asciiname": "Huimin",
    "gn:country_code": "CN",
    "gn:dem": 6,
    "gn:feature_class": "P",
    "gn:feature_code": "PPLA4",
    "gn:name": "Huimin",
    "gn:population": 0,
    "gn:timezone": "Asia/Shanghai",
    "iso:country": "CN",
    "name:ceb_x_preferred": [
      "Huimin"
    ],
    "name:deu_x_preferred": [
      "Huimin"
    ],
    "name:fra_x_preferred": [
      "Huimin"
    ],
    "name:nor_x_preferred": [
      "Huimin"
    ],
    "name:rus_x_preferred": [
      "Хуэйминь"
    ],
    "name:swe_x_preferred": [
      "Huimin"
    ],
    "name:und_x_variant": [
      "惠民",
      "Huimin Zhen",
      "惠民镇"
    ],
    "wof:name": "Huimin",
    "wof:placetype": "locality"
  },
  "geometry": {
    "coordinates": [
      120.96989,
      30.83909
    ],
    "type": "Point"
  }
}