{
  "type": "Feature",
  "properties": {
    "gn:admin1_code": "4.0",
    "gn:asciiname": "Shuangduo",
    "gn:country_code": "CN",
    "gn:dem": 4,
    "gn:feature_class": "P",
    "gn:feature_code": "PPL",
    "gn:name": "Shuangduo",
    "gn:population": 0,
    "gn:timezone": "Asia/Shanghai",
    "iso:country": "CN",
    "name:zho_x_preferred": [
      "双垛"
    ],
    "wof:name": "Shuangduo",
    "wof:placetype": "locality"
  },
  "geometry": {
    "coordinates": [
      120.94872,
      31.34588
    ],
    "type": "Point"
  }
}