{
  "type": "Feature",
  "properties": {
    "gn:admin1_code": "02",
    "gn:asciiname": "Wuyushancun",
    "gn:country_code": "CN",
    "gn:dem": 1,
    "gn:feature_class": "P",
    "gn:feature_code": "PPL",
    "gn:name": "Wuyushancun",
    "gn:population": 0,
    "gn:timezone": "Asia/Shanghai",
    "iso:country": "CN",
    "name:und_x_variant": [
      "Wu-yü-shan-ts’un",
      "Wuyushan",
      "Wuyushancun"
    ],
    "name:zho_x_preferred": [
      "乌屿山"
    ],
    "name:zho_x_variant": [
      "乌屿山村"
    ],
    "wof:name": "Wuyushancun",
    "wof:placetype": "locality"
  },
  "geometry": {
    "coordinates": [
      121.88521,
      29.61664
    ],
    "type": "Point"
  }
}