{
  "type": "Feature",
  "properties": {
    "gn:admin1_code": "16.0",
    "gn:asciiname": "Tianliao",
    "gn:country_code": "CN",
    "gn:dem": 21,
    "gn:feature_class": "P",
    "gn:feature_code": "PPL",
    "gn:name": "Tianliao",
    "gn:population": 0,
    "gn:timezone": "Asia/Shanghai",
    "iso:country": "CN",
    "name:zho_x_preferred": [
      "田寮"
    ],
    "wof:name": "Tianliao",
    "wof:placetype": "locality"
  },
  "geometry": {
    "coordinates": [
      108.275,
      21.8085
    ],
    "type": "Point"
  }
}