{
  "type": "Feature",
  "properties": {
    "gn:admin1_code": "19.0",
    "gn:asciiname": "Taogou",
    "gn:country_code": "CN",
    "gn:dem": 18,
    "gn:feature_class": "P",
    "gn:feature_code": "PPL",
    "gn:name": "Taogou",
    "gn:population": 0,
    "gn:timezone": "Asia/Shanghai",
    "iso:country": "CN",
    "name:und_x_variant": [
      "桃沟"
    ],
    "wof:name": "Taogou",
    "wof:placetype": "locality"
  },
  "geometry": {
    "coordinates": [
      122.42761000000002,
      40.48636
    ],
    "type": "Point"
  }
}