{
  "type": "Feature",
  "properties": {
    "gn:admin1_code": "15.0",
    "gn:asciiname": "Yangpozhuang",
    "gn:country_code": "CN",
    "gn:dem": 1405,
    "gn:feature_class": "P",
    "gn:feature_code": "PPL",
    "gn:name": "Yangpozhuang",
    "gn:population": 0,
    "gn:timezone": "Asia/Shanghai",
    "iso:country": "CN",
    "name:zho_x_preferred": [
      "阳坡庄"
    ],
    "wof:name": "Yangpozhuang",
    "wof:placetype": "locality"
  },
  "geometry": {
    "coordinates": [
      105.442,
      34.6024
    ],
    "type": "Point"
  }
}