{
  "type": "Feature",
  "properties": {
    "gn:admin1_code": "9.0",
    "gn:asciiname": "Hekou",
    "gn:country_code": "CN",
    "gn:dem": 226,
    "gn:feature_class": "P",
    "gn:feature_code": "PPL",
    "gn:name": "Hekou",
    "gn:population": 0,
    "gn:timezone": "Asia/Shanghai",
    "iso:country": "CN",
    "name:ceb_x_preferred": [
      "Hekou"
    ],
    "name:deu_x_preferred": [
      "Hekou"
    ],
    "name:fra_x_preferred": [
      "Hekou"
    ],
    "name:nor_x_preferred": [
      "Hekou"
    ],
    "name:rus_x_preferred": [
      "Хэкоу"
    ],
    "name:swe_x_preferred": [
      "Hekou"
    ],
    "name:und_x_variant": [
      "河口"
    ],
    "wof:name": "Hekou",
    "wof:placetype": "locality"
  },
  "geometry": {
    "coordinates": [
      112.02494,
      33.23562
    ],
    "type": "Point"
  }
}