{
  "type": "Feature",
  "properties": {
    "gn:admin1_code": "03",
    "gn:asciiname": "Dajishan",
    "gn:country_code": "CN",
    "gn:dem": 417,
    "gn:feature_class": "P",
    "gn:feature_code": "PPLA4",
    "gn:name": "Dajishan",
    "gn:population": 0,
    "gn:timezone": "Asia/Shanghai",
    "iso:country": "CN",
    "name:und_x_variant": [
      "Ta-chi-shan",
      "Dajishan",
      "大吉山",
      "Dajishan Zhen",
      "大吉山镇"
    ],
    "wof:name": "Dajishan",
    "wof:placetype": "locality"
  },
  "geometry": {
    "coordinates": [
      114.3614,
      24.60521
    ],
    "type": "Point"
  }
}