{
  "type": "Feature",
  "properties": {
    "gn:admin1_code": "16.0",
    "gn:asciiname": "Pinglin",
    "gn:country_code": "CN",
    "gn:dem": 528,
    "gn:feature_class": "P",
    "gn:feature_code": "PPL",
    "gn:name": "Pinglin",
    "gn:population": 0,
    "gn:timezone": "Asia/Shanghai",
    "iso:country": "CN",
    "name:zho_x_preferred": [
      "平林"
    ],
    "wof:name": "Pinglin",
    "wof:placetype": "locality"
  },
  "geometry": {
    "coordinates": [
      106.046,
      24.0958
    ],
    "type": "Point"
  }
}