{
  "type": "Feature",
  "properties": {
    "gn:country": "CN",
    "gn:fcode": "PPL",
    "gn:population": 74725,
    "iso:country": "CN",
    "name:ceb_x_preferred": [
      "Yanggu Xian"
    ],
    "name:deu_x_preferred": [
      "Yanggu"
    ],
    "name:eng_x_preferred": [
      "Yanggu County"
    ],
    "name:fas_x_preferred": [
      "یانگو"
    ],
    "name:gan_x_preferred": [
      "阳谷县"
    ],
    "name:jpn_x_preferred": [
      "陽谷県"
    ],
    "name:kor_x_preferred": [
      "양구현"
    ],
    "name:nan_x_preferred": [
      "Iông-kok-koān"
    ],
    "name:nld_x_preferred": [
      "Yanggu"
    ],
    "name:nob_x_preferred": [
      "Yanggu"
    ],
    "name:rus_x_preferred": [
      "Янг"
    ],
    "name:rus_x_variant": [
      "Янгу"
    ],
    "name:swe_x_preferred": [
      "Yanggu"
    ],
    "name:und_x_variant": [
      "Yang-ku"
    ],
    "name:urd_x_preferred": [
      "ینگگو کاؤنٹی"
    ],
    "name:vie_x_preferred": [
      "Dương Cốc"
    ],
    "name:wuu_x_preferred": [
      "阳谷县"
    ],
    "name:yue_x_preferred": [
      "陽穀"
    ],
    "name:zho_x_preferred": [
      "阳谷县"
    ],
    "qs:name": "阳谷",
    "qs:name_adm0": "中國",
    "qs:name_adm1": "山东省",
    "qs:photos_9r": 0,
    "qs:photos_sr": 0,
    "qs:placetype": "Town",
    "qs:pop_sr": "8",
    "wd:wordcount": 71,
    "wof:name": "阳谷",
    "wof:placetype": "locality",
    "wof:population": 74725
  },
  "geometry": {
    "coordinates": [
      115.77528,
      36.11056
    ],
    "type": "Point"
  }
}