{
  "type": "Feature",
  "properties": {
    "gn:admin1_code": "2.0",
    "gn:asciiname": "Dama",
    "gn:country_code": "CN",
    "gn:dem": 62,
    "gn:feature_class": "P",
    "gn:feature_code": "PPL",
    "gn:name": "Dama",
    "gn:population": 0,
    "gn:timezone": "Asia/Shanghai",
    "iso:country": "CN",
    "name:aze_x_preferred": [
      "Dama"
    ],
    "name:bel_x_preferred": [
      "Дама"
    ],
    "name:bul_x_preferred": [
      "Дама"
    ],
    "name:cat_x_preferred": [
      "Dama"
    ],
    "name:ceb_x_preferred": [
      "Dama"
    ],
    "name:ces_x_preferred": [
      "Dáma"
    ],
    "name:deu_x_preferred": [
      "Dama"
    ],
    "name:ell_x_preferred": [
      "Ντάμα"
    ],
    "name:eus_x_preferred": [
      "Dama"
    ],
    "name:fra_x_preferred": [
      "Dama"
    ],
    "name:heb_x_preferred": [
      "דמה"
    ],
    "name:ita_x_preferred": [
      "Dama"
    ],
    "name:nor_x_preferred": [
      "Dama"
    ],
    "name:pol_x_preferred": [
      "Dama"
    ],
    "name:por_x_preferred": [
      "Dama"
    ],
    "name:rus_x_preferred": [
      "Дама"
    ],
    "name:slk_x_preferred": [
      "Dáma"
    ],
    "name:slv_x_preferred": [
      "Dama"
    ],
    "name:spa_x_preferred": [
      "Dama"
    ],
    "name:srp_x_preferred": [
      "Дама"
    ],
    "name:swe_x_preferred": [
      "Dama"
    ],
    "name:ukr_x_preferred": [
      "Дама"
    ],
    "name:und_x_variant": [
      "大马"
    ],
    "wof:name": "Dama",
    "wof:placetype": "locality"
  },
  "geometry": {
    "coordinates": [
      119.69377,
      30.28304
    ],
    "type": "Point"
  }
}