{
  "type": "Feature",
  "properties": {
    "gn:admin1_code": "19.0",
    "gn:asciiname": "Huangjiagou",
    "gn:country_code": "CN",
    "gn:dem": 88,
    "gn:feature_class": "P",
    "gn:feature_code": "PPL",
    "gn:name": "Huangjiagou",
    "gn:population": 0,
    "gn:timezone": "Asia/Shanghai",
    "iso:country": "CN",
    "name:zho_x_preferred": [
      "黄家沟"
    ],
    "wof:name": "Huangjiagou",
    "wof:placetype": "locality"
  },
  "geometry": {
    "coordinates": [
      122.734,
      39.8442
    ],
    "type": "Point"
  }
}