{
  "type": "Feature",
  "properties": {
    "gn:admin1_code": "11.0",
    "gn:asciiname": "Lutian",
    "gn:country_code": "CN",
    "gn:dem": 88,
    "gn:feature_class": "P",
    "gn:feature_code": "PPL",
    "gn:name": "Lütian",
    "gn:population": 0,
    "gn:timezone": "Asia/Shanghai",
    "iso:country": "CN",
    "name:und_x_variant": [
      "Lütian"
    ],
    "name:zho_x_preferred": [
      "绿田"
    ],
    "wof:name": "Lutian",
    "wof:placetype": "locality"
  },
  "geometry": {
    "coordinates": [
      112.70799,
      26.54993
    ],
    "type": "Point"
  }
}