{
  "type": "Feature",
  "properties": {
    "gn:admin1_code": "2.0",
    "gn:asciiname": "Xumu",
    "gn:country_code": "CN",
    "gn:dem": 430,
    "gn:feature_class": "P",
    "gn:feature_code": "PPL",
    "gn:name": "Xumu",
    "gn:population": 0,
    "gn:timezone": "Asia/Shanghai",
    "iso:country": "CN",
    "name:und_x_variant": [
      "续目"
    ],
    "wof:name": "Xumu",
    "wof:placetype": "locality"
  },
  "geometry": {
    "coordinates": [
      119.66232,
      30.44119
    ],
    "type": "Point"
  }
}