{
  "type": "Feature",
  "properties": {
    "gn:admin1_code": "13.0",
    "gn:asciiname": "Korgas",
    "gn:cc2": "CN",
    "gn:country_code": "CN",
    "gn:dem": 648,
    "gn:feature_class": "P",
    "gn:feature_code": "PPL",
    "gn:name": "Korgas",
    "gn:population": 0,
    "gn:timezone": "Asia/Shanghai",
    "iso:country": "CN",
    "name:deu_x_preferred": [
      "Korgas"
    ],
    "name:fas_x_preferred": [
      "قورغاس"
    ],
    "name:fra_x_preferred": [
      "Khorgos"
    ],
    "name:jpn_x_preferred": [
      "コルガス市"
    ],
    "name:kik_x_preferred": [
      "Khorgas"
    ],
    "name:nld_x_preferred": [
      "Khorgos"
    ],
    "name:rus_x_preferred": [
      "Хоргос"
    ],
    "name:spa_x_preferred": [
      "Horgos"
    ],
    "name:tur_x_preferred": [
      "Korgas"
    ],
    "name:uig_x_preferred": [
      "K̩orƣas"
    ],
    "name:uig_x_variant": [
      "Qorghas",
      "قورغاس",
      "Қорғас",
      "قورغاس شەھىرى"
    ],
    "name:und_x_variant": [
      "Huo-ch’eng",
      "Ho-ch’eng",
      "Kung-ch’en",
      "Chorgos",
      "Huo-erh-kuo-ssu",
      "Gorgos",
      "Ho-erh-kuo-ssu",
      "Khorges",
      "Kung-ch’en-ch’eng",
      "Kurgash",
      "Hoerkwosze",
      "Ho-ch’eng-chen",
      "Ho-ch’eng-hsien"
    ],
    "name:urd_x_preferred": [
      "قورغاس"
    ],
    "name:vie_x_preferred": [
      "Khorgas"
    ],
    "name:zho_x_preferred": [
      "霍尔果斯市"
    ],
    "wof:name": "Korgas",
    "wof:placetype": "locality"
  },
  "geometry": {
    "coordinates": [
      80.41444,
      44.12556
    ],
    "type": "Point"
  }
}