{
  "type": "Feature",
  "properties": {
    "gn:admin1_code": "02",
    "gn:asciiname": "Kengkou",
    "gn:country_code": "CN",
    "gn:dem": 370,
    "gn:feature_class": "P",
    "gn:feature_code": "PPL",
    "gn:name": "Kengkou",
    "gn:population": 0,
    "gn:timezone": "Asia/Shanghai",
    "iso:country": "CN",
    "name:zho_x_preferred": [
      "坑口"
    ],
    "wof:name": "Kengkou",
    "wof:placetype": "locality"
  },
  "geometry": {
    "coordinates": [
      120.53435,
      27.44236
    ],
    "type": "Point"
  }
}