{
  "type": "Feature",
  "properties": {
    "gn:admin1_code": "16.0",
    "gn:asciiname": "Lanan",
    "gn:country_code": "CN",
    "gn:dem": 382,
    "gn:feature_class": "P",
    "gn:feature_code": "PPL",
    "gn:name": "Lanan",
    "gn:population": 0,
    "gn:timezone": "Asia/Shanghai",
    "iso:country": "CN",
    "name:zho_x_preferred": [
      "拉南"
    ],
    "wof:name": "Lanan",
    "wof:placetype": "locality"
  },
  "geometry": {
    "coordinates": [
      107.65,
      24.6999
    ],
    "type": "Point"
  }
}