{
  "type": "Feature",
  "properties": {
    "gn:admin1_code": "30.0",
    "gn:asciiname": "Lidong",
    "gn:country_code": "CN",
    "gn:dem": 223,
    "gn:feature_class": "P",
    "gn:feature_code": "PPL",
    "gn:name": "Lidong",
    "gn:population": 0,
    "gn:timezone": "Asia/Shanghai",
    "iso:country": "CN",
    "name:afr_x_preferred": [
      "Lidong"
    ],
    "name:cdo_x_preferred": [
      "Lĭk-dĕ̤ng"
    ],
    "name:hak_x_preferred": [
      "Li̍p-tûng"
    ],
    "name:swe_x_preferred": [
      "Lidong"
    ],
    "name:vie_x_preferred": [
      "Lập đông"
    ],
    "name:zha_x_preferred": [
      "Laebdoeng"
    ],
    "name:zho_x_preferred": [
      "礼洞"
    ],
    "wof:name": "Lidong",
    "wof:placetype": "locality"
  },
  "geometry": {
    "coordinates": [
      112.25438,
      23.63925
    ],
    "type": "Point"
  }
}