{
  "type": "Feature",
  "properties": {
    "gn:admin1_code": "12.0",
    "gn:asciiname": "Shangma Yatou",
    "gn:country_code": "CN",
    "gn:dem": 545,
    "gn:feature_class": "P",
    "gn:feature_code": "PPL",
    "gn:name": "Shangma Yatou",
    "gn:population": 0,
    "gn:timezone": "Asia/Shanghai",
    "iso:country": "CN",
    "name:zho_x_preferred": [
      "上麻垭头"
    ],
    "wof:name": "Shangma Yatou",
    "wof:placetype": "locality"
  },
  "geometry": {
    "coordinates": [
      110.42893,
      29.68446
    ],
    "type": "Point"
  }
}