{
  "type": "Feature",
  "properties": {
    "gn:admin1_code": "15.0",
    "gn:asciiname": "Jianzi",
    "gn:country_code": "CN",
    "gn:dem": 2587,
    "gn:feature_class": "P",
    "gn:feature_code": "PPL",
    "gn:name": "Jianzi",
    "gn:population": 0,
    "gn:timezone": "Asia/Shanghai",
    "iso:country": "CN",
    "name:ces_x_preferred": [
      "Vietnamský badminton"
    ],
    "name:deu_x_preferred": [
      "Federfußball"
    ],
    "name:fas_x_preferred": [
      "جیانزی"
    ],
    "name:fra_x_preferred": [
      "Plumfoot"
    ],
    "name:ind_x_preferred": [
      "Jiànzi"
    ],
    "name:ita_x_preferred": [
      "Shuttlecock"
    ],
    "name:jpn_x_preferred": [
      "ジェンズ"
    ],
    "name:por_x_preferred": [
      "Jianzi"
    ],
    "name:spa_x_preferred": [
      "Jian zi"
    ],
    "name:tur_x_preferred": [
      "Jianzi"
    ],
    "name:und_x_variant": [
      "尖子"
    ],
    "name:vie_x_preferred": [
      "Đá cầu"
    ],
    "wof:name": "Jianzi",
    "wof:placetype": "locality"
  },
  "geometry": {
    "coordinates": [
      104.11196,
      34.82227
    ],
    "type": "Point"
  }
}