{
  "type": "Feature",
  "properties": {
    "gn:admin1_code": "1.0",
    "gn:asciiname": "Luhecun",
    "gn:country_code": "CN",
    "gn:dem": 179,
    "gn:feature_class": "P",
    "gn:feature_code": "PPL",
    "gn:name": "Lühecun",
    "gn:population": 0,
    "gn:timezone": "Asia/Shanghai",
    "iso:country": "CN",
    "name:und_x_variant": [
      "Lühecun"
    ],
    "name:zho_x_preferred": [
      "吕河村"
    ],
    "wof:name": "Luhecun",
    "wof:placetype": "locality"
  },
  "geometry": {
    "coordinates": [
      115.8819,
      30.6521
    ],
    "type": "Point"
  }
}