{
  "type": "Feature",
  "properties": {
    "gn:admin1_code": "16.0",
    "gn:asciiname": "San",
    "gn:country_code": "CN",
    "gn:dem": 429,
    "gn:feature_class": "P",
    "gn:feature_code": "PPL",
    "gn:name": "San",
    "gn:population": 0,
    "gn:timezone": "Asia/Shanghai",
    "iso:country": "CN",
    "name:ben_x_preferred": [
      "সান"
    ],
    "name:ell_x_preferred": [
      "Σαν"
    ],
    "name:heb_x_preferred": [
      "סאן"
    ],
    "name:hin_x_preferred": [
      "सैन"
    ],
    "name:hun_x_preferred": [
      "San"
    ],
    "name:ind_x_preferred": [
      "San"
    ],
    "name:kor_x_preferred": [
      "산"
    ],
    "name:tur_x_preferred": [
      "San"
    ],
    "name:ukr_x_preferred": [
      "Сан"
    ],
    "name:urd_x_preferred": [
      "سان"
    ],
    "name:vie_x_preferred": [
      "San"
    ],
    "name:zho_x_preferred": [
      "三寸"
    ],
    "wof:name": "San",
    "wof:placetype": "locality"
  },
  "geometry": {
    "coordinates": [
      109.314,
      25.3958
    ],
    "type": "Point"
  }
}