{
  "type": "Feature",
  "properties": {
    "gn:admin1_code": "13.0",
    "gn:asciiname": "Chaiwopu",
    "gn:country_code": "CN",
    "gn:dem": 1116,
    "gn:feature_class": "P",
    "gn:feature_code": "PPL",
    "gn:name": "Chaiwopu",
    "gn:population": 0,
    "gn:timezone": "Asia/Urumqi",
    "iso:country": "CN",
    "name:und_x_variant": [
      "Ts’ai-ho-p’u",
      "Ch’ai-o-i",
      "Ts’ai-o-pao",
      "Ch’ai-o-pao",
      "Tsaiopu",
      "Tsayvopu",
      "Ch’ai-o-p’u",
      "Tsayvotu",
      "T’saiwop’u",
      "Chaiwopu"
    ],
    "name:zho_x_preferred": [
      "柴窝堡"
    ],
    "wof:name": "Chaiwopu",
    "wof:placetype": "locality"
  },
  "geometry": {
    "coordinates": [
      87.94111,
      43.53871
    ],
    "type": "Point"
  }
}