{
  "type": "Feature",
  "properties": {
    "gn:admin1_code": "8.0",
    "gn:asciiname": "Zoujiatun",
    "gn:country_code": "CN",
    "gn:dem": 240,
    "gn:feature_class": "P",
    "gn:feature_code": "PPL",
    "gn:name": "Zoujiatun",
    "gn:population": 0,
    "gn:timezone": "Asia/Shanghai",
    "iso:country": "CN",
    "name:zho_x_preferred": [
      "邹家屯"
    ],
    "wof:name": "Zoujiatun",
    "wof:placetype": "locality"
  },
  "geometry": {
    "coordinates": [
      125.73728,
      47.6488
    ],
    "type": "Point"
  }
}