{
  "type": "Feature",
  "properties": {
    "gn:admin1_code": "32.0",
    "gn:asciiname": "Changchong",
    "gn:country_code": "CN",
    "gn:dem": 341,
    "gn:feature_class": "P",
    "gn:feature_code": "PPL",
    "gn:name": "Changchong",
    "gn:population": 0,
    "gn:timezone": "Asia/Shanghai",
    "iso:country": "CN",
    "name:zho_x_preferred": [
      "长冲"
    ],
    "wof:name": "Changchong",
    "wof:placetype": "locality"
  },
  "geometry": {
    "coordinates": [
      104.06807,
      29.13056
    ],
    "type": "Point"
  }
}