{
  "type": "Feature",
  "properties": {
    "gn:admin1_code": "4.0",
    "gn:asciiname": "Wafangcun",
    "gn:country_code": "CN",
    "gn:dem": 29,
    "gn:feature_class": "P",
    "gn:feature_code": "PPL",
    "gn:name": "Wafangcun",
    "gn:population": 0,
    "gn:timezone": "Asia/Shanghai",
    "iso:country": "CN",
    "name:zho_x_preferred": [
      "瓦房村"
    ],
    "wof:name": "Wafangcun",
    "wof:placetype": "locality"
  },
  "geometry": {
    "coordinates": [
      117.9657,
      34.06592
    ],
    "type": "Point"
  }
}