{
  "type": "Feature",
  "properties": {
    "gn:admin1_code": "7",
    "gn:asciiname": "Xikou",
    "gn:country_code": "CN",
    "gn:dem": 313,
    "gn:feature_class": "P",
    "gn:feature_code": "PPLA4",
    "gn:name": "Xikou",
    "gn:population": 0,
    "gn:timezone": "Asia/Shanghai",
    "iso:country": "CN",
    "name:fas_x_preferred": [
      "شیکو"
    ],
    "name:ita_x_preferred": [
      "Xikou"
    ],
    "name:nor_x_preferred": [
      "Xikou"
    ],
    "name:swe_x_preferred": [
      "Xikou"
    ],
    "name:und_x_variant": [
      "溪口",
      "Xikou Xiang",
      "溪口乡"
    ],
    "name:zho_x_preferred": [
      "溪口镇"
    ],
    "wof:name": "Xikou",
    "wof:placetype": "locality"
  },
  "geometry": {
    "coordinates": [
      116.67504,
      25.06415
    ],
    "type": "Point"
  }
}