{
  "type": "Feature",
  "properties": {
    "gn:admin1_code": "15.0",
    "gn:asciiname": "Hongshui",
    "gn:country_code": "CN",
    "gn:dem": 2276,
    "gn:feature_class": "P",
    "gn:feature_code": "PPL",
    "gn:name": "Hongshui",
    "gn:population": 0,
    "gn:timezone": "Asia/Shanghai",
    "iso:country": "CN",
    "name:ara_x_preferred": [
      "هونغشوي"
    ],
    "name:ben_x_preferred": [
      "হংশ্যুই"
    ],
    "name:deu_x_preferred": [
      "Hongshui"
    ],
    "name:ell_x_preferred": [
      "Χονγκσούι"
    ],
    "name:fas_x_preferred": [
      "هونگشوی"
    ],
    "name:heb_x_preferred": [
      "הונגשוי"
    ],
    "name:hin_x_preferred": [
      "होंगशुई"
    ],
    "name:hun_x_preferred": [
      "Hongshui"
    ],
    "name:ind_x_preferred": [
      "Hongshui"
    ],
    "name:ita_x_preferred": [
      "Hongshui"
    ],
    "name:jpn_x_preferred": [
      "紅水河"
    ],
    "name:kor_x_preferred": [
      "홍수이"
    ],
    "name:nld_x_preferred": [
      "Hongshui"
    ],
    "name:por_x_preferred": [
      "Hongshui"
    ],
    "name:tur_x_preferred": [
      "Hongshui"
    ],
    "name:ukr_x_preferred": [
      "Хуншуйхе"
    ],
    "name:und_x_variant": [
      "红水"
    ],
    "name:urd_x_preferred": [
      "ہانگشوئی"
    ],
    "wof:name": "Hongshui",
    "wof:placetype": "locality"
  },
  "geometry": {
    "coordinates": [
      104.07332,
      34.52299
    ],
    "type": "Point"
  }
}