{
  "type": "Feature",
  "properties": {
    "gn:admin1_code": "2.0",
    "gn:asciiname": "Bantang",
    "gn:country_code": "CN",
    "gn:dem": 525,
    "gn:feature_class": "P",
    "gn:feature_code": "PPL",
    "gn:name": "Bantang",
    "gn:population": 0,
    "gn:timezone": "Asia/Shanghai",
    "iso:country": "CN",
    "name:zho_x_preferred": [
      "半塘"
    ],
    "wof:name": "Bantang",
    "wof:placetype": "locality"
  },
  "geometry": {
    "coordinates": [
      119.53996,
      28.60373
    ],
    "type": "Point"
  }
}