{
  "type": "Feature",
  "properties": {
    "gn:admin1_code": "26.0",
    "gn:asciiname": "Bangouli",
    "gn:country_code": "CN",
    "gn:dem": 1150,
    "gn:feature_class": "P",
    "gn:feature_code": "PPL",
    "gn:name": "Bangouli",
    "gn:population": 0,
    "gn:timezone": "Asia/Shanghai",
    "iso:country": "CN",
    "name:zho_x_preferred": [
      "半沟里"
    ],
    "wof:name": "Bangouli",
    "wof:placetype": "locality"
  },
  "geometry": {
    "coordinates": [
      109.67768999999998,
      33.84326
    ],
    "type": "Point"
  }
}