{
  "type": "Feature",
  "properties": {
    "gn:admin1_code": "12.0",
    "gn:asciiname": "Tangjiahe",
    "gn:country_code": "CN",
    "gn:dem": 240,
    "gn:feature_class": "P",
    "gn:feature_code": "PPL",
    "gn:name": "Tangjiahe",
    "gn:population": 0,
    "gn:timezone": "Asia/Shanghai",
    "iso:country": "CN",
    "name:zho_x_preferred": [
      "唐家河"
    ],
    "wof:name": "Tangjiahe",
    "wof:placetype": "locality"
  },
  "geometry": {
    "coordinates": [
      112.86862,
      31.46318
    ],
    "type": "Point"
  }
}