{
  "type": "Feature",
  "properties": {
    "gn:admin1_code": "7.0",
    "gn:asciiname": "Liqian",
    "gn:country_code": "CN",
    "gn:dem": 297,
    "gn:feature_class": "P",
    "gn:feature_code": "PPL",
    "gn:name": "Liqian",
    "gn:population": 0,
    "gn:timezone": "Asia/Shanghai",
    "iso:country": "CN",
    "name:cat_x_preferred": [
      "Liqian"
    ],
    "name:deu_x_preferred": [
      "Liqian"
    ],
    "name:fas_x_preferred": [
      "لیچیان"
    ],
    "name:fra_x_preferred": [
      "Liqian"
    ],
    "name:ind_x_preferred": [
      "Desa Liqian"
    ],
    "name:ita_x_preferred": [
      "Liqian"
    ],
    "name:spa_x_preferred": [
      "Li Jien"
    ],
    "name:vie_x_preferred": [
      "Ly Kiền"
    ],
    "name:zho_x_preferred": [
      "黎前"
    ],
    "name:zho_x_variant": [
      "骊靬村"
    ],
    "wof:name": "Liqian",
    "wof:placetype": "locality"
  },
  "geometry": {
    "coordinates": [
      117.82763,
      27.52632
    ],
    "type": "Point"
  }
}