{
  "type": "Feature",
  "properties": {
    "gn:admin1_code": "12.0",
    "gn:asciiname": "Yihe",
    "gn:country_code": "CN",
    "gn:dem": 101,
    "gn:feature_class": "P",
    "gn:feature_code": "PPL",
    "gn:name": "Yihe",
    "gn:population": 0,
    "gn:timezone": "Asia/Shanghai",
    "iso:country": "CN",
    "name:zho_x_preferred": [
      "义和"
    ],
    "wof:name": "Yihe",
    "wof:placetype": "locality"
  },
  "geometry": {
    "coordinates": [
      113.02809,
      30.8991
    ],
    "type": "Point"
  }
}