{
  "type": "Feature",
  "properties": {
    "gn:admin1_code": "5.0",
    "gn:asciiname": "Gong'ao",
    "gn:country_code": "CN",
    "gn:dem": 148,
    "gn:feature_class": "P",
    "gn:feature_code": "PPL",
    "gn:name": "Gong’ao",
    "gn:population": 0,
    "gn:timezone": "Asia/Shanghai",
    "iso:country": "CN",
    "name:und_x_variant": [
      "Gong’ao"
    ],
    "name:zho_x_preferred": [
      "公敖"
    ],
    "wof:name": "Gong'ao",
    "wof:placetype": "locality"
  },
  "geometry": {
    "coordinates": [
      123.18558,
      44.66982
    ],
    "type": "Point"
  }
}