{
  "type": "Feature",
  "properties": {
    "gn:admin1_code": "10.0",
    "gn:asciiname": "Zhangmazhuang",
    "gn:country_code": "CN",
    "gn:dem": 29,
    "gn:feature_class": "P",
    "gn:feature_code": "PPL",
    "gn:name": "Zhangmazhuang",
    "gn:population": 0,
    "gn:timezone": "Asia/Shanghai",
    "iso:country": "CN",
    "name:zho_x_preferred": [
      "张马庄"
    ],
    "wof:name": "Zhangmazhuang",
    "wof:placetype": "locality"
  },
  "geometry": {
    "coordinates": [
      115.338,
      38.6613
    ],
    "type": "Point"
  }
}