{
  "type": "Feature",
  "properties": {
    "gn:admin1_code": "19.0",
    "gn:asciiname": "Xizhalanyingzicun",
    "gn:country_code": "CN",
    "gn:dem": 120,
    "gn:feature_class": "P",
    "gn:feature_code": "PPL",
    "gn:name": "Xizhalanyingzicun",
    "gn:population": 0,
    "gn:timezone": "Asia/Shanghai",
    "iso:country": "CN",
    "name:zho_x_preferred": [
      "西扎兰营子村"
    ],
    "wof:name": "Xizhalanyingzicun",
    "wof:placetype": "locality"
  },
  "geometry": {
    "coordinates": [
      121.483,
      41.8992
    ],
    "type": "Point"
  }
}