{
  "type": "Feature",
  "properties": {
    "gn:admin1_code": "11.0",
    "gn:asciiname": "Guanyindong",
    "gn:country_code": "CN",
    "gn:dem": 363,
    "gn:feature_class": "P",
    "gn:feature_code": "PPL",
    "gn:name": "Guanyindong",
    "gn:population": 0,
    "gn:timezone": "Asia/Shanghai",
    "iso:country": "CN",
    "name:deu_x_preferred": [
      "Guanyindong"
    ],
    "name:zho_x_preferred": [
      "Guanyindong"
    ],
    "name:zho_x_variant": [
      "观音洞"
    ],
    "wof:name": "Guanyindong",
    "wof:placetype": "locality"
  },
  "geometry": {
    "coordinates": [
      111.14108,
      29.12663
    ],
    "type": "Point"
  }
}