{
  "type": "Feature",
  "properties": {
    "gn:admin1_code": "30",
    "gn:asciiname": "Huozhucun",
    "gn:country_code": "CN",
    "gn:dem": 118,
    "gn:feature_class": "P",
    "gn:feature_code": "PPL",
    "gn:name": "Huozhucun",
    "gn:population": 0,
    "gn:timezone": "Asia/Urumqi",
    "iso:country": "CN",
    "name:zho_x_preferred": [
      "活竹村"
    ],
    "wof:name": "Huozhucun",
    "wof:placetype": "locality"
  },
  "geometry": {
    "coordinates": [
      111.20491,
      21.60995
    ],
    "type": "Point"
  }
}