{
  "type": "Feature",
  "properties": {
    "gn:admin1_code": "15.0",
    "gn:asciiname": "Haolin",
    "gn:country_code": "CN",
    "gn:dem": 1114,
    "gn:feature_class": "P",
    "gn:feature_code": "PPLA4",
    "gn:name": "Haolin",
    "gn:population": 0,
    "gn:timezone": "Asia/Shanghai",
    "iso:country": "CN",
    "name:und_x_variant": [
      "蒿林"
    ],
    "wof:name": "Haolin",
    "wof:placetype": "locality"
  },
  "geometry": {
    "coordinates": [
      105.21345,
      33.76791
    ],
    "type": "Point"
  }
}