{
  "type": "Feature",
  "properties": {
    "gn:admin1_code": "8.0",
    "gn:asciiname": "Fuhecun",
    "gn:country_code": "CN",
    "gn:dem": 59,
    "gn:feature_class": "P",
    "gn:feature_code": "PPL",
    "gn:name": "Fuhecun",
    "gn:population": 0,
    "gn:timezone": "Asia/Shanghai",
    "iso:country": "CN",
    "name:zho_x_preferred": [
      "福合村"
    ],
    "wof:name": "Fuhecun",
    "wof:placetype": "locality"
  },
  "geometry": {
    "coordinates": [
      131.82513,
      47.41803
    ],
    "type": "Point"
  }
}