{
  "type": "Feature",
  "properties": {
    "gn:admin1_code": "16.0",
    "gn:asciiname": "Nanxiong",
    "gn:country_code": "CN",
    "gn:dem": 1060,
    "gn:feature_class": "P",
    "gn:feature_code": "PPL",
    "gn:name": "Nanxiong",
    "gn:population": 0,
    "gn:timezone": "Asia/Shanghai",
    "iso:country": "CN",
    "name:ara_x_preferred": [
      "نانشيانغ"
    ],
    "name:ces_x_preferred": [
      "Nan-siung"
    ],
    "name:deu_x_preferred": [
      "Nanxiong"
    ],
    "name:fas_x_preferred": [
      "نانشیانگ"
    ],
    "name:fra_x_preferred": [
      "Nanxiong"
    ],
    "name:hak_x_preferred": [
      "Nàm-hiùng-sṳ"
    ],
    "name:ita_x_preferred": [
      "Nanxiong"
    ],
    "name:jpn_x_preferred": [
      "南雄市"
    ],
    "name:kik_x_preferred": [
      "Nanxiong"
    ],
    "name:kor_x_preferred": [
      "난슝시"
    ],
    "name:mwl_x_preferred": [
      "Nanxiong"
    ],
    "name:nld_x_preferred": [
      "Nanxiong"
    ],
    "name:nor_x_preferred": [
      "Nanxiong"
    ],
    "name:pam_x_preferred": [
      "Nanxiong"
    ],
    "name:pnb_x_preferred": [
      "نانسی اونگ"
    ],
    "name:swe_x_preferred": [
      "Nanxiong"
    ],
    "name:urd_x_preferred": [
      "نانشیونگ"
    ],
    "name:vie_x_preferred": [
      "Nam Hùng"
    ],
    "name:zho_x_preferred": [
      "南熊"
    ],
    "name:zho_x_variant": [
      "南雄市"
    ],
    "wof:name": "Nanxiong",
    "wof:placetype": "locality"
  },
  "geometry": {
    "coordinates": [
      105.945,
      24.5285
    ],
    "type": "Point"
  }
}