{
  "type": "Feature",
  "properties": {
    "gn:admin1_code": "8.0",
    "gn:asciiname": "Lidafang",
    "gn:country_code": "CN",
    "gn:dem": 189,
    "gn:feature_class": "P",
    "gn:feature_code": "PPL",
    "gn:name": "Lidafang",
    "gn:population": 0,
    "gn:timezone": "Asia/Shanghai",
    "iso:country": "CN",
    "name:zho_x_preferred": [
      "李大房"
    ],
    "wof:name": "Lidafang",
    "wof:placetype": "locality"
  },
  "geometry": {
    "coordinates": [
      127.5049,
      46.81895
    ],
    "type": "Point"
  }
}