{
  "type": "Feature",
  "properties": {
    "gn:admin1_code": "10",
    "gn:asciiname": "Ligoumen",
    "gn:country_code": "CN",
    "gn:dem": 866,
    "gn:feature_class": "P",
    "gn:feature_code": "PPL",
    "gn:name": "Ligoumen",
    "gn:population": 0,
    "gn:timezone": "Asia/Shanghai",
    "iso:country": "CN",
    "name:zho_x_preferred": [
      "里沟门"
    ],
    "wof:name": "Ligoumen",
    "wof:placetype": "locality"
  },
  "geometry": {
    "coordinates": [
      117.01137,
      41.68571
    ],
    "type": "Point"
  }
}