{
  "type": "Feature",
  "properties": {
    "gn:admin1_code": "18.0",
    "gn:asciiname": "Zhongyuan",
    "gn:country_code": "CN",
    "gn:dem": 1231,
    "gn:feature_class": "P",
    "gn:feature_code": "PPL",
    "gn:name": "Zhongyuan",
    "gn:population": 0,
    "gn:timezone": "Asia/Shanghai",
    "iso:country": "CN",
    "name:bul_x_preferred": [
      "Джунюен"
    ],
    "name:deu_x_preferred": [
      "Zentralchinesische Ebene"
    ],
    "name:fas_x_preferred": [
      "ژانگیوان"
    ],
    "name:fra_x_preferred": [
      "Plaine centrale"
    ],
    "name:ind_x_preferred": [
      "Zhongyuan"
    ],
    "name:ita_x_preferred": [
      "Zhongyuan"
    ],
    "name:kor_x_preferred": [
      "중원"
    ],
    "name:lit_x_preferred": [
      "Vidurio lyguma"
    ],
    "name:nld_x_preferred": [
      "Zhongyuan"
    ],
    "name:spa_x_preferred": [
      "Llanura Central"
    ],
    "name:ukr_x_preferred": [
      "Центральна рівнина"
    ],
    "name:vie_x_preferred": [
      "Trung Nguyên"
    ],
    "name:wuu_x_preferred": [
      "中原地区"
    ],
    "name:zho_x_preferred": [
      "中院"
    ],
    "wof:name": "Zhongyuan",
    "wof:placetype": "locality"
  },
  "geometry": {
    "coordinates": [
      107.038,
      26.8086
    ],
    "type": "Point"
  }
}