{
  "type": "Feature",
  "properties": {
    "gn:admin1_code": "10",
    "gn:asciiname": "Goumen",
    "gn:country_code": "CN",
    "gn:dem": 946,
    "gn:feature_class": "P",
    "gn:feature_code": "PPL",
    "gn:name": "Goumen",
    "gn:population": 0,
    "gn:timezone": "Asia/Shanghai",
    "iso:country": "CN",
    "name:zho_x_preferred": [
      "沟门"
    ],
    "wof:name": "Goumen",
    "wof:placetype": "locality"
  },
  "geometry": {
    "coordinates": [
      116.97422,
      41.53245
    ],
    "type": "Point"
  }
}