{
  "type": "Feature",
  "properties": {
    "gn:admin1_code": "26.0",
    "gn:asciiname": "Shangzhujia Shancun",
    "gn:country_code": "CN",
    "gn:dem": 966,
    "gn:feature_class": "P",
    "gn:feature_code": "PPL",
    "gn:name": "Shangzhujia Shancun",
    "gn:population": 0,
    "gn:timezone": "Asia/Shanghai",
    "iso:country": "CN",
    "name:zho_x_preferred": [
      "上朱家山村"
    ],
    "wof:name": "Shangzhujia Shancun",
    "wof:placetype": "locality"
  },
  "geometry": {
    "coordinates": [
      110.55,
      37.2352
    ],
    "type": "Point"
  }
}