{
  "type": "Feature",
  "properties": {
    "gn:admin1_code": "02",
    "gn:asciiname": "Zhanghancun",
    "gn:country_code": "CN",
    "gn:dem": 58,
    "gn:feature_class": "P",
    "gn:feature_code": "PPL",
    "gn:name": "Zhanghancun",
    "gn:population": 0,
    "gn:timezone": "Asia/Shanghai",
    "iso:country": "CN",
    "name:und_x_variant": [
      "Chang-han-ts’un",
      "Zhanghan",
      "Zhanghancun"
    ],
    "name:zho_x_preferred": [
      "张韩"
    ],
    "name:zho_x_variant": [
      "张韩村"
    ],
    "wof:name": "Zhanghancun",
    "wof:placetype": "locality"
  },
  "geometry": {
    "coordinates": [
      121.69411,
      29.37812000000001
    ],
    "type": "Point"
  }
}