{
  "type": "Feature",
  "properties": {
    "gn:admin1_code": "1.0",
    "gn:asciiname": "Shanghetan",
    "gn:country_code": "CN",
    "gn:dem": 79,
    "gn:feature_class": "P",
    "gn:feature_code": "PPL",
    "gn:name": "Shanghetan",
    "gn:population": 0,
    "gn:timezone": "Asia/Shanghai",
    "iso:country": "CN",
    "name:zho_x_preferred": [
      "尚河滩"
    ],
    "wof:name": "Shanghetan",
    "wof:placetype": "locality"
  },
  "geometry": {
    "coordinates": [
      116.9809,
      29.75378
    ],
    "type": "Point"
  }
}