{
  "type": "Feature",
  "properties": {
    "gn:admin1_code": "16.0",
    "gn:asciiname": "Yixing",
    "gn:country_code": "CN",
    "gn:dem": 695,
    "gn:feature_class": "P",
    "gn:feature_code": "PPL",
    "gn:name": "Yixing",
    "gn:population": 0,
    "gn:timezone": "Asia/Shanghai",
    "iso:country": "CN",
    "name:bel_x_preferred": [
      "Ісін"
    ],
    "name:deu_x_preferred": [
      "Yixing"
    ],
    "name:fra_x_preferred": [
      "Yixing"
    ],
    "name:ita_x_preferred": [
      "Yixing"
    ],
    "name:jpn_x_preferred": [
      "宜興市"
    ],
    "name:kik_x_preferred": [
      "Yixing"
    ],
    "name:kor_x_preferred": [
      "이싱시"
    ],
    "name:nld_x_preferred": [
      "Yixing"
    ],
    "name:nno_x_preferred": [
      "Yixing"
    ],
    "name:nor_x_preferred": [
      "Yixing"
    ],
    "name:por_x_preferred": [
      "Yixing"
    ],
    "name:rus_x_preferred": [
      "Исин"
    ],
    "name:swe_x_preferred": [
      "Yixing"
    ],
    "name:tgl_x_preferred": [
      "Yixing"
    ],
    "name:tur_x_preferred": [
      "Yixing"
    ],
    "name:ukr_x_preferred": [
      "Ісин"
    ],
    "name:urd_x_preferred": [
      "ییشینگ"
    ],
    "name:vie_x_preferred": [
      "Nghi Hưng"
    ],
    "name:war_x_preferred": [
      "Yixing"
    ],
    "name:wuu_x_preferred": [
      "宜兴市"
    ],
    "name:zho_x_preferred": [
      "义兴"
    ],
    "name:zho_x_variant": [
      "宜兴市"
    ],
    "wof:name": "Yixing",
    "wof:placetype": "locality"
  },
  "geometry": {
    "coordinates": [
      106.584,
      23.1604
    ],
    "type": "Point"
  }
}