{
  "type": "Feature",
  "properties": {
    "gn:admin1_code": "32.0",
    "gn:asciiname": "Liujiao",
    "gn:country_code": "CN",
    "gn:dem": 361,
    "gn:feature_class": "P",
    "gn:feature_code": "PPL",
    "gn:name": "Liujiao",
    "gn:population": 0,
    "gn:timezone": "Asia/Shanghai",
    "iso:country": "CN",
    "name:hak_x_preferred": [
      "Liuk-kiok-hiông"
    ],
    "name:jpn_x_preferred": [
      "六脚郷"
    ],
    "name:kor_x_preferred": [
      "류자오향"
    ],
    "name:pol_x_preferred": [
      "Liujiao"
    ],
    "name:vie_x_preferred": [
      "Lục Cước"
    ],
    "name:zho_x_preferred": [
      "六角"
    ],
    "name:zho_x_variant": [
      "六腳鄉"
    ],
    "wof:name": "Liujiao",
    "wof:placetype": "locality"
  },
  "geometry": {
    "coordinates": [
      105.415,
      30.0056
    ],
    "type": "Point"
  }
}