{
  "type": "Feature",
  "properties": {
    "gn:admin1_code": "9.0",
    "gn:asciiname": "Jixi",
    "gn:country_code": "CN",
    "gn:dem": 120,
    "gn:feature_class": "P",
    "gn:feature_code": "PPL",
    "gn:name": "Jixi",
    "gn:population": 0,
    "gn:timezone": "Asia/Shanghai",
    "iso:country": "CN",
    "name:ara_x_preferred": [
      "جيشى"
    ],
    "name:cdo_x_preferred": [
      "Giĕ-să̤"
    ],
    "name:ceb_x_preferred": [
      "Jixi"
    ],
    "name:ces_x_preferred": [
      "Ťi-si"
    ],
    "name:dan_x_preferred": [
      "Jixi"
    ],
    "name:deu_x_preferred": [
      "Jixi"
    ],
    "name:eus_x_preferred": [
      "Jixi"
    ],
    "name:fas_x_preferred": [
      "جیشی"
    ],
    "name:fin_x_preferred": [
      "Jixi"
    ],
    "name:fra_x_preferred": [
      "Jixi"
    ],
    "name:ind_x_preferred": [
      "Jixi"
    ],
    "name:ita_x_preferred": [
      "Jixi"
    ],
    "name:jpn_x_preferred": [
      "鶏西"
    ],
    "name:jpn_x_variant": [
      "鶏西市"
    ],
    "name:kik_x_preferred": [
      "Jixi"
    ],
    "name:kor_x_preferred": [
      "지시시"
    ],
    "name:lit_x_preferred": [
      "Dzisi"
    ],
    "name:mlg_x_preferred": [
      "Jixi"
    ],
    "name:nld_x_preferred": [
      "Jixi"
    ],
    "name:nno_x_preferred": [
      "Jixi"
    ],
    "name:nor_x_preferred": [
      "Jixi"
    ],
    "name:pam_x_preferred": [
      "Jixi"
    ],
    "name:pol_x_preferred": [
      "Jixi"
    ],
    "name:por_x_preferred": [
      "Jixi"
    ],
    "name:rus_x_preferred": [
      "Цзиси"
    ],
    "name:spa_x_preferred": [
      "Jixi"
    ],
    "name:srp_x_preferred": [
      "Ђиси"
    ],
    "name:swe_x_preferred": [
      "Jixi"
    ],
    "name:tgl_x_preferred": [
      "Jixi"
    ],
    "name:tur_x_preferred": [
      "Jixi"
    ],
    "name:urd_x_preferred": [
      "جیشی"
    ],
    "name:vie_x_preferred": [
      "Kê Tây"
    ],
    "name:war_x_preferred": [
      "Jixi"
    ],
    "name:wuu_x_preferred": [
      "鸡西市"
    ],
    "name:zho_x_preferred": [
      "际西"
    ],
    "name:zho_x_variant": [
      "鸡西市"
    ],
    "wof:name": "Jixi",
    "wof:placetype": "locality"
  },
  "geometry": {
    "coordinates": [
      112.96737,
      35.11399
    ],
    "type": "Point"
  }
}