{
  "type": "Feature",
  "properties": {
    "gn:admin1_code": "14.0",
    "gn:asciiname": "Zhomda",
    "gn:country_code": "CN",
    "gn:dem": 3161,
    "gn:feature_class": "P",
    "gn:feature_code": "PPLA4",
    "gn:name": "Zhomda",
    "gn:population": 0,
    "gn:timezone": "Asia/Urumqi",
    "iso:country": "CN",
    "name:bod_x_preferred": [
      "Zhomda"
    ],
    "name:und_x_variant": [
      "Zhongda Xiang"
    ],
    "name:zho_x_preferred": [
      "Zhongda"
    ],
    "name:zho_x_variant": [
      "仲达",
      "Gurulangjie Qu",
      "古如朗杰区",
      "仲达乡"
    ],
    "wof:name": "Zhomda",
    "wof:placetype": "locality"
  },
  "geometry": {
    "coordinates": [
      92.83146,
      29.06999
    ],
    "type": "Point"
  }
}