{
  "type": "Feature",
  "properties": {
    "gn:admin1_code": "16",
    "gn:asciiname": "Tongshan",
    "gn:country_code": "CN",
    "gn:dem": 185,
    "gn:feature_class": "P",
    "gn:feature_code": "PPL",
    "gn:name": "Tongshan",
    "gn:population": 0,
    "gn:timezone": "Asia/Shanghai",
    "iso:country": "CN",
    "name:ceb_x_preferred": [
      "Tongshan"
    ],
    "name:deu_x_preferred": [
      "Tongshan"
    ],
    "name:fra_x_preferred": [
      "Tongshan"
    ],
    "name:mlg_x_preferred": [
      "Tongshan"
    ],
    "name:nor_x_preferred": [
      "Tongshan"
    ],
    "name:rus_x_preferred": [
      "Туншань"
    ],
    "name:swe_x_preferred": [
      "Tongshan"
    ],
    "name:zho_x_preferred": [
      "桐山"
    ],
    "wof:name": "Tongshan",
    "wof:placetype": "locality"
  },
  "geometry": {
    "coordinates": [
      110.079,
      24.9613
    ],
    "type": "Point"
  }
}