{
  "type": "Feature",
  "properties": {
    "gn:admin1_code": "26.0",
    "gn:asciiname": "Dianshi",
    "gn:country_code": "CN",
    "gn:dem": 1246,
    "gn:feature_class": "P",
    "gn:feature_code": "PPL",
    "gn:name": "Dianshi",
    "gn:population": 0,
    "gn:timezone": "Asia/Shanghai",
    "iso:country": "CN",
    "name:zho_x_preferred": [
      "点石"
    ],
    "wof:name": "Dianshi",
    "wof:placetype": "locality"
  },
  "geometry": {
    "coordinates": [
      109.13767,
      38.41704
    ],
    "type": "Point"
  }
}