{
  "type": "Feature",
  "properties": {
    "gn:admin1_code": "3.0",
    "gn:asciiname": "Gejiaping",
    "gn:country_code": "CN",
    "gn:dem": 271,
    "gn:feature_class": "P",
    "gn:feature_code": "PPL",
    "gn:name": "Gejiaping",
    "gn:population": 0,
    "gn:timezone": "Asia/Shanghai",
    "iso:country": "CN",
    "name:und_x_variant": [
      "Wojiaping"
    ],
    "name:zho_x_preferred": [
      "葛家坪"
    ],
    "name:zho_x_variant": [
      "窝家坪"
    ],
    "wof:name": "Gejiaping",
    "wof:placetype": "locality"
  },
  "geometry": {
    "coordinates": [
      117.021,
      27.6694
    ],
    "type": "Point"
  }
}