{
  "type": "Feature",
  "properties": {
    "gn:admin1_code": "29.0",
    "gn:asciiname": "Majia",
    "gn:country_code": "CN",
    "gn:dem": 1498,
    "gn:feature_class": "P",
    "gn:feature_code": "PPL",
    "gn:name": "Majia",
    "gn:population": 0,
    "gn:timezone": "Asia/Shanghai",
    "iso:country": "CN",
    "name:zho_x_preferred": [
      "马家"
    ],
    "wof:name": "Majia",
    "wof:placetype": "locality"
  },
  "geometry": {
    "coordinates": [
      98.6685,
      24.9547
    ],
    "type": "Point"
  }
}