{
  "type": "Feature",
  "properties": {
    "gn:admin1_code": "26.0",
    "gn:asciiname": "Xiong'ergou",
    "gn:country_code": "CN",
    "gn:dem": 1388,
    "gn:feature_class": "P",
    "gn:feature_code": "PPL",
    "gn:name": "Xiong’ergou",
    "gn:population": 0,
    "gn:timezone": "Asia/Shanghai",
    "iso:country": "CN",
    "name:und_x_variant": [
      "Xiong’ergou"
    ],
    "name:zho_x_preferred": [
      "熊耳沟"
    ],
    "wof:name": "Xiong'ergou",
    "wof:placetype": "locality"
  },
  "geometry": {
    "coordinates": [
      110.05997,
      34.28249
    ],
    "type": "Point"
  }
}