{
  "type": "Feature",
  "properties": {
    "gn:admin1_code": "32.0",
    "gn:asciiname": "Shatuo",
    "gn:country_code": "CN",
    "gn:dem": 3320,
    "gn:feature_class": "P",
    "gn:feature_code": "PPL",
    "gn:name": "Shatuo",
    "gn:population": 0,
    "gn:timezone": "Asia/Urumqi",
    "iso:country": "CN",
    "name:aze_x_preferred": [
      "Şatolar"
    ],
    "name:bul_x_preferred": [
      "Шатуо"
    ],
    "name:deu_x_preferred": [
      "Shatuo"
    ],
    "name:fra_x_preferred": [
      "Shatuo"
    ],
    "name:hrv_x_preferred": [
      "Shatuo"
    ],
    "name:ita_x_preferred": [
      "Shatuo"
    ],
    "name:jpn_x_preferred": [
      "沙陀族"
    ],
    "name:rus_x_preferred": [
      "Тюрки-шато"
    ],
    "name:tur_x_preferred": [
      "Şatuo"
    ],
    "name:ukr_x_preferred": [
      "Шато"
    ],
    "name:vie_x_preferred": [
      "Sa Đà"
    ],
    "name:zho_x_preferred": [
      "沙拖"
    ],
    "wof:name": "Shatuo",
    "wof:placetype": "locality"
  },
  "geometry": {
    "coordinates": [
      98.8941,
      30.812
    ],
    "type": "Point"
  }
}