{
  "type": "Feature",
  "properties": {
    "gn:admin1_code": "13.0",
    "gn:asciiname": "Taxmilik",
    "gn:cc2": "CN",
    "gn:country_code": "CN",
    "gn:dem": 1554,
    "gn:feature_class": "P",
    "gn:feature_code": "PPL",
    "gn:name": "Taxmilik",
    "gn:population": 0,
    "gn:timezone": "Asia/Shanghai",
    "iso:country": "CN",
    "name:uig_x_preferred": [
      "Taxmilik̩"
    ],
    "name:uig_x_variant": [
      "Tashmiliq",
      "تاشمىلىق",
      "Ташмилық"
    ],
    "name:und_x_variant": [
      "T’a-shih-ma-li-k’o",
      "Taxmilik"
    ],
    "wof:name": "Taxmilik",
    "wof:placetype": "locality"
  },
  "geometry": {
    "coordinates": [
      75.63944000000002,
      39.10167
    ],
    "type": "Point"
  }
}