{
  "type": "Feature",
  "properties": {
    "gn:admin1_code": "4.0",
    "gn:asciiname": "Hangjiapu",
    "gn:country_code": "CN",
    "gn:dem": 5,
    "gn:feature_class": "P",
    "gn:feature_code": "PPL",
    "gn:name": "Hangjiapu",
    "gn:population": 0,
    "gn:timezone": "Asia/Shanghai",
    "iso:country": "CN",
    "name:und_x_variant": [
      "杭家铺"
    ],
    "wof:name": "Hangjiapu",
    "wof:placetype": "locality"
  },
  "geometry": {
    "coordinates": [
      120.20055,
      32.50861
    ],
    "type": "Point"
  }
}