{
  "type": "Feature",
  "properties": {
    "gn:admin1_code": "30",
    "gn:asciiname": "Zhutian",
    "gn:country_code": "CN",
    "gn:dem": 130,
    "gn:feature_class": "P",
    "gn:feature_code": "PPLA4",
    "gn:name": "Zhutian",
    "gn:population": 0,
    "gn:timezone": "Asia/Shanghai",
    "iso:country": "CN",
    "name:hak_x_preferred": [
      "Tsuk-thièn-hiông"
    ],
    "name:jpn_x_preferred": [
      "竹田郷"
    ],
    "name:kor_x_preferred": [
      "주톈향"
    ],
    "name:und_x_variant": [
      "Zhutian Zhen",
      "主田镇"
    ],
    "name:vie_x_preferred": [
      "Trúc Điền"
    ],
    "name:zho_x_preferred": [
      "主田"
    ],
    "name:zho_x_variant": [
      "竹田鄉"
    ],
    "wof:name": "Zhutian",
    "wof:placetype": "locality"
  },
  "geometry": {
    "coordinates": [
      114.29583,
      25.06528
    ],
    "type": "Point"
  }
}