{
  "type": "Feature",
  "properties": {
    "gn:admin1_code": "15.0",
    "gn:asciiname": "Xiaowan",
    "gn:country_code": "CN",
    "gn:dem": 2035,
    "gn:feature_class": "P",
    "gn:feature_code": "PPL",
    "gn:name": "Xiaowan",
    "gn:population": 0,
    "gn:timezone": "Asia/Shanghai",
    "iso:country": "CN",
    "name:zho_x_preferred": [
      "小湾"
    ],
    "wof:name": "Xiaowan",
    "wof:placetype": "locality"
  },
  "geometry": {
    "coordinates": [
      104.734,
      35.3266
    ],
    "type": "Point"
  }
}