{
  "type": "Feature",
  "properties": {
    "gn:admin1_code": "7.0",
    "gn:asciiname": "Qinyang",
    "gn:country_code": "CN",
    "gn:dem": 492,
    "gn:feature_class": "P",
    "gn:feature_code": "PPL",
    "gn:name": "Qinyang",
    "gn:population": 0,
    "gn:timezone": "Asia/Shanghai",
    "iso:country": "CN",
    "name:cym_x_preferred": [
      "Qinyang"
    ],
    "name:deu_x_preferred": [
      "Qinyang"
    ],
    "name:fra_x_preferred": [
      "Qinyang"
    ],
    "name:ita_x_preferred": [
      "Qinyang"
    ],
    "name:jpn_x_preferred": [
      "沁陽市"
    ],
    "name:kik_x_preferred": [
      "Qinyang"
    ],
    "name:kor_x_preferred": [
      "친양시"
    ],
    "name:mlg_x_preferred": [
      "Qinyang"
    ],
    "name:mwl_x_preferred": [
      "Qinyang"
    ],
    "name:nld_x_preferred": [
      "Qinyang"
    ],
    "name:nor_x_preferred": [
      "Qinyang"
    ],
    "name:pam_x_preferred": [
      "Qinyang"
    ],
    "name:rus_x_preferred": [
      "Циньян"
    ],
    "name:swe_x_preferred": [
      "Qinyang"
    ],
    "name:vie_x_preferred": [
      "Thấm Dương"
    ],
    "name:war_x_preferred": [
      "Qinyang"
    ],
    "name:zho_x_preferred": [
      "芹洋"
    ],
    "name:zho_x_variant": [
      "沁阳市"
    ],
    "wof:name": "Qinyang",
    "wof:placetype": "locality"
  },
  "geometry": {
    "coordinates": [
      118.06779,
      26.00707
    ],
    "type": "Point"
  }
}