{
  "type": "Feature",
  "properties": {
    "gn:admin1_code": "26.0",
    "gn:asciiname": "Zhenziwancun",
    "gn:country_code": "CN",
    "gn:dem": 918,
    "gn:feature_class": "P",
    "gn:feature_code": "PPL",
    "gn:name": "Zhenziwancun",
    "gn:population": 0,
    "gn:timezone": "Asia/Shanghai",
    "iso:country": "CN",
    "name:zho_x_preferred": [
      "镇子湾村"
    ],
    "wof:name": "Zhenziwancun",
    "wof:placetype": "locality"
  },
  "geometry": {
    "coordinates": [
      110.12457,
      37.81038
    ],
    "type": "Point"
  }
}