{
  "type": "Feature",
  "properties": {
    "gn:admin1_code": "7",
    "gn:asciiname": "Zhongliao",
    "gn:country_code": "CN",
    "gn:dem": 721,
    "gn:feature_class": "P",
    "gn:feature_code": "PPL",
    "gn:name": "Zhongliao",
    "gn:population": 0,
    "gn:timezone": "Asia/Shanghai",
    "iso:country": "CN",
    "name:deu_x_preferred": [
      "Zhongliao"
    ],
    "name:hak_x_preferred": [
      "Chûng-liàu-hiông"
    ],
    "name:jpn_x_preferred": [
      "中寮郷"
    ],
    "name:kor_x_preferred": [
      "중랴오향"
    ],
    "name:pol_x_preferred": [
      "Zhongliao"
    ],
    "name:vie_x_preferred": [
      "Trung Liêu"
    ],
    "name:zho_x_preferred": [
      "中寮"
    ],
    "name:zho_x_variant": [
      "中寮鄉"
    ],
    "wof:name": "Zhongliao",
    "wof:placetype": "locality"
  },
  "geometry": {
    "coordinates": [
      117.22595,
      24.78055
    ],
    "type": "Point"
  }
}