{
  "type": "Feature",
  "properties": {
    "gn:admin1_code": "24",
    "gn:asciiname": "Shantou",
    "gn:country_code": "CN",
    "gn:dem": 840,
    "gn:feature_class": "P",
    "gn:feature_code": "PPL",
    "gn:name": "Shantou",
    "gn:population": 0,
    "gn:timezone": "Asia/Shanghai",
    "iso:country": "CN",
    "name:afr_x_preferred": [
      "Shantou"
    ],
    "name:ara_x_preferred": [
      "شانتو"
    ],
    "name:ast_x_preferred": [
      "Shantou"
    ],
    "name:bre_x_preferred": [
      "Shantou"
    ],
    "name:bul_x_preferred": [
      "Шантоу"
    ],
    "name:cat_x_preferred": [
      "Shantou"
    ],
    "name:cdo_x_preferred": [
      "Sáng-tàu"
    ],
    "name:ces_x_preferred": [
      "Šan-tchou"
    ],
    "name:cym_x_preferred": [
      "Shantou"
    ],
    "name:dan_x_preferred": [
      "Shantou"
    ],
    "name:deu_x_preferred": [
      "Shantou"
    ],
    "name:ell_x_preferred": [
      "Σαντόου"
    ],
    "name:epo_x_preferred": [
      "Ŝantoŭo"
    ],
    "name:est_x_preferred": [
      "Shantou Shi"
    ],
    "name:eus_x_preferred": [
      "Shantou"
    ],
    "name:fas_x_preferred": [
      "شانتو"
    ],
    "name:fin_x_preferred": [
      "Shantou"
    ],
    "name:fra_x_preferred": [
      "Shantou"
    ],
    "name:glg_x_preferred": [
      "Shantou"
    ],
    "name:hak_x_preferred": [
      "Sân-thèu-sṳ"
    ],
    "name:heb_x_preferred": [
      "שאנטואו"
    ],
    "name:hun_x_preferred": [
      "Santou"
    ],
    "name:ind_x_preferred": [
      "Shantou"
    ],
    "name:ita_x_preferred": [
      "Shantou"
    ],
    "name:jpn_x_preferred": [
      "汕頭市"
    ],
    "name:kik_x_preferred": [
      "Shantou"
    ],
    "name:kor_x_preferred": [
      "산터우시"
    ],
    "name:lit_x_preferred": [
      "Šantou"
    ],
    "name:mlg_x_preferred": [
      "Shantou"
    ],
    "name:nld_x_preferred": [
      "Shantou"
    ],
    "name:nno_x_preferred": [
      "Shantou"
    ],
    "name:nor_x_preferred": [
      "Shantou"
    ],
    "name:pam_x_preferred": [
      "Shantou"
    ],
    "name:pnb_x_preferred": [
      "شانتوؤ"
    ],
    "name:pol_x_preferred": [
      "Shantou"
    ],
    "name:por_x_preferred": [
      "Shantou"
    ],
    "name:rus_x_preferred": [
      "Шаньтоу"
    ],
    "name:sco_x_preferred": [
      "Shantou"
    ],
    "name:spa_x_preferred": [
      "Shantou"
    ],
    "name:srp_x_preferred": [
      "Шантоу"
    ],
    "name:swa_x_preferred": [
      "Shantou"
    ],
    "name:swe_x_preferred": [
      "Shantou"
    ],
    "name:tgl_x_preferred": [
      "Shantou"
    ],
    "name:tha_x_preferred": [
      "ซัวเถา"
    ],
    "name:tur_x_preferred": [
      "Shantou"
    ],
    "name:uig_x_preferred": [
      "شەنتۇ شەھىرى"
    ],
    "name:ukr_x_preferred": [
      "Шаньтоу"
    ],
    "name:urd_x_preferred": [
      "شانتو"
    ],
    "name:vie_x_preferred": [
      "Sán Đầu"
    ],
    "name:war_x_preferred": [
      "Shantou"
    ],
    "name:zho_x_preferred": [
      "汕头市"
    ],
    "wof:name": "Shantou",
    "wof:placetype": "locality"
  },
  "geometry": {
    "coordinates": [
      110.71667,
      37.23333
    ],
    "type": "Point"
  }
}