{
  "type": "Feature",
  "properties": {
    "gn:admin1_code": "1.0",
    "gn:asciiname": "Yangxi",
    "gn:country_code": "CN",
    "gn:dem": 240,
    "gn:feature_class": "P",
    "gn:feature_code": "PPLA4",
    "gn:name": "Yangxi",
    "gn:population": 0,
    "gn:timezone": "Asia/Shanghai",
    "iso:country": "CN",
    "name:ceb_x_preferred": [
      "Yangxi"
    ],
    "name:deu_x_preferred": [
      "Yangxi"
    ],
    "name:und_x_variant": [
      "Yang-ch’i",
      "Yang-hsi",
      "Yang-ch’i-chen",
      "杨溪",
      "Yangxi Zhen",
      "杨溪镇"
    ],
    "name:zho_x_preferred": [
      "洋溪镇"
    ],
    "wof:name": "Yangxi",
    "wof:placetype": "locality"
  },
  "geometry": {
    "coordinates": [
      118.6421,
      30.15667
    ],
    "type": "Point"
  }
}