{
  "type": "Feature",
  "properties": {
    "gn:admin1_code": "02",
    "gn:asciiname": "Li'aocun",
    "gn:country_code": "CN",
    "gn:dem": 704,
    "gn:feature_class": "P",
    "gn:feature_code": "PPL",
    "gn:name": "Li’aocun",
    "gn:population": 0,
    "gn:timezone": "Asia/Shanghai",
    "iso:country": "CN",
    "name:und_x_variant": [
      "Li’ao",
      "Li’aocun"
    ],
    "name:zho_x_preferred": [
      "里岙"
    ],
    "name:zho_x_variant": [
      "里岙村"
    ],
    "wof:name": "Li'aocun",
    "wof:placetype": "locality"
  },
  "geometry": {
    "coordinates": [
      120.92776,
      28.71358
    ],
    "type": "Point"
  }
}