{
  "type": "Feature",
  "properties": {
    "gn:admin1_code": "3.0",
    "gn:asciiname": "Meizhou",
    "gn:country_code": "CN",
    "gn:dem": 139,
    "gn:feature_class": "P",
    "gn:feature_code": "PPL",
    "gn:name": "Meizhou",
    "gn:population": 0,
    "gn:timezone": "Asia/Shanghai",
    "iso:country": "CN",
    "name:ara_x_preferred": [
      "ماوزو"
    ],
    "name:cdo_x_preferred": [
      "Mùi-ciŭ"
    ],
    "name:ceb_x_preferred": [
      "Meizhou"
    ],
    "name:ces_x_preferred": [
      "Mej-čou"
    ],
    "name:cym_x_preferred": [
      "Meizhou"
    ],
    "name:dan_x_preferred": [
      "Meizhou"
    ],
    "name:deu_x_preferred": [
      "Meizhou"
    ],
    "name:eus_x_preferred": [
      "Meizhou"
    ],
    "name:fas_x_preferred": [
      "ماوژوا"
    ],
    "name:fin_x_preferred": [
      "Meizhou"
    ],
    "name:fra_x_preferred": [
      "Meizhou"
    ],
    "name:hak_x_preferred": [
      "Mòi-chû-sṳ"
    ],
    "name:heb_x_preferred": [
      "מאיז'ואו"
    ],
    "name:hun_x_preferred": [
      "Meizhou"
    ],
    "name:ind_x_preferred": [
      "Meizhou"
    ],
    "name:ita_x_preferred": [
      "Meizhou"
    ],
    "name:jpn_x_preferred": [
      "梅州市"
    ],
    "name:kaz_x_preferred": [
      "Мэйчжоу"
    ],
    "name:kik_x_preferred": [
      "Meizhou"
    ],
    "name:kor_x_preferred": [
      "메이저우시"
    ],
    "name:mlg_x_preferred": [
      "Meizhou"
    ],
    "name:nld_x_preferred": [
      "Meizhou"
    ],
    "name:nno_x_preferred": [
      "Meizhou"
    ],
    "name:nor_x_preferred": [
      "Meizhou"
    ],
    "name:pam_x_preferred": [
      "Meizhou"
    ],
    "name:pnb_x_preferred": [
      "میئیژوؤ"
    ],
    "name:pol_x_preferred": [
      "Meizhou"
    ],
    "name:por_x_preferred": [
      "Meizhou"
    ],
    "name:rus_x_preferred": [
      "Мэйчжоу"
    ],
    "name:spa_x_preferred": [
      "Meizhóu"
    ],
    "name:swa_x_preferred": [
      "Meizhou"
    ],
    "name:swe_x_preferred": [
      "Meizhou"
    ],
    "name:tgl_x_preferred": [
      "Meizhou"
    ],
    "name:tur_x_preferred": [
      "Meizhou"
    ],
    "name:und_x_variant": [
      "梅洲"
    ],
    "name:urd_x_preferred": [
      "مئیژو"
    ],
    "name:vie_x_preferred": [
      "Mai Châu"
    ],
    "name:war_x_preferred": [
      "Meizhou"
    ],
    "name:zho_x_preferred": [
      "梅州市"
    ],
    "wof:name": "Meizhou",
    "wof:placetype": "locality"
  },
  "geometry": {
    "coordinates": [
      114.23963,
      27.09838
    ],
    "type": "Point"
  }
}