{
  "type": "Feature",
  "properties": {
    "gn:admin1_code": "16",
    "gn:asciiname": "Damian",
    "gn:country_code": "CN",
    "gn:dem": 263,
    "gn:feature_class": "P",
    "gn:feature_code": "PPL",
    "gn:name": "Damian",
    "gn:population": 0,
    "gn:timezone": "Asia/Shanghai",
    "iso:country": "CN",
    "name:bul_x_preferred": [
      "Дамян"
    ],
    "name:ceb_x_preferred": [
      "Damian"
    ],
    "name:deu_x_preferred": [
      "Damian"
    ],
    "name:ell_x_preferred": [
      "Δαμιανός"
    ],
    "name:hun_x_preferred": [
      "Damján"
    ],
    "name:ita_x_preferred": [
      "Damian"
    ],
    "name:jpn_x_preferred": [
      "ダミアン"
    ],
    "name:spa_x_preferred": [
      "Damián"
    ],
    "name:swe_x_preferred": [
      "Damian"
    ],
    "name:zho_x_preferred": [
      "大棉"
    ],
    "wof:name": "Damian",
    "wof:placetype": "locality"
  },
  "geometry": {
    "coordinates": [
      109.706,
      25.4724
    ],
    "type": "Point"
  }
}