{
  "type": "Feature",
  "properties": {
    "gn:admin1_code": "16.0",
    "gn:asciiname": "Daji",
    "gn:country_code": "CN",
    "gn:dem": 870,
    "gn:feature_class": "P",
    "gn:feature_code": "PPL",
    "gn:name": "Daji",
    "gn:population": 0,
    "gn:timezone": "Asia/Shanghai",
    "iso:country": "CN",
    "name:cat_x_preferred": [
      "Daji"
    ],
    "name:deu_x_preferred": [
      "Daji"
    ],
    "name:fra_x_preferred": [
      "Daji"
    ],
    "name:ind_x_preferred": [
      "Daji"
    ],
    "name:por_x_preferred": [
      "Daji"
    ],
    "name:spa_x_preferred": [
      "Daji"
    ],
    "name:tha_x_preferred": [
      "ต๋าจี่"
    ],
    "name:vie_x_preferred": [
      "Đát Kỷ"
    ],
    "name:zho_x_preferred": [
      "大吉"
    ],
    "wof:name": "Daji",
    "wof:placetype": "locality"
  },
  "geometry": {
    "coordinates": [
      106.421,
      23.5364
    ],
    "type": "Point"
  }
}