{
  "type": "Feature",
  "properties": {
    "gn:admin1_code": "06",
    "gn:asciiname": "Obo",
    "gn:country_code": "CN",
    "gn:dem": 3425,
    "gn:feature_class": "P",
    "gn:feature_code": "PPLA4",
    "gn:name": "Obo",
    "gn:population": 0,
    "gn:timezone": "Asia/Shanghai",
    "iso:country": "CN",
    "name:azb_x_preferred": [
      "اوبو"
    ],
    "name:ceb_x_preferred": [
      "Obo"
    ],
    "name:deu_x_preferred": [
      "Obo"
    ],
    "name:est_x_preferred": [
      "Obo"
    ],
    "name:fas_x_preferred": [
      "اوبو"
    ],
    "name:fra_x_preferred": [
      "Obo"
    ],
    "name:frr_x_preferred": [
      "Obo"
    ],
    "name:heb_x_preferred": [
      "אובו"
    ],
    "name:hun_x_preferred": [
      "Obo"
    ],
    "name:ita_x_preferred": [
      "Obo"
    ],
    "name:jpn_x_preferred": [
      "オボ"
    ],
    "name:lit_x_preferred": [
      "Obo"
    ],
    "name:nld_x_preferred": [
      "Obo"
    ],
    "name:pol_x_preferred": [
      "Obo"
    ],
    "name:ron_x_preferred": [
      "Obo"
    ],
    "name:rus_x_preferred": [
      "Обо"
    ],
    "name:sag_x_preferred": [
      "Obo"
    ],
    "name:sqi_x_preferred": [
      "Obo"
    ],
    "name:swe_x_preferred": [
      "Obo"
    ],
    "name:tur_x_preferred": [
      "Obo"
    ],
    "name:und_x_variant": [
      "Ebo",
      "O-po-ch’eng",
      "O-po",
      "Ebao",
      "Hongtu",
      "Ebao Zhen",
      "Hongtucheng"
    ],
    "name:urd_x_preferred": [
      "اوبو"
    ],
    "name:xmf_x_preferred": [
      "ობო"
    ],
    "name:zho_x_preferred": [
      "峨堡"
    ],
    "name:zho_x_variant": [
      "红土",
      "峨堡镇",
      "红土城"
    ],
    "wof:name": "Obo",
    "wof:placetype": "locality"
  },
  "geometry": {
    "coordinates": [
      100.93299,
      37.96463
    ],
    "type": "Point"
  }
}