{
  "type": "Feature",
  "properties": {
    "gn:admin1_code": "16.0",
    "gn:asciiname": "Dingqiu",
    "gn:country_code": "CN",
    "gn:dem": 83,
    "gn:feature_class": "P",
    "gn:feature_code": "PPL",
    "gn:name": "Dingqiu",
    "gn:population": 0,
    "gn:timezone": "Asia/Shanghai",
    "iso:country": "CN",
    "name:zho_x_preferred": [
      "定秋"
    ],
    "wof:name": "Dingqiu",
    "wof:placetype": "locality"
  },
  "geometry": {
    "coordinates": [
      108.242,
      22.8078
    ],
    "type": "Point"
  }
}