{
  "type": "Feature",
  "properties": {
    "gn:admin1_code": "10",
    "gn:asciiname": "Pengtou",
    "gn:country_code": "CN",
    "gn:dem": 346,
    "gn:feature_class": "P",
    "gn:feature_code": "PPL",
    "gn:name": "Pengtou",
    "gn:population": 0,
    "gn:timezone": "Asia/Shanghai",
    "iso:country": "CN",
    "name:und_x_variant": [
      "Feng-t’ou",
      "Pengtou Xiang",
      "Pengtoucun",
      "P’eng-t’ou-ts’un",
      "Pentou",
      "Pengtou"
    ],
    "name:zho_x_preferred": [
      "蓬头"
    ],
    "wof:name": "Pengtou",
    "wof:placetype": "locality"
  },
  "geometry": {
    "coordinates": [
      115.34977,
      39.72235
    ],
    "type": "Point"
  }
}