{
  "type": "Feature",
  "properties": {
    "gn:admin1_code": "1.0",
    "gn:asciiname": "Zhengji",
    "gn:country_code": "CN",
    "gn:dem": 35,
    "gn:feature_class": "P",
    "gn:feature_code": "PPLA4",
    "gn:name": "Zhengji",
    "gn:population": 0,
    "gn:timezone": "Asia/Shanghai",
    "iso:country": "CN",
    "name:und_x_variant": [
      "Zhengjiaji",
      "Zhengji Zhen"
    ],
    "name:zho_x_preferred": [
      "郑集"
    ],
    "name:zho_x_variant": [
      "郑家集",
      "郑集镇"
    ],
    "wof:name": "Zhengji",
    "wof:placetype": "locality"
  },
  "geometry": {
    "coordinates": [
      118.94611,
      32.59582
    ],
    "type": "Point"
  }
}