{
  "type": "Feature",
  "properties": {
    "gn:admin1_code": "3.0",
    "gn:asciiname": "Xiyuan",
    "gn:country_code": "CN",
    "gn:dem": 398,
    "gn:feature_class": "P",
    "gn:feature_code": "PPL",
    "gn:name": "Xiyuan",
    "gn:population": 0,
    "gn:timezone": "Asia/Shanghai",
    "iso:country": "CN",
    "name:deu_x_preferred": [
      "Xiyuan"
    ],
    "name:zho_x_preferred": [
      "西沅"
    ],
    "wof:name": "Xiyuan",
    "wof:placetype": "locality"
  },
  "geometry": {
    "coordinates": [
      117.72991,
      28.02388
    ],
    "type": "Point"
  }
}