{
  "type": "Feature",
  "properties": {
    "gn:admin1_code": "16.0",
    "gn:asciiname": "Shangdi",
    "gn:country_code": "CN",
    "gn:dem": 563,
    "gn:feature_class": "P",
    "gn:feature_code": "PPL",
    "gn:name": "Shangdi",
    "gn:population": 0,
    "gn:timezone": "Asia/Shanghai",
    "iso:country": "CN",
    "name:bel_x_preferred": [
      "Шандзі"
    ],
    "name:cat_x_preferred": [
      "Shangdi"
    ],
    "name:fas_x_preferred": [
      "شانگدی"
    ],
    "name:fra_x_preferred": [
      "Shang Di"
    ],
    "name:hun_x_preferred": [
      "Sang-ti"
    ],
    "name:ind_x_preferred": [
      "Shangdi"
    ],
    "name:ita_x_preferred": [
      "Shang Di"
    ],
    "name:msa_x_preferred": [
      "Shangdi"
    ],
    "name:nor_x_preferred": [
      "Shangdi"
    ],
    "name:pol_x_preferred": [
      "Shangdi"
    ],
    "name:por_x_preferred": [
      "Shangdi"
    ],
    "name:spa_x_preferred": [
      "Shangdi"
    ],
    "name:swe_x_preferred": [
      "Shang Di"
    ],
    "name:tur_x_preferred": [
      "Shangdi"
    ],
    "name:ukr_x_preferred": [
      "Шан-ді"
    ],
    "name:vie_x_preferred": [
      "Thượng đế"
    ],
    "name:zho_x_preferred": [
      "上第"
    ],
    "wof:name": "Shangdi",
    "wof:placetype": "locality"
  },
  "geometry": {
    "coordinates": [
      108.193,
      24.1891
    ],
    "type": "Point"
  }
}