{
  "type": "Feature",
  "properties": {
    "gn:admin1_code": "10",
    "gn:asciiname": "Qianbazhang",
    "gn:country_code": "CN",
    "gn:dem": 20,
    "gn:feature_class": "P",
    "gn:feature_code": "PPL",
    "gn:name": "Qianbazhang",
    "gn:population": 0,
    "gn:timezone": "Asia/Shanghai",
    "iso:country": "CN",
    "name:zho_x_preferred": [
      "前八丈"
    ],
    "wof:name": "Qianbazhang",
    "wof:placetype": "locality"
  },
  "geometry": {
    "coordinates": [
      116.15397,
      37.79929
    ],
    "type": "Point"
  }
}