{
  "type": "Feature",
  "properties": {
    "gn:admin1_code": "30.0",
    "gn:asciiname": "Zhoushan",
    "gn:country_code": "CN",
    "gn:dem": 10,
    "gn:feature_class": "P",
    "gn:feature_code": "PPL",
    "gn:name": "Zhoushan",
    "gn:population": 0,
    "gn:timezone": "Asia/Shanghai",
    "iso:country": "CN",
    "name:ara_x_preferred": [
      "زهوشان"
    ],
    "name:cdo_x_preferred": [
      "Ciŭ-săng"
    ],
    "name:ces_x_preferred": [
      "Čou-šan"
    ],
    "name:dan_x_preferred": [
      "Zhoushan"
    ],
    "name:deu_x_preferred": [
      "Zhoushan"
    ],
    "name:eus_x_preferred": [
      "Zhoushan"
    ],
    "name:fas_x_preferred": [
      "جواشان"
    ],
    "name:fin_x_preferred": [
      "Zhoushan"
    ],
    "name:fra_x_preferred": [
      "Zhoushan"
    ],
    "name:ind_x_preferred": [
      "Zhoushan"
    ],
    "name:ita_x_preferred": [
      "Zhoushan"
    ],
    "name:jpn_x_preferred": [
      "舟山市"
    ],
    "name:kik_x_preferred": [
      "Zhoushan"
    ],
    "name:kor_x_preferred": [
      "저우산시"
    ],
    "name:mlg_x_preferred": [
      "Zhoushan"
    ],
    "name:nld_x_preferred": [
      "Zhoushan"
    ],
    "name:nno_x_preferred": [
      "Zhoushan"
    ],
    "name:nor_x_preferred": [
      "Zhoushan"
    ],
    "name:pol_x_preferred": [
      "Zhoushan"
    ],
    "name:rus_x_preferred": [
      "Чжоушань"
    ],
    "name:spa_x_preferred": [
      "Zhoushan"
    ],
    "name:swe_x_preferred": [
      "Zhoushan"
    ],
    "name:tgl_x_preferred": [
      "Zhoushan"
    ],
    "name:tur_x_preferred": [
      "Zhoushan"
    ],
    "name:uig_x_preferred": [
      "جۇشەن شەھىرى"
    ],
    "name:urd_x_preferred": [
      "ژووشان"
    ],
    "name:vie_x_preferred": [
      "Chu San"
    ],
    "name:war_x_preferred": [
      "Zhoushan"
    ],
    "name:wuu_x_preferred": [
      "舟山市"
    ],
    "name:zho_x_preferred": [
      "洲山"
    ],
    "name:zho_x_variant": [
      "舟山市"
    ],
    "wof:name": "Zhoushan",
    "wof:placetype": "locality"
  },
  "geometry": {
    "coordinates": [
      112.85624,
      22.00195
    ],
    "type": "Point"
  }
}