{
  "type": "Feature",
  "properties": {
    "gn:admin1_code": "18.0",
    "gn:asciiname": "Longxi",
    "gn:country_code": "CN",
    "gn:dem": 879,
    "gn:feature_class": "P",
    "gn:feature_code": "PPL",
    "gn:name": "Longxi",
    "gn:population": 0,
    "gn:timezone": "Asia/Shanghai",
    "iso:country": "CN",
    "name:ara_x_preferred": [
      "لونجكسي"
    ],
    "name:ben_x_preferred": [
      "লংগক্সি"
    ],
    "name:ceb_x_preferred": [
      "Longxi"
    ],
    "name:deu_x_preferred": [
      "Longxi"
    ],
    "name:ell_x_preferred": [
      "Λόνγκξι"
    ],
    "name:eng_x_preferred": [
      "Longxi"
    ],
    "name:fas_x_preferred": [
      "لنگشی"
    ],
    "name:fra_x_preferred": [
      "Longxi"
    ],
    "name:heb_x_preferred": [
      "לונגקסי"
    ],
    "name:hin_x_preferred": [
      "लांगक्सी"
    ],
    "name:hun_x_preferred": [
      "Longxi"
    ],
    "name:ind_x_preferred": [
      "Longxi"
    ],
    "name:ita_x_preferred": [
      "Longxi"
    ],
    "name:jpn_x_preferred": [
      "隴西"
    ],
    "name:kor_x_preferred": [
      "룽시"
    ],
    "name:nld_x_preferred": [
      "Longxi"
    ],
    "name:pol_x_preferred": [
      "Longxi"
    ],
    "name:por_x_preferred": [
      "Longxi"
    ],
    "name:rus_x_preferred": [
      "Лунси"
    ],
    "name:spa_x_preferred": [
      "Longxi"
    ],
    "name:swe_x_preferred": [
      "Longxi"
    ],
    "name:tur_x_preferred": [
      "Longxi"
    ],
    "name:ukr_x_preferred": [
      "Лунсі"
    ],
    "name:urd_x_preferred": [
      "لونگزی"
    ],
    "name:vie_x_preferred": [
      "Lũng Tây"
    ],
    "name:zho_cn_x_preferred": [
      "陇西"
    ],
    "name:zho_tw_x_preferred": [
      "隴西"
    ],
    "name:zho_x_preferred": [
      "龙溪"
    ],
    "wof:name": "Longxi",
    "wof:placetype": "locality"
  },
  "geometry": {
    "coordinates": [
      108.773,
      26.3192
    ],
    "type": "Point"
  }
}