{
  "type": "Feature",
  "properties": {
    "gn:admin1_code": "11",
    "gn:asciiname": "Pengjiayuan",
    "gn:country_code": "CN",
    "gn:dem": 134,
    "gn:feature_class": "P",
    "gn:feature_code": "PPL",
    "gn:name": "Pengjiayuan",
    "gn:population": 0,
    "gn:timezone": "Asia/Shanghai",
    "iso:country": "CN",
    "name:zho_x_preferred": [
      "彭家院"
    ],
    "wof:name": "Pengjiayuan",
    "wof:placetype": "locality"
  },
  "geometry": {
    "coordinates": [
      111.99015,
      26.72454
    ],
    "type": "Point"
  }
}