{
  "type": "Feature",
  "properties": {
    "gn:admin1_code": "3",
    "gn:asciiname": "Sanqiao",
    "gn:country_code": "CN",
    "gn:dem": 59,
    "gn:feature_class": "P",
    "gn:feature_code": "PPL",
    "gn:name": "Sanqiao",
    "gn:population": 0,
    "gn:timezone": "Asia/Shanghai",
    "iso:country": "CN",
    "name:deu_x_preferred": [
      "Sanqiao"
    ],
    "name:und_x_variant": [
      "三桥",
      "Sanqiaoxiang",
      "三桥乡"
    ],
    "wof:name": "Sanqiao",
    "wof:placetype": "locality"
  },
  "geometry": {
    "coordinates": [
      116.15792,
      27.97419
    ],
    "type": "Point"
  }
}