{
  "type": "Feature",
  "properties": {
    "gn:admin1_code": "12",
    "gn:asciiname": "Meichuan",
    "gn:country_code": "CN",
    "gn:dem": 45,
    "gn:feature_class": "P",
    "gn:feature_code": "PPLA4",
    "gn:name": "Meichuan",
    "gn:population": 0,
    "gn:timezone": "Asia/Shanghai",
    "iso:country": "CN",
    "name:und_x_variant": [
      "Kwangchi",
      "Mei-ch’uan-chen",
      "Kuang-chi-hsien",
      "Kuang-chi",
      "Meichuan",
      "Meichuan Zhen"
    ],
    "name:zho_x_preferred": [
      "梅川"
    ],
    "name:zho_x_variant": [
      "梅川镇"
    ],
    "wof:name": "Meichuan",
    "wof:placetype": "locality"
  },
  "geometry": {
    "coordinates": [
      115.59597,
      30.12946
    ],
    "type": "Point"
  }
}