{
  "type": "Feature",
  "properties": {
    "gn:admin1_code": "19.0",
    "gn:asciiname": "Laomazi Beigou",
    "gn:country_code": "CN",
    "gn:dem": 191,
    "gn:feature_class": "P",
    "gn:feature_code": "PPL",
    "gn:name": "Laomazi Beigou",
    "gn:population": 0,
    "gn:timezone": "Asia/Shanghai",
    "iso:country": "CN",
    "name:und_x_variant": [
      "老妈子北沟"
    ],
    "wof:name": "Laomazi Beigou",
    "wof:placetype": "locality"
  },
  "geometry": {
    "coordinates": [
      122.81241,
      40.41302
    ],
    "type": "Point"
  }
}