{
  "type": "Feature",
  "properties": {
    "gn:admin1_code": "16",
    "gn:asciiname": "Huanghua",
    "gn:country_code": "CN",
    "gn:dem": 77,
    "gn:feature_class": "P",
    "gn:feature_code": "PPL",
    "gn:name": "Huanghua",
    "gn:population": 0,
    "gn:timezone": "Asia/Shanghai",
    "iso:country": "CN",
    "name:ara_x_preferred": [
      "هوانغوا"
    ],
    "name:deu_x_preferred": [
      "Huanghua"
    ],
    "name:fra_x_preferred": [
      "Huanghua"
    ],
    "name:ita_x_preferred": [
      "Huanghua"
    ],
    "name:jpn_x_preferred": [
      "黄驊"
    ],
    "name:jpn_x_variant": [
      "黄カ市"
    ],
    "name:kik_x_preferred": [
      "Huanghua"
    ],
    "name:kor_x_preferred": [
      "황화시"
    ],
    "name:nor_x_preferred": [
      "Huanghua"
    ],
    "name:pam_x_preferred": [
      "Huanghua"
    ],
    "name:pol_x_preferred": [
      "Huanghua"
    ],
    "name:rus_x_preferred": [
      "Хуанхуа"
    ],
    "name:swe_x_preferred": [
      "Huanghua"
    ],
    "name:urd_x_preferred": [
      "ہوانگہوا"
    ],
    "name:vie_x_preferred": [
      "Hoàng Hoa"
    ],
    "name:war_x_preferred": [
      "Huanghua"
    ],
    "name:zho_x_preferred": [
      "黄花"
    ],
    "name:zho_x_variant": [
      "黄骅市"
    ],
    "wof:name": "Huanghua",
    "wof:placetype": "locality"
  },
  "geometry": {
    "coordinates": [
      109.627,
      23.7229
    ],
    "type": "Point"
  }
}