{
  "type": "Feature",
  "properties": {
    "gn:admin1_code": "16.0",
    "gn:asciiname": "Long'an",
    "gn:country_code": "CN",
    "gn:dem": 61,
    "gn:feature_class": "P",
    "gn:feature_code": "PPL",
    "gn:name": "Long’an",
    "gn:population": 0,
    "gn:timezone": "Asia/Shanghai",
    "iso:country": "CN",
    "name:ceb_x_preferred": [
      "Long'an"
    ],
    "name:fra_x_preferred": [
      "Long'an"
    ],
    "name:nor_x_preferred": [
      "Long'an"
    ],
    "name:swe_x_preferred": [
      "Long'an"
    ],
    "name:und_x_variant": [
      "Long’an"
    ],
    "name:zho_x_preferred": [
      "龙安"
    ],
    "wof:name": "Long'an",
    "wof:placetype": "locality"
  },
  "geometry": {
    "coordinates": [
      110.294,
      23.4636
    ],
    "type": "Point"
  }
}