{
  "type": "Feature",
  "properties": {
    "gn:admin1_code": "11.0",
    "gn:asciiname": "Shishixi",
    "gn:country_code": "CN",
    "gn:dem": 282,
    "gn:feature_class": "P",
    "gn:feature_code": "PPL",
    "gn:name": "Shishixi",
    "gn:population": 0,
    "gn:timezone": "Asia/Shanghai",
    "iso:country": "CN",
    "name:zho_x_preferred": [
      "Shishixi"
    ],
    "name:zho_x_variant": [
      "石狮溪"
    ],
    "wof:name": "Shishixi",
    "wof:placetype": "locality"
  },
  "geometry": {
    "coordinates": [
      110.93032,
      28.98341
    ],
    "type": "Point"
  }
}