{
  "type": "Feature",
  "properties": {
    "gn:admin1_code": "10",
    "gn:asciiname": "Nanping",
    "gn:country_code": "CN",
    "gn:dem": 639,
    "gn:feature_class": "P",
    "gn:feature_code": "PPL",
    "gn:name": "Nanping",
    "gn:population": 0,
    "gn:timezone": "Asia/Shanghai",
    "iso:country": "CN",
    "name:afr_x_preferred": [
      "Nanping"
    ],
    "name:ara_x_preferred": [
      "نانبينغ"
    ],
    "name:bre_x_preferred": [
      "Nanping"
    ],
    "name:cdo_x_preferred": [
      "Nàng-bìng"
    ],
    "name:ceb_x_preferred": [
      "Nanping"
    ],
    "name:ces_x_preferred": [
      "Nan-pching"
    ],
    "name:cym_x_preferred": [
      "Nanping"
    ],
    "name:dan_x_preferred": [
      "Nanping"
    ],
    "name:deu_x_preferred": [
      "Nanping"
    ],
    "name:eus_x_preferred": [
      "Nanping"
    ],
    "name:fas_x_preferred": [
      "نانپینگ"
    ],
    "name:fin_x_preferred": [
      "Nanping"
    ],
    "name:fra_x_preferred": [
      "Nanping"
    ],
    "name:hak_x_preferred": [
      "Nàm-phìn-sṳ"
    ],
    "name:hun_x_preferred": [
      "Nanping"
    ],
    "name:ita_x_preferred": [
      "Nanping"
    ],
    "name:jpn_x_preferred": [
      "南平市"
    ],
    "name:kik_x_preferred": [
      "Nanping"
    ],
    "name:kor_x_preferred": [
      "난핑시"
    ],
    "name:mlg_x_preferred": [
      "Nanping"
    ],
    "name:nld_x_preferred": [
      "Nanping"
    ],
    "name:nno_x_preferred": [
      "Nanping"
    ],
    "name:nor_x_preferred": [
      "Nanping"
    ],
    "name:pam_x_preferred": [
      "Nanping"
    ],
    "name:pnb_x_preferred": [
      "نانپینگ"
    ],
    "name:pol_x_preferred": [
      "Nanping"
    ],
    "name:por_x_preferred": [
      "Nanping"
    ],
    "name:rus_x_preferred": [
      "Наньпин"
    ],
    "name:spa_x_preferred": [
      "Nanping"
    ],
    "name:swe_x_preferred": [
      "Nanping"
    ],
    "name:tgl_x_preferred": [
      "Nanping"
    ],
    "name:tur_x_preferred": [
      "Nanping"
    ],
    "name:uig_x_preferred": [
      "Nenping shehiri"
    ],
    "name:urd_x_preferred": [
      "نانپنگ"
    ],
    "name:vie_x_preferred": [
      "Nam Bình"
    ],
    "name:war_x_preferred": [
      "Nanping"
    ],
    "name:wuu_x_preferred": [
      "南平市"
    ],
    "name:zho_x_preferred": [
      "南坪"
    ],
    "name:zho_x_variant": [
      "南平市"
    ],
    "wof:name": "Nanping",
    "wof:placetype": "locality"
  },
  "geometry": {
    "coordinates": [
      113.951,
      36.5417
    ],
    "type": "Point"
  }
}