{
  "type": "Feature",
  "properties": {
    "gn:admin1_code": "16.0",
    "gn:asciiname": "Gulu",
    "gn:country_code": "CN",
    "gn:dem": 100,
    "gn:feature_class": "P",
    "gn:feature_code": "PPL",
    "gn:name": "Gulu",
    "gn:population": 0,
    "gn:timezone": "Asia/Shanghai",
    "iso:country": "CN",
    "name:ara_x_preferred": [
      "غولو"
    ],
    "name:azb_x_preferred": [
      "قولو"
    ],
    "name:ceb_x_preferred": [
      "Gulu"
    ],
    "name:dan_x_preferred": [
      "Gulu"
    ],
    "name:deu_x_preferred": [
      "Gulu"
    ],
    "name:ell_x_preferred": [
      "Γκουλού"
    ],
    "name:epo_x_preferred": [
      "Gulu"
    ],
    "name:eus_x_preferred": [
      "Gulu"
    ],
    "name:fas_x_preferred": [
      "گولو"
    ],
    "name:fin_x_preferred": [
      "Gulu"
    ],
    "name:fra_x_preferred": [
      "Gulu"
    ],
    "name:heb_x_preferred": [
      "גולו"
    ],
    "name:hrv_x_preferred": [
      "Gulu"
    ],
    "name:hun_x_preferred": [
      "Gulu"
    ],
    "name:ind_x_preferred": [
      "Gulu"
    ],
    "name:ita_x_preferred": [
      "Gulu"
    ],
    "name:jpn_x_preferred": [
      "グル"
    ],
    "name:kal_x_preferred": [
      "Gulu"
    ],
    "name:kat_x_preferred": [
      "გულუ"
    ],
    "name:lit_x_preferred": [
      "Gulu"
    ],
    "name:lug_x_preferred": [
      "Gulu"
    ],
    "name:mal_x_preferred": [
      "ഗുലു"
    ],
    "name:mri_x_preferred": [
      "Gulu"
    ],
    "name:nld_x_preferred": [
      "Gulu"
    ],
    "name:pol_x_preferred": [
      "Gulu"
    ],
    "name:por_x_preferred": [
      "Gulu"
    ],
    "name:ron_x_preferred": [
      "Gulu"
    ],
    "name:rus_x_preferred": [
      "Гулу"
    ],
    "name:spa_x_preferred": [
      "Gulu"
    ],
    "name:swa_x_preferred": [
      "Gulu"
    ],
    "name:swe_x_preferred": [
      "Gulu"
    ],
    "name:urd_x_preferred": [
      "گولو"
    ],
    "name:zho_x_preferred": [
      "古碌"
    ],
    "name:zho_x_variant": [
      "古盧"
    ],
    "wof:name": "Gulu",
    "wof:placetype": "locality"
  },
  "geometry": {
    "coordinates": [
      110.751,
      23.6245
    ],
    "type": "Point"
  }
}