{
  "type": "Feature",
  "properties": {
    "gn:admin1_code": "7.0",
    "gn:asciiname": "Banshan",
    "gn:country_code": "CN",
    "gn:dem": 152,
    "gn:feature_class": "P",
    "gn:feature_code": "PPL",
    "gn:name": "Banshan",
    "gn:population": 0,
    "gn:timezone": "Asia/Shanghai",
    "iso:country": "CN",
    "name:deu_x_preferred": [
      "Banshan-Machang-Kultur"
    ],
    "name:swe_x_preferred": [
      "Banshankulturen"
    ],
    "name:ukr_x_preferred": [
      "Баньшань"
    ],
    "name:zho_x_preferred": [
      "半山"
    ],
    "name:zho_x_variant": [
      "半山遺址"
    ],
    "wof:name": "Banshan",
    "wof:placetype": "locality"
  },
  "geometry": {
    "coordinates": [
      119.55992,
      26.84589
    ],
    "type": "Point"
  }
}