{
  "type": "Feature",
  "properties": {
    "gn:admin1_code": "26",
    "gn:asciiname": "Taoyuan",
    "gn:country_code": "CN",
    "gn:dem": 544,
    "gn:feature_class": "P",
    "gn:feature_code": "PPL",
    "gn:name": "Taoyuan",
    "gn:population": 0,
    "gn:timezone": "Asia/Shanghai",
    "iso:country": "CN",
    "name:ben_x_preferred": [
      "তায়োইউয়ান"
    ],
    "name:ceb_x_preferred": [
      "Taoyuan"
    ],
    "name:deu_x_preferred": [
      "Taoyuan"
    ],
    "name:ell_x_preferred": [
      "Ταογουάν"
    ],
    "name:fas_x_preferred": [
      "توئایوآن"
    ],
    "name:fra_x_preferred": [
      "Taoyuan"
    ],
    "name:heb_x_preferred": [
      "טאויואן"
    ],
    "name:hin_x_preferred": [
      "ताओयुआन"
    ],
    "name:hun_x_preferred": [
      "Taoyuan"
    ],
    "name:ind_x_preferred": [
      "Taoyuan"
    ],
    "name:kor_x_preferred": [
      "타오위안"
    ],
    "name:lit_x_preferred": [
      "Taojuanas"
    ],
    "name:nld_x_preferred": [
      "Taoyuan"
    ],
    "name:nor_x_preferred": [
      "Taoyuan"
    ],
    "name:por_x_preferred": [
      "Taoyuan"
    ],
    "name:tur_x_preferred": [
      "Taoyuan"
    ],
    "name:vie_x_preferred": [
      "Đào Viên"
    ],
    "name:zho_x_preferred": [
      "桃园"
    ],
    "name:zho_x_variant": [
      "桃園"
    ],
    "wof:name": "Taoyuan",
    "wof:placetype": "locality"
  },
  "geometry": {
    "coordinates": [
      108.22661,
      34.3408
    ],
    "type": "Point"
  }
}