{
  "type": "Feature",
  "properties": {
    "gn:admin1_code": "13.0",
    "gn:asciiname": "Kurti",
    "gn:country_code": "CN",
    "gn:dem": 1003,
    "gn:feature_class": "P",
    "gn:feature_code": "PPLA4",
    "gn:name": "Kürti",
    "gn:population": 0,
    "gn:timezone": "Asia/Urumqi",
    "iso:country": "CN",
    "name:ceb_x_preferred": [
      "Kurti"
    ],
    "name:deu_x_preferred": [
      "Kurti"
    ],
    "name:swe_x_preferred": [
      "Kurti"
    ],
    "name:uig_x_preferred": [
      "كۈرتى"
    ],
    "name:uig_x_variant": [
      "Күрти"
    ],
    "name:und_x_variant": [
      "Kürti",
      "Ku’er Te",
      "Ku’erte Xiang"
    ],
    "name:zho_x_preferred": [
      "库尔特"
    ],
    "name:zho_x_variant": [
      "库尔特乡"
    ],
    "wof:name": "Kurti",
    "wof:placetype": "locality"
  },
  "geometry": {
    "coordinates": [
      89.30530999999998,
      47.20003
    ],
    "type": "Point"
  }
}