{
  "type": "Feature",
  "properties": {
    "gn:admin1_code": "32.0",
    "gn:asciiname": "Yuhuangguan",
    "gn:country_code": "CN",
    "gn:dem": 403,
    "gn:feature_class": "P",
    "gn:feature_code": "PPL",
    "gn:name": "Yuhuangguan",
    "gn:population": 0,
    "gn:timezone": "Asia/Shanghai",
    "iso:country": "CN",
    "name:zho_x_preferred": [
      "玉皇观"
    ],
    "wof:name": "Yuhuangguan",
    "wof:placetype": "locality"
  },
  "geometry": {
    "coordinates": [
      105.24806,
      30.84573
    ],
    "type": "Point"
  }
}