{
  "type": "Feature",
  "properties": {
    "gn:admin1_code": "25.0",
    "gn:asciiname": "Xinjiayaocun",
    "gn:country_code": "CN",
    "gn:dem": 72,
    "gn:feature_class": "P",
    "gn:feature_code": "PPL",
    "gn:name": "Xinjiayaocun",
    "gn:population": 0,
    "gn:timezone": "Asia/Shanghai",
    "iso:country": "CN",
    "name:zho_x_preferred": [
      "辛家尧村"
    ],
    "wof:name": "Xinjiayaocun",
    "wof:placetype": "locality"
  },
  "geometry": {
    "coordinates": [
      119.40727,
      35.95105
    ],
    "type": "Point"
  }
}