{
  "type": "Feature",
  "properties": {
    "gn:admin1_code": "02",
    "gn:asciiname": "Kuangyan",
    "gn:country_code": "CN",
    "gn:dem": 8,
    "gn:feature_class": "P",
    "gn:feature_code": "PPLA4",
    "gn:name": "Kuangyan",
    "gn:population": 0,
    "gn:timezone": "Asia/Shanghai",
    "iso:country": "CN",
    "name:und_x_variant": [
      "K’uang-yen-shih",
      "K’uang-yen",
      "Kuangyan",
      "匡堰",
      "Kuangyan Zhen",
      "匡堰镇"
    ],
    "wof:name": "Kuangyan",
    "wof:placetype": "locality"
  },
  "geometry": {
    "coordinates": [
      121.29586,
      30.15127
    ],
    "type": "Point"
  }
}