{
  "type": "Feature",
  "properties": {
    "gn:admin1_code": "3.0",
    "gn:asciiname": "Anshan",
    "gn:country_code": "CN",
    "gn:dem": 43,
    "gn:feature_class": "P",
    "gn:feature_code": "PPL",
    "gn:name": "Anshan",
    "gn:population": 0,
    "gn:timezone": "Asia/Shanghai",
    "iso:country": "CN",
    "name:afr_x_preferred": [
      "Anshan"
    ],
    "name:ara_x_preferred": [
      "آنشان"
    ],
    "name:aze_x_preferred": [
      "Anşan"
    ],
    "name:bul_x_preferred": [
      "Аншан"
    ],
    "name:cdo_x_preferred": [
      "Ăng-săng"
    ],
    "name:ceb_x_preferred": [
      "Anshan"
    ],
    "name:ces_x_preferred": [
      "An-šan"
    ],
    "name:che_x_preferred": [
      "Аньшань"
    ],
    "name:dan_x_preferred": [
      "Anshan"
    ],
    "name:deu_x_preferred": [
      "Anshan"
    ],
    "name:epo_x_preferred": [
      "Anŝano"
    ],
    "name:est_x_preferred": [
      "Anshan Shi"
    ],
    "name:eus_x_preferred": [
      "Anshan"
    ],
    "name:fas_x_preferred": [
      "آنشان"
    ],
    "name:fin_x_preferred": [
      "Anshan"
    ],
    "name:fra_x_preferred": [
      "Anshan"
    ],
    "name:glg_x_preferred": [
      "Anshan"
    ],
    "name:heb_x_preferred": [
      "אנשאן"
    ],
    "name:hye_x_preferred": [
      "Անշան"
    ],
    "name:ind_x_preferred": [
      "Anshan"
    ],
    "name:ita_x_preferred": [
      "Anshan"
    ],
    "name:jpn_x_preferred": [
      "鞍山"
    ],
    "name:jpn_x_variant": [
      "鞍山市"
    ],
    "name:kaz_x_preferred": [
      "Аньшань"
    ],
    "name:kik_x_preferred": [
      "Anshan"
    ],
    "name:kir_x_preferred": [
      "Аньшань"
    ],
    "name:kor_x_preferred": [
      "안산시"
    ],
    "name:lit_x_preferred": [
      "Anšanas"
    ],
    "name:mlg_x_preferred": [
      "Anshan"
    ],
    "name:nld_x_preferred": [
      "Anshan"
    ],
    "name:nno_x_preferred": [
      "Anshan"
    ],
    "name:nor_x_preferred": [
      "Anshan"
    ],
    "name:pan_x_preferred": [
      "ਅਨਸ਼ਾਨ"
    ],
    "name:pol_x_preferred": [
      "Anshan"
    ],
    "name:por_x_preferred": [
      "Anshan"
    ],
    "name:rus_x_preferred": [
      "Аньшань"
    ],
    "name:sco_x_preferred": [
      "Anshan"
    ],
    "name:spa_x_preferred": [
      "Anshán"
    ],
    "name:srp_x_preferred": [
      "Аншан"
    ],
    "name:swe_x_preferred": [
      "Anshan"
    ],
    "name:tgl_x_preferred": [
      "Anshan"
    ],
    "name:tur_x_preferred": [
      "Anshan"
    ],
    "name:uig_x_preferred": [
      "ئەنشەن شەھىرى"
    ],
    "name:ukr_x_preferred": [
      "Аньшань"
    ],
    "name:und_x_variant": [
      "暗山"
    ],
    "name:urd_x_preferred": [
      "انشان"
    ],
    "name:uzb_x_preferred": [
      "Anshan"
    ],
    "name:vie_x_preferred": [
      "An Sơn"
    ],
    "name:war_x_preferred": [
      "Anshan"
    ],
    "name:wuu_x_preferred": [
      "鞍山市"
    ],
    "name:zho_x_preferred": [
      "鞍山市"
    ],
    "wof:name": "Anshan",
    "wof:placetype": "locality"
  },
  "geometry": {
    "coordinates": [
      115.40884,
      28.5184
    ],
    "type": "Point"
  }
}