{
  "type": "Feature",
  "properties": {
    "gn:admin1_code": "16.0",
    "gn:asciiname": "Namin",
    "gn:country_code": "CN",
    "gn:dem": 351,
    "gn:feature_class": "P",
    "gn:feature_code": "PPL",
    "gn:name": "Namin",
    "gn:population": 0,
    "gn:timezone": "Asia/Shanghai",
    "iso:country": "CN",
    "name:rus_x_preferred": [
      "Намин"
    ],
    "name:zho_x_preferred": [
      "那敏"
    ],
    "wof:name": "Namin",
    "wof:placetype": "locality"
  },
  "geometry": {
    "coordinates": [
      107.004,
      23.9809
    ],
    "type": "Point"
  }
}