{
  "type": "Feature",
  "properties": {
    "gn:admin1_code": "18.0",
    "gn:asciiname": "Song'e",
    "gn:country_code": "CN",
    "gn:dem": 819,
    "gn:feature_class": "P",
    "gn:feature_code": "PPL",
    "gn:name": "Song’e",
    "gn:population": 0,
    "gn:timezone": "Asia/Shanghai",
    "iso:country": "CN",
    "name:und_x_variant": [
      "Song’e"
    ],
    "name:zho_x_preferred": [
      "送俄"
    ],
    "wof:name": "Song'e",
    "wof:placetype": "locality"
  },
  "geometry": {
    "coordinates": [
      108.043,
      26.16
    ],
    "type": "Point"
  }
}