{
  "type": "Feature",
  "properties": {
    "gn:admin1_code": "18",
    "gn:asciiname": "Yongkang",
    "gn:country_code": "CN",
    "gn:dem": 746,
    "gn:feature_class": "P",
    "gn:feature_code": "PPL",
    "gn:name": "Yongkang",
    "gn:population": 0,
    "gn:timezone": "Asia/Shanghai",
    "iso:country": "CN",
    "name:ceb_x_preferred": [
      "Yongkang"
    ],
    "name:deu_x_preferred": [
      "Yongkang"
    ],
    "name:fra_x_preferred": [
      "Yongkang"
    ],
    "name:kor_x_preferred": [
      "융캉시"
    ],
    "name:swe_x_preferred": [
      "Yongkang"
    ],
    "name:ukr_x_preferred": [
      "Юнкан"
    ],
    "name:zho_x_preferred": [
      "永康市"
    ],
    "wof:name": "Yongkang",
    "wof:placetype": "locality"
  },
  "geometry": {
    "coordinates": [
      107.94639,
      25.34833
    ],
    "type": "Point"
  }
}