{
  "type": "Feature",
  "properties": {
    "gn:admin1_code": "18.0",
    "gn:asciiname": "Sanwan",
    "gn:country_code": "CN",
    "gn:dem": 1144,
    "gn:feature_class": "P",
    "gn:feature_code": "PPL",
    "gn:name": "Sanwan",
    "gn:population": 0,
    "gn:timezone": "Asia/Shanghai",
    "iso:country": "CN",
    "name:fra_x_preferred": [
      "Sanwan"
    ],
    "name:hak_x_preferred": [
      "Sâm-vân-hiông"
    ],
    "name:jpn_x_preferred": [
      "三湾郷"
    ],
    "name:kor_x_preferred": [
      "싼완향"
    ],
    "name:vie_x_preferred": [
      "Tam Loan"
    ],
    "name:zho_x_preferred": [
      "三湾"
    ],
    "name:zho_x_variant": [
      "三灣鄉"
    ],
    "wof:name": "Sanwan",
    "wof:placetype": "locality"
  },
  "geometry": {
    "coordinates": [
      107.356,
      26.0188
    ],
    "type": "Point"
  }
}