{
  "type": "Feature",
  "properties": {
    "gn:admin1_code": "29",
    "gn:asciiname": "Shangbenyakou",
    "gn:country_code": "CN",
    "gn:dem": 1900,
    "gn:feature_class": "P",
    "gn:feature_code": "PPL",
    "gn:name": "Shangbenyakou",
    "gn:population": 0,
    "gn:timezone": "Asia/Shanghai",
    "iso:country": "CN",
    "name:zho_x_preferred": [
      "上本丫口"
    ],
    "wof:name": "Shangbenyakou",
    "wof:placetype": "locality"
  },
  "geometry": {
    "coordinates": [
      101.537,
      24.9567
    ],
    "type": "Point"
  }
}