{
  "type": "Feature",
  "properties": {
    "gn:admin1_code": "12.0",
    "gn:asciiname": "Yuekou",
    "gn:cc2": "CN",
    "gn:country_code": "CN",
    "gn:dem": 35,
    "gn:feature_class": "P",
    "gn:feature_code": "PPL",
    "gn:name": "Yuekou",
    "gn:population": 0,
    "gn:timezone": "Asia/Shanghai",
    "iso:country": "CN",
    "name:eng_x_historical": [
      "Yokiakow"
    ],
    "name:eng_x_preferred": [
      "Yokiakow"
    ],
    "name:und_x_variant": [
      "Yo-k’ou-chen",
      "Yüeh-k’ou-chen",
      "Yüeh-k’ou-shih",
      "Yüeh-k’ou",
      "Yokow",
      "Yuekou",
      "Yuekou Jiedao"
    ],
    "name:zho_x_preferred": [
      "岳口"
    ],
    "name:zho_x_variant": [
      "岳口街道"
    ],
    "wof:name": "Yuekou",
    "wof:placetype": "locality"
  },
  "geometry": {
    "coordinates": [
      113.07764,
      30.51414
    ],
    "type": "Point"
  }
}