{
  "type": "Feature",
  "properties": {
    "gn:admin1_code": "20.0",
    "gn:asciiname": "Bayintala",
    "gn:country_code": "CN",
    "gn:dem": 582,
    "gn:feature_class": "P",
    "gn:feature_code": "PPL",
    "gn:name": "Bayintala",
    "gn:population": 0,
    "gn:timezone": "Asia/Shanghai",
    "iso:country": "CN",
    "name:zho_x_preferred": [
      "巴音塔拉"
    ],
    "wof:name": "Bayintala",
    "wof:placetype": "locality"
  },
  "geometry": {
    "coordinates": [
      117.80146,
      48.06174
    ],
    "type": "Point"
  }
}