{
  "type": "Feature",
  "properties": {
    "gn:admin1_code": "16",
    "gn:asciiname": "Shishanbei",
    "gn:country_code": "CN",
    "gn:dem": 453,
    "gn:feature_class": "P",
    "gn:feature_code": "PPL",
    "gn:name": "Shishanbei",
    "gn:population": 0,
    "gn:timezone": "Asia/Shanghai",
    "iso:country": "CN",
    "name:zho_x_preferred": [
      "石山背"
    ],
    "wof:name": "Shishanbei",
    "wof:placetype": "locality"
  },
  "geometry": {
    "coordinates": [
      110.64,
      25.9695
    ],
    "type": "Point"
  }
}