{
  "type": "Feature",
  "properties": {
    "gn:admin1_code": "26",
    "gn:asciiname": "Hengshan",
    "gn:cc2": "CN",
    "gn:country_code": "CN",
    "gn:dem": 1039,
    "gn:feature_class": "P",
    "gn:feature_code": "PPL",
    "gn:name": "Hengshan",
    "gn:population": 0,
    "gn:timezone": "Asia/Shanghai",
    "iso:country": "CN",
    "name:ceb_x_preferred": [
      "Hengshan"
    ],
    "name:deu_x_preferred": [
      "Hengshan"
    ],
    "name:fra_x_preferred": [
      "Hengshan"
    ],
    "name:nor_x_preferred": [
      "Hengshan"
    ],
    "name:pol_x_preferred": [
      "Heng Shan"
    ],
    "name:rus_x_preferred": [
      "Хэншань"
    ],
    "name:swe_x_preferred": [
      "Hengshan"
    ],
    "name:und_x_variant": [
      "Haiyüanhsien",
      "Heng-shan-hsien",
      "Huai-yüan",
      "Heng-shan-hsien-ch’eng"
    ],
    "wof:name": "Hengshan",
    "wof:placetype": "locality"
  },
  "geometry": {
    "coordinates": [
      109.28167,
      37.95833
    ],
    "type": "Point"
  }
}