{
  "type": "Feature",
  "properties": {
    "gn:admin1_code": "14.0",
    "gn:asciiname": "Yueqing",
    "gn:country_code": "CN",
    "gn:dem": 4955,
    "gn:feature_class": "P",
    "gn:feature_code": "PPL",
    "gn:name": "Yueqing",
    "gn:population": 0,
    "gn:timezone": "Asia/Urumqi",
    "iso:country": "CN",
    "name:deu_x_preferred": [
      "Yueqing"
    ],
    "name:fra_x_preferred": [
      "Yueqing"
    ],
    "name:hak_x_preferred": [
      "Ngo̍k-chhîn-sṳ"
    ],
    "name:ita_x_preferred": [
      "Yueqing"
    ],
    "name:jpn_x_preferred": [
      "楽清市"
    ],
    "name:kik_x_preferred": [
      "Yueqing"
    ],
    "name:kor_x_preferred": [
      "웨칭시"
    ],
    "name:mlg_x_preferred": [
      "Yueqing"
    ],
    "name:nld_x_preferred": [
      "Yueqing"
    ],
    "name:nor_x_preferred": [
      "Yueqing"
    ],
    "name:swe_x_preferred": [
      "Yueqing"
    ],
    "name:tgl_x_preferred": [
      "Yueqing"
    ],
    "name:tur_x_preferred": [
      "Yueqing"
    ],
    "name:urd_x_preferred": [
      "یوئچنگ"
    ],
    "name:vie_x_preferred": [
      "Nhạc Thanh"
    ],
    "name:war_x_preferred": [
      "Yueqing"
    ],
    "name:wuu_x_preferred": [
      "乐清市"
    ],
    "name:zho_x_preferred": [
      "越青"
    ],
    "name:zho_x_variant": [
      "乐清市"
    ],
    "wof:name": "Yueqing",
    "wof:placetype": "locality"
  },
  "geometry": {
    "coordinates": [
      85.1325,
      28.8303
    ],
    "type": "Point"
  }
}