{
  "type": "Feature",
  "properties": {
    "gn:admin1_code": "32.0",
    "gn:asciiname": "Yangang",
    "gn:country_code": "CN",
    "gn:dem": 656,
    "gn:feature_class": "P",
    "gn:feature_code": "PPL",
    "gn:name": "Yangang",
    "gn:population": 0,
    "gn:timezone": "Asia/Shanghai",
    "iso:country": "CN",
    "name:ukr_x_preferred": [
      "Янґанґ"
    ],
    "name:urd_x_preferred": [
      "یانگ گانگ"
    ],
    "name:zho_x_preferred": [
      "烟岗"
    ],
    "wof:name": "Yangang",
    "wof:placetype": "locality"
  },
  "geometry": {
    "coordinates": [
      103.375,
      30.0203
    ],
    "type": "Point"
  }
}