{
  "type": "Feature",
  "properties": {
    "gn:admin1_code": "3.0",
    "gn:asciiname": "Daba",
    "gn:country_code": "CN",
    "gn:dem": 445,
    "gn:feature_class": "P",
    "gn:feature_code": "PPL",
    "gn:name": "Daba",
    "gn:population": 0,
    "gn:timezone": "Asia/Shanghai",
    "iso:country": "CN",
    "name:ceb_x_preferred": [
      "Daba"
    ],
    "name:fra_x_preferred": [
      "Daba"
    ],
    "name:kat_x_preferred": [
      "დაბა"
    ],
    "name:rus_x_preferred": [
      "Даба"
    ],
    "name:swe_x_preferred": [
      "Daba"
    ],
    "name:zho_x_preferred": [
      "大坝"
    ],
    "wof:name": "Daba",
    "wof:placetype": "locality"
  },
  "geometry": {
    "coordinates": [
      115.466,
      25.082
    ],
    "type": "Point"
  }
}