{
  "type": "Feature",
  "properties": {
    "gn:admin1_code": "32.0",
    "gn:asciiname": "Wenchang",
    "gn:country_code": "CN",
    "gn:dem": 666,
    "gn:feature_class": "P",
    "gn:feature_code": "PPL",
    "gn:name": "Wenchang",
    "gn:population": 0,
    "gn:timezone": "Asia/Shanghai",
    "iso:country": "CN",
    "name:ara_x_preferred": [
      "وينشانغ"
    ],
    "name:ceb_x_preferred": [
      "Wenchang Shi"
    ],
    "name:dan_x_preferred": [
      "Wenchang"
    ],
    "name:deu_x_preferred": [
      "Wenchang"
    ],
    "name:eus_x_preferred": [
      "Wenchang"
    ],
    "name:fin_x_preferred": [
      "Wenchang"
    ],
    "name:fra_x_preferred": [
      "Wenchang"
    ],
    "name:ita_x_preferred": [
      "Wenchang"
    ],
    "name:jpn_x_preferred": [
      "文昌市"
    ],
    "name:kaz_x_preferred": [
      "Вэньчан"
    ],
    "name:kik_x_preferred": [
      "Wenchang"
    ],
    "name:kor_x_preferred": [
      "원창시"
    ],
    "name:mlg_x_preferred": [
      "Wenchang"
    ],
    "name:nld_x_preferred": [
      "Wenchang"
    ],
    "name:nor_x_preferred": [
      "Wenchang"
    ],
    "name:pam_x_preferred": [
      "Wenchang"
    ],
    "name:pol_x_preferred": [
      "Wenchang"
    ],
    "name:rus_x_preferred": [
      "Вэньчан"
    ],
    "name:spa_x_preferred": [
      "Wenchang"
    ],
    "name:swe_x_preferred": [
      "Wenchang"
    ],
    "name:tur_x_preferred": [
      "Wenchang"
    ],
    "name:und_x_variant": [
      "文昌"
    ],
    "name:urd_x_preferred": [
      "وینچانگ"
    ],
    "name:vie_x_preferred": [
      "Văn Xương"
    ],
    "name:zho_x_preferred": [
      "文昌市"
    ],
    "wof:name": "Wenchang",
    "wof:placetype": "locality"
  },
  "geometry": {
    "coordinates": [
      106.73971,
      32.10361
    ],
    "type": "Point"
  }
}