{
  "type": "Feature",
  "properties": {
    "gn:admin1_code": "12.0",
    "gn:asciiname": "Yanglinqiao",
    "gn:country_code": "CN",
    "gn:dem": 385,
    "gn:feature_class": "P",
    "gn:feature_code": "PPLA4",
    "gn:name": "Yanglinqiao",
    "gn:population": 0,
    "gn:timezone": "Asia/Shanghai",
    "iso:country": "CN",
    "name:und_x_variant": [
      "Yanglinqiao Zhen"
    ],
    "name:zho_x_preferred": [
      "杨林桥"
    ],
    "name:zho_x_variant": [
      "杨林桥镇"
    ],
    "wof:name": "Yanglinqiao",
    "wof:placetype": "locality"
  },
  "geometry": {
    "coordinates": [
      110.75912,
      30.74911
    ],
    "type": "Point"
  }
}