{
  "type": "Feature",
  "properties": {
    "gn:admin1_code": "19.0",
    "gn:asciiname": "Liujia Buzi",
    "gn:country_code": "CN",
    "gn:dem": 270,
    "gn:feature_class": "P",
    "gn:feature_code": "PPL",
    "gn:name": "Liujia Buzi",
    "gn:population": 0,
    "gn:timezone": "Asia/Shanghai",
    "iso:country": "CN",
    "name:und_x_variant": [
      "Liujia Puzi",
      "Liujia Buzi"
    ],
    "name:zho_x_preferred": [
      "刘家堡子"
    ],
    "wof:name": "Liujia Buzi",
    "wof:placetype": "locality"
  },
  "geometry": {
    "coordinates": [
      122.40087,
      40.12001
    ],
    "type": "Point"
  }
}