{
  "type": "Feature",
  "properties": {
    "gn:admin1_code": "14.0",
    "gn:asciiname": "Puqiong",
    "gn:country_code": "CN",
    "gn:dem": 4601,
    "gn:feature_class": "P",
    "gn:feature_code": "PPL",
    "gn:name": "Puqiong",
    "gn:population": 0,
    "gn:timezone": "Asia/Urumqi",
    "iso:country": "CN",
    "name:und_x_variant": [
      "Puqiongcun"
    ],
    "name:zho_x_preferred": [
      "普穷"
    ],
    "name:zho_x_variant": [
      "普琼",
      "普琼村"
    ],
    "wof:name": "Puqiong",
    "wof:placetype": "locality"
  },
  "geometry": {
    "coordinates": [
      83.1329,
      30.116
    ],
    "type": "Point"
  }
}