{
  "type": "Feature",
  "properties": {
    "gn:admin1_code": "24.0",
    "gn:asciiname": "Shaling",
    "gn:country_code": "CN",
    "gn:dem": 975,
    "gn:feature_class": "P",
    "gn:feature_code": "PPL",
    "gn:name": "Shaling",
    "gn:population": 0,
    "gn:timezone": "Asia/Shanghai",
    "iso:country": "CN",
    "name:zho_x_preferred": [
      "沙岭"
    ],
    "wof:name": "Shaling",
    "wof:placetype": "locality"
  },
  "geometry": {
    "coordinates": [
      113.52698,
      39.88858
    ],
    "type": "Point"
  }
}