{
  "type": "Feature",
  "properties": {
    "gn:admin1_code": "16",
    "gn:asciiname": "Huangling'an",
    "gn:country_code": "CN",
    "gn:dem": 844,
    "gn:feature_class": "P",
    "gn:feature_code": "PPL",
    "gn:name": "Huangling’an",
    "gn:population": 0,
    "gn:timezone": "Asia/Shanghai",
    "iso:country": "CN",
    "name:und_x_variant": [
      "Huangling’an"
    ],
    "name:zho_x_preferred": [
      "黄岭庵"
    ],
    "wof:name": "Huangling'an",
    "wof:placetype": "locality"
  },
  "geometry": {
    "coordinates": [
      110.795,
      26.0289
    ],
    "type": "Point"
  }
}