{
  "type": "Feature",
  "properties": {
    "gn:country": "CN",
    "gn:fcode": "PPL",
    "gn:population": 108883,
    "iso:country": "CN",
    "name:ben_x_preferred": [
      "ঝংজিয়াং শহর"
    ],
    "name:ceb_x_preferred": [
      "Zhongxiang"
    ],
    "name:ces_x_preferred": [
      "Čung-siang"
    ],
    "name:dan_x_preferred": [
      "Zhongxiang"
    ],
    "name:deu_x_preferred": [
      "Zhongxiang"
    ],
    "name:ell_x_preferred": [
      "Τσονγκσιάνγκ"
    ],
    "name:eng_x_historical": [
      "Anlu"
    ],
    "name:eng_x_preferred": [
      "Anlu"
    ],
    "name:eng_x_variant": [
      "Zhongxiang City"
    ],
    "name:epo_x_preferred": [
      "Zhongxiang"
    ],
    "name:fin_x_preferred": [
      "Zhongxiang City"
    ],
    "name:fra_x_preferred": [
      "Zhongxiang"
    ],
    "name:gan_x_preferred": [
      "钟祥市"
    ],
    "name:guj_x_preferred": [
      "ઝોંગસિઆંગ શહેર"
    ],
    "name:hin_x_preferred": [
      "ज़्होंगसिआंग सिटी"
    ],
    "name:ind_x_preferred": [
      "Zhongxiang City"
    ],
    "name:ita_x_preferred": [
      "Zhongxiang"
    ],
    "name:jpn_x_preferred": [
      "鍾祥市"
    ],
    "name:kan_x_preferred": [
      "ಝೋಂಗ್ಕ್ಸಿಯಾಂಗ್ ನಗರ"
    ],
    "name:kik_x_preferred": [
      "Zhongxiang"
    ],
    "name:kor_x_preferred": [
      "중샹시"
    ],
    "name:lav_x_preferred": [
      "Žongsiango"
    ],
    "name:lit_x_preferred": [
      "Džongsiango miestas"
    ],
    "name:mar_x_preferred": [
      "झॊन्गसीआंग शहर"
    ],
    "name:mlg_x_preferred": [
      "Zhongxiang"
    ],
    "name:msa_x_preferred": [
      "Zhongxiang City"
    ],
    "name:nan_x_preferred": [
      "Cheng-siông-chhī"
    ],
    "name:nld_x_preferred": [
      "Zhongxiang"
    ],
    "name:nob_x_preferred": [
      "Zhongxiang"
    ],
    "name:pam_x_preferred": [
      "Zhongxiang"
    ],
    "name:pol_x_preferred": [
      "Zhongxiang"
    ],
    "name:por_x_preferred": [
      "Zhongxiang"
    ],
    "name:rus_x_preferred": [
      "Чжунсян"
    ],
    "name:sin_x_preferred": [
      "සොන්ක්සියැන් නගරය"
    ],
    "name:spa_x_preferred": [
      "Zhongxiang"
    ],
    "name:swe_x_preferred": [
      "Zhongxiang"
    ],
    "name:tha_x_preferred": [
      "จงเซียง ซิตี้"
    ],
    "name:tur_x_preferred": [
      "Zhongxiang City"
    ],
    "name:ukr_x_preferred": [
      "Чжунсян"
    ],
    "name:und_x_variant": [
      "Anlufu"
    ],
    "name:urd_x_preferred": [
      "زحونجزیانج شہر"
    ],
    "name:vie_x_preferred": [
      "Chung Tường"
    ],
    "name:wuu_x_preferred": [
      "钟祥市"
    ],
    "name:yue_x_preferred": [
      "鍾祥"
    ],
    "name:zho_x_preferred": [
      "钟祥市"
    ],
    "qs:name": "Zhongxiang",
    "qs:photos_9r": 0,
    "qs:photos_sr": 0,
    "qs:pop_sr": "9",
    "wd:wordcount": 1133,
    "wof:name": "Zhongxiang",
    "wof:placetype": "locality",
    "wof:population": 108883
  },
  "geometry": {
    "coordinates": [
      112.58306,
      31.16611
    ],
    "type": "Point"
  }
}