{
  "type": "Feature",
  "properties": {
    "gn:admin1_code": "26.0",
    "gn:asciiname": "Lujiashancun",
    "gn:country_code": "CN",
    "gn:dem": 1039,
    "gn:feature_class": "P",
    "gn:feature_code": "PPL",
    "gn:name": "Lüjiashancun",
    "gn:population": 0,
    "gn:timezone": "Asia/Shanghai",
    "iso:country": "CN",
    "name:und_x_variant": [
      "Lüjiashancun"
    ],
    "name:zho_x_preferred": [
      "吕家山村"
    ],
    "wof:name": "Lujiashancun",
    "wof:placetype": "locality"
  },
  "geometry": {
    "coordinates": [
      109.66174,
      35.43808
    ],
    "type": "Point"
  }
}