{
  "type": "Feature",
  "properties": {
    "gn:admin1_code": "19.0",
    "gn:asciiname": "Hujialing",
    "gn:country_code": "CN",
    "gn:dem": 400,
    "gn:feature_class": "P",
    "gn:feature_code": "PPL",
    "gn:name": "Hujialing",
    "gn:population": 0,
    "gn:timezone": "Asia/Shanghai",
    "iso:country": "CN",
    "name:zho_x_preferred": [
      "胡家岭"
    ],
    "wof:name": "Hujialing",
    "wof:placetype": "locality"
  },
  "geometry": {
    "coordinates": [
      121.768,
      41.9362
    ],
    "type": "Point"
  }
}