{
  "type": "Feature",
  "properties": {
    "gn:admin1_code": "16.0",
    "gn:asciiname": "Bandong",
    "gn:country_code": "CN",
    "gn:dem": 38,
    "gn:feature_class": "P",
    "gn:feature_code": "PPL",
    "gn:name": "Bandong",
    "gn:population": 0,
    "gn:timezone": "Asia/Shanghai",
    "iso:country": "CN",
    "name:zho_x_preferred": [
      "湴垌"
    ],
    "wof:name": "Bandong",
    "wof:placetype": "locality"
  },
  "geometry": {
    "coordinates": [
      110.433,
      23.3719
    ],
    "type": "Point"
  }
}