{
  "type": "Feature",
  "properties": {
    "gn:admin1_code": "26.0",
    "gn:asciiname": "Beigoucun",
    "gn:country_code": "CN",
    "gn:dem": 973,
    "gn:feature_class": "P",
    "gn:feature_code": "PPL",
    "gn:name": "Beigoucun",
    "gn:population": 0,
    "gn:timezone": "Asia/Shanghai",
    "iso:country": "CN",
    "name:zho_x_preferred": [
      "背沟村"
    ],
    "wof:name": "Beigoucun",
    "wof:placetype": "locality"
  },
  "geometry": {
    "coordinates": [
      110.56654,
      37.81476
    ],
    "type": "Point"
  }
}