{
  "type": "Feature",
  "properties": {
    "gn:admin1_code": "10",
    "gn:asciiname": "Baicheng",
    "gn:country_code": "CN",
    "gn:dem": 28,
    "gn:feature_class": "P",
    "gn:feature_code": "PPL",
    "gn:name": "Baicheng",
    "gn:population": 0,
    "gn:timezone": "Asia/Shanghai",
    "iso:country": "CN",
    "name:ara_x_preferred": [
      "بايتشنغ"
    ],
    "name:bak_x_preferred": [
      "Байчэн"
    ],
    "name:cdo_x_preferred": [
      "Băh-siàng"
    ],
    "name:ceb_x_preferred": [
      "Baicheng"
    ],
    "name:ces_x_preferred": [
      "Paj-čcheng"
    ],
    "name:dan_x_preferred": [
      "Baicheng"
    ],
    "name:deu_x_preferred": [
      "Baicheng"
    ],
    "name:eus_x_preferred": [
      "Baicheng"
    ],
    "name:fas_x_preferred": [
      "بایچنگ"
    ],
    "name:fin_x_preferred": [
      "Baicheng"
    ],
    "name:fra_x_preferred": [
      "Baicheng"
    ],
    "name:heb_x_preferred": [
      "באיצ'נג"
    ],
    "name:hun_x_preferred": [
      "Baicheng"
    ],
    "name:ind_x_preferred": [
      "Baicheng"
    ],
    "name:ita_x_preferred": [
      "Baicheng"
    ],
    "name:jpn_x_preferred": [
      "白城市"
    ],
    "name:kik_x_preferred": [
      "Baicheng"
    ],
    "name:kor_x_preferred": [
      "바이청시"
    ],
    "name:lit_x_preferred": [
      "Baičengas"
    ],
    "name:mlg_x_preferred": [
      "Baicheng"
    ],
    "name:nld_x_preferred": [
      "Baicheng"
    ],
    "name:nno_x_preferred": [
      "Baicheng"
    ],
    "name:nor_x_preferred": [
      "Baicheng"
    ],
    "name:pol_x_preferred": [
      "Baicheng"
    ],
    "name:por_x_preferred": [
      "Baicheng"
    ],
    "name:rus_x_preferred": [
      "Байчэн"
    ],
    "name:spa_x_preferred": [
      "Baicheng"
    ],
    "name:srp_x_preferred": [
      "Бајченг"
    ],
    "name:swe_x_preferred": [
      "Baicheng"
    ],
    "name:tur_x_preferred": [
      "Baicheng"
    ],
    "name:urd_x_preferred": [
      "بائچینگ"
    ],
    "name:vie_x_preferred": [
      "Bạch Thành"
    ],
    "name:war_x_preferred": [
      "Baicheng"
    ],
    "name:wuu_x_preferred": [
      "白城市"
    ],
    "name:zho_x_preferred": [
      "白城"
    ],
    "name:zho_x_variant": [
      "白城市"
    ],
    "wof:name": "Baicheng",
    "wof:placetype": "locality"
  },
  "geometry": {
    "coordinates": [
      115.386,
      38.7279
    ],
    "type": "Point"
  }
}