{
  "type": "Feature",
  "properties": {
    "gn:admin1_code": "14.0",
    "gn:asciiname": "Ga'erdong",
    "gn:country_code": "CN",
    "gn:dem": 4190,
    "gn:feature_class": "P",
    "gn:feature_code": "PPL",
    "gn:name": "Ga’erdong",
    "gn:population": 0,
    "gn:timezone": "Asia/Shanghai",
    "iso:country": "CN",
    "name:und_x_variant": [
      "Ga’erdong"
    ],
    "name:zho_x_preferred": [
      "嘎尔东"
    ],
    "wof:name": "Ga'erdong",
    "wof:placetype": "locality"
  },
  "geometry": {
    "coordinates": [
      81.0996,
      30.5009
    ],
    "type": "Point"
  }
}