{
  "type": "Feature",
  "properties": {
    "gn:admin1_code": "12.0",
    "gn:asciiname": "Neijing",
    "gn:country_code": "CN",
    "gn:dem": 22,
    "gn:feature_class": "P",
    "gn:feature_code": "PPL",
    "gn:name": "Neijing",
    "gn:population": 0,
    "gn:timezone": "Asia/Shanghai",
    "iso:country": "CN",
    "name:bul_x_preferred": [
      "Ней-Дзя"
    ],
    "name:zho_x_preferred": [
      "内荆"
    ],
    "wof:name": "Neijing",
    "wof:placetype": "locality"
  },
  "geometry": {
    "coordinates": [
      113.84026,
      30.24453
    ],
    "type": "Point"
  }
}