{
  "type": "Feature",
  "properties": {
    "gn:admin1_code": "13",
    "gn:asciiname": "Gongqingtuan Nongchang Jiudui",
    "gn:country_code": "CN",
    "gn:dem": 451,
    "gn:feature_class": "P",
    "gn:feature_code": "PPLF",
    "gn:name": "Gongqingtuan Nongchang Jiudui",
    "gn:population": 0,
    "gn:timezone": "Asia/Urumqi",
    "iso:country": "CN",
    "name:zho_x_preferred": [
      "共青团农场九队"
    ],
    "wof:name": "Gongqingtuan Nongchang Jiudui",
    "wof:placetype": "locality"
  },
  "geometry": {
    "coordinates": [
      87.41505,
      44.33264000000001
    ],
    "type": "Point"
  }
}