{
  "type": "Feature",
  "properties": {
    "gn:admin1_code": "30",
    "gn:asciiname": "Magong",
    "gn:country_code": "CN",
    "gn:dem": 7,
    "gn:feature_class": "P",
    "gn:feature_code": "PPLA4",
    "gn:name": "Magong",
    "gn:population": 0,
    "gn:timezone": "Asia/Shanghai",
    "iso:country": "CN",
    "name:ara_x_preferred": [
      "ماغونغ"
    ],
    "name:ben_x_preferred": [
      "ম্যাগং"
    ],
    "name:ces_x_preferred": [
      "Ma-kung"
    ],
    "name:deu_x_preferred": [
      "Magong"
    ],
    "name:ell_x_preferred": [
      "Μαγκόνγκ"
    ],
    "name:fas_x_preferred": [
      "ماگونگ"
    ],
    "name:fra_x_preferred": [
      "Magong"
    ],
    "name:hak_x_preferred": [
      "Mâ-kûng-sṳ"
    ],
    "name:hin_x_preferred": [
      "मैगोंग"
    ],
    "name:hun_x_preferred": [
      "Makung"
    ],
    "name:ind_x_preferred": [
      "Magong"
    ],
    "name:ita_x_preferred": [
      "Magong"
    ],
    "name:jpn_x_preferred": [
      "馬公市"
    ],
    "name:kor_x_preferred": [
      "마궁시"
    ],
    "name:lit_x_preferred": [
      "Magongas"
    ],
    "name:nld_x_preferred": [
      "Magong"
    ],
    "name:pol_x_preferred": [
      "Magong"
    ],
    "name:por_x_preferred": [
      "Magong"
    ],
    "name:rus_x_preferred": [
      "Магун"
    ],
    "name:swe_x_preferred": [
      "Magong"
    ],
    "name:tur_x_preferred": [
      "Magong"
    ],
    "name:ukr_x_preferred": [
      "Магонг"
    ],
    "name:und_x_variant": [
      "Ma-tsung"
    ],
    "name:urd_x_preferred": [
      "میگانگ"
    ],
    "name:vie_x_preferred": [
      "Mã Công"
    ],
    "name:zho_x_preferred": [
      "马宫"
    ],
    "name:zho_x_variant": [
      "馬公市"
    ],
    "wof:name": "Magong",
    "wof:placetype": "locality"
  },
  "geometry": {
    "coordinates": [
      115.23853,
      22.79019
    ],
    "type": "Point"
  }
}