{
  "type": "Feature",
  "properties": {
    "gn:admin1_code": "26.0",
    "gn:asciiname": "Licha",
    "gn:country_code": "CN",
    "gn:dem": 1152,
    "gn:feature_class": "P",
    "gn:feature_code": "PPL",
    "gn:name": "Licha",
    "gn:population": 0,
    "gn:timezone": "Asia/Shanghai",
    "iso:country": "CN",
    "name:ceb_x_preferred": [
      "Licha"
    ],
    "name:swe_x_preferred": [
      "Licha"
    ],
    "name:vie_x_preferred": [
      "Licha"
    ],
    "name:war_x_preferred": [
      "Licha"
    ],
    "name:zho_x_preferred": [
      "李岔"
    ],
    "wof:name": "Licha",
    "wof:placetype": "locality"
  },
  "geometry": {
    "coordinates": [
      110.80393,
      39.01732
    ],
    "type": "Point"
  }
}