{
  "type": "Feature",
  "properties": {
    "gn:admin1_code": "3.0",
    "gn:asciiname": "Dongkeng",
    "gn:country_code": "CN",
    "gn:dem": 129,
    "gn:feature_class": "P",
    "gn:feature_code": "PPL",
    "gn:name": "Dongkeng",
    "gn:population": 0,
    "gn:timezone": "Asia/Shanghai",
    "iso:country": "CN",
    "name:fas_x_preferred": [
      "دونگکنگ"
    ],
    "name:sco_x_preferred": [
      "Dongkeng"
    ],
    "name:und_x_variant": [
      "东坑"
    ],
    "name:zho_x_preferred": [
      "东坑镇"
    ],
    "wof:name": "Dongkeng",
    "wof:placetype": "locality"
  },
  "geometry": {
    "coordinates": [
      115.46968,
      26.03147
    ],
    "type": "Point"
  }
}