{
  "type": "Feature",
  "properties": {
    "gn:admin1_code": "07",
    "gn:asciiname": "Zhongqiu",
    "gn:country_code": "CN",
    "gn:dem": 813,
    "gn:feature_class": "P",
    "gn:feature_code": "PPL",
    "gn:name": "Zhongqiu",
    "gn:population": 0,
    "gn:timezone": "Asia/Shanghai",
    "iso:country": "CN",
    "name:und_x_variant": [
      "中秋",
      "Zhongqiu"
    ],
    "wof:name": "Zhongqiu",
    "wof:placetype": "locality"
  },
  "geometry": {
    "coordinates": [
      118.72799,
      26.91436
    ],
    "type": "Point"
  }
}