{
  "type": "Feature",
  "properties": {
    "gn:admin1_code": "26.0",
    "gn:asciiname": "Dacaotan",
    "gn:country_code": "CN",
    "gn:dem": 1155,
    "gn:feature_class": "P",
    "gn:feature_code": "PPL",
    "gn:name": "Dacaotan",
    "gn:population": 0,
    "gn:timezone": "Asia/Shanghai",
    "iso:country": "CN",
    "name:zho_x_preferred": [
      "大草滩"
    ],
    "wof:name": "Dacaotan",
    "wof:placetype": "locality"
  },
  "geometry": {
    "coordinates": [
      109.79668999999998,
      36.85408
    ],
    "type": "Point"
  }
}