{
  "type": "Feature",
  "properties": {
    "gn:admin1_code": "12.0",
    "gn:asciiname": "Chenjia'ao",
    "gn:country_code": "CN",
    "gn:dem": 29,
    "gn:feature_class": "P",
    "gn:feature_code": "PPL",
    "gn:name": "Chenjia’ao",
    "gn:population": 0,
    "gn:timezone": "Asia/Shanghai",
    "iso:country": "CN",
    "name:zho_x_preferred": [
      "Chenjia’ao"
    ],
    "name:zho_x_variant": [
      "陈家坳"
    ],
    "wof:name": "Chenjia'ao",
    "wof:placetype": "locality"
  },
  "geometry": {
    "coordinates": [
      115.1088,
      30.37718
    ],
    "type": "Point"
  }
}