{
  "type": "Feature",
  "properties": {
    "gn:admin1_code": "18",
    "gn:asciiname": "Gebang",
    "gn:country_code": "CN",
    "gn:dem": 1421,
    "gn:feature_class": "P",
    "gn:feature_code": "PPL",
    "gn:name": "Gebang",
    "gn:population": 0,
    "gn:timezone": "Asia/Shanghai",
    "iso:country": "CN",
    "name:bih_x_preferred": [
      "गेबांग"
    ],
    "name:ind_x_preferred": [
      "Candi Gebang"
    ],
    "name:jav_x_preferred": [
      "Candhi Gebang"
    ],
    "name:tat_x_preferred": [
      "Гебанг"
    ],
    "name:zho_x_preferred": [
      "革帮"
    ],
    "wof:name": "Gebang",
    "wof:placetype": "locality"
  },
  "geometry": {
    "coordinates": [
      105.943,
      25.9978
    ],
    "type": "Point"
  }
}