{
  "type": "Feature",
  "properties": {
    "gn:admin1_code": "26.0",
    "gn:asciiname": "Tuojiamaozi",
    "gn:country_code": "CN",
    "gn:dem": 1215,
    "gn:feature_class": "P",
    "gn:feature_code": "PPL",
    "gn:name": "Tuojiamaozi",
    "gn:population": 0,
    "gn:timezone": "Asia/Shanghai",
    "iso:country": "CN",
    "name:zho_x_preferred": [
      "拓家峁子"
    ],
    "wof:name": "Tuojiamaozi",
    "wof:placetype": "locality"
  },
  "geometry": {
    "coordinates": [
      109.31261,
      36.99455
    ],
    "type": "Point"
  }
}