{
  "type": "Feature",
  "properties": {
    "gn:admin1_code": "8.0",
    "gn:asciiname": "Shuanghe",
    "gn:country_code": "CN",
    "gn:dem": 226,
    "gn:feature_class": "P",
    "gn:feature_code": "PPL",
    "gn:name": "Shuanghe",
    "gn:population": 0,
    "gn:timezone": "Asia/Shanghai",
    "iso:country": "CN",
    "name:cdo_x_preferred": [
      "Sĕ̤ng-ò̤"
    ],
    "name:deu_x_preferred": [
      "Shuanghe"
    ],
    "name:ell_x_preferred": [
      "Σουανγκχέ"
    ],
    "name:ita_x_preferred": [
      "Shuanghe"
    ],
    "name:jpn_x_preferred": [
      "双河市"
    ],
    "name:kik_x_preferred": [
      "Shuanghe"
    ],
    "name:kor_x_preferred": [
      "솽허시"
    ],
    "name:rus_x_preferred": [
      "Шуанхэ"
    ],
    "name:tur_x_preferred": [
      "Koşöküz"
    ],
    "name:uig_x_preferred": [
      "قوشئۆگۈز شەھىرى"
    ],
    "name:urd_x_preferred": [
      "شوانگہے"
    ],
    "name:vie_x_preferred": [
      "Song Hà"
    ],
    "name:zho_x_preferred": [
      "双合"
    ],
    "name:zho_x_variant": [
      "雙河市"
    ],
    "wof:name": "Shuanghe",
    "wof:placetype": "locality"
  },
  "geometry": {
    "coordinates": [
      125.89021,
      47.1361
    ],
    "type": "Point"
  }
}