{
  "type": "Feature",
  "properties": {
    "gn:admin1_code": "4.0",
    "gn:asciiname": "Wangxing",
    "gn:country_code": "CN",
    "gn:dem": 23,
    "gn:feature_class": "P",
    "gn:feature_code": "PPL",
    "gn:name": "Wangxing",
    "gn:population": 0,
    "gn:timezone": "Asia/Shanghai",
    "iso:country": "CN",
    "name:zho_x_preferred": [
      "王行"
    ],
    "wof:name": "Wangxing",
    "wof:placetype": "locality"
  },
  "geometry": {
    "coordinates": [
      117.913,
      34.0272
    ],
    "type": "Point"
  }
}