{
  "type": "Feature",
  "properties": {
    "gn:admin1_code": "30",
    "gn:asciiname": "Dahetang",
    "gn:country_code": "CN",
    "gn:dem": 58,
    "gn:feature_class": "P",
    "gn:feature_code": "PPL",
    "gn:name": "Dahetang",
    "gn:population": 0,
    "gn:timezone": "Asia/Urumqi",
    "iso:country": "CN",
    "name:zho_x_preferred": [
      "大禾塘"
    ],
    "name:zho_x_variant": [
      "大禾塘街道"
    ],
    "wof:name": "Dahetang",
    "wof:placetype": "locality"
  },
  "geometry": {
    "coordinates": [
      110.41568,
      21.89895
    ],
    "type": "Point"
  }
}