{
  "type": "Feature",
  "properties": {
    "gn:admin1_code": "25",
    "gn:asciiname": "Dongba",
    "gn:country_code": "CN",
    "gn:dem": 8,
    "gn:feature_class": "P",
    "gn:feature_code": "PPL",
    "gn:name": "Dongba",
    "gn:population": 0,
    "gn:timezone": "Asia/Shanghai",
    "iso:country": "CN",
    "name:deu_x_preferred": [
      "Dongba"
    ],
    "name:fra_x_preferred": [
      "Dongba"
    ],
    "name:ita_x_preferred": [
      "Dongba"
    ],
    "name:pol_x_preferred": [
      "Dongba"
    ],
    "name:por_x_preferred": [
      "Dongba"
    ],
    "name:tha_x_preferred": [
      "ลัทธิตงปา"
    ],
    "name:vie_x_preferred": [
      "Dongba"
    ],
    "name:zho_x_preferred": [
      "东坝"
    ],
    "name:zho_x_variant": [
      "東巴教"
    ],
    "wof:name": "Dongba",
    "wof:placetype": "locality"
  },
  "geometry": {
    "coordinates": [
      118.442,
      37.6382
    ],
    "type": "Point"
  }
}