{
  "type": "Feature",
  "properties": {
    "gn:admin1_code": "16",
    "gn:asciiname": "Yatoushui",
    "gn:country_code": "CN",
    "gn:dem": 886,
    "gn:feature_class": "P",
    "gn:feature_code": "PPL",
    "gn:name": "Yatoushui",
    "gn:population": 0,
    "gn:timezone": "Asia/Shanghai",
    "iso:country": "CN",
    "name:zho_x_preferred": [
      "鸭头水"
    ],
    "wof:name": "Yatoushui",
    "wof:placetype": "locality"
  },
  "geometry": {
    "coordinates": [
      110.528,
      26.099
    ],
    "type": "Point"
  }
}