{
  "type": "Feature",
  "properties": {
    "gn:admin1_code": "10.0",
    "gn:asciiname": "Xiaotun",
    "gn:country_code": "CN",
    "gn:dem": 17,
    "gn:feature_class": "P",
    "gn:feature_code": "PPL",
    "gn:name": "Xiaotun",
    "gn:population": 0,
    "gn:timezone": "Asia/Shanghai",
    "iso:country": "CN",
    "name:zho_x_preferred": [
      "小屯"
    ],
    "wof:name": "Xiaotun",
    "wof:placetype": "locality"
  },
  "geometry": {
    "coordinates": [
      116.193,
      38.1943
    ],
    "type": "Point"
  }
}