{
  "type": "Feature",
  "properties": {
    "gn:admin1_code": "10",
    "gn:asciiname": "Xinji",
    "gn:country_code": "CN",
    "gn:dem": 33,
    "gn:feature_class": "P",
    "gn:feature_code": "PPL",
    "gn:name": "Xinji",
    "gn:population": 0,
    "gn:timezone": "Asia/Shanghai",
    "iso:country": "CN",
    "name:ara_x_preferred": [
      "شينجي"
    ],
    "name:deu_x_preferred": [
      "Xinji"
    ],
    "name:eus_x_preferred": [
      "Xinji"
    ],
    "name:fra_x_preferred": [
      "Xinji"
    ],
    "name:ita_x_preferred": [
      "Xinji"
    ],
    "name:jpn_x_preferred": [
      "辛集市"
    ],
    "name:kik_x_preferred": [
      "Xinji"
    ],
    "name:kor_x_preferred": [
      "신지시"
    ],
    "name:mlg_x_preferred": [
      "Xinji"
    ],
    "name:nor_x_preferred": [
      "Xinji"
    ],
    "name:pam_x_preferred": [
      "Xinji"
    ],
    "name:rus_x_preferred": [
      "Синьцзи"
    ],
    "name:sco_x_preferred": [
      "Xinji"
    ],
    "name:swe_x_preferred": [
      "Xinji"
    ],
    "name:urd_x_preferred": [
      "شنجی"
    ],
    "name:vie_x_preferred": [
      "Tân Tập"
    ],
    "name:war_x_preferred": [
      "Xinji"
    ],
    "name:zho_x_preferred": [
      "辛集"
    ],
    "name:zho_x_variant": [
      "辛集市"
    ],
    "wof:name": "Xinji",
    "wof:placetype": "locality"
  },
  "geometry": {
    "coordinates": [
      115.68122,
      36.96577
    ],
    "type": "Point"
  }
}