{
  "type": "Feature",
  "properties": {
    "gn:admin1_code": "25.0",
    "gn:asciiname": "Beifengjia",
    "gn:country_code": "CN",
    "gn:dem": 43,
    "gn:feature_class": "P",
    "gn:feature_code": "PPL",
    "gn:name": "Beifengjia",
    "gn:population": 0,
    "gn:timezone": "Asia/Shanghai",
    "iso:country": "CN",
    "name:zho_x_preferred": [
      "北冯家"
    ],
    "wof:name": "Beifengjia",
    "wof:placetype": "locality"
  },
  "geometry": {
    "coordinates": [
      119.26601,
      36.71808
    ],
    "type": "Point"
  }
}