{
  "type": "Feature",
  "properties": {
    "gn:admin1_code": "26",
    "gn:asciiname": "Donggoujiecun",
    "gn:country_code": "CN",
    "gn:dem": 410,
    "gn:feature_class": "P",
    "gn:feature_code": "PPL",
    "gn:name": "Donggoujiecun",
    "gn:population": 0,
    "gn:timezone": "Asia/Shanghai",
    "iso:country": "CN",
    "name:und_x_variant": [
      "Donggoujie",
      "Tung-kou-k’ou",
      "Tung-kou",
      "Donggou",
      "Donggoujiecun"
    ],
    "name:zho_x_preferred": [
      "洞沟街村"
    ],
    "wof:name": "Donggoujiecun",
    "wof:placetype": "locality"
  },
  "geometry": {
    "coordinates": [
      109.8361,
      33.30922
    ],
    "type": "Point"
  }
}