{
  "type": "Feature",
  "properties": {
    "gn:admin1_code": "25.0",
    "gn:asciiname": "Nanzhao",
    "gn:country_code": "CN",
    "gn:dem": 114,
    "gn:feature_class": "P",
    "gn:feature_code": "PPL",
    "gn:name": "Nanzhao",
    "gn:population": 0,
    "gn:timezone": "Asia/Shanghai",
    "iso:country": "CN",
    "name:ben_x_preferred": [
      "নানঝাও রাজ্য"
    ],
    "name:bul_x_preferred": [
      "Нанджао"
    ],
    "name:cat_x_preferred": [
      "Nan Chao"
    ],
    "name:deu_x_preferred": [
      "Nanzhao"
    ],
    "name:epo_x_preferred": [
      "Nanchao"
    ],
    "name:hin_x_preferred": [
      "नानझाओ राज्य"
    ],
    "name:kat_x_preferred": [
      "ნანჯაო"
    ],
    "name:kor_x_preferred": [
      "남조"
    ],
    "name:lat_x_preferred": [
      "Nanzhao"
    ],
    "name:lit_x_preferred": [
      "Nanzhao"
    ],
    "name:nld_x_preferred": [
      "Nan Chao"
    ],
    "name:nor_x_preferred": [
      "Nanzhao"
    ],
    "name:pol_x_preferred": [
      "Nanzhao"
    ],
    "name:rus_x_preferred": [
      "Наньчжао"
    ],
    "name:sco_x_preferred": [
      "Nanzhao"
    ],
    "name:swe_x_preferred": [
      "Nanzhaoriket"
    ],
    "name:tha_x_preferred": [
      "อาณาจักรน่านเจ้า"
    ],
    "name:ukr_x_preferred": [
      "Наньчжао"
    ],
    "name:vie_x_preferred": [
      "Nam Chiếu"
    ],
    "name:zho_x_preferred": [
      "南照"
    ],
    "wof:name": "Nanzhao",
    "wof:placetype": "locality"
  },
  "geometry": {
    "coordinates": [
      120.63277,
      37.16589000000001
    ],
    "type": "Point"
  }
}