{
  "type": "Feature",
  "properties": {
    "gn:admin1_code": "32.0",
    "gn:asciiname": "Liujiazui",
    "gn:country_code": "CN",
    "gn:dem": 353,
    "gn:feature_class": "P",
    "gn:feature_code": "PPL",
    "gn:name": "Liujiazui",
    "gn:population": 0,
    "gn:timezone": "Asia/Shanghai",
    "iso:country": "CN",
    "name:zho_x_preferred": [
      "刘家咀"
    ],
    "wof:name": "Liujiazui",
    "wof:placetype": "locality"
  },
  "geometry": {
    "coordinates": [
      107.11,
      30.1919
    ],
    "type": "Point"
  }
}