{
  "type": "Feature",
  "properties": {
    "gn:admin1_code": "26.0",
    "gn:asciiname": "Lianggou",
    "gn:country_code": "CN",
    "gn:dem": 636,
    "gn:feature_class": "P",
    "gn:feature_code": "PPL",
    "gn:name": "Lianggou",
    "gn:population": 0,
    "gn:timezone": "Asia/Shanghai",
    "iso:country": "CN",
    "name:und_x_variant": [
      "梁沟"
    ],
    "wof:name": "Lianggou",
    "wof:placetype": "locality"
  },
  "geometry": {
    "coordinates": [
      107.73768,
      33.16148
    ],
    "type": "Point"
  }
}