{
  "type": "Feature",
  "properties": {
    "gn:admin1_code": "26.0",
    "gn:asciiname": "Siheyuan",
    "gn:country_code": "CN",
    "gn:dem": 1214,
    "gn:feature_class": "P",
    "gn:feature_code": "PPL",
    "gn:name": "Siheyuan",
    "gn:population": 0,
    "gn:timezone": "Asia/Shanghai",
    "iso:country": "CN",
    "name:deu_x_preferred": [
      "Siheyuan"
    ],
    "name:fra_x_preferred": [
      "Siheyuan"
    ],
    "name:jpn_x_preferred": [
      "四合院"
    ],
    "name:kor_x_preferred": [
      "쓰허위안"
    ],
    "name:msa_x_preferred": [
      "Siheyuan"
    ],
    "name:nld_x_preferred": [
      "Siheyuan"
    ],
    "name:nor_x_preferred": [
      "Siheyuan"
    ],
    "name:pol_x_preferred": [
      "Siheyuan"
    ],
    "name:rus_x_preferred": [
      "Сыхэюань"
    ],
    "name:spa_x_preferred": [
      "Siheyuan"
    ],
    "name:swe_x_preferred": [
      "Siheyuan"
    ],
    "name:ukr_x_preferred": [
      "Сихеюань"
    ],
    "name:zho_x_preferred": [
      "四合院"
    ],
    "wof:name": "Siheyuan",
    "wof:placetype": "locality"
  },
  "geometry": {
    "coordinates": [
      106.79537,
      32.74897
    ],
    "type": "Point"
  }
}