{
  "type": "Feature",
  "properties": {
    "gn:admin1_code": "19.0",
    "gn:asciiname": "Shuikouzicun",
    "gn:country_code": "CN",
    "gn:dem": 186,
    "gn:feature_class": "P",
    "gn:feature_code": "PPL",
    "gn:name": "Shuikouzicun",
    "gn:population": 0,
    "gn:timezone": "Asia/Shanghai",
    "iso:country": "CN",
    "name:zho_x_preferred": [
      "水口子村"
    ],
    "wof:name": "Shuikouzicun",
    "wof:placetype": "locality"
  },
  "geometry": {
    "coordinates": [
      120.938,
      41.5409
    ],
    "type": "Point"
  }
}