{
  "type": "Feature",
  "properties": {
    "gn:admin1_code": "4.0",
    "gn:asciiname": "Tiangou",
    "gn:country_code": "CN",
    "gn:dem": 0,
    "gn:feature_class": "P",
    "gn:feature_code": "PPL",
    "gn:name": "Tiangou",
    "gn:population": 0,
    "gn:timezone": "Asia/Shanghai",
    "iso:country": "CN",
    "name:deu_x_preferred": [
      "Tiangou"
    ],
    "name:fra_x_preferred": [
      "Tiāngǒu"
    ],
    "name:ind_x_preferred": [
      "Tiangou"
    ],
    "name:por_x_preferred": [
      "Tien-koan"
    ],
    "name:rus_x_preferred": [
      "Тяньгоу"
    ],
    "name:spa_x_preferred": [
      "Tiangou"
    ],
    "name:zho_x_preferred": [
      "Tiangou"
    ],
    "name:zho_x_variant": [
      "天沟",
      "天狗"
    ],
    "wof:name": "Tiangou",
    "wof:placetype": "locality"
  },
  "geometry": {
    "coordinates": [
      119.72827,
      33.89228
    ],
    "type": "Point"
  }
}