{
  "type": "Feature",
  "properties": {
    "gn:admin1_code": "11.0",
    "gn:asciiname": "Weizi'ao",
    "gn:country_code": "CN",
    "gn:dem": 466,
    "gn:feature_class": "P",
    "gn:feature_code": "PPL",
    "gn:name": "Weizi’ao",
    "gn:population": 0,
    "gn:timezone": "Asia/Shanghai",
    "iso:country": "CN",
    "name:und_x_variant": [
      "Weizi’ao"
    ],
    "name:zho_x_preferred": [
      "围子坳"
    ],
    "wof:name": "Weizi'ao",
    "wof:placetype": "locality"
  },
  "geometry": {
    "coordinates": [
      111.3102,
      28.54619000000001
    ],
    "type": "Point"
  }
}