{
  "type": "Feature",
  "properties": {
    "gn:admin1_code": "16",
    "gn:asciiname": "Polian",
    "gn:country_code": "CN",
    "gn:dem": 486,
    "gn:feature_class": "P",
    "gn:feature_code": "PPL",
    "gn:name": "Polian",
    "gn:population": 0,
    "gn:timezone": "Asia/Shanghai",
    "iso:country": "CN",
    "name:zho_x_preferred": [
      "坡莲"
    ],
    "wof:name": "Polian",
    "wof:placetype": "locality"
  },
  "geometry": {
    "coordinates": [
      109.835,
      25.6407
    ],
    "type": "Point"
  }
}