{
  "type": "Feature",
  "properties": {
    "gn:admin1_code": "02",
    "gn:asciiname": "Lengshui",
    "gn:country_code": "CN",
    "gn:dem": 267,
    "gn:feature_class": "P",
    "gn:feature_code": "PPLA4",
    "gn:name": "Lengshui",
    "gn:population": 0,
    "gn:timezone": "Asia/Shanghai",
    "iso:country": "CN",
    "name:und_x_variant": [
      "Lengshui Zhen"
    ],
    "name:zho_x_preferred": [
      "冷水"
    ],
    "name:zho_x_variant": [
      "冷水镇"
    ],
    "wof:name": "Lengshui",
    "wof:placetype": "locality"
  },
  "geometry": {
    "coordinates": [
      120.34615,
      28.89994
    ],
    "type": "Point"
  }
}