{
  "type": "Feature",
  "properties": {
    "gn:admin1_code": "16.0",
    "gn:asciiname": "Laixu",
    "gn:country_code": "CN",
    "gn:dem": 142,
    "gn:feature_class": "P",
    "gn:feature_code": "PPL",
    "gn:name": "Laixu",
    "gn:population": 0,
    "gn:timezone": "Asia/Shanghai",
    "iso:country": "CN",
    "name:zho_x_preferred": [
      "来圩"
    ],
    "wof:name": "Laixu",
    "wof:placetype": "locality"
  },
  "geometry": {
    "coordinates": [
      107.566,
      23.3668
    ],
    "type": "Point"
  }
}