{
  "type": "Feature",
  "properties": {
    "gn:admin1_code": "13",
    "gn:asciiname": "Bugedayili Kejianggale",
    "gn:country_code": "CN",
    "gn:dem": 1202,
    "gn:feature_class": "P",
    "gn:feature_code": "PPL",
    "gn:name": "Bugedayili Kejianggale",
    "gn:population": 0,
    "gn:timezone": "Asia/Shanghai",
    "iso:country": "CN",
    "name:zho_x_preferred": [
      "布格达依里克江尕勒"
    ],
    "wof:name": "Bugedayili Kejianggale",
    "wof:placetype": "locality"
  },
  "geometry": {
    "coordinates": [
      76.76175,
      39.04796
    ],
    "type": "Point"
  }
}