{
  "type": "Feature",
  "properties": {
    "gn:admin1_code": "18.0",
    "gn:asciiname": "Gelie",
    "gn:country_code": "CN",
    "gn:dem": 598,
    "gn:feature_class": "P",
    "gn:feature_code": "PPL",
    "gn:name": "Gelie",
    "gn:population": 0,
    "gn:timezone": "Asia/Shanghai",
    "iso:country": "CN",
    "name:zho_x_preferred": [
      "格烈"
    ],
    "wof:name": "Gelie",
    "wof:placetype": "locality"
  },
  "geometry": {
    "coordinates": [
      108.913,
      26.7743
    ],
    "type": "Point"
  }
}