{
  "type": "Feature",
  "properties": {
    "gn:admin1_code": "32.0",
    "gn:asciiname": "Shiba",
    "gn:country_code": "CN",
    "gn:dem": 243,
    "gn:feature_class": "P",
    "gn:feature_code": "PPL",
    "gn:name": "Shiba",
    "gn:population": 0,
    "gn:timezone": "Asia/Shanghai",
    "iso:country": "CN",
    "name:ceb_x_preferred": [
      "Shiba"
    ],
    "name:deu_x_preferred": [
      "Shiba"
    ],
    "name:fas_x_preferred": [
      "شیبا"
    ],
    "name:fra_x_preferred": [
      "Shiba"
    ],
    "name:ita_x_preferred": [
      "Shiba"
    ],
    "name:pol_x_preferred": [
      "Shiba"
    ],
    "name:rus_x_preferred": [
      "Сиба"
    ],
    "name:zho_x_preferred": [
      "史坝"
    ],
    "wof:name": "Shiba",
    "wof:placetype": "locality"
  },
  "geometry": {
    "coordinates": [
      105.884,
      28.8851
    ],
    "type": "Point"
  }
}