{
  "type": "Feature",
  "properties": {
    "gn:admin1_code": "16",
    "gn:asciiname": "Dalong'an",
    "gn:country_code": "CN",
    "gn:dem": 177,
    "gn:feature_class": "P",
    "gn:feature_code": "PPL",
    "gn:name": "Dalong’an",
    "gn:population": 0,
    "gn:timezone": "Asia/Shanghai",
    "iso:country": "CN",
    "name:und_x_variant": [
      "Dalong’an"
    ],
    "name:zho_x_preferred": [
      "大龙岸"
    ],
    "wof:name": "Dalong'an",
    "wof:placetype": "locality"
  },
  "geometry": {
    "coordinates": [
      110.444,
      24.5423
    ],
    "type": "Point"
  }
}