{
  "type": "Feature",
  "properties": {
    "gn:admin1_code": "32.0",
    "gn:asciiname": "Dawan",
    "gn:country_code": "CN",
    "gn:dem": 277,
    "gn:feature_class": "P",
    "gn:feature_code": "PPL",
    "gn:name": "Dawan",
    "gn:population": 0,
    "gn:timezone": "Asia/Shanghai",
    "iso:country": "CN",
    "name:ceb_x_preferred": [
      "Dawan"
    ],
    "name:deu_x_preferred": [
      "Dawan"
    ],
    "name:ind_x_preferred": [
      "Dawan"
    ],
    "name:swe_x_preferred": [
      "Dawan"
    ],
    "name:zho_x_preferred": [
      "大塆"
    ],
    "wof:name": "Dawan",
    "wof:placetype": "locality"
  },
  "geometry": {
    "coordinates": [
      105.527,
      30.291
    ],
    "type": "Point"
  }
}