{
  "type": "Feature",
  "properties": {
    "gn:admin1_code": "15.0",
    "gn:asciiname": "Sihetai",
    "gn:country_code": "CN",
    "gn:dem": 1434,
    "gn:feature_class": "P",
    "gn:feature_code": "PPL",
    "gn:name": "Sihetai",
    "gn:population": 0,
    "gn:timezone": "Asia/Shanghai",
    "iso:country": "CN",
    "name:zho_x_preferred": [
      "四合台"
    ],
    "wof:name": "Sihetai",
    "wof:placetype": "locality"
  },
  "geometry": {
    "coordinates": [
      108.418,
      36.3622
    ],
    "type": "Point"
  }
}