{
  "type": "Feature",
  "properties": {
    "gn:admin1_code": "10",
    "gn:asciiname": "Jiecun",
    "gn:country_code": "CN",
    "gn:dem": 87,
    "gn:feature_class": "P",
    "gn:feature_code": "PPL",
    "gn:name": "Jiecun",
    "gn:population": 0,
    "gn:timezone": "Asia/Shanghai",
    "iso:country": "CN",
    "name:zho_x_preferred": [
      "解村"
    ],
    "wof:name": "Jiecun",
    "wof:placetype": "locality"
  },
  "geometry": {
    "coordinates": [
      114.516,
      37.4066
    ],
    "type": "Point"
  }
}