{
  "type": "Feature",
  "properties": {
    "gn:admin1_code": "15.0",
    "gn:asciiname": "Huangchuanji",
    "gn:country_code": "CN",
    "gn:dem": 1794,
    "gn:feature_class": "P",
    "gn:feature_code": "PPL",
    "gn:name": "Huangchuanji",
    "gn:population": 0,
    "gn:timezone": "Asia/Shanghai",
    "iso:country": "CN",
    "name:zho_x_preferred": [
      "黄川集"
    ],
    "wof:name": "Huangchuanji",
    "wof:placetype": "locality"
  },
  "geometry": {
    "coordinates": [
      105.266,
      36.0588
    ],
    "type": "Point"
  }
}