{
  "type": "Feature",
  "properties": {
    "gn:admin1_code": "26.0",
    "gn:asciiname": "Sidaoyaozi",
    "gn:country_code": "CN",
    "gn:dem": 1158,
    "gn:feature_class": "P",
    "gn:feature_code": "PPL",
    "gn:name": "Sidaoyaozi",
    "gn:population": 0,
    "gn:timezone": "Asia/Shanghai",
    "iso:country": "CN",
    "name:zho_x_preferred": [
      "四道窑子"
    ],
    "wof:name": "Sidaoyaozi",
    "wof:placetype": "locality"
  },
  "geometry": {
    "coordinates": [
      109.88361,
      36.03923
    ],
    "type": "Point"
  }
}