{
  "type": "Feature",
  "properties": {
    "gn:admin1_code": "9.0",
    "gn:asciiname": "Yulin",
    "gn:country_code": "CN",
    "gn:dem": 105,
    "gn:feature_class": "P",
    "gn:feature_code": "PPL",
    "gn:name": "Yulin",
    "gn:population": 0,
    "gn:timezone": "Asia/Shanghai",
    "iso:country": "CN",
    "name:ceb_x_preferred": [
      "Yulin"
    ],
    "name:deu_x_preferred": [
      "Yulin"
    ],
    "name:eus_x_preferred": [
      "Yulin"
    ],
    "name:fin_x_preferred": [
      "Yulin"
    ],
    "name:fra_x_preferred": [
      "Yulin"
    ],
    "name:heb_x_preferred": [
      "יולין"
    ],
    "name:hun_x_preferred": [
      "Jülin"
    ],
    "name:kor_x_preferred": [
      "위린시"
    ],
    "name:nld_x_preferred": [
      "Yulin"
    ],
    "name:nor_x_preferred": [
      "Yulin"
    ],
    "name:pol_x_preferred": [
      "Yulin"
    ],
    "name:por_x_preferred": [
      "Yulin"
    ],
    "name:rus_x_preferred": [
      "Юйлинь"
    ],
    "name:spa_x_preferred": [
      "Yulin"
    ],
    "name:swe_x_preferred": [
      "Yulin"
    ],
    "name:tur_x_preferred": [
      "Yulin"
    ],
    "name:zho_x_preferred": [
      "榆林"
    ],
    "wof:name": "Yulin",
    "wof:placetype": "locality"
  },
  "geometry": {
    "coordinates": [
      112.13946,
      32.64762
    ],
    "type": "Point"
  }
}