{
  "type": "Feature",
  "properties": {
    "gn:admin1_code": "16.0",
    "gn:asciiname": "Longwan",
    "gn:country_code": "CN",
    "gn:dem": 44,
    "gn:feature_class": "P",
    "gn:feature_code": "PPL",
    "gn:name": "Longwan",
    "gn:population": 0,
    "gn:timezone": "Asia/Shanghai",
    "iso:country": "CN",
    "name:zho_x_preferred": [
      "龙湾"
    ],
    "wof:name": "Longwan",
    "wof:placetype": "locality"
  },
  "geometry": {
    "coordinates": [
      109.237,
      21.9534
    ],
    "type": "Point"
  }
}