{
  "type": "Feature",
  "properties": {
    "gn:admin1_code": "12.0",
    "gn:asciiname": "Zhongshang Wangjia",
    "gn:country_code": "CN",
    "gn:dem": 61,
    "gn:feature_class": "P",
    "gn:feature_code": "PPL",
    "gn:name": "Zhongshang Wangjia",
    "gn:population": 0,
    "gn:timezone": "Asia/Shanghai",
    "iso:country": "CN",
    "name:zho_x_preferred": [
      "Zhongshang Wangjia"
    ],
    "name:zho_x_variant": [
      "中上王家"
    ],
    "wof:name": "Zhongshang Wangjia",
    "wof:placetype": "locality"
  },
  "geometry": {
    "coordinates": [
      114.06834,
      29.51098
    ],
    "type": "Point"
  }
}