{
  "type": "Feature",
  "properties": {
    "gn:admin1_code": "16.0",
    "gn:asciiname": "Likou",
    "gn:country_code": "CN",
    "gn:dem": 164,
    "gn:feature_class": "P",
    "gn:feature_code": "PPL",
    "gn:name": "Likou",
    "gn:population": 0,
    "gn:timezone": "Asia/Shanghai",
    "iso:country": "CN",
    "name:fas_x_preferred": [
      "لیکوو"
    ],
    "name:zho_x_preferred": [
      "力口"
    ],
    "name:zho_x_variant": [
      "历口镇"
    ],
    "wof:name": "Likou",
    "wof:placetype": "locality"
  },
  "geometry": {
    "coordinates": [
      108.445,
      24.1202
    ],
    "type": "Point"
  }
}