{
  "type": "Feature",
  "properties": {
    "gn:admin1_code": "06",
    "gn:asciiname": "Qumarleb",
    "gn:country_code": "CN",
    "gn:dem": 4296,
    "gn:feature_class": "P",
    "gn:feature_code": "PPL",
    "gn:name": "Qumarlêb",
    "gn:population": 0,
    "gn:timezone": "Asia/Urumqi",
    "iso:country": "CN",
    "name:bod_x_preferred": [
      "ཆུ་དམར་ལེབ"
    ],
    "name:und_x_variant": [
      "Shaiwugou"
    ],
    "name:zho_x_preferred": [
      "色吾沟"
    ],
    "wof:name": "Qumarleb",
    "wof:placetype": "locality"
  },
  "geometry": {
    "coordinates": [
      95.61976,
      34.55068
    ],
    "type": "Point"
  }
}