{
  "type": "Feature",
  "properties": {
    "gn:admin1_code": "18.0",
    "gn:asciiname": "Yuxi",
    "gn:country_code": "CN",
    "gn:dem": 686,
    "gn:feature_class": "P",
    "gn:feature_code": "PPLA3",
    "gn:name": "Yuxi",
    "gn:population": 0,
    "gn:timezone": "Asia/Shanghai",
    "iso:country": "CN",
    "name:ara_x_preferred": [
      "يوشى"
    ],
    "name:aze_x_preferred": [
      "Yuxi"
    ],
    "name:cdo_x_preferred": [
      "Ngṳ̆k-kă̤"
    ],
    "name:ceb_x_preferred": [
      "Yuxi"
    ],
    "name:ces_x_preferred": [
      "Jü-si"
    ],
    "name:cym_x_preferred": [
      "Yuxi"
    ],
    "name:dan_x_preferred": [
      "Yuxi"
    ],
    "name:deu_x_preferred": [
      "Yuxi"
    ],
    "name:est_x_preferred": [
      "Yuxi"
    ],
    "name:eus_x_preferred": [
      "Yuxi"
    ],
    "name:fas_x_preferred": [
      "یوکسی"
    ],
    "name:fin_x_preferred": [
      "Yuxi"
    ],
    "name:fra_x_preferred": [
      "Yuxi"
    ],
    "name:hun_x_preferred": [
      "Yuxi"
    ],
    "name:ita_x_preferred": [
      "Yuxi"
    ],
    "name:jpn_x_preferred": [
      "玉渓市"
    ],
    "name:kik_x_preferred": [
      "Yuxi"
    ],
    "name:kor_x_preferred": [
      "위시시"
    ],
    "name:mlg_x_preferred": [
      "Yuxi"
    ],
    "name:nld_x_preferred": [
      "Yuxi"
    ],
    "name:nno_x_preferred": [
      "Yuxi"
    ],
    "name:nor_x_preferred": [
      "Yuxi"
    ],
    "name:pol_x_preferred": [
      "Yuxi"
    ],
    "name:por_x_preferred": [
      "Yuxi"
    ],
    "name:rus_x_preferred": [
      "Юйси"
    ],
    "name:spa_x_preferred": [
      "Yuxi"
    ],
    "name:swe_x_preferred": [
      "Yuxi"
    ],
    "name:tgl_x_preferred": [
      "Yuxi"
    ],
    "name:tha_x_preferred": [
      "อฺวี้ซี"
    ],
    "name:tur_x_preferred": [
      "Yuxi"
    ],
    "name:und_x_variant": [
      "Tao-chen-hsien",
      "Tukichang",
      "Yü-ch’i-chen",
      "Daozhen",
      "Tao-chen",
      "T’u-ch’i-ch’ang",
      "Yü-ch’i",
      "Yü-hsi",
      "Daozhen Gelaozu Miaozu Zizhixian",
      "Yuxi Zhen"
    ],
    "name:urd_x_preferred": [
      "یگزی"
    ],
    "name:vie_x_preferred": [
      "Ngọc Khê"
    ],
    "name:war_x_preferred": [
      "Yuxi"
    ],
    "name:zho_x_preferred": [
      "玉溪"
    ],
    "name:zho_x_variant": [
      "道真仡佬族苗族自治县",
      "玉溪镇",
      "玉溪市"
    ],
    "wof:name": "Yuxi",
    "wof:placetype": "locality"
  },
  "geometry": {
    "coordinates": [
      107.594,
      28.889
    ],
    "type": "Point"
  }
}