{
  "type": "Feature",
  "properties": {
    "gn:admin1_code": "31",
    "gn:asciiname": "Yangyue",
    "gn:country_code": "CN",
    "gn:dem": 27,
    "gn:feature_class": "P",
    "gn:feature_code": "PPL",
    "gn:name": "Yangyue",
    "gn:population": 0,
    "gn:timezone": "Asia/Shanghai",
    "iso:country": "CN",
    "name:und_x_variant": [
      "Meng-yüeh",
      "Yangyue",
      "漾月"
    ],
    "wof:name": "Yangyue",
    "wof:placetype": "locality"
  },
  "geometry": {
    "coordinates": [
      109.24,
      19.8168
    ],
    "type": "Point"
  }
}