{
  "type": "Feature",
  "properties": {
    "gn:admin1_code": "12.0",
    "gn:asciiname": "Xiangtan",
    "gn:country_code": "CN",
    "gn:dem": 1159,
    "gn:feature_class": "P",
    "gn:feature_code": "PPL",
    "gn:name": "Xiangtan",
    "gn:population": 0,
    "gn:timezone": "Asia/Shanghai",
    "iso:country": "CN",
    "name:afr_x_preferred": [
      "Xiangtan"
    ],
    "name:ara_x_preferred": [
      "شيانغتان"
    ],
    "name:bul_x_preferred": [
      "Сянтан"
    ],
    "name:cdo_x_preferred": [
      "Siŏng-tàng"
    ],
    "name:ceb_x_preferred": [
      "Xiangtan"
    ],
    "name:ces_x_preferred": [
      "Siang-tchan"
    ],
    "name:dan_x_preferred": [
      "Xiangtan"
    ],
    "name:deu_x_preferred": [
      "Xiangtan"
    ],
    "name:epo_x_preferred": [
      "Sjantan"
    ],
    "name:est_x_preferred": [
      "Xiangtan Shi"
    ],
    "name:eus_x_preferred": [
      "Xiangtan"
    ],
    "name:fas_x_preferred": [
      "شیانگتان"
    ],
    "name:fin_x_preferred": [
      "Xiangtan"
    ],
    "name:fra_x_preferred": [
      "Xiangtan"
    ],
    "name:hak_x_preferred": [
      "Siong-thâm-sṳ"
    ],
    "name:hun_x_preferred": [
      "Xiangtan"
    ],
    "name:ind_x_preferred": [
      "Xiangtan"
    ],
    "name:ita_x_preferred": [
      "Xiangtan"
    ],
    "name:jpn_x_preferred": [
      "湘潭市"
    ],
    "name:kat_x_preferred": [
      "სიანტანი"
    ],
    "name:kik_x_preferred": [
      "Xiangtan"
    ],
    "name:kor_x_preferred": [
      "샹탄시"
    ],
    "name:mlg_x_preferred": [
      "Xiangtan"
    ],
    "name:nld_x_preferred": [
      "Xiangtan"
    ],
    "name:nno_x_preferred": [
      "Xiangtan"
    ],
    "name:nor_x_preferred": [
      "Xiangtan"
    ],
    "name:pam_x_preferred": [
      "Xiangtan"
    ],
    "name:pol_x_preferred": [
      "Xiangtan"
    ],
    "name:por_x_preferred": [
      "Xiangtan"
    ],
    "name:rus_x_preferred": [
      "Сянтань"
    ],
    "name:spa_x_preferred": [
      "Xiangtan"
    ],
    "name:srp_x_preferred": [
      "Сјангтан"
    ],
    "name:swe_x_preferred": [
      "Xiangtan"
    ],
    "name:tur_x_preferred": [
      "Xiangtan"
    ],
    "name:urd_x_preferred": [
      "شیانگتان"
    ],
    "name:vie_x_preferred": [
      "Tương Đàm"
    ],
    "name:war_x_preferred": [
      "Xiangtan"
    ],
    "name:wuu_x_preferred": [
      "湘潭市"
    ],
    "name:zho_x_preferred": [
      "响滩"
    ],
    "name:zho_x_variant": [
      "湘潭市"
    ],
    "wof:name": "Xiangtan",
    "wof:placetype": "locality"
  },
  "geometry": {
    "coordinates": [
      108.85075,
      30.46817
    ],
    "type": "Point"
  }
}