{
  "type": "Feature",
  "properties": {
    "gn:admin1_code": "15.0",
    "gn:asciiname": "Dongsanshilipu",
    "gn:country_code": "CN",
    "gn:dem": 1658,
    "gn:feature_class": "P",
    "gn:feature_code": "PPL",
    "gn:name": "Dongsanshilipu",
    "gn:population": 0,
    "gn:timezone": "Asia/Shanghai",
    "iso:country": "CN",
    "name:und_x_variant": [
      "东三十里铺"
    ],
    "wof:name": "Dongsanshilipu",
    "wof:placetype": "locality"
  },
  "geometry": {
    "coordinates": [
      104.7194,
      34.91383
    ],
    "type": "Point"
  }
}