{
  "type": "Feature",
  "properties": {
    "gn:admin1_code": "3.0",
    "gn:asciiname": "Zhapu Kouxia",
    "gn:country_code": "CN",
    "gn:dem": 16,
    "gn:feature_class": "P",
    "gn:feature_code": "PPL",
    "gn:name": "Zhapu Kouxia",
    "gn:population": 0,
    "gn:timezone": "Asia/Shanghai",
    "iso:country": "CN",
    "name:und_x_variant": [
      "榨浦口下"
    ],
    "wof:name": "Zhapu Kouxia",
    "wof:placetype": "locality"
  },
  "geometry": {
    "coordinates": [
      116.15161,
      28.83026
    ],
    "type": "Point"
  }
}