{
  "type": "Feature",
  "properties": {
    "gn:admin1_code": "19.0",
    "gn:asciiname": "Shangxianyu",
    "gn:country_code": "CN",
    "gn:dem": 220,
    "gn:feature_class": "P",
    "gn:feature_code": "PPL",
    "gn:name": "Shangxianyu",
    "gn:population": 0,
    "gn:timezone": "Asia/Shanghai",
    "iso:country": "CN",
    "name:und_x_variant": [
      "上仙峪"
    ],
    "wof:name": "Shangxianyu",
    "wof:placetype": "locality"
  },
  "geometry": {
    "coordinates": [
      122.83573,
      40.43258
    ],
    "type": "Point"
  }
}