{
  "type": "Feature",
  "properties": {
    "gn:admin1_code": "32.0",
    "gn:asciiname": "Kaya",
    "gn:country_code": "CN",
    "gn:dem": 3080,
    "gn:feature_class": "P",
    "gn:feature_code": "PPL",
    "gn:name": "Kaya",
    "gn:population": 0,
    "gn:timezone": "Asia/Shanghai",
    "iso:country": "CN",
    "name:bel_x_preferred": [
      "Кая"
    ],
    "name:ben_x_preferred": [
      "কায়া"
    ],
    "name:ceb_x_preferred": [
      "Kaya"
    ],
    "name:deu_x_preferred": [
      "Kaya"
    ],
    "name:fas_x_preferred": [
      "کایا"
    ],
    "name:fra_x_preferred": [
      "Kaya"
    ],
    "name:heb_x_preferred": [
      "קאיה"
    ],
    "name:hin_x_preferred": [
      "काया"
    ],
    "name:hun_x_preferred": [
      "Kaya"
    ],
    "name:ind_x_preferred": [
      "Kaya"
    ],
    "name:ita_x_preferred": [
      "Kaya"
    ],
    "name:jpn_x_preferred": [
      "カヤ"
    ],
    "name:kaz_x_preferred": [
      "Кая"
    ],
    "name:msa_x_preferred": [
      "Kaya"
    ],
    "name:nld_x_preferred": [
      "Kaya"
    ],
    "name:nor_x_preferred": [
      "Kaya"
    ],
    "name:pol_x_preferred": [
      "Kaya"
    ],
    "name:por_x_preferred": [
      "Kaya"
    ],
    "name:rus_x_preferred": [
      "Кая"
    ],
    "name:spa_x_preferred": [
      "Kaya"
    ],
    "name:srp_x_preferred": [
      "Каја"
    ],
    "name:swe_x_preferred": [
      "Kaya"
    ],
    "name:ukr_x_preferred": [
      "Кая"
    ],
    "name:vie_x_preferred": [
      "Kaya"
    ],
    "name:zho_x_preferred": [
      "卡亚"
    ],
    "wof:name": "Kaya",
    "wof:placetype": "locality"
  },
  "geometry": {
    "coordinates": [
      103.376,
      32.606
    ],
    "type": "Point"
  }
}