{
  "type": "Feature",
  "properties": {
    "gn:admin1_code": "18",
    "gn:asciiname": "Deming",
    "gn:country_code": "CN",
    "gn:dem": 679,
    "gn:feature_class": "P",
    "gn:feature_code": "PPL",
    "gn:name": "Deming",
    "gn:population": 0,
    "gn:timezone": "Asia/Shanghai",
    "iso:country": "CN",
    "name:ben_x_preferred": [
      "ডেমিং"
    ],
    "name:cat_x_preferred": [
      "Deming"
    ],
    "name:ceb_x_preferred": [
      "Deming"
    ],
    "name:deu_x_preferred": [
      "Deming"
    ],
    "name:ell_x_preferred": [
      "Ντέμινγκ"
    ],
    "name:fra_x_preferred": [
      "Deming"
    ],
    "name:heb_x_preferred": [
      "דמינג"
    ],
    "name:hin_x_preferred": [
      "डेमिंग"
    ],
    "name:ind_x_preferred": [
      "Deming"
    ],
    "name:ita_x_preferred": [
      "Deming"
    ],
    "name:jpn_x_preferred": [
      "デミング"
    ],
    "name:kor_x_preferred": [
      "데밍"
    ],
    "name:nld_x_preferred": [
      "Deming"
    ],
    "name:por_x_preferred": [
      "Deming"
    ],
    "name:rus_x_preferred": [
      "Деминг"
    ],
    "name:srp_x_preferred": [
      "Деминг"
    ],
    "name:swe_x_preferred": [
      "Deming"
    ],
    "name:ukr_x_preferred": [
      "Демінг"
    ],
    "name:vie_x_preferred": [
      "Deming"
    ],
    "name:vol_x_preferred": [
      "Deming"
    ],
    "name:zho_x_preferred": [
      "德明"
    ],
    "wof:name": "Deming",
    "wof:placetype": "locality"
  },
  "geometry": {
    "coordinates": [
      108.576,
      26.9441
    ],
    "type": "Point"
  }
}