{
  "type": "Feature",
  "properties": {
    "gn:admin1_code": "29.0",
    "gn:asciiname": "Nanlang",
    "gn:country_code": "CN",
    "gn:dem": 1592,
    "gn:feature_class": "P",
    "gn:feature_code": "PPL",
    "gn:name": "Nanlang",
    "gn:population": 0,
    "gn:timezone": "Asia/Shanghai",
    "iso:country": "CN",
    "name:fas_x_preferred": [
      "نانلانگ"
    ],
    "name:mlg_x_preferred": [
      "Nanlang"
    ],
    "name:nld_x_preferred": [
      "Nanlang"
    ],
    "name:swe_x_preferred": [
      "Nanlang"
    ],
    "name:zho_x_preferred": [
      "南榔"
    ],
    "name:zho_x_variant": [
      "南朗镇"
    ],
    "wof:name": "Nanlang",
    "wof:placetype": "locality"
  },
  "geometry": {
    "coordinates": [
      99.8409,
      23.3025
    ],
    "type": "Point"
  }
}