{
  "type": "Feature",
  "properties": {
    "gn:admin1_code": "2.0",
    "gn:asciiname": "Zhongzhaiji",
    "gn:country_code": "CN",
    "gn:dem": 60,
    "gn:feature_class": "P",
    "gn:feature_code": "PPL",
    "gn:name": "Zhongzhaiji",
    "gn:population": 0,
    "gn:timezone": "Asia/Shanghai",
    "iso:country": "CN",
    "name:und_x_variant": [
      "中宅基",
      "Zhongzhaiji"
    ],
    "wof:name": "Zhongzhaiji",
    "wof:placetype": "locality"
  },
  "geometry": {
    "coordinates": [
      119.52781,
      29.3499
    ],
    "type": "Point"
  }
}