{
  "type": "Feature",
  "properties": {
    "gn:admin1_code": "24.0",
    "gn:asciiname": "Huojialing",
    "gn:country_code": "CN",
    "gn:dem": 1194,
    "gn:feature_class": "P",
    "gn:feature_code": "PPL",
    "gn:name": "Huojialing",
    "gn:population": 0,
    "gn:timezone": "Asia/Shanghai",
    "iso:country": "CN",
    "name:zho_x_preferred": [
      "霍家岭"
    ],
    "wof:name": "Huojialing",
    "wof:placetype": "locality"
  },
  "geometry": {
    "coordinates": [
      110.56001,
      36.77026
    ],
    "type": "Point"
  }
}