{
  "type": "Feature",
  "properties": {
    "gn:admin1_code": "29.0",
    "gn:asciiname": "Zhuji",
    "gn:country_code": "CN",
    "gn:dem": 2216,
    "gn:feature_class": "P",
    "gn:feature_code": "PPL",
    "gn:name": "Zhuji",
    "gn:population": 0,
    "gn:timezone": "Asia/Shanghai",
    "iso:country": "CN",
    "name:cat_x_preferred": [
      "Zhuji"
    ],
    "name:ceb_x_preferred": [
      "Zhuji"
    ],
    "name:deu_x_preferred": [
      "Zhuji"
    ],
    "name:fra_x_preferred": [
      "Zhuji"
    ],
    "name:gle_x_preferred": [
      "Zhuji"
    ],
    "name:hak_x_preferred": [
      "Chû-ki-sṳ"
    ],
    "name:ita_x_preferred": [
      "Zhuji"
    ],
    "name:jpn_x_preferred": [
      "諸曁市"
    ],
    "name:kik_x_preferred": [
      "Zhuji"
    ],
    "name:kor_x_preferred": [
      "주지시"
    ],
    "name:mlg_x_preferred": [
      "Zhuji"
    ],
    "name:nor_x_preferred": [
      "Zhuji"
    ],
    "name:pol_x_preferred": [
      "Zhuji"
    ],
    "name:sco_x_preferred": [
      "Zhuji"
    ],
    "name:swe_x_preferred": [
      "Zhuji"
    ],
    "name:tgl_x_preferred": [
      "Zhuji"
    ],
    "name:und_x_variant": [
      "住基"
    ],
    "name:urd_x_preferred": [
      "ژوجی"
    ],
    "name:vie_x_preferred": [
      "Chư Kỵ"
    ],
    "name:war_x_preferred": [
      "Zhuji"
    ],
    "name:wuu_x_preferred": [
      "诸暨市"
    ],
    "name:zho_x_preferred": [
      "诸暨市"
    ],
    "wof:name": "Zhuji",
    "wof:placetype": "locality"
  },
  "geometry": {
    "coordinates": [
      102.69859,
      26.11033
    ],
    "type": "Point"
  }
}