{
  "type": "Feature",
  "properties": {
    "gn:admin1_code": "3.0",
    "gn:asciiname": "Nanyuan",
    "gn:country_code": "CN",
    "gn:dem": 155,
    "gn:feature_class": "P",
    "gn:feature_code": "PPL",
    "gn:name": "Nanyuan",
    "gn:population": 0,
    "gn:timezone": "Asia/Shanghai",
    "iso:country": "CN",
    "name:ceb_x_preferred": [
      "Nanyuan"
    ],
    "name:swe_x_preferred": [
      "Nanyuan"
    ],
    "name:und_x_variant": [
      "南元"
    ],
    "name:zho_x_preferred": [
      "南苑"
    ],
    "wof:name": "Nanyuan",
    "wof:placetype": "locality"
  },
  "geometry": {
    "coordinates": [
      115.0048,
      26.07275
    ],
    "type": "Point"
  }
}