{
  "type": "Feature",
  "properties": {
    "gn:admin1_code": "3.0",
    "gn:asciiname": "Gangxia",
    "gn:country_code": "CN",
    "gn:dem": 132,
    "gn:feature_class": "P",
    "gn:feature_code": "PPL",
    "gn:name": "Gangxia",
    "gn:population": 0,
    "gn:timezone": "Asia/Shanghai",
    "iso:country": "CN",
    "name:und_x_variant": [
      "港下",
      "Gangxiaxiang",
      "港下乡"
    ],
    "wof:name": "Gangxia",
    "wof:placetype": "locality"
  },
  "geometry": {
    "coordinates": [
      116.0717,
      27.51366
    ],
    "type": "Point"
  }
}