{
  "type": "Feature",
  "properties": {
    "gn:admin1_code": "29",
    "gn:asciiname": "Luhe",
    "gn:country_code": "CN",
    "gn:dem": 1833,
    "gn:feature_class": "P",
    "gn:feature_code": "PPL",
    "gn:name": "Lühe",
    "gn:population": 0,
    "gn:timezone": "Asia/Shanghai",
    "iso:country": "CN",
    "name:ceb_x_preferred": [
      "Luhe"
    ],
    "name:dan_x_preferred": [
      "Luhe"
    ],
    "name:deu_x_preferred": [
      "Luhe"
    ],
    "name:fra_x_preferred": [
      "Luhe"
    ],
    "name:nor_x_preferred": [
      "Luhe"
    ],
    "name:pol_x_preferred": [
      "Luhe"
    ],
    "name:swe_x_preferred": [
      "Luhe"
    ],
    "name:und_x_variant": [
      "Lü-ho-chen",
      "Lü-ho",
      "Lühe"
    ],
    "name:zho_x_preferred": [
      "吕合"
    ],
    "wof:name": "Luhe",
    "wof:placetype": "locality"
  },
  "geometry": {
    "coordinates": [
      101.37,
      25.1479
    ],
    "type": "Point"
  }
}