{
  "type": "Feature",
  "properties": {
    "gn:admin1_code": "04",
    "gn:asciiname": "Huaisi",
    "gn:country_code": "CN",
    "gn:dem": 12,
    "gn:feature_class": "P",
    "gn:feature_code": "PPL",
    "gn:name": "Huaisi",
    "gn:population": 0,
    "gn:timezone": "Asia/Shanghai",
    "iso:country": "CN",
    "name:und_x_variant": [
      "Huaisiqiao",
      "Huai-tzu-ch’iao",
      "Huai-ssu-ch’iao",
      "Huaisi"
    ],
    "name:zho_x_preferred": [
      "槐泗"
    ],
    "wof:name": "Huaisi",
    "wof:placetype": "locality"
  },
  "geometry": {
    "coordinates": [
      119.43779,
      32.45950999999999
    ],
    "type": "Point"
  }
}