{
  "type": "Feature",
  "properties": {
    "gn:admin1_code": "30",
    "gn:asciiname": "Shanxu",
    "gn:country_code": "CN",
    "gn:dem": 9,
    "gn:feature_class": "P",
    "gn:feature_code": "PPL",
    "gn:name": "Shanxu",
    "gn:population": 0,
    "gn:timezone": "Asia/Urumqi",
    "iso:country": "CN",
    "name:fas_x_preferred": [
      "شانشو"
    ],
    "name:zha_x_preferred": [
      "Sanhih"
    ],
    "name:zho_x_preferred": [
      "山圩"
    ],
    "name:zho_x_variant": [
      "山圩镇"
    ],
    "wof:name": "Shanxu",
    "wof:placetype": "locality"
  },
  "geometry": {
    "coordinates": [
      110.66689,
      21.43002000000001
    ],
    "type": "Point"
  }
}