{
  "type": "Feature",
  "properties": {
    "gn:admin1_code": "7.0",
    "gn:asciiname": "Xiaofenliu",
    "gn:country_code": "CN",
    "gn:dem": 655,
    "gn:feature_class": "P",
    "gn:feature_code": "PPL",
    "gn:name": "Xiaofenliu",
    "gn:population": 0,
    "gn:timezone": "Asia/Shanghai",
    "iso:country": "CN",
    "name:zho_x_preferred": [
      "小分流"
    ],
    "wof:name": "Xiaofenliu",
    "wof:placetype": "locality"
  },
  "geometry": {
    "coordinates": [
      117.73561,
      25.0061
    ],
    "type": "Point"
  }
}