{
  "type": "Feature",
  "properties": {
    "gn:admin1_code": "25",
    "gn:asciiname": "Weihai",
    "gn:country_code": "CN",
    "gn:dem": 45,
    "gn:feature_class": "P",
    "gn:feature_code": "PPL",
    "gn:name": "Weihai",
    "gn:population": 0,
    "gn:timezone": "Asia/Shanghai",
    "iso:country": "CN",
    "name:afr_x_preferred": [
      "Weihai"
    ],
    "name:ara_x_preferred": [
      "ويهاي"
    ],
    "name:cat_x_preferred": [
      "Weihai"
    ],
    "name:cdo_x_preferred": [
      "Ŭi-hāi"
    ],
    "name:ceb_x_preferred": [
      "Weihai"
    ],
    "name:ces_x_preferred": [
      "Wej-chaj"
    ],
    "name:dan_x_preferred": [
      "Weihai"
    ],
    "name:deu_x_preferred": [
      "Weihai"
    ],
    "name:eus_x_preferred": [
      "Weihai"
    ],
    "name:fas_x_preferred": [
      "ویهای"
    ],
    "name:fin_x_preferred": [
      "Weihai"
    ],
    "name:fra_x_preferred": [
      "Weihai"
    ],
    "name:hun_x_preferred": [
      "Weihai"
    ],
    "name:ind_x_preferred": [
      "Weihai"
    ],
    "name:ita_x_preferred": [
      "Weihai"
    ],
    "name:jpn_x_preferred": [
      "威海市"
    ],
    "name:kik_x_preferred": [
      "Weihai"
    ],
    "name:kor_x_preferred": [
      "웨이하이시"
    ],
    "name:mlg_x_preferred": [
      "Weihai"
    ],
    "name:mya_x_preferred": [
      "ဝေးဟိုင်မြို့"
    ],
    "name:nld_x_preferred": [
      "Weihai"
    ],
    "name:nno_x_preferred": [
      "Weihai"
    ],
    "name:nor_x_preferred": [
      "Weihai"
    ],
    "name:pol_x_preferred": [
      "Weihai"
    ],
    "name:por_x_preferred": [
      "Weihai"
    ],
    "name:rus_x_preferred": [
      "Вэйхай"
    ],
    "name:spa_x_preferred": [
      "Weihai"
    ],
    "name:swe_x_preferred": [
      "Weihai"
    ],
    "name:tgl_x_preferred": [
      "Weihai"
    ],
    "name:tha_x_preferred": [
      "เวยไห่"
    ],
    "name:tur_x_preferred": [
      "Weihai"
    ],
    "name:ukr_x_preferred": [
      "Вейхай"
    ],
    "name:urd_x_preferred": [
      "وییہائی"
    ],
    "name:vep_x_preferred": [
      "Veihai"
    ],
    "name:vie_x_preferred": [
      "Uy Hải"
    ],
    "name:war_x_preferred": [
      "Weihai"
    ],
    "name:wuu_x_preferred": [
      "威海市"
    ],
    "name:zho_x_preferred": [
      "魏海"
    ],
    "name:zho_x_variant": [
      "威海市"
    ],
    "wof:name": "Weihai",
    "wof:placetype": "locality"
  },
  "geometry": {
    "coordinates": [
      115.77682,
      36.07285
    ],
    "type": "Point"
  }
}