{
  "type": "Feature",
  "properties": {
    "gn:admin1_code": "19.0",
    "gn:asciiname": "Yangwanshao",
    "gn:country_code": "CN",
    "gn:dem": 153,
    "gn:feature_class": "P",
    "gn:feature_code": "PPL",
    "gn:name": "Yangwanshao",
    "gn:population": 0,
    "gn:timezone": "Asia/Shanghai",
    "iso:country": "CN",
    "name:und_x_variant": [
      "杨湾哨"
    ],
    "wof:name": "Yangwanshao",
    "wof:placetype": "locality"
  },
  "geometry": {
    "coordinates": [
      122.183,
      40.0223
    ],
    "type": "Point"
  }
}