{
  "type": "Feature",
  "properties": {
    "gn:admin1_code": "32.0",
    "gn:asciiname": "Pingqiao",
    "gn:country_code": "CN",
    "gn:dem": 395,
    "gn:feature_class": "P",
    "gn:feature_code": "PPL",
    "gn:name": "Pingqiao",
    "gn:population": 0,
    "gn:timezone": "Asia/Shanghai",
    "iso:country": "CN",
    "name:zho_x_preferred": [
      "平桥"
    ],
    "wof:name": "Pingqiao",
    "wof:placetype": "locality"
  },
  "geometry": {
    "coordinates": [
      106.951,
      30.3909
    ],
    "type": "Point"
  }
}