{
  "type": "Feature",
  "properties": {
    "gn:admin1_code": "1.0",
    "gn:asciiname": "Yuanlin",
    "gn:country_code": "CN",
    "gn:dem": 46,
    "gn:feature_class": "P",
    "gn:feature_code": "PPL",
    "gn:name": "Yuanlin",
    "gn:population": 0,
    "gn:timezone": "Asia/Shanghai",
    "iso:country": "CN",
    "name:deu_x_preferred": [
      "Yuanlin"
    ],
    "name:fas_x_preferred": [
      "یوانلین"
    ],
    "name:hak_x_preferred": [
      "Yèn-lìm-chṳ́n"
    ],
    "name:ita_x_preferred": [
      "Yuanlin"
    ],
    "name:jpn_x_preferred": [
      "員林市"
    ],
    "name:kor_x_preferred": [
      "위안린시"
    ],
    "name:pol_x_preferred": [
      "Yuanlin"
    ],
    "name:rus_x_preferred": [
      "Юаньлинь"
    ],
    "name:urd_x_preferred": [
      "یوآنلن"
    ],
    "name:vie_x_preferred": [
      "Viên Lâm"
    ],
    "name:war_x_preferred": [
      "Yuanlin"
    ],
    "name:zho_x_preferred": [
      "园林"
    ],
    "name:zho_x_variant": [
      "員林市"
    ],
    "wof:name": "Yuanlin",
    "wof:placetype": "locality"
  },
  "geometry": {
    "coordinates": [
      118.35427,
      30.68754
    ],
    "type": "Point"
  }
}