{
  "type": "Feature",
  "properties": {
    "gn:admin1_code": "20",
    "gn:admin2_code": "8617184",
    "gn:asciiname": "Bayan Hot",
    "gn:country_code": "CN",
    "gn:dem": 1529,
    "gn:feature_class": "P",
    "gn:feature_code": "PPLA3",
    "gn:name": "Bayan Hot",
    "gn:population": 0,
    "gn:timezone": "Asia/Shanghai",
    "iso:country": "CN",
    "name:und_x_variant": [
      "Pa-yen-hao-t’e-shih",
      "Bayinhot",
      "Pa-yin-hao-t’e",
      "Bayenhot",
      "Pa-yen-hao-t’e",
      "A-la-shan-tso-ch’i",
      "Pa-yen-hao-t’e-chen",
      "A-la-shan-ch’i",
      "Ting-yüan-ying",
      "Alxa Zuoqi",
      "Tszökhushechzhitszyuy",
      "Tzu-hu-she-chih-chü",
      "Tzu-hu",
      "Bayan Hot",
      "巴彦浩特",
      "Bayanhaote Zhen",
      "Alashanzuo Qi",
      "巴彦浩特镇",
      "阿拉善左旗"
    ],
    "wof:name": "Bayan Hot",
    "wof:placetype": "locality"
  },
  "geometry": {
    "coordinates": [
      105.66861000000002,
      38.83861
    ],
    "type": "Point"
  }
}