{
  "type": "Feature",
  "properties": {
    "gn:admin1_code": "32.0",
    "gn:asciiname": "Taipingqiao",
    "gn:country_code": "CN",
    "gn:dem": 507,
    "gn:feature_class": "P",
    "gn:feature_code": "PPL",
    "gn:name": "Taipingqiao",
    "gn:population": 0,
    "gn:timezone": "Asia/Shanghai",
    "iso:country": "CN",
    "name:zho_x_preferred": [
      "太平桥"
    ],
    "wof:name": "Taipingqiao",
    "wof:placetype": "locality"
  },
  "geometry": {
    "coordinates": [
      103.97123,
      30.66474
    ],
    "type": "Point"
  }
}