{
  "type": "Feature",
  "properties": {
    "gn:admin1_code": "26.0",
    "gn:asciiname": "Suncha",
    "gn:country_code": "CN",
    "gn:dem": 1233,
    "gn:feature_class": "P",
    "gn:feature_code": "PPL",
    "gn:name": "Suncha",
    "gn:population": 0,
    "gn:timezone": "Asia/Shanghai",
    "iso:country": "CN",
    "name:zho_x_preferred": [
      "孙岔"
    ],
    "wof:name": "Suncha",
    "wof:placetype": "locality"
  },
  "geometry": {
    "coordinates": [
      109.09536,
      36.62765
    ],
    "type": "Point"
  }
}