{
  "type": "Feature",
  "properties": {
    "gn:country": "CN",
    "gn:fcode": "PPL",
    "gn:population": 98259,
    "iso:country": "CN",
    "name:ceb_x_preferred": [
      "Xinyi"
    ],
    "name:deu_x_preferred": [
      "Xinyi"
    ],
    "name:fas_x_preferred": [
      "شینی"
    ],
    "name:fra_x_preferred": [
      "Xinyi"
    ],
    "name:heb_x_preferred": [
      "קסיניי"
    ],
    "name:hun_x_preferred": [
      "Xinyi"
    ],
    "name:jpn_x_preferred": [
      "シンイー"
    ],
    "name:kor_x_preferred": [
      "신이시"
    ],
    "name:mlg_x_preferred": [
      "Xinyi"
    ],
    "name:nor_x_preferred": [
      "Xinyi"
    ],
    "name:rus_x_preferred": [
      "Синьи"
    ],
    "name:swe_x_preferred": [
      "Xinyi"
    ],
    "name:und_x_variant": [
      "Hsin-i"
    ],
    "name:zho_x_preferred": [
      "信宜"
    ],
    "qs:name": "Xinyi",
    "qs:photos_9r": 0,
    "qs:photos_sr": 0,
    "qs:pop_sr": "8",
    "wd:wordcount": 176,
    "wof:name": "Xinyi",
    "wof:placetype": "locality",
    "wof:population": 98259
  },
  "geometry": {
    "coordinates": [
      110.94746,
      22.37303
    ],
    "type": "Point"
  }
}