{
  "type": "Feature",
  "properties": {
    "gn:admin1_code": "15.0",
    "gn:asciiname": "Xiamen",
    "gn:country_code": "CN",
    "gn:dem": 1288,
    "gn:feature_class": "P",
    "gn:feature_code": "PPL",
    "gn:name": "Xiamen",
    "gn:population": 0,
    "gn:timezone": "Asia/Shanghai",
    "iso:country": "CN",
    "name:afr_x_preferred": [
      "Xiamen"
    ],
    "name:ara_x_preferred": [
      "شيامن"
    ],
    "name:ast_x_preferred": [
      "Xiamen"
    ],
    "name:bre_x_preferred": [
      "Xiamen"
    ],
    "name:bul_x_preferred": [
      "Сямън"
    ],
    "name:cat_x_preferred": [
      "Xiamen"
    ],
    "name:cdo_x_preferred": [
      "Â-muòng"
    ],
    "name:ceb_x_preferred": [
      "Xiamen"
    ],
    "name:ces_x_preferred": [
      "Sia-men"
    ],
    "name:cym_x_preferred": [
      "Xiamen"
    ],
    "name:dan_x_preferred": [
      "Xiamen"
    ],
    "name:deu_x_preferred": [
      "Xiamen"
    ],
    "name:ell_x_preferred": [
      "Σιαμέν"
    ],
    "name:epo_x_preferred": [
      "Sjamen"
    ],
    "name:est_x_preferred": [
      "Xiamen Shi"
    ],
    "name:eus_x_preferred": [
      "Xiamen"
    ],
    "name:fas_x_preferred": [
      "شیامن"
    ],
    "name:fin_x_preferred": [
      "Xiamen"
    ],
    "name:fra_x_preferred": [
      "Xiamen"
    ],
    "name:glg_x_preferred": [
      "Xiamen"
    ],
    "name:hak_x_preferred": [
      "Ha-mùn-sṳ"
    ],
    "name:heb_x_preferred": [
      "שיאמן"
    ],
    "name:hrv_x_preferred": [
      "Xiamen"
    ],
    "name:hun_x_preferred": [
      "Hsziamen"
    ],
    "name:hye_x_preferred": [
      "Սյամին"
    ],
    "name:ind_x_preferred": [
      "Xiamen"
    ],
    "name:ita_x_preferred": [
      "Xiamen"
    ],
    "name:jpn_x_preferred": [
      "廈門市"
    ],
    "name:kat_x_preferred": [
      "სიამინი"
    ],
    "name:kik_x_preferred": [
      "Xiamen"
    ],
    "name:kor_x_preferred": [
      "샤먼시"
    ],
    "name:lit_x_preferred": [
      "Siamenas"
    ],
    "name:mlg_x_preferred": [
      "Xiamen"
    ],
    "name:msa_x_preferred": [
      "Xiamen"
    ],
    "name:nld_x_preferred": [
      "Xiamen"
    ],
    "name:nno_x_preferred": [
      "Xiamen"
    ],
    "name:nor_x_preferred": [
      "Xiamen"
    ],
    "name:pam_x_preferred": [
      "Xiamen"
    ],
    "name:pnb_x_preferred": [
      "شیامن"
    ],
    "name:pol_x_preferred": [
      "Xiamen"
    ],
    "name:por_x_preferred": [
      "Xiamen"
    ],
    "name:que_x_preferred": [
      "Hiyamin"
    ],
    "name:rus_x_preferred": [
      "Сямынь"
    ],
    "name:sco_x_preferred": [
      "Xiamen"
    ],
    "name:spa_x_preferred": [
      "Xiamen"
    ],
    "name:sqi_x_preferred": [
      "Siamen"
    ],
    "name:srp_x_preferred": [
      "Сјамен"
    ],
    "name:swe_x_preferred": [
      "Xiamen"
    ],
    "name:tgl_x_preferred": [
      "Xiamen"
    ],
    "name:tha_x_preferred": [
      "เซี่ยเหมิน"
    ],
    "name:tur_x_preferred": [
      "Xiamen"
    ],
    "name:uig_x_preferred": [
      "شيامېن شەھىرى"
    ],
    "name:ukr_x_preferred": [
      "Сямень"
    ],
    "name:urd_x_preferred": [
      "شیامین"
    ],
    "name:vie_x_preferred": [
      "Hạ Môn"
    ],
    "name:war_x_preferred": [
      "Xiamen"
    ],
    "name:wuu_x_preferred": [
      "厦门市"
    ],
    "name:zho_x_preferred": [
      "峡门"
    ],
    "name:zho_x_variant": [
      "厦门市"
    ],
    "wof:name": "Xiamen",
    "wof:placetype": "locality"
  },
  "geometry": {
    "coordinates": [
      106.857,
      35.2724
    ],
    "type": "Point"
  }
}