{
  "type": "Feature",
  "properties": {
    "gn:admin1_code": "21.0",
    "gn:asciiname": "Suohutou",
    "gn:country_code": "CN",
    "gn:dem": 1497,
    "gn:feature_class": "P",
    "gn:feature_code": "PPL",
    "gn:name": "Suohutou",
    "gn:population": 0,
    "gn:timezone": "Asia/Shanghai",
    "iso:country": "CN",
    "name:zho_x_preferred": [
      "锁虎头"
    ],
    "wof:name": "Suohutou",
    "wof:placetype": "locality"
  },
  "geometry": {
    "coordinates": [
      105.616,
      37.1053
    ],
    "type": "Point"
  }
}