{
  "type": "Feature",
  "properties": {
    "gn:admin1_code": "07",
    "gn:asciiname": "Cuntou",
    "gn:country_code": "CN",
    "gn:dem": 583,
    "gn:feature_class": "P",
    "gn:feature_code": "PPL",
    "gn:name": "Cuntou",
    "gn:population": 0,
    "gn:timezone": "Asia/Shanghai",
    "iso:country": "CN",
    "name:zho_x_preferred": [
      "村头"
    ],
    "wof:name": "Cuntou",
    "wof:placetype": "locality"
  },
  "geometry": {
    "coordinates": [
      118.579,
      26.83228
    ],
    "type": "Point"
  }
}