{
  "type": "Feature",
  "properties": {
    "gn:admin1_code": "26.0",
    "gn:asciiname": "Lucungoucun",
    "gn:country_code": "CN",
    "gn:dem": 1079,
    "gn:feature_class": "P",
    "gn:feature_code": "PPL",
    "gn:name": "Lucungoucun",
    "gn:population": 0,
    "gn:timezone": "Asia/Shanghai",
    "iso:country": "CN",
    "name:zho_x_preferred": [
      "芦村沟村"
    ],
    "wof:name": "Lucungoucun",
    "wof:placetype": "locality"
  },
  "geometry": {
    "coordinates": [
      109.02905,
      35.88915
    ],
    "type": "Point"
  }
}