{
  "type": "Feature",
  "properties": {
    "gn:admin1_code": "14.0",
    "gn:asciiname": "Wage",
    "gn:country_code": "CN",
    "gn:dem": 3288,
    "gn:feature_class": "P",
    "gn:feature_code": "PPL",
    "gn:name": "Wage",
    "gn:population": 0,
    "gn:timezone": "Asia/Shanghai",
    "iso:country": "CN",
    "name:ara_x_preferred": [
      "أجر"
    ],
    "name:bel_x_preferred": [
      "Заработная плата"
    ],
    "name:bul_x_preferred": [
      "Заплата"
    ],
    "name:ces_x_preferred": [
      "Mzda"
    ],
    "name:ckb_x_preferred": [
      "کرێ"
    ],
    "name:cym_x_preferred": [
      "Cyflog"
    ],
    "name:deu_x_preferred": [
      "Zeitlohn"
    ],
    "name:est_x_preferred": [
      "Töötasu"
    ],
    "name:fas_x_preferred": [
      "دستمزد"
    ],
    "name:hin_x_preferred": [
      "मजदूरी"
    ],
    "name:ind_x_preferred": [
      "Upah"
    ],
    "name:kan_x_preferred": [
      "ಕೂಲಿ"
    ],
    "name:kaz_x_preferred": [
      "Еңбекақы"
    ],
    "name:kor_x_preferred": [
      "임금"
    ],
    "name:msa_x_preferred": [
      "Upah"
    ],
    "name:nep_x_preferred": [
      "ज्याला"
    ],
    "name:pan_x_preferred": [
      "ਉਜਰਤ"
    ],
    "name:rus_x_preferred": [
      "Заработная плата"
    ],
    "name:slk_x_preferred": [
      "Mzda"
    ],
    "name:tam_x_preferred": [
      "கூலி"
    ],
    "name:tat_x_preferred": [
      "Хезмәт хакы"
    ],
    "name:tur_x_preferred": [
      "Maaş"
    ],
    "name:ukr_x_preferred": [
      "Заробітна плата"
    ],
    "name:uzb_x_preferred": [
      "Ish haqi"
    ],
    "name:vie_x_preferred": [
      "Tiền công"
    ],
    "name:zho_x_preferred": [
      "瓦格"
    ],
    "wof:name": "Wage",
    "wof:placetype": "locality"
  },
  "geometry": {
    "coordinates": [
      98.28446,
      32.1612
    ],
    "type": "Point"
  }
}