{
  "type": "Feature",
  "properties": {
    "gn:admin1_code": "26.0",
    "gn:asciiname": "Shidukou",
    "gn:country_code": "CN",
    "gn:dem": 1588,
    "gn:feature_class": "P",
    "gn:feature_code": "PPL",
    "gn:name": "Shidukou",
    "gn:population": 0,
    "gn:timezone": "Asia/Shanghai",
    "iso:country": "CN",
    "name:zho_x_preferred": [
      "石渡口"
    ],
    "wof:name": "Shidukou",
    "wof:placetype": "locality"
  },
  "geometry": {
    "coordinates": [
      108.49381,
      37.26994000000001
    ],
    "type": "Point"
  }
}