{
  "type": "Feature",
  "properties": {
    "gn:admin1_code": "19",
    "gn:asciiname": "Qikou",
    "gn:country_code": "CN",
    "gn:dem": 6,
    "gn:feature_class": "P",
    "gn:feature_code": "PPLA4",
    "gn:name": "Qikou",
    "gn:population": 0,
    "gn:timezone": "Asia/Shanghai",
    "iso:country": "CN",
    "name:und_x_variant": [
      "Ch’i-k’ou",
      "Lan-ch’i-k’ou-ts’un",
      "Lan-ch’i-p’u",
      "Qikou",
      "旗口",
      "Qikou Zhen"
    ],
    "name:zho_x_preferred": [
      "旗口镇"
    ],
    "wof:name": "Qikou",
    "wof:placetype": "locality"
  },
  "geometry": {
    "coordinates": [
      122.42337,
      40.85492
    ],
    "type": "Point"
  }
}