{
  "type": "Feature",
  "properties": {
    "gn:admin1_code": "18",
    "gn:asciiname": "Daweng",
    "gn:country_code": "CN",
    "gn:dem": 1209,
    "gn:feature_class": "P",
    "gn:feature_code": "PPL",
    "gn:name": "Daweng",
    "gn:population": 0,
    "gn:timezone": "Asia/Shanghai",
    "iso:country": "CN",
    "name:zho_x_preferred": [
      "打翁"
    ],
    "wof:name": "Daweng",
    "wof:placetype": "locality"
  },
  "geometry": {
    "coordinates": [
      105.659,
      25.9569
    ],
    "type": "Point"
  }
}