{
  "type": "Feature",
  "properties": {
    "gn:admin1_code": "12.0",
    "gn:asciiname": "Liangmiao",
    "gn:country_code": "CN",
    "gn:dem": 32,
    "gn:feature_class": "P",
    "gn:feature_code": "PPL",
    "gn:name": "Liangmiao",
    "gn:population": 0,
    "gn:timezone": "Asia/Shanghai",
    "iso:country": "CN",
    "name:zho_x_preferred": [
      "梁庙"
    ],
    "wof:name": "Liangmiao",
    "wof:placetype": "locality"
  },
  "geometry": {
    "coordinates": [
      112.94721,
      30.27705
    ],
    "type": "Point"
  }
}