{
  "type": "Feature",
  "properties": {
    "gn:admin1_code": "30.0",
    "gn:asciiname": "Zhangshutou",
    "gn:country_code": "CN",
    "gn:dem": 70,
    "gn:feature_class": "P",
    "gn:feature_code": "PPL",
    "gn:name": "Zhangshutou",
    "gn:population": 0,
    "gn:timezone": "Asia/Shanghai",
    "iso:country": "CN",
    "name:und_x_variant": [
      "Tanshutou"
    ],
    "name:zho_x_preferred": [
      "樟树头"
    ],
    "name:zho_x_variant": [
      "檀树头"
    ],
    "wof:name": "Zhangshutou",
    "wof:placetype": "locality"
  },
  "geometry": {
    "coordinates": [
      115.63873999999998,
      23.24182
    ],
    "type": "Point"
  }
}