{
  "type": "Feature",
  "properties": {
    "gn:admin1_code": "26.0",
    "gn:asciiname": "Xiaojianzicun",
    "gn:country_code": "CN",
    "gn:dem": 1684,
    "gn:feature_class": "P",
    "gn:feature_code": "PPL",
    "gn:name": "Xiaojianzicun",
    "gn:population": 0,
    "gn:timezone": "Asia/Shanghai",
    "iso:country": "CN",
    "name:und_x_variant": [
      "Hsiao-chien-tzu",
      "Xiaojianzi",
      "Xiaojianzicun"
    ],
    "name:zho_x_preferred": [
      "小涧子村"
    ],
    "wof:name": "Xiaojianzicun",
    "wof:placetype": "locality"
  },
  "geometry": {
    "coordinates": [
      107.628,
      37.33
    ],
    "type": "Point"
  }
}