{
  "type": "Feature",
  "properties": {
    "gn:admin1_code": "14.0",
    "gn:asciiname": "Nagqu",
    "gn:country_code": "CN",
    "gn:dem": 4609,
    "gn:feature_class": "P",
    "gn:feature_code": "PPLF",
    "gn:name": "Nagqu",
    "gn:population": 0,
    "gn:timezone": "Asia/Urumqi",
    "iso:country": "CN",
    "name:ben_x_preferred": [
      "নাগ-ছু বিভাগ"
    ],
    "name:bod_x_preferred": [
      "Nagqu"
    ],
    "name:bod_x_variant": [
      "ནག་ཆུ་ས་ཁུལ།"
    ],
    "name:cdo_x_preferred": [
      "Nagqu"
    ],
    "name:ceb_x_preferred": [
      "Nagqu"
    ],
    "name:ces_x_preferred": [
      "Nagčhu"
    ],
    "name:dan_x_preferred": [
      "Nagqu"
    ],
    "name:deu_x_preferred": [
      "Nagqu"
    ],
    "name:eus_x_preferred": [
      "Nagqu Prefektura"
    ],
    "name:fas_x_preferred": [
      "ناچو"
    ],
    "name:fin_x_preferred": [
      "Nagqu"
    ],
    "name:hak_x_preferred": [
      "Nagqu"
    ],
    "name:hin_x_preferred": [
      "नगचु विभाग"
    ],
    "name:jpn_x_preferred": [
      "ナクチュ市"
    ],
    "name:kor_x_preferred": [
      "나취시"
    ],
    "name:lit_x_preferred": [
      "Nagču prefektūra"
    ],
    "name:mlg_x_preferred": [
      "Nagqu"
    ],
    "name:nld_x_preferred": [
      "Nagchu"
    ],
    "name:nor_x_preferred": [
      "Nagqu"
    ],
    "name:pol_x_preferred": [
      "Nagqu"
    ],
    "name:rus_x_preferred": [
      "Нагчу"
    ],
    "name:spa_x_preferred": [
      "Nagqu"
    ],
    "name:swe_x_preferred": [
      "Nagchu"
    ],
    "name:tur_x_preferred": [
      "Nagqu"
    ],
    "name:urd_x_preferred": [
      "ناگچو"
    ],
    "name:vie_x_preferred": [
      "Nagqu"
    ],
    "name:wuu_x_preferred": [
      "那曲市"
    ],
    "name:zho_x_preferred": [
      "Naqu"
    ],
    "name:zho_x_variant": [
      "纳曲",
      "Xiongrurisu",
      "雄如日苏",
      "那曲市"
    ],
    "wof:name": "Nagqu",
    "wof:placetype": "locality"
  },
  "geometry": {
    "coordinates": [
      83.40100000000002,
      29.701
    ],
    "type": "Point"
  }
}