{
  "type": "Feature",
  "properties": {
    "gn:admin1_code": "02",
    "gn:asciiname": "Huangnan",
    "gn:country_code": "CN",
    "gn:dem": 167,
    "gn:feature_class": "P",
    "gn:feature_code": "PPLA4",
    "gn:name": "Huangnan",
    "gn:population": 0,
    "gn:timezone": "Asia/Shanghai",
    "iso:country": "CN",
    "name:und_x_variant": [
      "Huangnan Xiang"
    ],
    "name:zho_x_preferred": [
      "黄南"
    ],
    "name:zho_x_variant": [
      "黄南乡"
    ],
    "wof:name": "Huangnan",
    "wof:placetype": "locality"
  },
  "geometry": {
    "coordinates": [
      120.68128,
      28.52913
    ],
    "type": "Point"
  }
}