{
  "type": "Feature",
  "properties": {
    "gn:admin1_code": "13.0",
    "gn:asciiname": "Tuwat",
    "gn:country_code": "CN",
    "gn:dem": 1315,
    "gn:feature_class": "P",
    "gn:feature_code": "PPL",
    "gn:name": "Tüwat",
    "gn:population": 0,
    "gn:timezone": "Asia/Shanghai",
    "iso:country": "CN",
    "name:uig_x_preferred": [
      "Tüwət"
    ],
    "name:uig_x_variant": [
      "Tüwet",
      "تۈۋەت",
      "Түвәт"
    ],
    "name:und_x_variant": [
      "Tüwat"
    ],
    "wof:name": "Tuwat",
    "wof:placetype": "locality"
  },
  "geometry": {
    "coordinates": [
      79.78333,
      37.33333
    ],
    "type": "Point"
  }
}