{
  "type": "Feature",
  "properties": {
    "gn:admin1_code": "13.0",
    "gn:asciiname": "Shuiding",
    "gn:cc2": "CN",
    "gn:country_code": "CN",
    "gn:dem": 601,
    "gn:feature_class": "P",
    "gn:feature_code": "PPL",
    "gn:name": "Shuiding",
    "gn:population": 0,
    "gn:timezone": "Asia/Shanghai",
    "iso:country": "CN",
    "name:por_x_preferred": [
      "Suiding"
    ],
    "name:rus_x_preferred": [
      "Шуйдин"
    ],
    "name:uig_x_preferred": [
      "سۈيدۈڭ بازىرى"
    ],
    "name:und_x_variant": [
      "Huo-ch’eng-hsien",
      "Sui-ting",
      "I-li",
      "Sui-ting-chen",
      "Huocheng",
      "Shui-ting-chen",
      "Huocheng Xian",
      "Sui-ting-hsien",
      "Sui-ding",
      "Suydun",
      "Shuiding"
    ],
    "name:zho_x_preferred": [
      "水定镇"
    ],
    "wof:name": "Shuiding",
    "wof:placetype": "locality"
  },
  "geometry": {
    "coordinates": [
      80.80778000000002,
      44.01
    ],
    "type": "Point"
  }
}