{
  "type": "Feature",
  "properties": {
    "gn:admin1_code": "19.0",
    "gn:asciiname": "Lengjiacun",
    "gn:country_code": "CN",
    "gn:dem": 234,
    "gn:feature_class": "P",
    "gn:feature_code": "PPL",
    "gn:name": "Lengjiacun",
    "gn:population": 0,
    "gn:timezone": "Asia/Shanghai",
    "iso:country": "CN",
    "name:und_x_variant": [
      "Lengjiawobao",
      "Lengjia Wobu"
    ],
    "name:zho_x_preferred": [
      "冷家村"
    ],
    "name:zho_x_variant": [
      "冷家窝堡"
    ],
    "wof:name": "Lengjiacun",
    "wof:placetype": "locality"
  },
  "geometry": {
    "coordinates": [
      122.005,
      42.62
    ],
    "type": "Point"
  }
}