{
  "type": "Feature",
  "properties": {
    "gn:admin1_code": "12.0",
    "gn:asciiname": "Mintian",
    "gn:country_code": "CN",
    "gn:dem": 26,
    "gn:feature_class": "P",
    "gn:feature_code": "PPLA4",
    "gn:name": "Mintian",
    "gn:population": 0,
    "gn:timezone": "Asia/Shanghai",
    "iso:country": "CN",
    "name:und_x_variant": [
      "民田",
      "Jinghe",
      "Jinghe Jiedao",
      "经河",
      "经河街道"
    ],
    "wof:name": "Mintian",
    "wof:placetype": "locality"
  },
  "geometry": {
    "coordinates": [
      114.15912,
      30.68309
    ],
    "type": "Point"
  }
}