{
  "type": "Feature",
  "properties": {
    "gn:admin1_code": "16.0",
    "gn:asciiname": "Banding",
    "gn:country_code": "CN",
    "gn:dem": 164,
    "gn:feature_class": "P",
    "gn:feature_code": "PPL",
    "gn:name": "Banding",
    "gn:population": 0,
    "gn:timezone": "Asia/Shanghai",
    "iso:country": "CN",
    "name:deu_x_preferred": [
      "Banding"
    ],
    "name:jpn_x_preferred": [
      "バンディング"
    ],
    "name:nld_x_preferred": [
      "Banding"
    ],
    "name:zho_x_preferred": [
      "板定"
    ],
    "wof:name": "Banding",
    "wof:placetype": "locality"
  },
  "geometry": {
    "coordinates": [
      108.439,
      24.1176
    ],
    "type": "Point"
  }
}