{
  "type": "Feature",
  "properties": {
    "gn:admin1_code": "29.0",
    "gn:asciiname": "Yanjiao",
    "gn:country_code": "CN",
    "gn:dem": 1866,
    "gn:feature_class": "P",
    "gn:feature_code": "PPL",
    "gn:name": "Yanjiao",
    "gn:population": 0,
    "gn:timezone": "Asia/Shanghai",
    "iso:country": "CN",
    "name:zho_x_preferred": [
      "岩脚"
    ],
    "name:zho_x_variant": [
      "燕郊镇"
    ],
    "wof:name": "Yanjiao",
    "wof:placetype": "locality"
  },
  "geometry": {
    "coordinates": [
      98.9301,
      23.3438
    ],
    "type": "Point"
  }
}