{
  "type": "Feature",
  "properties": {
    "gn:admin1_code": "18",
    "gn:asciiname": "Daguochang",
    "gn:country_code": "CN",
    "gn:dem": 767,
    "gn:feature_class": "P",
    "gn:feature_code": "PPL",
    "gn:name": "Daguochang",
    "gn:population": 0,
    "gn:timezone": "Asia/Shanghai",
    "iso:country": "CN",
    "name:zho_x_preferred": [
      "大锅厂"
    ],
    "wof:name": "Daguochang",
    "wof:placetype": "locality"
  },
  "geometry": {
    "coordinates": [
      106.478,
      28.1287
    ],
    "type": "Point"
  }
}