{
  "type": "Feature",
  "properties": {
    "gn:admin1_code": "2.0",
    "gn:asciiname": "Huafeng",
    "gn:country_code": "CN",
    "gn:dem": 169,
    "gn:feature_class": "P",
    "gn:feature_code": "PPL",
    "gn:name": "Huafeng",
    "gn:population": 0,
    "gn:timezone": "Asia/Shanghai",
    "iso:country": "CN",
    "name:zho_x_preferred": [
      "华峰"
    ],
    "wof:name": "Huafeng",
    "wof:placetype": "locality"
  },
  "geometry": {
    "coordinates": [
      118.60538,
      28.6118
    ],
    "type": "Point"
  }
}