{
  "type": "Feature",
  "properties": {
    "gn:admin1_code": "4.0",
    "gn:asciiname": "Zhujiazhuang",
    "gn:country_code": "CN",
    "gn:dem": 6,
    "gn:feature_class": "P",
    "gn:feature_code": "PPL",
    "gn:name": "Zhujiazhuang",
    "gn:population": 0,
    "gn:timezone": "Asia/Shanghai",
    "iso:country": "CN",
    "name:zho_x_preferred": [
      "朱家庄"
    ],
    "wof:name": "Zhujiazhuang",
    "wof:placetype": "locality"
  },
  "geometry": {
    "coordinates": [
      119.53364,
      32.8559
    ],
    "type": "Point"
  }
}