{
  "type": "Feature",
  "properties": {
    "gn:admin1_code": "7.0",
    "gn:asciiname": "Xiaze",
    "gn:country_code": "CN",
    "gn:dem": 743,
    "gn:feature_class": "P",
    "gn:feature_code": "PPL",
    "gn:name": "Xiaze",
    "gn:population": 0,
    "gn:timezone": "Asia/Shanghai",
    "iso:country": "CN",
    "name:zho_x_preferred": [
      "下则"
    ],
    "wof:name": "Xiaze",
    "wof:placetype": "locality"
  },
  "geometry": {
    "coordinates": [
      118.45665,
      25.94964
    ],
    "type": "Point"
  }
}