{
  "type": "Feature",
  "properties": {
    "gn:admin1_code": "9",
    "gn:asciiname": "Guozhuyuan",
    "gn:country_code": "CN",
    "gn:dem": 41,
    "gn:feature_class": "P",
    "gn:feature_code": "PPL",
    "gn:name": "Guozhuyuan",
    "gn:population": 0,
    "gn:timezone": "Asia/Shanghai",
    "iso:country": "CN",
    "name:zho_x_preferred": [
      "郭竹园"
    ],
    "wof:name": "Guozhuyuan",
    "wof:placetype": "locality"
  },
  "geometry": {
    "coordinates": [
      115.505,
      33.7276
    ],
    "type": "Point"
  }
}