{
  "type": "Feature",
  "properties": {
    "gn:admin1_code": "32.0",
    "gn:asciiname": "Mase",
    "gn:country_code": "CN",
    "gn:dem": 3817,
    "gn:feature_class": "P",
    "gn:feature_code": "PPL",
    "gn:name": "Mase",
    "gn:population": 0,
    "gn:timezone": "Asia/Shanghai",
    "iso:country": "CN",
    "name:ast_x_preferred": [
      "Mase"
    ],
    "name:ces_x_preferred": [
      "Mase"
    ],
    "name:dan_x_preferred": [
      "Mase"
    ],
    "name:deu_x_preferred": [
      "Mase"
    ],
    "name:fas_x_preferred": [
      "میس"
    ],
    "name:fin_x_preferred": [
      "Ma$e"
    ],
    "name:fra_x_preferred": [
      "Ma$e"
    ],
    "name:ita_x_preferred": [
      "Ma$e"
    ],
    "name:jpn_x_preferred": [
      "メイス"
    ],
    "name:kor_x_preferred": [
      "메이스"
    ],
    "name:nld_x_preferred": [
      "Ma$e"
    ],
    "name:por_x_preferred": [
      "Mase"
    ],
    "name:rus_x_preferred": [
      "Mase"
    ],
    "name:spa_x_preferred": [
      "Mase"
    ],
    "name:swa_x_preferred": [
      "Mase"
    ],
    "name:swe_x_preferred": [
      "Mase"
    ],
    "name:tur_x_preferred": [
      "Mase"
    ],
    "name:zho_x_preferred": [
      "马色"
    ],
    "wof:name": "Mase",
    "wof:placetype": "locality"
  },
  "geometry": {
    "coordinates": [
      101.423,
      29.8676
    ],
    "type": "Point"
  }
}