{
  "type": "Feature",
  "properties": {
    "gn:admin1_code": "12.0",
    "gn:asciiname": "Huangjiatian",
    "gn:country_code": "CN",
    "gn:dem": 98,
    "gn:feature_class": "P",
    "gn:feature_code": "PPL",
    "gn:name": "Huangjiatian",
    "gn:population": 0,
    "gn:timezone": "Asia/Shanghai",
    "iso:country": "CN",
    "name:zho_x_preferred": [
      "黄家田"
    ],
    "wof:name": "Huangjiatian",
    "wof:placetype": "locality"
  },
  "geometry": {
    "coordinates": [
      114.86825,
      31.40598
    ],
    "type": "Point"
  }
}