{
  "type": "Feature",
  "properties": {
    "gn:admin1_code": "26.0",
    "gn:asciiname": "Hongyangou",
    "gn:country_code": "CN",
    "gn:dem": 970,
    "gn:feature_class": "P",
    "gn:feature_code": "PPL",
    "gn:name": "Hongyangou",
    "gn:population": 0,
    "gn:timezone": "Asia/Shanghai",
    "iso:country": "CN",
    "name:zho_x_preferred": [
      "红岩沟"
    ],
    "wof:name": "Hongyangou",
    "wof:placetype": "locality"
  },
  "geometry": {
    "coordinates": [
      110.34821,
      33.27008
    ],
    "type": "Point"
  }
}