{
  "type": "Feature",
  "properties": {
    "gn:admin1_code": "12",
    "gn:asciiname": "Guishan",
    "gn:country_code": "CN",
    "gn:dem": 299,
    "gn:feature_class": "P",
    "gn:feature_code": "PPLA4",
    "gn:name": "Guishan",
    "gn:population": 0,
    "gn:timezone": "Asia/Shanghai",
    "iso:country": "CN",
    "name:deu_x_preferred": [
      "Guishan"
    ],
    "name:kor_x_preferred": [
      "구이산"
    ],
    "name:und_x_variant": [
      "Guishan Xiang",
      "龟山乡"
    ],
    "name:zho_x_preferred": [
      "龟山"
    ],
    "wof:name": "Guishan",
    "wof:placetype": "locality"
  },
  "geometry": {
    "coordinates": [
      115.18184,
      31.07566
    ],
    "type": "Point"
  }
}