{
  "type": "Feature",
  "properties": {
    "gn:admin1_code": "16.0",
    "gn:asciiname": "Nayin",
    "gn:country_code": "CN",
    "gn:dem": 142,
    "gn:feature_class": "P",
    "gn:feature_code": "PPL",
    "gn:name": "Nayin",
    "gn:population": 0,
    "gn:timezone": "Asia/Shanghai",
    "iso:country": "CN",
    "name:zho_x_preferred": [
      "那印"
    ],
    "wof:name": "Nayin",
    "wof:placetype": "locality"
  },
  "geometry": {
    "coordinates": [
      106.903,
      22.2792
    ],
    "type": "Point"
  }
}