{
  "type": "Feature",
  "properties": {
    "gn:admin1_code": "30.0",
    "gn:asciiname": "Sansha",
    "gn:country_code": "CN",
    "gn:dem": -4,
    "gn:feature_class": "P",
    "gn:feature_code": "PPL",
    "gn:name": "Sansha",
    "gn:population": 0,
    "gn:timezone": "Asia/Shanghai",
    "iso:country": "CN",
    "name:ara_x_preferred": [
      "سانشا"
    ],
    "name:cat_x_preferred": [
      "Sansha"
    ],
    "name:cdo_x_preferred": [
      "Săng-să"
    ],
    "name:deu_x_preferred": [
      "Sansha"
    ],
    "name:fas_x_preferred": [
      "سانشا"
    ],
    "name:fin_x_preferred": [
      "Sansha"
    ],
    "name:fra_x_preferred": [
      "Sansha"
    ],
    "name:hak_x_preferred": [
      "Sâm-sâ-sṳ"
    ],
    "name:ita_x_preferred": [
      "Sansha"
    ],
    "name:jpn_x_preferred": [
      "三沙市"
    ],
    "name:kik_x_preferred": [
      "Sansha"
    ],
    "name:kor_x_preferred": [
      "싼사시"
    ],
    "name:msa_x_preferred": [
      "Sansha"
    ],
    "name:nor_x_preferred": [
      "Sansha"
    ],
    "name:pam_x_preferred": [
      "Sansha"
    ],
    "name:pol_x_preferred": [
      "Sansha"
    ],
    "name:por_x_preferred": [
      "Sansha"
    ],
    "name:rus_x_preferred": [
      "Саньша"
    ],
    "name:swe_x_preferred": [
      "Sansha"
    ],
    "name:tgl_x_preferred": [
      "Sansha"
    ],
    "name:tha_x_preferred": [
      "ซันชา"
    ],
    "name:tur_x_preferred": [
      "Sansha"
    ],
    "name:urd_x_preferred": [
      "سانشا"
    ],
    "name:vie_x_preferred": [
      "Tam Sa"
    ],
    "name:wuu_x_preferred": [
      "三沙市"
    ],
    "name:zho_x_preferred": [
      "三沙"
    ],
    "name:zho_x_variant": [
      "三沙市"
    ],
    "wof:name": "Sansha",
    "wof:placetype": "locality"
  },
  "geometry": {
    "coordinates": [
      113.49139,
      22.89172
    ],
    "type": "Point"
  }
}