{
  "type": "Feature",
  "properties": {
    "gn:admin1_code": "16.0",
    "gn:asciiname": "Daoping",
    "gn:country_code": "CN",
    "gn:dem": 64,
    "gn:feature_class": "P",
    "gn:feature_code": "PPL",
    "gn:name": "Daoping",
    "gn:population": 0,
    "gn:timezone": "Asia/Shanghai",
    "iso:country": "CN",
    "name:zho_x_preferred": [
      "道平"
    ],
    "wof:name": "Daoping",
    "wof:placetype": "locality"
  },
  "geometry": {
    "coordinates": [
      109.728,
      23.0259
    ],
    "type": "Point"
  }
}