{
  "type": "Feature",
  "properties": {
    "gn:admin1_code": "14.0",
    "gn:asciiname": "Ri'nga",
    "gn:country_code": "CN",
    "gn:dem": 4025,
    "gn:feature_class": "P",
    "gn:feature_code": "PPL",
    "gn:name": "Ri’nga",
    "gn:population": 0,
    "gn:timezone": "Asia/Urumqi",
    "iso:country": "CN",
    "name:bod_x_preferred": [
      "Ri’nga"
    ],
    "name:zho_x_preferred": [
      "Ren’a"
    ],
    "name:zho_x_variant": [
      "仁阿",
      "Dejilin Gongshe",
      "德吉林公社"
    ],
    "wof:name": "Ri'nga",
    "wof:placetype": "locality"
  },
  "geometry": {
    "coordinates": [
      89.90299999999998,
      29.20300000000001
    ],
    "type": "Point"
  }
}