{
  "type": "Feature",
  "properties": {
    "gn:admin1_code": "3.0",
    "gn:asciiname": "Niujiaoguo",
    "gn:country_code": "CN",
    "gn:dem": 545,
    "gn:feature_class": "P",
    "gn:feature_code": "PPL",
    "gn:name": "Niujiaoguo",
    "gn:population": 0,
    "gn:timezone": "Asia/Shanghai",
    "iso:country": "CN",
    "name:zho_x_preferred": [
      "牛角埚"
    ],
    "wof:name": "Niujiaoguo",
    "wof:placetype": "locality"
  },
  "geometry": {
    "coordinates": [
      114.293,
      29.349
    ],
    "type": "Point"
  }
}