{
  "type": "Feature",
  "properties": {
    "gn:admin1_code": "19",
    "gn:asciiname": "Tianshifu",
    "gn:country_code": "CN",
    "gn:dem": 285,
    "gn:feature_class": "P",
    "gn:feature_code": "PPLA4",
    "gn:name": "Tianshifu",
    "gn:population": 0,
    "gn:timezone": "Asia/Shanghai",
    "iso:country": "CN",
    "name:und_x_variant": [
      "T’ien-shih-fu-kow",
      "T’ien-shih-fu-ku-k’ou",
      "Tien-shi-fu",
      "T’ien-shih-fu-kou",
      "T’ien-shih-fu-kou-k’ou",
      "T’ien-tzu-fu-kou-k’ou",
      "T’ien-shih-fu",
      "T’ien-tzu-fu",
      "Tianshifu",
      "田师付",
      "Tianshifu Zhen",
      "Dapu",
      "田师付镇",
      "大堡"
    ],
    "name:zho_x_preferred": [
      "田师傅镇"
    ],
    "wof:name": "Tianshifu",
    "wof:placetype": "locality"
  },
  "geometry": {
    "coordinates": [
      124.35313,
      41.25563
    ],
    "type": "Point"
  }
}