{
  "type": "Feature",
  "properties": {
    "gn:country": "CN",
    "gn:fcode": "PPL",
    "gn:population": 0,
    "iso:country": "CN",
    "name:deu_x_preferred": [
      "Shule"
    ],
    "name:eng_x_preferred": [
      "Shule County"
    ],
    "name:fas_x_preferred": [
      "شهرستان شوله"
    ],
    "name:fin_x_preferred": [
      "Shule"
    ],
    "name:gan_x_preferred": [
      "疏勒县"
    ],
    "name:jpn_x_preferred": [
      "疏勒県"
    ],
    "name:kor_x_preferred": [
      "수러현"
    ],
    "name:nan_x_preferred": [
      "So͘-le̍k-koān"
    ],
    "name:nld_x_preferred": [
      "Shule"
    ],
    "name:nob_x_preferred": [
      "Shule"
    ],
    "name:pol_x_preferred": [
      "Shule"
    ],
    "name:rus_x_preferred": [
      "Янгишар"
    ],
    "name:swe_x_preferred": [
      "Shule"
    ],
    "name:uig_x_preferred": [
      "Yengixəh̨ər"
    ],
    "name:uig_x_variant": [
      "Yéngisheher",
      "يېڭىشەھەر",
      "Еңишәһәр"
    ],
    "name:und_x_variant": [
      "Su-lo"
    ],
    "name:urd_x_preferred": [
      "شولے کاؤنٹی"
    ],
    "name:vie_x_preferred": [
      "Sơ Lặc"
    ],
    "name:wuu_x_preferred": [
      "疏勒县"
    ],
    "name:zho_x_preferred": [
      "疏勒"
    ],
    "name:zho_x_variant": [
      "疏勒县"
    ],
    "qs:name": "疏勒",
    "qs:name_adm0": "中國",
    "qs:name_adm1": "新疆维吾尔自治区",
    "qs:photos": 12,
    "qs:photos_1k": 2,
    "qs:photos_9k": 1,
    "qs:photos_9r": 1,
    "qs:photos_all": 12,
    "qs:photos_sr": 1,
    "qs:placetype": "Town",
    "qs:pop_sr": "6",
    "wd:wordcount": 85,
    "wof:name": "疏勒",
    "wof:placetype": "locality",
    "wof:population": 0
  },
  "geometry": {
    "coordinates": [
      76.04,
      39.39139
    ],
    "type": "Point"
  }
}