{
  "type": "Feature",
  "properties": {
    "gn:admin1_code": "07",
    "gn:asciiname": "Maodi",
    "gn:country_code": "CN",
    "gn:dem": 780,
    "gn:feature_class": "P",
    "gn:feature_code": "PPLA4",
    "gn:name": "Maodi",
    "gn:population": 0,
    "gn:timezone": "Asia/Shanghai",
    "iso:country": "CN",
    "name:und_x_variant": [
      "Mao-ti",
      "Maodi",
      "茂地",
      "Maodi Zhen",
      "茂地镇"
    ],
    "wof:name": "Maodi",
    "wof:placetype": "locality"
  },
  "geometry": {
    "coordinates": [
      118.07365,
      26.70251
    ],
    "type": "Point"
  }
}