{
  "type": "Feature",
  "properties": {
    "gn:country": "CN",
    "gn:fcode": "PPL",
    "gn:population": 153714,
    "iso:country": "CN",
    "name:cym_x_preferred": [
      "Ardal Sanshui"
    ],
    "name:deu_x_preferred": [
      "Sanshui"
    ],
    "name:eng_x_preferred": [
      "Sanshui District"
    ],
    "name:fas_x_preferred": [
      "سانشوی"
    ],
    "name:gan_x_preferred": [
      "三水区"
    ],
    "name:hak_x_preferred": [
      "Sâm-súi-khî"
    ],
    "name:jpn_x_preferred": [
      "三水区"
    ],
    "name:kor_x_preferred": [
      "싼수이구"
    ],
    "name:mwl_x_preferred": [
      "Sanshui"
    ],
    "name:nan_x_preferred": [
      "Sam-súi-khu"
    ],
    "name:nld_x_preferred": [
      "Sanshui"
    ],
    "name:nob_x_preferred": [
      "Sanshui"
    ],
    "name:spa_x_preferred": [
      "Sanshui"
    ],
    "name:swe_x_preferred": [
      "Sanshui"
    ],
    "name:und_x_variant": [
      "Sainam"
    ],
    "name:vie_x_preferred": [
      "Tam Thủy"
    ],
    "name:wuu_x_preferred": [
      "三水区"
    ],
    "name:yue_x_preferred": [
      "三水"
    ],
    "name:zho_x_preferred": [
      "三水"
    ],
    "name:zho_x_variant": [
      "三水区"
    ],
    "qs:name": "Sanshui",
    "qs:photos_9r": 0,
    "qs:photos_sr": 0,
    "qs:pop_sr": "9",
    "wd:wordcount": 426,
    "wof:name": "Sanshui",
    "wof:placetype": "locality",
    "wof:population": 153714
  },
  "geometry": {
    "coordinates": [
      112.89161,
      23.15486
    ],
    "type": "Point"
  }
}