{
  "type": "Feature",
  "properties": {
    "gn:admin1_code": "10",
    "gn:asciiname": "Xishan",
    "gn:country_code": "CN",
    "gn:dem": 1081,
    "gn:feature_class": "P",
    "gn:feature_code": "PPL",
    "gn:name": "Xishan",
    "gn:population": 0,
    "gn:timezone": "Asia/Shanghai",
    "iso:country": "CN",
    "name:ceb_x_preferred": [
      "Xishan"
    ],
    "name:deu_x_preferred": [
      "Xishan"
    ],
    "name:fra_x_preferred": [
      "Xishan"
    ],
    "name:kor_x_preferred": [
      "시산구"
    ],
    "name:mlg_x_preferred": [
      "Xishan"
    ],
    "name:nor_x_preferred": [
      "Xishan"
    ],
    "name:rus_x_preferred": [
      "Сишань"
    ],
    "name:swe_x_preferred": [
      "Xishan"
    ],
    "name:zho_x_preferred": [
      "西山"
    ],
    "wof:name": "Xishan",
    "wof:placetype": "locality"
  },
  "geometry": {
    "coordinates": [
      116.39145,
      41.2489
    ],
    "type": "Point"
  }
}