{
  "type": "Feature",
  "properties": {
    "gn:admin1_code": "30",
    "gn:asciiname": "Huangwu Linchang",
    "gn:country_code": "CN",
    "gn:dem": 92,
    "gn:feature_class": "P",
    "gn:feature_code": "PPLF",
    "gn:name": "Huangwu Linchang",
    "gn:population": 0,
    "gn:timezone": "Asia/Shanghai",
    "iso:country": "CN",
    "name:und_x_variant": [
      "Danxia Linchang",
      "Huangwu Linchang",
      "黄屋林场"
    ],
    "wof:name": "Huangwu Linchang",
    "wof:placetype": "locality"
  },
  "geometry": {
    "coordinates": [
      113.76,
      25.06
    ],
    "type": "Point"
  }
}