{
  "type": "Feature",
  "properties": {
    "gn:admin1_code": "19.0",
    "gn:asciiname": "Housifangtai",
    "gn:country_code": "CN",
    "gn:dem": 36,
    "gn:feature_class": "P",
    "gn:feature_code": "PPL",
    "gn:name": "Housifangtai",
    "gn:population": 0,
    "gn:timezone": "Asia/Shanghai",
    "iso:country": "CN",
    "name:zho_x_preferred": [
      "后四方台"
    ],
    "wof:name": "Housifangtai",
    "wof:placetype": "locality"
  },
  "geometry": {
    "coordinates": [
      120.471,
      40.405
    ],
    "type": "Point"
  }
}