{
  "type": "Feature",
  "properties": {
    "gn:admin1_code": "11.0",
    "gn:asciiname": "Badouqiu",
    "gn:country_code": "CN",
    "gn:dem": 317,
    "gn:feature_class": "P",
    "gn:feature_code": "PPL",
    "gn:name": "Badouqiu",
    "gn:population": 0,
    "gn:timezone": "Asia/Shanghai",
    "iso:country": "CN",
    "name:zho_x_preferred": [
      "Badouqiu"
    ],
    "name:zho_x_variant": [
      "八斗丘"
    ],
    "wof:name": "Badouqiu",
    "wof:placetype": "locality"
  },
  "geometry": {
    "coordinates": [
      111.07137,
      29.1291
    ],
    "type": "Point"
  }
}