{
  "type": "Feature",
  "properties": {
    "gn:admin1_code": "3.0",
    "gn:asciiname": "Qiantang",
    "gn:country_code": "CN",
    "gn:dem": 278,
    "gn:feature_class": "P",
    "gn:feature_code": "PPL",
    "gn:name": "Qiantang",
    "gn:population": 0,
    "gn:timezone": "Asia/Shanghai",
    "iso:country": "CN",
    "name:deu_x_preferred": [
      "Qiantang"
    ],
    "name:ita_x_preferred": [
      "Qiantang"
    ],
    "name:und_x_variant": [
      "潜塘"
    ],
    "wof:name": "Qiantang",
    "wof:placetype": "locality"
  },
  "geometry": {
    "coordinates": [
      114.05597,
      28.06482
    ],
    "type": "Point"
  }
}