{
  "type": "Feature",
  "properties": {
    "gn:admin1_code": "10",
    "gn:asciiname": "Yongcheng",
    "gn:country_code": "CN",
    "gn:dem": 11,
    "gn:feature_class": "P",
    "gn:feature_code": "PPL",
    "gn:name": "Yongcheng",
    "gn:population": 0,
    "gn:timezone": "Asia/Shanghai",
    "iso:country": "CN",
    "name:ara_x_preferred": [
      "يونغتشينغ"
    ],
    "name:deu_x_preferred": [
      "Yongcheng"
    ],
    "name:fra_x_preferred": [
      "Yongcheng"
    ],
    "name:ita_x_preferred": [
      "Yongcheng"
    ],
    "name:jpn_x_preferred": [
      "永城市"
    ],
    "name:kik_x_preferred": [
      "Yongcheng"
    ],
    "name:kor_x_preferred": [
      "융청시"
    ],
    "name:mlg_x_preferred": [
      "Yongcheng"
    ],
    "name:nor_x_preferred": [
      "Yongcheng"
    ],
    "name:pam_x_preferred": [
      "Yongcheng"
    ],
    "name:rus_x_preferred": [
      "Юнчэн"
    ],
    "name:swe_x_preferred": [
      "Yongcheng"
    ],
    "name:urd_x_preferred": [
      "یونگچینگ"
    ],
    "name:vie_x_preferred": [
      "Vĩnh Thành"
    ],
    "name:zho_x_preferred": [
      "拥城"
    ],
    "name:zho_x_variant": [
      "永城市"
    ],
    "wof:name": "Yongcheng",
    "wof:placetype": "locality"
  },
  "geometry": {
    "coordinates": [
      115.864,
      38.7528
    ],
    "type": "Point"
  }
}