{
  "type": "Feature",
  "properties": {
    "gn:admin1_code": "14.0",
    "gn:asciiname": "Namling",
    "gn:country_code": "CN",
    "gn:dem": 4004,
    "gn:feature_class": "P",
    "gn:feature_code": "PPLA3",
    "gn:name": "Namling",
    "gn:population": 0,
    "gn:timezone": "Asia/Urumqi",
    "iso:country": "CN",
    "name:bod_x_preferred": [
      "Namling"
    ],
    "name:fas_x_preferred": [
      "ناملینگ"
    ],
    "name:msa_x_preferred": [
      "Namlingxoi"
    ],
    "name:und_x_variant": [
      "Na-mu-lin-tsung",
      "Nan-mu-lin",
      "Na-lin",
      "Na-mu-ling-hsün",
      "Na-mu-ling-tsung",
      "Namling Dzong",
      "Na-mu-ling",
      "Nanmulin Zhen"
    ],
    "name:zho_x_preferred": [
      "Nanmulin"
    ],
    "name:zho_x_variant": [
      "南木林",
      "Renwu",
      "仁伍",
      "南木林镇"
    ],
    "wof:name": "Namling",
    "wof:placetype": "locality"
  },
  "geometry": {
    "coordinates": [
      89.09555999999998,
      29.68527000000001
    ],
    "type": "Point"
  }
}