{
  "type": "Feature",
  "properties": {
    "gn:admin1_code": "10",
    "gn:asciiname": "Luanzhou",
    "gn:country_code": "CN",
    "gn:dem": 34,
    "gn:feature_class": "P",
    "gn:feature_code": "PPLA3",
    "gn:name": "Luanzhou",
    "gn:population": 0,
    "gn:timezone": "Asia/Shanghai",
    "iso:country": "CN",
    "name:deu_x_preferred": [
      "Luanzhou"
    ],
    "name:fas_x_preferred": [
      "شهرستان لوانژوو"
    ],
    "name:ita_x_preferred": [
      "Luanzhou"
    ],
    "name:jpn_x_preferred": [
      "ラン州市"
    ],
    "name:kor_x_preferred": [
      "롼저우시"
    ],
    "name:nor_x_preferred": [
      "Luan"
    ],
    "name:rus_x_preferred": [
      "Луаньчжоу"
    ],
    "name:swe_x_preferred": [
      "Luan"
    ],
    "name:und_x_variant": [
      "Lwanchow",
      "Luan-hsien-ch’eng",
      "Lwanhsien",
      "Luan-hsien-ch’eng-kuan",
      "Luan-hsien",
      "Lu-an",
      "Luan-chou",
      "Luan Xian"
    ],
    "name:urd_x_preferred": [
      "لوانژؤ"
    ],
    "name:vie_x_preferred": [
      "Loan Châu"
    ],
    "name:zho_x_preferred": [
      "滦州"
    ],
    "name:zho_x_variant": [
      "滦县",
      "滦州市"
    ],
    "wof:name": "Luanzhou",
    "wof:placetype": "locality"
  },
  "geometry": {
    "coordinates": [
      118.73333,
      39.75
    ],
    "type": "Point"
  }
}