{
  "type": "Feature",
  "properties": {
    "gn:admin1_code": "15.0",
    "gn:asciiname": "Zuitou",
    "gn:country_code": "CN",
    "gn:dem": 1945,
    "gn:feature_class": "P",
    "gn:feature_code": "PPL",
    "gn:name": "Zuitou",
    "gn:population": 0,
    "gn:timezone": "Asia/Shanghai",
    "iso:country": "CN",
    "name:zho_x_preferred": [
      "咀头"
    ],
    "name:zho_x_variant": [
      "咀头镇"
    ],
    "wof:name": "Zuitou",
    "wof:placetype": "locality"
  },
  "geometry": {
    "coordinates": [
      104.962,
      35.5759
    ],
    "type": "Point"
  }
}