{
  "type": "Feature",
  "properties": {
    "gn:admin1_code": "10",
    "gn:asciiname": "Laochangzigou",
    "gn:country_code": "CN",
    "gn:dem": 359,
    "gn:feature_class": "P",
    "gn:feature_code": "PPL",
    "gn:name": "Laochangzigou",
    "gn:population": 0,
    "gn:timezone": "Asia/Shanghai",
    "iso:country": "CN",
    "name:zho_x_preferred": [
      "老厂子沟"
    ],
    "wof:name": "Laochangzigou",
    "wof:placetype": "locality"
  },
  "geometry": {
    "coordinates": [
      119.27157,
      40.3192
    ],
    "type": "Point"
  }
}