{
  "type": "Feature",
  "properties": {
    "gn:admin1_code": "4.0",
    "gn:asciiname": "Bangxing",
    "gn:country_code": "CN",
    "gn:dem": 6,
    "gn:feature_class": "P",
    "gn:feature_code": "PPL",
    "gn:name": "Bangxing",
    "gn:population": 0,
    "gn:timezone": "Asia/Shanghai",
    "iso:country": "CN",
    "name:ceb_x_preferred": [
      "Bangxing"
    ],
    "name:fas_x_preferred": [
      "بانگشینگ"
    ],
    "name:fra_x_preferred": [
      "Bangxing"
    ],
    "name:msa_x_preferred": [
      "Bangxing"
    ],
    "name:swe_x_preferred": [
      "Bangxing"
    ],
    "name:zho_x_preferred": [
      "傍杏"
    ],
    "name:zho_x_variant": [
      "旁辛乡"
    ],
    "wof:name": "Bangxing",
    "wof:placetype": "locality"
  },
  "geometry": {
    "coordinates": [
      119.09446,
      31.88096
    ],
    "type": "Point"
  }
}