{
  "type": "Feature",
  "properties": {
    "gn:admin1_code": "2.0",
    "gn:asciiname": "Jinlingtou",
    "gn:country_code": "CN",
    "gn:dem": 598,
    "gn:feature_class": "P",
    "gn:feature_code": "PPL",
    "gn:name": "Jinlingtou",
    "gn:population": 0,
    "gn:timezone": "Asia/Shanghai",
    "iso:country": "CN",
    "name:zho_x_preferred": [
      "金岭头"
    ],
    "wof:name": "Jinlingtou",
    "wof:placetype": "locality"
  },
  "geometry": {
    "coordinates": [
      119.90883,
      28.62435
    ],
    "type": "Point"
  }
}