{
  "type": "Feature",
  "properties": {
    "gn:admin1_code": "25",
    "gn:asciiname": "Dazhuanggao",
    "gn:country_code": "CN",
    "gn:dem": 125,
    "gn:feature_class": "P",
    "gn:feature_code": "PPL",
    "gn:name": "Dazhuanggao",
    "gn:population": 0,
    "gn:timezone": "Asia/Shanghai",
    "iso:country": "CN",
    "name:zho_x_preferred": [
      "大庄皋"
    ],
    "wof:name": "Dazhuanggao",
    "wof:placetype": "locality"
  },
  "geometry": {
    "coordinates": [
      118.948,
      36.4267
    ],
    "type": "Point"
  }
}