{
  "type": "Feature",
  "properties": {
    "gn:admin1_code": "32.0",
    "gn:asciiname": "Zhaojiawan",
    "gn:country_code": "CN",
    "gn:dem": 461,
    "gn:feature_class": "P",
    "gn:feature_code": "PPL",
    "gn:name": "Zhaojiawan",
    "gn:population": 0,
    "gn:timezone": "Asia/Shanghai",
    "iso:country": "CN",
    "name:zho_x_preferred": [
      "赵家塆"
    ],
    "wof:name": "Zhaojiawan",
    "wof:placetype": "locality"
  },
  "geometry": {
    "coordinates": [
      105.09169,
      30.41372
    ],
    "type": "Point"
  }
}