{
  "type": "Feature",
  "properties": {
    "gn:admin1_code": "31.0",
    "gn:asciiname": "Shangxianpo",
    "gn:country_code": "CN",
    "gn:dem": 9,
    "gn:feature_class": "P",
    "gn:feature_code": "PPL",
    "gn:name": "Shangxianpo",
    "gn:population": 0,
    "gn:timezone": "Asia/Shanghai",
    "iso:country": "CN",
    "name:zho_x_preferred": [
      "Shangxianpo"
    ],
    "name:zho_x_variant": [
      "尚贤坡"
    ],
    "wof:name": "Shangxianpo",
    "wof:placetype": "locality"
  },
  "geometry": {
    "coordinates": [
      110.68627,
      19.91687
    ],
    "type": "Point"
  }
}