{
  "type": "Feature",
  "properties": {
    "gn:admin1_code": "19.0",
    "gn:asciiname": "Xiaodian",
    "gn:country_code": "CN",
    "gn:dem": 560,
    "gn:feature_class": "P",
    "gn:feature_code": "PPL",
    "gn:name": "Xiaodian",
    "gn:population": 0,
    "gn:timezone": "Asia/Shanghai",
    "iso:country": "CN",
    "name:zho_x_preferred": [
      "小店"
    ],
    "wof:name": "Xiaodian",
    "wof:placetype": "locality"
  },
  "geometry": {
    "coordinates": [
      119.16729,
      40.98691
    ],
    "type": "Point"
  }
}