{
  "type": "Feature",
  "properties": {
    "gn:admin1_code": "10",
    "gn:asciiname": "Luogezhuang",
    "gn:country_code": "CN",
    "gn:dem": 41,
    "gn:feature_class": "P",
    "gn:feature_code": "PPL",
    "gn:name": "Luogezhuang",
    "gn:population": 0,
    "gn:timezone": "Asia/Shanghai",
    "iso:country": "CN",
    "name:zho_x_preferred": [
      "骆各庄"
    ],
    "wof:name": "Luogezhuang",
    "wof:placetype": "locality"
  },
  "geometry": {
    "coordinates": [
      117.95729,
      40.12372
    ],
    "type": "Point"
  }
}