{
  "type": "Feature",
  "properties": {
    "gn:admin1_code": "15.0",
    "gn:asciiname": "Suheinian",
    "gn:country_code": "CN",
    "gn:dem": 2217,
    "gn:feature_class": "P",
    "gn:feature_code": "PPL",
    "gn:name": "Suheinian",
    "gn:population": 0,
    "gn:timezone": "Asia/Shanghai",
    "iso:country": "CN",
    "name:zho_x_preferred": [
      "苏黑念"
    ],
    "wof:name": "Suheinian",
    "wof:placetype": "locality"
  },
  "geometry": {
    "coordinates": [
      103.487,
      35.7171
    ],
    "type": "Point"
  }
}