{
  "type": "Feature",
  "properties": {
    "gn:admin1_code": "18",
    "gn:asciiname": "Baiguoyuan",
    "gn:country_code": "CN",
    "gn:dem": 966,
    "gn:feature_class": "P",
    "gn:feature_code": "PPL",
    "gn:name": "Baiguoyuan",
    "gn:population": 0,
    "gn:timezone": "Asia/Shanghai",
    "iso:country": "CN",
    "name:zho_x_preferred": [
      "白果园"
    ],
    "wof:name": "Baiguoyuan",
    "wof:placetype": "locality"
  },
  "geometry": {
    "coordinates": [
      106.769,
      27.4848
    ],
    "type": "Point"
  }
}