{
  "type": "Feature",
  "properties": {
    "gn:admin1_code": "8.0",
    "gn:asciiname": "Zhaojiagang",
    "gn:country_code": "CN",
    "gn:dem": 182,
    "gn:feature_class": "P",
    "gn:feature_code": "PPL",
    "gn:name": "Zhaojiagang",
    "gn:population": 0,
    "gn:timezone": "Asia/Shanghai",
    "iso:country": "CN",
    "name:zho_x_preferred": [
      "赵家岗"
    ],
    "name:zho_x_variant": [
      "赵家岗土家族乡"
    ],
    "wof:name": "Zhaojiagang",
    "wof:placetype": "locality"
  },
  "geometry": {
    "coordinates": [
      125.86394,
      45.77231
    ],
    "type": "Point"
  }
}