{
  "type": "Feature",
  "properties": {
    "gn:admin1_code": "12.0",
    "gn:asciiname": "Santangwan",
    "gn:country_code": "CN",
    "gn:dem": 58,
    "gn:feature_class": "P",
    "gn:feature_code": "PPL",
    "gn:name": "Santangwan",
    "gn:population": 0,
    "gn:timezone": "Asia/Shanghai",
    "iso:country": "CN",
    "name:zho_x_preferred": [
      "三唐湾"
    ],
    "wof:name": "Santangwan",
    "wof:placetype": "locality"
  },
  "geometry": {
    "coordinates": [
      113.98882,
      31.12211
    ],
    "type": "Point"
  }
}