{
  "type": "Feature",
  "properties": {
    "gn:admin1_code": "4.0",
    "gn:asciiname": "Sima",
    "gn:country_code": "CN",
    "gn:dem": 9,
    "gn:feature_class": "P",
    "gn:feature_code": "PPL",
    "gn:name": "Sima",
    "gn:population": 0,
    "gn:timezone": "Asia/Shanghai",
    "iso:country": "CN",
    "name:ceb_x_preferred": [
      "Sima"
    ],
    "name:deu_x_preferred": [
      "Sima"
    ],
    "name:ell_x_preferred": [
      "Σήμα"
    ],
    "name:est_x_preferred": [
      "Sima"
    ],
    "name:fin_x_preferred": [
      "Sima"
    ],
    "name:fra_x_preferred": [
      "Sima"
    ],
    "name:heb_x_preferred": [
      "סימה"
    ],
    "name:hye_x_preferred": [
      "Սիմա"
    ],
    "name:ind_x_preferred": [
      "Sima"
    ],
    "name:ita_x_preferred": [
      "Sima"
    ],
    "name:jav_x_preferred": [
      "Sima"
    ],
    "name:kan_x_preferred": [
      "ಸಿಮಾ"
    ],
    "name:new_x_preferred": [
      "सिमा गाविस"
    ],
    "name:nld_x_preferred": [
      "Sima"
    ],
    "name:pol_x_preferred": [
      "Sima"
    ],
    "name:ron_x_preferred": [
      "Sima"
    ],
    "name:rus_x_preferred": [
      "Сима"
    ],
    "name:slk_x_preferred": [
      "Sima"
    ],
    "name:slv_x_preferred": [
      "Sima"
    ],
    "name:spa_x_preferred": [
      "Sima"
    ],
    "name:swe_x_preferred": [
      "Sima"
    ],
    "name:tgl_x_preferred": [
      "Sima"
    ],
    "name:ukr_x_preferred": [
      "Сима"
    ],
    "name:und_x_variant": [
      "Hsi-ma",
      "Hsi-ma-chen",
      "Xima"
    ],
    "name:zho_x_preferred": [
      "嘶马"
    ],
    "wof:name": "Sima",
    "wof:placetype": "locality"
  },
  "geometry": {
    "coordinates": [
      119.77386,
      32.33898
    ],
    "type": "Point"
  }
}