{
  "type": "Feature",
  "properties": {
    "gn:admin1_code": "32.0",
    "gn:asciiname": "Heping",
    "gn:country_code": "CN",
    "gn:dem": 516,
    "gn:feature_class": "P",
    "gn:feature_code": "PPL",
    "gn:name": "Heping",
    "gn:population": 0,
    "gn:timezone": "Asia/Shanghai",
    "iso:country": "CN",
    "name:ceb_x_preferred": [
      "Heping"
    ],
    "name:deu_x_preferred": [
      "Heping"
    ],
    "name:eus_x_preferred": [
      "Heping"
    ],
    "name:fra_x_preferred": [
      "Heping"
    ],
    "name:jpn_x_preferred": [
      "和平区"
    ],
    "name:kor_x_preferred": [
      "허핑구"
    ],
    "name:nor_x_preferred": [
      "Heping"
    ],
    "name:sco_x_preferred": [
      "Heping"
    ],
    "name:swe_x_preferred": [
      "Heping"
    ],
    "name:vie_x_preferred": [
      "Hòa Bình"
    ],
    "name:zho_x_preferred": [
      "和平"
    ],
    "name:zho_x_variant": [
      "和平区"
    ],
    "wof:name": "Heping",
    "wof:placetype": "locality"
  },
  "geometry": {
    "coordinates": [
      105.339,
      31.6197
    ],
    "type": "Point"
  }
}