{
  "type": "Feature",
  "properties": {
    "gn:admin1_code": "29.0",
    "gn:asciiname": "Chayelin",
    "gn:country_code": "CN",
    "gn:dem": 1251,
    "gn:feature_class": "P",
    "gn:feature_code": "PPL",
    "gn:name": "Chayelin",
    "gn:population": 0,
    "gn:timezone": "Asia/Shanghai",
    "iso:country": "CN",
    "name:zho_x_preferred": [
      "茶叶林"
    ],
    "wof:name": "Chayelin",
    "wof:placetype": "locality"
  },
  "geometry": {
    "coordinates": [
      98.9138,
      23.9883
    ],
    "type": "Point"
  }
}