{
  "type": "Feature",
  "properties": {
    "gn:admin1_code": "30",
    "gn:asciiname": "Jianghu",
    "gn:country_code": "CN",
    "gn:dem": 28,
    "gn:feature_class": "P",
    "gn:feature_code": "PPLA4",
    "gn:name": "Jianghu",
    "gn:population": 0,
    "gn:timezone": "Asia/Urumqi",
    "iso:country": "CN",
    "name:und_x_variant": [
      "Jianghu Zhen",
      "江湖镇"
    ],
    "name:zho_x_preferred": [
      "江湖"
    ],
    "wof:name": "Jianghu",
    "wof:placetype": "locality"
  },
  "geometry": {
    "coordinates": [
      110.60472,
      21.87083
    ],
    "type": "Point"
  }
}