{
  "type": "Feature",
  "properties": {
    "gn:admin1_code": "18",
    "gn:asciiname": "Wangcao",
    "gn:country_code": "CN",
    "gn:dem": 695,
    "gn:feature_class": "P",
    "gn:feature_code": "PPLA4",
    "gn:name": "Wangcao",
    "gn:population": 0,
    "gn:timezone": "Asia/Shanghai",
    "iso:country": "CN",
    "name:und_x_variant": [
      "Wang-ts’ao-pa",
      "Wangcaoba",
      "Wang-ts’ao-ch’ang",
      "Wangcao",
      "Wangcao Zhen"
    ],
    "name:zho_x_preferred": [
      "旺草"
    ],
    "name:zho_x_variant": [
      "旺草镇"
    ],
    "wof:name": "Wangcao",
    "wof:placetype": "locality"
  },
  "geometry": {
    "coordinates": [
      107.26672,
      28.11711
    ],
    "type": "Point"
  }
}