{
  "type": "Feature",
  "properties": {
    "gn:country": "CN",
    "gn:fcode": "PPL",
    "gn:population": 425,
    "iso:country": "CN",
    "name:cym_x_preferred": [
      "Ardal Baodi"
    ],
    "name:deu_x_preferred": [
      "Baodi"
    ],
    "name:eng_x_preferred": [
      "Baodi District"
    ],
    "name:eus_x_preferred": [
      "Baodi Barrutia"
    ],
    "name:gan_x_preferred": [
      "宝坻区"
    ],
    "name:jpn_x_preferred": [
      "宝テイ区"
    ],
    "name:kor_x_preferred": [
      "바오디구"
    ],
    "name:nan_x_preferred": [
      "Pó-tî-khu"
    ],
    "name:nld_x_preferred": [
      "Baodi District"
    ],
    "name:nob_x_preferred": [
      "Baodi"
    ],
    "name:rus_x_preferred": [
      "Баоди"
    ],
    "name:swe_x_preferred": [
      "Baodi"
    ],
    "name:urd_x_preferred": [
      "باودی ضلع"
    ],
    "name:vie_x_preferred": [
      "Bảo Trì"
    ],
    "name:wuu_x_preferred": [
      "宝坻区"
    ],
    "name:zho_x_preferred": [
      "宝坻区"
    ],
    "qs:name": "Datangzhuang",
    "qs:photos_9r": 0,
    "qs:photos_sr": 0,
    "qs:pop_sr": "2",
    "wd:wordcount": 192,
    "wof:name": "Datangzhuang",
    "wof:placetype": "locality",
    "wof:population": 425
  },
  "geometry": {
    "coordinates": [
      117.34306,
      39.98667
    ],
    "type": "Point"
  }
}