{
  "type": "Feature",
  "properties": {
    "gn:country": "CN",
    "gn:fcode": "PPL",
    "gn:population": 82641,
    "iso:country": "CN",
    "name:ara_x_preferred": [
      "بيجو"
    ],
    "name:ben_x_preferred": [
      "পিঝু"
    ],
    "name:dan_x_preferred": [
      "Pizhou"
    ],
    "name:deu_x_preferred": [
      "Pizhou"
    ],
    "name:ell_x_preferred": [
      "Πίζου"
    ],
    "name:eng_x_preferred": [
      "Pizhou"
    ],
    "name:fin_x_preferred": [
      "Pizhou"
    ],
    "name:fra_x_preferred": [
      "Pizhou"
    ],
    "name:gan_x_preferred": [
      "邳州市"
    ],
    "name:guj_x_preferred": [
      "પીઝોઉ"
    ],
    "name:hin_x_preferred": [
      "पिज़्हौ"
    ],
    "name:ind_x_preferred": [
      "Pizhou"
    ],
    "name:ita_x_preferred": [
      "Pizhou"
    ],
    "name:jpn_x_preferred": [
      "ヒ州市"
    ],
    "name:kan_x_preferred": [
      "ಪಿಝೌ"
    ],
    "name:kik_x_preferred": [
      "Pizhou"
    ],
    "name:kor_x_preferred": [
      "피저우시"
    ],
    "name:lav_x_preferred": [
      "Pižou"
    ],
    "name:lit_x_preferred": [
      "Pižou"
    ],
    "name:mar_x_preferred": [
      "पिझोउ"
    ],
    "name:msa_x_preferred": [
      "Pizhou"
    ],
    "name:nan_x_preferred": [
      "Phi-chiu-chhī"
    ],
    "name:nld_x_preferred": [
      "Pizhou"
    ],
    "name:nob_x_preferred": [
      "Pizhou"
    ],
    "name:pol_x_preferred": [
      "Pizhou"
    ],
    "name:rus_x_preferred": [
      "Пичжоу"
    ],
    "name:sin_x_preferred": [
      "පිසෞ"
    ],
    "name:swe_x_preferred": [
      "Pizhou"
    ],
    "name:tam_x_preferred": [
      "பிஷோவு"
    ],
    "name:tel_x_preferred": [
      "పిజ్హౌ"
    ],
    "name:tgl_x_preferred": [
      "Pizhou"
    ],
    "name:tha_x_preferred": [
      "ผีโจว"
    ],
    "name:tur_x_preferred": [
      "Pizhou"
    ],
    "name:ukr_x_preferred": [
      "Пічжоу"
    ],
    "name:und_x_variant": [
      "P’ei-hsien"
    ],
    "name:urd_x_preferred": [
      "پیزحوو"
    ],
    "name:vie_x_preferred": [
      "Bi Châu"
    ],
    "name:wuu_x_preferred": [
      "邳州市"
    ],
    "name:yue_x_preferred": [
      "邳州"
    ],
    "name:zho_x_preferred": [
      "邳州市"
    ],
    "qs:name": "Pizhou",
    "qs:name_adm0": "中國",
    "qs:name_adm1": "江苏省",
    "qs:photos_9k": 1,
    "qs:photos_9r": 1,
    "qs:photos_all": 1,
    "qs:photos_sr": 0,
    "qs:placetype": "Town",
    "qs:pop_sr": "8",
    "wd:wordcount": 372,
    "wof:name": "Pizhou",
    "wof:placetype": "locality",
    "wof:population": 82641
  },
  "geometry": {
    "coordinates": [
      117.95028,
      34.31139
    ],
    "type": "Point"
  }
}