{
  "type": "Feature",
  "properties": {
    "gn:admin1_code": "10.0",
    "gn:asciiname": "Rulin",
    "gn:country_code": "CN",
    "gn:dem": 10,
    "gn:feature_class": "P",
    "gn:feature_code": "PPL",
    "gn:name": "Rulin",
    "gn:population": 0,
    "gn:timezone": "Asia/Shanghai",
    "iso:country": "CN",
    "name:zho_x_preferred": [
      "儒林"
    ],
    "name:zho_x_variant": [
      "儒林镇"
    ],
    "wof:name": "Rulin",
    "wof:placetype": "locality"
  },
  "geometry": {
    "coordinates": [
      116.778,
      38.5072
    ],
    "type": "Point"
  }
}