{
  "type": "Feature",
  "properties": {
    "gn:admin1_code": "4.0",
    "gn:asciiname": "Bayicun",
    "gn:country_code": "CN",
    "gn:dem": 4,
    "gn:feature_class": "P",
    "gn:feature_code": "PPL",
    "gn:name": "Bayicun",
    "gn:population": 0,
    "gn:timezone": "Asia/Shanghai",
    "iso:country": "CN",
    "name:zho_x_preferred": [
      "八一村"
    ],
    "wof:name": "Bayicun",
    "wof:placetype": "locality"
  },
  "geometry": {
    "coordinates": [
      121.36853,
      31.99652
    ],
    "type": "Point"
  }
}