{
  "type": "Feature",
  "properties": {
    "gn:admin1_code": "16",
    "gn:asciiname": "Quanfeng",
    "gn:country_code": "CN",
    "gn:dem": 129,
    "gn:feature_class": "P",
    "gn:feature_code": "PPL",
    "gn:name": "Quanfeng",
    "gn:population": 0,
    "gn:timezone": "Asia/Shanghai",
    "iso:country": "CN",
    "name:zho_x_preferred": [
      "全凤"
    ],
    "name:zho_x_variant": [
      "泉峰街道"
    ],
    "wof:name": "Quanfeng",
    "wof:placetype": "locality"
  },
  "geometry": {
    "coordinates": [
      107.455,
      22.4078
    ],
    "type": "Point"
  }
}