{
  "type": "Feature",
  "properties": {
    "gn:admin1_code": "7.0",
    "gn:asciiname": "Keshan",
    "gn:country_code": "CN",
    "gn:dem": 939,
    "gn:feature_class": "P",
    "gn:feature_code": "PPL",
    "gn:name": "Keshan",
    "gn:population": 0,
    "gn:timezone": "Asia/Shanghai",
    "iso:country": "CN",
    "name:ara_x_preferred": [
      "كيشان"
    ],
    "name:ben_x_preferred": [
      "কেশান"
    ],
    "name:deu_x_preferred": [
      "Keshan"
    ],
    "name:ell_x_preferred": [
      "Κέσαν"
    ],
    "name:eng_x_preferred": [
      "Keshan"
    ],
    "name:fas_x_preferred": [
      "کشان"
    ],
    "name:fra_x_preferred": [
      "Keshan"
    ],
    "name:heb_x_preferred": [
      "קשאן"
    ],
    "name:hin_x_preferred": [
      "केशान"
    ],
    "name:hun_x_preferred": [
      "Keshan"
    ],
    "name:ind_x_preferred": [
      "Keshan"
    ],
    "name:ita_x_preferred": [
      "Keshan"
    ],
    "name:kor_x_preferred": [
      "케산"
    ],
    "name:nld_x_preferred": [
      "Keshan"
    ],
    "name:pol_x_preferred": [
      "Keshan"
    ],
    "name:por_x_preferred": [
      "Keshan"
    ],
    "name:rus_x_preferred": [
      "Кэшань"
    ],
    "name:spa_x_preferred": [
      "Keshan"
    ],
    "name:swe_x_preferred": [
      "Keshan"
    ],
    "name:tur_x_preferred": [
      "Keshan"
    ],
    "name:ukr_x_preferred": [
      "Кешань"
    ],
    "name:urd_x_preferred": [
      "کیشان"
    ],
    "name:vie_x_preferred": [
      "Khắc Sơn"
    ],
    "name:zho_x_preferred": [
      "科山"
    ],
    "wof:name": "Keshan",
    "wof:placetype": "locality"
  },
  "geometry": {
    "coordinates": [
      116.97825,
      25.22191
    ],
    "type": "Point"
  }
}