{
  "type": "Feature",
  "properties": {
    "gn:admin1_code": "3.0",
    "gn:asciiname": "Wenfeng",
    "gn:country_code": "CN",
    "gn:dem": 48,
    "gn:feature_class": "P",
    "gn:feature_code": "PPLA3",
    "gn:name": "Wenfeng",
    "gn:population": 0,
    "gn:timezone": "Asia/Shanghai",
    "iso:country": "CN",
    "name:ceb_x_preferred": [
      "Jishui Xian"
    ],
    "name:deu_x_preferred": [
      "Jishui"
    ],
    "name:fas_x_preferred": [
      "شهرستان جیشوی"
    ],
    "name:jpn_x_preferred": [
      "吉水県"
    ],
    "name:kor_x_preferred": [
      "지수이현"
    ],
    "name:nor_x_preferred": [
      "Jishui"
    ],
    "name:swe_x_preferred": [
      "Jishui"
    ],
    "name:und_x_variant": [
      "Kishui",
      "Chi-shui",
      "Kishuihsien",
      "Chi-shai-hsien",
      "Chi-shui-hsien-ch’eng",
      "Wenfeng",
      "文峰",
      "Wenfeng Zhen",
      "文峰镇"
    ],
    "name:vie_x_preferred": [
      "Cát Thủy"
    ],
    "name:zho_x_preferred": [
      "吉水县"
    ],
    "wof:name": "Wenfeng",
    "wof:placetype": "locality"
  },
  "geometry": {
    "coordinates": [
      115.11963,
      27.19899
    ],
    "type": "Point"
  }
}