{
  "type": "Feature",
  "properties": {
    "gn:admin1_code": "10",
    "gn:asciiname": "Changliu",
    "gn:country_code": "CN",
    "gn:dem": 46,
    "gn:feature_class": "P",
    "gn:feature_code": "PPL",
    "gn:name": "Changliu",
    "gn:population": 0,
    "gn:timezone": "Asia/Shanghai",
    "iso:country": "CN",
    "name:fas_x_preferred": [
      "چانگلیو"
    ],
    "name:zho_x_preferred": [
      "常刘"
    ],
    "name:zho_x_variant": [
      "长流镇"
    ],
    "wof:name": "Changliu",
    "wof:placetype": "locality"
  },
  "geometry": {
    "coordinates": [
      115.03872,
      36.7028
    ],
    "type": "Point"
  }
}