{
  "type": "Feature",
  "properties": {
    "gn:admin1_code": "29.0",
    "gn:asciiname": "Moyang",
    "gn:country_code": "CN",
    "gn:dem": 1146,
    "gn:feature_class": "P",
    "gn:feature_code": "PPL",
    "gn:name": "Moyang",
    "gn:population": 0,
    "gn:timezone": "Asia/Shanghai",
    "iso:country": "CN",
    "name:zho_x_preferred": [
      "莫秧"
    ],
    "wof:name": "Moyang",
    "wof:placetype": "locality"
  },
  "geometry": {
    "coordinates": [
      99.3892,
      22.4656
    ],
    "type": "Point"
  }
}