{
  "type": "Feature",
  "properties": {
    "gn:admin1_code": "01",
    "gn:asciiname": "Tanggou",
    "gn:country_code": "CN",
    "gn:dem": 9,
    "gn:feature_class": "P",
    "gn:feature_code": "PPL",
    "gn:name": "Tanggou",
    "gn:population": 0,
    "gn:timezone": "Asia/Shanghai",
    "iso:country": "CN",
    "name:und_x_variant": [
      "T’ang-chia-kou",
      "T’ang-kou",
      "Tangjiagou",
      "Tanggouzhen",
      "Tanggou Zhen",
      "汤沟镇",
      "Tanggou"
    ],
    "name:zho_x_preferred": [
      "汤沟"
    ],
    "wof:name": "Tanggou",
    "wof:placetype": "locality"
  },
  "geometry": {
    "coordinates": [
      118.17844,
      31.321
    ],
    "type": "Point"
  }
}