{
  "type": "Feature",
  "properties": {
    "gn:country": "CN",
    "gn:fcode": "PPLA3",
    "gn:population": 204368,
    "iso:country": "CN",
    "name:afr_x_preferred": [
      "Nanchong"
    ],
    "name:ara_x_preferred": [
      "نانتشونغ"
    ],
    "name:ben_x_preferred": [
      "নানচং"
    ],
    "name:cdo_x_preferred": [
      "Nàng-chṳ̆ng"
    ],
    "name:ceb_x_preferred": [
      "Nanchong"
    ],
    "name:ces_x_preferred": [
      "Nan-čchung"
    ],
    "name:dan_x_preferred": [
      "Nanchong"
    ],
    "name:deu_x_preferred": [
      "Nanchong"
    ],
    "name:ell_x_preferred": [
      "Νάντσονγκ"
    ],
    "name:eng_x_preferred": [
      "Nanchong"
    ],
    "name:eus_x_preferred": [
      "Nanchong"
    ],
    "name:fas_x_preferred": [
      "نانچونگ"
    ],
    "name:fin_x_preferred": [
      "Nanchong"
    ],
    "name:fra_x_preferred": [
      "Nanchong"
    ],
    "name:gan_x_preferred": [
      "南充市"
    ],
    "name:guj_x_preferred": [
      "નાનચોંગ"
    ],
    "name:hin_x_preferred": [
      "नान्चॉन्ग"
    ],
    "name:ind_x_preferred": [
      "Nanchong"
    ],
    "name:ita_x_preferred": [
      "Nanchong"
    ],
    "name:jpn_x_preferred": [
      "南充市"
    ],
    "name:kan_x_preferred": [
      "ನ್ಯಾಂಚೊಂಗ್"
    ],
    "name:kaz_x_preferred": [
      "Наньчун"
    ],
    "name:kik_x_preferred": [
      "Nanchong"
    ],
    "name:kor_x_preferred": [
      "난충 시"
    ],
    "name:kor_x_variant": [
      "난충시"
    ],
    "name:lav_x_preferred": [
      "Nančonga"
    ],
    "name:lit_x_preferred": [
      "Nančongas"
    ],
    "name:lzh_x_preferred": [
      "南充市"
    ],
    "name:mar_x_preferred": [
      "नानचॉँग"
    ],
    "name:msa_x_preferred": [
      "Nanchong"
    ],
    "name:nan_x_preferred": [
      "Lâm-chhiong-chhī"
    ],
    "name:nld_x_preferred": [
      "Nanchong"
    ],
    "name:nno_x_preferred": [
      "Nanchong"
    ],
    "name:nob_x_preferred": [
      "Nanchong"
    ],
    "name:pol_x_preferred": [
      "Nanchong"
    ],
    "name:por_x_preferred": [
      "Nanchong"
    ],
    "name:rus_x_preferred": [
      "Наньчун"
    ],
    "name:sin_x_preferred": [
      "නැන්චොන්ග්"
    ],
    "name:slv_x_preferred": [
      "Nanchong"
    ],
    "name:spa_x_preferred": [
      "Nanchong"
    ],
    "name:srp_x_preferred": [
      "Нанчунг"
    ],
    "name:swe_x_preferred": [
      "Nanchong"
    ],
    "name:tam_x_preferred": [
      "நன்சோங்"
    ],
    "name:tel_x_preferred": [
      "నాన్ చాంగ్"
    ],
    "name:tha_x_preferred": [
      "หนานชง"
    ],
    "name:tur_x_preferred": [
      "Nanchong"
    ],
    "name:ukr_x_preferred": [
      "Наньчун"
    ],
    "name:urd_x_preferred": [
      "نانچونگ"
    ],
    "name:vie_x_preferred": [
      "Nam Sung"
    ],
    "name:war_x_preferred": [
      "Nanchong"
    ],
    "name:wuu_x_preferred": [
      "南充市"
    ],
    "name:yue_x_preferred": [
      "南充"
    ],
    "name:zho_x_preferred": [
      "高坪"
    ],
    "name:zho_x_variant": [
      "南充市"
    ],
    "qs:name": "Gaoping",
    "qs:photos_9r": 0,
    "qs:photos_sr": 0,
    "qs:pop_sr": "10",
    "wd:wordcount": 336,
    "wof:name": "Gaoping",
    "wof:placetype": "locality",
    "wof:population": 204368
  },
  "geometry": {
    "coordinates": [
      106.10294,
      30.77576
    ],
    "type": "Point"
  }
}