{
  "type": "Feature",
  "properties": {
    "gn:admin1_code": "19.0",
    "gn:asciiname": "Ba'erhugou",
    "gn:country_code": "CN",
    "gn:dem": 45,
    "gn:feature_class": "P",
    "gn:feature_code": "PPL",
    "gn:name": "Ba’erhugou",
    "gn:population": 0,
    "gn:timezone": "Asia/Shanghai",
    "iso:country": "CN",
    "name:und_x_variant": [
      "Ba’erhugou"
    ],
    "name:zho_x_preferred": [
      "巴尔虎沟"
    ],
    "wof:name": "Ba'erhugou",
    "wof:placetype": "locality"
  },
  "geometry": {
    "coordinates": [
      121.832,
      39.6909
    ],
    "type": "Point"
  }
}