{
  "type": "Feature",
  "properties": {
    "gn:admin1_code": "29.0",
    "gn:asciiname": "Nandian",
    "gn:country_code": "CN",
    "gn:dem": 1639,
    "gn:feature_class": "P",
    "gn:feature_code": "PPL",
    "gn:name": "Nandian",
    "gn:population": 0,
    "gn:timezone": "Asia/Shanghai",
    "iso:country": "CN",
    "name:zho_x_preferred": [
      "南甸"
    ],
    "name:zho_x_variant": [
      "南甸镇"
    ],
    "wof:name": "Nandian",
    "wof:placetype": "locality"
  },
  "geometry": {
    "coordinates": [
      100.032,
      22.3955
    ],
    "type": "Point"
  }
}