{
  "type": "Feature",
  "properties": {
    "gn:admin1_code": "13.0",
    "gn:asciiname": "Qaxa",
    "gn:country_code": "CN",
    "gn:dem": 657,
    "gn:feature_class": "P",
    "gn:feature_code": "PPLA4",
    "gn:name": "Qaxa",
    "gn:population": 0,
    "gn:timezone": "Asia/Urumqi",
    "iso:country": "CN",
    "name:uig_x_preferred": [
      "Chasha"
    ],
    "name:uig_x_variant": [
      "چاشا",
      "Чаша"
    ],
    "name:und_x_variant": [
      "Qaxa Xiang",
      "Qaxa",
      "Qiaxia",
      "Qiaxia Xiang"
    ],
    "name:zho_x_preferred": [
      "恰夏"
    ],
    "name:zho_x_variant": [
      "恰夏乡"
    ],
    "wof:name": "Qaxa",
    "wof:placetype": "locality"
  },
  "geometry": {
    "coordinates": [
      83.4053,
      46.68861
    ],
    "type": "Point"
  }
}