{
  "type": "Feature",
  "properties": {
    "gn:admin1_code": "11",
    "gn:asciiname": "Xinwu Zhoujia",
    "gn:country_code": "CN",
    "gn:dem": 132,
    "gn:feature_class": "P",
    "gn:feature_code": "PPL",
    "gn:name": "Xinwu Zhoujia",
    "gn:population": 0,
    "gn:timezone": "Asia/Shanghai",
    "iso:country": "CN",
    "name:zho_x_preferred": [
      "新屋周家"
    ],
    "wof:name": "Xinwu Zhoujia",
    "wof:placetype": "locality"
  },
  "geometry": {
    "coordinates": [
      112.14169,
      26.39537
    ],
    "type": "Point"
  }
}