{
  "type": "Feature",
  "properties": {
    "gn:admin1_code": "30",
    "gn:asciiname": "Chashan",
    "gn:country_code": "CN",
    "gn:dem": 375,
    "gn:feature_class": "P",
    "gn:feature_code": "PPLA4",
    "gn:name": "Chashan",
    "gn:population": 0,
    "gn:timezone": "Asia/Urumqi",
    "iso:country": "CN",
    "name:fas_x_preferred": [
      "چاشان"
    ],
    "name:mlg_x_preferred": [
      "Chashan"
    ],
    "name:und_x_variant": [
      "Chashan Zhen"
    ],
    "name:zho_x_preferred": [
      "茶山"
    ],
    "name:zho_x_variant": [
      "茶山镇"
    ],
    "wof:name": "Chashan",
    "wof:placetype": "locality"
  },
  "geometry": {
    "coordinates": [
      111.13972,
      22.55778
    ],
    "type": "Point"
  }
}