{
  "type": "Feature",
  "properties": {
    "gn:admin1_code": "5.0",
    "gn:asciiname": "Sidaohuanggoucun",
    "gn:country_code": "CN",
    "gn:dem": 584,
    "gn:feature_class": "P",
    "gn:feature_code": "PPL",
    "gn:name": "Sidaohuanggoucun",
    "gn:population": 0,
    "gn:timezone": "Asia/Shanghai",
    "iso:country": "CN",
    "name:zho_x_preferred": [
      "四道荒沟村"
    ],
    "wof:name": "Sidaohuanggoucun",
    "wof:placetype": "locality"
  },
  "geometry": {
    "coordinates": [
      128.05681,
      43.15545
    ],
    "type": "Point"
  }
}