{
  "type": "Feature",
  "properties": {
    "gn:admin1_code": "3.0",
    "gn:asciiname": "Xixin",
    "gn:country_code": "CN",
    "gn:dem": 134,
    "gn:feature_class": "P",
    "gn:feature_code": "PPL",
    "gn:name": "Xixin",
    "gn:population": 0,
    "gn:timezone": "Asia/Shanghai",
    "iso:country": "CN",
    "name:und_x_variant": [
      "洗心"
    ],
    "wof:name": "Xixin",
    "wof:placetype": "locality"
  },
  "geometry": {
    "coordinates": [
      115.78664,
      27.1969
    ],
    "type": "Point"
  }
}