{
  "type": "Feature",
  "properties": {
    "gn:admin1_code": "9.0",
    "gn:asciiname": "Xiawan",
    "gn:country_code": "CN",
    "gn:dem": 1312,
    "gn:feature_class": "P",
    "gn:feature_code": "PPL",
    "gn:name": "Xiawan",
    "gn:population": 0,
    "gn:timezone": "Asia/Shanghai",
    "iso:country": "CN",
    "name:zho_x_preferred": [
      "下湾"
    ],
    "wof:name": "Xiawan",
    "wof:placetype": "locality"
  },
  "geometry": {
    "coordinates": [
      111.28723,
      33.94985
    ],
    "type": "Point"
  }
}