{
  "type": "Feature",
  "properties": {
    "gn:admin1_code": "30.0",
    "gn:asciiname": "Huitang",
    "gn:country_code": "CN",
    "gn:dem": 360,
    "gn:feature_class": "P",
    "gn:feature_code": "PPL",
    "gn:name": "Huitang",
    "gn:population": 0,
    "gn:timezone": "Asia/Shanghai",
    "iso:country": "CN",
    "name:fas_x_preferred": [
      "هویتانگ"
    ],
    "name:jpn_x_preferred": [
      "灰湯鎮"
    ],
    "name:zho_x_preferred": [
      "灰塘"
    ],
    "name:zho_x_variant": [
      "灰汤镇"
    ],
    "wof:name": "Huitang",
    "wof:placetype": "locality"
  },
  "geometry": {
    "coordinates": [
      112.21868,
      24.16503
    ],
    "type": "Point"
  }
}