{
  "type": "Feature",
  "properties": {
    "gn:admin1_code": "6.0",
    "gn:asciiname": "Jiande",
    "gn:country_code": "CN",
    "gn:dem": 3440,
    "gn:feature_class": "P",
    "gn:feature_code": "PPL",
    "gn:name": "Jiande",
    "gn:population": 0,
    "gn:timezone": "Asia/Shanghai",
    "iso:country": "CN",
    "name:deu_x_preferred": [
      "Jiande"
    ],
    "name:eus_x_preferred": [
      "Jiande"
    ],
    "name:fra_x_preferred": [
      "Jiande"
    ],
    "name:hak_x_preferred": [
      "Kien-tet-sṳ"
    ],
    "name:ita_x_preferred": [
      "Jiande"
    ],
    "name:jpn_x_preferred": [
      "建徳市"
    ],
    "name:kik_x_preferred": [
      "Jiande"
    ],
    "name:kor_x_preferred": [
      "젠더시"
    ],
    "name:nld_x_preferred": [
      "Jiande"
    ],
    "name:nor_x_preferred": [
      "Jiande"
    ],
    "name:pol_x_preferred": [
      "Jiande"
    ],
    "name:spa_x_preferred": [
      "Jiande"
    ],
    "name:swe_x_preferred": [
      "Jiande"
    ],
    "name:tgl_x_preferred": [
      "Jiate"
    ],
    "name:und_x_variant": [
      "尖德"
    ],
    "name:urd_x_preferred": [
      "جیاندو"
    ],
    "name:vie_x_preferred": [
      "Kiến Đức"
    ],
    "name:wuu_x_preferred": [
      "建德市"
    ],
    "name:zho_x_preferred": [
      "建德市"
    ],
    "wof:name": "Jiande",
    "wof:placetype": "locality"
  },
  "geometry": {
    "coordinates": [
      102.33897,
      35.23931
    ],
    "type": "Point"
  }
}