{
  "type": "Feature",
  "properties": {
    "gn:admin1_code": "1.0",
    "gn:asciiname": "Wuyue",
    "gn:country_code": "CN",
    "gn:dem": 21,
    "gn:feature_class": "P",
    "gn:feature_code": "PPL",
    "gn:name": "Wuyue",
    "gn:population": 0,
    "gn:timezone": "Asia/Shanghai",
    "iso:country": "CN",
    "name:ces_x_preferred": [
      "Wu-jüe"
    ],
    "name:deu_x_preferred": [
      "Wuyue-Reich"
    ],
    "name:fra_x_preferred": [
      "Wuyue"
    ],
    "name:hrv_x_preferred": [
      "Wuyue"
    ],
    "name:nor_x_preferred": [
      "Wuyue"
    ],
    "name:pol_x_preferred": [
      "Wuyue"
    ],
    "name:swe_x_preferred": [
      "Wuyue"
    ],
    "name:ukr_x_preferred": [
      "Уюе"
    ],
    "name:vie_x_preferred": [
      "Ngô Việt"
    ],
    "name:wuu_x_preferred": [
      "吴越国"
    ],
    "name:zho_x_preferred": [
      "五月"
    ],
    "name:zho_x_variant": [
      "吴越国"
    ],
    "wof:name": "Wuyue",
    "wof:placetype": "locality"
  },
  "geometry": {
    "coordinates": [
      118.16595,
      31.85673
    ],
    "type": "Point"
  }
}