{
  "type": "Feature",
  "properties": {
    "gn:admin1_code": "10.0",
    "gn:asciiname": "Xinzhuang",
    "gn:country_code": "CN",
    "gn:dem": 11,
    "gn:feature_class": "P",
    "gn:feature_code": "PPL",
    "gn:name": "Xinzhuang",
    "gn:population": 0,
    "gn:timezone": "Asia/Shanghai",
    "iso:country": "CN",
    "name:ceb_x_preferred": [
      "Xinzhuang"
    ],
    "name:deu_x_preferred": [
      "Xinzhuang"
    ],
    "name:zho_x_preferred": [
      "信庄"
    ],
    "wof:name": "Xinzhuang",
    "wof:placetype": "locality"
  },
  "geometry": {
    "coordinates": [
      119.02441,
      39.4793
    ],
    "type": "Point"
  }
}