{
  "type": "Feature",
  "properties": {
    "gn:admin1_code": "25",
    "gn:asciiname": "Longwangmiao",
    "gn:country_code": "CN",
    "gn:dem": 194,
    "gn:feature_class": "P",
    "gn:feature_code": "PPL",
    "gn:name": "Longwangmiao",
    "gn:population": 0,
    "gn:timezone": "Asia/Shanghai",
    "iso:country": "CN",
    "name:zho_x_preferred": [
      "龙王庙"
    ],
    "wof:name": "Longwangmiao",
    "wof:placetype": "locality"
  },
  "geometry": {
    "coordinates": [
      118.793,
      36.2904
    ],
    "type": "Point"
  }
}