{
  "type": "Feature",
  "properties": {
    "gn:admin1_code": "12.0",
    "gn:asciiname": "Tianxing",
    "gn:country_code": "CN",
    "gn:dem": 16,
    "gn:feature_class": "P",
    "gn:feature_code": "PPLA4",
    "gn:name": "Tianxing",
    "gn:population": 0,
    "gn:timezone": "Asia/Shanghai",
    "iso:country": "CN",
    "name:ceb_x_preferred": [
      "Tianxing"
    ],
    "name:deu_x_preferred": [
      "Tianxing"
    ],
    "name:swe_x_preferred": [
      "Tianxing"
    ],
    "name:und_x_variant": [
      "天兴",
      "Tianxing Xiang",
      "天兴乡"
    ],
    "wof:name": "Tianxing",
    "wof:placetype": "locality"
  },
  "geometry": {
    "coordinates": [
      114.41456,
      30.669
    ],
    "type": "Point"
  }
}