{
  "type": "Feature",
  "properties": {
    "gn:admin1_code": "15.0",
    "gn:asciiname": "Putao",
    "gn:country_code": "CN",
    "gn:dem": 998,
    "gn:feature_class": "P",
    "gn:feature_code": "PPL",
    "gn:name": "Putao",
    "gn:population": 0,
    "gn:timezone": "Asia/Shanghai",
    "iso:country": "CN",
    "name:cat_x_preferred": [
      "Putao"
    ],
    "name:deu_x_preferred": [
      "Putao"
    ],
    "name:ell_x_preferred": [
      "Πουτάο"
    ],
    "name:fra_x_preferred": [
      "Putao"
    ],
    "name:ita_x_preferred": [
      "Putao"
    ],
    "name:mya_x_preferred": [
      "ပူတာအိုမြို့"
    ],
    "name:shn_x_preferred": [
      "ပူႇတႂ်း၊ ဝဵင်း"
    ],
    "name:swe_x_preferred": [
      "Putao"
    ],
    "name:tha_x_preferred": [
      "ปูดาโอ"
    ],
    "name:zho_x_preferred": [
      "葡萄"
    ],
    "wof:name": "Putao",
    "wof:placetype": "locality"
  },
  "geometry": {
    "coordinates": [
      106.278,
      34.5244
    ],
    "type": "Point"
  }
}