{
  "type": "Feature",
  "properties": {
    "gn:admin1_code": "15.0",
    "gn:asciiname": "Lang'ertan",
    "gn:country_code": "CN",
    "gn:dem": 1804,
    "gn:feature_class": "P",
    "gn:feature_code": "PPL",
    "gn:name": "Lang’ertan",
    "gn:population": 0,
    "gn:timezone": "Asia/Shanghai",
    "iso:country": "CN",
    "name:und_x_variant": [
      "Lang’ertan",
      "狼儿滩"
    ],
    "wof:name": "Lang'ertan",
    "wof:placetype": "locality"
  },
  "geometry": {
    "coordinates": [
      106.70251,
      36.94541
    ],
    "type": "Point"
  }
}