{
  "type": "Feature",
  "properties": {
    "gn:admin1_code": "11.0",
    "gn:asciiname": "Washi",
    "gn:country_code": "CN",
    "gn:dem": 368,
    "gn:feature_class": "P",
    "gn:feature_code": "PPL",
    "gn:name": "Washi",
    "gn:population": 0,
    "gn:timezone": "Asia/Shanghai",
    "iso:country": "CN",
    "name:cat_x_preferred": [
      "Washi"
    ],
    "name:dan_x_preferred": [
      "Japanpapir"
    ],
    "name:deu_x_preferred": [
      "Japanpapier"
    ],
    "name:epo_x_preferred": [
      "Washi"
    ],
    "name:fas_x_preferred": [
      "واشی"
    ],
    "name:fin_x_preferred": [
      "Japaninpaperi"
    ],
    "name:fra_x_preferred": [
      "Washi"
    ],
    "name:hrv_x_preferred": [
      "Japanski papir"
    ],
    "name:hun_x_preferred": [
      "Vasi"
    ],
    "name:ind_x_preferred": [
      "Washi"
    ],
    "name:ita_x_preferred": [
      "Washi"
    ],
    "name:jav_x_preferred": [
      "Washi"
    ],
    "name:msa_x_preferred": [
      "Washi"
    ],
    "name:nld_x_preferred": [
      "Washi"
    ],
    "name:nno_x_preferred": [
      "Japanpapir"
    ],
    "name:nor_x_preferred": [
      "Japanpapir"
    ],
    "name:por_x_preferred": [
      "Washi"
    ],
    "name:ron_x_preferred": [
      "Washi"
    ],
    "name:rus_x_preferred": [
      "Васи"
    ],
    "name:spa_x_preferred": [
      "Washi"
    ],
    "name:swe_x_preferred": [
      "Japanpapper"
    ],
    "name:tur_x_preferred": [
      "Washi"
    ],
    "name:ukr_x_preferred": [
      "Японський папір"
    ],
    "name:vie_x_preferred": [
      "Giấy washi"
    ],
    "name:zho_x_preferred": [
      "瓦石"
    ],
    "wof:name": "Washi",
    "wof:placetype": "locality"
  },
  "geometry": {
    "coordinates": [
      112.51601,
      25.55147
    ],
    "type": "Point"
  }
}