{
  "type": "Feature",
  "properties": {
    "gn:admin1_code": "10",
    "gn:asciiname": "Nanqiao",
    "gn:country_code": "CN",
    "gn:dem": 113,
    "gn:feature_class": "P",
    "gn:feature_code": "PPLA4",
    "gn:name": "Nanqiao",
    "gn:population": 0,
    "gn:timezone": "Asia/Shanghai",
    "iso:country": "CN",
    "name:und_x_variant": [
      "南桥",
      "Nanqiao Zhen",
      "南桥镇"
    ],
    "wof:name": "Nanqiao",
    "wof:placetype": "locality"
  },
  "geometry": {
    "coordinates": [
      114.56206,
      38.51511
    ],
    "type": "Point"
  }
}