{
  "type": "Feature",
  "properties": {
    "gn:admin1_code": "14.0",
    "gn:asciiname": "Zanlalong",
    "gn:country_code": "CN",
    "gn:dem": 4267,
    "gn:feature_class": "P",
    "gn:feature_code": "PPL",
    "gn:name": "Zanlalong",
    "gn:population": 0,
    "gn:timezone": "Asia/Urumqi",
    "iso:country": "CN",
    "name:zho_x_preferred": [
      "咱拉拢"
    ],
    "wof:name": "Zanlalong",
    "wof:placetype": "locality"
  },
  "geometry": {
    "coordinates": [
      95.43483,
      30.79793
    ],
    "type": "Point"
  }
}