{
  "type": "Feature",
  "properties": {
    "gn:admin1_code": "32.0",
    "gn:asciiname": "Changxugongma",
    "gn:country_code": "CN",
    "gn:dem": 3931,
    "gn:feature_class": "P",
    "gn:feature_code": "PPL",
    "gn:name": "Changxugongma",
    "gn:population": 0,
    "gn:timezone": "Asia/Shanghai",
    "iso:country": "CN",
    "name:und_x_variant": [
      "Choxükongma",
      "Changxugongma"
    ],
    "name:zho_x_preferred": [
      "长须贡马"
    ],
    "wof:name": "Changxugongma",
    "wof:placetype": "locality"
  },
  "geometry": {
    "coordinates": [
      98.93901,
      32.76444
    ],
    "type": "Point"
  }
}