{
  "type": "Feature",
  "properties": {
    "gn:admin1_code": "33.0",
    "gn:asciiname": "Zhongshan",
    "gn:country_code": "CN",
    "gn:dem": 389,
    "gn:feature_class": "P",
    "gn:feature_code": "PPL",
    "gn:name": "Zhongshan",
    "gn:population": 0,
    "gn:timezone": "Asia/Shanghai",
    "iso:country": "CN",
    "name:ara_x_preferred": [
      "زونغشان"
    ],
    "name:cdo_x_preferred": [
      "Dṳ̆ng-săng"
    ],
    "name:ceb_x_preferred": [
      "Zhongshan Prefecture"
    ],
    "name:ces_x_preferred": [
      "Čung-šan"
    ],
    "name:cym_x_preferred": [
      "Zhongshan"
    ],
    "name:dan_x_preferred": [
      "Zhongshan"
    ],
    "name:deu_x_preferred": [
      "Zhongshan"
    ],
    "name:eus_x_preferred": [
      "Zhongshan"
    ],
    "name:fas_x_preferred": [
      "ژونگشان"
    ],
    "name:fin_x_preferred": [
      "Zhongshan"
    ],
    "name:fra_x_preferred": [
      "Zhongshan"
    ],
    "name:hak_x_preferred": [
      "Chûng-sân-sṳ"
    ],
    "name:ind_x_preferred": [
      "Zhongshan"
    ],
    "name:ita_x_preferred": [
      "Zhongshan"
    ],
    "name:jpn_x_preferred": [
      "中山市"
    ],
    "name:kik_x_preferred": [
      "Zhongshan"
    ],
    "name:kor_x_preferred": [
      "중산시"
    ],
    "name:mlg_x_preferred": [
      "Zhongshan"
    ],
    "name:nld_x_preferred": [
      "Zhongshan"
    ],
    "name:nno_x_preferred": [
      "Zhongshan"
    ],
    "name:nor_x_preferred": [
      "Zhongshan"
    ],
    "name:pam_x_preferred": [
      "Zhongshan"
    ],
    "name:pnb_x_preferred": [
      "ژونگشان"
    ],
    "name:pol_x_preferred": [
      "Zhongshan"
    ],
    "name:por_x_preferred": [
      "Zhongshan"
    ],
    "name:rus_x_preferred": [
      "Чжуншань"
    ],
    "name:sco_x_preferred": [
      "Zhongshan"
    ],
    "name:spa_x_preferred": [
      "Zhongshán"
    ],
    "name:srp_x_preferred": [
      "Џунгшан"
    ],
    "name:swa_x_preferred": [
      "Zhongshan"
    ],
    "name:swe_x_preferred": [
      "Zhongshan"
    ],
    "name:tgl_x_preferred": [
      "Zhongshan"
    ],
    "name:tur_x_preferred": [
      "Zhongshan"
    ],
    "name:uig_x_preferred": [
      "Jongshen shehiri"
    ],
    "name:urd_x_preferred": [
      "ژونگشان"
    ],
    "name:vie_x_preferred": [
      "Trung Sơn"
    ],
    "name:war_x_preferred": [
      "Zhongshan"
    ],
    "name:zho_x_preferred": [
      "中山"
    ],
    "name:zho_x_variant": [
      "中山市"
    ],
    "wof:name": "Zhongshan",
    "wof:placetype": "locality"
  },
  "geometry": {
    "coordinates": [
      107.81788,
      30.24211
    ],
    "type": "Point"
  }
}