{
  "type": "Feature",
  "properties": {
    "gn:admin1_code": "25",
    "gn:asciiname": "Hulin",
    "gn:country_code": "CN",
    "gn:dem": 98,
    "gn:feature_class": "P",
    "gn:feature_code": "PPL",
    "gn:name": "Hulin",
    "gn:population": 0,
    "gn:timezone": "Asia/Shanghai",
    "iso:country": "CN",
    "name:ara_x_preferred": [
      "هولين"
    ],
    "name:deu_x_preferred": [
      "Hulin"
    ],
    "name:ell_x_preferred": [
      "Χουλίν"
    ],
    "name:fas_x_preferred": [
      "هولین"
    ],
    "name:fra_x_preferred": [
      "Hulin"
    ],
    "name:heb_x_preferred": [
      "חולין"
    ],
    "name:hin_x_preferred": [
      "ह्यूलिन"
    ],
    "name:hun_x_preferred": [
      "Hulin"
    ],
    "name:ind_x_preferred": [
      "Hulin"
    ],
    "name:ita_x_preferred": [
      "Hulin"
    ],
    "name:jpn_x_preferred": [
      "虎林市"
    ],
    "name:kik_x_preferred": [
      "Hulin"
    ],
    "name:kor_x_preferred": [
      "후린시"
    ],
    "name:mlg_x_preferred": [
      "Hulin"
    ],
    "name:nld_x_preferred": [
      "Hulin"
    ],
    "name:nor_x_preferred": [
      "Hulin"
    ],
    "name:pam_x_preferred": [
      "Hulin"
    ],
    "name:pol_x_preferred": [
      "Hulin"
    ],
    "name:por_x_preferred": [
      "Hulín"
    ],
    "name:rus_x_preferred": [
      "Хулинь"
    ],
    "name:spa_x_preferred": [
      "Hulin"
    ],
    "name:swe_x_preferred": [
      "Hulin"
    ],
    "name:ukr_x_preferred": [
      "Хулінь"
    ],
    "name:urd_x_preferred": [
      "ہولن"
    ],
    "name:vie_x_preferred": [
      "Hổ Lâm"
    ],
    "name:zho_x_preferred": [
      "胡林"
    ],
    "name:zho_x_variant": [
      "虎林市"
    ],
    "wof:name": "Hulin",
    "wof:placetype": "locality"
  },
  "geometry": {
    "coordinates": [
      116.643,
      36.3856
    ],
    "type": "Point"
  }
}