{
  "type": "Feature",
  "properties": {
    "gn:admin1_code": "24.0",
    "gn:asciiname": "Dujiata",
    "gn:country_code": "CN",
    "gn:dem": 1010,
    "gn:feature_class": "P",
    "gn:feature_code": "PPL",
    "gn:name": "Dujiata",
    "gn:population": 0,
    "gn:timezone": "Asia/Shanghai",
    "iso:country": "CN",
    "name:zho_x_preferred": [
      "杜家塔"
    ],
    "wof:name": "Dujiata",
    "wof:placetype": "locality"
  },
  "geometry": {
    "coordinates": [
      111.09424,
      38.80021
    ],
    "type": "Point"
  }
}