{
  "type": "Feature",
  "properties": {
    "gn:admin1_code": "4.0",
    "gn:asciiname": "Lanshan",
    "gn:country_code": "CN",
    "gn:dem": 26,
    "gn:feature_class": "P",
    "gn:feature_code": "PPL",
    "gn:name": "Lanshan",
    "gn:population": 0,
    "gn:timezone": "Asia/Shanghai",
    "iso:country": "CN",
    "name:ceb_x_preferred": [
      "Lanshan"
    ],
    "name:deu_x_preferred": [
      "Lanshan"
    ],
    "name:fra_x_preferred": [
      "Lanshan"
    ],
    "name:nor_x_preferred": [
      "Lanshan"
    ],
    "name:rus_x_preferred": [
      "Ланьшань"
    ],
    "name:swe_x_preferred": [
      "Lanshan"
    ],
    "wof:name": "Lanshan",
    "wof:placetype": "locality"
  },
  "geometry": {
    "coordinates": [
      117.725,
      33.93611
    ],
    "type": "Point"
  }
}