{
  "type": "Feature",
  "properties": {
    "gn:admin1_code": "19.0",
    "gn:asciiname": "Fanjiacun",
    "gn:country_code": "CN",
    "gn:dem": 14,
    "gn:feature_class": "P",
    "gn:feature_code": "PPL",
    "gn:name": "Fanjiacun",
    "gn:population": 0,
    "gn:timezone": "Asia/Shanghai",
    "iso:country": "CN",
    "name:zho_x_preferred": [
      "范家村"
    ],
    "wof:name": "Fanjiacun",
    "wof:placetype": "locality"
  },
  "geometry": {
    "coordinates": [
      122.176,
      41.5642
    ],
    "type": "Point"
  }
}