{
  "type": "Feature",
  "properties": {
    "gn:admin1_code": "16",
    "gn:asciiname": "Jingle",
    "gn:country_code": "CN",
    "gn:dem": 50,
    "gn:feature_class": "P",
    "gn:feature_code": "PPL",
    "gn:name": "Jingle",
    "gn:population": 0,
    "gn:timezone": "Asia/Shanghai",
    "iso:country": "CN",
    "name:ara_x_preferred": [
      "جلجل"
    ],
    "name:bar_x_preferred": [
      "Jingle"
    ],
    "name:cat_x_preferred": [
      "Jingle"
    ],
    "name:dan_x_preferred": [
      "Jingle"
    ],
    "name:deu_x_preferred": [
      "Jingle"
    ],
    "name:fas_x_preferred": [
      "زنگوله"
    ],
    "name:fin_x_preferred": [
      "Jingle"
    ],
    "name:fra_x_preferred": [
      "Jingle"
    ],
    "name:heb_x_preferred": [
      "זמריר"
    ],
    "name:jpn_x_preferred": [
      "ジングル"
    ],
    "name:nld_x_preferred": [
      "Jingle"
    ],
    "name:pol_x_preferred": [
      "Dżingiel"
    ],
    "name:por_x_preferred": [
      "Jingle"
    ],
    "name:rus_x_preferred": [
      "Джингл"
    ],
    "name:slv_x_preferred": [
      "Jingle"
    ],
    "name:spa_x_preferred": [
      "Jingle"
    ],
    "name:swe_x_preferred": [
      "Jingel"
    ],
    "name:tha_x_preferred": [
      "เพลงโฆษณา"
    ],
    "name:tur_x_preferred": [
      "Jingle"
    ],
    "name:ukr_x_preferred": [
      "Джинґл"
    ],
    "name:zho_x_preferred": [
      "景乐"
    ],
    "name:zho_x_variant": [
      "Jingle"
    ],
    "wof:name": "Jingle",
    "wof:placetype": "locality"
  },
  "geometry": {
    "coordinates": [
      109.927,
      23.1676
    ],
    "type": "Point"
  }
}