{
  "type": "Feature",
  "properties": {
    "gn:admin1_code": "19.0",
    "gn:asciiname": "Shahe Hougou",
    "gn:country_code": "CN",
    "gn:dem": 477,
    "gn:feature_class": "P",
    "gn:feature_code": "PPL",
    "gn:name": "Shahe Hougou",
    "gn:population": 0,
    "gn:timezone": "Asia/Shanghai",
    "iso:country": "CN",
    "name:zho_x_preferred": [
      "Shahe Hougou"
    ],
    "name:zho_x_variant": [
      "沙河后沟"
    ],
    "wof:name": "Shahe Hougou",
    "wof:placetype": "locality"
  },
  "geometry": {
    "coordinates": [
      124.93023,
      41.98248
    ],
    "type": "Point"
  }
}