{
  "type": "Feature",
  "properties": {
    "gn:admin1_code": "30",
    "gn:asciiname": "Nanlang",
    "gn:country_code": "CN",
    "gn:dem": 17,
    "gn:feature_class": "P",
    "gn:feature_code": "PPLA4",
    "gn:name": "Nanlang",
    "gn:population": 0,
    "gn:timezone": "Asia/Shanghai",
    "iso:country": "CN",
    "name:fas_x_preferred": [
      "نانلانگ"
    ],
    "name:mlg_x_preferred": [
      "Nanlang"
    ],
    "name:nld_x_preferred": [
      "Nanlang"
    ],
    "name:swe_x_preferred": [
      "Nanlang"
    ],
    "name:und_x_variant": [
      "Namlong",
      "Nan-lang-hsü",
      "Nanlang Zhen"
    ],
    "name:zho_x_preferred": [
      "南蓢"
    ],
    "name:zho_x_variant": [
      "南朗镇"
    ],
    "wof:name": "Nanlang",
    "wof:placetype": "locality"
  },
  "geometry": {
    "coordinates": [
      113.53736,
      22.49171
    ],
    "type": "Point"
  }
}