{
  "type": "Feature",
  "properties": {
    "gn:admin1_code": "8.0",
    "gn:asciiname": "Hejiacun",
    "gn:country_code": "CN",
    "gn:dem": 352,
    "gn:feature_class": "P",
    "gn:feature_code": "PPL",
    "gn:name": "Hejiacun",
    "gn:population": 0,
    "gn:timezone": "Asia/Shanghai",
    "iso:country": "CN",
    "name:zho_x_preferred": [
      "禾嘉村"
    ],
    "wof:name": "Hejiacun",
    "wof:placetype": "locality"
  },
  "geometry": {
    "coordinates": [
      130.40175,
      45.29432
    ],
    "type": "Point"
  }
}