{
  "type": "Feature",
  "properties": {
    "gn:admin1_code": "16.0",
    "gn:asciiname": "Huangni'ao",
    "gn:country_code": "CN",
    "gn:dem": 426,
    "gn:feature_class": "P",
    "gn:feature_code": "PPL",
    "gn:name": "Huangni’ao",
    "gn:population": 0,
    "gn:timezone": "Asia/Shanghai",
    "iso:country": "CN",
    "name:und_x_variant": [
      "Huangni’ao"
    ],
    "name:zho_x_preferred": [
      "黄坭坳"
    ],
    "wof:name": "Huangni'ao",
    "wof:placetype": "locality"
  },
  "geometry": {
    "coordinates": [
      108.831,
      25.2324
    ],
    "type": "Point"
  }
}