{
  "type": "Feature",
  "properties": {
    "gn:admin1_code": "23.0",
    "gn:asciiname": "Beige",
    "gn:country_code": "CN",
    "gn:dem": 5,
    "gn:feature_class": "P",
    "gn:feature_code": "PPL",
    "gn:name": "Beige",
    "gn:population": 0,
    "gn:timezone": "Asia/Shanghai",
    "iso:country": "CN",
    "name:afr_x_preferred": [
      "Beige"
    ],
    "name:ara_x_preferred": [
      "بيج"
    ],
    "name:bel_x_preferred": [
      "Бэж"
    ],
    "name:ben_x_preferred": [
      "বেজেরাঙা"
    ],
    "name:cat_x_preferred": [
      "Beix"
    ],
    "name:ces_x_preferred": [
      "Béžová"
    ],
    "name:dan_x_preferred": [
      "Beige"
    ],
    "name:eus_x_preferred": [
      "Beix"
    ],
    "name:fas_x_preferred": [
      "نخودی"
    ],
    "name:fra_x_preferred": [
      "Beige"
    ],
    "name:heb_x_preferred": [
      "בז'"
    ],
    "name:hin_x_preferred": [
      "बेज रंग"
    ],
    "name:ind_x_preferred": [
      "Krem"
    ],
    "name:ita_x_preferred": [
      "Beige"
    ],
    "name:jpn_x_preferred": [
      "ベージュ"
    ],
    "name:kor_x_preferred": [
      "베이지색"
    ],
    "name:nld_x_preferred": [
      "Beige"
    ],
    "name:nno_x_preferred": [
      "Besj"
    ],
    "name:nor_x_preferred": [
      "Beige"
    ],
    "name:nso_x_preferred": [
      "Beige"
    ],
    "name:pol_x_preferred": [
      "Barwa beżowa"
    ],
    "name:por_x_preferred": [
      "Bege"
    ],
    "name:rus_x_preferred": [
      "Беж"
    ],
    "name:slk_x_preferred": [
      "Béžová"
    ],
    "name:spa_x_preferred": [
      "Beige"
    ],
    "name:srp_x_preferred": [
      "Беж боја"
    ],
    "name:swe_x_preferred": [
      "Beige"
    ],
    "name:tur_x_preferred": [
      "Bej"
    ],
    "name:ukr_x_preferred": [
      "Бежевий колір"
    ],
    "name:vie_x_preferred": [
      "Màu be"
    ],
    "name:yid_x_preferred": [
      "בייזש"
    ],
    "name:zho_x_preferred": [
      "Beige"
    ],
    "name:zho_x_variant": [
      "北葛"
    ],
    "wof:name": "Beige",
    "wof:placetype": "locality"
  },
  "geometry": {
    "coordinates": [
      121.2314,
      31.21498
    ],
    "type": "Point"
  }
}