{
  "type": "Feature",
  "properties": {
    "gn:admin1_code": "19",
    "gn:asciiname": "Baoshan",
    "gn:country_code": "CN",
    "gn:dem": 84,
    "gn:feature_class": "P",
    "gn:feature_code": "PPLA4",
    "gn:name": "Baoshan",
    "gn:population": 0,
    "gn:timezone": "Asia/Shanghai",
    "iso:country": "CN",
    "name:ceb_x_preferred": [
      "Baoshan"
    ],
    "name:ces_x_preferred": [
      "Pao-šan"
    ],
    "name:deu_x_preferred": [
      "Baoshan"
    ],
    "name:eus_x_preferred": [
      "Baoshan"
    ],
    "name:fra_x_preferred": [
      "Baoshan"
    ],
    "name:heb_x_preferred": [
      "באושאן"
    ],
    "name:hun_x_preferred": [
      "Paosan"
    ],
    "name:mlg_x_preferred": [
      "Baoshan"
    ],
    "name:nld_x_preferred": [
      "Baoshan"
    ],
    "name:nor_x_preferred": [
      "Baoshan"
    ],
    "name:por_x_preferred": [
      "Baoshan"
    ],
    "name:rus_x_preferred": [
      "Баошань"
    ],
    "name:swe_x_preferred": [
      "Baoshan"
    ],
    "name:tur_x_preferred": [
      "Baoshan"
    ],
    "name:und_x_variant": [
      "宝山",
      "Baoshan Zhen",
      "宝山镇"
    ],
    "name:vie_x_preferred": [
      "Bảo Sơn"
    ],
    "wof:name": "Baoshan",
    "wof:placetype": "locality"
  },
  "geometry": {
    "coordinates": [
      123.8615,
      40.36384
    ],
    "type": "Point"
  }
}