{
  "type": "Feature",
  "properties": {
    "gn:admin1_code": "02",
    "gn:asciiname": "Chang'anqiaocun",
    "gn:country_code": "CN",
    "gn:dem": 6,
    "gn:feature_class": "P",
    "gn:feature_code": "PPL",
    "gn:name": "Chang’anqiaocun",
    "gn:population": 0,
    "gn:timezone": "Asia/Shanghai",
    "iso:country": "CN",
    "name:und_x_variant": [
      "Ch’ang-an-ch’iao",
      "Chang’anqiao",
      "长安桥",
      "Chang’anqiaocun"
    ],
    "name:zho_x_preferred": [
      "长安桥村"
    ],
    "wof:name": "Chang'anqiaocun",
    "wof:placetype": "locality"
  },
  "geometry": {
    "coordinates": [
      121.13831,
      30.63099
    ],
    "type": "Point"
  }
}