{
  "type": "Feature",
  "properties": {
    "gn:admin1_code": "10",
    "gn:asciiname": "Tangshugou",
    "gn:country_code": "CN",
    "gn:dem": 761,
    "gn:feature_class": "P",
    "gn:feature_code": "PPL",
    "gn:name": "Tangshugou",
    "gn:population": 0,
    "gn:timezone": "Asia/Shanghai",
    "iso:country": "CN",
    "name:zho_x_preferred": [
      "棠树沟"
    ],
    "wof:name": "Tangshugou",
    "wof:placetype": "locality"
  },
  "geometry": {
    "coordinates": [
      116.58241,
      41.23501
    ],
    "type": "Point"
  }
}