{
  "type": "Feature",
  "properties": {
    "gn:admin1_code": "04",
    "gn:asciiname": "Baqiao",
    "gn:country_code": "CN",
    "gn:dem": 6,
    "gn:feature_class": "P",
    "gn:feature_code": "PPLA4",
    "gn:name": "Baqiao",
    "gn:population": 0,
    "gn:timezone": "Asia/Shanghai",
    "iso:country": "CN",
    "name:und_x_variant": [
      "Pa-tzu-ch’iao",
      "Baqiao Zhen",
      "Pa-ch’iao-chen",
      "Baqiao"
    ],
    "name:zho_x_preferred": [
      "八桥"
    ],
    "name:zho_x_variant": [
      "八桥镇"
    ],
    "wof:name": "Baqiao",
    "wof:placetype": "locality"
  },
  "geometry": {
    "coordinates": [
      119.58244,
      32.67975999999999
    ],
    "type": "Point"
  }
}