{
  "type": "Feature",
  "properties": {
    "gn:admin1_code": "19.0",
    "gn:asciiname": "Zhaotuncun",
    "gn:country_code": "CN",
    "gn:dem": 46,
    "gn:feature_class": "P",
    "gn:feature_code": "PPL",
    "gn:name": "Zhaotuncun",
    "gn:population": 0,
    "gn:timezone": "Asia/Shanghai",
    "iso:country": "CN",
    "name:und_x_variant": [
      "Zhaotun",
      "赵屯"
    ],
    "name:zho_x_preferred": [
      "赵屯村"
    ],
    "wof:name": "Zhaotuncun",
    "wof:placetype": "locality"
  },
  "geometry": {
    "coordinates": [
      122.18335,
      39.53494
    ],
    "type": "Point"
  }
}