{
  "type": "Feature",
  "properties": {
    "gn:admin1_code": "16",
    "gn:asciiname": "Hezuo",
    "gn:country_code": "CN",
    "gn:dem": 297,
    "gn:feature_class": "P",
    "gn:feature_code": "PPL",
    "gn:name": "Hezuo",
    "gn:population": 0,
    "gn:timezone": "Asia/Shanghai",
    "iso:country": "CN",
    "name:ara_x_preferred": [
      "هيزو"
    ],
    "name:bod_x_preferred": [
      "གཙོས་གྲོང་ཁྱིར།"
    ],
    "name:deu_x_preferred": [
      "Hezuo"
    ],
    "name:fin_x_preferred": [
      "Hezuo"
    ],
    "name:fra_x_preferred": [
      "Hezuo"
    ],
    "name:ita_x_preferred": [
      "Hezuo"
    ],
    "name:jpn_x_preferred": [
      "合作市"
    ],
    "name:kik_x_preferred": [
      "Hezuo"
    ],
    "name:kor_x_preferred": [
      "허쭤시"
    ],
    "name:mlg_x_preferred": [
      "Hezuo"
    ],
    "name:mwl_x_preferred": [
      "Hezuo"
    ],
    "name:nor_x_preferred": [
      "Hezuo"
    ],
    "name:pam_x_preferred": [
      "Hezuo"
    ],
    "name:pnb_x_preferred": [
      "ہیزوؤ"
    ],
    "name:rus_x_preferred": [
      "Хэцзо"
    ],
    "name:spa_x_preferred": [
      "Hézuò Shì"
    ],
    "name:swe_x_preferred": [
      "Hezuo"
    ],
    "name:urd_x_preferred": [
      "ہیزوو"
    ],
    "name:vie_x_preferred": [
      "Hợp Tác"
    ],
    "name:zho_x_preferred": [
      "合作"
    ],
    "name:zho_x_variant": [
      "合作市"
    ],
    "wof:name": "Hezuo",
    "wof:placetype": "locality"
  },
  "geometry": {
    "coordinates": [
      110.047,
      25.5859
    ],
    "type": "Point"
  }
}