{
  "type": "Feature",
  "properties": {
    "gn:admin1_code": "19.0",
    "gn:asciiname": "Heshen",
    "gn:country_code": "CN",
    "gn:dem": 25,
    "gn:feature_class": "P",
    "gn:feature_code": "PPL",
    "gn:name": "Heshen",
    "gn:population": 0,
    "gn:timezone": "Asia/Shanghai",
    "iso:country": "CN",
    "name:ara_x_preferred": [
      "خو شين"
    ],
    "name:cat_x_preferred": [
      "Heshen"
    ],
    "name:cdo_x_preferred": [
      "Huò-sĭng"
    ],
    "name:deu_x_preferred": [
      "Heshen"
    ],
    "name:fra_x_preferred": [
      "Heshen"
    ],
    "name:jpn_x_preferred": [
      "ヘシェン"
    ],
    "name:kor_x_preferred": [
      "화신"
    ],
    "name:nld_x_preferred": [
      "Heshen"
    ],
    "name:nor_x_preferred": [
      "Heshen"
    ],
    "name:pol_x_preferred": [
      "Heshen"
    ],
    "name:rus_x_preferred": [
      "Хэшэнь"
    ],
    "name:spa_x_preferred": [
      "Heshen"
    ],
    "name:swe_x_preferred": [
      "Heshen"
    ],
    "name:tha_x_preferred": [
      "เหอเชิน"
    ],
    "name:vie_x_preferred": [
      "Hòa Thân"
    ],
    "name:zho_x_preferred": [
      "和申"
    ],
    "wof:name": "Heshen",
    "wof:placetype": "locality"
  },
  "geometry": {
    "coordinates": [
      122.324,
      41.7855
    ],
    "type": "Point"
  }
}