{
  "type": "Feature",
  "properties": {
    "gn:admin1_code": "29",
    "gn:asciiname": "Pingtian",
    "gn:country_code": "CN",
    "gn:dem": 1809,
    "gn:feature_class": "P",
    "gn:feature_code": "PPL",
    "gn:name": "Pingtian",
    "gn:population": 0,
    "gn:timezone": "Asia/Shanghai",
    "iso:country": "CN",
    "name:zho_x_preferred": [
      "平田"
    ],
    "wof:name": "Pingtian",
    "wof:placetype": "locality"
  },
  "geometry": {
    "coordinates": [
      101.658,
      25.1484
    ],
    "type": "Point"
  }
}