{
  "type": "Feature",
  "properties": {
    "gn:admin1_code": "14.0",
    "gn:asciiname": "Quxar",
    "gn:country_code": "CN",
    "gn:dem": 4950,
    "gn:feature_class": "P",
    "gn:feature_code": "PPLF",
    "gn:name": "Quxar",
    "gn:population": 0,
    "gn:timezone": "Asia/Urumqi",
    "iso:country": "CN",
    "name:bod_x_preferred": [
      "Quxar"
    ],
    "name:msa_x_preferred": [
      "Quxar"
    ],
    "name:zho_x_preferred": [
      "Quxia"
    ],
    "name:zho_x_variant": [
      "曲夏",
      "Gongbajiarao",
      "贡巴加绕",
      "曲下镇"
    ],
    "wof:name": "Quxar",
    "wof:placetype": "locality"
  },
  "geometry": {
    "coordinates": [
      89.803,
      28.503
    ],
    "type": "Point"
  }
}