{
  "type": "Feature",
  "properties": {
    "gn:admin1_code": "16.0",
    "gn:asciiname": "Nalang",
    "gn:country_code": "CN",
    "gn:dem": 129,
    "gn:feature_class": "P",
    "gn:feature_code": "PPL",
    "gn:name": "Nalang",
    "gn:population": 0,
    "gn:timezone": "Asia/Shanghai",
    "iso:country": "CN",
    "name:ceb_x_preferred": [
      "Nalang"
    ],
    "name:msa_x_preferred": [
      "Nalang"
    ],
    "name:new_x_preferred": [
      "नालाङ"
    ],
    "name:pol_x_preferred": [
      "Nalang"
    ],
    "name:zho_x_preferred": [
      "那琅"
    ],
    "wof:name": "Nalang",
    "wof:placetype": "locality"
  },
  "geometry": {
    "coordinates": [
      107.983,
      23.2421
    ],
    "type": "Point"
  }
}