{
  "type": "Feature",
  "properties": {
    "gn:admin1_code": "26.0",
    "gn:asciiname": "Maliangou",
    "gn:country_code": "CN",
    "gn:dem": 1338,
    "gn:feature_class": "P",
    "gn:feature_code": "PPL",
    "gn:name": "Maliangou",
    "gn:population": 0,
    "gn:timezone": "Asia/Shanghai",
    "iso:country": "CN",
    "name:zho_x_preferred": [
      "麻莲沟"
    ],
    "wof:name": "Maliangou",
    "wof:placetype": "locality"
  },
  "geometry": {
    "coordinates": [
      108.72883,
      36.2972
    ],
    "type": "Point"
  }
}