{
  "type": "Feature",
  "properties": {
    "iso:country": "CN",
    "name:deu_x_preferred": [
      "Jianshui"
    ],
    "name:eng_x_preferred": [
      "Jianshui County"
    ],
    "name:fas_x_preferred": [
      "شهرستان جیانشوی"
    ],
    "name:gan_x_preferred": [
      "建水县"
    ],
    "name:ind_x_preferred": [
      "Wilayah Jianshui"
    ],
    "name:jpn_x_preferred": [
      "建水県"
    ],
    "name:kor_x_preferred": [
      "젠수이현"
    ],
    "name:nan_x_preferred": [
      "Kiàn-súi-koān"
    ],
    "name:nld_x_preferred": [
      "Jianshui"
    ],
    "name:nob_x_preferred": [
      "Jianshui"
    ],
    "name:swe_x_preferred": [
      "Jianshui"
    ],
    "name:urd_x_preferred": [
      "جیانشوی کاؤنٹی"
    ],
    "name:vie_x_preferred": [
      "Kiến Thủy"
    ],
    "name:wuu_x_preferred": [
      "建水县"
    ],
    "name:yue_x_preferred": [
      "建水"
    ],
    "name:zho_x_preferred": [
      "建水县"
    ],
    "qs:name": "建水",
    "qs:name_adm0": "中國",
    "qs:name_adm1": "云南省",
    "qs:photos": 469,
    "qs:photos_1k": 95,
    "qs:photos_9k": 2,
    "qs:photos_9r": 5,
    "qs:photos_all": 469,
    "qs:photos_sr": 7,
    "qs:placetype": "Town",
    "qs:pop_sr": "0",
    "wd:wordcount": 166,
    "wof:name": "建水",
    "wof:placetype": "locality"
  },
  "geometry": {
    "coordinates": [
      102.822074,
      23.620384
    ],
    "type": "Point"
  }
}