{
  "type": "Feature",
  "properties": {
    "gn:admin1_code": "32.0",
    "gn:asciiname": "Wujiaqiao",
    "gn:country_code": "CN",
    "gn:dem": 432,
    "gn:feature_class": "P",
    "gn:feature_code": "PPL",
    "gn:name": "Wujiaqiao",
    "gn:population": 0,
    "gn:timezone": "Asia/Shanghai",
    "iso:country": "CN",
    "name:zho_x_preferred": [
      "吴家桥"
    ],
    "wof:name": "Wujiaqiao",
    "wof:placetype": "locality"
  },
  "geometry": {
    "coordinates": [
      104.98913,
      30.96543
    ],
    "type": "Point"
  }
}