{
  "type": "Feature",
  "properties": {
    "gn:admin1_code": "30",
    "gn:asciiname": "Dengta",
    "gn:country_code": "CN",
    "gn:dem": 126,
    "gn:feature_class": "P",
    "gn:feature_code": "PPLA4",
    "gn:name": "Dengta",
    "gn:population": 0,
    "gn:timezone": "Asia/Shanghai",
    "iso:country": "CN",
    "name:ara_x_preferred": [
      "دينغتا"
    ],
    "name:deu_x_preferred": [
      "Dengta"
    ],
    "name:fra_x_preferred": [
      "Dengta"
    ],
    "name:ita_x_preferred": [
      "Dengta"
    ],
    "name:jpn_x_preferred": [
      "灯塔市"
    ],
    "name:kik_x_preferred": [
      "Dengta"
    ],
    "name:kor_x_preferred": [
      "덩타시"
    ],
    "name:nor_x_preferred": [
      "Dengta"
    ],
    "name:rus_x_preferred": [
      "Дэнта"
    ],
    "name:swe_x_preferred": [
      "Dengta"
    ],
    "name:und_x_variant": [
      "Teng-t’a-hsü",
      "Teng-t’a",
      "灯塔",
      "Dengta Zhen",
      "灯塔镇"
    ],
    "name:urd_x_preferred": [
      "دینگتا"
    ],
    "name:vie_x_preferred": [
      "Đăng Tháp"
    ],
    "name:zho_x_preferred": [
      "灯塔市"
    ],
    "wof:name": "Dengta",
    "wof:placetype": "locality"
  },
  "geometry": {
    "coordinates": [
      114.7872,
      24.01094
    ],
    "type": "Point"
  }
}