{
  "type": "Feature",
  "properties": {
    "gn:admin1_code": "30.0",
    "gn:asciiname": "Huanglingxia",
    "gn:country_code": "CN",
    "gn:dem": 145,
    "gn:feature_class": "P",
    "gn:feature_code": "PPL",
    "gn:name": "Huanglingxia",
    "gn:population": 0,
    "gn:timezone": "Asia/Shanghai",
    "iso:country": "CN",
    "name:zho_x_preferred": [
      "黄岭下"
    ],
    "wof:name": "Huanglingxia",
    "wof:placetype": "locality"
  },
  "geometry": {
    "coordinates": [
      113.73278,
      24.34
    ],
    "type": "Point"
  }
}