{
  "type": "Feature",
  "properties": {
    "gn:admin1_code": "11.0",
    "gn:asciiname": "Shimen Wuchang",
    "gn:country_code": "CN",
    "gn:dem": 69,
    "gn:feature_class": "P",
    "gn:feature_code": "PPL",
    "gn:name": "Shimen Wuchang",
    "gn:population": 0,
    "gn:timezone": "Asia/Shanghai",
    "iso:country": "CN",
    "name:zho_x_preferred": [
      "石门屋场"
    ],
    "wof:name": "Shimen Wuchang",
    "wof:placetype": "locality"
  },
  "geometry": {
    "coordinates": [
      112.87864,
      27.07769
    ],
    "type": "Point"
  }
}