{
  "type": "Feature",
  "properties": {
    "gn:admin1_code": "15",
    "gn:asciiname": "Chengjiao Chengguanzhen",
    "gn:country_code": "CN",
    "gn:dem": 2316,
    "gn:feature_class": "P",
    "gn:feature_code": "PPLA3",
    "gn:name": "Chengjiao Chengguanzhen",
    "gn:population": 0,
    "gn:timezone": "Asia/Shanghai",
    "iso:country": "CN",
    "name:deu_x_preferred": [
      "Min"
    ],
    "name:fas_x_preferred": [
      "شهرستان مین"
    ],
    "name:kor_x_preferred": [
      "민현"
    ],
    "name:mwl_x_preferred": [
      "Minxian"
    ],
    "name:nor_x_preferred": [
      "Min"
    ],
    "name:rus_x_preferred": [
      "Миньсянь"
    ],
    "name:swe_x_preferred": [
      "Min"
    ],
    "name:und_x_variant": [
      "Min-hsien",
      "Minchow",
      "MIN’SYAN",
      "Chengjiao Chengguanzhen",
      "城郊城关镇",
      "Min Xian",
      "Chengguanzhen",
      "Chengjiao",
      "Min Xian Chengjiao Chengguanzhen",
      "岷县",
      "城关镇",
      "城郊",
      "岷县城郊城关镇"
    ],
    "name:urd_x_preferred": [
      "مین کاؤنٹی"
    ],
    "name:vie_x_preferred": [
      "Mân"
    ],
    "wof:name": "Chengjiao Chengguanzhen",
    "wof:placetype": "locality"
  },
  "geometry": {
    "coordinates": [
      104.03056,
      34.43583
    ],
    "type": "Point"
  }
}