{
  "type": "Feature",
  "properties": {
    "gn:country": "CN",
    "gn:fcode": "PPLA4",
    "gn:population": 0,
    "iso:country": "CN",
    "name:ara_x_preferred": [
      "شيتشنغ"
    ],
    "name:ceb_x_preferred": [
      "Xicheng Qu"
    ],
    "name:ces_x_preferred": [
      "Si-čcheng"
    ],
    "name:cym_x_preferred": [
      "Ardal Xicheng"
    ],
    "name:deu_x_preferred": [
      "Xicheng"
    ],
    "name:eng_x_preferred": [
      "Xicheng District"
    ],
    "name:eus_x_preferred": [
      "Xicheng Barrutia"
    ],
    "name:fas_x_preferred": [
      "شیچنگ"
    ],
    "name:gan_x_preferred": [
      "西城区"
    ],
    "name:heb_x_preferred": [
      "בייג'ינג/רובע קסיצ'נג"
    ],
    "name:hun_x_preferred": [
      "Hszicseng"
    ],
    "name:jpn_x_preferred": [
      "西城区"
    ],
    "name:kor_x_preferred": [
      "시청구"
    ],
    "name:lez_x_preferred": [
      "Сичэн"
    ],
    "name:lit_x_preferred": [
      "Sičengas"
    ],
    "name:lzh_x_preferred": [
      "西城區"
    ],
    "name:mkd_x_preferred": [
      "Сиченг"
    ],
    "name:mwl_x_preferred": [
      "Xicheng"
    ],
    "name:nan_x_preferred": [
      "Sai-siâⁿ-khu"
    ],
    "name:nld_x_preferred": [
      "Xicheng-district"
    ],
    "name:nob_x_preferred": [
      "Xicheng"
    ],
    "name:pol_x_preferred": [
      "Xicheng"
    ],
    "name:rus_x_preferred": [
      "Сичэн"
    ],
    "name:sco_x_preferred": [
      "Xicheng"
    ],
    "name:spa_x_preferred": [
      "Xicheng"
    ],
    "name:swe_x_preferred": [
      "Xicheng"
    ],
    "name:tur_x_preferred": [
      "Xicheng"
    ],
    "name:und_x_variant": [
      "Baizhifang Jiedao"
    ],
    "name:urd_x_preferred": [
      "شیچینگ ضلع"
    ],
    "name:vie_x_preferred": [
      "Tây Thành"
    ],
    "name:wuu_x_preferred": [
      "西城區"
    ],
    "name:yue_x_preferred": [
      "西城區"
    ],
    "name:zha_x_preferred": [
      "Sihcwngz Gih"
    ],
    "name:zho_x_preferred": [
      "白纸坊"
    ],
    "name:zho_x_variant": [
      "白纸坊街道",
      "宣武区",
      "西城区"
    ],
    "qs:name": "Baizhifang",
    "qs:photos_9r": 0,
    "qs:photos_sr": 0,
    "qs:pop_sr": "0",
    "wd:wordcount": 964,
    "wof:name": "Baizhifang",
    "wof:placetype": "locality",
    "wof:population": 0
  },
  "geometry": {
    "coordinates": [
      116.35174,
      39.88287
    ],
    "type": "Point"
  }
}