{
  "type": "Feature",
  "properties": {
    "gn:admin1_code": "11.0",
    "gn:asciiname": "Liangjia",
    "gn:country_code": "CN",
    "gn:dem": 571,
    "gn:feature_class": "P",
    "gn:feature_code": "PPL",
    "gn:name": "Liangjia",
    "gn:population": 0,
    "gn:timezone": "Asia/Shanghai",
    "iso:country": "CN",
    "name:zho_x_preferred": [
      "梁家"
    ],
    "name:zho_x_variant": [
      "梁家镇"
    ],
    "wof:name": "Liangjia",
    "wof:placetype": "locality"
  },
  "geometry": {
    "coordinates": [
      110.12718,
      26.71138
    ],
    "type": "Point"
  }
}