{
  "type": "Feature",
  "properties": {
    "gn:admin1_code": "9.0",
    "gn:asciiname": "Lushigou",
    "gn:country_code": "CN",
    "gn:dem": 1054,
    "gn:feature_class": "P",
    "gn:feature_code": "PPL",
    "gn:name": "Lushigou",
    "gn:population": 0,
    "gn:timezone": "Asia/Shanghai",
    "iso:country": "CN",
    "name:zho_x_preferred": [
      "卢氏沟"
    ],
    "wof:name": "Lushigou",
    "wof:placetype": "locality"
  },
  "geometry": {
    "coordinates": [
      110.8174,
      34.12018
    ],
    "type": "Point"
  }
}