{
  "type": "Feature",
  "properties": {
    "gn:admin1_code": "5.0",
    "gn:asciiname": "Xiaoying",
    "gn:country_code": "CN",
    "gn:dem": 166,
    "gn:feature_class": "P",
    "gn:feature_code": "PPL",
    "gn:name": "Xiaoying",
    "gn:population": 0,
    "gn:timezone": "Asia/Shanghai",
    "iso:country": "CN",
    "name:und_x_variant": [
      "小营"
    ],
    "wof:name": "Xiaoying",
    "wof:placetype": "locality"
  },
  "geometry": {
    "coordinates": [
      129.57355,
      42.91663
    ],
    "type": "Point"
  }
}