{
  "type": "Feature",
  "properties": {
    "gn:admin1_code": "3.0",
    "gn:asciiname": "Wangfang",
    "gn:country_code": "CN",
    "gn:dem": 112,
    "gn:feature_class": "P",
    "gn:feature_code": "PPL",
    "gn:name": "Wangfang",
    "gn:population": 0,
    "gn:timezone": "Asia/Shanghai",
    "iso:country": "CN",
    "name:ceb_x_preferred": [
      "Wangfang"
    ],
    "name:swe_x_preferred": [
      "Wangfang"
    ],
    "name:zho_x_preferred": [
      "王坊"
    ],
    "name:zho_x_variant": [
      "王坊镇"
    ],
    "wof:name": "Wangfang",
    "wof:placetype": "locality"
  },
  "geometry": {
    "coordinates": [
      117.09037,
      28.50938
    ],
    "type": "Point"
  }
}