{
  "type": "Feature",
  "properties": {
    "gn:admin1_code": "20",
    "gn:asciiname": "Qagan Nur",
    "gn:country_code": "CN",
    "gn:dem": 1024,
    "gn:feature_class": "P",
    "gn:feature_code": "PPL",
    "gn:name": "Qagan Nur",
    "gn:population": 0,
    "gn:timezone": "Asia/Shanghai",
    "iso:country": "CN",
    "name:ben_x_preferred": [
      "কাগান নুর"
    ],
    "name:ell_x_preferred": [
      "Καγκάν Νουρ"
    ],
    "name:fas_x_preferred": [
      "کاگان نور"
    ],
    "name:heb_x_preferred": [
      "אגם קאגאן"
    ],
    "name:hin_x_preferred": [
      "कगन नूर"
    ],
    "name:hun_x_preferred": [
      "Qagan Nur"
    ],
    "name:ind_x_preferred": [
      "Qagan Nur"
    ],
    "name:ita_x_preferred": [
      "Qagan Nur"
    ],
    "name:nld_x_preferred": [
      "Qagan Nur"
    ],
    "name:pol_x_preferred": [
      "Qagan Nur"
    ],
    "name:por_x_preferred": [
      "Laco Qagan"
    ],
    "name:spa_x_preferred": [
      "Qagan Nur"
    ],
    "name:tur_x_preferred": [
      "Qagan Nur"
    ],
    "name:ukr_x_preferred": [
      "Кваган Нур"
    ],
    "name:urd_x_preferred": [
      "قاگان نور"
    ],
    "name:vie_x_preferred": [
      "Qagan Nur"
    ],
    "wof:name": "Qagan Nur",
    "wof:placetype": "locality"
  },
  "geometry": {
    "coordinates": [
      114.23639,
      43.29806
    ],
    "type": "Point"
  }
}