{
  "type": "Feature",
  "properties": {
    "gn:admin1_code": "9",
    "gn:asciiname": "Caiyoufang",
    "gn:country_code": "CN",
    "gn:dem": 67,
    "gn:feature_class": "P",
    "gn:feature_code": "PPL",
    "gn:name": "Caiyoufang",
    "gn:population": 0,
    "gn:timezone": "Asia/Shanghai",
    "iso:country": "CN",
    "name:zho_x_preferred": [
      "蔡油坊"
    ],
    "wof:name": "Caiyoufang",
    "wof:placetype": "locality"
  },
  "geometry": {
    "coordinates": [
      115.314,
      34.7315
    ],
    "type": "Point"
  }
}