{
  "type": "Feature",
  "properties": {
    "gn:admin1_code": "19.0",
    "gn:asciiname": "Xitangjiatun",
    "gn:country_code": "CN",
    "gn:dem": 52,
    "gn:feature_class": "P",
    "gn:feature_code": "PPL",
    "gn:name": "Xitangjiatun",
    "gn:population": 0,
    "gn:timezone": "Asia/Shanghai",
    "iso:country": "CN",
    "name:zho_x_preferred": [
      "西唐家屯"
    ],
    "wof:name": "Xitangjiatun",
    "wof:placetype": "locality"
  },
  "geometry": {
    "coordinates": [
      122.47074,
      39.7352
    ],
    "type": "Point"
  }
}