{
  "type": "Feature",
  "properties": {
    "gn:admin1_code": "4.0",
    "gn:asciiname": "Anqing",
    "gn:country_code": "CN",
    "gn:dem": 5,
    "gn:feature_class": "P",
    "gn:feature_code": "PPL",
    "gn:name": "Anqing",
    "gn:population": 0,
    "gn:timezone": "Asia/Shanghai",
    "iso:country": "CN",
    "name:afr_x_preferred": [
      "Anqing"
    ],
    "name:ara_x_preferred": [
      "أنكينغ"
    ],
    "name:bul_x_preferred": [
      "Анцин"
    ],
    "name:bxr_x_preferred": [
      "Аньцин"
    ],
    "name:cdo_x_preferred": [
      "Ăng-kéng"
    ],
    "name:ceb_x_preferred": [
      "Anqing Shi"
    ],
    "name:ces_x_preferred": [
      "An-čching"
    ],
    "name:cym_x_preferred": [
      "Anqing"
    ],
    "name:dan_x_preferred": [
      "Anqing"
    ],
    "name:deu_x_preferred": [
      "Anqing"
    ],
    "name:epo_x_preferred": [
      "Ankingo"
    ],
    "name:eus_x_preferred": [
      "Anqing"
    ],
    "name:fas_x_preferred": [
      "انگینگ"
    ],
    "name:fin_x_preferred": [
      "Anqing"
    ],
    "name:fra_x_preferred": [
      "Anqing"
    ],
    "name:heb_x_preferred": [
      "אנקינג"
    ],
    "name:hye_x_preferred": [
      "Անցին"
    ],
    "name:ita_x_preferred": [
      "Anqing"
    ],
    "name:jpn_x_preferred": [
      "安慶市"
    ],
    "name:kik_x_preferred": [
      "Anqing"
    ],
    "name:kor_x_preferred": [
      "안칭시"
    ],
    "name:lit_x_preferred": [
      "Ančingas"
    ],
    "name:mlg_x_preferred": [
      "Anqing"
    ],
    "name:nld_x_preferred": [
      "Anqing"
    ],
    "name:nno_x_preferred": [
      "Anqing"
    ],
    "name:nor_x_preferred": [
      "Anqing"
    ],
    "name:pam_x_preferred": [
      "Anqing"
    ],
    "name:pnb_x_preferred": [
      "انکنگ"
    ],
    "name:pol_x_preferred": [
      "Anqing"
    ],
    "name:por_x_preferred": [
      "Anqing"
    ],
    "name:rus_x_preferred": [
      "Аньцин"
    ],
    "name:sco_x_preferred": [
      "Anqing"
    ],
    "name:spa_x_preferred": [
      "Anqing"
    ],
    "name:srp_x_preferred": [
      "Анћинг"
    ],
    "name:swe_x_preferred": [
      "Anqing"
    ],
    "name:tam_x_preferred": [
      "அன்கிங்"
    ],
    "name:tgl_x_preferred": [
      "Anqing"
    ],
    "name:tur_x_preferred": [
      "Anqing"
    ],
    "name:uig_x_preferred": [
      "ئەنچىڭ شەھىرى"
    ],
    "name:ukr_x_preferred": [
      "Аньцін"
    ],
    "name:urd_x_preferred": [
      "انچنگ"
    ],
    "name:vie_x_preferred": [
      "An Khánh"
    ],
    "name:war_x_preferred": [
      "Anqing"
    ],
    "name:wuu_x_preferred": [
      "安庆市"
    ],
    "name:zho_x_preferred": [
      "安庆"
    ],
    "name:zho_x_variant": [
      "安庆市"
    ],
    "wof:name": "Anqing",
    "wof:placetype": "locality"
  },
  "geometry": {
    "coordinates": [
      121.37726,
      32.05312
    ],
    "type": "Point"
  }
}