{
  "type": "Feature",
  "properties": {
    "gn:admin1_code": "1.0",
    "gn:asciiname": "Sanhe",
    "gn:country_code": "CN",
    "gn:dem": 165,
    "gn:feature_class": "P",
    "gn:feature_code": "PPL",
    "gn:name": "Sanhe",
    "gn:population": 0,
    "gn:timezone": "Asia/Shanghai",
    "iso:country": "CN",
    "name:ceb_x_preferred": [
      "Sanhe"
    ],
    "name:deu_x_preferred": [
      "Sanhe"
    ],
    "name:nor_x_preferred": [
      "Sanhe"
    ],
    "name:und_x_variant": [
      "三合",
      "三合村"
    ],
    "name:zho_x_preferred": [
      "Sanhecun"
    ],
    "wof:name": "Sanhe",
    "wof:placetype": "locality"
  },
  "geometry": {
    "coordinates": [
      118.98686,
      30.84937
    ],
    "type": "Point"
  }
}