{
  "type": "Feature",
  "properties": {
    "gn:admin1_code": "32.0",
    "gn:asciiname": "Laba",
    "gn:country_code": "CN",
    "gn:dem": 561,
    "gn:feature_class": "P",
    "gn:feature_code": "PPL",
    "gn:name": "Laba",
    "gn:population": 0,
    "gn:timezone": "Asia/Shanghai",
    "iso:country": "CN",
    "name:bel_x_preferred": [
      "Лаба"
    ],
    "name:ceb_x_preferred": [
      "Laba"
    ],
    "name:ces_x_preferred": [
      "Laba"
    ],
    "name:deu_x_preferred": [
      "Laba"
    ],
    "name:est_x_preferred": [
      "Laba"
    ],
    "name:kat_x_preferred": [
      "ლაბა"
    ],
    "name:lit_x_preferred": [
      "Laba"
    ],
    "name:oss_x_preferred": [
      "Лабæ"
    ],
    "name:pol_x_preferred": [
      "Łaba"
    ],
    "name:rus_x_preferred": [
      "Лаба"
    ],
    "name:spa_x_preferred": [
      "Laba"
    ],
    "name:swe_x_preferred": [
      "Laba"
    ],
    "name:ukr_x_preferred": [
      "Лаба"
    ],
    "name:zho_x_preferred": [
      "喇叭"
    ],
    "wof:name": "Laba",
    "wof:placetype": "locality"
  },
  "geometry": {
    "coordinates": [
      104.503,
      31.6145
    ],
    "type": "Point"
  }
}