{
  "type": "Feature",
  "properties": {
    "gn:admin1_code": "24",
    "gn:asciiname": "Fenghuang",
    "gn:country_code": "CN",
    "gn:dem": 1046,
    "gn:feature_class": "P",
    "gn:feature_code": "PPL",
    "gn:name": "Fenghuang",
    "gn:population": 0,
    "gn:timezone": "Asia/Shanghai",
    "iso:country": "CN",
    "name:ara_x_preferred": [
      "فنغهوانغ"
    ],
    "name:aze_x_preferred": [
      "Çin feniksi"
    ],
    "name:cat_x_preferred": [
      "Fenghuang"
    ],
    "name:cdo_x_preferred": [
      "Hông-huòng"
    ],
    "name:ces_x_preferred": [
      "Feng-chuang"
    ],
    "name:deu_x_preferred": [
      "Fenghuang"
    ],
    "name:fra_x_preferred": [
      "Fenghuang"
    ],
    "name:hak_x_preferred": [
      "Fung-fòng"
    ],
    "name:hrv_x_preferred": [
      "Fenghuang"
    ],
    "name:hun_x_preferred": [
      "Feng-huang"
    ],
    "name:ind_x_preferred": [
      "Fenghuang"
    ],
    "name:isl_x_preferred": [
      "Fènghuáng"
    ],
    "name:ita_x_preferred": [
      "Fenghuang"
    ],
    "name:mlg_x_preferred": [
      "Fenghuang"
    ],
    "name:msa_x_preferred": [
      "Fenghuang"
    ],
    "name:nld_x_preferred": [
      "Feng Huang"
    ],
    "name:nor_x_preferred": [
      "Fenghuang"
    ],
    "name:pol_x_preferred": [
      "Fenghuang"
    ],
    "name:por_x_preferred": [
      "Fenghuang"
    ],
    "name:rus_x_preferred": [
      "Китайский феникс"
    ],
    "name:slk_x_preferred": [
      "Feng-chuang"
    ],
    "name:spa_x_preferred": [
      "Fenghuang"
    ],
    "name:swe_x_preferred": [
      "Fenghuang"
    ],
    "name:tur_x_preferred": [
      "Fenghuang"
    ],
    "name:ukr_x_preferred": [
      "Китайський фенікс"
    ],
    "name:vie_x_preferred": [
      "Phượng hoàng"
    ],
    "name:war_x_preferred": [
      "Fenghuang"
    ],
    "name:zha_x_preferred": [
      "Roegfunghvuengz"
    ],
    "wof:name": "Fenghuang",
    "wof:placetype": "locality"
  },
  "geometry": {
    "coordinates": [
      113.31722,
      35.57389000000001
    ],
    "type": "Point"
  }
}