{
  "type": "Feature",
  "properties": {
    "gn:admin1_code": "16.0",
    "gn:asciiname": "Longyan",
    "gn:country_code": "CN",
    "gn:dem": 193,
    "gn:feature_class": "P",
    "gn:feature_code": "PPL",
    "gn:name": "Longyan",
    "gn:population": 0,
    "gn:timezone": "Asia/Shanghai",
    "iso:country": "CN",
    "name:ara_x_preferred": [
      "لونغيان"
    ],
    "name:cdo_x_preferred": [
      "Lṳ̀ng-ngàng"
    ],
    "name:ces_x_preferred": [
      "Lung-jen"
    ],
    "name:dan_x_preferred": [
      "Longyan"
    ],
    "name:deu_x_preferred": [
      "Longyan"
    ],
    "name:eus_x_preferred": [
      "Longyan"
    ],
    "name:fas_x_preferred": [
      "لانگیان"
    ],
    "name:fin_x_preferred": [
      "Longyan"
    ],
    "name:fra_x_preferred": [
      "Longyan"
    ],
    "name:hak_x_preferred": [
      "Liùng-ngàm-sṳ"
    ],
    "name:hun_x_preferred": [
      "Longyan"
    ],
    "name:ita_x_preferred": [
      "Longyan"
    ],
    "name:jpn_x_preferred": [
      "竜岩市"
    ],
    "name:kaz_x_preferred": [
      "Лунъянь"
    ],
    "name:kik_x_preferred": [
      "Longyan"
    ],
    "name:kor_x_preferred": [
      "룽옌시"
    ],
    "name:mlg_x_preferred": [
      "Longyan"
    ],
    "name:nld_x_preferred": [
      "Longyan"
    ],
    "name:nno_x_preferred": [
      "Longyan"
    ],
    "name:nor_x_preferred": [
      "Longyan"
    ],
    "name:pam_x_preferred": [
      "Longyan"
    ],
    "name:pol_x_preferred": [
      "Longyan"
    ],
    "name:por_x_preferred": [
      "Longyan"
    ],
    "name:rus_x_preferred": [
      "Лунъянь"
    ],
    "name:sco_x_preferred": [
      "Longyan"
    ],
    "name:spa_x_preferred": [
      "Longyan"
    ],
    "name:swe_x_preferred": [
      "Longyan"
    ],
    "name:tgl_x_preferred": [
      "Longyan"
    ],
    "name:tur_x_preferred": [
      "Longyan"
    ],
    "name:uig_x_preferred": [
      "Longyen shehiri"
    ],
    "name:urd_x_preferred": [
      "لونگیان"
    ],
    "name:vie_x_preferred": [
      "Long Nham"
    ],
    "name:war_x_preferred": [
      "Longyan"
    ],
    "name:wuu_x_preferred": [
      "龙岩市"
    ],
    "name:zho_x_preferred": [
      "龙岩"
    ],
    "name:zho_x_variant": [
      "龙岩市"
    ],
    "wof:name": "Longyan",
    "wof:placetype": "locality"
  },
  "geometry": {
    "coordinates": [
      111.259,
      24.7568
    ],
    "type": "Point"
  }
}