{
  "type": "Feature",
  "properties": {
    "gn:admin1_code": "15.0",
    "gn:asciiname": "Tianmen",
    "gn:country_code": "CN",
    "gn:dem": 1400,
    "gn:feature_class": "P",
    "gn:feature_code": "PPL",
    "gn:name": "Tianmen",
    "gn:population": 0,
    "gn:timezone": "Asia/Shanghai",
    "iso:country": "CN",
    "name:deu_x_preferred": [
      "Tianmen"
    ],
    "name:fas_x_preferred": [
      "تیانمن"
    ],
    "name:fin_x_preferred": [
      "Tianmen"
    ],
    "name:fra_x_preferred": [
      "Tianmen"
    ],
    "name:ita_x_preferred": [
      "Tianmen"
    ],
    "name:jpn_x_preferred": [
      "天門市"
    ],
    "name:kik_x_preferred": [
      "Tianmen"
    ],
    "name:kor_x_preferred": [
      "톈먼시"
    ],
    "name:mlg_x_preferred": [
      "Tianmen"
    ],
    "name:nld_x_preferred": [
      "Tianmen"
    ],
    "name:nno_x_preferred": [
      "Tianmen"
    ],
    "name:nor_x_preferred": [
      "Tianmen"
    ],
    "name:pam_x_preferred": [
      "Tianmen"
    ],
    "name:pol_x_preferred": [
      "Tianmen"
    ],
    "name:por_x_preferred": [
      "Tianmen"
    ],
    "name:rus_x_preferred": [
      "Тяньмэнь"
    ],
    "name:srp_x_preferred": [
      "Тјенмен"
    ],
    "name:swe_x_preferred": [
      "Tianmen"
    ],
    "name:tur_x_preferred": [
      "Tianmen"
    ],
    "name:urd_x_preferred": [
      "تیانمین"
    ],
    "name:vie_x_preferred": [
      "Thiên Môn"
    ],
    "name:war_x_preferred": [
      "Tianmen"
    ],
    "name:wuu_x_preferred": [
      "天门市"
    ],
    "name:zho_x_preferred": [
      "天门"
    ],
    "name:zho_x_variant": [
      "天门市"
    ],
    "wof:name": "Tianmen",
    "wof:placetype": "locality"
  },
  "geometry": {
    "coordinates": [
      106.643,
      35.5474
    ],
    "type": "Point"
  }
}