{
  "type": "Feature",
  "properties": {
    "gn:admin1_code": "11.0",
    "gn:asciiname": "Gujia",
    "gn:country_code": "CN",
    "gn:dem": 447,
    "gn:feature_class": "P",
    "gn:feature_code": "PPL",
    "gn:name": "Gujia",
    "gn:population": 0,
    "gn:timezone": "Asia/Shanghai",
    "iso:country": "CN",
    "name:bih_x_preferred": [
      "गोझिया"
    ],
    "name:fra_x_preferred": [
      "Gujia"
    ],
    "name:hin_x_preferred": [
      "गुझिया"
    ],
    "name:mai_x_preferred": [
      "पुड़ुकिया"
    ],
    "name:mal_x_preferred": [
      "ഗുജിയ"
    ],
    "name:ori_x_preferred": [
      "କରଞ୍ଜି"
    ],
    "name:pan_x_preferred": [
      "ਗੁਜੀਆ"
    ],
    "name:pnb_x_preferred": [
      "گجیا"
    ],
    "name:tel_x_preferred": [
      "కజ్జికాయ"
    ],
    "name:zho_x_preferred": [
      "古家"
    ],
    "wof:name": "Gujia",
    "wof:placetype": "locality"
  },
  "geometry": {
    "coordinates": [
      113.46371,
      26.35141
    ],
    "type": "Point"
  }
}