{
  "type": "Feature",
  "properties": {
    "gn:admin1_code": "1.0",
    "gn:asciiname": "Shangzhucun",
    "gn:country_code": "CN",
    "gn:dem": 124,
    "gn:feature_class": "P",
    "gn:feature_code": "PPL",
    "gn:name": "Shangzhucun",
    "gn:population": 0,
    "gn:timezone": "Asia/Shanghai",
    "iso:country": "CN",
    "name:zho_x_preferred": [
      "上朱村"
    ],
    "wof:name": "Shangzhucun",
    "wof:placetype": "locality"
  },
  "geometry": {
    "coordinates": [
      118.34369,
      29.84167
    ],
    "type": "Point"
  }
}