{
  "type": "Feature",
  "properties": {
    "gn:admin1_code": "32.0",
    "gn:asciiname": "Changshi",
    "gn:country_code": "CN",
    "gn:dem": 336,
    "gn:feature_class": "P",
    "gn:feature_code": "PPL",
    "gn:name": "Changshi",
    "gn:population": 0,
    "gn:timezone": "Asia/Shanghai",
    "iso:country": "CN",
    "name:cat_x_preferred": [
      "Txangxi"
    ],
    "name:ita_x_preferred": [
      "Changshi Khan"
    ],
    "name:mon_x_preferred": [
      "Чанши"
    ],
    "name:uig_x_preferred": [
      "چاڭشى"
    ],
    "name:ukr_x_preferred": [
      "Чанкші-хан"
    ],
    "name:uzb_x_preferred": [
      "Djenkshi"
    ],
    "name:zho_x_preferred": [
      "长石"
    ],
    "wof:name": "Changshi",
    "wof:placetype": "locality"
  },
  "geometry": {
    "coordinates": [
      106.714,
      31.0097
    ],
    "type": "Point"
  }
}