{
  "type": "Feature",
  "properties": {
    "gn:admin1_code": "7.0",
    "gn:asciiname": "Danian",
    "gn:country_code": "CN",
    "gn:dem": 373,
    "gn:feature_class": "P",
    "gn:feature_code": "PPL",
    "gn:name": "Danian",
    "gn:population": 0,
    "gn:timezone": "Asia/Shanghai",
    "iso:country": "CN",
    "name:afr_x_preferred": [
      "Danium"
    ],
    "name:ara_x_preferred": [
      "الداني"
    ],
    "name:ast_x_preferred": [
      "Danianu"
    ],
    "name:cat_x_preferred": [
      "Danià"
    ],
    "name:dan_x_preferred": [
      "Danien"
    ],
    "name:deu_x_preferred": [
      "Danium"
    ],
    "name:eus_x_preferred": [
      "Daniar"
    ],
    "name:fas_x_preferred": [
      "دانین"
    ],
    "name:fin_x_preferred": [
      "Dania-vaihe"
    ],
    "name:fra_x_preferred": [
      "Danien"
    ],
    "name:ita_x_preferred": [
      "Daniano"
    ],
    "name:jpn_x_preferred": [
      "ダニアン"
    ],
    "name:nds_x_preferred": [
      "Danium"
    ],
    "name:nld_x_preferred": [
      "Danien"
    ],
    "name:nno_x_preferred": [
      "Danium"
    ],
    "name:pol_x_preferred": [
      "Dan"
    ],
    "name:por_x_preferred": [
      "Daniano"
    ],
    "name:rus_x_preferred": [
      "Датский ярус"
    ],
    "name:spa_x_preferred": [
      "Daniense"
    ],
    "name:swe_x_preferred": [
      "Dan"
    ],
    "name:ukr_x_preferred": [
      "Данський ярус"
    ],
    "name:zho_x_preferred": [
      "大年"
    ],
    "name:zho_x_variant": [
      "达宁期"
    ],
    "wof:name": "Danian",
    "wof:placetype": "locality"
  },
  "geometry": {
    "coordinates": [
      117.62556,
      27.56561
    ],
    "type": "Point"
  }
}