{
  "type": "Feature",
  "properties": {
    "gn:admin1_code": "16.0",
    "gn:asciiname": "Nala",
    "gn:country_code": "CN",
    "gn:dem": 460,
    "gn:feature_class": "P",
    "gn:feature_code": "PPL",
    "gn:name": "Nala",
    "gn:population": 0,
    "gn:timezone": "Asia/Shanghai",
    "iso:country": "CN",
    "name:hin_x_preferred": [
      "नल-दमयन्ती"
    ],
    "name:ind_x_preferred": [
      "Nala"
    ],
    "name:mai_x_preferred": [
      "नल-दमयन्ती"
    ],
    "name:mal_x_preferred": [
      "നളൻ"
    ],
    "name:rus_x_preferred": [
      "Нала"
    ],
    "name:san_x_preferred": [
      "नलः"
    ],
    "name:spa_x_preferred": [
      "Nala"
    ],
    "name:tam_x_preferred": [
      "நளன்"
    ],
    "name:tel_x_preferred": [
      "నలుడు"
    ],
    "name:zho_x_preferred": [
      "那腊"
    ],
    "wof:name": "Nala",
    "wof:placetype": "locality"
  },
  "geometry": {
    "coordinates": [
      105.67,
      24.0956
    ],
    "type": "Point"
  }
}