{
  "type": "Feature",
  "properties": {
    "gn:admin1_code": "2.0",
    "gn:asciiname": "Lingshangcun",
    "gn:country_code": "CN",
    "gn:dem": 26,
    "gn:feature_class": "P",
    "gn:feature_code": "PPL",
    "gn:name": "Lingshangcun",
    "gn:population": 0,
    "gn:timezone": "Asia/Shanghai",
    "iso:country": "CN",
    "name:zho_x_preferred": [
      "岭上村"
    ],
    "wof:name": "Lingshangcun",
    "wof:placetype": "locality"
  },
  "geometry": {
    "coordinates": [
      120.27514,
      27.60484000000001
    ],
    "type": "Point"
  }
}