{
  "type": "Feature",
  "properties": {
    "gn:admin1_code": "2.0",
    "gn:asciiname": "Tianchang",
    "gn:country_code": "CN",
    "gn:dem": 533,
    "gn:feature_class": "P",
    "gn:feature_code": "PPL",
    "gn:name": "Tianchang",
    "gn:population": 0,
    "gn:timezone": "Asia/Shanghai",
    "iso:country": "CN",
    "name:ara_x_preferred": [
      "تيانشانغ"
    ],
    "name:deu_x_preferred": [
      "Tianchang"
    ],
    "name:fas_x_preferred": [
      "تیانچانگ"
    ],
    "name:fra_x_preferred": [
      "Tianchang"
    ],
    "name:ita_x_preferred": [
      "Tianchang"
    ],
    "name:jpn_x_preferred": [
      "天長市"
    ],
    "name:kik_x_preferred": [
      "Tianchang"
    ],
    "name:kor_x_preferred": [
      "톈창시"
    ],
    "name:mlg_x_preferred": [
      "Tianchang"
    ],
    "name:mwl_x_preferred": [
      "Tianchang"
    ],
    "name:nld_x_preferred": [
      "Tianchang"
    ],
    "name:nor_x_preferred": [
      "Tianchang"
    ],
    "name:pam_x_preferred": [
      "Tianchang"
    ],
    "name:spa_x_preferred": [
      "Tiāncháng Shì"
    ],
    "name:swe_x_preferred": [
      "Tianchang"
    ],
    "name:urd_x_preferred": [
      "تیانچانگ"
    ],
    "name:vie_x_preferred": [
      "Thiên Trường"
    ],
    "name:wuu_x_preferred": [
      "天长市"
    ],
    "name:zho_x_preferred": [
      "田厂"
    ],
    "name:zho_x_variant": [
      "天长市"
    ],
    "wof:name": "Tianchang",
    "wof:placetype": "locality"
  },
  "geometry": {
    "coordinates": [
      120.11758,
      27.69056
    ],
    "type": "Point"
  }
}