{
  "type": "Feature",
  "properties": {
    "gn:admin1_code": "2.0",
    "gn:asciiname": "Daling",
    "gn:country_code": "CN",
    "gn:dem": 97,
    "gn:feature_class": "P",
    "gn:feature_code": "PPL",
    "gn:name": "Daling",
    "gn:population": 0,
    "gn:timezone": "Asia/Shanghai",
    "iso:country": "CN",
    "name:ara_x_preferred": [
      "دالينغ"
    ],
    "name:ben_x_preferred": [
      "দালিং"
    ],
    "name:ceb_x_preferred": [
      "Daling"
    ],
    "name:deu_x_preferred": [
      "Daling"
    ],
    "name:ell_x_preferred": [
      "Ντάλινγκ"
    ],
    "name:fas_x_preferred": [
      "دالینگ"
    ],
    "name:fra_x_preferred": [
      "Daling"
    ],
    "name:heb_x_preferred": [
      "דאלינג"
    ],
    "name:hin_x_preferred": [
      "डालिंग"
    ],
    "name:hun_x_preferred": [
      "Daling"
    ],
    "name:ind_x_preferred": [
      "Daling"
    ],
    "name:ita_x_preferred": [
      "Daling"
    ],
    "name:nld_x_preferred": [
      "Daling"
    ],
    "name:pol_x_preferred": [
      "Daling"
    ],
    "name:por_x_preferred": [
      "Daling"
    ],
    "name:spa_x_preferred": [
      "Daling"
    ],
    "name:swe_x_preferred": [
      "Daling"
    ],
    "name:tur_x_preferred": [
      "Daling"
    ],
    "name:ukr_x_preferred": [
      "Далінг"
    ],
    "name:urd_x_preferred": [
      "ڈالنگ"
    ],
    "name:vie_x_preferred": [
      "Sông Daling"
    ],
    "name:zho_x_preferred": [
      "大岭"
    ],
    "wof:name": "Daling",
    "wof:placetype": "locality"
  },
  "geometry": {
    "coordinates": [
      122.04829,
      30.10006
    ],
    "type": "Point"
  }
}