{
  "type": "Feature",
  "properties": {
    "gn:admin1_code": "11",
    "gn:asciiname": "Sangesi",
    "gn:country_code": "CN",
    "gn:dem": 254,
    "gn:feature_class": "P",
    "gn:feature_code": "PPLA4",
    "gn:name": "Sangesi",
    "gn:population": 0,
    "gn:timezone": "Asia/Shanghai",
    "iso:country": "CN",
    "name:und_x_variant": [
      "Sangesi Xiang"
    ],
    "name:zho_x_preferred": [
      "三阁司"
    ],
    "name:zho_x_variant": [
      "三阁司乡"
    ],
    "wof:name": "Sangesi",
    "wof:placetype": "locality"
  },
  "geometry": {
    "coordinates": [
      110.95444,
      27.06694
    ],
    "type": "Point"
  }
}