{
  "type": "Feature",
  "properties": {
    "gn:admin1_code": "32.0",
    "gn:asciiname": "Miaofeng",
    "gn:country_code": "CN",
    "gn:dem": 475,
    "gn:feature_class": "P",
    "gn:feature_code": "PPL",
    "gn:name": "Miaofeng",
    "gn:population": 0,
    "gn:timezone": "Asia/Shanghai",
    "iso:country": "CN",
    "name:zho_x_preferred": [
      "妙峰"
    ],
    "name:zho_x_variant": [
      "妙丰"
    ],
    "wof:name": "Miaofeng",
    "wof:placetype": "locality"
  },
  "geometry": {
    "coordinates": [
      104.83399,
      30.6763
    ],
    "type": "Point"
  }
}