{
  "type": "Feature",
  "properties": {
    "gn:admin1_code": "2.0",
    "gn:asciiname": "Yuyan",
    "gn:country_code": "CN",
    "gn:dem": 61,
    "gn:feature_class": "P",
    "gn:feature_code": "PPL",
    "gn:name": "Yuyan",
    "gn:population": 0,
    "gn:timezone": "Asia/Shanghai",
    "iso:country": "CN",
    "name:fra_x_preferred": [
      "Yuyan"
    ],
    "name:jpn_x_preferred": [
      "愛新覚羅毓嵒"
    ],
    "name:kor_x_preferred": [
      "아이신기오로 유얀"
    ],
    "name:tha_x_preferred": [
      "ยวี่เหยียน"
    ],
    "name:zho_x_preferred": [
      "余严"
    ],
    "wof:name": "Yuyan",
    "wof:placetype": "locality"
  },
  "geometry": {
    "coordinates": [
      121.61733,
      30.03519
    ],
    "type": "Point"
  }
}