{
  "type": "Feature",
  "properties": {
    "gn:admin1_code": "29.0",
    "gn:asciiname": "Mina",
    "gn:country_code": "CN",
    "gn:dem": 1283,
    "gn:feature_class": "P",
    "gn:feature_code": "PPL",
    "gn:name": "Mina",
    "gn:population": 0,
    "gn:timezone": "Asia/Shanghai",
    "iso:country": "CN",
    "name:ara_x_preferred": [
      "مينا"
    ],
    "name:aze_x_preferred": [
      "Mina"
    ],
    "name:bos_x_preferred": [
      "Mina"
    ],
    "name:bul_x_preferred": [
      "Мина"
    ],
    "name:cat_x_preferred": [
      "Mina"
    ],
    "name:ceb_x_preferred": [
      "Mina"
    ],
    "name:ces_x_preferred": [
      "Mina"
    ],
    "name:dan_x_preferred": [
      "Mina"
    ],
    "name:deu_x_preferred": [
      "Mina"
    ],
    "name:fas_x_preferred": [
      "مینا"
    ],
    "name:fin_x_preferred": [
      "Mina"
    ],
    "name:fra_x_preferred": [
      "Mina"
    ],
    "name:glg_x_preferred": [
      "Mina"
    ],
    "name:heb_x_preferred": [
      "מינה"
    ],
    "name:hrv_x_preferred": [
      "Mina"
    ],
    "name:hun_x_preferred": [
      "Mina"
    ],
    "name:ind_x_preferred": [
      "Mina"
    ],
    "name:ita_x_preferred": [
      "Mina"
    ],
    "name:jpn_x_preferred": [
      "Mina"
    ],
    "name:kir_x_preferred": [
      "Мина"
    ],
    "name:lit_x_preferred": [
      "Mina"
    ],
    "name:nld_x_preferred": [
      "Mina"
    ],
    "name:nor_x_preferred": [
      "Mina"
    ],
    "name:pol_x_preferred": [
      "Mina"
    ],
    "name:por_x_preferred": [
      "Mina"
    ],
    "name:ron_x_preferred": [
      "Mină"
    ],
    "name:rus_x_preferred": [
      "Мина"
    ],
    "name:sco_x_preferred": [
      "Mina"
    ],
    "name:slk_x_preferred": [
      "Mína"
    ],
    "name:spa_x_preferred": [
      "Mina"
    ],
    "name:srp_x_preferred": [
      "Мина"
    ],
    "name:swe_x_preferred": [
      "Mina"
    ],
    "name:tur_x_preferred": [
      "Mina"
    ],
    "name:ukr_x_preferred": [
      "Міна"
    ],
    "name:zho_x_preferred": [
      "迷那"
    ],
    "wof:name": "Mina",
    "wof:placetype": "locality"
  },
  "geometry": {
    "coordinates": [
      101.866,
      22.9385
    ],
    "type": "Point"
  }
}