{
  "type": "Feature",
  "properties": {
    "gn:admin1_code": "10",
    "gn:asciiname": "Chenjiazhai",
    "gn:country_code": "CN",
    "gn:dem": 22,
    "gn:feature_class": "P",
    "gn:feature_code": "PPL",
    "gn:name": "Chenjiazhai",
    "gn:population": 0,
    "gn:timezone": "Asia/Shanghai",
    "iso:country": "CN",
    "name:zho_x_preferred": [
      "陈家寨"
    ],
    "wof:name": "Chenjiazhai",
    "wof:placetype": "locality"
  },
  "geometry": {
    "coordinates": [
      115.526,
      37.5144
    ],
    "type": "Point"
  }
}