{
  "type": "Feature",
  "properties": {
    "gn:admin1_code": "10",
    "gn:asciiname": "Longwangmiao",
    "gn:country_code": "CN",
    "gn:dem": 455,
    "gn:feature_class": "P",
    "gn:feature_code": "PPL",
    "gn:name": "Longwangmiao",
    "gn:population": 0,
    "gn:timezone": "Asia/Shanghai",
    "iso:country": "CN",
    "name:und_x_variant": [
      "Lunwan’myao",
      "Lung-wang-miao",
      "Longwangmiao"
    ],
    "name:zho_x_preferred": [
      "龙王庙"
    ],
    "wof:name": "Longwangmiao",
    "wof:placetype": "locality"
  },
  "geometry": {
    "coordinates": [
      115.2532,
      39.49367
    ],
    "type": "Point"
  }
}