{
  "type": "Feature",
  "properties": {
    "gn:admin1_code": "5.0",
    "gn:asciiname": "Xidazhang",
    "gn:country_code": "CN",
    "gn:dem": 405,
    "gn:feature_class": "P",
    "gn:feature_code": "PPL",
    "gn:name": "Xidazhang",
    "gn:population": 0,
    "gn:timezone": "Asia/Shanghai",
    "iso:country": "CN",
    "name:zho_x_preferred": [
      "西大仗"
    ],
    "wof:name": "Xidazhang",
    "wof:placetype": "locality"
  },
  "geometry": {
    "coordinates": [
      125.4366,
      43.00897
    ],
    "type": "Point"
  }
}