{
  "type": "Feature",
  "properties": {
    "gn:admin1_code": "22.0",
    "gn:asciiname": "Ping'anjiecun",
    "gn:country_code": "CN",
    "gn:dem": 35,
    "gn:feature_class": "P",
    "gn:feature_code": "PPL",
    "gn:name": "Ping’anjiecun",
    "gn:population": 0,
    "gn:timezone": "Asia/Shanghai",
    "iso:country": "CN",
    "name:und_x_variant": [
      "Ping’anjiecun"
    ],
    "name:zho_x_preferred": [
      "平安街村"
    ],
    "wof:name": "Ping'anjiecun",
    "wof:placetype": "locality"
  },
  "geometry": {
    "coordinates": [
      117.11645,
      40.14218
    ],
    "type": "Point"
  }
}