{
  "type": "Feature",
  "properties": {
    "gn:admin1_code": "6.0",
    "gn:asciiname": "Zhihe Mari",
    "gn:country_code": "CN",
    "gn:dem": 3480,
    "gn:feature_class": "P",
    "gn:feature_code": "PPL",
    "gn:name": "Zhihe Mari",
    "gn:population": 0,
    "gn:timezone": "Asia/Shanghai",
    "iso:country": "CN",
    "name:zho_x_preferred": [
      "直禾麻日"
    ],
    "wof:name": "Zhihe Mari",
    "wof:placetype": "locality"
  },
  "geometry": {
    "coordinates": [
      101.10793,
      35.30408
    ],
    "type": "Point"
  }
}