{
  "type": "Feature",
  "properties": {
    "gn:admin1_code": "29.0",
    "gn:asciiname": "Xiazigou",
    "gn:country_code": "CN",
    "gn:dem": 1896,
    "gn:feature_class": "P",
    "gn:feature_code": "PPL",
    "gn:name": "Xiazigou",
    "gn:population": 0,
    "gn:timezone": "Asia/Shanghai",
    "iso:country": "CN",
    "name:zho_x_preferred": [
      "虾子沟"
    ],
    "wof:name": "Xiazigou",
    "wof:placetype": "locality"
  },
  "geometry": {
    "coordinates": [
      104.058,
      24.9621
    ],
    "type": "Point"
  }
}