{
  "type": "Feature",
  "properties": {
    "gn:admin1_code": "11.0",
    "gn:asciiname": "Dashuitang",
    "gn:country_code": "CN",
    "gn:dem": 477,
    "gn:feature_class": "P",
    "gn:feature_code": "PPL",
    "gn:name": "Dashuitang",
    "gn:population": 0,
    "gn:timezone": "Asia/Shanghai",
    "iso:country": "CN",
    "name:zho_x_preferred": [
      "大水塘"
    ],
    "wof:name": "Dashuitang",
    "wof:placetype": "locality"
  },
  "geometry": {
    "coordinates": [
      110.66531,
      26.55101
    ],
    "type": "Point"
  }
}