{
  "type": "Feature",
  "properties": {
    "gn:admin1_code": "29.0",
    "gn:asciiname": "Hongtupo",
    "gn:country_code": "CN",
    "gn:dem": 1338,
    "gn:feature_class": "P",
    "gn:feature_code": "PPL",
    "gn:name": "Hongtupo",
    "gn:population": 0,
    "gn:timezone": "Asia/Shanghai",
    "iso:country": "CN",
    "name:zho_x_preferred": [
      "红土坡"
    ],
    "wof:name": "Hongtupo",
    "wof:placetype": "locality"
  },
  "geometry": {
    "coordinates": [
      99.4981,
      24.2658
    ],
    "type": "Point"
  }
}