{
  "type": "Feature",
  "properties": {
    "gn:admin1_code": "31.0",
    "gn:asciiname": "Yufu",
    "gn:country_code": "CN",
    "gn:dem": 32,
    "gn:feature_class": "P",
    "gn:feature_code": "PPL",
    "gn:name": "Yufu",
    "gn:population": 0,
    "gn:timezone": "Asia/Shanghai",
    "iso:country": "CN",
    "name:ara_x_preferred": [
      "يوفو"
    ],
    "name:bul_x_preferred": [
      "Юфу"
    ],
    "name:ceb_x_preferred": [
      "Yufu-shi"
    ],
    "name:deu_x_preferred": [
      "Yufu"
    ],
    "name:fas_x_preferred": [
      "یوفو"
    ],
    "name:fin_x_preferred": [
      "Yufu"
    ],
    "name:fra_x_preferred": [
      "Yufu"
    ],
    "name:glg_x_preferred": [
      "Yufu"
    ],
    "name:ita_x_preferred": [
      "Yufu"
    ],
    "name:jpn_x_preferred": [
      "由布市"
    ],
    "name:kor_x_preferred": [
      "유후시"
    ],
    "name:mzn_x_preferred": [
      "یوفو"
    ],
    "name:nld_x_preferred": [
      "Yufu"
    ],
    "name:pol_x_preferred": [
      "Yufu"
    ],
    "name:ron_x_preferred": [
      "Yufu"
    ],
    "name:rus_x_preferred": [
      "Юфу"
    ],
    "name:swe_x_preferred": [
      "Yufu"
    ],
    "name:tgl_x_preferred": [
      "Yufu"
    ],
    "name:tum_x_preferred": [
      "Yufu"
    ],
    "name:tur_x_preferred": [
      "Yufu"
    ],
    "name:ukr_x_preferred": [
      "Юфу"
    ],
    "name:urd_x_preferred": [
      "یوفو"
    ],
    "name:vie_x_preferred": [
      "Yufu"
    ],
    "name:war_x_preferred": [
      "Yufu"
    ],
    "name:zho_x_preferred": [
      "玉符"
    ],
    "name:zho_x_variant": [
      "由布市"
    ],
    "wof:name": "Yufu",
    "wof:placetype": "locality"
  },
  "geometry": {
    "coordinates": [
      110.37761,
      19.90724
    ],
    "type": "Point"
  }
}