{
  "type": "Feature",
  "properties": {
    "gn:admin1_code": "10.0",
    "gn:asciiname": "Hanjiapo",
    "gn:country_code": "CN",
    "gn:dem": 1119,
    "gn:feature_class": "P",
    "gn:feature_code": "PPL",
    "gn:name": "Hanjiapo",
    "gn:population": 0,
    "gn:timezone": "Asia/Shanghai",
    "iso:country": "CN",
    "name:zho_x_preferred": [
      "韩家坡"
    ],
    "wof:name": "Hanjiapo",
    "wof:placetype": "locality"
  },
  "geometry": {
    "coordinates": [
      114.81838,
      40.34803
    ],
    "type": "Point"
  }
}