{
  "type": "Feature",
  "properties": {
    "gn:admin1_code": "3.0",
    "gn:asciiname": "Yanjia",
    "gn:country_code": "CN",
    "gn:dem": 122,
    "gn:feature_class": "P",
    "gn:feature_code": "PPL",
    "gn:name": "Yanjia",
    "gn:population": 0,
    "gn:timezone": "Asia/Shanghai",
    "iso:country": "CN",
    "name:zho_x_preferred": [
      "严家"
    ],
    "wof:name": "Yanjia",
    "wof:placetype": "locality"
  },
  "geometry": {
    "coordinates": [
      117.64098,
      28.17082000000001
    ],
    "type": "Point"
  }
}