{
  "type": "Feature",
  "properties": {
    "gn:admin1_code": "29.0",
    "gn:asciiname": "Huaying",
    "gn:country_code": "CN",
    "gn:dem": 1993,
    "gn:feature_class": "P",
    "gn:feature_code": "PPL",
    "gn:name": "Huaying",
    "gn:population": 0,
    "gn:timezone": "Asia/Shanghai",
    "iso:country": "CN",
    "name:ara_x_preferred": [
      "هواينغ"
    ],
    "name:dan_x_preferred": [
      "Huaying"
    ],
    "name:deu_x_preferred": [
      "Huaying"
    ],
    "name:fas_x_preferred": [
      "هوایینگ"
    ],
    "name:fra_x_preferred": [
      "Huaying"
    ],
    "name:hak_x_preferred": [
      "Fà-yìn-sṳ"
    ],
    "name:ita_x_preferred": [
      "Huaying"
    ],
    "name:jpn_x_preferred": [
      "華エイ市"
    ],
    "name:kik_x_preferred": [
      "Huaying"
    ],
    "name:kor_x_preferred": [
      "화잉시"
    ],
    "name:nor_x_preferred": [
      "Huaying"
    ],
    "name:rus_x_preferred": [
      "Хуаин"
    ],
    "name:swe_x_preferred": [
      "Huaying"
    ],
    "name:vie_x_preferred": [
      "Hoa Dinh"
    ],
    "name:war_x_preferred": [
      "Huaying"
    ],
    "name:zho_x_preferred": [
      "华营"
    ],
    "name:zho_x_variant": [
      "华蓥市"
    ],
    "wof:name": "Huaying",
    "wof:placetype": "locality"
  },
  "geometry": {
    "coordinates": [
      100.324,
      25.6243
    ],
    "type": "Point"
  }
}