{
  "type": "Feature",
  "properties": {
    "gn:admin1_code": "10.0",
    "gn:asciiname": "Xiaoxizhuang",
    "gn:country_code": "CN",
    "gn:dem": 69,
    "gn:feature_class": "P",
    "gn:feature_code": "PPL",
    "gn:name": "Xiaoxizhuang",
    "gn:population": 0,
    "gn:timezone": "Asia/Shanghai",
    "iso:country": "CN",
    "name:zho_x_preferred": [
      "小西庄"
    ],
    "wof:name": "Xiaoxizhuang",
    "wof:placetype": "locality"
  },
  "geometry": {
    "coordinates": [
      118.80053,
      40.08901
    ],
    "type": "Point"
  }
}