{
  "type": "Feature",
  "properties": {
    "gn:admin1_code": "13.0",
    "gn:asciiname": "Taldi",
    "gn:country_code": "CN",
    "gn:dem": 897,
    "gn:feature_class": "P",
    "gn:feature_code": "PPLA4",
    "gn:name": "Taldi",
    "gn:population": 0,
    "gn:timezone": "Asia/Urumqi",
    "iso:country": "CN",
    "name:uig_x_preferred": [
      "تالدى"
    ],
    "name:uig_x_variant": [
      "Талди"
    ],
    "name:und_x_variant": [
      "Taldi Xiang",
      "Taldi",
      "Talede",
      "Talede Xiang"
    ],
    "name:zho_x_preferred": [
      "塔勒德"
    ],
    "name:zho_x_variant": [
      "塔勒德乡"
    ],
    "wof:name": "Taldi",
    "wof:placetype": "locality"
  },
  "geometry": {
    "coordinates": [
      83.05389,
      43.41353
    ],
    "type": "Point"
  }
}