{
  "type": "Feature",
  "properties": {
    "gn:admin1_code": "11.0",
    "gn:asciiname": "Kongjialong",
    "gn:country_code": "CN",
    "gn:dem": 35,
    "gn:feature_class": "P",
    "gn:feature_code": "PPL",
    "gn:name": "Kongjialong",
    "gn:population": 0,
    "gn:timezone": "Asia/Shanghai",
    "iso:country": "CN",
    "name:zho_x_preferred": [
      "孔家龙"
    ],
    "wof:name": "Kongjialong",
    "wof:placetype": "locality"
  },
  "geometry": {
    "coordinates": [
      112.7188,
      28.38179
    ],
    "type": "Point"
  }
}