{
  "type": "Feature",
  "properties": {
    "gn:admin1_code": "7.0",
    "gn:asciiname": "Zhulinwei",
    "gn:country_code": "CN",
    "gn:dem": 177,
    "gn:feature_class": "P",
    "gn:feature_code": "PPL",
    "gn:name": "Zhulinwei",
    "gn:population": 0,
    "gn:timezone": "Asia/Shanghai",
    "iso:country": "CN",
    "name:zho_x_preferred": [
      "朱林尾"
    ],
    "wof:name": "Zhulinwei",
    "wof:placetype": "locality"
  },
  "geometry": {
    "coordinates": [
      118.18885,
      26.02843
    ],
    "type": "Point"
  }
}