{
  "type": "Feature",
  "properties": {
    "gn:admin1_code": "30",
    "gn:asciiname": "Ebu",
    "gn:country_code": "CN",
    "gn:dem": 13,
    "gn:feature_class": "P",
    "gn:feature_code": "PPLA4",
    "gn:name": "Ebu",
    "gn:population": 0,
    "gn:timezone": "Asia/Shanghai",
    "iso:country": "CN",
    "name:fas_x_preferred": [
      "ایبو"
    ],
    "name:swe_x_preferred": [
      "Ebu"
    ],
    "name:und_x_variant": [
      "Ebu Zhen"
    ],
    "name:zho_x_preferred": [
      "鹅埠"
    ],
    "name:zho_x_variant": [
      "鹅埠镇"
    ],
    "wof:name": "Ebu",
    "wof:placetype": "locality"
  },
  "geometry": {
    "coordinates": [
      114.9943,
      22.83197
    ],
    "type": "Point"
  }
}