{
  "type": "Feature",
  "properties": {
    "gn:admin1_code": "10",
    "gn:asciiname": "Wafangdian",
    "gn:country_code": "CN",
    "gn:dem": 625,
    "gn:feature_class": "P",
    "gn:feature_code": "PPL",
    "gn:name": "Wafangdian",
    "gn:population": 0,
    "gn:timezone": "Asia/Shanghai",
    "iso:country": "CN",
    "name:ara_x_preferred": [
      "وافانغديان"
    ],
    "name:ast_x_preferred": [
      "Wafangdian"
    ],
    "name:ben_x_preferred": [
      "ওয়াফ্যাংদিয়ান"
    ],
    "name:ceb_x_preferred": [
      "Wafangdian"
    ],
    "name:deu_x_preferred": [
      "Wafangdian"
    ],
    "name:ell_x_preferred": [
      "Γουαφανγντιάν"
    ],
    "name:fas_x_preferred": [
      "وافانگدیان"
    ],
    "name:fra_x_preferred": [
      "Wafangdian"
    ],
    "name:heb_x_preferred": [
      "וופאנגדיאן"
    ],
    "name:hin_x_preferred": [
      "वफांगदियान"
    ],
    "name:hun_x_preferred": [
      "Wafangdian"
    ],
    "name:ind_x_preferred": [
      "Wafangdian"
    ],
    "name:ita_x_preferred": [
      "Wafangdian"
    ],
    "name:jpn_x_preferred": [
      "瓦房店市"
    ],
    "name:kik_x_preferred": [
      "Wafangdian"
    ],
    "name:kor_x_preferred": [
      "와팡뎬시"
    ],
    "name:mlg_x_preferred": [
      "Wafangdian"
    ],
    "name:nor_x_preferred": [
      "Wafangdian"
    ],
    "name:pol_x_preferred": [
      "Wafangdian"
    ],
    "name:por_x_preferred": [
      "Wafangdian"
    ],
    "name:rus_x_preferred": [
      "Вафандянь"
    ],
    "name:spa_x_preferred": [
      "Wafangdian"
    ],
    "name:srp_x_preferred": [
      "Вафангдјен"
    ],
    "name:swe_x_preferred": [
      "Wafangdian"
    ],
    "name:tur_x_preferred": [
      "Wafangdian"
    ],
    "name:ukr_x_preferred": [
      "Вафандянь"
    ],
    "name:urd_x_preferred": [
      "وافانگدیان"
    ],
    "name:war_x_preferred": [
      "Wafangdian"
    ],
    "name:zho_x_preferred": [
      "瓦房店"
    ],
    "name:zho_x_variant": [
      "瓦房店市"
    ],
    "wof:name": "Wafangdian",
    "wof:placetype": "locality"
  },
  "geometry": {
    "coordinates": [
      118.7422,
      41.1443
    ],
    "type": "Point"
  }
}