{
  "type": "Feature",
  "properties": {
    "gn:admin1_code": "30",
    "gn:asciiname": "Nabu",
    "gn:country_code": "CN",
    "gn:dem": 138,
    "gn:feature_class": "P",
    "gn:feature_code": "PPL",
    "gn:name": "Nabu",
    "gn:population": 0,
    "gn:timezone": "Asia/Urumqi",
    "iso:country": "CN",
    "name:als_x_preferred": [
      "Nabu"
    ],
    "name:ara_x_preferred": [
      "نابو"
    ],
    "name:aze_x_preferred": [
      "Nabu"
    ],
    "name:cat_x_preferred": [
      "Nabu"
    ],
    "name:ces_x_preferred": [
      "Nabu"
    ],
    "name:deu_x_preferred": [
      "Nabu"
    ],
    "name:ell_x_preferred": [
      "Ναμπού"
    ],
    "name:eus_x_preferred": [
      "Nabu"
    ],
    "name:fas_x_preferred": [
      "نبو"
    ],
    "name:fra_x_preferred": [
      "Nabû"
    ],
    "name:glg_x_preferred": [
      "Nabu"
    ],
    "name:heb_x_preferred": [
      "נבו"
    ],
    "name:ind_x_preferred": [
      "Nabu"
    ],
    "name:ita_x_preferred": [
      "Nabu"
    ],
    "name:jpn_x_preferred": [
      "ナブー"
    ],
    "name:msa_x_preferred": [
      "Nabu"
    ],
    "name:nld_x_preferred": [
      "Nabu"
    ],
    "name:nor_x_preferred": [
      "Nebo"
    ],
    "name:oci_x_preferred": [
      "Nabu"
    ],
    "name:pol_x_preferred": [
      "Nabu"
    ],
    "name:por_x_preferred": [
      "Nabu"
    ],
    "name:ron_x_preferred": [
      "Nabu"
    ],
    "name:rus_x_preferred": [
      "Набу"
    ],
    "name:slk_x_preferred": [
      "Nabú"
    ],
    "name:slv_x_preferred": [
      "Nabu"
    ],
    "name:snd_x_preferred": [
      "نابو"
    ],
    "name:spa_x_preferred": [
      "Nabu"
    ],
    "name:swe_x_preferred": [
      "Nabu"
    ],
    "name:tgl_x_preferred": [
      "Nabu"
    ],
    "name:tha_x_preferred": [
      "เนโบ"
    ],
    "name:tur_x_preferred": [
      "Nabu"
    ],
    "name:ukr_x_preferred": [
      "Набу"
    ],
    "name:und_x_variant": [
      "Na-pu"
    ],
    "name:urd_x_preferred": [
      "نابو"
    ],
    "name:zho_x_preferred": [
      "那卜"
    ],
    "wof:name": "Nabu",
    "wof:placetype": "locality"
  },
  "geometry": {
    "coordinates": [
      110.18483,
      20.56565
    ],
    "type": "Point"
  }
}