{
  "type": "Feature",
  "properties": {
    "gn:admin1_code": "05",
    "gn:asciiname": "Sandaoyangcha",
    "gn:country_code": "CN",
    "gn:dem": 516,
    "gn:feature_class": "P",
    "gn:feature_code": "PPL",
    "gn:name": "Sandaoyangcha",
    "gn:population": 0,
    "gn:timezone": "Asia/Shanghai",
    "iso:country": "CN",
    "name:und_x_variant": [
      "三道阳岔",
      "San-tao-yang-ch’a"
    ],
    "wof:name": "Sandaoyangcha",
    "wof:placetype": "locality"
  },
  "geometry": {
    "coordinates": [
      126.02778,
      41.50306
    ],
    "type": "Point"
  }
}