{
  "type": "Feature",
  "properties": {
    "gn:admin1_code": "3.0",
    "gn:asciiname": "Jiantang",
    "gn:country_code": "CN",
    "gn:dem": 77,
    "gn:feature_class": "P",
    "gn:feature_code": "PPL",
    "gn:name": "Jiantang",
    "gn:population": 0,
    "gn:timezone": "Asia/Shanghai",
    "iso:country": "CN",
    "name:und_x_variant": [
      "枧塘"
    ],
    "name:zho_x_preferred": [
      "建塘镇"
    ],
    "wof:name": "Jiantang",
    "wof:placetype": "locality"
  },
  "geometry": {
    "coordinates": [
      116.61196,
      27.6014
    ],
    "type": "Point"
  }
}