{
  "type": "Feature",
  "properties": {
    "gn:admin1_code": "12.0",
    "gn:asciiname": "Liangjiayuan",
    "gn:country_code": "CN",
    "gn:dem": 31,
    "gn:feature_class": "P",
    "gn:feature_code": "PPL",
    "gn:name": "Liangjiayuan",
    "gn:population": 0,
    "gn:timezone": "Asia/Shanghai",
    "iso:country": "CN",
    "name:zho_x_preferred": [
      "Liangjiayuan"
    ],
    "name:zho_x_variant": [
      "梁家垸"
    ],
    "wof:name": "Liangjiayuan",
    "wof:placetype": "locality"
  },
  "geometry": {
    "coordinates": [
      115.35789,
      29.89224
    ],
    "type": "Point"
  }
}