{
  "type": "Feature",
  "properties": {
    "gn:admin1_code": "8.0",
    "gn:asciiname": "Banlashantun",
    "gn:country_code": "CN",
    "gn:dem": 129,
    "gn:feature_class": "P",
    "gn:feature_code": "PPL",
    "gn:name": "Banlashantun",
    "gn:population": 0,
    "gn:timezone": "Asia/Shanghai",
    "iso:country": "CN",
    "name:zho_x_preferred": [
      "半拉山屯"
    ],
    "wof:name": "Banlashantun",
    "wof:placetype": "locality"
  },
  "geometry": {
    "coordinates": [
      127.54954,
      45.909
    ],
    "type": "Point"
  }
}