{
  "type": "Feature",
  "properties": {
    "gn:admin1_code": "16",
    "gn:asciiname": "Yandi",
    "gn:country_code": "CN",
    "gn:dem": 922,
    "gn:feature_class": "P",
    "gn:feature_code": "PPL",
    "gn:name": "Yandi",
    "gn:population": 0,
    "gn:timezone": "Asia/Shanghai",
    "iso:country": "CN",
    "name:ceb_x_preferred": [
      "Yandi"
    ],
    "name:swe_x_preferred": [
      "Yandi"
    ],
    "name:zho_x_preferred": [
      "岩底"
    ],
    "wof:name": "Yandi",
    "wof:placetype": "locality"
  },
  "geometry": {
    "coordinates": [
      110.008,
      25.7194
    ],
    "type": "Point"
  }
}