{
  "type": "Feature",
  "properties": {
    "gn:admin1_code": "25.0",
    "gn:asciiname": "Yingli",
    "gn:country_code": "CN",
    "gn:dem": 53,
    "gn:feature_class": "P",
    "gn:feature_code": "PPL",
    "gn:name": "Yingli",
    "gn:population": 0,
    "gn:timezone": "Asia/Shanghai",
    "iso:country": "CN",
    "name:fin_x_preferred": [
      "Yingli"
    ],
    "name:fra_x_preferred": [
      "Yingli"
    ],
    "name:ita_x_preferred": [
      "Yingli"
    ],
    "name:jpn_x_preferred": [
      "英利緑色能源"
    ],
    "name:rus_x_preferred": [
      "Yingli"
    ],
    "name:spa_x_preferred": [
      "Yingli"
    ],
    "name:zho_x_preferred": [
      "营里"
    ],
    "name:zho_x_variant": [
      "英利绿色能源控股有限公司"
    ],
    "wof:name": "Yingli",
    "wof:placetype": "locality"
  },
  "geometry": {
    "coordinates": [
      119.84328,
      37.06918
    ],
    "type": "Point"
  }
}