{
  "type": "Feature",
  "properties": {
    "gn:admin1_code": "31.0",
    "gn:asciiname": "Miaocun",
    "gn:country_code": "CN",
    "gn:dem": 175,
    "gn:feature_class": "P",
    "gn:feature_code": "PPL",
    "gn:name": "Miaocun",
    "gn:population": 0,
    "gn:timezone": "Asia/Shanghai",
    "iso:country": "CN",
    "name:zho_x_preferred": [
      "苗村"
    ],
    "wof:name": "Miaocun",
    "wof:placetype": "locality"
  },
  "geometry": {
    "coordinates": [
      109.04017,
      18.929
    ],
    "type": "Point"
  }
}