{
  "type": "Feature",
  "properties": {
    "gn:admin1_code": "2",
    "gn:asciiname": "Zhouzhuang",
    "gn:country_code": "CN",
    "gn:dem": 48,
    "gn:feature_class": "P",
    "gn:feature_code": "PPL",
    "gn:name": "Zhouzhuang",
    "gn:population": 0,
    "gn:timezone": "Asia/Shanghai",
    "iso:country": "CN",
    "name:ceb_x_preferred": [
      "Zhouzhuang"
    ],
    "name:deu_x_preferred": [
      "Zhouzhuang"
    ],
    "name:fas_x_preferred": [
      "ژوژوانگ"
    ],
    "name:fra_x_preferred": [
      "Zhouzhuang"
    ],
    "name:ita_x_preferred": [
      "Zhouzhuang"
    ],
    "name:jpn_x_preferred": [
      "周荘鎮"
    ],
    "name:kor_x_preferred": [
      "저우장 진"
    ],
    "name:nor_x_preferred": [
      "Zhouzhuang"
    ],
    "name:spa_x_preferred": [
      "Zhouzhuang"
    ],
    "name:sqi_x_preferred": [
      "Zhouzhuan"
    ],
    "name:swe_x_preferred": [
      "Zhouzhuang"
    ],
    "name:ukr_x_preferred": [
      "Чжоучжуан"
    ],
    "name:vie_x_preferred": [
      "Chu Trang"
    ],
    "name:wuu_x_preferred": [
      "周庄镇"
    ],
    "name:zho_x_preferred": [
      "周庄"
    ],
    "name:zho_x_variant": [
      "周庄镇"
    ],
    "wof:name": "Zhouzhuang",
    "wof:placetype": "locality"
  },
  "geometry": {
    "coordinates": [
      120.3422,
      29.55029
    ],
    "type": "Point"
  }
}