{
  "type": "Feature",
  "properties": {
    "gn:admin1_code": "26",
    "gn:asciiname": "Dancun",
    "gn:country_code": "CN",
    "gn:dem": 504,
    "gn:feature_class": "P",
    "gn:feature_code": "PPLA4",
    "gn:name": "Dancun",
    "gn:population": 0,
    "gn:timezone": "Asia/Shanghai",
    "iso:country": "CN",
    "name:und_x_variant": [
      "Tan-ts’un",
      "Tan-ts’un-chen",
      "Dancun",
      "Dancun Zhen"
    ],
    "name:zho_x_preferred": [
      "淡村"
    ],
    "wof:name": "Dancun",
    "wof:placetype": "locality"
  },
  "geometry": {
    "coordinates": [
      109.05352,
      34.71947
    ],
    "type": "Point"
  }
}