{
  "type": "Feature",
  "properties": {
    "gn:admin1_code": "16.0",
    "gn:asciiname": "Gongtang",
    "gn:country_code": "CN",
    "gn:dem": 65,
    "gn:feature_class": "P",
    "gn:feature_code": "PPL",
    "gn:name": "Gongtang",
    "gn:population": 0,
    "gn:timezone": "Asia/Shanghai",
    "iso:country": "CN",
    "name:ceb_x_preferred": [
      "Gongtang"
    ],
    "name:fas_x_preferred": [
      "گونگتانگ"
    ],
    "name:msa_x_preferred": [
      "Gongtang"
    ],
    "name:swe_x_preferred": [
      "Gongtang"
    ],
    "name:zho_x_preferred": [
      "公塘"
    ],
    "name:zho_x_variant": [
      "公塘乡"
    ],
    "wof:name": "Gongtang",
    "wof:placetype": "locality"
  },
  "geometry": {
    "coordinates": [
      109.742,
      23.2574
    ],
    "type": "Point"
  }
}