{
  "type": "Feature",
  "properties": {
    "gn:admin1_code": "33.0",
    "gn:asciiname": "Yinjia",
    "gn:country_code": "CN",
    "gn:dem": 401,
    "gn:feature_class": "P",
    "gn:feature_code": "PPL",
    "gn:name": "Yinjia",
    "gn:population": 0,
    "gn:timezone": "Asia/Shanghai",
    "iso:country": "CN",
    "name:zho_x_preferred": [
      "殷家"
    ],
    "wof:name": "Yinjia",
    "wof:placetype": "locality"
  },
  "geometry": {
    "coordinates": [
      107.59915,
      29.99045
    ],
    "type": "Point"
  }
}