{
  "type": "Feature",
  "properties": {
    "gn:admin1_code": "11.0",
    "gn:asciiname": "Wu'erdong",
    "gn:country_code": "CN",
    "gn:dem": 341,
    "gn:feature_class": "P",
    "gn:feature_code": "PPL",
    "gn:name": "Wu’erdong",
    "gn:population": 0,
    "gn:timezone": "Asia/Shanghai",
    "iso:country": "CN",
    "name:und_x_variant": [
      "Wu’erdong"
    ],
    "name:zho_x_preferred": [
      "屋二洞"
    ],
    "wof:name": "Wu'erdong",
    "wof:placetype": "locality"
  },
  "geometry": {
    "coordinates": [
      109.81394,
      28.38418
    ],
    "type": "Point"
  }
}