{
  "type": "Feature",
  "properties": {
    "gn:admin1_code": "3.0",
    "gn:asciiname": "Xujiazhai",
    "gn:country_code": "CN",
    "gn:dem": 389,
    "gn:feature_class": "P",
    "gn:feature_code": "PPL",
    "gn:name": "Xujiazhai",
    "gn:population": 0,
    "gn:timezone": "Asia/Shanghai",
    "iso:country": "CN",
    "name:und_x_variant": [
      "徐家寨"
    ],
    "wof:name": "Xujiazhai",
    "wof:placetype": "locality"
  },
  "geometry": {
    "coordinates": [
      115.87616,
      27.07229
    ],
    "type": "Point"
  }
}