{
  "type": "Feature",
  "properties": {
    "gn:admin1_code": "7.0",
    "gn:asciiname": "Linkou",
    "gn:country_code": "CN",
    "gn:dem": 60,
    "gn:feature_class": "P",
    "gn:feature_code": "PPL",
    "gn:name": "Linkou",
    "gn:population": 0,
    "gn:timezone": "Asia/Shanghai",
    "iso:country": "CN",
    "name:ara_x_preferred": [
      "لينكو"
    ],
    "name:ben_x_preferred": [
      "লিনকোউ"
    ],
    "name:deu_x_preferred": [
      "Linkou"
    ],
    "name:ell_x_preferred": [
      "Λίνκου"
    ],
    "name:fas_x_preferred": [
      "لینکو"
    ],
    "name:fra_x_preferred": [
      "Linkou"
    ],
    "name:heb_x_preferred": [
      "לינוקואו"
    ],
    "name:hin_x_preferred": [
      "लिंकाउ"
    ],
    "name:hun_x_preferred": [
      "Linkou"
    ],
    "name:ind_x_preferred": [
      "Linkou"
    ],
    "name:ita_x_preferred": [
      "Linkou"
    ],
    "name:jpn_x_preferred": [
      "林口"
    ],
    "name:kor_x_preferred": [
      "린커우"
    ],
    "name:mlg_x_preferred": [
      "Linkou"
    ],
    "name:nld_x_preferred": [
      "Linkou"
    ],
    "name:pol_x_preferred": [
      "Linkou"
    ],
    "name:por_x_preferred": [
      "Linkou"
    ],
    "name:rus_x_preferred": [
      "Линькоу"
    ],
    "name:spa_x_preferred": [
      "Linkou"
    ],
    "name:swe_x_preferred": [
      "Linkou"
    ],
    "name:tur_x_preferred": [
      "Linkou"
    ],
    "name:ukr_x_preferred": [
      "Лінькоу"
    ],
    "name:urd_x_preferred": [
      "لنکو"
    ],
    "name:vie_x_preferred": [
      "Lâm Khẩu"
    ],
    "name:zho_tw_x_preferred": [
      "林口"
    ],
    "name:zho_x_preferred": [
      "林口"
    ],
    "wof:name": "Linkou",
    "wof:placetype": "locality"
  },
  "geometry": {
    "coordinates": [
      118.74794,
      25.03136
    ],
    "type": "Point"
  }
}