{
  "type": "Feature",
  "properties": {
    "gn:admin1_code": "4.0",
    "gn:asciiname": "Xiantian",
    "gn:country_code": "CN",
    "gn:dem": 15,
    "gn:feature_class": "P",
    "gn:feature_code": "PPL",
    "gn:name": "Xiantian",
    "gn:population": 0,
    "gn:timezone": "Asia/Shanghai",
    "iso:country": "CN",
    "name:und_x_variant": [
      "Su-ts’un",
      "Hsien-t’ien",
      "Hsien-t’ien-ts’un",
      "Xiantiancun",
      "Xiantian",
      "咸田"
    ],
    "name:zho_x_preferred": [
      "咸田"
    ],
    "wof:name": "Xiantian",
    "wof:placetype": "locality"
  },
  "geometry": {
    "coordinates": [
      118.94025,
      31.90314
    ],
    "type": "Point"
  }
}