{
  "type": "Feature",
  "properties": {
    "gn:admin1_code": "31",
    "gn:asciiname": "Shuidong",
    "gn:country_code": "CN",
    "gn:dem": 21,
    "gn:feature_class": "P",
    "gn:feature_code": "PPL",
    "gn:name": "Shuidong",
    "gn:population": 0,
    "gn:timezone": "Asia/Shanghai",
    "iso:country": "CN",
    "name:und_x_variant": [
      "水东",
      "Shuiliudong",
      "Shuiliu",
      "水流东"
    ],
    "name:zho_x_preferred": [
      "水流"
    ],
    "wof:name": "Shuidong",
    "wof:placetype": "locality"
  },
  "geometry": {
    "coordinates": [
      108.731,
      19.2069
    ],
    "type": "Point"
  }
}