{
  "type": "Feature",
  "properties": {
    "gn:admin1_code": "19.0",
    "gn:asciiname": "Lujiatun",
    "gn:country_code": "CN",
    "gn:dem": 158,
    "gn:feature_class": "P",
    "gn:feature_code": "PPL",
    "gn:name": "Lüjiatun",
    "gn:population": 0,
    "gn:timezone": "Asia/Shanghai",
    "iso:country": "CN",
    "name:zho_x_preferred": [
      "Lüjiatun"
    ],
    "name:zho_x_variant": [
      "吕家屯"
    ],
    "wof:name": "Lujiatun",
    "wof:placetype": "locality"
  },
  "geometry": {
    "coordinates": [
      124.2549,
      42.30401
    ],
    "type": "Point"
  }
}