{
  "type": "Feature",
  "properties": {
    "gn:admin1_code": "7.0",
    "gn:asciiname": "Dahu",
    "gn:country_code": "CN",
    "gn:dem": 336,
    "gn:feature_class": "P",
    "gn:feature_code": "PPL",
    "gn:name": "Dahu",
    "gn:population": 0,
    "gn:timezone": "Asia/Shanghai",
    "iso:country": "CN",
    "name:deu_x_preferred": [
      "Dahu"
    ],
    "name:fra_x_preferred": [
      "Dahu"
    ],
    "name:frp_x_preferred": [
      "Dahu"
    ],
    "name:heb_x_preferred": [
      "Dahu"
    ],
    "name:ita_x_preferred": [
      "Dahu"
    ],
    "name:lmo_x_preferred": [
      "Daù"
    ],
    "name:mkd_x_preferred": [
      "Даху"
    ],
    "name:nld_x_preferred": [
      "Dahu"
    ],
    "name:por_x_preferred": [
      "Dahu"
    ],
    "name:rus_x_preferred": [
      "Даху"
    ],
    "name:spa_x_preferred": [
      "Dahu"
    ],
    "name:srp_x_preferred": [
      "Даху"
    ],
    "name:zho_x_preferred": [
      "大湖"
    ],
    "wof:name": "Dahu",
    "wof:placetype": "locality"
  },
  "geometry": {
    "coordinates": [
      117.16943,
      24.30877000000001
    ],
    "type": "Point"
  }
}