{
  "type": "Feature",
  "properties": {
    "gn:admin1_code": "8.0",
    "gn:asciiname": "Sidaogoucun",
    "gn:country_code": "CN",
    "gn:dem": 441,
    "gn:feature_class": "P",
    "gn:feature_code": "PPL",
    "gn:name": "Sidaogoucun",
    "gn:population": 0,
    "gn:timezone": "Asia/Shanghai",
    "iso:country": "CN",
    "name:zho_x_preferred": [
      "四道沟村"
    ],
    "wof:name": "Sidaogoucun",
    "wof:placetype": "locality"
  },
  "geometry": {
    "coordinates": [
      128.95429,
      43.6784
    ],
    "type": "Point"
  }
}