{
  "type": "Feature",
  "properties": {
    "gn:admin1_code": "33.0",
    "gn:asciiname": "Gaofeng",
    "gn:country_code": "CN",
    "gn:dem": 719,
    "gn:feature_class": "P",
    "gn:feature_code": "PPL",
    "gn:name": "Gaofeng",
    "gn:population": 0,
    "gn:timezone": "Asia/Shanghai",
    "iso:country": "CN",
    "name:zho_x_preferred": [
      "高峰"
    ],
    "wof:name": "Gaofeng",
    "wof:placetype": "locality"
  },
  "geometry": {
    "coordinates": [
      107.76511,
      30.06213
    ],
    "type": "Point"
  }
}