{
  "type": "Feature",
  "properties": {
    "gn:admin1_code": "32.0",
    "gn:asciiname": "Xionghuatang",
    "gn:country_code": "CN",
    "gn:dem": 328,
    "gn:feature_class": "P",
    "gn:feature_code": "PPL",
    "gn:name": "Xionghuatang",
    "gn:population": 0,
    "gn:timezone": "Asia/Shanghai",
    "iso:country": "CN",
    "name:zho_x_preferred": [
      "熊华堂"
    ],
    "wof:name": "Xionghuatang",
    "wof:placetype": "locality"
  },
  "geometry": {
    "coordinates": [
      104.66529,
      29.47861
    ],
    "type": "Point"
  }
}