{
  "type": "Feature",
  "properties": {
    "gn:admin1_code": "26",
    "gn:asciiname": "Hetaoba",
    "gn:country_code": "CN",
    "gn:dem": 1280,
    "gn:feature_class": "P",
    "gn:feature_code": "PPL",
    "gn:name": "Hetaoba",
    "gn:population": 0,
    "gn:timezone": "Asia/Shanghai",
    "iso:country": "CN",
    "name:und_x_variant": [
      "Khetaotszyuy",
      "Ho-t’ao-chü",
      "Ho-t’ao-pa",
      "Hetaoba",
      "核桃坝"
    ],
    "wof:name": "Hetaoba",
    "wof:placetype": "locality"
  },
  "geometry": {
    "coordinates": [
      106.97176,
      33.98005999999999
    ],
    "type": "Point"
  }
}