{
  "type": "Feature",
  "properties": {
    "gn:admin1_code": "21.0",
    "gn:asciiname": "Yin'erxian",
    "gn:country_code": "CN",
    "gn:dem": 1844,
    "gn:feature_class": "P",
    "gn:feature_code": "PPL",
    "gn:name": "Yin’erxian",
    "gn:population": 0,
    "gn:timezone": "Asia/Shanghai",
    "iso:country": "CN",
    "name:und_x_variant": [
      "Yin’erxian"
    ],
    "name:zho_x_preferred": [
      "因儿岘"
    ],
    "wof:name": "Yin'erxian",
    "wof:placetype": "locality"
  },
  "geometry": {
    "coordinates": [
      105.359,
      36.7743
    ],
    "type": "Point"
  }
}