{
  "type": "Feature",
  "properties": {
    "gn:admin1_code": "18.0",
    "gn:asciiname": "Beichong",
    "gn:country_code": "CN",
    "gn:dem": 603,
    "gn:feature_class": "P",
    "gn:feature_code": "PPL",
    "gn:name": "Beichong",
    "gn:population": 0,
    "gn:timezone": "Asia/Shanghai",
    "iso:country": "CN",
    "name:zho_x_preferred": [
      "北冲"
    ],
    "wof:name": "Beichong",
    "wof:placetype": "locality"
  },
  "geometry": {
    "coordinates": [
      109.178,
      26.1589
    ],
    "type": "Point"
  }
}