{
  "type": "Feature",
  "properties": {
    "gn:admin1_code": "19.0",
    "gn:asciiname": "Ba'erhu Yingzi",
    "gn:country_code": "CN",
    "gn:dem": 26,
    "gn:feature_class": "P",
    "gn:feature_code": "PPL",
    "gn:name": "Ba’erhu Yingzi",
    "gn:population": 0,
    "gn:timezone": "Asia/Shanghai",
    "iso:country": "CN",
    "name:und_x_variant": [
      "Ba’erhu Yingzi"
    ],
    "name:zho_x_preferred": [
      "巴尔虎营子"
    ],
    "wof:name": "Ba'erhu Yingzi",
    "wof:placetype": "locality"
  },
  "geometry": {
    "coordinates": [
      123.06,
      39.82
    ],
    "type": "Point"
  }
}