{
  "type": "Feature",
  "properties": {
    "gn:admin1_code": "4.0",
    "gn:asciiname": "Yanshanhe",
    "gn:country_code": "CN",
    "gn:dem": 10,
    "gn:feature_class": "P",
    "gn:feature_code": "PPL",
    "gn:name": "Yanshanhe",
    "gn:population": 0,
    "gn:timezone": "Asia/Shanghai",
    "iso:country": "CN",
    "name:zho_x_preferred": [
      "沿山河"
    ],
    "wof:name": "Yanshanhe",
    "wof:placetype": "locality"
  },
  "geometry": {
    "coordinates": [
      119.33509,
      32.37838
    ],
    "type": "Point"
  }
}