{
  "type": "Feature",
  "properties": {
    "gn:admin1_code": "1.0",
    "gn:asciiname": "Xuqiaocun",
    "gn:country_code": "CN",
    "gn:dem": 33,
    "gn:feature_class": "P",
    "gn:feature_code": "PPL",
    "gn:name": "Xuqiaocun",
    "gn:population": 0,
    "gn:timezone": "Asia/Shanghai",
    "iso:country": "CN",
    "name:zho_x_preferred": [
      "徐桥村"
    ],
    "wof:name": "Xuqiaocun",
    "wof:placetype": "locality"
  },
  "geometry": {
    "coordinates": [
      116.3561,
      33.37563
    ],
    "type": "Point"
  }
}