{
  "type": "Feature",
  "properties": {
    "gn:admin1_code": "11.0",
    "gn:asciiname": "Shanghuashuilao",
    "gn:country_code": "CN",
    "gn:dem": 32,
    "gn:feature_class": "P",
    "gn:feature_code": "PPL",
    "gn:name": "Shanghuashuilao",
    "gn:population": 0,
    "gn:timezone": "Asia/Shanghai",
    "iso:country": "CN",
    "name:zho_x_preferred": [
      "上花水老"
    ],
    "wof:name": "Shanghuashuilao",
    "wof:placetype": "locality"
  },
  "geometry": {
    "coordinates": [
      112.11852,
      29.0828
    ],
    "type": "Point"
  }
}