{
  "type": "Feature",
  "properties": {
    "gn:admin1_code": "26.0",
    "gn:asciiname": "Awucun",
    "gn:country_code": "CN",
    "gn:dem": 1244,
    "gn:feature_class": "P",
    "gn:feature_code": "PPL",
    "gn:name": "Awucun",
    "gn:population": 0,
    "gn:timezone": "Asia/Shanghai",
    "iso:country": "CN",
    "name:zho_x_preferred": [
      "阿吾村"
    ],
    "wof:name": "Awucun",
    "wof:placetype": "locality"
  },
  "geometry": {
    "coordinates": [
      109.51577,
      35.85975
    ],
    "type": "Point"
  }
}