{
  "type": "Feature",
  "properties": {
    "gn:admin1_code": "16.0",
    "gn:asciiname": "Lasha",
    "gn:country_code": "CN",
    "gn:dem": 230,
    "gn:feature_class": "P",
    "gn:feature_code": "PPL",
    "gn:name": "Lasha",
    "gn:population": 0,
    "gn:timezone": "Asia/Shanghai",
    "iso:country": "CN",
    "name:ell_x_preferred": [
      "Λασά"
    ],
    "name:rus_x_preferred": [
      "Лаша"
    ],
    "name:zho_x_preferred": [
      "拉沙"
    ],
    "wof:name": "Lasha",
    "wof:placetype": "locality"
  },
  "geometry": {
    "coordinates": [
      108.297,
      24.4712
    ],
    "type": "Point"
  }
}