{
  "type": "Feature",
  "properties": {
    "gn:admin1_code": "30.0",
    "gn:asciiname": "Lundaocun",
    "gn:country_code": "CN",
    "gn:dem": 52,
    "gn:feature_class": "P",
    "gn:feature_code": "PPL",
    "gn:name": "Lundaocun",
    "gn:population": 0,
    "gn:timezone": "Asia/Urumqi",
    "iso:country": "CN",
    "name:zho_x_preferred": [
      "伦道村"
    ],
    "wof:name": "Lundaocun",
    "wof:placetype": "locality"
  },
  "geometry": {
    "coordinates": [
      110.72195,
      22.03925
    ],
    "type": "Point"
  }
}