{
  "type": "Feature",
  "properties": {
    "gn:admin1_code": "29.0",
    "gn:asciiname": "Kaji",
    "gn:country_code": "CN",
    "gn:dem": 1989,
    "gn:feature_class": "P",
    "gn:feature_code": "PPL",
    "gn:name": "Kaji",
    "gn:population": 0,
    "gn:timezone": "Asia/Shanghai",
    "iso:country": "CN",
    "name:ceb_x_preferred": [
      "Kaji"
    ],
    "name:deu_x_preferred": [
      "Kaji"
    ],
    "name:rus_x_preferred": [
      "Кадзи"
    ],
    "name:swe_x_preferred": [
      "Kaji"
    ],
    "name:und_x_variant": [
      "卡基"
    ],
    "wof:name": "Kaji",
    "wof:placetype": "locality"
  },
  "geometry": {
    "coordinates": [
      104.13581,
      25.25034
    ],
    "type": "Point"
  }
}