{
  "type": "Feature",
  "properties": {
    "gn:admin1_code": "12",
    "gn:asciiname": "Siping",
    "gn:country_code": "CN",
    "gn:dem": 249,
    "gn:feature_class": "P",
    "gn:feature_code": "PPLA4",
    "gn:name": "Siping",
    "gn:population": 0,
    "gn:timezone": "Asia/Shanghai",
    "iso:country": "CN",
    "name:ceb_x_preferred": [
      "Siping"
    ],
    "name:heb_x_preferred": [
      "סיפינג"
    ],
    "name:und_x_variant": [
      "Ssu-p’ing",
      "Siping Zhen"
    ],
    "name:zho_x_preferred": [
      "寺坪"
    ],
    "name:zho_x_variant": [
      "寺坪镇"
    ],
    "wof:name": "Siping",
    "wof:placetype": "locality"
  },
  "geometry": {
    "coordinates": [
      111.13187,
      31.98691
    ],
    "type": "Point"
  }
}