{
  "type": "Feature",
  "properties": {
    "gn:admin1_code": "24.0",
    "gn:asciiname": "Shiban",
    "gn:country_code": "CN",
    "gn:dem": 1164,
    "gn:feature_class": "P",
    "gn:feature_code": "PPL",
    "gn:name": "Shiban",
    "gn:population": 0,
    "gn:timezone": "Asia/Shanghai",
    "iso:country": "CN",
    "name:ara_x_preferred": [
      "شيبان"
    ],
    "name:aze_x_preferred": [
      "Şeyban xan"
    ],
    "name:cat_x_preferred": [
      "Xiban"
    ],
    "name:deu_x_preferred": [
      "Shibani Khan"
    ],
    "name:fra_x_preferred": [
      "Chayban"
    ],
    "name:ita_x_preferred": [
      "Shibani Khan"
    ],
    "name:jpn_x_preferred": [
      "シバン"
    ],
    "name:kor_x_preferred": [
      "샤이반"
    ],
    "name:mon_x_preferred": [
      "Шибан"
    ],
    "name:nld_x_preferred": [
      "Siban"
    ],
    "name:rus_x_preferred": [
      "Шибан"
    ],
    "name:tat_x_preferred": [
      "Шәйбән"
    ],
    "name:tur_x_preferred": [
      "Şiban"
    ],
    "name:ukr_x_preferred": [
      "Шибан"
    ],
    "name:uzb_x_preferred": [
      "Shaybon"
    ],
    "name:zho_x_preferred": [
      "石板"
    ],
    "wof:name": "Shiban",
    "wof:placetype": "locality"
  },
  "geometry": {
    "coordinates": [
      112.23021,
      35.28115
    ],
    "type": "Point"
  }
}