{
  "type": "Feature",
  "properties": {
    "gn:admin1_code": "19.0",
    "gn:asciiname": "Zhanjia Buzicun",
    "gn:country_code": "CN",
    "gn:dem": 168,
    "gn:feature_class": "P",
    "gn:feature_code": "PPL",
    "gn:name": "Zhanjia Buzicun",
    "gn:population": 0,
    "gn:timezone": "Asia/Shanghai",
    "iso:country": "CN",
    "name:zho_x_preferred": [
      "詹家堡子村"
    ],
    "wof:name": "Zhanjia Buzicun",
    "wof:placetype": "locality"
  },
  "geometry": {
    "coordinates": [
      123.442,
      40.9534
    ],
    "type": "Point"
  }
}