{
  "type": "Feature",
  "properties": {
    "gn:admin1_code": "11.0",
    "gn:asciiname": "Mati",
    "gn:country_code": "CN",
    "gn:dem": 179,
    "gn:feature_class": "P",
    "gn:feature_code": "PPL",
    "gn:name": "Mati",
    "gn:population": 0,
    "gn:timezone": "Asia/Shanghai",
    "iso:country": "CN",
    "name:ceb_x_preferred": [
      "Mati"
    ],
    "name:deu_x_preferred": [
      "Mati"
    ],
    "name:ell_x_preferred": [
      "Μάτι"
    ],
    "name:fra_x_preferred": [
      "Mati"
    ],
    "name:ita_x_preferred": [
      "Mati"
    ],
    "name:nld_x_preferred": [
      "Mati"
    ],
    "name:que_x_preferred": [
      "Mati"
    ],
    "name:slk_x_preferred": [
      "Mati"
    ],
    "name:spa_x_preferred": [
      "Mati"
    ],
    "name:swe_x_preferred": [
      "Mati"
    ],
    "name:zho_x_preferred": [
      "马蹄"
    ],
    "wof:name": "Mati",
    "wof:placetype": "locality"
  },
  "geometry": {
    "coordinates": [
      111.67642,
      25.63726
    ],
    "type": "Point"
  }
}