{
  "type": "Feature",
  "properties": {
    "gn:admin1_code": "10",
    "gn:asciiname": "Beishikou",
    "gn:country_code": "CN",
    "gn:dem": 73,
    "gn:feature_class": "P",
    "gn:feature_code": "PPL",
    "gn:name": "Beishikou",
    "gn:population": 0,
    "gn:timezone": "Asia/Shanghai",
    "iso:country": "CN",
    "name:zho_x_preferred": [
      "北石口"
    ],
    "wof:name": "Beishikou",
    "wof:placetype": "locality"
  },
  "geometry": {
    "coordinates": [
      114.441,
      36.8029
    ],
    "type": "Point"
  }
}