{
  "type": "Feature",
  "properties": {
    "gn:admin1_code": "32.0",
    "gn:asciiname": "Leipo",
    "gn:country_code": "CN",
    "gn:dem": 493,
    "gn:feature_class": "P",
    "gn:feature_code": "PPL",
    "gn:name": "Leipo",
    "gn:population": 0,
    "gn:timezone": "Asia/Shanghai",
    "iso:country": "CN",
    "name:zho_x_preferred": [
      "雷坡"
    ],
    "wof:name": "Leipo",
    "wof:placetype": "locality"
  },
  "geometry": {
    "coordinates": [
      103.926,
      30.4051
    ],
    "type": "Point"
  }
}