{
  "type": "Feature",
  "properties": {
    "gn:admin1_code": "2.0",
    "gn:asciiname": "Changtangxu",
    "gn:country_code": "CN",
    "gn:dem": 115,
    "gn:feature_class": "P",
    "gn:feature_code": "PPL",
    "gn:name": "Changtangxu",
    "gn:population": 0,
    "gn:timezone": "Asia/Shanghai",
    "iso:country": "CN",
    "name:zho_x_preferred": [
      "长塘徐"
    ],
    "wof:name": "Changtangxu",
    "wof:placetype": "locality"
  },
  "geometry": {
    "coordinates": [
      119.84357,
      29.27137
    ],
    "type": "Point"
  }
}