{
  "type": "Feature",
  "properties": {
    "gn:admin1_code": "07",
    "gn:asciiname": "Chadi",
    "gn:country_code": "CN",
    "gn:dem": 420,
    "gn:feature_class": "P",
    "gn:feature_code": "PPLA4",
    "gn:name": "Chadi",
    "gn:population": 0,
    "gn:timezone": "Asia/Shanghai",
    "iso:country": "CN",
    "name:ara_x_preferred": [
      "شادي"
    ],
    "name:und_x_variant": [
      "Dianqian",
      "Chadi",
      "Chadi Xiang",
      "茶地乡"
    ],
    "name:zho_x_preferred": [
      "Ch’a-ti"
    ],
    "name:zho_x_variant": [
      "茶地"
    ],
    "wof:name": "Chadi",
    "wof:placetype": "locality"
  },
  "geometry": {
    "coordinates": [
      116.58014,
      25.02466
    ],
    "type": "Point"
  }
}