{
  "type": "Feature",
  "properties": {
    "gn:admin1_code": "26.0",
    "gn:asciiname": "Beishijiazhuangcun",
    "gn:country_code": "CN",
    "gn:dem": 857,
    "gn:feature_class": "P",
    "gn:feature_code": "PPL",
    "gn:name": "Beishijiazhuangcun",
    "gn:population": 0,
    "gn:timezone": "Asia/Shanghai",
    "iso:country": "CN",
    "name:zho_x_preferred": [
      "北史家庄村"
    ],
    "wof:name": "Beishijiazhuangcun",
    "wof:placetype": "locality"
  },
  "geometry": {
    "coordinates": [
      110.39295,
      36.18927
    ],
    "type": "Point"
  }
}