{
  "type": "Feature",
  "properties": {
    "gn:admin1_code": "29.0",
    "gn:asciiname": "Laowuchong",
    "gn:country_code": "CN",
    "gn:dem": 1867,
    "gn:feature_class": "P",
    "gn:feature_code": "PPL",
    "gn:name": "Laowuchong",
    "gn:population": 0,
    "gn:timezone": "Asia/Shanghai",
    "iso:country": "CN",
    "name:zho_x_preferred": [
      "老吴冲"
    ],
    "wof:name": "Laowuchong",
    "wof:placetype": "locality"
  },
  "geometry": {
    "coordinates": [
      103.853,
      25.2017
    ],
    "type": "Point"
  }
}