{
  "type": "Feature",
  "properties": {
    "gn:admin1_code": "3.0",
    "gn:asciiname": "Yangjiang",
    "gn:country_code": "CN",
    "gn:dem": 81,
    "gn:feature_class": "P",
    "gn:feature_code": "PPLA4",
    "gn:name": "Yangjiang",
    "gn:population": 0,
    "gn:timezone": "Asia/Shanghai",
    "iso:country": "CN",
    "name:afr_x_preferred": [
      "Yangjiang"
    ],
    "name:ara_x_preferred": [
      "يانغجيانغ"
    ],
    "name:cdo_x_preferred": [
      "Iòng-gŏng"
    ],
    "name:ceb_x_preferred": [
      "Yangjiang"
    ],
    "name:ces_x_preferred": [
      "Jang-ťiang"
    ],
    "name:cym_x_preferred": [
      "Yangjiang"
    ],
    "name:dan_x_preferred": [
      "Yangjiang"
    ],
    "name:deu_x_preferred": [
      "Yangjiang"
    ],
    "name:eus_x_preferred": [
      "Yangjiang"
    ],
    "name:fas_x_preferred": [
      "یانگژیانگ"
    ],
    "name:fin_x_preferred": [
      "Yangjiang"
    ],
    "name:fra_x_preferred": [
      "Yangjiang"
    ],
    "name:hak_x_preferred": [
      "Yòng-kông-sṳ"
    ],
    "name:ind_x_preferred": [
      "Yangjiang"
    ],
    "name:ita_x_preferred": [
      "Yangjiang"
    ],
    "name:jpn_x_preferred": [
      "陽江"
    ],
    "name:jpn_x_variant": [
      "陽江市"
    ],
    "name:kik_x_preferred": [
      "Yangjiang"
    ],
    "name:kor_x_preferred": [
      "양장시"
    ],
    "name:mlg_x_preferred": [
      "Yangjiang"
    ],
    "name:nld_x_preferred": [
      "Yangjiang"
    ],
    "name:nno_x_preferred": [
      "Yangjiang"
    ],
    "name:nor_x_preferred": [
      "Yangjiang"
    ],
    "name:pam_x_preferred": [
      "Yangjiang"
    ],
    "name:pnb_x_preferred": [
      "یانگ جیانگ"
    ],
    "name:pol_x_preferred": [
      "Yangjiang"
    ],
    "name:por_x_preferred": [
      "Yangjiang"
    ],
    "name:rus_x_preferred": [
      "Янцзян"
    ],
    "name:spa_x_preferred": [
      "Yangjiang"
    ],
    "name:srp_x_preferred": [
      "Јангђанг"
    ],
    "name:swa_x_preferred": [
      "Yangjiang"
    ],
    "name:swe_x_preferred": [
      "Yangjiang"
    ],
    "name:tur_x_preferred": [
      "Yangjiang"
    ],
    "name:und_x_variant": [
      "Yang-chiang",
      "洋江",
      "Yangjiang Xiang",
      "洋江乡"
    ],
    "name:urd_x_preferred": [
      "ینگجیانگ"
    ],
    "name:vie_x_preferred": [
      "Dương Giang"
    ],
    "name:war_x_preferred": [
      "Yangjiang"
    ],
    "name:zho_x_preferred": [
      "阳江市"
    ],
    "wof:name": "Yangjiang",
    "wof:placetype": "locality"
  },
  "geometry": {
    "coordinates": [
      114.53405,
      27.85658
    ],
    "type": "Point"
  }
}