{
  "type": "Feature",
  "properties": {
    "gn:admin1_code": "1.0",
    "gn:asciiname": "Bei'an",
    "gn:country_code": "CN",
    "gn:dem": 151,
    "gn:feature_class": "P",
    "gn:feature_code": "PPLA4",
    "gn:name": "Bei’an",
    "gn:population": 0,
    "gn:timezone": "Asia/Shanghai",
    "iso:country": "CN",
    "name:ara_x_preferred": [
      "بيؤان"
    ],
    "name:deu_x_preferred": [
      "Bei’an"
    ],
    "name:fra_x_preferred": [
      "Bei'an"
    ],
    "name:ita_x_preferred": [
      "Bei'an"
    ],
    "name:jpn_x_preferred": [
      "北安市"
    ],
    "name:kik_x_preferred": [
      "Bei'an"
    ],
    "name:kor_x_preferred": [
      "베이안시"
    ],
    "name:mlg_x_preferred": [
      "Bei'an"
    ],
    "name:nor_x_preferred": [
      "Bei'an"
    ],
    "name:pam_x_preferred": [
      "Bei'an"
    ],
    "name:rus_x_preferred": [
      "Бэйань"
    ],
    "name:swe_x_preferred": [
      "Bei'an"
    ],
    "name:urd_x_preferred": [
      "بیئآن"
    ],
    "name:vie_x_preferred": [
      "Bắc An"
    ],
    "name:war_x_preferred": [
      "Beian"
    ],
    "name:zho_x_preferred": [
      "北岸"
    ],
    "name:zho_x_variant": [
      "Bei’anzhen",
      "北岸镇",
      "Bei’an",
      "北安市"
    ],
    "wof:name": "Bei'an",
    "wof:placetype": "locality"
  },
  "geometry": {
    "coordinates": [
      118.57532,
      29.90989
    ],
    "type": "Point"
  }
}