{
  "type": "Feature",
  "properties": {
    "gn:admin1_code": "10",
    "gn:asciiname": "Xingrenbu",
    "gn:country_code": "CN",
    "gn:dem": 866,
    "gn:feature_class": "P",
    "gn:feature_code": "PPL",
    "gn:name": "Xingrenbu",
    "gn:population": 0,
    "gn:timezone": "Asia/Shanghai",
    "iso:country": "CN",
    "name:und_x_variant": [
      "Hsing-jen-pu",
      "Xingrenbu"
    ],
    "name:zho_x_preferred": [
      "兴仁堡"
    ],
    "wof:name": "Xingrenbu",
    "wof:placetype": "locality"
  },
  "geometry": {
    "coordinates": [
      115.84359,
      40.87776
    ],
    "type": "Point"
  }
}