{
  "type": "Feature",
  "properties": {
    "gn:admin1_code": "19.0",
    "gn:asciiname": "Shajiantun",
    "gn:country_code": "CN",
    "gn:dem": 3,
    "gn:feature_class": "P",
    "gn:feature_code": "PPL",
    "gn:name": "Shajiantun",
    "gn:population": 0,
    "gn:timezone": "Asia/Shanghai",
    "iso:country": "CN",
    "name:zho_x_preferred": [
      "沙尖屯"
    ],
    "wof:name": "Shajiantun",
    "wof:placetype": "locality"
  },
  "geometry": {
    "coordinates": [
      122.756,
      39.6097
    ],
    "type": "Point"
  }
}