{
  "type": "Feature",
  "properties": {
    "gn:admin1_code": "26.0",
    "gn:asciiname": "Honglin",
    "gn:country_code": "CN",
    "gn:dem": 370,
    "gn:feature_class": "P",
    "gn:feature_code": "PPL",
    "gn:name": "Honglin",
    "gn:population": 0,
    "gn:timezone": "Asia/Shanghai",
    "iso:country": "CN",
    "name:zho_x_preferred": [
      "红林"
    ],
    "wof:name": "Honglin",
    "wof:placetype": "locality"
  },
  "geometry": {
    "coordinates": [
      109.54136,
      34.77207
    ],
    "type": "Point"
  }
}