{
  "type": "Feature",
  "properties": {
    "gn:admin1_code": "10",
    "gn:asciiname": "Laoxiying",
    "gn:country_code": "CN",
    "gn:dem": 1127,
    "gn:feature_class": "P",
    "gn:feature_code": "PPL",
    "gn:name": "Laoxiying",
    "gn:population": 0,
    "gn:timezone": "Asia/Shanghai",
    "iso:country": "CN",
    "name:zho_x_preferred": [
      "老西营"
    ],
    "wof:name": "Laoxiying",
    "wof:placetype": "locality"
  },
  "geometry": {
    "coordinates": [
      116.8557,
      41.54915
    ],
    "type": "Point"
  }
}