{
  "type": "Feature",
  "properties": {
    "gn:admin1_code": "10.0",
    "gn:asciiname": "Shangfa",
    "gn:country_code": "CN",
    "gn:dem": 26,
    "gn:feature_class": "P",
    "gn:feature_code": "PPL",
    "gn:name": "Shangfa",
    "gn:population": 0,
    "gn:timezone": "Asia/Shanghai",
    "iso:country": "CN",
    "name:zho_x_preferred": [
      "尚垡"
    ],
    "wof:name": "Shangfa",
    "wof:placetype": "locality"
  },
  "geometry": {
    "coordinates": [
      116.07161,
      39.30623
    ],
    "type": "Point"
  }
}