{
  "type": "Feature",
  "properties": {
    "gn:admin1_code": "18.0",
    "gn:asciiname": "Gaomianlao",
    "gn:country_code": "CN",
    "gn:dem": 980,
    "gn:feature_class": "P",
    "gn:feature_code": "PPL",
    "gn:name": "Gaomianlao",
    "gn:population": 0,
    "gn:timezone": "Asia/Shanghai",
    "iso:country": "CN",
    "name:zho_x_preferred": [
      "高面老"
    ],
    "wof:name": "Gaomianlao",
    "wof:placetype": "locality"
  },
  "geometry": {
    "coordinates": [
      108.85,
      26.4055
    ],
    "type": "Point"
  }
}