{
  "type": "Feature",
  "properties": {
    "gn:admin1_code": "29.0",
    "gn:asciiname": "Guanposi",
    "gn:country_code": "CN",
    "gn:dem": 1877,
    "gn:feature_class": "P",
    "gn:feature_code": "PPL",
    "gn:name": "Guanposi",
    "gn:population": 0,
    "gn:timezone": "Asia/Shanghai",
    "iso:country": "CN",
    "name:zho_x_preferred": [
      "官坡寺"
    ],
    "wof:name": "Guanposi",
    "wof:placetype": "locality"
  },
  "geometry": {
    "coordinates": [
      103.805,
      25.5044
    ],
    "type": "Point"
  }
}