{
  "type": "Feature",
  "properties": {
    "gn:admin1_code": "29.0",
    "gn:asciiname": "Shijiawan",
    "gn:country_code": "CN",
    "gn:dem": 792,
    "gn:feature_class": "P",
    "gn:feature_code": "PPL",
    "gn:name": "Shijiawan",
    "gn:population": 0,
    "gn:timezone": "Asia/Shanghai",
    "iso:country": "CN",
    "name:zho_x_preferred": [
      "石家湾"
    ],
    "wof:name": "Shijiawan",
    "wof:placetype": "locality"
  },
  "geometry": {
    "coordinates": [
      104.073,
      28.1834
    ],
    "type": "Point"
  }
}