{
  "type": "Feature",
  "properties": {
    "gn:admin1_code": "7.0",
    "gn:asciiname": "Shanwei",
    "gn:country_code": "CN",
    "gn:dem": 24,
    "gn:feature_class": "P",
    "gn:feature_code": "PPL",
    "gn:name": "Shanwei",
    "gn:population": 0,
    "gn:timezone": "Asia/Shanghai",
    "iso:country": "CN",
    "name:ara_x_preferred": [
      "شانوي"
    ],
    "name:cdo_x_preferred": [
      "Sáng-muōi"
    ],
    "name:ces_x_preferred": [
      "Šan-wej"
    ],
    "name:cym_x_preferred": [
      "Shanwei"
    ],
    "name:dan_x_preferred": [
      "Shanwei"
    ],
    "name:deu_x_preferred": [
      "Shanwei"
    ],
    "name:eus_x_preferred": [
      "Shanwei"
    ],
    "name:fas_x_preferred": [
      "شانوی"
    ],
    "name:fin_x_preferred": [
      "Shanwei"
    ],
    "name:fra_x_preferred": [
      "Shanwei"
    ],
    "name:hak_x_preferred": [
      "Sân-mî-sṳ"
    ],
    "name:ind_x_preferred": [
      "Shanwei"
    ],
    "name:ita_x_preferred": [
      "Shanwei"
    ],
    "name:jpn_x_preferred": [
      "汕尾市"
    ],
    "name:kik_x_preferred": [
      "Shanwei"
    ],
    "name:kor_x_preferred": [
      "산웨이시"
    ],
    "name:mlg_x_preferred": [
      "Shanwei"
    ],
    "name:nld_x_preferred": [
      "Shanwei"
    ],
    "name:nno_x_preferred": [
      "Shanwei"
    ],
    "name:nor_x_preferred": [
      "Shanwei"
    ],
    "name:pam_x_preferred": [
      "Shanwei"
    ],
    "name:pnb_x_preferred": [
      "شانویئی"
    ],
    "name:pol_x_preferred": [
      "Shanwei"
    ],
    "name:por_x_preferred": [
      "Shanwei"
    ],
    "name:rus_x_preferred": [
      "Шаньвэй"
    ],
    "name:spa_x_preferred": [
      "Shanwéi"
    ],
    "name:swa_x_preferred": [
      "Shanwei"
    ],
    "name:swe_x_preferred": [
      "Shanwei"
    ],
    "name:tur_x_preferred": [
      "Shanwei"
    ],
    "name:urd_x_preferred": [
      "شانوئی"
    ],
    "name:vie_x_preferred": [
      "Sán Vĩ"
    ],
    "name:war_x_preferred": [
      "Shanwei"
    ],
    "name:zho_x_preferred": [
      "汕尾"
    ],
    "name:zho_x_variant": [
      "汕尾市"
    ],
    "wof:name": "Shanwei",
    "wof:placetype": "locality"
  },
  "geometry": {
    "coordinates": [
      119.11312,
      25.07243
    ],
    "type": "Point"
  }
}