{
  "type": "Feature",
  "properties": {
    "gn:admin1_code": "29.0",
    "gn:asciiname": "Xiaxishan",
    "gn:country_code": "CN",
    "gn:dem": 1932,
    "gn:feature_class": "P",
    "gn:feature_code": "PPL",
    "gn:name": "Xiaxishan",
    "gn:population": 0,
    "gn:timezone": "Asia/Shanghai",
    "iso:country": "CN",
    "name:zho_x_preferred": [
      "下西山"
    ],
    "wof:name": "Xiaxishan",
    "wof:placetype": "locality"
  },
  "geometry": {
    "coordinates": [
      103.711,
      25.514
    ],
    "type": "Point"
  }
}