{
  "type": "Feature",
  "properties": {
    "gn:admin1_code": "11",
    "gn:asciiname": "Shenzhangtang",
    "gn:country_code": "CN",
    "gn:dem": 198,
    "gn:feature_class": "P",
    "gn:feature_code": "PPLA4",
    "gn:name": "Shenzhangtang",
    "gn:population": 0,
    "gn:timezone": "Asia/Shanghai",
    "iso:country": "CN",
    "name:und_x_variant": [
      "Shenzhangtang Yaozuxiang",
      "审章塘瑶族乡",
      "Shenzhangtang"
    ],
    "name:zho_x_preferred": [
      "审章塘"
    ],
    "wof:name": "Shenzhangtang",
    "wof:placetype": "locality"
  },
  "geometry": {
    "coordinates": [
      111.59972,
      25.35528
    ],
    "type": "Point"
  }
}