{
  "type": "Feature",
  "properties": {
    "gn:admin1_code": "30.0",
    "gn:asciiname": "Feng'ercun",
    "gn:country_code": "CN",
    "gn:dem": 187,
    "gn:feature_class": "P",
    "gn:feature_code": "PPL",
    "gn:name": "Feng’ercun",
    "gn:population": 0,
    "gn:timezone": "Asia/Shanghai",
    "iso:country": "CN",
    "name:und_x_variant": [
      "Feng’ercun"
    ],
    "name:zho_x_preferred": [
      "凤二村"
    ],
    "wof:name": "Feng'ercun",
    "wof:placetype": "locality"
  },
  "geometry": {
    "coordinates": [
      115.84651,
      24.58275
    ],
    "type": "Point"
  }
}