{
  "type": "Feature",
  "properties": {
    "gn:admin1_code": "14.0",
    "gn:asciiname": "Xainbatang",
    "gn:country_code": "CN",
    "gn:dem": 4701,
    "gn:feature_class": "P",
    "gn:feature_code": "PPLF",
    "gn:name": "Xainbatang",
    "gn:population": 0,
    "gn:timezone": "Asia/Urumqi",
    "iso:country": "CN",
    "name:bod_x_preferred": [
      "Xainbatang"
    ],
    "name:zho_x_preferred": [
      "Xianbatang"
    ],
    "name:zho_x_variant": [
      "先巴塘"
    ],
    "wof:name": "Xainbatang",
    "wof:placetype": "locality"
  },
  "geometry": {
    "coordinates": [
      92.801,
      29.901
    ],
    "type": "Point"
  }
}