{
  "type": "Feature",
  "properties": {
    "gn:admin1_code": "7.0",
    "gn:asciiname": "Jinli",
    "gn:country_code": "CN",
    "gn:dem": 13,
    "gn:feature_class": "P",
    "gn:feature_code": "PPL",
    "gn:name": "Jinli",
    "gn:population": 0,
    "gn:timezone": "Asia/Shanghai",
    "iso:country": "CN",
    "name:ita_x_preferred": [
      "Jin Li"
    ],
    "name:zho_x_preferred": [
      "金里"
    ],
    "name:zho_x_variant": [
      "锦里古街"
    ],
    "wof:name": "Jinli",
    "wof:placetype": "locality"
  },
  "geometry": {
    "coordinates": [
      117.73566,
      24.61237
    ],
    "type": "Point"
  }
}