{
  "type": "Feature",
  "properties": {
    "gn:admin1_code": "5.0",
    "gn:asciiname": "Bei'ancun",
    "gn:country_code": "CN",
    "gn:dem": 299,
    "gn:feature_class": "P",
    "gn:feature_code": "PPL",
    "gn:name": "Bei’ancun",
    "gn:population": 0,
    "gn:timezone": "Asia/Shanghai",
    "iso:country": "CN",
    "name:und_x_variant": [
      "Bei’ancun"
    ],
    "name:zho_x_preferred": [
      "北安村"
    ],
    "wof:name": "Bei'ancun",
    "wof:placetype": "locality"
  },
  "geometry": {
    "coordinates": [
      125.06458,
      42.83531
    ],
    "type": "Point"
  }
}