{
  "type": "Feature",
  "properties": {
    "gn:admin1_code": "7",
    "gn:asciiname": "Dujiayang",
    "gn:country_code": "CN",
    "gn:dem": 530,
    "gn:feature_class": "P",
    "gn:feature_code": "PPL",
    "gn:name": "Dujiayang",
    "gn:population": 0,
    "gn:timezone": "Asia/Shanghai",
    "iso:country": "CN",
    "name:und_x_variant": [
      "杜家洋",
      "Dujiayang"
    ],
    "wof:name": "Dujiayang",
    "wof:placetype": "locality"
  },
  "geometry": {
    "coordinates": [
      119.51231,
      27.00168
    ],
    "type": "Point"
  }
}