{
  "type": "Feature",
  "properties": {
    "gn:admin1_code": "4.0",
    "gn:asciiname": "Shachi",
    "gn:country_code": "CN",
    "gn:dem": 9,
    "gn:feature_class": "P",
    "gn:feature_code": "PPL",
    "gn:name": "Shachi",
    "gn:population": 0,
    "gn:timezone": "Asia/Shanghai",
    "iso:country": "CN",
    "name:ben_x_preferred": [
      "শচী"
    ],
    "name:ces_x_preferred": [
      "Šačí"
    ],
    "name:hin_x_preferred": [
      "शची"
    ],
    "name:hrv_x_preferred": [
      "Shachi"
    ],
    "name:ind_x_preferred": [
      "Saci"
    ],
    "name:jpn_x_preferred": [
      "シャチー"
    ],
    "name:kan_x_preferred": [
      "ಇಂದ್ರಾಣಿ"
    ],
    "name:mar_x_preferred": [
      "इंद्राणी"
    ],
    "name:nep_x_preferred": [
      "शची"
    ],
    "name:nld_x_preferred": [
      "Sachi"
    ],
    "name:pan_x_preferred": [
      "ਸ਼ਚੀ"
    ],
    "name:rus_x_preferred": [
      "Шачи"
    ],
    "name:san_x_preferred": [
      "शची"
    ],
    "name:sin_x_preferred": [
      "ශචී"
    ],
    "name:swe_x_preferred": [
      "Indrani"
    ],
    "name:tam_x_preferred": [
      "இந்திராணி"
    ],
    "name:zho_x_preferred": [
      "沙池"
    ],
    "wof:name": "Shachi",
    "wof:placetype": "locality"
  },
  "geometry": {
    "coordinates": [
      119.22425,
      32.17182
    ],
    "type": "Point"
  }
}