{
  "type": "Feature",
  "properties": {
    "gn:admin1_code": "4.0",
    "gn:asciiname": "Jiamiaocun",
    "gn:country_code": "CN",
    "gn:dem": 4,
    "gn:feature_class": "P",
    "gn:feature_code": "PPL",
    "gn:name": "Jiamiaocun",
    "gn:population": 0,
    "gn:timezone": "Asia/Shanghai",
    "iso:country": "CN",
    "name:und_x_variant": [
      "Jiamiao",
      "Jiamiaocun"
    ],
    "name:zho_x_preferred": [
      "贾庙"
    ],
    "name:zho_x_variant": [
      "贾庙村"
    ],
    "wof:name": "Jiamiaocun",
    "wof:placetype": "locality"
  },
  "geometry": {
    "coordinates": [
      118.88892,
      34.43487
    ],
    "type": "Point"
  }
}