{
  "type": "Feature",
  "properties": {
    "gn:admin1_code": "1.0",
    "gn:asciiname": "Gaohu",
    "gn:country_code": "CN",
    "gn:dem": 36,
    "gn:feature_class": "P",
    "gn:feature_code": "PPL",
    "gn:name": "Gaohu",
    "gn:population": 0,
    "gn:timezone": "Asia/Shanghai",
    "iso:country": "CN",
    "name:ara_x_preferred": [
      "قاو هو"
    ],
    "name:epo_x_preferred": [
      "Gaŭhuo"
    ],
    "name:fra_x_preferred": [
      "Gaohu"
    ],
    "name:hun_x_preferred": [
      "Kao-hu"
    ],
    "name:hye_x_preferred": [
      "Գաոհու"
    ],
    "name:ind_x_preferred": [
      "Gaohu"
    ],
    "name:und_x_variant": [
      "高湖"
    ],
    "wof:name": "Gaohu",
    "wof:placetype": "locality"
  },
  "geometry": {
    "coordinates": [
      119.41651,
      30.95567
    ],
    "type": "Point"
  }
}