{
  "type": "Feature",
  "properties": {
    "gn:admin1_code": "30.0",
    "gn:asciiname": "Chi'an",
    "gn:country_code": "CN",
    "gn:dem": 121,
    "gn:feature_class": "P",
    "gn:feature_code": "PPL",
    "gn:name": "Chi’an",
    "gn:population": 0,
    "gn:timezone": "Asia/Shanghai",
    "iso:country": "CN",
    "name:und_x_variant": [
      "Chi’an"
    ],
    "name:zho_x_preferred": [
      "赤岸"
    ],
    "wof:name": "Chi'an",
    "wof:placetype": "locality"
  },
  "geometry": {
    "coordinates": [
      113.62843,
      24.88751
    ],
    "type": "Point"
  }
}