{
  "type": "Feature",
  "properties": {
    "gn:admin1_code": "4.0",
    "gn:asciiname": "Zhongzhai Yicun",
    "gn:country_code": "CN",
    "gn:dem": 5,
    "gn:feature_class": "P",
    "gn:feature_code": "PPL",
    "gn:name": "Zhongzhai Yicun",
    "gn:population": 0,
    "gn:timezone": "Asia/Shanghai",
    "iso:country": "CN",
    "name:zho_x_preferred": [
      "仲寨一村"
    ],
    "wof:name": "Zhongzhai Yicun",
    "wof:placetype": "locality"
  },
  "geometry": {
    "coordinates": [
      119.68519,
      33.11236
    ],
    "type": "Point"
  }
}