{
  "type": "Feature",
  "properties": {
    "gn:admin1_code": "1.0",
    "gn:asciiname": "Dafei",
    "gn:country_code": "CN",
    "gn:dem": 380,
    "gn:feature_class": "P",
    "gn:feature_code": "PPL",
    "gn:name": "Dafei",
    "gn:population": 0,
    "gn:timezone": "Asia/Shanghai",
    "iso:country": "CN",
    "name:zho_x_preferred": [
      "大斐"
    ],
    "wof:name": "Dafei",
    "wof:placetype": "locality"
  },
  "geometry": {
    "coordinates": [
      118.08366,
      29.84871
    ],
    "type": "Point"
  }
}