{
  "type": "Feature",
  "properties": {
    "gn:admin1_code": "1.0",
    "gn:asciiname": "Sencun",
    "gn:country_code": "CN",
    "gn:dem": 147,
    "gn:feature_class": "P",
    "gn:feature_code": "PPLA4",
    "gn:name": "Sencun",
    "gn:population": 0,
    "gn:timezone": "Asia/Shanghai",
    "iso:country": "CN",
    "name:und_x_variant": [
      "Sencun Xiang"
    ],
    "name:zho_x_preferred": [
      "森村"
    ],
    "name:zho_x_variant": [
      "森村乡"
    ],
    "wof:name": "Sencun",
    "wof:placetype": "locality"
  },
  "geometry": {
    "coordinates": [
      118.47861,
      29.75818
    ],
    "type": "Point"
  }
}