{
  "type": "Feature",
  "properties": {
    "gn:admin1_code": "12.0",
    "gn:asciiname": "Shangchen",
    "gn:country_code": "CN",
    "gn:dem": 55,
    "gn:feature_class": "P",
    "gn:feature_code": "PPL",
    "gn:name": "Shangchen",
    "gn:population": 0,
    "gn:timezone": "Asia/Shanghai",
    "iso:country": "CN",
    "name:ara_x_preferred": [
      "شانغشن"
    ],
    "name:fas_x_preferred": [
      "شانگچن"
    ],
    "name:ind_x_preferred": [
      "Shangchen"
    ],
    "name:spa_x_preferred": [
      "Shangchen"
    ],
    "name:vie_x_preferred": [
      "Thượng Trần"
    ],
    "name:zho_x_preferred": [
      "Shangchen"
    ],
    "name:zho_x_variant": [
      "上陈",
      "上陈遗址"
    ],
    "wof:name": "Shangchen",
    "wof:placetype": "locality"
  },
  "geometry": {
    "coordinates": [
      115.30744,
      29.67887
    ],
    "type": "Point"
  }
}