{
  "type": "Feature",
  "properties": {
    "gn:admin1_code": "10",
    "gn:asciiname": "Daxinzhuang",
    "gn:country_code": "CN",
    "gn:dem": 14,
    "gn:feature_class": "P",
    "gn:feature_code": "PPL",
    "gn:name": "Daxinzhuang",
    "gn:population": 0,
    "gn:timezone": "Asia/Shanghai",
    "iso:country": "CN",
    "name:zho_x_preferred": [
      "大辛庄"
    ],
    "wof:name": "Daxinzhuang",
    "wof:placetype": "locality"
  },
  "geometry": {
    "coordinates": [
      115.741,
      38.9568
    ],
    "type": "Point"
  }
}