{
  "type": "Feature",
  "properties": {
    "gn:admin1_code": "29.0",
    "gn:asciiname": "Wubadong",
    "gn:country_code": "CN",
    "gn:dem": 2778,
    "gn:feature_class": "P",
    "gn:feature_code": "PPL",
    "gn:name": "Wubadong",
    "gn:population": 0,
    "gn:timezone": "Asia/Shanghai",
    "iso:country": "CN",
    "name:zho_x_preferred": [
      "乌巴东"
    ],
    "wof:name": "Wubadong",
    "wof:placetype": "locality"
  },
  "geometry": {
    "coordinates": [
      98.8848,
      27.9994
    ],
    "type": "Point"
  }
}