{
  "type": "Feature",
  "properties": {
    "gn:admin1_code": "10.0",
    "gn:asciiname": "Cheye Xinzhuang",
    "gn:country_code": "CN",
    "gn:dem": 1080,
    "gn:feature_class": "P",
    "gn:feature_code": "PPL",
    "gn:name": "Cheye Xinzhuang",
    "gn:population": 0,
    "gn:timezone": "Asia/Shanghai",
    "iso:country": "CN",
    "name:zho_x_preferred": [
      "扯业辛庄"
    ],
    "wof:name": "Cheye Xinzhuang",
    "wof:placetype": "locality"
  },
  "geometry": {
    "coordinates": [
      115.00692,
      40.02107
    ],
    "type": "Point"
  }
}