{
  "type": "Feature",
  "properties": {
    "gn:admin1_code": "13",
    "gn:asciiname": "Shuigongchu Erlian",
    "gn:country_code": "CN",
    "gn:dem": 503,
    "gn:feature_class": "P",
    "gn:feature_code": "PPL",
    "gn:name": "Shuigongchu Erlian",
    "gn:population": 0,
    "gn:timezone": "Asia/Urumqi",
    "iso:country": "CN",
    "name:zho_x_preferred": [
      "水工处二连"
    ],
    "wof:name": "Shuigongchu Erlian",
    "wof:placetype": "locality"
  },
  "geometry": {
    "coordinates": [
      87.50361,
      44.07008
    ],
    "type": "Point"
  }
}