{
  "type": "Feature",
  "properties": {
    "gn:admin1_code": "8.0",
    "gn:asciiname": "Hepingcun",
    "gn:country_code": "CN",
    "gn:dem": 146,
    "gn:feature_class": "P",
    "gn:feature_code": "PPL",
    "gn:name": "Hepingcun",
    "gn:population": 0,
    "gn:timezone": "Asia/Shanghai",
    "iso:country": "CN",
    "name:zho_x_preferred": [
      "和平村"
    ],
    "wof:name": "Hepingcun",
    "wof:placetype": "locality"
  },
  "geometry": {
    "coordinates": [
      126.06551,
      45.21524
    ],
    "type": "Point"
  }
}