{
  "type": "Feature",
  "properties": {
    "gn:admin1_code": "18.0",
    "gn:asciiname": "Gaocen",
    "gn:country_code": "CN",
    "gn:dem": 833,
    "gn:feature_class": "P",
    "gn:feature_code": "PPL",
    "gn:name": "Gaocen",
    "gn:population": 0,
    "gn:timezone": "Asia/Shanghai",
    "iso:country": "CN",
    "name:zho_x_preferred": [
      "高岑"
    ],
    "wof:name": "Gaocen",
    "wof:placetype": "locality"
  },
  "geometry": {
    "coordinates": [
      108.976,
      26.7018
    ],
    "type": "Point"
  }
}