{
  "type": "Feature",
  "properties": {
    "gn:admin1_code": "16.0",
    "gn:asciiname": "Tangshang",
    "gn:country_code": "CN",
    "gn:dem": 195,
    "gn:feature_class": "P",
    "gn:feature_code": "PPL",
    "gn:name": "Tangshang",
    "gn:population": 0,
    "gn:timezone": "Asia/Shanghai",
    "iso:country": "CN",
    "name:zho_x_preferred": [
      "塘上"
    ],
    "wof:name": "Tangshang",
    "wof:placetype": "locality"
  },
  "geometry": {
    "coordinates": [
      108.408,
      24.171
    ],
    "type": "Point"
  }
}