{
  "type": "Feature",
  "properties": {
    "gn:admin1_code": "25",
    "gn:asciiname": "Shiliquancun",
    "gn:country_code": "CN",
    "gn:dem": 60,
    "gn:feature_class": "P",
    "gn:feature_code": "PPL",
    "gn:name": "Shiliquancun",
    "gn:population": 0,
    "gn:timezone": "Asia/Shanghai",
    "iso:country": "CN",
    "name:und_x_variant": [
      "Shiliquan",
      "Shiliquancun"
    ],
    "name:zho_x_preferred": [
      "十里泉"
    ],
    "name:zho_x_variant": [
      "十里泉村"
    ],
    "wof:name": "Shiliquancun",
    "wof:placetype": "locality"
  },
  "geometry": {
    "coordinates": [
      117.5512,
      34.81002
    ],
    "type": "Point"
  }
}