{
  "type": "Feature",
  "properties": {
    "gn:admin1_code": "16.0",
    "gn:asciiname": "Menlou",
    "gn:country_code": "CN",
    "gn:dem": 206,
    "gn:feature_class": "P",
    "gn:feature_code": "PPL",
    "gn:name": "Menlou",
    "gn:population": 0,
    "gn:timezone": "Asia/Shanghai",
    "iso:country": "CN",
    "name:zho_x_preferred": [
      "门楼"
    ],
    "wof:name": "Menlou",
    "wof:placetype": "locality"
  },
  "geometry": {
    "coordinates": [
      110.954,
      24.4488
    ],
    "type": "Point"
  }
}