{
  "type": "Feature",
  "properties": {
    "gn:admin1_code": "02",
    "gn:asciiname": "Niutaicun",
    "gn:country_code": "CN",
    "gn:dem": 14,
    "gn:feature_class": "P",
    "gn:feature_code": "PPL",
    "gn:name": "Niutaicun",
    "gn:population": 0,
    "gn:timezone": "Asia/Shanghai",
    "iso:country": "CN",
    "name:und_x_variant": [
      "Niu-t’ui-ts’un",
      "Niutai",
      "Niutaicun"
    ],
    "name:zho_x_preferred": [
      "牛台"
    ],
    "name:zho_x_variant": [
      "牛台村"
    ],
    "wof:name": "Niutaicun",
    "wof:placetype": "locality"
  },
  "geometry": {
    "coordinates": [
      121.48108,
      29.16913
    ],
    "type": "Point"
  }
}