{
  "type": "Feature",
  "properties": {
    "gn:admin1_code": "25",
    "gn:asciiname": "Qianjiangzhuang",
    "gn:country_code": "CN",
    "gn:dem": 18,
    "gn:feature_class": "P",
    "gn:feature_code": "PPL",
    "gn:name": "Qianjiangzhuang",
    "gn:population": 0,
    "gn:timezone": "Asia/Shanghai",
    "iso:country": "CN",
    "name:zho_x_preferred": [
      "前姜庄"
    ],
    "wof:name": "Qianjiangzhuang",
    "wof:placetype": "locality"
  },
  "geometry": {
    "coordinates": [
      116.737,
      37.5997
    ],
    "type": "Point"
  }
}