{
  "type": "Feature",
  "properties": {
    "gn:admin1_code": "26.0",
    "gn:asciiname": "Hejiawan",
    "gn:country_code": "CN",
    "gn:dem": 654,
    "gn:feature_class": "P",
    "gn:feature_code": "PPL",
    "gn:name": "Hejiawan",
    "gn:population": 0,
    "gn:timezone": "Asia/Shanghai",
    "iso:country": "CN",
    "name:zho_x_preferred": [
      "贺家湾"
    ],
    "wof:name": "Hejiawan",
    "wof:placetype": "locality"
  },
  "geometry": {
    "coordinates": [
      108.15605,
      33.34856
    ],
    "type": "Point"
  }
}