{
  "type": "Feature",
  "properties": {
    "gn:admin1_code": "12",
    "gn:asciiname": "Xia'eping",
    "gn:country_code": "CN",
    "gn:dem": 729,
    "gn:feature_class": "P",
    "gn:feature_code": "PPL",
    "gn:name": "Xia’eping",
    "gn:population": 0,
    "gn:timezone": "Asia/Shanghai",
    "iso:country": "CN",
    "wof:name": "Xia'eping",
    "wof:placetype": "locality"
  },
  "geometry": {
    "coordinates": [
      109.66389,
      32.19167
    ],
    "type": "Point"
  }
}