{
  "type": "Feature",
  "properties": {
    "gn:admin1_code": "16.0",
    "gn:asciiname": "Xiahe",
    "gn:country_code": "CN",
    "gn:dem": 336,
    "gn:feature_class": "P",
    "gn:feature_code": "PPL",
    "gn:name": "Xiahe",
    "gn:population": 0,
    "gn:timezone": "Asia/Shanghai",
    "iso:country": "CN",
    "name:zho_x_preferred": [
      "下河"
    ],
    "wof:name": "Xiahe",
    "wof:placetype": "locality"
  },
  "geometry": {
    "coordinates": [
      107.919,
      24.6337
    ],
    "type": "Point"
  }
}