{
  "type": "Feature",
  "properties": {
    "gn:admin1_code": "33.0",
    "gn:asciiname": "Gulong",
    "gn:country_code": "CN",
    "gn:dem": 401,
    "gn:feature_class": "P",
    "gn:feature_code": "PPLA4",
    "gn:name": "Gulong",
    "gn:population": 0,
    "gn:timezone": "Asia/Shanghai",
    "iso:country": "CN",
    "name:und_x_variant": [
      "Gulong Xiang",
      "Longjia Shuijing Wuji"
    ],
    "name:zho_x_preferred": [
      "古龙"
    ],
    "name:zho_x_variant": [
      "古龙乡",
      "龙家水井屋基"
    ],
    "wof:name": "Gulong",
    "wof:placetype": "locality"
  },
  "geometry": {
    "coordinates": [
      106.00383,
      29.70472
    ],
    "type": "Point"
  }
}