{
  "type": "Feature",
  "properties": {
    "gn:admin1_code": "10",
    "gn:asciiname": "Shangwopu",
    "gn:country_code": "CN",
    "gn:dem": 547,
    "gn:feature_class": "P",
    "gn:feature_code": "PPL",
    "gn:name": "Shangwopu",
    "gn:population": 0,
    "gn:timezone": "Asia/Shanghai",
    "iso:country": "CN",
    "name:zho_x_preferred": [
      "上窝铺"
    ],
    "wof:name": "Shangwopu",
    "wof:placetype": "locality"
  },
  "geometry": {
    "coordinates": [
      117.92352,
      41.17319000000001
    ],
    "type": "Point"
  }
}