{
  "type": "Feature",
  "properties": {
    "gn:admin1_code": "26",
    "gn:asciiname": "Jiezihecun",
    "gn:country_code": "CN",
    "gn:dem": 1018,
    "gn:feature_class": "P",
    "gn:feature_code": "PPL",
    "gn:name": "Jiezihecun",
    "gn:population": 0,
    "gn:timezone": "Asia/Shanghai",
    "iso:country": "CN",
    "name:und_x_variant": [
      "Chieh-tzu-ho",
      "Jiezihe",
      "Jiezihecun"
    ],
    "name:zho_x_preferred": [
      "界子河村"
    ],
    "wof:name": "Jiezihecun",
    "wof:placetype": "locality"
  },
  "geometry": {
    "coordinates": [
      109.40455,
      35.86793
    ],
    "type": "Point"
  }
}