{
  "type": "Feature",
  "properties": {
    "gn:admin1_code": "7.0",
    "gn:asciiname": "Bapu",
    "gn:country_code": "CN",
    "gn:dem": 560,
    "gn:feature_class": "P",
    "gn:feature_code": "PPL",
    "gn:name": "Bapu",
    "gn:population": 0,
    "gn:timezone": "Asia/Shanghai",
    "iso:country": "CN",
    "name:deu_x_preferred": [
      "Bapu"
    ],
    "name:fra_x_preferred": [
      "Bapu"
    ],
    "name:hin_x_preferred": [
      "बापू"
    ],
    "name:pol_x_preferred": [
      "Bapu"
    ],
    "name:zho_x_preferred": [
      "八蒲"
    ],
    "wof:name": "Bapu",
    "wof:placetype": "locality"
  },
  "geometry": {
    "coordinates": [
      119.37045,
      27.04955
    ],
    "type": "Point"
  }
}