{
  "type": "Feature",
  "properties": {
    "gn:admin1_code": "10",
    "gn:asciiname": "Jiangwucheng",
    "gn:country_code": "CN",
    "gn:dem": 88,
    "gn:feature_class": "P",
    "gn:feature_code": "PPL",
    "gn:name": "Jiangwucheng",
    "gn:population": 0,
    "gn:timezone": "Asia/Shanghai",
    "iso:country": "CN",
    "wof:name": "Jiangwucheng",
    "wof:placetype": "locality"
  },
  "geometry": {
    "coordinates": [
      114.33333,
      36.28333
    ],
    "type": "Point"
  }
}