{
  "type": "Feature",
  "properties": {
    "gn:admin1_code": "9",
    "gn:asciiname": "Huanglu",
    "gn:country_code": "CN",
    "gn:dem": 50,
    "gn:feature_class": "P",
    "gn:feature_code": "PPL",
    "gn:name": "Huanglü",
    "gn:population": 0,
    "gn:timezone": "Asia/Shanghai",
    "iso:country": "CN",
    "name:und_x_variant": [
      "Huanglü"
    ],
    "name:zho_x_preferred": [
      "黄吕"
    ],
    "wof:name": "Huanglu",
    "wof:placetype": "locality"
  },
  "geometry": {
    "coordinates": [
      115.66687,
      35.84878
    ],
    "type": "Point"
  }
}