{
  "type": "Feature",
  "properties": {
    "gn:admin1_code": "10",
    "gn:asciiname": "Nei-wu-fu-ch'uan",
    "gn:country_code": "CN",
    "gn:dem": 118,
    "gn:feature_class": "P",
    "gn:feature_code": "PPL",
    "gn:name": "Nei-wu-fu-ch’uan",
    "gn:population": 0,
    "gn:timezone": "Asia/Shanghai",
    "iso:country": "CN",
    "wof:name": "Nei-wu-fu-ch'uan",
    "wof:placetype": "locality"
  },
  "geometry": {
    "coordinates": [
      117.64028,
      40.17833
    ],
    "type": "Point"
  }
}