{
  "type": "Feature",
  "properties": {
    "gn:admin1_code": "10.0",
    "gn:asciiname": "Hutudi",
    "gn:country_code": "CN",
    "gn:dem": 657,
    "gn:feature_class": "P",
    "gn:feature_code": "PPL",
    "gn:name": "Hutudi",
    "gn:population": 0,
    "gn:timezone": "Asia/Shanghai",
    "iso:country": "CN",
    "name:zho_x_preferred": [
      "鹄突地"
    ],
    "wof:name": "Hutudi",
    "wof:placetype": "locality"
  },
  "geometry": {
    "coordinates": [
      114.85601,
      40.68493
    ],
    "type": "Point"
  }
}