{
  "type": "Feature",
  "properties": {
    "gn:admin1_code": "02",
    "gn:asciiname": "Dayin",
    "gn:country_code": "CN",
    "gn:dem": 1,
    "gn:feature_class": "P",
    "gn:feature_code": "PPLA4",
    "gn:name": "Dayin",
    "gn:population": 0,
    "gn:timezone": "Asia/Shanghai",
    "iso:country": "CN",
    "name:fas_x_preferred": [
      "دایین"
    ],
    "name:und_x_variant": [
      "Ta-yin",
      "Dayin",
      "Dayin Zhen"
    ],
    "name:zho_x_preferred": [
      "大隐"
    ],
    "name:zho_x_variant": [
      "大隐镇"
    ],
    "wof:name": "Dayin",
    "wof:placetype": "locality"
  },
  "geometry": {
    "coordinates": [
      121.37107,
      29.94005
    ],
    "type": "Point"
  }
}