{
  "type": "Feature",
  "properties": {
    "gn:admin1_code": "10.0",
    "gn:asciiname": "Zaoqiang",
    "gn:cc2": "CN",
    "gn:country_code": "CN",
    "gn:dem": 28,
    "gn:feature_class": "P",
    "gn:feature_code": "PPL",
    "gn:name": "Zaoqiang",
    "gn:population": 0,
    "gn:timezone": "Asia/Shanghai",
    "iso:country": "CN",
    "name:deu_x_preferred": [
      "Zaoqiang"
    ],
    "name:fas_x_preferred": [
      "شهرستان زاوچیانگ"
    ],
    "name:jpn_x_preferred": [
      "棗強県"
    ],
    "name:kor_x_preferred": [
      "짜오창현"
    ],
    "name:nor_x_preferred": [
      "Zaoqiang"
    ],
    "name:rus_x_preferred": [
      "Цзаоцян"
    ],
    "name:swe_x_preferred": [
      "Zaoqiang"
    ],
    "name:und_x_variant": [
      "Tsao-ch’iang-ch’eng-kuan",
      "Ts’ao-ch’iang",
      "Tsaokianghsien",
      "Tsao-ch’iang-hsien",
      "Tszaotsyan"
    ],
    "name:urd_x_preferred": [
      "زاوچیانگ کاؤنٹی"
    ],
    "name:vie_x_preferred": [
      "Tảo Cường"
    ],
    "name:zho_x_preferred": [
      "枣强县"
    ],
    "wof:name": "Zaoqiang",
    "wof:placetype": "locality"
  },
  "geometry": {
    "coordinates": [
      115.71583,
      37.50611
    ],
    "type": "Point"
  }
}