{
  "type": "Feature",
  "properties": {
    "gn:admin1_code": "1.0",
    "gn:asciiname": "Xiaochi",
    "gn:cc2": "CN",
    "gn:country_code": "CN",
    "gn:dem": 42,
    "gn:feature_class": "P",
    "gn:feature_code": "PPL",
    "gn:name": "Xiaochi",
    "gn:population": 0,
    "gn:timezone": "Asia/Shanghai",
    "iso:country": "CN",
    "name:ind_x_preferred": [
      "Xiaochi"
    ],
    "name:ita_x_preferred": [
      "Xiaochi"
    ],
    "name:rus_x_preferred": [
      "Сяочи"
    ],
    "name:und_x_variant": [
      "Hsiao-ch’ih-i",
      "Hsiao-ch’ih"
    ],
    "name:zho_x_preferred": [
      "中式小吃"
    ],
    "wof:name": "Xiaochi",
    "wof:placetype": "locality"
  },
  "geometry": {
    "coordinates": [
      116.38889,
      30.52556
    ],
    "type": "Point"
  }
}