{
  "type": "Feature",
  "properties": {
    "gn:admin1_code": "15.0",
    "gn:asciiname": "Hujiagou",
    "gn:country_code": "CN",
    "gn:dem": 1080,
    "gn:feature_class": "P",
    "gn:feature_code": "PPL",
    "gn:name": "Hujiagou",
    "gn:population": 0,
    "gn:timezone": "Asia/Shanghai",
    "iso:country": "CN",
    "name:und_x_variant": [
      "胡家沟"
    ],
    "wof:name": "Hujiagou",
    "wof:placetype": "locality"
  },
  "geometry": {
    "coordinates": [
      106.0573,
      33.82928
    ],
    "type": "Point"
  }
}