{
  "type": "Feature",
  "properties": {
    "gn:admin1_code": "7.0",
    "gn:asciiname": "Shangyuan",
    "gn:country_code": "CN",
    "gn:dem": 271,
    "gn:feature_class": "P",
    "gn:feature_code": "PPL",
    "gn:name": "Shangyuan",
    "gn:population": 0,
    "gn:timezone": "Asia/Shanghai",
    "iso:country": "CN",
    "name:zho_x_preferred": [
      "上源"
    ],
    "name:zho_x_variant": [
      "上元"
    ],
    "wof:name": "Shangyuan",
    "wof:placetype": "locality"
  },
  "geometry": {
    "coordinates": [
      117.71737,
      26.71215
    ],
    "type": "Point"
  }
}