{
  "type": "Feature",
  "properties": {
    "gn:admin1_code": "14.0",
    "gn:asciiname": "Biniancun",
    "gn:country_code": "CN",
    "gn:dem": 4009,
    "gn:feature_class": "P",
    "gn:feature_code": "PPL",
    "gn:name": "Biniancun",
    "gn:population": 0,
    "gn:timezone": "Asia/Urumqi",
    "iso:country": "CN",
    "name:zho_x_preferred": [
      "毕念村"
    ],
    "wof:name": "Biniancun",
    "wof:placetype": "locality"
  },
  "geometry": {
    "coordinates": [
      92.24272,
      28.43707
    ],
    "type": "Point"
  }
}