{
  "type": "Feature",
  "properties": {
    "gn:admin1_code": "3",
    "gn:asciiname": "Shihoucun",
    "gn:country_code": "CN",
    "gn:dem": 76,
    "gn:feature_class": "P",
    "gn:feature_code": "PPL",
    "gn:name": "Shihoucun",
    "gn:population": 0,
    "gn:timezone": "Asia/Shanghai",
    "iso:country": "CN",
    "name:und_x_variant": [
      "世厚村",
      "Shihou"
    ],
    "name:zho_x_preferred": [
      "Shihoucun"
    ],
    "wof:name": "Shihoucun",
    "wof:placetype": "locality"
  },
  "geometry": {
    "coordinates": [
      116.61344,
      27.50851
    ],
    "type": "Point"
  }
}