{
  "type": "Feature",
  "properties": {
    "gn:admin1_code": "33.0",
    "gn:asciiname": "Yinglong",
    "gn:country_code": "CN",
    "gn:dem": 681,
    "gn:feature_class": "P",
    "gn:feature_code": "PPL",
    "gn:name": "Yinglong",
    "gn:population": 0,
    "gn:timezone": "Asia/Shanghai",
    "iso:country": "CN",
    "name:fas_x_preferred": [
      "یینگ لانگ"
    ],
    "name:ita_x_preferred": [
      "Yinglong"
    ],
    "name:msa_x_preferred": [
      "Yinglong"
    ],
    "name:pol_x_preferred": [
      "Yinglong"
    ],
    "name:rus_x_preferred": [
      "Инлун"
    ],
    "name:sco_x_preferred": [
      "Yinglong"
    ],
    "name:spa_x_preferred": [
      "Yinglong"
    ],
    "name:vie_x_preferred": [
      "Ứng Long"
    ],
    "name:zho_x_preferred": [
      "迎龙"
    ],
    "wof:name": "Yinglong",
    "wof:placetype": "locality"
  },
  "geometry": {
    "coordinates": [
      107.14821,
      29.54781
    ],
    "type": "Point"
  }
}