{
  "type": "Feature",
  "properties": {
    "gn:admin1_code": "4.0",
    "gn:asciiname": "Zhunan",
    "gn:country_code": "CN",
    "gn:dem": 51,
    "gn:feature_class": "P",
    "gn:feature_code": "PPL",
    "gn:name": "Zhunan",
    "gn:population": 0,
    "gn:timezone": "Asia/Shanghai",
    "iso:country": "CN",
    "name:ceb_x_preferred": [
      "Zhunan Zhen"
    ],
    "name:fra_x_preferred": [
      "Zhunan"
    ],
    "name:hak_x_preferred": [
      "Tsuk-nàm-chṳ́n"
    ],
    "name:ita_x_preferred": [
      "Zhunan"
    ],
    "name:jpn_x_preferred": [
      "竹南鎮"
    ],
    "name:kor_x_preferred": [
      "주난진"
    ],
    "name:und_x_variant": [
      "竹南"
    ],
    "name:vie_x_preferred": [
      "Trúc Nam"
    ],
    "name:zho_x_preferred": [
      "竹南鎮"
    ],
    "wof:name": "Zhunan",
    "wof:placetype": "locality"
  },
  "geometry": {
    "coordinates": [
      118.57654,
      34.54604
    ],
    "type": "Point"
  }
}