{
  "type": "Feature",
  "properties": {
    "gn:admin1_code": "12.0",
    "gn:asciiname": "Caishenmiao",
    "gn:country_code": "CN",
    "gn:dem": 533,
    "gn:feature_class": "P",
    "gn:feature_code": "PPL",
    "gn:name": "Caishenmiao",
    "gn:population": 0,
    "gn:timezone": "Asia/Shanghai",
    "iso:country": "CN",
    "name:zho_x_preferred": [
      "财神庙"
    ],
    "wof:name": "Caishenmiao",
    "wof:placetype": "locality"
  },
  "geometry": {
    "coordinates": [
      111.04255,
      32.43598
    ],
    "type": "Point"
  }
}