{
  "type": "Feature",
  "properties": {
    "gn:admin1_code": "11.0",
    "gn:asciiname": "Zhangjiading",
    "gn:country_code": "CN",
    "gn:dem": 158,
    "gn:feature_class": "P",
    "gn:feature_code": "PPL",
    "gn:name": "Zhangjiading",
    "gn:population": 0,
    "gn:timezone": "Asia/Shanghai",
    "iso:country": "CN",
    "name:zho_x_preferred": [
      "张家顶"
    ],
    "wof:name": "Zhangjiading",
    "wof:placetype": "locality"
  },
  "geometry": {
    "coordinates": [
      110.21311,
      28.00473
    ],
    "type": "Point"
  }
}