{
  "type": "Feature",
  "properties": {
    "gn:admin1_code": "15.0",
    "gn:asciiname": "Dongfeng Nongchang Erzhan",
    "gn:country_code": "CN",
    "gn:dem": 1089,
    "gn:feature_class": "P",
    "gn:feature_code": "PPLF",
    "gn:name": "Dongfeng Nongchang Erzhan",
    "gn:population": 0,
    "gn:timezone": "Asia/Urumqi",
    "iso:country": "CN",
    "name:eng_x_preferred": [
      "Dongfeng Nongchang Second Station"
    ],
    "name:zho_x_preferred": [
      "东风农场二站"
    ],
    "wof:name": "Dongfeng Nongchang Erzhan",
    "wof:placetype": "locality"
  },
  "geometry": {
    "coordinates": [
      94.84592,
      40.22954
    ],
    "type": "Point"
  }
}