{
  "type": "Feature",
  "properties": {
    "gn:admin1_code": "4.0",
    "gn:asciiname": "Luoxucun",
    "gn:country_code": "CN",
    "gn:dem": 18,
    "gn:feature_class": "P",
    "gn:feature_code": "PPL",
    "gn:name": "Luoxucun",
    "gn:population": 0,
    "gn:timezone": "Asia/Shanghai",
    "iso:country": "CN",
    "name:zho_x_preferred": [
      "罗圩村"
    ],
    "wof:name": "Luoxucun",
    "wof:placetype": "locality"
  },
  "geometry": {
    "coordinates": [
      118.69647,
      33.63647
    ],
    "type": "Point"
  }
}