{
  "type": "Feature",
  "properties": {
    "gn:admin1_code": "24.0",
    "gn:asciiname": "Hanjiayuan",
    "gn:country_code": "CN",
    "gn:dem": 920,
    "gn:feature_class": "P",
    "gn:feature_code": "PPL",
    "gn:name": "Hanjiayuan",
    "gn:population": 0,
    "gn:timezone": "Asia/Shanghai",
    "iso:country": "CN",
    "name:fas_x_preferred": [
      "هانجیایوان"
    ],
    "name:zho_x_preferred": [
      "韩家塬"
    ],
    "name:zho_x_variant": [
      "韩家园镇"
    ],
    "wof:name": "Hanjiayuan",
    "wof:placetype": "locality"
  },
  "geometry": {
    "coordinates": [
      110.62382,
      36.6954
    ],
    "type": "Point"
  }
}