{
  "type": "Feature",
  "properties": {
    "gn:admin1_code": "4.0",
    "gn:asciiname": "Xiao'aocun",
    "gn:country_code": "CN",
    "gn:dem": 2,
    "gn:feature_class": "P",
    "gn:feature_code": "PPL",
    "gn:name": "Xiao’aocun",
    "gn:population": 0,
    "gn:timezone": "Asia/Shanghai",
    "iso:country": "CN",
    "name:und_x_variant": [
      "Xiao’aocun"
    ],
    "name:zho_x_preferred": [
      "肖坳村"
    ],
    "wof:name": "Xiao'aocun",
    "wof:placetype": "locality"
  },
  "geometry": {
    "coordinates": [
      120.3949,
      32.99652
    ],
    "type": "Point"
  }
}