{
  "type": "Feature",
  "properties": {
    "gn:admin1_code": "04",
    "gn:asciiname": "Huitongcun",
    "gn:country_code": "CN",
    "gn:dem": 7,
    "gn:feature_class": "P",
    "gn:feature_code": "PPL",
    "gn:name": "Huitongcun",
    "gn:population": 0,
    "gn:timezone": "Asia/Shanghai",
    "iso:country": "CN",
    "name:und_x_variant": [
      "Hui-t’ung-chen",
      "Huitongzhen",
      "Huitong",
      "汇通",
      "Huitongcun"
    ],
    "name:zho_x_preferred": [
      "汇通镇"
    ],
    "name:zho_x_variant": [
      "汇通村"
    ],
    "wof:name": "Huitongcun",
    "wof:placetype": "locality"
  },
  "geometry": {
    "coordinates": [
      121.135,
      31.9774
    ],
    "type": "Point"
  }
}