{
  "type": "Feature",
  "properties": {
    "gn:admin1_code": "11.0",
    "gn:asciiname": "Lao'antang",
    "gn:country_code": "CN",
    "gn:dem": 773,
    "gn:feature_class": "P",
    "gn:feature_code": "PPL",
    "gn:name": "Lao’antang",
    "gn:population": 0,
    "gn:timezone": "Asia/Shanghai",
    "iso:country": "CN",
    "name:und_x_variant": [
      "Lao’antang"
    ],
    "name:zho_x_preferred": [
      "老安塘"
    ],
    "wof:name": "Lao'antang",
    "wof:placetype": "locality"
  },
  "geometry": {
    "coordinates": [
      113.59684,
      26.14639
    ],
    "type": "Point"
  }
}