{
  "type": "Feature",
  "properties": {
    "gn:admin1_code": "4.0",
    "gn:asciiname": "Fangzhuang",
    "gn:country_code": "CN",
    "gn:dem": 27,
    "gn:feature_class": "P",
    "gn:feature_code": "PPL",
    "gn:name": "Fangzhuang",
    "gn:population": 0,
    "gn:timezone": "Asia/Shanghai",
    "iso:country": "CN",
    "name:zho_x_preferred": [
      "方庄"
    ],
    "name:zho_x_variant": [
      "方庄地区"
    ],
    "wof:name": "Fangzhuang",
    "wof:placetype": "locality"
  },
  "geometry": {
    "coordinates": [
      119.34605,
      32.50895999999999
    ],
    "type": "Point"
  }
}