{
  "type": "Feature",
  "properties": {
    "gn:admin1_code": "10",
    "gn:asciiname": "Dayushu",
    "gn:country_code": "CN",
    "gn:dem": 949,
    "gn:feature_class": "P",
    "gn:feature_code": "PPL",
    "gn:name": "Dayushu",
    "gn:population": 0,
    "gn:timezone": "Asia/Shanghai",
    "iso:country": "CN",
    "name:zho_x_preferred": [
      "大榆树"
    ],
    "wof:name": "Dayushu",
    "wof:placetype": "locality"
  },
  "geometry": {
    "coordinates": [
      115.70481,
      40.71754
    ],
    "type": "Point"
  }
}