{
  "type": "Feature",
  "properties": {
    "iso:country": "CN",
    "name:eng_x_preferred": [
      "Pengbu"
    ],
    "name:zho_x_preferred": [
      "彭埠镇"
    ],
    "qs:name": "彭埠镇",
    "qs:name_adm0": "中國",
    "qs:name_adm1": "浙江省",
    "qs:photos": 32,
    "qs:photos_1k": 6,
    "qs:photos_9k": 1,
    "qs:photos_9r": 2,
    "qs:photos_all": 32,
    "qs:photos_sr": 2,
    "qs:placetype": "Town",
    "qs:pop_sr": "0",
    "wof:name": "Pengbu",
    "wof:placetype": "locality"
  },
  "geometry": {
    "coordinates": [
      120.224789,
      30.303462
    ],
    "type": "Point"
  }
}