{
  "type": "Feature",
  "properties": {
    "gn:admin1_code": "15.0",
    "gn:asciiname": "Xianfeng",
    "gn:country_code": "CN",
    "gn:dem": 934,
    "gn:feature_class": "P",
    "gn:feature_code": "PPL",
    "gn:name": "Xianfeng",
    "gn:population": 0,
    "gn:timezone": "Asia/Shanghai",
    "iso:country": "CN",
    "name:ceb_x_preferred": [
      "Xianfeng"
    ],
    "name:deu_x_preferred": [
      "Xianfeng"
    ],
    "name:fra_x_preferred": [
      "Xianfeng"
    ],
    "name:nor_x_preferred": [
      "Xianfeng"
    ],
    "name:zho_x_preferred": [
      "先峰"
    ],
    "wof:name": "Xianfeng",
    "wof:placetype": "locality"
  },
  "geometry": {
    "coordinates": [
      107.797,
      35.2974
    ],
    "type": "Point"
  }
}