{
  "type": "Feature",
  "properties": {
    "gn:admin1_code": "2.0",
    "gn:asciiname": "Hexing",
    "gn:country_code": "CN",
    "gn:dem": 235,
    "gn:feature_class": "P",
    "gn:feature_code": "PPL",
    "gn:name": "Hexing",
    "gn:population": 0,
    "gn:timezone": "Asia/Shanghai",
    "iso:country": "CN",
    "name:ces_x_preferred": [
      "Hexing"
    ],
    "name:fra_x_preferred": [
      "Hexing"
    ],
    "name:mal_x_preferred": [
      "ഹെക്സിങ്ങ്"
    ],
    "name:nld_x_preferred": [
      "Hexing"
    ],
    "name:ori_x_preferred": [
      "Hexing"
    ],
    "name:pol_x_preferred": [
      "Hexing"
    ],
    "name:por_x_preferred": [
      "Hexing qingyi"
    ],
    "name:spa_x_preferred": [
      "Hexing qingyi"
    ],
    "name:vie_x_preferred": [
      "Hexing"
    ],
    "name:zho_x_preferred": [
      "合星"
    ],
    "name:zho_x_variant": [
      "鶴形龍屬"
    ],
    "wof:name": "Hexing",
    "wof:placetype": "locality"
  },
  "geometry": {
    "coordinates": [
      120.87659,
      29.43919
    ],
    "type": "Point"
  }
}