{
  "type": "Feature",
  "properties": {
    "gn:admin1_code": "19.0",
    "gn:asciiname": "Xiamiaocun",
    "gn:country_code": "CN",
    "gn:dem": 109,
    "gn:feature_class": "P",
    "gn:feature_code": "PPL",
    "gn:name": "Xiamiaocun",
    "gn:population": 0,
    "gn:timezone": "Asia/Shanghai",
    "iso:country": "CN",
    "name:zho_x_preferred": [
      "下庙村"
    ],
    "wof:name": "Xiamiaocun",
    "wof:placetype": "locality"
  },
  "geometry": {
    "coordinates": [
      122.162,
      39.6898
    ],
    "type": "Point"
  }
}