{
  "type": "Feature",
  "properties": {
    "gn:admin1_code": "16.0",
    "gn:asciiname": "Ping'en",
    "gn:country_code": "CN",
    "gn:dem": 946,
    "gn:feature_class": "P",
    "gn:feature_code": "PPL",
    "gn:name": "Ping’en",
    "gn:population": 0,
    "gn:timezone": "Asia/Shanghai",
    "iso:country": "CN",
    "name:und_x_variant": [
      "Ping’en"
    ],
    "name:zho_x_preferred": [
      "平恩"
    ],
    "wof:name": "Ping'en",
    "wof:placetype": "locality"
  },
  "geometry": {
    "coordinates": [
      105.96,
      23.2824
    ],
    "type": "Point"
  }
}