{
  "type": "Feature",
  "properties": {
    "gn:admin1_code": "13",
    "gn:asciiname": "Yilingsantuan Balian",
    "gn:country_code": "CN",
    "gn:dem": 435,
    "gn:feature_class": "P",
    "gn:feature_code": "PPL",
    "gn:name": "Yilingsantuan Balian",
    "gn:population": 0,
    "gn:timezone": "Asia/Urumqi",
    "iso:country": "CN",
    "name:zho_x_preferred": [
      "一零三团八连"
    ],
    "wof:name": "Yilingsantuan Balian",
    "wof:placetype": "locality"
  },
  "geometry": {
    "coordinates": [
      87.50559,
      44.45781
    ],
    "type": "Point"
  }
}