{
  "type": "Feature",
  "properties": {
    "gn:admin1_code": "12.0",
    "gn:asciiname": "Yangzhou",
    "gn:country_code": "CN",
    "gn:dem": 31,
    "gn:feature_class": "P",
    "gn:feature_code": "PPL",
    "gn:name": "Yangzhou",
    "gn:population": 0,
    "gn:timezone": "Asia/Shanghai",
    "iso:country": "CN",
    "name:afr_x_preferred": [
      "Yangzhou"
    ],
    "name:als_x_preferred": [
      "Yangzhou"
    ],
    "name:ara_x_preferred": [
      "يانغتشو"
    ],
    "name:ast_x_preferred": [
      "Yangzhou"
    ],
    "name:bod_x_preferred": [
      "ཡྰང་ཀྲོའུ།"
    ],
    "name:bre_x_preferred": [
      "Yangzhou"
    ],
    "name:bul_x_preferred": [
      "Янджоу"
    ],
    "name:cat_x_preferred": [
      "Yangzhou"
    ],
    "name:cdo_x_preferred": [
      "Iòng-ciŭ"
    ],
    "name:ceb_x_preferred": [
      "Yangzhou"
    ],
    "name:ces_x_preferred": [
      "Jang-čou"
    ],
    "name:cym_x_preferred": [
      "Yangzhou"
    ],
    "name:dan_x_preferred": [
      "Yangzhou"
    ],
    "name:deu_x_preferred": [
      "Yangzhou"
    ],
    "name:epo_x_preferred": [
      "Janĉĵou"
    ],
    "name:eus_x_preferred": [
      "Yangzhou"
    ],
    "name:fas_x_preferred": [
      "یانگژو"
    ],
    "name:fin_x_preferred": [
      "Yangzhou"
    ],
    "name:fra_x_preferred": [
      "Yangzhou"
    ],
    "name:heb_x_preferred": [
      "יאנגג'ואו"
    ],
    "name:ind_x_preferred": [
      "Yangzhou"
    ],
    "name:ita_x_preferred": [
      "Yangzhou"
    ],
    "name:jpn_x_preferred": [
      "揚州市"
    ],
    "name:kik_x_preferred": [
      "Yangzhou"
    ],
    "name:kor_x_preferred": [
      "양저우시"
    ],
    "name:mlg_x_preferred": [
      "Yangzhou"
    ],
    "name:nld_x_preferred": [
      "Yangzhou"
    ],
    "name:nno_x_preferred": [
      "Yangzhou"
    ],
    "name:nor_x_preferred": [
      "Yangzhou"
    ],
    "name:pol_x_preferred": [
      "Yangzhou"
    ],
    "name:por_x_preferred": [
      "Yangzhou"
    ],
    "name:rus_x_preferred": [
      "Янчжоу"
    ],
    "name:spa_x_preferred": [
      "Yangzhou"
    ],
    "name:srp_x_preferred": [
      "Јангџоу"
    ],
    "name:swe_x_preferred": [
      "Yangzhou"
    ],
    "name:tgl_x_preferred": [
      "Yangzhou"
    ],
    "name:tur_x_preferred": [
      "Yangzhou"
    ],
    "name:uig_x_preferred": [
      "Yangjo shehiri"
    ],
    "name:ukr_x_preferred": [
      "Янчжоу"
    ],
    "name:urd_x_preferred": [
      "یانگژو"
    ],
    "name:vie_x_preferred": [
      "Dương Châu"
    ],
    "name:war_x_preferred": [
      "Yangzhou"
    ],
    "name:wuu_x_preferred": [
      "扬州市"
    ],
    "name:zho_x_preferred": [
      "杨洲"
    ],
    "name:zho_x_variant": [
      "扬州市"
    ],
    "wof:name": "Yangzhou",
    "wof:placetype": "locality"
  },
  "geometry": {
    "coordinates": [
      113.29604,
      30.27187
    ],
    "type": "Point"
  }
}