{
  "type": "Feature",
  "properties": {
    "iso:country": "CN",
    "name:eng_x_preferred": [
      "Nankou"
    ],
    "name:zho_x_preferred": [
      "南口"
    ],
    "qs:name": "南口",
    "qs:name_adm0": "中國",
    "qs:name_adm1": "北京直辖市",
    "qs:photos": 261,
    "qs:photos_1k": 53,
    "qs:photos_9k": 1,
    "qs:photos_9r": 4,
    "qs:photos_all": 261,
    "qs:photos_sr": 5,
    "qs:placetype": "Town",
    "qs:pop_sr": "0",
    "wof:name": "Nankou",
    "wof:placetype": "locality"
  },
  "geometry": {
    "coordinates": [
      116.126861,
      40.241705
    ],
    "type": "Point"
  }
}