{
  "type": "Feature",
  "properties": {
    "gn:admin1_code": "25",
    "gn:asciiname": "Lulou",
    "gn:country_code": "CN",
    "gn:dem": 42,
    "gn:feature_class": "P",
    "gn:feature_code": "PPL",
    "gn:name": "Lülou",
    "gn:population": 0,
    "gn:timezone": "Asia/Shanghai",
    "iso:country": "CN",
    "name:und_x_variant": [
      "Lülou"
    ],
    "name:zho_x_preferred": [
      "吕楼"
    ],
    "wof:name": "Lulou",
    "wof:placetype": "locality"
  },
  "geometry": {
    "coordinates": [
      116.227,
      35.6733
    ],
    "type": "Point"
  }
}