{
  "type": "Feature",
  "properties": {
    "gn:admin1_code": "30.0",
    "gn:asciiname": "Xinqiao",
    "gn:country_code": "CN",
    "gn:dem": 15,
    "gn:feature_class": "P",
    "gn:feature_code": "PPLA4",
    "gn:name": "Xinqiao",
    "gn:population": 0,
    "gn:timezone": "Asia/Shanghai",
    "iso:country": "CN",
    "name:fas_x_preferred": [
      "شینکیاو"
    ],
    "name:und_x_variant": [
      "Hsin-ch’iao",
      "Hsin-ch’iao-hsü",
      "Xinqiao",
      "Xinqiao Zhen"
    ],
    "name:zho_x_preferred": [
      "新桥"
    ],
    "name:zho_x_variant": [
      "新桥镇"
    ],
    "wof:name": "Xinqiao",
    "wof:placetype": "locality"
  },
  "geometry": {
    "coordinates": [
      112.41026,
      22.95447
    ],
    "type": "Point"
  }
}