{
  "type": "Feature",
  "properties": {
    "gn:admin1_code": "8.0",
    "gn:asciiname": "Jiangdayuan",
    "gn:country_code": "CN",
    "gn:dem": 239,
    "gn:feature_class": "P",
    "gn:feature_code": "PPL",
    "gn:name": "Jiangdayuan",
    "gn:population": 0,
    "gn:timezone": "Asia/Shanghai",
    "iso:country": "CN",
    "name:zho_x_preferred": [
      "姜大院"
    ],
    "wof:name": "Jiangdayuan",
    "wof:placetype": "locality"
  },
  "geometry": {
    "coordinates": [
      127.57985,
      44.56878
    ],
    "type": "Point"
  }
}