{
  "type": "Feature",
  "properties": {
    "gn:admin1_code": "32.0",
    "gn:asciiname": "Dazhaizi",
    "gn:country_code": "CN",
    "gn:dem": 3547,
    "gn:feature_class": "P",
    "gn:feature_code": "PPL",
    "gn:name": "Dazhaizi",
    "gn:population": 0,
    "gn:timezone": "Asia/Shanghai",
    "iso:country": "CN",
    "name:zho_x_preferred": [
      "大寨子"
    ],
    "wof:name": "Dazhaizi",
    "wof:placetype": "locality"
  },
  "geometry": {
    "coordinates": [
      103.778,
      32.2988
    ],
    "type": "Point"
  }
}