{
  "type": "Feature",
  "properties": {
    "gn:admin1_code": "30",
    "gn:asciiname": "Shangguankeng",
    "gn:country_code": "CN",
    "gn:dem": 332,
    "gn:feature_class": "P",
    "gn:feature_code": "PPL",
    "gn:name": "Shangguankeng",
    "gn:population": 0,
    "gn:timezone": "Asia/Shanghai",
    "iso:country": "CN",
    "name:zho_x_preferred": [
      "上官坑"
    ],
    "wof:name": "Shangguankeng",
    "wof:placetype": "locality"
  },
  "geometry": {
    "coordinates": [
      115.82143,
      24.68722
    ],
    "type": "Point"
  }
}