{
  "type": "Feature",
  "properties": {
    "gn:admin1_code": "19.0",
    "gn:asciiname": "Yujia Gouli",
    "gn:country_code": "CN",
    "gn:dem": 222,
    "gn:feature_class": "P",
    "gn:feature_code": "PPL",
    "gn:name": "Yujia Gouli",
    "gn:population": 0,
    "gn:timezone": "Asia/Shanghai",
    "iso:country": "CN",
    "name:zho_x_preferred": [
      "于家沟里"
    ],
    "wof:name": "Yujia Gouli",
    "wof:placetype": "locality"
  },
  "geometry": {
    "coordinates": [
      120.047,
      40.7093
    ],
    "type": "Point"
  }
}