{
  "type": "Feature",
  "properties": {
    "gn:admin1_code": "16.0",
    "gn:asciiname": "Yaoqiu",
    "gn:country_code": "CN",
    "gn:dem": 880,
    "gn:feature_class": "P",
    "gn:feature_code": "PPL",
    "gn:name": "Yaoqiu",
    "gn:population": 0,
    "gn:timezone": "Asia/Shanghai",
    "iso:country": "CN",
    "name:zho_x_preferred": [
      "尧丘"
    ],
    "wof:name": "Yaoqiu",
    "wof:placetype": "locality"
  },
  "geometry": {
    "coordinates": [
      107.344,
      25.2186
    ],
    "type": "Point"
  }
}