{
  "type": "Feature",
  "properties": {
    "gn:admin1_code": "11.0",
    "gn:asciiname": "Shuidongcun",
    "gn:country_code": "CN",
    "gn:dem": 72,
    "gn:feature_class": "P",
    "gn:feature_code": "PPL",
    "gn:name": "Shuidongcun",
    "gn:population": 0,
    "gn:timezone": "Asia/Shanghai",
    "iso:country": "CN",
    "name:zho_x_preferred": [
      "水东村"
    ],
    "wof:name": "Shuidongcun",
    "wof:placetype": "locality"
  },
  "geometry": {
    "coordinates": [
      112.41339,
      27.65793
    ],
    "type": "Point"
  }
}