{
  "type": "Feature",
  "properties": {
    "gn:admin1_code": "5.0",
    "gn:asciiname": "Daqinghuoshuo",
    "gn:country_code": "CN",
    "gn:dem": 135,
    "gn:feature_class": "P",
    "gn:feature_code": "PPL",
    "gn:name": "Daqinghuoshuo",
    "gn:population": 0,
    "gn:timezone": "Asia/Shanghai",
    "iso:country": "CN",
    "name:zho_x_preferred": [
      "大青火硕"
    ],
    "wof:name": "Daqinghuoshuo",
    "wof:placetype": "locality"
  },
  "geometry": {
    "coordinates": [
      123.45436,
      46.22024
    ],
    "type": "Point"
  }
}