{
  "type": "Feature",
  "properties": {
    "gn:admin1_code": "10",
    "gn:asciiname": "Lizhangzi",
    "gn:country_code": "CN",
    "gn:dem": 238,
    "gn:feature_class": "P",
    "gn:feature_code": "PPL",
    "gn:name": "Lizhangzi",
    "gn:population": 0,
    "gn:timezone": "Asia/Shanghai",
    "iso:country": "CN",
    "name:zho_x_preferred": [
      "李仗子"
    ],
    "wof:name": "Lizhangzi",
    "wof:placetype": "locality"
  },
  "geometry": {
    "coordinates": [
      119.10711,
      40.40336
    ],
    "type": "Point"
  }
}