{
  "type": "Feature",
  "properties": {
    "gn:admin1_code": "24.0",
    "gn:asciiname": "Caojia Yadicun",
    "gn:country_code": "CN",
    "gn:dem": 993,
    "gn:feature_class": "P",
    "gn:feature_code": "PPL",
    "gn:name": "Caojia Yadicun",
    "gn:population": 0,
    "gn:timezone": "Asia/Shanghai",
    "iso:country": "CN",
    "name:zho_x_preferred": [
      "曹家崖底村"
    ],
    "wof:name": "Caojia Yadicun",
    "wof:placetype": "locality"
  },
  "geometry": {
    "coordinates": [
      110.95879,
      37.31411
    ],
    "type": "Point"
  }
}