{
  "type": "Feature",
  "properties": {
    "gn:admin1_code": "25",
    "gn:asciiname": "Liujia Guanzhuang",
    "gn:country_code": "CN",
    "gn:dem": 47,
    "gn:feature_class": "P",
    "gn:feature_code": "PPL",
    "gn:name": "Liujia Guanzhuang",
    "gn:population": 0,
    "gn:timezone": "Asia/Shanghai",
    "iso:country": "CN",
    "name:zho_x_preferred": [
      "刘家官庄"
    ],
    "wof:name": "Liujia Guanzhuang",
    "wof:placetype": "locality"
  },
  "geometry": {
    "coordinates": [
      117.945,
      34.8107
    ],
    "type": "Point"
  }
}