{
  "type": "Feature",
  "properties": {
    "gn:admin1_code": "16",
    "gn:asciiname": "Mojia Dayuan",
    "gn:country_code": "CN",
    "gn:dem": 657,
    "gn:feature_class": "P",
    "gn:feature_code": "PPL",
    "gn:name": "Mojia Dayuan",
    "gn:population": 0,
    "gn:timezone": "Asia/Shanghai",
    "iso:country": "CN",
    "name:zho_x_preferred": [
      "莫家大源"
    ],
    "wof:name": "Mojia Dayuan",
    "wof:placetype": "locality"
  },
  "geometry": {
    "coordinates": [
      110.652,
      24.9202
    ],
    "type": "Point"
  }
}