{
  "type": "Feature",
  "properties": {
    "gn:admin1_code": "19.0",
    "gn:asciiname": "Chuangouzi Yidui",
    "gn:country_code": "CN",
    "gn:dem": 242,
    "gn:feature_class": "P",
    "gn:feature_code": "PPLF",
    "gn:name": "Chuangouzi Yidui",
    "gn:population": 0,
    "gn:timezone": "Asia/Shanghai",
    "iso:country": "CN",
    "name:zho_x_preferred": [
      "川沟子一队"
    ],
    "wof:name": "Chuangouzi Yidui",
    "wof:placetype": "locality"
  },
  "geometry": {
    "coordinates": [
      125.591,
      40.8484
    ],
    "type": "Point"
  }
}