{
  "type": "Feature",
  "properties": {
    "gn:admin1_code": "11.0",
    "gn:asciiname": "Longmenquan",
    "gn:country_code": "CN",
    "gn:dem": 78,
    "gn:feature_class": "P",
    "gn:feature_code": "PPL",
    "gn:name": "Longmenquan",
    "gn:population": 0,
    "gn:timezone": "Asia/Shanghai",
    "iso:country": "CN",
    "name:zho_x_preferred": [
      "龙门泉"
    ],
    "wof:name": "Longmenquan",
    "wof:placetype": "locality"
  },
  "geometry": {
    "coordinates": [
      112.94356,
      27.05516
    ],
    "type": "Point"
  }
}