{
  "type": "Feature",
  "properties": {
    "gn:admin1_code": "30.0",
    "gn:asciiname": "Hengshui",
    "gn:country_code": "CN",
    "gn:dem": 556,
    "gn:feature_class": "P",
    "gn:feature_code": "PPL",
    "gn:name": "Hengshui",
    "gn:population": 0,
    "gn:timezone": "Asia/Shanghai",
    "iso:country": "CN",
    "name:ara_x_preferred": [
      "هنغشوي"
    ],
    "name:cdo_x_preferred": [
      "Hèng-cūi"
    ],
    "name:ces_x_preferred": [
      "Cheng-šuej"
    ],
    "name:cym_x_preferred": [
      "Hengshui"
    ],
    "name:dan_x_preferred": [
      "Hengshui"
    ],
    "name:deu_x_preferred": [
      "Hengshui"
    ],
    "name:eus_x_preferred": [
      "Hengshui"
    ],
    "name:fas_x_preferred": [
      "هنگشوی"
    ],
    "name:fin_x_preferred": [
      "Hengshui"
    ],
    "name:fra_x_preferred": [
      "Hengshui"
    ],
    "name:heb_x_preferred": [
      "חנגשואי"
    ],
    "name:ind_x_preferred": [
      "Hengshui"
    ],
    "name:ita_x_preferred": [
      "Hengshui"
    ],
    "name:jpn_x_preferred": [
      "衡水市"
    ],
    "name:kik_x_preferred": [
      "Hengshui"
    ],
    "name:kor_x_preferred": [
      "헝수이시"
    ],
    "name:mlg_x_preferred": [
      "Hengshui"
    ],
    "name:nld_x_preferred": [
      "Hengshui"
    ],
    "name:nno_x_preferred": [
      "Hengshui"
    ],
    "name:nor_x_preferred": [
      "Hengshui"
    ],
    "name:pam_x_preferred": [
      "Hengshui"
    ],
    "name:pol_x_preferred": [
      "Hengshui"
    ],
    "name:por_x_preferred": [
      "Hengshui"
    ],
    "name:rus_x_preferred": [
      "Хэншуй"
    ],
    "name:spa_x_preferred": [
      "Hengshui"
    ],
    "name:srp_x_preferred": [
      "Хенгшуеј"
    ],
    "name:swe_x_preferred": [
      "Hengshui"
    ],
    "name:tur_x_preferred": [
      "Hengshui"
    ],
    "name:urd_x_preferred": [
      "ہینگشوئی"
    ],
    "name:vie_x_preferred": [
      "Hành Thủy"
    ],
    "name:war_x_preferred": [
      "Hengshui"
    ],
    "name:wuu_x_preferred": [
      "衡水市"
    ],
    "name:zho_x_preferred": [
      "Hengshui"
    ],
    "name:zho_x_variant": [
      "横水",
      "衡水市"
    ],
    "wof:name": "Hengshui",
    "wof:placetype": "locality"
  },
  "geometry": {
    "coordinates": [
      112.85583,
      24.87694
    ],
    "type": "Point"
  }
}