{
  "type": "Feature",
  "properties": {
    "gn:admin1_code": "7",
    "gn:asciiname": "Duxia",
    "gn:country_code": "CN",
    "gn:dem": 608,
    "gn:feature_class": "P",
    "gn:feature_code": "PPL",
    "gn:name": "Duxia",
    "gn:population": 0,
    "gn:timezone": "Asia/Shanghai",
    "iso:country": "CN",
    "name:zho_x_preferred": [
      "度下"
    ],
    "wof:name": "Duxia",
    "wof:placetype": "locality"
  },
  "geometry": {
    "coordinates": [
      118.78459,
      25.50354
    ],
    "type": "Point"
  }
}