{
  "type": "Feature",
  "properties": {
    "gn:admin1_code": "12.0",
    "gn:asciiname": "Sankuaibei",
    "gn:country_code": "CN",
    "gn:dem": 816,
    "gn:feature_class": "P",
    "gn:feature_code": "PPL",
    "gn:name": "Sankuaibei",
    "gn:population": 0,
    "gn:timezone": "Asia/Shanghai",
    "iso:country": "CN",
    "name:zho_x_preferred": [
      "三块碑"
    ],
    "wof:name": "Sankuaibei",
    "wof:placetype": "locality"
  },
  "geometry": {
    "coordinates": [
      109.75616,
      30.73445
    ],
    "type": "Point"
  }
}