{
  "type": "Feature",
  "properties": {
    "gn:admin1_code": "11.0",
    "gn:asciiname": "Xiaojiafang",
    "gn:country_code": "CN",
    "gn:dem": 110,
    "gn:feature_class": "P",
    "gn:feature_code": "PPL",
    "gn:name": "Xiaojiafang",
    "gn:population": 0,
    "gn:timezone": "Asia/Shanghai",
    "iso:country": "CN",
    "name:zho_x_preferred": [
      "肖家坊"
    ],
    "wof:name": "Xiaojiafang",
    "wof:placetype": "locality"
  },
  "geometry": {
    "coordinates": [
      113.56302,
      26.76739
    ],
    "type": "Point"
  }
}