{
  "type": "Feature",
  "properties": {
    "gn:admin1_code": "16.0",
    "gn:asciiname": "He'er",
    "gn:country_code": "CN",
    "gn:dem": 140,
    "gn:feature_class": "P",
    "gn:feature_code": "PPL",
    "gn:name": "He’er",
    "gn:population": 0,
    "gn:timezone": "Asia/Shanghai",
    "iso:country": "CN",
    "name:und_x_variant": [
      "He’er"
    ],
    "name:zho_x_preferred": [
      "河儿"
    ],
    "wof:name": "He'er",
    "wof:placetype": "locality"
  },
  "geometry": {
    "coordinates": [
      111.185,
      23.6945
    ],
    "type": "Point"
  }
}