{
  "type": "Feature",
  "properties": {
    "gn:admin1_code": "19",
    "gn:asciiname": "Quangou",
    "gn:country_code": "CN",
    "gn:dem": 174,
    "gn:feature_class": "P",
    "gn:feature_code": "PPLA4",
    "gn:name": "Quangou",
    "gn:population": 0,
    "gn:timezone": "Asia/Shanghai",
    "iso:country": "CN",
    "name:und_x_variant": [
      "Laosiping Zhen",
      "Laosiping",
      "Quangou"
    ],
    "name:zho_x_preferred": [
      "泉沟"
    ],
    "name:zho_x_variant": [
      "老四平镇",
      "老四平"
    ],
    "wof:name": "Quangou",
    "wof:placetype": "locality"
  },
  "geometry": {
    "coordinates": [
      124.26121,
      43.18198
    ],
    "type": "Point"
  }
}