{
  "type": "Feature",
  "properties": {
    "gn:admin1_code": "16.0",
    "gn:asciiname": "Gushunkou",
    "gn:country_code": "CN",
    "gn:dem": 230,
    "gn:feature_class": "P",
    "gn:feature_code": "PPL",
    "gn:name": "Gushunkou",
    "gn:population": 0,
    "gn:timezone": "Asia/Shanghai",
    "iso:country": "CN",
    "name:zho_x_preferred": [
      "古舜口"
    ],
    "wof:name": "Gushunkou",
    "wof:placetype": "locality"
  },
  "geometry": {
    "coordinates": [
      111.302,
      23.8159
    ],
    "type": "Point"
  }
}