{
  "type": "Feature",
  "properties": {
    "gn:admin1_code": "32.0",
    "gn:asciiname": "Tianshui",
    "gn:country_code": "CN",
    "gn:dem": 562,
    "gn:feature_class": "P",
    "gn:feature_code": "PPL",
    "gn:name": "Tianshui",
    "gn:population": 0,
    "gn:timezone": "Asia/Shanghai",
    "iso:country": "CN",
    "name:ara_x_preferred": [
      "تيانشوي"
    ],
    "name:cdo_x_preferred": [
      "Tiĕng-cūi"
    ],
    "name:ces_x_preferred": [
      "Tchien-šuej"
    ],
    "name:dan_x_preferred": [
      "Tianshui"
    ],
    "name:deu_x_preferred": [
      "Tianshui"
    ],
    "name:eus_x_preferred": [
      "Tianshui"
    ],
    "name:fas_x_preferred": [
      "تیانشوی"
    ],
    "name:fin_x_preferred": [
      "Tianshui"
    ],
    "name:fra_x_preferred": [
      "Tianshui"
    ],
    "name:heb_x_preferred": [
      "טיאנשוי"
    ],
    "name:hun_x_preferred": [
      "Tianshui"
    ],
    "name:hye_x_preferred": [
      "Տյանշույ"
    ],
    "name:ind_x_preferred": [
      "Tianshui"
    ],
    "name:ita_x_preferred": [
      "Tianshui"
    ],
    "name:jpn_x_preferred": [
      "天水市"
    ],
    "name:kik_x_preferred": [
      "Tianshui"
    ],
    "name:kor_x_preferred": [
      "톈수이시"
    ],
    "name:mlg_x_preferred": [
      "Tianshui"
    ],
    "name:mon_x_preferred": [
      "Тяньшуй"
    ],
    "name:nld_x_preferred": [
      "Tianshui"
    ],
    "name:nno_x_preferred": [
      "Tianshui"
    ],
    "name:nor_x_preferred": [
      "Tianshui"
    ],
    "name:pam_x_preferred": [
      "Tianshui"
    ],
    "name:pnb_x_preferred": [
      "تیان شوئی"
    ],
    "name:pol_x_preferred": [
      "Tianshui"
    ],
    "name:por_x_preferred": [
      "Tianshui"
    ],
    "name:rus_x_preferred": [
      "Тяньшуй"
    ],
    "name:sco_x_preferred": [
      "Tianshui"
    ],
    "name:spa_x_preferred": [
      "Tianshui"
    ],
    "name:swe_x_preferred": [
      "Tianshui"
    ],
    "name:tgl_x_preferred": [
      "Tianshui"
    ],
    "name:tur_x_preferred": [
      "Tianshui"
    ],
    "name:ukr_x_preferred": [
      "Тяньшуй"
    ],
    "name:urd_x_preferred": [
      "تیانشوئی"
    ],
    "name:vie_x_preferred": [
      "Thiên Thủy"
    ],
    "name:war_x_preferred": [
      "Tianshui"
    ],
    "name:wuu_x_preferred": [
      "天水市"
    ],
    "name:zho_x_preferred": [
      "天水"
    ],
    "name:zho_x_variant": [
      "天水市"
    ],
    "wof:name": "Tianshui",
    "wof:placetype": "locality"
  },
  "geometry": {
    "coordinates": [
      103.601,
      30.6882
    ],
    "type": "Point"
  }
}