{
  "type": "Feature",
  "properties": {
    "gn:admin1_code": "30",
    "gn:asciiname": "Poping",
    "gn:country_code": "CN",
    "gn:dem": 0,
    "gn:feature_class": "P",
    "gn:feature_code": "PPL",
    "gn:name": "Poping",
    "gn:population": 0,
    "gn:timezone": "Asia/Shanghai",
    "iso:country": "CN",
    "name:zho_x_preferred": [
      "坡平"
    ],
    "wof:name": "Poping",
    "wof:placetype": "locality"
  },
  "geometry": {
    "coordinates": [
      115.24796,
      22.88228
    ],
    "type": "Point"
  }
}