{
  "type": "Feature",
  "properties": {
    "gn:admin1_code": "01",
    "gn:asciiname": "Guilin",
    "gn:country_code": "CN",
    "gn:dem": 127,
    "gn:feature_class": "P",
    "gn:feature_code": "PPLA4",
    "gn:name": "Guilin",
    "gn:population": 0,
    "gn:timezone": "Asia/Shanghai",
    "iso:country": "CN",
    "name:afr_x_preferred": [
      "Guilin"
    ],
    "name:ara_x_preferred": [
      "غويلين"
    ],
    "name:aym_x_preferred": [
      "Guilin"
    ],
    "name:bel_x_preferred": [
      "Гуйлінь"
    ],
    "name:bul_x_preferred": [
      "Гуейлин"
    ],
    "name:cat_x_preferred": [
      "Guilin"
    ],
    "name:cdo_x_preferred": [
      "Gié-lìng"
    ],
    "name:ceb_x_preferred": [
      "Guilin Shi"
    ],
    "name:ces_x_preferred": [
      "Kuej-lin"
    ],
    "name:dan_x_preferred": [
      "Guilin"
    ],
    "name:deu_x_preferred": [
      "Guilin"
    ],
    "name:epo_x_preferred": [
      "Gujlin"
    ],
    "name:est_x_preferred": [
      "Guilin Shi"
    ],
    "name:eus_x_preferred": [
      "Guilin"
    ],
    "name:fas_x_preferred": [
      "گویلین"
    ],
    "name:fin_x_preferred": [
      "Guilin"
    ],
    "name:fra_x_preferred": [
      "Guilin"
    ],
    "name:hak_x_preferred": [
      "Kui-lìm-sṳ"
    ],
    "name:heb_x_preferred": [
      "גווילין"
    ],
    "name:hin_x_preferred": [
      "गुइलिन"
    ],
    "name:hun_x_preferred": [
      "Kujlin"
    ],
    "name:ido_x_preferred": [
      "Guilin"
    ],
    "name:ind_x_preferred": [
      "Guilin"
    ],
    "name:ita_x_preferred": [
      "Guilin"
    ],
    "name:jpn_x_preferred": [
      "桂林市"
    ],
    "name:kik_x_preferred": [
      "Guilin"
    ],
    "name:kor_x_preferred": [
      "구이린시"
    ],
    "name:lat_x_preferred": [
      "Guilin"
    ],
    "name:lit_x_preferred": [
      "Guilinas"
    ],
    "name:ltz_x_preferred": [
      "Guilin"
    ],
    "name:mal_x_preferred": [
      "ഗ്വൈലിൻ"
    ],
    "name:mlg_x_preferred": [
      "Guilin"
    ],
    "name:mwl_x_preferred": [
      "Guilin"
    ],
    "name:mya_x_preferred": [
      "ကွေ့လိန်မြို့"
    ],
    "name:nld_x_preferred": [
      "Guilin"
    ],
    "name:nor_x_preferred": [
      "Guilin"
    ],
    "name:pnb_x_preferred": [
      "گوئیلن"
    ],
    "name:pol_x_preferred": [
      "Guilin"
    ],
    "name:por_x_preferred": [
      "Guilin"
    ],
    "name:rus_x_preferred": [
      "Гуйлинь"
    ],
    "name:sco_x_preferred": [
      "Guilin"
    ],
    "name:spa_x_preferred": [
      "Guilin"
    ],
    "name:srp_x_preferred": [
      "Гуејлин"
    ],
    "name:swe_x_preferred": [
      "Guilin"
    ],
    "name:tha_x_preferred": [
      "กุ้ยหลิน"
    ],
    "name:tur_x_preferred": [
      "Guilin"
    ],
    "name:uig_x_preferred": [
      "گۇيلىن شەھىرى"
    ],
    "name:ukr_x_preferred": [
      "Ґуйлінь"
    ],
    "name:und_x_variant": [
      "Kuei-lin",
      "Kuei-lin-chen",
      "Guilin Zhen"
    ],
    "name:urd_x_preferred": [
      "گوئلن"
    ],
    "name:vie_x_preferred": [
      "Quế Lâm"
    ],
    "name:war_x_preferred": [
      "Guilin"
    ],
    "name:zha_x_preferred": [
      "Gveilinz"
    ],
    "name:zho_x_preferred": [
      "桂林"
    ],
    "name:zho_x_variant": [
      "桂林镇",
      "桂林市"
    ],
    "wof:name": "Guilin",
    "wof:placetype": "locality"
  },
  "geometry": {
    "coordinates": [
      118.46802,
      29.922
    ],
    "type": "Point"
  }
}