{
  "type": "Feature",
  "properties": {
    "gn:admin1_code": "19.0",
    "gn:asciiname": "Zhujiagou",
    "gn:country_code": "CN",
    "gn:dem": 74,
    "gn:feature_class": "P",
    "gn:feature_code": "PPL",
    "gn:name": "Zhujiagou",
    "gn:population": 0,
    "gn:timezone": "Asia/Shanghai",
    "iso:country": "CN",
    "name:zho_x_preferred": [
      "祝家沟"
    ],
    "wof:name": "Zhujiagou",
    "wof:placetype": "locality"
  },
  "geometry": {
    "coordinates": [
      122.77,
      39.7982
    ],
    "type": "Point"
  }
}