{
  "type": "Feature",
  "properties": {
    "gn:admin1_code": "10",
    "gn:asciiname": "Huashugoumen",
    "gn:country_code": "CN",
    "gn:dem": 466,
    "gn:feature_class": "P",
    "gn:feature_code": "PPL",
    "gn:name": "Huashugoumen",
    "gn:population": 0,
    "gn:timezone": "Asia/Shanghai",
    "iso:country": "CN",
    "name:zho_x_preferred": [
      "桦树沟门"
    ],
    "wof:name": "Huashugoumen",
    "wof:placetype": "locality"
  },
  "geometry": {
    "coordinates": [
      117.79762,
      40.68565
    ],
    "type": "Point"
  }
}