{
  "type": "Feature",
  "properties": {
    "gn:country": "CN",
    "gn:fcode": "PPL",
    "gn:population": 0,
    "iso:country": "CN",
    "name:und_x_variant": [
      "Yushu"
    ],
    "qs:name": "结古",
    "qs:name_adm0": "中國",
    "qs:name_adm1": "青海省",
    "qs:photos": 151,
    "qs:photos_1k": 31,
    "qs:photos_9k": 1,
    "qs:photos_9r": 4,
    "qs:photos_all": 151,
    "qs:photos_sr": 4,
    "qs:placetype": "Town",
    "qs:pop_sr": "4",
    "wof:name": "结古",
    "wof:placetype": "locality",
    "wof:population": 0
  },
  "geometry": {
    "coordinates": [
      97.00893,
      33.00118
    ],
    "type": "Point"
  }
}