{
  "type": "Feature",
  "properties": {
    "gn:admin1_code": "10",
    "gn:asciiname": "Lianggen",
    "gn:country_code": "CN",
    "gn:dem": 608,
    "gn:feature_class": "P",
    "gn:feature_code": "PPL",
    "gn:name": "Lianggen",
    "gn:population": 0,
    "gn:timezone": "Asia/Shanghai",
    "iso:country": "CN",
    "name:zho_x_preferred": [
      "梁根"
    ],
    "wof:name": "Lianggen",
    "wof:placetype": "locality"
  },
  "geometry": {
    "coordinates": [
      117.91036,
      40.62327
    ],
    "type": "Point"
  }
}