{
  "type": "Feature",
  "properties": {
    "gn:admin1_code": "2.0",
    "gn:asciiname": "Liujiatang",
    "gn:country_code": "CN",
    "gn:dem": 64,
    "gn:feature_class": "P",
    "gn:feature_code": "PPL",
    "gn:name": "Liujiatang",
    "gn:population": 0,
    "gn:timezone": "Asia/Shanghai",
    "iso:country": "CN",
    "name:und_x_variant": [
      "刘家塘"
    ],
    "wof:name": "Liujiatang",
    "wof:placetype": "locality"
  },
  "geometry": {
    "coordinates": [
      119.59301,
      30.57097000000001
    ],
    "type": "Point"
  }
}