{
  "type": "Feature",
  "properties": {
    "gn:admin1_code": "12.0",
    "gn:asciiname": "Dongyukou",
    "gn:country_code": "CN",
    "gn:dem": 502,
    "gn:feature_class": "P",
    "gn:feature_code": "PPL",
    "gn:name": "Dongyukou",
    "gn:population": 0,
    "gn:timezone": "Asia/Shanghai",
    "iso:country": "CN",
    "name:zho_x_preferred": [
      "东于口"
    ],
    "wof:name": "Dongyukou",
    "wof:placetype": "locality"
  },
  "geometry": {
    "coordinates": [
      110.29275,
      31.30831
    ],
    "type": "Point"
  }
}