{
  "type": "Feature",
  "properties": {
    "gn:admin1_code": "10",
    "gn:asciiname": "Dahei Goumen",
    "gn:country_code": "CN",
    "gn:dem": 666,
    "gn:feature_class": "P",
    "gn:feature_code": "PPL",
    "gn:name": "Dahei Goumen",
    "gn:population": 0,
    "gn:timezone": "Asia/Shanghai",
    "iso:country": "CN",
    "name:zho_x_preferred": [
      "大黑沟门"
    ],
    "wof:name": "Dahei Goumen",
    "wof:placetype": "locality"
  },
  "geometry": {
    "coordinates": [
      117.75809,
      41.59095
    ],
    "type": "Point"
  }
}