{
  "type": "Feature",
  "properties": {
    "gn:admin1_code": "30",
    "gn:asciiname": "Xincuo",
    "gn:country_code": "CN",
    "gn:dem": 4,
    "gn:feature_class": "P",
    "gn:feature_code": "PPL",
    "gn:name": "Xincuo",
    "gn:population": 0,
    "gn:timezone": "Asia/Shanghai",
    "iso:country": "CN",
    "name:zho_x_preferred": [
      "新厝"
    ],
    "wof:name": "Xincuo",
    "wof:placetype": "locality"
  },
  "geometry": {
    "coordinates": [
      116.40077,
      23.32727
    ],
    "type": "Point"
  }
}