{
  "type": "Feature",
  "properties": {
    "gn:admin1_code": "7",
    "gn:asciiname": "Luopu",
    "gn:country_code": "CN",
    "gn:dem": 597,
    "gn:feature_class": "P",
    "gn:feature_code": "PPL",
    "gn:name": "Luopu",
    "gn:population": 0,
    "gn:timezone": "Asia/Shanghai",
    "iso:country": "CN",
    "name:zho_x_preferred": [
      "罗埔"
    ],
    "wof:name": "Luopu",
    "wof:placetype": "locality"
  },
  "geometry": {
    "coordinates": [
      118.805,
      25.49028
    ],
    "type": "Point"
  }
}