{
  "type": "Feature",
  "properties": {
    "gn:country": "CN",
    "gn:fcode": "PPLA4",
    "gn:population": 7071,
    "iso:country": "CN",
    "name:ceb_x_preferred": [
      "Ninghe Xian"
    ],
    "name:cym_x_preferred": [
      "Ardal Ninghe"
    ],
    "name:deu_x_preferred": [
      "Ninghe"
    ],
    "name:eng_x_preferred": [
      "Ninghe District"
    ],
    "name:eus_x_preferred": [
      "Ninghe konderria"
    ],
    "name:fas_x_preferred": [
      "شهرستان نینگهه"
    ],
    "name:gan_x_preferred": [
      "宁河区"
    ],
    "name:jpn_x_preferred": [
      "寧河区"
    ],
    "name:kor_x_preferred": [
      "닝허구"
    ],
    "name:nan_x_preferred": [
      "Lêng-hô-khu"
    ],
    "name:nld_x_preferred": [
      "Ninghe"
    ],
    "name:nob_x_preferred": [
      "Ninghe"
    ],
    "name:rus_x_preferred": [
      "Нинхэ"
    ],
    "name:swe_x_preferred": [
      "Ninghe"
    ],
    "name:und_x_variant": [
      "Zaojiacheng Zhen"
    ],
    "name:urd_x_preferred": [
      "نینگہے ضلع"
    ],
    "name:vie_x_preferred": [
      "Ninh Hà"
    ],
    "name:wuu_x_preferred": [
      "宁河区"
    ],
    "name:zho_x_preferred": [
      "造甲城"
    ],
    "name:zho_x_variant": [
      "造甲城镇",
      "宁河区"
    ],
    "qs:name": "Zaojiacheng",
    "qs:photos_9r": 0,
    "qs:photos_sr": 0,
    "qs:pop_sr": "5",
    "wd:wordcount": 173,
    "wof:name": "Zaojiacheng",
    "wof:placetype": "locality",
    "wof:population": 7071
  },
  "geometry": {
    "coordinates": [
      117.43574,
      39.27706
    ],
    "type": "Point"
  }
}