{
  "type": "Feature",
  "properties": {
    "gn:admin1_code": "15.0",
    "gn:asciiname": "Liushuwan",
    "gn:country_code": "CN",
    "gn:dem": 2107,
    "gn:feature_class": "P",
    "gn:feature_code": "PPL",
    "gn:name": "Liushuwan",
    "gn:population": 0,
    "gn:timezone": "Asia/Shanghai",
    "iso:country": "CN",
    "name:zho_x_preferred": [
      "柳树湾"
    ],
    "wof:name": "Liushuwan",
    "wof:placetype": "locality"
  },
  "geometry": {
    "coordinates": [
      104.216,
      35.758
    ],
    "type": "Point"
  }
}