{
  "type": "Feature",
  "properties": {
    "gn:admin1_code": "2.0",
    "gn:asciiname": "Tangkeng",
    "gn:country_code": "CN",
    "gn:dem": 214,
    "gn:feature_class": "P",
    "gn:feature_code": "PPL",
    "gn:name": "Tangkeng",
    "gn:population": 0,
    "gn:timezone": "Asia/Shanghai",
    "iso:country": "CN",
    "name:zho_x_preferred": [
      "塘坑"
    ],
    "name:zho_x_variant": [
      "汤坑镇"
    ],
    "wof:name": "Tangkeng",
    "wof:placetype": "locality"
  },
  "geometry": {
    "coordinates": [
      120.62579,
      28.11307
    ],
    "type": "Point"
  }
}