{
  "type": "Feature",
  "properties": {
    "gn:admin1_code": "26.0",
    "gn:asciiname": "Zhoujia Dayuanzi",
    "gn:country_code": "CN",
    "gn:dem": 671,
    "gn:feature_class": "P",
    "gn:feature_code": "PPL",
    "gn:name": "Zhoujia Dayuanzi",
    "gn:population": 0,
    "gn:timezone": "Asia/Shanghai",
    "iso:country": "CN",
    "name:zho_x_preferred": [
      "周家大院子"
    ],
    "wof:name": "Zhoujia Dayuanzi",
    "wof:placetype": "locality"
  },
  "geometry": {
    "coordinates": [
      109.7845,
      32.70732
    ],
    "type": "Point"
  }
}