{
  "type": "Feature",
  "properties": {
    "gn:admin1_code": "3.0",
    "gn:asciiname": "Hezhou",
    "gn:country_code": "CN",
    "gn:dem": 84,
    "gn:feature_class": "P",
    "gn:feature_code": "PPL",
    "gn:name": "Hezhou",
    "gn:population": 0,
    "gn:timezone": "Asia/Shanghai",
    "iso:country": "CN",
    "name:afr_x_preferred": [
      "Hezhou"
    ],
    "name:ara_x_preferred": [
      "هيشو"
    ],
    "name:cat_x_preferred": [
      "Hezhou"
    ],
    "name:cdo_x_preferred": [
      "Hô̤-ciŭ"
    ],
    "name:ces_x_preferred": [
      "Che-čou"
    ],
    "name:dan_x_preferred": [
      "Hezhou"
    ],
    "name:deu_x_preferred": [
      "Hezhou"
    ],
    "name:eus_x_preferred": [
      "Hezhou"
    ],
    "name:fas_x_preferred": [
      "هیژو"
    ],
    "name:fin_x_preferred": [
      "Hezhou"
    ],
    "name:fra_x_preferred": [
      "Hezhou"
    ],
    "name:hak_x_preferred": [
      "Fo-chû-sṳ"
    ],
    "name:ita_x_preferred": [
      "Hezhou"
    ],
    "name:jpn_x_preferred": [
      "賀州市"
    ],
    "name:kik_x_preferred": [
      "Hezhou"
    ],
    "name:kor_x_preferred": [
      "허저우시"
    ],
    "name:nld_x_preferred": [
      "Hezhou"
    ],
    "name:nor_x_preferred": [
      "Hezhou"
    ],
    "name:pnb_x_preferred": [
      "ہیژوؤ"
    ],
    "name:pol_x_preferred": [
      "Hezhou"
    ],
    "name:por_x_preferred": [
      "Hezhou"
    ],
    "name:rus_x_preferred": [
      "Хэчжоу"
    ],
    "name:spa_x_preferred": [
      "Hezhou"
    ],
    "name:swe_x_preferred": [
      "Hezhou"
    ],
    "name:tur_x_preferred": [
      "Hezhou"
    ],
    "name:ukr_x_preferred": [
      "Хечжоу"
    ],
    "name:und_x_variant": [
      "荷洲"
    ],
    "name:urd_x_preferred": [
      "ہیژوو"
    ],
    "name:vie_x_preferred": [
      "Hạ Châu"
    ],
    "name:zha_x_preferred": [
      "Hohcouh"
    ],
    "name:zho_x_preferred": [
      "贺州市"
    ],
    "wof:name": "Hezhou",
    "wof:placetype": "locality"
  },
  "geometry": {
    "coordinates": [
      115.16346,
      29.45188
    ],
    "type": "Point"
  }
}