{
  "type": "Feature",
  "properties": {
    "gn:admin1_code": "30",
    "gn:asciiname": "Ganzi Shuxia",
    "gn:country_code": "CN",
    "gn:dem": 225,
    "gn:feature_class": "P",
    "gn:feature_code": "PPL",
    "gn:name": "Ganzi Shuxia",
    "gn:population": 0,
    "gn:timezone": "Asia/Shanghai",
    "iso:country": "CN",
    "name:zho_x_preferred": [
      "柑子树下"
    ],
    "wof:name": "Ganzi Shuxia",
    "wof:placetype": "locality"
  },
  "geometry": {
    "coordinates": [
      115.8148,
      24.3998
    ],
    "type": "Point"
  }
}