{
  "type": "Feature",
  "properties": {
    "gn:admin1_code": "08",
    "gn:asciiname": "Shangji",
    "gn:country_code": "CN",
    "gn:dem": 207,
    "gn:feature_class": "P",
    "gn:feature_code": "PPLA4",
    "gn:name": "Shangji",
    "gn:population": 0,
    "gn:timezone": "Asia/Shanghai",
    "iso:country": "CN",
    "name:und_x_variant": [
      "Chiu-sui-leng",
      "Shang-chi",
      "Shang-chi-ch’ang",
      "Sui-leng",
      "Shangji",
      "Shangji Zhen"
    ],
    "name:zho_x_preferred": [
      "上集"
    ],
    "name:zho_x_variant": [
      "上集镇"
    ],
    "wof:name": "Shangji",
    "wof:placetype": "locality"
  },
  "geometry": {
    "coordinates": [
      127.32153,
      47.15215
    ],
    "type": "Point"
  }
}