{
  "type": "Feature",
  "properties": {
    "gn:admin1_code": "14.0",
    "gn:asciiname": "Duoqiong",
    "gn:country_code": "CN",
    "gn:dem": 4680,
    "gn:feature_class": "P",
    "gn:feature_code": "PPL",
    "gn:name": "Duoqiong",
    "gn:population": 0,
    "gn:timezone": "Asia/Urumqi",
    "iso:country": "CN",
    "name:zho_x_preferred": [
      "躲穷"
    ],
    "wof:name": "Duoqiong",
    "wof:placetype": "locality"
  },
  "geometry": {
    "coordinates": [
      85.8074,
      29.0964
    ],
    "type": "Point"
  }
}