{
  "type": "Feature",
  "properties": {
    "gn:admin1_code": "31.0",
    "gn:asciiname": "Luoding",
    "gn:country_code": "CN",
    "gn:dem": 6,
    "gn:feature_class": "P",
    "gn:feature_code": "PPL",
    "gn:name": "Luoding",
    "gn:population": 0,
    "gn:timezone": "Asia/Shanghai",
    "iso:country": "CN",
    "name:ara_x_preferred": [
      "لودينغ"
    ],
    "name:deu_x_preferred": [
      "Luoding"
    ],
    "name:fas_x_preferred": [
      "لودینگ"
    ],
    "name:fra_x_preferred": [
      "Luoding"
    ],
    "name:ita_x_preferred": [
      "Luoding"
    ],
    "name:jpn_x_preferred": [
      "羅定市"
    ],
    "name:kik_x_preferred": [
      "Luoding"
    ],
    "name:kor_x_preferred": [
      "뤄딩시"
    ],
    "name:mwl_x_preferred": [
      "Luoding"
    ],
    "name:nld_x_preferred": [
      "Luoding"
    ],
    "name:nor_x_preferred": [
      "Luoding"
    ],
    "name:pam_x_preferred": [
      "Luoding"
    ],
    "name:pnb_x_preferred": [
      "لوؤڈینگ"
    ],
    "name:swe_x_preferred": [
      "Luoding"
    ],
    "name:urd_x_preferred": [
      "لؤودنگ"
    ],
    "name:vie_x_preferred": [
      "La Định"
    ],
    "name:zho_x_preferred": [
      "Luoding"
    ],
    "name:zho_x_variant": [
      "罗丁",
      "罗定市"
    ],
    "wof:name": "Luoding",
    "wof:placetype": "locality"
  },
  "geometry": {
    "coordinates": [
      110.55687,
      19.97221
    ],
    "type": "Point"
  }
}