{
  "type": "Feature",
  "properties": {
    "gn:admin1_code": "4.0",
    "gn:asciiname": "Pushan",
    "gn:country_code": "CN",
    "gn:dem": 2,
    "gn:feature_class": "P",
    "gn:feature_code": "PPL",
    "gn:name": "Pushan",
    "gn:population": 0,
    "gn:timezone": "Asia/Shanghai",
    "iso:country": "CN",
    "name:als_x_preferred": [
      "Pushan"
    ],
    "name:deu_x_preferred": [
      "Pushan"
    ],
    "name:fra_x_preferred": [
      "Pushan"
    ],
    "name:jpn_x_preferred": [
      "プーシャン"
    ],
    "name:lit_x_preferred": [
      "Pūšanas"
    ],
    "name:pol_x_preferred": [
      "Puszan"
    ],
    "name:por_x_preferred": [
      "Puchan"
    ],
    "name:rus_x_preferred": [
      "Пушан"
    ],
    "name:spa_x_preferred": [
      "Pushán"
    ],
    "name:swe_x_preferred": [
      "Pushan"
    ],
    "name:zho_x_preferred": [
      "Pushan"
    ],
    "name:zho_x_variant": [
      "普山"
    ],
    "wof:name": "Pushan",
    "wof:placetype": "locality"
  },
  "geometry": {
    "coordinates": [
      119.27585,
      34.57623
    ],
    "type": "Point"
  }
}