{
  "type": "Feature",
  "properties": {
    "gn:admin1_code": "3.0",
    "gn:asciiname": "Yangchun",
    "gn:country_code": "CN",
    "gn:dem": 311,
    "gn:feature_class": "P",
    "gn:feature_code": "PPL",
    "gn:name": "Yangchun",
    "gn:population": 0,
    "gn:timezone": "Asia/Shanghai",
    "iso:country": "CN",
    "name:ara_x_preferred": [
      "يانغشون"
    ],
    "name:ceb_x_preferred": [
      "Yangchun"
    ],
    "name:deu_x_preferred": [
      "Yangchun"
    ],
    "name:fas_x_preferred": [
      "یانگچون"
    ],
    "name:fra_x_preferred": [
      "Yangchun"
    ],
    "name:hak_x_preferred": [
      "Yòng-chhûn-sṳ"
    ],
    "name:ita_x_preferred": [
      "Yangchun"
    ],
    "name:jpn_x_preferred": [
      "陽春市"
    ],
    "name:kik_x_preferred": [
      "Yangchun"
    ],
    "name:kor_x_preferred": [
      "양춘시"
    ],
    "name:mlg_x_preferred": [
      "Yangchun"
    ],
    "name:mwl_x_preferred": [
      "Yangchun"
    ],
    "name:nld_x_preferred": [
      "Yangchun"
    ],
    "name:nor_x_preferred": [
      "Yangchun"
    ],
    "name:pam_x_preferred": [
      "Yangchun"
    ],
    "name:pnb_x_preferred": [
      "یانگچن"
    ],
    "name:swe_x_preferred": [
      "Yangchun"
    ],
    "name:und_x_variant": [
      "阳春"
    ],
    "name:urd_x_preferred": [
      "ینگچن"
    ],
    "name:vie_x_preferred": [
      "Dương Xuân"
    ],
    "name:zho_x_preferred": [
      "阳春市"
    ],
    "wof:name": "Yangchun",
    "wof:placetype": "locality"
  },
  "geometry": {
    "coordinates": [
      114.12549,
      27.26753
    ],
    "type": "Point"
  }
}