{
  "type": "Feature",
  "properties": {
    "gn:admin1_code": "11",
    "gn:asciiname": "Huangshi",
    "gn:country_code": "CN",
    "gn:dem": 226,
    "gn:feature_class": "P",
    "gn:feature_code": "PPL",
    "gn:name": "Huangshi",
    "gn:population": 0,
    "gn:timezone": "Asia/Shanghai",
    "iso:country": "CN",
    "name:afr_x_preferred": [
      "Huangshi"
    ],
    "name:ara_x_preferred": [
      "هوانغشي"
    ],
    "name:bul_x_preferred": [
      "Хуаншъ"
    ],
    "name:cdo_x_preferred": [
      "Uòng-siŏh"
    ],
    "name:ces_x_preferred": [
      "Chuang-š'"
    ],
    "name:dan_x_preferred": [
      "Huangshi"
    ],
    "name:deu_x_preferred": [
      "Huangshi"
    ],
    "name:epo_x_preferred": [
      "Huangŝi"
    ],
    "name:eus_x_preferred": [
      "Huangshi"
    ],
    "name:fas_x_preferred": [
      "هوانگشی"
    ],
    "name:fin_x_preferred": [
      "Huangshi"
    ],
    "name:fra_x_preferred": [
      "Huangshi"
    ],
    "name:ind_x_preferred": [
      "Huangshi"
    ],
    "name:ita_x_preferred": [
      "Huangshi"
    ],
    "name:jpn_x_preferred": [
      "黄石"
    ],
    "name:jpn_x_variant": [
      "黄石市"
    ],
    "name:kik_x_preferred": [
      "Huangshi"
    ],
    "name:kor_x_preferred": [
      "황스시"
    ],
    "name:lit_x_preferred": [
      "Huangši"
    ],
    "name:mlg_x_preferred": [
      "Huangshi"
    ],
    "name:nld_x_preferred": [
      "Huangshi"
    ],
    "name:nno_x_preferred": [
      "Huangshi"
    ],
    "name:nor_x_preferred": [
      "Huangshi"
    ],
    "name:pam_x_preferred": [
      "Huangshi"
    ],
    "name:pol_x_preferred": [
      "Huangshi"
    ],
    "name:por_x_preferred": [
      "Huangshi"
    ],
    "name:rus_x_preferred": [
      "Хуанши"
    ],
    "name:spa_x_preferred": [
      "Huangshi"
    ],
    "name:srp_x_preferred": [
      "Хуангши"
    ],
    "name:swe_x_preferred": [
      "Huangshi"
    ],
    "name:tgl_x_preferred": [
      "Huangshi"
    ],
    "name:tur_x_preferred": [
      "Huangshi"
    ],
    "name:uig_x_preferred": [
      "خۇئاڭشى شەھىرى"
    ],
    "name:urd_x_preferred": [
      "ہوانگشی"
    ],
    "name:vie_x_preferred": [
      "Hoàng Thạch"
    ],
    "name:war_x_preferred": [
      "Huangshi"
    ],
    "name:zho_x_preferred": [
      "黄石市"
    ],
    "wof:name": "Huangshi",
    "wof:placetype": "locality"
  },
  "geometry": {
    "coordinates": [
      112.94583,
      26.22778
    ],
    "type": "Point"
  }
}