{
  "type": "Feature",
  "properties": {
    "gn:admin1_code": "12.0",
    "gn:asciiname": "Henao",
    "gn:country_code": "CN",
    "gn:dem": 42,
    "gn:feature_class": "P",
    "gn:feature_code": "PPL",
    "gn:name": "Henao",
    "gn:population": 0,
    "gn:timezone": "Asia/Shanghai",
    "iso:country": "CN",
    "name:und_x_variant": [
      "河垴"
    ],
    "wof:name": "Henao",
    "wof:placetype": "locality"
  },
  "geometry": {
    "coordinates": [
      114.26829,
      30.06978
    ],
    "type": "Point"
  }
}