{
  "type": "Feature",
  "properties": {
    "gn:admin1_code": "16.0",
    "gn:asciiname": "Yiwu",
    "gn:country_code": "CN",
    "gn:dem": 260,
    "gn:feature_class": "P",
    "gn:feature_code": "PPL",
    "gn:name": "Yiwu",
    "gn:population": 0,
    "gn:timezone": "Asia/Shanghai",
    "iso:country": "CN",
    "name:ara_x_preferred": [
      "ييوو"
    ],
    "name:cat_x_preferred": [
      "Yiwu"
    ],
    "name:ceb_x_preferred": [
      "Yiwu"
    ],
    "name:ces_x_preferred": [
      "I-wu"
    ],
    "name:deu_x_preferred": [
      "Yiwu"
    ],
    "name:fas_x_preferred": [
      "ایوو"
    ],
    "name:fra_x_preferred": [
      "Yiwu"
    ],
    "name:heb_x_preferred": [
      "יי-וו"
    ],
    "name:hin_x_preferred": [
      "यीवू"
    ],
    "name:ita_x_preferred": [
      "Yiwu"
    ],
    "name:jpn_x_preferred": [
      "義烏市"
    ],
    "name:kik_x_preferred": [
      "Yiwu"
    ],
    "name:kor_x_preferred": [
      "이우시"
    ],
    "name:mlg_x_preferred": [
      "Yiwu"
    ],
    "name:nld_x_preferred": [
      "Yiwu"
    ],
    "name:nor_x_preferred": [
      "Yiwu"
    ],
    "name:pol_x_preferred": [
      "Yiwu"
    ],
    "name:por_x_preferred": [
      "Yìwū"
    ],
    "name:rus_x_preferred": [
      "Иу"
    ],
    "name:spa_x_preferred": [
      "Yiwu"
    ],
    "name:swe_x_preferred": [
      "Yiwu"
    ],
    "name:tgl_x_preferred": [
      "Yiwu"
    ],
    "name:tur_x_preferred": [
      "Yiwu"
    ],
    "name:urd_x_preferred": [
      "یوو"
    ],
    "name:vie_x_preferred": [
      "Nghĩa"
    ],
    "name:war_x_preferred": [
      "Yiwu"
    ],
    "name:wuu_x_preferred": [
      "義烏市"
    ],
    "name:zho_x_preferred": [
      "义伍"
    ],
    "name:zho_x_variant": [
      "义乌市"
    ],
    "wof:name": "Yiwu",
    "wof:placetype": "locality"
  },
  "geometry": {
    "coordinates": [
      111.285,
      24.33
    ],
    "type": "Point"
  }
}