{
  "type": "Feature",
  "properties": {
    "gn:admin1_code": "25",
    "gn:asciiname": "Baishui Niushi Qiancun",
    "gn:country_code": "CN",
    "gn:dem": 80,
    "gn:feature_class": "P",
    "gn:feature_code": "PPL",
    "gn:name": "Baishui Niushi Qiancun",
    "gn:population": 0,
    "gn:timezone": "Asia/Shanghai",
    "iso:country": "CN",
    "name:zho_x_preferred": [
      "白水牛石前村"
    ],
    "wof:name": "Baishui Niushi Qiancun",
    "wof:placetype": "locality"
  },
  "geometry": {
    "coordinates": [
      117.817,
      34.8523
    ],
    "type": "Point"
  }
}