{
  "type": "Feature",
  "properties": {
    "gn:admin1_code": "10",
    "gn:asciiname": "Haojiagou",
    "gn:country_code": "CN",
    "gn:dem": 517,
    "gn:feature_class": "P",
    "gn:feature_code": "PPL",
    "gn:name": "Haojiagou",
    "gn:population": 0,
    "gn:timezone": "Asia/Shanghai",
    "iso:country": "CN",
    "name:zho_x_preferred": [
      "郝家沟"
    ],
    "wof:name": "Haojiagou",
    "wof:placetype": "locality"
  },
  "geometry": {
    "coordinates": [
      118.30064,
      40.99744000000001
    ],
    "type": "Point"
  }
}