{
  "type": "Feature",
  "properties": {
    "gn:admin1_code": "4.0",
    "gn:asciiname": "Tangdong",
    "gn:country_code": "CN",
    "gn:dem": 3,
    "gn:feature_class": "P",
    "gn:feature_code": "PPL",
    "gn:name": "Tangdong",
    "gn:population": 0,
    "gn:timezone": "Asia/Shanghai",
    "iso:country": "CN",
    "name:und_x_variant": [
      "Tangdongcun",
      "Tangdong",
      "塘东"
    ],
    "name:zho_x_preferred": [
      "塘东村"
    ],
    "name:zho_x_variant": [
      "唐洞街道"
    ],
    "wof:name": "Tangdong",
    "wof:placetype": "locality"
  },
  "geometry": {
    "coordinates": [
      121.04875,
      31.52777
    ],
    "type": "Point"
  }
}