{
  "type": "Feature",
  "properties": {
    "gn:admin1_code": "7.0",
    "gn:asciiname": "Xinzheng",
    "gn:country_code": "CN",
    "gn:dem": 69,
    "gn:feature_class": "P",
    "gn:feature_code": "PPL",
    "gn:name": "Xinzheng",
    "gn:population": 0,
    "gn:timezone": "Asia/Shanghai",
    "iso:country": "CN",
    "name:amh_x_preferred": [
      "ሺንዠንግ"
    ],
    "name:deu_x_preferred": [
      "Xinzheng"
    ],
    "name:eus_x_preferred": [
      "Xinzheng"
    ],
    "name:fra_x_preferred": [
      "Xinzheng"
    ],
    "name:ind_x_preferred": [
      "Xinzheng"
    ],
    "name:ita_x_preferred": [
      "Xinzheng"
    ],
    "name:jpn_x_preferred": [
      "新鄭市"
    ],
    "name:kik_x_preferred": [
      "Xinzheng"
    ],
    "name:kor_x_preferred": [
      "신정시"
    ],
    "name:mlg_x_preferred": [
      "Xinzheng"
    ],
    "name:nor_x_preferred": [
      "Xinzheng"
    ],
    "name:pam_x_preferred": [
      "Xinzheng"
    ],
    "name:pol_x_preferred": [
      "Xinzheng"
    ],
    "name:rus_x_preferred": [
      "Синьчжэн"
    ],
    "name:spa_x_preferred": [
      "Xinzheng"
    ],
    "name:swe_x_preferred": [
      "Xinzheng"
    ],
    "name:urd_x_preferred": [
      "شینژینگ"
    ],
    "name:vie_x_preferred": [
      "Tân Trịnh"
    ],
    "name:zho_x_preferred": [
      "新郑"
    ],
    "name:zho_x_variant": [
      "新郑市"
    ],
    "wof:name": "Xinzheng",
    "wof:placetype": "locality"
  },
  "geometry": {
    "coordinates": [
      118.77971,
      25.43407
    ],
    "type": "Point"
  }
}