{
  "type": "Feature",
  "properties": {
    "gn:admin1_code": "8.0",
    "gn:asciiname": "Wuyi",
    "gn:country_code": "CN",
    "gn:dem": 287,
    "gn:feature_class": "P",
    "gn:feature_code": "PPL",
    "gn:name": "Wuyi",
    "gn:population": 0,
    "gn:timezone": "Asia/Shanghai",
    "iso:country": "CN",
    "name:ceb_x_preferred": [
      "Wuyi"
    ],
    "name:deu_x_preferred": [
      "Wuyi"
    ],
    "name:fas_x_preferred": [
      "وو یی"
    ],
    "name:fra_x_preferred": [
      "Wuyi"
    ],
    "name:kor_x_preferred": [
      "우이현"
    ],
    "name:nor_x_preferred": [
      "Wuyi"
    ],
    "name:swe_x_preferred": [
      "Wuyi"
    ],
    "name:zho_x_preferred": [
      "五一"
    ],
    "wof:name": "Wuyi",
    "wof:placetype": "locality"
  },
  "geometry": {
    "coordinates": [
      127.97928,
      47.67748
    ],
    "type": "Point"
  }
}