{
  "type": "Feature",
  "properties": {
    "gn:admin1_code": "19.0",
    "gn:asciiname": "Gaohuawobu",
    "gn:country_code": "CN",
    "gn:dem": 225,
    "gn:feature_class": "P",
    "gn:feature_code": "PPL",
    "gn:name": "Gaohuawobu",
    "gn:population": 0,
    "gn:timezone": "Asia/Shanghai",
    "iso:country": "CN",
    "name:zho_x_preferred": [
      "高花窝堡"
    ],
    "wof:name": "Gaohuawobu",
    "wof:placetype": "locality"
  },
  "geometry": {
    "coordinates": [
      122.398,
      42.6949
    ],
    "type": "Point"
  }
}