{
  "type": "Feature",
  "properties": {
    "gn:admin1_code": "2.0",
    "gn:asciiname": "Xiaogang",
    "gn:country_code": "CN",
    "gn:dem": 9,
    "gn:feature_class": "P",
    "gn:feature_code": "PPL",
    "gn:name": "Xiaogang",
    "gn:population": 0,
    "gn:timezone": "Asia/Shanghai",
    "iso:country": "CN",
    "name:ces_x_preferred": [
      "Siao-kang"
    ],
    "name:deu_x_preferred": [
      "Xiaogang"
    ],
    "name:fra_x_preferred": [
      "Xiaogang"
    ],
    "name:zho_x_preferred": [
      "小港"
    ],
    "wof:name": "Xiaogang",
    "wof:placetype": "locality"
  },
  "geometry": {
    "coordinates": [
      120.86275,
      28.01191
    ],
    "type": "Point"
  }
}