{
  "type": "Feature",
  "properties": {
    "gn:admin1_code": "10",
    "gn:asciiname": "Xidi",
    "gn:country_code": "CN",
    "gn:dem": 439,
    "gn:feature_class": "P",
    "gn:feature_code": "PPL",
    "gn:name": "Xidi",
    "gn:population": 0,
    "gn:timezone": "Asia/Shanghai",
    "iso:country": "CN",
    "name:ara_x_preferred": [
      "شيدي"
    ],
    "name:ast_x_preferred": [
      "Xidi"
    ],
    "name:ces_x_preferred": [
      "Si-ti"
    ],
    "name:eus_x_preferred": [
      "Xidi"
    ],
    "name:fas_x_preferred": [
      "شیدی"
    ],
    "name:fin_x_preferred": [
      "Xidi"
    ],
    "name:fra_x_preferred": [
      "Xidi"
    ],
    "name:heb_x_preferred": [
      "שידי"
    ],
    "name:hrv_x_preferred": [
      "Xidi"
    ],
    "name:ita_x_preferred": [
      "Xidi"
    ],
    "name:jpn_x_preferred": [
      "西逓村"
    ],
    "name:kat_x_preferred": [
      "სიდი"
    ],
    "name:kor_x_preferred": [
      "시디춘"
    ],
    "name:mal_x_preferred": [
      "ഷീദി"
    ],
    "name:nld_x_preferred": [
      "Xidi"
    ],
    "name:nor_x_preferred": [
      "Xidi"
    ],
    "name:por_x_preferred": [
      "Xidi"
    ],
    "name:slk_x_preferred": [
      "Si-ti"
    ],
    "name:spa_x_preferred": [
      "Xidi"
    ],
    "name:swe_x_preferred": [
      "Xidi"
    ],
    "name:tur_x_preferred": [
      "Xidi"
    ],
    "name:vie_x_preferred": [
      "Tây Đệ"
    ],
    "name:zho_x_preferred": [
      "西地"
    ],
    "name:zho_x_variant": [
      "西递村"
    ],
    "wof:name": "Xidi",
    "wof:placetype": "locality"
  },
  "geometry": {
    "coordinates": [
      118.01093,
      41.15093
    ],
    "type": "Point"
  }
}