{
  "type": "Feature",
  "properties": {
    "gn:admin1_code": "9.0",
    "gn:asciiname": "Qianxi",
    "gn:country_code": "CN",
    "gn:dem": 57,
    "gn:feature_class": "P",
    "gn:feature_code": "PPL",
    "gn:name": "Qianxi",
    "gn:population": 0,
    "gn:timezone": "Asia/Shanghai",
    "iso:country": "CN",
    "name:ceb_x_preferred": [
      "Qianxi"
    ],
    "name:deu_x_preferred": [
      "Qianxi"
    ],
    "name:fra_x_preferred": [
      "Qianxi"
    ],
    "name:kor_x_preferred": [
      "첸시현"
    ],
    "name:nor_x_preferred": [
      "Qianxi"
    ],
    "name:swe_x_preferred": [
      "Qianxi"
    ],
    "name:zho_x_preferred": [
      "前席"
    ],
    "wof:name": "Qianxi",
    "wof:placetype": "locality"
  },
  "geometry": {
    "coordinates": [
      114.27612,
      33.81952
    ],
    "type": "Point"
  }
}