{
  "type": "Feature",
  "properties": {
    "gn:admin1_code": "8.0",
    "gn:asciiname": "Gonghecun",
    "gn:country_code": "CN",
    "gn:dem": 214,
    "gn:feature_class": "P",
    "gn:feature_code": "PPL",
    "gn:name": "Gonghecun",
    "gn:population": 0,
    "gn:timezone": "Asia/Shanghai",
    "iso:country": "CN",
    "name:zho_x_preferred": [
      "共合村"
    ],
    "wof:name": "Gonghecun",
    "wof:placetype": "locality"
  },
  "geometry": {
    "coordinates": [
      127.3678,
      47.32001
    ],
    "type": "Point"
  }
}