{
  "type": "Feature",
  "properties": {
    "iso:country": "CN",
    "name:eng_x_preferred": [
      "Chongdui"
    ],
    "name:zho_x_preferred": [
      "冲堆"
    ],
    "qs:name": "冲堆",
    "qs:name_adm0": "中國",
    "qs:name_adm1": "西藏自治区",
    "qs:photos": 23,
    "qs:photos_1k": 5,
    "qs:photos_9k": 1,
    "qs:photos_9r": 1,
    "qs:photos_all": 23,
    "qs:photos_sr": 1,
    "qs:placetype": "Town",
    "qs:pop_sr": "0",
    "wof:name": "Chongdui",
    "wof:placetype": "locality"
  },
  "geometry": {
    "coordinates": [
      85.97852,
      28.14517
    ],
    "type": "Point"
  }
}