{
  "type": "Feature",
  "properties": {
    "gn:admin1_code": "32.0",
    "gn:asciiname": "Shihuopen",
    "gn:country_code": "CN",
    "gn:dem": 341,
    "gn:feature_class": "P",
    "gn:feature_code": "PPL",
    "gn:name": "Shihuopen",
    "gn:population": 0,
    "gn:timezone": "Asia/Shanghai",
    "iso:country": "CN",
    "name:zho_x_preferred": [
      "石火盆"
    ],
    "wof:name": "Shihuopen",
    "wof:placetype": "locality"
  },
  "geometry": {
    "coordinates": [
      103.8422,
      29.32432
    ],
    "type": "Point"
  }
}