{
  "type": "Feature",
  "properties": {
    "gn:admin1_code": "1.0",
    "gn:asciiname": "Jinqiaocun",
    "gn:country_code": "CN",
    "gn:dem": 139,
    "gn:feature_class": "P",
    "gn:feature_code": "PPL",
    "gn:name": "Jinqiaocun",
    "gn:population": 0,
    "gn:timezone": "Asia/Shanghai",
    "iso:country": "CN",
    "name:zho_x_preferred": [
      "金桥村"
    ],
    "wof:name": "Jinqiaocun",
    "wof:placetype": "locality"
  },
  "geometry": {
    "coordinates": [
      115.7425,
      31.54747
    ],
    "type": "Point"
  }
}