{
  "type": "Feature",
  "properties": {
    "gn:admin1_code": "16.0",
    "gn:asciiname": "Pingxiang",
    "gn:country_code": "CN",
    "gn:dem": 656,
    "gn:feature_class": "P",
    "gn:feature_code": "PPL",
    "gn:name": "Pingxiang",
    "gn:population": 0,
    "gn:timezone": "Asia/Shanghai",
    "iso:country": "CN",
    "name:ara_x_preferred": [
      "بينغشيانغ"
    ],
    "name:cdo_x_preferred": [
      "Bìng-hiŏng"
    ],
    "name:ceb_x_preferred": [
      "Pingxiang"
    ],
    "name:ces_x_preferred": [
      "Pching-siang"
    ],
    "name:cym_x_preferred": [
      "Pingxiang"
    ],
    "name:dan_x_preferred": [
      "Pingxiang"
    ],
    "name:deu_x_preferred": [
      "Pingxiang"
    ],
    "name:ell_x_preferred": [
      "Πινγκξιάνγκ"
    ],
    "name:eus_x_preferred": [
      "Pingxiang"
    ],
    "name:fas_x_preferred": [
      "پینگشیانگ"
    ],
    "name:fin_x_preferred": [
      "Pingxiang"
    ],
    "name:fra_x_preferred": [
      "Pingxiang"
    ],
    "name:hak_x_preferred": [
      "Phìn-hiông-sṳ"
    ],
    "name:heb_x_preferred": [
      "פינגקסיאנג"
    ],
    "name:hin_x_preferred": [
      "पिंगक्सियांग"
    ],
    "name:hun_x_preferred": [
      "Pingxiang"
    ],
    "name:ind_x_preferred": [
      "Pingxiang"
    ],
    "name:ita_x_preferred": [
      "Pingxiang"
    ],
    "name:jpn_x_preferred": [
      "萍郷市"
    ],
    "name:kik_x_preferred": [
      "Pingxiang"
    ],
    "name:kor_x_preferred": [
      "핑샹시"
    ],
    "name:mlg_x_preferred": [
      "Pingxiang"
    ],
    "name:nld_x_preferred": [
      "Pingxiang"
    ],
    "name:nno_x_preferred": [
      "Pingxiang"
    ],
    "name:nor_x_preferred": [
      "Pingxiang"
    ],
    "name:pol_x_preferred": [
      "Pingxiang"
    ],
    "name:por_x_preferred": [
      "Pingxiang"
    ],
    "name:rus_x_preferred": [
      "Пинсян"
    ],
    "name:spa_x_preferred": [
      "Pingxiang"
    ],
    "name:srp_x_preferred": [
      "Пингсјанг"
    ],
    "name:swe_x_preferred": [
      "Pingxiang"
    ],
    "name:tur_x_preferred": [
      "Pingxiang"
    ],
    "name:ukr_x_preferred": [
      "Пінсян"
    ],
    "name:urd_x_preferred": [
      "پنگشیانگ"
    ],
    "name:vie_x_preferred": [
      "Bình Hương"
    ],
    "name:war_x_preferred": [
      "Pingxiang"
    ],
    "name:wuu_x_preferred": [
      "萍乡市"
    ],
    "name:zho_x_preferred": [
      "平祥"
    ],
    "name:zho_x_variant": [
      "萍乡市"
    ],
    "wof:name": "Pingxiang",
    "wof:placetype": "locality"
  },
  "geometry": {
    "coordinates": [
      106.963,
      24.4467
    ],
    "type": "Point"
  }
}