{
  "type": "Feature",
  "properties": {
    "gn:admin1_code": "25",
    "gn:asciiname": "Shiqiaogoudong",
    "gn:country_code": "CN",
    "gn:dem": 31,
    "gn:feature_class": "P",
    "gn:feature_code": "PPL",
    "gn:name": "Shiqiaogoudong",
    "gn:population": 0,
    "gn:timezone": "Asia/Shanghai",
    "iso:country": "CN",
    "name:zho_x_preferred": [
      "石桥沟东"
    ],
    "wof:name": "Shiqiaogoudong",
    "wof:placetype": "locality"
  },
  "geometry": {
    "coordinates": [
      119.789,
      36.9082
    ],
    "type": "Point"
  }
}