{
  "type": "Feature",
  "properties": {
    "gn:admin1_code": "26.0",
    "gn:asciiname": "Hujiachuancun",
    "gn:country_code": "CN",
    "gn:dem": 851,
    "gn:feature_class": "P",
    "gn:feature_code": "PPL",
    "gn:name": "Hujiachuancun",
    "gn:population": 0,
    "gn:timezone": "Asia/Shanghai",
    "iso:country": "CN",
    "name:zho_x_preferred": [
      "呼家川村"
    ],
    "wof:name": "Hujiachuancun",
    "wof:placetype": "locality"
  },
  "geometry": {
    "coordinates": [
      110.05149,
      36.56555
    ],
    "type": "Point"
  }
}