{
  "type": "Feature",
  "properties": {
    "gn:admin1_code": "32.0",
    "gn:asciiname": "Hejiaoqiu",
    "gn:country_code": "CN",
    "gn:dem": 381,
    "gn:feature_class": "P",
    "gn:feature_code": "PPL",
    "gn:name": "Hejiaoqiu",
    "gn:population": 0,
    "gn:timezone": "Asia/Shanghai",
    "iso:country": "CN",
    "name:zho_x_preferred": [
      "河角丘"
    ],
    "wof:name": "Hejiaoqiu",
    "wof:placetype": "locality"
  },
  "geometry": {
    "coordinates": [
      107.288,
      30.5114
    ],
    "type": "Point"
  }
}