{
  "type": "Feature",
  "properties": {
    "gn:admin1_code": "8.0",
    "gn:asciiname": "Dong'ercun",
    "gn:country_code": "CN",
    "gn:dem": 77,
    "gn:feature_class": "P",
    "gn:feature_code": "PPL",
    "gn:name": "Dong’ercun",
    "gn:population": 0,
    "gn:timezone": "Asia/Shanghai",
    "iso:country": "CN",
    "name:und_x_variant": [
      "Dong’ercun"
    ],
    "name:zho_x_preferred": [
      "东二村"
    ],
    "wof:name": "Dong'ercun",
    "wof:placetype": "locality"
  },
  "geometry": {
    "coordinates": [
      130.88019,
      46.89071
    ],
    "type": "Point"
  }
}