{
  "type": "Feature",
  "properties": {
    "gn:admin1_code": "25",
    "gn:asciiname": "Donglizhuang",
    "gn:country_code": "CN",
    "gn:dem": 182,
    "gn:feature_class": "P",
    "gn:feature_code": "PPL",
    "gn:name": "Donglizhuang",
    "gn:population": 0,
    "gn:timezone": "Asia/Shanghai",
    "iso:country": "CN",
    "name:zho_x_preferred": [
      "东里庄"
    ],
    "name:zho_x_variant": [
      "东里庄镇"
    ],
    "wof:name": "Donglizhuang",
    "wof:placetype": "locality"
  },
  "geometry": {
    "coordinates": [
      118.055,
      35.7729
    ],
    "type": "Point"
  }
}