{
  "type": "Feature",
  "properties": {
    "gn:admin1_code": "11.0",
    "gn:asciiname": "Pangongtan",
    "gn:country_code": "CN",
    "gn:dem": 291,
    "gn:feature_class": "P",
    "gn:feature_code": "PPL",
    "gn:name": "Pangongtan",
    "gn:population": 0,
    "gn:timezone": "Asia/Shanghai",
    "iso:country": "CN",
    "name:zho_x_preferred": [
      "潘公潭"
    ],
    "wof:name": "Pangongtan",
    "wof:placetype": "locality"
  },
  "geometry": {
    "coordinates": [
      109.60357,
      27.87331
    ],
    "type": "Point"
  }
}