{
  "type": "Feature",
  "properties": {
    "gn:admin1_code": "32.0",
    "gn:asciiname": "Chadian",
    "gn:country_code": "CN",
    "gn:dem": 511,
    "gn:feature_class": "P",
    "gn:feature_code": "PPL",
    "gn:name": "Chadian",
    "gn:population": 0,
    "gn:timezone": "Asia/Shanghai",
    "iso:country": "CN",
    "name:ceb_x_preferred": [
      "Chadian"
    ],
    "name:swe_x_preferred": [
      "Chadian"
    ],
    "name:zho_x_preferred": [
      "茶店"
    ],
    "wof:name": "Chadian",
    "wof:placetype": "locality"
  },
  "geometry": {
    "coordinates": [
      104.025,
      30.7006
    ],
    "type": "Point"
  }
}