{
  "type": "Feature",
  "properties": {
    "gn:admin1_code": "6.0",
    "gn:asciiname": "Yidadui Yixiaodui",
    "gn:country_code": "CN",
    "gn:dem": 3221,
    "gn:feature_class": "P",
    "gn:feature_code": "PPLF",
    "gn:name": "Yidadui Yixiaodui",
    "gn:population": 0,
    "gn:timezone": "Asia/Shanghai",
    "iso:country": "CN",
    "name:und_x_variant": [
      "一大队一小队"
    ],
    "wof:name": "Yidadui Yixiaodui",
    "wof:placetype": "locality"
  },
  "geometry": {
    "coordinates": [
      100.13861,
      37.22852
    ],
    "type": "Point"
  }
}