{
  "type": "Feature",
  "properties": {
    "gn:admin1_code": "07",
    "gn:asciiname": "Changting",
    "gn:country_code": "CN",
    "gn:dem": 394,
    "gn:feature_class": "P",
    "gn:feature_code": "PPL",
    "gn:name": "Changting",
    "gn:population": 0,
    "gn:timezone": "Asia/Shanghai",
    "iso:country": "CN",
    "name:ara_x_preferred": [
      "تشانغتينغ"
    ],
    "name:ben_x_preferred": [
      "চ্যাংতিং"
    ],
    "name:deu_x_preferred": [
      "Changting"
    ],
    "name:ell_x_preferred": [
      "Τσανγκτίνγκ"
    ],
    "name:eng_x_preferred": [
      "Changting"
    ],
    "name:fas_x_preferred": [
      "چانگ تینگ"
    ],
    "name:fra_x_preferred": [
      "Changting"
    ],
    "name:heb_x_preferred": [
      "צ'נגטינג"
    ],
    "name:hin_x_preferred": [
      "चैंगटिंग"
    ],
    "name:hun_x_preferred": [
      "Changting"
    ],
    "name:ind_x_preferred": [
      "Changting"
    ],
    "name:ita_x_preferred": [
      "Changting"
    ],
    "name:jpn_x_preferred": [
      "長汀"
    ],
    "name:kor_x_preferred": [
      "창팅"
    ],
    "name:nld_x_preferred": [
      "Changting"
    ],
    "name:pol_x_preferred": [
      "Changting"
    ],
    "name:por_x_preferred": [
      "Changting"
    ],
    "name:rus_x_preferred": [
      "Чантин"
    ],
    "name:spa_x_preferred": [
      "Changting"
    ],
    "name:swe_x_preferred": [
      "Changting"
    ],
    "name:tur_x_preferred": [
      "Changting"
    ],
    "name:ukr_x_preferred": [
      "Чжантін"
    ],
    "name:urd_x_preferred": [
      "چینگٹنگ"
    ],
    "name:vie_x_preferred": [
      "Trường Đinh"
    ],
    "name:zho_cn_x_preferred": [
      "长汀县"
    ],
    "name:zho_tw_x_preferred": [
      "長汀"
    ],
    "name:zho_x_preferred": [
      "长汀"
    ],
    "wof:name": "Changting",
    "wof:placetype": "locality"
  },
  "geometry": {
    "coordinates": [
      117.92067,
      25.43284
    ],
    "type": "Point"
  }
}