{
  "type": "Feature",
  "properties": {
    "gn:admin1_code": "26.0",
    "gn:asciiname": "Shishibucun",
    "gn:country_code": "CN",
    "gn:dem": 1067,
    "gn:feature_class": "P",
    "gn:feature_code": "PPL",
    "gn:name": "Shishibucun",
    "gn:population": 0,
    "gn:timezone": "Asia/Shanghai",
    "iso:country": "CN",
    "name:zho_x_preferred": [
      "师师堡村"
    ],
    "wof:name": "Shishibucun",
    "wof:placetype": "locality"
  },
  "geometry": {
    "coordinates": [
      109.60137,
      35.51325999999999
    ],
    "type": "Point"
  }
}