{
  "type": "Feature",
  "properties": {
    "gn:admin1_code": "2",
    "gn:asciiname": "Lanju",
    "gn:cc2": "CN",
    "gn:country_code": "CN",
    "gn:dem": 242,
    "gn:feature_class": "P",
    "gn:feature_code": "PPL",
    "gn:name": "Lanju",
    "gn:population": 0,
    "gn:timezone": "Asia/Shanghai",
    "iso:country": "CN",
    "name:und_x_variant": [
      "Wumeiyang",
      "Lanju",
      "兰巨",
      "Lanju Xiang"
    ],
    "name:zho_x_preferred": [
      "五梅垟"
    ],
    "name:zho_x_variant": [
      "兰巨乡"
    ],
    "wof:name": "Lanju",
    "wof:placetype": "locality"
  },
  "geometry": {
    "coordinates": [
      119.09389,
      27.9875
    ],
    "type": "Point"
  }
}