{
  "type": "Feature",
  "properties": {
    "gn:admin1_code": "25",
    "gn:asciiname": "Baoji",
    "gn:country_code": "CN",
    "gn:dem": 7,
    "gn:feature_class": "P",
    "gn:feature_code": "PPL",
    "gn:name": "Baoji",
    "gn:population": 0,
    "gn:timezone": "Asia/Shanghai",
    "iso:country": "CN",
    "name:ara_x_preferred": [
      "باوجى"
    ],
    "name:bxr_x_preferred": [
      "Баоцзи"
    ],
    "name:cdo_x_preferred": [
      "Bō̤-giĕ"
    ],
    "name:ceb_x_preferred": [
      "Baoji Shi"
    ],
    "name:ces_x_preferred": [
      "Pao-ťi"
    ],
    "name:dan_x_preferred": [
      "Baoji"
    ],
    "name:deu_x_preferred": [
      "Baoji"
    ],
    "name:eus_x_preferred": [
      "Baoji"
    ],
    "name:fas_x_preferred": [
      "باوژی"
    ],
    "name:fin_x_preferred": [
      "Baoji"
    ],
    "name:fra_x_preferred": [
      "Baoji"
    ],
    "name:heb_x_preferred": [
      "באוג'י"
    ],
    "name:hun_x_preferred": [
      "Baoji"
    ],
    "name:hye_x_preferred": [
      "Բոացզի"
    ],
    "name:ita_x_preferred": [
      "Baoji"
    ],
    "name:jpn_x_preferred": [
      "宝鶏市"
    ],
    "name:kaz_x_preferred": [
      "Баоцзи"
    ],
    "name:kik_x_preferred": [
      "Baoji"
    ],
    "name:kor_x_preferred": [
      "바오지시"
    ],
    "name:lit_x_preferred": [
      "Baodzi"
    ],
    "name:mlg_x_preferred": [
      "Baoji"
    ],
    "name:nld_x_preferred": [
      "Baoji"
    ],
    "name:nno_x_preferred": [
      "Baoji"
    ],
    "name:nor_x_preferred": [
      "Baoji"
    ],
    "name:pol_x_preferred": [
      "Baoji"
    ],
    "name:rus_x_preferred": [
      "Баоцзи"
    ],
    "name:spa_x_preferred": [
      "Baoji"
    ],
    "name:srp_x_preferred": [
      "Баођи"
    ],
    "name:swe_x_preferred": [
      "Baoji"
    ],
    "name:tur_x_preferred": [
      "Baoji"
    ],
    "name:urd_x_preferred": [
      "باوجی"
    ],
    "name:vie_x_preferred": [
      "Bảo Kê"
    ],
    "name:war_x_preferred": [
      "Baoji"
    ],
    "name:zho_x_preferred": [
      "宝鸡市"
    ],
    "wof:name": "Baoji",
    "wof:placetype": "locality"
  },
  "geometry": {
    "coordinates": [
      117.85917,
      37.50389
    ],
    "type": "Point"
  }
}