{
  "type": "Feature",
  "properties": {
    "gn:admin1_code": "9",
    "gn:asciiname": "Liuhe",
    "gn:country_code": "CN",
    "gn:dem": 53,
    "gn:feature_class": "P",
    "gn:feature_code": "PPL",
    "gn:name": "Liuhe",
    "gn:population": 0,
    "gn:timezone": "Asia/Shanghai",
    "iso:country": "CN",
    "name:ara_x_preferred": [
      "يوخيه"
    ],
    "name:ben_x_preferred": [
      "লিউহে"
    ],
    "name:ceb_x_preferred": [
      "Liuhe"
    ],
    "name:deu_x_preferred": [
      "Liuhe"
    ],
    "name:ell_x_preferred": [
      "Λιούχε"
    ],
    "name:fas_x_preferred": [
      "لیوهه"
    ],
    "name:fra_x_preferred": [
      "Liuhe"
    ],
    "name:heb_x_preferred": [
      "ליאוחה"
    ],
    "name:hin_x_preferred": [
      "ल्यूहे"
    ],
    "name:hun_x_preferred": [
      "Liuhe"
    ],
    "name:ind_x_preferred": [
      "Liuhe"
    ],
    "name:ita_x_preferred": [
      "Liuhe"
    ],
    "name:kor_x_preferred": [
      "류허"
    ],
    "name:nld_x_preferred": [
      "Liuhe"
    ],
    "name:pol_x_preferred": [
      "Liuhe"
    ],
    "name:por_x_preferred": [
      "Liuhe"
    ],
    "name:rus_x_preferred": [
      "Люхэ"
    ],
    "name:spa_x_preferred": [
      "Liuhe"
    ],
    "name:swe_x_preferred": [
      "Liuhe"
    ],
    "name:tur_x_preferred": [
      "Liuhe"
    ],
    "name:ukr_x_preferred": [
      "Люхе"
    ],
    "name:urd_x_preferred": [
      "لیوہی"
    ],
    "name:vie_x_preferred": [
      "Liễu Hà"
    ],
    "name:zho_x_preferred": [
      "柳河"
    ],
    "wof:name": "Liuhe",
    "wof:placetype": "locality"
  },
  "geometry": {
    "coordinates": [
      115.037,
      34.2194
    ],
    "type": "Point"
  }
}