{
  "type": "Feature",
  "properties": {
    "gn:admin1_code": "2.0",
    "gn:asciiname": "Shamaolu",
    "gn:country_code": "CN",
    "gn:dem": 5,
    "gn:feature_class": "P",
    "gn:feature_code": "PPL",
    "gn:name": "Shamaolü",
    "gn:population": 0,
    "gn:timezone": "Asia/Shanghai",
    "iso:country": "CN",
    "name:und_x_variant": [
      "Shamaolü"
    ],
    "name:zho_x_preferred": [
      "纱帽绿"
    ],
    "wof:name": "Shamaolu",
    "wof:placetype": "locality"
  },
  "geometry": {
    "coordinates": [
      121.78961,
      29.13996
    ],
    "type": "Point"
  }
}