{
  "type": "Feature",
  "properties": {
    "gn:admin1_code": "02",
    "gn:asciiname": "Muli",
    "gn:country_code": "CN",
    "gn:dem": 733,
    "gn:feature_class": "P",
    "gn:feature_code": "PPLA4",
    "gn:name": "Muli",
    "gn:population": 0,
    "gn:timezone": "Asia/Shanghai",
    "iso:country": "CN",
    "name:ceb_x_preferred": [
      "Muli"
    ],
    "name:deu_x_preferred": [
      "Muli"
    ],
    "name:div_x_preferred": [
      "މުލި"
    ],
    "name:fas_x_preferred": [
      "مولی"
    ],
    "name:nld_x_preferred": [
      "Muli"
    ],
    "name:swe_x_preferred": [
      "Muli"
    ],
    "name:und_x_variant": [
      "Muli Xiang"
    ],
    "name:zho_x_preferred": [
      "木栗"
    ],
    "name:zho_x_variant": [
      "木栗乡"
    ],
    "wof:name": "Muli",
    "wof:placetype": "locality"
  },
  "geometry": {
    "coordinates": [
      120.34098,
      28.44918
    ],
    "type": "Point"
  }
}