{
  "type": "Feature",
  "properties": {
    "gn:admin1_code": "6.0",
    "gn:asciiname": "Heihe",
    "gn:country_code": "CN",
    "gn:dem": 4302,
    "gn:feature_class": "P",
    "gn:feature_code": "PPLA4",
    "gn:name": "Heihe",
    "gn:population": 0,
    "gn:timezone": "Asia/Urumqi",
    "iso:country": "CN",
    "name:ara_x_preferred": [
      "خيخه"
    ],
    "name:bak_x_preferred": [
      "Хэйхэ"
    ],
    "name:cdo_x_preferred": [
      "Háik-ò̤"
    ],
    "name:ceb_x_preferred": [
      "Heihe"
    ],
    "name:ces_x_preferred": [
      "Chej-che"
    ],
    "name:dan_x_preferred": [
      "Heihe"
    ],
    "name:deu_x_preferred": [
      "Heihe"
    ],
    "name:ell_x_preferred": [
      "Χέιχε"
    ],
    "name:epo_x_preferred": [
      "Heihe"
    ],
    "name:est_x_preferred": [
      "Heihe Shi"
    ],
    "name:eus_x_preferred": [
      "Heihe"
    ],
    "name:fas_x_preferred": [
      "هایهی"
    ],
    "name:fin_x_preferred": [
      "Heihe"
    ],
    "name:fra_x_preferred": [
      "Heihe"
    ],
    "name:hin_x_preferred": [
      "हेइहे"
    ],
    "name:ind_x_preferred": [
      "Heihe"
    ],
    "name:ita_x_preferred": [
      "Heihe"
    ],
    "name:jpn_x_preferred": [
      "黒河"
    ],
    "name:jpn_x_variant": [
      "黒河市"
    ],
    "name:kik_x_preferred": [
      "Heihe"
    ],
    "name:kor_x_preferred": [
      "헤이허시"
    ],
    "name:mlg_x_preferred": [
      "Heihe"
    ],
    "name:nld_x_preferred": [
      "Heihe"
    ],
    "name:nno_x_preferred": [
      "Heihe"
    ],
    "name:nor_x_preferred": [
      "Heihe"
    ],
    "name:pam_x_preferred": [
      "Heihe"
    ],
    "name:pol_x_preferred": [
      "Heihe"
    ],
    "name:por_x_preferred": [
      "Heihe"
    ],
    "name:rus_x_preferred": [
      "Хэйхэ"
    ],
    "name:sah_x_preferred": [
      "Хэйхэ"
    ],
    "name:spa_x_preferred": [
      "Heihe"
    ],
    "name:swe_x_preferred": [
      "Heihe"
    ],
    "name:tgl_x_preferred": [
      "Heihe"
    ],
    "name:tur_x_preferred": [
      "Heihe"
    ],
    "name:und_x_variant": [
      "Heihe Xiang",
      "Zuowei Longwa"
    ],
    "name:urd_x_preferred": [
      "ہئیہے"
    ],
    "name:vie_x_preferred": [
      "Hắc Hà"
    ],
    "name:war_x_preferred": [
      "Heihe"
    ],
    "name:wuu_x_preferred": [
      "黑河市"
    ],
    "name:zho_x_preferred": [
      "黑河"
    ],
    "name:zho_x_variant": [
      "黑河乡",
      "作维隆哇",
      "黑河市"
    ],
    "wof:name": "Heihe",
    "wof:placetype": "locality"
  },
  "geometry": {
    "coordinates": [
      98.12923,
      34.79677
    ],
    "type": "Point"
  }
}