{
  "type": "Feature",
  "properties": {
    "gn:admin1_code": "30.0",
    "gn:asciiname": "Mandi",
    "gn:country_code": "CN",
    "gn:dem": 97,
    "gn:feature_class": "P",
    "gn:feature_code": "PPL",
    "gn:name": "Mandi",
    "gn:population": 0,
    "gn:timezone": "Asia/Shanghai",
    "iso:country": "CN",
    "name:ara_x_preferred": [
      "ماندي"
    ],
    "name:ceb_x_preferred": [
      "Mandi"
    ],
    "name:deu_x_preferred": [
      "Mandi"
    ],
    "name:fin_x_preferred": [
      "Mandi"
    ],
    "name:ita_x_preferred": [
      "Mandi"
    ],
    "name:nld_x_preferred": [
      "Mandi"
    ],
    "name:pol_x_preferred": [
      "Mandi"
    ],
    "name:rus_x_preferred": [
      "Манди"
    ],
    "name:spa_x_preferred": [
      "Mandi"
    ],
    "name:swe_x_preferred": [
      "Mandi"
    ],
    "name:ukr_x_preferred": [
      "Манді"
    ],
    "name:zho_x_preferred": [
      "Mandi"
    ],
    "name:zho_x_variant": [
      "满地"
    ],
    "wof:name": "Mandi",
    "wof:placetype": "locality"
  },
  "geometry": {
    "coordinates": [
      112.35,
      24.79806
    ],
    "type": "Point"
  }
}