{
  "type": "Feature",
  "properties": {
    "gn:admin1_code": "21",
    "gn:asciiname": "Mataigou",
    "gn:country_code": "CN",
    "gn:dem": 1101,
    "gn:feature_class": "P",
    "gn:feature_code": "PPL",
    "gn:name": "Mataigou",
    "gn:population": 0,
    "gn:timezone": "Asia/Shanghai",
    "iso:country": "CN",
    "name:und_x_variant": [
      "Mataygou",
      "Ma-t’ai-kou",
      "T’ao-lo",
      "Taole",
      "Mataigou",
      "马太沟",
      "Mataigou Xiang",
      "马太沟乡"
    ],
    "wof:name": "Mataigou",
    "wof:placetype": "locality"
  },
  "geometry": {
    "coordinates": [
      106.67222,
      38.79667
    ],
    "type": "Point"
  }
}