{
  "type": "Feature",
  "properties": {
    "gn:admin1_code": "5.0",
    "gn:asciiname": "Yushancun",
    "gn:country_code": "CN",
    "gn:dem": 545,
    "gn:feature_class": "P",
    "gn:feature_code": "PPL",
    "gn:name": "Yushancun",
    "gn:population": 0,
    "gn:timezone": "Asia/Shanghai",
    "iso:country": "CN",
    "name:zho_x_preferred": [
      "裕山村"
    ],
    "wof:name": "Yushancun",
    "wof:placetype": "locality"
  },
  "geometry": {
    "coordinates": [
      128.5152,
      43.39292
    ],
    "type": "Point"
  }
}