{
  "type": "Feature",
  "properties": {
    "gn:admin1_code": "7",
    "gn:asciiname": "Zhanghekeng",
    "gn:country_code": "CN",
    "gn:dem": 354,
    "gn:feature_class": "P",
    "gn:feature_code": "PPL",
    "gn:name": "Zhanghekeng",
    "gn:population": 0,
    "gn:timezone": "Asia/Shanghai",
    "iso:country": "CN",
    "name:und_x_variant": [
      "张河坑"
    ],
    "wof:name": "Zhanghekeng",
    "wof:placetype": "locality"
  },
  "geometry": {
    "coordinates": [
      116.68901,
      26.18052
    ],
    "type": "Point"
  }
}