{
  "type": "Feature",
  "properties": {
    "gn:admin1_code": "9.0",
    "gn:asciiname": "Ligang",
    "gn:country_code": "CN",
    "gn:dem": 109,
    "gn:feature_class": "P",
    "gn:feature_code": "PPL",
    "gn:name": "Ligang",
    "gn:population": 0,
    "gn:timezone": "Asia/Shanghai",
    "iso:country": "CN",
    "name:hak_x_preferred": [
      "Lî-kóng-hiông"
    ],
    "name:jpn_x_preferred": [
      "里港郷"
    ],
    "name:kor_x_preferred": [
      "리강향"
    ],
    "name:vie_x_preferred": [
      "Lí Cảng"
    ],
    "name:zho_x_preferred": [
      "李岗"
    ],
    "name:zho_x_variant": [
      "里港鄉"
    ],
    "wof:name": "Ligang",
    "wof:placetype": "locality"
  },
  "geometry": {
    "coordinates": [
      113.93507,
      32.65932
    ],
    "type": "Point"
  }
}