{
  "type": "Feature",
  "properties": {
    "gn:admin1_code": "2.0",
    "gn:asciiname": "Wudu",
    "gn:cc2": "CN",
    "gn:country_code": "CN",
    "gn:dem": 334,
    "gn:feature_class": "P",
    "gn:feature_code": "PPL",
    "gn:name": "Wudu",
    "gn:population": 0,
    "gn:timezone": "Asia/Shanghai",
    "iso:country": "CN",
    "name:ara_x_preferred": [
      "وضوء"
    ],
    "name:aze_x_preferred": [
      "Dəstəmaz"
    ],
    "name:ben_x_preferred": [
      "অযু"
    ],
    "name:bos_x_preferred": [
      "Abdest"
    ],
    "name:bul_x_preferred": [
      "Абдест"
    ],
    "name:dan_x_preferred": [
      "Abdest"
    ],
    "name:deu_x_preferred": [
      "Wudū'"
    ],
    "name:epo_x_preferred": [
      "Vozuo"
    ],
    "name:est_x_preferred": [
      "Abdest"
    ],
    "name:fas_x_preferred": [
      "وضو"
    ],
    "name:fin_x_preferred": [
      "Abdest"
    ],
    "name:fra_x_preferred": [
      "Wodzū"
    ],
    "name:guj_x_preferred": [
      "વુઝૂ"
    ],
    "name:hau_x_preferred": [
      "Alwala"
    ],
    "name:heb_x_preferred": [
      "וודוא"
    ],
    "name:hin_x_preferred": [
      "वुज़ू"
    ],
    "name:hrv_x_preferred": [
      "Abdest"
    ],
    "name:ind_x_preferred": [
      "Wudu"
    ],
    "name:ita_x_preferred": [
      "Wuḍūʾ"
    ],
    "name:jav_x_preferred": [
      "Wudu"
    ],
    "name:jpn_x_preferred": [
      "ウドゥ"
    ],
    "name:kor_x_preferred": [
      "우두"
    ],
    "name:kur_x_preferred": [
      "Destnimêj"
    ],
    "name:lbe_x_preferred": [
      "Иссаву"
    ],
    "name:mal_x_preferred": [
      "വുദു"
    ],
    "name:mkd_x_preferred": [
      "Абдест"
    ],
    "name:msa_x_preferred": [
      "Wuduk"
    ],
    "name:nld_x_preferred": [
      "Woedoe"
    ],
    "name:nor_x_preferred": [
      "Wudu"
    ],
    "name:pol_x_preferred": [
      "Abdest"
    ],
    "name:por_x_preferred": [
      "Abdesto"
    ],
    "name:rus_x_preferred": [
      "Вуду"
    ],
    "name:spa_x_preferred": [
      "Wudu"
    ],
    "name:sqi_x_preferred": [
      "Abdesi"
    ],
    "name:srp_x_preferred": [
      "Абдест"
    ],
    "name:sun_x_preferred": [
      "Abdas"
    ],
    "name:swe_x_preferred": [
      "Abdest"
    ],
    "name:tgk_x_preferred": [
      "Вузӯ"
    ],
    "name:tur_x_preferred": [
      "Abdest"
    ],
    "name:und_x_variant": [
      "Wu-tu"
    ],
    "name:urd_x_preferred": [
      "وضو"
    ],
    "name:zho_x_preferred": [
      "五都"
    ],
    "wof:name": "Wudu",
    "wof:placetype": "locality"
  },
  "geometry": {
    "coordinates": [
      119.00194,
      27.62
    ],
    "type": "Point"
  }
}