{
  "type": "Feature",
  "properties": {
    "gn:admin1_code": "24",
    "gn:asciiname": "Nantou",
    "gn:country_code": "CN",
    "gn:dem": 1330,
    "gn:feature_class": "P",
    "gn:feature_code": "PPL",
    "gn:name": "Nantou",
    "gn:population": 0,
    "gn:timezone": "Asia/Shanghai",
    "iso:country": "CN",
    "name:ben_x_preferred": [
      "নান্তৌ"
    ],
    "name:ceb_x_preferred": [
      "Nantou"
    ],
    "name:deu_x_preferred": [
      "Nantou"
    ],
    "name:ell_x_preferred": [
      "Νάντου"
    ],
    "name:fas_x_preferred": [
      "نانتو"
    ],
    "name:heb_x_preferred": [
      "נאנטו"
    ],
    "name:hin_x_preferred": [
      "नंताऊ"
    ],
    "name:hun_x_preferred": [
      "Nantou"
    ],
    "name:ind_x_preferred": [
      "Nantou"
    ],
    "name:kor_x_preferred": [
      "난터우"
    ],
    "name:nld_x_preferred": [
      "Nantou"
    ],
    "name:por_x_preferred": [
      "Nantou"
    ],
    "name:swe_x_preferred": [
      "Nantou"
    ],
    "name:ukr_x_preferred": [
      "Наньтоу"
    ],
    "name:urd_x_preferred": [
      "نانتو"
    ],
    "name:zho_x_preferred": [
      "南头"
    ],
    "wof:name": "Nantou",
    "wof:placetype": "locality"
  },
  "geometry": {
    "coordinates": [
      112.01382,
      37.78248
    ],
    "type": "Point"
  }
}