{
  "type": "Feature",
  "properties": {
    "gn:admin1_code": "2",
    "gn:asciiname": "Wazaotou",
    "gn:country_code": "CN",
    "gn:dem": 35,
    "gn:feature_class": "P",
    "gn:feature_code": "PPL",
    "gn:name": "Wazaotou",
    "gn:population": 0,
    "gn:timezone": "Asia/Shanghai",
    "iso:country": "CN",
    "name:und_x_variant": [
      "瓦灶头",
      "Wazaotou"
    ],
    "wof:name": "Wazaotou",
    "wof:placetype": "locality"
  },
  "geometry": {
    "coordinates": [
      119.45449,
      29.16742
    ],
    "type": "Point"
  }
}