{
  "type": "Feature",
  "properties": {
    "gn:admin1_code": "1.0",
    "gn:asciiname": "Wufancun",
    "gn:country_code": "CN",
    "gn:dem": 203,
    "gn:feature_class": "P",
    "gn:feature_code": "PPL",
    "gn:name": "Wufancun",
    "gn:population": 0,
    "gn:timezone": "Asia/Shanghai",
    "iso:country": "CN",
    "name:zho_x_preferred": [
      "吴畈村"
    ],
    "wof:name": "Wufancun",
    "wof:placetype": "locality"
  },
  "geometry": {
    "coordinates": [
      115.93829,
      30.62689
    ],
    "type": "Point"
  }
}