{
  "type": "Feature",
  "properties": {
    "gn:admin1_code": "16",
    "gn:asciiname": "Liutian",
    "gn:country_code": "CN",
    "gn:dem": 151,
    "gn:feature_class": "P",
    "gn:feature_code": "PPL",
    "gn:name": "Liutian",
    "gn:population": 0,
    "gn:timezone": "Asia/Shanghai",
    "iso:country": "CN",
    "name:zho_x_preferred": [
      "留田"
    ],
    "wof:name": "Liutian",
    "wof:placetype": "locality"
  },
  "geometry": {
    "coordinates": [
      110.343,
      25.1161
    ],
    "type": "Point"
  }
}