{
  "type": "Feature",
  "properties": {
    "gn:admin1_code": "11.0",
    "gn:asciiname": "Dangtianqiu",
    "gn:country_code": "CN",
    "gn:dem": 396,
    "gn:feature_class": "P",
    "gn:feature_code": "PPL",
    "gn:name": "Dangtianqiu",
    "gn:population": 0,
    "gn:timezone": "Asia/Shanghai",
    "iso:country": "CN",
    "name:zho_x_preferred": [
      "当天坵"
    ],
    "name:zho_x_variant": [
      "当天丘"
    ],
    "wof:name": "Dangtianqiu",
    "wof:placetype": "locality"
  },
  "geometry": {
    "coordinates": [
      113.72836,
      26.88746
    ],
    "type": "Point"
  }
}