{
  "type": "Feature",
  "properties": {
    "gn:admin1_code": "02",
    "gn:asciiname": "Zheng'aocun",
    "gn:country_code": "CN",
    "gn:dem": 10,
    "gn:feature_class": "P",
    "gn:feature_code": "PPL",
    "gn:name": "Zheng’aocun",
    "gn:population": 0,
    "gn:timezone": "Asia/Shanghai",
    "iso:country": "CN",
    "name:und_x_variant": [
      "Cheng-ao",
      "Zheng’aocun"
    ],
    "name:zho_x_preferred": [
      "郑岙"
    ],
    "name:zho_x_variant": [
      "Zheng’ao",
      "郑岙村"
    ],
    "wof:name": "Zheng'aocun",
    "wof:placetype": "locality"
  },
  "geometry": {
    "coordinates": [
      120.76032,
      27.86529
    ],
    "type": "Point"
  }
}