{
  "type": "Feature",
  "properties": {
    "gn:admin1_code": "26.0",
    "gn:asciiname": "Chengjiazhifangcun",
    "gn:country_code": "CN",
    "gn:dem": 1075,
    "gn:feature_class": "P",
    "gn:feature_code": "PPL",
    "gn:name": "Chengjiazhifangcun",
    "gn:population": 0,
    "gn:timezone": "Asia/Shanghai",
    "iso:country": "CN",
    "name:zho_x_preferred": [
      "程家纸坊村"
    ],
    "wof:name": "Chengjiazhifangcun",
    "wof:placetype": "locality"
  },
  "geometry": {
    "coordinates": [
      109.05572,
      36.44876
    ],
    "type": "Point"
  }
}