{
  "type": "Feature",
  "properties": {
    "gn:admin1_code": "2.0",
    "gn:asciiname": "Jinxing",
    "gn:country_code": "CN",
    "gn:dem": 394,
    "gn:feature_class": "P",
    "gn:feature_code": "PPL",
    "gn:name": "Jinxing",
    "gn:population": 0,
    "gn:timezone": "Asia/Shanghai",
    "iso:country": "CN",
    "name:zho_x_preferred": [
      "金星"
    ],
    "wof:name": "Jinxing",
    "wof:placetype": "locality"
  },
  "geometry": {
    "coordinates": [
      118.63052,
      28.53237
    ],
    "type": "Point"
  }
}