{
  "type": "Feature",
  "properties": {
    "gn:admin1_code": "16",
    "gn:asciiname": "Debao Chengguanzhen",
    "gn:country_code": "CN",
    "gn:dem": 688,
    "gn:feature_class": "P",
    "gn:feature_code": "PPLA3",
    "gn:name": "Debao Chengguanzhen",
    "gn:population": 0,
    "gn:timezone": "Asia/Shanghai",
    "iso:country": "CN",
    "name:deu_x_preferred": [
      "Debao"
    ],
    "name:fas_x_preferred": [
      "شهرستان دباو"
    ],
    "name:hak_x_preferred": [
      "Tet-pó-yen"
    ],
    "name:jpn_x_preferred": [
      "徳保県"
    ],
    "name:kor_x_preferred": [
      "더바오현"
    ],
    "name:nor_x_preferred": [
      "Debao"
    ],
    "name:swe_x_preferred": [
      "Debao"
    ],
    "name:und_x_variant": [
      "Chenan",
      "Chenanfu",
      "Te-pao",
      "Debao Chengguanzhen"
    ],
    "name:vie_x_preferred": [
      "Đức Bảo"
    ],
    "name:zho_x_preferred": [
      "T’ien-pao"
    ],
    "name:zho_x_variant": [
      "T’ien-pao-hsien-ch’eng",
      "T’ien-pao-hsien",
      "德保县"
    ],
    "wof:name": "Debao Chengguanzhen",
    "wof:placetype": "locality"
  },
  "geometry": {
    "coordinates": [
      106.57352,
      23.38471
    ],
    "type": "Point"
  }
}