{
  "type": "Feature",
  "properties": {
    "gn:admin1_code": "7.0",
    "gn:asciiname": "Gaocun",
    "gn:country_code": "CN",
    "gn:dem": 570,
    "gn:feature_class": "P",
    "gn:feature_code": "PPL",
    "gn:name": "Gaocun",
    "gn:population": 0,
    "gn:timezone": "Asia/Shanghai",
    "iso:country": "CN",
    "name:zho_x_preferred": [
      "高村"
    ],
    "name:zho_x_variant": [
      "高村镇"
    ],
    "wof:name": "Gaocun",
    "wof:placetype": "locality"
  },
  "geometry": {
    "coordinates": [
      117.67681,
      25.06789
    ],
    "type": "Point"
  }
}