{
  "type": "Feature",
  "properties": {
    "gn:admin1_code": "8.0",
    "gn:asciiname": "Shuanghecun",
    "gn:country_code": "CN",
    "gn:dem": 152,
    "gn:feature_class": "P",
    "gn:feature_code": "PPL",
    "gn:name": "Shuanghecun",
    "gn:population": 0,
    "gn:timezone": "Asia/Shanghai",
    "iso:country": "CN",
    "name:zho_x_preferred": [
      "双河村"
    ],
    "wof:name": "Shuanghecun",
    "wof:placetype": "locality"
  },
  "geometry": {
    "coordinates": [
      127.50168,
      46.22718
    ],
    "type": "Point"
  }
}