{
  "type": "Feature",
  "properties": {
    "gn:admin1_code": "04",
    "gn:asciiname": "Lianyun",
    "gn:country_code": "CN",
    "gn:dem": 238,
    "gn:feature_class": "P",
    "gn:feature_code": "PPLA4",
    "gn:name": "Lianyun",
    "gn:population": 0,
    "gn:timezone": "Asia/Shanghai",
    "iso:country": "CN",
    "name:deu_x_preferred": [
      "Lianyun"
    ],
    "name:jpn_x_preferred": [
      "連雲区"
    ],
    "name:kor_x_preferred": [
      "롄윈구"
    ],
    "name:nor_x_preferred": [
      "Lianyun"
    ],
    "name:rus_x_preferred": [
      "Ляньюнь"
    ],
    "name:swe_x_preferred": [
      "Lianyun"
    ],
    "name:und_x_variant": [
      "Lianyungang Shi",
      "Lien-yün-shih",
      "Lien-yün",
      "Lao-yao",
      "Lien-yün-kang",
      "Lien-yün-chiang",
      "Lianyungang",
      "连云",
      "Lianyun Jiedao",
      "连云街道",
      "连云港"
    ],
    "name:vie_x_preferred": [
      "Liên Vân"
    ],
    "name:zho_x_preferred": [
      "连云区"
    ],
    "wof:name": "Lianyun",
    "wof:placetype": "locality"
  },
  "geometry": {
    "coordinates": [
      119.4425,
      34.73194
    ],
    "type": "Point"
  }
}