{
  "type": "Feature",
  "properties": {
    "gn:admin1_code": "10.0",
    "gn:asciiname": "Maguantun",
    "gn:country_code": "CN",
    "gn:dem": 29,
    "gn:feature_class": "P",
    "gn:feature_code": "PPL",
    "gn:name": "Maguantun",
    "gn:population": 0,
    "gn:timezone": "Asia/Shanghai",
    "iso:country": "CN",
    "name:zho_x_preferred": [
      "马官屯"
    ],
    "wof:name": "Maguantun",
    "wof:placetype": "locality"
  },
  "geometry": {
    "coordinates": [
      116.01685,
      39.30942
    ],
    "type": "Point"
  }
}