{
  "type": "Feature",
  "properties": {
    "gn:admin1_code": "4.0",
    "gn:asciiname": "Zhuhai",
    "gn:country_code": "CN",
    "gn:dem": 59,
    "gn:feature_class": "P",
    "gn:feature_code": "PPL",
    "gn:name": "Zhuhai",
    "gn:population": 0,
    "gn:timezone": "Asia/Shanghai",
    "iso:country": "CN",
    "name:afr_x_preferred": [
      "Zhuhai"
    ],
    "name:ara_x_preferred": [
      "زوهاي"
    ],
    "name:bre_x_preferred": [
      "Zhuhai"
    ],
    "name:bul_x_preferred": [
      "Джухай"
    ],
    "name:cdo_x_preferred": [
      "Ciŏ-hāi"
    ],
    "name:ceb_x_preferred": [
      "Zhuhai"
    ],
    "name:ces_x_preferred": [
      "Ču-chaj"
    ],
    "name:cym_x_preferred": [
      "Zhuhai"
    ],
    "name:dan_x_preferred": [
      "Zhuhai"
    ],
    "name:deu_x_preferred": [
      "Zhuhai"
    ],
    "name:epo_x_preferred": [
      "Ĝuhaj"
    ],
    "name:est_x_preferred": [
      "Zhuhai"
    ],
    "name:eus_x_preferred": [
      "Zhuhai"
    ],
    "name:fas_x_preferred": [
      "جوهای"
    ],
    "name:fin_x_preferred": [
      "Zhuhai"
    ],
    "name:fra_x_preferred": [
      "Zhuhai"
    ],
    "name:hak_x_preferred": [
      "Chû-hói-sṳ"
    ],
    "name:ind_x_preferred": [
      "Zhuhai"
    ],
    "name:ita_x_preferred": [
      "Zhuhai"
    ],
    "name:jpn_x_preferred": [
      "珠海市"
    ],
    "name:kik_x_preferred": [
      "Zhuhai"
    ],
    "name:kor_x_preferred": [
      "주하이시"
    ],
    "name:mlg_x_preferred": [
      "Zhuhai"
    ],
    "name:msa_x_preferred": [
      "Zhuhai"
    ],
    "name:nld_x_preferred": [
      "Zhuhai"
    ],
    "name:nno_x_preferred": [
      "Zhuhai"
    ],
    "name:nor_x_preferred": [
      "Zhuhai"
    ],
    "name:pam_x_preferred": [
      "Zhuhai"
    ],
    "name:pol_x_preferred": [
      "Zhuhai"
    ],
    "name:por_x_preferred": [
      "Zhuhai"
    ],
    "name:rus_x_preferred": [
      "Чжухай"
    ],
    "name:sco_x_preferred": [
      "Zhuhai"
    ],
    "name:snd_x_preferred": [
      "جوھائي"
    ],
    "name:spa_x_preferred": [
      "Zhuhai"
    ],
    "name:srp_x_preferred": [
      "Џухај"
    ],
    "name:swa_x_preferred": [
      "Zhuhai"
    ],
    "name:swe_x_preferred": [
      "Zhuhai"
    ],
    "name:tgl_x_preferred": [
      "Zhuhai"
    ],
    "name:tur_x_preferred": [
      "Zhuhai"
    ],
    "name:uig_x_preferred": [
      "Juxey shehiri"
    ],
    "name:ukr_x_preferred": [
      "Чжухай"
    ],
    "name:urd_x_preferred": [
      "ژوہوئی"
    ],
    "name:vie_x_preferred": [
      "Châu Hải"
    ],
    "name:war_x_preferred": [
      "Zhuhai"
    ],
    "name:wuu_x_preferred": [
      "珠海市"
    ],
    "name:zho_x_preferred": [
      "竹海"
    ],
    "name:zho_x_variant": [
      "珠海市"
    ],
    "wof:name": "Zhuhai",
    "wof:placetype": "locality"
  },
  "geometry": {
    "coordinates": [
      119.72983,
      31.19305
    ],
    "type": "Point"
  }
}