{
  "type": "Feature",
  "properties": {
    "gn:admin1_code": "10",
    "gn:asciiname": "Sujiatuan",
    "gn:country_code": "CN",
    "gn:dem": 64,
    "gn:feature_class": "P",
    "gn:feature_code": "PPL",
    "gn:name": "Sujiatuan",
    "gn:population": 0,
    "gn:timezone": "Asia/Shanghai",
    "iso:country": "CN",
    "name:zho_x_preferred": [
      "苏家疃"
    ],
    "wof:name": "Sujiatuan",
    "wof:placetype": "locality"
  },
  "geometry": {
    "coordinates": [
      115.126,
      38.874
    ],
    "type": "Point"
  }
}