{
  "type": "Feature",
  "properties": {
    "gn:country": "CN",
    "gn:fcode": "PPL",
    "gn:population": 2300,
    "iso:country": "CN",
    "name:hak_x_preferred": [
      "Tsuk-khì-hiông"
    ],
    "name:jpn_x_preferred": [
      "竹崎郷"
    ],
    "name:kor_x_preferred": [
      "주치향"
    ],
    "name:pol_x_preferred": [
      "Zhuqi"
    ],
    "name:und_x_variant": [
      "Chu-ch’i"
    ],
    "name:vie_x_preferred": [
      "Trúc Khi"
    ],
    "name:zho_x_preferred": [
      "竹岐"
    ],
    "name:zho_x_variant": [
      "竹岐乡",
      "竹崎鄉"
    ],
    "qs:name": "Zhuqi",
    "qs:photos_9r": 0,
    "qs:photos_sr": 0,
    "qs:pop_sr": "4",
    "wd:wordcount": 188,
    "wof:name": "Zhuqi",
    "wof:placetype": "locality",
    "wof:population": 2300
  },
  "geometry": {
    "coordinates": [
      119.10194,
      26.14611
    ],
    "type": "Point"
  }
}