{
  "type": "Feature",
  "properties": {
    "gn:admin1_code": "9.0",
    "gn:asciiname": "Kangcun",
    "gn:country_code": "CN",
    "gn:dem": 229,
    "gn:feature_class": "P",
    "gn:feature_code": "PPL",
    "gn:name": "Kangcun",
    "gn:population": 0,
    "gn:timezone": "Asia/Shanghai",
    "iso:country": "CN",
    "name:zho_x_preferred": [
      "康村"
    ],
    "wof:name": "Kangcun",
    "wof:placetype": "locality"
  },
  "geometry": {
    "coordinates": [
      112.59142,
      35.1715
    ],
    "type": "Point"
  }
}