{
  "type": "Feature",
  "properties": {
    "gn:admin1_code": "13.0",
    "gn:asciiname": "Akdala",
    "gn:country_code": "CN",
    "gn:dem": 1488,
    "gn:feature_class": "P",
    "gn:feature_code": "PPLA4",
    "gn:name": "Akdala",
    "gn:population": 0,
    "gn:timezone": "Asia/Shanghai",
    "iso:country": "CN",
    "name:ceb_x_preferred": [
      "Akdala"
    ],
    "name:fas_x_preferred": [
      "اکدالا"
    ],
    "name:kaz_x_preferred": [
      "Ақдала"
    ],
    "name:mkd_x_preferred": [
      "Акдала"
    ],
    "name:msa_x_preferred": [
      "Akdala"
    ],
    "name:por_x_preferred": [
      "Akdala"
    ],
    "name:rus_x_preferred": [
      "Акдала"
    ],
    "name:swe_x_preferred": [
      "Akdala"
    ],
    "name:uig_x_preferred": [
      "Aqdala"
    ],
    "name:uig_x_variant": [
      "ئاقدالا",
      "Ақдала"
    ],
    "name:ukr_x_preferred": [
      "Акдала"
    ],
    "name:und_x_variant": [
      "Akdala Xiang",
      "Akedala",
      "Akedala Xiang"
    ],
    "name:zho_x_preferred": [
      "阿克达拉"
    ],
    "name:zho_x_variant": [
      "阿克达拉乡"
    ],
    "wof:name": "Akdala",
    "wof:placetype": "locality"
  },
  "geometry": {
    "coordinates": [
      81.38,
      42.98861
    ],
    "type": "Point"
  }
}