{
  "type": "Feature",
  "properties": {
    "gn:admin1_code": "30.0",
    "gn:asciiname": "Macheng",
    "gn:country_code": "CN",
    "gn:dem": 25,
    "gn:feature_class": "P",
    "gn:feature_code": "PPL",
    "gn:name": "Macheng",
    "gn:population": 0,
    "gn:timezone": "Asia/Urumqi",
    "iso:country": "CN",
    "name:ceb_x_preferred": [
      "Macheng Shi"
    ],
    "name:deu_x_preferred": [
      "Macheng"
    ],
    "name:fin_x_preferred": [
      "Macheng"
    ],
    "name:fra_x_preferred": [
      "Macheng"
    ],
    "name:ita_x_preferred": [
      "Macheng"
    ],
    "name:jpn_x_preferred": [
      "麻城"
    ],
    "name:jpn_x_variant": [
      "麻城市"
    ],
    "name:kik_x_preferred": [
      "Macheng"
    ],
    "name:kor_x_preferred": [
      "마청시"
    ],
    "name:mlg_x_preferred": [
      "Macheng"
    ],
    "name:nor_x_preferred": [
      "Macheng"
    ],
    "name:pam_x_preferred": [
      "Macheng"
    ],
    "name:pol_x_preferred": [
      "Macheng"
    ],
    "name:swe_x_preferred": [
      "Macheng"
    ],
    "name:urd_x_preferred": [
      "ماچینگ"
    ],
    "name:vie_x_preferred": [
      "Ma Thành"
    ],
    "name:war_x_preferred": [
      "Macheng"
    ],
    "name:zho_x_preferred": [
      "麻城"
    ],
    "name:zho_x_variant": [
      "麻城市"
    ],
    "wof:name": "Macheng",
    "wof:placetype": "locality"
  },
  "geometry": {
    "coordinates": [
      110.18143,
      20.27812
    ],
    "type": "Point"
  }
}