{
  "type": "Feature",
  "properties": {
    "gn:admin1_code": "26.0",
    "gn:asciiname": "Zuitou",
    "gn:country_code": "CN",
    "gn:dem": 1542,
    "gn:feature_class": "P",
    "gn:feature_code": "PPLA3",
    "gn:name": "Zuitou",
    "gn:population": 0,
    "gn:timezone": "Asia/Shanghai",
    "iso:country": "CN",
    "name:und_x_variant": [
      "T’ai-pai",
      "Zuitou Zhen",
      "Taibai Xian",
      "Zuitoujie",
      "T’ai-pai-ch’ü",
      "Ta-pai",
      "Tsui-t’ou",
      "Tsui-t’ou-chen",
      "Tszuytouchzhen’",
      "Zuitou",
      "嘴头",
      "太白县"
    ],
    "name:zho_x_preferred": [
      "咀头镇"
    ],
    "wof:name": "Zuitou",
    "wof:placetype": "locality"
  },
  "geometry": {
    "coordinates": [
      107.31266,
      34.06219
    ],
    "type": "Point"
  }
}