{
  "type": "Feature",
  "properties": {
    "gn:admin1_code": "15.0",
    "gn:asciiname": "Zhangjiagou",
    "gn:country_code": "CN",
    "gn:dem": 1207,
    "gn:feature_class": "P",
    "gn:feature_code": "PPL",
    "gn:name": "Zhangjiagou",
    "gn:population": 0,
    "gn:timezone": "Asia/Shanghai",
    "iso:country": "CN",
    "name:zho_x_preferred": [
      "张家沟"
    ],
    "wof:name": "Zhangjiagou",
    "wof:placetype": "locality"
  },
  "geometry": {
    "coordinates": [
      104.82645,
      32.91121
    ],
    "type": "Point"
  }
}