{
  "type": "Feature",
  "properties": {
    "gn:admin1_code": "9",
    "gn:asciiname": "Linzhuang",
    "gn:country_code": "CN",
    "gn:dem": 43,
    "gn:feature_class": "P",
    "gn:feature_code": "PPL",
    "gn:name": "Linzhuang",
    "gn:population": 0,
    "gn:timezone": "Asia/Shanghai",
    "iso:country": "CN",
    "name:zho_x_preferred": [
      "林庄"
    ],
    "wof:name": "Linzhuang",
    "wof:placetype": "locality"
  },
  "geometry": {
    "coordinates": [
      116.043,
      34.0904
    ],
    "type": "Point"
  }
}