{
  "type": "Feature",
  "properties": {
    "gn:admin1_code": "5.0",
    "gn:asciiname": "Yong'antun",
    "gn:country_code": "CN",
    "gn:dem": 167,
    "gn:feature_class": "P",
    "gn:feature_code": "PPL",
    "gn:name": "Yong’antun",
    "gn:population": 0,
    "gn:timezone": "Asia/Shanghai",
    "iso:country": "CN",
    "name:und_x_variant": [
      "Yong’antun"
    ],
    "name:zho_x_preferred": [
      "永安屯"
    ],
    "wof:name": "Yong'antun",
    "wof:placetype": "locality"
  },
  "geometry": {
    "coordinates": [
      126.43397,
      44.4304
    ],
    "type": "Point"
  }
}