{
  "type": "Feature",
  "properties": {
    "gn:admin1_code": "8.0",
    "gn:asciiname": "Anshantun",
    "gn:country_code": "CN",
    "gn:dem": 233,
    "gn:feature_class": "P",
    "gn:feature_code": "PPL",
    "gn:name": "Anshantun",
    "gn:population": 0,
    "gn:timezone": "Asia/Shanghai",
    "iso:country": "CN",
    "name:zho_x_preferred": [
      "安山屯"
    ],
    "wof:name": "Anshantun",
    "wof:placetype": "locality"
  },
  "geometry": {
    "coordinates": [
      127.83836,
      45.25662
    ],
    "type": "Point"
  }
}