{
  "type": "Feature",
  "properties": {
    "gn:admin1_code": "16",
    "gn:asciiname": "Xiaodong",
    "gn:country_code": "CN",
    "gn:dem": 149,
    "gn:feature_class": "P",
    "gn:feature_code": "PPL",
    "gn:name": "Xiaodong",
    "gn:population": 0,
    "gn:timezone": "Asia/Shanghai",
    "iso:country": "CN",
    "name:zho_x_preferred": [
      "小垌"
    ],
    "wof:name": "Xiaodong",
    "wof:placetype": "locality"
  },
  "geometry": {
    "coordinates": [
      110.662,
      24.5003
    ],
    "type": "Point"
  }
}