{
  "type": "Feature",
  "properties": {
    "gn:admin1_code": "12.0",
    "gn:asciiname": "Jiahe",
    "gn:country_code": "CN",
    "gn:dem": 36,
    "gn:feature_class": "P",
    "gn:feature_code": "PPL",
    "gn:name": "Jiahe",
    "gn:population": 0,
    "gn:timezone": "Asia/Shanghai",
    "iso:country": "CN",
    "name:zho_x_preferred": [
      "夹河"
    ],
    "wof:name": "Jiahe",
    "wof:placetype": "locality"
  },
  "geometry": {
    "coordinates": [
      113.64683,
      31.17163
    ],
    "type": "Point"
  }
}