{
  "type": "Feature",
  "properties": {
    "gn:admin1_code": "13.0",
    "gn:asciiname": "Kostik",
    "gn:country_code": "CN",
    "gn:dem": 513,
    "gn:feature_class": "P",
    "gn:feature_code": "PPLA4",
    "gn:name": "Kostik",
    "gn:population": 0,
    "gn:timezone": "Asia/Urumqi",
    "iso:country": "CN",
    "name:uig_x_preferred": [
      "K̩ostik̩"
    ],
    "name:uig_x_variant": [
      "Qostiq",
      "قوستىق",
      "Қостық"
    ],
    "name:und_x_variant": [
      "Kostik Xiang",
      "Kostik",
      "Kuositeke",
      "Kuositeke Xiang"
    ],
    "name:zho_x_preferred": [
      "阔斯特克"
    ],
    "name:zho_x_variant": [
      "阔斯特克乡"
    ],
    "wof:name": "Kostik",
    "wof:placetype": "locality"
  },
  "geometry": {
    "coordinates": [
      87.33078,
      47.78682
    ],
    "type": "Point"
  }
}