{
  "type": "Feature",
  "properties": {
    "gn:admin1_code": "11.0",
    "gn:asciiname": "Zhuzhai",
    "gn:country_code": "CN",
    "gn:dem": 412,
    "gn:feature_class": "P",
    "gn:feature_code": "PPL",
    "gn:name": "Zhuzhai",
    "gn:population": 0,
    "gn:timezone": "Asia/Shanghai",
    "iso:country": "CN",
    "name:zho_x_preferred": [
      "竹寨"
    ],
    "name:zho_x_variant": [
      "朱寨镇"
    ],
    "wof:name": "Zhuzhai",
    "wof:placetype": "locality"
  },
  "geometry": {
    "coordinates": [
      109.80974,
      28.37125
    ],
    "type": "Point"
  }
}