{
  "type": "Feature",
  "properties": {
    "gn:admin1_code": "11.0",
    "gn:asciiname": "Shuangjiangkou",
    "gn:country_code": "CN",
    "gn:dem": 136,
    "gn:feature_class": "P",
    "gn:feature_code": "PPL",
    "gn:name": "Shuangjiangkou",
    "gn:population": 0,
    "gn:timezone": "Asia/Shanghai",
    "iso:country": "CN",
    "name:fra_x_preferred": [
      "Shuangjiangkou"
    ],
    "name:jpn_x_preferred": [
      "双江口鎮"
    ],
    "name:zho_x_preferred": [
      "双江口"
    ],
    "name:zho_x_variant": [
      "双江口镇"
    ],
    "wof:name": "Shuangjiangkou",
    "wof:placetype": "locality"
  },
  "geometry": {
    "coordinates": [
      113.68065,
      28.19474
    ],
    "type": "Point"
  }
}