{
  "type": "Feature",
  "properties": {
    "gn:admin1_code": "9.0",
    "gn:asciiname": "Gangkou'an",
    "gn:country_code": "CN",
    "gn:dem": 87,
    "gn:feature_class": "P",
    "gn:feature_code": "PPL",
    "gn:name": "Gangkou’an",
    "gn:population": 0,
    "gn:timezone": "Asia/Shanghai",
    "iso:country": "CN",
    "name:und_x_variant": [
      "Gangkou’an"
    ],
    "name:zho_x_preferred": [
      "岗口岸"
    ],
    "wof:name": "Gangkou'an",
    "wof:placetype": "locality"
  },
  "geometry": {
    "coordinates": [
      112.5867,
      32.54996
    ],
    "type": "Point"
  }
}