{
  "type": "Feature",
  "properties": {
    "gn:admin1_code": "14.0",
    "gn:asciiname": "Muchangangcun",
    "gn:country_code": "CN",
    "gn:dem": 3984,
    "gn:feature_class": "P",
    "gn:feature_code": "PPL",
    "gn:name": "Muchangangcun",
    "gn:population": 0,
    "gn:timezone": "Asia/Urumqi",
    "iso:country": "CN",
    "name:zho_x_preferred": [
      "然昌村"
    ],
    "wof:name": "Muchangangcun",
    "wof:placetype": "locality"
  },
  "geometry": {
    "coordinates": [
      95.79471,
      30.67922
    ],
    "type": "Point"
  }
}