{
  "type": "Feature",
  "properties": {
    "gn:admin1_code": "24.0",
    "gn:asciiname": "Xisongjiachangcun",
    "gn:country_code": "CN",
    "gn:dem": 1002,
    "gn:feature_class": "P",
    "gn:feature_code": "PPL",
    "gn:name": "Xisongjiachangcun",
    "gn:population": 0,
    "gn:timezone": "Asia/Shanghai",
    "iso:country": "CN",
    "name:zho_x_preferred": [
      "西宋家厂村"
    ],
    "wof:name": "Xisongjiachangcun",
    "wof:placetype": "locality"
  },
  "geometry": {
    "coordinates": [
      114.02115,
      40.40272
    ],
    "type": "Point"
  }
}