{
  "type": "Feature",
  "properties": {
    "gn:admin1_code": "18.0",
    "gn:asciiname": "Xinzhai",
    "gn:country_code": "CN",
    "gn:dem": 1111,
    "gn:feature_class": "P",
    "gn:feature_code": "PPL",
    "gn:name": "Xinzhai",
    "gn:population": 0,
    "gn:timezone": "Asia/Shanghai",
    "iso:country": "CN",
    "name:nor_x_preferred": [
      "Xinzhai"
    ],
    "name:swe_x_preferred": [
      "Xinzhai"
    ],
    "name:zho_x_preferred": [
      "新寨"
    ],
    "name:zho_x_variant": [
      "新砦遗址"
    ],
    "wof:name": "Xinzhai",
    "wof:placetype": "locality"
  },
  "geometry": {
    "coordinates": [
      107.367,
      26.4853
    ],
    "type": "Point"
  }
}