{
  "type": "Feature",
  "properties": {
    "gn:admin1_code": "18",
    "gn:asciiname": "Dayuan",
    "gn:country_code": "CN",
    "gn:dem": 1071,
    "gn:feature_class": "P",
    "gn:feature_code": "PPL",
    "gn:name": "Dayuan",
    "gn:population": 0,
    "gn:timezone": "Asia/Shanghai",
    "iso:country": "CN",
    "name:ces_x_preferred": [
      "Ta-jüan"
    ],
    "name:deu_x_preferred": [
      "Dayuan"
    ],
    "name:ell_x_preferred": [
      "Νταγιουάν"
    ],
    "name:fas_x_preferred": [
      "دایوان"
    ],
    "name:hye_x_preferred": [
      "Տայյուան"
    ],
    "name:ido_x_preferred": [
      "Ta-Yuan"
    ],
    "name:ind_x_preferred": [
      "Dayuan"
    ],
    "name:ita_x_preferred": [
      "Dayuan"
    ],
    "name:kir_x_preferred": [
      "Дабан мамлекети"
    ],
    "name:lat_x_preferred": [
      "Taiuani"
    ],
    "name:lit_x_preferred": [
      "Dajuanas"
    ],
    "name:rus_x_preferred": [
      "Давань"
    ],
    "name:ukr_x_preferred": [
      "Даюань"
    ],
    "name:uzb_x_preferred": [
      "Davan"
    ],
    "name:vie_x_preferred": [
      "Đại Uyên"
    ],
    "name:zho_x_preferred": [
      "大院"
    ],
    "wof:name": "Dayuan",
    "wof:placetype": "locality"
  },
  "geometry": {
    "coordinates": [
      107.783,
      27.0855
    ],
    "type": "Point"
  }
}