{
  "type": "Feature",
  "properties": {
    "gn:admin1_code": "26.0",
    "gn:asciiname": "Huoshao'an",
    "gn:country_code": "CN",
    "gn:dem": 918,
    "gn:feature_class": "P",
    "gn:feature_code": "PPL",
    "gn:name": "Huoshao’an",
    "gn:population": 0,
    "gn:timezone": "Asia/Shanghai",
    "iso:country": "CN",
    "name:und_x_variant": [
      "Huoshao’an"
    ],
    "name:zho_x_preferred": [
      "火烧庵"
    ],
    "wof:name": "Huoshao'an",
    "wof:placetype": "locality"
  },
  "geometry": {
    "coordinates": [
      108.36789,
      32.90639
    ],
    "type": "Point"
  }
}