{
  "type": "Feature",
  "properties": {
    "gn:admin1_code": "3.0",
    "gn:asciiname": "Ganjia Tukuli",
    "gn:country_code": "CN",
    "gn:dem": 465,
    "gn:feature_class": "P",
    "gn:feature_code": "PPL",
    "gn:name": "Ganjia Tukuli",
    "gn:population": 0,
    "gn:timezone": "Asia/Shanghai",
    "iso:country": "CN",
    "name:zho_x_preferred": [
      "甘家土库里"
    ],
    "wof:name": "Ganjia Tukuli",
    "wof:placetype": "locality"
  },
  "geometry": {
    "coordinates": [
      115.149,
      28.8419
    ],
    "type": "Point"
  }
}