{
  "type": "Feature",
  "properties": {
    "gn:admin1_code": "3.0",
    "gn:asciiname": "Yunting",
    "gn:country_code": "CN",
    "gn:dem": 109,
    "gn:feature_class": "P",
    "gn:feature_code": "PPL",
    "gn:name": "Yunting",
    "gn:population": 0,
    "gn:timezone": "Asia/Shanghai",
    "iso:country": "CN",
    "name:und_x_variant": [
      "云亭"
    ],
    "wof:name": "Yunting",
    "wof:placetype": "locality"
  },
  "geometry": {
    "coordinates": [
      115.9651,
      27.85897000000001
    ],
    "type": "Point"
  }
}