{
  "type": "Feature",
  "properties": {
    "gn:admin1_code": "07",
    "gn:asciiname": "Laiwu",
    "gn:country_code": "CN",
    "gn:dem": 476,
    "gn:feature_class": "P",
    "gn:feature_code": "PPL",
    "gn:name": "Laiwu",
    "gn:population": 0,
    "gn:timezone": "Asia/Shanghai",
    "iso:country": "CN",
    "name:afr_x_preferred": [
      "Laiwu"
    ],
    "name:ara_x_preferred": [
      "لايوو"
    ],
    "name:cdo_x_preferred": [
      "Lài-ù"
    ],
    "name:ceb_x_preferred": [
      "Laiwu"
    ],
    "name:ces_x_preferred": [
      "Laj-wu"
    ],
    "name:dan_x_preferred": [
      "Laiwu"
    ],
    "name:deu_x_preferred": [
      "Laiwu"
    ],
    "name:eus_x_preferred": [
      "Laiwu"
    ],
    "name:fas_x_preferred": [
      "لایوو"
    ],
    "name:fin_x_preferred": [
      "Laiwu"
    ],
    "name:fra_x_preferred": [
      "Laiwu"
    ],
    "name:heb_x_preferred": [
      "לאיוו"
    ],
    "name:hun_x_preferred": [
      "Laiwu"
    ],
    "name:ita_x_preferred": [
      "Laiwu"
    ],
    "name:jpn_x_preferred": [
      "莱蕪市"
    ],
    "name:kik_x_preferred": [
      "Laiwu"
    ],
    "name:kor_x_preferred": [
      "라이우시"
    ],
    "name:mlg_x_preferred": [
      "Laiwu"
    ],
    "name:nld_x_preferred": [
      "Laiwu"
    ],
    "name:nno_x_preferred": [
      "Laiwu"
    ],
    "name:nor_x_preferred": [
      "Laiwu"
    ],
    "name:pol_x_preferred": [
      "Laiwu"
    ],
    "name:rus_x_preferred": [
      "Лайу"
    ],
    "name:spa_x_preferred": [
      "Laiwu"
    ],
    "name:swe_x_preferred": [
      "Laiwu"
    ],
    "name:tgl_x_preferred": [
      "Laiwu"
    ],
    "name:tha_x_preferred": [
      "ไหลอู๋"
    ],
    "name:tur_x_preferred": [
      "Laiwu"
    ],
    "name:urd_x_preferred": [
      "لائوو"
    ],
    "name:vie_x_preferred": [
      "Lai Vu"
    ],
    "name:war_x_preferred": [
      "Laiwu"
    ],
    "name:wuu_x_preferred": [
      "莱芜市"
    ],
    "name:zho_x_preferred": [
      "赖屋"
    ],
    "name:zho_x_variant": [
      "莱芜市"
    ],
    "wof:name": "Laiwu",
    "wof:placetype": "locality"
  },
  "geometry": {
    "coordinates": [
      116.33879,
      24.89821
    ],
    "type": "Point"
  }
}