{
  "type": "Feature",
  "properties": {
    "gn:admin1_code": "25",
    "gn:asciiname": "Xiguotuan",
    "gn:country_code": "CN",
    "gn:dem": 61,
    "gn:feature_class": "P",
    "gn:feature_code": "PPL",
    "gn:name": "Xiguotuan",
    "gn:population": 0,
    "gn:timezone": "Asia/Shanghai",
    "iso:country": "CN",
    "name:zho_x_preferred": [
      "西郭疃"
    ],
    "wof:name": "Xiguotuan",
    "wof:placetype": "locality"
  },
  "geometry": {
    "coordinates": [
      118.448,
      34.8324
    ],
    "type": "Point"
  }
}