{
  "type": "Feature",
  "properties": {
    "gn:admin1_code": "26.0",
    "gn:asciiname": "Chang'ao",
    "gn:country_code": "CN",
    "gn:dem": 607,
    "gn:feature_class": "P",
    "gn:feature_code": "PPL",
    "gn:name": "Chang’ao",
    "gn:population": 0,
    "gn:timezone": "Asia/Shanghai",
    "iso:country": "CN",
    "name:und_x_variant": [
      "Chang’ao",
      "长凹"
    ],
    "wof:name": "Chang'ao",
    "wof:placetype": "locality"
  },
  "geometry": {
    "coordinates": [
      107.85252,
      34.17602
    ],
    "type": "Point"
  }
}