{
  "type": "Feature",
  "properties": {
    "gn:admin1_code": "14.0",
    "gn:asciiname": "Parecun",
    "gn:country_code": "CN",
    "gn:dem": 4095,
    "gn:feature_class": "P",
    "gn:feature_code": "PPL",
    "gn:name": "Parecun",
    "gn:population": 0,
    "gn:timezone": "Asia/Urumqi",
    "iso:country": "CN",
    "name:zho_x_preferred": [
      "帕热村"
    ],
    "wof:name": "Parecun",
    "wof:placetype": "locality"
  },
  "geometry": {
    "coordinates": [
      87.39275,
      29.11894
    ],
    "type": "Point"
  }
}