{
  "type": "Feature",
  "properties": {
    "gn:admin1_code": "18",
    "gn:asciiname": "Liangshuijing",
    "gn:country_code": "CN",
    "gn:dem": 1202,
    "gn:feature_class": "P",
    "gn:feature_code": "PPL",
    "gn:name": "Liangshuijing",
    "gn:population": 0,
    "gn:timezone": "Asia/Shanghai",
    "iso:country": "CN",
    "name:zho_x_preferred": [
      "凉水井"
    ],
    "wof:name": "Liangshuijing",
    "wof:placetype": "locality"
  },
  "geometry": {
    "coordinates": [
      106.76,
      28.3366
    ],
    "type": "Point"
  }
}