{
  "type": "Feature",
  "properties": {
    "gn:admin1_code": "7.0",
    "gn:asciiname": "Luoyang",
    "gn:country_code": "CN",
    "gn:dem": 936,
    "gn:feature_class": "P",
    "gn:feature_code": "PPL",
    "gn:name": "Luoyang",
    "gn:population": 0,
    "gn:timezone": "Asia/Shanghai",
    "iso:country": "CN",
    "name:afr_x_preferred": [
      "Luoyang"
    ],
    "name:ara_x_preferred": [
      "لويانغ"
    ],
    "name:ast_x_preferred": [
      "Luoyang"
    ],
    "name:bel_x_preferred": [
      "Лаян"
    ],
    "name:bod_x_preferred": [
      "ལུའོ་དབྱང་།"
    ],
    "name:bre_x_preferred": [
      "Luoyang"
    ],
    "name:bul_x_preferred": [
      "Луоян"
    ],
    "name:cat_x_preferred": [
      "Luoyang"
    ],
    "name:cdo_x_preferred": [
      "Lŏk-iòng"
    ],
    "name:ces_x_preferred": [
      "Luo-jang"
    ],
    "name:cym_x_preferred": [
      "Luoyang"
    ],
    "name:dan_x_preferred": [
      "Luoyang"
    ],
    "name:deu_x_preferred": [
      "Luoyang"
    ],
    "name:ell_x_preferred": [
      "Λουογιάνγκ"
    ],
    "name:epo_x_preferred": [
      "Lŭojango"
    ],
    "name:est_x_preferred": [
      "Luoyang"
    ],
    "name:eus_x_preferred": [
      "Luoyang"
    ],
    "name:fas_x_preferred": [
      "لوئویانگ"
    ],
    "name:fin_x_preferred": [
      "Luoyang"
    ],
    "name:fra_x_preferred": [
      "Luoyang"
    ],
    "name:heb_x_preferred": [
      "לוו-יאנג"
    ],
    "name:hin_x_preferred": [
      "लुओयांग"
    ],
    "name:hrv_x_preferred": [
      "Luoyang"
    ],
    "name:hun_x_preferred": [
      "Lojang"
    ],
    "name:ind_x_preferred": [
      "Luoyang"
    ],
    "name:ita_x_preferred": [
      "Luoyang"
    ],
    "name:jpn_x_preferred": [
      "洛陽市"
    ],
    "name:kat_x_preferred": [
      "ლოიანი"
    ],
    "name:kik_x_preferred": [
      "Luoyang"
    ],
    "name:kir_x_preferred": [
      "Лоян шаары"
    ],
    "name:kor_x_preferred": [
      "뤄양시"
    ],
    "name:lit_x_preferred": [
      "Luojangas"
    ],
    "name:mkd_x_preferred": [
      "Луојанг"
    ],
    "name:mlg_x_preferred": [
      "Luoyang"
    ],
    "name:nld_x_preferred": [
      "Luoyang"
    ],
    "name:nno_x_preferred": [
      "Luoyang"
    ],
    "name:nor_x_preferred": [
      "Luoyang"
    ],
    "name:pam_x_preferred": [
      "Luoyang"
    ],
    "name:pol_x_preferred": [
      "Luoyang"
    ],
    "name:por_x_preferred": [
      "Luoyang"
    ],
    "name:rus_x_preferred": [
      "Лоян"
    ],
    "name:sco_x_preferred": [
      "Luoyang"
    ],
    "name:spa_x_preferred": [
      "Luoyang"
    ],
    "name:srp_x_preferred": [
      "Луојанг"
    ],
    "name:swe_x_preferred": [
      "Luoyang"
    ],
    "name:tam_x_preferred": [
      "இலுவோயங்"
    ],
    "name:tgl_x_preferred": [
      "Luoyang"
    ],
    "name:tha_x_preferred": [
      "ลั่วหยาง"
    ],
    "name:tur_x_preferred": [
      "Luoyang"
    ],
    "name:uig_x_preferred": [
      "لوياڭ شەھىرى"
    ],
    "name:ukr_x_preferred": [
      "Лоян"
    ],
    "name:urd_x_preferred": [
      "لوویانگ"
    ],
    "name:vie_x_preferred": [
      "Lạc Dương"
    ],
    "name:war_x_preferred": [
      "Luoyang"
    ],
    "name:zho_x_preferred": [
      "Luoyang"
    ],
    "name:zho_x_variant": [
      "罗洋",
      "洛阳市"
    ],
    "wof:name": "Luoyang",
    "wof:placetype": "locality"
  },
  "geometry": {
    "coordinates": [
      118.83523999999998,
      26.44538
    ],
    "type": "Point"
  }
}