{
  "type": "Feature",
  "properties": {
    "gn:admin1_code": "9.0",
    "gn:asciiname": "Dongzhuang",
    "gn:country_code": "CN",
    "gn:dem": 79,
    "gn:feature_class": "P",
    "gn:feature_code": "PPL",
    "gn:name": "Dongzhuang",
    "gn:population": 0,
    "gn:timezone": "Asia/Shanghai",
    "iso:country": "CN",
    "name:zho_x_preferred": [
      "董庄"
    ],
    "wof:name": "Dongzhuang",
    "wof:placetype": "locality"
  },
  "geometry": {
    "coordinates": [
      113.70192,
      35.21658
    ],
    "type": "Point"
  }
}