{
  "type": "Feature",
  "properties": {
    "gn:admin1_code": "19.0",
    "gn:asciiname": "Tabu",
    "gn:country_code": "CN",
    "gn:dem": 141,
    "gn:feature_class": "P",
    "gn:feature_code": "PPL",
    "gn:name": "Tabu",
    "gn:population": 0,
    "gn:timezone": "Asia/Shanghai",
    "iso:country": "CN",
    "name:ceb_x_preferred": [
      "Tabu"
    ],
    "name:deu_x_preferred": [
      "Tabu"
    ],
    "name:fin_x_preferred": [
      "Tabu"
    ],
    "name:fra_x_preferred": [
      "Tabu"
    ],
    "name:ita_x_preferred": [
      "Tabù"
    ],
    "name:jpn_x_preferred": [
      "タブウ"
    ],
    "name:nds_x_preferred": [
      "Tabu"
    ],
    "name:pol_x_preferred": [
      "Tabu"
    ],
    "name:por_x_preferred": [
      "Tabu"
    ],
    "name:rus_x_preferred": [
      "Табу"
    ],
    "name:slk_x_preferred": [
      "Tabu"
    ],
    "name:slv_x_preferred": [
      "Tabu"
    ],
    "name:swe_x_preferred": [
      "Tabu"
    ],
    "name:zho_x_preferred": [
      "塔堡"
    ],
    "wof:name": "Tabu",
    "wof:placetype": "locality"
  },
  "geometry": {
    "coordinates": [
      124.032,
      40.6832
    ],
    "type": "Point"
  }
}