{
  "type": "Feature",
  "properties": {
    "gn:admin1_code": "10.0",
    "gn:asciiname": "Yingtou",
    "gn:country_code": "CN",
    "gn:dem": 247,
    "gn:feature_class": "P",
    "gn:feature_code": "PPL",
    "gn:name": "Yingtou",
    "gn:population": 0,
    "gn:timezone": "Asia/Shanghai",
    "iso:country": "CN",
    "name:und_x_variant": [
      "Ying-t’ou-chen",
      "Yingtou"
    ],
    "name:zho_x_preferred": [
      "营头"
    ],
    "wof:name": "Yingtou",
    "wof:placetype": "locality"
  },
  "geometry": {
    "coordinates": [
      114.132,
      37.0559
    ],
    "type": "Point"
  }
}