{
  "type": "Feature",
  "properties": {
    "gn:admin1_code": "32.0",
    "gn:asciiname": "Shiwei",
    "gn:country_code": "CN",
    "gn:dem": 861,
    "gn:feature_class": "P",
    "gn:feature_code": "PPL",
    "gn:name": "Shiwei",
    "gn:population": 0,
    "gn:timezone": "Asia/Shanghai",
    "iso:country": "CN",
    "name:aze_x_preferred": [
      "Şiveylər"
    ],
    "name:bul_x_preferred": [
      "Шъуей"
    ],
    "name:mon_x_preferred": [
      "Шивэй"
    ],
    "name:rus_x_preferred": [
      "Шивэй"
    ],
    "name:szl_x_preferred": [
      "Siyłeje"
    ],
    "name:ukr_x_preferred": [
      "Шивей"
    ],
    "name:und_x_variant": [
      "石桅"
    ],
    "wof:name": "Shiwei",
    "wof:placetype": "locality"
  },
  "geometry": {
    "coordinates": [
      106.29874,
      32.17726
    ],
    "type": "Point"
  }
}