{
  "type": "Feature",
  "properties": {
    "gn:admin1_code": "10",
    "gn:asciiname": "Huangmenzi",
    "gn:country_code": "CN",
    "gn:dem": 345,
    "gn:feature_class": "P",
    "gn:feature_code": "PPL",
    "gn:name": "Huangmenzi",
    "gn:population": 0,
    "gn:timezone": "Asia/Shanghai",
    "iso:country": "CN",
    "name:zho_x_preferred": [
      "黄门子"
    ],
    "wof:name": "Huangmenzi",
    "wof:placetype": "locality"
  },
  "geometry": {
    "coordinates": [
      117.8119,
      40.37796
    ],
    "type": "Point"
  }
}