{
  "type": "Feature",
  "properties": {
    "gn:admin1_code": "33",
    "gn:asciiname": "Tuxiang",
    "gn:country_code": "CN",
    "gn:dem": 842,
    "gn:feature_class": "P",
    "gn:feature_code": "PPLA4",
    "gn:name": "Tuxiang",
    "gn:population": 0,
    "gn:timezone": "Asia/Shanghai",
    "iso:country": "CN",
    "name:und_x_variant": [
      "T’u-hsiang",
      "T’u-hsiang-pa",
      "Tuxiang",
      "Tuxiang Zhen",
      "Xiongjiabang"
    ],
    "name:zho_x_preferred": [
      "吐祥"
    ],
    "name:zho_x_variant": [
      "吐祥镇",
      "熊家塝"
    ],
    "wof:name": "Tuxiang",
    "wof:placetype": "locality"
  },
  "geometry": {
    "coordinates": [
      109.15556,
      30.71293
    ],
    "type": "Point"
  }
}