{
  "type": "Feature",
  "properties": {
    "gn:admin1_code": "05",
    "gn:asciiname": "Choushui",
    "gn:country_code": "CN",
    "gn:dem": 503,
    "gn:feature_class": "P",
    "gn:feature_code": "PPLA4",
    "gn:name": "Choushui",
    "gn:population": 0,
    "gn:timezone": "Asia/Shanghai",
    "iso:country": "CN",
    "name:und_x_variant": [
      "Ch’ou-shui-ho",
      "Choushui",
      "抽水",
      "Choushui Xiang",
      "抽水乡"
    ],
    "wof:name": "Choushui",
    "wof:placetype": "locality"
  },
  "geometry": {
    "coordinates": [
      127.07627,
      42.39463
    ],
    "type": "Point"
  }
}