{
  "type": "Feature",
  "properties": {
    "gn:admin1_code": "20.0",
    "gn:asciiname": "Xiaozhuangwo",
    "gn:country_code": "CN",
    "gn:dem": 1435,
    "gn:feature_class": "P",
    "gn:feature_code": "PPL",
    "gn:name": "Xiaozhuangwo",
    "gn:population": 0,
    "gn:timezone": "Asia/Shanghai",
    "iso:country": "CN",
    "name:und_x_variant": [
      "小庄窝"
    ],
    "wof:name": "Xiaozhuangwo",
    "wof:placetype": "locality"
  },
  "geometry": {
    "coordinates": [
      111.81128,
      39.64535
    ],
    "type": "Point"
  }
}