{
  "type": "Feature",
  "properties": {
    "gn:admin1_code": "30.0",
    "gn:asciiname": "Guantoudong",
    "gn:country_code": "CN",
    "gn:dem": 495,
    "gn:feature_class": "P",
    "gn:feature_code": "PPL",
    "gn:name": "Guantoudong",
    "gn:population": 0,
    "gn:timezone": "Asia/Shanghai",
    "iso:country": "CN",
    "name:zho_x_preferred": [
      "Guantoudong"
    ],
    "name:zho_x_variant": [
      "观头洞"
    ],
    "wof:name": "Guantoudong",
    "wof:placetype": "locality"
  },
  "geometry": {
    "coordinates": [
      112.59722,
      25.10083
    ],
    "type": "Point"
  }
}