{
  "type": "Feature",
  "properties": {
    "gn:admin1_code": "3",
    "gn:asciiname": "Xiayu",
    "gn:country_code": "CN",
    "gn:dem": 202,
    "gn:feature_class": "P",
    "gn:feature_code": "PPL",
    "gn:name": "Xiayu",
    "gn:population": 0,
    "gn:timezone": "Asia/Shanghai",
    "iso:country": "CN",
    "name:zho_x_preferred": [
      "下雨"
    ],
    "name:zho_x_variant": [
      "夏雨"
    ],
    "wof:name": "Xiayu",
    "wof:placetype": "locality"
  },
  "geometry": {
    "coordinates": [
      113.96188,
      26.90865
    ],
    "type": "Point"
  }
}