{
  "type": "Feature",
  "properties": {
    "gn:admin1_code": "9.0",
    "gn:asciiname": "Taicang",
    "gn:country_code": "CN",
    "gn:dem": 162,
    "gn:feature_class": "P",
    "gn:feature_code": "PPL",
    "gn:name": "Taicang",
    "gn:population": 0,
    "gn:timezone": "Asia/Shanghai",
    "iso:country": "CN",
    "name:ces_x_preferred": [
      "Tchaj-cchang"
    ],
    "name:cym_x_preferred": [
      "Taicang"
    ],
    "name:deu_x_preferred": [
      "Taicang"
    ],
    "name:fas_x_preferred": [
      "تایکانگ"
    ],
    "name:fra_x_preferred": [
      "Taicang"
    ],
    "name:ita_x_preferred": [
      "Taicang"
    ],
    "name:jpn_x_preferred": [
      "太倉市"
    ],
    "name:kik_x_preferred": [
      "Taicang"
    ],
    "name:kor_x_preferred": [
      "타이창시"
    ],
    "name:nld_x_preferred": [
      "Taicang"
    ],
    "name:nor_x_preferred": [
      "Taicang"
    ],
    "name:pol_x_preferred": [
      "Taicang"
    ],
    "name:rus_x_preferred": [
      "Тайцан"
    ],
    "name:spa_x_preferred": [
      "Taicang"
    ],
    "name:swe_x_preferred": [
      "Taicang"
    ],
    "name:tgl_x_preferred": [
      "Taicang"
    ],
    "name:urd_x_preferred": [
      "تایکانگ"
    ],
    "name:vie_x_preferred": [
      "Thái Thương"
    ],
    "name:zho_x_preferred": [
      "太仓"
    ],
    "name:zho_x_variant": [
      "太仓市"
    ],
    "wof:name": "Taicang",
    "wof:placetype": "locality"
  },
  "geometry": {
    "coordinates": [
      112.55241,
      34.75251
    ],
    "type": "Point"
  }
}