{
  "type": "Feature",
  "properties": {
    "gn:admin1_code": "16",
    "gn:asciiname": "Sanchatian",
    "gn:country_code": "CN",
    "gn:dem": 438,
    "gn:feature_class": "P",
    "gn:feature_code": "PPL",
    "gn:name": "Sanchatian",
    "gn:population": 0,
    "gn:timezone": "Asia/Shanghai",
    "iso:country": "CN",
    "name:zho_x_preferred": [
      "三叉田"
    ],
    "wof:name": "Sanchatian",
    "wof:placetype": "locality"
  },
  "geometry": {
    "coordinates": [
      110.46,
      25.8043
    ],
    "type": "Point"
  }
}