{
  "type": "Feature",
  "properties": {
    "gn:admin1_code": "03",
    "gn:asciiname": "Furong",
    "gn:country_code": "CN",
    "gn:dem": 139,
    "gn:feature_class": "P",
    "gn:feature_code": "PPLA3",
    "gn:name": "Furong",
    "gn:population": 0,
    "gn:timezone": "Asia/Shanghai",
    "iso:country": "CN",
    "name:ces_x_preferred": [
      "Wan-an"
    ],
    "name:deu_x_preferred": [
      "Wan’an"
    ],
    "name:fas_x_preferred": [
      "شهرستان وانان"
    ],
    "name:jpn_x_preferred": [
      "万安県"
    ],
    "name:kor_x_preferred": [
      "완안현"
    ],
    "name:nor_x_preferred": [
      "Wan'an"
    ],
    "name:swe_x_preferred": [
      "Wan'an"
    ],
    "name:und_x_variant": [
      "Wan-an-hsien-ch’eng",
      "Wan-an-hsien",
      "Furong",
      "Wan’an Xian"
    ],
    "name:vie_x_preferred": [
      "Vạn An"
    ],
    "name:zho_x_preferred": [
      "芙蓉"
    ],
    "name:zho_x_variant": [
      "万安县"
    ],
    "wof:name": "Furong",
    "wof:placetype": "locality"
  },
  "geometry": {
    "coordinates": [
      114.76667,
      26.45
    ],
    "type": "Point"
  }
}