{
  "type": "Feature",
  "properties": {
    "gn:admin1_code": "16.0",
    "gn:asciiname": "Napo",
    "gn:country_code": "CN",
    "gn:dem": 240,
    "gn:feature_class": "P",
    "gn:feature_code": "PPL",
    "gn:name": "Napo",
    "gn:population": 0,
    "gn:timezone": "Asia/Shanghai",
    "iso:country": "CN",
    "name:ben_x_preferred": [
      "নাপো"
    ],
    "name:ceb_x_preferred": [
      "Napo"
    ],
    "name:deu_x_preferred": [
      "Napo"
    ],
    "name:fas_x_preferred": [
      "ناپو"
    ],
    "name:fra_x_preferred": [
      "Napo"
    ],
    "name:heb_x_preferred": [
      "נאפו"
    ],
    "name:hin_x_preferred": [
      "नेपो"
    ],
    "name:hun_x_preferred": [
      "Napo"
    ],
    "name:ind_x_preferred": [
      "Napo"
    ],
    "name:ita_x_preferred": [
      "Napo"
    ],
    "name:nld_x_preferred": [
      "Napo"
    ],
    "name:nor_x_preferred": [
      "Napo"
    ],
    "name:por_x_preferred": [
      "Napo"
    ],
    "name:que_x_preferred": [
      "Napu"
    ],
    "name:ron_x_preferred": [
      "Napo"
    ],
    "name:spa_x_preferred": [
      "Napo"
    ],
    "name:swe_x_preferred": [
      "Napo"
    ],
    "name:tur_x_preferred": [
      "Napo"
    ],
    "name:urd_x_preferred": [
      "ناپو"
    ],
    "name:zho_x_preferred": [
      "那坡"
    ],
    "wof:name": "Napo",
    "wof:placetype": "locality"
  },
  "geometry": {
    "coordinates": [
      107.957,
      21.9651
    ],
    "type": "Point"
  }
}