{
  "type": "Feature",
  "properties": {
    "gn:admin1_code": "32.0",
    "gn:asciiname": "Sanjiaosi",
    "gn:country_code": "CN",
    "gn:dem": 362,
    "gn:feature_class": "P",
    "gn:feature_code": "PPL",
    "gn:name": "Sanjiaosi",
    "gn:population": 0,
    "gn:timezone": "Asia/Shanghai",
    "iso:country": "CN",
    "name:zho_x_preferred": [
      "三教寺"
    ],
    "wof:name": "Sanjiaosi",
    "wof:placetype": "locality"
  },
  "geometry": {
    "coordinates": [
      104.51836,
      28.72751
    ],
    "type": "Point"
  }
}