{
  "type": "Feature",
  "properties": {
    "gn:admin1_code": "16",
    "gn:asciiname": "Yutang",
    "gn:country_code": "CN",
    "gn:dem": 204,
    "gn:feature_class": "P",
    "gn:feature_code": "PPL",
    "gn:name": "Yutang",
    "gn:population": 0,
    "gn:timezone": "Asia/Shanghai",
    "iso:country": "CN",
    "name:zho_x_preferred": [
      "鱼塘"
    ],
    "wof:name": "Yutang",
    "wof:placetype": "locality"
  },
  "geometry": {
    "coordinates": [
      110.329,
      24.6813
    ],
    "type": "Point"
  }
}