{
  "type": "Feature",
  "properties": {
    "gn:admin1_code": "16",
    "gn:asciiname": "Nawancun",
    "gn:country_code": "CN",
    "gn:dem": 368,
    "gn:feature_class": "P",
    "gn:feature_code": "PPL",
    "gn:name": "Nawancun",
    "gn:population": 0,
    "gn:timezone": "Asia/Shanghai",
    "iso:country": "CN",
    "name:und_x_variant": [
      "Na-wu-ts’un",
      "Nawancun"
    ],
    "name:zho_x_preferred": [
      "那万村"
    ],
    "wof:name": "Nawancun",
    "wof:placetype": "locality"
  },
  "geometry": {
    "coordinates": [
      105.906,
      23.0618
    ],
    "type": "Point"
  }
}