{
  "type": "Feature",
  "properties": {
    "gn:admin1_code": "14.0",
    "gn:asciiname": "Bomu",
    "gn:country_code": "CN",
    "gn:dem": 4705,
    "gn:feature_class": "P",
    "gn:feature_code": "PPL",
    "gn:name": "Bomu",
    "gn:population": 0,
    "gn:timezone": "Asia/Urumqi",
    "iso:country": "CN",
    "name:ara_x_preferred": [
      "بومو"
    ],
    "name:ben_x_preferred": [
      "বোমু"
    ],
    "name:ceb_x_preferred": [
      "Bomu"
    ],
    "name:ell_x_preferred": [
      "Μπόμου"
    ],
    "name:fas_x_preferred": [
      "بومو"
    ],
    "name:fra_x_preferred": [
      "Bomu"
    ],
    "name:heb_x_preferred": [
      "בומו"
    ],
    "name:ind_x_preferred": [
      "Bomu"
    ],
    "name:kor_x_preferred": [
      "보무"
    ],
    "name:swe_x_preferred": [
      "Bomu"
    ],
    "name:tur_x_preferred": [
      "Bomu"
    ],
    "name:urd_x_preferred": [
      "بومو"
    ],
    "name:zho_x_preferred": [
      "波木"
    ],
    "wof:name": "Bomu",
    "wof:placetype": "locality"
  },
  "geometry": {
    "coordinates": [
      85.8492,
      28.8351
    ],
    "type": "Point"
  }
}