{
  "type": "Feature",
  "properties": {
    "gn:admin1_code": "4.0",
    "gn:asciiname": "Xinnan",
    "gn:country_code": "CN",
    "gn:dem": 28,
    "gn:feature_class": "P",
    "gn:feature_code": "PPL",
    "gn:name": "Xinnan",
    "gn:population": 0,
    "gn:timezone": "Asia/Shanghai",
    "iso:country": "CN",
    "name:zho_x_preferred": [
      "新南"
    ],
    "wof:name": "Xinnan",
    "wof:placetype": "locality"
  },
  "geometry": {
    "coordinates": [
      118.3414,
      34.34459
    ],
    "type": "Point"
  }
}