{
  "type": "Feature",
  "properties": {
    "gn:admin1_code": "4.0",
    "gn:asciiname": "Yanshan",
    "gn:country_code": "CN",
    "gn:dem": 10,
    "gn:feature_class": "P",
    "gn:feature_code": "PPL",
    "gn:name": "Yanshan",
    "gn:population": 0,
    "gn:timezone": "Asia/Shanghai",
    "iso:country": "CN",
    "name:ceb_x_preferred": [
      "Yanshan"
    ],
    "name:deu_x_preferred": [
      "Yanshan"
    ],
    "name:fra_x_preferred": [
      "Yanshan"
    ],
    "name:nor_x_preferred": [
      "Yanshan"
    ],
    "name:rus_x_preferred": [
      "Яньшань"
    ],
    "name:swe_x_preferred": [
      "Yanshan"
    ],
    "name:zho_x_preferred": [
      "烟山"
    ],
    "wof:name": "Yanshan",
    "wof:placetype": "locality"
  },
  "geometry": {
    "coordinates": [
      119.60299,
      31.34949000000001
    ],
    "type": "Point"
  }
}