{
  "type": "Feature",
  "properties": {
    "gn:admin1_code": "32.0",
    "gn:asciiname": "Shizi",
    "gn:country_code": "CN",
    "gn:dem": 459,
    "gn:feature_class": "P",
    "gn:feature_code": "PPL",
    "gn:name": "Shizi",
    "gn:population": 0,
    "gn:timezone": "Asia/Shanghai",
    "iso:country": "CN",
    "name:ceb_x_preferred": [
      "Shizi"
    ],
    "name:swe_x_preferred": [
      "Shizi"
    ],
    "name:zho_x_preferred": [
      "十字"
    ],
    "wof:name": "Shizi",
    "wof:placetype": "locality"
  },
  "geometry": {
    "coordinates": [
      103.981,
      30.3383
    ],
    "type": "Point"
  }
}