{
  "type": "Feature",
  "properties": {
    "gn:admin1_code": "14.0",
    "gn:asciiname": "Renqinggang",
    "gn:country_code": "CN",
    "gn:dem": 3477,
    "gn:feature_class": "P",
    "gn:feature_code": "PPLF",
    "gn:name": "Renqinggang",
    "gn:population": 0,
    "gn:timezone": "Asia/Urumqi",
    "iso:country": "CN",
    "name:bod_x_preferred": [
      "Rinqêngang"
    ],
    "name:zho_x_preferred": [
      "Renqinggang"
    ],
    "name:zho_x_variant": [
      "仁青岗",
      "Xiayadong Qu",
      "下亚东区"
    ],
    "wof:name": "Renqinggang",
    "wof:placetype": "locality"
  },
  "geometry": {
    "coordinates": [
      88.91,
      27.41
    ],
    "type": "Point"
  }
}