{
  "type": "Feature",
  "properties": {
    "gn:admin1_code": "30",
    "gn:asciiname": "Huguang",
    "gn:country_code": "CN",
    "gn:dem": 30,
    "gn:feature_class": "P",
    "gn:feature_code": "PPLA4",
    "gn:name": "Huguang",
    "gn:population": 0,
    "gn:timezone": "Asia/Urumqi",
    "iso:country": "CN",
    "name:ces_x_preferred": [
      "Chu-kuang"
    ],
    "name:fra_x_preferred": [
      "Huguang"
    ],
    "name:ind_x_preferred": [
      "Huguang"
    ],
    "name:jpn_x_preferred": [
      "湖広省"
    ],
    "name:nor_x_preferred": [
      "Huguang"
    ],
    "name:pol_x_preferred": [
      "Huguang"
    ],
    "name:rus_x_preferred": [
      "Хугуан"
    ],
    "name:swe_x_preferred": [
      "Huguang"
    ],
    "name:und_x_variant": [
      "Huguang Zhen",
      "湖光镇"
    ],
    "name:zho_x_preferred": [
      "湖光"
    ],
    "wof:name": "Huguang",
    "wof:placetype": "locality"
  },
  "geometry": {
    "coordinates": [
      110.28872,
      21.12582
    ],
    "type": "Point"
  }
}