{
  "type": "Feature",
  "properties": {
    "gn:admin1_code": "3.0",
    "gn:asciiname": "Shilong",
    "gn:country_code": "CN",
    "gn:dem": 63,
    "gn:feature_class": "P",
    "gn:feature_code": "PPL",
    "gn:name": "Shilong",
    "gn:population": 0,
    "gn:timezone": "Asia/Shanghai",
    "iso:country": "CN",
    "name:ceb_x_preferred": [
      "Shilong"
    ],
    "name:deu_x_preferred": [
      "Shilong"
    ],
    "name:fra_x_preferred": [
      "Shilong"
    ],
    "name:mlg_x_preferred": [
      "Shilong"
    ],
    "name:sco_x_preferred": [
      "Shilong"
    ],
    "name:und_x_variant": [
      "石垅"
    ],
    "name:zho_x_preferred": [
      "石龙镇"
    ],
    "wof:name": "Shilong",
    "wof:placetype": "locality"
  },
  "geometry": {
    "coordinates": [
      114.83159,
      27.41033
    ],
    "type": "Point"
  }
}