{
  "type": "Feature",
  "properties": {
    "gn:admin1_code": "16.0",
    "gn:asciiname": "Pipa",
    "gn:country_code": "CN",
    "gn:dem": 87,
    "gn:feature_class": "P",
    "gn:feature_code": "PPL",
    "gn:name": "Pipa",
    "gn:population": 0,
    "gn:timezone": "Asia/Shanghai",
    "iso:country": "CN",
    "name:cat_x_preferred": [
      "Pipa"
    ],
    "name:cdo_x_preferred": [
      "Bì-bà"
    ],
    "name:ces_x_preferred": [
      "Pipa"
    ],
    "name:dan_x_preferred": [
      "Biwa"
    ],
    "name:deu_x_preferred": [
      "Pipa"
    ],
    "name:epo_x_preferred": [
      "Ĉinbivo"
    ],
    "name:eus_x_preferred": [
      "Pipa"
    ],
    "name:fin_x_preferred": [
      "Pipa"
    ],
    "name:fra_x_preferred": [
      "Pipa"
    ],
    "name:hun_x_preferred": [
      "Pi-pá"
    ],
    "name:hye_x_preferred": [
      "Պիպա"
    ],
    "name:ind_x_preferred": [
      "Pipa"
    ],
    "name:jpn_x_preferred": [
      "琵琶#中国琵琶"
    ],
    "name:msa_x_preferred": [
      "Pipa"
    ],
    "name:nld_x_preferred": [
      "Pipa"
    ],
    "name:nor_x_preferred": [
      "Pipa"
    ],
    "name:oci_x_preferred": [
      "Pipa"
    ],
    "name:pol_x_preferred": [
      "Pipa"
    ],
    "name:rus_x_preferred": [
      "Пипа"
    ],
    "name:slv_x_preferred": [
      "Pipa"
    ],
    "name:spa_x_preferred": [
      "Pipa"
    ],
    "name:tha_x_preferred": [
      "ผีผา"
    ],
    "name:tur_x_preferred": [
      "Pipa"
    ],
    "name:ukr_x_preferred": [
      "Піпа"
    ],
    "name:zho_x_preferred": [
      "琵琶"
    ],
    "name:zho_x_variant": [
      "中國琵琶"
    ],
    "wof:name": "Pipa",
    "wof:placetype": "locality"
  },
  "geometry": {
    "coordinates": [
      109.015,
      22.4772
    ],
    "type": "Point"
  }
}