{
  "type": "Feature",
  "properties": {
    "gn:admin1_code": "10",
    "gn:asciiname": "Wushiqihao",
    "gn:country_code": "CN",
    "gn:dem": 1189,
    "gn:feature_class": "P",
    "gn:feature_code": "PPLF",
    "gn:name": "Wushiqihao",
    "gn:population": 0,
    "gn:timezone": "Asia/Shanghai",
    "iso:country": "CN",
    "name:und_x_variant": [
      "Wu-shih-ch’i-hao"
    ],
    "name:zho_x_preferred": [
      "五十七号"
    ],
    "wof:name": "Wushiqihao",
    "wof:placetype": "locality"
  },
  "geometry": {
    "coordinates": [
      117.3075,
      42.1275
    ],
    "type": "Point"
  }
}