{
  "type": "Feature",
  "properties": {
    "gn:admin1_code": "8.0",
    "gn:asciiname": "Shisangongli",
    "gn:country_code": "CN",
    "gn:dem": 418,
    "gn:feature_class": "P",
    "gn:feature_code": "PPL",
    "gn:name": "Shisangongli",
    "gn:population": 0,
    "gn:timezone": "Asia/Shanghai",
    "iso:country": "CN",
    "name:zho_x_preferred": [
      "十三公里"
    ],
    "wof:name": "Shisangongli",
    "wof:placetype": "locality"
  },
  "geometry": {
    "coordinates": [
      129.26019,
      48.28892000000001
    ],
    "type": "Point"
  }
}