{
  "type": "Feature",
  "properties": {
    "gn:admin1_code": "3.0",
    "gn:asciiname": "Xiaojiashan",
    "gn:country_code": "CN",
    "gn:dem": 413,
    "gn:feature_class": "P",
    "gn:feature_code": "PPL",
    "gn:name": "Xiaojiashan",
    "gn:population": 0,
    "gn:timezone": "Asia/Shanghai",
    "iso:country": "CN",
    "name:und_x_variant": [
      "肖家山"
    ],
    "wof:name": "Xiaojiashan",
    "wof:placetype": "locality"
  },
  "geometry": {
    "coordinates": [
      116.36607,
      26.55654
    ],
    "type": "Point"
  }
}