{
  "type": "Feature",
  "properties": {
    "gn:admin1_code": "3.0",
    "gn:asciiname": "Xuyuan",
    "gn:country_code": "CN",
    "gn:dem": 82,
    "gn:feature_class": "P",
    "gn:feature_code": "PPL",
    "gn:name": "Xuyuan",
    "gn:population": 0,
    "gn:timezone": "Asia/Shanghai",
    "iso:country": "CN",
    "name:und_x_variant": [
      "徐源"
    ],
    "wof:name": "Xuyuan",
    "wof:placetype": "locality"
  },
  "geometry": {
    "coordinates": [
      116.71613,
      27.79458
    ],
    "type": "Point"
  }
}