{
  "type": "Feature",
  "properties": {
    "gn:admin1_code": "15.0",
    "gn:asciiname": "Baiyin",
    "gn:country_code": "CN",
    "gn:dem": 2168,
    "gn:feature_class": "P",
    "gn:feature_code": "PPLA4",
    "gn:name": "Baiyin",
    "gn:population": 0,
    "gn:timezone": "Asia/Shanghai",
    "iso:country": "CN",
    "name:ara_x_preferred": [
      "بايين"
    ],
    "name:cdo_x_preferred": [
      "Băh-ngṳ̀ng"
    ],
    "name:ceb_x_preferred": [
      "Baiyin"
    ],
    "name:ces_x_preferred": [
      "Paj-jin"
    ],
    "name:dan_x_preferred": [
      "Baiyin"
    ],
    "name:deu_x_preferred": [
      "Baiyin"
    ],
    "name:est_x_preferred": [
      "Baiyin"
    ],
    "name:eus_x_preferred": [
      "Baiyin"
    ],
    "name:fas_x_preferred": [
      "بایین"
    ],
    "name:fin_x_preferred": [
      "Baiyin"
    ],
    "name:fra_x_preferred": [
      "Baiyin"
    ],
    "name:hye_x_preferred": [
      "Բային"
    ],
    "name:ita_x_preferred": [
      "Baiyin"
    ],
    "name:jpn_x_preferred": [
      "白銀市"
    ],
    "name:kik_x_preferred": [
      "Baiyin"
    ],
    "name:kor_x_preferred": [
      "바이인시"
    ],
    "name:mlg_x_preferred": [
      "Baiyin"
    ],
    "name:nld_x_preferred": [
      "Baiyin"
    ],
    "name:nno_x_preferred": [
      "Baiyin"
    ],
    "name:nor_x_preferred": [
      "Baiyin"
    ],
    "name:pam_x_preferred": [
      "Baiyin"
    ],
    "name:pnb_x_preferred": [
      "بائی ین"
    ],
    "name:pol_x_preferred": [
      "Baiyin"
    ],
    "name:rus_x_preferred": [
      "Байинь"
    ],
    "name:sco_x_preferred": [
      "Baiyin"
    ],
    "name:spa_x_preferred": [
      "Baiyin"
    ],
    "name:swe_x_preferred": [
      "Baiyin"
    ],
    "name:tgl_x_preferred": [
      "Baiyin"
    ],
    "name:tur_x_preferred": [
      "Baiyin"
    ],
    "name:und_x_variant": [
      "Baiyin Mengguzu Xiang"
    ],
    "name:urd_x_preferred": [
      "بائیین"
    ],
    "name:vie_x_preferred": [
      "Bạch Ngân"
    ],
    "name:war_x_preferred": [
      "Baiyin"
    ],
    "name:wuu_x_preferred": [
      "白银市"
    ],
    "name:zho_x_preferred": [
      "白银"
    ],
    "name:zho_x_variant": [
      "白银蒙古族乡",
      "白银市"
    ],
    "wof:name": "Baiyin",
    "wof:placetype": "locality"
  },
  "geometry": {
    "coordinates": [
      99.88851,
      38.91824
    ],
    "type": "Point"
  }
}