{
  "type": "Feature",
  "properties": {
    "gn:admin1_code": "32.0",
    "gn:asciiname": "Wali",
    "gn:country_code": "CN",
    "gn:dem": 3191,
    "gn:feature_class": "P",
    "gn:feature_code": "PPL",
    "gn:name": "Wali",
    "gn:population": 0,
    "gn:timezone": "Asia/Shanghai",
    "iso:country": "CN",
    "name:ara_x_preferred": [
      "ولي"
    ],
    "name:aze_x_preferred": [
      "Əl-Vəli"
    ],
    "name:ben_x_preferred": [
      "ওয়ালি"
    ],
    "name:bul_x_preferred": [
      "Валия"
    ],
    "name:cat_x_preferred": [
      "Valí"
    ],
    "name:deu_x_preferred": [
      "Walī"
    ],
    "name:epo_x_preferred": [
      "Ŭalio"
    ],
    "name:fas_x_preferred": [
      "ولی"
    ],
    "name:fra_x_preferred": [
      "Wali"
    ],
    "name:heb_x_preferred": [
      "ולי"
    ],
    "name:ind_x_preferred": [
      "Wali"
    ],
    "name:ita_x_preferred": [
      "Wali"
    ],
    "name:lav_x_preferred": [
      "Vali"
    ],
    "name:mkd_x_preferred": [
      "Валија"
    ],
    "name:msa_x_preferred": [
      "Wali"
    ],
    "name:nld_x_preferred": [
      "Wali"
    ],
    "name:pol_x_preferred": [
      "Wali"
    ],
    "name:por_x_preferred": [
      "Uale"
    ],
    "name:ron_x_preferred": [
      "Wali"
    ],
    "name:rus_x_preferred": [
      "Вали"
    ],
    "name:spa_x_preferred": [
      "Valí"
    ],
    "name:sqi_x_preferred": [
      "Evlija"
    ],
    "name:srp_x_preferred": [
      "Валија"
    ],
    "name:swa_x_preferred": [
      "Liwali"
    ],
    "name:swe_x_preferred": [
      "Vali"
    ],
    "name:tur_x_preferred": [
      "Velî"
    ],
    "name:ukr_x_preferred": [
      "Валі"
    ],
    "name:urd_x_preferred": [
      "ولی"
    ],
    "name:zho_x_preferred": [
      "娃里"
    ],
    "name:zho_x_variant": [
      "瓦利"
    ],
    "wof:name": "Wali",
    "wof:placetype": "locality"
  },
  "geometry": {
    "coordinates": [
      100.309,
      30.4394
    ],
    "type": "Point"
  }
}