{
  "type": "Feature",
  "properties": {
    "gn:admin1_code": "7.0",
    "gn:asciiname": "Jiaojing",
    "gn:country_code": "CN",
    "gn:dem": 718,
    "gn:feature_class": "P",
    "gn:feature_code": "PPL",
    "gn:name": "Jiaojing",
    "gn:population": 0,
    "gn:timezone": "Asia/Shanghai",
    "iso:country": "CN",
    "name:ara_x_preferred": [
      "جاوتشينغ"
    ],
    "name:ben_x_preferred": [
      "জিয়াওজিং"
    ],
    "name:ell_x_preferred": [
      "Τζιαοτζίνγκ"
    ],
    "name:fas_x_preferred": [
      "جیاوجینگ"
    ],
    "name:heb_x_preferred": [
      "ג'יאוג'ינג"
    ],
    "name:hin_x_preferred": [
      "ज्याओज़िंग"
    ],
    "name:hun_x_preferred": [
      "Jiaojing"
    ],
    "name:ind_x_preferred": [
      "Jiaojing"
    ],
    "name:pol_x_preferred": [
      "Jiaojing"
    ],
    "name:por_x_preferred": [
      "Jiaojiang"
    ],
    "name:spa_x_preferred": [
      "Jiaojing"
    ],
    "name:tur_x_preferred": [
      "Jiaojing"
    ],
    "name:ukr_x_preferred": [
      "Цзяоцзин"
    ],
    "name:urd_x_preferred": [
      "جیاوجنگ"
    ],
    "name:zho_x_preferred": [
      "角井"
    ],
    "wof:name": "Jiaojing",
    "wof:placetype": "locality"
  },
  "geometry": {
    "coordinates": [
      118.8415,
      27.25321
    ],
    "type": "Point"
  }
}