{
  "type": "Feature",
  "properties": {
    "gn:admin1_code": "4.0",
    "gn:asciiname": "Yuduo",
    "gn:country_code": "CN",
    "gn:dem": 6,
    "gn:feature_class": "P",
    "gn:feature_code": "PPLA4",
    "gn:name": "Yuduo",
    "gn:population": 0,
    "gn:timezone": "Asia/Shanghai",
    "iso:country": "CN",
    "name:und_x_variant": [
      "Yujiaduo",
      "俞家垛",
      "Yuduo",
      "Yuduo Zhen",
      "俞垛",
      "俞垛镇"
    ],
    "wof:name": "Yuduo",
    "wof:placetype": "locality"
  },
  "geometry": {
    "coordinates": [
      120.01283,
      32.64077
    ],
    "type": "Point"
  }
}