{
  "type": "Feature",
  "properties": {
    "gn:admin1_code": "29.0",
    "gn:asciiname": "Michu",
    "gn:country_code": "CN",
    "gn:dem": 1333,
    "gn:feature_class": "P",
    "gn:feature_code": "PPL",
    "gn:name": "Michu",
    "gn:population": 0,
    "gn:timezone": "Asia/Shanghai",
    "iso:country": "CN",
    "name:ara_x_preferred": [
      "ميتشو"
    ],
    "name:ast_x_preferred": [
      "Michu"
    ],
    "name:azb_x_preferred": [
      "میچو"
    ],
    "name:bul_x_preferred": [
      "Мичу"
    ],
    "name:cat_x_preferred": [
      "Michu"
    ],
    "name:ces_x_preferred": [
      "Michu"
    ],
    "name:dan_x_preferred": [
      "Michu"
    ],
    "name:deu_x_preferred": [
      "Michu"
    ],
    "name:fas_x_preferred": [
      "میچو"
    ],
    "name:fin_x_preferred": [
      "Michu"
    ],
    "name:fra_x_preferred": [
      "Michu"
    ],
    "name:hun_x_preferred": [
      "Michu"
    ],
    "name:hye_x_preferred": [
      "Միչու"
    ],
    "name:ita_x_preferred": [
      "Michu"
    ],
    "name:jpn_x_preferred": [
      "ミゲル・ペレス・クエスタ"
    ],
    "name:mkd_x_preferred": [
      "Мичу"
    ],
    "name:msa_x_preferred": [
      "Michu"
    ],
    "name:nld_x_preferred": [
      "Michu"
    ],
    "name:pol_x_preferred": [
      "Michu"
    ],
    "name:por_x_preferred": [
      "Michu"
    ],
    "name:rus_x_preferred": [
      "Мичу"
    ],
    "name:spa_x_preferred": [
      "Michu"
    ],
    "name:swe_x_preferred": [
      "Michu"
    ],
    "name:tgk_x_preferred": [
      "Мику"
    ],
    "name:tha_x_preferred": [
      "มิชู"
    ],
    "name:tur_x_preferred": [
      "Michu"
    ],
    "name:vie_x_preferred": [
      "Michu"
    ],
    "name:zho_x_preferred": [
      "咪初"
    ],
    "wof:name": "Michu",
    "wof:placetype": "locality"
  },
  "geometry": {
    "coordinates": [
      102.124,
      23.1517
    ],
    "type": "Point"
  }
}