{
  "type": "Feature",
  "properties": {
    "gn:admin1_code": "15.0",
    "gn:asciiname": "Liziping",
    "gn:country_code": "CN",
    "gn:dem": 1259,
    "gn:feature_class": "P",
    "gn:feature_code": "PPL",
    "gn:name": "Liziping",
    "gn:population": 0,
    "gn:timezone": "Asia/Shanghai",
    "iso:country": "CN",
    "name:und_x_variant": [
      "李子坪"
    ],
    "wof:name": "Liziping",
    "wof:placetype": "locality"
  },
  "geometry": {
    "coordinates": [
      105.25466000000002,
      32.95719
    ],
    "type": "Point"
  }
}