{
  "type": "Feature",
  "properties": {
    "gn:admin1_code": "15.0",
    "gn:asciiname": "Zaoyang",
    "gn:country_code": "CN",
    "gn:dem": 1576,
    "gn:feature_class": "P",
    "gn:feature_code": "PPL",
    "gn:name": "Zaoyang",
    "gn:population": 0,
    "gn:timezone": "Asia/Shanghai",
    "iso:country": "CN",
    "name:ceb_x_preferred": [
      "Zaoyang"
    ],
    "name:deu_x_preferred": [
      "Zaoyang"
    ],
    "name:fra_x_preferred": [
      "Zaoyang"
    ],
    "name:ita_x_preferred": [
      "Zaoyang"
    ],
    "name:jpn_x_preferred": [
      "棗陽市"
    ],
    "name:kik_x_preferred": [
      "Zaoyang"
    ],
    "name:kor_x_preferred": [
      "짜오양시"
    ],
    "name:mlg_x_preferred": [
      "Zaoyang"
    ],
    "name:nor_x_preferred": [
      "Zaoyang"
    ],
    "name:pam_x_preferred": [
      "Zaoyang"
    ],
    "name:swe_x_preferred": [
      "Zaoyang"
    ],
    "name:vie_x_preferred": [
      "Tảo Dương"
    ],
    "name:war_x_preferred": [
      "Zaoyang"
    ],
    "name:zho_x_preferred": [
      "早阳"
    ],
    "name:zho_x_variant": [
      "枣阳市"
    ],
    "wof:name": "Zaoyang",
    "wof:placetype": "locality"
  },
  "geometry": {
    "coordinates": [
      105.427,
      34.174
    ],
    "type": "Point"
  }
}