{
  "type": "Feature",
  "properties": {
    "gn:admin1_code": "32.0",
    "gn:asciiname": "Sima",
    "gn:country_code": "CN",
    "gn:dem": 378,
    "gn:feature_class": "P",
    "gn:feature_code": "PPL",
    "gn:name": "Sima",
    "gn:population": 0,
    "gn:timezone": "Asia/Shanghai",
    "iso:country": "CN",
    "name:ceb_x_preferred": [
      "Sima"
    ],
    "name:deu_x_preferred": [
      "Sima"
    ],
    "name:ell_x_preferred": [
      "Σήμα"
    ],
    "name:est_x_preferred": [
      "Sima"
    ],
    "name:fin_x_preferred": [
      "Sima"
    ],
    "name:fra_x_preferred": [
      "Sima"
    ],
    "name:heb_x_preferred": [
      "סימה"
    ],
    "name:hye_x_preferred": [
      "Սիմա"
    ],
    "name:ind_x_preferred": [
      "Sima"
    ],
    "name:ita_x_preferred": [
      "Sima"
    ],
    "name:jav_x_preferred": [
      "Sima"
    ],
    "name:kan_x_preferred": [
      "ಸಿಮಾ"
    ],
    "name:new_x_preferred": [
      "सिमा गाविस"
    ],
    "name:nld_x_preferred": [
      "Sima"
    ],
    "name:pol_x_preferred": [
      "Sima"
    ],
    "name:ron_x_preferred": [
      "Sima"
    ],
    "name:rus_x_preferred": [
      "Сима"
    ],
    "name:slk_x_preferred": [
      "Sima"
    ],
    "name:slv_x_preferred": [
      "Sima"
    ],
    "name:spa_x_preferred": [
      "Sima"
    ],
    "name:swe_x_preferred": [
      "Sima"
    ],
    "name:tgl_x_preferred": [
      "Sima"
    ],
    "name:ukr_x_preferred": [
      "Сима"
    ],
    "name:zho_x_preferred": [
      "司马"
    ],
    "wof:name": "Sima",
    "wof:placetype": "locality"
  },
  "geometry": {
    "coordinates": [
      106.72,
      30.6115
    ],
    "type": "Point"
  }
}