{
  "type": "Feature",
  "properties": {
    "gn:admin1_code": "16.0",
    "gn:asciiname": "Pangu",
    "gn:country_code": "CN",
    "gn:dem": 39,
    "gn:feature_class": "P",
    "gn:feature_code": "PPL",
    "gn:name": "Pangu",
    "gn:population": 0,
    "gn:timezone": "Asia/Shanghai",
    "iso:country": "CN",
    "name:ara_x_preferred": [
      "بان كو"
    ],
    "name:cat_x_preferred": [
      "Pangu"
    ],
    "name:ces_x_preferred": [
      "Pangu"
    ],
    "name:cym_x_preferred": [
      "Pangu"
    ],
    "name:deu_x_preferred": [
      "Pangu"
    ],
    "name:fas_x_preferred": [
      "پانگو"
    ],
    "name:fra_x_preferred": [
      "Pangu"
    ],
    "name:hak_x_preferred": [
      "Phàn-kú"
    ],
    "name:hun_x_preferred": [
      "Pan-ku"
    ],
    "name:ind_x_preferred": [
      "Pangu"
    ],
    "name:ita_x_preferred": [
      "Pangu"
    ],
    "name:kor_x_preferred": [
      "반고"
    ],
    "name:nld_x_preferred": [
      "Pangu"
    ],
    "name:nor_x_preferred": [
      "Pangu"
    ],
    "name:pol_x_preferred": [
      "Pangu"
    ],
    "name:por_x_preferred": [
      "Pan Ku"
    ],
    "name:ron_x_preferred": [
      "Pan ku"
    ],
    "name:rus_x_preferred": [
      "Паньгу"
    ],
    "name:spa_x_preferred": [
      "Pangu"
    ],
    "name:swe_x_preferred": [
      "Pangu"
    ],
    "name:tam_x_preferred": [
      "பன்கு"
    ],
    "name:tha_x_preferred": [
      "ผานกู่"
    ],
    "name:tur_x_preferred": [
      "Pan Gu"
    ],
    "name:ukr_x_preferred": [
      "Пань-гу"
    ],
    "name:vie_x_preferred": [
      "Bàn Cổ"
    ],
    "name:zho_x_preferred": [
      "蟠古"
    ],
    "wof:name": "Pangu",
    "wof:placetype": "locality"
  },
  "geometry": {
    "coordinates": [
      110.741,
      23.5475
    ],
    "type": "Point"
  }
}