{
  "type": "Feature",
  "properties": {
    "gn:admin1_code": "9.0",
    "gn:asciiname": "Nanquan",
    "gn:country_code": "CN",
    "gn:dem": 381,
    "gn:feature_class": "P",
    "gn:feature_code": "PPL",
    "gn:name": "Nanquan",
    "gn:population": 0,
    "gn:timezone": "Asia/Shanghai",
    "iso:country": "CN",
    "name:deu_x_preferred": [
      "Nanquan"
    ],
    "name:fas_x_preferred": [
      "نان‌چوئن"
    ],
    "name:fra_x_preferred": [
      "Nan quan"
    ],
    "name:ita_x_preferred": [
      "Nanquan"
    ],
    "name:por_x_preferred": [
      "Nan quan"
    ],
    "name:spa_x_preferred": [
      "Nanquan"
    ],
    "name:vie_x_preferred": [
      "Nam quyền"
    ],
    "name:zho_x_preferred": [
      "南泉"
    ],
    "wof:name": "Nanquan",
    "wof:placetype": "locality"
  },
  "geometry": {
    "coordinates": [
      110.91834,
      34.57657
    ],
    "type": "Point"
  }
}