{
  "type": "Feature",
  "properties": {
    "gn:admin1_code": "03",
    "gn:asciiname": "Qingxi",
    "gn:country_code": "CN",
    "gn:dem": 530,
    "gn:feature_class": "P",
    "gn:feature_code": "PPLA4",
    "gn:name": "Qingxi",
    "gn:population": 0,
    "gn:timezone": "Asia/Shanghai",
    "iso:country": "CN",
    "name:ceb_x_preferred": [
      "Qingxi"
    ],
    "name:deu_x_preferred": [
      "Qingxi"
    ],
    "name:swe_x_preferred": [
      "Qingxi"
    ],
    "name:und_x_variant": [
      "Ch’ing-ch’i",
      "Ch’ing-ch’i-hsü",
      "清溪",
      "Qingxi Xiang",
      "清溪乡"
    ],
    "wof:name": "Qingxi",
    "wof:placetype": "locality"
  },
  "geometry": {
    "coordinates": [
      115.61392,
      25.22949
    ],
    "type": "Point"
  }
}