{
  "type": "Feature",
  "properties": {
    "gn:admin1_code": "14.0",
    "gn:asciiname": "Jiaruzuoba",
    "gn:country_code": "CN",
    "gn:dem": 3973,
    "gn:feature_class": "P",
    "gn:feature_code": "PPL",
    "gn:name": "Jiaruzuoba",
    "gn:population": 0,
    "gn:timezone": "Asia/Urumqi",
    "iso:country": "CN",
    "name:zho_x_preferred": [
      "加如作把"
    ],
    "wof:name": "Jiaruzuoba",
    "wof:placetype": "locality"
  },
  "geometry": {
    "coordinates": [
      90.85053,
      29.65544
    ],
    "type": "Point"
  }
}