{
  "type": "Feature",
  "properties": {
    "gn:admin1_code": "16.0",
    "gn:asciiname": "Wuwu Xincun",
    "gn:country_code": "CN",
    "gn:dem": 51,
    "gn:feature_class": "P",
    "gn:feature_code": "PPL",
    "gn:name": "Wuwu Xincun",
    "gn:population": 0,
    "gn:timezone": "Asia/Shanghai",
    "iso:country": "CN",
    "name:zho_x_preferred": [
      "伍屋新村"
    ],
    "wof:name": "Wuwu Xincun",
    "wof:placetype": "locality"
  },
  "geometry": {
    "coordinates": [
      109.631,
      23.0284
    ],
    "type": "Point"
  }
}