{
  "type": "Feature",
  "properties": {
    "gn:admin1_code": "30.0",
    "gn:asciiname": "Xiaochi",
    "gn:country_code": "CN",
    "gn:dem": 217,
    "gn:feature_class": "P",
    "gn:feature_code": "PPL",
    "gn:name": "Xiaochi",
    "gn:population": 0,
    "gn:timezone": "Asia/Shanghai",
    "iso:country": "CN",
    "name:ind_x_preferred": [
      "Xiaochi"
    ],
    "name:ita_x_preferred": [
      "Xiaochi"
    ],
    "name:rus_x_preferred": [
      "Сяочи"
    ],
    "name:zho_x_preferred": [
      "小池"
    ],
    "name:zho_x_variant": [
      "中式小吃"
    ],
    "wof:name": "Xiaochi",
    "wof:placetype": "locality"
  },
  "geometry": {
    "coordinates": [
      112.39364,
      24.14817
    ],
    "type": "Point"
  }
}