{
  "type": "Feature",
  "properties": {
    "gn:admin1_code": "30",
    "gn:asciiname": "Yangjia",
    "gn:country_code": "CN",
    "gn:dem": 16,
    "gn:feature_class": "P",
    "gn:feature_code": "PPLA4",
    "gn:name": "Yangjia",
    "gn:population": 0,
    "gn:timezone": "Asia/Urumqi",
    "iso:country": "CN",
    "name:und_x_variant": [
      "Yangjia Zhen",
      "杨家镇"
    ],
    "name:zho_x_preferred": [
      "杨家"
    ],
    "wof:name": "Yangjia",
    "wof:placetype": "locality"
  },
  "geometry": {
    "coordinates": [
      109.96031,
      20.89802
    ],
    "type": "Point"
  }
}