{
  "type": "Feature",
  "properties": {
    "gn:admin1_code": "19.0",
    "gn:asciiname": "Qianyaobucun",
    "gn:country_code": "CN",
    "gn:dem": 79,
    "gn:feature_class": "P",
    "gn:feature_code": "PPL",
    "gn:name": "Qianyaobucun",
    "gn:population": 0,
    "gn:timezone": "Asia/Shanghai",
    "iso:country": "CN",
    "name:zho_x_preferred": [
      "前腰堡村"
    ],
    "wof:name": "Qianyaobucun",
    "wof:placetype": "locality"
  },
  "geometry": {
    "coordinates": [
      123.609,
      42.0374
    ],
    "type": "Point"
  }
}