{
  "type": "Feature",
  "properties": {
    "gn:admin1_code": "5.0",
    "gn:asciiname": "Huashu Zuizi Nangou",
    "gn:country_code": "CN",
    "gn:dem": 219,
    "gn:feature_class": "P",
    "gn:feature_code": "PPL",
    "gn:name": "Huashu Zuizi Nangou",
    "gn:population": 0,
    "gn:timezone": "Asia/Shanghai",
    "iso:country": "CN",
    "name:zho_x_preferred": [
      "桦树咀子南沟"
    ],
    "wof:name": "Huashu Zuizi Nangou",
    "wof:placetype": "locality"
  },
  "geometry": {
    "coordinates": [
      126.6072,
      44.12864
    ],
    "type": "Point"
  }
}