{
  "type": "Feature",
  "properties": {
    "gn:admin1_code": "15.0",
    "gn:asciiname": "Shishuali",
    "gn:country_code": "CN",
    "gn:dem": 2130,
    "gn:feature_class": "P",
    "gn:feature_code": "PPL",
    "gn:name": "Shishuali",
    "gn:population": 0,
    "gn:timezone": "Asia/Shanghai",
    "iso:country": "CN",
    "name:zho_x_preferred": [
      "石刷里"
    ],
    "wof:name": "Shishuali",
    "wof:placetype": "locality"
  },
  "geometry": {
    "coordinates": [
      104.52732,
      34.00719
    ],
    "type": "Point"
  }
}