{
  "type": "Feature",
  "properties": {
    "gn:admin1_code": "05",
    "gn:asciiname": "Dapuchaihe",
    "gn:country_code": "CN",
    "gn:dem": 563,
    "gn:feature_class": "P",
    "gn:feature_code": "PPLA4",
    "gn:name": "Dapuchaihe",
    "gn:population": 0,
    "gn:timezone": "Asia/Shanghai",
    "iso:country": "CN",
    "name:und_x_variant": [
      "Ta-p’u-ch’ai-ho",
      "Dapuchaihe Zhen",
      "Ta-pu-ts’ai-ho",
      "Dapuchaihe",
      "大蒲柴河",
      "大蒲柴河镇"
    ],
    "wof:name": "Dapuchaihe",
    "wof:placetype": "locality"
  },
  "geometry": {
    "coordinates": [
      128.03049,
      42.87973
    ],
    "type": "Point"
  }
}