{
  "type": "Feature",
  "properties": {
    "gn:admin1_code": "19",
    "gn:asciiname": "Qingyang",
    "gn:country_code": "CN",
    "gn:dem": 34,
    "gn:feature_class": "P",
    "gn:feature_code": "PPL",
    "gn:name": "Qingyang",
    "gn:population": 0,
    "gn:timezone": "Asia/Shanghai",
    "iso:country": "CN",
    "name:ara_x_preferred": [
      "كينغيانغ"
    ],
    "name:cdo_x_preferred": [
      "Kéng-iòng"
    ],
    "name:ces_x_preferred": [
      "Čching-jang"
    ],
    "name:dan_x_preferred": [
      "Qingyang"
    ],
    "name:deu_x_preferred": [
      "Qingyang"
    ],
    "name:eus_x_preferred": [
      "Qingyang"
    ],
    "name:fas_x_preferred": [
      "کینگیانگ"
    ],
    "name:fin_x_preferred": [
      "Qingyang"
    ],
    "name:fra_x_preferred": [
      "Qingyang"
    ],
    "name:hye_x_preferred": [
      "Ցինյան"
    ],
    "name:ita_x_preferred": [
      "Qingyang"
    ],
    "name:jpn_x_preferred": [
      "慶陽市"
    ],
    "name:kik_x_preferred": [
      "Qingyang"
    ],
    "name:kor_x_preferred": [
      "칭양시"
    ],
    "name:mlg_x_preferred": [
      "Qingyang"
    ],
    "name:nld_x_preferred": [
      "Qingyang"
    ],
    "name:nno_x_preferred": [
      "Qingyang"
    ],
    "name:nor_x_preferred": [
      "Qingyang"
    ],
    "name:pam_x_preferred": [
      "Qingyang"
    ],
    "name:pnb_x_preferred": [
      "چنگیانگ"
    ],
    "name:pol_x_preferred": [
      "Qingyang"
    ],
    "name:rus_x_preferred": [
      "Цинъян"
    ],
    "name:spa_x_preferred": [
      "Qingyang"
    ],
    "name:swe_x_preferred": [
      "Qingyang"
    ],
    "name:tgl_x_preferred": [
      "Qingyang"
    ],
    "name:tur_x_preferred": [
      "Qingyang"
    ],
    "name:urd_x_preferred": [
      "چنگیانگ"
    ],
    "name:vie_x_preferred": [
      "Khánh Dương"
    ],
    "name:war_x_preferred": [
      "Qingyang"
    ],
    "name:wuu_x_preferred": [
      "庆阳市"
    ],
    "name:zho_x_preferred": [
      "庆阳市"
    ],
    "wof:name": "Qingyang",
    "wof:placetype": "locality"
  },
  "geometry": {
    "coordinates": [
      123.27806,
      41.25222
    ],
    "type": "Point"
  }
}