{
  "type": "Feature",
  "properties": {
    "gn:admin1_code": "10",
    "gn:asciiname": "Qiaomuliang",
    "gn:country_code": "CN",
    "gn:dem": 315,
    "gn:feature_class": "P",
    "gn:feature_code": "PPL",
    "gn:name": "Qiaomuliang",
    "gn:population": 0,
    "gn:timezone": "Asia/Shanghai",
    "iso:country": "CN",
    "name:zho_x_preferred": [
      "桥木梁"
    ],
    "wof:name": "Qiaomuliang",
    "wof:placetype": "locality"
  },
  "geometry": {
    "coordinates": [
      118.01802,
      40.60342
    ],
    "type": "Point"
  }
}