{
  "type": "Feature",
  "properties": {
    "gn:admin1_code": "16.0",
    "gn:asciiname": "Linghu",
    "gn:country_code": "CN",
    "gn:dem": 61,
    "gn:feature_class": "P",
    "gn:feature_code": "PPL",
    "gn:name": "Linghu",
    "gn:population": 0,
    "gn:timezone": "Asia/Shanghai",
    "iso:country": "CN",
    "name:rus_x_preferred": [
      "Линху"
    ],
    "name:vie_x_preferred": [
      "Lệnh Hồ"
    ],
    "name:zho_x_preferred": [
      "岭护"
    ],
    "name:zho_x_variant": [
      "令狐姓"
    ],
    "wof:name": "Linghu",
    "wof:placetype": "locality"
  },
  "geometry": {
    "coordinates": [
      109.745,
      22.8665
    ],
    "type": "Point"
  }
}