{
  "type": "Feature",
  "properties": {
    "gn:admin1_code": "32.0",
    "gn:asciiname": "Aidi",
    "gn:country_code": "CN",
    "gn:dem": 3615,
    "gn:feature_class": "P",
    "gn:feature_code": "PPL",
    "gn:name": "Aidi",
    "gn:population": 0,
    "gn:timezone": "Asia/Shanghai",
    "iso:country": "CN",
    "name:ara_x_preferred": [
      "آيدي"
    ],
    "name:bul_x_preferred": [
      "Аиди"
    ],
    "name:ces_x_preferred": [
      "Aidi"
    ],
    "name:deu_x_preferred": [
      "Aïdi"
    ],
    "name:est_x_preferred": [
      "Aïdi"
    ],
    "name:fin_x_preferred": [
      "Aidi"
    ],
    "name:fra_x_preferred": [
      "Aïdi"
    ],
    "name:heb_x_preferred": [
      "אידי"
    ],
    "name:hin_x_preferred": [
      "एडी"
    ],
    "name:hun_x_preferred": [
      "Atlaszi hegyikutya"
    ],
    "name:ita_x_preferred": [
      "Cane dell'Atlas"
    ],
    "name:jpn_x_preferred": [
      "アイディ"
    ],
    "name:msa_x_preferred": [
      "Aidi"
    ],
    "name:nld_x_preferred": [
      "Aidi"
    ],
    "name:nor_x_preferred": [
      "Aidi"
    ],
    "name:pnb_x_preferred": [
      "ایڈی"
    ],
    "name:pol_x_preferred": [
      "Aidi"
    ],
    "name:por_x_preferred": [
      "Aidi"
    ],
    "name:rus_x_preferred": [
      "Аиди"
    ],
    "name:slk_x_preferred": [
      "Aidi"
    ],
    "name:spa_x_preferred": [
      "Aïdi"
    ],
    "name:swe_x_preferred": [
      "Aidi"
    ],
    "name:tur_x_preferred": [
      "Aidi"
    ],
    "name:vie_x_preferred": [
      "Chó Aidi"
    ],
    "name:zho_x_preferred": [
      "埃地"
    ],
    "wof:name": "Aidi",
    "wof:placetype": "locality"
  },
  "geometry": {
    "coordinates": [
      100.683,
      29.0335
    ],
    "type": "Point"
  }
}