{
  "type": "Feature",
  "properties": {
    "gn:admin1_code": "16.0",
    "gn:asciiname": "Changtang",
    "gn:country_code": "CN",
    "gn:dem": 115,
    "gn:feature_class": "P",
    "gn:feature_code": "PPL",
    "gn:name": "Changtang",
    "gn:population": 0,
    "gn:timezone": "Asia/Shanghai",
    "iso:country": "CN",
    "name:bih_x_preferred": [
      "चांगतांग"
    ],
    "name:ces_x_preferred": [
      "Čhangthang"
    ],
    "name:deu_x_preferred": [
      "Changthang"
    ],
    "name:fin_x_preferred": [
      "Changtang"
    ],
    "name:fra_x_preferred": [
      "Changtang"
    ],
    "name:hin_x_preferred": [
      "चांगथंग"
    ],
    "name:ita_x_preferred": [
      "Qiangtang"
    ],
    "name:lit_x_preferred": [
      "Čangtangas"
    ],
    "name:mwl_x_preferred": [
      "Changtang"
    ],
    "name:nld_x_preferred": [
      "Changthang"
    ],
    "name:pnb_x_preferred": [
      "چانگ تھانگ"
    ],
    "name:rus_x_preferred": [
      "Чангтан"
    ],
    "name:zho_x_preferred": [
      "长塘"
    ],
    "name:zho_x_variant": [
      "藏北高原"
    ],
    "wof:name": "Changtang",
    "wof:placetype": "locality"
  },
  "geometry": {
    "coordinates": [
      109.496,
      22.4048
    ],
    "type": "Point"
  }
}