{
  "type": "Feature",
  "properties": {
    "gn:admin1_code": "25",
    "gn:asciiname": "Zhumiao",
    "gn:country_code": "CN",
    "gn:dem": 35,
    "gn:feature_class": "P",
    "gn:feature_code": "PPL",
    "gn:name": "Zhumiao",
    "gn:population": 0,
    "gn:timezone": "Asia/Shanghai",
    "iso:country": "CN",
    "name:zho_x_preferred": [
      "朱庙"
    ],
    "wof:name": "Zhumiao",
    "wof:placetype": "locality"
  },
  "geometry": {
    "coordinates": [
      116.046,
      36.9165
    ],
    "type": "Point"
  }
}