{
  "type": "Feature",
  "properties": {
    "gn:admin1_code": "24.0",
    "gn:asciiname": "Xingyuan",
    "gn:country_code": "CN",
    "gn:dem": 1385,
    "gn:feature_class": "P",
    "gn:feature_code": "PPL",
    "gn:name": "Xingyuan",
    "gn:population": 0,
    "gn:timezone": "Asia/Shanghai",
    "iso:country": "CN",
    "name:und_x_variant": [
      "杏园"
    ],
    "wof:name": "Xingyuan",
    "wof:placetype": "locality"
  },
  "geometry": {
    "coordinates": [
      112.46332,
      39.49862
    ],
    "type": "Point"
  }
}