{
  "type": "Feature",
  "properties": {
    "gn:admin1_code": "11.0",
    "gn:asciiname": "Wuxia",
    "gn:country_code": "CN",
    "gn:dem": 212,
    "gn:feature_class": "P",
    "gn:feature_code": "PPL",
    "gn:name": "Wuxia",
    "gn:population": 0,
    "gn:timezone": "Asia/Shanghai",
    "iso:country": "CN",
    "name:ast_x_preferred": [
      "Wuxia"
    ],
    "name:cat_x_preferred": [
      "Wuxia"
    ],
    "name:deu_x_preferred": [
      "Wuxia"
    ],
    "name:eus_x_preferred": [
      "Wuxia"
    ],
    "name:fas_x_preferred": [
      "ووشیا"
    ],
    "name:fin_x_preferred": [
      "Wuxia"
    ],
    "name:fra_x_preferred": [
      "Wuxia"
    ],
    "name:glg_x_preferred": [
      "Wuxia"
    ],
    "name:heb_x_preferred": [
      "וושיה"
    ],
    "name:hun_x_preferred": [
      "Vu-hszia"
    ],
    "name:hye_x_preferred": [
      "Ուսյա"
    ],
    "name:ind_x_preferred": [
      "Cerita silat"
    ],
    "name:ita_x_preferred": [
      "Wuxia"
    ],
    "name:nor_x_preferred": [
      "Wuxia"
    ],
    "name:pol_x_preferred": [
      "Wuxia"
    ],
    "name:por_x_preferred": [
      "Wuxia"
    ],
    "name:rus_x_preferred": [
      "Уся"
    ],
    "name:spa_x_preferred": [
      "Wuxia"
    ],
    "name:srp_x_preferred": [
      "Vusja"
    ],
    "name:swe_x_preferred": [
      "Wuxia"
    ],
    "name:tha_x_preferred": [
      "บันเทิงคดีกำลังภายใน"
    ],
    "name:ukr_x_preferred": [
      "Уся"
    ],
    "name:vie_x_preferred": [
      "Võ hiệp"
    ],
    "name:zho_x_preferred": [
      "吴下"
    ],
    "name:zho_x_variant": [
      "武侠文化"
    ],
    "wof:name": "Wuxia",
    "wof:placetype": "locality"
  },
  "geometry": {
    "coordinates": [
      113.87695,
      26.92315
    ],
    "type": "Point"
  }
}