{
  "type": "Feature",
  "properties": {
    "gn:admin1_code": "14",
    "gn:asciiname": "Karlung",
    "gn:country_code": "CN",
    "gn:dem": 4480,
    "gn:feature_class": "P",
    "gn:feature_code": "PPL",
    "gn:name": "Karlung",
    "gn:population": 0,
    "gn:timezone": "Asia/Urumqi",
    "iso:country": "CN",
    "name:bod_x_preferred": [
      "མཁར་ལུང"
    ],
    "name:bod_x_variant": [
      "གདོང་དཀར"
    ],
    "name:und_x_variant": [
      "Donggar",
      "Kalong"
    ],
    "name:zho_x_preferred": [
      "咔龙"
    ],
    "name:zho_x_variant": [
      "卡龙"
    ],
    "wof:name": "Karlung",
    "wof:placetype": "locality"
  },
  "geometry": {
    "coordinates": [
      90.47155,
      29.03614
    ],
    "type": "Point"
  }
}