{
  "type": "Feature",
  "properties": {
    "gn:admin1_code": "2",
    "gn:asciiname": "Huangshan",
    "gn:country_code": "CN",
    "gn:dem": 700,
    "gn:feature_class": "P",
    "gn:feature_code": "PPL",
    "gn:name": "Huangshan",
    "gn:population": 0,
    "gn:timezone": "Asia/Shanghai",
    "iso:country": "CN",
    "name:ara_x_preferred": [
      "جبل هوانغشان"
    ],
    "name:ast_x_preferred": [
      "Montes Huang"
    ],
    "name:bod_x_preferred": [
      "ཧོང་ཧྲན་རི་བོ།"
    ],
    "name:bul_x_preferred": [
      "Хуаншан"
    ],
    "name:cat_x_preferred": [
      "Huang Shan"
    ],
    "name:ceb_x_preferred": [
      "Huang Shan"
    ],
    "name:ces_x_preferred": [
      "Žluté hory"
    ],
    "name:dan_x_preferred": [
      "Huangshan"
    ],
    "name:deu_x_preferred": [
      "Huang Shan"
    ],
    "name:epo_x_preferred": [
      "Huangŝan"
    ],
    "name:eus_x_preferred": [
      "Huang mendia"
    ],
    "name:fas_x_preferred": [
      "کوهستان هونگ‌شان"
    ],
    "name:fin_x_preferred": [
      "Huangshan"
    ],
    "name:fra_x_preferred": [
      "Monts Huang"
    ],
    "name:heb_x_preferred": [
      "חואנגשאן"
    ],
    "name:hrv_x_preferred": [
      "Huang Shan"
    ],
    "name:hun_x_preferred": [
      "Huang-san"
    ],
    "name:hye_x_preferred": [
      "Հուանշան"
    ],
    "name:ind_x_preferred": [
      "Huangshan"
    ],
    "name:ita_x_preferred": [
      "Huangshan"
    ],
    "name:kat_x_preferred": [
      "ხუანშანი"
    ],
    "name:kor_x_preferred": [
      "황산"
    ],
    "name:lit_x_preferred": [
      "Huan Šanas"
    ],
    "name:mal_x_preferred": [
      "ഹ്വാങ് പർവ്വതം"
    ],
    "name:mlg_x_preferred": [
      "Huangshan"
    ],
    "name:nep_x_preferred": [
      "माउन्ट हुआंग"
    ],
    "name:nld_x_preferred": [
      "Huangshan"
    ],
    "name:nno_x_preferred": [
      "Huangfjella"
    ],
    "name:nor_x_preferred": [
      "Huang Shan"
    ],
    "name:pol_x_preferred": [
      "Huang Shan"
    ],
    "name:por_x_preferred": [
      "Montanhas Huangshan"
    ],
    "name:rus_x_preferred": [
      "Хуаншань"
    ],
    "name:slk_x_preferred": [
      "Chuang-šan"
    ],
    "name:spa_x_preferred": [
      "Montes Huang"
    ],
    "name:sqi_x_preferred": [
      "Huangshan"
    ],
    "name:swe_x_preferred": [
      "Huangshan"
    ],
    "name:tam_x_preferred": [
      "மஞ்சள் மலைகள்"
    ],
    "name:tha_x_preferred": [
      "เขาหวง"
    ],
    "name:tur_x_preferred": [
      "Huangshan"
    ],
    "name:ukr_x_preferred": [
      "Гори Хуаншань"
    ],
    "name:urd_x_preferred": [
      "ہوانگشان"
    ],
    "name:vie_x_preferred": [
      "Hoàng Sơn"
    ],
    "name:zho_x_preferred": [
      "黄山"
    ],
    "wof:name": "Huangshan",
    "wof:placetype": "locality"
  },
  "geometry": {
    "coordinates": [
      119.59306,
      27.92778
    ],
    "type": "Point"
  }
}