{
  "type": "Feature",
  "properties": {
    "gn:admin1_code": "8.0",
    "gn:asciiname": "Yulin",
    "gn:country_code": "CN",
    "gn:dem": 188,
    "gn:feature_class": "P",
    "gn:feature_code": "PPLA4",
    "gn:name": "Yulin",
    "gn:population": 0,
    "gn:timezone": "Asia/Shanghai",
    "iso:country": "CN",
    "name:ceb_x_preferred": [
      "Yulin"
    ],
    "name:deu_x_preferred": [
      "Yulin"
    ],
    "name:eus_x_preferred": [
      "Yulin"
    ],
    "name:fin_x_preferred": [
      "Yulin"
    ],
    "name:fra_x_preferred": [
      "Yulin"
    ],
    "name:heb_x_preferred": [
      "יולין"
    ],
    "name:hun_x_preferred": [
      "Jülin"
    ],
    "name:kor_x_preferred": [
      "위린시"
    ],
    "name:nld_x_preferred": [
      "Yulin"
    ],
    "name:nor_x_preferred": [
      "Yulin"
    ],
    "name:pol_x_preferred": [
      "Yulin"
    ],
    "name:por_x_preferred": [
      "Yulin"
    ],
    "name:rus_x_preferred": [
      "Юйлинь"
    ],
    "name:spa_x_preferred": [
      "Yulin"
    ],
    "name:swe_x_preferred": [
      "Yulin"
    ],
    "name:tur_x_preferred": [
      "Yulin"
    ],
    "name:und_x_variant": [
      "Yulin Zhen"
    ],
    "name:zho_x_preferred": [
      "榆林"
    ],
    "name:zho_x_variant": [
      "榆林镇"
    ],
    "wof:name": "Yulin",
    "wof:placetype": "locality"
  },
  "geometry": {
    "coordinates": [
      126.27798,
      46.10995
    ],
    "type": "Point"
  }
}