{
  "type": "Feature",
  "properties": {
    "gn:admin1_code": "11",
    "gn:asciiname": "Niu'etang",
    "gn:country_code": "CN",
    "gn:dem": 343,
    "gn:feature_class": "P",
    "gn:feature_code": "PPL",
    "gn:name": "Niu’etang",
    "gn:population": 0,
    "gn:timezone": "Asia/Shanghai",
    "iso:country": "CN",
    "name:und_x_variant": [
      "Niu’etang"
    ],
    "name:zho_x_preferred": [
      "牛扼塘"
    ],
    "name:zho_x_variant": [
      "牛轭塘"
    ],
    "wof:name": "Niu'etang",
    "wof:placetype": "locality"
  },
  "geometry": {
    "coordinates": [
      111.22159,
      27.21613
    ],
    "type": "Point"
  }
}