{
  "type": "Feature",
  "properties": {
    "gn:admin1_code": "16.0",
    "gn:asciiname": "Nongna",
    "gn:country_code": "CN",
    "gn:dem": 447,
    "gn:feature_class": "P",
    "gn:feature_code": "PPL",
    "gn:name": "Nongna",
    "gn:population": 0,
    "gn:timezone": "Asia/Shanghai",
    "iso:country": "CN",
    "name:zho_x_preferred": [
      "弄那"
    ],
    "wof:name": "Nongna",
    "wof:placetype": "locality"
  },
  "geometry": {
    "coordinates": [
      107.795,
      23.9131
    ],
    "type": "Point"
  }
}