{
  "type": "Feature",
  "properties": {
    "gn:admin1_code": "18",
    "gn:asciiname": "Sandanba",
    "gn:country_code": "CN",
    "gn:dem": 1152,
    "gn:feature_class": "P",
    "gn:feature_code": "PPL",
    "gn:name": "Sandanba",
    "gn:population": 0,
    "gn:timezone": "Asia/Shanghai",
    "iso:country": "CN",
    "name:zho_x_preferred": [
      "三担坝"
    ],
    "wof:name": "Sandanba",
    "wof:placetype": "locality"
  },
  "geometry": {
    "coordinates": [
      107.99,
      28.4497
    ],
    "type": "Point"
  }
}