{
  "type": "Feature",
  "properties": {
    "gn:admin1_code": "30",
    "gn:asciiname": "Maxu",
    "gn:country_code": "CN",
    "gn:dem": 21,
    "gn:feature_class": "P",
    "gn:feature_code": "PPLA4",
    "gn:name": "Maxu",
    "gn:population": 0,
    "gn:timezone": "Asia/Shanghai",
    "iso:country": "CN",
    "name:und_x_variant": [
      "Mawei",
      "Maxu",
      "Mayu Zhen",
      "马圩镇"
    ],
    "name:zho_x_preferred": [
      "马圩"
    ],
    "wof:name": "Maxu",
    "wof:placetype": "locality"
  },
  "geometry": {
    "coordinates": [
      111.83678,
      23.23974
    ],
    "type": "Point"
  }
}