{
  "type": "Feature",
  "properties": {
    "gn:admin1_code": "12.0",
    "gn:asciiname": "Niulanjie",
    "gn:country_code": "CN",
    "gn:dem": 732,
    "gn:feature_class": "P",
    "gn:feature_code": "PPL",
    "gn:name": "Niulanjie",
    "gn:population": 0,
    "gn:timezone": "Asia/Shanghai",
    "iso:country": "CN",
    "name:und_x_variant": [
      "Niulangai",
      "Niulanjie",
      "牛栏界"
    ],
    "name:zho_x_preferred": [
      "牛兰盖"
    ],
    "wof:name": "Niulanjie",
    "wof:placetype": "locality"
  },
  "geometry": {
    "coordinates": [
      109.2833,
      29.82597
    ],
    "type": "Point"
  }
}