{
  "type": "Feature",
  "properties": {
    "gn:admin1_code": "15.0",
    "gn:asciiname": "Maquantan",
    "gn:country_code": "CN",
    "gn:dem": 1085,
    "gn:feature_class": "P",
    "gn:feature_code": "PPL",
    "gn:name": "Maquantan",
    "gn:population": 0,
    "gn:timezone": "Asia/Urumqi",
    "iso:country": "CN",
    "name:zho_x_preferred": [
      "马圈滩"
    ],
    "wof:name": "Maquantan",
    "wof:placetype": "locality"
  },
  "geometry": {
    "coordinates": [
      94.6864,
      40.3079
    ],
    "type": "Point"
  }
}