{
  "type": "Feature",
  "properties": {
    "gn:admin1_code": "24",
    "gn:asciiname": "Taipingbu",
    "gn:country_code": "CN",
    "gn:dem": 1052,
    "gn:feature_class": "P",
    "gn:feature_code": "PPL",
    "gn:name": "Taipingbu",
    "gn:population": 0,
    "gn:timezone": "Asia/Shanghai",
    "iso:country": "CN",
    "name:und_x_variant": [
      "T’ai-p’ing-p’u",
      "T’ai-p’ing-pao",
      "Taipingbu"
    ],
    "name:zho_x_preferred": [
      "太平堡"
    ],
    "wof:name": "Taipingbu",
    "wof:placetype": "locality"
  },
  "geometry": {
    "coordinates": [
      113.93495,
      40.42941
    ],
    "type": "Point"
  }
}