{
  "type": "Feature",
  "properties": {
    "gn:admin1_code": "32.0",
    "gn:asciiname": "Zuoshuitang",
    "gn:country_code": "CN",
    "gn:dem": 1200,
    "gn:feature_class": "P",
    "gn:feature_code": "PPL",
    "gn:name": "Zuoshuitang",
    "gn:population": 0,
    "gn:timezone": "Asia/Shanghai",
    "iso:country": "CN",
    "name:zho_x_preferred": [
      "坐水塘"
    ],
    "wof:name": "Zuoshuitang",
    "wof:placetype": "locality"
  },
  "geometry": {
    "coordinates": [
      104.632,
      32.3574
    ],
    "type": "Point"
  }
}