{
  "type": "Feature",
  "properties": {
    "gn:admin1_code": "14.0",
    "gn:asciiname": "Lerao",
    "gn:country_code": "CN",
    "gn:dem": 3902,
    "gn:feature_class": "P",
    "gn:feature_code": "PPL",
    "gn:name": "Lerao",
    "gn:population": 0,
    "gn:timezone": "Asia/Urumqi",
    "iso:country": "CN",
    "name:zho_x_preferred": [
      "勒绕"
    ],
    "wof:name": "Lerao",
    "wof:placetype": "locality"
  },
  "geometry": {
    "coordinates": [
      96.1224,
      30.30026
    ],
    "type": "Point"
  }
}