{
  "type": "Feature",
  "properties": {
    "gn:admin1_code": "8.0",
    "gn:asciiname": "Xinjian Yidui",
    "gn:country_code": "CN",
    "gn:dem": 419,
    "gn:feature_class": "P",
    "gn:feature_code": "PPLF",
    "gn:name": "Xinjian Yidui",
    "gn:population": 0,
    "gn:timezone": "Asia/Shanghai",
    "iso:country": "CN",
    "name:zho_x_preferred": [
      "新建一队"
    ],
    "wof:name": "Xinjian Yidui",
    "wof:placetype": "locality"
  },
  "geometry": {
    "coordinates": [
      130.37066000000002,
      44.82227
    ],
    "type": "Point"
  }
}