{
  "type": "Feature",
  "properties": {
    "gn:admin1_code": "31.0",
    "gn:asciiname": "Xinxiang",
    "gn:country_code": "CN",
    "gn:dem": 91,
    "gn:feature_class": "P",
    "gn:feature_code": "PPL",
    "gn:name": "Xinxiang",
    "gn:population": 0,
    "gn:timezone": "Asia/Shanghai",
    "iso:country": "CN",
    "name:afr_x_preferred": [
      "Xinxiang"
    ],
    "name:ara_x_preferred": [
      "شينشيانغ"
    ],
    "name:ast_x_preferred": [
      "Xinxiang"
    ],
    "name:bul_x_preferred": [
      "Синсян"
    ],
    "name:cdo_x_preferred": [
      "Sĭng-hiŏng"
    ],
    "name:ces_x_preferred": [
      "Sin-siang"
    ],
    "name:dan_x_preferred": [
      "Xinxiang"
    ],
    "name:deu_x_preferred": [
      "Xinxiang"
    ],
    "name:epo_x_preferred": [
      "Sinsjan"
    ],
    "name:eus_x_preferred": [
      "Xinxiang"
    ],
    "name:fas_x_preferred": [
      "شینشیانگ"
    ],
    "name:fin_x_preferred": [
      "Xinxiang"
    ],
    "name:fra_x_preferred": [
      "Xinxiang"
    ],
    "name:heb_x_preferred": [
      "קסינקסיאנג"
    ],
    "name:hun_x_preferred": [
      "Xinxiang"
    ],
    "name:ind_x_preferred": [
      "Xinxiang"
    ],
    "name:ita_x_preferred": [
      "Xinxiang"
    ],
    "name:jpn_x_preferred": [
      "新郷市"
    ],
    "name:kik_x_preferred": [
      "Xinxiang"
    ],
    "name:kor_x_preferred": [
      "신샹시"
    ],
    "name:mlg_x_preferred": [
      "Xinxiang"
    ],
    "name:nld_x_preferred": [
      "Xinxiang"
    ],
    "name:nno_x_preferred": [
      "Xinxiang"
    ],
    "name:nor_x_preferred": [
      "Xinxiang"
    ],
    "name:pam_x_preferred": [
      "Xinxiang"
    ],
    "name:pol_x_preferred": [
      "Xinxiang"
    ],
    "name:por_x_preferred": [
      "Xinxiang"
    ],
    "name:rus_x_preferred": [
      "Синьсян"
    ],
    "name:spa_x_preferred": [
      "Xinxiang"
    ],
    "name:srp_x_preferred": [
      "Синсјанг"
    ],
    "name:swe_x_preferred": [
      "Xinxiang"
    ],
    "name:tur_x_preferred": [
      "Xinxiang"
    ],
    "name:uig_x_preferred": [
      "شىنشياڭ شەھىرى"
    ],
    "name:urd_x_preferred": [
      "شنشیانگ"
    ],
    "name:vie_x_preferred": [
      "Tân Hương"
    ],
    "name:war_x_preferred": [
      "Xinxiang"
    ],
    "name:zho_x_preferred": [
      "Xinxiang"
    ],
    "name:zho_x_variant": [
      "新香",
      "新乡市"
    ],
    "wof:name": "Xinxiang",
    "wof:placetype": "locality"
  },
  "geometry": {
    "coordinates": [
      110.19456,
      19.92264
    ],
    "type": "Point"
  }
}