{
  "type": "Feature",
  "properties": {
    "gn:admin1_code": "11",
    "gn:asciiname": "Wuxi",
    "gn:country_code": "CN",
    "gn:dem": 296,
    "gn:feature_class": "P",
    "gn:feature_code": "PPL",
    "gn:name": "Wuxi",
    "gn:population": 0,
    "gn:timezone": "Asia/Shanghai",
    "iso:country": "CN",
    "name:afr_x_preferred": [
      "Wuxi"
    ],
    "name:ara_x_preferred": [
      "ووشي"
    ],
    "name:ast_x_preferred": [
      "Wuxi"
    ],
    "name:aze_x_preferred": [
      "Usi"
    ],
    "name:bel_x_preferred": [
      "Усі"
    ],
    "name:bod_x_preferred": [
      "ཝུའུ་ཞི།"
    ],
    "name:bul_x_preferred": [
      "Уси"
    ],
    "name:cat_x_preferred": [
      "Wuxi"
    ],
    "name:cdo_x_preferred": [
      "Ù-sék"
    ],
    "name:ceb_x_preferred": [
      "Wuxi"
    ],
    "name:ces_x_preferred": [
      "Wu-si"
    ],
    "name:cym_x_preferred": [
      "Wuxi"
    ],
    "name:dan_x_preferred": [
      "Wuxi"
    ],
    "name:deu_x_preferred": [
      "Wuxi"
    ],
    "name:epo_x_preferred": [
      "Vuŝio"
    ],
    "name:est_x_preferred": [
      "Wuxi"
    ],
    "name:eus_x_preferred": [
      "Wuxi"
    ],
    "name:fas_x_preferred": [
      "ووشی"
    ],
    "name:fin_x_preferred": [
      "Wuxi"
    ],
    "name:fra_x_preferred": [
      "Wuxi"
    ],
    "name:heb_x_preferred": [
      "וושי"
    ],
    "name:hun_x_preferred": [
      "Vuhszi"
    ],
    "name:ina_x_preferred": [
      "Wuxi"
    ],
    "name:ind_x_preferred": [
      "Wuxi"
    ],
    "name:ita_x_preferred": [
      "Wuxi"
    ],
    "name:jpn_x_preferred": [
      "無錫市"
    ],
    "name:kik_x_preferred": [
      "Wuxi"
    ],
    "name:kir_x_preferred": [
      "Уси"
    ],
    "name:kor_x_preferred": [
      "우시시"
    ],
    "name:lit_x_preferred": [
      "Usis"
    ],
    "name:mlg_x_preferred": [
      "Wuxi"
    ],
    "name:mon_x_preferred": [
      "Үши"
    ],
    "name:nld_x_preferred": [
      "Wuxi"
    ],
    "name:nno_x_preferred": [
      "Wuxi"
    ],
    "name:nor_x_preferred": [
      "Wuxi"
    ],
    "name:pan_x_preferred": [
      "ਵੁਕਸੀ"
    ],
    "name:pol_x_preferred": [
      "Wuxi"
    ],
    "name:por_x_preferred": [
      "Wuxi"
    ],
    "name:ron_x_preferred": [
      "Wuxi"
    ],
    "name:rus_x_preferred": [
      "Уси"
    ],
    "name:sah_x_preferred": [
      "Уси"
    ],
    "name:sco_x_preferred": [
      "Wuxi"
    ],
    "name:spa_x_preferred": [
      "Wuxi"
    ],
    "name:srp_x_preferred": [
      "Вуси"
    ],
    "name:swe_x_preferred": [
      "Wuxi"
    ],
    "name:tgl_x_preferred": [
      "Wuxi"
    ],
    "name:tha_x_preferred": [
      "อู๋ซี"
    ],
    "name:tur_x_preferred": [
      "Wuxi"
    ],
    "name:uig_x_preferred": [
      "ۋۇشى شەھىرى"
    ],
    "name:ukr_x_preferred": [
      "Усі"
    ],
    "name:urd_x_preferred": [
      "ووشی"
    ],
    "name:vie_x_preferred": [
      "Vô Tích"
    ],
    "name:war_x_preferred": [
      "Wuxi"
    ],
    "name:wuu_x_preferred": [
      "无锡市"
    ],
    "name:zha_x_preferred": [
      "Vuzsiz"
    ],
    "name:zho_x_preferred": [
      "无锡市"
    ],
    "wof:name": "Wuxi",
    "wof:placetype": "locality"
  },
  "geometry": {
    "coordinates": [
      109.98694,
      27.40889
    ],
    "type": "Point"
  }
}