{
  "type": "Feature",
  "properties": {
    "gn:admin1_code": "15.0",
    "gn:asciiname": "Gaoyao",
    "gn:country_code": "CN",
    "gn:dem": 1727,
    "gn:feature_class": "P",
    "gn:feature_code": "PPL",
    "gn:name": "Gaoyao",
    "gn:population": 0,
    "gn:timezone": "Asia/Shanghai",
    "iso:country": "CN",
    "name:und_x_variant": [
      "高尧"
    ],
    "wof:name": "Gaoyao",
    "wof:placetype": "locality"
  },
  "geometry": {
    "coordinates": [
      104.59897,
      34.79056
    ],
    "type": "Point"
  }
}