{
  "type": "Feature",
  "properties": {
    "gn:admin1_code": "32.0",
    "gn:asciiname": "Huijue",
    "gn:country_code": "CN",
    "gn:dem": 532,
    "gn:feature_class": "P",
    "gn:feature_code": "PPL",
    "gn:name": "Huijue",
    "gn:population": 0,
    "gn:timezone": "Asia/Shanghai",
    "iso:country": "CN",
    "name:zho_x_preferred": [
      "慧觉"
    ],
    "wof:name": "Huijue",
    "wof:placetype": "locality"
  },
  "geometry": {
    "coordinates": [
      104.62796,
      31.33945
    ],
    "type": "Point"
  }
}