{
  "type": "Feature",
  "properties": {
    "gn:admin1_code": "1.0",
    "gn:asciiname": "Wazikoucun",
    "gn:country_code": "CN",
    "gn:dem": 39,
    "gn:feature_class": "P",
    "gn:feature_code": "PPL",
    "gn:name": "Wazikoucun",
    "gn:population": 0,
    "gn:timezone": "Asia/Shanghai",
    "iso:country": "CN",
    "name:und_x_variant": [
      "Wa-tzu-k’ou",
      "Wazikou",
      "Wazikoucun"
    ],
    "name:zho_x_preferred": [
      "瓦子口村"
    ],
    "wof:name": "Wazikoucun",
    "wof:placetype": "locality"
  },
  "geometry": {
    "coordinates": [
      116.81583,
      34.095
    ],
    "type": "Point"
  }
}