{
  "type": "Feature",
  "properties": {
    "gn:admin1_code": "15.0",
    "gn:asciiname": "Shang'erjie",
    "gn:country_code": "CN",
    "gn:dem": 1847,
    "gn:feature_class": "P",
    "gn:feature_code": "PPL",
    "gn:name": "Shang’erjie",
    "gn:population": 0,
    "gn:timezone": "Asia/Shanghai",
    "iso:country": "CN",
    "name:und_x_variant": [
      "Shang’erjie"
    ],
    "name:zho_x_preferred": [
      "上二截"
    ],
    "wof:name": "Shang'erjie",
    "wof:placetype": "locality"
  },
  "geometry": {
    "coordinates": [
      98.7979,
      39.39
    ],
    "type": "Point"
  }
}