{
  "type": "Feature",
  "properties": {
    "gn:admin1_code": "3.0",
    "gn:asciiname": "Shuibiancun",
    "gn:country_code": "CN",
    "gn:dem": 35,
    "gn:feature_class": "P",
    "gn:feature_code": "PPL",
    "gn:name": "Shuibiancun",
    "gn:population": 0,
    "gn:timezone": "Asia/Shanghai",
    "iso:country": "CN",
    "name:und_x_variant": [
      "水边村"
    ],
    "wof:name": "Shuibiancun",
    "wof:placetype": "locality"
  },
  "geometry": {
    "coordinates": [
      115.40782,
      28.09182
    ],
    "type": "Point"
  }
}