{
  "type": "Feature",
  "properties": {
    "gn:admin1_code": "26.0",
    "gn:asciiname": "Sanqiao",
    "gn:country_code": "CN",
    "gn:dem": 1065,
    "gn:feature_class": "P",
    "gn:feature_code": "PPL",
    "gn:name": "Sanqiao",
    "gn:population": 0,
    "gn:timezone": "Asia/Shanghai",
    "iso:country": "CN",
    "name:deu_x_preferred": [
      "Sanqiao"
    ],
    "name:und_x_variant": [
      "三桥"
    ],
    "wof:name": "Sanqiao",
    "wof:placetype": "locality"
  },
  "geometry": {
    "coordinates": [
      107.76687,
      34.94519
    ],
    "type": "Point"
  }
}