{
  "type": "Feature",
  "properties": {
    "gn:admin1_code": "11",
    "gn:asciiname": "Yagongchong",
    "gn:country_code": "CN",
    "gn:dem": 681,
    "gn:feature_class": "P",
    "gn:feature_code": "PPL",
    "gn:name": "Yagongchong",
    "gn:population": 0,
    "gn:timezone": "Asia/Shanghai",
    "iso:country": "CN",
    "name:zho_x_preferred": [
      "鸭公冲"
    ],
    "wof:name": "Yagongchong",
    "wof:placetype": "locality"
  },
  "geometry": {
    "coordinates": [
      111.18279,
      25.32384
    ],
    "type": "Point"
  }
}