{
  "type": "Feature",
  "properties": {
    "gn:admin1_code": "16.0",
    "gn:asciiname": "Nanchong",
    "gn:country_code": "CN",
    "gn:dem": 144,
    "gn:feature_class": "P",
    "gn:feature_code": "PPL",
    "gn:name": "Nanchong",
    "gn:population": 0,
    "gn:timezone": "Asia/Shanghai",
    "iso:country": "CN",
    "name:afr_x_preferred": [
      "Nanchong"
    ],
    "name:ara_x_preferred": [
      "نانتشونغ"
    ],
    "name:cdo_x_preferred": [
      "Nàng-chṳ̆ng"
    ],
    "name:ceb_x_preferred": [
      "Nanchong"
    ],
    "name:ces_x_preferred": [
      "Nan-čchung"
    ],
    "name:dan_x_preferred": [
      "Nanchong"
    ],
    "name:deu_x_preferred": [
      "Nanchong"
    ],
    "name:eus_x_preferred": [
      "Nanchong"
    ],
    "name:fas_x_preferred": [
      "نانچونگ"
    ],
    "name:fin_x_preferred": [
      "Nanchong"
    ],
    "name:fra_x_preferred": [
      "Nanchong"
    ],
    "name:heb_x_preferred": [
      "נאנצ'ונג"
    ],
    "name:hun_x_preferred": [
      "Nancsung"
    ],
    "name:ind_x_preferred": [
      "Nanchong"
    ],
    "name:ita_x_preferred": [
      "Nanchong"
    ],
    "name:jpn_x_preferred": [
      "南充市"
    ],
    "name:kaz_x_preferred": [
      "Наньчун"
    ],
    "name:kik_x_preferred": [
      "Nanchong"
    ],
    "name:kor_x_preferred": [
      "난충시"
    ],
    "name:mlg_x_preferred": [
      "Nanchong"
    ],
    "name:nld_x_preferred": [
      "Nanchong"
    ],
    "name:nno_x_preferred": [
      "Nanchong"
    ],
    "name:nor_x_preferred": [
      "Nanchong"
    ],
    "name:pol_x_preferred": [
      "Nanchong"
    ],
    "name:rus_x_preferred": [
      "Наньчун"
    ],
    "name:spa_x_preferred": [
      "Nanchong"
    ],
    "name:srp_x_preferred": [
      "Нанчунг"
    ],
    "name:swe_x_preferred": [
      "Nanchong"
    ],
    "name:tur_x_preferred": [
      "Nanchong"
    ],
    "name:urd_x_preferred": [
      "نانچونگ"
    ],
    "name:vie_x_preferred": [
      "Nam Sung"
    ],
    "name:war_x_preferred": [
      "Nanchong"
    ],
    "name:zho_x_preferred": [
      "南冲"
    ],
    "name:zho_x_variant": [
      "南充市"
    ],
    "wof:name": "Nanchong",
    "wof:placetype": "locality"
  },
  "geometry": {
    "coordinates": [
      110.437,
      23.1767
    ],
    "type": "Point"
  }
}