{
  "type": "Feature",
  "properties": {
    "gn:admin1_code": "26.0",
    "gn:asciiname": "Hujiazhuang",
    "gn:country_code": "CN",
    "gn:dem": 1499,
    "gn:feature_class": "P",
    "gn:feature_code": "PPL",
    "gn:name": "Hujiazhuang",
    "gn:population": 0,
    "gn:timezone": "Asia/Shanghai",
    "iso:country": "CN",
    "name:zho_x_preferred": [
      "胡家庄"
    ],
    "wof:name": "Hujiazhuang",
    "wof:placetype": "locality"
  },
  "geometry": {
    "coordinates": [
      108.54911,
      36.49888
    ],
    "type": "Point"
  }
}