{
  "type": "Feature",
  "properties": {
    "gn:admin1_code": "10",
    "gn:asciiname": "Balisenggou",
    "gn:country_code": "CN",
    "gn:dem": 954,
    "gn:feature_class": "P",
    "gn:feature_code": "PPL",
    "gn:name": "Balisenggou",
    "gn:population": 0,
    "gn:timezone": "Asia/Shanghai",
    "iso:country": "CN",
    "name:zho_x_preferred": [
      "八里僧沟"
    ],
    "wof:name": "Balisenggou",
    "wof:placetype": "locality"
  },
  "geometry": {
    "coordinates": [
      117.51135,
      41.61547
    ],
    "type": "Point"
  }
}