{
  "type": "Feature",
  "properties": {
    "gn:admin1_code": "19.0",
    "gn:asciiname": "Xuannucun",
    "gn:country_code": "CN",
    "gn:dem": 74,
    "gn:feature_class": "P",
    "gn:feature_code": "PPL",
    "gn:name": "Xuannücun",
    "gn:population": 0,
    "gn:timezone": "Asia/Shanghai",
    "iso:country": "CN",
    "name:und_x_variant": [
      "Xuannücun",
      "Xuannüwobao",
      "Xuannü Wobu"
    ],
    "name:zho_x_preferred": [
      "宣女村"
    ],
    "name:zho_x_variant": [
      "宣女窝堡"
    ],
    "wof:name": "Xuannucun",
    "wof:placetype": "locality"
  },
  "geometry": {
    "coordinates": [
      122.414,
      42.2525
    ],
    "type": "Point"
  }
}