{
  "type": "Feature",
  "properties": {
    "gn:admin1_code": "8.0",
    "gn:asciiname": "Henancun",
    "gn:country_code": "CN",
    "gn:dem": 132,
    "gn:feature_class": "P",
    "gn:feature_code": "PPL",
    "gn:name": "Henancun",
    "gn:population": 0,
    "gn:timezone": "Asia/Shanghai",
    "iso:country": "CN",
    "name:zho_x_preferred": [
      "河南村"
    ],
    "wof:name": "Henancun",
    "wof:placetype": "locality"
  },
  "geometry": {
    "coordinates": [
      124.19164,
      45.84051
    ],
    "type": "Point"
  }
}