{
  "type": "Feature",
  "properties": {
    "iso:country": "CN",
    "name:eng_x_preferred": [
      "Yanziji"
    ],
    "name:zho_x_preferred": [
      "燕子矶"
    ],
    "qs:name": "燕子矶",
    "qs:name_adm0": "中國",
    "qs:name_adm1": "江苏省",
    "qs:photos": 66,
    "qs:photos_1k": 13,
    "qs:photos_9k": 1,
    "qs:photos_9r": 2,
    "qs:photos_all": 66,
    "qs:photos_sr": 2,
    "qs:placetype": "Town",
    "qs:pop_sr": "0",
    "wof:name": "Yanziji",
    "wof:placetype": "locality"
  },
  "geometry": {
    "coordinates": [
      118.781433,
      32.125616
    ],
    "type": "Point"
  }
}