{
  "type": "Feature",
  "properties": {
    "gn:admin1_code": "30.0",
    "gn:asciiname": "Songyuan",
    "gn:country_code": "CN",
    "gn:dem": 33,
    "gn:feature_class": "P",
    "gn:feature_code": "PPL",
    "gn:name": "Songyuan",
    "gn:population": 0,
    "gn:timezone": "Asia/Shanghai",
    "iso:country": "CN",
    "name:ara_x_preferred": [
      "سونغيوان"
    ],
    "name:cdo_x_preferred": [
      "Sṳ̀ng-nguòng"
    ],
    "name:ces_x_preferred": [
      "Sung-jüan"
    ],
    "name:dan_x_preferred": [
      "Songyuan"
    ],
    "name:deu_x_preferred": [
      "Songyuan"
    ],
    "name:eus_x_preferred": [
      "Songyuan"
    ],
    "name:fas_x_preferred": [
      "سانگیوان"
    ],
    "name:fin_x_preferred": [
      "Songyuan"
    ],
    "name:fra_x_preferred": [
      "Songyuan"
    ],
    "name:heb_x_preferred": [
      "סונגיואן"
    ],
    "name:hun_x_preferred": [
      "Songyuan"
    ],
    "name:ita_x_preferred": [
      "Songyuan"
    ],
    "name:jpn_x_preferred": [
      "松原市"
    ],
    "name:kik_x_preferred": [
      "Songyuan"
    ],
    "name:kor_x_preferred": [
      "쑹위안시"
    ],
    "name:mlg_x_preferred": [
      "Songyuan"
    ],
    "name:nld_x_preferred": [
      "Songyuan"
    ],
    "name:nno_x_preferred": [
      "Songyuan"
    ],
    "name:nor_x_preferred": [
      "Songyuan"
    ],
    "name:pol_x_preferred": [
      "Songyuan"
    ],
    "name:rus_x_preferred": [
      "Сунъюань"
    ],
    "name:spa_x_preferred": [
      "Songyuan"
    ],
    "name:swe_x_preferred": [
      "Songyuan"
    ],
    "name:tur_x_preferred": [
      "Songyuan"
    ],
    "name:ukr_x_preferred": [
      "Сун’юань"
    ],
    "name:urd_x_preferred": [
      "سونگیوان"
    ],
    "name:vie_x_preferred": [
      "Tùng Nguyên"
    ],
    "name:war_x_preferred": [
      "Songyuan"
    ],
    "name:wuu_x_preferred": [
      "松原市"
    ],
    "name:zho_x_preferred": [
      "松元"
    ],
    "name:zho_x_variant": [
      "松原市"
    ],
    "wof:name": "Songyuan",
    "wof:placetype": "locality"
  },
  "geometry": {
    "coordinates": [
      114.44445,
      23.47402
    ],
    "type": "Point"
  }
}