{
  "type": "Feature",
  "properties": {
    "gn:admin1_code": "18.0",
    "gn:asciiname": "Tuanjie",
    "gn:country_code": "CN",
    "gn:dem": 501,
    "gn:feature_class": "P",
    "gn:feature_code": "PPL",
    "gn:name": "Tuanjie",
    "gn:population": 0,
    "gn:timezone": "Asia/Shanghai",
    "iso:country": "CN",
    "name:zho_x_preferred": [
      "团结"
    ],
    "wof:name": "Tuanjie",
    "wof:placetype": "locality"
  },
  "geometry": {
    "coordinates": [
      108.701,
      25.831
    ],
    "type": "Point"
  }
}