{
  "type": "Feature",
  "properties": {
    "gn:admin1_code": "16",
    "gn:asciiname": "Xinhe",
    "gn:country_code": "CN",
    "gn:dem": 244,
    "gn:feature_class": "P",
    "gn:feature_code": "PPL",
    "gn:name": "Xinhe",
    "gn:population": 0,
    "gn:timezone": "Asia/Shanghai",
    "iso:country": "CN",
    "name:ceb_x_preferred": [
      "Xinhe"
    ],
    "name:deu_x_preferred": [
      "Xinhe"
    ],
    "name:fra_x_preferred": [
      "Xinhe"
    ],
    "name:kor_x_preferred": [
      "신허현"
    ],
    "name:zho_x_preferred": [
      "新合"
    ],
    "wof:name": "Xinhe",
    "wof:placetype": "locality"
  },
  "geometry": {
    "coordinates": [
      110.715,
      24.9086
    ],
    "type": "Point"
  }
}