{
  "type": "Feature",
  "properties": {
    "gn:admin1_code": "29.0",
    "gn:asciiname": "Jinpu",
    "gn:country_code": "CN",
    "gn:dem": 2249,
    "gn:feature_class": "P",
    "gn:feature_code": "PPL",
    "gn:name": "Jinpu",
    "gn:population": 0,
    "gn:timezone": "Asia/Shanghai",
    "iso:country": "CN",
    "name:zho_x_preferred": [
      "金普"
    ],
    "name:zho_x_variant": [
      "金铺镇"
    ],
    "wof:name": "Jinpu",
    "wof:placetype": "locality"
  },
  "geometry": {
    "coordinates": [
      99.9293,
      26.817
    ],
    "type": "Point"
  }
}