{
  "type": "Feature",
  "properties": {
    "gn:admin1_code": "30",
    "gn:asciiname": "Lu'an",
    "gn:country_code": "CN",
    "gn:dem": 18,
    "gn:feature_class": "P",
    "gn:feature_code": "PPL",
    "gn:name": "Lu’an",
    "gn:population": 0,
    "gn:timezone": "Asia/Shanghai",
    "iso:country": "CN",
    "name:afr_x_preferred": [
      "Lu'an"
    ],
    "name:ara_x_preferred": [
      "لوان"
    ],
    "name:cdo_x_preferred": [
      "Lĕ̤k-ăng"
    ],
    "name:ceb_x_preferred": [
      "Lu'an Shi"
    ],
    "name:ces_x_preferred": [
      "Lu-an"
    ],
    "name:cym_x_preferred": [
      "Lu'an"
    ],
    "name:dan_x_preferred": [
      "Lu'an"
    ],
    "name:deu_x_preferred": [
      "Lu’an"
    ],
    "name:eus_x_preferred": [
      "Lu'an"
    ],
    "name:fas_x_preferred": [
      "لوآن"
    ],
    "name:fin_x_preferred": [
      "Lu’an"
    ],
    "name:fra_x_preferred": [
      "Lu'an"
    ],
    "name:hye_x_preferred": [
      "Լուան"
    ],
    "name:ind_x_preferred": [
      "Lu'an"
    ],
    "name:ita_x_preferred": [
      "Lu'an"
    ],
    "name:jpn_x_preferred": [
      "六安市"
    ],
    "name:kik_x_preferred": [
      "Lu'an"
    ],
    "name:kor_x_preferred": [
      "루안시"
    ],
    "name:mlg_x_preferred": [
      "Lu'an"
    ],
    "name:nld_x_preferred": [
      "Lu'an"
    ],
    "name:nno_x_preferred": [
      "Lu'an"
    ],
    "name:nor_x_preferred": [
      "Lu'an"
    ],
    "name:pam_x_preferred": [
      "Lu'an"
    ],
    "name:pnb_x_preferred": [
      "لوآن"
    ],
    "name:pol_x_preferred": [
      "Lu’an"
    ],
    "name:rus_x_preferred": [
      "Луань"
    ],
    "name:spa_x_preferred": [
      "Lu'an"
    ],
    "name:swe_x_preferred": [
      "Lu'an"
    ],
    "name:tam_x_preferred": [
      "லுவான்"
    ],
    "name:tgl_x_preferred": [
      "Lu'an"
    ],
    "name:tur_x_preferred": [
      "Lu'an"
    ],
    "name:urd_x_preferred": [
      "لوآن"
    ],
    "name:vie_x_preferred": [
      "Lục An"
    ],
    "name:war_x_preferred": [
      "Lu'an"
    ],
    "name:wuu_x_preferred": [
      "六安市"
    ],
    "name:zho_x_preferred": [
      "禄岸"
    ],
    "name:zho_x_variant": [
      "Lu’an",
      "六安市"
    ],
    "wof:name": "Lu'an",
    "wof:placetype": "locality"
  },
  "geometry": {
    "coordinates": [
      112.30761,
      23.04721
    ],
    "type": "Point"
  }
}