{
  "type": "Feature",
  "properties": {
    "gn:admin1_code": "19.0",
    "gn:asciiname": "Tangligou Xigou",
    "gn:country_code": "CN",
    "gn:dem": 90,
    "gn:feature_class": "P",
    "gn:feature_code": "PPL",
    "gn:name": "Tangligou Xigou",
    "gn:population": 0,
    "gn:timezone": "Asia/Shanghai",
    "iso:country": "CN",
    "name:zho_x_preferred": [
      "唐梨沟西沟"
    ],
    "wof:name": "Tangligou Xigou",
    "wof:placetype": "locality"
  },
  "geometry": {
    "coordinates": [
      122.428,
      39.8426
    ],
    "type": "Point"
  }
}