{
  "type": "Feature",
  "properties": {
    "gn:admin1_code": "13.0",
    "gn:asciiname": "Qarek",
    "gn:cc2": "CN",
    "gn:country_code": "CN",
    "gn:dem": 1259,
    "gn:feature_class": "P",
    "gn:feature_code": "PPL",
    "gn:name": "Qarek",
    "gn:population": 0,
    "gn:timezone": "Asia/Shanghai",
    "iso:country": "CN",
    "name:uig_x_preferred": [
      "Qarək"
    ],
    "name:uig_x_variant": [
      "Charek",
      "چارەك",
      "Чарәк"
    ],
    "name:und_x_variant": [
      "Ch’ia-je-k’o",
      "Qarak",
      "Qarek"
    ],
    "wof:name": "Qarek",
    "wof:placetype": "locality"
  },
  "geometry": {
    "coordinates": [
      76.99028,
      38.37222
    ],
    "type": "Point"
  }
}