{
  "type": "Feature",
  "properties": {
    "gn:admin1_code": "7.0",
    "gn:asciiname": "Wenyuan",
    "gn:country_code": "CN",
    "gn:dem": 674,
    "gn:feature_class": "P",
    "gn:feature_code": "PPL",
    "gn:name": "Wenyuan",
    "gn:population": 0,
    "gn:timezone": "Asia/Shanghai",
    "iso:country": "CN",
    "name:zho_x_preferred": [
      "文元"
    ],
    "wof:name": "Wenyuan",
    "wof:placetype": "locality"
  },
  "geometry": {
    "coordinates": [
      116.80208,
      25.20894
    ],
    "type": "Point"
  }
}