{
  "type": "Feature",
  "properties": {
    "gn:admin1_code": "13.0",
    "gn:asciiname": "Yanqi",
    "gn:country_code": "CN",
    "gn:dem": 1059,
    "gn:feature_class": "P",
    "gn:feature_code": "PPLA3",
    "gn:name": "Yanqi",
    "gn:population": 0,
    "gn:timezone": "Asia/Urumqi",
    "iso:country": "CN",
    "name:bul_x_preferred": [
      "Карашар"
    ],
    "name:cat_x_preferred": [
      "Qaraixahr"
    ],
    "name:deu_x_preferred": [
      "Karashahr"
    ],
    "name:fas_x_preferred": [
      "قره‌شهر"
    ],
    "name:fra_x_preferred": [
      "Karachahr"
    ],
    "name:hin_x_preferred": [
      "काराशहर"
    ],
    "name:ind_x_preferred": [
      "Karasahr"
    ],
    "name:ita_x_preferred": [
      "Karasahr"
    ],
    "name:kor_x_preferred": [
      "카라샤르"
    ],
    "name:lit_x_preferred": [
      "Karašaras"
    ],
    "name:mon_x_preferred": [
      "Карашар"
    ],
    "name:pnb_x_preferred": [
      "کاراشہر"
    ],
    "name:por_x_preferred": [
      "Karasahr"
    ],
    "name:rus_x_preferred": [
      "Карашар"
    ],
    "name:tur_x_preferred": [
      "Karaşehir"
    ],
    "name:uig_x_preferred": [
      "K̩araxəh̨ər"
    ],
    "name:uig_x_variant": [
      "Qarasheher",
      "قاراشەھەر",
      "Қарашәһәр",
      "قاراشەھەر بازىرى"
    ],
    "name:ukr_x_preferred": [
      "Карашар"
    ],
    "name:und_x_variant": [
      "K’o-la-sha-erh",
      "Yen-ch’i-hui-tsu-tzu-chih-ch’ü",
      "Kara-schahr",
      "Yinki",
      "K’a-la-sha-erh",
      "Yen-ch’i-chen",
      "Khara Shar",
      "Yenki",
      "Ha-la-sha-erh",
      "Yen-ch’i",
      "Kurashar’",
      "Yan’tsy",
      "Yen-ch’i-hui-tsu-tzu-chih-hsien",
      "Karashar",
      "Yen-ch’i-hsien",
      "Qara Shahr",
      "Yanqi",
      "焉耆",
      "Yanqi Zhen",
      "焉耆镇"
    ],
    "name:vie_x_preferred": [
      "Yên Kỳ"
    ],
    "wof:name": "Yanqi",
    "wof:placetype": "locality"
  },
  "geometry": {
    "coordinates": [
      86.56631999999998,
      42.06204
    ],
    "type": "Point"
  }
}