{
  "type": "Feature",
  "properties": {
    "gn:admin1_code": "16.0",
    "gn:asciiname": "Xiajiacha",
    "gn:country_code": "CN",
    "gn:dem": 540,
    "gn:feature_class": "P",
    "gn:feature_code": "PPL",
    "gn:name": "Xiajiacha",
    "gn:population": 0,
    "gn:timezone": "Asia/Shanghai",
    "iso:country": "CN",
    "name:zho_x_preferred": [
      "下加茶"
    ],
    "wof:name": "Xiajiacha",
    "wof:placetype": "locality"
  },
  "geometry": {
    "coordinates": [
      108.467,
      24.1923
    ],
    "type": "Point"
  }
}