{
  "type": "Feature",
  "properties": {
    "gn:admin1_code": "15.0",
    "gn:asciiname": "Zhonghua",
    "gn:country_code": "CN",
    "gn:dem": 1894,
    "gn:feature_class": "P",
    "gn:feature_code": "PPL",
    "gn:name": "Zhonghua",
    "gn:population": 0,
    "gn:timezone": "Asia/Shanghai",
    "iso:country": "CN",
    "name:cdo_x_preferred": [
      "Dṳ̆ng-huà"
    ],
    "name:deu_x_preferred": [
      "Zhonghua"
    ],
    "name:hak_x_preferred": [
      "Chûng-fà"
    ],
    "name:zho_x_preferred": [
      "中华"
    ],
    "name:zho_x_variant": [
      "中華"
    ],
    "wof:name": "Zhonghua",
    "wof:placetype": "locality"
  },
  "geometry": {
    "coordinates": [
      103.369,
      36.5305
    ],
    "type": "Point"
  }
}