{
  "type": "Feature",
  "properties": {
    "gn:admin1_code": "16.0",
    "gn:asciiname": "Taixing",
    "gn:country_code": "CN",
    "gn:dem": 60,
    "gn:feature_class": "P",
    "gn:feature_code": "PPL",
    "gn:name": "Taixing",
    "gn:population": 0,
    "gn:timezone": "Asia/Shanghai",
    "iso:country": "CN",
    "name:ceb_x_preferred": [
      "Taixing Shi"
    ],
    "name:cym_x_preferred": [
      "Taixing"
    ],
    "name:deu_x_preferred": [
      "Taixing"
    ],
    "name:fas_x_preferred": [
      "تایشینگ"
    ],
    "name:fra_x_preferred": [
      "Taixing"
    ],
    "name:ita_x_preferred": [
      "Taixing"
    ],
    "name:jpn_x_preferred": [
      "泰興市"
    ],
    "name:kik_x_preferred": [
      "Taixing"
    ],
    "name:kor_x_preferred": [
      "타이싱시"
    ],
    "name:mlg_x_preferred": [
      "Taixing"
    ],
    "name:nld_x_preferred": [
      "Taixing"
    ],
    "name:nor_x_preferred": [
      "Taixing"
    ],
    "name:rus_x_preferred": [
      "Тайсин"
    ],
    "name:swe_x_preferred": [
      "Taixing"
    ],
    "name:tgl_x_preferred": [
      "Taixing"
    ],
    "name:urd_x_preferred": [
      "تائیشنگ"
    ],
    "name:vie_x_preferred": [
      "Thái Hưng"
    ],
    "name:zho_x_preferred": [
      "泰兴"
    ],
    "name:zho_x_variant": [
      "泰兴市"
    ],
    "wof:name": "Taixing",
    "wof:placetype": "locality"
  },
  "geometry": {
    "coordinates": [
      109.722,
      24.1406
    ],
    "type": "Point"
  }
}