{
  "type": "Feature",
  "properties": {
    "gn:admin1_code": "13.0",
    "gn:asciiname": "Kokterak",
    "gn:country_code": "CN",
    "gn:dem": 1641,
    "gn:feature_class": "P",
    "gn:feature_code": "PPL",
    "gn:name": "Kokterak",
    "gn:population": 0,
    "gn:timezone": "Asia/Shanghai",
    "iso:country": "CN",
    "name:uig_x_preferred": [
      "Kɵk Terək"
    ],
    "name:uig_x_variant": [
      "Kök Térek",
      "كۆك تېرەك",
      "Көк Терәк"
    ],
    "wof:name": "Kokterak",
    "wof:placetype": "locality"
  },
  "geometry": {
    "coordinates": [
      81.59194000000002,
      42.97972
    ],
    "type": "Point"
  }
}