{
  "type": "Feature",
  "properties": {
    "gn:admin1_code": "1.0",
    "gn:asciiname": "Baihua",
    "gn:country_code": "CN",
    "gn:dem": 141,
    "gn:feature_class": "P",
    "gn:feature_code": "PPL",
    "gn:name": "Baihua",
    "gn:population": 0,
    "gn:timezone": "Asia/Shanghai",
    "iso:country": "CN",
    "name:vie_x_preferred": [
      "Bạch thoại"
    ],
    "name:zho_x_preferred": [
      "白华"
    ],
    "wof:name": "Baihua",
    "wof:placetype": "locality"
  },
  "geometry": {
    "coordinates": [
      118.47287,
      30.511
    ],
    "type": "Point"
  }
}