{
  "type": "Feature",
  "properties": {
    "gn:admin1_code": "21.0",
    "gn:asciiname": "Hequan",
    "gn:country_code": "CN",
    "gn:dem": 1822,
    "gn:feature_class": "P",
    "gn:feature_code": "PPL",
    "gn:name": "Hequan",
    "gn:population": 0,
    "gn:timezone": "Asia/Shanghai",
    "iso:country": "CN",
    "name:zho_x_preferred": [
      "和全"
    ],
    "wof:name": "Hequan",
    "wof:placetype": "locality"
  },
  "geometry": {
    "coordinates": [
      106.253,
      35.9545
    ],
    "type": "Point"
  }
}