{
  "type": "Feature",
  "properties": {
    "gn:admin1_code": "8.0",
    "gn:asciiname": "Jiefangtun",
    "gn:country_code": "CN",
    "gn:dem": 235,
    "gn:feature_class": "P",
    "gn:feature_code": "PPL",
    "gn:name": "Jiefangtun",
    "gn:population": 0,
    "gn:timezone": "Asia/Shanghai",
    "iso:country": "CN",
    "name:zho_x_preferred": [
      "解放屯"
    ],
    "wof:name": "Jiefangtun",
    "wof:placetype": "locality"
  },
  "geometry": {
    "coordinates": [
      125.45808,
      48.59721
    ],
    "type": "Point"
  }
}