{
  "type": "Feature",
  "properties": {
    "gn:admin1_code": "16.0",
    "gn:asciiname": "Nawan",
    "gn:country_code": "CN",
    "gn:dem": 51,
    "gn:feature_class": "P",
    "gn:feature_code": "PPL",
    "gn:name": "Nawan",
    "gn:population": 0,
    "gn:timezone": "Asia/Shanghai",
    "iso:country": "CN",
    "name:fas_x_preferred": [
      "نوان"
    ],
    "name:hin_x_preferred": [
      "नौवाँ"
    ],
    "name:urd_x_preferred": [
      "نواں"
    ],
    "name:zho_x_preferred": [
      "那湾"
    ],
    "wof:name": "Nawan",
    "wof:placetype": "locality"
  },
  "geometry": {
    "coordinates": [
      108.19,
      21.7845
    ],
    "type": "Point"
  }
}