{
  "type": "Feature",
  "properties": {
    "gn:admin1_code": "02",
    "gn:asciiname": "Lin'aocun",
    "gn:country_code": "CN",
    "gn:dem": 55,
    "gn:feature_class": "P",
    "gn:feature_code": "PPL",
    "gn:name": "Lin’aocun",
    "gn:population": 0,
    "gn:timezone": "Asia/Shanghai",
    "iso:country": "CN",
    "name:und_x_variant": [
      "Lin’aocun"
    ],
    "name:zho_x_preferred": [
      "林岙"
    ],
    "name:zho_x_variant": [
      "Lin’ao",
      "林岙村"
    ],
    "wof:name": "Lin'aocun",
    "wof:placetype": "locality"
  },
  "geometry": {
    "coordinates": [
      120.42657,
      28.03542
    ],
    "type": "Point"
  }
}