{
  "type": "Feature",
  "properties": {
    "gn:admin1_code": "26.0",
    "gn:asciiname": "Zhaozhuang",
    "gn:country_code": "CN",
    "gn:dem": 1325,
    "gn:feature_class": "P",
    "gn:feature_code": "PPL",
    "gn:name": "Zhaozhuang",
    "gn:population": 0,
    "gn:timezone": "Asia/Shanghai",
    "iso:country": "CN",
    "name:zho_x_preferred": [
      "赵庄"
    ],
    "wof:name": "Zhaozhuang",
    "wof:placetype": "locality"
  },
  "geometry": {
    "coordinates": [
      108.65014,
      36.74571
    ],
    "type": "Point"
  }
}