{
  "type": "Feature",
  "properties": {
    "gn:admin1_code": "31.0",
    "gn:asciiname": "Lizhang",
    "gn:country_code": "CN",
    "gn:dem": 6,
    "gn:feature_class": "P",
    "gn:feature_code": "PPL",
    "gn:name": "Lizhang",
    "gn:population": 0,
    "gn:timezone": "Asia/Shanghai",
    "iso:country": "CN",
    "name:zho_x_preferred": [
      "利章"
    ],
    "wof:name": "Lizhang",
    "wof:placetype": "locality"
  },
  "geometry": {
    "coordinates": [
      108.67536,
      18.7981
    ],
    "type": "Point"
  }
}