{
  "type": "Feature",
  "properties": {
    "gn:admin1_code": "18.0",
    "gn:asciiname": "Xiaopingcha",
    "gn:country_code": "CN",
    "gn:dem": 789,
    "gn:feature_class": "P",
    "gn:feature_code": "PPL",
    "gn:name": "Xiaopingcha",
    "gn:population": 0,
    "gn:timezone": "Asia/Shanghai",
    "iso:country": "CN",
    "name:zho_x_preferred": [
      "小平茶"
    ],
    "wof:name": "Xiaopingcha",
    "wof:placetype": "locality"
  },
  "geometry": {
    "coordinates": [
      107.949,
      26.6398
    ],
    "type": "Point"
  }
}