{
  "type": "Feature",
  "properties": {
    "gn:admin1_code": "19.0",
    "gn:asciiname": "Hedong",
    "gn:country_code": "CN",
    "gn:dem": 381,
    "gn:feature_class": "P",
    "gn:feature_code": "PPL",
    "gn:name": "Hedong",
    "gn:population": 0,
    "gn:timezone": "Asia/Shanghai",
    "iso:country": "CN",
    "name:ceb_x_preferred": [
      "Hedong"
    ],
    "name:deu_x_preferred": [
      "Hedong"
    ],
    "name:eus_x_preferred": [
      "Hedong"
    ],
    "name:fra_x_preferred": [
      "Hedong"
    ],
    "name:nor_x_preferred": [
      "Hedong"
    ],
    "name:rus_x_preferred": [
      "Хэдун"
    ],
    "name:swe_x_preferred": [
      "Hedong"
    ],
    "name:zho_x_preferred": [
      "河东"
    ],
    "wof:name": "Hedong",
    "wof:placetype": "locality"
  },
  "geometry": {
    "coordinates": [
      122.80805,
      40.3035
    ],
    "type": "Point"
  }
}