{
  "type": "Feature",
  "properties": {
    "gn:admin1_code": "19.0",
    "gn:asciiname": "Houbolihongwa",
    "gn:country_code": "CN",
    "gn:dem": 227,
    "gn:feature_class": "P",
    "gn:feature_code": "PPL",
    "gn:name": "Houbolihongwa",
    "gn:population": 0,
    "gn:timezone": "Asia/Shanghai",
    "iso:country": "CN",
    "name:zho_x_preferred": [
      "后玻力洪洼"
    ],
    "name:zho_x_variant": [
      "后玻璃红洼"
    ],
    "wof:name": "Houbolihongwa",
    "wof:placetype": "locality"
  },
  "geometry": {
    "coordinates": [
      122.643,
      42.7705
    ],
    "type": "Point"
  }
}