{
  "type": "Feature",
  "properties": {
    "gn:admin1_code": "30",
    "gn:asciiname": "Yadao",
    "gn:country_code": "CN",
    "gn:dem": 18,
    "gn:feature_class": "P",
    "gn:feature_code": "PPL",
    "gn:name": "Yadao",
    "gn:population": 0,
    "gn:timezone": "Asia/Urumqi",
    "iso:country": "CN",
    "name:zho_x_preferred": [
      "雅道"
    ],
    "wof:name": "Yadao",
    "wof:placetype": "locality"
  },
  "geometry": {
    "coordinates": [
      110.54869,
      21.54035
    ],
    "type": "Point"
  }
}