{
  "type": "Feature",
  "properties": {
    "gn:admin1_code": "4.0",
    "gn:asciiname": "Zhangzhai",
    "gn:country_code": "CN",
    "gn:dem": 20,
    "gn:feature_class": "P",
    "gn:feature_code": "PPL",
    "gn:name": "Zhangzhai",
    "gn:population": 0,
    "gn:timezone": "Asia/Shanghai",
    "iso:country": "CN",
    "name:zho_x_preferred": [
      "张宅"
    ],
    "wof:name": "Zhangzhai",
    "wof:placetype": "locality"
  },
  "geometry": {
    "coordinates": [
      118.227,
      33.7064
    ],
    "type": "Point"
  }
}