{
  "type": "Feature",
  "properties": {
    "gn:admin1_code": "26.0",
    "gn:asciiname": "Liangfengya",
    "gn:country_code": "CN",
    "gn:dem": 1029,
    "gn:feature_class": "P",
    "gn:feature_code": "PPL",
    "gn:name": "Liangfengya",
    "gn:population": 0,
    "gn:timezone": "Asia/Shanghai",
    "iso:country": "CN",
    "name:und_x_variant": [
      "凉风垭"
    ],
    "wof:name": "Liangfengya",
    "wof:placetype": "locality"
  },
  "geometry": {
    "coordinates": [
      107.99119,
      33.25363
    ],
    "type": "Point"
  }
}