{
  "type": "Feature",
  "properties": {
    "gn:admin1_code": "29.0",
    "gn:asciiname": "Hukong",
    "gn:country_code": "CN",
    "gn:dem": 1850,
    "gn:feature_class": "P",
    "gn:feature_code": "PPL",
    "gn:name": "Hukong",
    "gn:population": 0,
    "gn:timezone": "Asia/Shanghai",
    "iso:country": "CN",
    "name:zho_x_preferred": [
      "户孔"
    ],
    "wof:name": "Hukong",
    "wof:placetype": "locality"
  },
  "geometry": {
    "coordinates": [
      98.5205,
      24.6018
    ],
    "type": "Point"
  }
}