{
  "type": "Feature",
  "properties": {
    "gn:admin1_code": "25.0",
    "gn:asciiname": "Tanjiazhuang",
    "gn:country_code": "CN",
    "gn:dem": 73,
    "gn:feature_class": "P",
    "gn:feature_code": "PPL",
    "gn:name": "Tanjiazhuang",
    "gn:population": 0,
    "gn:timezone": "Asia/Shanghai",
    "iso:country": "CN",
    "name:zho_x_preferred": [
      "谭家庄"
    ],
    "wof:name": "Tanjiazhuang",
    "wof:placetype": "locality"
  },
  "geometry": {
    "coordinates": [
      119.29837,
      35.94382
    ],
    "type": "Point"
  }
}