{
  "type": "Feature",
  "properties": {
    "gn:admin1_code": "15.0",
    "gn:asciiname": "Changguan",
    "gn:country_code": "CN",
    "gn:dem": 1707,
    "gn:feature_class": "P",
    "gn:feature_code": "PPL",
    "gn:name": "Changguan",
    "gn:population": 0,
    "gn:timezone": "Asia/Shanghai",
    "iso:country": "CN",
    "name:zho_x_preferred": [
      "长官"
    ],
    "name:zho_x_variant": [
      "长官镇"
    ],
    "wof:name": "Changguan",
    "wof:placetype": "locality"
  },
  "geometry": {
    "coordinates": [
      105.713,
      34.241
    ],
    "type": "Point"
  }
}