{
  "type": "Feature",
  "properties": {
    "gn:admin1_code": "15.0",
    "gn:asciiname": "Chuan'er",
    "gn:country_code": "CN",
    "gn:dem": 1289,
    "gn:feature_class": "P",
    "gn:feature_code": "PPL",
    "gn:name": "Chuan’er",
    "gn:population": 0,
    "gn:timezone": "Asia/Shanghai",
    "iso:country": "CN",
    "name:und_x_variant": [
      "Chuan’er"
    ],
    "name:zho_x_preferred": [
      "川儿"
    ],
    "wof:name": "Chuan'er",
    "wof:placetype": "locality"
  },
  "geometry": {
    "coordinates": [
      105.815,
      34.725
    ],
    "type": "Point"
  }
}