{
  "type": "Feature",
  "properties": {
    "gn:admin1_code": "03",
    "gn:asciiname": "Madang",
    "gn:country_code": "CN",
    "gn:dem": 20,
    "gn:feature_class": "P",
    "gn:feature_code": "PPLA4",
    "gn:name": "Madang",
    "gn:population": 0,
    "gn:timezone": "Asia/Shanghai",
    "iso:country": "CN",
    "name:ceb_x_preferred": [
      "Madang"
    ],
    "name:deu_x_preferred": [
      "Madang"
    ],
    "name:eng_x_historical": [
      "Matung"
    ],
    "name:eng_x_preferred": [
      "Matung"
    ],
    "name:fas_x_preferred": [
      "مادانگ"
    ],
    "name:fin_x_preferred": [
      "Madang"
    ],
    "name:fra_x_preferred": [
      "Madang"
    ],
    "name:glg_x_preferred": [
      "Madang"
    ],
    "name:heb_x_preferred": [
      "האי מדירה"
    ],
    "name:heb_x_variant": [
      "מדנג"
    ],
    "name:hin_x_preferred": [
      "मदांग"
    ],
    "name:hun_x_preferred": [
      "Madang"
    ],
    "name:ind_x_preferred": [
      "Madang"
    ],
    "name:ita_x_preferred": [
      "Madang"
    ],
    "name:jpn_x_preferred": [
      "マダン"
    ],
    "name:kor_x_preferred": [
      "마당"
    ],
    "name:lit_x_preferred": [
      "Madangas"
    ],
    "name:nld_x_preferred": [
      "Madang"
    ],
    "name:pol_x_preferred": [
      "Madang"
    ],
    "name:por_x_preferred": [
      "Madang"
    ],
    "name:rus_x_preferred": [
      "Маданг"
    ],
    "name:spa_x_preferred": [
      "Madang"
    ],
    "name:swe_x_preferred": [
      "Madang"
    ],
    "name:tpi_x_preferred": [
      "Madang"
    ],
    "name:ukr_x_preferred": [
      "Маданг"
    ],
    "name:und_x_variant": [
      "Ma-tang",
      "马垱",
      "Madang Zhen",
      "马垱镇"
    ],
    "name:urd_x_preferred": [
      "مادنگ"
    ],
    "name:vie_x_preferred": [
      "Madang"
    ],
    "wof:name": "Madang",
    "wof:placetype": "locality"
  },
  "geometry": {
    "coordinates": [
      116.65443,
      29.99064
    ],
    "type": "Point"
  }
}