{
  "type": "Feature",
  "properties": {
    "gn:admin1_code": "29.0",
    "gn:asciiname": "Habapu",
    "gn:country_code": "CN",
    "gn:dem": 1379,
    "gn:feature_class": "P",
    "gn:feature_code": "PPL",
    "gn:name": "Habapu",
    "gn:population": 0,
    "gn:timezone": "Asia/Shanghai",
    "iso:country": "CN",
    "name:zho_x_preferred": [
      "哈扒普"
    ],
    "wof:name": "Habapu",
    "wof:placetype": "locality"
  },
  "geometry": {
    "coordinates": [
      102.343,
      22.907
    ],
    "type": "Point"
  }
}