{
  "type": "Feature",
  "properties": {
    "gn:admin1_code": "8.0",
    "gn:asciiname": "Xinfu",
    "gn:country_code": "CN",
    "gn:dem": 137,
    "gn:feature_class": "P",
    "gn:feature_code": "PPLA4",
    "gn:name": "Xinfu",
    "gn:population": 0,
    "gn:timezone": "Asia/Shanghai",
    "iso:country": "CN",
    "name:ceb_x_preferred": [
      "Xinfu"
    ],
    "name:deu_x_preferred": [
      "Xinfu"
    ],
    "name:fra_x_preferred": [
      "Xinfu"
    ],
    "name:kor_x_preferred": [
      "신푸구"
    ],
    "name:nor_x_preferred": [
      "Xinfu"
    ],
    "name:rus_x_preferred": [
      "Синьфу"
    ],
    "name:swe_x_preferred": [
      "Xinfu"
    ],
    "name:und_x_variant": [
      "幸福",
      "Xinfu Xiang"
    ],
    "name:zho_x_preferred": [
      "幸福乡"
    ],
    "wof:name": "Xinfu",
    "wof:placetype": "locality"
  },
  "geometry": {
    "coordinates": [
      127.48997,
      50.23784000000001
    ],
    "type": "Point"
  }
}