{
  "type": "Feature",
  "properties": {
    "gn:admin1_code": "30.0",
    "gn:asciiname": "Yingzai",
    "gn:country_code": "CN",
    "gn:dem": 22,
    "gn:feature_class": "P",
    "gn:feature_code": "PPLA4",
    "gn:name": "Yingzai",
    "gn:population": 0,
    "gn:timezone": "Asia/Urumqi",
    "iso:country": "CN",
    "name:und_x_variant": [
      "Yingzai Zhen",
      "营仔镇"
    ],
    "name:zho_x_preferred": [
      "营仔"
    ],
    "wof:name": "Yingzai",
    "wof:placetype": "locality"
  },
  "geometry": {
    "coordinates": [
      109.9252,
      21.49052
    ],
    "type": "Point"
  }
}