{
  "type": "Feature",
  "properties": {
    "gn:admin1_code": "9",
    "gn:asciiname": "Gaofanzhuang",
    "gn:country_code": "CN",
    "gn:dem": 50,
    "gn:feature_class": "P",
    "gn:feature_code": "PPL",
    "gn:name": "Gaofanzhuang",
    "gn:population": 0,
    "gn:timezone": "Asia/Shanghai",
    "iso:country": "CN",
    "name:zho_x_preferred": [
      "高范庄"
    ],
    "wof:name": "Gaofanzhuang",
    "wof:placetype": "locality"
  },
  "geometry": {
    "coordinates": [
      116.083,
      34.5084
    ],
    "type": "Point"
  }
}