{
  "type": "Feature",
  "properties": {
    "gn:admin1_code": "16",
    "gn:asciiname": "Pojie",
    "gn:cc2": "CN",
    "gn:country_code": "CN",
    "gn:dem": 420,
    "gn:feature_class": "P",
    "gn:feature_code": "PPL",
    "gn:name": "Pojie",
    "gn:population": 0,
    "gn:timezone": "Asia/Shanghai",
    "iso:country": "CN",
    "name:und_x_variant": [
      "P’o-chieh",
      "P’o-chieh-t’un",
      "Pojie"
    ],
    "wof:name": "Pojie",
    "wof:placetype": "locality"
  },
  "geometry": {
    "coordinates": [
      107.06667,
      25.15
    ],
    "type": "Point"
  }
}