{
  "type": "Feature",
  "properties": {
    "gn:admin1_code": "10.0",
    "gn:asciiname": "Jianshao",
    "gn:country_code": "CN",
    "gn:dem": 381,
    "gn:feature_class": "P",
    "gn:feature_code": "PPL",
    "gn:name": "Jianshao",
    "gn:population": 0,
    "gn:timezone": "Asia/Shanghai",
    "iso:country": "CN",
    "name:zho_x_preferred": [
      "尖稍"
    ],
    "wof:name": "Jianshao",
    "wof:placetype": "locality"
  },
  "geometry": {
    "coordinates": [
      114.6959,
      39.00289
    ],
    "type": "Point"
  }
}