{
  "type": "Feature",
  "properties": {
    "gn:admin1_code": "11.0",
    "gn:asciiname": "Shibanxi",
    "gn:country_code": "CN",
    "gn:dem": 288,
    "gn:feature_class": "P",
    "gn:feature_code": "PPL",
    "gn:name": "Shibanxi",
    "gn:population": 0,
    "gn:timezone": "Asia/Shanghai",
    "iso:country": "CN",
    "name:zho_x_preferred": [
      "石板溪"
    ],
    "wof:name": "Shibanxi",
    "wof:placetype": "locality"
  },
  "geometry": {
    "coordinates": [
      110.98494,
      28.46096
    ],
    "type": "Point"
  }
}