{
  "type": "Feature",
  "properties": {
    "gn:admin1_code": "29.0",
    "gn:asciiname": "Nasu",
    "gn:country_code": "CN",
    "gn:dem": 1482,
    "gn:feature_class": "P",
    "gn:feature_code": "PPL",
    "gn:name": "Nasu",
    "gn:population": 0,
    "gn:timezone": "Asia/Shanghai",
    "iso:country": "CN",
    "name:ceb_x_preferred": [
      "Nasu"
    ],
    "name:ces_x_preferred": [
      "Nasu"
    ],
    "name:deu_x_preferred": [
      "Nasu"
    ],
    "name:ita_x_preferred": [
      "Nasu"
    ],
    "name:jpn_x_preferred": [
      "ナス"
    ],
    "name:nld_x_preferred": [
      "Nasu"
    ],
    "name:rus_x_preferred": [
      "Насу"
    ],
    "name:scn_x_preferred": [
      "Nasu"
    ],
    "name:slk_x_preferred": [
      "Nasu"
    ],
    "name:ukr_x_preferred": [
      "Насу"
    ],
    "name:zho_x_preferred": [
      "那苏"
    ],
    "wof:name": "Nasu",
    "wof:placetype": "locality"
  },
  "geometry": {
    "coordinates": [
      101.835,
      23.116
    ],
    "type": "Point"
  }
}