{
  "type": "Feature",
  "properties": {
    "gn:country": "CN",
    "gn:fcode": "PPLA3",
    "gn:population": 0,
    "iso:country": "CN",
    "name:cym_x_preferred": [
      "Ardal Yangling"
    ],
    "name:deu_x_preferred": [
      "Yangling"
    ],
    "name:eng_x_preferred": [
      "Yangling District"
    ],
    "name:gan_x_preferred": [
      "杨陵区"
    ],
    "name:ind_x_preferred": [
      "Distrik Yangling"
    ],
    "name:jpn_x_preferred": [
      "楊陵区"
    ],
    "name:kor_x_preferred": [
      "양링구"
    ],
    "name:nan_x_preferred": [
      "Iông-lêng-khu"
    ],
    "name:nld_x_preferred": [
      "Yangling"
    ],
    "name:nob_x_preferred": [
      "Yangling"
    ],
    "name:rus_x_preferred": [
      "Янлин"
    ],
    "name:swe_x_preferred": [
      "Yangling"
    ],
    "name:und_x_variant": [
      "Yang-ling-chen"
    ],
    "name:urd_x_preferred": [
      "ینگلنگ ضلع"
    ],
    "name:vie_x_preferred": [
      "Dương Lăng"
    ],
    "name:wuu_x_preferred": [
      "杨陵区"
    ],
    "name:yue_x_preferred": [
      "楊陵區"
    ],
    "name:zho_x_preferred": [
      "杨陵"
    ],
    "name:zho_x_variant": [
      "杨陵区"
    ],
    "qs:name": "Yangling",
    "qs:photos_9r": 0,
    "qs:photos_sr": 0,
    "qs:pop_sr": "0",
    "wd:wordcount": 275,
    "wof:name": "Yangling",
    "wof:placetype": "locality",
    "wof:population": 0
  },
  "geometry": {
    "coordinates": [
      108.07891,
      34.27173
    ],
    "type": "Point"
  }
}