{
  "type": "Feature",
  "properties": {
    "gn:admin1_code": "26.0",
    "gn:asciiname": "Yang'erba",
    "gn:country_code": "CN",
    "gn:dem": 790,
    "gn:feature_class": "P",
    "gn:feature_code": "PPL",
    "gn:name": "Yang’erba",
    "gn:population": 0,
    "gn:timezone": "Asia/Shanghai",
    "iso:country": "CN",
    "name:und_x_variant": [
      "Yang’erba",
      "羊儿坝"
    ],
    "wof:name": "Yang'erba",
    "wof:placetype": "locality"
  },
  "geometry": {
    "coordinates": [
      106.36469,
      33.3562
    ],
    "type": "Point"
  }
}