{
  "type": "Feature",
  "properties": {
    "gn:admin1_code": "29",
    "gn:asciiname": "Hengdalu",
    "gn:country_code": "CN",
    "gn:dem": 1857,
    "gn:feature_class": "P",
    "gn:feature_code": "PPL",
    "gn:name": "Hengdalu",
    "gn:population": 0,
    "gn:timezone": "Asia/Shanghai",
    "iso:country": "CN",
    "name:und_x_variant": [
      "横大路"
    ],
    "wof:name": "Hengdalu",
    "wof:placetype": "locality"
  },
  "geometry": {
    "coordinates": [
      103.83525,
      25.29609
    ],
    "type": "Point"
  }
}