{
  "type": "Feature",
  "properties": {
    "gn:admin1_code": "19.0",
    "gn:asciiname": "Beiling",
    "gn:country_code": "CN",
    "gn:dem": 226,
    "gn:feature_class": "P",
    "gn:feature_code": "PPL",
    "gn:name": "Beiling",
    "gn:population": 0,
    "gn:timezone": "Asia/Shanghai",
    "iso:country": "CN",
    "name:zho_x_preferred": [
      "北岭"
    ],
    "wof:name": "Beiling",
    "wof:placetype": "locality"
  },
  "geometry": {
    "coordinates": [
      120.448,
      40.9157
    ],
    "type": "Point"
  }
}