{
  "type": "Feature",
  "properties": {
    "gn:admin1_code": "14.0",
    "gn:asciiname": "Chongbaga",
    "gn:country_code": "CN",
    "gn:dem": 4125,
    "gn:feature_class": "P",
    "gn:feature_code": "PPL",
    "gn:name": "Chongbaga",
    "gn:population": 0,
    "gn:timezone": "Asia/Urumqi",
    "iso:country": "CN",
    "name:zho_x_preferred": [
      "冲巴嘎"
    ],
    "wof:name": "Chongbaga",
    "wof:placetype": "locality"
  },
  "geometry": {
    "coordinates": [
      92.11418,
      28.49625
    ],
    "type": "Point"
  }
}