{
  "type": "Feature",
  "properties": {
    "gn:admin1_code": "19.0",
    "gn:asciiname": "Kaoshantun",
    "gn:country_code": "CN",
    "gn:dem": 59,
    "gn:feature_class": "P",
    "gn:feature_code": "PPL",
    "gn:name": "Kaoshantun",
    "gn:population": 0,
    "gn:timezone": "Asia/Shanghai",
    "iso:country": "CN",
    "name:zho_x_preferred": [
      "靠山屯"
    ],
    "wof:name": "Kaoshantun",
    "wof:placetype": "locality"
  },
  "geometry": {
    "coordinates": [
      122.98713,
      42.24476
    ],
    "type": "Point"
  }
}