{
  "type": "Feature",
  "properties": {
    "gn:admin1_code": "21.0",
    "gn:asciiname": "Shangduancha",
    "gn:country_code": "CN",
    "gn:dem": 1950,
    "gn:feature_class": "P",
    "gn:feature_code": "PPL",
    "gn:name": "Shangduancha",
    "gn:population": 0,
    "gn:timezone": "Asia/Shanghai",
    "iso:country": "CN",
    "name:zho_x_preferred": [
      "上短岔"
    ],
    "wof:name": "Shangduancha",
    "wof:placetype": "locality"
  },
  "geometry": {
    "coordinates": [
      105.93724,
      35.56361
    ],
    "type": "Point"
  }
}