{
  "type": "Feature",
  "properties": {
    "gn:admin1_code": "22",
    "gn:asciiname": "Lugouqiao",
    "gn:country_code": "CN",
    "gn:dem": 54,
    "gn:feature_class": "P",
    "gn:feature_code": "PPLA4",
    "gn:name": "Lugouqiao",
    "gn:population": 0,
    "gn:timezone": "Asia/Shanghai",
    "iso:country": "CN",
    "name:deu_x_preferred": [
      "Wanping-Festung"
    ],
    "name:nor_x_preferred": [
      "Wanpingfortet"
    ],
    "name:pol_x_preferred": [
      "Twierdza Wanping"
    ],
    "name:rus_x_preferred": [
      "Ваньпин"
    ],
    "name:swe_x_preferred": [
      "Wanping"
    ],
    "name:ukr_x_preferred": [
      "Ваньпін"
    ],
    "name:und_x_variant": [
      "Van’pin",
      "Lu-kou-ch’iao",
      "Wan-p’ing-hsien",
      "Lugouqiao",
      "Lugouqiao Jiedao"
    ],
    "name:zho_x_preferred": [
      "卢沟桥"
    ],
    "name:zho_x_variant": [
      "卢沟桥街道",
      "宛平城"
    ],
    "wof:name": "Lugouqiao",
    "wof:placetype": "locality"
  },
  "geometry": {
    "coordinates": [
      116.27745,
      39.8688
    ],
    "type": "Point"
  }
}