{
  "type": "Feature",
  "properties": {
    "gn:admin1_code": "25",
    "gn:asciiname": "Songlaozhi Xicun",
    "gn:country_code": "CN",
    "gn:dem": 42,
    "gn:feature_class": "P",
    "gn:feature_code": "PPL",
    "gn:name": "Songlaozhi Xicun",
    "gn:population": 0,
    "gn:timezone": "Asia/Shanghai",
    "iso:country": "CN",
    "name:zho_x_preferred": [
      "宋涝枝西村"
    ],
    "wof:name": "Songlaozhi Xicun",
    "wof:placetype": "locality"
  },
  "geometry": {
    "coordinates": [
      118.71,
      34.7024
    ],
    "type": "Point"
  }
}