{
  "type": "Feature",
  "properties": {
    "gn:admin1_code": "16.0",
    "gn:asciiname": "Shangzhi",
    "gn:country_code": "CN",
    "gn:dem": 152,
    "gn:feature_class": "P",
    "gn:feature_code": "PPL",
    "gn:name": "Shangzhi",
    "gn:population": 0,
    "gn:timezone": "Asia/Shanghai",
    "iso:country": "CN",
    "name:ara_x_preferred": [
      "شانغزي"
    ],
    "name:ceb_x_preferred": [
      "Shangzhi"
    ],
    "name:deu_x_preferred": [
      "Shangzhi"
    ],
    "name:eus_x_preferred": [
      "Shangzhi"
    ],
    "name:fas_x_preferred": [
      "شانگزی"
    ],
    "name:fra_x_preferred": [
      "Shangzhi"
    ],
    "name:glg_x_preferred": [
      "Shangzhi"
    ],
    "name:heb_x_preferred": [
      "שאנג'י"
    ],
    "name:hin_x_preferred": [
      "शांगझी"
    ],
    "name:hun_x_preferred": [
      "Shangzhi"
    ],
    "name:ita_x_preferred": [
      "Shangzhi"
    ],
    "name:jpn_x_preferred": [
      "尚志市"
    ],
    "name:kik_x_preferred": [
      "Shangzhi"
    ],
    "name:kor_x_preferred": [
      "상즈시"
    ],
    "name:mlg_x_preferred": [
      "Shangzhi"
    ],
    "name:nor_x_preferred": [
      "Shangzhi"
    ],
    "name:pam_x_preferred": [
      "Shangzhi"
    ],
    "name:rus_x_preferred": [
      "Шанчжи"
    ],
    "name:spa_x_preferred": [
      "Shangzhi"
    ],
    "name:swe_x_preferred": [
      "Shangzhi"
    ],
    "name:tgl_x_preferred": [
      "Shangzhi"
    ],
    "name:urd_x_preferred": [
      "شانگژی"
    ],
    "name:vie_x_preferred": [
      "Thượng Chí"
    ],
    "name:war_x_preferred": [
      "Shangzhi"
    ],
    "name:zho_x_preferred": [
      "尚智"
    ],
    "name:zho_x_variant": [
      "尚志市"
    ],
    "wof:name": "Shangzhi",
    "wof:placetype": "locality"
  },
  "geometry": {
    "coordinates": [
      110.936,
      22.6849
    ],
    "type": "Point"
  }
}