{
  "type": "Feature",
  "properties": {
    "gn:admin1_code": "12.0",
    "gn:asciiname": "Xiongjianao",
    "gn:country_code": "CN",
    "gn:dem": 33,
    "gn:feature_class": "P",
    "gn:feature_code": "PPL",
    "gn:name": "Xiongjianao",
    "gn:population": 0,
    "gn:timezone": "Asia/Shanghai",
    "iso:country": "CN",
    "name:zho_x_preferred": [
      "Xiongjianao"
    ],
    "name:zho_x_variant": [
      "熊家垴"
    ],
    "wof:name": "Xiongjianao",
    "wof:placetype": "locality"
  },
  "geometry": {
    "coordinates": [
      115.19884,
      29.87003
    ],
    "type": "Point"
  }
}