{
  "type": "Feature",
  "properties": {
    "gn:admin1_code": "8.0",
    "gn:asciiname": "Hongshengcun",
    "gn:country_code": "CN",
    "gn:dem": 110,
    "gn:feature_class": "P",
    "gn:feature_code": "PPL",
    "gn:name": "Hongshengcun",
    "gn:population": 0,
    "gn:timezone": "Asia/Shanghai",
    "iso:country": "CN",
    "name:zho_x_preferred": [
      "红胜村"
    ],
    "wof:name": "Hongshengcun",
    "wof:placetype": "locality"
  },
  "geometry": {
    "coordinates": [
      129.53252,
      46.16098
    ],
    "type": "Point"
  }
}