{
  "type": "Feature",
  "properties": {
    "gn:admin1_code": "11.0",
    "gn:asciiname": "Suode",
    "gn:country_code": "CN",
    "gn:dem": 788,
    "gn:feature_class": "P",
    "gn:feature_code": "PPL",
    "gn:name": "Suode",
    "gn:population": 0,
    "gn:timezone": "Asia/Shanghai",
    "iso:country": "CN",
    "name:zho_x_preferred": [
      "所德"
    ],
    "wof:name": "Suode",
    "wof:placetype": "locality"
  },
  "geometry": {
    "coordinates": [
      109.35969,
      28.07078
    ],
    "type": "Point"
  }
}