{
  "type": "Feature",
  "properties": {
    "gn:admin1_code": "26.0",
    "gn:asciiname": "Jiaoziyuan",
    "gn:country_code": "CN",
    "gn:dem": 1629,
    "gn:feature_class": "P",
    "gn:feature_code": "PPL",
    "gn:name": "Jiaoziyuan",
    "gn:population": 0,
    "gn:timezone": "Asia/Shanghai",
    "iso:country": "CN",
    "name:zho_x_preferred": [
      "焦子园"
    ],
    "wof:name": "Jiaoziyuan",
    "wof:placetype": "locality"
  },
  "geometry": {
    "coordinates": [
      107.48378,
      32.56242
    ],
    "type": "Point"
  }
}