{
  "type": "Feature",
  "properties": {
    "iso:country": "CN",
    "name:ara_x_preferred": [
      "تشانغبينغ"
    ],
    "name:ben_x_preferred": [
      "চ্যাংপিং"
    ],
    "name:deu_x_preferred": [
      "Changping"
    ],
    "name:ell_x_preferred": [
      "Τσανγκπίνγκ"
    ],
    "name:eng_x_preferred": [
      "Changping"
    ],
    "name:fas_x_preferred": [
      "چانگ پینگ"
    ],
    "name:fra_x_preferred": [
      "Changping"
    ],
    "name:heb_x_preferred": [
      "צ'נגפינג"
    ],
    "name:hin_x_preferred": [
      "चैंगपिंग"
    ],
    "name:hun_x_preferred": [
      "Changping"
    ],
    "name:ind_x_preferred": [
      "Changping"
    ],
    "name:ita_x_preferred": [
      "Changping"
    ],
    "name:jpn_x_preferred": [
      "常平镇"
    ],
    "name:kor_x_preferred": [
      "창핑"
    ],
    "name:nld_x_preferred": [
      "Changping"
    ],
    "name:pol_x_preferred": [
      "Changping"
    ],
    "name:por_x_preferred": [
      "Changping"
    ],
    "name:rus_x_preferred": [
      "Чанпин"
    ],
    "name:spa_x_preferred": [
      "Changping"
    ],
    "name:swe_x_preferred": [
      "Changping"
    ],
    "name:tur_x_preferred": [
      "Changping"
    ],
    "name:ukr_x_preferred": [
      "Чанпін"
    ],
    "name:urd_x_preferred": [
      "چینگپنگ"
    ],
    "name:vie_x_preferred": [
      "Xương Bình"
    ],
    "name:zho_cn_x_preferred": [
      "常平镇"
    ],
    "name:zho_tw_x_preferred": [
      "常平"
    ],
    "name:zho_x_preferred": [
      "常平镇"
    ],
    "qs:name": "常平镇",
    "qs:name_adm0": "中國",
    "qs:name_adm1": "广东省",
    "qs:photos": 95,
    "qs:photos_1k": 19,
    "qs:photos_9k": 1,
    "qs:photos_9r": 3,
    "qs:photos_all": 95,
    "qs:photos_sr": 3,
    "qs:placetype": "Town",
    "qs:pop_sr": "0",
    "wof:name": "Changping",
    "wof:placetype": "locality"
  },
  "geometry": {
    "coordinates": [
      113.997745,
      22.972177
    ],
    "type": "Point"
  }
}