{
  "type": "Feature",
  "properties": {
    "gn:admin1_code": "3.0",
    "gn:asciiname": "Zengjianghe",
    "gn:country_code": "CN",
    "gn:dem": 185,
    "gn:feature_class": "P",
    "gn:feature_code": "PPL",
    "gn:name": "Zengjianghe",
    "gn:population": 0,
    "gn:timezone": "Asia/Shanghai",
    "iso:country": "CN",
    "name:und_x_variant": [
      "增江河"
    ],
    "wof:name": "Zengjianghe",
    "wof:placetype": "locality"
  },
  "geometry": {
    "coordinates": [
      116.16692,
      26.76572
    ],
    "type": "Point"
  }
}