{
  "type": "Feature",
  "properties": {
    "gn:admin1_code": "19.0",
    "gn:asciiname": "Hantuncun",
    "gn:country_code": "CN",
    "gn:dem": 222,
    "gn:feature_class": "P",
    "gn:feature_code": "PPL",
    "gn:name": "Hantuncun",
    "gn:population": 0,
    "gn:timezone": "Asia/Shanghai",
    "iso:country": "CN",
    "name:zho_x_preferred": [
      "韩屯村"
    ],
    "wof:name": "Hantuncun",
    "wof:placetype": "locality"
  },
  "geometry": {
    "coordinates": [
      122.338,
      40.0475
    ],
    "type": "Point"
  }
}