{
  "type": "Feature",
  "properties": {
    "gn:admin1_code": "29.0",
    "gn:asciiname": "Yansi",
    "gn:country_code": "CN",
    "gn:dem": 1341,
    "gn:feature_class": "P",
    "gn:feature_code": "PPL",
    "gn:name": "Yansi",
    "gn:population": 0,
    "gn:timezone": "Asia/Shanghai",
    "iso:country": "CN",
    "name:zho_x_preferred": [
      "燕寺"
    ],
    "wof:name": "Yansi",
    "wof:placetype": "locality"
  },
  "geometry": {
    "coordinates": [
      98.626,
      24.6637
    ],
    "type": "Point"
  }
}