{
  "type": "Feature",
  "properties": {
    "gn:admin1_code": "19.0",
    "gn:asciiname": "Baimagou",
    "gn:country_code": "CN",
    "gn:dem": 289,
    "gn:feature_class": "P",
    "gn:feature_code": "PPL",
    "gn:name": "Baimagou",
    "gn:population": 0,
    "gn:timezone": "Asia/Shanghai",
    "iso:country": "CN",
    "name:zho_x_preferred": [
      "白马沟"
    ],
    "wof:name": "Baimagou",
    "wof:placetype": "locality"
  },
  "geometry": {
    "coordinates": [
      120.317,
      40.8269
    ],
    "type": "Point"
  }
}