{
  "type": "Feature",
  "properties": {
    "gn:admin1_code": "16",
    "gn:asciiname": "Bada",
    "gn:country_code": "CN",
    "gn:dem": 304,
    "gn:feature_class": "P",
    "gn:feature_code": "PPL",
    "gn:name": "Bada",
    "gn:population": 0,
    "gn:timezone": "Asia/Shanghai",
    "iso:country": "CN",
    "name:ara_x_preferred": [
      "بادا"
    ],
    "name:aze_x_preferred": [
      "Bada"
    ],
    "name:ces_x_preferred": [
      "Bada"
    ],
    "name:ckb_x_preferred": [
      "بادا"
    ],
    "name:deu_x_preferred": [
      "Bada"
    ],
    "name:fas_x_preferred": [
      "بادا"
    ],
    "name:fin_x_preferred": [
      "Bada"
    ],
    "name:fra_x_preferred": [
      "Bada"
    ],
    "name:heb_x_preferred": [
      "Bada"
    ],
    "name:hun_x_preferred": [
      "Bada"
    ],
    "name:hye_x_preferred": [
      "Բադա"
    ],
    "name:ind_x_preferred": [
      "Samsung bada"
    ],
    "name:ita_x_preferred": [
      "Bada"
    ],
    "name:jpn_x_preferred": [
      "Bada"
    ],
    "name:kor_x_preferred": [
      "바다"
    ],
    "name:nep_x_preferred": [
      "बडा"
    ],
    "name:nld_x_preferred": [
      "Bada"
    ],
    "name:pol_x_preferred": [
      "Bada"
    ],
    "name:por_x_preferred": [
      "Bada"
    ],
    "name:rus_x_preferred": [
      "Bada"
    ],
    "name:spa_x_preferred": [
      "Bada"
    ],
    "name:swe_x_preferred": [
      "Bada"
    ],
    "name:tam_x_preferred": [
      "படா"
    ],
    "name:tha_x_preferred": [
      "บาดา"
    ],
    "name:tur_x_preferred": [
      "Bada"
    ],
    "name:ukr_x_preferred": [
      "Bada"
    ],
    "name:urd_x_preferred": [
      "باڈا"
    ],
    "name:vie_x_preferred": [
      "Bada"
    ],
    "name:zho_x_preferred": [
      "八打"
    ],
    "name:zho_x_variant": [
      "Bada"
    ],
    "wof:name": "Bada",
    "wof:placetype": "locality"
  },
  "geometry": {
    "coordinates": [
      109.604,
      25.2271
    ],
    "type": "Point"
  }
}