{
  "type": "Feature",
  "properties": {
    "gn:admin1_code": "15.0",
    "gn:asciiname": "Xiachejiashan",
    "gn:country_code": "CN",
    "gn:dem": 2009,
    "gn:feature_class": "P",
    "gn:feature_code": "PPL",
    "gn:name": "Xiachejiashan",
    "gn:population": 0,
    "gn:timezone": "Asia/Shanghai",
    "iso:country": "CN",
    "name:zho_x_preferred": [
      "下车家山"
    ],
    "wof:name": "Xiachejiashan",
    "wof:placetype": "locality"
  },
  "geometry": {
    "coordinates": [
      104.714,
      35.9624
    ],
    "type": "Point"
  }
}