{
  "type": "Feature",
  "properties": {
    "gn:admin1_code": "6.0",
    "gn:asciiname": "Kasha",
    "gn:country_code": "CN",
    "gn:dem": 3712,
    "gn:feature_class": "P",
    "gn:feature_code": "PPL",
    "gn:name": "Kasha",
    "gn:population": 0,
    "gn:timezone": "Asia/Urumqi",
    "iso:country": "CN",
    "name:ara_x_preferred": [
      "كشكاة"
    ],
    "name:aze_x_preferred": [
      "Qarabaşaq sıyığı"
    ],
    "name:chv_x_preferred": [
      "Пăтă"
    ],
    "name:deu_x_preferred": [
      "Gretschnewaja Kascha"
    ],
    "name:epo_x_preferred": [
      "Fagopira grio"
    ],
    "name:est_x_preferred": [
      "Tatrapuder"
    ],
    "name:fas_x_preferred": [
      "کاشا"
    ],
    "name:fra_x_preferred": [
      "Kacha"
    ],
    "name:heb_x_preferred": [
      "קאשה"
    ],
    "name:hun_x_preferred": [
      "Kása"
    ],
    "name:hye_x_preferred": [
      "Հնդկացորենի շիլա"
    ],
    "name:ita_x_preferred": [
      "Kaša"
    ],
    "name:jpn_x_preferred": [
      "カーシャ"
    ],
    "name:kat_x_preferred": [
      "ფაფა"
    ],
    "name:lit_x_preferred": [
      "Grikių košė"
    ],
    "name:nld_x_preferred": [
      "Kasja"
    ],
    "name:pol_x_preferred": [
      "Kasza gryczana"
    ],
    "name:por_x_preferred": [
      "Kasha"
    ],
    "name:rus_x_preferred": [
      "Гречневая каша"
    ],
    "name:sah_x_preferred": [
      "Гречневай хааһы"
    ],
    "name:spa_x_preferred": [
      "Kasha"
    ],
    "name:szl_x_preferred": [
      "Pogańske krupy"
    ],
    "name:tur_x_preferred": [
      "Düğürcük çorbası"
    ],
    "name:ukr_x_preferred": [
      "Гречана каша"
    ],
    "name:zho_x_preferred": [
      "卡沙"
    ],
    "wof:name": "Kasha",
    "wof:placetype": "locality"
  },
  "geometry": {
    "coordinates": [
      97.37125,
      32.73051
    ],
    "type": "Point"
  }
}