{
  "type": "Feature",
  "properties": {
    "gn:admin1_code": "3.0",
    "gn:asciiname": "Xinzhou",
    "gn:country_code": "CN",
    "gn:dem": 14,
    "gn:feature_class": "P",
    "gn:feature_code": "PPL",
    "gn:name": "Xinzhou",
    "gn:population": 0,
    "gn:timezone": "Asia/Shanghai",
    "iso:country": "CN",
    "name:ara_x_preferred": [
      "شينتشو"
    ],
    "name:bel_x_preferred": [
      "Сіньджоў"
    ],
    "name:cdo_x_preferred": [
      "Hṳ̆ng-ciŭ"
    ],
    "name:ceb_x_preferred": [
      "Xinzhou"
    ],
    "name:ces_x_preferred": [
      "Sin-čou"
    ],
    "name:dan_x_preferred": [
      "Xinzhou"
    ],
    "name:deu_x_preferred": [
      "Xinzhou"
    ],
    "name:eus_x_preferred": [
      "Xinzhou"
    ],
    "name:fas_x_preferred": [
      "شینجو"
    ],
    "name:fin_x_preferred": [
      "Xinzhou"
    ],
    "name:fra_x_preferred": [
      "Xinzhou"
    ],
    "name:hun_x_preferred": [
      "Xinzhou"
    ],
    "name:ita_x_preferred": [
      "Xinzhou"
    ],
    "name:jpn_x_preferred": [
      "忻州市"
    ],
    "name:kik_x_preferred": [
      "Xinzhou"
    ],
    "name:kor_x_preferred": [
      "신저우시"
    ],
    "name:mlg_x_preferred": [
      "Xinzhou"
    ],
    "name:nld_x_preferred": [
      "Xinzhou"
    ],
    "name:nno_x_preferred": [
      "Xinzhou"
    ],
    "name:nor_x_preferred": [
      "Xinzhou"
    ],
    "name:pol_x_preferred": [
      "Xinzhou"
    ],
    "name:rus_x_preferred": [
      "Синьчжоу"
    ],
    "name:spa_x_preferred": [
      "Xinzhóu"
    ],
    "name:swe_x_preferred": [
      "Xinzhou"
    ],
    "name:tur_x_preferred": [
      "Xinzhou"
    ],
    "name:ukr_x_preferred": [
      "Сіньчжоу"
    ],
    "name:und_x_variant": [
      "新洲"
    ],
    "name:urd_x_preferred": [
      "شنژوو"
    ],
    "name:vie_x_preferred": [
      "Hãn Châu"
    ],
    "name:war_x_preferred": [
      "Xinzhou"
    ],
    "name:wuu_x_preferred": [
      "忻州市"
    ],
    "name:zho_x_preferred": [
      "忻州市"
    ],
    "wof:name": "Xinzhou",
    "wof:placetype": "locality"
  },
  "geometry": {
    "coordinates": [
      116.02108,
      29.0458
    ],
    "type": "Point"
  }
}