{
  "type": "Feature",
  "properties": {
    "gn:admin1_code": "33.0",
    "gn:asciiname": "Hetao",
    "gn:country_code": "CN",
    "gn:dem": 443,
    "gn:feature_class": "P",
    "gn:feature_code": "PPL",
    "gn:name": "Hetao",
    "gn:population": 0,
    "gn:timezone": "Asia/Shanghai",
    "iso:country": "CN",
    "name:deu_x_preferred": [
      "Hetao-Ebene"
    ],
    "name:fra_x_preferred": [
      "Hetao"
    ],
    "name:kor_x_preferred": [
      "허타오"
    ],
    "name:pol_x_preferred": [
      "Hetao"
    ],
    "name:rus_x_preferred": [
      "Хэтао"
    ],
    "name:zho_x_preferred": [
      "核桃"
    ],
    "wof:name": "Hetao",
    "wof:placetype": "locality"
  },
  "geometry": {
    "coordinates": [
      107.54196,
      29.43833
    ],
    "type": "Point"
  }
}