{
  "type": "Feature",
  "properties": {
    "gn:admin1_code": "16.0",
    "gn:asciiname": "Lulin",
    "gn:country_code": "CN",
    "gn:dem": 572,
    "gn:feature_class": "P",
    "gn:feature_code": "PPL",
    "gn:name": "Lulin",
    "gn:population": 0,
    "gn:timezone": "Asia/Shanghai",
    "iso:country": "CN",
    "name:deu_x_preferred": [
      "Lülin"
    ],
    "name:jpn_x_preferred": [
      "緑林軍"
    ],
    "name:kor_x_preferred": [
      "녹림군"
    ],
    "name:wuu_x_preferred": [
      "绿林军"
    ],
    "name:zho_x_preferred": [
      "渌吝"
    ],
    "name:zho_x_variant": [
      "绿林军"
    ],
    "wof:name": "Lulin",
    "wof:placetype": "locality"
  },
  "geometry": {
    "coordinates": [
      106.844,
      23.3839
    ],
    "type": "Point"
  }
}