{
  "type": "Feature",
  "properties": {
    "gn:admin1_code": "10",
    "gn:asciiname": "Liangjiaying",
    "gn:country_code": "CN",
    "gn:dem": 1419,
    "gn:feature_class": "P",
    "gn:feature_code": "PPL",
    "gn:name": "Liangjiaying",
    "gn:population": 0,
    "gn:timezone": "Asia/Shanghai",
    "iso:country": "CN",
    "name:zho_x_preferred": [
      "梁家营"
    ],
    "wof:name": "Liangjiaying",
    "wof:placetype": "locality"
  },
  "geometry": {
    "coordinates": [
      114.67311,
      41.73477000000001
    ],
    "type": "Point"
  }
}