{
  "type": "Feature",
  "properties": {
    "gn:admin1_code": "26.0",
    "gn:asciiname": "Gaowacun",
    "gn:country_code": "CN",
    "gn:dem": 348,
    "gn:feature_class": "P",
    "gn:feature_code": "PPL",
    "gn:name": "Gaowacun",
    "gn:population": 0,
    "gn:timezone": "Asia/Shanghai",
    "iso:country": "CN",
    "name:zho_x_preferred": [
      "高洼村"
    ],
    "wof:name": "Gaowacun",
    "wof:placetype": "locality"
  },
  "geometry": {
    "coordinates": [
      110.02678,
      34.70199
    ],
    "type": "Point"
  }
}