{
  "type": "Feature",
  "properties": {
    "gn:admin1_code": "16.0",
    "gn:asciiname": "Dong'ou",
    "gn:country_code": "CN",
    "gn:dem": 630,
    "gn:feature_class": "P",
    "gn:feature_code": "PPL",
    "gn:name": "Dong’ou",
    "gn:population": 0,
    "gn:timezone": "Asia/Shanghai",
    "iso:country": "CN",
    "name:cdo_x_preferred": [
      "Dĕ̤ng-ĕu-guók"
    ],
    "name:und_x_variant": [
      "Dong’ou"
    ],
    "name:vie_x_preferred": [
      "Đông Âu"
    ],
    "name:wuu_x_preferred": [
      "东瓯国"
    ],
    "name:zho_x_preferred": [
      "洞欧"
    ],
    "name:zho_x_variant": [
      "东瓯国"
    ],
    "wof:name": "Dong'ou",
    "wof:placetype": "locality"
  },
  "geometry": {
    "coordinates": [
      108.379,
      25.3959
    ],
    "type": "Point"
  }
}