{
  "type": "Feature",
  "properties": {
    "gn:admin1_code": "4.0",
    "gn:asciiname": "Xiaoliuzhuang",
    "gn:country_code": "CN",
    "gn:dem": 8,
    "gn:feature_class": "P",
    "gn:feature_code": "PPL",
    "gn:name": "Xiaoliuzhuang",
    "gn:population": 0,
    "gn:timezone": "Asia/Shanghai",
    "iso:country": "CN",
    "name:zho_x_preferred": [
      "Xiaoliuzhuang"
    ],
    "name:zho_x_variant": [
      "小刘庄"
    ],
    "wof:name": "Xiaoliuzhuang",
    "wof:placetype": "locality"
  },
  "geometry": {
    "coordinates": [
      119.6265,
      33.87410999999999
    ],
    "type": "Point"
  }
}