{
  "type": "Feature",
  "properties": {
    "gn:admin1_code": "11",
    "gn:asciiname": "Shuangqiaoping",
    "gn:country_code": "CN",
    "gn:dem": 53,
    "gn:feature_class": "P",
    "gn:feature_code": "PPLA4",
    "gn:name": "Shuangqiaoping",
    "gn:population": 0,
    "gn:timezone": "Asia/Shanghai",
    "iso:country": "CN",
    "name:und_x_variant": [
      "双桥坪",
      "Shuangqiaoping Zhen",
      "双桥坪镇"
    ],
    "wof:name": "Shuangqiaoping",
    "wof:placetype": "locality"
  },
  "geometry": {
    "coordinates": [
      111.77283,
      29.2662
    ],
    "type": "Point"
  }
}