{
  "type": "Feature",
  "properties": {
    "gn:admin1_code": "30",
    "gn:asciiname": "Feng'an",
    "gn:country_code": "CN",
    "gn:dem": 500,
    "gn:feature_class": "P",
    "gn:feature_code": "PPL",
    "gn:name": "Feng’an",
    "gn:population": 0,
    "gn:timezone": "Asia/Shanghai",
    "iso:country": "CN",
    "name:zho_x_preferred": [
      "丰安"
    ],
    "name:zho_x_variant": [
      "Feng’an"
    ],
    "wof:name": "Feng'an",
    "wof:placetype": "locality"
  },
  "geometry": {
    "coordinates": [
      111.36273,
      22.22089
    ],
    "type": "Point"
  }
}