{
  "type": "Feature",
  "properties": {
    "gn:admin1_code": "16.0",
    "gn:asciiname": "Hetong",
    "gn:country_code": "CN",
    "gn:dem": 111,
    "gn:feature_class": "P",
    "gn:feature_code": "PPL",
    "gn:name": "Hetong",
    "gn:population": 0,
    "gn:timezone": "Asia/Shanghai",
    "iso:country": "CN",
    "name:zho_x_preferred": [
      "和同"
    ],
    "wof:name": "Hetong",
    "wof:placetype": "locality"
  },
  "geometry": {
    "coordinates": [
      107.222,
      23.5893
    ],
    "type": "Point"
  }
}