{
  "type": "Feature",
  "properties": {
    "gn:admin1_code": "7.0",
    "gn:asciiname": "Daping",
    "gn:country_code": "CN",
    "gn:dem": 823,
    "gn:feature_class": "P",
    "gn:feature_code": "PPL",
    "gn:name": "Daping",
    "gn:population": 0,
    "gn:timezone": "Asia/Shanghai",
    "iso:country": "CN",
    "name:ceb_x_preferred": [
      "Daping"
    ],
    "name:deu_x_preferred": [
      "Daping"
    ],
    "name:swe_x_preferred": [
      "Daping"
    ],
    "name:zho_x_preferred": [
      "大坪"
    ],
    "wof:name": "Daping",
    "wof:placetype": "locality"
  },
  "geometry": {
    "coordinates": [
      118.06613,
      26.69396
    ],
    "type": "Point"
  }
}