{
  "type": "Feature",
  "properties": {
    "gn:admin1_code": "26.0",
    "gn:asciiname": "Liujiawancun",
    "gn:country_code": "CN",
    "gn:dem": 755,
    "gn:feature_class": "P",
    "gn:feature_code": "PPL",
    "gn:name": "Liujiawancun",
    "gn:population": 0,
    "gn:timezone": "Asia/Shanghai",
    "iso:country": "CN",
    "name:zho_x_preferred": [
      "刘家湾村"
    ],
    "wof:name": "Liujiawancun",
    "wof:placetype": "locality"
  },
  "geometry": {
    "coordinates": [
      110.20181,
      36.85941
    ],
    "type": "Point"
  }
}