{
  "type": "Feature",
  "properties": {
    "gn:admin1_code": "2.0",
    "gn:asciiname": "Youchebang",
    "gn:country_code": "CN",
    "gn:dem": 8,
    "gn:feature_class": "P",
    "gn:feature_code": "PPL",
    "gn:name": "Youchebang",
    "gn:population": 0,
    "gn:timezone": "Asia/Shanghai",
    "iso:country": "CN",
    "name:und_x_variant": [
      "油车浜"
    ],
    "wof:name": "Youchebang",
    "wof:placetype": "locality"
  },
  "geometry": {
    "coordinates": [
      120.84414,
      30.69332
    ],
    "type": "Point"
  }
}