{
  "type": "Feature",
  "properties": {
    "gn:admin1_code": "32.0",
    "gn:asciiname": "Yuri",
    "gn:country_code": "CN",
    "gn:dem": 2699,
    "gn:feature_class": "P",
    "gn:feature_code": "PPL",
    "gn:name": "Yuri",
    "gn:population": 0,
    "gn:timezone": "Asia/Shanghai",
    "iso:country": "CN",
    "name:ara_x_preferred": [
      "يوري"
    ],
    "name:ceb_x_preferred": [
      "Yuri"
    ],
    "name:est_x_preferred": [
      "Juri"
    ],
    "name:fas_x_preferred": [
      "یوری"
    ],
    "name:fin_x_preferred": [
      "Yuri"
    ],
    "name:fra_x_preferred": [
      "Yuri"
    ],
    "name:heb_x_preferred": [
      "יורי"
    ],
    "name:ita_x_preferred": [
      "Yuri"
    ],
    "name:kor_x_preferred": [
      "유리"
    ],
    "name:nld_x_preferred": [
      "Yuri"
    ],
    "name:rus_x_preferred": [
      "Юри"
    ],
    "name:slk_x_preferred": [
      "Yuri"
    ],
    "name:spa_x_preferred": [
      "Yuri"
    ],
    "name:swe_x_preferred": [
      "Yuri"
    ],
    "name:tgl_x_preferred": [
      "Yuri"
    ],
    "name:tha_x_preferred": [
      "ยูริ"
    ],
    "name:ukr_x_preferred": [
      "Юрі"
    ],
    "name:vie_x_preferred": [
      "Yuri"
    ],
    "name:zho_x_preferred": [
      "鱼日"
    ],
    "wof:name": "Yuri",
    "wof:placetype": "locality"
  },
  "geometry": {
    "coordinates": [
      101.986,
      30.7021
    ],
    "type": "Point"
  }
}