{
  "type": "Feature",
  "properties": {
    "gn:admin1_code": "24",
    "gn:asciiname": "Fengcun",
    "gn:cc2": "CN",
    "gn:country_code": "CN",
    "gn:dem": 1015,
    "gn:feature_class": "P",
    "gn:feature_code": "PPL",
    "gn:name": "Fengcun",
    "gn:population": 0,
    "gn:timezone": "Asia/Shanghai",
    "iso:country": "CN",
    "name:und_x_variant": [
      "Feng-ts’un",
      "Fengcun"
    ],
    "wof:name": "Fengcun",
    "wof:placetype": "locality"
  },
  "geometry": {
    "coordinates": [
      111.83333,
      36.68333
    ],
    "type": "Point"
  }
}