{
  "type": "Feature",
  "properties": {
    "gn:admin1_code": "24.0",
    "gn:asciiname": "Guancunling",
    "gn:country_code": "CN",
    "gn:dem": 736,
    "gn:feature_class": "P",
    "gn:feature_code": "PPL",
    "gn:name": "Guancunling",
    "gn:population": 0,
    "gn:timezone": "Asia/Shanghai",
    "iso:country": "CN",
    "name:und_x_variant": [
      "关村岭"
    ],
    "wof:name": "Guancunling",
    "wof:placetype": "locality"
  },
  "geometry": {
    "coordinates": [
      111.08144,
      35.43934
    ],
    "type": "Point"
  }
}