{
  "type": "Feature",
  "properties": {
    "gn:admin1_code": "10",
    "gn:asciiname": "Daguo",
    "gn:country_code": "CN",
    "gn:dem": 91,
    "gn:feature_class": "P",
    "gn:feature_code": "PPLA4",
    "gn:name": "Daguo",
    "gn:population": 0,
    "gn:timezone": "Asia/Shanghai",
    "iso:country": "CN",
    "name:fas_x_preferred": [
      "داگئو"
    ],
    "name:und_x_variant": [
      "大郭",
      "Daguo Zhen",
      "大郭镇"
    ],
    "name:zho_x_preferred": [
      "大郭街道"
    ],
    "wof:name": "Daguo",
    "wof:placetype": "locality"
  },
  "geometry": {
    "coordinates": [
      114.4103,
      38.07388
    ],
    "type": "Point"
  }
}