{
  "type": "Feature",
  "properties": {
    "gn:admin1_code": "4.0",
    "gn:asciiname": "Fanbu",
    "gn:country_code": "CN",
    "gn:dem": 16,
    "gn:feature_class": "P",
    "gn:feature_code": "PPL",
    "gn:name": "Fanbu",
    "gn:population": 0,
    "gn:timezone": "Asia/Shanghai",
    "iso:country": "CN",
    "name:zho_x_preferred": [
      "范埠"
    ],
    "wof:name": "Fanbu",
    "wof:placetype": "locality"
  },
  "geometry": {
    "coordinates": [
      118.817,
      34.5509
    ],
    "type": "Point"
  }
}