{
  "type": "Feature",
  "properties": {
    "gn:admin1_code": "16",
    "gn:asciiname": "Liujia",
    "gn:country_code": "CN",
    "gn:dem": 213,
    "gn:feature_class": "P",
    "gn:feature_code": "PPL",
    "gn:name": "Liujia",
    "gn:population": 0,
    "gn:timezone": "Asia/Shanghai",
    "iso:country": "CN",
    "name:ceb_x_preferred": [
      "Liujia"
    ],
    "name:deu_x_preferred": [
      "Liujia"
    ],
    "name:swe_x_preferred": [
      "Liujia"
    ],
    "name:und_x_variant": [
      "Liu-chia-hsü"
    ],
    "name:zho_x_preferred": [
      "刘家"
    ],
    "wof:name": "Liujia",
    "wof:placetype": "locality"
  },
  "geometry": {
    "coordinates": [
      107.534,
      22.965
    ],
    "type": "Point"
  }
}