{
  "type": "Feature",
  "properties": {
    "gn:admin1_code": "11.0",
    "gn:asciiname": "Misha",
    "gn:country_code": "CN",
    "gn:dem": 250,
    "gn:feature_class": "P",
    "gn:feature_code": "PPL",
    "gn:name": "Misha",
    "gn:population": 0,
    "gn:timezone": "Asia/Shanghai",
    "iso:country": "CN",
    "name:bel_x_preferred": [
      "Алімпійскі Мішка"
    ],
    "name:bul_x_preferred": [
      "Миша"
    ],
    "name:cat_x_preferred": [
      "Misha"
    ],
    "name:ces_x_preferred": [
      "Míša"
    ],
    "name:deu_x_preferred": [
      "Mischa"
    ],
    "name:ell_x_preferred": [
      "Μίσα"
    ],
    "name:eus_x_preferred": [
      "Misha"
    ],
    "name:fin_x_preferred": [
      "Miska-karhu"
    ],
    "name:fra_x_preferred": [
      "Misha"
    ],
    "name:heb_x_preferred": [
      "מישה"
    ],
    "name:hye_x_preferred": [
      "Օլիմպիական արջուկ"
    ],
    "name:kor_x_preferred": [
      "미샤"
    ],
    "name:nld_x_preferred": [
      "Misha"
    ],
    "name:pol_x_preferred": [
      "Misza"
    ],
    "name:por_x_preferred": [
      "Misha"
    ],
    "name:rus_x_preferred": [
      "Олимпийский Мишка"
    ],
    "name:sah_x_preferred": [
      "Миша"
    ],
    "name:spa_x_preferred": [
      "Misha"
    ],
    "name:swe_x_preferred": [
      "Misja"
    ],
    "name:tha_x_preferred": [
      "มีชา"
    ],
    "name:tur_x_preferred": [
      "Mişa"
    ],
    "name:ukr_x_preferred": [
      "Олімпійський Мішка"
    ],
    "name:zho_x_preferred": [
      "米沙"
    ],
    "name:zho_x_variant": [
      "米沙熊"
    ],
    "wof:name": "Misha",
    "wof:placetype": "locality"
  },
  "geometry": {
    "coordinates": [
      109.46826,
      27.71448
    ],
    "type": "Point"
  }
}