{
  "type": "Feature",
  "properties": {
    "gn:admin1_code": "7",
    "gn:asciiname": "Shuyang",
    "gn:country_code": "CN",
    "gn:dem": 240,
    "gn:feature_class": "P",
    "gn:feature_code": "PPL",
    "gn:name": "Shuyang",
    "gn:population": 0,
    "gn:timezone": "Asia/Shanghai",
    "iso:country": "CN",
    "name:ara_x_preferred": [
      "شويانغ"
    ],
    "name:ben_x_preferred": [
      "শুইয়াং"
    ],
    "name:deu_x_preferred": [
      "Shuyang"
    ],
    "name:ell_x_preferred": [
      "Σουιάνγκ"
    ],
    "name:eng_x_preferred": [
      "Shuyang"
    ],
    "name:fas_x_preferred": [
      "شویانگ"
    ],
    "name:fra_x_preferred": [
      "Shuyang"
    ],
    "name:heb_x_preferred": [
      "שויאנג"
    ],
    "name:hin_x_preferred": [
      "शुयांग"
    ],
    "name:hun_x_preferred": [
      "Shuyang"
    ],
    "name:ind_x_preferred": [
      "Shuyang"
    ],
    "name:ita_x_preferred": [
      "Shuyang"
    ],
    "name:jpn_x_preferred": [
      "ジュツ陽"
    ],
    "name:kor_x_preferred": [
      "슈양"
    ],
    "name:nld_x_preferred": [
      "Shuyang"
    ],
    "name:pol_x_preferred": [
      "Shuyang"
    ],
    "name:por_x_preferred": [
      "Shuyang"
    ],
    "name:rus_x_preferred": [
      "Шуян"
    ],
    "name:spa_x_preferred": [
      "Shuyang"
    ],
    "name:swe_x_preferred": [
      "Shuyang"
    ],
    "name:tur_x_preferred": [
      "Shuyang"
    ],
    "name:ukr_x_preferred": [
      "Шуян"
    ],
    "name:und_x_variant": [
      "枢洋",
      "Shuyang"
    ],
    "name:urd_x_preferred": [
      "شویانگ"
    ],
    "name:vie_x_preferred": [
      "Thuật Dương"
    ],
    "name:zho_cn_x_preferred": [
      "沭阳县"
    ],
    "name:zho_tw_x_preferred": [
      "沭陽"
    ],
    "wof:name": "Shuyang",
    "wof:placetype": "locality"
  },
  "geometry": {
    "coordinates": [
      119.67703,
      27.16427
    ],
    "type": "Point"
  }
}