{
  "type": "Feature",
  "properties": {
    "gn:admin1_code": "30",
    "gn:asciiname": "Luduan",
    "gn:country_code": "CN",
    "gn:dem": 33,
    "gn:feature_class": "P",
    "gn:feature_code": "PPL",
    "gn:name": "Luduan",
    "gn:population": 0,
    "gn:timezone": "Asia/Urumqi",
    "iso:country": "CN",
    "name:ara_x_preferred": [
      "لو دوان"
    ],
    "name:rus_x_preferred": [
      "Лудунь"
    ],
    "name:zho_x_preferred": [
      "禄段"
    ],
    "wof:name": "Luduan",
    "wof:placetype": "locality"
  },
  "geometry": {
    "coordinates": [
      110.97425,
      21.75368
    ],
    "type": "Point"
  }
}