{
  "type": "Feature",
  "properties": {
    "gn:admin1_code": "9.0",
    "gn:asciiname": "Tieli",
    "gn:country_code": "CN",
    "gn:dem": 128,
    "gn:feature_class": "P",
    "gn:feature_code": "PPL",
    "gn:name": "Tieli",
    "gn:population": 0,
    "gn:timezone": "Asia/Shanghai",
    "iso:country": "CN",
    "name:ara_x_preferred": [
      "تيلي"
    ],
    "name:bxr_x_preferred": [
      "Тели"
    ],
    "name:ceb_x_preferred": [
      "Tieli"
    ],
    "name:deu_x_preferred": [
      "Tieli"
    ],
    "name:fas_x_preferred": [
      "تیلی"
    ],
    "name:fra_x_preferred": [
      "Tieli"
    ],
    "name:heb_x_preferred": [
      "טיאלי"
    ],
    "name:hun_x_preferred": [
      "Tieli"
    ],
    "name:ita_x_preferred": [
      "Tieli"
    ],
    "name:jpn_x_preferred": [
      "鉄力市"
    ],
    "name:kik_x_preferred": [
      "Tieli"
    ],
    "name:kor_x_preferred": [
      "톄리시"
    ],
    "name:mlg_x_preferred": [
      "Tieli"
    ],
    "name:nor_x_preferred": [
      "Tieli"
    ],
    "name:pam_x_preferred": [
      "Tieli"
    ],
    "name:rus_x_preferred": [
      "Тели"
    ],
    "name:spa_x_preferred": [
      "Tieli"
    ],
    "name:swe_x_preferred": [
      "Tieli"
    ],
    "name:urd_x_preferred": [
      "تیئلی"
    ],
    "name:vie_x_preferred": [
      "Thiết Lực"
    ],
    "name:war_x_preferred": [
      "Tieli"
    ],
    "name:zho_x_preferred": [
      "铁李"
    ],
    "name:zho_x_variant": [
      "铁力市"
    ],
    "wof:name": "Tieli",
    "wof:placetype": "locality"
  },
  "geometry": {
    "coordinates": [
      113.84868,
      34.45012
    ],
    "type": "Point"
  }
}