{
  "type": "Feature",
  "properties": {
    "gn:admin1_code": "22.0",
    "gn:asciiname": "Beibadaohecun",
    "gn:country_code": "CN",
    "gn:dem": 428,
    "gn:feature_class": "P",
    "gn:feature_code": "PPL",
    "gn:name": "Beibadaohecun",
    "gn:population": 0,
    "gn:timezone": "Asia/Shanghai",
    "iso:country": "CN",
    "name:zho_x_preferred": [
      "北八道河村"
    ],
    "wof:name": "Beibadaohecun",
    "wof:placetype": "locality"
  },
  "geometry": {
    "coordinates": [
      116.6974,
      40.85619000000001
    ],
    "type": "Point"
  }
}