{
  "type": "Feature",
  "properties": {
    "gn:admin1_code": "2.0",
    "gn:asciiname": "Shuitou",
    "gn:country_code": "CN",
    "gn:dem": 574,
    "gn:feature_class": "P",
    "gn:feature_code": "PPL",
    "gn:name": "Shuitou",
    "gn:population": 0,
    "gn:timezone": "Asia/Shanghai",
    "iso:country": "CN",
    "name:zho_x_preferred": [
      "水头"
    ],
    "name:zho_x_variant": [
      "水头镇"
    ],
    "wof:name": "Shuitou",
    "wof:placetype": "locality"
  },
  "geometry": {
    "coordinates": [
      119.7164,
      28.57961
    ],
    "type": "Point"
  }
}