{
  "type": "Feature",
  "properties": {
    "gn:admin1_code": "2.0",
    "gn:asciiname": "Miaobian",
    "gn:country_code": "CN",
    "gn:dem": 279,
    "gn:feature_class": "P",
    "gn:feature_code": "PPL",
    "gn:name": "Miaobian",
    "gn:population": 0,
    "gn:timezone": "Asia/Shanghai",
    "iso:country": "CN",
    "name:zho_x_preferred": [
      "庙边"
    ],
    "wof:name": "Miaobian",
    "wof:placetype": "locality"
  },
  "geometry": {
    "coordinates": [
      118.87389,
      28.6259
    ],
    "type": "Point"
  }
}