{
  "type": "Feature",
  "properties": {
    "gn:admin1_code": "32.0",
    "gn:asciiname": "Huixian",
    "gn:country_code": "CN",
    "gn:dem": 473,
    "gn:feature_class": "P",
    "gn:feature_code": "PPL",
    "gn:name": "Huixian",
    "gn:population": 0,
    "gn:timezone": "Asia/Shanghai",
    "iso:country": "CN",
    "name:deu_x_preferred": [
      "Huixian"
    ],
    "name:fra_x_preferred": [
      "Huixian"
    ],
    "name:hak_x_preferred": [
      "Fî-yen"
    ],
    "name:ita_x_preferred": [
      "Huixian"
    ],
    "name:jpn_x_preferred": [
      "輝県市"
    ],
    "name:kik_x_preferred": [
      "Huixian"
    ],
    "name:kor_x_preferred": [
      "후이셴시"
    ],
    "name:mlg_x_preferred": [
      "Huixian"
    ],
    "name:nld_x_preferred": [
      "Huixian"
    ],
    "name:nor_x_preferred": [
      "Huixian"
    ],
    "name:pam_x_preferred": [
      "Huixian"
    ],
    "name:pol_x_preferred": [
      "Huixian"
    ],
    "name:rus_x_preferred": [
      "Хуэйсянь"
    ],
    "name:swe_x_preferred": [
      "Huixian"
    ],
    "name:vie_x_preferred": [
      "Huy Huyện"
    ],
    "name:war_x_preferred": [
      "Huixian"
    ],
    "name:zho_x_preferred": [
      "会贤"
    ],
    "name:zho_x_variant": [
      "辉县市"
    ],
    "wof:name": "Huixian",
    "wof:placetype": "locality"
  },
  "geometry": {
    "coordinates": [
      105.555,
      28.4949
    ],
    "type": "Point"
  }
}