{
  "type": "Feature",
  "properties": {
    "gn:admin1_code": "19.0",
    "gn:asciiname": "Xiaoweizi",
    "gn:country_code": "CN",
    "gn:dem": 216,
    "gn:feature_class": "P",
    "gn:feature_code": "PPL",
    "gn:name": "Xiaoweizi",
    "gn:population": 0,
    "gn:timezone": "Asia/Shanghai",
    "iso:country": "CN",
    "name:zho_x_preferred": [
      "小围子"
    ],
    "wof:name": "Xiaoweizi",
    "wof:placetype": "locality"
  },
  "geometry": {
    "coordinates": [
      125.52152,
      41.10262
    ],
    "type": "Point"
  }
}