{
  "type": "Feature",
  "properties": {
    "gn:admin1_code": "1.0",
    "gn:asciiname": "Baliyangcun",
    "gn:country_code": "CN",
    "gn:dem": 22,
    "gn:feature_class": "P",
    "gn:feature_code": "PPL",
    "gn:name": "Baliyangcun",
    "gn:population": 0,
    "gn:timezone": "Asia/Shanghai",
    "iso:country": "CN",
    "name:zho_x_preferred": [
      "八里杨村"
    ],
    "wof:name": "Baliyangcun",
    "wof:placetype": "locality"
  },
  "geometry": {
    "coordinates": [
      117.23838,
      32.59654
    ],
    "type": "Point"
  }
}