{
  "type": "Feature",
  "properties": {
    "gn:admin1_code": "1.0",
    "gn:asciiname": "Sanlian",
    "gn:country_code": "CN",
    "gn:dem": 66,
    "gn:feature_class": "P",
    "gn:feature_code": "PPL",
    "gn:name": "Sanlian",
    "gn:population": 0,
    "gn:timezone": "Asia/Shanghai",
    "iso:country": "CN",
    "name:zho_x_preferred": [
      "三联"
    ],
    "wof:name": "Sanlian",
    "wof:placetype": "locality"
  },
  "geometry": {
    "coordinates": [
      118.14595,
      30.47637000000001
    ],
    "type": "Point"
  }
}