{
  "type": "Feature",
  "properties": {
    "gn:admin1_code": "12.0",
    "gn:asciiname": "Huangpingshan",
    "gn:country_code": "CN",
    "gn:dem": 500,
    "gn:feature_class": "P",
    "gn:feature_code": "PPL",
    "gn:name": "Huangpingshan",
    "gn:population": 0,
    "gn:timezone": "Asia/Shanghai",
    "iso:country": "CN",
    "name:zho_x_preferred": [
      "Huangpingshan"
    ],
    "name:zho_x_variant": [
      "黄坪山"
    ],
    "wof:name": "Huangpingshan",
    "wof:placetype": "locality"
  },
  "geometry": {
    "coordinates": [
      114.96757,
      29.96338
    ],
    "type": "Point"
  }
}