{
  "type": "Feature",
  "properties": {
    "gn:admin1_code": "32.0",
    "gn:asciiname": "Tagu",
    "gn:country_code": "CN",
    "gn:dem": 561,
    "gn:feature_class": "P",
    "gn:feature_code": "PPL",
    "gn:name": "Tagu",
    "gn:population": 0,
    "gn:timezone": "Asia/Shanghai",
    "iso:country": "CN",
    "name:mya_x_preferred": [
      "တန်ခူးလ"
    ],
    "name:zho_x_preferred": [
      "挞谷"
    ],
    "wof:name": "Tagu",
    "wof:placetype": "locality"
  },
  "geometry": {
    "coordinates": [
      103.434,
      30.3508
    ],
    "type": "Point"
  }
}