{
  "type": "Feature",
  "properties": {
    "gn:admin1_code": "16",
    "gn:asciiname": "Jiangnan",
    "gn:country_code": "CN",
    "gn:dem": 236,
    "gn:feature_class": "P",
    "gn:feature_code": "PPL",
    "gn:name": "Jiangnan",
    "gn:population": 0,
    "gn:timezone": "Asia/Shanghai",
    "iso:country": "CN",
    "name:cat_x_preferred": [
      "Jiangnan"
    ],
    "name:ces_x_preferred": [
      "Ťiang-nan"
    ],
    "name:deu_x_preferred": [
      "Jiangnan"
    ],
    "name:epo_x_preferred": [
      "Jiangnano"
    ],
    "name:fra_x_preferred": [
      "Jiangnan"
    ],
    "name:hin_x_preferred": [
      "जियांगनान"
    ],
    "name:ind_x_preferred": [
      "Jiangnan"
    ],
    "name:ita_x_preferred": [
      "Jiangnan"
    ],
    "name:msa_x_preferred": [
      "Jiangnan"
    ],
    "name:nld_x_preferred": [
      "Jiangnan"
    ],
    "name:nor_x_preferred": [
      "Jiangnan"
    ],
    "name:por_x_preferred": [
      "Jiangnan"
    ],
    "name:rus_x_preferred": [
      "Цзяннань"
    ],
    "name:spa_x_preferred": [
      "Jiangnan"
    ],
    "name:tha_x_preferred": [
      "เจียงหนาน"
    ],
    "name:vie_x_preferred": [
      "Giang Nam"
    ],
    "name:zho_x_preferred": [
      "江南"
    ],
    "wof:name": "Jiangnan",
    "wof:placetype": "locality"
  },
  "geometry": {
    "coordinates": [
      110.706,
      25.7629
    ],
    "type": "Point"
  }
}