{
  "type": "Feature",
  "properties": {
    "gn:admin1_code": "26.0",
    "gn:asciiname": "Xiaoxigounao",
    "gn:country_code": "CN",
    "gn:dem": 1371,
    "gn:feature_class": "P",
    "gn:feature_code": "PPL",
    "gn:name": "Xiaoxigounao",
    "gn:population": 0,
    "gn:timezone": "Asia/Shanghai",
    "iso:country": "CN",
    "name:zho_x_preferred": [
      "小西沟脑"
    ],
    "wof:name": "Xiaoxigounao",
    "wof:placetype": "locality"
  },
  "geometry": {
    "coordinates": [
      109.31975,
      33.47158
    ],
    "type": "Point"
  }
}