{
  "type": "Feature",
  "properties": {
    "gn:admin1_code": "24.0",
    "gn:asciiname": "Zhaojiaqu",
    "gn:country_code": "CN",
    "gn:dem": 588,
    "gn:feature_class": "P",
    "gn:feature_code": "PPL",
    "gn:name": "Zhaojiaqu",
    "gn:population": 0,
    "gn:timezone": "Asia/Shanghai",
    "iso:country": "CN",
    "name:zho_x_preferred": [
      "赵家渠"
    ],
    "wof:name": "Zhaojiaqu",
    "wof:placetype": "locality"
  },
  "geometry": {
    "coordinates": [
      110.40744,
      36.82798
    ],
    "type": "Point"
  }
}