{
  "type": "Feature",
  "properties": {
    "gn:admin1_code": "32.0",
    "gn:asciiname": "Puzi",
    "gn:country_code": "CN",
    "gn:dem": 686,
    "gn:feature_class": "P",
    "gn:feature_code": "PPL",
    "gn:name": "Puzi",
    "gn:population": 0,
    "gn:timezone": "Asia/Shanghai",
    "iso:country": "CN",
    "name:ben_x_preferred": [
      "পুজি"
    ],
    "name:deu_x_preferred": [
      "Puzi"
    ],
    "name:ell_x_preferred": [
      "Πούζι"
    ],
    "name:fas_x_preferred": [
      "پوزی"
    ],
    "name:hak_x_preferred": [
      "Phú-chṳ́-sṳ"
    ],
    "name:heb_x_preferred": [
      "פוזי"
    ],
    "name:hin_x_preferred": [
      "पूज़ी"
    ],
    "name:hun_x_preferred": [
      "Puzi"
    ],
    "name:ind_x_preferred": [
      "Puzi"
    ],
    "name:ita_x_preferred": [
      "Puzi"
    ],
    "name:jpn_x_preferred": [
      "朴子市"
    ],
    "name:kor_x_preferred": [
      "푸쯔시"
    ],
    "name:lit_x_preferred": [
      "Pudzi"
    ],
    "name:nld_x_preferred": [
      "Puzi"
    ],
    "name:pol_x_preferred": [
      "Pozi"
    ],
    "name:rus_x_preferred": [
      "Пуцзы"
    ],
    "name:spa_x_preferred": [
      "Puzi"
    ],
    "name:swe_x_preferred": [
      "Puzi"
    ],
    "name:ukr_x_preferred": [
      "Пузі"
    ],
    "name:und_x_variant": [
      "普子"
    ],
    "name:urd_x_preferred": [
      "پوزی"
    ],
    "name:vie_x_preferred": [
      "Phác Tử"
    ],
    "name:zho_x_preferred": [
      "朴子市"
    ],
    "wof:name": "Puzi",
    "wof:placetype": "locality"
  },
  "geometry": {
    "coordinates": [
      106.01153,
      32.28665
    ],
    "type": "Point"
  }
}