{
  "type": "Feature",
  "properties": {
    "gn:admin1_code": "26.0",
    "gn:asciiname": "Mu'ermao",
    "gn:country_code": "CN",
    "gn:dem": 1146,
    "gn:feature_class": "P",
    "gn:feature_code": "PPL",
    "gn:name": "Mu’ermao",
    "gn:population": 0,
    "gn:timezone": "Asia/Shanghai",
    "iso:country": "CN",
    "name:und_x_variant": [
      "Mu’ermao"
    ],
    "name:zho_x_preferred": [
      "木耳峁"
    ],
    "wof:name": "Mu'ermao",
    "wof:placetype": "locality"
  },
  "geometry": {
    "coordinates": [
      109.21215,
      37.85785
    ],
    "type": "Point"
  }
}