{
  "type": "Feature",
  "properties": {
    "gn:admin1_code": "1.0",
    "gn:asciiname": "Heshan",
    "gn:country_code": "CN",
    "gn:dem": 34,
    "gn:feature_class": "P",
    "gn:feature_code": "PPL",
    "gn:name": "Heshan",
    "gn:population": 0,
    "gn:timezone": "Asia/Shanghai",
    "iso:country": "CN",
    "name:ceb_x_preferred": [
      "Heshan"
    ],
    "name:deu_x_preferred": [
      "Heshan"
    ],
    "name:fra_x_preferred": [
      "Heshan"
    ],
    "name:kor_x_preferred": [
      "허산시"
    ],
    "name:nor_x_preferred": [
      "Heshan"
    ],
    "name:rus_x_preferred": [
      "Хэшань"
    ],
    "name:swe_x_preferred": [
      "Heshan"
    ],
    "name:und_x_variant": [
      "合山"
    ],
    "wof:name": "Heshan",
    "wof:placetype": "locality"
  },
  "geometry": {
    "coordinates": [
      118.61667,
      30.85
    ],
    "type": "Point"
  }
}