{
  "type": "Feature",
  "properties": {
    "gn:admin1_code": "26.0",
    "gn:asciiname": "Majiashan",
    "gn:country_code": "CN",
    "gn:dem": 1549,
    "gn:feature_class": "P",
    "gn:feature_code": "PPL",
    "gn:name": "Majiashan",
    "gn:population": 0,
    "gn:timezone": "Asia/Shanghai",
    "iso:country": "CN",
    "name:zho_x_preferred": [
      "马家山"
    ],
    "wof:name": "Majiashan",
    "wof:placetype": "locality"
  },
  "geometry": {
    "coordinates": [
      108.88853,
      36.80931
    ],
    "type": "Point"
  }
}