{
  "type": "Feature",
  "properties": {
    "gn:admin1_code": "26.0",
    "gn:asciiname": "Lujiagou",
    "gn:country_code": "CN",
    "gn:dem": 1736,
    "gn:feature_class": "P",
    "gn:feature_code": "PPL",
    "gn:name": "Lujiagou",
    "gn:population": 0,
    "gn:timezone": "Asia/Shanghai",
    "iso:country": "CN",
    "name:und_x_variant": [
      "芦家沟"
    ],
    "wof:name": "Lujiagou",
    "wof:placetype": "locality"
  },
  "geometry": {
    "coordinates": [
      106.60941,
      34.05019
    ],
    "type": "Point"
  }
}