{
  "type": "Feature",
  "properties": {
    "gn:admin1_code": "7.0",
    "gn:asciiname": "Jinshi",
    "gn:country_code": "CN",
    "gn:dem": 23,
    "gn:feature_class": "P",
    "gn:feature_code": "PPL",
    "gn:name": "Jinshi",
    "gn:population": 0,
    "gn:timezone": "Asia/Shanghai",
    "iso:country": "CN",
    "name:fas_x_preferred": [
      "جینشی"
    ],
    "name:heb_x_preferred": [
      "ג'ינשי"
    ],
    "name:hun_x_preferred": [
      "Jinshi"
    ],
    "name:kor_x_preferred": [
      "진사"
    ],
    "name:mlg_x_preferred": [
      "Jinshi"
    ],
    "name:nld_x_preferred": [
      "Jinshi"
    ],
    "name:zho_x_preferred": [
      "金石"
    ],
    "wof:name": "Jinshi",
    "wof:placetype": "locality"
  },
  "geometry": {
    "coordinates": [
      117.43397,
      23.68549
    ],
    "type": "Point"
  }
}