{
  "type": "Feature",
  "properties": {
    "gn:admin1_code": "15.0",
    "gn:asciiname": "Toufen",
    "gn:country_code": "CN",
    "gn:dem": 1180,
    "gn:feature_class": "P",
    "gn:feature_code": "PPL",
    "gn:name": "Toufen",
    "gn:population": 0,
    "gn:timezone": "Asia/Shanghai",
    "iso:country": "CN",
    "name:deu_x_preferred": [
      "Toufen"
    ],
    "name:fas_x_preferred": [
      "توفن"
    ],
    "name:fra_x_preferred": [
      "Toufen"
    ],
    "name:hak_x_preferred": [
      "Thèu-fun-sṳ"
    ],
    "name:ita_x_preferred": [
      "Toufen"
    ],
    "name:jpn_x_preferred": [
      "頭フン市"
    ],
    "name:kor_x_preferred": [
      "터우펀시"
    ],
    "name:pol_x_preferred": [
      "Toufen"
    ],
    "name:rus_x_preferred": [
      "Тоуфэнь"
    ],
    "name:szl_x_preferred": [
      "Toufen"
    ],
    "name:vie_x_preferred": [
      "Đầu Phần"
    ],
    "name:zho_x_preferred": [
      "头分"
    ],
    "name:zho_x_variant": [
      "頭份市"
    ],
    "wof:name": "Toufen",
    "wof:placetype": "locality"
  },
  "geometry": {
    "coordinates": [
      99.5259,
      40.2939
    ],
    "type": "Point"
  }
}