{
  "type": "Feature",
  "properties": {
    "gn:admin1_code": "19",
    "gn:asciiname": "Yangshufang",
    "gn:country_code": "CN",
    "gn:dem": 206,
    "gn:feature_class": "P",
    "gn:feature_code": "PPLA4",
    "gn:name": "Yangshufang",
    "gn:population": 0,
    "gn:timezone": "Asia/Shanghai",
    "iso:country": "CN",
    "name:und_x_variant": [
      "杨树房",
      "Xiaoshipeng Xiang",
      "小石棚乡"
    ],
    "wof:name": "Yangshufang",
    "wof:placetype": "locality"
  },
  "geometry": {
    "coordinates": [
      122.43281,
      40.24254000000001
    ],
    "type": "Point"
  }
}