{
  "type": "Feature",
  "properties": {
    "gn:admin1_code": "32.0",
    "gn:asciiname": "Shama",
    "gn:country_code": "CN",
    "gn:dem": 4338,
    "gn:feature_class": "P",
    "gn:feature_code": "PPL",
    "gn:name": "Shama",
    "gn:population": 0,
    "gn:timezone": "Asia/Shanghai",
    "iso:country": "CN",
    "name:ara_x_preferred": [
      "شامة"
    ],
    "name:ben_x_preferred": [
      "শামা"
    ],
    "name:ceb_x_preferred": [
      "Shama"
    ],
    "name:deu_x_preferred": [
      "Shama"
    ],
    "name:ell_x_preferred": [
      "Σάμα"
    ],
    "name:fas_x_preferred": [
      "شاما"
    ],
    "name:fra_x_preferred": [
      "Shama"
    ],
    "name:heb_x_preferred": [
      "שאמה"
    ],
    "name:hin_x_preferred": [
      "शमा"
    ],
    "name:hun_x_preferred": [
      "Shama"
    ],
    "name:ind_x_preferred": [
      "Shama"
    ],
    "name:ita_x_preferred": [
      "Shama"
    ],
    "name:jpn_x_preferred": [
      "シャマ川"
    ],
    "name:kor_x_preferred": [
      "샤마"
    ],
    "name:nld_x_preferred": [
      "Shama"
    ],
    "name:pol_x_preferred": [
      "Shama"
    ],
    "name:por_x_preferred": [
      "Shama"
    ],
    "name:spa_x_preferred": [
      "Shama"
    ],
    "name:swe_x_preferred": [
      "Shama"
    ],
    "name:tur_x_preferred": [
      "Shama"
    ],
    "name:ukr_x_preferred": [
      "Шама"
    ],
    "name:urd_x_preferred": [
      "شاما"
    ],
    "name:vie_x_preferred": [
      "Sông Shama"
    ],
    "name:zho_cn_x_preferred": [
      "莎玛河"
    ],
    "name:zho_tw_x_preferred": [
      "沙瑪河"
    ],
    "name:zho_x_preferred": [
      "沙马"
    ],
    "wof:name": "Shama",
    "wof:placetype": "locality"
  },
  "geometry": {
    "coordinates": [
      98.0173,
      32.9391
    ],
    "type": "Point"
  }
}