{
  "type": "Feature",
  "properties": {
    "gn:admin1_code": "12.0",
    "gn:asciiname": "Maojialong",
    "gn:country_code": "CN",
    "gn:dem": 198,
    "gn:feature_class": "P",
    "gn:feature_code": "PPL",
    "gn:name": "Maojialong",
    "gn:population": 0,
    "gn:timezone": "Asia/Shanghai",
    "iso:country": "CN",
    "name:zho_x_preferred": [
      "毛家垄"
    ],
    "wof:name": "Maojialong",
    "wof:placetype": "locality"
  },
  "geometry": {
    "coordinates": [
      113.38118,
      31.49628
    ],
    "type": "Point"
  }
}