{
  "type": "Feature",
  "properties": {
    "gn:admin1_code": "18.0",
    "gn:asciiname": "Potouyang",
    "gn:country_code": "CN",
    "gn:dem": 351,
    "gn:feature_class": "P",
    "gn:feature_code": "PPL",
    "gn:name": "Potouyang",
    "gn:population": 0,
    "gn:timezone": "Asia/Shanghai",
    "iso:country": "CN",
    "name:zho_x_preferred": [
      "坡头阳"
    ],
    "wof:name": "Potouyang",
    "wof:placetype": "locality"
  },
  "geometry": {
    "coordinates": [
      109.445,
      27.1014
    ],
    "type": "Point"
  }
}