{
  "type": "Feature",
  "properties": {
    "gn:admin1_code": "10",
    "gn:asciiname": "Yanjiagou",
    "gn:country_code": "CN",
    "gn:dem": 663,
    "gn:feature_class": "P",
    "gn:feature_code": "PPL",
    "gn:name": "Yanjiagou",
    "gn:population": 0,
    "gn:timezone": "Asia/Shanghai",
    "iso:country": "CN",
    "name:zho_x_preferred": [
      "闫家沟"
    ],
    "wof:name": "Yanjiagou",
    "wof:placetype": "locality"
  },
  "geometry": {
    "coordinates": [
      118.99307,
      41.11175
    ],
    "type": "Point"
  }
}