{
  "type": "Feature",
  "properties": {
    "gn:admin1_code": "7",
    "gn:asciiname": "Yuanli",
    "gn:country_code": "CN",
    "gn:dem": 578,
    "gn:feature_class": "P",
    "gn:feature_code": "PPL",
    "gn:name": "Yuanli",
    "gn:population": 0,
    "gn:timezone": "Asia/Shanghai",
    "iso:country": "CN",
    "name:fra_x_preferred": [
      "Yuanli"
    ],
    "name:hak_x_preferred": [
      "Yen-lî-chṳ́n"
    ],
    "name:ita_x_preferred": [
      "Yuanli"
    ],
    "name:jpn_x_preferred": [
      "苑裡鎮"
    ],
    "name:kor_x_preferred": [
      "위안리진"
    ],
    "name:vie_x_preferred": [
      "Uyển Lý"
    ],
    "name:zho_x_preferred": [
      "院里"
    ],
    "name:zho_x_variant": [
      "苑裡鎮"
    ],
    "wof:name": "Yuanli",
    "wof:placetype": "locality"
  },
  "geometry": {
    "coordinates": [
      118.80104,
      25.66496
    ],
    "type": "Point"
  }
}