{
  "type": "Feature",
  "properties": {
    "gn:admin1_code": "26.0",
    "gn:asciiname": "Lianhuataicun",
    "gn:country_code": "CN",
    "gn:dem": 539,
    "gn:feature_class": "P",
    "gn:feature_code": "PPL",
    "gn:name": "Lianhuataicun",
    "gn:population": 0,
    "gn:timezone": "Asia/Shanghai",
    "iso:country": "CN",
    "name:zho_x_preferred": [
      "莲花台村"
    ],
    "wof:name": "Lianhuataicun",
    "wof:placetype": "locality"
  },
  "geometry": {
    "coordinates": [
      109.14907,
      32.34663
    ],
    "type": "Point"
  }
}