{
  "type": "Feature",
  "properties": {
    "gn:admin1_code": "32",
    "gn:asciiname": "Enyang",
    "gn:country_code": "CN",
    "gn:dem": 367,
    "gn:feature_class": "P",
    "gn:feature_code": "PPL",
    "gn:name": "Enyang",
    "gn:population": 0,
    "gn:timezone": "Asia/Shanghai",
    "iso:country": "CN",
    "name:deu_x_preferred": [
      "Enyang"
    ],
    "name:ell_x_preferred": [
      "Επαρχία Ενγιάνγκ"
    ],
    "name:jpn_x_preferred": [
      "恩陽区"
    ],
    "name:kor_x_preferred": [
      "언양구"
    ],
    "name:rus_x_preferred": [
      "Эньян"
    ],
    "name:swe_x_preferred": [
      "Enyang"
    ],
    "name:und_x_variant": [
      "En-yang-ho",
      "Enyangzhen"
    ],
    "name:urd_x_preferred": [
      "عنیانگ ضلع"
    ],
    "name:vie_x_preferred": [
      "Ân Dương"
    ],
    "name:zho_x_preferred": [
      "En’yankhe"
    ],
    "name:zho_x_variant": [
      "恩阳",
      "恩阳区"
    ],
    "wof:name": "Enyang",
    "wof:placetype": "locality"
  },
  "geometry": {
    "coordinates": [
      106.62707,
      31.79397
    ],
    "type": "Point"
  }
}