{
  "type": "Feature",
  "properties": {
    "gn:admin1_code": "19.0",
    "gn:asciiname": "Tuanjiedui",
    "gn:country_code": "CN",
    "gn:dem": 2,
    "gn:feature_class": "P",
    "gn:feature_code": "PPLF",
    "gn:name": "Tuanjiedui",
    "gn:population": 0,
    "gn:timezone": "Asia/Shanghai",
    "iso:country": "CN",
    "name:zho_x_preferred": [
      "团结队"
    ],
    "wof:name": "Tuanjiedui",
    "wof:placetype": "locality"
  },
  "geometry": {
    "coordinates": [
      121.731,
      41.2814
    ],
    "type": "Point"
  }
}