{
  "type": "Feature",
  "properties": {
    "gn:admin1_code": "26.0",
    "gn:asciiname": "Zhujiawan",
    "gn:country_code": "CN",
    "gn:dem": 1129,
    "gn:feature_class": "P",
    "gn:feature_code": "PPL",
    "gn:name": "Zhujiawan",
    "gn:population": 0,
    "gn:timezone": "Asia/Shanghai",
    "iso:country": "CN",
    "name:zho_x_preferred": [
      "朱家湾"
    ],
    "wof:name": "Zhujiawan",
    "wof:placetype": "locality"
  },
  "geometry": {
    "coordinates": [
      109.77572,
      33.6959
    ],
    "type": "Point"
  }
}