{
  "type": "Feature",
  "properties": {
    "gn:admin1_code": "14.0",
    "gn:asciiname": "Qunub",
    "gn:country_code": "CN",
    "gn:dem": 3985,
    "gn:feature_class": "P",
    "gn:feature_code": "PPLF",
    "gn:name": "Qunub",
    "gn:population": 0,
    "gn:timezone": "Asia/Urumqi",
    "iso:country": "CN",
    "name:bod_x_preferred": [
      "Qunub"
    ],
    "name:und_x_variant": [
      "Qunu Xiang"
    ],
    "name:zho_x_preferred": [
      "Qunu"
    ],
    "name:zho_x_variant": [
      "曲奴",
      "Angga",
      "昂嘎",
      "曲奴乡"
    ],
    "wof:name": "Qunub",
    "wof:placetype": "locality"
  },
  "geometry": {
    "coordinates": [
      89.19639000000002,
      29.06291
    ],
    "type": "Point"
  }
}