{
  "type": "Feature",
  "properties": {
    "gn:admin1_code": "10",
    "gn:asciiname": "Leting",
    "gn:cc2": "CN",
    "gn:country_code": "CN",
    "gn:dem": 11,
    "gn:feature_class": "P",
    "gn:feature_code": "PPL",
    "gn:name": "Leting",
    "gn:population": 0,
    "gn:timezone": "Asia/Shanghai",
    "iso:country": "CN",
    "name:deu_x_preferred": [
      "Laoting"
    ],
    "name:fas_x_preferred": [
      "شهرستان لاوتینگ"
    ],
    "name:jpn_x_preferred": [
      "楽亭県"
    ],
    "name:kor_x_preferred": [
      "러딩현"
    ],
    "name:nor_x_preferred": [
      "Leting"
    ],
    "name:rus_x_preferred": [
      "Лаотин"
    ],
    "name:swe_x_preferred": [
      "Laoting"
    ],
    "name:und_x_variant": [
      "Lo-t’ing-hsien",
      "Lao-t’ing",
      "Lo-t’ing",
      "Lo-t’ing-ch’eng-kuan"
    ],
    "name:urd_x_preferred": [
      "لاوٹینگ کاؤنٹی"
    ],
    "name:vie_x_preferred": [
      "Lạc Đình"
    ],
    "name:zho_x_preferred": [
      "乐亭县"
    ],
    "wof:name": "Leting",
    "wof:placetype": "locality"
  },
  "geometry": {
    "coordinates": [
      118.93333,
      39.43333
    ],
    "type": "Point"
  }
}