{
  "type": "Feature",
  "properties": {
    "gn:admin1_code": "3",
    "gn:asciiname": "Waling",
    "gn:country_code": "CN",
    "gn:dem": 151,
    "gn:feature_class": "P",
    "gn:feature_code": "PPL",
    "gn:name": "Waling",
    "gn:population": 0,
    "gn:timezone": "Asia/Shanghai",
    "iso:country": "CN",
    "name:deu_x_preferred": [
      "Waling"
    ],
    "name:hin_x_preferred": [
      "वालिङ नगरपालिका"
    ],
    "name:mai_x_preferred": [
      "वालिङ नगरपालिका"
    ],
    "name:msa_x_preferred": [
      "Waling"
    ],
    "name:nep_x_preferred": [
      "वालिङ नगरपालिका"
    ],
    "name:new_x_preferred": [
      "वालिङ नगरपालिका"
    ],
    "name:pol_x_preferred": [
      "Waling"
    ],
    "name:urd_x_preferred": [
      "والنگ"
    ],
    "name:zho_x_preferred": [
      "瓦岭"
    ],
    "name:zho_x_variant": [
      "沃林格"
    ],
    "wof:name": "Waling",
    "wof:placetype": "locality"
  },
  "geometry": {
    "coordinates": [
      114.68473,
      25.63031
    ],
    "type": "Point"
  }
}