{
  "type": "Feature",
  "properties": {
    "gn:admin1_code": "16.0",
    "gn:asciiname": "Jiangmen",
    "gn:country_code": "CN",
    "gn:dem": 93,
    "gn:feature_class": "P",
    "gn:feature_code": "PPL",
    "gn:name": "Jiangmen",
    "gn:population": 0,
    "gn:timezone": "Asia/Shanghai",
    "iso:country": "CN",
    "name:afr_x_preferred": [
      "Jiangmen"
    ],
    "name:ara_x_preferred": [
      "جيانغمن"
    ],
    "name:bre_x_preferred": [
      "Jiangmen"
    ],
    "name:bul_x_preferred": [
      "Дзянмън"
    ],
    "name:cdo_x_preferred": [
      "Gĕ̤ng-muòng"
    ],
    "name:ceb_x_preferred": [
      "Jiangmen"
    ],
    "name:ces_x_preferred": [
      "Ťiang-men"
    ],
    "name:cym_x_preferred": [
      "Jiangmen"
    ],
    "name:dan_x_preferred": [
      "Jiangmen"
    ],
    "name:deu_x_preferred": [
      "Jiangmen"
    ],
    "name:epo_x_preferred": [
      "Ĝjanmen"
    ],
    "name:eus_x_preferred": [
      "Jiangmen"
    ],
    "name:fas_x_preferred": [
      "ژیانگمن"
    ],
    "name:fin_x_preferred": [
      "Jiangmen"
    ],
    "name:fra_x_preferred": [
      "Jiangmen"
    ],
    "name:hak_x_preferred": [
      "Kông-mùn-sṳ"
    ],
    "name:heb_x_preferred": [
      "ג'יאנגמן"
    ],
    "name:hun_x_preferred": [
      "Jiangmen"
    ],
    "name:ind_x_preferred": [
      "Jiangmen"
    ],
    "name:ita_x_preferred": [
      "Jiangmen"
    ],
    "name:jpn_x_preferred": [
      "江門市"
    ],
    "name:kik_x_preferred": [
      "Jiangmen"
    ],
    "name:kor_x_preferred": [
      "장먼시"
    ],
    "name:lit_x_preferred": [
      "Dziangmenas"
    ],
    "name:mlg_x_preferred": [
      "Jiangmen"
    ],
    "name:nld_x_preferred": [
      "Jiangmen"
    ],
    "name:nno_x_preferred": [
      "Jiangmen"
    ],
    "name:nor_x_preferred": [
      "Jiangmen"
    ],
    "name:pam_x_preferred": [
      "Jiangmen"
    ],
    "name:pnb_x_preferred": [
      "جیانگمن"
    ],
    "name:pol_x_preferred": [
      "Jiangmen"
    ],
    "name:por_x_preferred": [
      "Jiangmen"
    ],
    "name:rus_x_preferred": [
      "Цзянмынь"
    ],
    "name:spa_x_preferred": [
      "Jiangmen"
    ],
    "name:srp_x_preferred": [
      "Ђангмен"
    ],
    "name:swa_x_preferred": [
      "Jiangmen"
    ],
    "name:swe_x_preferred": [
      "Jiangmen"
    ],
    "name:tgl_x_preferred": [
      "Jiangmen"
    ],
    "name:tur_x_preferred": [
      "Jiangmen"
    ],
    "name:urd_x_preferred": [
      "جیانگمین"
    ],
    "name:vie_x_preferred": [
      "Giang Môn"
    ],
    "name:war_x_preferred": [
      "Jiangmen"
    ],
    "name:wuu_x_preferred": [
      "江门市"
    ],
    "name:zho_x_preferred": [
      "江门"
    ],
    "name:zho_x_variant": [
      "江门市"
    ],
    "wof:name": "Jiangmen",
    "wof:placetype": "locality"
  },
  "geometry": {
    "coordinates": [
      109.304,
      24.4001
    ],
    "type": "Point"
  }
}