{
  "type": "Feature",
  "properties": {
    "gn:admin1_code": "32.0",
    "gn:asciiname": "Chunlinshan",
    "gn:country_code": "CN",
    "gn:dem": 1347,
    "gn:feature_class": "P",
    "gn:feature_code": "PPL",
    "gn:name": "Chunlinshan",
    "gn:population": 0,
    "gn:timezone": "Asia/Shanghai",
    "iso:country": "CN",
    "name:zho_x_preferred": [
      "春林山"
    ],
    "wof:name": "Chunlinshan",
    "wof:placetype": "locality"
  },
  "geometry": {
    "coordinates": [
      104.23775,
      32.00615
    ],
    "type": "Point"
  }
}