{
  "type": "Feature",
  "properties": {
    "gn:admin1_code": "10.0",
    "gn:asciiname": "Ligezhuang",
    "gn:country_code": "CN",
    "gn:dem": 97,
    "gn:feature_class": "P",
    "gn:feature_code": "PPL",
    "gn:name": "Ligezhuang",
    "gn:population": 0,
    "gn:timezone": "Asia/Shanghai",
    "iso:country": "CN",
    "name:zho_x_preferred": [
      "李各庄"
    ],
    "wof:name": "Ligezhuang",
    "wof:placetype": "locality"
  },
  "geometry": {
    "coordinates": [
      119.03151,
      40.05522
    ],
    "type": "Point"
  }
}