{
  "type": "Feature",
  "properties": {
    "gn:admin1_code": "21",
    "gn:asciiname": "Nanqiao",
    "gn:country_code": "CN",
    "gn:dem": 1192,
    "gn:feature_class": "P",
    "gn:feature_code": "PPL",
    "gn:name": "Nanqiao",
    "gn:population": 0,
    "gn:timezone": "Asia/Shanghai",
    "iso:country": "CN",
    "wof:name": "Nanqiao",
    "wof:placetype": "locality"
  },
  "geometry": {
    "coordinates": [
      105.76667,
      37.48333
    ],
    "type": "Point"
  }
}