{
  "type": "Feature",
  "properties": {
    "gn:admin1_code": "18",
    "gn:asciiname": "Suona",
    "gn:country_code": "CN",
    "gn:dem": 1060,
    "gn:feature_class": "P",
    "gn:feature_code": "PPL",
    "gn:name": "Suona",
    "gn:population": 0,
    "gn:timezone": "Asia/Shanghai",
    "iso:country": "CN",
    "name:bod_x_preferred": [
      "རྒྱ་གླིང་།"
    ],
    "name:cat_x_preferred": [
      "Suona"
    ],
    "name:cdo_x_preferred": [
      "Dĭ-dă"
    ],
    "name:deu_x_preferred": [
      "Suona"
    ],
    "name:epo_x_preferred": [
      "Suona"
    ],
    "name:fra_x_preferred": [
      "Suona"
    ],
    "name:ita_x_preferred": [
      "Suona"
    ],
    "name:jpn_x_preferred": [
      "チャルメラ"
    ],
    "name:nor_x_preferred": [
      "Suona"
    ],
    "name:que_x_preferred": [
      "Suona"
    ],
    "name:rus_x_preferred": [
      "Сона"
    ],
    "name:spa_x_preferred": [
      "Suona"
    ],
    "name:swe_x_preferred": [
      "Suona"
    ],
    "name:ukr_x_preferred": [
      "Сона"
    ],
    "name:zho_x_preferred": [
      "所纳"
    ],
    "wof:name": "Suona",
    "wof:placetype": "locality"
  },
  "geometry": {
    "coordinates": [
      106.611,
      25.8465
    ],
    "type": "Point"
  }
}