{
  "type": "Feature",
  "properties": {
    "gn:admin1_code": "11.0",
    "gn:asciiname": "Huangmu'ao",
    "gn:country_code": "CN",
    "gn:dem": 791,
    "gn:feature_class": "P",
    "gn:feature_code": "PPL",
    "gn:name": "Huangmu’ao",
    "gn:population": 0,
    "gn:timezone": "Asia/Shanghai",
    "iso:country": "CN",
    "name:und_x_variant": [
      "Huangmu’ao"
    ],
    "name:zho_x_preferred": [
      "黄木坳"
    ],
    "wof:name": "Huangmu'ao",
    "wof:placetype": "locality"
  },
  "geometry": {
    "coordinates": [
      112.3996,
      25.19051
    ],
    "type": "Point"
  }
}