{
  "type": "Feature",
  "properties": {
    "gn:admin1_code": "10.0",
    "gn:asciiname": "Hejiazhai",
    "gn:country_code": "CN",
    "gn:dem": 1218,
    "gn:feature_class": "P",
    "gn:feature_code": "PPL",
    "gn:name": "Hejiazhai",
    "gn:population": 0,
    "gn:timezone": "Asia/Shanghai",
    "iso:country": "CN",
    "name:zho_x_preferred": [
      "贺家砦"
    ],
    "wof:name": "Hejiazhai",
    "wof:placetype": "locality"
  },
  "geometry": {
    "coordinates": [
      114.48605,
      40.06608
    ],
    "type": "Point"
  }
}