{
  "type": "Feature",
  "properties": {
    "gn:admin1_code": "10",
    "gn:asciiname": "Moding",
    "gn:country_code": "CN",
    "gn:dem": 64,
    "gn:feature_class": "P",
    "gn:feature_code": "PPL",
    "gn:name": "Moding",
    "gn:population": 0,
    "gn:timezone": "Asia/Shanghai",
    "iso:country": "CN",
    "name:zho_x_preferred": [
      "抹町"
    ],
    "wof:name": "Moding",
    "wof:placetype": "locality"
  },
  "geometry": {
    "coordinates": [
      114.757,
      36.328
    ],
    "type": "Point"
  }
}