{
  "type": "Feature",
  "properties": {
    "gn:admin1_code": "26.0",
    "gn:asciiname": "Wangzhuang",
    "gn:country_code": "CN",
    "gn:dem": 1593,
    "gn:feature_class": "P",
    "gn:feature_code": "PPL",
    "gn:name": "Wangzhuang",
    "gn:population": 0,
    "gn:timezone": "Asia/Shanghai",
    "iso:country": "CN",
    "name:zho_x_preferred": [
      "王庄"
    ],
    "wof:name": "Wangzhuang",
    "wof:placetype": "locality"
  },
  "geometry": {
    "coordinates": [
      108.11472,
      37.12008
    ],
    "type": "Point"
  }
}