{
  "type": "Feature",
  "properties": {
    "gn:admin1_code": "16",
    "gn:asciiname": "Jiangyou",
    "gn:country_code": "CN",
    "gn:dem": 119,
    "gn:feature_class": "P",
    "gn:feature_code": "PPL",
    "gn:name": "Jiangyou",
    "gn:population": 0,
    "gn:timezone": "Asia/Shanghai",
    "iso:country": "CN",
    "name:ara_x_preferred": [
      "جيانغيو"
    ],
    "name:deu_x_preferred": [
      "Jiangyou"
    ],
    "name:epo_x_preferred": [
      "Jiangyou"
    ],
    "name:fas_x_preferred": [
      "جیانگیو"
    ],
    "name:fra_x_preferred": [
      "Jiangyou"
    ],
    "name:ita_x_preferred": [
      "Jiangyou"
    ],
    "name:jpn_x_preferred": [
      "江油市"
    ],
    "name:kik_x_preferred": [
      "Jiangyou"
    ],
    "name:kor_x_preferred": [
      "장유시"
    ],
    "name:mlg_x_preferred": [
      "Jiangyou"
    ],
    "name:nor_x_preferred": [
      "Jiangyou"
    ],
    "name:rus_x_preferred": [
      "Цзянъю"
    ],
    "name:swe_x_preferred": [
      "Jiangyou"
    ],
    "name:urd_x_preferred": [
      "جیانگیوو"
    ],
    "name:vie_x_preferred": [
      "Giang Du"
    ],
    "name:war_x_preferred": [
      "Jiangyou"
    ],
    "name:zho_x_preferred": [
      "江右"
    ],
    "name:zho_x_variant": [
      "江油市"
    ],
    "wof:name": "Jiangyou",
    "wof:placetype": "locality"
  },
  "geometry": {
    "coordinates": [
      110.645,
      24.6828
    ],
    "type": "Point"
  }
}