{
  "type": "Feature",
  "properties": {
    "gn:admin1_code": "16",
    "gn:asciiname": "Moshitou",
    "gn:country_code": "CN",
    "gn:dem": 1148,
    "gn:feature_class": "P",
    "gn:feature_code": "PPL",
    "gn:name": "Moshitou",
    "gn:population": 0,
    "gn:timezone": "Asia/Shanghai",
    "iso:country": "CN",
    "name:zho_x_preferred": [
      "磨石头"
    ],
    "wof:name": "Moshitou",
    "wof:placetype": "locality"
  },
  "geometry": {
    "coordinates": [
      110.458,
      26.0963
    ],
    "type": "Point"
  }
}