{
  "type": "Feature",
  "properties": {
    "gn:admin1_code": "8.0",
    "gn:asciiname": "Shantoucun",
    "gn:country_code": "CN",
    "gn:dem": 141,
    "gn:feature_class": "P",
    "gn:feature_code": "PPL",
    "gn:name": "Shantoucun",
    "gn:population": 0,
    "gn:timezone": "Asia/Shanghai",
    "iso:country": "CN",
    "name:zho_x_preferred": [
      "山头村"
    ],
    "wof:name": "Shantoucun",
    "wof:placetype": "locality"
  },
  "geometry": {
    "coordinates": [
      123.4647,
      46.58069
    ],
    "type": "Point"
  }
}