{
  "type": "Feature",
  "properties": {
    "gn:admin1_code": "2",
    "gn:asciiname": "Shangdian",
    "gn:country_code": "CN",
    "gn:dem": 196,
    "gn:feature_class": "P",
    "gn:feature_code": "PPL",
    "gn:name": "Shangdian",
    "gn:population": 0,
    "gn:timezone": "Asia/Shanghai",
    "iso:country": "CN",
    "name:und_x_variant": [
      "上店"
    ],
    "wof:name": "Shangdian",
    "wof:placetype": "locality"
  },
  "geometry": {
    "coordinates": [
      119.81611,
      29.78306
    ],
    "type": "Point"
  }
}