{
  "type": "Feature",
  "properties": {
    "gn:admin1_code": "10",
    "gn:asciiname": "Baozhugoumen",
    "gn:country_code": "CN",
    "gn:dem": 352,
    "gn:feature_class": "P",
    "gn:feature_code": "PPL",
    "gn:name": "Baozhugoumen",
    "gn:population": 0,
    "gn:timezone": "Asia/Shanghai",
    "iso:country": "CN",
    "name:zho_x_preferred": [
      "爆竹沟门"
    ],
    "wof:name": "Baozhugoumen",
    "wof:placetype": "locality"
  },
  "geometry": {
    "coordinates": [
      118.0263,
      40.77767
    ],
    "type": "Point"
  }
}