{
  "type": "Feature",
  "properties": {
    "gn:admin1_code": "3.0",
    "gn:asciiname": "Ma'ancun",
    "gn:country_code": "CN",
    "gn:dem": 74,
    "gn:feature_class": "P",
    "gn:feature_code": "PPL",
    "gn:name": "Ma’ancun",
    "gn:population": 0,
    "gn:timezone": "Asia/Shanghai",
    "iso:country": "CN",
    "name:und_x_variant": [
      "Ma’ancun",
      "Ma’anbei"
    ],
    "name:zho_x_preferred": [
      "马鞍村"
    ],
    "name:zho_x_variant": [
      "马鞍碑"
    ],
    "wof:name": "Ma'ancun",
    "wof:placetype": "locality"
  },
  "geometry": {
    "coordinates": [
      117.477,
      28.4975
    ],
    "type": "Point"
  }
}