{
  "type": "Feature",
  "properties": {
    "gn:admin1_code": "7",
    "gn:asciiname": "Nanyang",
    "gn:country_code": "CN",
    "gn:dem": 690,
    "gn:feature_class": "P",
    "gn:feature_code": "PPL",
    "gn:name": "Nanyang",
    "gn:population": 0,
    "gn:timezone": "Asia/Shanghai",
    "iso:country": "CN",
    "name:ceb_x_preferred": [
      "Nanyang"
    ],
    "name:deu_x_preferred": [
      "Nanyang"
    ],
    "name:heb_x_preferred": [
      "נניאנג"
    ],
    "name:hun_x_preferred": [
      "Nanjang"
    ],
    "name:mlg_x_preferred": [
      "Nanyang"
    ],
    "name:nor_x_preferred": [
      "Nanyang"
    ],
    "name:swe_x_preferred": [
      "Nanyang"
    ],
    "name:und_x_variant": [
      "南洋"
    ],
    "name:vie_x_preferred": [
      "Nam Dương"
    ],
    "wof:name": "Nanyang",
    "wof:placetype": "locality"
  },
  "geometry": {
    "coordinates": [
      118.92333,
      27.15556
    ],
    "type": "Point"
  }
}