{
  "type": "Feature",
  "properties": {
    "gn:admin1_code": "15.0",
    "gn:asciiname": "Jincha",
    "gn:country_code": "CN",
    "gn:dem": 1358,
    "gn:feature_class": "P",
    "gn:feature_code": "PPL",
    "gn:name": "Jincha",
    "gn:population": 0,
    "gn:timezone": "Asia/Shanghai",
    "iso:country": "CN",
    "name:und_x_variant": [
      "金岔"
    ],
    "wof:name": "Jincha",
    "wof:placetype": "locality"
  },
  "geometry": {
    "coordinates": [
      107.62141,
      36.66208
    ],
    "type": "Point"
  }
}