{
  "type": "Feature",
  "properties": {
    "gn:admin1_code": "16.0",
    "gn:asciiname": "Longzao",
    "gn:country_code": "CN",
    "gn:dem": 566,
    "gn:feature_class": "P",
    "gn:feature_code": "PPL",
    "gn:name": "Longzao",
    "gn:population": 0,
    "gn:timezone": "Asia/Shanghai",
    "iso:country": "CN",
    "name:zho_x_preferred": [
      "龙早"
    ],
    "wof:name": "Longzao",
    "wof:placetype": "locality"
  },
  "geometry": {
    "coordinates": [
      106.921,
      22.8694
    ],
    "type": "Point"
  }
}