{
  "type": "Feature",
  "properties": {
    "gn:admin1_code": "2.0",
    "gn:asciiname": "Shankengwei",
    "gn:country_code": "CN",
    "gn:dem": 625,
    "gn:feature_class": "P",
    "gn:feature_code": "PPL",
    "gn:name": "Shankengwei",
    "gn:population": 0,
    "gn:timezone": "Asia/Shanghai",
    "iso:country": "CN",
    "name:zho_x_preferred": [
      "山坑尾"
    ],
    "wof:name": "Shankengwei",
    "wof:placetype": "locality"
  },
  "geometry": {
    "coordinates": [
      118.55022,
      28.31372
    ],
    "type": "Point"
  }
}