{
  "type": "Feature",
  "properties": {
    "gn:admin1_code": "15.0",
    "gn:asciiname": "Wangjiadun",
    "gn:country_code": "CN",
    "gn:dem": 1499,
    "gn:feature_class": "P",
    "gn:feature_code": "PPL",
    "gn:name": "Wangjiadun",
    "gn:population": 0,
    "gn:timezone": "Asia/Shanghai",
    "iso:country": "CN",
    "name:zho_x_preferred": [
      "王家墩"
    ],
    "wof:name": "Wangjiadun",
    "wof:placetype": "locality"
  },
  "geometry": {
    "coordinates": [
      102.732,
      37.9728
    ],
    "type": "Point"
  }
}