{
  "type": "Feature",
  "properties": {
    "gn:admin1_code": "29.0",
    "gn:asciiname": "Ma'an",
    "gn:country_code": "CN",
    "gn:dem": 1579,
    "gn:feature_class": "P",
    "gn:feature_code": "PPL",
    "gn:name": "Ma’an",
    "gn:population": 0,
    "gn:timezone": "Asia/Shanghai",
    "iso:country": "CN",
    "name:ara_x_preferred": [
      "معان"
    ],
    "name:ben_x_preferred": [
      "মান"
    ],
    "name:cat_x_preferred": [
      "Maan"
    ],
    "name:ceb_x_preferred": [
      "Ma'an"
    ],
    "name:ces_x_preferred": [
      "Ma'án"
    ],
    "name:cym_x_preferred": [
      "Ma'an"
    ],
    "name:dan_x_preferred": [
      "Ma'an"
    ],
    "name:deu_x_preferred": [
      "Maʿan"
    ],
    "name:fas_x_preferred": [
      "معان"
    ],
    "name:fin_x_preferred": [
      "Ma’an"
    ],
    "name:fra_x_preferred": [
      "Ma'an"
    ],
    "name:heb_x_preferred": [
      "מעאן"
    ],
    "name:hin_x_preferred": [
      "मान"
    ],
    "name:hun_x_preferred": [
      "Maán"
    ],
    "name:hye_x_preferred": [
      "Մաան"
    ],
    "name:ind_x_preferred": [
      "Ma'an"
    ],
    "name:ita_x_preferred": [
      "Ma'an"
    ],
    "name:jpn_x_preferred": [
      "マアーン"
    ],
    "name:kaz_x_preferred": [
      "Маан қаласы"
    ],
    "name:lit_x_preferred": [
      "Maanas"
    ],
    "name:mzn_x_preferred": [
      "معان"
    ],
    "name:nld_x_preferred": [
      "Ma'an"
    ],
    "name:nno_x_preferred": [
      "Ma'an"
    ],
    "name:nor_x_preferred": [
      "Ma'an"
    ],
    "name:pnb_x_preferred": [
      "معان"
    ],
    "name:pol_x_preferred": [
      "Ma’an"
    ],
    "name:rus_x_preferred": [
      "Маан"
    ],
    "name:sco_x_preferred": [
      "Ma'an"
    ],
    "name:spa_x_preferred": [
      "Ma'an"
    ],
    "name:sqi_x_preferred": [
      "Ma'an"
    ],
    "name:swe_x_preferred": [
      "Ma'an"
    ],
    "name:tur_x_preferred": [
      "Ma'an"
    ],
    "name:urd_x_preferred": [
      "معان"
    ],
    "name:vie_x_preferred": [
      "Ma'an"
    ],
    "name:zho_x_preferred": [
      "马鞍"
    ],
    "wof:name": "Ma'an",
    "wof:placetype": "locality"
  },
  "geometry": {
    "coordinates": [
      99.0038,
      25.1279
    ],
    "type": "Point"
  }
}