{
  "type": "Feature",
  "properties": {
    "gn:admin1_code": "4.0",
    "gn:asciiname": "Sangfu",
    "gn:country_code": "CN",
    "gn:dem": 5,
    "gn:feature_class": "P",
    "gn:feature_code": "PPL",
    "gn:name": "Sangfu",
    "gn:population": 0,
    "gn:timezone": "Asia/Shanghai",
    "iso:country": "CN",
    "name:zho_x_preferred": [
      "桑富"
    ],
    "wof:name": "Sangfu",
    "wof:placetype": "locality"
  },
  "geometry": {
    "coordinates": [
      120.16214,
      33.00371
    ],
    "type": "Point"
  }
}