{
  "type": "Feature",
  "properties": {
    "gn:admin1_code": "29.0",
    "gn:asciiname": "Da'aba",
    "gn:country_code": "CN",
    "gn:dem": 1405,
    "gn:feature_class": "P",
    "gn:feature_code": "PPL",
    "gn:name": "Da’aba",
    "gn:population": 0,
    "gn:timezone": "Asia/Shanghai",
    "iso:country": "CN",
    "name:und_x_variant": [
      "Da’aba"
    ],
    "name:zho_x_preferred": [
      "大阿巴"
    ],
    "wof:name": "Da'aba",
    "wof:placetype": "locality"
  },
  "geometry": {
    "coordinates": [
      102.007,
      22.8985
    ],
    "type": "Point"
  }
}