{
  "type": "Feature",
  "properties": {
    "gn:admin1_code": "10.0",
    "gn:asciiname": "Dongbimeng",
    "gn:country_code": "CN",
    "gn:dem": 10,
    "gn:feature_class": "P",
    "gn:feature_code": "PPL",
    "gn:name": "Dongbimeng",
    "gn:population": 0,
    "gn:timezone": "Asia/Shanghai",
    "iso:country": "CN",
    "name:zho_x_preferred": [
      "东毕孟"
    ],
    "wof:name": "Dongbimeng",
    "wof:placetype": "locality"
  },
  "geometry": {
    "coordinates": [
      117.18,
      38.2299
    ],
    "type": "Point"
  }
}