{
  "type": "Feature",
  "properties": {
    "gn:admin1_code": "8.0",
    "gn:asciiname": "Zhaoxingwutun",
    "gn:country_code": "CN",
    "gn:dem": 193,
    "gn:feature_class": "P",
    "gn:feature_code": "PPL",
    "gn:name": "Zhaoxingwutun",
    "gn:population": 0,
    "gn:timezone": "Asia/Shanghai",
    "iso:country": "CN",
    "name:zho_x_preferred": [
      "赵兴武屯"
    ],
    "wof:name": "Zhaoxingwutun",
    "wof:placetype": "locality"
  },
  "geometry": {
    "coordinates": [
      126.05625,
      46.69377
    ],
    "type": "Point"
  }
}