{
  "type": "Feature",
  "properties": {
    "gn:admin1_code": "1.0",
    "gn:asciiname": "Shahecun",
    "gn:country_code": "CN",
    "gn:dem": 183,
    "gn:feature_class": "P",
    "gn:feature_code": "PPL",
    "gn:name": "Shahecun",
    "gn:population": 0,
    "gn:timezone": "Asia/Shanghai",
    "iso:country": "CN",
    "name:zho_x_preferred": [
      "沙河村"
    ],
    "wof:name": "Shahecun",
    "wof:placetype": "locality"
  },
  "geometry": {
    "coordinates": [
      115.87952,
      30.65912
    ],
    "type": "Point"
  }
}