{
  "type": "Feature",
  "properties": {
    "gn:admin1_code": "31.0",
    "gn:asciiname": "Zhizhou",
    "gn:country_code": "CN",
    "gn:dem": 47,
    "gn:feature_class": "P",
    "gn:feature_code": "PPL",
    "gn:name": "Zhizhou",
    "gn:population": 0,
    "gn:timezone": "Asia/Shanghai",
    "iso:country": "CN",
    "name:zho_x_preferred": [
      "知州"
    ],
    "wof:name": "Zhizhou",
    "wof:placetype": "locality"
  },
  "geometry": {
    "coordinates": [
      110.46139,
      19.78077
    ],
    "type": "Point"
  }
}