{
  "type": "Feature",
  "properties": {
    "gn:country": "CN",
    "gn:fcode": "PPLA4",
    "gn:population": 0,
    "iso:country": "CN",
    "name:ara_x_preferred": [
      "تونغلي"
    ],
    "name:deu_x_preferred": [
      "Tongli"
    ],
    "name:eng_x_preferred": [
      "Tongli"
    ],
    "name:fra_x_preferred": [
      "Tongli"
    ],
    "name:gan_x_preferred": [
      "同里镇"
    ],
    "name:hun_x_preferred": [
      "Tungli"
    ],
    "name:jpn_x_preferred": [
      "同里鎮"
    ],
    "name:kor_x_preferred": [
      "퉁리 진"
    ],
    "name:nob_x_preferred": [
      "Tongli"
    ],
    "name:swe_x_preferred": [
      "Tongli"
    ],
    "name:tha_x_preferred": [
      "ถงหลี่"
    ],
    "name:und_x_variant": [
      "T’ung-li-chen"
    ],
    "name:vie_x_preferred": [
      "Đồng Lý"
    ],
    "name:wuu_x_preferred": [
      "同里镇"
    ],
    "name:zho_x_preferred": [
      "同里镇"
    ],
    "qs:name": "Tongli",
    "qs:photos_9r": 0,
    "qs:photos_sr": 0,
    "qs:pop_sr": "0",
    "wd:wordcount": 374,
    "wof:name": "Tongli",
    "wof:placetype": "locality",
    "wof:population": 0
  },
  "geometry": {
    "coordinates": [
      120.71177,
      31.16097
    ],
    "type": "Point"
  }
}