{
  "type": "Feature",
  "properties": {
    "gn:admin1_code": "30.0",
    "gn:asciiname": "Minshengcun",
    "gn:country_code": "CN",
    "gn:dem": 64,
    "gn:feature_class": "P",
    "gn:feature_code": "PPL",
    "gn:name": "Minshengcun",
    "gn:population": 0,
    "gn:timezone": "Asia/Shanghai",
    "iso:country": "CN",
    "name:zho_x_preferred": [
      "民生村"
    ],
    "wof:name": "Minshengcun",
    "wof:placetype": "locality"
  },
  "geometry": {
    "coordinates": [
      111.75945,
      23.23343
    ],
    "type": "Point"
  }
}