{
  "type": "Feature",
  "properties": {
    "gn:admin1_code": "3.0",
    "gn:asciiname": "Kengxi",
    "gn:country_code": "CN",
    "gn:dem": 62,
    "gn:feature_class": "P",
    "gn:feature_code": "PPL",
    "gn:name": "Kengxi",
    "gn:population": 0,
    "gn:timezone": "Asia/Shanghai",
    "iso:country": "CN",
    "name:und_x_variant": [
      "坑西"
    ],
    "wof:name": "Kengxi",
    "wof:placetype": "locality"
  },
  "geometry": {
    "coordinates": [
      115.31303,
      27.56022
    ],
    "type": "Point"
  }
}