{
  "type": "Feature",
  "properties": {
    "gn:admin1_code": "16.0",
    "gn:asciiname": "Hema Zhongzhai",
    "gn:country_code": "CN",
    "gn:dem": 1112,
    "gn:feature_class": "P",
    "gn:feature_code": "PPL",
    "gn:name": "Hema Zhongzhai",
    "gn:population": 0,
    "gn:timezone": "Asia/Shanghai",
    "iso:country": "CN",
    "name:zho_x_preferred": [
      "河马中寨"
    ],
    "wof:name": "Hema Zhongzhai",
    "wof:placetype": "locality"
  },
  "geometry": {
    "coordinates": [
      105.442,
      24.6225
    ],
    "type": "Point"
  }
}