{
  "type": "Feature",
  "properties": {
    "gn:admin1_code": "11.0",
    "gn:asciiname": "Lianhua",
    "gn:country_code": "CN",
    "gn:dem": 51,
    "gn:feature_class": "P",
    "gn:feature_code": "PPL",
    "gn:name": "Lianhua",
    "gn:population": 0,
    "gn:timezone": "Asia/Shanghai",
    "iso:country": "CN",
    "name:ceb_x_preferred": [
      "Lianhua"
    ],
    "name:deu_x_preferred": [
      "Lianhua"
    ],
    "name:nor_x_preferred": [
      "Lianhua"
    ],
    "name:zho_x_preferred": [
      "莲花"
    ],
    "wof:name": "Lianhua",
    "wof:placetype": "locality"
  },
  "geometry": {
    "coordinates": [
      113.19573,
      28.7868
    ],
    "type": "Point"
  }
}