{
  "type": "Feature",
  "properties": {
    "gn:admin1_code": "24.0",
    "gn:asciiname": "Xituanbu",
    "gn:country_code": "CN",
    "gn:dem": 1014,
    "gn:feature_class": "P",
    "gn:feature_code": "PPL",
    "gn:name": "Xituanbu",
    "gn:population": 0,
    "gn:timezone": "Asia/Shanghai",
    "iso:country": "CN",
    "name:und_x_variant": [
      "T’uan-pao-ts’un",
      "Hsi-t’uan-pao",
      "Xituanbu",
      "西团堡"
    ],
    "wof:name": "Xituanbu",
    "wof:placetype": "locality"
  },
  "geometry": {
    "coordinates": [
      113.86002,
      39.93554
    ],
    "type": "Point"
  }
}