{
  "type": "Feature",
  "properties": {
    "gn:admin1_code": "06",
    "gn:asciiname": "Bayan",
    "gn:country_code": "CN",
    "gn:dem": 2797,
    "gn:feature_class": "P",
    "gn:feature_code": "PPLA4",
    "gn:name": "Bayan",
    "gn:population": 0,
    "gn:timezone": "Asia/Shanghai",
    "iso:country": "CN",
    "name:ara_x_preferred": [
      "البيان"
    ],
    "name:aze_x_preferred": [
      "Bayan"
    ],
    "name:cat_x_preferred": [
      "Bayan"
    ],
    "name:ceb_x_preferred": [
      "Bayan"
    ],
    "name:deu_x_preferred": [
      "Bayan"
    ],
    "name:fra_x_preferred": [
      "Bayan"
    ],
    "name:glg_x_preferred": [
      "Baian"
    ],
    "name:ind_x_preferred": [
      "Bayan"
    ],
    "name:ita_x_preferred": [
      "Bayan"
    ],
    "name:jpn_x_preferred": [
      "バヤン"
    ],
    "name:kat_x_preferred": [
      "ბაიანი"
    ],
    "name:kaz_x_preferred": [
      "Баян"
    ],
    "name:mlg_x_preferred": [
      "Bayan"
    ],
    "name:nld_x_preferred": [
      "Bayan"
    ],
    "name:nor_x_preferred": [
      "Bayan"
    ],
    "name:rus_x_preferred": [
      "Баян"
    ],
    "name:swe_x_preferred": [
      "Bayan"
    ],
    "name:tgl_x_preferred": [
      "Bayan"
    ],
    "name:tur_x_preferred": [
      "Bayan"
    ],
    "name:ukr_x_preferred": [
      "Баян"
    ],
    "name:und_x_variant": [
      "Pa-yen",
      "Bayan Xiang"
    ],
    "name:zho_x_preferred": [
      "巴燕"
    ],
    "name:zho_x_variant": [
      "巴燕乡"
    ],
    "wof:name": "Bayan",
    "wof:placetype": "locality"
  },
  "geometry": {
    "coordinates": [
      101.13194,
      36.76611
    ],
    "type": "Point"
  }
}