{
  "type": "Feature",
  "properties": {
    "gn:admin1_code": "32.0",
    "gn:asciiname": "Wang'anhe",
    "gn:country_code": "CN",
    "gn:dem": 417,
    "gn:feature_class": "P",
    "gn:feature_code": "PPL",
    "gn:name": "Wang’anhe",
    "gn:population": 0,
    "gn:timezone": "Asia/Shanghai",
    "iso:country": "CN",
    "name:zho_x_preferred": [
      "王安河"
    ],
    "name:zho_x_variant": [
      "Wang’anhe"
    ],
    "wof:name": "Wang'anhe",
    "wof:placetype": "locality"
  },
  "geometry": {
    "coordinates": [
      104.95358,
      30.05967
    ],
    "type": "Point"
  }
}