{
  "type": "Feature",
  "properties": {
    "gn:admin1_code": "20.0",
    "gn:asciiname": "Dahuhuadai",
    "gn:country_code": "CN",
    "gn:dem": 1931,
    "gn:feature_class": "P",
    "gn:feature_code": "PPL",
    "gn:name": "Dahuhuadai",
    "gn:population": 0,
    "gn:timezone": "Asia/Shanghai",
    "iso:country": "CN",
    "name:und_x_variant": [
      "大虎花岱"
    ],
    "wof:name": "Dahuhuadai",
    "wof:placetype": "locality"
  },
  "geometry": {
    "coordinates": [
      110.74975,
      41.13128
    ],
    "type": "Point"
  }
}