{
  "type": "Feature",
  "properties": {
    "gn:admin1_code": "32.0",
    "gn:asciiname": "Pujiawan",
    "gn:country_code": "CN",
    "gn:dem": 471,
    "gn:feature_class": "P",
    "gn:feature_code": "PPL",
    "gn:name": "Pujiawan",
    "gn:population": 0,
    "gn:timezone": "Asia/Shanghai",
    "iso:country": "CN",
    "name:zho_x_preferred": [
      "普家湾"
    ],
    "wof:name": "Pujiawan",
    "wof:placetype": "locality"
  },
  "geometry": {
    "coordinates": [
      105.04255,
      30.42864
    ],
    "type": "Point"
  }
}