{
  "type": "Feature",
  "properties": {
    "gn:admin1_code": "16.0",
    "gn:asciiname": "Bafang",
    "gn:country_code": "CN",
    "gn:dem": 493,
    "gn:feature_class": "P",
    "gn:feature_code": "PPL",
    "gn:name": "Bafang",
    "gn:population": 0,
    "gn:timezone": "Asia/Shanghai",
    "iso:country": "CN",
    "name:ben_x_preferred": [
      "বাফাংগ"
    ],
    "name:ceb_x_preferred": [
      "Bafang"
    ],
    "name:ces_x_preferred": [
      "Bafang"
    ],
    "name:deu_x_preferred": [
      "Bafang"
    ],
    "name:ell_x_preferred": [
      "Μπαφάνγκ"
    ],
    "name:fas_x_preferred": [
      "بافانگ"
    ],
    "name:fra_x_preferred": [
      "Bafang"
    ],
    "name:heb_x_preferred": [
      "בפנג"
    ],
    "name:hin_x_preferred": [
      "बफांग"
    ],
    "name:hun_x_preferred": [
      "Bafang"
    ],
    "name:ind_x_preferred": [
      "Bafang"
    ],
    "name:ita_x_preferred": [
      "Bafang"
    ],
    "name:jpn_x_preferred": [
      "バファン"
    ],
    "name:kor_x_preferred": [
      "바팡"
    ],
    "name:msa_x_preferred": [
      "Bafang"
    ],
    "name:pol_x_preferred": [
      "Bafang"
    ],
    "name:por_x_preferred": [
      "Bafang"
    ],
    "name:ron_x_preferred": [
      "Bafang"
    ],
    "name:rus_x_preferred": [
      "Бафан"
    ],
    "name:spa_x_preferred": [
      "Bafang"
    ],
    "name:swe_x_preferred": [
      "Bafang"
    ],
    "name:tur_x_preferred": [
      "Bafang"
    ],
    "name:ukr_x_preferred": [
      "Бафанг"
    ],
    "name:urd_x_preferred": [
      "بافانگ"
    ],
    "name:vie_x_preferred": [
      "Bafang"
    ],
    "name:zho_x_preferred": [
      "岜防"
    ],
    "wof:name": "Bafang",
    "wof:placetype": "locality"
  },
  "geometry": {
    "coordinates": [
      107.293,
      24.4663
    ],
    "type": "Point"
  }
}