{
  "type": "Feature",
  "properties": {
    "gn:admin1_code": "15.0",
    "gn:asciiname": "Wangjiapan",
    "gn:country_code": "CN",
    "gn:dem": 1362,
    "gn:feature_class": "P",
    "gn:feature_code": "PPL",
    "gn:name": "Wangjiapan",
    "gn:population": 0,
    "gn:timezone": "Asia/Shanghai",
    "iso:country": "CN",
    "name:zho_x_preferred": [
      "王家畔"
    ],
    "wof:name": "Wangjiapan",
    "wof:placetype": "locality"
  },
  "geometry": {
    "coordinates": [
      107.772,
      35.8649
    ],
    "type": "Point"
  }
}