{
  "type": "Feature",
  "properties": {
    "gn:admin1_code": "2.0",
    "gn:asciiname": "Huangbaikeng",
    "gn:country_code": "CN",
    "gn:dem": 183,
    "gn:feature_class": "P",
    "gn:feature_code": "PPL",
    "gn:name": "Huangbaikeng",
    "gn:population": 0,
    "gn:timezone": "Asia/Shanghai",
    "iso:country": "CN",
    "name:zho_x_preferred": [
      "黄柏坑"
    ],
    "wof:name": "Huangbaikeng",
    "wof:placetype": "locality"
  },
  "geometry": {
    "coordinates": [
      118.2246,
      28.97674
    ],
    "type": "Point"
  }
}