{
  "type": "Feature",
  "properties": {
    "gn:admin1_code": "26",
    "gn:asciiname": "Guoyuancun",
    "gn:country_code": "CN",
    "gn:dem": 346,
    "gn:feature_class": "P",
    "gn:feature_code": "PPL",
    "gn:name": "Guoyuancun",
    "gn:population": 0,
    "gn:timezone": "Asia/Shanghai",
    "iso:country": "CN",
    "name:und_x_variant": [
      "Kuo-yüan",
      "Guoyuan",
      "Guoyuancun"
    ],
    "name:zho_x_preferred": [
      "果园村"
    ],
    "wof:name": "Guoyuancun",
    "wof:placetype": "locality"
  },
  "geometry": {
    "coordinates": [
      109.67011,
      34.65091
    ],
    "type": "Point"
  }
}