{
  "type": "Feature",
  "properties": {
    "gn:admin1_code": "12.0",
    "gn:asciiname": "Gou'ertan",
    "gn:country_code": "CN",
    "gn:dem": 441,
    "gn:feature_class": "P",
    "gn:feature_code": "PPL",
    "gn:name": "Gou’ertan",
    "gn:population": 0,
    "gn:timezone": "Asia/Shanghai",
    "iso:country": "CN",
    "name:und_x_variant": [
      "Gou’ertan"
    ],
    "name:zho_x_preferred": [
      "沟二滩"
    ],
    "wof:name": "Gou'ertan",
    "wof:placetype": "locality"
  },
  "geometry": {
    "coordinates": [
      110.77395,
      31.40995
    ],
    "type": "Point"
  }
}