{
  "type": "Feature",
  "properties": {
    "gn:admin1_code": "11",
    "gn:asciiname": "Anshun",
    "gn:country_code": "CN",
    "gn:dem": 820,
    "gn:feature_class": "P",
    "gn:feature_code": "PPL",
    "gn:name": "Anshun",
    "gn:population": 0,
    "gn:timezone": "Asia/Shanghai",
    "iso:country": "CN",
    "name:ara_x_preferred": [
      "أنشون"
    ],
    "name:cdo_x_preferred": [
      "Ăng-sông"
    ],
    "name:ceb_x_preferred": [
      "Anshun"
    ],
    "name:ces_x_preferred": [
      "An-šun"
    ],
    "name:cym_x_preferred": [
      "Anshun"
    ],
    "name:dan_x_preferred": [
      "Anshun"
    ],
    "name:deu_x_preferred": [
      "Anshun"
    ],
    "name:eus_x_preferred": [
      "Anshun"
    ],
    "name:fas_x_preferred": [
      "انشون"
    ],
    "name:fin_x_preferred": [
      "Anshun"
    ],
    "name:fra_x_preferred": [
      "Anshun"
    ],
    "name:heb_x_preferred": [
      "אנשון"
    ],
    "name:hun_x_preferred": [
      "Anshun"
    ],
    "name:ita_x_preferred": [
      "Anshun"
    ],
    "name:jpn_x_preferred": [
      "安順市"
    ],
    "name:kik_x_preferred": [
      "Anshun"
    ],
    "name:kor_x_preferred": [
      "안순시"
    ],
    "name:lit_x_preferred": [
      "Anšunas"
    ],
    "name:mlg_x_preferred": [
      "Anshun"
    ],
    "name:nld_x_preferred": [
      "Anshun"
    ],
    "name:nno_x_preferred": [
      "Anshun"
    ],
    "name:nor_x_preferred": [
      "Anshun"
    ],
    "name:pam_x_preferred": [
      "Anshun"
    ],
    "name:pnb_x_preferred": [
      "انشون"
    ],
    "name:pol_x_preferred": [
      "Anshun"
    ],
    "name:por_x_preferred": [
      "Anshun"
    ],
    "name:rus_x_preferred": [
      "Аньшунь"
    ],
    "name:spa_x_preferred": [
      "Anshun"
    ],
    "name:srp_x_preferred": [
      "Аншун"
    ],
    "name:swe_x_preferred": [
      "Anshun"
    ],
    "name:tur_x_preferred": [
      "Anshun"
    ],
    "name:ukr_x_preferred": [
      "Аньшунь"
    ],
    "name:urd_x_preferred": [
      "انشون"
    ],
    "name:vie_x_preferred": [
      "An Thuận"
    ],
    "name:war_x_preferred": [
      "Anshun"
    ],
    "name:zho_x_preferred": [
      "安顺市"
    ],
    "wof:name": "Anshun",
    "wof:placetype": "locality"
  },
  "geometry": {
    "coordinates": [
      110.16333,
      27.04028
    ],
    "type": "Point"
  }
}