{
  "type": "Feature",
  "properties": {
    "gn:admin1_code": "30.0",
    "gn:asciiname": "Dajiangjiao",
    "gn:country_code": "CN",
    "gn:dem": 59,
    "gn:feature_class": "P",
    "gn:feature_code": "PPL",
    "gn:name": "Dajiangjiao",
    "gn:population": 0,
    "gn:timezone": "Asia/Shanghai",
    "iso:country": "CN",
    "name:zho_x_preferred": [
      "大江脚"
    ],
    "wof:name": "Dajiangjiao",
    "wof:placetype": "locality"
  },
  "geometry": {
    "coordinates": [
      112.65341,
      23.32747
    ],
    "type": "Point"
  }
}