{
  "type": "Feature",
  "properties": {
    "gn:admin1_code": "16.0",
    "gn:asciiname": "Zhili",
    "gn:country_code": "CN",
    "gn:dem": 154,
    "gn:feature_class": "P",
    "gn:feature_code": "PPL",
    "gn:name": "Zhili",
    "gn:population": 0,
    "gn:timezone": "Asia/Shanghai",
    "iso:country": "CN",
    "name:ces_x_preferred": [
      "Č’-li"
    ],
    "name:deu_x_preferred": [
      "Zhili"
    ],
    "name:fra_x_preferred": [
      "Zhili"
    ],
    "name:ind_x_preferred": [
      "Zhili"
    ],
    "name:ita_x_preferred": [
      "Zhili"
    ],
    "name:oss_x_preferred": [
      "Чжили"
    ],
    "name:pol_x_preferred": [
      "Zhili"
    ],
    "name:rus_x_preferred": [
      "Чжили"
    ],
    "name:srp_x_preferred": [
      "Џили"
    ],
    "name:ukr_x_preferred": [
      "Чжилі"
    ],
    "name:vie_x_preferred": [
      "Trực Lệ"
    ],
    "name:zho_x_preferred": [
      "止礼"
    ],
    "wof:name": "Zhili",
    "wof:placetype": "locality"
  },
  "geometry": {
    "coordinates": [
      109.461,
      23.4299
    ],
    "type": "Point"
  }
}