{
  "type": "Feature",
  "properties": {
    "gn:admin1_code": "26.0",
    "gn:asciiname": "Shibucun",
    "gn:country_code": "CN",
    "gn:dem": 1032,
    "gn:feature_class": "P",
    "gn:feature_code": "PPL",
    "gn:name": "Shibucun",
    "gn:population": 0,
    "gn:timezone": "Asia/Shanghai",
    "iso:country": "CN",
    "name:zho_x_preferred": [
      "石堡村"
    ],
    "wof:name": "Shibucun",
    "wof:placetype": "locality"
  },
  "geometry": {
    "coordinates": [
      110.9562,
      38.94966
    ],
    "type": "Point"
  }
}