{
  "type": "Feature",
  "properties": {
    "gn:admin1_code": "10",
    "gn:asciiname": "Donghoufang",
    "gn:country_code": "CN",
    "gn:dem": 52,
    "gn:feature_class": "P",
    "gn:feature_code": "PPLA4",
    "gn:name": "Donghoufang",
    "gn:population": 0,
    "gn:timezone": "Asia/Shanghai",
    "iso:country": "CN",
    "name:fas_x_preferred": [
      "شهر دونگهوفانگ"
    ],
    "name:und_x_variant": [
      "东侯坊",
      "Donghoufang Xiang"
    ],
    "name:zho_x_preferred": [
      "东侯坊乡"
    ],
    "wof:name": "Donghoufang",
    "wof:placetype": "locality"
  },
  "geometry": {
    "coordinates": [
      114.89778,
      38.1825
    ],
    "type": "Point"
  }
}