{
  "type": "Feature",
  "properties": {
    "gn:admin1_code": "12.0",
    "gn:asciiname": "Tianjiashan",
    "gn:country_code": "CN",
    "gn:dem": 1604,
    "gn:feature_class": "P",
    "gn:feature_code": "PPL",
    "gn:name": "Tianjiashan",
    "gn:population": 0,
    "gn:timezone": "Asia/Shanghai",
    "iso:country": "CN",
    "name:zho_x_preferred": [
      "田家山"
    ],
    "wof:name": "Tianjiashan",
    "wof:placetype": "locality"
  },
  "geometry": {
    "coordinates": [
      110.43219,
      31.64098
    ],
    "type": "Point"
  }
}