{
  "type": "Feature",
  "properties": {
    "gn:admin1_code": "8.0",
    "gn:asciiname": "Xingwen Qibadui",
    "gn:country_code": "CN",
    "gn:dem": 198,
    "gn:feature_class": "P",
    "gn:feature_code": "PPLF",
    "gn:name": "Xingwen Qibadui",
    "gn:population": 0,
    "gn:timezone": "Asia/Shanghai",
    "iso:country": "CN",
    "name:zho_x_preferred": [
      "兴温七八队"
    ],
    "wof:name": "Xingwen Qibadui",
    "wof:placetype": "locality"
  },
  "geometry": {
    "coordinates": [
      125.5294,
      47.39195
    ],
    "type": "Point"
  }
}