{
  "type": "Feature",
  "properties": {
    "gn:admin1_code": "4.0",
    "gn:asciiname": "Xiangyang",
    "gn:country_code": "CN",
    "gn:dem": 168,
    "gn:feature_class": "P",
    "gn:feature_code": "PPL",
    "gn:name": "Xiangyang",
    "gn:population": 0,
    "gn:timezone": "Asia/Shanghai",
    "iso:country": "CN",
    "name:afr_x_preferred": [
      "Xiangyang"
    ],
    "name:ara_x_preferred": [
      "شيانغيانغ"
    ],
    "name:cdo_x_preferred": [
      "Siŏng-iòng"
    ],
    "name:ceb_x_preferred": [
      "Xiangyang"
    ],
    "name:ces_x_preferred": [
      "Siang-jang"
    ],
    "name:cym_x_preferred": [
      "Xiangyang"
    ],
    "name:dan_x_preferred": [
      "Xiangfan"
    ],
    "name:deu_x_preferred": [
      "Xiangyang"
    ],
    "name:eus_x_preferred": [
      "Xiangfan"
    ],
    "name:fas_x_preferred": [
      "شیانگیانگ"
    ],
    "name:fin_x_preferred": [
      "Xiangyang"
    ],
    "name:fra_x_preferred": [
      "Xiangyang"
    ],
    "name:heb_x_preferred": [
      "קסיאנגיאנג"
    ],
    "name:hun_x_preferred": [
      "Xiangyang"
    ],
    "name:ind_x_preferred": [
      "Xiangyang"
    ],
    "name:ita_x_preferred": [
      "Xiangyang"
    ],
    "name:jpn_x_preferred": [
      "襄陽市"
    ],
    "name:kik_x_preferred": [
      "Xiangyang"
    ],
    "name:kor_x_preferred": [
      "샹양시"
    ],
    "name:mlg_x_preferred": [
      "Xiangyang"
    ],
    "name:nld_x_preferred": [
      "Xiangyang"
    ],
    "name:nno_x_preferred": [
      "Xiangyang"
    ],
    "name:nor_x_preferred": [
      "Xiangfan"
    ],
    "name:pam_x_preferred": [
      "Xiangyang"
    ],
    "name:pol_x_preferred": [
      "Xiangyang"
    ],
    "name:por_x_preferred": [
      "Xiangyang"
    ],
    "name:rus_x_preferred": [
      "Сянъян"
    ],
    "name:spa_x_preferred": [
      "Xiangyang"
    ],
    "name:srp_x_preferred": [
      "Сјангјанг"
    ],
    "name:swe_x_preferred": [
      "Xiangyang"
    ],
    "name:tgl_x_preferred": [
      "Xiangyang"
    ],
    "name:tur_x_preferred": [
      "Xiangyang"
    ],
    "name:ukr_x_preferred": [
      "Сян'ян"
    ],
    "name:und_x_variant": [
      "Hsiang-yang"
    ],
    "name:urd_x_preferred": [
      "شیانگیانگ"
    ],
    "name:vie_x_preferred": [
      "Tương Dương"
    ],
    "name:war_x_preferred": [
      "Xiangfan"
    ],
    "name:zho_x_preferred": [
      "襄阳"
    ],
    "name:zho_x_variant": [
      "襄阳市"
    ],
    "wof:name": "Xiangyang",
    "wof:placetype": "locality"
  },
  "geometry": {
    "coordinates": [
      119.62278,
      31.15401
    ],
    "type": "Point"
  }
}