{
  "type": "Feature",
  "properties": {
    "iso:country": "CN",
    "name:eng_x_preferred": [
      "Yunjinghong"
    ],
    "name:zho_x_preferred": [
      "允景洪"
    ],
    "qs:name": "允景洪",
    "qs:name_adm0": "中國",
    "qs:name_adm1": "云南省",
    "qs:photos": 1704,
    "qs:photos_1k": 345,
    "qs:photos_9k": 8,
    "qs:photos_9r": 8,
    "qs:photos_all": 1704,
    "qs:photos_sr": 14,
    "qs:placetype": "Town",
    "qs:pop_sr": "0",
    "wof:name": "Yunjinghong",
    "wof:placetype": "locality"
  },
  "geometry": {
    "coordinates": [
      100.811576,
      21.972021
    ],
    "type": "Point"
  }
}