{
  "type": "Feature",
  "properties": {
    "gn:admin1_code": "29.0",
    "gn:asciiname": "Tagu",
    "gn:country_code": "CN",
    "gn:dem": 1690,
    "gn:feature_class": "P",
    "gn:feature_code": "PPL",
    "gn:name": "Tagu",
    "gn:population": 0,
    "gn:timezone": "Asia/Shanghai",
    "iso:country": "CN",
    "name:mya_x_preferred": [
      "တန်ခူးလ"
    ],
    "name:zho_x_preferred": [
      "他谷"
    ],
    "wof:name": "Tagu",
    "wof:placetype": "locality"
  },
  "geometry": {
    "coordinates": [
      104.135,
      24.9001
    ],
    "type": "Point"
  }
}