{
  "type": "Feature",
  "properties": {
    "iso:country": "CN",
    "name:ara_x_preferred": [
      "لويانغ"
    ],
    "name:bel_x_preferred": [
      "Горад Лаян"
    ],
    "name:bod_x_preferred": [
      "ལུའོ་དབྱང་།"
    ],
    "name:bul_x_preferred": [
      "Луоян"
    ],
    "name:cat_x_preferred": [
      "Luoyang"
    ],
    "name:cdo_x_preferred": [
      "Lŏk-iòng"
    ],
    "name:ces_x_preferred": [
      "Luo-jang"
    ],
    "name:deu_x_preferred": [
      "Luoyang"
    ],
    "name:eng_x_preferred": [
      "Luoyang"
    ],
    "name:epo_x_preferred": [
      "Lŭojango"
    ],
    "name:fas_x_preferred": [
      "لوئویانگ"
    ],
    "name:fra_x_preferred": [
      "Luoyang"
    ],
    "name:gan_x_preferred": [
      "罗阳镇"
    ],
    "name:heb_x_preferred": [
      "לוו-יאנג"
    ],
    "name:hin_x_preferred": [
      "लुओयांग"
    ],
    "name:hun_x_preferred": [
      "Lojang"
    ],
    "name:ind_x_preferred": [
      "Luoyang"
    ],
    "name:ita_x_preferred": [
      "Luoyang"
    ],
    "name:jpn_x_preferred": [
      "洛陽市"
    ],
    "name:jpn_x_variant": [
      "羅陽鎮"
    ],
    "name:kat_x_preferred": [
      "ლოიანი"
    ],
    "name:kir_x_preferred": [
      "Лоян шаары"
    ],
    "name:kor_x_preferred": [
      "뤄양 시"
    ],
    "name:lit_x_preferred": [
      "Luojangas"
    ],
    "name:lzh_x_preferred": [
      "洛陽"
    ],
    "name:mkd_x_preferred": [
      "Луојанг"
    ],
    "name:nan_x_preferred": [
      "Lo̍k-iông-chhī"
    ],
    "name:nld_x_preferred": [
      "Luoyang"
    ],
    "name:nor_x_preferred": [
      "Luoyang"
    ],
    "name:pol_x_preferred": [
      "Luoyang"
    ],
    "name:por_x_preferred": [
      "Luoyang"
    ],
    "name:rus_x_preferred": [
      "Лоян"
    ],
    "name:spa_x_preferred": [
      "Luoyang"
    ],
    "name:srp_x_preferred": [
      "Луојанг"
    ],
    "name:tha_x_preferred": [
      "ลกเอี๋ยง"
    ],
    "name:uig_x_preferred": [
      "لوياڭ شەھىرى"
    ],
    "name:ukr_x_preferred": [
      "Лоян"
    ],
    "name:und_x_variant": [
      "Honanfu"
    ],
    "name:urd_x_preferred": [
      "لوویانگ"
    ],
    "name:vie_x_preferred": [
      "Lạc Dương"
    ],
    "name:wuu_x_preferred": [
      "洛阳"
    ],
    "name:wuu_x_variant": [
      "罗阳镇"
    ],
    "name:yue_x_preferred": [
      "洛陽"
    ],
    "name:zho_x_preferred": [
      "洛阳市"
    ],
    "name:zho_x_variant": [
      "罗阳镇"
    ],
    "qs:name": "洛阳",
    "qs:name_adm0": "中國",
    "qs:name_adm1": "广东省",
    "qs:photos": 136,
    "qs:photos_1k": 28,
    "qs:photos_9k": 1,
    "qs:photos_9r": 3,
    "qs:photos_all": 136,
    "qs:photos_sr": 3,
    "qs:placetype": "Town",
    "qs:pop_sr": "0",
    "wof:name": "洛阳",
    "wof:placetype": "locality"
  },
  "geometry": {
    "coordinates": [
      114.279121,
      23.170945
    ],
    "type": "Point"
  }
}