{
  "type": "Feature",
  "properties": {
    "gn:admin1_code": "10",
    "gn:asciiname": "Guanchaigou",
    "gn:country_code": "CN",
    "gn:dem": 894,
    "gn:feature_class": "P",
    "gn:feature_code": "PPL",
    "gn:name": "Guanchaigou",
    "gn:population": 0,
    "gn:timezone": "Asia/Shanghai",
    "iso:country": "CN",
    "name:zho_x_preferred": [
      "官柴沟"
    ],
    "wof:name": "Guanchaigou",
    "wof:placetype": "locality"
  },
  "geometry": {
    "coordinates": [
      117.8864,
      41.9076
    ],
    "type": "Point"
  }
}