{
  "type": "Feature",
  "properties": {
    "gn:admin1_code": "3.0",
    "gn:asciiname": "Shitang",
    "gn:country_code": "CN",
    "gn:dem": 134,
    "gn:feature_class": "P",
    "gn:feature_code": "PPL",
    "gn:name": "Shitang",
    "gn:population": 0,
    "gn:timezone": "Asia/Shanghai",
    "iso:country": "CN",
    "name:zho_x_preferred": [
      "石塘"
    ],
    "wof:name": "Shitang",
    "wof:placetype": "locality"
  },
  "geometry": {
    "coordinates": [
      118.16315,
      28.46716
    ],
    "type": "Point"
  }
}