{
  "type": "Feature",
  "properties": {
    "gn:admin1_code": "30",
    "gn:asciiname": "Tangjiling",
    "gn:country_code": "CN",
    "gn:dem": 6,
    "gn:feature_class": "P",
    "gn:feature_code": "PPL",
    "gn:name": "Tangjiling",
    "gn:population": 0,
    "gn:timezone": "Asia/Shanghai",
    "iso:country": "CN",
    "name:und_x_variant": [
      "T’ang-chi-ling",
      "Tangjiling"
    ],
    "name:zho_x_preferred": [
      "塘基岭"
    ],
    "wof:name": "Tangjiling",
    "wof:placetype": "locality"
  },
  "geometry": {
    "coordinates": [
      112.98686,
      23.52211
    ],
    "type": "Point"
  }
}