{
  "type": "Feature",
  "properties": {
    "gn:admin1_code": "30.0",
    "gn:asciiname": "Xiaodao",
    "gn:country_code": "CN",
    "gn:dem": 8,
    "gn:feature_class": "P",
    "gn:feature_code": "PPL",
    "gn:name": "Xiaodao",
    "gn:population": 0,
    "gn:timezone": "Asia/Shanghai",
    "iso:country": "CN",
    "name:zho_x_preferred": [
      "小道"
    ],
    "wof:name": "Xiaodao",
    "wof:placetype": "locality"
  },
  "geometry": {
    "coordinates": [
      112.85456,
      22.03076
    ],
    "type": "Point"
  }
}