{
  "type": "Feature",
  "properties": {
    "gn:admin1_code": "18",
    "gn:asciiname": "Gugu",
    "gn:country_code": "CN",
    "gn:dem": 1339,
    "gn:feature_class": "P",
    "gn:feature_code": "PPL",
    "gn:name": "Gugu",
    "gn:population": 0,
    "gn:timezone": "Asia/Shanghai",
    "iso:country": "CN",
    "name:ara_x_preferred": [
      "جوجو"
    ],
    "name:ben_x_preferred": [
      "গুগু"
    ],
    "name:ceb_x_preferred": [
      "Gugu"
    ],
    "name:deu_x_preferred": [
      "Berg Gugu"
    ],
    "name:deu_x_variant": [
      "Gugu"
    ],
    "name:ell_x_preferred": [
      "Γκούγκου"
    ],
    "name:eng_x_preferred": [
      "Gugu"
    ],
    "name:fas_x_preferred": [
      "گوگو"
    ],
    "name:fra_x_preferred": [
      "Gugu"
    ],
    "name:heb_x_preferred": [
      "גוגו"
    ],
    "name:hin_x_preferred": [
      "गुगु"
    ],
    "name:hun_x_preferred": [
      "Gugu"
    ],
    "name:ind_x_preferred": [
      "Gugu"
    ],
    "name:ita_x_preferred": [
      "Gugu"
    ],
    "name:jpn_x_preferred": [
      "ググ山"
    ],
    "name:kor_x_preferred": [
      "구구"
    ],
    "name:pol_x_preferred": [
      "Gugu"
    ],
    "name:por_x_preferred": [
      "Gugu"
    ],
    "name:rus_x_preferred": [
      "гора Гугу"
    ],
    "name:spa_x_preferred": [
      "Gugu"
    ],
    "name:swe_x_preferred": [
      "Gugu"
    ],
    "name:tur_x_preferred": [
      "Gugu"
    ],
    "name:ukr_x_preferred": [
      "Гугу"
    ],
    "name:urd_x_preferred": [
      "گوگو"
    ],
    "name:vie_x_preferred": [
      "Núi Gugu"
    ],
    "name:zho_cn_x_preferred": [
      "古古山"
    ],
    "name:zho_tw_x_preferred": [
      "古固山"
    ],
    "name:zho_x_preferred": [
      "故古"
    ],
    "wof:name": "Gugu",
    "wof:placetype": "locality"
  },
  "geometry": {
    "coordinates": [
      104.959,
      25.2231
    ],
    "type": "Point"
  }
}