{
  "type": "Feature",
  "properties": {
    "gn:admin1_code": "11.0",
    "gn:admin2_code": "1795852",
    "gn:admin3_code": "1791269.0",
    "gn:asciiname": "Wugang",
    "gn:country_code": "CN",
    "gn:dem": 319,
    "gn:feature_class": "P",
    "gn:feature_code": "PPL",
    "gn:name": "Wugang",
    "gn:population": 0,
    "gn:timezone": "Asia/Shanghai",
    "iso:country": "CN",
    "name:deu_x_preferred": [
      "Wugang"
    ],
    "name:eng_x_preferred": [
      "Wugang"
    ],
    "name:fra_x_preferred": [
      "Wugang"
    ],
    "name:ita_x_preferred": [
      "Wugang"
    ],
    "name:jpn_x_preferred": [
      "武岡市"
    ],
    "name:kik_x_preferred": [
      "Wugang"
    ],
    "name:kor_x_preferred": [
      "우강시"
    ],
    "name:nor_x_preferred": [
      "Wugang"
    ],
    "name:pam_x_preferred": [
      "Wugang"
    ],
    "name:swe_x_preferred": [
      "Wugang"
    ],
    "name:und_x_variant": [
      "Ugan",
      "Wu-kang-hsien-ch’eng",
      "Wukangchow",
      "Wu-kang-hsien",
      "Wu-kang"
    ],
    "name:vie_x_preferred": [
      "Vũ Cương"
    ],
    "name:war_x_preferred": [
      "Wugang"
    ],
    "name:zho_x_preferred": [
      "武冈市"
    ],
    "wof:name": "Wugang",
    "wof:placetype": "locality"
  },
  "geometry": {
    "coordinates": [
      110.63198,
      26.7279
    ],
    "type": "Point"
  }
}