{
  "type": "Feature",
  "properties": {
    "gn:admin1_code": "33.0",
    "gn:asciiname": "Taiyang",
    "gn:country_code": "CN",
    "gn:dem": 1109,
    "gn:feature_class": "P",
    "gn:feature_code": "PPLA4",
    "gn:name": "Taiyang",
    "gn:population": 0,
    "gn:timezone": "Asia/Shanghai",
    "iso:country": "CN",
    "name:und_x_variant": [
      "Taiyang Xiang",
      "Ranfang Wuji"
    ],
    "name:zho_x_preferred": [
      "太阳"
    ],
    "name:zho_x_variant": [
      "太阳乡",
      "染房屋基"
    ],
    "wof:name": "Taiyang",
    "wof:placetype": "locality"
  },
  "geometry": {
    "coordinates": [
      109.01017,
      31.16345
    ],
    "type": "Point"
  }
}