{
  "type": "Feature",
  "properties": {
    "gn:admin1_code": "13.0",
    "gn:asciiname": "Yengiawat",
    "gn:country_code": "CN",
    "gn:dem": 1310,
    "gn:feature_class": "P",
    "gn:feature_code": "PPLA4",
    "gn:name": "Yengiawat",
    "gn:population": 0,
    "gn:timezone": "Asia/Shanghai",
    "iso:country": "CN",
    "name:uig_x_preferred": [
      "Yéngiawat"
    ],
    "name:uig_x_variant": [
      "يېڭىئاۋات",
      "Еңиават"
    ],
    "name:und_x_variant": [
      "Ying’awati",
      "Ying’awati Xiang"
    ],
    "name:zho_x_preferred": [
      "英阿瓦提"
    ],
    "name:zho_x_variant": [
      "英阿瓦提乡"
    ],
    "wof:name": "Yengiawat",
    "wof:placetype": "locality"
  },
  "geometry": {
    "coordinates": [
      79.46861,
      41.3525
    ],
    "type": "Point"
  }
}