{
  "type": "Feature",
  "properties": {
    "gn:admin1_code": "32.0",
    "gn:asciiname": "Wu'an",
    "gn:country_code": "CN",
    "gn:dem": 613,
    "gn:feature_class": "P",
    "gn:feature_code": "PPL",
    "gn:name": "Wu’an",
    "gn:population": 0,
    "gn:timezone": "Asia/Shanghai",
    "iso:country": "CN",
    "name:ara_x_preferred": [
      "ووان"
    ],
    "name:deu_x_preferred": [
      "Wu’an"
    ],
    "name:fra_x_preferred": [
      "Wu'an"
    ],
    "name:ita_x_preferred": [
      "Wu'an"
    ],
    "name:jpn_x_preferred": [
      "武安市"
    ],
    "name:kik_x_preferred": [
      "Wu'an"
    ],
    "name:kor_x_preferred": [
      "우안시"
    ],
    "name:nor_x_preferred": [
      "Wu'an"
    ],
    "name:pam_x_preferred": [
      "Wu'an"
    ],
    "name:rus_x_preferred": [
      "Уань"
    ],
    "name:swe_x_preferred": [
      "Wu'an"
    ],
    "name:urd_x_preferred": [
      "ووآن"
    ],
    "name:vie_x_preferred": [
      "Vũ An"
    ],
    "name:war_x_preferred": [
      "Wu'an"
    ],
    "name:zho_x_preferred": [
      "武庵"
    ],
    "name:zho_x_variant": [
      "武安市"
    ],
    "wof:name": "Wu'an",
    "wof:placetype": "locality"
  },
  "geometry": {
    "coordinates": [
      105.253,
      31.7978
    ],
    "type": "Point"
  }
}