{
  "type": "Feature",
  "properties": {
    "gn:admin1_code": "9",
    "gn:asciiname": "Xihejiao",
    "gn:country_code": "CN",
    "gn:dem": 83,
    "gn:feature_class": "P",
    "gn:feature_code": "PPL",
    "gn:name": "Xihejiao",
    "gn:population": 0,
    "gn:timezone": "Asia/Shanghai",
    "iso:country": "CN",
    "name:zho_x_preferred": [
      "西合角"
    ],
    "wof:name": "Xihejiao",
    "wof:placetype": "locality"
  },
  "geometry": {
    "coordinates": [
      113.85766,
      35.02081
    ],
    "type": "Point"
  }
}