{
  "type": "Feature",
  "properties": {
    "gn:admin1_code": "07",
    "gn:asciiname": "Gekeng",
    "gn:country_code": "CN",
    "gn:dem": 872,
    "gn:feature_class": "P",
    "gn:feature_code": "PPLA4",
    "gn:name": "Gekeng",
    "gn:population": 0,
    "gn:timezone": "Asia/Shanghai",
    "iso:country": "CN",
    "name:und_x_variant": [
      "Ko-k’eng",
      "Gekeng",
      "Gekeng Zhen",
      "Gekeng Xiang"
    ],
    "name:zho_x_preferred": [
      "葛坑"
    ],
    "name:zho_x_variant": [
      "葛坑镇",
      "葛坑乡"
    ],
    "wof:name": "Gekeng",
    "wof:placetype": "locality"
  },
  "geometry": {
    "coordinates": [
      118.20123999999998,
      25.84713
    ],
    "type": "Point"
  }
}