{
  "type": "Feature",
  "properties": {
    "gn:admin1_code": "19.0",
    "gn:asciiname": "Chujiajie",
    "gn:country_code": "CN",
    "gn:dem": 114,
    "gn:feature_class": "P",
    "gn:feature_code": "PPL",
    "gn:name": "Chujiajie",
    "gn:population": 0,
    "gn:timezone": "Asia/Shanghai",
    "iso:country": "CN",
    "name:zho_x_preferred": [
      "初家街"
    ],
    "wof:name": "Chujiajie",
    "wof:placetype": "locality"
  },
  "geometry": {
    "coordinates": [
      123.784,
      43.4776
    ],
    "type": "Point"
  }
}