{
  "type": "Feature",
  "properties": {
    "iso:country": "CN",
    "name:ceb_x_preferred": [
      "Chenghai Qu"
    ],
    "name:cym_x_preferred": [
      "Ardal Chenghai"
    ],
    "name:deu_x_preferred": [
      "Chenghai"
    ],
    "name:eng_x_preferred": [
      "Chenghai District"
    ],
    "name:fas_x_preferred": [
      "چنگهای"
    ],
    "name:gan_x_preferred": [
      "澄海区"
    ],
    "name:hak_x_preferred": [
      "Tshîn-hói-khî"
    ],
    "name:jpn_x_preferred": [
      "澄海区"
    ],
    "name:kor_x_preferred": [
      "청하이구"
    ],
    "name:mwl_x_preferred": [
      "Chenghai"
    ],
    "name:nan_x_preferred": [
      "Têng-hái-khu"
    ],
    "name:nld_x_preferred": [
      "Chenghai"
    ],
    "name:nob_x_preferred": [
      "Chenghai"
    ],
    "name:swe_x_preferred": [
      "Chenghai"
    ],
    "name:vie_x_preferred": [
      "Trừng Hải"
    ],
    "name:wuu_x_preferred": [
      "澄海区"
    ],
    "name:yue_x_preferred": [
      "澄海"
    ],
    "name:zho_x_preferred": [
      "澄海区"
    ],
    "qs:name": "澄海",
    "qs:name_adm0": "中國",
    "qs:name_adm1": "广东省",
    "qs:photos": 187,
    "qs:photos_1k": 38,
    "qs:photos_9k": 1,
    "qs:photos_9r": 4,
    "qs:photos_all": 187,
    "qs:photos_sr": 4,
    "qs:placetype": "Town",
    "qs:pop_sr": "0",
    "wd:wordcount": 1586,
    "wof:name": "澄海",
    "wof:placetype": "locality"
  },
  "geometry": {
    "coordinates": [
      116.764755,
      23.471906
    ],
    "type": "Point"
  }
}