{
  "type": "Feature",
  "properties": {
    "gn:admin1_code": "9.0",
    "gn:asciiname": "Zhuquan",
    "gn:country_code": "CN",
    "gn:dem": 298,
    "gn:feature_class": "P",
    "gn:feature_code": "PPL",
    "gn:name": "Zhuquan",
    "gn:population": 0,
    "gn:timezone": "Asia/Shanghai",
    "iso:country": "CN",
    "name:zho_x_preferred": [
      "竹泉"
    ],
    "name:zho_x_variant": [
      "珠泉镇"
    ],
    "wof:name": "Zhuquan",
    "wof:placetype": "locality"
  },
  "geometry": {
    "coordinates": [
      112.17159,
      35.11107
    ],
    "type": "Point"
  }
}