{
  "type": "Feature",
  "properties": {
    "gn:admin1_code": "12.0",
    "gn:asciiname": "Zhangdongtai",
    "gn:country_code": "CN",
    "gn:dem": 33,
    "gn:feature_class": "P",
    "gn:feature_code": "PPL",
    "gn:name": "Zhangdongtai",
    "gn:population": 0,
    "gn:timezone": "Asia/Shanghai",
    "iso:country": "CN",
    "name:zho_x_preferred": [
      "张董台"
    ],
    "wof:name": "Zhangdongtai",
    "wof:placetype": "locality"
  },
  "geometry": {
    "coordinates": [
      112.75916,
      30.62637
    ],
    "type": "Point"
  }
}