{
  "type": "Feature",
  "properties": {
    "gn:admin1_code": "11.0",
    "gn:asciiname": "Xiaolong",
    "gn:country_code": "CN",
    "gn:dem": 509,
    "gn:feature_class": "P",
    "gn:feature_code": "PPL",
    "gn:name": "Xiaolong",
    "gn:population": 0,
    "gn:timezone": "Asia/Shanghai",
    "iso:country": "CN",
    "name:zho_x_preferred": [
      "小垄"
    ],
    "wof:name": "Xiaolong",
    "wof:placetype": "locality"
  },
  "geometry": {
    "coordinates": [
      109.37256,
      27.82882
    ],
    "type": "Point"
  }
}