{
  "type": "Feature",
  "properties": {
    "gn:admin1_code": "7",
    "gn:asciiname": "Gaozhou",
    "gn:country_code": "CN",
    "gn:dem": 457,
    "gn:feature_class": "P",
    "gn:feature_code": "PPL",
    "gn:name": "Gaozhou",
    "gn:population": 0,
    "gn:timezone": "Asia/Shanghai",
    "iso:country": "CN",
    "name:ara_x_preferred": [
      "غاوزو"
    ],
    "name:ceb_x_preferred": [
      "Gaozhou"
    ],
    "name:deu_x_preferred": [
      "Gaozhou"
    ],
    "name:fas_x_preferred": [
      "گاوژو"
    ],
    "name:fra_x_preferred": [
      "Gaozhou"
    ],
    "name:hak_x_preferred": [
      "Kô-chû-sṳ"
    ],
    "name:ita_x_preferred": [
      "Gaozhou"
    ],
    "name:jpn_x_preferred": [
      "高州市"
    ],
    "name:kik_x_preferred": [
      "Gaozhou"
    ],
    "name:kor_x_preferred": [
      "가오저우시"
    ],
    "name:mlg_x_preferred": [
      "Gaozhou"
    ],
    "name:mwl_x_preferred": [
      "Gaozhou"
    ],
    "name:nld_x_preferred": [
      "Gaozhou"
    ],
    "name:nor_x_preferred": [
      "Gaozhou"
    ],
    "name:pam_x_preferred": [
      "Gaozhou"
    ],
    "name:pnb_x_preferred": [
      "گاؤژوؤ"
    ],
    "name:swe_x_preferred": [
      "Gaozhou"
    ],
    "name:urd_x_preferred": [
      "گاوژوو"
    ],
    "name:vie_x_preferred": [
      "Cao Châu"
    ],
    "name:zho_x_preferred": [
      "高州市"
    ],
    "wof:name": "Gaozhou",
    "wof:placetype": "locality"
  },
  "geometry": {
    "coordinates": [
      117.78111,
      25.63111
    ],
    "type": "Point"
  }
}