{
  "type": "Feature",
  "properties": {
    "gn:admin1_code": "5.0",
    "gn:asciiname": "Dalidian",
    "gn:country_code": "CN",
    "gn:dem": 229,
    "gn:feature_class": "P",
    "gn:feature_code": "PPL",
    "gn:name": "Dalidian",
    "gn:population": 0,
    "gn:timezone": "Asia/Shanghai",
    "iso:country": "CN",
    "name:zho_x_preferred": [
      "大李店"
    ],
    "wof:name": "Dalidian",
    "wof:placetype": "locality"
  },
  "geometry": {
    "coordinates": [
      124.92754,
      43.05549
    ],
    "type": "Point"
  }
}