{
  "type": "Feature",
  "properties": {
    "gn:admin1_code": "8.0",
    "gn:asciiname": "Shangjia Youfang",
    "gn:country_code": "CN",
    "gn:dem": 150,
    "gn:feature_class": "P",
    "gn:feature_code": "PPL",
    "gn:name": "Shangjia Youfang",
    "gn:population": 0,
    "gn:timezone": "Asia/Shanghai",
    "iso:country": "CN",
    "name:zho_x_preferred": [
      "商家油房"
    ],
    "wof:name": "Shangjia Youfang",
    "wof:placetype": "locality"
  },
  "geometry": {
    "coordinates": [
      127.32727,
      46.26711
    ],
    "type": "Point"
  }
}