{
  "type": "Feature",
  "properties": {
    "gn:admin1_code": "11.0",
    "gn:asciiname": "Fenshui'ao",
    "gn:country_code": "CN",
    "gn:dem": 389,
    "gn:feature_class": "P",
    "gn:feature_code": "PPL",
    "gn:name": "Fenshui’ao",
    "gn:population": 0,
    "gn:timezone": "Asia/Shanghai",
    "iso:country": "CN",
    "name:und_x_variant": [
      "Fenshui’ao"
    ],
    "name:zho_x_preferred": [
      "分水坳"
    ],
    "wof:name": "Fenshui'ao",
    "wof:placetype": "locality"
  },
  "geometry": {
    "coordinates": [
      109.7316,
      26.24068
    ],
    "type": "Point"
  }
}