{
  "type": "Feature",
  "properties": {
    "gn:admin1_code": "20.0",
    "gn:asciiname": "Saihannao'er Gacha",
    "gn:country_code": "CN",
    "gn:dem": 934,
    "gn:feature_class": "P",
    "gn:feature_code": "PPL",
    "gn:name": "Saihannao’er Gacha",
    "gn:population": 0,
    "gn:timezone": "Asia/Shanghai",
    "iso:country": "CN",
    "name:und_x_variant": [
      "Saihannao’er Gacha"
    ],
    "name:zho_x_preferred": [
      "赛罕淖尔嘎查"
    ],
    "wof:name": "Saihannao'er Gacha",
    "wof:placetype": "locality"
  },
  "geometry": {
    "coordinates": [
      100.84085,
      42.12832
    ],
    "type": "Point"
  }
}