{
  "type": "Feature",
  "properties": {
    "gn:admin1_code": "19.0",
    "gn:asciiname": "Dongxiaofang Shencun",
    "gn:country_code": "CN",
    "gn:dem": 119,
    "gn:feature_class": "P",
    "gn:feature_code": "PPL",
    "gn:name": "Dongxiaofang Shencun",
    "gn:population": 0,
    "gn:timezone": "Asia/Shanghai",
    "iso:country": "CN",
    "name:und_x_variant": [
      "Dongxiaofangshencun",
      "Dongxiaofang Shencun"
    ],
    "name:zho_x_preferred": [
      "东小房身村"
    ],
    "wof:name": "Dongxiaofang Shencun",
    "wof:placetype": "locality"
  },
  "geometry": {
    "coordinates": [
      123.28153,
      42.62205
    ],
    "type": "Point"
  }
}