{
  "type": "Feature",
  "properties": {
    "gn:admin1_code": "9",
    "gn:asciiname": "Beilijia",
    "gn:country_code": "CN",
    "gn:dem": 51,
    "gn:feature_class": "P",
    "gn:feature_code": "PPL",
    "gn:name": "Beilijia",
    "gn:population": 0,
    "gn:timezone": "Asia/Shanghai",
    "iso:country": "CN",
    "name:zho_x_preferred": [
      "北李家"
    ],
    "wof:name": "Beilijia",
    "wof:placetype": "locality"
  },
  "geometry": {
    "coordinates": [
      115.15614,
      35.97839000000001
    ],
    "type": "Point"
  }
}