{
  "type": "Feature",
  "properties": {
    "gn:admin1_code": "11.0",
    "gn:asciiname": "Jiejiawan",
    "gn:country_code": "CN",
    "gn:dem": 877,
    "gn:feature_class": "P",
    "gn:feature_code": "PPL",
    "gn:name": "Jiejiawan",
    "gn:population": 0,
    "gn:timezone": "Asia/Shanghai",
    "iso:country": "CN",
    "name:zho_x_preferred": [
      "揭家弯"
    ],
    "wof:name": "Jiejiawan",
    "wof:placetype": "locality"
  },
  "geometry": {
    "coordinates": [
      110.57752,
      29.43946
    ],
    "type": "Point"
  }
}