{
  "type": "Feature",
  "properties": {
    "gn:admin1_code": "11.0",
    "gn:asciiname": "Yangyahu",
    "gn:country_code": "CN",
    "gn:dem": 110,
    "gn:feature_class": "P",
    "gn:feature_code": "PPL",
    "gn:name": "Yangyahu",
    "gn:population": 0,
    "gn:timezone": "Asia/Shanghai",
    "iso:country": "CN",
    "name:zho_x_preferred": [
      "洋鸭湖"
    ],
    "wof:name": "Yangyahu",
    "wof:placetype": "locality"
  },
  "geometry": {
    "coordinates": [
      113.20463,
      27.04048
    ],
    "type": "Point"
  }
}