{
  "type": "Feature",
  "properties": {
    "gn:admin1_code": "5.0",
    "gn:asciiname": "Baizigoutun",
    "gn:country_code": "CN",
    "gn:dem": 325,
    "gn:feature_class": "P",
    "gn:feature_code": "PPL",
    "gn:name": "Baizigoutun",
    "gn:population": 0,
    "gn:timezone": "Asia/Shanghai",
    "iso:country": "CN",
    "name:und_x_variant": [
      "稗子沟屯"
    ],
    "wof:name": "Baizigoutun",
    "wof:placetype": "locality"
  },
  "geometry": {
    "coordinates": [
      126.96556,
      43.02185
    ],
    "type": "Point"
  }
}