{
  "type": "Feature",
  "properties": {
    "gn:admin1_code": "16.0",
    "gn:asciiname": "Nonglang",
    "gn:country_code": "CN",
    "gn:dem": 360,
    "gn:feature_class": "P",
    "gn:feature_code": "PPL",
    "gn:name": "Nonglang",
    "gn:population": 0,
    "gn:timezone": "Asia/Shanghai",
    "iso:country": "CN",
    "name:zho_x_preferred": [
      "弄浪"
    ],
    "wof:name": "Nonglang",
    "wof:placetype": "locality"
  },
  "geometry": {
    "coordinates": [
      107.945,
      23.7328
    ],
    "type": "Point"
  }
}