{
  "type": "Feature",
  "properties": {
    "gn:country": "CN",
    "gn:fcode": "PPL",
    "gn:population": 166507,
    "iso:country": "CN",
    "name:ceb_x_preferred": [
      "Fuling Qu"
    ],
    "name:cym_x_preferred": [
      "Ardal Fuling"
    ],
    "name:deu_x_preferred": [
      "Fuling"
    ],
    "name:eng_x_preferred": [
      "Fuling District"
    ],
    "name:eus_x_preferred": [
      "Fuling Barrutia"
    ],
    "name:fas_x_preferred": [
      "فیولینگ"
    ],
    "name:gan_x_preferred": [
      "涪陵区"
    ],
    "name:ind_x_preferred": [
      "Fuling"
    ],
    "name:jpn_x_preferred": [
      "フ陵区"
    ],
    "name:kor_x_preferred": [
      "푸링구"
    ],
    "name:mwl_x_preferred": [
      "Fuling"
    ],
    "name:nan_x_preferred": [
      "Hô͘-lêng-khu"
    ],
    "name:nld_x_preferred": [
      "Fuling District"
    ],
    "name:nob_x_preferred": [
      "Fuling"
    ],
    "name:rus_x_preferred": [
      "Фулин"
    ],
    "name:spa_x_preferred": [
      "Fuling"
    ],
    "name:swe_x_preferred": [
      "Fuling"
    ],
    "name:tur_x_preferred": [
      "Fuling"
    ],
    "name:und_x_variant": [
      "Pei-ling"
    ],
    "name:vie_x_preferred": [
      "Phù Lăng"
    ],
    "name:war_x_preferred": [
      "Fuling"
    ],
    "name:wuu_x_preferred": [
      "涪陵区"
    ],
    "name:yue_x_preferred": [
      "涪陵"
    ],
    "name:zho_x_preferred": [
      "涪陵"
    ],
    "name:zho_x_variant": [
      "涪陵區"
    ],
    "qs:name": "涪陵",
    "qs:name_adm0": "中國",
    "qs:name_adm1": "重庆直辖市",
    "qs:photos": 244,
    "qs:photos_1k": 49,
    "qs:photos_9k": 1,
    "qs:photos_9r": 4,
    "qs:photos_all": 244,
    "qs:photos_sr": 4,
    "qs:placetype": "Town",
    "qs:pop_sr": "9",
    "wd:wordcount": 1195,
    "wof:name": "涪陵",
    "wof:placetype": "locality",
    "wof:population": 166507
  },
  "geometry": {
    "coordinates": [
      107.39575,
      29.706
    ],
    "type": "Point"
  }
}