{
  "type": "Feature",
  "properties": {
    "gn:admin1_code": "16",
    "gn:asciiname": "Pingle",
    "gn:country_code": "CN",
    "gn:dem": 102,
    "gn:feature_class": "P",
    "gn:feature_code": "PPLA3",
    "gn:name": "Pingle",
    "gn:population": 0,
    "gn:timezone": "Asia/Shanghai",
    "iso:country": "CN",
    "name:deu_x_preferred": [
      "Pingle"
    ],
    "name:fas_x_preferred": [
      "شهرستان پینگله"
    ],
    "name:hak_x_preferred": [
      "Phìn-lo̍k-yen"
    ],
    "name:jpn_x_preferred": [
      "平楽県"
    ],
    "name:kor_x_preferred": [
      "핑러현"
    ],
    "name:nor_x_preferred": [
      "Pingle"
    ],
    "name:swe_x_preferred": [
      "Pingle"
    ],
    "name:vie_x_preferred": [
      "Bình Lạc"
    ],
    "name:zho_x_preferred": [
      "Chiu-p’ing-lo"
    ],
    "name:zho_x_variant": [
      "P’ing-lo-hsien",
      "P’ing-lo",
      "P’ing-lo-chen",
      "平乐",
      "平乐县"
    ],
    "wof:name": "Pingle",
    "wof:placetype": "locality"
  },
  "geometry": {
    "coordinates": [
      110.64306,
      24.64522
    ],
    "type": "Point"
  }
}