{
  "type": "Feature",
  "properties": {
    "gn:admin1_code": "14.0",
    "gn:asciiname": "Jiru",
    "gn:country_code": "CN",
    "gn:dem": 4606,
    "gn:feature_class": "P",
    "gn:feature_code": "PPLA4",
    "gn:name": "Jiru",
    "gn:population": 0,
    "gn:timezone": "Asia/Urumqi",
    "iso:country": "CN",
    "name:bod_x_preferred": [
      "Gyêru"
    ],
    "name:und_x_variant": [
      "Jiru Xiang"
    ],
    "name:zho_x_preferred": [
      "Jiru"
    ],
    "name:zho_x_variant": [
      "吉汝",
      "吉汝乡"
    ],
    "wof:name": "Jiru",
    "wof:placetype": "locality"
  },
  "geometry": {
    "coordinates": [
      89.04859,
      28.17834
    ],
    "type": "Point"
  }
}