{
  "type": "Feature",
  "properties": {
    "gn:admin1_code": "19.0",
    "gn:asciiname": "Kangjiagou",
    "gn:country_code": "CN",
    "gn:dem": 202,
    "gn:feature_class": "P",
    "gn:feature_code": "PPL",
    "gn:name": "Kangjiagou",
    "gn:population": 0,
    "gn:timezone": "Asia/Shanghai",
    "iso:country": "CN",
    "name:zho_x_preferred": [
      "康家沟"
    ],
    "wof:name": "Kangjiagou",
    "wof:placetype": "locality"
  },
  "geometry": {
    "coordinates": [
      122.697,
      39.9851
    ],
    "type": "Point"
  }
}