{
  "type": "Feature",
  "properties": {
    "gn:admin1_code": "30",
    "gn:asciiname": "Xincun",
    "gn:country_code": "CN",
    "gn:dem": 28,
    "gn:feature_class": "P",
    "gn:feature_code": "PPL",
    "gn:name": "Xincun",
    "gn:population": 0,
    "gn:timezone": "Asia/Shanghai",
    "iso:country": "CN",
    "name:ceb_x_preferred": [
      "Xincun"
    ],
    "name:deu_x_preferred": [
      "Xincun"
    ],
    "name:swe_x_preferred": [
      "Xincun"
    ],
    "name:zho_x_preferred": [
      "新村"
    ],
    "wof:name": "Xincun",
    "wof:placetype": "locality"
  },
  "geometry": {
    "coordinates": [
      116.48563,
      23.90671
    ],
    "type": "Point"
  }
}