{
  "type": "Feature",
  "properties": {
    "gn:admin1_code": "10",
    "gn:asciiname": "Yuliangzi Nangou",
    "gn:country_code": "CN",
    "gn:dem": 818,
    "gn:feature_class": "P",
    "gn:feature_code": "PPL",
    "gn:name": "Yuliangzi Nangou",
    "gn:population": 0,
    "gn:timezone": "Asia/Shanghai",
    "iso:country": "CN",
    "name:zho_x_preferred": [
      "鱼亮子南沟"
    ],
    "wof:name": "Yuliangzi Nangou",
    "wof:placetype": "locality"
  },
  "geometry": {
    "coordinates": [
      117.18637,
      41.52522
    ],
    "type": "Point"
  }
}