{
  "type": "Feature",
  "properties": {
    "gn:admin1_code": "2.0",
    "gn:asciiname": "Xiaoxizhuang",
    "gn:country_code": "CN",
    "gn:dem": 13,
    "gn:feature_class": "P",
    "gn:feature_code": "PPL",
    "gn:name": "Xiaoxizhuang",
    "gn:population": 0,
    "gn:timezone": "Asia/Shanghai",
    "iso:country": "CN",
    "name:und_x_variant": [
      "小西庄"
    ],
    "wof:name": "Xiaoxizhuang",
    "wof:placetype": "locality"
  },
  "geometry": {
    "coordinates": [
      120.48612,
      30.15747
    ],
    "type": "Point"
  }
}