{
  "type": "Feature",
  "properties": {
    "gn:admin1_code": "29",
    "gn:asciiname": "Jiudu",
    "gn:country_code": "CN",
    "gn:dem": 1853,
    "gn:feature_class": "P",
    "gn:feature_code": "PPL",
    "gn:name": "Jiudu",
    "gn:population": 0,
    "gn:timezone": "Asia/Shanghai",
    "iso:country": "CN",
    "name:zho_x_preferred": [
      "九度"
    ],
    "wof:name": "Jiudu",
    "wof:placetype": "locality"
  },
  "geometry": {
    "coordinates": [
      102.305,
      24.8987
    ],
    "type": "Point"
  }
}