{
  "type": "Feature",
  "properties": {
    "gn:admin1_code": "19.0",
    "gn:asciiname": "Hugujiazi",
    "gn:country_code": "CN",
    "gn:dem": 49,
    "gn:feature_class": "P",
    "gn:feature_code": "PPL",
    "gn:name": "Hugujiazi",
    "gn:population": 0,
    "gn:timezone": "Asia/Shanghai",
    "iso:country": "CN",
    "name:zho_x_preferred": [
      "胡古家子"
    ],
    "wof:name": "Hugujiazi",
    "wof:placetype": "locality"
  },
  "geometry": {
    "coordinates": [
      123.44444,
      41.52845
    ],
    "type": "Point"
  }
}