{
  "type": "Feature",
  "properties": {
    "gn:admin1_code": "8.0",
    "gn:asciiname": "Gongyi",
    "gn:country_code": "CN",
    "gn:dem": 165,
    "gn:feature_class": "P",
    "gn:feature_code": "PPL",
    "gn:name": "Gongyi",
    "gn:population": 0,
    "gn:timezone": "Asia/Shanghai",
    "iso:country": "CN",
    "name:ara_x_preferred": [
      "غونغيي"
    ],
    "name:deu_x_preferred": [
      "Gongyi"
    ],
    "name:eus_x_preferred": [
      "Gongyi"
    ],
    "name:fra_x_preferred": [
      "Gongyi"
    ],
    "name:ita_x_preferred": [
      "Gongyi"
    ],
    "name:jpn_x_preferred": [
      "鞏義市"
    ],
    "name:kik_x_preferred": [
      "Gongyi"
    ],
    "name:kor_x_preferred": [
      "궁이시"
    ],
    "name:nor_x_preferred": [
      "Gongyi"
    ],
    "name:pam_x_preferred": [
      "Gongyi"
    ],
    "name:rus_x_preferred": [
      "Гунъи"
    ],
    "name:swe_x_preferred": [
      "Gongyi"
    ],
    "name:ukr_x_preferred": [
      "Ґун'ї"
    ],
    "name:urd_x_preferred": [
      "گونگیی"
    ],
    "name:vie_x_preferred": [
      "Củng Nghĩa"
    ],
    "name:zho_x_preferred": [
      "公议"
    ],
    "name:zho_x_variant": [
      "巩义市"
    ],
    "wof:name": "Gongyi",
    "wof:placetype": "locality"
  },
  "geometry": {
    "coordinates": [
      124.14871,
      47.92361
    ],
    "type": "Point"
  }
}