{
  "type": "Feature",
  "properties": {
    "gn:admin1_code": "8.0",
    "gn:asciiname": "Junchuan Sanshiqidui",
    "gn:country_code": "CN",
    "gn:dem": 67,
    "gn:feature_class": "P",
    "gn:feature_code": "PPLF",
    "gn:name": "Junchuan Sanshiqidui",
    "gn:population": 0,
    "gn:timezone": "Asia/Shanghai",
    "iso:country": "CN",
    "name:zho_x_preferred": [
      "军川三十七队"
    ],
    "wof:name": "Junchuan Sanshiqidui",
    "wof:placetype": "locality"
  },
  "geometry": {
    "coordinates": [
      131.13212,
      47.52239
    ],
    "type": "Point"
  }
}