{
  "type": "Feature",
  "properties": {
    "gn:admin1_code": "32.0",
    "gn:asciiname": "Gongqiaonian",
    "gn:country_code": "CN",
    "gn:dem": 503,
    "gn:feature_class": "P",
    "gn:feature_code": "PPL",
    "gn:name": "Gongqiaonian",
    "gn:population": 0,
    "gn:timezone": "Asia/Shanghai",
    "iso:country": "CN",
    "name:zho_x_preferred": [
      "拱桥碾"
    ],
    "wof:name": "Gongqiaonian",
    "wof:placetype": "locality"
  },
  "geometry": {
    "coordinates": [
      104.15896,
      31.03311
    ],
    "type": "Point"
  }
}