{
  "type": "Feature",
  "properties": {
    "gn:admin1_code": "32.0",
    "gn:asciiname": "Qingshan",
    "gn:country_code": "CN",
    "gn:dem": 1137,
    "gn:feature_class": "P",
    "gn:feature_code": "PPL",
    "gn:name": "Qingshan",
    "gn:population": 0,
    "gn:timezone": "Asia/Shanghai",
    "iso:country": "CN",
    "name:ceb_x_preferred": [
      "Qingshan"
    ],
    "name:deu_x_preferred": [
      "Qingshan"
    ],
    "name:fra_x_preferred": [
      "Qingshan"
    ],
    "name:nor_x_preferred": [
      "Qingshan"
    ],
    "name:rus_x_preferred": [
      "Циншань"
    ],
    "name:swe_x_preferred": [
      "Qingshan"
    ],
    "name:zho_x_preferred": [
      "青山"
    ],
    "wof:name": "Qingshan",
    "wof:placetype": "locality"
  },
  "geometry": {
    "coordinates": [
      105.379,
      32.3356
    ],
    "type": "Point"
  }
}