{
  "type": "Feature",
  "properties": {
    "gn:admin1_code": "6.0",
    "gn:asciiname": "Duocai",
    "gn:country_code": "CN",
    "gn:dem": 4294,
    "gn:feature_class": "P",
    "gn:feature_code": "PPLA4",
    "gn:name": "Duocai",
    "gn:population": 0,
    "gn:timezone": "Asia/Urumqi",
    "iso:country": "CN",
    "name:mon_x_preferred": [
      "Doicê"
    ],
    "name:und_x_variant": [
      "Duocai Xiang",
      "Saimoyong"
    ],
    "name:zho_x_preferred": [
      "多采"
    ],
    "name:zho_x_variant": [
      "多采乡",
      "赛莫涌"
    ],
    "wof:name": "Duocai",
    "wof:placetype": "locality"
  },
  "geometry": {
    "coordinates": [
      95.42127,
      33.81034
    ],
    "type": "Point"
  }
}