{
  "type": "Feature",
  "properties": {
    "gn:admin1_code": "03",
    "gn:asciiname": "Lieqiao",
    "gn:country_code": "CN",
    "gn:dem": 81,
    "gn:feature_class": "P",
    "gn:feature_code": "PPLA4",
    "gn:name": "Lieqiao",
    "gn:population": 0,
    "gn:timezone": "Asia/Shanghai",
    "iso:country": "CN",
    "name:und_x_variant": [
      "Lieh-ch’iao",
      "Lieqiao Xiang",
      "烈桥乡",
      "Lieqiao"
    ],
    "name:zho_x_preferred": [
      "烈桥"
    ],
    "wof:name": "Lieqiao",
    "wof:placetype": "locality"
  },
  "geometry": {
    "coordinates": [
      117.52232,
      28.56377
    ],
    "type": "Point"
  }
}