{
  "type": "Feature",
  "properties": {
    "gn:admin1_code": "14.0",
    "gn:asciiname": "Xiaxicun",
    "gn:country_code": "CN",
    "gn:dem": 4466,
    "gn:feature_class": "P",
    "gn:feature_code": "PPL",
    "gn:name": "Xiaxicun",
    "gn:population": 0,
    "gn:timezone": "Asia/Urumqi",
    "iso:country": "CN",
    "name:zho_x_preferred": [
      "下西村"
    ],
    "wof:name": "Xiaxicun",
    "wof:placetype": "locality"
  },
  "geometry": {
    "coordinates": [
      91.05666,
      28.90905
    ],
    "type": "Point"
  }
}