{
  "type": "Feature",
  "properties": {
    "gn:admin1_code": "14.0",
    "gn:asciiname": "Kailahor",
    "gn:country_code": "CN",
    "gn:dem": 3934,
    "gn:feature_class": "P",
    "gn:feature_code": "PPLF",
    "gn:name": "Kailahor",
    "gn:population": 0,
    "gn:timezone": "Asia/Urumqi",
    "iso:country": "CN",
    "name:bod_x_preferred": [
      "Kailahor"
    ],
    "name:bod_x_variant": [
      "གད་ལ་ཧོར"
    ],
    "name:zho_x_preferred": [
      "Gelawo"
    ],
    "name:zho_x_variant": [
      "格拉沃",
      "格老窝",
      "格荖窝",
      "Gelaowo",
      "改拉霍",
      "Gailahuo"
    ],
    "wof:name": "Kailahor",
    "wof:placetype": "locality"
  },
  "geometry": {
    "coordinates": [
      91.75841,
      30.07998
    ],
    "type": "Point"
  }
}