{
  "type": "Feature",
  "properties": {
    "gn:admin1_code": "7",
    "gn:asciiname": "Chihu",
    "gn:country_code": "CN",
    "gn:dem": 25,
    "gn:feature_class": "P",
    "gn:feature_code": "PPL",
    "gn:name": "Chihu",
    "gn:population": 0,
    "gn:timezone": "Asia/Shanghai",
    "iso:country": "CN",
    "name:und_x_variant": [
      "Ch’ih-hu",
      "Chihu"
    ],
    "name:zho_x_preferred": [
      "赤湖"
    ],
    "wof:name": "Chihu",
    "wof:placetype": "locality"
  },
  "geometry": {
    "coordinates": [
      118.89958,
      24.92164
    ],
    "type": "Point"
  }
}