{
  "type": "Feature",
  "properties": {
    "gn:admin1_code": "19.0",
    "gn:asciiname": "Tazixia",
    "gn:country_code": "CN",
    "gn:dem": 314,
    "gn:feature_class": "P",
    "gn:feature_code": "PPL",
    "gn:name": "Tazixia",
    "gn:population": 0,
    "gn:timezone": "Asia/Shanghai",
    "iso:country": "CN",
    "name:zho_x_preferred": [
      "塔子下"
    ],
    "wof:name": "Tazixia",
    "wof:placetype": "locality"
  },
  "geometry": {
    "coordinates": [
      119.82,
      41.3479
    ],
    "type": "Point"
  }
}