{
  "type": "Feature",
  "properties": {
    "gn:admin1_code": "5.0",
    "gn:asciiname": "Xinlitun",
    "gn:country_code": "CN",
    "gn:dem": 135,
    "gn:feature_class": "P",
    "gn:feature_code": "PPL",
    "gn:name": "Xinlitun",
    "gn:population": 0,
    "gn:timezone": "Asia/Shanghai",
    "iso:country": "CN",
    "name:zho_x_preferred": [
      "新立屯"
    ],
    "name:zho_x_variant": [
      "新立屯镇"
    ],
    "wof:name": "Xinlitun",
    "wof:placetype": "locality"
  },
  "geometry": {
    "coordinates": [
      123.47178999999998,
      45.79172
    ],
    "type": "Point"
  }
}