{
  "type": "Feature",
  "properties": {
    "gn:admin1_code": "12",
    "gn:asciiname": "Libu",
    "gn:country_code": "CN",
    "gn:dem": 33,
    "gn:feature_class": "P",
    "gn:feature_code": "PPLA4",
    "gn:name": "Libu",
    "gn:population": 0,
    "gn:timezone": "Asia/Shanghai",
    "iso:country": "CN",
    "name:ara_x_preferred": [
      "الليبو"
    ],
    "name:bel_x_preferred": [
      "Старажытныя лівійцы"
    ],
    "name:cat_x_preferred": [
      "Libu"
    ],
    "name:dan_x_preferred": [
      "Libu"
    ],
    "name:ell_x_preferred": [
      "Λίμπου"
    ],
    "name:fin_x_preferred": [
      "Libu"
    ],
    "name:fra_x_preferred": [
      "Libou"
    ],
    "name:ita_x_preferred": [
      "Libu"
    ],
    "name:jpn_x_preferred": [
      "リブ"
    ],
    "name:nld_x_preferred": [
      "Liboe"
    ],
    "name:nor_x_preferred": [
      "Libu"
    ],
    "name:spa_x_preferred": [
      "Libu"
    ],
    "name:und_x_variant": [
      "Li-chia-pu",
      "李埠",
      "Libu Zhen",
      "李埠镇"
    ],
    "wof:name": "Libu",
    "wof:placetype": "locality"
  },
  "geometry": {
    "coordinates": [
      112.06667,
      30.32223
    ],
    "type": "Point"
  }
}