{
  "type": "Feature",
  "properties": {
    "gn:admin1_code": "16.0",
    "gn:asciiname": "Xingcheng",
    "gn:country_code": "CN",
    "gn:dem": 115,
    "gn:feature_class": "P",
    "gn:feature_code": "PPL",
    "gn:name": "Xingcheng",
    "gn:population": 0,
    "gn:timezone": "Asia/Shanghai",
    "iso:country": "CN",
    "name:ara_x_preferred": [
      "شينغتشينغ"
    ],
    "name:ceb_x_preferred": [
      "Xingcheng"
    ],
    "name:deu_x_preferred": [
      "Xingcheng"
    ],
    "name:fra_x_preferred": [
      "Xingcheng"
    ],
    "name:ita_x_preferred": [
      "Xingcheng"
    ],
    "name:jpn_x_preferred": [
      "興城市"
    ],
    "name:kik_x_preferred": [
      "Xingcheng"
    ],
    "name:kor_x_preferred": [
      "싱청시"
    ],
    "name:mlg_x_preferred": [
      "Xingcheng"
    ],
    "name:nor_x_preferred": [
      "Xingcheng"
    ],
    "name:rus_x_preferred": [
      "Синчэн"
    ],
    "name:swe_x_preferred": [
      "Xingcheng"
    ],
    "name:urd_x_preferred": [
      "شنگچینگ"
    ],
    "name:vie_x_preferred": [
      "Hưng Thành"
    ],
    "name:war_x_preferred": [
      "Xingcheng"
    ],
    "name:zho_x_preferred": [
      "兴城"
    ],
    "name:zho_x_variant": [
      "兴城市"
    ],
    "wof:name": "Xingcheng",
    "wof:placetype": "locality"
  },
  "geometry": {
    "coordinates": [
      106.887,
      23.7266
    ],
    "type": "Point"
  }
}