{
  "type": "Feature",
  "properties": {
    "iso:country": "CN",
    "name:ara_x_preferred": [
      "مقاطعة كارغيليك"
    ],
    "name:ben_x_preferred": [
      "কারজিলিক কাউন্টি"
    ],
    "name:dan_x_preferred": [
      "Yecheng"
    ],
    "name:deu_x_preferred": [
      "Kargilik"
    ],
    "name:ell_x_preferred": [
      "Κάρτζιλικ"
    ],
    "name:eng_x_preferred": [
      "Kargilik County"
    ],
    "name:fas_x_preferred": [
      "شهرستان کارگیلیک"
    ],
    "name:fin_x_preferred": [
      "Kargilikin kunta"
    ],
    "name:gan_x_preferred": [
      "叶城县"
    ],
    "name:guj_x_preferred": [
      "કારગિલીક કાઉન્ટી"
    ],
    "name:hin_x_preferred": [
      "क़ारग़िलिक ज़िला"
    ],
    "name:ind_x_preferred": [
      "Kargilik County"
    ],
    "name:ita_x_preferred": [
      "Kargilik"
    ],
    "name:jpn_x_preferred": [
      "カルギリク県"
    ],
    "name:kan_x_preferred": [
      "ಕಾರ್ಗಿಲಿಕ್ ಕೌಂಟಿ"
    ],
    "name:kor_x_preferred": [
      "예청현"
    ],
    "name:lav_x_preferred": [
      "Kargiliko apgabals"
    ],
    "name:lit_x_preferred": [
      "Kargiliko sritis"
    ],
    "name:mar_x_preferred": [
      "कारगिलक काउंटी"
    ],
    "name:msa_x_preferred": [
      "Kargilik County"
    ],
    "name:nan_x_preferred": [
      "Kargilik-koān"
    ],
    "name:nld_x_preferred": [
      "Karghilik"
    ],
    "name:nob_x_preferred": [
      "Kargilik"
    ],
    "name:pnb_x_preferred": [
      "قاغیلیق کاؤنٹی"
    ],
    "name:pol_x_preferred": [
      "Yecheng"
    ],
    "name:por_x_preferred": [
      "Kargilik"
    ],
    "name:rus_x_preferred": [
      "Каргалык"
    ],
    "name:sin_x_preferred": [
      "කර්ගිලික් ප්‍රාන්තය"
    ],
    "name:spa_x_preferred": [
      "Kargilik"
    ],
    "name:swe_x_preferred": [
      "Kargilik"
    ],
    "name:tel_x_preferred": [
      "కార్గిలిక్ కౌంటీ"
    ],
    "name:tha_x_preferred": [
      "คากิลิค ครันที่"
    ],
    "name:tur_x_preferred": [
      "Kağılık İlçesi"
    ],
    "name:uig_x_preferred": [
      "قاغىلىق ناھىيىسى"
    ],
    "name:ukr_x_preferred": [
      "Каргілик"
    ],
    "name:urd_x_preferred": [
      "قاغلیق کاؤنٹی"
    ],
    "name:vie_x_preferred": [
      "Kargilik"
    ],
    "name:wuu_x_preferred": [
      "叶城县"
    ],
    "name:zho_x_preferred": [
      "叶城县"
    ],
    "qs:name": "叶城",
    "qs:name_adm0": "中國",
    "qs:name_adm1": "新疆维吾尔自治区",
    "qs:photos": 52,
    "qs:photos_1k": 11,
    "qs:photos_9k": 1,
    "qs:photos_9r": 2,
    "qs:photos_all": 52,
    "qs:photos_sr": 2,
    "qs:placetype": "Town",
    "qs:pop_sr": "0",
    "wd:wordcount": 66,
    "wof:name": "叶城",
    "wof:placetype": "locality"
  },
  "geometry": {
    "coordinates": [
      77.413873,
      37.884258
    ],
    "type": "Point"
  }
}