{
  "type": "Feature",
  "properties": {
    "gn:admin1_code": "10",
    "gn:asciiname": "Douyu",
    "gn:cc2": "CN",
    "gn:country_code": "CN",
    "gn:dem": 66,
    "gn:feature_class": "P",
    "gn:feature_code": "PPL",
    "gn:name": "Douyu",
    "gn:population": 0,
    "gn:timezone": "Asia/Shanghai",
    "iso:country": "CN",
    "name:und_x_variant": [
      "Tou-yü",
      "Tou-yu-ts’un",
      "Tou-yü-chen",
      "Towyü",
      "Douyu"
    ],
    "name:zho_x_preferred": [
      "窦妪镇"
    ],
    "wof:name": "Douyu",
    "wof:placetype": "locality"
  },
  "geometry": {
    "coordinates": [
      114.50083,
      37.89639
    ],
    "type": "Point"
  }
}