{
  "type": "Feature",
  "properties": {
    "gn:admin1_code": "26.0",
    "gn:asciiname": "Guanzhuang",
    "gn:country_code": "CN",
    "gn:dem": 723,
    "gn:feature_class": "P",
    "gn:feature_code": "PPL",
    "gn:name": "Guanzhuang",
    "gn:population": 0,
    "gn:timezone": "Asia/Shanghai",
    "iso:country": "CN",
    "name:ceb_x_preferred": [
      "Guanzhuang"
    ],
    "name:swe_x_preferred": [
      "Guanzhuang"
    ],
    "name:zho_x_preferred": [
      "关庄"
    ],
    "name:zho_x_variant": [
      "官庄镇"
    ],
    "wof:name": "Guanzhuang",
    "wof:placetype": "locality"
  },
  "geometry": {
    "coordinates": [
      110.44467,
      36.32531
    ],
    "type": "Point"
  }
}