{
  "type": "Feature",
  "properties": {
    "gn:admin1_code": "3.0",
    "gn:asciiname": "Zhangzhou",
    "gn:country_code": "CN",
    "gn:dem": 82,
    "gn:feature_class": "P",
    "gn:feature_code": "PPL",
    "gn:name": "Zhangzhou",
    "gn:population": 0,
    "gn:timezone": "Asia/Shanghai",
    "iso:country": "CN",
    "name:afr_x_preferred": [
      "Zhangzhou"
    ],
    "name:ara_x_preferred": [
      "زهانغزهو"
    ],
    "name:bul_x_preferred": [
      "Джанджоу"
    ],
    "name:cdo_x_preferred": [
      "Ciŏng-ciŭ"
    ],
    "name:ceb_x_preferred": [
      "Zhangzhou"
    ],
    "name:ces_x_preferred": [
      "Čang-čou"
    ],
    "name:dan_x_preferred": [
      "Zhangzhou"
    ],
    "name:deu_x_preferred": [
      "Zhangzhou"
    ],
    "name:epo_x_preferred": [
      "Ĝanĝou"
    ],
    "name:est_x_preferred": [
      "Zhangzhou"
    ],
    "name:eus_x_preferred": [
      "Zhangzhou"
    ],
    "name:fas_x_preferred": [
      "جانگجاو"
    ],
    "name:fin_x_preferred": [
      "Zhangzhou"
    ],
    "name:fra_x_preferred": [
      "Zhangzhou"
    ],
    "name:hak_x_preferred": [
      "Chông-chû-sṳ"
    ],
    "name:heb_x_preferred": [
      "ז'נג'ואו"
    ],
    "name:hrv_x_preferred": [
      "Zhangzhou"
    ],
    "name:hun_x_preferred": [
      "Zhangzhou"
    ],
    "name:ind_x_preferred": [
      "Zhangzhou"
    ],
    "name:ita_x_preferred": [
      "Zhangzhou"
    ],
    "name:jpn_x_preferred": [
      "ショウ州市"
    ],
    "name:kik_x_preferred": [
      "Zhangzhou"
    ],
    "name:kor_x_preferred": [
      "장저우시"
    ],
    "name:mlg_x_preferred": [
      "Zhangzhou"
    ],
    "name:nld_x_preferred": [
      "Zhangzhou"
    ],
    "name:nno_x_preferred": [
      "Zhangzhou"
    ],
    "name:nor_x_preferred": [
      "Zhangzhou"
    ],
    "name:pam_x_preferred": [
      "Zhangzhou"
    ],
    "name:pnb_x_preferred": [
      "ژانگژو"
    ],
    "name:pol_x_preferred": [
      "Zhangzhou"
    ],
    "name:por_x_preferred": [
      "Zhangzhou"
    ],
    "name:rus_x_preferred": [
      "Чжанчжоу"
    ],
    "name:sco_x_preferred": [
      "Zhangzhou"
    ],
    "name:spa_x_preferred": [
      "Zhangzhou"
    ],
    "name:srp_x_preferred": [
      "Џангџоу"
    ],
    "name:swe_x_preferred": [
      "Zhangzhou"
    ],
    "name:tgl_x_preferred": [
      "Zhangzhou"
    ],
    "name:tur_x_preferred": [
      "Zhangzhou"
    ],
    "name:uig_x_preferred": [
      "Jyangju shehiri"
    ],
    "name:und_x_variant": [
      "樟洲"
    ],
    "name:urd_x_preferred": [
      "ژانگژو"
    ],
    "name:uzb_x_preferred": [
      "Chjenchjou"
    ],
    "name:vie_x_preferred": [
      "Chương Châu"
    ],
    "name:war_x_preferred": [
      "Zhangzhou"
    ],
    "name:wuu_x_preferred": [
      "漳州市"
    ],
    "name:zho_x_preferred": [
      "漳州市"
    ],
    "wof:name": "Zhangzhou",
    "wof:placetype": "locality"
  },
  "geometry": {
    "coordinates": [
      117.44114,
      29.52653
    ],
    "type": "Point"
  }
}