{
  "type": "Feature",
  "properties": {
    "gn:admin1_code": "4.0",
    "gn:asciiname": "Lintan",
    "gn:country_code": "CN",
    "gn:dem": 2,
    "gn:feature_class": "P",
    "gn:feature_code": "PPL",
    "gn:name": "Lintan",
    "gn:population": 0,
    "gn:timezone": "Asia/Shanghai",
    "iso:country": "CN",
    "name:und_x_variant": [
      "林潭"
    ],
    "wof:name": "Lintan",
    "wof:placetype": "locality"
  },
  "geometry": {
    "coordinates": [
      120.13611000000002,
      32.95556
    ],
    "type": "Point"
  }
}