{
  "type": "Feature",
  "properties": {
    "gn:admin1_code": "15.0",
    "gn:asciiname": "Shangmahuanggou",
    "gn:country_code": "CN",
    "gn:dem": 1997,
    "gn:feature_class": "P",
    "gn:feature_code": "PPL",
    "gn:name": "Shangmahuanggou",
    "gn:population": 0,
    "gn:timezone": "Asia/Shanghai",
    "iso:country": "CN",
    "name:zho_x_preferred": [
      "上麻黄沟"
    ],
    "wof:name": "Shangmahuanggou",
    "wof:placetype": "locality"
  },
  "geometry": {
    "coordinates": [
      103.28,
      37.5225
    ],
    "type": "Point"
  }
}