{
  "type": "Feature",
  "properties": {
    "gn:admin1_code": "8.0",
    "gn:asciiname": "Liujiadian",
    "gn:country_code": "CN",
    "gn:dem": 142,
    "gn:feature_class": "P",
    "gn:feature_code": "PPL",
    "gn:name": "Liujiadian",
    "gn:population": 0,
    "gn:timezone": "Asia/Shanghai",
    "iso:country": "CN",
    "name:zho_x_preferred": [
      "刘家店"
    ],
    "wof:name": "Liujiadian",
    "wof:placetype": "locality"
  },
  "geometry": {
    "coordinates": [
      127.52738,
      46.33956
    ],
    "type": "Point"
  }
}