{
  "type": "Feature",
  "properties": {
    "gn:admin1_code": "15.0",
    "gn:asciiname": "Maquzi",
    "gn:country_code": "CN",
    "gn:dem": 1401,
    "gn:feature_class": "P",
    "gn:feature_code": "PPL",
    "gn:name": "Maquzi",
    "gn:population": 0,
    "gn:timezone": "Asia/Shanghai",
    "iso:country": "CN",
    "name:und_x_variant": [
      "马渠子"
    ],
    "wof:name": "Maquzi",
    "wof:placetype": "locality"
  },
  "geometry": {
    "coordinates": [
      107.28207,
      36.92271
    ],
    "type": "Point"
  }
}