{
  "type": "Feature",
  "properties": {
    "gn:admin1_code": "5.0",
    "gn:asciiname": "Yuda Fangzi",
    "gn:country_code": "CN",
    "gn:dem": 224,
    "gn:feature_class": "P",
    "gn:feature_code": "PPL",
    "gn:name": "Yuda Fangzi",
    "gn:population": 0,
    "gn:timezone": "Asia/Shanghai",
    "iso:country": "CN",
    "name:zho_x_preferred": [
      "于大房子"
    ],
    "wof:name": "Yuda Fangzi",
    "wof:placetype": "locality"
  },
  "geometry": {
    "coordinates": [
      126.67016,
      44.07348
    ],
    "type": "Point"
  }
}