{
  "type": "Feature",
  "properties": {
    "gn:admin1_code": "7.0",
    "gn:asciiname": "Dakeng",
    "gn:country_code": "CN",
    "gn:dem": 470,
    "gn:feature_class": "P",
    "gn:feature_code": "PPL",
    "gn:name": "Dakeng",
    "gn:population": 0,
    "gn:timezone": "Asia/Shanghai",
    "iso:country": "CN",
    "name:ceb_x_preferred": [
      "Dakeng"
    ],
    "name:zho_x_preferred": [
      "大坑"
    ],
    "name:zho_x_variant": [
      "大坑風景區"
    ],
    "wof:name": "Dakeng",
    "wof:placetype": "locality"
  },
  "geometry": {
    "coordinates": [
      118.18067,
      26.47454
    ],
    "type": "Point"
  }
}