{
  "type": "Feature",
  "properties": {
    "gn:admin1_code": "15.0",
    "gn:asciiname": "Dafangshan",
    "gn:country_code": "CN",
    "gn:dem": 1504,
    "gn:feature_class": "P",
    "gn:feature_code": "PPL",
    "gn:name": "Dafangshan",
    "gn:population": 0,
    "gn:timezone": "Asia/Shanghai",
    "iso:country": "CN",
    "name:und_x_variant": [
      "大方山"
    ],
    "wof:name": "Dafangshan",
    "wof:placetype": "locality"
  },
  "geometry": {
    "coordinates": [
      107.27523,
      36.02377
    ],
    "type": "Point"
  }
}