{
  "type": "Feature",
  "properties": {
    "gn:admin1_code": "14.0",
    "gn:asciiname": "Rizhong",
    "gn:country_code": "CN",
    "gn:dem": 3596,
    "gn:feature_class": "P",
    "gn:feature_code": "PPL",
    "gn:name": "Rizhong",
    "gn:population": 0,
    "gn:timezone": "Asia/Urumqi",
    "iso:country": "CN",
    "name:zho_x_preferred": [
      "日中"
    ],
    "wof:name": "Rizhong",
    "wof:placetype": "locality"
  },
  "geometry": {
    "coordinates": [
      98.66463,
      29.3889
    ],
    "type": "Point"
  }
}