{
  "type": "Feature",
  "properties": {
    "gn:admin1_code": "3.0",
    "gn:asciiname": "Xiabuji",
    "gn:country_code": "CN",
    "gn:dem": 21,
    "gn:feature_class": "P",
    "gn:feature_code": "PPLA4",
    "gn:name": "Xiabuji",
    "gn:population": 0,
    "gn:timezone": "Asia/Shanghai",
    "iso:country": "CN",
    "name:und_x_variant": [
      "Hsia-pu-chi",
      "Xiabuji",
      "下埠集",
      "Xiabuji Xiang",
      "下埠集乡"
    ],
    "wof:name": "Xiabuji",
    "wof:placetype": "locality"
  },
  "geometry": {
    "coordinates": [
      116.38205,
      28.30858
    ],
    "type": "Point"
  }
}