{
  "type": "Feature",
  "properties": {
    "gn:admin1_code": "26.0",
    "gn:asciiname": "Tongdi",
    "gn:country_code": "CN",
    "gn:dem": 355,
    "gn:feature_class": "P",
    "gn:feature_code": "PPL",
    "gn:name": "Tongdi",
    "gn:population": 0,
    "gn:timezone": "Asia/Shanghai",
    "iso:country": "CN",
    "name:zho_x_preferred": [
      "同堤"
    ],
    "wof:name": "Tongdi",
    "wof:placetype": "locality"
  },
  "geometry": {
    "coordinates": [
      109.85975,
      34.78266
    ],
    "type": "Point"
  }
}