{
  "type": "Feature",
  "properties": {
    "gn:admin1_code": "29",
    "gn:asciiname": "Jincheng",
    "gn:country_code": "CN",
    "gn:dem": 1911,
    "gn:feature_class": "P",
    "gn:feature_code": "PPLA4",
    "gn:name": "Jincheng",
    "gn:population": 0,
    "gn:timezone": "Asia/Shanghai",
    "iso:country": "CN",
    "name:ara_x_preferred": [
      "جينتشنغ"
    ],
    "name:bul_x_preferred": [
      "Дзинчън"
    ],
    "name:cdo_x_preferred": [
      "Céng-siàng"
    ],
    "name:ceb_x_preferred": [
      "Jincheng"
    ],
    "name:dan_x_preferred": [
      "Jincheng"
    ],
    "name:deu_x_preferred": [
      "Jincheng"
    ],
    "name:eus_x_preferred": [
      "Jincheng"
    ],
    "name:fas_x_preferred": [
      "جینچن"
    ],
    "name:fin_x_preferred": [
      "Jincheng"
    ],
    "name:fra_x_preferred": [
      "Jincheng"
    ],
    "name:heb_x_preferred": [
      "ג'ינצ'נג"
    ],
    "name:hun_x_preferred": [
      "Jincheng"
    ],
    "name:ind_x_preferred": [
      "Jincheng"
    ],
    "name:ita_x_preferred": [
      "Jincheng"
    ],
    "name:jpn_x_preferred": [
      "晋城市"
    ],
    "name:kik_x_preferred": [
      "Jincheng"
    ],
    "name:kor_x_preferred": [
      "진청시"
    ],
    "name:mlg_x_preferred": [
      "Jincheng"
    ],
    "name:nld_x_preferred": [
      "Jincheng"
    ],
    "name:nno_x_preferred": [
      "Jincheng"
    ],
    "name:nor_x_preferred": [
      "Jincheng"
    ],
    "name:pol_x_preferred": [
      "Jincheng"
    ],
    "name:rus_x_preferred": [
      "Цзиньчэн"
    ],
    "name:spa_x_preferred": [
      "Jincheng"
    ],
    "name:srp_x_preferred": [
      "Ђинченг"
    ],
    "name:swe_x_preferred": [
      "Jincheng"
    ],
    "name:tur_x_preferred": [
      "Jincheng"
    ],
    "name:und_x_variant": [
      "Chin-ning",
      "Chin-ch’eng",
      "晋城",
      "Jincheng Zhen",
      "晋城镇"
    ],
    "name:urd_x_preferred": [
      "جنچینگ"
    ],
    "name:vie_x_preferred": [
      "Tấn Thành"
    ],
    "name:war_x_preferred": [
      "Jincheng"
    ],
    "name:wuu_x_preferred": [
      "晋城市"
    ],
    "name:zho_x_preferred": [
      "晋城市"
    ],
    "wof:name": "Jincheng",
    "wof:placetype": "locality"
  },
  "geometry": {
    "coordinates": [
      102.74417,
      24.70222
    ],
    "type": "Point"
  }
}