{
  "type": "Feature",
  "properties": {
    "gn:admin1_code": "4.0",
    "gn:asciiname": "Jinxi",
    "gn:country_code": "CN",
    "gn:dem": 6,
    "gn:feature_class": "P",
    "gn:feature_code": "PPLA4",
    "gn:name": "Jinxi",
    "gn:population": 0,
    "gn:timezone": "Asia/Shanghai",
    "iso:country": "CN",
    "name:ara_x_preferred": [
      "جينشى"
    ],
    "name:ben_x_preferred": [
      "জিনশি"
    ],
    "name:ceb_x_preferred": [
      "Jinxi"
    ],
    "name:deu_x_preferred": [
      "Jinxi"
    ],
    "name:ell_x_preferred": [
      "Τζίνξι"
    ],
    "name:fas_x_preferred": [
      "جینکسی"
    ],
    "name:heb_x_preferred": [
      "ג'ינקסי"
    ],
    "name:hin_x_preferred": [
      "जिंक्सी"
    ],
    "name:hun_x_preferred": [
      "Csinhszi"
    ],
    "name:ind_x_preferred": [
      "Jinxi"
    ],
    "name:ita_x_preferred": [
      "Jinxi"
    ],
    "name:jpn_x_preferred": [
      "錦渓鎮"
    ],
    "name:kor_x_preferred": [
      "진시"
    ],
    "name:nld_x_preferred": [
      "Jinxi"
    ],
    "name:pol_x_preferred": [
      "Jinxi"
    ],
    "name:rus_x_preferred": [
      "Цзиньси"
    ],
    "name:swe_x_preferred": [
      "Jinxi"
    ],
    "name:tur_x_preferred": [
      "Jinxi"
    ],
    "name:ukr_x_preferred": [
      "Цзиньсі"
    ],
    "name:und_x_variant": [
      "Jinxi Zhen"
    ],
    "name:urd_x_preferred": [
      "جنزی"
    ],
    "name:vie_x_preferred": [
      "Kim Khê"
    ],
    "name:zho_cn_x_preferred": [
      "锦溪"
    ],
    "name:zho_tw_x_preferred": [
      "錦溪"
    ],
    "name:zho_x_preferred": [
      "锦溪"
    ],
    "name:zho_x_variant": [
      "锦溪镇"
    ],
    "wof:name": "Jinxi",
    "wof:placetype": "locality"
  },
  "geometry": {
    "coordinates": [
      120.8933,
      31.1793
    ],
    "type": "Point"
  }
}