{
  "type": "Feature",
  "properties": {
    "gn:admin1_code": "4.0",
    "gn:asciiname": "Dong'ou",
    "gn:country_code": "CN",
    "gn:dem": 7,
    "gn:feature_class": "P",
    "gn:feature_code": "PPL",
    "gn:name": "Dong’ou",
    "gn:population": 0,
    "gn:timezone": "Asia/Shanghai",
    "iso:country": "CN",
    "name:cdo_x_preferred": [
      "Dĕ̤ng-ĕu-guók"
    ],
    "name:vie_x_preferred": [
      "Đông Âu"
    ],
    "name:wuu_x_preferred": [
      "东瓯国"
    ],
    "name:zho_x_preferred": [
      "东瓯国"
    ],
    "wof:name": "Dong'ou",
    "wof:placetype": "locality"
  },
  "geometry": {
    "coordinates": [
      120.46667,
      32.16389
    ],
    "type": "Point"
  }
}