{
  "type": "Feature",
  "properties": {
    "gn:admin1_code": "19.0",
    "gn:asciiname": "Laobianwai",
    "gn:country_code": "CN",
    "gn:dem": 431,
    "gn:feature_class": "P",
    "gn:feature_code": "PPL",
    "gn:name": "Laobianwai",
    "gn:population": 0,
    "gn:timezone": "Asia/Shanghai",
    "iso:country": "CN",
    "name:und_x_variant": [
      "老边外"
    ],
    "wof:name": "Laobianwai",
    "wof:placetype": "locality"
  },
  "geometry": {
    "coordinates": [
      122.94244,
      40.47439
    ],
    "type": "Point"
  }
}