{
  "type": "Feature",
  "properties": {
    "gn:admin1_code": "26.0",
    "gn:asciiname": "Renli",
    "gn:country_code": "CN",
    "gn:dem": 347,
    "gn:feature_class": "P",
    "gn:feature_code": "PPL",
    "gn:name": "Renli",
    "gn:population": 0,
    "gn:timezone": "Asia/Shanghai",
    "iso:country": "CN",
    "name:zho_x_preferred": [
      "任李"
    ],
    "wof:name": "Renli",
    "wof:placetype": "locality"
  },
  "geometry": {
    "coordinates": [
      109.6248,
      34.57891
    ],
    "type": "Point"
  }
}