{
  "type": "Feature",
  "properties": {
    "gn:admin1_code": "8.0",
    "gn:asciiname": "Datong",
    "gn:country_code": "CN",
    "gn:dem": 206,
    "gn:feature_class": "P",
    "gn:feature_code": "PPL",
    "gn:name": "Datong",
    "gn:population": 0,
    "gn:timezone": "Asia/Shanghai",
    "iso:country": "CN",
    "name:afr_x_preferred": [
      "Datong"
    ],
    "name:ara_x_preferred": [
      "داتونغ"
    ],
    "name:bre_x_preferred": [
      "Datong"
    ],
    "name:bul_x_preferred": [
      "Датун"
    ],
    "name:cat_x_preferred": [
      "Datong"
    ],
    "name:cdo_x_preferred": [
      "Dâi-dùng"
    ],
    "name:ceb_x_preferred": [
      "Datong Shi"
    ],
    "name:ces_x_preferred": [
      "Ta-tchung"
    ],
    "name:dan_x_preferred": [
      "Datong"
    ],
    "name:deu_x_preferred": [
      "Datong"
    ],
    "name:epo_x_preferred": [
      "Datongo"
    ],
    "name:eus_x_preferred": [
      "Datong"
    ],
    "name:fas_x_preferred": [
      "داتونگ"
    ],
    "name:fin_x_preferred": [
      "Datong"
    ],
    "name:fra_x_preferred": [
      "Datong"
    ],
    "name:heb_x_preferred": [
      "דאטונג"
    ],
    "name:hun_x_preferred": [
      "Datong"
    ],
    "name:ina_x_preferred": [
      "Datong"
    ],
    "name:ind_x_preferred": [
      "Datong"
    ],
    "name:ita_x_preferred": [
      "Datong"
    ],
    "name:jpn_x_preferred": [
      "大同市"
    ],
    "name:kaz_x_preferred": [
      "Датун"
    ],
    "name:kik_x_preferred": [
      "Datong"
    ],
    "name:kor_x_preferred": [
      "다퉁시"
    ],
    "name:lit_x_preferred": [
      "Datongas"
    ],
    "name:mlg_x_preferred": [
      "Datong"
    ],
    "name:mon_x_preferred": [
      "Датун"
    ],
    "name:nld_x_preferred": [
      "Datong"
    ],
    "name:nno_x_preferred": [
      "Datong"
    ],
    "name:nor_x_preferred": [
      "Datong"
    ],
    "name:pol_x_preferred": [
      "Datong"
    ],
    "name:por_x_preferred": [
      "Datong"
    ],
    "name:rus_x_preferred": [
      "Датун"
    ],
    "name:spa_x_preferred": [
      "Datong"
    ],
    "name:srp_x_preferred": [
      "Датунг"
    ],
    "name:swe_x_preferred": [
      "Datong"
    ],
    "name:tgl_x_preferred": [
      "Datong"
    ],
    "name:tur_x_preferred": [
      "Datong"
    ],
    "name:uig_x_preferred": [
      "داتۇڭ شەھىر"
    ],
    "name:ukr_x_preferred": [
      "Датун"
    ],
    "name:urd_x_preferred": [
      "داتونگ"
    ],
    "name:vie_x_preferred": [
      "Đại Đồng"
    ],
    "name:war_x_preferred": [
      "Datong"
    ],
    "name:wuu_x_preferred": [
      "大同市"
    ],
    "name:zho_x_preferred": [
      "大同"
    ],
    "name:zho_x_variant": [
      "大同市"
    ],
    "wof:name": "Datong",
    "wof:placetype": "locality"
  },
  "geometry": {
    "coordinates": [
      127.55566,
      45.71538
    ],
    "type": "Point"
  }
}