{
  "type": "Feature",
  "properties": {
    "gn:admin1_code": "16.0",
    "gn:asciiname": "Liuliao",
    "gn:country_code": "CN",
    "gn:dem": 123,
    "gn:feature_class": "P",
    "gn:feature_code": "PPL",
    "gn:name": "Liuliao",
    "gn:population": 0,
    "gn:timezone": "Asia/Shanghai",
    "iso:country": "CN",
    "name:zho_x_preferred": [
      "六辽"
    ],
    "wof:name": "Liuliao",
    "wof:placetype": "locality"
  },
  "geometry": {
    "coordinates": [
      109.275,
      22.5435
    ],
    "type": "Point"
  }
}