{
  "type": "Feature",
  "properties": {
    "gn:admin1_code": "2.0",
    "gn:asciiname": "Hongcun",
    "gn:country_code": "CN",
    "gn:dem": 47,
    "gn:feature_class": "P",
    "gn:feature_code": "PPL",
    "gn:name": "Hongcun",
    "gn:population": 0,
    "gn:timezone": "Asia/Shanghai",
    "iso:country": "CN",
    "name:ast_x_preferred": [
      "Hongcun"
    ],
    "name:ces_x_preferred": [
      "Chung-cchun"
    ],
    "name:eus_x_preferred": [
      "Hongcun"
    ],
    "name:fas_x_preferred": [
      "هانگکن"
    ],
    "name:fin_x_preferred": [
      "Hongcun"
    ],
    "name:fra_x_preferred": [
      "Hongcun"
    ],
    "name:heb_x_preferred": [
      "הונגצון"
    ],
    "name:hrv_x_preferred": [
      "Hongcun"
    ],
    "name:ita_x_preferred": [
      "Hongcun"
    ],
    "name:kat_x_preferred": [
      "ხუნცუნი"
    ],
    "name:mal_x_preferred": [
      "ഹോങ്സുൻ"
    ],
    "name:nld_x_preferred": [
      "Hongcun"
    ],
    "name:por_x_preferred": [
      "Hongcun"
    ],
    "name:slk_x_preferred": [
      "Chung-cchun"
    ],
    "name:spa_x_preferred": [
      "Hongcun"
    ],
    "name:swe_x_preferred": [
      "Hongcun"
    ],
    "name:tur_x_preferred": [
      "Hongcun"
    ],
    "name:vie_x_preferred": [
      "Hoành thôn"
    ],
    "name:zho_x_preferred": [
      "洪村"
    ],
    "wof:name": "Hongcun",
    "wof:placetype": "locality"
  },
  "geometry": {
    "coordinates": [
      119.78351,
      29.10413
    ],
    "type": "Point"
  }
}