{
  "type": "Feature",
  "properties": {
    "gn:admin1_code": "31",
    "gn:asciiname": "Shangmingshan",
    "gn:country_code": "CN",
    "gn:dem": 27,
    "gn:feature_class": "P",
    "gn:feature_code": "PPL",
    "gn:name": "Shangmingshan",
    "gn:population": 0,
    "gn:timezone": "Asia/Shanghai",
    "iso:country": "CN",
    "name:und_x_variant": [
      "上名山"
    ],
    "wof:name": "Shangmingshan",
    "wof:placetype": "locality"
  },
  "geometry": {
    "coordinates": [
      108.709,
      19.0377
    ],
    "type": "Point"
  }
}