{
  "type": "Feature",
  "properties": {
    "gn:admin1_code": "19.0",
    "gn:asciiname": "Liangjiagou",
    "gn:country_code": "CN",
    "gn:dem": 495,
    "gn:feature_class": "P",
    "gn:feature_code": "PPL",
    "gn:name": "Liangjiagou",
    "gn:population": 0,
    "gn:timezone": "Asia/Shanghai",
    "iso:country": "CN",
    "name:zho_x_preferred": [
      "梁家沟"
    ],
    "wof:name": "Liangjiagou",
    "wof:placetype": "locality"
  },
  "geometry": {
    "coordinates": [
      119.99,
      41.6029
    ],
    "type": "Point"
  }
}