{
  "type": "Feature",
  "properties": {
    "gn:admin1_code": "15",
    "gn:asciiname": "Huocheng",
    "gn:country_code": "CN",
    "gn:dem": 2391,
    "gn:feature_class": "P",
    "gn:feature_code": "PPLA4",
    "gn:name": "Huocheng",
    "gn:population": 0,
    "gn:timezone": "Asia/Shanghai",
    "iso:country": "CN",
    "name:und_x_variant": [
      "Huocheng Zhen"
    ],
    "name:zho_x_preferred": [
      "霍城"
    ],
    "name:zho_x_variant": [
      "霍城镇"
    ],
    "wof:name": "Huocheng",
    "wof:placetype": "locality"
  },
  "geometry": {
    "coordinates": [
      101.05487,
      38.40318
    ],
    "type": "Point"
  }
}