{
  "type": "Feature",
  "properties": {
    "gn:admin1_code": "16.0",
    "gn:asciiname": "Guli",
    "gn:country_code": "CN",
    "gn:dem": 148,
    "gn:feature_class": "P",
    "gn:feature_code": "PPL",
    "gn:name": "Guli",
    "gn:population": 0,
    "gn:timezone": "Asia/Shanghai",
    "iso:country": "CN",
    "name:bel_x_preferred": [
      "Гулі"
    ],
    "name:ceb_x_preferred": [
      "Guli"
    ],
    "name:hye_x_preferred": [
      "Գուլի"
    ],
    "name:mlg_x_preferred": [
      "Guli"
    ],
    "name:rus_x_preferred": [
      "Гули"
    ],
    "name:swe_x_preferred": [
      "Guli"
    ],
    "name:ukr_x_preferred": [
      "Гулі"
    ],
    "name:zho_x_preferred": [
      "谷里"
    ],
    "wof:name": "Guli",
    "wof:placetype": "locality"
  },
  "geometry": {
    "coordinates": [
      108.866,
      24.5666
    ],
    "type": "Point"
  }
}