{
  "type": "Feature",
  "properties": {
    "gn:admin1_code": "26.0",
    "gn:asciiname": "Caojiayuan",
    "gn:country_code": "CN",
    "gn:dem": 1060,
    "gn:feature_class": "P",
    "gn:feature_code": "PPL",
    "gn:name": "Caojiayuan",
    "gn:population": 0,
    "gn:timezone": "Asia/Shanghai",
    "iso:country": "CN",
    "name:zho_x_preferred": [
      "曹家院"
    ],
    "wof:name": "Caojiayuan",
    "wof:placetype": "locality"
  },
  "geometry": {
    "coordinates": [
      109.69708,
      33.83130999999999
    ],
    "type": "Point"
  }
}