{
  "type": "Feature",
  "properties": {
    "gn:admin1_code": "26.0",
    "gn:asciiname": "Shipancun",
    "gn:country_code": "CN",
    "gn:dem": 1142,
    "gn:feature_class": "P",
    "gn:feature_code": "PPL",
    "gn:name": "Shipancun",
    "gn:population": 0,
    "gn:timezone": "Asia/Shanghai",
    "iso:country": "CN",
    "name:zho_x_preferred": [
      "石畔村"
    ],
    "wof:name": "Shipancun",
    "wof:placetype": "locality"
  },
  "geometry": {
    "coordinates": [
      108.78154,
      36.51718
    ],
    "type": "Point"
  }
}