{
  "type": "Feature",
  "properties": {
    "gn:admin1_code": "12.0",
    "gn:asciiname": "Baiquan",
    "gn:country_code": "CN",
    "gn:dem": 117,
    "gn:feature_class": "P",
    "gn:feature_code": "PPL",
    "gn:name": "Baiquan",
    "gn:population": 0,
    "gn:timezone": "Asia/Shanghai",
    "iso:country": "CN",
    "name:ara_x_preferred": [
      "بايكوان"
    ],
    "name:ben_x_preferred": [
      "বাইকুয়ান"
    ],
    "name:ell_x_preferred": [
      "Μπαϊκουάν"
    ],
    "name:heb_x_preferred": [
      "באינגואן"
    ],
    "name:hin_x_preferred": [
      "बाइकुआन"
    ],
    "name:hun_x_preferred": [
      "Baiquan"
    ],
    "name:ind_x_preferred": [
      "Baiquan"
    ],
    "name:pol_x_preferred": [
      "Baiquan"
    ],
    "name:por_x_preferred": [
      "Baiquan"
    ],
    "name:spa_x_preferred": [
      "Baiquan"
    ],
    "name:tur_x_preferred": [
      "Baiquan"
    ],
    "name:ukr_x_preferred": [
      "Байцюань"
    ],
    "name:zho_x_preferred": [
      "Baiquan"
    ],
    "name:zho_x_variant": [
      "白泉"
    ],
    "wof:name": "Baiquan",
    "wof:placetype": "locality"
  },
  "geometry": {
    "coordinates": [
      114.40025,
      29.69134
    ],
    "type": "Point"
  }
}