{
  "type": "Feature",
  "properties": {
    "gn:admin1_code": "26.0",
    "gn:asciiname": "Zhaolaozhuang",
    "gn:country_code": "CN",
    "gn:dem": 1608,
    "gn:feature_class": "P",
    "gn:feature_code": "PPL",
    "gn:name": "Zhaolaozhuang",
    "gn:population": 0,
    "gn:timezone": "Asia/Shanghai",
    "iso:country": "CN",
    "name:zho_x_preferred": [
      "赵老庄"
    ],
    "wof:name": "Zhaolaozhuang",
    "wof:placetype": "locality"
  },
  "geometry": {
    "coordinates": [
      108.12269,
      37.16293
    ],
    "type": "Point"
  }
}