{
  "type": "Feature",
  "properties": {
    "gn:admin1_code": "32.0",
    "gn:asciiname": "Jinguochang",
    "gn:country_code": "CN",
    "gn:dem": 379,
    "gn:feature_class": "P",
    "gn:feature_code": "PPL",
    "gn:name": "Jinguochang",
    "gn:population": 0,
    "gn:timezone": "Asia/Shanghai",
    "iso:country": "CN",
    "name:zho_x_preferred": [
      "金锅场"
    ],
    "wof:name": "Jinguochang",
    "wof:placetype": "locality"
  },
  "geometry": {
    "coordinates": [
      106.386,
      31.4138
    ],
    "type": "Point"
  }
}