{
  "type": "Feature",
  "properties": {
    "gn:admin1_code": "16.0",
    "gn:asciiname": "Tangshan",
    "gn:country_code": "CN",
    "gn:dem": 111,
    "gn:feature_class": "P",
    "gn:feature_code": "PPL",
    "gn:name": "Tangshan",
    "gn:population": 0,
    "gn:timezone": "Asia/Shanghai",
    "iso:country": "CN",
    "name:afr_x_preferred": [
      "Tangshan"
    ],
    "name:ara_x_preferred": [
      "تانغشان"
    ],
    "name:ast_x_preferred": [
      "Tangshan"
    ],
    "name:bul_x_preferred": [
      "Таншан"
    ],
    "name:cdo_x_preferred": [
      "Dòng-săng"
    ],
    "name:ceb_x_preferred": [
      "Tangshan Shi"
    ],
    "name:ces_x_preferred": [
      "Tchang-šan"
    ],
    "name:che_x_preferred": [
      "Таншань"
    ],
    "name:cym_x_preferred": [
      "Tangshan"
    ],
    "name:dan_x_preferred": [
      "Tangshan"
    ],
    "name:deu_x_preferred": [
      "Tangshan"
    ],
    "name:ell_x_preferred": [
      "Τανγκσάν"
    ],
    "name:epo_x_preferred": [
      "Tangŝano"
    ],
    "name:eus_x_preferred": [
      "Tangshan"
    ],
    "name:fas_x_preferred": [
      "تانگشان"
    ],
    "name:fin_x_preferred": [
      "Tangshan"
    ],
    "name:fra_x_preferred": [
      "Tangshan"
    ],
    "name:heb_x_preferred": [
      "טאנגשאן"
    ],
    "name:hun_x_preferred": [
      "Tangsan"
    ],
    "name:hye_x_preferred": [
      "Տանշան"
    ],
    "name:ind_x_preferred": [
      "Tangshan"
    ],
    "name:ita_x_preferred": [
      "Tangshan"
    ],
    "name:jpn_x_preferred": [
      "唐山市"
    ],
    "name:kik_x_preferred": [
      "Tangshan"
    ],
    "name:kir_x_preferred": [
      "Таншань"
    ],
    "name:kor_x_preferred": [
      "탕산시"
    ],
    "name:lit_x_preferred": [
      "Tangšanas"
    ],
    "name:ltz_x_preferred": [
      "Tangshan"
    ],
    "name:mal_x_preferred": [
      "ടാങ്ഷാൻ"
    ],
    "name:mar_x_preferred": [
      "तांग्शान"
    ],
    "name:mlg_x_preferred": [
      "Tangshan"
    ],
    "name:nld_x_preferred": [
      "Tangshan"
    ],
    "name:nno_x_preferred": [
      "Tangshan"
    ],
    "name:nor_x_preferred": [
      "Tangshan"
    ],
    "name:pam_x_preferred": [
      "Tangshan"
    ],
    "name:pan_x_preferred": [
      "ਤਾਂਗਸ਼ਾਨ"
    ],
    "name:pol_x_preferred": [
      "Tangshan"
    ],
    "name:por_x_preferred": [
      "Tangshan"
    ],
    "name:rus_x_preferred": [
      "Таншань"
    ],
    "name:sco_x_preferred": [
      "Tangshan"
    ],
    "name:spa_x_preferred": [
      "Tangshan"
    ],
    "name:srp_x_preferred": [
      "Тангшан"
    ],
    "name:swe_x_preferred": [
      "Tangshan"
    ],
    "name:tur_x_preferred": [
      "Tangshan"
    ],
    "name:uig_x_preferred": [
      "تاڭشەن شەھىرى"
    ],
    "name:ukr_x_preferred": [
      "Таншань"
    ],
    "name:urd_x_preferred": [
      "تانگشان"
    ],
    "name:vie_x_preferred": [
      "Đường Sơn"
    ],
    "name:war_x_preferred": [
      "Tangshan"
    ],
    "name:wuu_x_preferred": [
      "唐山市"
    ],
    "name:zho_x_preferred": [
      "塘山"
    ],
    "name:zho_x_variant": [
      "唐山市"
    ],
    "wof:name": "Tangshan",
    "wof:placetype": "locality"
  },
  "geometry": {
    "coordinates": [
      110.734,
      24.0711
    ],
    "type": "Point"
  }
}