{
  "type": "Feature",
  "properties": {
    "gn:admin1_code": "12.0",
    "gn:asciiname": "Moyun Shanzhai",
    "gn:country_code": "CN",
    "gn:dem": 820,
    "gn:feature_class": "P",
    "gn:feature_code": "PPL",
    "gn:name": "Moyun Shanzhai",
    "gn:population": 0,
    "gn:timezone": "Asia/Shanghai",
    "iso:country": "CN",
    "name:zho_x_preferred": [
      "磨云山寨"
    ],
    "wof:name": "Moyun Shanzhai",
    "wof:placetype": "locality"
  },
  "geometry": {
    "coordinates": [
      113.24421,
      32.3935
    ],
    "type": "Point"
  }
}