{
  "type": "Feature",
  "properties": {
    "gn:admin1_code": "16.0",
    "gn:asciiname": "Batou",
    "gn:country_code": "CN",
    "gn:dem": 237,
    "gn:feature_class": "P",
    "gn:feature_code": "PPL",
    "gn:name": "Batou",
    "gn:population": 0,
    "gn:timezone": "Asia/Shanghai",
    "iso:country": "CN",
    "name:jpn_x_preferred": [
      "バトー"
    ],
    "name:spa_x_preferred": [
      "Batou"
    ],
    "name:zho_x_preferred": [
      "坝头"
    ],
    "wof:name": "Batou",
    "wof:placetype": "locality"
  },
  "geometry": {
    "coordinates": [
      108.364,
      24.3694
    ],
    "type": "Point"
  }
}