{
  "type": "Feature",
  "properties": {
    "gn:admin1_code": "30",
    "gn:asciiname": "Tangtang",
    "gn:country_code": "CN",
    "gn:dem": 25,
    "gn:feature_class": "P",
    "gn:feature_code": "PPLA4",
    "gn:name": "Tangtang",
    "gn:population": 0,
    "gn:timezone": "Asia/Shanghai",
    "iso:country": "CN",
    "name:und_x_variant": [
      "T’ang-tang-hsü",
      "T’ang-ho-hsü",
      "Tangtang",
      "Tangtang Zhen",
      "汤塘镇"
    ],
    "name:zho_x_preferred": [
      "汤塘"
    ],
    "wof:name": "Tangtang",
    "wof:placetype": "locality"
  },
  "geometry": {
    "coordinates": [
      113.46734,
      23.74309
    ],
    "type": "Point"
  }
}