{
  "type": "Feature",
  "properties": {
    "gn:admin1_code": "5.0",
    "gn:asciiname": "Jing'antun",
    "gn:country_code": "CN",
    "gn:dem": 177,
    "gn:feature_class": "P",
    "gn:feature_code": "PPL",
    "gn:name": "Jing’antun",
    "gn:population": 0,
    "gn:timezone": "Asia/Shanghai",
    "iso:country": "CN",
    "name:und_x_variant": [
      "Jing’antun"
    ],
    "name:zho_x_preferred": [
      "靖安屯"
    ],
    "wof:name": "Jing'antun",
    "wof:placetype": "locality"
  },
  "geometry": {
    "coordinates": [
      123.80861000000002,
      44.1382
    ],
    "type": "Point"
  }
}