{
  "type": "Feature",
  "properties": {
    "gn:admin1_code": "14.0",
    "gn:asciiname": "Kabuqie",
    "gn:country_code": "CN",
    "gn:dem": 4494,
    "gn:feature_class": "P",
    "gn:feature_code": "PPL",
    "gn:name": "Kabuqie",
    "gn:population": 0,
    "gn:timezone": "Asia/Urumqi",
    "iso:country": "CN",
    "name:zho_x_preferred": [
      "卡布切"
    ],
    "wof:name": "Kabuqie",
    "wof:placetype": "locality"
  },
  "geometry": {
    "coordinates": [
      86.8944,
      29.1558
    ],
    "type": "Point"
  }
}