{
  "type": "Feature",
  "properties": {
    "gn:admin1_code": "09",
    "gn:asciiname": "Luanchuan Chengguanzhen",
    "gn:country_code": "CN",
    "gn:dem": 742,
    "gn:feature_class": "P",
    "gn:feature_code": "PPLA3",
    "gn:name": "Luanchuan Chengguanzhen",
    "gn:population": 0,
    "gn:timezone": "Asia/Shanghai",
    "iso:country": "CN",
    "name:deu_x_preferred": [
      "Luanchuan"
    ],
    "name:fas_x_preferred": [
      "شهرستان لوانچوان"
    ],
    "name:jpn_x_preferred": [
      "欒川県"
    ],
    "name:kor_x_preferred": [
      "롼촨현"
    ],
    "name:nor_x_preferred": [
      "Luanchuan"
    ],
    "name:rus_x_preferred": [
      "Луаньчуань"
    ],
    "name:swe_x_preferred": [
      "Luanchuan"
    ],
    "name:und_x_variant": [
      "Luan-ch’uan-chen",
      "Luanchuan Chengguanzhen",
      "Luanchuan Xiang"
    ],
    "name:urd_x_preferred": [
      "لوانچوان کاؤنٹی"
    ],
    "name:vie_x_preferred": [
      "Loan Xuyên"
    ],
    "name:zho_x_preferred": [
      "栾川城关镇"
    ],
    "name:zho_x_variant": [
      "栾川",
      "栾川乡",
      "栾川县"
    ],
    "wof:name": "Luanchuan Chengguanzhen",
    "wof:placetype": "locality"
  },
  "geometry": {
    "coordinates": [
      111.613,
      33.7808
    ],
    "type": "Point"
  }
}