{
  "type": "Feature",
  "properties": {
    "gn:admin1_code": "7.0",
    "gn:asciiname": "Yangmei",
    "gn:country_code": "CN",
    "gn:dem": 104,
    "gn:feature_class": "P",
    "gn:feature_code": "PPL",
    "gn:name": "Yangmei",
    "gn:population": 0,
    "gn:timezone": "Asia/Shanghai",
    "iso:country": "CN",
    "name:ara_x_preferred": [
      "يانغ ماي"
    ],
    "name:ben_x_preferred": [
      "ইয়াংমেই"
    ],
    "name:ceb_x_preferred": [
      "Yangmei"
    ],
    "name:deu_x_preferred": [
      "Yangmei"
    ],
    "name:ell_x_preferred": [
      "Γιανγκμέι"
    ],
    "name:fas_x_preferred": [
      "یانگمی"
    ],
    "name:heb_x_preferred": [
      "יאנגמאי"
    ],
    "name:hin_x_preferred": [
      "यांगमी"
    ],
    "name:hun_x_preferred": [
      "Yangmei"
    ],
    "name:ind_x_preferred": [
      "Yangmei"
    ],
    "name:jpn_x_preferred": [
      "楊梅鎮"
    ],
    "name:por_x_preferred": [
      "Yangmei"
    ],
    "name:swe_x_preferred": [
      "Yangmei"
    ],
    "name:tur_x_preferred": [
      "Yangmei"
    ],
    "name:ukr_x_preferred": [
      "Янгмей"
    ],
    "name:vie_x_preferred": [
      "Dương mai"
    ],
    "name:zho_x_preferred": [
      "杨美"
    ],
    "name:zho_x_variant": [
      "楊梅鎮"
    ],
    "wof:name": "Yangmei",
    "wof:placetype": "locality"
  },
  "geometry": {
    "coordinates": [
      117.30011,
      24.13919
    ],
    "type": "Point"
  }
}