{
  "type": "Feature",
  "properties": {
    "gn:admin1_code": "20.0",
    "gn:asciiname": "Baidongqu",
    "gn:country_code": "CN",
    "gn:dem": 1451,
    "gn:feature_class": "P",
    "gn:feature_code": "PPL",
    "gn:name": "Baidongqu",
    "gn:population": 0,
    "gn:timezone": "Asia/Shanghai",
    "iso:country": "CN",
    "name:und_x_variant": [
      "白洞渠"
    ],
    "wof:name": "Baidongqu",
    "wof:placetype": "locality"
  },
  "geometry": {
    "coordinates": [
      110.2726,
      40.89539
    ],
    "type": "Point"
  }
}