{
  "type": "Feature",
  "properties": {
    "gn:admin1_code": "15.0",
    "gn:asciiname": "Xiaogouzi",
    "gn:country_code": "CN",
    "gn:dem": 1411,
    "gn:feature_class": "P",
    "gn:feature_code": "PPL",
    "gn:name": "Xiaogouzi",
    "gn:population": 0,
    "gn:timezone": "Asia/Shanghai",
    "iso:country": "CN",
    "name:zho_x_preferred": [
      "小沟子"
    ],
    "wof:name": "Xiaogouzi",
    "wof:placetype": "locality"
  },
  "geometry": {
    "coordinates": [
      102.356,
      38.6345
    ],
    "type": "Point"
  }
}