{
  "type": "Feature",
  "properties": {
    "gn:admin1_code": "29.0",
    "gn:asciiname": "Nuopushan",
    "gn:country_code": "CN",
    "gn:dem": 1716,
    "gn:feature_class": "P",
    "gn:feature_code": "PPL",
    "gn:name": "Nuopushan",
    "gn:population": 0,
    "gn:timezone": "Asia/Shanghai",
    "iso:country": "CN",
    "name:zho_x_preferred": [
      "糯普山"
    ],
    "wof:name": "Nuopushan",
    "wof:placetype": "locality"
  },
  "geometry": {
    "coordinates": [
      101.24,
      23.7419
    ],
    "type": "Point"
  }
}