{
  "type": "Feature",
  "properties": {
    "gn:admin1_code": "11.0",
    "gn:asciiname": "Muyushan",
    "gn:country_code": "CN",
    "gn:dem": 39,
    "gn:feature_class": "P",
    "gn:feature_code": "PPL",
    "gn:name": "Muyushan",
    "gn:population": 0,
    "gn:timezone": "Asia/Shanghai",
    "iso:country": "CN",
    "name:zho_x_preferred": [
      "木鱼山"
    ],
    "wof:name": "Muyushan",
    "wof:placetype": "locality"
  },
  "geometry": {
    "coordinates": [
      112.05679,
      28.79173
    ],
    "type": "Point"
  }
}