{
  "type": "Feature",
  "properties": {
    "gn:admin1_code": "30.0",
    "gn:asciiname": "Dayan",
    "gn:country_code": "CN",
    "gn:dem": 81,
    "gn:feature_class": "P",
    "gn:feature_code": "PPL",
    "gn:name": "Dayan",
    "gn:population": 0,
    "gn:timezone": "Asia/Shanghai",
    "iso:country": "CN",
    "name:deu_x_preferred": [
      "Dayan"
    ],
    "name:fra_x_preferred": [
      "Dayan"
    ],
    "name:heb_x_preferred": [
      "דיין"
    ],
    "name:ita_x_preferred": [
      "Dayan"
    ],
    "name:jpn_x_preferred": [
      "ダヤン"
    ],
    "name:nds_x_preferred": [
      "Dayan"
    ],
    "name:rus_x_preferred": [
      "Даян"
    ],
    "name:zho_x_preferred": [
      "大岩"
    ],
    "wof:name": "Dayan",
    "wof:placetype": "locality"
  },
  "geometry": {
    "coordinates": [
      113.53889,
      24.32861
    ],
    "type": "Point"
  }
}