{
  "type": "Feature",
  "properties": {
    "gn:admin1_code": "16.0",
    "gn:asciiname": "Luopan",
    "gn:country_code": "CN",
    "gn:dem": 225,
    "gn:feature_class": "P",
    "gn:feature_code": "PPL",
    "gn:name": "Luopan",
    "gn:population": 0,
    "gn:timezone": "Asia/Shanghai",
    "iso:country": "CN",
    "name:deu_x_preferred": [
      "Lo Pan"
    ],
    "name:fin_x_preferred": [
      "Luopan"
    ],
    "name:hrv_x_preferred": [
      "Luo Pan"
    ],
    "name:jpn_x_preferred": [
      "風水羅盤"
    ],
    "name:mkd_x_preferred": [
      "Луопан"
    ],
    "name:nor_x_preferred": [
      "Luopan"
    ],
    "name:pol_x_preferred": [
      "Kompas geomantyczny"
    ],
    "name:rus_x_preferred": [
      "Китайский компас"
    ],
    "name:spa_x_preferred": [
      "Luopan"
    ],
    "name:ukr_x_preferred": [
      "Китайський компас"
    ],
    "name:zho_x_preferred": [
      "洛潘"
    ],
    "wof:name": "Luopan",
    "wof:placetype": "locality"
  },
  "geometry": {
    "coordinates": [
      109.492,
      25.4347
    ],
    "type": "Point"
  }
}