{
  "type": "Feature",
  "properties": {
    "gn:admin1_code": "19.0",
    "gn:asciiname": "Houxuejia Wobu",
    "gn:country_code": "CN",
    "gn:dem": 32,
    "gn:feature_class": "P",
    "gn:feature_code": "PPL",
    "gn:name": "Houxuejia Wobu",
    "gn:population": 0,
    "gn:timezone": "Asia/Shanghai",
    "iso:country": "CN",
    "name:zho_x_preferred": [
      "后薛家窝堡"
    ],
    "wof:name": "Houxuejia Wobu",
    "wof:placetype": "locality"
  },
  "geometry": {
    "coordinates": [
      122.441,
      41.8821
    ],
    "type": "Point"
  }
}