{
  "type": "Feature",
  "properties": {
    "gn:admin1_code": "21.0",
    "gn:asciiname": "Chen'ergou",
    "gn:country_code": "CN",
    "gn:dem": 2245,
    "gn:feature_class": "P",
    "gn:feature_code": "PPL",
    "gn:name": "Chen’ergou",
    "gn:population": 0,
    "gn:timezone": "Asia/Shanghai",
    "iso:country": "CN",
    "name:und_x_variant": [
      "Chen’ergou"
    ],
    "name:zho_x_preferred": [
      "陈儿沟"
    ],
    "wof:name": "Chen'ergou",
    "wof:placetype": "locality"
  },
  "geometry": {
    "coordinates": [
      106.129,
      35.8731
    ],
    "type": "Point"
  }
}