{
  "type": "Feature",
  "properties": {
    "gn:admin1_code": "33.0",
    "gn:asciiname": "Shili",
    "gn:country_code": "CN",
    "gn:dem": 233,
    "gn:feature_class": "P",
    "gn:feature_code": "PPL",
    "gn:name": "Shili",
    "gn:population": 0,
    "gn:timezone": "Asia/Shanghai",
    "iso:country": "CN",
    "name:ara_x_preferred": [
      "شيلي"
    ],
    "name:fas_x_preferred": [
      "شیلی"
    ],
    "name:msa_x_preferred": [
      "Shili"
    ],
    "name:zho_x_preferred": [
      "十里"
    ],
    "wof:name": "Shili",
    "wof:placetype": "locality"
  },
  "geometry": {
    "coordinates": [
      109.46878999999998,
      31.02076
    ],
    "type": "Point"
  }
}