{
  "type": "Feature",
  "properties": {
    "gn:admin1_code": "32.0",
    "gn:asciiname": "Guangming",
    "gn:country_code": "CN",
    "gn:dem": 258,
    "gn:feature_class": "P",
    "gn:feature_code": "PPL",
    "gn:name": "Guangming",
    "gn:population": 0,
    "gn:timezone": "Asia/Shanghai",
    "iso:country": "CN",
    "name:ceb_x_preferred": [
      "Guangming"
    ],
    "name:deu_x_preferred": [
      "Guangming"
    ],
    "name:jpn_x_preferred": [
      "光明"
    ],
    "name:mlg_x_preferred": [
      "Guangming"
    ],
    "name:swe_x_preferred": [
      "Guangming"
    ],
    "name:zho_x_preferred": [
      "光明"
    ],
    "wof:name": "Guangming",
    "wof:placetype": "locality"
  },
  "geometry": {
    "coordinates": [
      106.697,
      30.5334
    ],
    "type": "Point"
  }
}