{
  "type": "Feature",
  "properties": {
    "gn:admin1_code": "12",
    "gn:asciiname": "Donglang",
    "gn:country_code": "CN",
    "gn:dem": 757,
    "gn:feature_class": "P",
    "gn:feature_code": "PPL",
    "gn:name": "Donglang",
    "gn:population": 0,
    "gn:timezone": "Asia/Shanghai",
    "iso:country": "CN",
    "name:und_x_variant": [
      "Tung-lang",
      "Donglang"
    ],
    "name:zho_x_preferred": [
      "东浪"
    ],
    "wof:name": "Donglang",
    "wof:placetype": "locality"
  },
  "geometry": {
    "coordinates": [
      110.81732,
      32.24215
    ],
    "type": "Point"
  }
}