{
  "type": "Feature",
  "properties": {
    "gn:admin1_code": "14.0",
    "gn:asciiname": "Puri",
    "gn:country_code": "CN",
    "gn:dem": 4435,
    "gn:feature_class": "P",
    "gn:feature_code": "PPL",
    "gn:name": "Puri",
    "gn:population": 0,
    "gn:timezone": "Asia/Urumqi",
    "iso:country": "CN",
    "name:ara_x_preferred": [
      "بوري"
    ],
    "name:asm_x_preferred": [
      "পুৰী"
    ],
    "name:bel_x_preferred": [
      "Пуры"
    ],
    "name:ben_x_preferred": [
      "পুরী"
    ],
    "name:bih_x_preferred": [
      "पुरी"
    ],
    "name:bpy_x_preferred": [
      "পুরি"
    ],
    "name:cat_x_preferred": [
      "Puri"
    ],
    "name:ceb_x_preferred": [
      "Puri"
    ],
    "name:ces_x_preferred": [
      "Purí"
    ],
    "name:cym_x_preferred": [
      "Puri"
    ],
    "name:deu_x_preferred": [
      "Puri"
    ],
    "name:dsb_x_preferred": [
      "Puri"
    ],
    "name:fas_x_preferred": [
      "پوری"
    ],
    "name:fin_x_preferred": [
      "Puri"
    ],
    "name:fra_x_preferred": [
      "Purî"
    ],
    "name:guj_x_preferred": [
      "જગન્નાથપુરી"
    ],
    "name:heb_x_preferred": [
      "פורי"
    ],
    "name:hin_x_preferred": [
      "पुरी"
    ],
    "name:hun_x_preferred": [
      "Puri"
    ],
    "name:ind_x_preferred": [
      "Puri"
    ],
    "name:ita_x_preferred": [
      "Puri"
    ],
    "name:jpn_x_preferred": [
      "プリー"
    ],
    "name:kan_x_preferred": [
      "ಪುರಿ"
    ],
    "name:kat_x_preferred": [
      "პური"
    ],
    "name:lit_x_preferred": [
      "Puris"
    ],
    "name:mai_x_preferred": [
      "पुरी"
    ],
    "name:mal_x_preferred": [
      "പുരി"
    ],
    "name:mar_x_preferred": [
      "पुरी"
    ],
    "name:msa_x_preferred": [
      "Puri"
    ],
    "name:nep_x_preferred": [
      "पुरी"
    ],
    "name:nld_x_preferred": [
      "Puri"
    ],
    "name:nno_x_preferred": [
      "Puri"
    ],
    "name:nor_x_preferred": [
      "Puri"
    ],
    "name:ori_x_preferred": [
      "ପୁରୀ"
    ],
    "name:pam_x_preferred": [
      "Puri"
    ],
    "name:pol_x_preferred": [
      "Puri"
    ],
    "name:ron_x_preferred": [
      "Puri"
    ],
    "name:rus_x_preferred": [
      "Пури"
    ],
    "name:san_x_preferred": [
      "जगन्नाथपुरी"
    ],
    "name:sco_x_preferred": [
      "Puri"
    ],
    "name:spa_x_preferred": [
      "Puri"
    ],
    "name:sqi_x_preferred": [
      "Puri"
    ],
    "name:srp_x_preferred": [
      "Пури"
    ],
    "name:swe_x_preferred": [
      "Puri"
    ],
    "name:tam_x_preferred": [
      "புரி"
    ],
    "name:tat_x_preferred": [
      "Пури"
    ],
    "name:tel_x_preferred": [
      "పూరీ పట్టణం"
    ],
    "name:ukr_x_preferred": [
      "Пурі"
    ],
    "name:urd_x_preferred": [
      "پوری"
    ],
    "name:vie_x_preferred": [
      "Puri"
    ],
    "name:war_x_preferred": [
      "Puri"
    ],
    "name:zho_x_preferred": [
      "普日"
    ],
    "wof:name": "Puri",
    "wof:placetype": "locality"
  },
  "geometry": {
    "coordinates": [
      86.2624,
      28.8099
    ],
    "type": "Point"
  }
}