{
  "type": "Feature",
  "properties": {
    "gn:admin1_code": "16.0",
    "gn:asciiname": "Layou",
    "gn:country_code": "CN",
    "gn:dem": 195,
    "gn:feature_class": "P",
    "gn:feature_code": "PPL",
    "gn:name": "Layou",
    "gn:population": 0,
    "gn:timezone": "Asia/Shanghai",
    "iso:country": "CN",
    "name:ara_x_preferred": [
      "لايو"
    ],
    "name:ceb_x_preferred": [
      "Layou"
    ],
    "name:deu_x_preferred": [
      "Layou"
    ],
    "name:fra_x_preferred": [
      "Layou"
    ],
    "name:lit_x_preferred": [
      "Laju"
    ],
    "name:pol_x_preferred": [
      "Layou"
    ],
    "name:ron_x_preferred": [
      "Layou"
    ],
    "name:rus_x_preferred": [
      "Лею"
    ],
    "name:urd_x_preferred": [
      "لایو"
    ],
    "name:zho_x_preferred": [
      "拉幽"
    ],
    "wof:name": "Layou",
    "wof:placetype": "locality"
  },
  "geometry": {
    "coordinates": [
      109.948,
      24.9587
    ],
    "type": "Point"
  }
}