{
  "type": "Feature",
  "properties": {
    "gn:admin1_code": "25",
    "gn:asciiname": "Fanzhuang",
    "gn:country_code": "CN",
    "gn:dem": 54,
    "gn:feature_class": "P",
    "gn:feature_code": "PPL",
    "gn:name": "Fanzhuang",
    "gn:population": 0,
    "gn:timezone": "Asia/Shanghai",
    "iso:country": "CN",
    "name:zho_x_preferred": [
      "樊庄"
    ],
    "name:zho_x_variant": [
      "范庄镇"
    ],
    "wof:name": "Fanzhuang",
    "wof:placetype": "locality"
  },
  "geometry": {
    "coordinates": [
      115.441,
      35.129
    ],
    "type": "Point"
  }
}