{
  "type": "Feature",
  "properties": {
    "gn:admin1_code": "30.0",
    "gn:asciiname": "Changjiaocun",
    "gn:country_code": "CN",
    "gn:dem": 240,
    "gn:feature_class": "P",
    "gn:feature_code": "PPL",
    "gn:name": "Changjiaocun",
    "gn:population": 0,
    "gn:timezone": "Asia/Shanghai",
    "iso:country": "CN",
    "name:und_x_variant": [
      "Changjiao"
    ],
    "name:zho_x_preferred": [
      "长教村"
    ],
    "name:zho_x_variant": [
      "长教"
    ],
    "wof:name": "Changjiaocun",
    "wof:placetype": "locality"
  },
  "geometry": {
    "coordinates": [
      116.36898,
      24.37532
    ],
    "type": "Point"
  }
}