{
  "type": "Feature",
  "properties": {
    "gn:admin1_code": "16.0",
    "gn:asciiname": "Tongzhi",
    "gn:country_code": "CN",
    "gn:dem": 151,
    "gn:feature_class": "P",
    "gn:feature_code": "PPL",
    "gn:name": "Tongzhi",
    "gn:population": 0,
    "gn:timezone": "Asia/Shanghai",
    "iso:country": "CN",
    "name:deu_x_preferred": [
      "Tongzhi"
    ],
    "name:ind_x_preferred": [
      "Tongzhi"
    ],
    "name:rus_x_preferred": [
      "Тунчжи"
    ],
    "name:ukr_x_preferred": [
      "Тунчжи"
    ],
    "name:zho_x_preferred": [
      "桐枝"
    ],
    "wof:name": "Tongzhi",
    "wof:placetype": "locality"
  },
  "geometry": {
    "coordinates": [
      107.635,
      22.3112
    ],
    "type": "Point"
  }
}