{
  "type": "Feature",
  "properties": {
    "gn:admin1_code": "12.0",
    "gn:asciiname": "Ganlu'an",
    "gn:country_code": "CN",
    "gn:dem": 61,
    "gn:feature_class": "P",
    "gn:feature_code": "PPL",
    "gn:name": "Ganlu’an",
    "gn:population": 0,
    "gn:timezone": "Asia/Shanghai",
    "iso:country": "CN",
    "name:zho_x_preferred": [
      "Ganlu’an"
    ],
    "name:zho_x_variant": [
      "甘露庵"
    ],
    "wof:name": "Ganlu'an",
    "wof:placetype": "locality"
  },
  "geometry": {
    "coordinates": [
      113.61881,
      31.24979
    ],
    "type": "Point"
  }
}