{
  "type": "Feature",
  "properties": {
    "gn:admin1_code": "25.0",
    "gn:asciiname": "Chewodaocun",
    "gn:country_code": "CN",
    "gn:dem": 32,
    "gn:feature_class": "P",
    "gn:feature_code": "PPL",
    "gn:name": "Chewodaocun",
    "gn:population": 0,
    "gn:timezone": "Asia/Shanghai",
    "iso:country": "CN",
    "name:zho_x_preferred": [
      "车卧岛村"
    ],
    "wof:name": "Chewodaocun",
    "wof:placetype": "locality"
  },
  "geometry": {
    "coordinates": [
      122.10014,
      37.09198
    ],
    "type": "Point"
  }
}