{
  "type": "Feature",
  "properties": {
    "gn:admin1_code": "04",
    "gn:asciiname": "Qidaogoucun",
    "gn:country_code": "CN",
    "gn:dem": 0,
    "gn:feature_class": "P",
    "gn:feature_code": "PPL",
    "gn:name": "Qidaogoucun",
    "gn:population": 0,
    "gn:timezone": "Asia/Shanghai",
    "iso:country": "CN",
    "name:und_x_variant": [
      "Ch’i-tao-kou",
      "Qidaogou",
      "七道沟",
      "Qidaogoucun"
    ],
    "name:zho_x_preferred": [
      "七道沟村"
    ],
    "wof:name": "Qidaogoucun",
    "wof:placetype": "locality"
  },
  "geometry": {
    "coordinates": [
      119.61249,
      34.35468
    ],
    "type": "Point"
  }
}