{
  "type": "Feature",
  "properties": {
    "gn:admin1_code": "30.0",
    "gn:asciiname": "Tangbei",
    "gn:country_code": "CN",
    "gn:dem": 55,
    "gn:feature_class": "P",
    "gn:feature_code": "PPL",
    "gn:name": "Tangbei",
    "gn:population": 0,
    "gn:timezone": "Asia/Shanghai",
    "iso:country": "CN",
    "name:zho_x_preferred": [
      "塘背"
    ],
    "wof:name": "Tangbei",
    "wof:placetype": "locality"
  },
  "geometry": {
    "coordinates": [
      112.20705,
      22.34653
    ],
    "type": "Point"
  }
}