{
  "type": "Feature",
  "properties": {
    "gn:admin1_code": "11.0",
    "gn:asciiname": "Lilin",
    "gn:country_code": "CN",
    "gn:dem": 186,
    "gn:feature_class": "P",
    "gn:feature_code": "PPL",
    "gn:name": "Lilin",
    "gn:population": 0,
    "gn:timezone": "Asia/Shanghai",
    "iso:country": "CN",
    "name:ara_x_preferred": [
      "ليلين"
    ],
    "name:ces_x_preferred": [
      "Lilú"
    ],
    "name:fra_x_preferred": [
      "Lilū"
    ],
    "name:hun_x_preferred": [
      "Lilin"
    ],
    "name:ita_x_preferred": [
      "Lilim"
    ],
    "name:jpn_x_preferred": [
      "リリン"
    ],
    "name:rus_x_preferred": [
      "Лилим"
    ],
    "name:spa_x_preferred": [
      "Lilim"
    ],
    "name:swe_x_preferred": [
      "Lilim"
    ],
    "name:zho_x_preferred": [
      "栎林"
    ],
    "wof:name": "Lilin",
    "wof:placetype": "locality"
  },
  "geometry": {
    "coordinates": [
      110.63183,
      27.99777000000001
    ],
    "type": "Point"
  }
}