{
  "type": "Feature",
  "properties": {
    "gn:admin1_code": "30",
    "gn:asciiname": "Baiji",
    "gn:country_code": "CN",
    "gn:dem": 25,
    "gn:feature_class": "P",
    "gn:feature_code": "PPL",
    "gn:name": "Baiji",
    "gn:population": 0,
    "gn:timezone": "Asia/Urumqi",
    "iso:country": "CN",
    "name:afr_x_preferred": [
      "Baiji"
    ],
    "name:ara_x_preferred": [
      "بايجي"
    ],
    "name:bre_x_preferred": [
      "Baiji"
    ],
    "name:ceb_x_preferred": [
      "Lipotes vexillifer"
    ],
    "name:ces_x_preferred": [
      "Delfínovec čínský"
    ],
    "name:dan_x_preferred": [
      "Kinesisk floddelfin"
    ],
    "name:deu_x_preferred": [
      "Chinesischer Flussdelfin"
    ],
    "name:epo_x_preferred": [
      "Blanknaĝila delfeno"
    ],
    "name:eus_x_preferred": [
      "Lipotes vexillifer"
    ],
    "name:fin_x_preferred": [
      "Kiinanjokidelfiini"
    ],
    "name:glg_x_preferred": [
      "Lipotes vexillifer"
    ],
    "name:hrv_x_preferred": [
      "Baiji"
    ],
    "name:hun_x_preferred": [
      "Kínai folyamidelfin"
    ],
    "name:ido_x_preferred": [
      "Baijio"
    ],
    "name:ina_x_preferred": [
      "Lipotes vexillifer"
    ],
    "name:ind_x_preferred": [
      "Baiji"
    ],
    "name:ita_x_preferred": [
      "Lipotes vexillifer"
    ],
    "name:jpn_x_preferred": [
      "ヨウスコウカワイルカ"
    ],
    "name:kaz_x_preferred": [
      "Байцзи дельфині"
    ],
    "name:kor_x_preferred": [
      "양쯔강돌고래"
    ],
    "name:nld_x_preferred": [
      "Chinese vlagdolfijn"
    ],
    "name:nno_x_preferred": [
      "Kinesisk elvedelfin"
    ],
    "name:nov_x_preferred": [
      "Lipotes vexillifer"
    ],
    "name:pnb_x_preferred": [
      "بائجی"
    ],
    "name:pol_x_preferred": [
      "Baji chiński"
    ],
    "name:por_x_preferred": [
      "Lipotes vexillifer"
    ],
    "name:ron_x_preferred": [
      "Baiji"
    ],
    "name:sco_x_preferred": [
      "Baiji"
    ],
    "name:spa_x_preferred": [
      "Lipotes vexillifer"
    ],
    "name:swe_x_preferred": [
      "Asiatisk floddelfin"
    ],
    "name:tha_x_preferred": [
      "โลมาแม่น้ำจีน"
    ],
    "name:ukr_x_preferred": [
      "Дельфін озерний"
    ],
    "name:war_x_preferred": [
      "Lipotes vexillifer"
    ],
    "name:wuu_x_preferred": [
      "白鳍豚"
    ],
    "name:zho_x_preferred": [
      "柏基"
    ],
    "name:zho_x_variant": [
      "白鱀豚"
    ],
    "wof:name": "Baiji",
    "wof:placetype": "locality"
  },
  "geometry": {
    "coordinates": [
      109.9455,
      21.22512
    ],
    "type": "Point"
  }
}