{
  "type": "Feature",
  "properties": {
    "gn:admin1_code": "29.0",
    "gn:asciiname": "Meizi",
    "gn:country_code": "CN",
    "gn:dem": 2368,
    "gn:feature_class": "P",
    "gn:feature_code": "PPL",
    "gn:name": "Meizi",
    "gn:population": 0,
    "gn:timezone": "Asia/Shanghai",
    "iso:country": "CN",
    "name:zho_x_preferred": [
      "美自"
    ],
    "wof:name": "Meizi",
    "wof:placetype": "locality"
  },
  "geometry": {
    "coordinates": [
      100.298,
      26.8191
    ],
    "type": "Point"
  }
}