{
  "type": "Feature",
  "properties": {
    "gn:admin1_code": "12.0",
    "gn:asciiname": "Xiaqi Nanping",
    "gn:country_code": "CN",
    "gn:dem": 908,
    "gn:feature_class": "P",
    "gn:feature_code": "PPL",
    "gn:name": "Xiaqi Nanping",
    "gn:population": 0,
    "gn:timezone": "Asia/Shanghai",
    "iso:country": "CN",
    "name:zho_x_preferred": [
      "Xiaqi Nanping"
    ],
    "name:zho_x_variant": [
      "下七男坪"
    ],
    "wof:name": "Xiaqi Nanping",
    "wof:placetype": "locality"
  },
  "geometry": {
    "coordinates": [
      110.25431,
      29.73308
    ],
    "type": "Point"
  }
}