{
  "type": "Feature",
  "properties": {
    "gn:admin1_code": "19",
    "gn:asciiname": "Luyang",
    "gn:country_code": "CN",
    "gn:dem": 16,
    "gn:elevation": "0.0",
    "gn:feature_class": "P",
    "gn:feature_code": "PPLA4",
    "gn:name": "Lüyang",
    "gn:population": 0,
    "gn:timezone": "Asia/Shanghai",
    "iso:country": "CN",
    "name:und_x_variant": [
      "Yen-yang-tse",
      "Lüyangyi",
      "Lü-yang-i",
      "Lüyang"
    ],
    "name:zho_x_preferred": [
      "闾阳"
    ],
    "name:zho_x_variant": [
      "Lüyang Zhen",
      "闾阳镇"
    ],
    "wof:name": "Luyang",
    "wof:placetype": "locality"
  },
  "geometry": {
    "coordinates": [
      121.66632,
      41.38193
    ],
    "type": "Point"
  }
}