{
  "type": "Feature",
  "properties": {
    "gn:admin1_code": "16.0",
    "gn:asciiname": "Honglai",
    "gn:country_code": "CN",
    "gn:dem": 138,
    "gn:feature_class": "P",
    "gn:feature_code": "PPL",
    "gn:name": "Honglai",
    "gn:population": 0,
    "gn:timezone": "Asia/Shanghai",
    "iso:country": "CN",
    "name:zho_x_preferred": [
      "红赖"
    ],
    "wof:name": "Honglai",
    "wof:placetype": "locality"
  },
  "geometry": {
    "coordinates": [
      109.594,
      24.1368
    ],
    "type": "Point"
  }
}