{
  "type": "Feature",
  "properties": {
    "gn:admin1_code": "12.0",
    "gn:asciiname": "Hejiapo",
    "gn:country_code": "CN",
    "gn:dem": 778,
    "gn:feature_class": "P",
    "gn:feature_code": "PPL",
    "gn:name": "Hejiapo",
    "gn:population": 0,
    "gn:timezone": "Asia/Shanghai",
    "iso:country": "CN",
    "name:zho_x_preferred": [
      "何家坡"
    ],
    "wof:name": "Hejiapo",
    "wof:placetype": "locality"
  },
  "geometry": {
    "coordinates": [
      109.3691,
      29.57141
    ],
    "type": "Point"
  }
}