{
  "type": "Feature",
  "properties": {
    "gn:admin1_code": "5.0",
    "gn:asciiname": "Yuejia Shaoguo",
    "gn:country_code": "CN",
    "gn:dem": 331,
    "gn:feature_class": "P",
    "gn:feature_code": "PPL",
    "gn:name": "Yuejia Shaoguo",
    "gn:population": 0,
    "gn:timezone": "Asia/Shanghai",
    "iso:country": "CN",
    "name:zho_x_preferred": [
      "岳家烧锅"
    ],
    "wof:name": "Yuejia Shaoguo",
    "wof:placetype": "locality"
  },
  "geometry": {
    "coordinates": [
      125.01662,
      42.78291
    ],
    "type": "Point"
  }
}