{
  "type": "Feature",
  "properties": {
    "gn:admin1_code": "19.0",
    "gn:asciiname": "Yejia Wopeng",
    "gn:country_code": "CN",
    "gn:dem": 46,
    "gn:feature_class": "P",
    "gn:feature_code": "PPL",
    "gn:name": "Yejia Wopeng",
    "gn:population": 0,
    "gn:timezone": "Asia/Shanghai",
    "iso:country": "CN",
    "name:zho_x_preferred": [
      "叶家窝棚"
    ],
    "wof:name": "Yejia Wopeng",
    "wof:placetype": "locality"
  },
  "geometry": {
    "coordinates": [
      120.2146,
      40.27352
    ],
    "type": "Point"
  }
}