{
  "type": "Feature",
  "properties": {
    "gn:admin1_code": "7.0",
    "gn:asciiname": "Qiaoli",
    "gn:country_code": "CN",
    "gn:dem": 191,
    "gn:feature_class": "P",
    "gn:feature_code": "PPL",
    "gn:name": "Qiaoli",
    "gn:population": 0,
    "gn:timezone": "Asia/Shanghai",
    "iso:country": "CN",
    "name:zho_x_preferred": [
      "桥里"
    ],
    "wof:name": "Qiaoli",
    "wof:placetype": "locality"
  },
  "geometry": {
    "coordinates": [
      119.46711,
      25.80635
    ],
    "type": "Point"
  }
}