{
  "type": "Feature",
  "properties": {
    "gn:admin1_code": "16.0",
    "gn:asciiname": "Anle",
    "gn:country_code": "CN",
    "gn:dem": 799,
    "gn:feature_class": "P",
    "gn:feature_code": "PPL",
    "gn:name": "Anle",
    "gn:population": 0,
    "gn:timezone": "Asia/Shanghai",
    "iso:country": "CN",
    "name:ceb_x_preferred": [
      "Anle"
    ],
    "name:deu_x_preferred": [
      "Anle"
    ],
    "name:swe_x_preferred": [
      "Anle"
    ],
    "name:zho_x_preferred": [
      "安乐"
    ],
    "wof:name": "Anle",
    "wof:placetype": "locality"
  },
  "geometry": {
    "coordinates": [
      106.344,
      23.2972
    ],
    "type": "Point"
  }
}