{
  "type": "Feature",
  "properties": {
    "gn:admin1_code": "8.0",
    "gn:asciiname": "Jinhe Erfenchang Sanshiqidui",
    "gn:country_code": "CN",
    "gn:dem": 370,
    "gn:feature_class": "P",
    "gn:feature_code": "PPLF",
    "gn:name": "Jinhe Erfenchang Sanshiqidui",
    "gn:population": 0,
    "gn:timezone": "Asia/Shanghai",
    "iso:country": "CN",
    "name:und_x_variant": [
      "锦河二分场三十七队"
    ],
    "wof:name": "Jinhe Erfenchang Sanshiqidui",
    "wof:placetype": "locality"
  },
  "geometry": {
    "coordinates": [
      127.03819,
      49.88531
    ],
    "type": "Point"
  }
}