{
  "type": "Feature",
  "properties": {
    "gn:admin1_code": "12.0",
    "gn:asciiname": "Huangchang",
    "gn:country_code": "CN",
    "gn:dem": 54,
    "gn:feature_class": "P",
    "gn:feature_code": "PPL",
    "gn:name": "Huangchang",
    "gn:population": 0,
    "gn:timezone": "Asia/Shanghai",
    "iso:country": "CN",
    "name:zho_x_preferred": [
      "黄厂"
    ],
    "wof:name": "Huangchang",
    "wof:placetype": "locality"
  },
  "geometry": {
    "coordinates": [
      115.53736,
      30.22037000000001
    ],
    "type": "Point"
  }
}