{
  "type": "Feature",
  "properties": {
    "gn:admin1_code": "30.0",
    "gn:asciiname": "Xinyu",
    "gn:country_code": "CN",
    "gn:dem": 22,
    "gn:feature_class": "P",
    "gn:feature_code": "PPL",
    "gn:name": "Xinyu",
    "gn:population": 0,
    "gn:timezone": "Asia/Shanghai",
    "iso:country": "CN",
    "name:ara_x_preferred": [
      "شينيو"
    ],
    "name:cdo_x_preferred": [
      "Sĭng-ṳ̀"
    ],
    "name:ceb_x_preferred": [
      "Xinyu"
    ],
    "name:ces_x_preferred": [
      "Sin-jü"
    ],
    "name:dan_x_preferred": [
      "Xinyu"
    ],
    "name:deu_x_preferred": [
      "Xinyu"
    ],
    "name:eus_x_preferred": [
      "Xinyu"
    ],
    "name:fas_x_preferred": [
      "شینیو"
    ],
    "name:fin_x_preferred": [
      "Xinyu"
    ],
    "name:fra_x_preferred": [
      "Xinyu"
    ],
    "name:hak_x_preferred": [
      "Sîn-yì-sṳ"
    ],
    "name:heb_x_preferred": [
      "קסיניו"
    ],
    "name:hun_x_preferred": [
      "Xinyu"
    ],
    "name:ita_x_preferred": [
      "Xinyu"
    ],
    "name:jpn_x_preferred": [
      "新余市"
    ],
    "name:kik_x_preferred": [
      "Xinyu"
    ],
    "name:kor_x_preferred": [
      "신위시"
    ],
    "name:mlg_x_preferred": [
      "Xinyu"
    ],
    "name:nld_x_preferred": [
      "Xinyu"
    ],
    "name:nno_x_preferred": [
      "Xinyu"
    ],
    "name:nor_x_preferred": [
      "Xinyu"
    ],
    "name:pol_x_preferred": [
      "Xinyu"
    ],
    "name:rus_x_preferred": [
      "Синьюй"
    ],
    "name:spa_x_preferred": [
      "Xinyu"
    ],
    "name:swe_x_preferred": [
      "Xinyu"
    ],
    "name:tur_x_preferred": [
      "Xinyu"
    ],
    "name:urd_x_preferred": [
      "شینیو"
    ],
    "name:vie_x_preferred": [
      "Tân Dư"
    ],
    "name:war_x_preferred": [
      "Xinyu"
    ],
    "name:wuu_x_preferred": [
      "新余市"
    ],
    "name:zho_x_preferred": [
      "新余"
    ],
    "name:zho_x_variant": [
      "新余市"
    ],
    "wof:name": "Xinyu",
    "wof:placetype": "locality"
  },
  "geometry": {
    "coordinates": [
      112.70091,
      22.27236
    ],
    "type": "Point"
  }
}