{
  "type": "Feature",
  "properties": {
    "gn:admin1_code": "3.0",
    "gn:asciiname": "Yangfancun",
    "gn:country_code": "CN",
    "gn:dem": 26,
    "gn:feature_class": "P",
    "gn:feature_code": "PPL",
    "gn:name": "Yangfancun",
    "gn:population": 0,
    "gn:timezone": "Asia/Shanghai",
    "iso:country": "CN",
    "name:und_x_variant": [
      "秧畈村"
    ],
    "wof:name": "Yangfancun",
    "wof:placetype": "locality"
  },
  "geometry": {
    "coordinates": [
      116.88805,
      28.35196
    ],
    "type": "Point"
  }
}