{
  "type": "Feature",
  "properties": {
    "gn:admin1_code": "2.0",
    "gn:asciiname": "Shangfang",
    "gn:country_code": "CN",
    "gn:dem": 36,
    "gn:feature_class": "P",
    "gn:feature_code": "PPL",
    "gn:name": "Shangfang",
    "gn:population": 0,
    "gn:timezone": "Asia/Shanghai",
    "iso:country": "CN",
    "name:zho_x_preferred": [
      "上方"
    ],
    "name:zho_x_variant": [
      "上方山国家森林公园"
    ],
    "wof:name": "Shangfang",
    "wof:placetype": "locality"
  },
  "geometry": {
    "coordinates": [
      120.25709,
      29.60036
    ],
    "type": "Point"
  }
}