{
  "type": "Feature",
  "properties": {
    "gn:admin1_code": "5.0",
    "gn:asciiname": "Wudao Yingzi Wopu",
    "gn:country_code": "CN",
    "gn:dem": 163,
    "gn:feature_class": "P",
    "gn:feature_code": "PPL",
    "gn:name": "Wudao Yingzi Wopu",
    "gn:population": 0,
    "gn:timezone": "Asia/Shanghai",
    "iso:country": "CN",
    "name:zho_x_preferred": [
      "五道营子窝铺"
    ],
    "wof:name": "Wudao Yingzi Wopu",
    "wof:placetype": "locality"
  },
  "geometry": {
    "coordinates": [
      122.33826,
      44.31921
    ],
    "type": "Point"
  }
}