{
  "type": "Feature",
  "properties": {
    "gn:admin1_code": "11.0",
    "gn:asciiname": "Yijiawan",
    "gn:country_code": "CN",
    "gn:dem": 187,
    "gn:feature_class": "P",
    "gn:feature_code": "PPL",
    "gn:name": "Yijiawan",
    "gn:population": 0,
    "gn:timezone": "Asia/Shanghai",
    "iso:country": "CN",
    "name:zho_x_preferred": [
      "易家湾"
    ],
    "name:zho_x_variant": [
      "易家湾镇"
    ],
    "wof:name": "Yijiawan",
    "wof:placetype": "locality"
  },
  "geometry": {
    "coordinates": [
      113.74653,
      28.95327
    ],
    "type": "Point"
  }
}