{
  "type": "Feature",
  "properties": {
    "gn:admin1_code": "25",
    "gn:asciiname": "Yulindian",
    "gn:country_code": "CN",
    "gn:dem": 90,
    "gn:feature_class": "P",
    "gn:feature_code": "PPL",
    "gn:name": "Yulindian",
    "gn:population": 0,
    "gn:timezone": "Asia/Shanghai",
    "iso:country": "CN",
    "name:fas_x_preferred": [
      "یولیندیان"
    ],
    "name:urd_x_preferred": [
      "یولانڈین"
    ],
    "name:zho_x_preferred": [
      "榆林店"
    ],
    "name:zho_x_variant": [
      "玉林店镇"
    ],
    "wof:name": "Yulindian",
    "wof:placetype": "locality"
  },
  "geometry": {
    "coordinates": [
      118.571,
      36.549
    ],
    "type": "Point"
  }
}