{
  "type": "Feature",
  "properties": {
    "gn:admin1_code": "26.0",
    "gn:asciiname": "Songjialingcun",
    "gn:country_code": "CN",
    "gn:dem": 1296,
    "gn:feature_class": "P",
    "gn:feature_code": "PPL",
    "gn:name": "Songjialingcun",
    "gn:population": 0,
    "gn:timezone": "Asia/Shanghai",
    "iso:country": "CN",
    "name:zho_x_preferred": [
      "宋家岭村"
    ],
    "wof:name": "Songjialingcun",
    "wof:placetype": "locality"
  },
  "geometry": {
    "coordinates": [
      106.75979,
      34.81547
    ],
    "type": "Point"
  }
}