{
  "type": "Feature",
  "properties": {
    "gn:admin1_code": "18",
    "gn:asciiname": "Zhaoshanba",
    "gn:country_code": "CN",
    "gn:dem": 808,
    "gn:feature_class": "P",
    "gn:feature_code": "PPL",
    "gn:name": "Zhaoshanba",
    "gn:population": 0,
    "gn:timezone": "Asia/Shanghai",
    "iso:country": "CN",
    "name:zho_x_preferred": [
      "赵山坝"
    ],
    "wof:name": "Zhaoshanba",
    "wof:placetype": "locality"
  },
  "geometry": {
    "coordinates": [
      107.233,
      27.6215
    ],
    "type": "Point"
  }
}