{
  "type": "Feature",
  "properties": {
    "gn:admin1_code": "24",
    "gn:asciiname": "Zhiyu",
    "gn:country_code": "CN",
    "gn:dem": 1259,
    "gn:feature_class": "P",
    "gn:feature_code": "PPL",
    "gn:name": "Zhiyu",
    "gn:population": 0,
    "gn:timezone": "Asia/Shanghai",
    "iso:country": "CN",
    "name:und_x_variant": [
      "Chih-yü-ts’un",
      "Ssu-yü-ts’un",
      "Ssu-yü",
      "Zhiyu",
      "峙峪"
    ],
    "wof:name": "Zhiyu",
    "wof:placetype": "locality"
  },
  "geometry": {
    "coordinates": [
      112.3486,
      39.39908
    ],
    "type": "Point"
  }
}