{
  "type": "Feature",
  "properties": {
    "gn:admin1_code": "26.0",
    "gn:asciiname": "Shaoguoyuan",
    "gn:country_code": "CN",
    "gn:dem": 1129,
    "gn:feature_class": "P",
    "gn:feature_code": "PPL",
    "gn:name": "Shaoguoyuan",
    "gn:population": 0,
    "gn:timezone": "Asia/Shanghai",
    "iso:country": "CN",
    "name:zho_x_preferred": [
      "烧锅院"
    ],
    "wof:name": "Shaoguoyuan",
    "wof:placetype": "locality"
  },
  "geometry": {
    "coordinates": [
      108.94204,
      35.43916
    ],
    "type": "Point"
  }
}