{
  "type": "Feature",
  "properties": {
    "gn:admin1_code": "31.0",
    "gn:asciiname": "Lanxi",
    "gn:country_code": "CN",
    "gn:dem": 83,
    "gn:feature_class": "P",
    "gn:feature_code": "PPL",
    "gn:name": "Lanxi",
    "gn:population": 0,
    "gn:timezone": "Asia/Shanghai",
    "iso:country": "CN",
    "name:ara_x_preferred": [
      "لانكسي"
    ],
    "name:ben_x_preferred": [
      "ল্যানশি"
    ],
    "name:ceb_x_preferred": [
      "Lanxi"
    ],
    "name:deu_x_preferred": [
      "Lanxi"
    ],
    "name:ell_x_preferred": [
      "Λάνξι"
    ],
    "name:eng_x_preferred": [
      "Lanxi"
    ],
    "name:fas_x_preferred": [
      "لانکسی"
    ],
    "name:fra_x_preferred": [
      "Lanxi"
    ],
    "name:heb_x_preferred": [
      "לנקסי"
    ],
    "name:hin_x_preferred": [
      "लैंक्सी"
    ],
    "name:hun_x_preferred": [
      "Lanxi"
    ],
    "name:ind_x_preferred": [
      "Lanxi"
    ],
    "name:ita_x_preferred": [
      "Lanxi"
    ],
    "name:kor_x_preferred": [
      "란시"
    ],
    "name:mlg_x_preferred": [
      "Lanxi"
    ],
    "name:nld_x_preferred": [
      "Lanxi"
    ],
    "name:nor_x_preferred": [
      "Lanxi"
    ],
    "name:pol_x_preferred": [
      "Lanxi"
    ],
    "name:por_x_preferred": [
      "Lanxi"
    ],
    "name:rus_x_preferred": [
      "Ланьси"
    ],
    "name:spa_x_preferred": [
      "Lanxi"
    ],
    "name:tur_x_preferred": [
      "Lanxi"
    ],
    "name:ukr_x_preferred": [
      "Ланьсі"
    ],
    "name:urd_x_preferred": [
      "لینزی"
    ],
    "name:vie_x_preferred": [
      "Lan Khê"
    ],
    "name:zho_x_preferred": [
      "兰溪"
    ],
    "wof:name": "Lanxi",
    "wof:placetype": "locality"
  },
  "geometry": {
    "coordinates": [
      110.50446,
      19.54404
    ],
    "type": "Point"
  }
}