{
  "type": "Feature",
  "properties": {
    "gn:admin1_code": "3.0",
    "gn:asciiname": "Huairen",
    "gn:country_code": "CN",
    "gn:dem": 177,
    "gn:feature_class": "P",
    "gn:feature_code": "PPL",
    "gn:name": "Huairen",
    "gn:population": 0,
    "gn:timezone": "Asia/Shanghai",
    "iso:country": "CN",
    "name:ceb_x_preferred": [
      "Huairen Xian"
    ],
    "name:deu_x_preferred": [
      "Huairen"
    ],
    "name:fas_x_preferred": [
      "شهرستان هوایرن"
    ],
    "name:ita_x_preferred": [
      "Huairen"
    ],
    "name:jpn_x_preferred": [
      "懐仁市"
    ],
    "name:kor_x_preferred": [
      "화이런시"
    ],
    "name:nor_x_preferred": [
      "Huairen"
    ],
    "name:rus_x_preferred": [
      "Хуайжэнь"
    ],
    "name:swe_x_preferred": [
      "Huairen"
    ],
    "name:und_x_variant": [
      "怀仁"
    ],
    "name:urd_x_preferred": [
      "ہوایرین"
    ],
    "name:vie_x_preferred": [
      "Hoài Nhân"
    ],
    "name:zho_x_preferred": [
      "怀仁市"
    ],
    "wof:name": "Huairen",
    "wof:placetype": "locality"
  },
  "geometry": {
    "coordinates": [
      115.73623,
      25.62543
    ],
    "type": "Point"
  }
}