{
  "type": "Feature",
  "properties": {
    "gn:admin1_code": "2.0",
    "gn:asciiname": "Changyang",
    "gn:country_code": "CN",
    "gn:dem": 604,
    "gn:feature_class": "P",
    "gn:feature_code": "PPL",
    "gn:name": "Changyang",
    "gn:population": 0,
    "gn:timezone": "Asia/Shanghai",
    "iso:country": "CN",
    "name:zho_x_preferred": [
      "长洋"
    ],
    "name:zho_x_variant": [
      "长阳"
    ],
    "wof:name": "Changyang",
    "wof:placetype": "locality"
  },
  "geometry": {
    "coordinates": [
      120.33848,
      28.97606
    ],
    "type": "Point"
  }
}