{
  "type": "Feature",
  "properties": {
    "gn:admin1_code": "26.0",
    "gn:asciiname": "Changjia Hutong",
    "gn:country_code": "CN",
    "gn:dem": 1173,
    "gn:feature_class": "P",
    "gn:feature_code": "PPL",
    "gn:name": "Changjia Hutong",
    "gn:population": 0,
    "gn:timezone": "Asia/Shanghai",
    "iso:country": "CN",
    "name:zho_x_preferred": [
      "常家胡同"
    ],
    "wof:name": "Changjia Hutong",
    "wof:placetype": "locality"
  },
  "geometry": {
    "coordinates": [
      107.74357,
      35.19318
    ],
    "type": "Point"
  }
}