{
  "type": "Feature",
  "properties": {
    "gn:admin1_code": "11.0",
    "gn:asciiname": "Maoping Lijia",
    "gn:country_code": "CN",
    "gn:dem": 333,
    "gn:feature_class": "P",
    "gn:feature_code": "PPL",
    "gn:name": "Maoping Lijia",
    "gn:population": 0,
    "gn:timezone": "Asia/Shanghai",
    "iso:country": "CN",
    "name:zho_x_preferred": [
      "茅坪李家"
    ],
    "wof:name": "Maoping Lijia",
    "wof:placetype": "locality"
  },
  "geometry": {
    "coordinates": [
      111.00611,
      26.81784
    ],
    "type": "Point"
  }
}