{
  "type": "Feature",
  "properties": {
    "gn:admin1_code": "2.0",
    "gn:asciiname": "Zongtang",
    "gn:country_code": "CN",
    "gn:dem": 82,
    "gn:feature_class": "P",
    "gn:feature_code": "PPL",
    "gn:name": "Zongtang",
    "gn:population": 0,
    "gn:timezone": "Asia/Shanghai",
    "iso:country": "CN",
    "name:zho_x_preferred": [
      "宗塘"
    ],
    "wof:name": "Zongtang",
    "wof:placetype": "locality"
  },
  "geometry": {
    "coordinates": [
      120.09974,
      29.29761
    ],
    "type": "Point"
  }
}