{
  "type": "Feature",
  "properties": {
    "gn:admin1_code": "11.0",
    "gn:asciiname": "Banqiao",
    "gn:country_code": "CN",
    "gn:dem": 73,
    "gn:feature_class": "P",
    "gn:feature_code": "PPL",
    "gn:name": "Banqiao",
    "gn:population": 0,
    "gn:timezone": "Asia/Shanghai",
    "iso:country": "CN",
    "name:ceb_x_preferred": [
      "Banqiao"
    ],
    "name:deu_x_preferred": [
      "Banqiao"
    ],
    "name:kor_x_preferred": [
      "판교구"
    ],
    "name:swe_x_preferred": [
      "Banqiao"
    ],
    "name:zho_x_preferred": [
      "板桥"
    ],
    "name:zho_x_variant": [
      "板橋區"
    ],
    "wof:name": "Banqiao",
    "wof:placetype": "locality"
  },
  "geometry": {
    "coordinates": [
      112.88882,
      27.27212
    ],
    "type": "Point"
  }
}