{
  "type": "Feature",
  "properties": {
    "gn:admin1_code": "11.0",
    "gn:asciiname": "Da'ao",
    "gn:country_code": "CN",
    "gn:dem": 771,
    "gn:feature_class": "P",
    "gn:feature_code": "PPL",
    "gn:name": "Da’ao",
    "gn:population": 0,
    "gn:timezone": "Asia/Shanghai",
    "iso:country": "CN",
    "name:und_x_variant": [
      "Da’ao"
    ],
    "name:zho_x_preferred": [
      "大坳"
    ],
    "wof:name": "Da'ao",
    "wof:placetype": "locality"
  },
  "geometry": {
    "coordinates": [
      110.46573,
      28.09281
    ],
    "type": "Point"
  }
}