{
  "type": "Feature",
  "properties": {
    "gn:admin1_code": "16",
    "gn:asciiname": "Fuyang",
    "gn:country_code": "CN",
    "gn:dem": 222,
    "gn:feature_class": "P",
    "gn:feature_code": "PPLA3",
    "gn:name": "Fuyang",
    "gn:population": 0,
    "gn:timezone": "Asia/Shanghai",
    "iso:country": "CN",
    "name:afr_x_preferred": [
      "Fuyang"
    ],
    "name:ara_x_preferred": [
      "فويانغ"
    ],
    "name:cdo_x_preferred": [
      "Pâiu-iòng"
    ],
    "name:ceb_x_preferred": [
      "Fuyang Shi"
    ],
    "name:ces_x_preferred": [
      "Fu-jang"
    ],
    "name:cym_x_preferred": [
      "Fuyang"
    ],
    "name:dan_x_preferred": [
      "Fuyang"
    ],
    "name:deu_x_preferred": [
      "Fuyang"
    ],
    "name:eus_x_preferred": [
      "Fuyang"
    ],
    "name:fas_x_preferred": [
      "فویانگ"
    ],
    "name:fin_x_preferred": [
      "Fuyang"
    ],
    "name:fra_x_preferred": [
      "Fuyang"
    ],
    "name:hak_x_preferred": [
      "Fu-yòng-sṳ"
    ],
    "name:hye_x_preferred": [
      "Ֆույան"
    ],
    "name:ita_x_preferred": [
      "Fuyang"
    ],
    "name:jpn_x_preferred": [
      "阜陽"
    ],
    "name:jpn_x_variant": [
      "阜陽市"
    ],
    "name:kik_x_preferred": [
      "Fuyang"
    ],
    "name:kor_x_preferred": [
      "푸양시"
    ],
    "name:mlg_x_preferred": [
      "Fuyang"
    ],
    "name:nld_x_preferred": [
      "Fuyang"
    ],
    "name:nno_x_preferred": [
      "Fuyang"
    ],
    "name:nor_x_preferred": [
      "Fuyang"
    ],
    "name:pam_x_preferred": [
      "Fuyang"
    ],
    "name:pnb_x_preferred": [
      "فویانگ"
    ],
    "name:pol_x_preferred": [
      "Fuyang"
    ],
    "name:por_x_preferred": [
      "Fuyang"
    ],
    "name:rus_x_preferred": [
      "Фуян"
    ],
    "name:spa_x_preferred": [
      "Fuyang"
    ],
    "name:swe_x_preferred": [
      "Fuyang"
    ],
    "name:tgl_x_preferred": [
      "Fuyang"
    ],
    "name:tur_x_preferred": [
      "Fuyang"
    ],
    "name:und_x_variant": [
      "Fuchuan",
      "Fuchwan",
      "Fu-yang-chen",
      "Fuchwan-hsien"
    ],
    "name:urd_x_preferred": [
      "فویانگ"
    ],
    "name:vie_x_preferred": [
      "Phụ Dương"
    ],
    "name:war_x_preferred": [
      "Fuyang"
    ],
    "name:wuu_x_preferred": [
      "阜阳市"
    ],
    "name:zho_x_preferred": [
      "Chiu-fu-ch’uan"
    ],
    "name:zho_x_variant": [
      "Fu-ch’uan-hsien",
      "阜阳市"
    ],
    "wof:name": "Fuyang",
    "wof:placetype": "locality"
  },
  "geometry": {
    "coordinates": [
      111.25802,
      24.83441
    ],
    "type": "Point"
  }
}