{
  "type": "Feature",
  "properties": {
    "gn:admin1_code": "8.0",
    "gn:asciiname": "Hongshilazi",
    "gn:country_code": "CN",
    "gn:dem": 213,
    "gn:feature_class": "P",
    "gn:feature_code": "PPL",
    "gn:name": "Hongshilazi",
    "gn:population": 0,
    "gn:timezone": "Asia/Shanghai",
    "iso:country": "CN",
    "name:und_x_variant": [
      "红石砬子"
    ],
    "wof:name": "Hongshilazi",
    "wof:placetype": "locality"
  },
  "geometry": {
    "coordinates": [
      130.7969,
      43.99947
    ],
    "type": "Point"
  }
}