{
  "type": "Feature",
  "properties": {
    "gn:admin1_code": "30.0",
    "gn:asciiname": "Changling",
    "gn:country_code": "CN",
    "gn:dem": 12,
    "gn:feature_class": "P",
    "gn:feature_code": "PPL",
    "gn:name": "Changling",
    "gn:population": 0,
    "gn:timezone": "Asia/Shanghai",
    "iso:country": "CN",
    "name:ara_x_preferred": [
      "تشانجلينج"
    ],
    "name:ben_x_preferred": [
      "চ্যাংলিং"
    ],
    "name:ceb_x_preferred": [
      "Changling"
    ],
    "name:deu_x_preferred": [
      "Changling"
    ],
    "name:ell_x_preferred": [
      "Τσαντσλίνγκ"
    ],
    "name:heb_x_preferred": [
      "צ'אנגלינג"
    ],
    "name:hin_x_preferred": [
      "चैंगलिंग"
    ],
    "name:hun_x_preferred": [
      "Changling"
    ],
    "name:ind_x_preferred": [
      "Changling"
    ],
    "name:mlg_x_preferred": [
      "Changling"
    ],
    "name:por_x_preferred": [
      "Changling"
    ],
    "name:swe_x_preferred": [
      "Changling"
    ],
    "name:tur_x_preferred": [
      "Changling"
    ],
    "name:ukr_x_preferred": [
      "Чанлін"
    ],
    "name:zho_x_preferred": [
      "长岭"
    ],
    "wof:name": "Changling",
    "wof:placetype": "locality"
  },
  "geometry": {
    "coordinates": [
      114.51039,
      23.14466
    ],
    "type": "Point"
  }
}