{
  "type": "Feature",
  "properties": {
    "gn:admin1_code": "21.0",
    "gn:asciiname": "Langshui",
    "gn:country_code": "CN",
    "gn:dem": 1860,
    "gn:feature_class": "P",
    "gn:feature_code": "PPL",
    "gn:name": "Langshui",
    "gn:population": 0,
    "gn:timezone": "Asia/Shanghai",
    "iso:country": "CN",
    "name:zho_x_preferred": [
      "浪水"
    ],
    "wof:name": "Langshui",
    "wof:placetype": "locality"
  },
  "geometry": {
    "coordinates": [
      105.431,
      36.7893
    ],
    "type": "Point"
  }
}