{
  "type": "Feature",
  "properties": {
    "gn:admin1_code": "13",
    "gn:asciiname": "Yiling'ertuannong Sanlian",
    "gn:country_code": "CN",
    "gn:dem": 446,
    "gn:feature_class": "P",
    "gn:feature_code": "PPL",
    "gn:name": "Yiling’ertuannong Sanlian",
    "gn:population": 0,
    "gn:timezone": "Asia/Urumqi",
    "iso:country": "CN",
    "name:und_x_variant": [
      "Yiling’ertuannong Sanlian"
    ],
    "name:zho_x_preferred": [
      "一零二团农三连"
    ],
    "wof:name": "Yiling'ertuannong Sanlian",
    "wof:placetype": "locality"
  },
  "geometry": {
    "coordinates": [
      87.61655,
      44.32579000000001
    ],
    "type": "Point"
  }
}