{
  "type": "Feature",
  "properties": {
    "gn:admin1_code": "18.0",
    "gn:asciiname": "Jiaolong",
    "gn:country_code": "CN",
    "gn:dem": 692,
    "gn:feature_class": "P",
    "gn:feature_code": "PPL",
    "gn:name": "Jiaolong",
    "gn:population": 0,
    "gn:timezone": "Asia/Shanghai",
    "iso:country": "CN",
    "name:msa_x_preferred": [
      "Jiaolong"
    ],
    "name:pol_x_preferred": [
      "Jiaolong"
    ],
    "name:vie_x_preferred": [
      "Thuồng luồng"
    ],
    "name:zho_x_preferred": [
      "蛟龙"
    ],
    "wof:name": "Jiaolong",
    "wof:placetype": "locality"
  },
  "geometry": {
    "coordinates": [
      107.742,
      27.0281
    ],
    "type": "Point"
  }
}