{
  "type": "Feature",
  "properties": {
    "gn:admin1_code": "12.0",
    "gn:asciiname": "Xintai",
    "gn:country_code": "CN",
    "gn:dem": 27,
    "gn:feature_class": "P",
    "gn:feature_code": "PPL",
    "gn:name": "Xintai",
    "gn:population": 0,
    "gn:timezone": "Asia/Shanghai",
    "iso:country": "CN",
    "name:ceb_x_preferred": [
      "Xintai"
    ],
    "name:deu_x_preferred": [
      "Xintai"
    ],
    "name:fra_x_preferred": [
      "Xintai"
    ],
    "name:ita_x_preferred": [
      "Xintai"
    ],
    "name:jpn_x_preferred": [
      "新泰市"
    ],
    "name:kik_x_preferred": [
      "Xintai"
    ],
    "name:kor_x_preferred": [
      "신타이시"
    ],
    "name:mlg_x_preferred": [
      "Xintai"
    ],
    "name:nor_x_preferred": [
      "Xintai"
    ],
    "name:rus_x_preferred": [
      "Синьтай"
    ],
    "name:srp_x_preferred": [
      "Синтај"
    ],
    "name:swe_x_preferred": [
      "Xintai"
    ],
    "name:ukr_x_preferred": [
      "Сіньтай"
    ],
    "name:vie_x_preferred": [
      "Tân Thái"
    ],
    "name:war_x_preferred": [
      "Xintai"
    ],
    "name:zho_x_preferred": [
      "新台"
    ],
    "name:zho_x_variant": [
      "新泰市"
    ],
    "wof:name": "Xintai",
    "wof:placetype": "locality"
  },
  "geometry": {
    "coordinates": [
      113.57923,
      30.80354
    ],
    "type": "Point"
  }
}