{
  "type": "Feature",
  "properties": {
    "gn:admin1_code": "29",
    "gn:asciiname": "Datun",
    "gn:country_code": "CN",
    "gn:dem": 1892,
    "gn:feature_class": "P",
    "gn:feature_code": "PPL",
    "gn:name": "Datun",
    "gn:population": 0,
    "gn:timezone": "Asia/Shanghai",
    "iso:country": "CN",
    "name:rus_x_preferred": [
      "Датун"
    ],
    "name:zho_x_preferred": [
      "大屯"
    ],
    "wof:name": "Datun",
    "wof:placetype": "locality"
  },
  "geometry": {
    "coordinates": [
      102.463,
      24.9103
    ],
    "type": "Point"
  }
}