{
  "type": "Feature",
  "properties": {
    "gn:admin1_code": "19.0",
    "gn:asciiname": "Xinihezi",
    "gn:country_code": "CN",
    "gn:dem": 23,
    "gn:feature_class": "P",
    "gn:feature_code": "PPL",
    "gn:name": "Xinihezi",
    "gn:population": 0,
    "gn:timezone": "Asia/Shanghai",
    "iso:country": "CN",
    "name:zho_x_preferred": [
      "西泥河子"
    ],
    "wof:name": "Xinihezi",
    "wof:placetype": "locality"
  },
  "geometry": {
    "coordinates": [
      121.20729,
      38.89335
    ],
    "type": "Point"
  }
}