{
  "type": "Feature",
  "properties": {
    "gn:admin1_code": "21.0",
    "gn:asciiname": "Huangwan",
    "gn:country_code": "CN",
    "gn:dem": 2088,
    "gn:feature_class": "P",
    "gn:feature_code": "PPL",
    "gn:name": "Huangwan",
    "gn:population": 0,
    "gn:timezone": "Asia/Shanghai",
    "iso:country": "CN",
    "name:zho_x_preferred": [
      "黄湾"
    ],
    "wof:name": "Huangwan",
    "wof:placetype": "locality"
  },
  "geometry": {
    "coordinates": [
      106.061,
      35.7786
    ],
    "type": "Point"
  }
}