{
  "type": "Feature",
  "properties": {
    "gn:admin1_code": "3.0",
    "gn:asciiname": "Meiziyuan",
    "gn:country_code": "CN",
    "gn:dem": 276,
    "gn:feature_class": "P",
    "gn:feature_code": "PPL",
    "gn:name": "Meiziyuan",
    "gn:population": 0,
    "gn:timezone": "Asia/Shanghai",
    "iso:country": "CN",
    "name:und_x_variant": [
      "梅子园"
    ],
    "wof:name": "Meiziyuan",
    "wof:placetype": "locality"
  },
  "geometry": {
    "coordinates": [
      115.13938,
      25.6884
    ],
    "type": "Point"
  }
}