{
  "type": "Feature",
  "properties": {
    "gn:admin1_code": "11.0",
    "gn:asciiname": "Chengjiachong",
    "gn:country_code": "CN",
    "gn:dem": 78,
    "gn:feature_class": "P",
    "gn:feature_code": "PPL",
    "gn:name": "Chengjiachong",
    "gn:population": 0,
    "gn:timezone": "Asia/Shanghai",
    "iso:country": "CN",
    "name:zho_x_preferred": [
      "程家冲"
    ],
    "wof:name": "Chengjiachong",
    "wof:placetype": "locality"
  },
  "geometry": {
    "coordinates": [
      113.39208,
      29.27026
    ],
    "type": "Point"
  }
}