{
  "type": "Feature",
  "properties": {
    "gn:admin1_code": "9.0",
    "gn:asciiname": "Xiaohuzhuang",
    "gn:country_code": "CN",
    "gn:dem": 110,
    "gn:feature_class": "P",
    "gn:feature_code": "PPL",
    "gn:name": "Xiaohuzhuang",
    "gn:population": 0,
    "gn:timezone": "Asia/Shanghai",
    "iso:country": "CN",
    "name:zho_x_preferred": [
      "小胡庄"
    ],
    "wof:name": "Xiaohuzhuang",
    "wof:placetype": "locality"
  },
  "geometry": {
    "coordinates": [
      113.96667,
      32.32697
    ],
    "type": "Point"
  }
}