{
  "type": "Feature",
  "properties": {
    "gn:admin1_code": "25.0",
    "gn:asciiname": "Magezhuang",
    "gn:country_code": "CN",
    "gn:dem": 116,
    "gn:feature_class": "P",
    "gn:feature_code": "PPL",
    "gn:name": "Magezhuang",
    "gn:population": 0,
    "gn:timezone": "Asia/Shanghai",
    "iso:country": "CN",
    "name:zho_x_preferred": [
      "马格庄"
    ],
    "wof:name": "Magezhuang",
    "wof:placetype": "locality"
  },
  "geometry": {
    "coordinates": [
      120.93415,
      37.11841
    ],
    "type": "Point"
  }
}