{
  "type": "Feature",
  "properties": {
    "gn:admin1_code": "30",
    "gn:asciiname": "Pimian",
    "gn:country_code": "CN",
    "gn:dem": 25,
    "gn:feature_class": "P",
    "gn:feature_code": "PPLA4",
    "gn:name": "Pimian",
    "gn:population": 0,
    "gn:timezone": "Asia/Shanghai",
    "iso:country": "CN",
    "name:und_x_variant": [
      "陂面",
      "Pimian Zhen",
      "陂面镇"
    ],
    "wof:name": "Pimian",
    "wof:placetype": "locality"
  },
  "geometry": {
    "coordinates": [
      111.8475,
      22.34417
    ],
    "type": "Point"
  }
}