{
  "type": "Feature",
  "properties": {
    "gn:admin1_code": "15.0",
    "gn:asciiname": "Liudawa",
    "gn:country_code": "CN",
    "gn:dem": 1145,
    "gn:feature_class": "P",
    "gn:feature_code": "PPL",
    "gn:name": "Liudawa",
    "gn:population": 0,
    "gn:timezone": "Asia/Shanghai",
    "iso:country": "CN",
    "name:zho_x_preferred": [
      "刘大洼"
    ],
    "wof:name": "Liudawa",
    "wof:placetype": "locality"
  },
  "geometry": {
    "coordinates": [
      107.484,
      35.3185
    ],
    "type": "Point"
  }
}