{
  "type": "Feature",
  "properties": {
    "gn:admin1_code": "16.0",
    "gn:asciiname": "Anma",
    "gn:country_code": "CN",
    "gn:dem": 139,
    "gn:feature_class": "P",
    "gn:feature_code": "PPL",
    "gn:name": "Anma",
    "gn:population": 0,
    "gn:timezone": "Asia/Shanghai",
    "iso:country": "CN",
    "name:ara_x_preferred": [
      "ضغط إبري"
    ],
    "name:fra_x_preferred": [
      "Anma"
    ],
    "name:kor_x_preferred": [
      "안마"
    ],
    "name:por_x_preferred": [
      "Anma"
    ],
    "name:zho_x_preferred": [
      "安马"
    ],
    "wof:name": "Anma",
    "wof:placetype": "locality"
  },
  "geometry": {
    "coordinates": [
      107.111,
      22.0957
    ],
    "type": "Point"
  }
}