{
  "type": "Feature",
  "properties": {
    "gn:admin1_code": "14.0",
    "gn:asciiname": "Anguo",
    "gn:country_code": "CN",
    "gn:dem": 4155,
    "gn:feature_class": "P",
    "gn:feature_code": "PPL",
    "gn:name": "Anguo",
    "gn:population": 0,
    "gn:timezone": "Asia/Urumqi",
    "iso:country": "CN",
    "name:ara_x_preferred": [
      "أنغوو"
    ],
    "name:deu_x_preferred": [
      "Anguo"
    ],
    "name:fra_x_preferred": [
      "Anguo"
    ],
    "name:ita_x_preferred": [
      "Anguo"
    ],
    "name:jpn_x_preferred": [
      "安国市"
    ],
    "name:kik_x_preferred": [
      "Anguo"
    ],
    "name:kor_x_preferred": [
      "안궈시"
    ],
    "name:nno_x_preferred": [
      "Anguo"
    ],
    "name:nor_x_preferred": [
      "Anguo"
    ],
    "name:pam_x_preferred": [
      "Anguo"
    ],
    "name:rus_x_preferred": [
      "Аньго"
    ],
    "name:swe_x_preferred": [
      "Anguo"
    ],
    "name:urd_x_preferred": [
      "انگوو"
    ],
    "name:vie_x_preferred": [
      "An Quốc"
    ],
    "name:zho_x_preferred": [
      "安果"
    ],
    "name:zho_x_variant": [
      "安国市"
    ],
    "wof:name": "Anguo",
    "wof:placetype": "locality"
  },
  "geometry": {
    "coordinates": [
      97.43346,
      30.22489
    ],
    "type": "Point"
  }
}