{
  "type": "Feature",
  "properties": {
    "gn:country": "CN",
    "gn:fcode": "PPL",
    "gn:population": 60202,
    "iso:country": "CN",
    "name:deu_x_preferred": [
      "Runan"
    ],
    "name:eng_x_preferred": [
      "Runan County"
    ],
    "name:fas_x_preferred": [
      "شهرستان رونان"
    ],
    "name:gan_x_preferred": [
      "汝南县"
    ],
    "name:hrv_x_preferred": [
      "Runan"
    ],
    "name:jpn_x_preferred": [
      "汝南県"
    ],
    "name:kor_x_preferred": [
      "루난현"
    ],
    "name:nan_x_preferred": [
      "Jú-lâm-koān"
    ],
    "name:nld_x_preferred": [
      "Runan"
    ],
    "name:nob_x_preferred": [
      "Runan"
    ],
    "name:rus_x_preferred": [
      "Жунань"
    ],
    "name:spa_x_preferred": [
      "Ru'nan"
    ],
    "name:swe_x_preferred": [
      "Runan"
    ],
    "name:tha_x_preferred": [
      "เมืองรูหนาน"
    ],
    "name:und_x_variant": [
      "Ju-nan"
    ],
    "name:vie_x_preferred": [
      "Nhữ Nam"
    ],
    "name:wuu_x_preferred": [
      "汝南县"
    ],
    "name:yue_x_preferred": [
      "汝南"
    ],
    "name:zho_x_preferred": [
      "汝宁"
    ],
    "name:zho_x_variant": [
      "汝南县"
    ],
    "qs:name": "汝南",
    "qs:name_adm0": "中國",
    "qs:name_adm1": "河南省",
    "qs:photos_9r": 0,
    "qs:photos_sr": 0,
    "qs:placetype": "Town",
    "qs:pop_sr": "8",
    "wd:wordcount": 434,
    "wof:name": "汝南",
    "wof:placetype": "locality",
    "wof:population": 60202
  },
  "geometry": {
    "coordinates": [
      114.35417,
      33.00111
    ],
    "type": "Point"
  }
}