{
  "type": "Feature",
  "properties": {
    "gn:admin1_code": "12.0",
    "gn:asciiname": "Dujiaqiao",
    "gn:country_code": "CN",
    "gn:dem": 27,
    "gn:feature_class": "P",
    "gn:feature_code": "PPL",
    "gn:name": "Dujiaqiao",
    "gn:population": 0,
    "gn:timezone": "Asia/Shanghai",
    "iso:country": "CN",
    "name:zho_x_preferred": [
      "杜家桥"
    ],
    "wof:name": "Dujiaqiao",
    "wof:placetype": "locality"
  },
  "geometry": {
    "coordinates": [
      113.21668,
      30.15185
    ],
    "type": "Point"
  }
}