{
  "type": "Feature",
  "properties": {
    "gn:admin1_code": "29.0",
    "gn:asciiname": "Chashanhe",
    "gn:country_code": "CN",
    "gn:dem": 1936,
    "gn:feature_class": "P",
    "gn:feature_code": "PPL",
    "gn:name": "Chashanhe",
    "gn:population": 0,
    "gn:timezone": "Asia/Shanghai",
    "iso:country": "CN",
    "name:zho_x_preferred": [
      "茶山河"
    ],
    "wof:name": "Chashanhe",
    "wof:placetype": "locality"
  },
  "geometry": {
    "coordinates": [
      98.5396,
      25.6712
    ],
    "type": "Point"
  }
}