{
  "type": "Feature",
  "properties": {
    "gn:admin1_code": "14.0",
    "gn:asciiname": "Goinsargoin",
    "gn:cc2": "CN",
    "gn:country_code": "CN",
    "gn:dem": 3976,
    "gn:feature_class": "P",
    "gn:feature_code": "PPL",
    "gn:name": "Goinsargoin",
    "gn:population": 0,
    "gn:timezone": "Asia/Urumqi",
    "iso:country": "CN",
    "name:ara_x_preferred": [
      "غوانسرغوان"
    ],
    "name:bod_x_preferred": [
      "Goinsargoin"
    ],
    "name:fas_x_preferred": [
      "گوینسارگوین"
    ],
    "name:msa_x_preferred": [
      "Goinsargoin"
    ],
    "name:und_x_variant": [
      "Ken-sha-kun"
    ],
    "name:zho_x_preferred": [
      "Genshagong"
    ],
    "name:zho_x_variant": [
      "根沙贡",
      "Renzhenduo Gongshe",
      "仁真多公社"
    ],
    "wof:name": "Goinsargoin",
    "wof:placetype": "locality"
  },
  "geometry": {
    "coordinates": [
      98.06667,
      31.93333
    ],
    "type": "Point"
  }
}