{
  "type": "Feature",
  "properties": {
    "gn:admin1_code": "7.0",
    "gn:asciiname": "Da'ercun",
    "gn:country_code": "CN",
    "gn:dem": 142,
    "gn:feature_class": "P",
    "gn:feature_code": "PPL",
    "gn:name": "Da’ercun",
    "gn:population": 0,
    "gn:timezone": "Asia/Shanghai",
    "iso:country": "CN",
    "name:und_x_variant": [
      "Da’ercun"
    ],
    "name:zho_x_preferred": [
      "大二村"
    ],
    "wof:name": "Da'ercun",
    "wof:placetype": "locality"
  },
  "geometry": {
    "coordinates": [
      117.18507,
      24.09832
    ],
    "type": "Point"
  }
}