{
  "type": "Feature",
  "properties": {
    "gn:admin1_code": "12.0",
    "gn:asciiname": "Chenjiadu",
    "gn:country_code": "CN",
    "gn:dem": 43,
    "gn:feature_class": "P",
    "gn:feature_code": "PPL",
    "gn:name": "Chenjiadu",
    "gn:population": 0,
    "gn:timezone": "Asia/Shanghai",
    "iso:country": "CN",
    "name:zho_x_preferred": [
      "Chenjiadu"
    ],
    "name:zho_x_variant": [
      "陈家渡"
    ],
    "wof:name": "Chenjiadu",
    "wof:placetype": "locality"
  },
  "geometry": {
    "coordinates": [
      111.7237,
      30.39947
    ],
    "type": "Point"
  }
}