{
  "type": "Feature",
  "properties": {
    "gn:admin1_code": "16.0",
    "gn:asciiname": "Tianwei",
    "gn:country_code": "CN",
    "gn:dem": 278,
    "gn:feature_class": "P",
    "gn:feature_code": "PPL",
    "gn:name": "Tianwei",
    "gn:population": 0,
    "gn:timezone": "Asia/Shanghai",
    "iso:country": "CN",
    "name:hak_x_preferred": [
      "Thièn-mî-hiông"
    ],
    "name:ita_x_preferred": [
      "Tianwei"
    ],
    "name:jpn_x_preferred": [
      "田尾郷"
    ],
    "name:kor_x_preferred": [
      "톈웨이향"
    ],
    "name:pol_x_preferred": [
      "Tianwei"
    ],
    "name:vie_x_preferred": [
      "Điền Vĩ"
    ],
    "name:zho_x_preferred": [
      "田尾"
    ],
    "name:zho_x_variant": [
      "田尾鄉"
    ],
    "wof:name": "Tianwei",
    "wof:placetype": "locality"
  },
  "geometry": {
    "coordinates": [
      110.429,
      24.3442
    ],
    "type": "Point"
  }
}