{
  "type": "Feature",
  "properties": {
    "gn:admin1_code": "25",
    "gn:asciiname": "Baizhongquan",
    "gn:country_code": "CN",
    "gn:dem": 184,
    "gn:feature_class": "P",
    "gn:feature_code": "PPL",
    "gn:name": "Baizhongquan",
    "gn:population": 0,
    "gn:timezone": "Asia/Shanghai",
    "iso:country": "CN",
    "name:zho_x_preferred": [
      "白仲泉"
    ],
    "wof:name": "Baizhongquan",
    "wof:placetype": "locality"
  },
  "geometry": {
    "coordinates": [
      117.327,
      35.5833
    ],
    "type": "Point"
  }
}