{
  "type": "Feature",
  "properties": {
    "gn:admin1_code": "1.0",
    "gn:asciiname": "Zhaochong",
    "gn:country_code": "CN",
    "gn:dem": 346,
    "gn:feature_class": "P",
    "gn:feature_code": "PPL",
    "gn:name": "Zhaochong",
    "gn:population": 0,
    "gn:timezone": "Asia/Shanghai",
    "iso:country": "CN",
    "name:zho_x_preferred": [
      "赵冲"
    ],
    "wof:name": "Zhaochong",
    "wof:placetype": "locality"
  },
  "geometry": {
    "coordinates": [
      115.94712,
      30.45435
    ],
    "type": "Point"
  }
}