{
  "type": "Feature",
  "properties": {
    "gn:admin1_code": "8.0",
    "gn:asciiname": "Danjiatun",
    "gn:country_code": "CN",
    "gn:dem": 126,
    "gn:feature_class": "P",
    "gn:feature_code": "PPL",
    "gn:name": "Danjiatun",
    "gn:population": 0,
    "gn:timezone": "Asia/Shanghai",
    "iso:country": "CN",
    "name:zho_x_preferred": [
      "单家屯"
    ],
    "wof:name": "Danjiatun",
    "wof:placetype": "locality"
  },
  "geometry": {
    "coordinates": [
      125.99631,
      45.53333
    ],
    "type": "Point"
  }
}