{
  "type": "Feature",
  "properties": {
    "gn:admin1_code": "25",
    "gn:asciiname": "Ciyu",
    "gn:country_code": "CN",
    "gn:dem": 378,
    "gn:feature_class": "P",
    "gn:feature_code": "PPL",
    "gn:name": "Ciyu",
    "gn:population": 0,
    "gn:timezone": "Asia/Shanghai",
    "iso:country": "CN",
    "name:fas_x_preferred": [
      "سییو"
    ],
    "name:zho_x_preferred": [
      "茨峪"
    ],
    "name:zho_x_variant": [
      "慈峪镇"
    ],
    "wof:name": "Ciyu",
    "wof:placetype": "locality"
  },
  "geometry": {
    "coordinates": [
      118.112,
      36.2587
    ],
    "type": "Point"
  }
}