{
  "type": "Feature",
  "properties": {
    "gn:admin1_code": "05",
    "gn:asciiname": "Jiulong",
    "gn:country_code": "CN",
    "gn:dem": 229,
    "gn:feature_class": "P",
    "gn:feature_code": "PPLA4",
    "gn:name": "Jiulong",
    "gn:population": 0,
    "gn:timezone": "Asia/Shanghai",
    "iso:country": "CN",
    "name:ceb_x_preferred": [
      "Jiulong"
    ],
    "name:deu_x_preferred": [
      "Jiulong"
    ],
    "name:fra_x_preferred": [
      "Jiulong"
    ],
    "name:nor_x_preferred": [
      "Jiulong"
    ],
    "name:swe_x_preferred": [
      "Jiulong"
    ],
    "name:und_x_variant": [
      "I-lan-kou",
      "Yilan Zhen",
      "九龙",
      "依兰镇"
    ],
    "name:vie_x_preferred": [
      "Sông Cửu Long"
    ],
    "name:vie_x_variant": [
      "Cửu Long"
    ],
    "name:zho_x_preferred": [
      "九龍"
    ],
    "wof:name": "Jiulong",
    "wof:placetype": "locality"
  },
  "geometry": {
    "coordinates": [
      129.51716,
      43.10683
    ],
    "type": "Point"
  }
}