{
  "type": "Feature",
  "properties": {
    "gn:admin1_code": "30",
    "gn:asciiname": "Ximaoshe",
    "gn:country_code": "CN",
    "gn:dem": 263,
    "gn:feature_class": "P",
    "gn:feature_code": "PPL",
    "gn:name": "Ximaoshe",
    "gn:population": 0,
    "gn:timezone": "Asia/Shanghai",
    "iso:country": "CN",
    "name:zho_x_preferred": [
      "葸茅畬"
    ],
    "wof:name": "Ximaoshe",
    "wof:placetype": "locality"
  },
  "geometry": {
    "coordinates": [
      116.31218,
      24.5022
    ],
    "type": "Point"
  }
}