{
  "type": "Feature",
  "properties": {
    "gn:admin1_code": "14.0",
    "gn:asciiname": "Gala",
    "gn:country_code": "CN",
    "gn:dem": 4445,
    "gn:feature_class": "P",
    "gn:feature_code": "PPLA4",
    "gn:name": "Gala",
    "gn:population": 0,
    "gn:timezone": "Asia/Urumqi",
    "iso:country": "CN",
    "name:ara_x_preferred": [
      "غالا"
    ],
    "name:bod_x_preferred": [
      "Gala"
    ],
    "name:fas_x_preferred": [
      "گالا"
    ],
    "name:msa_x_preferred": [
      "Gala"
    ],
    "name:und_x_variant": [
      "Kalbashar",
      "K’a-la",
      "K’ai-la",
      "Kalashar",
      "K’a-la-sha-erh",
      "K’a-la-sha",
      "K’a-la-sa",
      "Gala Xiang"
    ],
    "name:zho_x_preferred": [
      "嘎拉"
    ],
    "name:zho_x_variant": [
      "Galaxia",
      "嘎拉夏",
      "嘎拉乡"
    ],
    "wof:name": "Gala",
    "wof:placetype": "locality"
  },
  "geometry": {
    "coordinates": [
      89.38186999999998,
      28.26311
    ],
    "type": "Point"
  }
}