{
  "type": "Feature",
  "properties": {
    "gn:admin1_code": "10.0",
    "gn:asciiname": "Yutian",
    "gn:country_code": "CN",
    "gn:dem": 19,
    "gn:feature_class": "P",
    "gn:feature_code": "PPLA3",
    "gn:name": "Yutian",
    "gn:population": 0,
    "gn:timezone": "Asia/Shanghai",
    "iso:country": "CN",
    "name:deu_x_preferred": [
      "Yutian"
    ],
    "name:fas_x_preferred": [
      "شهرستان یوتیان"
    ],
    "name:jpn_x_preferred": [
      "玉田県"
    ],
    "name:kor_x_preferred": [
      "위톈현"
    ],
    "name:nor_x_preferred": [
      "Yutian"
    ],
    "name:rus_x_preferred": [
      "Юйтянь"
    ],
    "name:swe_x_preferred": [
      "Yutian"
    ],
    "name:und_x_variant": [
      "Yü-t’ien-hsien",
      "Yü-t’ien-ch’eng-kuan",
      "Yü-t’ien"
    ],
    "name:urd_x_preferred": [
      "یتین کاؤنٹی"
    ],
    "name:vie_x_preferred": [
      "Ngọc Điền"
    ],
    "name:zho_x_preferred": [
      "玉田"
    ],
    "name:zho_x_variant": [
      "玉田县"
    ],
    "wof:name": "Yutian",
    "wof:placetype": "locality"
  },
  "geometry": {
    "coordinates": [
      117.73917,
      39.87861
    ],
    "type": "Point"
  }
}