{
  "type": "Feature",
  "properties": {
    "gn:admin1_code": "22.0",
    "gn:asciiname": "Beitumencun",
    "gn:country_code": "CN",
    "gn:dem": 201,
    "gn:feature_class": "P",
    "gn:feature_code": "PPL",
    "gn:name": "Beitumencun",
    "gn:population": 0,
    "gn:timezone": "Asia/Shanghai",
    "iso:country": "CN",
    "name:zho_x_preferred": [
      "北土门村"
    ],
    "wof:name": "Beitumencun",
    "wof:placetype": "locality"
  },
  "geometry": {
    "coordinates": [
      117.11789,
      40.26393
    ],
    "type": "Point"
  }
}