{
  "type": "Feature",
  "properties": {
    "gn:admin1_code": "8.0",
    "gn:asciiname": "Beiningcun",
    "gn:country_code": "CN",
    "gn:dem": 231,
    "gn:feature_class": "P",
    "gn:feature_code": "PPL",
    "gn:name": "Beiningcun",
    "gn:population": 0,
    "gn:timezone": "Asia/Shanghai",
    "iso:country": "CN",
    "name:zho_x_preferred": [
      "北宁村"
    ],
    "wof:name": "Beiningcun",
    "wof:placetype": "locality"
  },
  "geometry": {
    "coordinates": [
      129.6663,
      45.17075
    ],
    "type": "Point"
  }
}