{
  "type": "Feature",
  "properties": {
    "gn:admin1_code": "32.0",
    "gn:asciiname": "Shuiguanyin",
    "gn:country_code": "CN",
    "gn:dem": 646,
    "gn:feature_class": "P",
    "gn:feature_code": "PPL",
    "gn:name": "Shuiguanyin",
    "gn:population": 0,
    "gn:timezone": "Asia/Shanghai",
    "iso:country": "CN",
    "name:zho_x_preferred": [
      "水观音"
    ],
    "wof:name": "Shuiguanyin",
    "wof:placetype": "locality"
  },
  "geometry": {
    "coordinates": [
      104.57365,
      31.12876
    ],
    "type": "Point"
  }
}