{
  "type": "Feature",
  "properties": {
    "gn:admin1_code": "29",
    "gn:asciiname": "Xiaobanqiao",
    "gn:country_code": "CN",
    "gn:dem": 1901,
    "gn:feature_class": "P",
    "gn:feature_code": "PPLA4",
    "gn:name": "Xiaobanqiao",
    "gn:population": 0,
    "gn:timezone": "Asia/Shanghai",
    "iso:country": "CN",
    "name:und_x_variant": [
      "Xiaobanqiao Zhen",
      "小板桥镇",
      "Xiaobanqiao"
    ],
    "name:zho_x_preferred": [
      "小板桥"
    ],
    "wof:name": "Xiaobanqiao",
    "wof:placetype": "locality"
  },
  "geometry": {
    "coordinates": [
      102.7738,
      24.97944
    ],
    "type": "Point"
  }
}