{
  "type": "Feature",
  "properties": {
    "gn:admin1_code": "15.0",
    "gn:asciiname": "Yitiaoshan",
    "gn:country_code": "CN",
    "gn:dem": 1616,
    "gn:feature_class": "P",
    "gn:feature_code": "PPLA3",
    "gn:name": "Yitiaoshan",
    "gn:population": 0,
    "gn:timezone": "Asia/Shanghai",
    "iso:country": "CN",
    "name:und_x_variant": [
      "Hung-shui",
      "Tsintay",
      "Khunshuy",
      "Lu-yang",
      "Ching-t’ai",
      "Ta-lu-t’ang",
      "Ityaoshan’",
      "I-t’iao-shan",
      "Jingtai",
      "Yitiaoshan",
      "Jingtai Xian"
    ],
    "name:zho_x_preferred": [
      "一条山"
    ],
    "name:zho_x_variant": [
      "景泰县"
    ],
    "wof:name": "Yitiaoshan",
    "wof:placetype": "locality"
  },
  "geometry": {
    "coordinates": [
      104.062,
      37.1533
    ],
    "type": "Point"
  }
}