{
  "type": "Feature",
  "properties": {
    "gn:admin1_code": "1.0",
    "gn:asciiname": "Hankou",
    "gn:country_code": "CN",
    "gn:dem": 9,
    "gn:feature_class": "P",
    "gn:feature_code": "PPL",
    "gn:name": "Hankou",
    "gn:population": 0,
    "gn:timezone": "Asia/Shanghai",
    "iso:country": "CN",
    "name:ell_x_preferred": [
      "Χανκόου"
    ],
    "name:fas_x_preferred": [
      "هانکو"
    ],
    "name:fin_x_preferred": [
      "Hankou"
    ],
    "name:fra_x_preferred": [
      "Hankou"
    ],
    "name:ind_x_preferred": [
      "Hankou"
    ],
    "name:ita_x_preferred": [
      "Hankou"
    ],
    "name:kor_x_preferred": [
      "한커우"
    ],
    "name:mlg_x_preferred": [
      "Hankou"
    ],
    "name:nor_x_preferred": [
      "Hankou"
    ],
    "name:pol_x_preferred": [
      "Hankou"
    ],
    "name:spa_x_preferred": [
      "Hankou"
    ],
    "name:swe_x_preferred": [
      "Hankou"
    ],
    "name:ukr_x_preferred": [
      "Ханькоу"
    ],
    "name:vie_x_preferred": [
      "Hán Khẩu"
    ],
    "name:zho_x_preferred": [
      "涵口"
    ],
    "wof:name": "Hankou",
    "wof:placetype": "locality"
  },
  "geometry": {
    "coordinates": [
      118.67048,
      31.31554
    ],
    "type": "Point"
  }
}