{
  "type": "Feature",
  "properties": {
    "gn:admin1_code": "12.0",
    "gn:asciiname": "Xiaochayuan",
    "gn:country_code": "CN",
    "gn:dem": 724,
    "gn:feature_class": "P",
    "gn:feature_code": "PPL",
    "gn:name": "Xiaochayuan",
    "gn:population": 0,
    "gn:timezone": "Asia/Shanghai",
    "iso:country": "CN",
    "name:zho_x_preferred": [
      "小茶园"
    ],
    "wof:name": "Xiaochayuan",
    "wof:placetype": "locality"
  },
  "geometry": {
    "coordinates": [
      109.77629,
      30.75684
    ],
    "type": "Point"
  }
}