{
  "type": "Feature",
  "properties": {
    "gn:admin1_code": "14.0",
    "gn:asciiname": "Guangti Niuchang",
    "gn:country_code": "CN",
    "gn:dem": 4285,
    "gn:feature_class": "P",
    "gn:feature_code": "PPLF",
    "gn:name": "Guangti Niuchang",
    "gn:population": 0,
    "gn:timezone": "Asia/Urumqi",
    "iso:country": "CN",
    "name:zho_x_preferred": [
      "广提牛场"
    ],
    "wof:name": "Guangti Niuchang",
    "wof:placetype": "locality"
  },
  "geometry": {
    "coordinates": [
      98.3899,
      29.774
    ],
    "type": "Point"
  }
}