{
  "type": "Feature",
  "properties": {
    "gn:admin1_code": "02",
    "gn:asciiname": "Nubu",
    "gn:country_code": "CN",
    "gn:dem": 37,
    "gn:feature_class": "P",
    "gn:feature_code": "PPLA4",
    "gn:name": "Nübu",
    "gn:population": 0,
    "gn:timezone": "Asia/Shanghai",
    "iso:country": "CN",
    "name:und_x_variant": [
      "女埠",
      "Nübu",
      "Nübu Zhen"
    ],
    "name:zho_x_preferred": [
      "女埠镇"
    ],
    "wof:name": "Nubu",
    "wof:placetype": "locality"
  },
  "geometry": {
    "coordinates": [
      119.46114,
      29.26259000000001
    ],
    "type": "Point"
  }
}