{
  "type": "Feature",
  "properties": {
    "gn:admin1_code": "16",
    "gn:asciiname": "Shijianping",
    "gn:country_code": "CN",
    "gn:dem": 811,
    "gn:feature_class": "P",
    "gn:feature_code": "PPL",
    "gn:name": "Shijianping",
    "gn:population": 0,
    "gn:timezone": "Asia/Shanghai",
    "iso:country": "CN",
    "name:zho_x_preferred": [
      "石枧坪"
    ],
    "wof:name": "Shijianping",
    "wof:placetype": "locality"
  },
  "geometry": {
    "coordinates": [
      111.434,
      25.8614
    ],
    "type": "Point"
  }
}