{
  "type": "Feature",
  "properties": {
    "gn:admin1_code": "16.0",
    "gn:asciiname": "Laye",
    "gn:country_code": "CN",
    "gn:dem": 739,
    "gn:feature_class": "P",
    "gn:feature_code": "PPL",
    "gn:name": "Laye",
    "gn:population": 0,
    "gn:timezone": "Asia/Shanghai",
    "iso:country": "CN",
    "name:bug_x_preferred": [
      "Laye"
    ],
    "name:cat_x_preferred": [
      "L'Aja"
    ],
    "name:ceb_x_preferred": [
      "Laye"
    ],
    "name:deu_x_preferred": [
      "Laye"
    ],
    "name:eus_x_preferred": [
      "Laye"
    ],
    "name:fra_x_preferred": [
      "Laye"
    ],
    "name:hun_x_preferred": [
      "Laye"
    ],
    "name:ita_x_preferred": [
      "Laye"
    ],
    "name:lat_x_preferred": [
      "Laye"
    ],
    "name:lmo_x_preferred": [
      "Laye"
    ],
    "name:ltz_x_preferred": [
      "Laye"
    ],
    "name:msa_x_preferred": [
      "Laye"
    ],
    "name:nld_x_preferred": [
      "Laye"
    ],
    "name:oci_x_preferred": [
      "L'Aja"
    ],
    "name:pms_x_preferred": [
      "Laye"
    ],
    "name:pol_x_preferred": [
      "Laye"
    ],
    "name:por_x_preferred": [
      "Laye"
    ],
    "name:ron_x_preferred": [
      "Laye"
    ],
    "name:rus_x_preferred": [
      "Лай"
    ],
    "name:slk_x_preferred": [
      "Laye"
    ],
    "name:spa_x_preferred": [
      "Laye"
    ],
    "name:sqi_x_preferred": [
      "Laye"
    ],
    "name:swe_x_preferred": [
      "Laye"
    ],
    "name:ukr_x_preferred": [
      "Лай"
    ],
    "name:vie_x_preferred": [
      "Laye"
    ],
    "name:vol_x_preferred": [
      "Laye"
    ],
    "name:war_x_preferred": [
      "Laye"
    ],
    "name:zho_x_preferred": [
      "拉也"
    ],
    "name:zho_x_variant": [
      "莱伊"
    ],
    "wof:name": "Laye",
    "wof:placetype": "locality"
  },
  "geometry": {
    "coordinates": [
      107.399,
      25.1127
    ],
    "type": "Point"
  }
}