{
  "type": "Feature",
  "properties": {
    "gn:admin1_code": "6.0",
    "gn:asciiname": "Kama",
    "gn:country_code": "CN",
    "gn:dem": 3896,
    "gn:feature_class": "P",
    "gn:feature_code": "PPL",
    "gn:name": "Kama",
    "gn:population": 0,
    "gn:timezone": "Asia/Urumqi",
    "iso:country": "CN",
    "name:ben_x_preferred": [
      "কামা"
    ],
    "name:bih_x_preferred": [
      "काम"
    ],
    "name:bul_x_preferred": [
      "Кама"
    ],
    "name:cat_x_preferred": [
      "Kama"
    ],
    "name:deu_x_preferred": [
      "Kama"
    ],
    "name:est_x_preferred": [
      "Kaama"
    ],
    "name:fra_x_preferred": [
      "Kama"
    ],
    "name:hin_x_preferred": [
      "काम"
    ],
    "name:hye_x_preferred": [
      "Կամա"
    ],
    "name:ind_x_preferred": [
      "Kama"
    ],
    "name:ita_x_preferred": [
      "Kamaloka"
    ],
    "name:jpn_x_preferred": [
      "カーマ"
    ],
    "name:kan_x_preferred": [
      "ಕಾಮ"
    ],
    "name:kat_x_preferred": [
      "კამა"
    ],
    "name:lit_x_preferred": [
      "Kama"
    ],
    "name:nld_x_preferred": [
      "Kama"
    ],
    "name:pol_x_preferred": [
      "Kama"
    ],
    "name:por_x_preferred": [
      "Kama"
    ],
    "name:rus_x_preferred": [
      "Кама"
    ],
    "name:san_x_preferred": [
      "कामः"
    ],
    "name:sin_x_preferred": [
      "කාම"
    ],
    "name:spa_x_preferred": [
      "Kāma"
    ],
    "name:tam_x_preferred": [
      "காமம்"
    ],
    "name:tha_x_preferred": [
      "กาม"
    ],
    "name:ukr_x_preferred": [
      "Кама"
    ],
    "name:urd_x_preferred": [
      "کام"
    ],
    "name:zho_x_preferred": [
      "卡麻"
    ],
    "wof:name": "Kama",
    "wof:placetype": "locality"
  },
  "geometry": {
    "coordinates": [
      95.90954,
      32.05977
    ],
    "type": "Point"
  }
}