{
  "type": "Feature",
  "properties": {
    "gn:admin1_code": "9.0",
    "gn:asciiname": "Luzhuang",
    "gn:country_code": "CN",
    "gn:dem": 61,
    "gn:feature_class": "P",
    "gn:feature_code": "PPL",
    "gn:name": "Lüzhuang",
    "gn:population": 0,
    "gn:timezone": "Asia/Shanghai",
    "iso:country": "CN",
    "name:und_x_variant": [
      "Lüzhuang"
    ],
    "name:zho_x_preferred": [
      "吕庄"
    ],
    "wof:name": "Luzhuang",
    "wof:placetype": "locality"
  },
  "geometry": {
    "coordinates": [
      114.54052,
      35.59638
    ],
    "type": "Point"
  }
}