{
  "type": "Feature",
  "properties": {
    "gn:admin1_code": "24.0",
    "gn:asciiname": "Zhangzuan",
    "gn:country_code": "CN",
    "gn:dem": 572,
    "gn:feature_class": "P",
    "gn:feature_code": "PPL",
    "gn:name": "Zhangzuan",
    "gn:population": 0,
    "gn:timezone": "Asia/Shanghai",
    "iso:country": "CN",
    "name:zho_x_preferred": [
      "张纂"
    ],
    "wof:name": "Zhangzuan",
    "wof:placetype": "locality"
  },
  "geometry": {
    "coordinates": [
      111.54238,
      35.89698
    ],
    "type": "Point"
  }
}