{
  "type": "Feature",
  "properties": {
    "gn:admin1_code": "11",
    "gn:asciiname": "Xiliwei",
    "gn:country_code": "CN",
    "gn:dem": 397,
    "gn:feature_class": "P",
    "gn:feature_code": "PPL",
    "gn:name": "Xiliwei",
    "gn:population": 0,
    "gn:timezone": "Asia/Shanghai",
    "iso:country": "CN",
    "name:zho_x_preferred": [
      "西栎尾"
    ],
    "wof:name": "Xiliwei",
    "wof:placetype": "locality"
  },
  "geometry": {
    "coordinates": [
      111.43409,
      25.06911
    ],
    "type": "Point"
  }
}