{
  "type": "Feature",
  "properties": {
    "gn:admin1_code": "16.0",
    "gn:asciiname": "Gulou",
    "gn:country_code": "CN",
    "gn:dem": 160,
    "gn:feature_class": "P",
    "gn:feature_code": "PPL",
    "gn:name": "Gulou",
    "gn:population": 0,
    "gn:timezone": "Asia/Shanghai",
    "iso:country": "CN",
    "name:ceb_x_preferred": [
      "Gulou"
    ],
    "name:deu_x_preferred": [
      "Gulou"
    ],
    "name:eus_x_preferred": [
      "Gulou"
    ],
    "name:fra_x_preferred": [
      "Gulou"
    ],
    "name:jpn_x_preferred": [
      "鼓楼区"
    ],
    "name:kor_x_preferred": [
      "구러우구"
    ],
    "name:nor_x_preferred": [
      "Gulou"
    ],
    "name:rus_x_preferred": [
      "Гулоу"
    ],
    "name:swe_x_preferred": [
      "Gulou"
    ],
    "name:vie_x_preferred": [
      "Cổ Lâu"
    ],
    "name:zho_x_preferred": [
      "古楼"
    ],
    "name:zho_x_variant": [
      "鼓楼区"
    ],
    "wof:name": "Gulou",
    "wof:placetype": "locality"
  },
  "geometry": {
    "coordinates": [
      108.082,
      23.9888
    ],
    "type": "Point"
  }
}