{
  "type": "Feature",
  "properties": {
    "gn:admin1_code": "8.0",
    "gn:asciiname": "Baoquanling Ershi'erdui",
    "gn:country_code": "CN",
    "gn:dem": 115,
    "gn:feature_class": "P",
    "gn:feature_code": "PPLF",
    "gn:name": "Baoquanling Ershi’erdui",
    "gn:population": 0,
    "gn:timezone": "Asia/Shanghai",
    "iso:country": "CN",
    "name:und_x_variant": [
      "Baoquanling Ershi’erdui"
    ],
    "name:zho_x_preferred": [
      "宝泉岭二十二队"
    ],
    "wof:name": "Baoquanling Ershi'erdui",
    "wof:placetype": "locality"
  },
  "geometry": {
    "coordinates": [
      130.43769,
      47.45413
    ],
    "type": "Point"
  }
}