{
  "type": "Feature",
  "properties": {
    "gn:admin1_code": "10.0",
    "gn:asciiname": "Beizhuang",
    "gn:country_code": "CN",
    "gn:dem": 65,
    "gn:feature_class": "P",
    "gn:feature_code": "PPL",
    "gn:name": "Beizhuang",
    "gn:population": 0,
    "gn:timezone": "Asia/Shanghai",
    "iso:country": "CN",
    "name:und_x_variant": [
      "北庄"
    ],
    "name:zho_x_preferred": [
      "北庄镇"
    ],
    "wof:name": "Beizhuang",
    "wof:placetype": "locality"
  },
  "geometry": {
    "coordinates": [
      114.6308,
      38.04311
    ],
    "type": "Point"
  }
}