{
  "type": "Feature",
  "properties": {
    "gn:admin1_code": "05",
    "gn:asciiname": "Kuaidamao",
    "gn:country_code": "CN",
    "gn:dem": 517,
    "gn:feature_class": "P",
    "gn:feature_code": "PPLA3",
    "gn:name": "Kuaidamao",
    "gn:population": 0,
    "gn:timezone": "Asia/Shanghai",
    "iso:country": "CN",
    "name:deu_x_preferred": [
      "Tonghua"
    ],
    "name:fas_x_preferred": [
      "شهرستان تونگهوا"
    ],
    "name:jpn_x_preferred": [
      "通化県"
    ],
    "name:kor_x_preferred": [
      "퉁화현"
    ],
    "name:nor_x_preferred": [
      "Tonghua"
    ],
    "name:pol_x_preferred": [
      "Tonghua"
    ],
    "name:rus_x_preferred": [
      "Тунхуа"
    ],
    "name:swe_x_preferred": [
      "Tonghua"
    ],
    "name:und_x_variant": [
      "Kuaidamao"
    ],
    "name:urd_x_preferred": [
      "تونگہوا کاؤنٹی"
    ],
    "name:vie_x_preferred": [
      "Thông Hóa"
    ],
    "name:zho_x_preferred": [
      "T’ung-hua-hsien"
    ],
    "name:zho_x_variant": [
      "K’uai-tang-mao-tzu",
      "K’uai-ta-mao-tzu",
      "K’uai-ta-mao",
      "快大茂",
      "通化县"
    ],
    "wof:name": "Kuaidamao",
    "wof:placetype": "locality"
  },
  "geometry": {
    "coordinates": [
      125.74225,
      41.65532
    ],
    "type": "Point"
  }
}