{
  "type": "Feature",
  "properties": {
    "gn:admin1_code": "06",
    "gn:asciiname": "Gyimkar",
    "gn:country_code": "CN",
    "gn:dem": 3865,
    "gn:feature_class": "P",
    "gn:feature_code": "PPLA4",
    "gn:name": "Gyimkar",
    "gn:population": 0,
    "gn:timezone": "Asia/Shanghai",
    "iso:country": "CN",
    "name:mon_x_preferred": [
      "Gyimkar"
    ],
    "name:und_x_variant": [
      "Jika",
      "Jika Xiang",
      "Jiyao Dangwuda"
    ],
    "name:zho_x_preferred": [
      "吉卡"
    ],
    "name:zho_x_variant": [
      "吉卡乡",
      "吉要当吾达"
    ],
    "wof:name": "Gyimkar",
    "wof:placetype": "locality"
  },
  "geometry": {
    "coordinates": [
      100.28038,
      32.81809000000001
    ],
    "type": "Point"
  }
}