{
  "type": "Feature",
  "properties": {
    "gn:admin1_code": "26.0",
    "gn:asciiname": "Mata",
    "gn:country_code": "CN",
    "gn:dem": 1197,
    "gn:feature_class": "P",
    "gn:feature_code": "PPL",
    "gn:name": "Mata",
    "gn:population": 0,
    "gn:timezone": "Asia/Shanghai",
    "iso:country": "CN",
    "name:bel_x_preferred": [
      "Мата"
    ],
    "name:bpy_x_preferred": [
      "মাটা"
    ],
    "name:cat_x_preferred": [
      "Mata"
    ],
    "name:ceb_x_preferred": [
      "Mata"
    ],
    "name:deu_x_preferred": [
      "Mata"
    ],
    "name:fin_x_preferred": [
      "Mata"
    ],
    "name:fra_x_preferred": [
      "Mata"
    ],
    "name:heb_x_preferred": [
      "מאטה"
    ],
    "name:hye_x_preferred": [
      "Մատա"
    ],
    "name:ind_x_preferred": [
      "Mata"
    ],
    "name:ita_x_preferred": [
      "Mata"
    ],
    "name:jav_x_preferred": [
      "Mata"
    ],
    "name:jpn_x_preferred": [
      "マータ"
    ],
    "name:lav_x_preferred": [
      "Mata"
    ],
    "name:msa_x_preferred": [
      "Mata"
    ],
    "name:nld_x_preferred": [
      "Mata"
    ],
    "name:pol_x_preferred": [
      "Mata"
    ],
    "name:por_x_preferred": [
      "Mata"
    ],
    "name:rus_x_preferred": [
      "Мата"
    ],
    "name:spa_x_preferred": [
      "Mata"
    ],
    "name:swe_x_preferred": [
      "Mata"
    ],
    "name:ukr_x_preferred": [
      "Мата"
    ],
    "name:vie_x_preferred": [
      "Mata"
    ],
    "name:zho_x_preferred": [
      "麻塔"
    ],
    "wof:name": "Mata",
    "wof:placetype": "locality"
  },
  "geometry": {
    "coordinates": [
      109.5279,
      36.47191
    ],
    "type": "Point"
  }
}