{
  "type": "Feature",
  "properties": {
    "gn:admin1_code": "23.0",
    "gn:asciiname": "Xinshi",
    "gn:cc2": "CN",
    "gn:country_code": "CN",
    "gn:dem": 4,
    "gn:feature_class": "P",
    "gn:feature_code": "PPL",
    "gn:name": "Xinshi",
    "gn:population": 0,
    "gn:timezone": "Asia/Shanghai",
    "iso:country": "CN",
    "name:ceb_x_preferred": [
      "Xinshi"
    ],
    "name:deu_x_preferred": [
      "Xinshi"
    ],
    "name:eus_x_preferred": [
      "Xinshi"
    ],
    "name:fra_x_preferred": [
      "Xinshi"
    ],
    "name:mlg_x_preferred": [
      "Xinshi"
    ],
    "name:nor_x_preferred": [
      "Xinshi"
    ],
    "name:rus_x_preferred": [
      "Синьши"
    ],
    "name:swe_x_preferred": [
      "Xinshi"
    ],
    "name:und_x_variant": [
      "Tung-hsin-shih",
      "Hsin-shih",
      "Tung-hsin-shih-chen",
      "新市"
    ],
    "name:vie_x_preferred": [
      "Tân Thị"
    ],
    "wof:name": "Xinshi",
    "wof:placetype": "locality"
  },
  "geometry": {
    "coordinates": [
      121.66472,
      30.97278
    ],
    "type": "Point"
  }
}