{
  "type": "Feature",
  "properties": {
    "gn:admin1_code": "13",
    "gn:asciiname": "Yangzi Jianglu",
    "gn:country_code": "CN",
    "gn:dem": 912,
    "gn:feature_class": "P",
    "gn:feature_code": "PPLA3",
    "gn:name": "Yangzi Jianglu",
    "gn:population": 0,
    "gn:timezone": "Asia/Urumqi",
    "iso:country": "CN",
    "name:und_x_variant": [
      "Saybagh Qu",
      "Saybagh",
      "Shayibake",
      "沙依巴克区",
      "沙依巴克"
    ],
    "name:zho_x_preferred": [
      "扬子江路"
    ],
    "wof:name": "Yangzi Jianglu",
    "wof:placetype": "locality"
  },
  "geometry": {
    "coordinates": [
      87.58879,
      43.77332
    ],
    "type": "Point"
  }
}