{
  "type": "Feature",
  "properties": {
    "gn:admin1_code": "1.0",
    "gn:asciiname": "Taishuangtangcun",
    "gn:country_code": "CN",
    "gn:dem": 80,
    "gn:feature_class": "P",
    "gn:feature_code": "PPL",
    "gn:name": "Taishuangtangcun",
    "gn:population": 0,
    "gn:timezone": "Asia/Shanghai",
    "iso:country": "CN",
    "name:zho_x_preferred": [
      "台双塘村"
    ],
    "wof:name": "Taishuangtangcun",
    "wof:placetype": "locality"
  },
  "geometry": {
    "coordinates": [
      115.93636,
      31.92333
    ],
    "type": "Point"
  }
}