{
  "type": "Feature",
  "properties": {
    "gn:admin1_code": "5.0",
    "gn:asciiname": "Songtiantun",
    "gn:country_code": "CN",
    "gn:dem": 170,
    "gn:feature_class": "P",
    "gn:feature_code": "PPL",
    "gn:name": "Songtiantun",
    "gn:population": 0,
    "gn:timezone": "Asia/Shanghai",
    "iso:country": "CN",
    "name:zho_x_preferred": [
      "松田屯"
    ],
    "wof:name": "Songtiantun",
    "wof:placetype": "locality"
  },
  "geometry": {
    "coordinates": [
      130.01762,
      43.06012
    ],
    "type": "Point"
  }
}