{
  "type": "Feature",
  "properties": {
    "gn:admin1_code": "19.0",
    "gn:asciiname": "Dong'ertaizi",
    "gn:country_code": "CN",
    "gn:dem": 94,
    "gn:feature_class": "P",
    "gn:feature_code": "PPL",
    "gn:name": "Dong’ertaizi",
    "gn:population": 0,
    "gn:timezone": "Asia/Shanghai",
    "iso:country": "CN",
    "name:zho_x_preferred": [
      "Dong’ertaizi"
    ],
    "name:zho_x_variant": [
      "东二台子"
    ],
    "wof:name": "Dong'ertaizi",
    "wof:placetype": "locality"
  },
  "geometry": {
    "coordinates": [
      123.52552,
      42.53457
    ],
    "type": "Point"
  }
}