{
  "type": "Feature",
  "properties": {
    "gn:admin1_code": "11.0",
    "gn:asciiname": "Beixicun",
    "gn:country_code": "CN",
    "gn:dem": 601,
    "gn:feature_class": "P",
    "gn:feature_code": "PPL",
    "gn:name": "Beixicun",
    "gn:population": 0,
    "gn:timezone": "Asia/Shanghai",
    "iso:country": "CN",
    "name:zho_x_preferred": [
      "背西村"
    ],
    "wof:name": "Beixicun",
    "wof:placetype": "locality"
  },
  "geometry": {
    "coordinates": [
      110.26932,
      26.4158
    ],
    "type": "Point"
  }
}