{
  "type": "Feature",
  "properties": {
    "gn:admin1_code": "15.0",
    "gn:asciiname": "Xiazhuang",
    "gn:country_code": "CN",
    "gn:dem": 2189,
    "gn:feature_class": "P",
    "gn:feature_code": "PPL",
    "gn:name": "Xiazhuang",
    "gn:population": 0,
    "gn:timezone": "Asia/Shanghai",
    "iso:country": "CN",
    "name:deu_x_preferred": [
      "Xiazhuang"
    ],
    "name:zho_x_preferred": [
      "下庄"
    ],
    "wof:name": "Xiazhuang",
    "wof:placetype": "locality"
  },
  "geometry": {
    "coordinates": [
      104.354,
      35.2631
    ],
    "type": "Point"
  }
}