{
  "type": "Feature",
  "properties": {
    "gn:admin1_code": "22.0",
    "gn:asciiname": "Zhaoxindian",
    "gn:country_code": "CN",
    "gn:dem": 52,
    "gn:feature_class": "P",
    "gn:feature_code": "PPL",
    "gn:name": "Zhaoxindian",
    "gn:population": 0,
    "gn:timezone": "Asia/Shanghai",
    "iso:country": "CN",
    "name:zho_x_preferred": [
      "赵辛店"
    ],
    "wof:name": "Zhaoxindian",
    "wof:placetype": "locality"
  },
  "geometry": {
    "coordinates": [
      116.19424,
      39.80599
    ],
    "type": "Point"
  }
}