{
  "type": "Feature",
  "properties": {
    "gn:admin1_code": "19.0",
    "gn:asciiname": "Xinglonggou",
    "gn:country_code": "CN",
    "gn:dem": 455,
    "gn:feature_class": "P",
    "gn:feature_code": "PPL",
    "gn:name": "Xinglonggou",
    "gn:population": 0,
    "gn:timezone": "Asia/Shanghai",
    "iso:country": "CN",
    "name:zho_x_preferred": [
      "兴隆沟"
    ],
    "name:zho_x_variant": [
      "兴隆沟遗址"
    ],
    "wof:name": "Xinglonggou",
    "wof:placetype": "locality"
  },
  "geometry": {
    "coordinates": [
      119.41,
      41.3033
    ],
    "type": "Point"
  }
}