{
  "type": "Feature",
  "properties": {
    "gn:admin1_code": "18.0",
    "gn:asciiname": "Shangdai",
    "gn:country_code": "CN",
    "gn:dem": 653,
    "gn:feature_class": "P",
    "gn:feature_code": "PPL",
    "gn:name": "Shangdai",
    "gn:population": 0,
    "gn:timezone": "Asia/Shanghai",
    "iso:country": "CN",
    "name:zho_x_preferred": [
      "上歹"
    ],
    "wof:name": "Shangdai",
    "wof:placetype": "locality"
  },
  "geometry": {
    "coordinates": [
      108.784,
      25.8051
    ],
    "type": "Point"
  }
}