{
  "type": "Feature",
  "properties": {
    "gn:admin1_code": "13.0",
    "gn:asciiname": "Karayulgun",
    "gn:cc2": "CN",
    "gn:country_code": "CN",
    "gn:dem": 1191,
    "gn:feature_class": "P",
    "gn:feature_code": "PPL",
    "gn:name": "Karayulgun",
    "gn:population": 0,
    "gn:timezone": "Asia/Shanghai",
    "iso:country": "CN",
    "name:uig_x_preferred": [
      "K̩arayulƣun"
    ],
    "name:uig_x_variant": [
      "Qarayulghun",
      "قارايۇلغۇن",
      "Қараюлғун"
    ],
    "name:und_x_variant": [
      "Qara Yulghun",
      "Karadzhulgun",
      "Karajulgun",
      "Ha-la-yü-erh-kun",
      "Ka-la-yü-erh-kun",
      "Karajylgun",
      "K’o-la-yü-erh-kun",
      "Kara Yulghun",
      "Karayulgun"
    ],
    "wof:name": "Karayulgun",
    "wof:placetype": "locality"
  },
  "geometry": {
    "coordinates": [
      80.79944,
      41.335
    ],
    "type": "Point"
  }
}