{
  "type": "Feature",
  "properties": {
    "gn:admin1_code": "18",
    "gn:asciiname": "Dandong",
    "gn:country_code": "CN",
    "gn:dem": 615,
    "gn:feature_class": "P",
    "gn:feature_code": "PPL",
    "gn:name": "Dandong",
    "gn:population": 0,
    "gn:timezone": "Asia/Shanghai",
    "iso:country": "CN",
    "name:afr_x_preferred": [
      "Dandong"
    ],
    "name:ara_x_preferred": [
      "داندونغ"
    ],
    "name:arz_x_preferred": [
      "داندونج"
    ],
    "name:aze_x_preferred": [
      "Dandun"
    ],
    "name:bre_x_preferred": [
      "Dandong"
    ],
    "name:bul_x_preferred": [
      "Дандун"
    ],
    "name:cat_x_preferred": [
      "Dandong"
    ],
    "name:cdo_x_preferred": [
      "Dăng-dŭng"
    ],
    "name:ceb_x_preferred": [
      "Dandong"
    ],
    "name:ces_x_preferred": [
      "Tan-tung"
    ],
    "name:dan_x_preferred": [
      "Dandong"
    ],
    "name:deu_x_preferred": [
      "Dandong"
    ],
    "name:ell_x_preferred": [
      "Ταντούνγκ"
    ],
    "name:epo_x_preferred": [
      "Dandong"
    ],
    "name:est_x_preferred": [
      "Dandong Shi"
    ],
    "name:eus_x_preferred": [
      "Dandong"
    ],
    "name:fas_x_preferred": [
      "داندونگ"
    ],
    "name:fin_x_preferred": [
      "Dandong"
    ],
    "name:fra_x_preferred": [
      "Dandong"
    ],
    "name:glg_x_preferred": [
      "Dandong"
    ],
    "name:heb_x_preferred": [
      "דנדונג"
    ],
    "name:hye_x_preferred": [
      "Դանդուն"
    ],
    "name:ind_x_preferred": [
      "Dandong"
    ],
    "name:ita_x_preferred": [
      "Dandong"
    ],
    "name:jpn_x_preferred": [
      "丹東市"
    ],
    "name:kaz_x_preferred": [
      "Даньдун"
    ],
    "name:kik_x_preferred": [
      "Dandong"
    ],
    "name:kor_x_preferred": [
      "단둥시"
    ],
    "name:lit_x_preferred": [
      "Dandongas"
    ],
    "name:mal_x_preferred": [
      "ഡാൻദോങ്"
    ],
    "name:mlg_x_preferred": [
      "Dandong"
    ],
    "name:nld_x_preferred": [
      "Dandong"
    ],
    "name:nno_x_preferred": [
      "Dandong"
    ],
    "name:nor_x_preferred": [
      "Dandong"
    ],
    "name:oci_x_preferred": [
      "Dandong"
    ],
    "name:pol_x_preferred": [
      "Dandong"
    ],
    "name:por_x_preferred": [
      "Dandong"
    ],
    "name:ron_x_preferred": [
      "Dandong"
    ],
    "name:rus_x_preferred": [
      "Даньдун"
    ],
    "name:sco_x_preferred": [
      "Dandong"
    ],
    "name:spa_x_preferred": [
      "Dandong"
    ],
    "name:srp_x_preferred": [
      "Дандунг"
    ],
    "name:swe_x_preferred": [
      "Dandong"
    ],
    "name:tha_x_preferred": [
      "ตานตง"
    ],
    "name:tur_x_preferred": [
      "Dandong"
    ],
    "name:ukr_x_preferred": [
      "Даньдун"
    ],
    "name:urd_x_preferred": [
      "داندونگ"
    ],
    "name:vie_x_preferred": [
      "Đan Đông"
    ],
    "name:war_x_preferred": [
      "Dandong"
    ],
    "name:wuu_x_preferred": [
      "丹东市"
    ],
    "name:zho_x_preferred": [
      "丹东市"
    ],
    "wof:name": "Dandong",
    "wof:placetype": "locality"
  },
  "geometry": {
    "coordinates": [
      108.90889,
      26.97944
    ],
    "type": "Point"
  }
}