{
  "type": "Feature",
  "properties": {
    "gn:admin1_code": "20.0",
    "gn:asciiname": "Xuejiawan",
    "gn:country_code": "CN",
    "gn:dem": 1138,
    "gn:feature_class": "P",
    "gn:feature_code": "PPLA3",
    "gn:name": "Xuejiawan",
    "gn:population": 0,
    "gn:timezone": "Asia/Shanghai",
    "iso:country": "CN",
    "name:deu_x_preferred": [
      "Jung-Gar-Banner"
    ],
    "name:jpn_x_preferred": [
      "ジュンガル旗"
    ],
    "name:kor_x_preferred": [
      "준거얼 기"
    ],
    "name:mon_x_preferred": [
      "Зүүнгар хошуу"
    ],
    "name:nor_x_preferred": [
      "Jungar"
    ],
    "name:pol_x_preferred": [
      "Jungar Qi"
    ],
    "name:rus_x_preferred": [
      "Джунгар-Ци"
    ],
    "name:swe_x_preferred": [
      "Jungar"
    ],
    "name:und_x_variant": [
      "薛家湾",
      "Xuejiawan Zhen",
      "Zhunge’er Qi",
      "薛家湾镇"
    ],
    "name:urd_x_preferred": [
      "جنگار پرچم"
    ],
    "name:vie_x_preferred": [
      "Jung Gar"
    ],
    "name:zho_x_preferred": [
      "Xuejiawan"
    ],
    "name:zho_x_variant": [
      "准格尔旗"
    ],
    "wof:name": "Xuejiawan",
    "wof:placetype": "locality"
  },
  "geometry": {
    "coordinates": [
      111.2208,
      39.86678
    ],
    "type": "Point"
  }
}