{
  "type": "Feature",
  "properties": {
    "gn:admin1_code": "19",
    "gn:asciiname": "Huanrenxian Balidianzi Guoyou Linchang",
    "gn:country_code": "CN",
    "gn:dem": 741,
    "gn:feature_class": "P",
    "gn:feature_code": "PPLF",
    "gn:name": "Huanrenxian Balidianzi Guoyou Linchang",
    "gn:population": 0,
    "gn:timezone": "Asia/Shanghai",
    "iso:country": "CN",
    "name:und_x_variant": [
      "Guoying Linchang",
      "Huanrenxian Balidianzi Guoyou Linchang",
      "桓仁县八里甸子国有林场",
      "Huanren Manzu Zhizixian Balidianzi Guoyou Linchang",
      "国营林场",
      "桓仁满族自治县八里甸子国有林场"
    ],
    "wof:name": "Huanrenxian Balidianzi Guoyou Linchang",
    "wof:placetype": "locality"
  },
  "geometry": {
    "coordinates": [
      124.78255,
      41.24033
    ],
    "type": "Point"
  }
}