{
  "type": "Feature",
  "properties": {
    "gn:admin1_code": "8.0",
    "gn:asciiname": "Chengjiucun",
    "gn:country_code": "CN",
    "gn:dem": 209,
    "gn:feature_class": "P",
    "gn:feature_code": "PPL",
    "gn:name": "Chengjiucun",
    "gn:population": 0,
    "gn:timezone": "Asia/Shanghai",
    "iso:country": "CN",
    "name:zho_x_preferred": [
      "城久村"
    ],
    "wof:name": "Chengjiucun",
    "wof:placetype": "locality"
  },
  "geometry": {
    "coordinates": [
      126.88384,
      47.76076
    ],
    "type": "Point"
  }
}