{
  "type": "Feature",
  "properties": {
    "gn:admin1_code": "2.0",
    "gn:asciiname": "Tongjia",
    "gn:country_code": "CN",
    "gn:dem": 122,
    "gn:feature_class": "P",
    "gn:feature_code": "PPL",
    "gn:name": "Tongjia",
    "gn:population": 0,
    "gn:timezone": "Asia/Shanghai",
    "iso:country": "CN",
    "name:zho_x_preferred": [
      "童家"
    ],
    "wof:name": "Tongjia",
    "wof:placetype": "locality"
  },
  "geometry": {
    "coordinates": [
      118.49813,
      28.94904
    ],
    "type": "Point"
  }
}