{
  "type": "Feature",
  "properties": {
    "gn:admin1_code": "26.0",
    "gn:asciiname": "Mengjia Laozhuang",
    "gn:country_code": "CN",
    "gn:dem": 1020,
    "gn:feature_class": "P",
    "gn:feature_code": "PPL",
    "gn:name": "Mengjia Laozhuang",
    "gn:population": 0,
    "gn:timezone": "Asia/Shanghai",
    "iso:country": "CN",
    "name:zho_x_preferred": [
      "孟家老庄"
    ],
    "wof:name": "Mengjia Laozhuang",
    "wof:placetype": "locality"
  },
  "geometry": {
    "coordinates": [
      110.71967,
      33.76137
    ],
    "type": "Point"
  }
}