{
  "type": "Feature",
  "properties": {
    "gn:admin1_code": "30",
    "gn:asciiname": "Baitang",
    "gn:country_code": "CN",
    "gn:dem": 33,
    "gn:feature_class": "P",
    "gn:feature_code": "PPLA4",
    "gn:name": "Baitang",
    "gn:population": 0,
    "gn:timezone": "Asia/Shanghai",
    "iso:country": "CN",
    "name:fas_x_preferred": [
      "بایتانگ"
    ],
    "name:hak_x_preferred": [
      "Pak-thòng-chṳ́n"
    ],
    "name:und_x_variant": [
      "Pai-t’ang-hsü",
      "Pai-t’ang",
      "Baitang Zhen",
      "Baitang",
      "Botang Zhen"
    ],
    "name:zho_x_preferred": [
      "柏塘"
    ],
    "name:zho_x_variant": [
      "柏塘镇"
    ],
    "wof:name": "Baitang",
    "wof:placetype": "locality"
  },
  "geometry": {
    "coordinates": [
      114.36043,
      23.39471
    ],
    "type": "Point"
  }
}