{
  "type": "Feature",
  "properties": {
    "gn:admin1_code": "10",
    "gn:asciiname": "Pengkong",
    "gn:cc2": "CN",
    "gn:country_code": "CN",
    "gn:dem": 1359,
    "gn:feature_class": "P",
    "gn:feature_code": "PPL",
    "gn:name": "Pengkong",
    "gn:population": 0,
    "gn:timezone": "Asia/Shanghai",
    "iso:country": "CN",
    "name:und_x_variant": [
      "P’eng-k’ung",
      "Pengkong"
    ],
    "wof:name": "Pengkong",
    "wof:placetype": "locality"
  },
  "geometry": {
    "coordinates": [
      114.38333,
      41.63333
    ],
    "type": "Point"
  }
}