{
  "type": "Feature",
  "properties": {
    "gn:admin1_code": "12.0",
    "gn:asciiname": "Xiaoxiniugou",
    "gn:country_code": "CN",
    "gn:dem": 685,
    "gn:feature_class": "P",
    "gn:feature_code": "PPL",
    "gn:name": "Xiaoxiniugou",
    "gn:population": 0,
    "gn:timezone": "Asia/Shanghai",
    "iso:country": "CN",
    "name:zho_x_preferred": [
      "小犀牛沟"
    ],
    "wof:name": "Xiaoxiniugou",
    "wof:placetype": "locality"
  },
  "geometry": {
    "coordinates": [
      110.77809,
      32.17513
    ],
    "type": "Point"
  }
}