{
  "type": "Feature",
  "properties": {
    "gn:admin1_code": "4.0",
    "gn:asciiname": "Tangjiazhuang",
    "gn:country_code": "CN",
    "gn:dem": 5,
    "gn:feature_class": "P",
    "gn:feature_code": "PPL",
    "gn:name": "Tangjiazhuang",
    "gn:population": 0,
    "gn:timezone": "Asia/Shanghai",
    "iso:country": "CN",
    "name:ceb_x_preferred": [
      "Tangjiazhuang"
    ],
    "name:nno_x_preferred": [
      "Tangjiazhuang"
    ],
    "name:nor_x_preferred": [
      "Tangjiazhuang"
    ],
    "name:swe_x_preferred": [
      "Tangjiazhuang"
    ],
    "name:zho_x_preferred": [
      "Tangjiazhuang"
    ],
    "name:zho_x_variant": [
      "汤家庄",
      "唐家庄街道"
    ],
    "wof:name": "Tangjiazhuang",
    "wof:placetype": "locality"
  },
  "geometry": {
    "coordinates": [
      120.50401,
      30.8233
    ],
    "type": "Point"
  }
}