{
  "type": "Feature",
  "properties": {
    "gn:admin1_code": "7",
    "gn:asciiname": "Pengzhou",
    "gn:country_code": "CN",
    "gn:dem": 20,
    "gn:feature_class": "P",
    "gn:feature_code": "PPL",
    "gn:name": "Pengzhou",
    "gn:population": 0,
    "gn:timezone": "Asia/Shanghai",
    "iso:country": "CN",
    "name:deu_x_preferred": [
      "Pengzhou"
    ],
    "name:eus_x_preferred": [
      "Pengzhou"
    ],
    "name:fas_x_preferred": [
      "پنگژو"
    ],
    "name:fra_x_preferred": [
      "Pengzhou"
    ],
    "name:hak_x_preferred": [
      "Phàng-chû-sṳ"
    ],
    "name:ita_x_preferred": [
      "Pengzhou"
    ],
    "name:jpn_x_preferred": [
      "彭州市"
    ],
    "name:kik_x_preferred": [
      "Pengzhou"
    ],
    "name:kor_x_preferred": [
      "펑저우시"
    ],
    "name:nor_x_preferred": [
      "Pengzhou"
    ],
    "name:rus_x_preferred": [
      "Пэнчжоу"
    ],
    "name:spa_x_preferred": [
      "Pengzhou"
    ],
    "name:swe_x_preferred": [
      "Pengzhou"
    ],
    "name:urd_x_preferred": [
      "پینگژوو"
    ],
    "name:vie_x_preferred": [
      "Bành Châu"
    ],
    "name:zho_x_preferred": [
      "蓬州"
    ],
    "name:zho_x_variant": [
      "彭州市"
    ],
    "wof:name": "Pengzhou",
    "wof:placetype": "locality"
  },
  "geometry": {
    "coordinates": [
      117.70472,
      24.57111
    ],
    "type": "Point"
  }
}