{
  "type": "Feature",
  "properties": {
    "gn:admin1_code": "18",
    "gn:asciiname": "Pudong",
    "gn:country_code": "CN",
    "gn:dem": 821,
    "gn:feature_class": "P",
    "gn:feature_code": "PPL",
    "gn:name": "Pudong",
    "gn:population": 0,
    "gn:timezone": "Asia/Shanghai",
    "iso:country": "CN",
    "name:ara_x_preferred": [
      "بودونغ"
    ],
    "name:ast_x_preferred": [
      "Pudong"
    ],
    "name:aze_x_preferred": [
      "Pudun"
    ],
    "name:ceb_x_preferred": [
      "Pudong Xinqu"
    ],
    "name:ces_x_preferred": [
      "Pchu-tung"
    ],
    "name:dan_x_preferred": [
      "Pudong"
    ],
    "name:deu_x_preferred": [
      "Pudong"
    ],
    "name:eus_x_preferred": [
      "Pudong barrutia"
    ],
    "name:fas_x_preferred": [
      "پودانگ"
    ],
    "name:fin_x_preferred": [
      "Pudong"
    ],
    "name:glg_x_preferred": [
      "Pudong"
    ],
    "name:heb_x_preferred": [
      "פודונג"
    ],
    "name:hun_x_preferred": [
      "Putung"
    ],
    "name:ind_x_preferred": [
      "Pudong"
    ],
    "name:ita_x_preferred": [
      "Pudong"
    ],
    "name:jpn_x_preferred": [
      "浦東新区"
    ],
    "name:kor_x_preferred": [
      "푸둥 신구"
    ],
    "name:lit_x_preferred": [
      "Pudongas"
    ],
    "name:nld_x_preferred": [
      "Pudong"
    ],
    "name:nno_x_preferred": [
      "Pudong"
    ],
    "name:nor_x_preferred": [
      "Pudong"
    ],
    "name:pol_x_preferred": [
      "Pudong"
    ],
    "name:por_x_preferred": [
      "Pudong"
    ],
    "name:ron_x_preferred": [
      "Pudong"
    ],
    "name:rus_x_preferred": [
      "Пудун"
    ],
    "name:slk_x_preferred": [
      "Pchu-tung"
    ],
    "name:spa_x_preferred": [
      "Pudong"
    ],
    "name:swe_x_preferred": [
      "Pudong"
    ],
    "name:tgl_x_preferred": [
      "Pudong"
    ],
    "name:tur_x_preferred": [
      "Pudong"
    ],
    "name:ukr_x_preferred": [
      "Пудун"
    ],
    "name:urd_x_preferred": [
      "پودانگ"
    ],
    "name:vie_x_preferred": [
      "Phố Đông"
    ],
    "name:wuu_x_preferred": [
      "浦东新区"
    ],
    "name:zho_x_preferred": [
      "蒲洞"
    ],
    "name:zho_x_variant": [
      "浦东新区"
    ],
    "wof:name": "Pudong",
    "wof:placetype": "locality"
  },
  "geometry": {
    "coordinates": [
      108.988,
      26.1719
    ],
    "type": "Point"
  }
}