{
  "type": "Feature",
  "properties": {
    "gn:admin1_code": "29.0",
    "gn:asciiname": "Dongjiazhai",
    "gn:country_code": "CN",
    "gn:dem": 1724,
    "gn:feature_class": "P",
    "gn:feature_code": "PPL",
    "gn:name": "Dongjiazhai",
    "gn:population": 0,
    "gn:timezone": "Asia/Shanghai",
    "iso:country": "CN",
    "name:zho_x_preferred": [
      "董家寨"
    ],
    "wof:name": "Dongjiazhai",
    "wof:placetype": "locality"
  },
  "geometry": {
    "coordinates": [
      98.282,
      25.3121
    ],
    "type": "Point"
  }
}