{
  "type": "Feature",
  "properties": {
    "gn:admin1_code": "26.0",
    "gn:asciiname": "Songjiashan",
    "gn:country_code": "CN",
    "gn:dem": 1317,
    "gn:feature_class": "P",
    "gn:feature_code": "PPL",
    "gn:name": "Songjiashan",
    "gn:population": 0,
    "gn:timezone": "Asia/Shanghai",
    "iso:country": "CN",
    "name:und_x_variant": [
      "宋家山"
    ],
    "wof:name": "Songjiashan",
    "wof:placetype": "locality"
  },
  "geometry": {
    "coordinates": [
      106.65792,
      33.85736
    ],
    "type": "Point"
  }
}