{
  "type": "Feature",
  "properties": {
    "gn:admin1_code": "25.0",
    "gn:asciiname": "Majiayaocun",
    "gn:country_code": "CN",
    "gn:dem": 203,
    "gn:feature_class": "P",
    "gn:feature_code": "PPL",
    "gn:name": "Majiayaocun",
    "gn:population": 0,
    "gn:timezone": "Asia/Shanghai",
    "iso:country": "CN",
    "name:zho_x_preferred": [
      "马家窑村"
    ],
    "wof:name": "Majiayaocun",
    "wof:placetype": "locality"
  },
  "geometry": {
    "coordinates": [
      120.95853,
      37.29604000000001
    ],
    "type": "Point"
  }
}