{
  "type": "Feature",
  "properties": {
    "gn:admin1_code": "32.0",
    "gn:asciiname": "Yegegengba",
    "gn:country_code": "CN",
    "gn:dem": 3182,
    "gn:feature_class": "P",
    "gn:feature_code": "PPL",
    "gn:name": "Yegegengba",
    "gn:population": 0,
    "gn:timezone": "Asia/Shanghai",
    "iso:country": "CN",
    "name:zho_x_preferred": [
      "业哥更巴"
    ],
    "wof:name": "Yegegengba",
    "wof:placetype": "locality"
  },
  "geometry": {
    "coordinates": [
      100.289,
      31.2136
    ],
    "type": "Point"
  }
}