{
  "type": "Feature",
  "properties": {
    "gn:admin1_code": "16.0",
    "gn:asciiname": "Huanggang",
    "gn:country_code": "CN",
    "gn:dem": 379,
    "gn:feature_class": "P",
    "gn:feature_code": "PPL",
    "gn:name": "Huanggang",
    "gn:population": 0,
    "gn:timezone": "Asia/Shanghai",
    "iso:country": "CN",
    "name:afr_x_preferred": [
      "Huanggang"
    ],
    "name:ara_x_preferred": [
      "هوانغقانغ"
    ],
    "name:bul_x_preferred": [
      "Хуанган"
    ],
    "name:cdo_x_preferred": [
      "Uòng-gŏng"
    ],
    "name:ces_x_preferred": [
      "Chuang-kang"
    ],
    "name:dan_x_preferred": [
      "Huanggang"
    ],
    "name:deu_x_preferred": [
      "Huanggang"
    ],
    "name:eus_x_preferred": [
      "Huanggang"
    ],
    "name:fas_x_preferred": [
      "هوانگانگ"
    ],
    "name:fin_x_preferred": [
      "Huanggang"
    ],
    "name:fra_x_preferred": [
      "Huanggang"
    ],
    "name:ita_x_preferred": [
      "Huanggang"
    ],
    "name:jpn_x_preferred": [
      "黄岡市"
    ],
    "name:kik_x_preferred": [
      "Huanggang"
    ],
    "name:kor_x_preferred": [
      "황강시"
    ],
    "name:mlg_x_preferred": [
      "Huanggang"
    ],
    "name:mya_x_preferred": [
      "ဟန်ကောင်မြို့"
    ],
    "name:nld_x_preferred": [
      "Huanggang"
    ],
    "name:nno_x_preferred": [
      "Huanggang"
    ],
    "name:nor_x_preferred": [
      "Huanggang"
    ],
    "name:pam_x_preferred": [
      "Huanggang"
    ],
    "name:pol_x_preferred": [
      "Huanggang"
    ],
    "name:rus_x_preferred": [
      "Хуанган"
    ],
    "name:spa_x_preferred": [
      "Huanggang"
    ],
    "name:srp_x_preferred": [
      "Хуанганг"
    ],
    "name:swa_x_preferred": [
      "Huanggang"
    ],
    "name:swe_x_preferred": [
      "Huanggang"
    ],
    "name:tgl_x_preferred": [
      "Huanggang"
    ],
    "name:tur_x_preferred": [
      "Huanggang"
    ],
    "name:ukr_x_preferred": [
      "Хуанган"
    ],
    "name:urd_x_preferred": [
      "ہوانگگانگ"
    ],
    "name:vie_x_preferred": [
      "Hoàng Cương"
    ],
    "name:zho_x_preferred": [
      "黄港"
    ],
    "name:zho_x_variant": [
      "黄冈市"
    ],
    "wof:name": "Huanggang",
    "wof:placetype": "locality"
  },
  "geometry": {
    "coordinates": [
      107.143,
      25.4284
    ],
    "type": "Point"
  }
}