{
  "type": "Feature",
  "properties": {
    "gn:admin1_code": "3.0",
    "gn:asciiname": "Kaifeng",
    "gn:country_code": "CN",
    "gn:dem": 335,
    "gn:feature_class": "P",
    "gn:feature_code": "PPL",
    "gn:name": "Kaifeng",
    "gn:population": 0,
    "gn:timezone": "Asia/Shanghai",
    "iso:country": "CN",
    "name:afr_x_preferred": [
      "Kaifeng"
    ],
    "name:amh_x_preferred": [
      "ካይፈንግ"
    ],
    "name:ara_x_preferred": [
      "كايفنغ"
    ],
    "name:ast_x_preferred": [
      "Kaifeng"
    ],
    "name:bel_x_preferred": [
      "Кайфэн"
    ],
    "name:cat_x_preferred": [
      "Kaifeng"
    ],
    "name:cdo_x_preferred": [
      "Kăi-hŭng"
    ],
    "name:ceb_x_preferred": [
      "Kaifeng"
    ],
    "name:ces_x_preferred": [
      "Kchaj-feng"
    ],
    "name:dan_x_preferred": [
      "Kaifeng"
    ],
    "name:deu_x_preferred": [
      "Kaifeng"
    ],
    "name:epo_x_preferred": [
      "Kajfengo"
    ],
    "name:est_x_preferred": [
      "Kaifeng"
    ],
    "name:eus_x_preferred": [
      "Kaifeng"
    ],
    "name:fas_x_preferred": [
      "کایفنگ"
    ],
    "name:fin_x_preferred": [
      "Kaifeng"
    ],
    "name:fra_x_preferred": [
      "Kaifeng"
    ],
    "name:heb_x_preferred": [
      "קאיפנג"
    ],
    "name:hrv_x_preferred": [
      "Kaifeng"
    ],
    "name:ind_x_preferred": [
      "Kaifeng"
    ],
    "name:ita_x_preferred": [
      "Kaifeng"
    ],
    "name:jpn_x_preferred": [
      "開封市"
    ],
    "name:kat_x_preferred": [
      "კაიფინი"
    ],
    "name:kik_x_preferred": [
      "Kaifeng"
    ],
    "name:kor_x_preferred": [
      "카이펑시"
    ],
    "name:mlg_x_preferred": [
      "Kaifeng"
    ],
    "name:mon_x_preferred": [
      "Кайфэн"
    ],
    "name:nld_x_preferred": [
      "Kaifeng"
    ],
    "name:nno_x_preferred": [
      "Kaifeng"
    ],
    "name:nor_x_preferred": [
      "Kaifeng"
    ],
    "name:pam_x_preferred": [
      "Kaifeng"
    ],
    "name:pol_x_preferred": [
      "Kaifeng"
    ],
    "name:por_x_preferred": [
      "Kaifeng"
    ],
    "name:ron_x_preferred": [
      "Kaifeng"
    ],
    "name:rus_x_preferred": [
      "Кайфын"
    ],
    "name:sco_x_preferred": [
      "Kaifeng"
    ],
    "name:spa_x_preferred": [
      "Kaifeng"
    ],
    "name:srp_x_preferred": [
      "Кајфенг"
    ],
    "name:swe_x_preferred": [
      "Kaifeng"
    ],
    "name:tam_x_preferred": [
      "கைஃபெங்"
    ],
    "name:tha_x_preferred": [
      "ไคเฟิง"
    ],
    "name:tur_x_preferred": [
      "Kaifeng"
    ],
    "name:uig_x_preferred": [
      "Keyféng shehiri"
    ],
    "name:ukr_x_preferred": [
      "Кайфен"
    ],
    "name:und_x_variant": [
      "凯丰"
    ],
    "name:urd_x_preferred": [
      "کائفینگ"
    ],
    "name:uzb_x_preferred": [
      "Kayfin"
    ],
    "name:vie_x_preferred": [
      "Khai Phong"
    ],
    "name:war_x_preferred": [
      "Kaifeng"
    ],
    "name:wuu_x_preferred": [
      "开封市"
    ],
    "name:zho_x_preferred": [
      "开封市"
    ],
    "wof:name": "Kaifeng",
    "wof:placetype": "locality"
  },
  "geometry": {
    "coordinates": [
      115.95995,
      25.96145
    ],
    "type": "Point"
  }
}