{
  "type": "Feature",
  "properties": {
    "gn:admin1_code": "19.0",
    "gn:asciiname": "Xiaolutun",
    "gn:country_code": "CN",
    "gn:dem": 15,
    "gn:feature_class": "P",
    "gn:feature_code": "PPL",
    "gn:name": "Xiaolütun",
    "gn:population": 0,
    "gn:timezone": "Asia/Shanghai",
    "iso:country": "CN",
    "name:zho_x_preferred": [
      "Xiaolütun"
    ],
    "name:zho_x_variant": [
      "小吕屯"
    ],
    "wof:name": "Xiaolutun",
    "wof:placetype": "locality"
  },
  "geometry": {
    "coordinates": [
      121.72732,
      39.40873
    ],
    "type": "Point"
  }
}