{
  "type": "Feature",
  "properties": {
    "gn:admin1_code": "11.0",
    "gn:asciiname": "Putou",
    "gn:country_code": "CN",
    "gn:dem": 452,
    "gn:feature_class": "P",
    "gn:feature_code": "PPL",
    "gn:name": "Putou",
    "gn:population": 0,
    "gn:timezone": "Asia/Shanghai",
    "iso:country": "CN",
    "name:zho_x_preferred": [
      "铺头"
    ],
    "wof:name": "Putou",
    "wof:placetype": "locality"
  },
  "geometry": {
    "coordinates": [
      109.76961,
      26.08866
    ],
    "type": "Point"
  }
}