{
  "type": "Feature",
  "properties": {
    "gn:admin1_code": "5.0",
    "gn:asciiname": "Hexintun",
    "gn:country_code": "CN",
    "gn:dem": 284,
    "gn:feature_class": "P",
    "gn:feature_code": "PPL",
    "gn:name": "Hexintun",
    "gn:population": 0,
    "gn:timezone": "Asia/Shanghai",
    "iso:country": "CN",
    "name:und_x_variant": [
      "合新屯"
    ],
    "wof:name": "Hexintun",
    "wof:placetype": "locality"
  },
  "geometry": {
    "coordinates": [
      129.44134,
      43.13449
    ],
    "type": "Point"
  }
}