{
  "type": "Feature",
  "properties": {
    "gn:admin1_code": "32.0",
    "gn:asciiname": "Zhanghua",
    "gn:country_code": "CN",
    "gn:dem": 465,
    "gn:feature_class": "P",
    "gn:feature_code": "PPLA4",
    "gn:name": "Zhanghua",
    "gn:population": 0,
    "gn:timezone": "Asia/Shanghai",
    "iso:country": "CN",
    "name:und_x_variant": [
      "Zhanghua Zhen",
      "张华镇"
    ],
    "name:zho_x_preferred": [
      "张华"
    ],
    "wof:name": "Zhanghua",
    "wof:placetype": "locality"
  },
  "geometry": {
    "coordinates": [
      106.18506,
      32.14784
    ],
    "type": "Point"
  }
}