{
  "type": "Feature",
  "properties": {
    "gn:admin1_code": "3.0",
    "gn:asciiname": "Youjia",
    "gn:country_code": "CN",
    "gn:dem": 247,
    "gn:feature_class": "P",
    "gn:feature_code": "PPL",
    "gn:name": "Youjia",
    "gn:population": 0,
    "gn:timezone": "Asia/Shanghai",
    "iso:country": "CN",
    "name:urd_x_preferred": [
      "یوجیہ"
    ],
    "name:zho_x_preferred": [
      "游家"
    ],
    "name:zho_x_variant": [
      "游家镇"
    ],
    "wof:name": "Youjia",
    "wof:placetype": "locality"
  },
  "geometry": {
    "coordinates": [
      117.09368,
      27.72383
    ],
    "type": "Point"
  }
}