{
  "type": "Feature",
  "properties": {
    "gn:admin1_code": "3.0",
    "gn:asciiname": "Dalong",
    "gn:country_code": "CN",
    "gn:dem": 24,
    "gn:feature_class": "P",
    "gn:feature_code": "PPL",
    "gn:name": "Dalong",
    "gn:population": 0,
    "gn:timezone": "Asia/Shanghai",
    "iso:country": "CN",
    "name:und_x_variant": [
      "大垄"
    ],
    "wof:name": "Dalong",
    "wof:placetype": "locality"
  },
  "geometry": {
    "coordinates": [
      115.76788,
      29.39117
    ],
    "type": "Point"
  }
}