{
  "type": "Feature",
  "properties": {
    "gn:admin1_code": "25",
    "gn:asciiname": "Xiangbotouwang",
    "gn:country_code": "CN",
    "gn:dem": 124,
    "gn:feature_class": "P",
    "gn:feature_code": "PPL",
    "gn:name": "Xiangbotouwang",
    "gn:population": 0,
    "gn:timezone": "Asia/Shanghai",
    "iso:country": "CN",
    "name:zho_x_preferred": [
      "响波头汪"
    ],
    "wof:name": "Xiangbotouwang",
    "wof:placetype": "locality"
  },
  "geometry": {
    "coordinates": [
      118.762,
      35.6021
    ],
    "type": "Point"
  }
}