{
  "type": "Feature",
  "properties": {
    "gn:admin1_code": "2.0",
    "gn:asciiname": "Quancun",
    "gn:country_code": "CN",
    "gn:dem": 67,
    "gn:feature_class": "P",
    "gn:feature_code": "PPL",
    "gn:name": "Quancun",
    "gn:population": 0,
    "gn:timezone": "Asia/Shanghai",
    "iso:country": "CN",
    "name:zho_x_preferred": [
      "全村"
    ],
    "wof:name": "Quancun",
    "wof:placetype": "locality"
  },
  "geometry": {
    "coordinates": [
      119.98264,
      29.24334
    ],
    "type": "Point"
  }
}