{
  "type": "Feature",
  "properties": {
    "gn:admin1_code": "19.0",
    "gn:asciiname": "Panjiabu",
    "gn:country_code": "CN",
    "gn:dem": 273,
    "gn:feature_class": "P",
    "gn:feature_code": "PPL",
    "gn:name": "Panjiabu",
    "gn:population": 0,
    "gn:timezone": "Asia/Shanghai",
    "iso:country": "CN",
    "name:und_x_variant": [
      "Panjiabaozi",
      "Panjia Buzi"
    ],
    "name:zho_x_preferred": [
      "潘家堡"
    ],
    "name:zho_x_variant": [
      "潘家堡子"
    ],
    "wof:name": "Panjiabu",
    "wof:placetype": "locality"
  },
  "geometry": {
    "coordinates": [
      125.103,
      40.8373
    ],
    "type": "Point"
  }
}