{
  "type": "Feature",
  "properties": {
    "gn:admin1_code": "19.0",
    "gn:asciiname": "Zhaojiacun",
    "gn:country_code": "CN",
    "gn:dem": 336,
    "gn:feature_class": "P",
    "gn:feature_code": "PPL",
    "gn:name": "Zhaojiacun",
    "gn:population": 0,
    "gn:timezone": "Asia/Shanghai",
    "iso:country": "CN",
    "name:zho_x_preferred": [
      "赵家村"
    ],
    "wof:name": "Zhaojiacun",
    "wof:placetype": "locality"
  },
  "geometry": {
    "coordinates": [
      124.565,
      41.65288
    ],
    "type": "Point"
  }
}