{
  "type": "Feature",
  "properties": {
    "gn:admin1_code": "8.0",
    "gn:asciiname": "Hongshengtun",
    "gn:country_code": "CN",
    "gn:dem": 299,
    "gn:feature_class": "P",
    "gn:feature_code": "PPL",
    "gn:name": "Hongshengtun",
    "gn:population": 0,
    "gn:timezone": "Asia/Shanghai",
    "iso:country": "CN",
    "name:zho_x_preferred": [
      "洪升屯"
    ],
    "wof:name": "Hongshengtun",
    "wof:placetype": "locality"
  },
  "geometry": {
    "coordinates": [
      127.83845,
      45.42247
    ],
    "type": "Point"
  }
}