{
  "type": "Feature",
  "properties": {
    "gn:admin1_code": "31.0",
    "gn:asciiname": "Yashang",
    "gn:country_code": "CN",
    "gn:dem": 60,
    "gn:feature_class": "P",
    "gn:feature_code": "PPL",
    "gn:name": "Yashang",
    "gn:population": 0,
    "gn:timezone": "Asia/Shanghai",
    "iso:country": "CN",
    "name:und_x_variant": [
      "Yashangpo",
      "Yashang",
      "亚上"
    ],
    "name:zho_x_preferred": [
      "亚上坡"
    ],
    "wof:name": "Yashang",
    "wof:placetype": "locality"
  },
  "geometry": {
    "coordinates": [
      109.9066,
      18.64252
    ],
    "type": "Point"
  }
}