{
  "type": "Feature",
  "properties": {
    "gn:admin1_code": "12.0",
    "gn:asciiname": "Tudi'ao",
    "gn:country_code": "CN",
    "gn:dem": 1729,
    "gn:feature_class": "P",
    "gn:feature_code": "PPL",
    "gn:name": "Tudi’ao",
    "gn:population": 0,
    "gn:timezone": "Asia/Shanghai",
    "iso:country": "CN",
    "name:und_x_variant": [
      "Tudi’ao"
    ],
    "name:zho_x_preferred": [
      "土地坳"
    ],
    "wof:name": "Tudi'ao",
    "wof:placetype": "locality"
  },
  "geometry": {
    "coordinates": [
      110.75892,
      30.5039
    ],
    "type": "Point"
  }
}