{
  "type": "Feature",
  "properties": {
    "gn:admin1_code": "29.0",
    "gn:asciiname": "Liushima Xiaozhai",
    "gn:country_code": "CN",
    "gn:dem": 1482,
    "gn:feature_class": "P",
    "gn:feature_code": "PPL",
    "gn:name": "Liushima Xiaozhai",
    "gn:population": 0,
    "gn:timezone": "Asia/Shanghai",
    "iso:country": "CN",
    "name:zho_x_preferred": [
      "六十骂小寨"
    ],
    "wof:name": "Liushima Xiaozhai",
    "wof:placetype": "locality"
  },
  "geometry": {
    "coordinates": [
      104.186,
      24.1158
    ],
    "type": "Point"
  }
}