{
  "type": "Feature",
  "properties": {
    "gn:admin1_code": "2.0",
    "gn:asciiname": "Shahe",
    "gn:country_code": "CN",
    "gn:dem": 8,
    "gn:feature_class": "P",
    "gn:feature_code": "PPL",
    "gn:name": "Shahe",
    "gn:population": 0,
    "gn:timezone": "Asia/Shanghai",
    "iso:country": "CN",
    "name:ceb_x_preferred": [
      "Shahe"
    ],
    "name:deu_x_preferred": [
      "Shahe"
    ],
    "name:rus_x_preferred": [
      "Шахэ"
    ],
    "name:swe_x_preferred": [
      "Shahe"
    ],
    "name:zho_x_preferred": [
      "沙河"
    ],
    "wof:name": "Shahe",
    "wof:placetype": "locality"
  },
  "geometry": {
    "coordinates": [
      121.60421,
      30.00205
    ],
    "type": "Point"
  }
}