{
  "type": "Feature",
  "properties": {
    "gn:admin1_code": "1.0",
    "gn:asciiname": "Yonghongcun",
    "gn:country_code": "CN",
    "gn:dem": 22,
    "gn:feature_class": "P",
    "gn:feature_code": "PPL",
    "gn:name": "Yonghongcun",
    "gn:population": 0,
    "gn:timezone": "Asia/Shanghai",
    "iso:country": "CN",
    "name:zho_x_preferred": [
      "永红村"
    ],
    "wof:name": "Yonghongcun",
    "wof:placetype": "locality"
  },
  "geometry": {
    "coordinates": [
      118.43183,
      32.27711
    ],
    "type": "Point"
  }
}