{
  "type": "Feature",
  "properties": {
    "gn:admin1_code": "10.0",
    "gn:asciiname": "Xiaxinglongzhuang",
    "gn:country_code": "CN",
    "gn:dem": 132,
    "gn:feature_class": "P",
    "gn:feature_code": "PPL",
    "gn:name": "Xiaxinglongzhuang",
    "gn:population": 0,
    "gn:timezone": "Asia/Shanghai",
    "iso:country": "CN",
    "name:zho_x_preferred": [
      "下兴隆庄"
    ],
    "wof:name": "Xiaxinglongzhuang",
    "wof:placetype": "locality"
  },
  "geometry": {
    "coordinates": [
      119.08854,
      40.06718
    ],
    "type": "Point"
  }
}