{
  "type": "Feature",
  "properties": {
    "gn:admin1_code": "26.0",
    "gn:asciiname": "Majialiang",
    "gn:country_code": "CN",
    "gn:dem": 1167,
    "gn:feature_class": "P",
    "gn:feature_code": "PPL",
    "gn:name": "Majialiang",
    "gn:population": 0,
    "gn:timezone": "Asia/Shanghai",
    "iso:country": "CN",
    "name:zho_x_preferred": [
      "马家梁"
    ],
    "wof:name": "Majialiang",
    "wof:placetype": "locality"
  },
  "geometry": {
    "coordinates": [
      110.88568,
      39.50534
    ],
    "type": "Point"
  }
}