{
  "type": "Feature",
  "properties": {
    "gn:admin1_code": "12.0",
    "gn:asciiname": "Liuhuachong",
    "gn:country_code": "CN",
    "gn:dem": 910,
    "gn:feature_class": "P",
    "gn:feature_code": "PPL",
    "gn:name": "Liuhuachong",
    "gn:population": 0,
    "gn:timezone": "Asia/Shanghai",
    "iso:country": "CN",
    "name:zho_x_preferred": [
      "刘划冲"
    ],
    "wof:name": "Liuhuachong",
    "wof:placetype": "locality"
  },
  "geometry": {
    "coordinates": [
      111.27419,
      31.42927
    ],
    "type": "Point"
  }
}