{
  "type": "Feature",
  "properties": {
    "gn:admin1_code": "11",
    "gn:asciiname": "Jiaoqi",
    "gn:country_code": "CN",
    "gn:dem": 38,
    "gn:feature_class": "P",
    "gn:feature_code": "PPLA4",
    "gn:name": "Jiaoqi",
    "gn:population": 0,
    "gn:timezone": "Asia/Shanghai",
    "iso:country": "CN",
    "name:und_x_variant": [
      "焦圻",
      "Jiaoqi Zhen",
      "焦圻镇"
    ],
    "wof:name": "Jiaoqi",
    "wof:placetype": "locality"
  },
  "geometry": {
    "coordinates": [
      112.08196,
      29.64833
    ],
    "type": "Point"
  }
}