{
  "type": "Feature",
  "properties": {
    "gn:admin1_code": "25.0",
    "gn:asciiname": "Gaogezhuang",
    "gn:country_code": "CN",
    "gn:dem": 100,
    "gn:feature_class": "P",
    "gn:feature_code": "PPL",
    "gn:name": "Gaogezhuang",
    "gn:population": 0,
    "gn:timezone": "Asia/Shanghai",
    "iso:country": "CN",
    "name:zho_x_preferred": [
      "高阁庄"
    ],
    "name:zho_x_variant": [
      "高格庄镇"
    ],
    "wof:name": "Gaogezhuang",
    "wof:placetype": "locality"
  },
  "geometry": {
    "coordinates": [
      119.42727,
      35.76009000000001
    ],
    "type": "Point"
  }
}