{
  "type": "Feature",
  "properties": {
    "gn:admin1_code": "25",
    "gn:asciiname": "Bama",
    "gn:country_code": "CN",
    "gn:dem": 200,
    "gn:feature_class": "P",
    "gn:feature_code": "PPL",
    "gn:name": "Bama",
    "gn:population": 0,
    "gn:timezone": "Asia/Shanghai",
    "iso:country": "CN",
    "name:ben_x_preferred": [
      "বামা"
    ],
    "name:cat_x_preferred": [
      "Bama"
    ],
    "name:ceb_x_preferred": [
      "Bama"
    ],
    "name:deu_x_preferred": [
      "Bama"
    ],
    "name:ell_x_preferred": [
      "Μπάμα"
    ],
    "name:fas_x_preferred": [
      "باما"
    ],
    "name:fra_x_preferred": [
      "Bama"
    ],
    "name:glg_x_preferred": [
      "Bama"
    ],
    "name:heb_x_preferred": [
      "במה"
    ],
    "name:hin_x_preferred": [
      "बामा"
    ],
    "name:hun_x_preferred": [
      "Bama"
    ],
    "name:ind_x_preferred": [
      "Bama"
    ],
    "name:ita_x_preferred": [
      "Bama"
    ],
    "name:jpn_x_preferred": [
      "バマ"
    ],
    "name:kor_x_preferred": [
      "바마"
    ],
    "name:nld_x_preferred": [
      "Bama"
    ],
    "name:nor_x_preferred": [
      "Bama"
    ],
    "name:rus_x_preferred": [
      "Бама"
    ],
    "name:swe_x_preferred": [
      "Bama"
    ],
    "name:tur_x_preferred": [
      "Bama"
    ],
    "name:ukr_x_preferred": [
      "Бама"
    ],
    "name:urd_x_preferred": [
      "باما"
    ],
    "name:vie_x_preferred": [
      "Bama"
    ],
    "name:zho_cn_x_preferred": [
      "巴马"
    ],
    "name:zho_tw_x_preferred": [
      "巴馬"
    ],
    "name:zho_x_preferred": [
      "拔麻"
    ],
    "wof:name": "Bama",
    "wof:placetype": "locality"
  },
  "geometry": {
    "coordinates": [
      118.305,
      35.6948
    ],
    "type": "Point"
  }
}