{
  "type": "Feature",
  "properties": {
    "gn:admin1_code": "32.0",
    "gn:asciiname": "Gaya",
    "gn:country_code": "CN",
    "gn:dem": 3533,
    "gn:feature_class": "P",
    "gn:feature_code": "PPL",
    "gn:name": "Gaya",
    "gn:population": 0,
    "gn:timezone": "Asia/Shanghai",
    "iso:country": "CN",
    "name:ara_x_preferred": [
      "جايا"
    ],
    "name:aze_x_preferred": [
      "Qaya"
    ],
    "name:ben_x_preferred": [
      "গায়া"
    ],
    "name:cat_x_preferred": [
      "Gaya"
    ],
    "name:ceb_x_preferred": [
      "Gaya"
    ],
    "name:ces_x_preferred": [
      "Gaya"
    ],
    "name:deu_x_preferred": [
      "Gaya"
    ],
    "name:ell_x_preferred": [
      "Γκάγια"
    ],
    "name:fas_x_preferred": [
      "گایا"
    ],
    "name:fra_x_preferred": [
      "Gaya"
    ],
    "name:heb_x_preferred": [
      "גאיה"
    ],
    "name:hif_x_preferred": [
      "Gaya"
    ],
    "name:hin_x_preferred": [
      "गया"
    ],
    "name:hun_x_preferred": [
      "Gaya"
    ],
    "name:hye_x_preferred": [
      "Գայա"
    ],
    "name:ind_x_preferred": [
      "Gaya"
    ],
    "name:ita_x_preferred": [
      "Gaya"
    ],
    "name:kor_x_preferred": [
      "가야"
    ],
    "name:lit_x_preferred": [
      "Gaja"
    ],
    "name:msa_x_preferred": [
      "Gaya"
    ],
    "name:nld_x_preferred": [
      "Gaya"
    ],
    "name:nor_x_preferred": [
      "Gaya"
    ],
    "name:pol_x_preferred": [
      "Gaya"
    ],
    "name:por_x_preferred": [
      "Gaya"
    ],
    "name:pus_x_preferred": [
      "گايا"
    ],
    "name:rus_x_preferred": [
      "Гая"
    ],
    "name:spa_x_preferred": [
      "Gaya"
    ],
    "name:swe_x_preferred": [
      "Gaya"
    ],
    "name:tur_x_preferred": [
      "Gaya"
    ],
    "name:ukr_x_preferred": [
      "Гая"
    ],
    "name:urd_x_preferred": [
      "گایا"
    ],
    "name:zho_x_preferred": [
      "嘎亚"
    ],
    "wof:name": "Gaya",
    "wof:placetype": "locality"
  },
  "geometry": {
    "coordinates": [
      101.096,
      31.0573
    ],
    "type": "Point"
  }
}