{
  "type": "Feature",
  "properties": {
    "gn:admin1_code": "15.0",
    "gn:asciiname": "Yanji",
    "gn:country_code": "CN",
    "gn:dem": 1596,
    "gn:feature_class": "P",
    "gn:feature_code": "PPL",
    "gn:name": "Yanji",
    "gn:population": 0,
    "gn:timezone": "Asia/Shanghai",
    "iso:country": "CN",
    "name:ara_x_preferred": [
      "يانجي"
    ],
    "name:cat_x_preferred": [
      "Yanji"
    ],
    "name:ceb_x_preferred": [
      "Yanji"
    ],
    "name:ces_x_preferred": [
      "Jongil"
    ],
    "name:deu_x_preferred": [
      "Yanji"
    ],
    "name:fas_x_preferred": [
      "یانگژی"
    ],
    "name:fra_x_preferred": [
      "Yanji"
    ],
    "name:heb_x_preferred": [
      "יאנג'י"
    ],
    "name:hun_x_preferred": [
      "Yanji"
    ],
    "name:ind_x_preferred": [
      "Yanji"
    ],
    "name:ita_x_preferred": [
      "Yanji"
    ],
    "name:jpn_x_preferred": [
      "延吉市"
    ],
    "name:kik_x_preferred": [
      "Yanji"
    ],
    "name:kor_x_preferred": [
      "옌지시"
    ],
    "name:mlg_x_preferred": [
      "Yanji"
    ],
    "name:nld_x_preferred": [
      "Yanji"
    ],
    "name:nor_x_preferred": [
      "Yanji"
    ],
    "name:pol_x_preferred": [
      "Yanji"
    ],
    "name:por_x_preferred": [
      "Yanji"
    ],
    "name:rus_x_preferred": [
      "Яньцзи"
    ],
    "name:spa_x_preferred": [
      "Yanji"
    ],
    "name:srp_x_preferred": [
      "Јанђи"
    ],
    "name:swe_x_preferred": [
      "Yanji"
    ],
    "name:tur_x_preferred": [
      "Yanji"
    ],
    "name:urd_x_preferred": [
      "یانجی"
    ],
    "name:vie_x_preferred": [
      "Diên Cát"
    ],
    "name:war_x_preferred": [
      "Yanji"
    ],
    "name:wuu_x_preferred": [
      "延吉市"
    ],
    "name:zho_x_preferred": [
      "阎集"
    ],
    "name:zho_x_variant": [
      "延吉市"
    ],
    "wof:name": "Yanji",
    "wof:placetype": "locality"
  },
  "geometry": {
    "coordinates": [
      105.602,
      34.2202
    ],
    "type": "Point"
  }
}