{
  "type": "Feature",
  "properties": {
    "gn:admin1_code": "7",
    "gn:asciiname": "Daji",
    "gn:country_code": "CN",
    "gn:dem": 69,
    "gn:feature_class": "P",
    "gn:feature_code": "PPLA4",
    "gn:name": "Daji",
    "gn:population": 0,
    "gn:timezone": "Asia/Shanghai",
    "iso:country": "CN",
    "name:cat_x_preferred": [
      "Daji"
    ],
    "name:deu_x_preferred": [
      "Daji"
    ],
    "name:fra_x_preferred": [
      "Daji"
    ],
    "name:ind_x_preferred": [
      "Daji"
    ],
    "name:por_x_preferred": [
      "Daji"
    ],
    "name:spa_x_preferred": [
      "Daji"
    ],
    "name:tha_x_preferred": [
      "ต๋าจี่"
    ],
    "name:und_x_variant": [
      "Daji Zhen"
    ],
    "name:vie_x_preferred": [
      "Đát Kỷ"
    ],
    "name:zho_x_preferred": [
      "大济"
    ],
    "name:zho_x_variant": [
      "大济镇"
    ],
    "wof:name": "Daji",
    "wof:placetype": "locality"
  },
  "geometry": {
    "coordinates": [
      118.63453,
      25.37261
    ],
    "type": "Point"
  }
}