{
  "type": "Feature",
  "properties": {
    "gn:admin1_code": "29.0",
    "gn:asciiname": "Muta",
    "gn:country_code": "CN",
    "gn:dem": 2060,
    "gn:feature_class": "P",
    "gn:feature_code": "PPL",
    "gn:name": "Muta",
    "gn:population": 0,
    "gn:timezone": "Asia/Shanghai",
    "iso:country": "CN",
    "name:ceb_x_preferred": [
      "Muta"
    ],
    "name:deu_x_preferred": [
      "Muta"
    ],
    "name:fra_x_preferred": [
      "Muta"
    ],
    "name:heb_x_preferred": [
      "מוינגה"
    ],
    "name:hun_x_preferred": [
      "Muta"
    ],
    "name:hye_x_preferred": [
      "Մուտա"
    ],
    "name:ita_x_preferred": [
      "Muta"
    ],
    "name:rus_x_preferred": [
      "Мута"
    ],
    "name:swe_x_preferred": [
      "Muta"
    ],
    "name:zho_x_preferred": [
      "木榻"
    ],
    "wof:name": "Muta",
    "wof:placetype": "locality"
  },
  "geometry": {
    "coordinates": [
      103.933,
      24.5195
    ],
    "type": "Point"
  }
}