{
  "type": "Feature",
  "properties": {
    "gn:admin1_code": "3",
    "gn:asciiname": "Huangzhou",
    "gn:country_code": "CN",
    "gn:dem": 33,
    "gn:feature_class": "P",
    "gn:feature_code": "PPL",
    "gn:name": "Huangzhou",
    "gn:population": 0,
    "gn:timezone": "Asia/Shanghai",
    "iso:country": "CN",
    "name:und_x_variant": [
      "黄洲",
      "Huangzhou Zhen",
      "黄洲镇"
    ],
    "wof:name": "Huangzhou",
    "wof:placetype": "locality"
  },
  "geometry": {
    "coordinates": [
      115.49308,
      28.73887
    ],
    "type": "Point"
  }
}