{
  "type": "Feature",
  "properties": {
    "gn:admin1_code": "30.0",
    "gn:asciiname": "Sanya",
    "gn:country_code": "CN",
    "gn:dem": 6,
    "gn:feature_class": "P",
    "gn:feature_code": "PPL",
    "gn:name": "Sanya",
    "gn:population": 0,
    "gn:timezone": "Asia/Shanghai",
    "iso:country": "CN",
    "name:ara_x_preferred": [
      "سانيا"
    ],
    "name:bel_x_preferred": [
      "Санья"
    ],
    "name:bod_x_preferred": [
      "སན་ཡ་གྲོང་ཁྱེར།"
    ],
    "name:cdo_x_preferred": [
      "Săng-ā"
    ],
    "name:ceb_x_preferred": [
      "Sanya"
    ],
    "name:ces_x_preferred": [
      "San-ja"
    ],
    "name:cym_x_preferred": [
      "Sanya"
    ],
    "name:dan_x_preferred": [
      "Sanya"
    ],
    "name:deu_x_preferred": [
      "Sanya"
    ],
    "name:eus_x_preferred": [
      "Sanya"
    ],
    "name:fas_x_preferred": [
      "سانیا"
    ],
    "name:fin_x_preferred": [
      "Sanya"
    ],
    "name:fra_x_preferred": [
      "Sanya"
    ],
    "name:heb_x_preferred": [
      "סניה"
    ],
    "name:hun_x_preferred": [
      "Sanya"
    ],
    "name:ind_x_preferred": [
      "Sanya"
    ],
    "name:isl_x_preferred": [
      "Sanya"
    ],
    "name:ita_x_preferred": [
      "Sanya"
    ],
    "name:jpn_x_preferred": [
      "三亜市"
    ],
    "name:kik_x_preferred": [
      "Sanya"
    ],
    "name:kor_x_preferred": [
      "싼야시"
    ],
    "name:mlg_x_preferred": [
      "Sanya"
    ],
    "name:nld_x_preferred": [
      "Sanya"
    ],
    "name:nor_x_preferred": [
      "Sanya"
    ],
    "name:pam_x_preferred": [
      "Sanya"
    ],
    "name:pol_x_preferred": [
      "Sanya"
    ],
    "name:por_x_preferred": [
      "Sanya"
    ],
    "name:ron_x_preferred": [
      "Sanya"
    ],
    "name:rus_x_preferred": [
      "Санья"
    ],
    "name:sah_x_preferred": [
      "Санья"
    ],
    "name:spa_x_preferred": [
      "Sanya"
    ],
    "name:swe_x_preferred": [
      "Sanya"
    ],
    "name:tgl_x_preferred": [
      "Sanya"
    ],
    "name:tha_x_preferred": [
      "ซานย่า"
    ],
    "name:tur_x_preferred": [
      "Sanya"
    ],
    "name:uig_x_preferred": [
      "Senya shehiri"
    ],
    "name:ukr_x_preferred": [
      "Санья"
    ],
    "name:urd_x_preferred": [
      "سانیا"
    ],
    "name:vep_x_preferred": [
      "Sanj"
    ],
    "name:vie_x_preferred": [
      "Tam"
    ],
    "name:war_x_preferred": [
      "Sanya"
    ],
    "name:zho_x_preferred": [
      "三崖"
    ],
    "name:zho_x_variant": [
      "三亚市"
    ],
    "wof:name": "Sanya",
    "wof:placetype": "locality"
  },
  "geometry": {
    "coordinates": [
      113.08964,
      22.22618
    ],
    "type": "Point"
  }
}