{
  "type": "Feature",
  "properties": {
    "gn:admin1_code": "7",
    "gn:asciiname": "Zhonglou",
    "gn:country_code": "CN",
    "gn:dem": 404,
    "gn:feature_class": "P",
    "gn:feature_code": "PPL",
    "gn:name": "Zhonglou",
    "gn:population": 0,
    "gn:timezone": "Asia/Shanghai",
    "iso:country": "CN",
    "name:zho_x_preferred": [
      "中楼"
    ],
    "wof:name": "Zhonglou",
    "wof:placetype": "locality"
  },
  "geometry": {
    "coordinates": [
      118.70444,
      25.28
    ],
    "type": "Point"
  }
}