{
  "type": "Feature",
  "properties": {
    "gn:admin1_code": "10.0",
    "gn:asciiname": "Dongyang",
    "gn:country_code": "CN",
    "gn:dem": 24,
    "gn:feature_class": "P",
    "gn:feature_code": "PPL",
    "gn:name": "Dongyang",
    "gn:population": 0,
    "gn:timezone": "Asia/Shanghai",
    "iso:country": "CN",
    "name:ara_x_preferred": [
      "دونغ يانغ"
    ],
    "name:ceb_x_preferred": [
      "Dongyang"
    ],
    "name:ces_x_preferred": [
      "Tung-jang"
    ],
    "name:deu_x_preferred": [
      "Dongyang"
    ],
    "name:fas_x_preferred": [
      "دونگ‌یانگ"
    ],
    "name:fra_x_preferred": [
      "Dongyang"
    ],
    "name:ita_x_preferred": [
      "Dongyang"
    ],
    "name:jpn_x_preferred": [
      "東陽市"
    ],
    "name:kik_x_preferred": [
      "Dongyang"
    ],
    "name:kor_x_preferred": [
      "둥양시"
    ],
    "name:mlg_x_preferred": [
      "Dongyang"
    ],
    "name:nld_x_preferred": [
      "Dongyang"
    ],
    "name:nor_x_preferred": [
      "Dongyang"
    ],
    "name:pol_x_preferred": [
      "Dongyang"
    ],
    "name:swe_x_preferred": [
      "Dongyang"
    ],
    "name:tgl_x_preferred": [
      "Dongyang"
    ],
    "name:ukr_x_preferred": [
      "Донян"
    ],
    "name:urd_x_preferred": [
      "ڈونگیانگ"
    ],
    "name:vie_x_preferred": [
      "Đông Dương"
    ],
    "name:war_x_preferred": [
      "Dongyang"
    ],
    "name:wuu_x_preferred": [
      "东阳市"
    ],
    "name:zho_x_preferred": [
      "东杨"
    ],
    "name:zho_x_variant": [
      "东阳市"
    ],
    "wof:name": "Dongyang",
    "wof:placetype": "locality"
  },
  "geometry": {
    "coordinates": [
      115.62,
      38.3375
    ],
    "type": "Point"
  }
}