{
  "type": "Feature",
  "properties": {
    "gn:admin1_code": "15.0",
    "gn:asciiname": "Hualinxiang",
    "gn:country_code": "CN",
    "gn:dem": 1588,
    "gn:feature_class": "P",
    "gn:feature_code": "PPL",
    "gn:name": "Hualinxiang",
    "gn:population": 0,
    "gn:timezone": "Asia/Shanghai",
    "iso:country": "CN",
    "name:und_x_variant": [
      "桦林乡"
    ],
    "wof:name": "Hualinxiang",
    "wof:placetype": "locality"
  },
  "geometry": {
    "coordinates": [
      104.75198,
      34.82559000000001
    ],
    "type": "Point"
  }
}