{
  "type": "Feature",
  "properties": {
    "gn:admin1_code": "18.0",
    "gn:asciiname": "Denglong",
    "gn:country_code": "CN",
    "gn:dem": 898,
    "gn:feature_class": "P",
    "gn:feature_code": "PPL",
    "gn:name": "Denglong",
    "gn:population": 0,
    "gn:timezone": "Asia/Shanghai",
    "iso:country": "CN",
    "name:jpn_x_preferred": [
      "コウ"
    ],
    "name:kor_x_preferred": [
      "조천후"
    ],
    "name:zho_x_preferred": [
      "邓龙"
    ],
    "wof:name": "Denglong",
    "wof:placetype": "locality"
  },
  "geometry": {
    "coordinates": [
      108.78,
      26.2089
    ],
    "type": "Point"
  }
}