{
  "type": "Feature",
  "properties": {
    "gn:admin1_code": "03",
    "gn:asciiname": "Jianchang",
    "gn:country_code": "CN",
    "gn:dem": 78,
    "gn:feature_class": "P",
    "gn:feature_code": "PPLA3",
    "gn:name": "Jianchang",
    "gn:population": 0,
    "gn:timezone": "Asia/Shanghai",
    "iso:country": "CN",
    "name:deu_x_preferred": [
      "Nancheng"
    ],
    "name:fas_x_preferred": [
      "شهرستان نانچنگ"
    ],
    "name:jpn_x_preferred": [
      "南城県"
    ],
    "name:kor_x_preferred": [
      "난청현"
    ],
    "name:nor_x_preferred": [
      "Nancheng"
    ],
    "name:swe_x_preferred": [
      "Nancheng"
    ],
    "name:und_x_variant": [
      "Chien-ch’ang",
      "Nan-ch’eng-hsien",
      "Kienchangfu",
      "Kienchang",
      "Jianchang",
      "建昌",
      "Nancheng Xian",
      "Jianchang Zhen",
      "建昌镇"
    ],
    "name:vie_x_preferred": [
      "Nam Thành"
    ],
    "name:zho_x_preferred": [
      "南城县"
    ],
    "wof:name": "Jianchang",
    "wof:placetype": "locality"
  },
  "geometry": {
    "coordinates": [
      116.63978,
      27.55831
    ],
    "type": "Point"
  }
}