{
  "type": "Feature",
  "properties": {
    "gn:admin1_code": "15.0",
    "gn:asciiname": "Luzhou",
    "gn:country_code": "CN",
    "gn:dem": 1548,
    "gn:feature_class": "P",
    "gn:feature_code": "PPL",
    "gn:name": "Luzhou",
    "gn:population": 0,
    "gn:timezone": "Asia/Shanghai",
    "iso:country": "CN",
    "name:afr_x_preferred": [
      "Luzhou"
    ],
    "name:ara_x_preferred": [
      "لوزهاو"
    ],
    "name:bul_x_preferred": [
      "Луджоу"
    ],
    "name:cdo_x_preferred": [
      "Lù-ciŭ"
    ],
    "name:ces_x_preferred": [
      "Lu-čou"
    ],
    "name:dan_x_preferred": [
      "Luzhou"
    ],
    "name:deu_x_preferred": [
      "Luzhou"
    ],
    "name:epo_x_preferred": [
      "Luzhoŭ"
    ],
    "name:eus_x_preferred": [
      "Luzhou"
    ],
    "name:fas_x_preferred": [
      "لوجو"
    ],
    "name:fin_x_preferred": [
      "Luzhou"
    ],
    "name:fra_x_preferred": [
      "Luzhou"
    ],
    "name:hak_x_preferred": [
      "Lû-chû-sṳ"
    ],
    "name:heb_x_preferred": [
      "לוז'ו"
    ],
    "name:ita_x_preferred": [
      "Luzhou"
    ],
    "name:jpn_x_preferred": [
      "瀘州市"
    ],
    "name:kik_x_preferred": [
      "Luzhou"
    ],
    "name:kor_x_preferred": [
      "루저우시"
    ],
    "name:nld_x_preferred": [
      "Luzhou"
    ],
    "name:nno_x_preferred": [
      "Luzhou"
    ],
    "name:nor_x_preferred": [
      "Luzhou"
    ],
    "name:pol_x_preferred": [
      "Luzhou"
    ],
    "name:por_x_preferred": [
      "Luzhou"
    ],
    "name:rus_x_preferred": [
      "Лучжоу"
    ],
    "name:spa_x_preferred": [
      "Luzhóu"
    ],
    "name:srp_x_preferred": [
      "Луџоу"
    ],
    "name:swe_x_preferred": [
      "Luzhou"
    ],
    "name:tur_x_preferred": [
      "Luzhou"
    ],
    "name:urd_x_preferred": [
      "لوژوو"
    ],
    "name:vie_x_preferred": [
      "Lô Châu"
    ],
    "name:war_x_preferred": [
      "Luzhou"
    ],
    "name:zho_x_preferred": [
      "碌碡"
    ],
    "name:zho_x_variant": [
      "泸州市"
    ],
    "wof:name": "Luzhou",
    "wof:placetype": "locality"
  },
  "geometry": {
    "coordinates": [
      102.674,
      37.9014
    ],
    "type": "Point"
  }
}