{
  "type": "Feature",
  "properties": {
    "gn:admin1_code": "16.0",
    "gn:asciiname": "Funing",
    "gn:country_code": "CN",
    "gn:dem": 159,
    "gn:feature_class": "P",
    "gn:feature_code": "PPL",
    "gn:name": "Funing",
    "gn:population": 0,
    "gn:timezone": "Asia/Shanghai",
    "iso:country": "CN",
    "name:ceb_x_preferred": [
      "Funing"
    ],
    "name:deu_x_preferred": [
      "Funing"
    ],
    "name:fra_x_preferred": [
      "Funing"
    ],
    "name:kor_x_preferred": [
      "푸닝현"
    ],
    "name:nor_x_preferred": [
      "Funing"
    ],
    "name:rus_x_preferred": [
      "Фунин"
    ],
    "name:swe_x_preferred": [
      "Funing"
    ],
    "name:zho_x_preferred": [
      "富宁"
    ],
    "wof:name": "Funing",
    "wof:placetype": "locality"
  },
  "geometry": {
    "coordinates": [
      111.072,
      23.1252
    ],
    "type": "Point"
  }
}