{
  "type": "Feature",
  "properties": {
    "gn:admin1_code": "32.0",
    "gn:asciiname": "Dongding'ao",
    "gn:country_code": "CN",
    "gn:dem": 334,
    "gn:feature_class": "P",
    "gn:feature_code": "PPL",
    "gn:name": "Dongding’ao",
    "gn:population": 0,
    "gn:timezone": "Asia/Shanghai",
    "iso:country": "CN",
    "name:zho_x_preferred": [
      "洞顶垇"
    ],
    "name:zho_x_variant": [
      "Dongding’ao"
    ],
    "wof:name": "Dongding'ao",
    "wof:placetype": "locality"
  },
  "geometry": {
    "coordinates": [
      104.71949,
      29.04126
    ],
    "type": "Point"
  }
}