{
  "type": "Feature",
  "properties": {
    "gn:admin1_code": "7.0",
    "gn:asciiname": "Maojia",
    "gn:country_code": "CN",
    "gn:dem": 363,
    "gn:feature_class": "P",
    "gn:feature_code": "PPL",
    "gn:name": "Maojia",
    "gn:population": 0,
    "gn:timezone": "Asia/Shanghai",
    "iso:country": "CN",
    "name:zho_x_preferred": [
      "毛家"
    ],
    "wof:name": "Maojia",
    "wof:placetype": "locality"
  },
  "geometry": {
    "coordinates": [
      117.47329,
      27.85608
    ],
    "type": "Point"
  }
}