{
  "type": "Feature",
  "properties": {
    "gn:admin1_code": "19.0",
    "gn:asciiname": "Dongfangjiatun",
    "gn:country_code": "CN",
    "gn:dem": 115,
    "gn:feature_class": "P",
    "gn:feature_code": "PPL",
    "gn:name": "Dongfangjiatun",
    "gn:population": 0,
    "gn:timezone": "Asia/Shanghai",
    "iso:country": "CN",
    "name:zho_x_preferred": [
      "东方家屯"
    ],
    "wof:name": "Dongfangjiatun",
    "wof:placetype": "locality"
  },
  "geometry": {
    "coordinates": [
      123.713,
      42.7494
    ],
    "type": "Point"
  }
}