{
  "type": "Feature",
  "properties": {
    "gn:admin1_code": "12.0",
    "gn:asciiname": "Ba'erwan",
    "gn:country_code": "CN",
    "gn:dem": 241,
    "gn:feature_class": "P",
    "gn:feature_code": "PPL",
    "gn:name": "Ba’erwan",
    "gn:population": 0,
    "gn:timezone": "Asia/Shanghai",
    "iso:country": "CN",
    "name:und_x_variant": [
      "Ba’erwan"
    ],
    "name:zho_x_preferred": [
      "八儿湾"
    ],
    "wof:name": "Ba'erwan",
    "wof:placetype": "locality"
  },
  "geometry": {
    "coordinates": [
      111.88291,
      31.37909
    ],
    "type": "Point"
  }
}