{
  "type": "Feature",
  "properties": {
    "gn:admin1_code": "19.0",
    "gn:asciiname": "Daxigou",
    "gn:country_code": "CN",
    "gn:dem": 220,
    "gn:feature_class": "P",
    "gn:feature_code": "PPL",
    "gn:name": "Daxigou",
    "gn:population": 0,
    "gn:timezone": "Asia/Shanghai",
    "iso:country": "CN",
    "name:zho_x_preferred": [
      "大西沟"
    ],
    "wof:name": "Daxigou",
    "wof:placetype": "locality"
  },
  "geometry": {
    "coordinates": [
      125.39522,
      40.65896
    ],
    "type": "Point"
  }
}