{
  "type": "Feature",
  "properties": {
    "gn:admin1_code": "25",
    "gn:asciiname": "Houwu",
    "gn:country_code": "CN",
    "gn:dem": 35,
    "gn:feature_class": "P",
    "gn:feature_code": "PPL",
    "gn:name": "Houwu",
    "gn:population": 0,
    "gn:timezone": "Asia/Shanghai",
    "iso:country": "CN",
    "name:zho_x_preferred": [
      "后吴"
    ],
    "wof:name": "Houwu",
    "wof:placetype": "locality"
  },
  "geometry": {
    "coordinates": [
      115.8778,
      36.64677
    ],
    "type": "Point"
  }
}