{
  "type": "Feature",
  "properties": {
    "gn:admin1_code": "30.0",
    "gn:asciiname": "Shanmen",
    "gn:country_code": "CN",
    "gn:dem": 8,
    "gn:feature_class": "P",
    "gn:feature_code": "PPL",
    "gn:name": "Shanmen",
    "gn:population": 0,
    "gn:timezone": "Asia/Shanghai",
    "iso:country": "CN",
    "name:zho_x_preferred": [
      "山门"
    ],
    "wof:name": "Shanmen",
    "wof:placetype": "locality"
  },
  "geometry": {
    "coordinates": [
      115.6858,
      22.88477
    ],
    "type": "Point"
  }
}