{
  "type": "Feature",
  "properties": {
    "gn:admin1_code": "30.0",
    "gn:asciiname": "Tuanjiewei",
    "gn:country_code": "CN",
    "gn:dem": 2,
    "gn:feature_class": "P",
    "gn:feature_code": "PPL",
    "gn:name": "Tuanjiewei",
    "gn:population": 0,
    "gn:timezone": "Asia/Shanghai",
    "iso:country": "CN",
    "name:zho_x_preferred": [
      "团结围"
    ],
    "wof:name": "Tuanjiewei",
    "wof:placetype": "locality"
  },
  "geometry": {
    "coordinates": [
      113.57693,
      22.60997
    ],
    "type": "Point"
  }
}