{
  "type": "Feature",
  "properties": {
    "gn:country": "CN",
    "gn:fcode": "PPL",
    "gn:population": 120514,
    "iso:country": "CN",
    "name:ara_x_preferred": [
      "فنغتشنغ"
    ],
    "name:ben_x_preferred": [
      "ফেংগচেন"
    ],
    "name:ceb_x_preferred": [
      "Fengcheng"
    ],
    "name:deu_x_preferred": [
      "Fengcheng"
    ],
    "name:ell_x_preferred": [
      "Φένγκτσενγκ"
    ],
    "name:fas_x_preferred": [
      "فنگچنگ"
    ],
    "name:fra_x_preferred": [
      "Fengcheng"
    ],
    "name:heb_x_preferred": [
      "פנגצ'נג"
    ],
    "name:hin_x_preferred": [
      "फ़ेंगचेंग"
    ],
    "name:hun_x_preferred": [
      "Fengcheng"
    ],
    "name:ind_x_preferred": [
      "Fengcheng"
    ],
    "name:kor_x_preferred": [
      "펑청시"
    ],
    "name:mlg_x_preferred": [
      "Fengcheng"
    ],
    "name:nor_x_preferred": [
      "Fengcheng"
    ],
    "name:pol_x_preferred": [
      "Fengcheng"
    ],
    "name:por_x_preferred": [
      "Fengcheng"
    ],
    "name:spa_x_preferred": [
      "Fengcheng"
    ],
    "name:swe_x_preferred": [
      "Fengcheng"
    ],
    "name:tur_x_preferred": [
      "Fengcheng"
    ],
    "name:ukr_x_preferred": [
      "Фенчен"
    ],
    "name:und_x_variant": [
      "Fenghwangcheng"
    ],
    "qs:name": "Fengcheng",
    "qs:photos_9r": 0,
    "qs:photos_sr": 0,
    "qs:pop_sr": "9",
    "wd:wordcount": 47,
    "wof:name": "Fengcheng",
    "wof:placetype": "locality",
    "wof:population": 120514
  },
  "geometry": {
    "coordinates": [
      124.07167,
      40.45361
    ],
    "type": "Point"
  }
}