{
  "type": "Feature",
  "properties": {
    "gn:admin1_code": "11.0",
    "gn:asciiname": "Duijiangtuan",
    "gn:country_code": "CN",
    "gn:dem": 393,
    "gn:feature_class": "P",
    "gn:feature_code": "PPL",
    "gn:name": "Duijiangtuan",
    "gn:population": 0,
    "gn:timezone": "Asia/Shanghai",
    "iso:country": "CN",
    "name:zho_x_preferred": [
      "对江团"
    ],
    "wof:name": "Duijiangtuan",
    "wof:placetype": "locality"
  },
  "geometry": {
    "coordinates": [
      109.65852,
      26.43939
    ],
    "type": "Point"
  }
}