{
  "type": "Feature",
  "properties": {
    "gn:admin1_code": "8.0",
    "gn:asciiname": "Gong'ancun",
    "gn:country_code": "CN",
    "gn:dem": 63,
    "gn:feature_class": "P",
    "gn:feature_code": "PPL",
    "gn:name": "Gong’ancun",
    "gn:population": 0,
    "gn:timezone": "Asia/Shanghai",
    "iso:country": "CN",
    "name:und_x_variant": [
      "Gong’ancun"
    ],
    "name:zho_x_preferred": [
      "公安村"
    ],
    "wof:name": "Gong'ancun",
    "wof:placetype": "locality"
  },
  "geometry": {
    "coordinates": [
      131.80101000000002,
      47.08223
    ],
    "type": "Point"
  }
}