{
  "type": "Feature",
  "properties": {
    "gn:admin1_code": "16.0",
    "gn:asciiname": "Liucun",
    "gn:country_code": "CN",
    "gn:dem": 172,
    "gn:feature_class": "P",
    "gn:feature_code": "PPL",
    "gn:name": "Liucun",
    "gn:population": 0,
    "gn:timezone": "Asia/Shanghai",
    "iso:country": "CN",
    "name:zho_x_preferred": [
      "六存"
    ],
    "wof:name": "Liucun",
    "wof:placetype": "locality"
  },
  "geometry": {
    "coordinates": [
      109.808,
      22.6271
    ],
    "type": "Point"
  }
}