{
  "type": "Feature",
  "properties": {
    "gn:admin1_code": "16.0",
    "gn:asciiname": "Gao'ai",
    "gn:country_code": "CN",
    "gn:dem": 686,
    "gn:feature_class": "P",
    "gn:feature_code": "PPL",
    "gn:name": "Gao’ai",
    "gn:population": 0,
    "gn:timezone": "Asia/Shanghai",
    "iso:country": "CN",
    "name:und_x_variant": [
      "Gao’ai"
    ],
    "name:zho_x_preferred": [
      "高矮"
    ],
    "wof:name": "Gao'ai",
    "wof:placetype": "locality"
  },
  "geometry": {
    "coordinates": [
      108.768,
      25.6286
    ],
    "type": "Point"
  }
}