{
  "type": "Feature",
  "properties": {
    "gn:admin1_code": "18",
    "gn:asciiname": "Baiguomiao",
    "gn:country_code": "CN",
    "gn:dem": 938,
    "gn:feature_class": "P",
    "gn:feature_code": "PPL",
    "gn:name": "Baiguomiao",
    "gn:population": 0,
    "gn:timezone": "Asia/Shanghai",
    "iso:country": "CN",
    "name:zho_x_preferred": [
      "白果庙"
    ],
    "wof:name": "Baiguomiao",
    "wof:placetype": "locality"
  },
  "geometry": {
    "coordinates": [
      107.432,
      27.9321
    ],
    "type": "Point"
  }
}