{
  "type": "Feature",
  "properties": {
    "gn:admin1_code": "18.0",
    "gn:asciiname": "Dadu",
    "gn:country_code": "CN",
    "gn:dem": 847,
    "gn:feature_class": "P",
    "gn:feature_code": "PPL",
    "gn:name": "Dadu",
    "gn:population": 0,
    "gn:timezone": "Asia/Shanghai",
    "iso:country": "CN",
    "name:ara_x_preferred": [
      "دادو"
    ],
    "name:ben_x_preferred": [
      "ডাদু"
    ],
    "name:ceb_x_preferred": [
      "Dadu"
    ],
    "name:ces_x_preferred": [
      "Ta-tu"
    ],
    "name:deu_x_preferred": [
      "Dadu"
    ],
    "name:ell_x_preferred": [
      "Μπατού"
    ],
    "name:fra_x_preferred": [
      "Dadu"
    ],
    "name:heb_x_preferred": [
      "דאדו"
    ],
    "name:hin_x_preferred": [
      "दादू"
    ],
    "name:hun_x_preferred": [
      "Dadu"
    ],
    "name:ind_x_preferred": [
      "Dadu"
    ],
    "name:nld_x_preferred": [
      "Dadu"
    ],
    "name:nor_x_preferred": [
      "Dadu"
    ],
    "name:por_x_preferred": [
      "Dadu"
    ],
    "name:scn_x_preferred": [
      "Dadu"
    ],
    "name:swe_x_preferred": [
      "Dadu"
    ],
    "name:urd_x_preferred": [
      "دادو"
    ],
    "wof:name": "Dadu",
    "wof:placetype": "locality"
  },
  "geometry": {
    "coordinates": [
      107.74,
      27.66472
    ],
    "type": "Point"
  }
}