{
  "type": "Feature",
  "properties": {
    "gn:admin1_code": "23.0",
    "gn:asciiname": "Yexie",
    "gn:country_code": "CN",
    "gn:dem": 6,
    "gn:feature_class": "P",
    "gn:feature_code": "PPLA4",
    "gn:name": "Yexie",
    "gn:population": 0,
    "gn:timezone": "Asia/Shanghai",
    "iso:country": "CN",
    "name:und_x_variant": [
      "Yeh-hsieh",
      "Yeh-hsieh-chen",
      "Yexie",
      "叶榭",
      "Yexie Zhen",
      "叶榭镇"
    ],
    "wof:name": "Yexie",
    "wof:placetype": "locality"
  },
  "geometry": {
    "coordinates": [
      121.31643,
      30.94543
    ],
    "type": "Point"
  }
}