{
  "type": "Feature",
  "properties": {
    "gn:admin1_code": "26.0",
    "gn:asciiname": "Jiajia Goucun",
    "gn:country_code": "CN",
    "gn:dem": 1096,
    "gn:feature_class": "P",
    "gn:feature_code": "PPL",
    "gn:name": "Jiajia Goucun",
    "gn:population": 0,
    "gn:timezone": "Asia/Shanghai",
    "iso:country": "CN",
    "name:zho_x_preferred": [
      "贾家沟村"
    ],
    "wof:name": "Jiajia Goucun",
    "wof:placetype": "locality"
  },
  "geometry": {
    "coordinates": [
      110.806,
      38.9113
    ],
    "type": "Point"
  }
}