{
  "type": "Feature",
  "properties": {
    "gn:admin1_code": "18",
    "gn:asciiname": "Zhejiao",
    "gn:country_code": "CN",
    "gn:dem": 695,
    "gn:feature_class": "P",
    "gn:feature_code": "PPL",
    "gn:name": "Zhejiao",
    "gn:population": 0,
    "gn:timezone": "Asia/Shanghai",
    "iso:country": "CN",
    "name:zho_x_preferred": [
      "这角"
    ],
    "wof:name": "Zhejiao",
    "wof:placetype": "locality"
  },
  "geometry": {
    "coordinates": [
      105.962,
      25.7131
    ],
    "type": "Point"
  }
}