{
  "type": "Feature",
  "properties": {
    "gn:admin1_code": "10",
    "gn:asciiname": "Henandian",
    "gn:country_code": "CN",
    "gn:dem": 999,
    "gn:feature_class": "P",
    "gn:feature_code": "PPL",
    "gn:name": "Henandian",
    "gn:population": 0,
    "gn:timezone": "Asia/Shanghai",
    "iso:country": "CN",
    "name:zho_x_preferred": [
      "河南店"
    ],
    "wof:name": "Henandian",
    "wof:placetype": "locality"
  },
  "geometry": {
    "coordinates": [
      116.98451,
      41.49534
    ],
    "type": "Point"
  }
}