{
  "type": "Feature",
  "properties": {
    "gn:admin1_code": "11.0",
    "gn:asciiname": "Gaoling",
    "gn:country_code": "CN",
    "gn:dem": 653,
    "gn:feature_class": "P",
    "gn:feature_code": "PPL",
    "gn:name": "Gaoling",
    "gn:population": 0,
    "gn:timezone": "Asia/Shanghai",
    "iso:country": "CN",
    "name:zho_x_preferred": [
      "高岭"
    ],
    "wof:name": "Gaoling",
    "wof:placetype": "locality"
  },
  "geometry": {
    "coordinates": [
      113.05579,
      26.86607
    ],
    "type": "Point"
  }
}