{
  "type": "Feature",
  "properties": {
    "gn:admin1_code": "32.0",
    "gn:asciiname": "Wukan",
    "gn:country_code": "CN",
    "gn:dem": 616,
    "gn:feature_class": "P",
    "gn:feature_code": "PPL",
    "gn:name": "Wukan",
    "gn:population": 0,
    "gn:timezone": "Asia/Shanghai",
    "iso:country": "CN",
    "name:deu_x_preferred": [
      "Wukan"
    ],
    "name:epo_x_preferred": [
      "Wukan"
    ],
    "name:fas_x_preferred": [
      "ووکان"
    ],
    "name:zho_x_preferred": [
      "伍坎"
    ],
    "name:zho_x_variant": [
      "烏坎村"
    ],
    "wof:name": "Wukan",
    "wof:placetype": "locality"
  },
  "geometry": {
    "coordinates": [
      103.467,
      29.5027
    ],
    "type": "Point"
  }
}