{
  "type": "Feature",
  "properties": {
    "gn:admin1_code": "01",
    "gn:asciiname": "Putang",
    "gn:country_code": "CN",
    "gn:dem": 36,
    "gn:feature_class": "P",
    "gn:feature_code": "PPLA4",
    "gn:name": "Putang",
    "gn:population": 0,
    "gn:timezone": "Asia/Shanghai",
    "iso:country": "CN",
    "name:und_x_variant": [
      "P’u-t’ang-chen",
      "Putang",
      "Putang Zhen"
    ],
    "name:zho_x_preferred": [
      "濮塘"
    ],
    "name:zho_x_variant": [
      "濮塘镇"
    ],
    "wof:name": "Putang",
    "wof:placetype": "locality"
  },
  "geometry": {
    "coordinates": [
      118.64924,
      31.7124
    ],
    "type": "Point"
  }
}