{
  "type": "Feature",
  "properties": {
    "gn:admin1_code": "30.0",
    "gn:asciiname": "Xixicun",
    "gn:country_code": "CN",
    "gn:dem": 123,
    "gn:feature_class": "P",
    "gn:feature_code": "PPL",
    "gn:name": "Xixicun",
    "gn:population": 0,
    "gn:timezone": "Asia/Shanghai",
    "iso:country": "CN",
    "name:zho_x_preferred": [
      "西溪村"
    ],
    "wof:name": "Xixicun",
    "wof:placetype": "locality"
  },
  "geometry": {
    "coordinates": [
      114.6081,
      24.01704
    ],
    "type": "Point"
  }
}