{
  "type": "Feature",
  "properties": {
    "gn:admin1_code": "7.0",
    "gn:asciiname": "Pushan",
    "gn:country_code": "CN",
    "gn:dem": 84,
    "gn:feature_class": "P",
    "gn:feature_code": "PPL",
    "gn:name": "Pushan",
    "gn:population": 0,
    "gn:timezone": "Asia/Shanghai",
    "iso:country": "CN",
    "name:als_x_preferred": [
      "Pushan"
    ],
    "name:deu_x_preferred": [
      "Pushan"
    ],
    "name:fra_x_preferred": [
      "Pushan"
    ],
    "name:jpn_x_preferred": [
      "プーシャン"
    ],
    "name:lit_x_preferred": [
      "Pūšanas"
    ],
    "name:pol_x_preferred": [
      "Puszan"
    ],
    "name:por_x_preferred": [
      "Puchan"
    ],
    "name:rus_x_preferred": [
      "Пушан"
    ],
    "name:spa_x_preferred": [
      "Pushán"
    ],
    "name:swe_x_preferred": [
      "Pushan"
    ],
    "name:zho_x_preferred": [
      "蒲山"
    ],
    "wof:name": "Pushan",
    "wof:placetype": "locality"
  },
  "geometry": {
    "coordinates": [
      118.64276,
      25.38479
    ],
    "type": "Point"
  }
}