{
  "type": "Feature",
  "properties": {
    "gn:admin1_code": "16.0",
    "gn:asciiname": "Nanpai",
    "gn:country_code": "CN",
    "gn:dem": 464,
    "gn:feature_class": "P",
    "gn:feature_code": "PPL",
    "gn:name": "Nanpai",
    "gn:population": 0,
    "gn:timezone": "Asia/Shanghai",
    "iso:country": "CN",
    "name:zho_x_preferred": [
      "南排"
    ],
    "wof:name": "Nanpai",
    "wof:placetype": "locality"
  },
  "geometry": {
    "coordinates": [
      107.626,
      24.626
    ],
    "type": "Point"
  }
}