{
  "type": "Feature",
  "properties": {
    "gn:admin1_code": "19.0",
    "gn:asciiname": "Xigong'ao",
    "gn:country_code": "CN",
    "gn:dem": 38,
    "gn:feature_class": "P",
    "gn:feature_code": "PPL",
    "gn:name": "Xigong’ao",
    "gn:population": 0,
    "gn:timezone": "Asia/Shanghai",
    "iso:country": "CN",
    "name:zho_x_preferred": [
      "Xigong’ao"
    ],
    "name:zho_x_variant": [
      "西公廒"
    ],
    "wof:name": "Xigong'ao",
    "wof:placetype": "locality"
  },
  "geometry": {
    "coordinates": [
      122.13328,
      41.84359
    ],
    "type": "Point"
  }
}