{
  "type": "Feature",
  "properties": {
    "gn:admin1_code": "16.0",
    "gn:asciiname": "Lamu",
    "gn:country_code": "CN",
    "gn:dem": 672,
    "gn:feature_class": "P",
    "gn:feature_code": "PPL",
    "gn:name": "Lamu",
    "gn:population": 0,
    "gn:timezone": "Asia/Shanghai",
    "iso:country": "CN",
    "name:ara_x_preferred": [
      "لامو"
    ],
    "name:azb_x_preferred": [
      "لامبو"
    ],
    "name:bel_x_preferred": [
      "Ламу"
    ],
    "name:cat_x_preferred": [
      "Lamu"
    ],
    "name:ceb_x_preferred": [
      "Lamu"
    ],
    "name:dan_x_preferred": [
      "Lamu"
    ],
    "name:epo_x_preferred": [
      "Lamu"
    ],
    "name:fas_x_preferred": [
      "لامبو"
    ],
    "name:fra_x_preferred": [
      "Lamu"
    ],
    "name:heb_x_preferred": [
      "לאמו"
    ],
    "name:hin_x_preferred": [
      "लामू"
    ],
    "name:hun_x_preferred": [
      "Lamu"
    ],
    "name:ind_x_preferred": [
      "Lamu"
    ],
    "name:ita_x_preferred": [
      "Lamu"
    ],
    "name:jpn_x_preferred": [
      "ラム"
    ],
    "name:kat_x_preferred": [
      "ლამუ"
    ],
    "name:lit_x_preferred": [
      "Lamu"
    ],
    "name:mal_x_preferred": [
      "ലമു"
    ],
    "name:nld_x_preferred": [
      "Lamu"
    ],
    "name:nor_x_preferred": [
      "Lamu"
    ],
    "name:pol_x_preferred": [
      "Lamu"
    ],
    "name:por_x_preferred": [
      "Lamu"
    ],
    "name:ron_x_preferred": [
      "Lamu"
    ],
    "name:rus_x_preferred": [
      "Ламу"
    ],
    "name:spa_x_preferred": [
      "Lamu"
    ],
    "name:srp_x_preferred": [
      "Ламу"
    ],
    "name:swa_x_preferred": [
      "Lamu"
    ],
    "name:swe_x_preferred": [
      "Lamu"
    ],
    "name:tgl_x_preferred": [
      "Lamu"
    ],
    "name:tur_x_preferred": [
      "Lamu"
    ],
    "name:vie_x_preferred": [
      "Lamu"
    ],
    "name:zho_x_preferred": [
      "拉母"
    ],
    "name:zho_x_variant": [
      "拉穆镇"
    ],
    "wof:name": "Lamu",
    "wof:placetype": "locality"
  },
  "geometry": {
    "coordinates": [
      107.268,
      25.294
    ],
    "type": "Point"
  }
}