{
  "type": "Feature",
  "properties": {
    "gn:admin1_code": "12.0",
    "gn:asciiname": "Zhaojia'ao",
    "gn:country_code": "CN",
    "gn:dem": 42,
    "gn:feature_class": "P",
    "gn:feature_code": "PPL",
    "gn:name": "Zhaojia’ao",
    "gn:population": 0,
    "gn:timezone": "Asia/Shanghai",
    "iso:country": "CN",
    "name:zho_x_preferred": [
      "Zhaojia’ao"
    ],
    "name:zho_x_variant": [
      "赵家坳"
    ],
    "wof:name": "Zhaojia'ao",
    "wof:placetype": "locality"
  },
  "geometry": {
    "coordinates": [
      115.10727,
      30.47098
    ],
    "type": "Point"
  }
}