{
  "type": "Feature",
  "properties": {
    "gn:admin1_code": "3",
    "gn:asciiname": "Hejia",
    "gn:country_code": "CN",
    "gn:dem": 118,
    "gn:feature_class": "P",
    "gn:feature_code": "PPL",
    "gn:name": "Hejia",
    "gn:population": 0,
    "gn:timezone": "Asia/Shanghai",
    "iso:country": "CN",
    "name:zho_x_preferred": [
      "合家"
    ],
    "wof:name": "Hejia",
    "wof:placetype": "locality"
  },
  "geometry": {
    "coordinates": [
      114.21202,
      27.03483
    ],
    "type": "Point"
  }
}