{
  "type": "Feature",
  "properties": {
    "gn:admin1_code": "32.0",
    "gn:asciiname": "Tong'an",
    "gn:country_code": "CN",
    "gn:dem": 517,
    "gn:feature_class": "P",
    "gn:feature_code": "PPL",
    "gn:name": "Tong’an",
    "gn:population": 0,
    "gn:timezone": "Asia/Shanghai",
    "iso:country": "CN",
    "name:zho_x_preferred": [
      "同安"
    ],
    "name:zho_x_variant": [
      "Tong’an"
    ],
    "wof:name": "Tong'an",
    "wof:placetype": "locality"
  },
  "geometry": {
    "coordinates": [
      104.30694,
      30.6039
    ],
    "type": "Point"
  }
}