{
  "type": "Feature",
  "properties": {
    "gn:admin1_code": "26.0",
    "gn:asciiname": "Housita",
    "gn:country_code": "CN",
    "gn:dem": 1442,
    "gn:feature_class": "P",
    "gn:feature_code": "PPL",
    "gn:name": "Housita",
    "gn:population": 0,
    "gn:timezone": "Asia/Shanghai",
    "iso:country": "CN",
    "name:zho_x_preferred": [
      "后寺塔"
    ],
    "wof:name": "Housita",
    "wof:placetype": "locality"
  },
  "geometry": {
    "coordinates": [
      108.33535,
      36.83759000000001
    ],
    "type": "Point"
  }
}