{
  "type": "Feature",
  "properties": {
    "gn:admin1_code": "10",
    "gn:asciiname": "Shenjiagou",
    "gn:country_code": "CN",
    "gn:dem": 659,
    "gn:feature_class": "P",
    "gn:feature_code": "PPL",
    "gn:name": "Shenjiagou",
    "gn:population": 0,
    "gn:timezone": "Asia/Shanghai",
    "iso:country": "CN",
    "name:zho_x_preferred": [
      "申家沟"
    ],
    "wof:name": "Shenjiagou",
    "wof:placetype": "locality"
  },
  "geometry": {
    "coordinates": [
      118.68062,
      41.10642
    ],
    "type": "Point"
  }
}