{
  "type": "Feature",
  "properties": {
    "gn:admin1_code": "15.0",
    "gn:asciiname": "Changjia Goumen",
    "gn:country_code": "CN",
    "gn:dem": 1086,
    "gn:feature_class": "P",
    "gn:feature_code": "PPL",
    "gn:name": "Changjia Goumen",
    "gn:population": 0,
    "gn:timezone": "Asia/Shanghai",
    "iso:country": "CN",
    "name:zho_x_preferred": [
      "常家沟门"
    ],
    "wof:name": "Changjia Goumen",
    "wof:placetype": "locality"
  },
  "geometry": {
    "coordinates": [
      108.181,
      35.6333
    ],
    "type": "Point"
  }
}