{
  "type": "Feature",
  "properties": {
    "gn:admin1_code": "4.0",
    "gn:asciiname": "Bali",
    "gn:country_code": "CN",
    "gn:dem": 4,
    "gn:feature_class": "P",
    "gn:feature_code": "PPLA4",
    "gn:name": "Bali",
    "gn:population": 0,
    "gn:timezone": "Asia/Shanghai",
    "iso:country": "CN",
    "name:ace_x_preferred": [
      "Bali"
    ],
    "name:ceb_x_preferred": [
      "Provinsi Bali"
    ],
    "name:est_x_preferred": [
      "Bali provints"
    ],
    "name:fra_x_preferred": [
      "Bali"
    ],
    "name:gor_x_preferred": [
      "Bali"
    ],
    "name:hin_x_preferred": [
      "बाली"
    ],
    "name:ind_x_preferred": [
      "Bali"
    ],
    "name:jav_x_preferred": [
      "Bali"
    ],
    "name:jpn_x_preferred": [
      "バリ州"
    ],
    "name:kor_x_preferred": [
      "발리주"
    ],
    "name:lav_x_preferred": [
      "Bali"
    ],
    "name:pol_x_preferred": [
      "Bali"
    ],
    "name:rus_x_preferred": [
      "Бали"
    ],
    "name:swe_x_preferred": [
      "Bali"
    ],
    "name:tur_x_preferred": [
      "Bali"
    ],
    "name:und_x_variant": [
      "Bali Zhen"
    ],
    "name:urd_x_preferred": [
      "بالی"
    ],
    "name:war_x_preferred": [
      "Bali"
    ],
    "name:zho_x_preferred": [
      "八里"
    ],
    "name:zho_x_variant": [
      "八里镇",
      "巴厘岛"
    ],
    "wof:name": "Bali",
    "wof:placetype": "locality"
  },
  "geometry": {
    "coordinates": [
      119.39918,
      32.29077
    ],
    "type": "Point"
  }
}