{
  "type": "Feature",
  "properties": {
    "gn:admin1_code": "31",
    "gn:asciiname": "Gancun",
    "gn:country_code": "CN",
    "gn:dem": 17,
    "gn:feature_class": "P",
    "gn:feature_code": "PPL",
    "gn:name": "Gancun",
    "gn:population": 0,
    "gn:timezone": "Asia/Shanghai",
    "iso:country": "CN",
    "name:und_x_variant": [
      "甘村"
    ],
    "wof:name": "Gancun",
    "wof:placetype": "locality"
  },
  "geometry": {
    "coordinates": [
      110.665,
      19.4248
    ],
    "type": "Point"
  }
}