{
  "type": "Feature",
  "properties": {
    "gn:admin1_code": "2.0",
    "gn:asciiname": "Ou'an",
    "gn:country_code": "CN",
    "gn:dem": 53,
    "gn:feature_class": "P",
    "gn:feature_code": "PPL",
    "gn:name": "Ou’an",
    "gn:population": 0,
    "gn:timezone": "Asia/Shanghai",
    "iso:country": "CN",
    "name:und_x_variant": [
      "Ou’an"
    ],
    "name:zho_x_preferred": [
      "藕岸"
    ],
    "wof:name": "Ou'an",
    "wof:placetype": "locality"
  },
  "geometry": {
    "coordinates": [
      120.98061,
      29.5361
    ],
    "type": "Point"
  }
}