{
  "type": "Feature",
  "properties": {
    "gn:admin1_code": "20.0",
    "gn:asciiname": "Bayanburide Gacha",
    "gn:country_code": "CN",
    "gn:dem": 598,
    "gn:feature_class": "P",
    "gn:feature_code": "PPL",
    "gn:name": "Bayanburide Gacha",
    "gn:population": 0,
    "gn:timezone": "Asia/Shanghai",
    "iso:country": "CN",
    "name:zho_x_preferred": [
      "巴彦布日德嘎查"
    ],
    "wof:name": "Bayanburide Gacha",
    "wof:placetype": "locality"
  },
  "geometry": {
    "coordinates": [
      119.31892,
      49.19895
    ],
    "type": "Point"
  }
}