{
  "type": "Feature",
  "properties": {
    "gn:admin1_code": "4.0",
    "gn:asciiname": "Yixingdai",
    "gn:country_code": "CN",
    "gn:dem": 5,
    "gn:feature_class": "P",
    "gn:feature_code": "PPL",
    "gn:name": "Yixingdai",
    "gn:population": 0,
    "gn:timezone": "Asia/Shanghai",
    "iso:country": "CN",
    "name:zho_x_preferred": [
      "义兴埭"
    ],
    "wof:name": "Yixingdai",
    "wof:placetype": "locality"
  },
  "geometry": {
    "coordinates": [
      120.40659,
      31.94922
    ],
    "type": "Point"
  }
}