{
  "type": "Feature",
  "properties": {
    "gn:admin1_code": "16.0",
    "gn:asciiname": "Guancang",
    "gn:country_code": "CN",
    "gn:dem": 685,
    "gn:feature_class": "P",
    "gn:feature_code": "PPL",
    "gn:name": "Guancang",
    "gn:population": 0,
    "gn:timezone": "Asia/Shanghai",
    "iso:country": "CN",
    "name:zho_x_preferred": [
      "官仓"
    ],
    "wof:name": "Guancang",
    "wof:placetype": "locality"
  },
  "geometry": {
    "coordinates": [
      106.598,
      24.4063
    ],
    "type": "Point"
  }
}