{
  "type": "Feature",
  "properties": {
    "gn:admin1_code": "26.0",
    "gn:asciiname": "Huashan Chengzi",
    "gn:country_code": "CN",
    "gn:dem": 1489,
    "gn:feature_class": "P",
    "gn:feature_code": "PPL",
    "gn:name": "Huashan Chengzi",
    "gn:population": 0,
    "gn:timezone": "Asia/Shanghai",
    "iso:country": "CN",
    "name:zho_x_preferred": [
      "花山城子"
    ],
    "wof:name": "Huashan Chengzi",
    "wof:placetype": "locality"
  },
  "geometry": {
    "coordinates": [
      108.161,
      37.1834
    ],
    "type": "Point"
  }
}