{
  "type": "Feature",
  "properties": {
    "gn:admin1_code": "16.0",
    "gn:asciiname": "Kawucun",
    "gn:country_code": "CN",
    "gn:dem": 637,
    "gn:feature_class": "P",
    "gn:feature_code": "PPL",
    "gn:name": "Kawucun",
    "gn:population": 0,
    "gn:timezone": "Asia/Shanghai",
    "iso:country": "CN",
    "name:zho_x_preferred": [
      "卡五村"
    ],
    "wof:name": "Kawucun",
    "wof:placetype": "locality"
  },
  "geometry": {
    "coordinates": [
      107.15,
      24.8137
    ],
    "type": "Point"
  }
}