{
  "type": "Feature",
  "properties": {
    "gn:admin1_code": "24.0",
    "gn:asciiname": "Sujiazhuang",
    "gn:country_code": "CN",
    "gn:dem": 1113,
    "gn:feature_class": "P",
    "gn:feature_code": "PPL",
    "gn:name": "Sujiazhuang",
    "gn:population": 0,
    "gn:timezone": "Asia/Shanghai",
    "iso:country": "CN",
    "name:zho_x_preferred": [
      "苏家庄"
    ],
    "wof:name": "Sujiazhuang",
    "wof:placetype": "locality"
  },
  "geometry": {
    "coordinates": [
      110.78194,
      36.5851
    ],
    "type": "Point"
  }
}