{
  "type": "Feature",
  "properties": {
    "gn:admin1_code": "19.0",
    "gn:asciiname": "Dong'a'er Xiang",
    "gn:country_code": "CN",
    "gn:dem": 254,
    "gn:feature_class": "P",
    "gn:feature_code": "PPL",
    "gn:name": "Dong’a’er Xiang",
    "gn:population": 0,
    "gn:timezone": "Asia/Shanghai",
    "iso:country": "CN",
    "name:und_x_variant": [
      "Dong’a’er Xiang"
    ],
    "name:zho_x_preferred": [
      "东阿尔乡"
    ],
    "wof:name": "Dong'a'er Xiang",
    "wof:placetype": "locality"
  },
  "geometry": {
    "coordinates": [
      122.436,
      42.8214
    ],
    "type": "Point"
  }
}