{
  "type": "Feature",
  "properties": {
    "gn:admin1_code": "2.0",
    "gn:asciiname": "Tongtian",
    "gn:country_code": "CN",
    "gn:dem": 550,
    "gn:feature_class": "P",
    "gn:feature_code": "PPL",
    "gn:name": "Tongtian",
    "gn:population": 0,
    "gn:timezone": "Asia/Shanghai",
    "iso:country": "CN",
    "name:ara_x_preferred": [
      "تونغتيان"
    ],
    "name:ben_x_preferred": [
      "টংটিয়ান"
    ],
    "name:deu_x_preferred": [
      "Zhi Qu"
    ],
    "name:deu_x_variant": [
      "Tongtian"
    ],
    "name:ell_x_preferred": [
      "Τόγκτιαν"
    ],
    "name:fas_x_preferred": [
      "تونگتیان"
    ],
    "name:heb_x_preferred": [
      "טונגטיאן"
    ],
    "name:hin_x_preferred": [
      "टोंगटियन"
    ],
    "name:hun_x_preferred": [
      "Tongtian"
    ],
    "name:ind_x_preferred": [
      "Tongtian"
    ],
    "name:ita_x_preferred": [
      "Tongtian"
    ],
    "name:jpn_x_preferred": [
      " 通天河"
    ],
    "name:kor_x_preferred": [
      "통천"
    ],
    "name:nld_x_preferred": [
      "Tongtian"
    ],
    "name:pol_x_preferred": [
      "Tongtian"
    ],
    "name:por_x_preferred": [
      "Tongtian"
    ],
    "name:rus_x_preferred": [
      "река Тунтянь"
    ],
    "name:spa_x_preferred": [
      "Tongtian"
    ],
    "name:swe_x_preferred": [
      "Tongtian"
    ],
    "name:tur_x_preferred": [
      "Tongtian"
    ],
    "name:ukr_x_preferred": [
      "Тонгтіан"
    ],
    "name:urd_x_preferred": [
      "ٹونگٹیان"
    ],
    "name:vie_x_preferred": [
      "Sông Thông Thiên"
    ],
    "name:zho_x_preferred": [
      "同田"
    ],
    "wof:name": "Tongtian",
    "wof:placetype": "locality"
  },
  "geometry": {
    "coordinates": [
      120.59793,
      29.11387
    ],
    "type": "Point"
  }
}