{
  "type": "Feature",
  "properties": {
    "gn:admin1_code": "13.0",
    "gn:asciiname": "Egiztobe",
    "gn:country_code": "CN",
    "gn:dem": 523,
    "gn:feature_class": "P",
    "gn:feature_code": "PPLA4",
    "gn:name": "Egiztobe",
    "gn:population": 0,
    "gn:timezone": "Asia/Urumqi",
    "iso:country": "CN",
    "name:kaz_x_preferred": [
      "ەگىزتوبە اۋىلى"
    ],
    "name:uig_x_preferred": [
      "Egiztɵbə"
    ],
    "name:uig_x_variant": [
      "Égiztöbe",
      "ئېگىزتۆبە",
      "Эгизтөбә",
      "ئېگىزتۆبە يېزىسى"
    ],
    "name:und_x_variant": [
      "Egiztobe Xiang",
      "Egiztobe",
      "Yegezituobie",
      "Yegezituobie Xiang"
    ],
    "name:zho_x_preferred": [
      "也格孜托别"
    ],
    "name:zho_x_variant": [
      "也格孜托别乡"
    ],
    "wof:name": "Egiztobe",
    "wof:placetype": "locality"
  },
  "geometry": {
    "coordinates": [
      87.00466,
      47.85938
    ],
    "type": "Point"
  }
}