{
  "type": "Feature",
  "properties": {
    "gn:admin1_code": "8.0",
    "gn:asciiname": "Beilincun",
    "gn:country_code": "CN",
    "gn:dem": 478,
    "gn:feature_class": "P",
    "gn:feature_code": "PPL",
    "gn:name": "Beilincun",
    "gn:population": 0,
    "gn:timezone": "Asia/Shanghai",
    "iso:country": "CN",
    "name:zho_x_preferred": [
      "北林村"
    ],
    "wof:name": "Beilincun",
    "wof:placetype": "locality"
  },
  "geometry": {
    "coordinates": [
      130.14827,
      44.50971
    ],
    "type": "Point"
  }
}