{
  "type": "Feature",
  "properties": {
    "gn:admin1_code": "26.0",
    "gn:asciiname": "Dadaohe",
    "gn:country_code": "CN",
    "gn:dem": 1004,
    "gn:feature_class": "P",
    "gn:feature_code": "PPL",
    "gn:name": "Dadaohe",
    "gn:population": 0,
    "gn:timezone": "Asia/Shanghai",
    "iso:country": "CN",
    "name:zho_x_preferred": [
      "大道河"
    ],
    "wof:name": "Dadaohe",
    "wof:placetype": "locality"
  },
  "geometry": {
    "coordinates": [
      110.12945,
      36.66346
    ],
    "type": "Point"
  }
}