{
  "type": "Feature",
  "properties": {
    "gn:admin1_code": "26.0",
    "gn:asciiname": "Liugou",
    "gn:country_code": "CN",
    "gn:dem": 1146,
    "gn:feature_class": "P",
    "gn:feature_code": "PPL",
    "gn:name": "Liugou",
    "gn:population": 0,
    "gn:timezone": "Asia/Shanghai",
    "iso:country": "CN",
    "name:zho_x_preferred": [
      "柳沟"
    ],
    "wof:name": "Liugou",
    "wof:placetype": "locality"
  },
  "geometry": {
    "coordinates": [
      110.90976,
      39.22809
    ],
    "type": "Point"
  }
}