{
  "type": "Feature",
  "properties": {
    "gn:admin1_code": "3.0",
    "gn:asciiname": "Luojia",
    "gn:country_code": "CN",
    "gn:dem": 210,
    "gn:feature_class": "P",
    "gn:feature_code": "PPL",
    "gn:name": "Luojia",
    "gn:population": 0,
    "gn:timezone": "Asia/Shanghai",
    "iso:country": "CN",
    "name:zho_x_preferred": [
      "罗家"
    ],
    "wof:name": "Luojia",
    "wof:placetype": "locality"
  },
  "geometry": {
    "coordinates": [
      117.56287,
      28.05342000000001
    ],
    "type": "Point"
  }
}