{
  "type": "Feature",
  "properties": {
    "gn:admin1_code": "19.0",
    "gn:asciiname": "Zhangdian",
    "gn:country_code": "CN",
    "gn:dem": 107,
    "gn:feature_class": "P",
    "gn:feature_code": "PPLA4",
    "gn:name": "Zhangdian",
    "gn:population": 0,
    "gn:timezone": "Asia/Shanghai",
    "iso:country": "CN",
    "name:und_x_variant": [
      "张甸",
      "Zhangdian Jiedao",
      "张甸街道"
    ],
    "wof:name": "Zhangdian",
    "wof:placetype": "locality"
  },
  "geometry": {
    "coordinates": [
      124.04135,
      41.8172
    ],
    "type": "Point"
  }
}