{
  "type": "Feature",
  "properties": {
    "gn:admin1_code": "29.0",
    "gn:asciiname": "Nabotian Xinzhai",
    "gn:country_code": "CN",
    "gn:dem": 1261,
    "gn:feature_class": "P",
    "gn:feature_code": "PPL",
    "gn:name": "Nabotian Xinzhai",
    "gn:population": 0,
    "gn:timezone": "Asia/Shanghai",
    "iso:country": "CN",
    "name:zho_x_preferred": [
      "哪波田新寨"
    ],
    "wof:name": "Nabotian Xinzhai",
    "wof:placetype": "locality"
  },
  "geometry": {
    "coordinates": [
      100.228,
      22.9097
    ],
    "type": "Point"
  }
}