{
  "type": "Feature",
  "properties": {
    "gn:admin1_code": "02",
    "gn:asciiname": "Jinkengcun",
    "gn:country_code": "CN",
    "gn:dem": 548,
    "gn:feature_class": "P",
    "gn:feature_code": "PPL",
    "gn:name": "Jinkengcun",
    "gn:population": 0,
    "gn:timezone": "Asia/Shanghai",
    "iso:country": "CN",
    "name:und_x_variant": [
      "Chin-k’eng-ti",
      "Jinkeng",
      "Jinkengcun"
    ],
    "name:zho_x_preferred": [
      "金坑"
    ],
    "name:zho_x_variant": [
      "金坑村"
    ],
    "wof:name": "Jinkengcun",
    "wof:placetype": "locality"
  },
  "geometry": {
    "coordinates": [
      120.37361,
      28.30252
    ],
    "type": "Point"
  }
}