{
  "type": "Feature",
  "properties": {
    "gn:admin1_code": "29.0",
    "gn:asciiname": "Kuluzhai",
    "gn:country_code": "CN",
    "gn:dem": 1654,
    "gn:feature_class": "P",
    "gn:feature_code": "PPL",
    "gn:name": "Kuluzhai",
    "gn:population": 0,
    "gn:timezone": "Asia/Shanghai",
    "iso:country": "CN",
    "name:zho_x_preferred": [
      "苦芦寨"
    ],
    "wof:name": "Kuluzhai",
    "wof:placetype": "locality"
  },
  "geometry": {
    "coordinates": [
      102.929,
      23.0927
    ],
    "type": "Point"
  }
}