{
  "type": "Feature",
  "properties": {
    "gn:admin1_code": "8.0",
    "gn:asciiname": "Ping'ancun",
    "gn:country_code": "CN",
    "gn:dem": 178,
    "gn:feature_class": "P",
    "gn:feature_code": "PPL",
    "gn:name": "Ping’ancun",
    "gn:population": 0,
    "gn:timezone": "Asia/Shanghai",
    "iso:country": "CN",
    "name:und_x_variant": [
      "Ping’ancun"
    ],
    "name:zho_x_preferred": [
      "平安村"
    ],
    "wof:name": "Ping'ancun",
    "wof:placetype": "locality"
  },
  "geometry": {
    "coordinates": [
      126.2423,
      46.39011
    ],
    "type": "Point"
  }
}