{
  "type": "Feature",
  "properties": {
    "gn:admin1_code": "4.0",
    "gn:asciiname": "Weiziyuan",
    "gn:country_code": "CN",
    "gn:dem": 37,
    "gn:feature_class": "P",
    "gn:feature_code": "PPL",
    "gn:name": "Weiziyuan",
    "gn:population": 0,
    "gn:timezone": "Asia/Shanghai",
    "iso:country": "CN",
    "name:zho_x_preferred": [
      "苇子园"
    ],
    "wof:name": "Weiziyuan",
    "wof:placetype": "locality"
  },
  "geometry": {
    "coordinates": [
      116.856,
      34.8338
    ],
    "type": "Point"
  }
}