{
  "type": "Feature",
  "properties": {
    "gn:admin1_code": "3.0",
    "gn:asciiname": "Tali",
    "gn:country_code": "CN",
    "gn:dem": 23,
    "gn:feature_class": "P",
    "gn:feature_code": "PPL",
    "gn:name": "Tali",
    "gn:population": 0,
    "gn:timezone": "Asia/Shanghai",
    "iso:country": "CN",
    "name:ceb_x_preferred": [
      "Tali"
    ],
    "name:deu_x_preferred": [
      "Tali"
    ],
    "name:fin_x_preferred": [
      "Tali"
    ],
    "name:fra_x_preferred": [
      "Tali"
    ],
    "name:heb_x_preferred": [
      "טלי"
    ],
    "name:nld_x_preferred": [
      "Tali"
    ],
    "name:ron_x_preferred": [
      "Tali"
    ],
    "name:rus_x_preferred": [
      "Тали"
    ],
    "name:swe_x_preferred": [
      "Tali"
    ],
    "name:und_x_variant": [
      "塔李"
    ],
    "wof:name": "Tali",
    "wof:placetype": "locality"
  },
  "geometry": {
    "coordinates": [
      116.56081,
      29.01613
    ],
    "type": "Point"
  }
}