{
  "type": "Feature",
  "properties": {
    "gn:admin1_code": "18.0",
    "gn:asciiname": "Anxi",
    "gn:country_code": "CN",
    "gn:dem": 416,
    "gn:feature_class": "P",
    "gn:feature_code": "PPL",
    "gn:name": "Anxi",
    "gn:population": 0,
    "gn:timezone": "Asia/Shanghai",
    "iso:country": "CN",
    "name:ara_x_preferred": [
      "أنكسي"
    ],
    "name:ben_x_preferred": [
      "আনক্সি"
    ],
    "name:ceb_x_preferred": [
      "Anxi"
    ],
    "name:deu_x_preferred": [
      "Anxi"
    ],
    "name:ell_x_preferred": [
      "Άνξι"
    ],
    "name:fas_x_preferred": [
      "آنشی"
    ],
    "name:fra_x_preferred": [
      "Anxi"
    ],
    "name:heb_x_preferred": [
      "אנקסי"
    ],
    "name:hin_x_preferred": [
      "एंक्सी"
    ],
    "name:hun_x_preferred": [
      "Anxi"
    ],
    "name:ind_x_preferred": [
      "Anxi"
    ],
    "name:ita_x_preferred": [
      "Anxi"
    ],
    "name:jpn_x_preferred": [
      "安渓"
    ],
    "name:kor_x_preferred": [
      "안시"
    ],
    "name:nld_x_preferred": [
      "Anxi"
    ],
    "name:pol_x_preferred": [
      "Anxi"
    ],
    "name:por_x_preferred": [
      "Anxi"
    ],
    "name:rus_x_preferred": [
      "Аньси"
    ],
    "name:spa_x_preferred": [
      "Anxi"
    ],
    "name:swe_x_preferred": [
      "Anxi"
    ],
    "name:tur_x_preferred": [
      "Anxi"
    ],
    "name:ukr_x_preferred": [
      "Ансі"
    ],
    "name:urd_x_preferred": [
      "انزی"
    ],
    "name:vie_x_preferred": [
      "An Khê"
    ],
    "name:zho_cn_x_preferred": [
      "安溪"
    ],
    "name:zho_tw_x_preferred": [
      "安溪"
    ],
    "name:zho_x_preferred": [
      "安溪"
    ],
    "wof:name": "Anxi",
    "wof:placetype": "locality"
  },
  "geometry": {
    "coordinates": [
      109.334,
      27.6466
    ],
    "type": "Point"
  }
}