{
  "type": "Feature",
  "properties": {
    "gn:admin1_code": "3.0",
    "gn:asciiname": "Xinpengxia",
    "gn:country_code": "CN",
    "gn:dem": 628,
    "gn:feature_class": "P",
    "gn:feature_code": "PPL",
    "gn:name": "Xinpengxia",
    "gn:population": 0,
    "gn:timezone": "Asia/Shanghai",
    "iso:country": "CN",
    "name:zho_x_preferred": [
      "新棚下"
    ],
    "wof:name": "Xinpengxia",
    "wof:placetype": "locality"
  },
  "geometry": {
    "coordinates": [
      113.933,
      27.4358
    ],
    "type": "Point"
  }
}