{
  "type": "Feature",
  "properties": {
    "gn:admin1_code": "11.0",
    "gn:asciiname": "Banshan'ao",
    "gn:country_code": "CN",
    "gn:dem": 99,
    "gn:feature_class": "P",
    "gn:feature_code": "PPL",
    "gn:name": "Banshan’ao",
    "gn:population": 0,
    "gn:timezone": "Asia/Shanghai",
    "iso:country": "CN",
    "name:und_x_variant": [
      "Banshan’ao"
    ],
    "name:zho_x_preferred": [
      "半山坳"
    ],
    "wof:name": "Banshan'ao",
    "wof:placetype": "locality"
  },
  "geometry": {
    "coordinates": [
      112.3355,
      28.41834
    ],
    "type": "Point"
  }
}