{
  "type": "Feature",
  "properties": {
    "gn:admin1_code": "10",
    "gn:asciiname": "Tunjunbu",
    "gn:country_code": "CN",
    "gn:dem": 1099,
    "gn:feature_class": "P",
    "gn:feature_code": "PPL",
    "gn:name": "Tunjunbu",
    "gn:population": 0,
    "gn:timezone": "Asia/Shanghai",
    "iso:country": "CN",
    "name:zho_x_preferred": [
      "屯军堡"
    ],
    "wof:name": "Tunjunbu",
    "wof:placetype": "locality"
  },
  "geometry": {
    "coordinates": [
      115.81034,
      40.81437
    ],
    "type": "Point"
  }
}