{
  "type": "Feature",
  "properties": {
    "gn:admin1_code": "15.0",
    "gn:asciiname": "Hongtu'ebo",
    "gn:country_code": "CN",
    "gn:dem": 2553,
    "gn:feature_class": "P",
    "gn:feature_code": "PPL",
    "gn:name": "Hongtu’ebo",
    "gn:population": 0,
    "gn:timezone": "Asia/Shanghai",
    "iso:country": "CN",
    "name:und_x_variant": [
      "Hongtu’ebo"
    ],
    "name:zho_x_preferred": [
      "红土鄂博"
    ],
    "wof:name": "Hongtu'ebo",
    "wof:placetype": "locality"
  },
  "geometry": {
    "coordinates": [
      103.446,
      37.2954
    ],
    "type": "Point"
  }
}