{
  "type": "Feature",
  "properties": {
    "gn:admin1_code": "20.0",
    "gn:asciiname": "Shao'er Baoge",
    "gn:country_code": "CN",
    "gn:dem": 545,
    "gn:feature_class": "P",
    "gn:feature_code": "PPL",
    "gn:name": "Shao’er Baoge",
    "gn:population": 0,
    "gn:timezone": "Asia/Shanghai",
    "iso:country": "CN",
    "name:und_x_variant": [
      "Shao’er Baoge"
    ],
    "name:zho_x_preferred": [
      "绍尔包格"
    ],
    "wof:name": "Shao'er Baoge",
    "wof:placetype": "locality"
  },
  "geometry": {
    "coordinates": [
      118.06453,
      48.90542
    ],
    "type": "Point"
  }
}