{
  "type": "Feature",
  "properties": {
    "gn:admin1_code": "2.0",
    "gn:asciiname": "Zhang'ao",
    "gn:country_code": "CN",
    "gn:dem": 229,
    "gn:feature_class": "P",
    "gn:feature_code": "PPL",
    "gn:name": "Zhang’ao",
    "gn:population": 0,
    "gn:timezone": "Asia/Shanghai",
    "iso:country": "CN",
    "name:zho_x_preferred": [
      "张岙"
    ],
    "name:zho_x_variant": [
      "Zhang’ao"
    ],
    "wof:name": "Zhang'ao",
    "wof:placetype": "locality"
  },
  "geometry": {
    "coordinates": [
      119.97954,
      28.03897000000001
    ],
    "type": "Point"
  }
}