{
  "type": "Feature",
  "properties": {
    "gn:admin1_code": "1.0",
    "gn:asciiname": "Jiangtuloucun",
    "gn:country_code": "CN",
    "gn:dem": 33,
    "gn:feature_class": "P",
    "gn:feature_code": "PPL",
    "gn:name": "Jiangtuloucun",
    "gn:population": 0,
    "gn:timezone": "Asia/Shanghai",
    "iso:country": "CN",
    "name:zho_x_preferred": [
      "江土楼村"
    ],
    "wof:name": "Jiangtuloucun",
    "wof:placetype": "locality"
  },
  "geometry": {
    "coordinates": [
      116.1623,
      33.3526
    ],
    "type": "Point"
  }
}