{
  "type": "Feature",
  "properties": {
    "gn:admin1_code": "16.0",
    "gn:asciiname": "Yanshi",
    "gn:country_code": "CN",
    "gn:dem": 89,
    "gn:feature_class": "P",
    "gn:feature_code": "PPL",
    "gn:name": "Yanshi",
    "gn:population": 0,
    "gn:timezone": "Asia/Shanghai",
    "iso:country": "CN",
    "name:deu_x_preferred": [
      "Yanshi"
    ],
    "name:epo_x_preferred": [
      "Janŝi"
    ],
    "name:fra_x_preferred": [
      "Yanshi"
    ],
    "name:ita_x_preferred": [
      "Yanshi"
    ],
    "name:jpn_x_preferred": [
      "偃師市"
    ],
    "name:kik_x_preferred": [
      "Yanshi"
    ],
    "name:kor_x_preferred": [
      "옌스시"
    ],
    "name:nor_x_preferred": [
      "Yanshi"
    ],
    "name:pam_x_preferred": [
      "Yanshi"
    ],
    "name:rus_x_preferred": [
      "Яньши"
    ],
    "name:swe_x_preferred": [
      "Yanshi"
    ],
    "name:vie_x_preferred": [
      "Yển Sư"
    ],
    "name:zho_x_preferred": [
      "岩石"
    ],
    "name:zho_x_variant": [
      "偃师市"
    ],
    "wof:name": "Yanshi",
    "wof:placetype": "locality"
  },
  "geometry": {
    "coordinates": [
      109.307,
      22.131
    ],
    "type": "Point"
  }
}