{
  "type": "Feature",
  "properties": {
    "gn:admin1_code": "24",
    "gn:asciiname": "Xubu",
    "gn:country_code": "CN",
    "gn:dem": 1041,
    "gn:feature_class": "P",
    "gn:feature_code": "PPLA4",
    "gn:name": "Xubu",
    "gn:population": 0,
    "gn:timezone": "Asia/Shanghai",
    "iso:country": "CN",
    "name:jpn_x_preferred": [
      "須卜氏"
    ],
    "name:kor_x_preferred": [
      "수복씨"
    ],
    "name:und_x_variant": [
      "Hsü-chia-pao",
      "Hsü-pao",
      "Hsü-chia-p’u",
      "Xubu",
      "许堡",
      "Xubu Zhen",
      "许堡镇"
    ],
    "name:zho_x_preferred": [
      "須卜氏"
    ],
    "wof:name": "Xubu",
    "wof:placetype": "locality"
  },
  "geometry": {
    "coordinates": [
      113.74473,
      40.02792
    ],
    "type": "Point"
  }
}