{
  "type": "Feature",
  "properties": {
    "gn:admin1_code": "18.0",
    "gn:asciiname": "Dapanyang",
    "gn:country_code": "CN",
    "gn:dem": 736,
    "gn:feature_class": "P",
    "gn:feature_code": "PPL",
    "gn:name": "Dapanyang",
    "gn:population": 0,
    "gn:timezone": "Asia/Shanghai",
    "iso:country": "CN",
    "name:zho_x_preferred": [
      "大盘羊"
    ],
    "wof:name": "Dapanyang",
    "wof:placetype": "locality"
  },
  "geometry": {
    "coordinates": [
      108.561,
      25.9013
    ],
    "type": "Point"
  }
}