{
  "type": "Feature",
  "properties": {
    "gn:admin1_code": "15.0",
    "gn:asciiname": "Macun",
    "gn:country_code": "CN",
    "gn:dem": 1437,
    "gn:feature_class": "P",
    "gn:feature_code": "PPL",
    "gn:name": "Macun",
    "gn:population": 0,
    "gn:timezone": "Asia/Shanghai",
    "iso:country": "CN",
    "name:cat_x_preferred": [
      "Macun şekeri"
    ],
    "name:rus_x_preferred": [
      "Маджун"
    ],
    "name:spa_x_preferred": [
      "Macun şekeri"
    ],
    "name:tur_x_preferred": [
      "Macun şekeri"
    ],
    "name:zho_x_preferred": [
      "马村"
    ],
    "wof:name": "Macun",
    "wof:placetype": "locality"
  },
  "geometry": {
    "coordinates": [
      105.015,
      34.775
    ],
    "type": "Point"
  }
}