{
  "type": "Feature",
  "properties": {
    "gn:admin1_code": "16.0",
    "gn:asciiname": "Banda",
    "gn:country_code": "CN",
    "gn:dem": 225,
    "gn:feature_class": "P",
    "gn:feature_code": "PPL",
    "gn:name": "Banda",
    "gn:population": 0,
    "gn:timezone": "Asia/Shanghai",
    "iso:country": "CN",
    "name:ast_x_preferred": [
      "Banda"
    ],
    "name:bel_x_preferred": [
      "Банда"
    ],
    "name:ben_x_preferred": [
      "বান্দা"
    ],
    "name:bih_x_preferred": [
      "बाँदा"
    ],
    "name:bos_x_preferred": [
      "Banda"
    ],
    "name:bpy_x_preferred": [
      "বান্দা"
    ],
    "name:bul_x_preferred": [
      "Банда"
    ],
    "name:cat_x_preferred": [
      "Banda"
    ],
    "name:ceb_x_preferred": [
      "Banda"
    ],
    "name:deu_x_preferred": [
      "Banda"
    ],
    "name:fra_x_preferred": [
      "Banda"
    ],
    "name:glg_x_preferred": [
      "Banda"
    ],
    "name:heb_x_preferred": [
      "באנדה"
    ],
    "name:hrv_x_preferred": [
      "Banda"
    ],
    "name:ind_x_preferred": [
      "Banda"
    ],
    "name:ita_x_preferred": [
      "Banda"
    ],
    "name:jpn_x_preferred": [
      "バンダ"
    ],
    "name:kat_x_preferred": [
      "ბანდა"
    ],
    "name:kaz_x_preferred": [
      "Банда"
    ],
    "name:lit_x_preferred": [
      "Banda"
    ],
    "name:new_x_preferred": [
      "बान्दा"
    ],
    "name:nld_x_preferred": [
      "Banda"
    ],
    "name:pnb_x_preferred": [
      "بندہ"
    ],
    "name:pol_x_preferred": [
      "Banda"
    ],
    "name:por_x_preferred": [
      "Banda"
    ],
    "name:rus_x_preferred": [
      "Банда"
    ],
    "name:slk_x_preferred": [
      "Banda"
    ],
    "name:spa_x_preferred": [
      "Banda"
    ],
    "name:swe_x_preferred": [
      "Banda"
    ],
    "name:ukr_x_preferred": [
      "Банда"
    ],
    "name:zho_x_preferred": [
      "板达"
    ],
    "wof:name": "Banda",
    "wof:placetype": "locality"
  },
  "geometry": {
    "coordinates": [
      108.539,
      25.1597
    ],
    "type": "Point"
  }
}