{
  "type": "Feature",
  "properties": {
    "gn:admin1_code": "26",
    "gn:asciiname": "Shuangquan",
    "gn:cc2": "CN",
    "gn:country_code": "CN",
    "gn:dem": 405,
    "gn:feature_class": "P",
    "gn:feature_code": "PPL",
    "gn:name": "Shuangquan",
    "gn:population": 0,
    "gn:timezone": "Asia/Shanghai",
    "iso:country": "CN",
    "name:und_x_variant": [
      "Shuang-ch’üan-chen",
      "Shuang-ch’üan",
      "Shuangquan"
    ],
    "wof:name": "Shuangquan",
    "wof:placetype": "locality"
  },
  "geometry": {
    "coordinates": [
      110.02028,
      34.93944
    ],
    "type": "Point"
  }
}