{
  "type": "Feature",
  "properties": {
    "gn:admin1_code": "16",
    "gn:asciiname": "Dazhou",
    "gn:country_code": "CN",
    "gn:dem": 72,
    "gn:feature_class": "P",
    "gn:feature_code": "PPL",
    "gn:name": "Dazhou",
    "gn:population": 0,
    "gn:timezone": "Asia/Shanghai",
    "iso:country": "CN",
    "name:ara_x_preferred": [
      "داتشو"
    ],
    "name:cdo_x_preferred": [
      "Dăk-ciŭ"
    ],
    "name:ceb_x_preferred": [
      "Dazhou"
    ],
    "name:ces_x_preferred": [
      "Ta-čou"
    ],
    "name:dan_x_preferred": [
      "Dazhou"
    ],
    "name:deu_x_preferred": [
      "Dazhou"
    ],
    "name:eus_x_preferred": [
      "Dazhou"
    ],
    "name:fas_x_preferred": [
      "داژو"
    ],
    "name:fin_x_preferred": [
      "Dazhou"
    ],
    "name:fra_x_preferred": [
      "Dazhou"
    ],
    "name:hak_x_preferred": [
      "Tha̍t-chû-sṳ"
    ],
    "name:ita_x_preferred": [
      "Dazhou"
    ],
    "name:jpn_x_preferred": [
      "達州市"
    ],
    "name:kaz_x_preferred": [
      "Дачжоу"
    ],
    "name:kik_x_preferred": [
      "Dazhou"
    ],
    "name:kor_x_preferred": [
      "다저우시"
    ],
    "name:mlg_x_preferred": [
      "Dazhou"
    ],
    "name:nld_x_preferred": [
      "Dazhou"
    ],
    "name:nno_x_preferred": [
      "Dazhou"
    ],
    "name:nor_x_preferred": [
      "Dazhou"
    ],
    "name:pol_x_preferred": [
      "Dazhou"
    ],
    "name:rus_x_preferred": [
      "Дачжоу"
    ],
    "name:spa_x_preferred": [
      "Dazhou"
    ],
    "name:swe_x_preferred": [
      "Dazhou"
    ],
    "name:tur_x_preferred": [
      "Dazhou"
    ],
    "name:urd_x_preferred": [
      "داژوو"
    ],
    "name:vie_x_preferred": [
      "Đạt Châu"
    ],
    "name:war_x_preferred": [
      "Dazhou"
    ],
    "name:wuu_x_preferred": [
      "达州市"
    ],
    "name:zho_x_preferred": [
      "达州市"
    ],
    "wof:name": "Dazhou",
    "wof:placetype": "locality"
  },
  "geometry": {
    "coordinates": [
      110.5925,
      23.27056
    ],
    "type": "Point"
  }
}