{
  "type": "Feature",
  "properties": {
    "gn:admin1_code": "12.0",
    "gn:asciiname": "Fengchuiling",
    "gn:country_code": "CN",
    "gn:dem": 840,
    "gn:feature_class": "P",
    "gn:feature_code": "PPL",
    "gn:name": "Fengchuiling",
    "gn:population": 0,
    "gn:timezone": "Asia/Shanghai",
    "iso:country": "CN",
    "name:zho_x_preferred": [
      "风吹岭"
    ],
    "wof:name": "Fengchuiling",
    "wof:placetype": "locality"
  },
  "geometry": {
    "coordinates": [
      109.65145,
      30.56397
    ],
    "type": "Point"
  }
}