{
  "type": "Feature",
  "properties": {
    "gn:admin1_code": "3",
    "gn:asciiname": "Chuzhou",
    "gn:country_code": "CN",
    "gn:dem": 363,
    "gn:feature_class": "P",
    "gn:feature_code": "PPL",
    "gn:name": "Chuzhou",
    "gn:population": 0,
    "gn:timezone": "Asia/Shanghai",
    "iso:country": "CN",
    "name:afr_x_preferred": [
      "Chuzhou"
    ],
    "name:ara_x_preferred": [
      "شوزو"
    ],
    "name:bre_x_preferred": [
      "Chuzhou"
    ],
    "name:bul_x_preferred": [
      "Чуджоу"
    ],
    "name:cdo_x_preferred": [
      "Dṳ̀-ciŭ"
    ],
    "name:ceb_x_preferred": [
      "Chuzhou Shi"
    ],
    "name:ces_x_preferred": [
      "Čchu-čou"
    ],
    "name:cym_x_preferred": [
      "Chuzhou"
    ],
    "name:dan_x_preferred": [
      "Chuzhou"
    ],
    "name:deu_x_preferred": [
      "Chuzhou"
    ],
    "name:eus_x_preferred": [
      "Chuzhou"
    ],
    "name:fas_x_preferred": [
      "چاجوا"
    ],
    "name:fin_x_preferred": [
      "Chuzhou"
    ],
    "name:fra_x_preferred": [
      "Chuzhou"
    ],
    "name:hye_x_preferred": [
      "Չուչժոու"
    ],
    "name:ita_x_preferred": [
      "Chuzhou"
    ],
    "name:jpn_x_preferred": [
      "ジョ州市"
    ],
    "name:kik_x_preferred": [
      "Chuzhou"
    ],
    "name:kor_x_preferred": [
      "추저우시"
    ],
    "name:mlg_x_preferred": [
      "Chuzhou"
    ],
    "name:nld_x_preferred": [
      "Chuzhou"
    ],
    "name:nno_x_preferred": [
      "Chuzhou"
    ],
    "name:nor_x_preferred": [
      "Chuzhou"
    ],
    "name:pam_x_preferred": [
      "Chuzhou"
    ],
    "name:pnb_x_preferred": [
      "چوژوؤ"
    ],
    "name:pol_x_preferred": [
      "Chuzhou"
    ],
    "name:por_x_preferred": [
      "Chuzhou"
    ],
    "name:rus_x_preferred": [
      "Чучжоу"
    ],
    "name:spa_x_preferred": [
      "Chuzhou"
    ],
    "name:srp_x_preferred": [
      "Чуџоу"
    ],
    "name:swe_x_preferred": [
      "Chuzhou"
    ],
    "name:tgl_x_preferred": [
      "Chuzhou"
    ],
    "name:tur_x_preferred": [
      "Chuzhou"
    ],
    "name:uig_x_preferred": [
      "Chuju shehiri"
    ],
    "name:urd_x_preferred": [
      "چوژوو"
    ],
    "name:vie_x_preferred": [
      "Trừ Châu"
    ],
    "name:war_x_preferred": [
      "Chuzhou"
    ],
    "name:wuu_x_preferred": [
      "滁州市"
    ],
    "name:zho_x_preferred": [
      "滁洲"
    ],
    "name:zho_x_variant": [
      "滁州市"
    ],
    "wof:name": "Chuzhou",
    "wof:placetype": "locality"
  },
  "geometry": {
    "coordinates": [
      114.13299,
      26.33388
    ],
    "type": "Point"
  }
}