{
  "type": "Feature",
  "properties": {
    "gn:admin1_code": "4.0",
    "gn:asciiname": "Gongjia",
    "gn:country_code": "CN",
    "gn:dem": 7,
    "gn:feature_class": "P",
    "gn:feature_code": "PPL",
    "gn:name": "Gongjia",
    "gn:population": 0,
    "gn:timezone": "Asia/Shanghai",
    "iso:country": "CN",
    "name:zho_x_preferred": [
      "贡家"
    ],
    "wof:name": "Gongjia",
    "wof:placetype": "locality"
  },
  "geometry": {
    "coordinates": [
      119.74706,
      32.10882
    ],
    "type": "Point"
  }
}