{
  "type": "Feature",
  "properties": {
    "gn:admin1_code": "30.0",
    "gn:asciiname": "Gongqiao",
    "gn:country_code": "CN",
    "gn:dem": 44,
    "gn:feature_class": "P",
    "gn:feature_code": "PPL",
    "gn:name": "Gongqiao",
    "gn:population": 0,
    "gn:timezone": "Asia/Shanghai",
    "iso:country": "CN",
    "name:zho_x_preferred": [
      "拱桥"
    ],
    "wof:name": "Gongqiao",
    "wof:placetype": "locality"
  },
  "geometry": {
    "coordinates": [
      111.4929,
      22.02066
    ],
    "type": "Point"
  }
}