{
  "type": "Feature",
  "properties": {
    "gn:admin1_code": "5.0",
    "gn:asciiname": "Ji'anxian Renao Linchang",
    "gn:country_code": "CN",
    "gn:dem": 733,
    "gn:feature_class": "P",
    "gn:feature_code": "PPLF",
    "gn:name": "Ji’anxian Renao Linchang",
    "gn:population": 0,
    "gn:timezone": "Asia/Shanghai",
    "iso:country": "CN",
    "name:und_x_variant": [
      "Ji’anxian Renao Linchang",
      "集安县热闹林场"
    ],
    "wof:name": "Ji'anxian Renao Linchang",
    "wof:placetype": "locality"
  },
  "geometry": {
    "coordinates": [
      126.11123,
      41.38535
    ],
    "type": "Point"
  }
}