{
  "type": "Feature",
  "properties": {
    "gn:admin1_code": "32.0",
    "gn:asciiname": "Nie'erlaiji",
    "gn:country_code": "CN",
    "gn:dem": 2617,
    "gn:feature_class": "P",
    "gn:feature_code": "PPL",
    "gn:name": "Nie’erlaiji",
    "gn:population": 0,
    "gn:timezone": "Asia/Shanghai",
    "iso:country": "CN",
    "name:und_x_variant": [
      "Nie’erlaiji"
    ],
    "name:zho_x_preferred": [
      "涅尔来及"
    ],
    "wof:name": "Nie'erlaiji",
    "wof:placetype": "locality"
  },
  "geometry": {
    "coordinates": [
      102.856,
      27.662
    ],
    "type": "Point"
  }
}