{
  "type": "Feature",
  "properties": {
    "gn:admin1_code": "8.0",
    "gn:asciiname": "Daijiatun",
    "gn:country_code": "CN",
    "gn:dem": 204,
    "gn:feature_class": "P",
    "gn:feature_code": "PPL",
    "gn:name": "Daijiatun",
    "gn:population": 0,
    "gn:timezone": "Asia/Shanghai",
    "iso:country": "CN",
    "name:zho_x_preferred": [
      "戴家屯"
    ],
    "wof:name": "Daijiatun",
    "wof:placetype": "locality"
  },
  "geometry": {
    "coordinates": [
      125.67007,
      47.60799
    ],
    "type": "Point"
  }
}