{
  "type": "Feature",
  "properties": {
    "gn:admin1_code": "16.0",
    "gn:asciiname": "Nali",
    "gn:country_code": "CN",
    "gn:dem": 242,
    "gn:feature_class": "P",
    "gn:feature_code": "PPL",
    "gn:name": "Nali",
    "gn:population": 0,
    "gn:timezone": "Asia/Shanghai",
    "iso:country": "CN",
    "name:ceb_x_preferred": [
      "Nali"
    ],
    "name:swe_x_preferred": [
      "Nali"
    ],
    "name:zho_x_preferred": [
      "那立"
    ],
    "wof:name": "Nali",
    "wof:placetype": "locality"
  },
  "geometry": {
    "coordinates": [
      107.278,
      23.8983
    ],
    "type": "Point"
  }
}