{
  "type": "Feature",
  "properties": {
    "gn:admin1_code": "9",
    "gn:asciiname": "Baoguduibei",
    "gn:country_code": "CN",
    "gn:dem": 43,
    "gn:feature_class": "P",
    "gn:feature_code": "PPL",
    "gn:name": "Baoguduibei",
    "gn:population": 0,
    "gn:timezone": "Asia/Shanghai",
    "iso:country": "CN",
    "name:zho_x_preferred": [
      "宝堌堆北"
    ],
    "wof:name": "Baoguduibei",
    "wof:placetype": "locality"
  },
  "geometry": {
    "coordinates": [
      115.341,
      33.8473
    ],
    "type": "Point"
  }
}