{
  "type": "Feature",
  "properties": {
    "gn:admin1_code": "11.0",
    "gn:asciiname": "Youlingchong",
    "gn:country_code": "CN",
    "gn:dem": 311,
    "gn:feature_class": "P",
    "gn:feature_code": "PPL",
    "gn:name": "Youlingchong",
    "gn:population": 0,
    "gn:timezone": "Asia/Shanghai",
    "iso:country": "CN",
    "name:zho_x_preferred": [
      "油岭冲"
    ],
    "wof:name": "Youlingchong",
    "wof:placetype": "locality"
  },
  "geometry": {
    "coordinates": [
      110.94189,
      27.00398
    ],
    "type": "Point"
  }
}