{
  "type": "Feature",
  "properties": {
    "gn:admin1_code": "4.0",
    "gn:asciiname": "Jingtailu",
    "gn:country_code": "CN",
    "gn:dem": 7,
    "gn:feature_class": "P",
    "gn:feature_code": "PPLA4",
    "gn:name": "Jingtailu",
    "gn:population": 0,
    "gn:timezone": "Asia/Shanghai",
    "iso:country": "CN",
    "name:und_x_variant": [
      "Jiuliqiao",
      "九里桥",
      "Taidong",
      "Taidong Zhen",
      "泰东",
      "泰东镇",
      "Jingtailu",
      "Jingtailu Jiedao"
    ],
    "name:zho_x_preferred": [
      "京泰路"
    ],
    "name:zho_x_variant": [
      "京泰路街道"
    ],
    "wof:name": "Jingtailu",
    "wof:placetype": "locality"
  },
  "geometry": {
    "coordinates": [
      119.97173,
      32.50471
    ],
    "type": "Point"
  }
}