{
  "type": "Feature",
  "properties": {
    "gn:admin1_code": "22.0",
    "gn:asciiname": "Dongying",
    "gn:country_code": "CN",
    "gn:dem": 30,
    "gn:feature_class": "P",
    "gn:feature_code": "PPL",
    "gn:name": "Dongying",
    "gn:population": 0,
    "gn:timezone": "Asia/Shanghai",
    "iso:country": "CN",
    "name:afr_x_preferred": [
      "Dongying"
    ],
    "name:ara_x_preferred": [
      "دونغ ينغ"
    ],
    "name:cdo_x_preferred": [
      "Dĕ̤ng-ìng"
    ],
    "name:ces_x_preferred": [
      "Tung-jing"
    ],
    "name:dan_x_preferred": [
      "Dongying"
    ],
    "name:deu_x_preferred": [
      "Dongying"
    ],
    "name:eus_x_preferred": [
      "Dongying"
    ],
    "name:fas_x_preferred": [
      "دونجینگ"
    ],
    "name:fin_x_preferred": [
      "Dongying"
    ],
    "name:fra_x_preferred": [
      "Dongying"
    ],
    "name:ind_x_preferred": [
      "Dongying"
    ],
    "name:ita_x_preferred": [
      "Dongying"
    ],
    "name:jpn_x_preferred": [
      "東営市"
    ],
    "name:kik_x_preferred": [
      "Dongying"
    ],
    "name:kor_x_preferred": [
      "둥잉시"
    ],
    "name:nld_x_preferred": [
      "Dongying"
    ],
    "name:nno_x_preferred": [
      "Dongying"
    ],
    "name:nor_x_preferred": [
      "Dongying"
    ],
    "name:pol_x_preferred": [
      "Dongying"
    ],
    "name:por_x_preferred": [
      "Dongying"
    ],
    "name:rus_x_preferred": [
      "Дунъин"
    ],
    "name:spa_x_preferred": [
      "Dongying"
    ],
    "name:srp_x_preferred": [
      "Дунгјинг"
    ],
    "name:swe_x_preferred": [
      "Dongying"
    ],
    "name:tgl_x_preferred": [
      "Dongying"
    ],
    "name:tur_x_preferred": [
      "Dongying"
    ],
    "name:urd_x_preferred": [
      "ڈونگینگ"
    ],
    "name:vie_x_preferred": [
      "Đông Dinh"
    ],
    "name:war_x_preferred": [
      "Dongying"
    ],
    "name:wuu_x_preferred": [
      "东营市"
    ],
    "name:zho_x_preferred": [
      "东营"
    ],
    "name:zho_x_variant": [
      "东营市"
    ],
    "wof:name": "Dongying",
    "wof:placetype": "locality"
  },
  "geometry": {
    "coordinates": [
      116.76132,
      40.07216
    ],
    "type": "Point"
  }
}