{
  "type": "Feature",
  "properties": {
    "gn:admin1_code": "14",
    "gn:asciiname": "Gangga",
    "gn:country_code": "CN",
    "gn:dem": 4055,
    "gn:feature_class": "P",
    "gn:feature_code": "PPL",
    "gn:name": "Gangga",
    "gn:population": 0,
    "gn:timezone": "Asia/Urumqi",
    "iso:country": "CN",
    "name:ceb_x_preferred": [
      "Gangga"
    ],
    "name:ind_x_preferred": [
      "Gangga"
    ],
    "name:jav_x_preferred": [
      "Gangga"
    ],
    "name:swe_x_preferred": [
      "Gangga"
    ],
    "name:zho_x_preferred": [
      "岗嘎"
    ],
    "wof:name": "Gangga",
    "wof:placetype": "locality"
  },
  "geometry": {
    "coordinates": [
      89.4981,
      29.4336
    ],
    "type": "Point"
  }
}