{
  "type": "Feature",
  "properties": {
    "gn:admin1_code": "26.0",
    "gn:asciiname": "Heyicun",
    "gn:country_code": "CN",
    "gn:dem": 358,
    "gn:feature_class": "P",
    "gn:feature_code": "PPL",
    "gn:name": "Heyicun",
    "gn:population": 0,
    "gn:timezone": "Asia/Shanghai",
    "iso:country": "CN",
    "name:zho_x_preferred": [
      "合义村"
    ],
    "wof:name": "Heyicun",
    "wof:placetype": "locality"
  },
  "geometry": {
    "coordinates": [
      109.77926,
      34.73027
    ],
    "type": "Point"
  }
}