{
  "type": "Feature",
  "properties": {
    "gn:admin1_code": "16.0",
    "gn:asciiname": "Jiangtou",
    "gn:country_code": "CN",
    "gn:dem": 411,
    "gn:feature_class": "P",
    "gn:feature_code": "PPL",
    "gn:name": "Jiangtou",
    "gn:population": 0,
    "gn:timezone": "Asia/Shanghai",
    "iso:country": "CN",
    "name:zho_x_preferred": [
      "江头"
    ],
    "wof:name": "Jiangtou",
    "wof:placetype": "locality"
  },
  "geometry": {
    "coordinates": [
      107.699,
      24.6942
    ],
    "type": "Point"
  }
}