{
  "type": "Feature",
  "properties": {
    "gn:admin1_code": "12.0",
    "gn:asciiname": "Dongwan",
    "gn:country_code": "CN",
    "gn:dem": 42,
    "gn:feature_class": "P",
    "gn:feature_code": "PPL",
    "gn:name": "Dongwan",
    "gn:population": 0,
    "gn:timezone": "Asia/Shanghai",
    "iso:country": "CN",
    "name:deu_x_preferred": [
      "Dongwan"
    ],
    "name:und_x_variant": [
      "董塆"
    ],
    "wof:name": "Dongwan",
    "wof:placetype": "locality"
  },
  "geometry": {
    "coordinates": [
      115.35435,
      30.25102
    ],
    "type": "Point"
  }
}