{
  "type": "Feature",
  "properties": {
    "gn:admin1_code": "32.0",
    "gn:asciiname": "Yong'an",
    "gn:country_code": "CN",
    "gn:dem": 331,
    "gn:feature_class": "P",
    "gn:feature_code": "PPL",
    "gn:name": "Yong’an",
    "gn:population": 0,
    "gn:timezone": "Asia/Shanghai",
    "iso:country": "CN",
    "name:ara_x_preferred": [
      "يانغان"
    ],
    "name:cdo_x_preferred": [
      "Īng-ăng"
    ],
    "name:deu_x_preferred": [
      "Yong’an"
    ],
    "name:fas_x_preferred": [
      "یانگان"
    ],
    "name:fra_x_preferred": [
      "Yong'an"
    ],
    "name:hak_x_preferred": [
      "Yún-ôn-sṳ"
    ],
    "name:ita_x_preferred": [
      "Yong'an"
    ],
    "name:jpn_x_preferred": [
      "永安市"
    ],
    "name:kik_x_preferred": [
      "Yong'an"
    ],
    "name:kor_x_preferred": [
      "융안시"
    ],
    "name:mlg_x_preferred": [
      "Yong'an"
    ],
    "name:nor_x_preferred": [
      "Yong'an"
    ],
    "name:pam_x_preferred": [
      "Yong'an"
    ],
    "name:pnb_x_preferred": [
      "یونگ آن"
    ],
    "name:por_x_preferred": [
      "Yong'an"
    ],
    "name:spa_x_preferred": [
      "Yŏng'ān Shì"
    ],
    "name:swe_x_preferred": [
      "Yong'an"
    ],
    "name:urd_x_preferred": [
      "یونگان"
    ],
    "name:vie_x_preferred": [
      "Vĩnh An"
    ],
    "name:war_x_preferred": [
      "Yongan"
    ],
    "name:zho_x_preferred": [
      "永安"
    ],
    "name:zho_x_variant": [
      "Yong’an",
      "永安市"
    ],
    "wof:name": "Yong'an",
    "wof:placetype": "locality"
  },
  "geometry": {
    "coordinates": [
      104.92767,
      29.51895
    ],
    "type": "Point"
  }
}