{
  "type": "Feature",
  "properties": {
    "gn:admin1_code": "29.0",
    "gn:asciiname": "Longma",
    "gn:country_code": "CN",
    "gn:dem": 840,
    "gn:feature_class": "P",
    "gn:feature_code": "PPL",
    "gn:name": "Longma",
    "gn:population": 0,
    "gn:timezone": "Asia/Shanghai",
    "iso:country": "CN",
    "name:cat_x_preferred": [
      "Longma"
    ],
    "name:fra_x_preferred": [
      "Longma"
    ],
    "name:msa_x_preferred": [
      "Longma"
    ],
    "name:rus_x_preferred": [
      "Лунма"
    ],
    "name:ukr_x_preferred": [
      "Лунма"
    ],
    "name:und_x_variant": [
      "龙马"
    ],
    "wof:name": "Longma",
    "wof:placetype": "locality"
  },
  "geometry": {
    "coordinates": [
      104.99783,
      28.05456
    ],
    "type": "Point"
  }
}