{
  "type": "Feature",
  "properties": {
    "gn:admin1_code": "8.0",
    "gn:asciiname": "Xincun Ershi'erhao",
    "gn:country_code": "CN",
    "gn:dem": 167,
    "gn:feature_class": "P",
    "gn:feature_code": "PPLF",
    "gn:name": "Xincun Ershi’erhao",
    "gn:population": 0,
    "gn:timezone": "Asia/Shanghai",
    "iso:country": "CN",
    "name:und_x_variant": [
      "Xincun Ershi’erhao"
    ],
    "name:zho_x_preferred": [
      "新村二十二号"
    ],
    "wof:name": "Xincun Ershi'erhao",
    "wof:placetype": "locality"
  },
  "geometry": {
    "coordinates": [
      125.18172,
      47.4172
    ],
    "type": "Point"
  }
}