{
  "type": "Feature",
  "properties": {
    "gn:admin1_code": "33",
    "gn:asciiname": "Yanshan",
    "gn:country_code": "CN",
    "gn:dem": 321,
    "gn:feature_class": "P",
    "gn:feature_code": "PPLA4",
    "gn:name": "Yanshan",
    "gn:population": 0,
    "gn:timezone": "Asia/Shanghai",
    "iso:country": "CN",
    "name:ceb_x_preferred": [
      "Yanshan"
    ],
    "name:deu_x_preferred": [
      "Yanshan"
    ],
    "name:fra_x_preferred": [
      "Yanshan"
    ],
    "name:nor_x_preferred": [
      "Yanshan"
    ],
    "name:rus_x_preferred": [
      "Яньшань"
    ],
    "name:swe_x_preferred": [
      "Yanshan"
    ],
    "name:und_x_variant": [
      "Yanshan Xiang",
      "Xiaxingchang"
    ],
    "name:zho_x_preferred": [
      "燕山"
    ],
    "name:zho_x_variant": [
      "燕山乡",
      "夏兴场"
    ],
    "wof:name": "Yanshan",
    "wof:placetype": "locality"
  },
  "geometry": {
    "coordinates": [
      108.30908,
      30.55435
    ],
    "type": "Point"
  }
}