{
  "type": "Feature",
  "properties": {
    "gn:admin1_code": "29.0",
    "gn:asciiname": "Yubeng",
    "gn:country_code": "CN",
    "gn:dem": 2848,
    "gn:feature_class": "P",
    "gn:feature_code": "PPL",
    "gn:name": "Yubeng",
    "gn:population": 0,
    "gn:timezone": "Asia/Shanghai",
    "iso:country": "CN",
    "name:zho_x_preferred": [
      "雨崩"
    ],
    "wof:name": "Yubeng",
    "wof:placetype": "locality"
  },
  "geometry": {
    "coordinates": [
      98.8162,
      28.3791
    ],
    "type": "Point"
  }
}