{
  "type": "Feature",
  "properties": {
    "gn:admin1_code": "16.0",
    "gn:asciiname": "Longyi",
    "gn:country_code": "CN",
    "gn:dem": 328,
    "gn:feature_class": "P",
    "gn:feature_code": "PPL",
    "gn:name": "Longyi",
    "gn:population": 0,
    "gn:timezone": "Asia/Shanghai",
    "iso:country": "CN",
    "name:aze_x_preferred": [
      "Londji"
    ],
    "name:deu_x_preferred": [
      "Longyi"
    ],
    "name:fin_x_preferred": [
      "Longyi"
    ],
    "name:fra_x_preferred": [
      "Longyi"
    ],
    "name:hye_x_preferred": [
      "Լոնջի"
    ],
    "name:ind_x_preferred": [
      "Longyi"
    ],
    "name:ita_x_preferred": [
      "Longyi"
    ],
    "name:jpn_x_preferred": [
      "ロンジー"
    ],
    "name:mya_x_preferred": [
      "လုံချည်"
    ],
    "name:rus_x_preferred": [
      "Лонджи"
    ],
    "name:zho_x_preferred": [
      "龙益"
    ],
    "wof:name": "Longyi",
    "wof:placetype": "locality"
  },
  "geometry": {
    "coordinates": [
      107.292,
      22.8898
    ],
    "type": "Point"
  }
}