{
  "type": "Feature",
  "properties": {
    "gn:admin1_code": "30.0",
    "gn:asciiname": "Qintou",
    "gn:country_code": "CN",
    "gn:dem": 6,
    "gn:feature_class": "P",
    "gn:feature_code": "PPL",
    "gn:name": "Qintou",
    "gn:population": 0,
    "gn:timezone": "Asia/Shanghai",
    "iso:country": "CN",
    "name:zho_x_preferred": [
      "钦头"
    ],
    "wof:name": "Qintou",
    "wof:placetype": "locality"
  },
  "geometry": {
    "coordinates": [
      112.95369,
      21.887
    ],
    "type": "Point"
  }
}