{
  "type": "Feature",
  "properties": {
    "gn:admin1_code": "16.0",
    "gn:asciiname": "Nalong",
    "gn:country_code": "CN",
    "gn:dem": 660,
    "gn:feature_class": "P",
    "gn:feature_code": "PPL",
    "gn:name": "Nalong",
    "gn:population": 0,
    "gn:timezone": "Asia/Shanghai",
    "iso:country": "CN",
    "name:jpn_x_preferred": [
      "トゥルトゥルトゥ ナロンイ"
    ],
    "name:kor_x_preferred": [
      "뚜루뚜루뚜 나롱이"
    ],
    "name:tha_x_preferred": [
      "นาลอง กระรอกน้อยเหินฟ้า"
    ],
    "name:zho_x_preferred": [
      "纳龙"
    ],
    "wof:name": "Nalong",
    "wof:placetype": "locality"
  },
  "geometry": {
    "coordinates": [
      107.074,
      25.3318
    ],
    "type": "Point"
  }
}