{
  "type": "Feature",
  "properties": {
    "gn:admin1_code": "12.0",
    "gn:asciiname": "Tianjiuwan",
    "gn:country_code": "CN",
    "gn:dem": 54,
    "gn:feature_class": "P",
    "gn:feature_code": "PPL",
    "gn:name": "Tianjiuwan",
    "gn:population": 0,
    "gn:timezone": "Asia/Shanghai",
    "iso:country": "CN",
    "name:und_x_variant": [
      "天九塆"
    ],
    "wof:name": "Tianjiuwan",
    "wof:placetype": "locality"
  },
  "geometry": {
    "coordinates": [
      115.23153,
      30.36286
    ],
    "type": "Point"
  }
}