{
  "type": "Feature",
  "properties": {
    "gn:admin1_code": "6.0",
    "gn:asciiname": "Ri'agou",
    "gn:country_code": "CN",
    "gn:dem": 3742,
    "gn:feature_class": "P",
    "gn:feature_code": "PPL",
    "gn:name": "Ri’agou",
    "gn:population": 0,
    "gn:timezone": "Asia/Urumqi",
    "iso:country": "CN",
    "name:und_x_variant": [
      "Ri’agou"
    ],
    "name:zho_x_preferred": [
      "日阿沟"
    ],
    "wof:name": "Ri'agou",
    "wof:placetype": "locality"
  },
  "geometry": {
    "coordinates": [
      96.77296,
      33.40176
    ],
    "type": "Point"
  }
}