{
  "type": "Feature",
  "properties": {
    "gn:admin1_code": "12.0",
    "gn:asciiname": "Nanying Jiahaopo",
    "gn:country_code": "CN",
    "gn:dem": 31,
    "gn:feature_class": "P",
    "gn:feature_code": "PPL",
    "gn:name": "Nanying Jiahaopo",
    "gn:population": 0,
    "gn:timezone": "Asia/Shanghai",
    "iso:country": "CN",
    "name:zho_x_preferred": [
      "南应家壕坡"
    ],
    "wof:name": "Nanying Jiahaopo",
    "wof:placetype": "locality"
  },
  "geometry": {
    "coordinates": [
      112.39047,
      30.1834
    ],
    "type": "Point"
  }
}