{
  "type": "Feature",
  "properties": {
    "gn:admin1_code": "19.0",
    "gn:asciiname": "Liujiatai",
    "gn:country_code": "CN",
    "gn:dem": 343,
    "gn:feature_class": "P",
    "gn:feature_code": "PPL",
    "gn:name": "Liujiatai",
    "gn:population": 0,
    "gn:timezone": "Asia/Shanghai",
    "iso:country": "CN",
    "name:und_x_variant": [
      "刘家台"
    ],
    "wof:name": "Liujiatai",
    "wof:placetype": "locality"
  },
  "geometry": {
    "coordinates": [
      122.87937,
      40.42926
    ],
    "type": "Point"
  }
}