{
  "type": "Feature",
  "properties": {
    "gn:admin1_code": "2",
    "gn:asciiname": "Yanxia Xiacun",
    "gn:country_code": "CN",
    "gn:dem": 147,
    "gn:feature_class": "P",
    "gn:feature_code": "PPL",
    "gn:name": "Yanxia Xiacun",
    "gn:population": 0,
    "gn:timezone": "Asia/Shanghai",
    "iso:country": "CN",
    "name:und_x_variant": [
      "Yanxia",
      "Yanxia Xiacun"
    ],
    "name:zho_x_preferred": [
      "岩下下村"
    ],
    "name:zho_x_variant": [
      "岩下"
    ],
    "wof:name": "Yanxia Xiacun",
    "wof:placetype": "locality"
  },
  "geometry": {
    "coordinates": [
      118.58741,
      28.78445
    ],
    "type": "Point"
  }
}