{
  "type": "Feature",
  "properties": {
    "gn:admin1_code": "32.0",
    "gn:asciiname": "Jinyuqiao",
    "gn:country_code": "CN",
    "gn:dem": 419,
    "gn:feature_class": "P",
    "gn:feature_code": "PPL",
    "gn:name": "Jinyuqiao",
    "gn:population": 0,
    "gn:timezone": "Asia/Shanghai",
    "iso:country": "CN",
    "name:zho_x_preferred": [
      "金鱼桥"
    ],
    "wof:name": "Jinyuqiao",
    "wof:placetype": "locality"
  },
  "geometry": {
    "coordinates": [
      105.48753,
      31.16068
    ],
    "type": "Point"
  }
}