{
  "type": "Feature",
  "properties": {
    "gn:admin1_code": "7.0",
    "gn:asciiname": "Shangcun",
    "gn:country_code": "CN",
    "gn:dem": 411,
    "gn:feature_class": "P",
    "gn:feature_code": "PPL",
    "gn:name": "Shangcun",
    "gn:population": 0,
    "gn:timezone": "Asia/Shanghai",
    "iso:country": "CN",
    "name:zho_x_preferred": [
      "上村"
    ],
    "wof:name": "Shangcun",
    "wof:placetype": "locality"
  },
  "geometry": {
    "coordinates": [
      118.10069,
      26.87327
    ],
    "type": "Point"
  }
}