{
  "type": "Feature",
  "properties": {
    "gn:admin1_code": "10.0",
    "gn:asciiname": "Nandi",
    "gn:country_code": "CN",
    "gn:dem": 8,
    "gn:feature_class": "P",
    "gn:feature_code": "PPL",
    "gn:name": "Nandi",
    "gn:population": 0,
    "gn:timezone": "Asia/Shanghai",
    "iso:country": "CN",
    "name:bar_x_preferred": [
      "Nandi"
    ],
    "name:ben_x_preferred": [
      "নান্দি"
    ],
    "name:ceb_x_preferred": [
      "Nandi"
    ],
    "name:deu_x_preferred": [
      "Nandi"
    ],
    "name:fra_x_preferred": [
      "Nandi"
    ],
    "name:hrv_x_preferred": [
      "Nandi"
    ],
    "name:hun_x_preferred": [
      "Nandi"
    ],
    "name:ind_x_preferred": [
      "Nandi"
    ],
    "name:nld_x_preferred": [
      "Nandi"
    ],
    "name:pol_x_preferred": [
      "Nandi"
    ],
    "name:rus_x_preferred": [
      "Нанди"
    ],
    "name:swe_x_preferred": [
      "Nandi"
    ],
    "name:tur_x_preferred": [
      "Nandi"
    ],
    "name:ukr_x_preferred": [
      "Нанді"
    ],
    "name:urd_x_preferred": [
      "نندی"
    ],
    "name:vie_x_preferred": [
      "Nandi"
    ],
    "name:zho_x_preferred": [
      "南堤"
    ],
    "wof:name": "Nandi",
    "wof:placetype": "locality"
  },
  "geometry": {
    "coordinates": [
      117.079,
      38.4616
    ],
    "type": "Point"
  }
}