{
  "type": "Feature",
  "properties": {
    "gn:admin1_code": "24.0",
    "gn:asciiname": "Chaisi",
    "gn:country_code": "CN",
    "gn:dem": 422,
    "gn:feature_class": "P",
    "gn:feature_code": "PPL",
    "gn:name": "Chaisi",
    "gn:population": 0,
    "gn:timezone": "Asia/Shanghai",
    "iso:country": "CN",
    "name:und_x_variant": [
      "柴寺"
    ],
    "wof:name": "Chaisi",
    "wof:placetype": "locality"
  },
  "geometry": {
    "coordinates": [
      111.41777,
      35.8656
    ],
    "type": "Point"
  }
}