{
  "type": "Feature",
  "properties": {
    "gn:admin1_code": "15.0",
    "gn:asciiname": "Majia Kouzi",
    "gn:country_code": "CN",
    "gn:dem": 1829,
    "gn:feature_class": "P",
    "gn:feature_code": "PPL",
    "gn:name": "Majia Kouzi",
    "gn:population": 0,
    "gn:timezone": "Asia/Shanghai",
    "iso:country": "CN",
    "name:zho_x_preferred": [
      "马家口子"
    ],
    "wof:name": "Majia Kouzi",
    "wof:placetype": "locality"
  },
  "geometry": {
    "coordinates": [
      106.671,
      37.0493
    ],
    "type": "Point"
  }
}