{
  "type": "Feature",
  "properties": {
    "gn:admin1_code": "3.0",
    "gn:asciiname": "Yujiashan Liujia",
    "gn:country_code": "CN",
    "gn:dem": 101,
    "gn:feature_class": "P",
    "gn:feature_code": "PPL",
    "gn:name": "Yujiashan Liujia",
    "gn:population": 0,
    "gn:timezone": "Asia/Shanghai",
    "iso:country": "CN",
    "name:und_x_variant": [
      "喻家山刘家"
    ],
    "wof:name": "Yujiashan Liujia",
    "wof:placetype": "locality"
  },
  "geometry": {
    "coordinates": [
      115.68803,
      29.47748
    ],
    "type": "Point"
  }
}