{
  "type": "Feature",
  "properties": {
    "gn:admin1_code": "16",
    "gn:asciiname": "Jinjiang",
    "gn:country_code": "CN",
    "gn:dem": 349,
    "gn:feature_class": "P",
    "gn:feature_code": "PPL",
    "gn:name": "Jinjiang",
    "gn:population": 0,
    "gn:timezone": "Asia/Shanghai",
    "iso:country": "CN",
    "name:ceb_x_preferred": [
      "Jinjiang"
    ],
    "name:ces_x_preferred": [
      "Ťin-ťiang"
    ],
    "name:deu_x_preferred": [
      "Jinjiang"
    ],
    "name:fra_x_preferred": [
      "Jinjiang"
    ],
    "name:mlg_x_preferred": [
      "Jinjiang"
    ],
    "name:nor_x_preferred": [
      "Jinjiang"
    ],
    "name:rus_x_preferred": [
      "Цзиньцзян"
    ],
    "name:swe_x_preferred": [
      "Jinjiang"
    ],
    "name:zho_x_preferred": [
      "金江"
    ],
    "wof:name": "Jinjiang",
    "wof:placetype": "locality"
  },
  "geometry": {
    "coordinates": [
      110.112,
      25.735
    ],
    "type": "Point"
  }
}