{
  "type": "Feature",
  "properties": {
    "gn:admin1_code": "16.0",
    "gn:asciiname": "Songxing",
    "gn:country_code": "CN",
    "gn:dem": 644,
    "gn:feature_class": "P",
    "gn:feature_code": "PPL",
    "gn:name": "Songxing",
    "gn:population": 0,
    "gn:timezone": "Asia/Shanghai",
    "iso:country": "CN",
    "name:zho_x_preferred": [
      "松杏"
    ],
    "wof:name": "Songxing",
    "wof:placetype": "locality"
  },
  "geometry": {
    "coordinates": [
      109.234,
      25.4959
    ],
    "type": "Point"
  }
}