{
  "type": "Feature",
  "properties": {
    "gn:admin1_code": "4.0",
    "gn:asciiname": "Zhangnian",
    "gn:country_code": "CN",
    "gn:dem": 8,
    "gn:feature_class": "P",
    "gn:feature_code": "PPL",
    "gn:name": "Zhangnian",
    "gn:population": 0,
    "gn:timezone": "Asia/Shanghai",
    "iso:country": "CN",
    "name:zho_x_preferred": [
      "张埝"
    ],
    "wof:name": "Zhangnian",
    "wof:placetype": "locality"
  },
  "geometry": {
    "coordinates": [
      119.73757,
      31.79345
    ],
    "type": "Point"
  }
}