{
  "type": "Feature",
  "properties": {
    "gn:admin1_code": "26.0",
    "gn:asciiname": "Xiaozhai",
    "gn:country_code": "CN",
    "gn:dem": 356,
    "gn:feature_class": "P",
    "gn:feature_code": "PPL",
    "gn:name": "Xiaozhai",
    "gn:population": 0,
    "gn:timezone": "Asia/Shanghai",
    "iso:country": "CN",
    "name:zho_x_preferred": [
      "小寨"
    ],
    "wof:name": "Xiaozhai",
    "wof:placetype": "locality"
  },
  "geometry": {
    "coordinates": [
      109.65215,
      34.72245
    ],
    "type": "Point"
  }
}