{
  "type": "Feature",
  "properties": {
    "gn:admin1_code": "19.0",
    "gn:asciiname": "Wangjiatun",
    "gn:country_code": "CN",
    "gn:dem": 124,
    "gn:feature_class": "P",
    "gn:feature_code": "PPL",
    "gn:name": "Wangjiatun",
    "gn:population": 0,
    "gn:timezone": "Asia/Shanghai",
    "iso:country": "CN",
    "name:zho_x_preferred": [
      "汪家屯"
    ],
    "wof:name": "Wangjiatun",
    "wof:placetype": "locality"
  },
  "geometry": {
    "coordinates": [
      120.17096,
      40.66112
    ],
    "type": "Point"
  }
}