{
  "type": "Feature",
  "properties": {
    "gn:admin1_code": "32.0",
    "gn:asciiname": "Huilong'an",
    "gn:country_code": "CN",
    "gn:dem": 492,
    "gn:feature_class": "P",
    "gn:feature_code": "PPL",
    "gn:name": "Huilong’an",
    "gn:population": 0,
    "gn:timezone": "Asia/Shanghai",
    "iso:country": "CN",
    "name:zho_x_preferred": [
      "回龙庵"
    ],
    "name:zho_x_variant": [
      "Huilong’an"
    ],
    "wof:name": "Huilong'an",
    "wof:placetype": "locality"
  },
  "geometry": {
    "coordinates": [
      103.7774,
      30.34045
    ],
    "type": "Point"
  }
}