{
  "type": "Feature",
  "properties": {
    "gn:admin1_code": "19.0",
    "gn:asciiname": "Dongtai",
    "gn:country_code": "CN",
    "gn:dem": 73,
    "gn:feature_class": "P",
    "gn:feature_code": "PPL",
    "gn:name": "Dongtai",
    "gn:population": 0,
    "gn:timezone": "Asia/Shanghai",
    "iso:country": "CN",
    "name:ceb_x_preferred": [
      "Dongtai Shi"
    ],
    "name:deu_x_preferred": [
      "Dongtai"
    ],
    "name:epo_x_preferred": [
      "Dongtaj"
    ],
    "name:fra_x_preferred": [
      "Dongtai"
    ],
    "name:ita_x_preferred": [
      "Dongtai"
    ],
    "name:jpn_x_preferred": [
      "東台市"
    ],
    "name:kik_x_preferred": [
      "Dongtai"
    ],
    "name:kor_x_preferred": [
      "둥타이시"
    ],
    "name:mlg_x_preferred": [
      "Dongtai"
    ],
    "name:nor_x_preferred": [
      "Dongtai"
    ],
    "name:pam_x_preferred": [
      "Dongtai"
    ],
    "name:rus_x_preferred": [
      "Дунтай"
    ],
    "name:swe_x_preferred": [
      "Dongtai"
    ],
    "name:tgl_x_preferred": [
      "Dongtai"
    ],
    "name:urd_x_preferred": [
      "دونگتائی"
    ],
    "name:vie_x_preferred": [
      "Đông Đài"
    ],
    "name:war_x_preferred": [
      "Dongtai"
    ],
    "name:wuu_x_preferred": [
      "东台市"
    ],
    "name:zho_x_preferred": [
      "东台"
    ],
    "name:zho_x_variant": [
      "东台市"
    ],
    "wof:name": "Dongtai",
    "wof:placetype": "locality"
  },
  "geometry": {
    "coordinates": [
      123.7044,
      41.78811
    ],
    "type": "Point"
  }
}