{
  "type": "Feature",
  "properties": {
    "gn:admin1_code": "16.0",
    "gn:asciiname": "Bade",
    "gn:country_code": "CN",
    "gn:dem": 353,
    "gn:feature_class": "P",
    "gn:feature_code": "PPL",
    "gn:name": "Bade",
    "gn:population": 0,
    "gn:timezone": "Asia/Shanghai",
    "iso:country": "CN",
    "name:ara_x_preferred": [
      "بيد"
    ],
    "name:ben_x_preferred": [
      "বডে"
    ],
    "name:ceb_x_preferred": [
      "Bade"
    ],
    "name:deu_x_preferred": [
      "Bade"
    ],
    "name:ell_x_preferred": [
      "Μπάντε"
    ],
    "name:fas_x_preferred": [
      "باده"
    ],
    "name:fra_x_preferred": [
      "Bade"
    ],
    "name:glg_x_preferred": [
      "Bade"
    ],
    "name:heb_x_preferred": [
      "בדה"
    ],
    "name:hin_x_preferred": [
      "बेड"
    ],
    "name:hun_x_preferred": [
      "Bade"
    ],
    "name:ind_x_preferred": [
      "Bade"
    ],
    "name:ita_x_preferred": [
      "Bade"
    ],
    "name:kat_x_preferred": [
      "ბადე"
    ],
    "name:nld_x_preferred": [
      "Bade"
    ],
    "name:rus_x_preferred": [
      "Баде"
    ],
    "name:spa_x_preferred": [
      "Bade"
    ],
    "name:swe_x_preferred": [
      "Bade"
    ],
    "name:tur_x_preferred": [
      "Bade"
    ],
    "name:ukr_x_preferred": [
      "Баде"
    ],
    "name:urd_x_preferred": [
      "بیڈے"
    ],
    "name:zho_x_preferred": [
      "巴的"
    ],
    "wof:name": "Bade",
    "wof:placetype": "locality"
  },
  "geometry": {
    "coordinates": [
      107.576,
      21.6703
    ],
    "type": "Point"
  }
}