{
  "type": "Feature",
  "properties": {
    "gn:admin1_code": "25",
    "gn:asciiname": "Zhaodong",
    "gn:country_code": "CN",
    "gn:dem": 15,
    "gn:feature_class": "P",
    "gn:feature_code": "PPL",
    "gn:name": "Zhaodong",
    "gn:population": 0,
    "gn:timezone": "Asia/Shanghai",
    "iso:country": "CN",
    "name:ara_x_preferred": [
      "جاودونغ"
    ],
    "name:ceb_x_preferred": [
      "Zhaodong"
    ],
    "name:deu_x_preferred": [
      "Zhaodong"
    ],
    "name:fas_x_preferred": [
      "ژائودونگ"
    ],
    "name:fin_x_preferred": [
      "Zhaodong"
    ],
    "name:fra_x_preferred": [
      "Zhaodong"
    ],
    "name:heb_x_preferred": [
      "ז'אודונג"
    ],
    "name:hun_x_preferred": [
      "Zhaodong"
    ],
    "name:ita_x_preferred": [
      "Zhaodong"
    ],
    "name:jpn_x_preferred": [
      "肇東市"
    ],
    "name:kik_x_preferred": [
      "Zhaodong"
    ],
    "name:kor_x_preferred": [
      "자오둥시"
    ],
    "name:mlg_x_preferred": [
      "Zhaodong"
    ],
    "name:nor_x_preferred": [
      "Zhaodong"
    ],
    "name:pam_x_preferred": [
      "Zhaodong"
    ],
    "name:rus_x_preferred": [
      "Чжаодун"
    ],
    "name:swe_x_preferred": [
      "Zhaodong"
    ],
    "name:urd_x_preferred": [
      "ژاودونگ"
    ],
    "name:vie_x_preferred": [
      "Triệu Đông"
    ],
    "name:war_x_preferred": [
      "Zhaodong"
    ],
    "name:zho_x_preferred": [
      "赵东"
    ],
    "name:zho_x_variant": [
      "肇东市"
    ],
    "wof:name": "Zhaodong",
    "wof:placetype": "locality"
  },
  "geometry": {
    "coordinates": [
      117.391,
      37.2706
    ],
    "type": "Point"
  }
}