{
  "type": "Feature",
  "properties": {
    "gn:admin1_code": "29.0",
    "gn:asciiname": "Dagoutou",
    "gn:country_code": "CN",
    "gn:dem": 2319,
    "gn:feature_class": "P",
    "gn:feature_code": "PPL",
    "gn:name": "Dagoutou",
    "gn:population": 0,
    "gn:timezone": "Asia/Shanghai",
    "iso:country": "CN",
    "name:und_x_variant": [
      "大沟头"
    ],
    "wof:name": "Dagoutou",
    "wof:placetype": "locality"
  },
  "geometry": {
    "coordinates": [
      103.4714,
      26.06238
    ],
    "type": "Point"
  }
}