{
  "type": "Feature",
  "properties": {
    "gn:admin1_code": "30.0",
    "gn:asciiname": "deng zhan hu",
    "gn:country_code": "CN",
    "gn:dem": 5,
    "gn:feature_class": "P",
    "gn:feature_code": "PPL",
    "gn:name": "灯盏湖",
    "gn:population": 0,
    "gn:timezone": "Asia/Shanghai",
    "iso:country": "CN",
    "name:und_x_variant": [
      "灯盏湖"
    ],
    "name:zho_x_preferred": [
      "东湾"
    ],
    "wof:name": "deng zhan hu",
    "wof:placetype": "locality"
  },
  "geometry": {
    "coordinates": [
      113.01323,
      22.66836
    ],
    "type": "Point"
  }
}