{
  "type": "Feature",
  "properties": {
    "gn:admin1_code": "10.0",
    "gn:asciiname": "Qingshuihe",
    "gn:country_code": "CN",
    "gn:dem": 490,
    "gn:feature_class": "P",
    "gn:feature_code": "PPL",
    "gn:name": "Qingshuihe",
    "gn:population": 0,
    "gn:timezone": "Asia/Shanghai",
    "iso:country": "CN",
    "name:zho_x_preferred": [
      "清水河"
    ],
    "wof:name": "Qingshuihe",
    "wof:placetype": "locality"
  },
  "geometry": {
    "coordinates": [
      115.85038,
      40.37002
    ],
    "type": "Point"
  }
}