{
  "type": "Feature",
  "properties": {
    "gn:admin1_code": "8.0",
    "gn:asciiname": "Shuangcheng",
    "gn:country_code": "CN",
    "gn:dem": 164,
    "gn:feature_class": "P",
    "gn:feature_code": "PPL",
    "gn:name": "Shuangcheng",
    "gn:population": 0,
    "gn:timezone": "Asia/Shanghai",
    "iso:country": "CN",
    "name:ara_x_preferred": [
      "شوانغ"
    ],
    "name:ben_x_preferred": [
      "শুয়াংচেং"
    ],
    "name:ell_x_preferred": [
      "Σουανγκτσένγκ"
    ],
    "name:fas_x_preferred": [
      "شوانگ چنگ"
    ],
    "name:heb_x_preferred": [
      "שואנגצ'נג"
    ],
    "name:hin_x_preferred": [
      "शुआंगचेंग"
    ],
    "name:hun_x_preferred": [
      "Shuangcheng"
    ],
    "name:ind_x_preferred": [
      "Shuangcheng"
    ],
    "name:pol_x_preferred": [
      "Shuangcheng"
    ],
    "name:por_x_preferred": [
      "Shuangcheng"
    ],
    "name:tur_x_preferred": [
      "Shuangcheng"
    ],
    "name:ukr_x_preferred": [
      "Шуанчен"
    ],
    "name:zho_x_preferred": [
      "双城"
    ],
    "wof:name": "Shuangcheng",
    "wof:placetype": "locality"
  },
  "geometry": {
    "coordinates": [
      123.44293,
      47.69528
    ],
    "type": "Point"
  }
}