{
  "type": "Feature",
  "properties": {
    "gn:admin1_code": "32.0",
    "gn:asciiname": "Jintang",
    "gn:country_code": "CN",
    "gn:dem": 419,
    "gn:feature_class": "P",
    "gn:feature_code": "PPL",
    "gn:name": "Jintang",
    "gn:population": 0,
    "gn:timezone": "Asia/Shanghai",
    "iso:country": "CN",
    "name:ceb_x_preferred": [
      "Jintang"
    ],
    "name:deu_x_preferred": [
      "Jintang"
    ],
    "name:rus_x_preferred": [
      "Цзиньтан"
    ],
    "name:zho_x_preferred": [
      "金堂"
    ],
    "wof:name": "Jintang",
    "wof:placetype": "locality"
  },
  "geometry": {
    "coordinates": [
      107.294,
      30.7825
    ],
    "type": "Point"
  }
}