{
  "type": "Feature",
  "properties": {
    "gn:admin1_code": "13.0",
    "gn:asciiname": "Asilanmaili",
    "gn:country_code": "CN",
    "gn:dem": 1403,
    "gn:feature_class": "P",
    "gn:feature_code": "PPL",
    "gn:name": "Asilanmaili",
    "gn:population": 0,
    "gn:timezone": "Asia/Shanghai",
    "iso:country": "CN",
    "name:und_x_variant": [
      "Asilan Maili"
    ],
    "name:zho_x_preferred": [
      "阿斯兰买里"
    ],
    "wof:name": "Asilanmaili",
    "wof:placetype": "locality"
  },
  "geometry": {
    "coordinates": [
      79.9348,
      37.07992
    ],
    "type": "Point"
  }
}