{
  "type": "Feature",
  "properties": {
    "gn:admin1_code": "4.0",
    "gn:asciiname": "Masai",
    "gn:country_code": "CN",
    "gn:dem": 5,
    "gn:feature_class": "P",
    "gn:feature_code": "PPL",
    "gn:name": "Masai",
    "gn:population": 0,
    "gn:timezone": "Asia/Shanghai",
    "iso:country": "CN",
    "name:ceb_x_preferred": [
      "Masai"
    ],
    "name:deu_x_preferred": [
      "Masai"
    ],
    "name:nor_x_preferred": [
      "Masai"
    ],
    "name:rus_x_preferred": [
      "Масаи"
    ],
    "name:swe_x_preferred": [
      "Masai"
    ],
    "name:zho_x_preferred": [
      "马赛"
    ],
    "wof:name": "Masai",
    "wof:placetype": "locality"
  },
  "geometry": {
    "coordinates": [
      120.20833,
      32.54739
    ],
    "type": "Point"
  }
}