{
  "type": "Feature",
  "properties": {
    "gn:admin1_code": "14.0",
    "gn:asciiname": "Qoigang",
    "gn:country_code": "CN",
    "gn:dem": 4156,
    "gn:feature_class": "P",
    "gn:feature_code": "PPL",
    "gn:name": "Qoigang",
    "gn:population": 0,
    "gn:timezone": "Asia/Urumqi",
    "iso:country": "CN",
    "name:bod_x_preferred": [
      "Qoigang"
    ],
    "name:zho_x_preferred": [
      "Qugang"
    ],
    "name:zho_x_variant": [
      "曲岗",
      "Jirong Gongshe",
      "吉绒公社"
    ],
    "wof:name": "Qoigang",
    "wof:placetype": "locality"
  },
  "geometry": {
    "coordinates": [
      92.005,
      29.205
    ],
    "type": "Point"
  }
}