{
  "type": "Feature",
  "properties": {
    "gn:admin1_code": "12.0",
    "gn:asciiname": "Dingjiahe",
    "gn:country_code": "CN",
    "gn:dem": 39,
    "gn:feature_class": "P",
    "gn:feature_code": "PPL",
    "gn:name": "Dingjiahe",
    "gn:population": 0,
    "gn:timezone": "Asia/Shanghai",
    "iso:country": "CN",
    "name:zho_x_preferred": [
      "丁家河"
    ],
    "wof:name": "Dingjiahe",
    "wof:placetype": "locality"
  },
  "geometry": {
    "coordinates": [
      113.967,
      31.2308
    ],
    "type": "Point"
  }
}