{
  "type": "Feature",
  "properties": {
    "gn:admin1_code": "26.0",
    "gn:asciiname": "Nandong",
    "gn:country_code": "CN",
    "gn:dem": 479,
    "gn:feature_class": "P",
    "gn:feature_code": "PPL",
    "gn:name": "Nandong",
    "gn:population": 0,
    "gn:timezone": "Asia/Shanghai",
    "iso:country": "CN",
    "name:fas_x_preferred": [
      "ناندونگ"
    ],
    "name:zho_x_preferred": [
      "南董"
    ],
    "name:zho_x_variant": [
      "南董镇"
    ],
    "wof:name": "Nandong",
    "wof:placetype": "locality"
  },
  "geometry": {
    "coordinates": [
      109.24057,
      34.81814
    ],
    "type": "Point"
  }
}