{
  "type": "Feature",
  "properties": {
    "gn:admin1_code": "11.0",
    "gn:asciiname": "Wangjiachang",
    "gn:country_code": "CN",
    "gn:dem": 57,
    "gn:feature_class": "P",
    "gn:feature_code": "PPLA4",
    "gn:name": "Wangjiachang",
    "gn:population": 0,
    "gn:timezone": "Asia/Shanghai",
    "iso:country": "CN",
    "name:und_x_variant": [
      "Wang-chia-ch’ang",
      "Wangjiachang",
      "王家厂",
      "Wangjiachang Zhen",
      "王家厂镇"
    ],
    "wof:name": "Wangjiachang",
    "wof:placetype": "locality"
  },
  "geometry": {
    "coordinates": [
      111.53444,
      29.76139
    ],
    "type": "Point"
  }
}