{
  "type": "Feature",
  "properties": {
    "gn:admin1_code": "25",
    "gn:asciiname": "Zhu'a",
    "gn:country_code": "CN",
    "gn:dem": 480,
    "gn:feature_class": "P",
    "gn:feature_code": "PPL",
    "gn:name": "Zhu’a",
    "gn:population": 0,
    "gn:timezone": "Asia/Shanghai",
    "iso:country": "CN",
    "name:und_x_variant": [
      "Zhu’a"
    ],
    "name:zho_x_preferred": [
      "朱阿"
    ],
    "wof:name": "Zhu'a",
    "wof:placetype": "locality"
  },
  "geometry": {
    "coordinates": [
      118.076,
      36.2722
    ],
    "type": "Point"
  }
}