{
  "type": "Feature",
  "properties": {
    "gn:admin1_code": "5.0",
    "gn:asciiname": "Long'anbu",
    "gn:country_code": "CN",
    "gn:dem": 260,
    "gn:feature_class": "P",
    "gn:feature_code": "PPL",
    "gn:name": "Long’anbu",
    "gn:population": 0,
    "gn:timezone": "Asia/Shanghai",
    "iso:country": "CN",
    "name:und_x_variant": [
      "Long’anbu"
    ],
    "name:zho_x_preferred": [
      "龙安堡"
    ],
    "wof:name": "Long'anbu",
    "wof:placetype": "locality"
  },
  "geometry": {
    "coordinates": [
      127.16603,
      44.38112
    ],
    "type": "Point"
  }
}