{
  "type": "Feature",
  "properties": {
    "gn:admin1_code": "8.0",
    "gn:asciiname": "Zhujiagou",
    "gn:country_code": "CN",
    "gn:dem": 136,
    "gn:feature_class": "P",
    "gn:feature_code": "PPL",
    "gn:name": "Zhujiagou",
    "gn:population": 0,
    "gn:timezone": "Asia/Shanghai",
    "iso:country": "CN",
    "name:zho_x_preferred": [
      "朱家沟"
    ],
    "wof:name": "Zhujiagou",
    "wof:placetype": "locality"
  },
  "geometry": {
    "coordinates": [
      126.28936000000002,
      46.21204
    ],
    "type": "Point"
  }
}