{
  "type": "Feature",
  "properties": {
    "gn:admin1_code": "32.0",
    "gn:asciiname": "Yunli",
    "gn:country_code": "CN",
    "gn:dem": 767,
    "gn:feature_class": "P",
    "gn:feature_code": "PPL",
    "gn:name": "Yunli",
    "gn:population": 0,
    "gn:timezone": "Asia/Shanghai",
    "iso:country": "CN",
    "name:tha_x_preferred": [
      "อิ้นหลี่"
    ],
    "name:vie_x_preferred": [
      "Dận Lễ"
    ],
    "name:zho_x_preferred": [
      "云里"
    ],
    "wof:name": "Yunli",
    "wof:placetype": "locality"
  },
  "geometry": {
    "coordinates": [
      104.546,
      31.8817
    ],
    "type": "Point"
  }
}