{
  "type": "Feature",
  "properties": {
    "gn:admin1_code": "25.0",
    "gn:asciiname": "Guge",
    "gn:country_code": "CN",
    "gn:dem": 52,
    "gn:feature_class": "P",
    "gn:feature_code": "PPL",
    "gn:name": "Guge",
    "gn:population": 0,
    "gn:timezone": "Asia/Shanghai",
    "iso:country": "CN",
    "name:ben_x_preferred": [
      "গুজ"
    ],
    "name:cat_x_preferred": [
      "Guge"
    ],
    "name:deu_x_preferred": [
      "Guge"
    ],
    "name:hin_x_preferred": [
      "गुगे"
    ],
    "name:jpn_x_preferred": [
      "グゲ王国"
    ],
    "name:kor_x_preferred": [
      "구게 왕국"
    ],
    "name:nld_x_preferred": [
      "Guge"
    ],
    "name:nor_x_preferred": [
      "Guge"
    ],
    "name:pnb_x_preferred": [
      "گگے راج"
    ],
    "name:por_x_preferred": [
      "Guge"
    ],
    "name:rus_x_preferred": [
      "Гуге"
    ],
    "name:spa_x_preferred": [
      "Guge"
    ],
    "name:swe_x_preferred": [
      "Guge"
    ],
    "name:vie_x_preferred": [
      "Cổ Cách"
    ],
    "name:zho_x_preferred": [
      "古格"
    ],
    "name:zho_x_variant": [
      "古格王朝"
    ],
    "wof:name": "Guge",
    "wof:placetype": "locality"
  },
  "geometry": {
    "coordinates": [
      122.33388,
      37.14711
    ],
    "type": "Point"
  }
}