{
  "type": "Feature",
  "properties": {
    "gn:admin1_code": "15.0",
    "gn:asciiname": "Liwan",
    "gn:country_code": "CN",
    "gn:dem": 988,
    "gn:feature_class": "P",
    "gn:feature_code": "PPL",
    "gn:name": "Liwan",
    "gn:population": 0,
    "gn:timezone": "Asia/Shanghai",
    "iso:country": "CN",
    "name:ara_x_preferred": [
      "ليوان"
    ],
    "name:heb_x_preferred": [
      "ליוואן"
    ],
    "name:ita_x_preferred": [
      "Līwān"
    ],
    "name:spa_x_preferred": [
      "Liwan"
    ],
    "name:und_x_variant": [
      "李湾"
    ],
    "name:urd_x_preferred": [
      "لیوان"
    ],
    "wof:name": "Liwan",
    "wof:placetype": "locality"
  },
  "geometry": {
    "coordinates": [
      105.73555,
      33.43685
    ],
    "type": "Point"
  }
}