{
  "type": "Feature",
  "properties": {
    "gn:admin1_code": "10",
    "gn:asciiname": "Hongshanzui",
    "gn:country_code": "CN",
    "gn:dem": 494,
    "gn:feature_class": "P",
    "gn:feature_code": "PPL",
    "gn:name": "Hongshanzui",
    "gn:population": 0,
    "gn:timezone": "Asia/Shanghai",
    "iso:country": "CN",
    "name:zho_x_preferred": [
      "红山嘴"
    ],
    "wof:name": "Hongshanzui",
    "wof:placetype": "locality"
  },
  "geometry": {
    "coordinates": [
      118.64575,
      40.97621
    ],
    "type": "Point"
  }
}