{
  "type": "Feature",
  "properties": {
    "gn:admin1_code": "32.0",
    "gn:asciiname": "Ganjianian",
    "gn:country_code": "CN",
    "gn:dem": 620,
    "gn:feature_class": "P",
    "gn:feature_code": "PPL",
    "gn:name": "Ganjianian",
    "gn:population": 0,
    "gn:timezone": "Asia/Shanghai",
    "iso:country": "CN",
    "name:zho_x_preferred": [
      "甘家碾"
    ],
    "wof:name": "Ganjianian",
    "wof:placetype": "locality"
  },
  "geometry": {
    "coordinates": [
      103.591,
      30.8215
    ],
    "type": "Point"
  }
}