{
  "type": "Feature",
  "properties": {
    "gn:admin1_code": "24.0",
    "gn:asciiname": "Lingnan",
    "gn:country_code": "CN",
    "gn:dem": 846,
    "gn:feature_class": "P",
    "gn:feature_code": "PPL",
    "gn:name": "Lingnan",
    "gn:population": 0,
    "gn:timezone": "Asia/Shanghai",
    "iso:country": "CN",
    "name:deu_x_preferred": [
      "Lingnan"
    ],
    "name:ind_x_preferred": [
      "Lingnan"
    ],
    "name:ita_x_preferred": [
      "Lingnan"
    ],
    "name:jpn_x_preferred": [
      "嶺南"
    ],
    "name:kor_x_preferred": [
      "영남"
    ],
    "name:rus_x_preferred": [
      "Линнань"
    ],
    "name:vie_x_preferred": [
      "Lĩnh Nam"
    ],
    "name:zho_x_preferred": [
      "岭南"
    ],
    "wof:name": "Lingnan",
    "wof:placetype": "locality"
  },
  "geometry": {
    "coordinates": [
      111.56261,
      36.46953
    ],
    "type": "Point"
  }
}