{
  "type": "Feature",
  "properties": {
    "gn:admin1_code": "26.0",
    "gn:asciiname": "Zhongzhuangtai",
    "gn:country_code": "CN",
    "gn:dem": 1335,
    "gn:feature_class": "P",
    "gn:feature_code": "PPL",
    "gn:name": "Zhongzhuangtai",
    "gn:population": 0,
    "gn:timezone": "Asia/Shanghai",
    "iso:country": "CN",
    "name:zho_x_preferred": [
      "钟庄台"
    ],
    "wof:name": "Zhongzhuangtai",
    "wof:placetype": "locality"
  },
  "geometry": {
    "coordinates": [
      108.7023,
      36.85359
    ],
    "type": "Point"
  }
}