{
  "type": "Feature",
  "properties": {
    "gn:admin1_code": "8.0",
    "gn:asciiname": "Yuanjia Wopeng",
    "gn:country_code": "CN",
    "gn:dem": 170,
    "gn:feature_class": "P",
    "gn:feature_code": "PPL",
    "gn:name": "Yuanjia Wopeng",
    "gn:population": 0,
    "gn:timezone": "Asia/Shanghai",
    "iso:country": "CN",
    "name:zho_x_preferred": [
      "袁家窝棚"
    ],
    "wof:name": "Yuanjia Wopeng",
    "wof:placetype": "locality"
  },
  "geometry": {
    "coordinates": [
      124.13571,
      47.98731
    ],
    "type": "Point"
  }
}