{
  "type": "Feature",
  "properties": {
    "gn:admin1_code": "07",
    "gn:asciiname": "Fuyuan",
    "gn:country_code": "CN",
    "gn:dem": 264,
    "gn:feature_class": "P",
    "gn:feature_code": "PPL",
    "gn:name": "Fuyuan",
    "gn:population": 0,
    "gn:timezone": "Asia/Shanghai",
    "iso:country": "CN",
    "name:ceb_x_preferred": [
      "Fuyuan"
    ],
    "name:deu_x_preferred": [
      "Fuyuan"
    ],
    "name:eus_x_preferred": [
      "Fuyuan"
    ],
    "name:fra_x_preferred": [
      "Fuyuan"
    ],
    "name:kor_x_preferred": [
      "푸위안"
    ],
    "name:mlg_x_preferred": [
      "Fuyuan"
    ],
    "name:nor_x_preferred": [
      "Fuyuan"
    ],
    "name:rus_x_preferred": [
      "Фуюань"
    ],
    "name:swe_x_preferred": [
      "Fuyuan"
    ],
    "name:zho_x_preferred": [
      "福源"
    ],
    "wof:name": "Fuyuan",
    "wof:placetype": "locality"
  },
  "geometry": {
    "coordinates": [
      118.5088,
      26.92559
    ],
    "type": "Point"
  }
}