{
  "type": "Feature",
  "properties": {
    "gn:admin1_code": "24.0",
    "gn:asciiname": "Jude",
    "gn:country_code": "CN",
    "gn:dem": 980,
    "gn:feature_class": "P",
    "gn:feature_code": "PPL",
    "gn:name": "Jude",
    "gn:population": 0,
    "gn:timezone": "Asia/Shanghai",
    "iso:country": "CN",
    "name:bar_x_preferred": [
      "Jude"
    ],
    "name:deu_x_preferred": [
      "Jude"
    ],
    "name:fra_x_preferred": [
      "Jude"
    ],
    "name:glg_x_preferred": [
      "Jude"
    ],
    "name:heb_x_preferred": [
      "ג'וד"
    ],
    "name:jpn_x_preferred": [
      "Jude"
    ],
    "name:kat_x_preferred": [
      "იუდა"
    ],
    "name:mlg_x_preferred": [
      "Joda"
    ],
    "name:pol_x_preferred": [
      "Jude"
    ],
    "name:zho_x_preferred": [
      "居德"
    ],
    "name:zho_x_variant": [
      "Jude"
    ],
    "wof:name": "Jude",
    "wof:placetype": "locality"
  },
  "geometry": {
    "coordinates": [
      112.72801,
      36.2008
    ],
    "type": "Point"
  }
}