{
  "type": "Feature",
  "properties": {
    "iso:country": "CN",
    "name:bod_x_preferred": [
      "ས་སྐྱ་རྫོང་།"
    ],
    "name:ceb_x_preferred": [
      "Sajia Xian"
    ],
    "name:deu_x_preferred": [
      "Sa’gya"
    ],
    "name:eng_x_preferred": [
      "Sa'gya County"
    ],
    "name:fas_x_preferred": [
      "شهرستان ساگیا"
    ],
    "name:gan_x_preferred": [
      "萨迦县"
    ],
    "name:jpn_x_preferred": [
      "サキャ県"
    ],
    "name:kor_x_preferred": [
      "싸자현"
    ],
    "name:nan_x_preferred": [
      "Sa'gya-koān"
    ],
    "name:nld_x_preferred": [
      "Sakya"
    ],
    "name:nob_x_preferred": [
      "Sa'gya"
    ],
    "name:pol_x_preferred": [
      "Sa’gya"
    ],
    "name:rus_x_preferred": [
      "Сакья"
    ],
    "name:swe_x_preferred": [
      "Sakya"
    ],
    "name:urd_x_preferred": [
      "ساگیا کاؤنٹی"
    ],
    "name:vie_x_preferred": [
      "Sa'gya"
    ],
    "name:wuu_x_preferred": [
      "萨迦县"
    ],
    "name:zho_x_preferred": [
      "萨迦县"
    ],
    "qs:name": "萨迦",
    "qs:name_adm0": "中國",
    "qs:name_adm1": "西藏自治区",
    "qs:photos": 353,
    "qs:photos_1k": 72,
    "qs:photos_9k": 2,
    "qs:photos_9r": 5,
    "qs:photos_all": 353,
    "qs:photos_sr": 6,
    "qs:placetype": "Town",
    "qs:pop_sr": "0",
    "wd:wordcount": 119,
    "wof:name": "萨迦",
    "wof:placetype": "locality"
  },
  "geometry": {
    "coordinates": [
      88.016452,
      28.90961
    ],
    "type": "Point"
  }
}