{
  "type": "Feature",
  "properties": {
    "gn:admin1_code": "11.0",
    "gn:asciiname": "Niuyan",
    "gn:country_code": "CN",
    "gn:dem": 472,
    "gn:feature_class": "P",
    "gn:feature_code": "PPL",
    "gn:name": "Niuyan",
    "gn:population": 0,
    "gn:timezone": "Asia/Shanghai",
    "iso:country": "CN",
    "name:zho_x_preferred": [
      "牛岩"
    ],
    "wof:name": "Niuyan",
    "wof:placetype": "locality"
  },
  "geometry": {
    "coordinates": [
      109.55071,
      28.0156
    ],
    "type": "Point"
  }
}