{
  "type": "Feature",
  "properties": {
    "gn:admin1_code": "14.0",
    "gn:asciiname": "Guru",
    "gn:country_code": "CN",
    "gn:dem": 4017,
    "gn:feature_class": "P",
    "gn:feature_code": "PPL",
    "gn:name": "Guru",
    "gn:population": 0,
    "gn:timezone": "Asia/Urumqi",
    "iso:country": "CN",
    "name:ara_x_preferred": [
      "غورو"
    ],
    "name:aze_x_preferred": [
      "Quru"
    ],
    "name:ben_x_preferred": [
      "গুরু"
    ],
    "name:bul_x_preferred": [
      "Гуру"
    ],
    "name:cat_x_preferred": [
      "Guru"
    ],
    "name:ces_x_preferred": [
      "Guru"
    ],
    "name:dan_x_preferred": [
      "Guru"
    ],
    "name:deu_x_preferred": [
      "Guru"
    ],
    "name:ell_x_preferred": [
      "Γκουρού"
    ],
    "name:epo_x_preferred": [
      "Guruo"
    ],
    "name:est_x_preferred": [
      "Guru"
    ],
    "name:eus_x_preferred": [
      "Guru"
    ],
    "name:fas_x_preferred": [
      "گورو"
    ],
    "name:fin_x_preferred": [
      "Guru"
    ],
    "name:fra_x_preferred": [
      "Guru"
    ],
    "name:gle_x_preferred": [
      "Gurú"
    ],
    "name:guj_x_preferred": [
      "ગુરુ"
    ],
    "name:heb_x_preferred": [
      "גורו"
    ],
    "name:hin_x_preferred": [
      "गुरु"
    ],
    "name:hrv_x_preferred": [
      "Guru"
    ],
    "name:hun_x_preferred": [
      "Guru"
    ],
    "name:hye_x_preferred": [
      "Գուրու"
    ],
    "name:ind_x_preferred": [
      "Guru"
    ],
    "name:isl_x_preferred": [
      "Gúru"
    ],
    "name:ita_x_preferred": [
      "Guru"
    ],
    "name:jav_x_preferred": [
      "Guru"
    ],
    "name:kan_x_preferred": [
      "ಗುರು"
    ],
    "name:kat_x_preferred": [
      "გურუ"
    ],
    "name:kor_x_preferred": [
      "구루"
    ],
    "name:lit_x_preferred": [
      "Gurus"
    ],
    "name:nld_x_preferred": [
      "Goeroe"
    ],
    "name:nno_x_preferred": [
      "Guru"
    ],
    "name:nor_x_preferred": [
      "Guru"
    ],
    "name:ori_x_preferred": [
      "ଗୁରୁ"
    ],
    "name:pli_x_preferred": [
      "गुरु"
    ],
    "name:pnb_x_preferred": [
      "گرو"
    ],
    "name:pol_x_preferred": [
      "Guru"
    ],
    "name:por_x_preferred": [
      "Guru"
    ],
    "name:ron_x_preferred": [
      "Guru"
    ],
    "name:rus_x_preferred": [
      "Гуру"
    ],
    "name:san_x_preferred": [
      "गुरुः"
    ],
    "name:sco_x_preferred": [
      "Guru"
    ],
    "name:spa_x_preferred": [
      "Gurú"
    ],
    "name:srp_x_preferred": [
      "Гуру"
    ],
    "name:swa_x_preferred": [
      "Guru"
    ],
    "name:swe_x_preferred": [
      "Guru"
    ],
    "name:tam_x_preferred": [
      "குரு"
    ],
    "name:tel_x_preferred": [
      "గురువు"
    ],
    "name:tha_x_preferred": [
      "คุรุ"
    ],
    "name:tur_x_preferred": [
      "Guru"
    ],
    "name:ukr_x_preferred": [
      "Ґуру"
    ],
    "name:urd_x_preferred": [
      "گرو"
    ],
    "name:uzb_x_preferred": [
      "Guru"
    ],
    "name:vie_x_preferred": [
      "Guru"
    ],
    "name:zho_x_preferred": [
      "古如"
    ],
    "wof:name": "Guru",
    "wof:placetype": "locality"
  },
  "geometry": {
    "coordinates": [
      91.20152,
      29.99614
    ],
    "type": "Point"
  }
}