{
  "type": "Feature",
  "properties": {
    "gn:admin1_code": "8.0",
    "gn:asciiname": "Xiaolu Defutun",
    "gn:country_code": "CN",
    "gn:dem": 125,
    "gn:feature_class": "P",
    "gn:feature_code": "PPL",
    "gn:name": "Xiaolü Defutun",
    "gn:population": 0,
    "gn:timezone": "Asia/Shanghai",
    "iso:country": "CN",
    "name:zho_x_preferred": [
      "Xiaolü Defutun"
    ],
    "name:zho_x_variant": [
      "小吕德福屯"
    ],
    "wof:name": "Xiaolu Defutun",
    "wof:placetype": "locality"
  },
  "geometry": {
    "coordinates": [
      128.04702,
      46.06513
    ],
    "type": "Point"
  }
}