{
  "type": "Feature",
  "properties": {
    "gn:admin1_code": "22.0",
    "gn:asciiname": "Baotaicun",
    "gn:country_code": "CN",
    "gn:dem": 52,
    "gn:feature_class": "P",
    "gn:feature_code": "PPL",
    "gn:name": "Baotaicun",
    "gn:population": 0,
    "gn:timezone": "Asia/Shanghai",
    "iso:country": "CN",
    "name:zho_x_preferred": [
      "葆台村"
    ],
    "wof:name": "Baotaicun",
    "wof:placetype": "locality"
  },
  "geometry": {
    "coordinates": [
      116.28441,
      39.807
    ],
    "type": "Point"
  }
}