{
  "type": "Feature",
  "properties": {
    "gn:admin1_code": "32.0",
    "gn:asciiname": "Tadun",
    "gn:country_code": "CN",
    "gn:dem": 3142,
    "gn:feature_class": "P",
    "gn:feature_code": "PPL",
    "gn:name": "Tadun",
    "gn:population": 0,
    "gn:timezone": "Asia/Shanghai",
    "iso:country": "CN",
    "name:jpn_x_preferred": [
      "トウ頓"
    ],
    "name:tha_x_preferred": [
      "เป๊กตุ้น"
    ],
    "name:vie_x_preferred": [
      "Đạp Đốn"
    ],
    "name:zho_x_preferred": [
      "塔敦"
    ],
    "wof:name": "Tadun",
    "wof:placetype": "locality"
  },
  "geometry": {
    "coordinates": [
      100.221,
      30.8941
    ],
    "type": "Point"
  }
}