{
  "type": "Feature",
  "properties": {
    "gn:admin1_code": "03",
    "gn:asciiname": "Daxi",
    "gn:country_code": "CN",
    "gn:dem": 21,
    "gn:feature_class": "P",
    "gn:feature_code": "PPLA4",
    "gn:name": "Daxi",
    "gn:population": 0,
    "gn:timezone": "Asia/Shanghai",
    "iso:country": "CN",
    "name:ceb_x_preferred": [
      "Daxi"
    ],
    "name:deu_x_preferred": [
      "Daxi"
    ],
    "name:swe_x_preferred": [
      "Daxi"
    ],
    "name:und_x_variant": [
      "Ta-hsi-tu",
      "大溪",
      "Daxidu",
      "Daxi Xiang",
      "大溪乡"
    ],
    "wof:name": "Daxi",
    "wof:placetype": "locality"
  },
  "geometry": {
    "coordinates": [
      116.69827,
      28.58819
    ],
    "type": "Point"
  }
}