{
  "type": "Feature",
  "properties": {
    "gn:admin1_code": "2.0",
    "gn:asciiname": "Lianhuarui",
    "gn:country_code": "CN",
    "gn:dem": 121,
    "gn:feature_class": "P",
    "gn:feature_code": "PPL",
    "gn:name": "Lianhuarui",
    "gn:population": 0,
    "gn:timezone": "Asia/Shanghai",
    "iso:country": "CN",
    "name:zho_x_preferred": [
      "莲花蕊"
    ],
    "wof:name": "Lianhuarui",
    "wof:placetype": "locality"
  },
  "geometry": {
    "coordinates": [
      118.29534,
      28.99088
    ],
    "type": "Point"
  }
}