{
  "type": "Feature",
  "properties": {
    "gn:admin1_code": "30.0",
    "gn:asciiname": "Dongzhaicun",
    "gn:country_code": "CN",
    "gn:dem": 9,
    "gn:feature_class": "P",
    "gn:feature_code": "PPL",
    "gn:name": "Dongzhaicun",
    "gn:population": 0,
    "gn:timezone": "Asia/Shanghai",
    "iso:country": "CN",
    "name:zho_x_preferred": [
      "东寨村"
    ],
    "wof:name": "Dongzhaicun",
    "wof:placetype": "locality"
  },
  "geometry": {
    "coordinates": [
      116.6488,
      23.51499
    ],
    "type": "Point"
  }
}