{
  "type": "Feature",
  "properties": {
    "gn:admin1_code": "10.0",
    "gn:asciiname": "Daguanzhuangzi",
    "gn:country_code": "CN",
    "gn:dem": 10,
    "gn:feature_class": "P",
    "gn:feature_code": "PPL",
    "gn:name": "Daguanzhuangzi",
    "gn:population": 0,
    "gn:timezone": "Asia/Shanghai",
    "iso:country": "CN",
    "name:zho_x_preferred": [
      "大官庄子"
    ],
    "wof:name": "Daguanzhuangzi",
    "wof:placetype": "locality"
  },
  "geometry": {
    "coordinates": [
      116.832,
      38.3754
    ],
    "type": "Point"
  }
}