{
  "type": "Feature",
  "properties": {
    "gn:admin1_code": "11.0",
    "gn:asciiname": "Dagaoyan",
    "gn:country_code": "CN",
    "gn:dem": 789,
    "gn:feature_class": "P",
    "gn:feature_code": "PPL",
    "gn:name": "Dagaoyan",
    "gn:population": 0,
    "gn:timezone": "Asia/Shanghai",
    "iso:country": "CN",
    "name:zho_x_preferred": [
      "大高岩"
    ],
    "wof:name": "Dagaoyan",
    "wof:placetype": "locality"
  },
  "geometry": {
    "coordinates": [
      109.41911,
      28.17409
    ],
    "type": "Point"
  }
}