{
  "type": "Feature",
  "properties": {
    "gn:admin1_code": "12.0",
    "gn:asciiname": "Guandao",
    "gn:country_code": "CN",
    "gn:dem": 114,
    "gn:feature_class": "P",
    "gn:feature_code": "PPLA4",
    "gn:name": "Guandao",
    "gn:population": 0,
    "gn:timezone": "Asia/Shanghai",
    "iso:country": "CN",
    "name:ces_x_preferred": [
      "Kuan tao"
    ],
    "name:deu_x_preferred": [
      "Guan Dao"
    ],
    "name:ind_x_preferred": [
      "Guan dao"
    ],
    "name:ita_x_preferred": [
      "Guan dao"
    ],
    "name:jpn_x_preferred": [
      "大刀"
    ],
    "name:kor_x_preferred": [
      "언월도"
    ],
    "name:lit_x_preferred": [
      "Guandao"
    ],
    "name:nor_x_preferred": [
      "Guan dao"
    ],
    "name:pol_x_preferred": [
      "Guan dao"
    ],
    "name:por_x_preferred": [
      "Guan dao"
    ],
    "name:rus_x_preferred": [
      "Гуань дао"
    ],
    "name:spa_x_preferred": [
      "Guan dao"
    ],
    "name:tha_x_preferred": [
      "ง้าว"
    ],
    "name:ukr_x_preferred": [
      "Цзінлун яньюедао"
    ],
    "name:und_x_variant": [
      "Guandao Zhen"
    ],
    "name:vie_x_preferred": [
      "Quan đao"
    ],
    "name:zho_x_preferred": [
      "关刀"
    ],
    "name:zho_x_variant": [
      "关刀镇",
      "偃月刀"
    ],
    "wof:name": "Guandao",
    "wof:placetype": "locality"
  },
  "geometry": {
    "coordinates": [
      113.90012,
      29.21745
    ],
    "type": "Point"
  }
}