{
  "type": "Feature",
  "properties": {
    "gn:admin1_code": "11.0",
    "gn:asciiname": "Huangjiachong",
    "gn:country_code": "CN",
    "gn:dem": 429,
    "gn:feature_class": "P",
    "gn:feature_code": "PPL",
    "gn:name": "Huangjiachong",
    "gn:population": 0,
    "gn:timezone": "Asia/Shanghai",
    "iso:country": "CN",
    "name:zho_x_preferred": [
      "黄家冲"
    ],
    "wof:name": "Huangjiachong",
    "wof:placetype": "locality"
  },
  "geometry": {
    "coordinates": [
      110.61352,
      27.17153
    ],
    "type": "Point"
  }
}