{
  "type": "Feature",
  "properties": {
    "gn:admin1_code": "19.0",
    "gn:asciiname": "Lufangsicun",
    "gn:country_code": "CN",
    "gn:dem": 38,
    "gn:feature_class": "P",
    "gn:feature_code": "PPL",
    "gn:name": "Lüfangsicun",
    "gn:population": 0,
    "gn:timezone": "Asia/Shanghai",
    "iso:country": "CN",
    "name:und_x_variant": [
      "Lüfangsicun"
    ],
    "name:zho_x_preferred": [
      "吕方寺村"
    ],
    "wof:name": "Lufangsicun",
    "wof:placetype": "locality"
  },
  "geometry": {
    "coordinates": [
      123.37376,
      41.4207
    ],
    "type": "Point"
  }
}