{
  "type": "Feature",
  "properties": {
    "gn:admin1_code": "25",
    "gn:asciiname": "Qingyunshan",
    "gn:country_code": "CN",
    "gn:dem": 249,
    "gn:feature_class": "P",
    "gn:feature_code": "PPL",
    "gn:name": "Qingyunshan",
    "gn:population": 0,
    "gn:timezone": "Asia/Shanghai",
    "iso:country": "CN",
    "name:zho_x_preferred": [
      "青云山"
    ],
    "name:zho_x_variant": [
      "庆云山街道"
    ],
    "wof:name": "Qingyunshan",
    "wof:placetype": "locality"
  },
  "geometry": {
    "coordinates": [
      117.82,
      35.8746
    ],
    "type": "Point"
  }
}