{
  "type": "Feature",
  "properties": {
    "gn:admin1_code": "25",
    "gn:asciiname": "Xisuzhuang",
    "gn:country_code": "CN",
    "gn:dem": 40,
    "gn:feature_class": "P",
    "gn:feature_code": "PPL",
    "gn:name": "Xisuzhuang",
    "gn:population": 0,
    "gn:timezone": "Asia/Shanghai",
    "iso:country": "CN",
    "name:zho_x_preferred": [
      "西苏庄"
    ],
    "wof:name": "Xisuzhuang",
    "wof:placetype": "locality"
  },
  "geometry": {
    "coordinates": [
      116.725,
      36.526
    ],
    "type": "Point"
  }
}