{
  "type": "Feature",
  "properties": {
    "gn:admin1_code": "14.0",
    "gn:asciiname": "Nieru",
    "gn:country_code": "CN",
    "gn:dem": 4486,
    "gn:feature_class": "P",
    "gn:feature_code": "PPLA4",
    "gn:name": "Nieru",
    "gn:population": 0,
    "gn:timezone": "Asia/Urumqi",
    "iso:country": "CN",
    "name:bod_x_preferred": [
      "Nyêru"
    ],
    "name:ceb_x_preferred": [
      "Nierudui"
    ],
    "name:msa_x_preferred": [
      "Nyêru"
    ],
    "name:swe_x_preferred": [
      "Nierudui"
    ],
    "name:und_x_variant": [
      "Nieru Xiang"
    ],
    "name:zho_x_preferred": [
      "Nieru"
    ],
    "name:zho_x_variant": [
      "涅如",
      "Nailong",
      "乃隆",
      "涅如乡",
      "涅如堆乡"
    ],
    "wof:name": "Nieru",
    "wof:placetype": "locality"
  },
  "geometry": {
    "coordinates": [
      89.85041,
      28.52517000000001
    ],
    "type": "Point"
  }
}