{
  "type": "Feature",
  "properties": {
    "gn:admin1_code": "2.0",
    "gn:asciiname": "Xiang'ao",
    "gn:country_code": "CN",
    "gn:dem": 12,
    "gn:feature_class": "P",
    "gn:feature_code": "PPL",
    "gn:name": "Xiang’ao",
    "gn:population": 0,
    "gn:timezone": "Asia/Shanghai",
    "iso:country": "CN",
    "name:und_x_variant": [
      "Xiang’ao"
    ],
    "name:zho_x_preferred": [
      "相岙"
    ],
    "wof:name": "Xiang'ao",
    "wof:placetype": "locality"
  },
  "geometry": {
    "coordinates": [
      121.3978,
      30.03892
    ],
    "type": "Point"
  }
}