{
  "type": "Feature",
  "properties": {
    "gn:admin1_code": "14",
    "gn:asciiname": "Serelong",
    "gn:country_code": "CN",
    "gn:dem": 4599,
    "gn:feature_class": "P",
    "gn:feature_code": "PPL",
    "gn:name": "Serelong",
    "gn:population": 0,
    "gn:timezone": "Asia/Urumqi",
    "iso:country": "CN",
    "name:zho_x_preferred": [
      "色热龙"
    ],
    "wof:name": "Serelong",
    "wof:placetype": "locality"
  },
  "geometry": {
    "coordinates": [
      89.3676,
      28.4769
    ],
    "type": "Point"
  }
}