{
  "type": "Feature",
  "properties": {
    "gn:admin1_code": "7",
    "gn:asciiname": "Xiacuo",
    "gn:country_code": "CN",
    "gn:dem": 267,
    "gn:feature_class": "P",
    "gn:feature_code": "PPL",
    "gn:name": "Xiacuo",
    "gn:population": 0,
    "gn:timezone": "Asia/Shanghai",
    "iso:country": "CN",
    "name:zho_x_preferred": [
      "下厝"
    ],
    "wof:name": "Xiacuo",
    "wof:placetype": "locality"
  },
  "geometry": {
    "coordinates": [
      117.23773,
      24.44178
    ],
    "type": "Point"
  }
}