{
  "type": "Feature",
  "properties": {
    "gn:admin1_code": "2",
    "gn:asciiname": "Huailu",
    "gn:country_code": "CN",
    "gn:dem": 118,
    "gn:feature_class": "P",
    "gn:feature_code": "PPLA4",
    "gn:name": "Huailu",
    "gn:population": 0,
    "gn:timezone": "Asia/Shanghai",
    "iso:country": "CN",
    "name:und_x_variant": [
      "Huailu Zhen",
      "Huailu"
    ],
    "name:zho_x_preferred": [
      "怀鲁镇"
    ],
    "name:zho_x_variant": [
      "怀鲁"
    ],
    "wof:name": "Huailu",
    "wof:placetype": "locality"
  },
  "geometry": {
    "coordinates": [
      120.38174,
      29.3433
    ],
    "type": "Point"
  }
}