{
  "type": "Feature",
  "properties": {
    "gn:admin1_code": "16.0",
    "gn:asciiname": "Shetou",
    "gn:country_code": "CN",
    "gn:dem": 122,
    "gn:feature_class": "P",
    "gn:feature_code": "PPL",
    "gn:name": "Shetou",
    "gn:population": 0,
    "gn:timezone": "Asia/Shanghai",
    "iso:country": "CN",
    "name:hak_x_preferred": [
      "Sa-thèu-hiông"
    ],
    "name:ita_x_preferred": [
      "Shetou"
    ],
    "name:jpn_x_preferred": [
      "社頭郷"
    ],
    "name:kor_x_preferred": [
      "서터우향"
    ],
    "name:pol_x_preferred": [
      "Shetou"
    ],
    "name:vie_x_preferred": [
      "Xã Đầu"
    ],
    "name:zho_x_preferred": [
      "社头"
    ],
    "name:zho_x_variant": [
      "社頭鄉"
    ],
    "wof:name": "Shetou",
    "wof:placetype": "locality"
  },
  "geometry": {
    "coordinates": [
      109.29,
      22.5357
    ],
    "type": "Point"
  }
}