{
  "type": "Feature",
  "properties": {
    "gn:admin1_code": "10.0",
    "gn:asciiname": "Xiaotankou",
    "gn:country_code": "CN",
    "gn:dem": 1033,
    "gn:feature_class": "P",
    "gn:feature_code": "PPL",
    "gn:name": "Xiaotankou",
    "gn:population": 0,
    "gn:timezone": "Asia/Shanghai",
    "iso:country": "CN",
    "name:zho_x_preferred": [
      "小探口"
    ],
    "wof:name": "Xiaotankou",
    "wof:placetype": "locality"
  },
  "geometry": {
    "coordinates": [
      114.55025,
      39.75279000000001
    ],
    "type": "Point"
  }
}