{
  "type": "Feature",
  "properties": {
    "iso:country": "CN",
    "name:eng_x_preferred": [
      "Xikou"
    ],
    "name:zho_x_preferred": [
      "溪口镇"
    ],
    "qs:name": "溪口镇",
    "qs:name_adm0": "中國",
    "qs:name_adm1": "浙江省",
    "qs:photos": 73,
    "qs:photos_1k": 15,
    "qs:photos_9k": 1,
    "qs:photos_9r": 2,
    "qs:photos_all": 73,
    "qs:photos_sr": 2,
    "qs:placetype": "Town",
    "qs:pop_sr": "0",
    "wof:name": "Xikou",
    "wof:placetype": "locality"
  },
  "geometry": {
    "coordinates": [
      121.2761,
      29.680819
    ],
    "type": "Point"
  }
}