{
  "type": "Feature",
  "properties": {
    "gn:admin1_code": "2.0",
    "gn:asciiname": "Xiyu",
    "gn:country_code": "CN",
    "gn:dem": 275,
    "gn:feature_class": "P",
    "gn:feature_code": "PPL",
    "gn:name": "Xiyu",
    "gn:population": 0,
    "gn:timezone": "Asia/Shanghai",
    "iso:country": "CN",
    "name:zho_x_preferred": [
      "西域"
    ],
    "wof:name": "Xiyu",
    "wof:placetype": "locality"
  },
  "geometry": {
    "coordinates": [
      120.59385,
      29.53039
    ],
    "type": "Point"
  }
}