{
  "type": "Feature",
  "properties": {
    "gn:admin1_code": "19.0",
    "gn:asciiname": "Douling",
    "gn:country_code": "CN",
    "gn:dem": 213,
    "gn:feature_class": "P",
    "gn:feature_code": "PPL",
    "gn:name": "Douling",
    "gn:population": 0,
    "gn:timezone": "Asia/Shanghai",
    "iso:country": "CN",
    "name:zho_x_preferred": [
      "陡岭"
    ],
    "wof:name": "Douling",
    "wof:placetype": "locality"
  },
  "geometry": {
    "coordinates": [
      124.57847,
      42.36048
    ],
    "type": "Point"
  }
}