{
  "type": "Feature",
  "properties": {
    "gn:admin1_code": "26.0",
    "gn:asciiname": "Getacun",
    "gn:country_code": "CN",
    "gn:dem": 1065,
    "gn:feature_class": "P",
    "gn:feature_code": "PPL",
    "gn:name": "Getacun",
    "gn:population": 0,
    "gn:timezone": "Asia/Shanghai",
    "iso:country": "CN",
    "name:zho_x_preferred": [
      "圪塔村"
    ],
    "wof:name": "Getacun",
    "wof:placetype": "locality"
  },
  "geometry": {
    "coordinates": [
      109.79333,
      36.80719000000001
    ],
    "type": "Point"
  }
}