{
  "type": "Feature",
  "properties": {
    "gn:admin1_code": "8.0",
    "gn:asciiname": "Nonggong",
    "gn:country_code": "CN",
    "gn:dem": 228,
    "gn:feature_class": "P",
    "gn:feature_code": "PPLF",
    "gn:name": "Nonggong",
    "gn:population": 0,
    "gn:timezone": "Asia/Shanghai",
    "iso:country": "CN",
    "name:zho_x_preferred": [
      "农工"
    ],
    "wof:name": "Nonggong",
    "wof:placetype": "locality"
  },
  "geometry": {
    "coordinates": [
      129.2402,
      47.45939
    ],
    "type": "Point"
  }
}