{
  "type": "Feature",
  "properties": {
    "gn:admin1_code": "16.0",
    "gn:asciiname": "Xinglongchang",
    "gn:country_code": "CN",
    "gn:dem": 860,
    "gn:feature_class": "P",
    "gn:feature_code": "PPL",
    "gn:name": "Xinglongchang",
    "gn:population": 0,
    "gn:timezone": "Asia/Shanghai",
    "iso:country": "CN",
    "name:zho_x_preferred": [
      "兴隆场"
    ],
    "wof:name": "Xinglongchang",
    "wof:placetype": "locality"
  },
  "geometry": {
    "coordinates": [
      106.722,
      24.4925
    ],
    "type": "Point"
  }
}