{
  "type": "Feature",
  "properties": {
    "gn:admin1_code": "15.0",
    "gn:asciiname": "Shangjia",
    "gn:country_code": "CN",
    "gn:dem": 1298,
    "gn:feature_class": "P",
    "gn:feature_code": "PPL",
    "gn:name": "Shangjia",
    "gn:population": 0,
    "gn:timezone": "Asia/Shanghai",
    "iso:country": "CN",
    "name:zho_x_preferred": [
      "上甲"
    ],
    "wof:name": "Shangjia",
    "wof:placetype": "locality"
  },
  "geometry": {
    "coordinates": [
      106.79,
      35.4927
    ],
    "type": "Point"
  }
}