{
  "type": "Feature",
  "properties": {
    "gn:admin1_code": "26.0",
    "gn:asciiname": "Lijiayuan",
    "gn:country_code": "CN",
    "gn:dem": 1357,
    "gn:feature_class": "P",
    "gn:feature_code": "PPL",
    "gn:name": "Lijiayuan",
    "gn:population": 0,
    "gn:timezone": "Asia/Shanghai",
    "iso:country": "CN",
    "name:zho_x_preferred": [
      "李家园"
    ],
    "wof:name": "Lijiayuan",
    "wof:placetype": "locality"
  },
  "geometry": {
    "coordinates": [
      109.5955,
      34.01262
    ],
    "type": "Point"
  }
}