{
  "type": "Feature",
  "properties": {
    "gn:admin1_code": "22",
    "gn:asciiname": "Donggaocun",
    "gn:country_code": "CN",
    "gn:dem": 31,
    "gn:feature_class": "P",
    "gn:feature_code": "PPLA4",
    "gn:name": "Donggaocun",
    "gn:population": 0,
    "gn:timezone": "Asia/Shanghai",
    "iso:country": "CN",
    "name:und_x_variant": [
      "Tung-kao-chuang",
      "Tung-kao-ts’un",
      "Donggaocun",
      "Donggaocun Zhen"
    ],
    "name:zho_x_preferred": [
      "东高村"
    ],
    "name:zho_x_variant": [
      "东高村镇"
    ],
    "wof:name": "Donggaocun",
    "wof:placetype": "locality"
  },
  "geometry": {
    "coordinates": [
      117.1119,
      40.10653
    ],
    "type": "Point"
  }
}