{
  "type": "Feature",
  "properties": {
    "gn:admin1_code": "01",
    "gn:asciiname": "Tongcheng",
    "gn:country_code": "CN",
    "gn:dem": 18,
    "gn:feature_class": "P",
    "gn:feature_code": "PPLA4",
    "gn:name": "Tongcheng",
    "gn:population": 0,
    "gn:timezone": "Asia/Shanghai",
    "iso:country": "CN",
    "name:ceb_x_preferred": [
      "Tongcheng"
    ],
    "name:deu_x_preferred": [
      "Tongcheng"
    ],
    "name:eus_x_preferred": [
      "Tongcheng"
    ],
    "name:fra_x_preferred": [
      "Tongcheng"
    ],
    "name:nor_x_preferred": [
      "Tongcheng"
    ],
    "name:rus_x_preferred": [
      "Тунчэн"
    ],
    "name:swe_x_preferred": [
      "Tongcheng"
    ],
    "name:und_x_variant": [
      "T’ung-ch’eng-chen",
      "T’ung-ch’eng",
      "Tongcheng Zhen"
    ],
    "name:zho_x_preferred": [
      "铜城"
    ],
    "wof:name": "Tongcheng",
    "wof:placetype": "locality"
  },
  "geometry": {
    "coordinates": [
      118.93203,
      32.89848
    ],
    "type": "Point"
  }
}