{
  "type": "Feature",
  "properties": {
    "gn:admin1_code": "7",
    "gn:asciiname": "Yuyao",
    "gn:country_code": "CN",
    "gn:dem": 15,
    "gn:feature_class": "P",
    "gn:feature_code": "PPL",
    "gn:name": "Yuyao",
    "gn:population": 0,
    "gn:timezone": "Asia/Shanghai",
    "iso:country": "CN",
    "name:ceb_x_preferred": [
      "Yuyao"
    ],
    "name:deu_x_preferred": [
      "Yuyao"
    ],
    "name:fas_x_preferred": [
      "یویائو"
    ],
    "name:fra_x_preferred": [
      "Yuyao"
    ],
    "name:hak_x_preferred": [
      "Yì-yàu-sṳ"
    ],
    "name:ita_x_preferred": [
      "Yuyao"
    ],
    "name:jpn_x_preferred": [
      "余姚市"
    ],
    "name:kik_x_preferred": [
      "Yuyao"
    ],
    "name:kor_x_preferred": [
      "위야오시"
    ],
    "name:mlg_x_preferred": [
      "Yuyao"
    ],
    "name:nld_x_preferred": [
      "Yuyao"
    ],
    "name:nno_x_preferred": [
      "Yuyao"
    ],
    "name:nor_x_preferred": [
      "Yuyao"
    ],
    "name:rus_x_preferred": [
      "Юйяо"
    ],
    "name:spa_x_preferred": [
      "Yuyao"
    ],
    "name:swe_x_preferred": [
      "Yuyao"
    ],
    "name:tgl_x_preferred": [
      "Yuyao"
    ],
    "name:urd_x_preferred": [
      "یویو"
    ],
    "name:vie_x_preferred": [
      "Dư Diêu"
    ],
    "name:war_x_preferred": [
      "Yuyao"
    ],
    "name:wuu_x_preferred": [
      "余姚市"
    ],
    "name:zho_x_preferred": [
      "玉瑶"
    ],
    "name:zho_x_variant": [
      "余姚市"
    ],
    "wof:name": "Yuyao",
    "wof:placetype": "locality"
  },
  "geometry": {
    "coordinates": [
      119.56543,
      25.53164
    ],
    "type": "Point"
  }
}