{
  "type": "Feature",
  "properties": {
    "gn:admin1_code": "29.0",
    "gn:asciiname": "Nanbanshui",
    "gn:country_code": "CN",
    "gn:dem": 1757,
    "gn:feature_class": "P",
    "gn:feature_code": "PPL",
    "gn:name": "Nanbanshui",
    "gn:population": 0,
    "gn:timezone": "Asia/Shanghai",
    "iso:country": "CN",
    "name:zho_x_preferred": [
      "南班水"
    ],
    "wof:name": "Nanbanshui",
    "wof:placetype": "locality"
  },
  "geometry": {
    "coordinates": [
      99.262,
      24.2378
    ],
    "type": "Point"
  }
}