{
  "type": "Feature",
  "properties": {
    "gn:admin1_code": "12.0",
    "gn:asciiname": "Chenjiaxiang",
    "gn:country_code": "CN",
    "gn:dem": 44,
    "gn:feature_class": "P",
    "gn:feature_code": "PPL",
    "gn:name": "Chenjiaxiang",
    "gn:population": 0,
    "gn:timezone": "Asia/Shanghai",
    "iso:country": "CN",
    "name:zho_x_preferred": [
      "陈家巷"
    ],
    "wof:name": "Chenjiaxiang",
    "wof:placetype": "locality"
  },
  "geometry": {
    "coordinates": [
      113.95815,
      31.03291
    ],
    "type": "Point"
  }
}