{
  "type": "Feature",
  "properties": {
    "gn:country": "CN",
    "gn:fcode": "PPLA4",
    "gn:population": 0,
    "iso:country": "CN",
    "name:bul_x_preferred": [
      "Антин"
    ],
    "name:ceb_x_preferred": [
      "Anting"
    ],
    "name:deu_x_preferred": [
      "Anting"
    ],
    "name:eng_x_preferred": [
      "Anting"
    ],
    "name:fas_x_preferred": [
      "انتینگ"
    ],
    "name:fra_x_preferred": [
      "Anting"
    ],
    "name:gan_x_preferred": [
      "安亭镇"
    ],
    "name:jpn_x_preferred": [
      "安亭鎮"
    ],
    "name:nld_x_preferred": [
      "Anting"
    ],
    "name:swe_x_preferred": [
      "Anting"
    ],
    "name:ukr_x_preferred": [
      "Аньтін"
    ],
    "name:und_x_variant": [
      "An-t’ing-chen"
    ],
    "name:wuu_x_preferred": [
      "安亭镇"
    ],
    "name:zho_x_preferred": [
      "安亭镇"
    ],
    "qs:name": "Anting",
    "qs:photos_9r": 0,
    "qs:photos_sr": 0,
    "qs:pop_sr": "0",
    "wd:wordcount": 489,
    "wof:name": "Anting",
    "wof:placetype": "locality",
    "wof:population": 0
  },
  "geometry": {
    "coordinates": [
      121.1576,
      31.2989
    ],
    "type": "Point"
  }
}