{
  "type": "Feature",
  "properties": {
    "gn:admin1_code": "26.0",
    "gn:asciiname": "Liujiagetacun",
    "gn:country_code": "CN",
    "gn:dem": 979,
    "gn:feature_class": "P",
    "gn:feature_code": "PPL",
    "gn:name": "Liujiagetacun",
    "gn:population": 0,
    "gn:timezone": "Asia/Shanghai",
    "iso:country": "CN",
    "name:zho_x_preferred": [
      "刘家圪塔村"
    ],
    "wof:name": "Liujiagetacun",
    "wof:placetype": "locality"
  },
  "geometry": {
    "coordinates": [
      109.90598,
      36.90268
    ],
    "type": "Point"
  }
}