{
  "type": "Feature",
  "properties": {
    "gn:admin1_code": "19.0",
    "gn:asciiname": "Shanghangutun",
    "gn:country_code": "CN",
    "gn:dem": 240,
    "gn:feature_class": "P",
    "gn:feature_code": "PPL",
    "gn:name": "Shanghangutun",
    "gn:population": 0,
    "gn:timezone": "Asia/Shanghai",
    "iso:country": "CN",
    "name:zho_x_preferred": [
      "上韩古屯"
    ],
    "wof:name": "Shanghangutun",
    "wof:placetype": "locality"
  },
  "geometry": {
    "coordinates": [
      120.9126,
      42.07667
    ],
    "type": "Point"
  }
}