{
  "type": "Feature",
  "properties": {
    "gn:admin1_code": "10.0",
    "gn:asciiname": "Tieling",
    "gn:country_code": "CN",
    "gn:dem": 291,
    "gn:feature_class": "P",
    "gn:feature_code": "PPL",
    "gn:name": "Tieling",
    "gn:population": 0,
    "gn:timezone": "Asia/Shanghai",
    "iso:country": "CN",
    "name:afr_x_preferred": [
      "Tieling"
    ],
    "name:ara_x_preferred": [
      "تيلينغ"
    ],
    "name:cdo_x_preferred": [
      "Tiék-liāng"
    ],
    "name:ceb_x_preferred": [
      "Tieling Shi"
    ],
    "name:ces_x_preferred": [
      "Tchie-ling"
    ],
    "name:dan_x_preferred": [
      "Tieling"
    ],
    "name:deu_x_preferred": [
      "Tieling"
    ],
    "name:eus_x_preferred": [
      "Tieling"
    ],
    "name:fas_x_preferred": [
      "تیلینگ"
    ],
    "name:fin_x_preferred": [
      "Tieling"
    ],
    "name:fra_x_preferred": [
      "Tieling"
    ],
    "name:heb_x_preferred": [
      "טיאלינג"
    ],
    "name:hun_x_preferred": [
      "Tieling"
    ],
    "name:ita_x_preferred": [
      "Tieling"
    ],
    "name:jpn_x_preferred": [
      "鉄嶺市"
    ],
    "name:kik_x_preferred": [
      "Tieling"
    ],
    "name:kor_x_preferred": [
      "톄링시"
    ],
    "name:mlg_x_preferred": [
      "Tieling"
    ],
    "name:nld_x_preferred": [
      "Tieling"
    ],
    "name:nno_x_preferred": [
      "Tieling"
    ],
    "name:nor_x_preferred": [
      "Tieling"
    ],
    "name:pol_x_preferred": [
      "Tieling"
    ],
    "name:rus_x_preferred": [
      "Телин"
    ],
    "name:spa_x_preferred": [
      "Tieling"
    ],
    "name:srp_x_preferred": [
      "Тјелинг"
    ],
    "name:swe_x_preferred": [
      "Tieling"
    ],
    "name:tur_x_preferred": [
      "Tieling"
    ],
    "name:und_x_variant": [
      "铁岭"
    ],
    "name:urd_x_preferred": [
      "تیئلنگ"
    ],
    "name:vie_x_preferred": [
      "Thiết Lĩnh"
    ],
    "name:war_x_preferred": [
      "Tieling"
    ],
    "name:wuu_x_preferred": [
      "铁岭市"
    ],
    "name:zho_x_preferred": [
      "铁岭市"
    ],
    "wof:name": "Tieling",
    "wof:placetype": "locality"
  },
  "geometry": {
    "coordinates": [
      114.43836,
      38.81709
    ],
    "type": "Point"
  }
}