{
  "type": "Feature",
  "properties": {
    "gn:admin1_code": "7",
    "gn:asciiname": "Puning",
    "gn:country_code": "CN",
    "gn:dem": 187,
    "gn:feature_class": "P",
    "gn:feature_code": "PPL",
    "gn:name": "Puning",
    "gn:population": 0,
    "gn:timezone": "Asia/Shanghai",
    "iso:country": "CN",
    "name:ara_x_preferred": [
      "بينينغ"
    ],
    "name:ceb_x_preferred": [
      "Puning"
    ],
    "name:ces_x_preferred": [
      "Pchu-ning"
    ],
    "name:deu_x_preferred": [
      "Puning"
    ],
    "name:fas_x_preferred": [
      "پونینگ"
    ],
    "name:fin_x_preferred": [
      "Puning"
    ],
    "name:fra_x_preferred": [
      "Puning"
    ],
    "name:ind_x_preferred": [
      "Puning"
    ],
    "name:ita_x_preferred": [
      "Puning"
    ],
    "name:jpn_x_preferred": [
      "普寧市"
    ],
    "name:kik_x_preferred": [
      "Puning"
    ],
    "name:kor_x_preferred": [
      "푸닝시"
    ],
    "name:mlg_x_preferred": [
      "Puning"
    ],
    "name:mwl_x_preferred": [
      "Puning"
    ],
    "name:nor_x_preferred": [
      "Puning"
    ],
    "name:pam_x_preferred": [
      "Puning"
    ],
    "name:pnb_x_preferred": [
      "پونینگ"
    ],
    "name:swe_x_preferred": [
      "Puning"
    ],
    "name:und_x_variant": [
      "埔宁"
    ],
    "name:urd_x_preferred": [
      "پونینگ"
    ],
    "name:vie_x_preferred": [
      "Phổ Ninh"
    ],
    "name:zho_x_preferred": [
      "普宁市"
    ],
    "wof:name": "Puning",
    "wof:placetype": "locality"
  },
  "geometry": {
    "coordinates": [
      118.33359,
      26.17316
    ],
    "type": "Point"
  }
}