{
  "type": "Feature",
  "properties": {
    "gn:admin1_code": "26.0",
    "gn:asciiname": "Yanfangping",
    "gn:country_code": "CN",
    "gn:dem": 1485,
    "gn:feature_class": "P",
    "gn:feature_code": "PPL",
    "gn:name": "Yanfangping",
    "gn:population": 0,
    "gn:timezone": "Asia/Shanghai",
    "iso:country": "CN",
    "name:und_x_variant": [
      "岩房坪"
    ],
    "wof:name": "Yanfangping",
    "wof:placetype": "locality"
  },
  "geometry": {
    "coordinates": [
      106.86566,
      32.74006
    ],
    "type": "Point"
  }
}