{
  "type": "Feature",
  "properties": {
    "gn:admin1_code": "2.0",
    "gn:asciiname": "Jinzhong",
    "gn:country_code": "CN",
    "gn:dem": 111,
    "gn:feature_class": "P",
    "gn:feature_code": "PPL",
    "gn:name": "Jinzhong",
    "gn:population": 0,
    "gn:timezone": "Asia/Shanghai",
    "iso:country": "CN",
    "name:ara_x_preferred": [
      "جينتشونغ"
    ],
    "name:bre_x_preferred": [
      "Jinzhong"
    ],
    "name:cdo_x_preferred": [
      "Céng-dṳ̆ng"
    ],
    "name:ceb_x_preferred": [
      "Jinzhong Shi"
    ],
    "name:ces_x_preferred": [
      "Ťin-čung"
    ],
    "name:dan_x_preferred": [
      "Jinzhong"
    ],
    "name:deu_x_preferred": [
      "Jinzhong"
    ],
    "name:eus_x_preferred": [
      "Jinzhong"
    ],
    "name:fas_x_preferred": [
      "جینجونگ"
    ],
    "name:fin_x_preferred": [
      "Jinzhong"
    ],
    "name:fra_x_preferred": [
      "Jinzhong"
    ],
    "name:ita_x_preferred": [
      "Jinzhong"
    ],
    "name:jpn_x_preferred": [
      "晋中市"
    ],
    "name:kik_x_preferred": [
      "Jinzhong"
    ],
    "name:kor_x_preferred": [
      "진중시"
    ],
    "name:mlg_x_preferred": [
      "Jinzhong"
    ],
    "name:nld_x_preferred": [
      "Jinzhong"
    ],
    "name:nno_x_preferred": [
      "Jinzhong"
    ],
    "name:nor_x_preferred": [
      "Jinzhong"
    ],
    "name:pol_x_preferred": [
      "Jinzhong"
    ],
    "name:rus_x_preferred": [
      "Цзиньчжун"
    ],
    "name:spa_x_preferred": [
      "Jinzhong"
    ],
    "name:swe_x_preferred": [
      "Jinzhong"
    ],
    "name:tur_x_preferred": [
      "Jinzhong"
    ],
    "name:und_x_variant": [
      "金钟"
    ],
    "name:urd_x_preferred": [
      "جنژونگ"
    ],
    "name:vie_x_preferred": [
      "Tấn Trung"
    ],
    "name:war_x_preferred": [
      "Jinzhong"
    ],
    "name:wuu_x_preferred": [
      "晋中市"
    ],
    "name:zho_x_preferred": [
      "晋中市"
    ],
    "wof:name": "Jinzhong",
    "wof:placetype": "locality"
  },
  "geometry": {
    "coordinates": [
      119.3804,
      29.35469
    ],
    "type": "Point"
  }
}