{
  "type": "Feature",
  "properties": {
    "gn:admin1_code": "11.0",
    "gn:asciiname": "Wujiazhai",
    "gn:country_code": "CN",
    "gn:dem": 573,
    "gn:feature_class": "P",
    "gn:feature_code": "PPL",
    "gn:name": "Wujiazhai",
    "gn:population": 0,
    "gn:timezone": "Asia/Shanghai",
    "iso:country": "CN",
    "name:zho_x_preferred": [
      "吴家寨"
    ],
    "wof:name": "Wujiazhai",
    "wof:placetype": "locality"
  },
  "geometry": {
    "coordinates": [
      109.42041,
      28.39494
    ],
    "type": "Point"
  }
}