{
  "type": "Feature",
  "properties": {
    "gn:admin1_code": "18.0",
    "gn:asciiname": "Xiaodifang",
    "gn:country_code": "CN",
    "gn:dem": 1092,
    "gn:feature_class": "P",
    "gn:feature_code": "PPL",
    "gn:name": "Xiaodifang",
    "gn:population": 0,
    "gn:timezone": "Asia/Shanghai",
    "iso:country": "CN",
    "name:zho_x_preferred": [
      "小地方"
    ],
    "wof:name": "Xiaodifang",
    "wof:placetype": "locality"
  },
  "geometry": {
    "coordinates": [
      107.129,
      26.3213
    ],
    "type": "Point"
  }
}