{
  "type": "Feature",
  "properties": {
    "gn:admin1_code": "31.0",
    "gn:asciiname": "Donghong Ershisidui",
    "gn:country_code": "CN",
    "gn:dem": 106,
    "gn:feature_class": "P",
    "gn:feature_code": "PPLF",
    "gn:name": "Donghong Ershisidui",
    "gn:population": 0,
    "gn:timezone": "Asia/Shanghai",
    "iso:country": "CN",
    "name:und_x_variant": [
      "东红二四队"
    ],
    "wof:name": "Donghong Ershisidui",
    "wof:placetype": "locality"
  },
  "geometry": {
    "coordinates": [
      110.52335,
      19.4582
    ],
    "type": "Point"
  }
}