{
  "type": "Feature",
  "properties": {
    "gn:admin1_code": "26.0",
    "gn:asciiname": "Shequ",
    "gn:country_code": "CN",
    "gn:dem": 1516,
    "gn:feature_class": "P",
    "gn:feature_code": "PPL",
    "gn:name": "Shequ",
    "gn:population": 0,
    "gn:timezone": "Asia/Shanghai",
    "iso:country": "CN",
    "name:deu_x_preferred": [
      "Einwohnergemeinschaft"
    ],
    "name:rus_x_preferred": [
      "Микрорайон"
    ],
    "name:uig_x_preferred": [
      "مەھەللە"
    ],
    "name:zho_x_preferred": [
      "佘渠"
    ],
    "name:zho_x_variant": [
      "社区"
    ],
    "wof:name": "Shequ",
    "wof:placetype": "locality"
  },
  "geometry": {
    "coordinates": [
      108.02331,
      37.4044
    ],
    "type": "Point"
  }
}