{
  "type": "Feature",
  "properties": {
    "gn:admin1_code": "16.0",
    "gn:asciiname": "Pingliang",
    "gn:country_code": "CN",
    "gn:dem": 520,
    "gn:feature_class": "P",
    "gn:feature_code": "PPL",
    "gn:name": "Pingliang",
    "gn:population": 0,
    "gn:timezone": "Asia/Shanghai",
    "iso:country": "CN",
    "name:ara_x_preferred": [
      "بينغليانغ"
    ],
    "name:ast_x_preferred": [
      "Pingliang"
    ],
    "name:cdo_x_preferred": [
      "Bìng-liòng"
    ],
    "name:ceb_x_preferred": [
      "Pingliang"
    ],
    "name:ces_x_preferred": [
      "Pching-liang"
    ],
    "name:dan_x_preferred": [
      "Pingliang"
    ],
    "name:deu_x_preferred": [
      "Pingliang"
    ],
    "name:eus_x_preferred": [
      "Pingliang"
    ],
    "name:fas_x_preferred": [
      "پینگلیانگ"
    ],
    "name:fin_x_preferred": [
      "Pingliang"
    ],
    "name:fra_x_preferred": [
      "Pingliang"
    ],
    "name:heb_x_preferred": [
      "פינליאנג"
    ],
    "name:hun_x_preferred": [
      "Pingliang"
    ],
    "name:hye_x_preferred": [
      "Պիլիան"
    ],
    "name:ita_x_preferred": [
      "Pingliang"
    ],
    "name:jpn_x_preferred": [
      "平涼市"
    ],
    "name:kik_x_preferred": [
      "Pingliang"
    ],
    "name:kor_x_preferred": [
      "핑량시"
    ],
    "name:mlg_x_preferred": [
      "Pingliang"
    ],
    "name:nld_x_preferred": [
      "Pingliang"
    ],
    "name:nno_x_preferred": [
      "Pingliang"
    ],
    "name:nor_x_preferred": [
      "Pingliang"
    ],
    "name:pam_x_preferred": [
      "Pingliang"
    ],
    "name:pnb_x_preferred": [
      "پنگلیانگ"
    ],
    "name:pol_x_preferred": [
      "Pingliang"
    ],
    "name:por_x_preferred": [
      "Pingliang"
    ],
    "name:rus_x_preferred": [
      "Пинлян"
    ],
    "name:spa_x_preferred": [
      "Pingliang"
    ],
    "name:swe_x_preferred": [
      "Pingliang"
    ],
    "name:tgl_x_preferred": [
      "Pingliang"
    ],
    "name:tur_x_preferred": [
      "Pingliang"
    ],
    "name:urd_x_preferred": [
      "پنگلیانگ"
    ],
    "name:vie_x_preferred": [
      "Bình Lương"
    ],
    "name:war_x_preferred": [
      "Pingliang"
    ],
    "name:wuu_x_preferred": [
      "平凉市"
    ],
    "name:zho_x_preferred": [
      "平量"
    ],
    "name:zho_x_variant": [
      "平凉市"
    ],
    "wof:name": "Pingliang",
    "wof:placetype": "locality"
  },
  "geometry": {
    "coordinates": [
      106.897,
      23.2723
    ],
    "type": "Point"
  }
}