{
  "type": "Feature",
  "properties": {
    "gn:admin1_code": "12.0",
    "gn:asciiname": "Xinyang",
    "gn:country_code": "CN",
    "gn:dem": 909,
    "gn:feature_class": "P",
    "gn:feature_code": "PPL",
    "gn:name": "Xinyang",
    "gn:population": 0,
    "gn:timezone": "Asia/Shanghai",
    "iso:country": "CN",
    "name:afr_x_preferred": [
      "Xinyang"
    ],
    "name:ara_x_preferred": [
      "شينيانج"
    ],
    "name:bul_x_preferred": [
      "Синян"
    ],
    "name:cat_x_preferred": [
      "Xinyang"
    ],
    "name:cdo_x_preferred": [
      "Séng-iòng"
    ],
    "name:ceb_x_preferred": [
      "Xinyang"
    ],
    "name:ces_x_preferred": [
      "Sin-jang"
    ],
    "name:dan_x_preferred": [
      "Xinyang"
    ],
    "name:deu_x_preferred": [
      "Xinyang"
    ],
    "name:epo_x_preferred": [
      "Ŝjinjango"
    ],
    "name:eus_x_preferred": [
      "Xinyang"
    ],
    "name:fas_x_preferred": [
      "شین‌یانگ"
    ],
    "name:fin_x_preferred": [
      "Xinyang"
    ],
    "name:fra_x_preferred": [
      "Xinyang"
    ],
    "name:heb_x_preferred": [
      "קסיניאנג"
    ],
    "name:ind_x_preferred": [
      "Xinyang"
    ],
    "name:ita_x_preferred": [
      "Xinyang"
    ],
    "name:jpn_x_preferred": [
      "信陽市"
    ],
    "name:kor_x_preferred": [
      "신양시"
    ],
    "name:lit_x_preferred": [
      "Sinjangas"
    ],
    "name:mlg_x_preferred": [
      "Xinyang"
    ],
    "name:nld_x_preferred": [
      "Xinyang"
    ],
    "name:nno_x_preferred": [
      "Xinyang"
    ],
    "name:nor_x_preferred": [
      "Xinyang"
    ],
    "name:pam_x_preferred": [
      "Xinyang"
    ],
    "name:pol_x_preferred": [
      "Xinyang"
    ],
    "name:por_x_preferred": [
      "Xinyang"
    ],
    "name:rus_x_preferred": [
      "Синьян"
    ],
    "name:spa_x_preferred": [
      "Xinyang"
    ],
    "name:srp_x_preferred": [
      "Синјанг"
    ],
    "name:swe_x_preferred": [
      "Xinyang"
    ],
    "name:tur_x_preferred": [
      "Xinyang"
    ],
    "name:uig_x_preferred": [
      "Shinyang shehiri"
    ],
    "name:urd_x_preferred": [
      "شنیانگ"
    ],
    "name:vie_x_preferred": [
      "Tín Dương"
    ],
    "name:war_x_preferred": [
      "Xinyang"
    ],
    "name:wuu_x_preferred": [
      "信阳市"
    ],
    "name:zho_x_preferred": [
      "新阳"
    ],
    "name:zho_x_variant": [
      "信阳市"
    ],
    "wof:name": "Xinyang",
    "wof:placetype": "locality"
  },
  "geometry": {
    "coordinates": [
      108.75971,
      29.94692
    ],
    "type": "Point"
  }
}