{
  "type": "Feature",
  "properties": {
    "gn:admin1_code": "26.0",
    "gn:asciiname": "Cangfangling",
    "gn:country_code": "CN",
    "gn:dem": 1087,
    "gn:feature_class": "P",
    "gn:feature_code": "PPL",
    "gn:name": "Cangfangling",
    "gn:population": 0,
    "gn:timezone": "Asia/Shanghai",
    "iso:country": "CN",
    "name:zho_x_preferred": [
      "仓房岭"
    ],
    "wof:name": "Cangfangling",
    "wof:placetype": "locality"
  },
  "geometry": {
    "coordinates": [
      109.19442,
      33.18510999999999
    ],
    "type": "Point"
  }
}