{
  "type": "Feature",
  "properties": {
    "gn:admin1_code": "13.0",
    "gn:asciiname": "Sarbulak",
    "gn:cc2": "CN",
    "gn:country_code": "CN",
    "gn:dem": 868,
    "gn:feature_class": "P",
    "gn:feature_code": "PPL",
    "gn:name": "Sarbulak",
    "gn:population": 0,
    "gn:timezone": "Asia/Shanghai",
    "iso:country": "CN",
    "name:uig_x_preferred": [
      "Sarbulak̩"
    ],
    "name:uig_x_variant": [
      "Sarbulaq",
      "ساربۇلاق",
      "Сарбулақ"
    ],
    "name:und_x_variant": [
      "Sarbulak Xiang",
      "Sarbulak"
    ],
    "wof:name": "Sarbulak",
    "wof:placetype": "locality"
  },
  "geometry": {
    "coordinates": [
      81.03639,
      44.21194000000001
    ],
    "type": "Point"
  }
}