{
  "type": "Feature",
  "properties": {
    "gn:admin1_code": "8.0",
    "gn:asciiname": "Gaoshengtun",
    "gn:country_code": "CN",
    "gn:dem": 91,
    "gn:feature_class": "P",
    "gn:feature_code": "PPL",
    "gn:name": "Gaoshengtun",
    "gn:population": 0,
    "gn:timezone": "Asia/Shanghai",
    "iso:country": "CN",
    "name:zho_x_preferred": [
      "高升屯"
    ],
    "wof:name": "Gaoshengtun",
    "wof:placetype": "locality"
  },
  "geometry": {
    "coordinates": [
      130.14875,
      48.91079000000001
    ],
    "type": "Point"
  }
}