{
  "type": "Feature",
  "properties": {
    "gn:admin1_code": "19.0",
    "gn:asciiname": "Shi'ertaigou",
    "gn:country_code": "CN",
    "gn:dem": 210,
    "gn:feature_class": "P",
    "gn:feature_code": "PPL",
    "gn:name": "Shi’ertaigou",
    "gn:population": 0,
    "gn:timezone": "Asia/Shanghai",
    "iso:country": "CN",
    "name:zho_x_preferred": [
      "Shi’ertaigou"
    ],
    "name:zho_x_variant": [
      "十二台沟"
    ],
    "wof:name": "Shi'ertaigou",
    "wof:placetype": "locality"
  },
  "geometry": {
    "coordinates": [
      120.95702,
      41.78558
    ],
    "type": "Point"
  }
}