{
  "type": "Feature",
  "properties": {
    "gn:admin1_code": "16.0",
    "gn:asciiname": "Nata",
    "gn:country_code": "CN",
    "gn:dem": 503,
    "gn:feature_class": "P",
    "gn:feature_code": "PPL",
    "gn:name": "Nata",
    "gn:population": 0,
    "gn:timezone": "Asia/Shanghai",
    "iso:country": "CN",
    "name:ara_x_preferred": [
      "ناتا"
    ],
    "name:ben_x_preferred": [
      "নাতা"
    ],
    "name:ceb_x_preferred": [
      "Nata"
    ],
    "name:deu_x_preferred": [
      "Nata"
    ],
    "name:ell_x_preferred": [
      "Νάτα"
    ],
    "name:fra_x_preferred": [
      "Nata"
    ],
    "name:glg_x_preferred": [
      "Nata"
    ],
    "name:heb_x_preferred": [
      "נטה"
    ],
    "name:hin_x_preferred": [
      "नाता"
    ],
    "name:ita_x_preferred": [
      "Nata"
    ],
    "name:kor_x_preferred": [
      "나타"
    ],
    "name:por_x_preferred": [
      "Nata"
    ],
    "name:spa_x_preferred": [
      "Nata"
    ],
    "name:swe_x_preferred": [
      "Nata"
    ],
    "name:tur_x_preferred": [
      "Nata"
    ],
    "name:ukr_x_preferred": [
      "Ната"
    ],
    "name:urd_x_preferred": [
      "نیٹا"
    ],
    "name:zho_x_preferred": [
      "那他"
    ],
    "wof:name": "Nata",
    "wof:placetype": "locality"
  },
  "geometry": {
    "coordinates": [
      105.439,
      24.7625
    ],
    "type": "Point"
  }
}