{
  "type": "Feature",
  "properties": {
    "gn:admin1_code": "8.0",
    "gn:asciiname": "Wanhecun",
    "gn:country_code": "CN",
    "gn:dem": 167,
    "gn:feature_class": "P",
    "gn:feature_code": "PPL",
    "gn:name": "Wanhecun",
    "gn:population": 0,
    "gn:timezone": "Asia/Shanghai",
    "iso:country": "CN",
    "name:zho_x_preferred": [
      "万合村"
    ],
    "wof:name": "Wanhecun",
    "wof:placetype": "locality"
  },
  "geometry": {
    "coordinates": [
      127.111,
      46.36937
    ],
    "type": "Point"
  }
}