{
  "type": "Feature",
  "properties": {
    "gn:admin1_code": "19.0",
    "gn:asciiname": "Zhaojiatun",
    "gn:country_code": "CN",
    "gn:dem": 29,
    "gn:feature_class": "P",
    "gn:feature_code": "PPL",
    "gn:name": "Zhaojiatun",
    "gn:population": 0,
    "gn:timezone": "Asia/Shanghai",
    "iso:country": "CN",
    "name:zho_x_preferred": [
      "赵家屯"
    ],
    "wof:name": "Zhaojiatun",
    "wof:placetype": "locality"
  },
  "geometry": {
    "coordinates": [
      122.535,
      39.3023
    ],
    "type": "Point"
  }
}