{
  "type": "Feature",
  "properties": {
    "gn:admin1_code": "16",
    "gn:asciiname": "Chuanshan",
    "gn:cc2": "CN",
    "gn:country_code": "CN",
    "gn:dem": 91,
    "gn:feature_class": "P",
    "gn:feature_code": "PPL",
    "gn:name": "Chuanshan",
    "gn:population": 0,
    "gn:timezone": "Asia/Shanghai",
    "iso:country": "CN",
    "name:und_x_variant": [
      "Chwanshan",
      "Ch’uan-shan-hsü",
      "Chuanshan"
    ],
    "wof:name": "Chuanshan",
    "wof:placetype": "locality"
  },
  "geometry": {
    "coordinates": [
      109.40222,
      24.03472
    ],
    "type": "Point"
  }
}