{
  "type": "Feature",
  "properties": {
    "gn:admin1_code": "12.0",
    "gn:asciiname": "Xinwuxia",
    "gn:country_code": "CN",
    "gn:dem": 51,
    "gn:feature_class": "P",
    "gn:feature_code": "PPL",
    "gn:name": "Xinwuxia",
    "gn:population": 0,
    "gn:timezone": "Asia/Shanghai",
    "iso:country": "CN",
    "name:zho_x_preferred": [
      "Xinwuxia"
    ],
    "name:zho_x_variant": [
      "新屋下"
    ],
    "wof:name": "Xinwuxia",
    "wof:placetype": "locality"
  },
  "geometry": {
    "coordinates": [
      114.99537,
      30.06225
    ],
    "type": "Point"
  }
}