{
  "type": "Feature",
  "properties": {
    "gn:admin1_code": "18",
    "gn:asciiname": "Tuchangping",
    "gn:country_code": "CN",
    "gn:dem": 1123,
    "gn:feature_class": "P",
    "gn:feature_code": "PPL",
    "gn:name": "Tuchangping",
    "gn:population": 0,
    "gn:timezone": "Asia/Shanghai",
    "iso:country": "CN",
    "name:zho_x_preferred": [
      "兔场坪"
    ],
    "wof:name": "Tuchangping",
    "wof:placetype": "locality"
  },
  "geometry": {
    "coordinates": [
      105.066,
      26.0477
    ],
    "type": "Point"
  }
}