{
  "type": "Feature",
  "properties": {
    "gn:admin1_code": "02",
    "gn:asciiname": "Shanghuangqiaocun",
    "gn:country_code": "CN",
    "gn:dem": 334,
    "gn:feature_class": "P",
    "gn:feature_code": "PPL",
    "gn:name": "Shanghuangqiaocun",
    "gn:population": 0,
    "gn:timezone": "Asia/Shanghai",
    "iso:country": "CN",
    "name:und_x_variant": [
      "Shang-huang-ch’iao",
      "Shanghuangqiao",
      "Shanghuangqiaocun"
    ],
    "name:zho_x_preferred": [
      "尚黄桥"
    ],
    "name:zho_x_variant": [
      "尚黄桥村"
    ],
    "wof:name": "Shanghuangqiaocun",
    "wof:placetype": "locality"
  },
  "geometry": {
    "coordinates": [
      120.28229,
      28.9411
    ],
    "type": "Point"
  }
}