{
  "type": "Feature",
  "properties": {
    "gn:admin1_code": "12.0",
    "gn:asciiname": "Chenjiayuan",
    "gn:country_code": "CN",
    "gn:dem": 25,
    "gn:feature_class": "P",
    "gn:feature_code": "PPL",
    "gn:name": "Chenjiayuan",
    "gn:population": 0,
    "gn:timezone": "Asia/Shanghai",
    "iso:country": "CN",
    "name:zho_x_preferred": [
      "陈家渊"
    ],
    "wof:name": "Chenjiayuan",
    "wof:placetype": "locality"
  },
  "geometry": {
    "coordinates": [
      113.11358,
      29.9713
    ],
    "type": "Point"
  }
}