{
  "type": "Feature",
  "properties": {
    "gn:admin1_code": "30.0",
    "gn:asciiname": "Tianliao Xincun",
    "gn:country_code": "CN",
    "gn:dem": 0,
    "gn:feature_class": "P",
    "gn:feature_code": "PPL",
    "gn:name": "Tianliao Xincun",
    "gn:population": 0,
    "gn:timezone": "Asia/Shanghai",
    "iso:country": "CN",
    "name:zho_x_preferred": [
      "田寮新村"
    ],
    "wof:name": "Tianliao Xincun",
    "wof:placetype": "locality"
  },
  "geometry": {
    "coordinates": [
      113.05755,
      22.32223
    ],
    "type": "Point"
  }
}