{
  "type": "Feature",
  "properties": {
    "gn:admin1_code": "32.0",
    "gn:asciiname": "Jinhua",
    "gn:country_code": "CN",
    "gn:dem": 498,
    "gn:feature_class": "P",
    "gn:feature_code": "PPL",
    "gn:name": "Jinhua",
    "gn:population": 0,
    "gn:timezone": "Asia/Shanghai",
    "iso:country": "CN",
    "name:afr_x_preferred": [
      "Jinhua"
    ],
    "name:ara_x_preferred": [
      "جينهوا"
    ],
    "name:cdo_x_preferred": [
      "Gĭng-huà"
    ],
    "name:ceb_x_preferred": [
      "Jinhua"
    ],
    "name:ces_x_preferred": [
      "Ťin-chua"
    ],
    "name:dan_x_preferred": [
      "Jinhua"
    ],
    "name:deu_x_preferred": [
      "Jinhua"
    ],
    "name:est_x_preferred": [
      "Jinhua"
    ],
    "name:eus_x_preferred": [
      "Jinhua"
    ],
    "name:fas_x_preferred": [
      "جینهوا"
    ],
    "name:fin_x_preferred": [
      "Jinhua"
    ],
    "name:fra_x_preferred": [
      "Jinhua"
    ],
    "name:hak_x_preferred": [
      "Kîm-fà-sṳ"
    ],
    "name:hun_x_preferred": [
      "Jinhua"
    ],
    "name:ind_x_preferred": [
      "Jinhua"
    ],
    "name:ita_x_preferred": [
      "Jinhua"
    ],
    "name:jpn_x_preferred": [
      "金華市"
    ],
    "name:kik_x_preferred": [
      "Jinhua"
    ],
    "name:kor_x_preferred": [
      "진화시"
    ],
    "name:mlg_x_preferred": [
      "Jinhua"
    ],
    "name:nld_x_preferred": [
      "Jinhua"
    ],
    "name:nno_x_preferred": [
      "Jinhua"
    ],
    "name:nor_x_preferred": [
      "Jinhua"
    ],
    "name:pol_x_preferred": [
      "Jinhua"
    ],
    "name:rus_x_preferred": [
      "Цзиньхуа"
    ],
    "name:spa_x_preferred": [
      "Jinhua"
    ],
    "name:swe_x_preferred": [
      "Jinhua"
    ],
    "name:tgl_x_preferred": [
      "Jinhua"
    ],
    "name:tur_x_preferred": [
      "Jinhua"
    ],
    "name:urd_x_preferred": [
      "جنہوا"
    ],
    "name:vie_x_preferred": [
      "Kim Hoa"
    ],
    "name:war_x_preferred": [
      "Jinhua"
    ],
    "name:wuu_x_preferred": [
      "金華市"
    ],
    "name:zho_x_preferred": [
      "金花"
    ],
    "name:zho_x_variant": [
      "金华市"
    ],
    "wof:name": "Jinhua",
    "wof:placetype": "locality"
  },
  "geometry": {
    "coordinates": [
      104.15097,
      29.22951
    ],
    "type": "Point"
  }
}