{
  "type": "Feature",
  "properties": {
    "gn:admin1_code": "19.0",
    "gn:asciiname": "Mu'ergangzi",
    "gn:country_code": "CN",
    "gn:dem": 21,
    "gn:feature_class": "P",
    "gn:feature_code": "PPL",
    "gn:name": "Mu’ergangzi",
    "gn:population": 0,
    "gn:timezone": "Asia/Shanghai",
    "iso:country": "CN",
    "name:zho_x_preferred": [
      "Mu’ergangzi"
    ],
    "name:zho_x_variant": [
      "木耳岗子"
    ],
    "wof:name": "Mu'ergangzi",
    "wof:placetype": "locality"
  },
  "geometry": {
    "coordinates": [
      122.88039,
      41.63865
    ],
    "type": "Point"
  }
}