{
  "type": "Feature",
  "properties": {
    "gn:admin1_code": "8.0",
    "gn:asciiname": "Lida",
    "gn:country_code": "CN",
    "gn:dem": 131,
    "gn:feature_class": "P",
    "gn:feature_code": "PPL",
    "gn:name": "Lida",
    "gn:population": 0,
    "gn:timezone": "Asia/Shanghai",
    "iso:country": "CN",
    "name:ara_x_preferred": [
      "ليدا"
    ],
    "name:aze_x_preferred": [
      "Lida"
    ],
    "name:bel_x_preferred": [
      "Ліда"
    ],
    "name:bul_x_preferred": [
      "Лида"
    ],
    "name:ceb_x_preferred": [
      "Lida"
    ],
    "name:ces_x_preferred": [
      "Lida"
    ],
    "name:che_x_preferred": [
      "Лида"
    ],
    "name:dan_x_preferred": [
      "Lida"
    ],
    "name:deu_x_preferred": [
      "Lida"
    ],
    "name:dsb_x_preferred": [
      "Lida"
    ],
    "name:epo_x_preferred": [
      "Lida"
    ],
    "name:est_x_preferred": [
      "Łida"
    ],
    "name:fas_x_preferred": [
      "لیدا"
    ],
    "name:fin_x_preferred": [
      "Lida"
    ],
    "name:fra_x_preferred": [
      "Lida"
    ],
    "name:frr_x_preferred": [
      "Lida"
    ],
    "name:heb_x_preferred": [
      "לידא"
    ],
    "name:hrv_x_preferred": [
      "Lida"
    ],
    "name:hsb_x_preferred": [
      "Lida"
    ],
    "name:hun_x_preferred": [
      "Lida"
    ],
    "name:ita_x_preferred": [
      "Lida"
    ],
    "name:kat_x_preferred": [
      "ლიდა"
    ],
    "name:lav_x_preferred": [
      "Ļida"
    ],
    "name:lit_x_preferred": [
      "Lyda"
    ],
    "name:mar_x_preferred": [
      "लिडा"
    ],
    "name:nld_x_preferred": [
      "Lida"
    ],
    "name:nor_x_preferred": [
      "Lida"
    ],
    "name:pol_x_preferred": [
      "Lida"
    ],
    "name:rus_x_preferred": [
      "Лида"
    ],
    "name:spa_x_preferred": [
      "Lida"
    ],
    "name:sqi_x_preferred": [
      "Lida"
    ],
    "name:srp_x_preferred": [
      "Лида"
    ],
    "name:swe_x_preferred": [
      "Lida"
    ],
    "name:szl_x_preferred": [
      "Lida"
    ],
    "name:tat_x_preferred": [
      "Лида"
    ],
    "name:tur_x_preferred": [
      "Lida"
    ],
    "name:udm_x_preferred": [
      "Лида"
    ],
    "name:ukr_x_preferred": [
      "Ліда"
    ],
    "name:urd_x_preferred": [
      "لیدا"
    ],
    "name:war_x_preferred": [
      "Lida"
    ],
    "name:yid_x_preferred": [
      "לידא"
    ],
    "name:zho_x_preferred": [
      "利达"
    ],
    "wof:name": "Lida",
    "wof:placetype": "locality"
  },
  "geometry": {
    "coordinates": [
      127.26403,
      45.94057
    ],
    "type": "Point"
  }
}