{
  "type": "Feature",
  "properties": {
    "gn:admin1_code": "3.0",
    "gn:asciiname": "Qianyeshan",
    "gn:country_code": "CN",
    "gn:dem": 52,
    "gn:feature_class": "P",
    "gn:feature_code": "PPL",
    "gn:name": "Qianyeshan",
    "gn:population": 0,
    "gn:timezone": "Asia/Shanghai",
    "iso:country": "CN",
    "name:und_x_variant": [
      "千叶山"
    ],
    "wof:name": "Qianyeshan",
    "wof:placetype": "locality"
  },
  "geometry": {
    "coordinates": [
      115.16643,
      28.13537
    ],
    "type": "Point"
  }
}