{
  "type": "Feature",
  "properties": {
    "gn:admin1_code": "16.0",
    "gn:asciiname": "Xiakou",
    "gn:country_code": "CN",
    "gn:dem": 197,
    "gn:feature_class": "P",
    "gn:feature_code": "PPL",
    "gn:name": "Xiakou",
    "gn:population": 0,
    "gn:timezone": "Asia/Shanghai",
    "iso:country": "CN",
    "name:zho_x_preferred": [
      "峡口"
    ],
    "wof:name": "Xiakou",
    "wof:placetype": "locality"
  },
  "geometry": {
    "coordinates": [
      110.453,
      24.2484
    ],
    "type": "Point"
  }
}