{
  "type": "Feature",
  "properties": {
    "gn:admin1_code": "1.0",
    "gn:asciiname": "Chenhoucun",
    "gn:country_code": "CN",
    "gn:dem": 119,
    "gn:feature_class": "P",
    "gn:feature_code": "PPL",
    "gn:name": "Chenhoucun",
    "gn:population": 0,
    "gn:timezone": "Asia/Shanghai",
    "iso:country": "CN",
    "name:zho_x_preferred": [
      "陈候村"
    ],
    "wof:name": "Chenhoucun",
    "wof:placetype": "locality"
  },
  "geometry": {
    "coordinates": [
      119.14084,
      30.73985
    ],
    "type": "Point"
  }
}