{
  "type": "Feature",
  "properties": {
    "gn:admin1_code": "26.0",
    "gn:asciiname": "Laoshugou",
    "gn:country_code": "CN",
    "gn:dem": 1053,
    "gn:feature_class": "P",
    "gn:feature_code": "PPL",
    "gn:name": "Laoshugou",
    "gn:population": 0,
    "gn:timezone": "Asia/Shanghai",
    "iso:country": "CN",
    "name:zho_x_preferred": [
      "老鼠沟"
    ],
    "wof:name": "Laoshugou",
    "wof:placetype": "locality"
  },
  "geometry": {
    "coordinates": [
      109.47168,
      33.40685
    ],
    "type": "Point"
  }
}