{
  "type": "Feature",
  "properties": {
    "gn:admin1_code": "10",
    "gn:asciiname": "Xiaowudeng",
    "gn:country_code": "CN",
    "gn:dem": 1326,
    "gn:feature_class": "P",
    "gn:feature_code": "PPL",
    "gn:name": "Xiaowudeng",
    "gn:population": 0,
    "gn:timezone": "Asia/Shanghai",
    "iso:country": "CN",
    "name:zho_x_preferred": [
      "小邬邓"
    ],
    "wof:name": "Xiaowudeng",
    "wof:placetype": "locality"
  },
  "geometry": {
    "coordinates": [
      114.3451,
      41.61253
    ],
    "type": "Point"
  }
}