{
  "type": "Feature",
  "properties": {
    "gn:admin1_code": "10",
    "gn:asciiname": "Liujiagou",
    "gn:country_code": "CN",
    "gn:dem": 141,
    "gn:feature_class": "P",
    "gn:feature_code": "PPL",
    "gn:name": "Liujiagou",
    "gn:population": 0,
    "gn:timezone": "Asia/Shanghai",
    "iso:country": "CN",
    "name:zho_x_preferred": [
      "刘家沟"
    ],
    "wof:name": "Liujiagou",
    "wof:placetype": "locality"
  },
  "geometry": {
    "coordinates": [
      118.31066,
      40.27897
    ],
    "type": "Point"
  }
}