{
  "type": "Feature",
  "properties": {
    "gn:admin1_code": "15.0",
    "gn:asciiname": "Zhangjiaping",
    "gn:country_code": "CN",
    "gn:dem": 1129,
    "gn:feature_class": "P",
    "gn:feature_code": "PPL",
    "gn:name": "Zhangjiaping",
    "gn:population": 0,
    "gn:timezone": "Asia/Shanghai",
    "iso:country": "CN",
    "name:zho_x_preferred": [
      "张家坪"
    ],
    "wof:name": "Zhangjiaping",
    "wof:placetype": "locality"
  },
  "geometry": {
    "coordinates": [
      107.769,
      35.8133
    ],
    "type": "Point"
  }
}