{
  "type": "Feature",
  "properties": {
    "gn:admin1_code": "26",
    "gn:asciiname": "Zaozhuang",
    "gn:country_code": "CN",
    "gn:dem": 434,
    "gn:feature_class": "P",
    "gn:feature_code": "PPL",
    "gn:name": "Zaozhuang",
    "gn:population": 0,
    "gn:timezone": "Asia/Shanghai",
    "iso:country": "CN",
    "name:afr_x_preferred": [
      "Zaozhuang"
    ],
    "name:ara_x_preferred": [
      "تساوتشوانغ"
    ],
    "name:ast_x_preferred": [
      "Zaozhuang"
    ],
    "name:cdo_x_preferred": [
      "Cō̤-cŏng"
    ],
    "name:ceb_x_preferred": [
      "Zaozhuang"
    ],
    "name:ces_x_preferred": [
      "Cao-čuang"
    ],
    "name:che_x_preferred": [
      "Цзаочжуан"
    ],
    "name:dan_x_preferred": [
      "Zaozhuang"
    ],
    "name:deu_x_preferred": [
      "Zaozhuang"
    ],
    "name:epo_x_preferred": [
      "Zaozhuang"
    ],
    "name:eus_x_preferred": [
      "Zaozhuang"
    ],
    "name:fas_x_preferred": [
      "زاوژوانگ"
    ],
    "name:fin_x_preferred": [
      "Zaozhuang"
    ],
    "name:fra_x_preferred": [
      "Zaozhuang"
    ],
    "name:heb_x_preferred": [
      "זאוז'ואנג"
    ],
    "name:hun_x_preferred": [
      "Csaocsuang"
    ],
    "name:ita_x_preferred": [
      "Zaozhuang"
    ],
    "name:jpn_x_preferred": [
      "棗荘市"
    ],
    "name:kik_x_preferred": [
      "Zaozhuang"
    ],
    "name:kor_x_preferred": [
      "짜오좡시"
    ],
    "name:mlg_x_preferred": [
      "Zaozhuang"
    ],
    "name:nld_x_preferred": [
      "Zaozhuang"
    ],
    "name:nno_x_preferred": [
      "Zaozhuang"
    ],
    "name:nor_x_preferred": [
      "Zaozhuang"
    ],
    "name:pol_x_preferred": [
      "Zaozhuang"
    ],
    "name:rus_x_preferred": [
      "Цзаочжуан"
    ],
    "name:spa_x_preferred": [
      "Zaozhuang"
    ],
    "name:swe_x_preferred": [
      "Zaozhuang"
    ],
    "name:tgl_x_preferred": [
      "Zaozhuang"
    ],
    "name:tur_x_preferred": [
      "Zaozhuang"
    ],
    "name:urd_x_preferred": [
      "زاوژوانگ"
    ],
    "name:vie_x_preferred": [
      "Tảo Trang"
    ],
    "name:war_x_preferred": [
      "Zaozhuang"
    ],
    "name:wuu_x_preferred": [
      "枣庄市"
    ],
    "name:zho_x_preferred": [
      "皂庄"
    ],
    "name:zho_x_variant": [
      "枣庄市"
    ],
    "wof:name": "Zaozhuang",
    "wof:placetype": "locality"
  },
  "geometry": {
    "coordinates": [
      108.2986,
      34.28846
    ],
    "type": "Point"
  }
}