{
  "type": "Feature",
  "properties": {
    "gn:admin1_code": "13.0",
    "gn:asciiname": "Patemankashi",
    "gn:country_code": "CN",
    "gn:dem": 1312,
    "gn:feature_class": "P",
    "gn:feature_code": "PPL",
    "gn:name": "Patemankashi",
    "gn:population": 0,
    "gn:timezone": "Asia/Shanghai",
    "iso:country": "CN",
    "name:und_x_variant": [
      "帕特曼喀什"
    ],
    "wof:name": "Patemankashi",
    "wof:placetype": "locality"
  },
  "geometry": {
    "coordinates": [
      77.12082,
      38.1886
    ],
    "type": "Point"
  }
}