{
  "type": "Feature",
  "properties": {
    "gn:admin1_code": "12.0",
    "gn:asciiname": "Chen'an Yicun",
    "gn:country_code": "CN",
    "gn:dem": 31,
    "gn:feature_class": "P",
    "gn:feature_code": "PPL",
    "gn:name": "Chen’an Yicun",
    "gn:population": 0,
    "gn:timezone": "Asia/Shanghai",
    "iso:country": "CN",
    "name:und_x_variant": [
      "Chen’an Yicun"
    ],
    "name:zho_x_preferred": [
      "陈安一村"
    ],
    "wof:name": "Chen'an Yicun",
    "wof:placetype": "locality"
  },
  "geometry": {
    "coordinates": [
      114.36397,
      30.30039
    ],
    "type": "Point"
  }
}