{
  "type": "Feature",
  "properties": {
    "gn:admin1_code": "14.0",
    "gn:asciiname": "Xoka",
    "gn:country_code": "CN",
    "gn:dem": 3232,
    "gn:feature_class": "P",
    "gn:feature_code": "PPL",
    "gn:name": "Xoka",
    "gn:population": 0,
    "gn:timezone": "Asia/Urumqi",
    "iso:country": "CN",
    "name:ara_x_preferred": [
      "سوكا"
    ],
    "name:bod_x_preferred": [
      "Xoka"
    ],
    "name:msa_x_preferred": [
      "Xoka"
    ],
    "name:zho_x_preferred": [
      "Xueka"
    ],
    "name:zho_x_variant": [
      "雪卡",
      "Pai Gongshe",
      "派公社"
    ],
    "wof:name": "Xoka",
    "wof:placetype": "locality"
  },
  "geometry": {
    "coordinates": [
      94.80808,
      29.49714
    ],
    "type": "Point"
  }
}