{
  "type": "Feature",
  "properties": {
    "gn:admin1_code": "30.0",
    "gn:asciiname": "Shangdong",
    "gn:country_code": "CN",
    "gn:dem": 568,
    "gn:feature_class": "P",
    "gn:feature_code": "PPL",
    "gn:name": "Shangdong",
    "gn:population": 0,
    "gn:timezone": "Asia/Shanghai",
    "iso:country": "CN",
    "name:zho_x_preferred": [
      "上峒"
    ],
    "wof:name": "Shangdong",
    "wof:placetype": "locality"
  },
  "geometry": {
    "coordinates": [
      114.0303,
      23.89149
    ],
    "type": "Point"
  }
}