{
  "type": "Feature",
  "properties": {
    "gn:admin1_code": "24.0",
    "gn:asciiname": "Yaoyuancun",
    "gn:country_code": "CN",
    "gn:dem": 493,
    "gn:feature_class": "P",
    "gn:feature_code": "PPL",
    "gn:name": "Yaoyuancun",
    "gn:population": 0,
    "gn:timezone": "Asia/Shanghai",
    "iso:country": "CN",
    "name:zho_x_preferred": [
      "窑院村"
    ],
    "wof:name": "Yaoyuancun",
    "wof:placetype": "locality"
  },
  "geometry": {
    "coordinates": [
      111.45472,
      35.60125
    ],
    "type": "Point"
  }
}