{
  "type": "Feature",
  "properties": {
    "gn:admin1_code": "15.0",
    "gn:asciiname": "Fu'an",
    "gn:country_code": "CN",
    "gn:dem": 1688,
    "gn:feature_class": "P",
    "gn:feature_code": "PPL",
    "gn:name": "Fu’an",
    "gn:population": 0,
    "gn:timezone": "Asia/Shanghai",
    "iso:country": "CN",
    "name:ara_x_preferred": [
      "فوان"
    ],
    "name:cdo_x_preferred": [
      "Hók-ăng"
    ],
    "name:deu_x_preferred": [
      "Fu’an"
    ],
    "name:fas_x_preferred": [
      "فوان"
    ],
    "name:fra_x_preferred": [
      "Fu'an"
    ],
    "name:hak_x_preferred": [
      "Fuk-ôn-sṳ"
    ],
    "name:ita_x_preferred": [
      "Fu'an"
    ],
    "name:jpn_x_preferred": [
      "福安市"
    ],
    "name:kik_x_preferred": [
      "Fu'an"
    ],
    "name:kor_x_preferred": [
      "푸안시"
    ],
    "name:mwl_x_preferred": [
      "Fu'an"
    ],
    "name:nor_x_preferred": [
      "Fu'an"
    ],
    "name:pam_x_preferred": [
      "Fu'an"
    ],
    "name:pnb_x_preferred": [
      "فوآن"
    ],
    "name:rus_x_preferred": [
      "Фуань"
    ],
    "name:spa_x_preferred": [
      "Fu'an"
    ],
    "name:swe_x_preferred": [
      "Fu'an"
    ],
    "name:urd_x_preferred": [
      "فوآن"
    ],
    "name:vie_x_preferred": [
      "Phúc An"
    ],
    "name:war_x_preferred": [
      "Fu'an"
    ],
    "name:zho_x_preferred": [
      "福安"
    ],
    "name:zho_x_variant": [
      "福安市"
    ],
    "wof:name": "Fu'an",
    "wof:placetype": "locality"
  },
  "geometry": {
    "coordinates": [
      103.871,
      37.5712
    ],
    "type": "Point"
  }
}