{
  "type": "Feature",
  "properties": {
    "gn:admin1_code": "10",
    "gn:asciiname": "Panyu",
    "gn:country_code": "CN",
    "gn:dem": 798,
    "gn:feature_class": "P",
    "gn:feature_code": "PPL",
    "gn:name": "Panyu",
    "gn:population": 0,
    "gn:timezone": "Asia/Shanghai",
    "iso:country": "CN",
    "name:zho_x_preferred": [
      "畔峪"
    ],
    "wof:name": "Panyu",
    "wof:placetype": "locality"
  },
  "geometry": {
    "coordinates": [
      113.698,
      36.7531
    ],
    "type": "Point"
  }
}