{
  "type": "Feature",
  "properties": {
    "gn:admin1_code": "4.0",
    "gn:asciiname": "Caoyuancun",
    "gn:country_code": "CN",
    "gn:dem": 2,
    "gn:feature_class": "P",
    "gn:feature_code": "PPL",
    "gn:name": "Caoyuancun",
    "gn:population": 0,
    "gn:timezone": "Asia/Shanghai",
    "iso:country": "CN",
    "name:und_x_variant": [
      "Caoyuan",
      "Caoyuancun"
    ],
    "name:zho_x_preferred": [
      "曹园"
    ],
    "name:zho_x_variant": [
      "曹园村"
    ],
    "wof:name": "Caoyuancun",
    "wof:placetype": "locality"
  },
  "geometry": {
    "coordinates": [
      120.65668,
      32.55908
    ],
    "type": "Point"
  }
}