{
  "type": "Feature",
  "properties": {
    "gn:admin1_code": "16.0",
    "gn:asciiname": "Poxu",
    "gn:country_code": "CN",
    "gn:dem": 122,
    "gn:feature_class": "P",
    "gn:feature_code": "PPL",
    "gn:name": "Poxu",
    "gn:population": 0,
    "gn:timezone": "Asia/Shanghai",
    "iso:country": "CN",
    "name:zho_x_preferred": [
      "坡圩"
    ],
    "wof:name": "Poxu",
    "wof:placetype": "locality"
  },
  "geometry": {
    "coordinates": [
      106.836,
      23.7869
    ],
    "type": "Point"
  }
}