{
  "type": "Feature",
  "properties": {
    "gn:admin1_code": "16.0",
    "gn:asciiname": "Guide",
    "gn:country_code": "CN",
    "gn:dem": 47,
    "gn:feature_class": "P",
    "gn:feature_code": "PPL",
    "gn:name": "Guide",
    "gn:population": 0,
    "gn:timezone": "Asia/Shanghai",
    "iso:country": "CN",
    "name:fas_x_preferred": [
      "راهنما"
    ],
    "name:fry_x_preferred": [
      "Gids"
    ],
    "name:kor_x_preferred": [
      "가이드"
    ],
    "name:kor_x_variant": [
      "길잡이"
    ],
    "name:nld_x_preferred": [
      "Guide"
    ],
    "name:pol_x_preferred": [
      "Guide"
    ],
    "name:por_x_preferred": [
      "Guide"
    ],
    "name:rus_x_preferred": [
      "Гуйдэ"
    ],
    "name:swe_x_preferred": [
      "Guide"
    ],
    "name:tur_x_preferred": [
      "Guide"
    ],
    "name:ukr_x_preferred": [
      "Гуйде"
    ],
    "name:urd_x_preferred": [
      "گائیڈ"
    ],
    "name:vie_x_preferred": [
      "Quý Đức"
    ],
    "name:zho_cn_x_preferred": [
      "贵德"
    ],
    "name:zho_tw_x_preferred": [
      "貴德"
    ],
    "name:zho_x_preferred": [
      "贵德"
    ],
    "wof:name": "Guide",
    "wof:placetype": "locality"
  },
  "geometry": {
    "coordinates": [
      110.065,
      23.4435
    ],
    "type": "Point"
  }
}