{
  "type": "Feature",
  "properties": {
    "gn:admin1_code": "8.0",
    "gn:asciiname": "Yingkou",
    "gn:country_code": "CN",
    "gn:dem": 143,
    "gn:feature_class": "P",
    "gn:feature_code": "PPL",
    "gn:name": "Yingkou",
    "gn:population": 0,
    "gn:timezone": "Asia/Shanghai",
    "iso:country": "CN",
    "name:afr_x_preferred": [
      "Yingkou"
    ],
    "name:ara_x_preferred": [
      "ينغكو"
    ],
    "name:bul_x_preferred": [
      "Инкоу"
    ],
    "name:cat_x_preferred": [
      "Yingkou"
    ],
    "name:cdo_x_preferred": [
      "Ìng-kāu"
    ],
    "name:ceb_x_preferred": [
      "Yingkou"
    ],
    "name:ces_x_preferred": [
      "Jing-kchou"
    ],
    "name:dan_x_preferred": [
      "Yingkou"
    ],
    "name:deu_x_preferred": [
      "Yingkou"
    ],
    "name:epo_x_preferred": [
      "Inkou"
    ],
    "name:eus_x_preferred": [
      "Yingkou"
    ],
    "name:fas_x_preferred": [
      "یینگکو"
    ],
    "name:fin_x_preferred": [
      "Yingkou"
    ],
    "name:fra_x_preferred": [
      "Yingkou"
    ],
    "name:glg_x_preferred": [
      "Yingkou"
    ],
    "name:ind_x_preferred": [
      "Yingkou"
    ],
    "name:ita_x_preferred": [
      "Yingkou"
    ],
    "name:jpn_x_preferred": [
      "営口市"
    ],
    "name:kik_x_preferred": [
      "Yingkou"
    ],
    "name:kor_x_preferred": [
      "잉커우시"
    ],
    "name:mlg_x_preferred": [
      "Yingkou"
    ],
    "name:mya_x_preferred": [
      "ယင်းခိုမြို့"
    ],
    "name:nld_x_preferred": [
      "Yingkou"
    ],
    "name:nno_x_preferred": [
      "Yingkou"
    ],
    "name:nor_x_preferred": [
      "Yingkou"
    ],
    "name:oci_x_preferred": [
      "Yingkou"
    ],
    "name:pol_x_preferred": [
      "Yingkou"
    ],
    "name:rus_x_preferred": [
      "Инкоу"
    ],
    "name:spa_x_preferred": [
      "Yingkóu"
    ],
    "name:srp_x_preferred": [
      "Јингкоу"
    ],
    "name:swe_x_preferred": [
      "Yingkou"
    ],
    "name:tur_x_preferred": [
      "Yingkou"
    ],
    "name:uig_x_preferred": [
      "يىڭكۇ شەھىرى"
    ],
    "name:ukr_x_preferred": [
      "Їнкоу"
    ],
    "name:urd_x_preferred": [
      "ینگکو"
    ],
    "name:vie_x_preferred": [
      "Dinh Khẩu"
    ],
    "name:war_x_preferred": [
      "Yingkou"
    ],
    "name:wuu_x_preferred": [
      "营口市"
    ],
    "name:zho_x_preferred": [
      "营口"
    ],
    "name:zho_x_variant": [
      "营口市"
    ],
    "wof:name": "Yingkou",
    "wof:placetype": "locality"
  },
  "geometry": {
    "coordinates": [
      127.81416000000002,
      45.79254
    ],
    "type": "Point"
  }
}