{
  "type": "Feature",
  "properties": {
    "gn:admin1_code": "26.0",
    "gn:asciiname": "Yong'ancun",
    "gn:country_code": "CN",
    "gn:dem": 348,
    "gn:feature_class": "P",
    "gn:feature_code": "PPL",
    "gn:name": "Yong’ancun",
    "gn:population": 0,
    "gn:timezone": "Asia/Shanghai",
    "iso:country": "CN",
    "name:und_x_variant": [
      "Yong’ancun"
    ],
    "name:zho_x_preferred": [
      "永安村"
    ],
    "wof:name": "Yong'ancun",
    "wof:placetype": "locality"
  },
  "geometry": {
    "coordinates": [
      110.0262,
      34.82698
    ],
    "type": "Point"
  }
}