{
  "type": "Feature",
  "properties": {
    "gn:admin1_code": "19.0",
    "gn:asciiname": "Linjia",
    "gn:country_code": "CN",
    "gn:dem": 299,
    "gn:feature_class": "P",
    "gn:feature_code": "PPL",
    "gn:name": "Linjia",
    "gn:population": 0,
    "gn:timezone": "Asia/Shanghai",
    "iso:country": "CN",
    "name:und_x_variant": [
      "林家"
    ],
    "wof:name": "Linjia",
    "wof:placetype": "locality"
  },
  "geometry": {
    "coordinates": [
      123.68371,
      40.7707
    ],
    "type": "Point"
  }
}