{
  "type": "Feature",
  "properties": {
    "gn:admin1_code": "30",
    "gn:asciiname": "Jiupu",
    "gn:country_code": "CN",
    "gn:dem": 17,
    "gn:feature_class": "P",
    "gn:feature_code": "PPL",
    "gn:name": "Jiupu",
    "gn:population": 0,
    "gn:timezone": "Asia/Urumqi",
    "iso:country": "CN",
    "name:zho_x_preferred": [
      "酒铺"
    ],
    "wof:name": "Jiupu",
    "wof:placetype": "locality"
  },
  "geometry": {
    "coordinates": [
      110.68448,
      21.68611
    ],
    "type": "Point"
  }
}