{
  "type": "Feature",
  "properties": {
    "gn:admin1_code": "11",
    "gn:asciiname": "Zhangmu",
    "gn:country_code": "CN",
    "gn:dem": 351,
    "gn:feature_class": "P",
    "gn:feature_code": "PPL",
    "gn:name": "Zhangmu",
    "gn:population": 0,
    "gn:timezone": "Asia/Shanghai",
    "iso:country": "CN",
    "name:ara_x_preferred": [
      "جام"
    ],
    "name:fas_x_preferred": [
      "ژانگمو"
    ],
    "name:fra_x_preferred": [
      "Zhangmu"
    ],
    "name:ita_x_preferred": [
      "Zhangmu"
    ],
    "name:jpn_x_preferred": [
      "ダム鎮"
    ],
    "name:lit_x_preferred": [
      "Dramas"
    ],
    "name:msa_x_preferred": [
      "Zham"
    ],
    "name:nep_x_preferred": [
      "खासा"
    ],
    "name:nld_x_preferred": [
      "Dram"
    ],
    "name:nor_x_preferred": [
      "Zhangmu"
    ],
    "name:urd_x_preferred": [
      "ژانگمو"
    ],
    "name:zho_x_preferred": [
      "樟木镇"
    ],
    "wof:name": "Zhangmu",
    "wof:placetype": "locality"
  },
  "geometry": {
    "coordinates": [
      111.40194,
      27.40778
    ],
    "type": "Point"
  }
}