{
  "type": "Feature",
  "properties": {
    "gn:admin1_code": "26.0",
    "gn:asciiname": "Guojiagou",
    "gn:country_code": "CN",
    "gn:dem": 813,
    "gn:feature_class": "P",
    "gn:feature_code": "PPL",
    "gn:name": "Guojiagou",
    "gn:population": 0,
    "gn:timezone": "Asia/Shanghai",
    "iso:country": "CN",
    "name:zho_x_preferred": [
      "郭家沟"
    ],
    "wof:name": "Guojiagou",
    "wof:placetype": "locality"
  },
  "geometry": {
    "coordinates": [
      110.98576,
      38.94504000000001
    ],
    "type": "Point"
  }
}