{
  "type": "Feature",
  "properties": {
    "gn:admin1_code": "32.0",
    "gn:asciiname": "Jinong",
    "gn:country_code": "CN",
    "gn:dem": 441,
    "gn:feature_class": "P",
    "gn:feature_code": "PPL",
    "gn:name": "Jinong",
    "gn:population": 0,
    "gn:timezone": "Asia/Shanghai",
    "iso:country": "CN",
    "name:fra_x_preferred": [
      "Jinong"
    ],
    "name:jpn_x_preferred": [
      "ジノン"
    ],
    "name:mon_x_preferred": [
      "Жонон"
    ],
    "name:rus_x_preferred": [
      "Джинон"
    ],
    "name:tam_x_preferred": [
      "ஜினோங்"
    ],
    "name:zho_x_preferred": [
      "集农"
    ],
    "wof:name": "Jinong",
    "wof:placetype": "locality"
  },
  "geometry": {
    "coordinates": [
      105.109,
      28.4825
    ],
    "type": "Point"
  }
}