{
  "type": "Feature",
  "properties": {
    "gn:admin1_code": "26.0",
    "gn:asciiname": "Gaobucun",
    "gn:country_code": "CN",
    "gn:dem": 1218,
    "gn:feature_class": "P",
    "gn:feature_code": "PPL",
    "gn:name": "Gaobucun",
    "gn:population": 0,
    "gn:timezone": "Asia/Shanghai",
    "iso:country": "CN",
    "name:zho_x_preferred": [
      "高堡村"
    ],
    "wof:name": "Gaobucun",
    "wof:placetype": "locality"
  },
  "geometry": {
    "coordinates": [
      110.0655,
      36.21748
    ],
    "type": "Point"
  }
}