{
  "type": "Feature",
  "properties": {
    "gn:admin1_code": "2.0",
    "gn:asciiname": "Chashan",
    "gn:country_code": "CN",
    "gn:dem": 300,
    "gn:feature_class": "P",
    "gn:feature_code": "PPL",
    "gn:name": "Chashan",
    "gn:population": 0,
    "gn:timezone": "Asia/Shanghai",
    "iso:country": "CN",
    "name:fas_x_preferred": [
      "چاشان"
    ],
    "name:mlg_x_preferred": [
      "Chashan"
    ],
    "name:zho_x_preferred": [
      "茶山"
    ],
    "name:zho_x_variant": [
      "茶山镇"
    ],
    "wof:name": "Chashan",
    "wof:placetype": "locality"
  },
  "geometry": {
    "coordinates": [
      118.92529,
      28.66682
    ],
    "type": "Point"
  }
}