{
  "type": "Feature",
  "properties": {
    "gn:admin1_code": "11",
    "gn:asciiname": "Laohukou",
    "gn:country_code": "CN",
    "gn:dem": 331,
    "gn:feature_class": "P",
    "gn:feature_code": "PPL",
    "gn:name": "Laohukou",
    "gn:population": 0,
    "gn:timezone": "Asia/Shanghai",
    "iso:country": "CN",
    "wof:name": "Laohukou",
    "wof:placetype": "locality"
  },
  "geometry": {
    "coordinates": [
      109.70556,
      28.08528
    ],
    "type": "Point"
  }
}