{
  "type": "Feature",
  "properties": {
    "gn:admin1_code": "5",
    "gn:asciiname": "Erdao",
    "gn:country_code": "CN",
    "gn:dem": 302,
    "gn:feature_class": "P",
    "gn:feature_code": "PPL",
    "gn:name": "Erdao",
    "gn:population": 0,
    "gn:timezone": "Asia/Shanghai",
    "iso:country": "CN",
    "name:ara_x_preferred": [
      "إرداو"
    ],
    "name:ben_x_preferred": [
      "এর্দাও"
    ],
    "name:deu_x_preferred": [
      "Erdao He"
    ],
    "name:ell_x_preferred": [
      "Ερντάο"
    ],
    "name:fas_x_preferred": [
      "ارادو"
    ],
    "name:fra_x_preferred": [
      "Erdao River"
    ],
    "name:heb_x_preferred": [
      "אֶרדאו"
    ],
    "name:hin_x_preferred": [
      "एर्दाओ"
    ],
    "name:hun_x_preferred": [
      "Erdao"
    ],
    "name:ind_x_preferred": [
      "Erdao"
    ],
    "name:ita_x_preferred": [
      "Erdao"
    ],
    "name:jpn_x_preferred": [
      "二道河"
    ],
    "name:kor_x_preferred": [
      "에르다오"
    ],
    "name:nld_x_preferred": [
      "Erdao"
    ],
    "name:pol_x_preferred": [
      "Erdao"
    ],
    "name:por_x_preferred": [
      "Erdao"
    ],
    "name:rus_x_preferred": [
      "река Эрдао"
    ],
    "name:spa_x_preferred": [
      "Erdao"
    ],
    "name:swe_x_preferred": [
      "Erdao"
    ],
    "name:tur_x_preferred": [
      "Erdao"
    ],
    "name:ukr_x_preferred": [
      "Ердао"
    ],
    "name:urd_x_preferred": [
      "ایرداؤ"
    ],
    "name:vie_x_preferred": [
      "Sông Erdao"
    ],
    "name:zho_cn_x_preferred": [
      "二道河"
    ],
    "name:zho_tw_x_preferred": [
      "二道河"
    ],
    "name:zho_x_preferred": [
      "二道"
    ],
    "wof:name": "Erdao",
    "wof:placetype": "locality"
  },
  "geometry": {
    "coordinates": [
      127.35558,
      43.29718
    ],
    "type": "Point"
  }
}