{
  "type": "Feature",
  "properties": {
    "gn:admin1_code": "3.0",
    "gn:asciiname": "Shawan",
    "gn:country_code": "CN",
    "gn:dem": 98,
    "gn:feature_class": "P",
    "gn:feature_code": "PPL",
    "gn:name": "Shawan",
    "gn:population": 0,
    "gn:timezone": "Asia/Shanghai",
    "iso:country": "CN",
    "name:ceb_x_preferred": [
      "Shawan"
    ],
    "name:deu_x_preferred": [
      "Shawan"
    ],
    "name:fra_x_preferred": [
      "Shawan"
    ],
    "name:nor_x_preferred": [
      "Shawan"
    ],
    "name:rus_x_preferred": [
      "Шавань"
    ],
    "name:swe_x_preferred": [
      "Shawan"
    ],
    "name:ukr_x_preferred": [
      "Шавань"
    ],
    "name:und_x_variant": [
      "沙湾"
    ],
    "wof:name": "Shawan",
    "wof:placetype": "locality"
  },
  "geometry": {
    "coordinates": [
      115.87431,
      27.76947
    ],
    "type": "Point"
  }
}