{
  "type": "Feature",
  "properties": {
    "gn:admin1_code": "32.0",
    "gn:asciiname": "Tiantai",
    "gn:country_code": "CN",
    "gn:dem": 668,
    "gn:feature_class": "P",
    "gn:feature_code": "PPL",
    "gn:name": "Tiantai",
    "gn:population": 0,
    "gn:timezone": "Asia/Shanghai",
    "iso:country": "CN",
    "name:cat_x_preferred": [
      "Budisme Tiantai"
    ],
    "name:deu_x_preferred": [
      "Tiantai zong"
    ],
    "name:est_x_preferred": [
      "Tiantai"
    ],
    "name:eus_x_preferred": [
      "Tiantai"
    ],
    "name:fas_x_preferred": [
      "تیانتای"
    ],
    "name:fin_x_preferred": [
      "Tiantai"
    ],
    "name:fra_x_preferred": [
      "Tiantai"
    ],
    "name:hun_x_preferred": [
      "Tientaj"
    ],
    "name:ind_x_preferred": [
      "Tiantai"
    ],
    "name:ita_x_preferred": [
      "Buddhismo Tiāntái"
    ],
    "name:jpn_x_preferred": [
      "天台宗"
    ],
    "name:kor_x_preferred": [
      "천태종"
    ],
    "name:nor_x_preferred": [
      "Tiantai"
    ],
    "name:pol_x_preferred": [
      "Tiantai"
    ],
    "name:por_x_preferred": [
      "Tiantai"
    ],
    "name:rus_x_preferred": [
      "Тяньтай"
    ],
    "name:srp_x_preferred": [
      "Tiantai"
    ],
    "name:swe_x_preferred": [
      "Tiantai"
    ],
    "name:tha_x_preferred": [
      "เทียนไถ"
    ],
    "name:tur_x_preferred": [
      "Tiantai"
    ],
    "name:wuu_x_preferred": [
      "天台宗"
    ],
    "name:zho_x_preferred": [
      "天台"
    ],
    "name:zho_x_variant": [
      "天台宗"
    ],
    "wof:name": "Tiantai",
    "wof:placetype": "locality"
  },
  "geometry": {
    "coordinates": [
      105.593,
      31.9367
    ],
    "type": "Point"
  }
}