{
  "type": "Feature",
  "properties": {
    "gn:admin1_code": "2.0",
    "gn:asciiname": "Zhilin",
    "gn:country_code": "CN",
    "gn:dem": 486,
    "gn:feature_class": "P",
    "gn:feature_code": "PPL",
    "gn:name": "Zhilin",
    "gn:population": 0,
    "gn:timezone": "Asia/Shanghai",
    "iso:country": "CN",
    "name:rus_x_preferred": [
      "Жилин"
    ],
    "name:ukr_x_preferred": [
      "Жилін"
    ],
    "name:zho_x_preferred": [
      "植林"
    ],
    "wof:name": "Zhilin",
    "wof:placetype": "locality"
  },
  "geometry": {
    "coordinates": [
      120.78902,
      29.25337
    ],
    "type": "Point"
  }
}