{
  "type": "Feature",
  "properties": {
    "gn:admin1_code": "25",
    "gn:asciiname": "Xing Yicun",
    "gn:country_code": "CN",
    "gn:dem": 154,
    "gn:feature_class": "P",
    "gn:feature_code": "PPL",
    "gn:name": "Xing Yicun",
    "gn:population": 0,
    "gn:timezone": "Asia/Shanghai",
    "iso:country": "CN",
    "name:zho_x_preferred": [
      "邢一村"
    ],
    "wof:name": "Xing Yicun",
    "wof:placetype": "locality"
  },
  "geometry": {
    "coordinates": [
      118.743,
      35.5939
    ],
    "type": "Point"
  }
}