{
  "type": "Feature",
  "properties": {
    "gn:admin1_code": "11.0",
    "gn:asciiname": "Majialong",
    "gn:country_code": "CN",
    "gn:dem": 380,
    "gn:feature_class": "P",
    "gn:feature_code": "PPL",
    "gn:name": "Majialong",
    "gn:population": 0,
    "gn:timezone": "Asia/Shanghai",
    "iso:country": "CN",
    "name:zho_x_preferred": [
      "马家垅"
    ],
    "wof:name": "Majialong",
    "wof:placetype": "locality"
  },
  "geometry": {
    "coordinates": [
      112.59733,
      27.24004
    ],
    "type": "Point"
  }
}