{
  "type": "Feature",
  "properties": {
    "gn:admin1_code": "8.0",
    "gn:asciiname": "Sanhecun",
    "gn:country_code": "CN",
    "gn:dem": 148,
    "gn:feature_class": "P",
    "gn:feature_code": "PPL",
    "gn:name": "Sanhecun",
    "gn:population": 0,
    "gn:timezone": "Asia/Shanghai",
    "iso:country": "CN",
    "name:zho_x_preferred": [
      "三合村"
    ],
    "wof:name": "Sanhecun",
    "wof:placetype": "locality"
  },
  "geometry": {
    "coordinates": [
      127.00858999999998,
      46.23292
    ],
    "type": "Point"
  }
}