{
  "type": "Feature",
  "properties": {
    "gn:admin1_code": "11",
    "gn:asciiname": "Liujiapu",
    "gn:country_code": "CN",
    "gn:dem": 32,
    "gn:feature_class": "P",
    "gn:feature_code": "PPL",
    "gn:name": "Liujiapu",
    "gn:population": 0,
    "gn:timezone": "Asia/Shanghai",
    "iso:country": "CN",
    "name:zho_x_preferred": [
      "刘家铺"
    ],
    "wof:name": "Liujiapu",
    "wof:placetype": "locality"
  },
  "geometry": {
    "coordinates": [
      112.74086,
      29.32307
    ],
    "type": "Point"
  }
}