{
  "type": "Feature",
  "properties": {
    "gn:admin1_code": "3.0",
    "gn:asciiname": "Huoshenmiao",
    "gn:country_code": "CN",
    "gn:dem": 109,
    "gn:feature_class": "P",
    "gn:feature_code": "PPL",
    "gn:name": "Huoshenmiao",
    "gn:population": 0,
    "gn:timezone": "Asia/Shanghai",
    "iso:country": "CN",
    "name:zho_x_preferred": [
      "火神庙"
    ],
    "wof:name": "Huoshenmiao",
    "wof:placetype": "locality"
  },
  "geometry": {
    "coordinates": [
      117.028,
      28.755
    ],
    "type": "Point"
  }
}