{
  "type": "Feature",
  "properties": {
    "gn:admin1_code": "10",
    "gn:asciiname": "Xishanwan",
    "gn:country_code": "CN",
    "gn:dem": 803,
    "gn:feature_class": "P",
    "gn:feature_code": "PPL",
    "gn:name": "Xishanwan",
    "gn:population": 0,
    "gn:timezone": "Asia/Shanghai",
    "iso:country": "CN",
    "name:zho_x_preferred": [
      "西山湾"
    ],
    "wof:name": "Xishanwan",
    "wof:placetype": "locality"
  },
  "geometry": {
    "coordinates": [
      117.169,
      41.39401
    ],
    "type": "Point"
  }
}