{
  "type": "Feature",
  "properties": {
    "gn:admin1_code": "32.0",
    "gn:asciiname": "Yaogouli",
    "gn:country_code": "CN",
    "gn:dem": 1561,
    "gn:feature_class": "P",
    "gn:feature_code": "PPL",
    "gn:name": "Yaogouli",
    "gn:population": 0,
    "gn:timezone": "Asia/Shanghai",
    "iso:country": "CN",
    "name:zho_x_preferred": [
      "窑沟里"
    ],
    "wof:name": "Yaogouli",
    "wof:placetype": "locality"
  },
  "geometry": {
    "coordinates": [
      104.9019,
      32.27127
    ],
    "type": "Point"
  }
}