{
  "type": "Feature",
  "properties": {
    "gn:admin1_code": "24",
    "gn:asciiname": "Liaoyuan",
    "gn:country_code": "CN",
    "gn:dem": 1070,
    "gn:feature_class": "P",
    "gn:feature_code": "PPL",
    "gn:name": "Liaoyuan",
    "gn:population": 0,
    "gn:timezone": "Asia/Shanghai",
    "iso:country": "CN",
    "name:ara_x_preferred": [
      "لياويوان"
    ],
    "name:ast_x_preferred": [
      "Liaoyuán"
    ],
    "name:bel_x_preferred": [
      "Ляаюань"
    ],
    "name:cdo_x_preferred": [
      "Lièu-nguòng"
    ],
    "name:ces_x_preferred": [
      "Liao-jüan"
    ],
    "name:dan_x_preferred": [
      "Liaoyuan"
    ],
    "name:deu_x_preferred": [
      "Liaoyuan"
    ],
    "name:eus_x_preferred": [
      "Liaoyuan"
    ],
    "name:fas_x_preferred": [
      "لیاویوان"
    ],
    "name:fin_x_preferred": [
      "Liaoyuan"
    ],
    "name:fra_x_preferred": [
      "Liaoyuan"
    ],
    "name:heb_x_preferred": [
      "ליאויואן"
    ],
    "name:hun_x_preferred": [
      "Liaoyuan"
    ],
    "name:ita_x_preferred": [
      "Liaoyuan"
    ],
    "name:jpn_x_preferred": [
      "遼源市"
    ],
    "name:kik_x_preferred": [
      "Liaoyuan"
    ],
    "name:kor_x_preferred": [
      "랴오위안시"
    ],
    "name:lit_x_preferred": [
      "Liaojuanas"
    ],
    "name:mlg_x_preferred": [
      "Liaoyuan"
    ],
    "name:nld_x_preferred": [
      "Liaoyuan"
    ],
    "name:nno_x_preferred": [
      "Liaoyuan"
    ],
    "name:nor_x_preferred": [
      "Liaoyuan"
    ],
    "name:pol_x_preferred": [
      "Liaoyuan"
    ],
    "name:rus_x_preferred": [
      "Ляоюань"
    ],
    "name:spa_x_preferred": [
      "Liaoyuán"
    ],
    "name:srp_x_preferred": [
      "Љаојуен"
    ],
    "name:swe_x_preferred": [
      "Liaoyuan"
    ],
    "name:tur_x_preferred": [
      "Liaoyuan"
    ],
    "name:urd_x_preferred": [
      "لیاویوان"
    ],
    "name:vep_x_preferred": [
      "Läojuan'"
    ],
    "name:vie_x_preferred": [
      "Liêu Nguyên"
    ],
    "name:war_x_preferred": [
      "Liaoyuan"
    ],
    "name:wuu_x_preferred": [
      "辽源市"
    ],
    "name:zho_x_preferred": [
      "辽源市"
    ],
    "wof:name": "Liaoyuan",
    "wof:placetype": "locality"
  },
  "geometry": {
    "coordinates": [
      112.79111,
      37.12278
    ],
    "type": "Point"
  }
}