{
  "type": "Feature",
  "properties": {
    "gn:admin1_code": "3.0",
    "gn:asciiname": "Dieshan",
    "gn:country_code": "CN",
    "gn:dem": 62,
    "gn:feature_class": "P",
    "gn:feature_code": "PPLA4",
    "gn:name": "Dieshan",
    "gn:population": 0,
    "gn:timezone": "Asia/Shanghai",
    "iso:country": "CN",
    "name:und_x_variant": [
      "Dieshan Zhen",
      "叠山镇",
      "Dieshan"
    ],
    "name:zho_x_preferred": [
      "叠山"
    ],
    "wof:name": "Dieshan",
    "wof:placetype": "locality"
  },
  "geometry": {
    "coordinates": [
      117.50866,
      28.21421
    ],
    "type": "Point"
  }
}