{
  "type": "Feature",
  "properties": {
    "gn:admin1_code": "10.0",
    "gn:asciiname": "Yang'erling",
    "gn:country_code": "CN",
    "gn:dem": 553,
    "gn:feature_class": "P",
    "gn:feature_code": "PPL",
    "gn:name": "Yang’erling",
    "gn:population": 0,
    "gn:timezone": "Asia/Shanghai",
    "iso:country": "CN",
    "name:und_x_variant": [
      "Yang’erling"
    ],
    "name:zho_x_preferred": [
      "羊儿岭"
    ],
    "wof:name": "Yang'erling",
    "wof:placetype": "locality"
  },
  "geometry": {
    "coordinates": [
      115.89481,
      40.34239
    ],
    "type": "Point"
  }
}