{
  "type": "Feature",
  "properties": {
    "gn:admin1_code": "2",
    "gn:asciiname": "Muzhuwu",
    "gn:country_code": "CN",
    "gn:dem": 384,
    "gn:feature_class": "P",
    "gn:feature_code": "PPL",
    "gn:name": "Muzhuwu",
    "gn:population": 0,
    "gn:timezone": "Asia/Shanghai",
    "iso:country": "CN",
    "name:und_x_variant": [
      "木竹坞"
    ],
    "wof:name": "Muzhuwu",
    "wof:placetype": "locality"
  },
  "geometry": {
    "coordinates": [
      119.80363,
      30.63761
    ],
    "type": "Point"
  }
}