{
  "type": "Feature",
  "properties": {
    "gn:admin1_code": "7.0",
    "gn:asciiname": "Dianshangpai",
    "gn:country_code": "CN",
    "gn:dem": 333,
    "gn:feature_class": "P",
    "gn:feature_code": "PPL",
    "gn:name": "Dianshangpai",
    "gn:population": 0,
    "gn:timezone": "Asia/Shanghai",
    "iso:country": "CN",
    "name:zho_x_preferred": [
      "店上排"
    ],
    "wof:name": "Dianshangpai",
    "wof:placetype": "locality"
  },
  "geometry": {
    "coordinates": [
      116.83571,
      26.77968
    ],
    "type": "Point"
  }
}