{
  "type": "Feature",
  "properties": {
    "gn:admin1_code": "12.0",
    "gn:asciiname": "Haojiaxiangzi",
    "gn:country_code": "CN",
    "gn:dem": 49,
    "gn:feature_class": "P",
    "gn:feature_code": "PPL",
    "gn:name": "Haojiaxiangzi",
    "gn:population": 0,
    "gn:timezone": "Asia/Shanghai",
    "iso:country": "CN",
    "name:zho_x_preferred": [
      "郝家巷子"
    ],
    "wof:name": "Haojiaxiangzi",
    "wof:placetype": "locality"
  },
  "geometry": {
    "coordinates": [
      113.01448,
      30.81228
    ],
    "type": "Point"
  }
}