{
  "type": "Feature",
  "properties": {
    "gn:admin1_code": "18",
    "gn:asciiname": "Yinlong",
    "gn:country_code": "CN",
    "gn:dem": 1168,
    "gn:feature_class": "P",
    "gn:feature_code": "PPL",
    "gn:name": "Yinlong",
    "gn:population": 0,
    "gn:timezone": "Asia/Shanghai",
    "iso:country": "CN",
    "name:cat_x_preferred": [
      "Yinlong"
    ],
    "name:ces_x_preferred": [
      "Yinlong"
    ],
    "name:deu_x_preferred": [
      "Yinlong"
    ],
    "name:fas_x_preferred": [
      "یین‌لانگ"
    ],
    "name:fra_x_preferred": [
      "Yinlong"
    ],
    "name:heb_x_preferred": [
      "יינלונג"
    ],
    "name:hun_x_preferred": [
      "Yinlong"
    ],
    "name:ita_x_preferred": [
      "Yinlong downsi"
    ],
    "name:jpn_x_preferred": [
      "インロング"
    ],
    "name:mal_x_preferred": [
      "യിൻലോങ്ങ്‌"
    ],
    "name:nld_x_preferred": [
      "Yinlong"
    ],
    "name:ori_x_preferred": [
      "Yinlong"
    ],
    "name:pol_x_preferred": [
      "Jinlong"
    ],
    "name:por_x_preferred": [
      "Yinlong"
    ],
    "name:rus_x_preferred": [
      "Yinlong"
    ],
    "name:spa_x_preferred": [
      "Yinlong"
    ],
    "name:swe_x_preferred": [
      "Yinlong"
    ],
    "name:ukr_x_preferred": [
      "Іньлун"
    ],
    "name:vie_x_preferred": [
      "Yinlong"
    ],
    "name:zho_x_preferred": [
      "银龙"
    ],
    "name:zho_x_variant": [
      "隱龍屬"
    ],
    "wof:name": "Yinlong",
    "wof:placetype": "locality"
  },
  "geometry": {
    "coordinates": [
      106.187,
      28.2998
    ],
    "type": "Point"
  }
}