{
  "type": "Feature",
  "properties": {
    "gn:admin1_code": "16.0",
    "gn:asciiname": "Tai'an",
    "gn:country_code": "CN",
    "gn:dem": 26,
    "gn:feature_class": "P",
    "gn:feature_code": "PPL",
    "gn:name": "Tai’an",
    "gn:population": 0,
    "gn:timezone": "Asia/Shanghai",
    "iso:country": "CN",
    "name:afr_x_preferred": [
      "Tai'an"
    ],
    "name:ara_x_preferred": [
      "تايآن"
    ],
    "name:bul_x_preferred": [
      "Тайан"
    ],
    "name:cdo_x_preferred": [
      "Tái-ăng"
    ],
    "name:ceb_x_preferred": [
      "Tai'an Shi"
    ],
    "name:ces_x_preferred": [
      "Tchaj-an"
    ],
    "name:dan_x_preferred": [
      "Tai'an"
    ],
    "name:deu_x_preferred": [
      "Tai’an"
    ],
    "name:epo_x_preferred": [
      "Tajan"
    ],
    "name:eus_x_preferred": [
      "Tai'an"
    ],
    "name:fas_x_preferred": [
      "تایان"
    ],
    "name:fin_x_preferred": [
      "Tai’an"
    ],
    "name:fra_x_preferred": [
      "Tai'an"
    ],
    "name:hak_x_preferred": [
      "Thai-ôn-sṳ"
    ],
    "name:hin_x_preferred": [
      "ताईआन"
    ],
    "name:ita_x_preferred": [
      "Tai'an"
    ],
    "name:jpn_x_preferred": [
      "泰安市"
    ],
    "name:kik_x_preferred": [
      "Tai'an"
    ],
    "name:kor_x_preferred": [
      "타이안시"
    ],
    "name:nld_x_preferred": [
      "Tai'an"
    ],
    "name:nno_x_preferred": [
      "Tai'an"
    ],
    "name:nor_x_preferred": [
      "Tai'an"
    ],
    "name:pol_x_preferred": [
      "Tai’an"
    ],
    "name:por_x_preferred": [
      "Tai'an"
    ],
    "name:ron_x_preferred": [
      "Tai'an"
    ],
    "name:rus_x_preferred": [
      "Тайань"
    ],
    "name:spa_x_preferred": [
      "Tai'an"
    ],
    "name:srp_x_preferred": [
      "Тајан"
    ],
    "name:swe_x_preferred": [
      "Tai'an"
    ],
    "name:tgl_x_preferred": [
      "Tai'an"
    ],
    "name:tur_x_preferred": [
      "Tai'an"
    ],
    "name:urd_x_preferred": [
      "تائیآن"
    ],
    "name:vie_x_preferred": [
      "Thái An"
    ],
    "name:war_x_preferred": [
      "Tai'an"
    ],
    "name:wuu_x_preferred": [
      "泰安市"
    ],
    "name:zho_x_preferred": [
      "太安"
    ],
    "name:zho_x_variant": [
      "泰安市"
    ],
    "wof:name": "Tai'an",
    "wof:placetype": "locality"
  },
  "geometry": {
    "coordinates": [
      111.266,
      23.5249
    ],
    "type": "Point"
  }
}