{
  "type": "Feature",
  "properties": {
    "gn:admin1_code": "14.0",
    "gn:asciiname": "Zhuogeduo",
    "gn:country_code": "CN",
    "gn:dem": 4182,
    "gn:feature_class": "P",
    "gn:feature_code": "PPL",
    "gn:name": "Zhuogeduo",
    "gn:population": 0,
    "gn:timezone": "Asia/Urumqi",
    "iso:country": "CN",
    "name:zho_x_preferred": [
      "卓格多"
    ],
    "wof:name": "Zhuogeduo",
    "wof:placetype": "locality"
  },
  "geometry": {
    "coordinates": [
      91.42825,
      30.33006
    ],
    "type": "Point"
  }
}