{
  "type": "Feature",
  "properties": {
    "gn:admin1_code": "16.0",
    "gn:asciiname": "Judongwei",
    "gn:country_code": "CN",
    "gn:dem": 312,
    "gn:feature_class": "P",
    "gn:feature_code": "PPL",
    "gn:name": "Judongwei",
    "gn:population": 0,
    "gn:timezone": "Asia/Shanghai",
    "iso:country": "CN",
    "name:zho_x_preferred": [
      "居洞尾"
    ],
    "wof:name": "Judongwei",
    "wof:placetype": "locality"
  },
  "geometry": {
    "coordinates": [
      109.084,
      25.1891
    ],
    "type": "Point"
  }
}