{
  "type": "Feature",
  "properties": {
    "gn:admin1_code": "32.0",
    "gn:asciiname": "Kaka",
    "gn:country_code": "CN",
    "gn:dem": 2015,
    "gn:feature_class": "P",
    "gn:feature_code": "PPL",
    "gn:name": "Kaka",
    "gn:population": 0,
    "gn:timezone": "Asia/Shanghai",
    "iso:country": "CN",
    "name:ara_x_preferred": [
      "كاكا"
    ],
    "name:ben_x_preferred": [
      "কাকা"
    ],
    "name:bul_x_preferred": [
      "Кака"
    ],
    "name:cat_x_preferred": [
      "Kaka"
    ],
    "name:ceb_x_preferred": [
      "Kaka"
    ],
    "name:dan_x_preferred": [
      "Kaka"
    ],
    "name:deu_x_preferred": [
      "Kaka"
    ],
    "name:ell_x_preferred": [
      "Κακά"
    ],
    "name:est_x_preferred": [
      "Kaka"
    ],
    "name:fas_x_preferred": [
      "کاکا"
    ],
    "name:fin_x_preferred": [
      "Kaka"
    ],
    "name:fra_x_preferred": [
      "Kaka"
    ],
    "name:heb_x_preferred": [
      "קקה"
    ],
    "name:hin_x_preferred": [
      "काका"
    ],
    "name:hrv_x_preferred": [
      "Kaka"
    ],
    "name:hun_x_preferred": [
      "Kaka"
    ],
    "name:ind_x_preferred": [
      "Kaka"
    ],
    "name:ita_x_preferred": [
      "Kaká"
    ],
    "name:jpn_x_preferred": [
      "カカ"
    ],
    "name:kor_x_preferred": [
      "카카"
    ],
    "name:lav_x_preferred": [
      "Kaka"
    ],
    "name:nld_x_preferred": [
      "Kaka"
    ],
    "name:nor_x_preferred": [
      "Kaka"
    ],
    "name:pol_x_preferred": [
      "Kaka"
    ],
    "name:por_x_preferred": [
      "Kaká"
    ],
    "name:rus_x_preferred": [
      "Кака"
    ],
    "name:spa_x_preferred": [
      "Kaka"
    ],
    "name:srp_x_preferred": [
      "Кака"
    ],
    "name:swe_x_preferred": [
      "Kaka"
    ],
    "name:tam_x_preferred": [
      "காக்கா"
    ],
    "name:tgl_x_preferred": [
      "Kaka"
    ],
    "name:tur_x_preferred": [
      "Kaka"
    ],
    "name:ukr_x_preferred": [
      "Кака"
    ],
    "name:vie_x_preferred": [
      "Kaka"
    ],
    "name:zho_x_preferred": [
      "卡卡"
    ],
    "wof:name": "Kaka",
    "wof:placetype": "locality"
  },
  "geometry": {
    "coordinates": [
      101.86455,
      31.04281
    ],
    "type": "Point"
  }
}