{
  "type": "Feature",
  "properties": {
    "gn:admin1_code": "12",
    "gn:asciiname": "Pengsi",
    "gn:country_code": "CN",
    "gn:dem": 40,
    "gn:feature_class": "P",
    "gn:feature_code": "PPLA4",
    "gn:name": "Pengsi",
    "gn:population": 0,
    "gn:timezone": "Asia/Shanghai",
    "iso:country": "CN",
    "name:und_x_variant": [
      "彭思",
      "Pengsi Zhen",
      "彭思镇"
    ],
    "wof:name": "Pengsi",
    "wof:placetype": "locality"
  },
  "geometry": {
    "coordinates": [
      115.27165,
      30.27258
    ],
    "type": "Point"
  }
}