{
  "type": "Feature",
  "properties": {
    "gn:admin1_code": "13",
    "gn:asciiname": "Bashisidai",
    "gn:country_code": "CN",
    "gn:dem": 1299,
    "gn:feature_class": "P",
    "gn:feature_code": "PPL",
    "gn:name": "Bashisidai",
    "gn:population": 0,
    "gn:timezone": "Asia/Shanghai",
    "iso:country": "CN",
    "name:und_x_variant": [
      "巴什斯代",
      "Bashisidaicun"
    ],
    "name:zho_x_preferred": [
      "巴什斯代村"
    ],
    "wof:name": "Bashisidai",
    "wof:placetype": "locality"
  },
  "geometry": {
    "coordinates": [
      76.11463,
      39.5279
    ],
    "type": "Point"
  }
}