{
  "type": "Feature",
  "properties": {
    "gn:admin1_code": "15.0",
    "gn:asciiname": "Luo'erqu",
    "gn:country_code": "CN",
    "gn:dem": 1367,
    "gn:feature_class": "P",
    "gn:feature_code": "PPL",
    "gn:name": "Luo’erqu",
    "gn:population": 0,
    "gn:timezone": "Asia/Shanghai",
    "iso:country": "CN",
    "name:und_x_variant": [
      "Luo’erqu"
    ],
    "name:zho_x_preferred": [
      "罗儿曲"
    ],
    "wof:name": "Luo'erqu",
    "wof:placetype": "locality"
  },
  "geometry": {
    "coordinates": [
      105.135,
      34.7698
    ],
    "type": "Point"
  }
}