{
  "type": "Feature",
  "properties": {
    "gn:admin1_code": "30.0",
    "gn:asciiname": "Luowu",
    "gn:country_code": "CN",
    "gn:dem": 84,
    "gn:feature_class": "P",
    "gn:feature_code": "PPL",
    "gn:name": "Luowu",
    "gn:population": 0,
    "gn:timezone": "Asia/Shanghai",
    "iso:country": "CN",
    "name:zho_x_preferred": [
      "罗屋"
    ],
    "wof:name": "Luowu",
    "wof:placetype": "locality"
  },
  "geometry": {
    "coordinates": [
      112.01637,
      24.03584
    ],
    "type": "Point"
  }
}