{
  "type": "Feature",
  "properties": {
    "gn:admin1_code": "11.0",
    "gn:asciiname": "Yaxi",
    "gn:country_code": "CN",
    "gn:dem": 431,
    "gn:feature_class": "P",
    "gn:feature_code": "PPL",
    "gn:name": "Yaxi",
    "gn:population": 0,
    "gn:timezone": "Asia/Shanghai",
    "iso:country": "CN",
    "name:fas_x_preferred": [
      "یاشی"
    ],
    "name:urd_x_preferred": [
      "یاکشی"
    ],
    "name:zho_x_preferred": [
      "鸭溪"
    ],
    "name:zho_x_variant": [
      "崖西镇"
    ],
    "wof:name": "Yaxi",
    "wof:placetype": "locality"
  },
  "geometry": {
    "coordinates": [
      110.249,
      28.43944
    ],
    "type": "Point"
  }
}