{
  "type": "Feature",
  "properties": {
    "gn:admin1_code": "32.0",
    "gn:asciiname": "Zemu Qinnian",
    "gn:country_code": "CN",
    "gn:dem": 3204,
    "gn:feature_class": "P",
    "gn:feature_code": "PPL",
    "gn:name": "Zemu Qinnian",
    "gn:population": 0,
    "gn:timezone": "Asia/Shanghai",
    "iso:country": "CN",
    "name:zho_x_preferred": [
      "泽母钦念"
    ],
    "wof:name": "Zemu Qinnian",
    "wof:placetype": "locality"
  },
  "geometry": {
    "coordinates": [
      103.682,
      33.326
    ],
    "type": "Point"
  }
}