{
  "type": "Feature",
  "properties": {
    "gn:admin1_code": "30",
    "gn:asciiname": "Luozhou",
    "gn:country_code": "CN",
    "gn:dem": 24,
    "gn:feature_class": "P",
    "gn:feature_code": "PPLA3",
    "gn:name": "Luozhou",
    "gn:population": 0,
    "gn:timezone": "Asia/Urumqi",
    "iso:country": "CN",
    "name:und_x_variant": [
      "Luozhou Jiedao",
      "罗州街道"
    ],
    "name:zho_x_preferred": [
      "罗州"
    ],
    "wof:name": "Luozhou",
    "wof:placetype": "locality"
  },
  "geometry": {
    "coordinates": [
      110.27705,
      21.60589
    ],
    "type": "Point"
  }
}