{
  "type": "Feature",
  "properties": {
    "gn:admin1_code": "11",
    "gn:asciiname": "Jingzhuzhai",
    "gn:country_code": "CN",
    "gn:dem": 930,
    "gn:feature_class": "P",
    "gn:feature_code": "PPL",
    "gn:name": "Jingzhuzhai",
    "gn:population": 0,
    "gn:timezone": "Asia/Shanghai",
    "iso:country": "CN",
    "name:und_x_variant": [
      "荆竹寨",
      "Jingzhuzhai"
    ],
    "wof:name": "Jingzhuzhai",
    "wof:placetype": "locality"
  },
  "geometry": {
    "coordinates": [
      111.97444,
      25.11611
    ],
    "type": "Point"
  }
}