{
  "type": "Feature",
  "properties": {
    "gn:admin1_code": "29.0",
    "gn:asciiname": "Daqing",
    "gn:country_code": "CN",
    "gn:dem": 1452,
    "gn:feature_class": "P",
    "gn:feature_code": "PPL",
    "gn:name": "Daqing",
    "gn:population": 0,
    "gn:timezone": "Asia/Shanghai",
    "iso:country": "CN",
    "name:afr_x_preferred": [
      "Daqing"
    ],
    "name:ara_x_preferred": [
      "داتشينغ"
    ],
    "name:bak_x_preferred": [
      "Дацин"
    ],
    "name:bel_x_preferred": [
      "Дацын"
    ],
    "name:cdo_x_preferred": [
      "Dâi-kéng"
    ],
    "name:ces_x_preferred": [
      "Ta-čching"
    ],
    "name:dan_x_preferred": [
      "Daqing"
    ],
    "name:deu_x_preferred": [
      "Daqing"
    ],
    "name:epo_x_preferred": [
      "Dacin"
    ],
    "name:eus_x_preferred": [
      "Daqing"
    ],
    "name:fas_x_preferred": [
      "داکینگ"
    ],
    "name:fin_x_preferred": [
      "Daqing"
    ],
    "name:fra_x_preferred": [
      "Daqing"
    ],
    "name:heb_x_preferred": [
      "דאגינג"
    ],
    "name:ind_x_preferred": [
      "Daqing"
    ],
    "name:ita_x_preferred": [
      "Daqing"
    ],
    "name:jpn_x_preferred": [
      "大慶市"
    ],
    "name:kik_x_preferred": [
      "Daqing"
    ],
    "name:kor_x_preferred": [
      "다칭시"
    ],
    "name:lit_x_preferred": [
      "Dačingas"
    ],
    "name:mlg_x_preferred": [
      "Daqing"
    ],
    "name:mon_x_preferred": [
      "Дачин"
    ],
    "name:nld_x_preferred": [
      "Daqing"
    ],
    "name:nno_x_preferred": [
      "Daqing"
    ],
    "name:nor_x_preferred": [
      "Daqing"
    ],
    "name:pam_x_preferred": [
      "Daqing"
    ],
    "name:pol_x_preferred": [
      "Daqing"
    ],
    "name:por_x_preferred": [
      "Daqing"
    ],
    "name:rus_x_preferred": [
      "Дацин"
    ],
    "name:spa_x_preferred": [
      "Daqing"
    ],
    "name:swe_x_preferred": [
      "Daqing"
    ],
    "name:tgl_x_preferred": [
      "Daqing"
    ],
    "name:tur_x_preferred": [
      "Daqing"
    ],
    "name:uig_x_preferred": [
      "داچىڭ شەھىر"
    ],
    "name:ukr_x_preferred": [
      "Дацін"
    ],
    "name:urd_x_preferred": [
      "داچینگ"
    ],
    "name:vie_x_preferred": [
      "Đại Khánh"
    ],
    "name:war_x_preferred": [
      "Daqing"
    ],
    "name:wuu_x_preferred": [
      "大庆市"
    ],
    "name:zho_x_preferred": [
      "大箐"
    ],
    "name:zho_x_variant": [
      "大庆市"
    ],
    "wof:name": "Daqing",
    "wof:placetype": "locality"
  },
  "geometry": {
    "coordinates": [
      100.876,
      22.9295
    ],
    "type": "Point"
  }
}