{
  "type": "Feature",
  "properties": {
    "gn:admin1_code": "4.0",
    "gn:asciiname": "Qianjiang",
    "gn:country_code": "CN",
    "gn:dem": 5,
    "gn:feature_class": "P",
    "gn:feature_code": "PPL",
    "gn:name": "Qianjiang",
    "gn:population": 0,
    "gn:timezone": "Asia/Shanghai",
    "iso:country": "CN",
    "name:ceb_x_preferred": [
      "Qianjiang"
    ],
    "name:ces_x_preferred": [
      "Čchien-ťiang"
    ],
    "name:deu_x_preferred": [
      "Qianjiang"
    ],
    "name:fra_x_preferred": [
      "Qianjiang"
    ],
    "name:mlg_x_preferred": [
      "Qianjiang"
    ],
    "name:nld_x_preferred": [
      "Qianjiang"
    ],
    "name:nor_x_preferred": [
      "Qianjiang"
    ],
    "name:rus_x_preferred": [
      "Цяньцзян"
    ],
    "name:swe_x_preferred": [
      "Qianjiang"
    ],
    "name:urd_x_preferred": [
      "چیانجیانگ"
    ],
    "name:zho_x_preferred": [
      "钱镜"
    ],
    "wof:name": "Qianjiang",
    "wof:placetype": "locality"
  },
  "geometry": {
    "coordinates": [
      119.56708,
      32.98772
    ],
    "type": "Point"
  }
}