{
  "type": "Feature",
  "properties": {
    "gn:admin1_code": "2.0",
    "gn:asciiname": "Longkou",
    "gn:country_code": "CN",
    "gn:dem": 8,
    "gn:feature_class": "P",
    "gn:feature_code": "PPL",
    "gn:name": "Longkou",
    "gn:population": 0,
    "gn:timezone": "Asia/Shanghai",
    "iso:country": "CN",
    "name:deu_x_preferred": [
      "Longkou"
    ],
    "name:fin_x_preferred": [
      "Longkou"
    ],
    "name:fra_x_preferred": [
      "Longkou"
    ],
    "name:ita_x_preferred": [
      "Longkou"
    ],
    "name:jpn_x_preferred": [
      "竜口市"
    ],
    "name:kik_x_preferred": [
      "Longkou"
    ],
    "name:kor_x_preferred": [
      "룽커우시"
    ],
    "name:nor_x_preferred": [
      "Longkou"
    ],
    "name:rus_x_preferred": [
      "Лункоу"
    ],
    "name:swe_x_preferred": [
      "Longkou"
    ],
    "name:und_x_variant": [
      "龙口"
    ],
    "name:urd_x_preferred": [
      "لونگکوو"
    ],
    "name:vie_x_preferred": [
      "Long Khẩu"
    ],
    "name:war_x_preferred": [
      "Longkou"
    ],
    "name:zho_x_preferred": [
      "龙口市"
    ],
    "wof:name": "Longkou",
    "wof:placetype": "locality"
  },
  "geometry": {
    "coordinates": [
      120.24068,
      30.46855
    ],
    "type": "Point"
  }
}