{
  "type": "Feature",
  "properties": {
    "gn:admin1_code": "1.0",
    "gn:asciiname": "Fangyuan",
    "gn:country_code": "CN",
    "gn:dem": 43,
    "gn:feature_class": "P",
    "gn:feature_code": "PPL",
    "gn:name": "Fangyuan",
    "gn:population": 0,
    "gn:timezone": "Asia/Shanghai",
    "iso:country": "CN",
    "name:hak_x_preferred": [
      "Fông-yen-hiông"
    ],
    "name:ita_x_preferred": [
      "Fangyuan"
    ],
    "name:jpn_x_preferred": [
      "芳苑郷"
    ],
    "name:kor_x_preferred": [
      "팡위안향"
    ],
    "name:pol_x_preferred": [
      "Fangyuan"
    ],
    "name:vie_x_preferred": [
      "Phương Uyển"
    ],
    "name:zho_x_preferred": [
      "方园"
    ],
    "name:zho_x_variant": [
      "芳苑鄉"
    ],
    "wof:name": "Fangyuan",
    "wof:placetype": "locality"
  },
  "geometry": {
    "coordinates": [
      115.79529,
      33.86353
    ],
    "type": "Point"
  }
}