{
  "type": "Feature",
  "properties": {
    "gn:admin1_code": "16.0",
    "gn:asciiname": "Liugui",
    "gn:country_code": "CN",
    "gn:dem": 335,
    "gn:feature_class": "P",
    "gn:feature_code": "PPL",
    "gn:name": "Liugui",
    "gn:population": 0,
    "gn:timezone": "Asia/Shanghai",
    "iso:country": "CN",
    "name:zho_x_preferred": [
      "六贵"
    ],
    "wof:name": "Liugui",
    "wof:placetype": "locality"
  },
  "geometry": {
    "coordinates": [
      110.091,
      24.4074
    ],
    "type": "Point"
  }
}