{
  "type": "Feature",
  "properties": {
    "gn:admin1_code": "32.0",
    "gn:asciiname": "Lushan",
    "gn:country_code": "CN",
    "gn:dem": 357,
    "gn:feature_class": "P",
    "gn:feature_code": "PPL",
    "gn:name": "Lushan",
    "gn:population": 0,
    "gn:timezone": "Asia/Shanghai",
    "iso:country": "CN",
    "name:zho_x_preferred": [
      "卢山"
    ],
    "wof:name": "Lushan",
    "wof:placetype": "locality"
  },
  "geometry": {
    "coordinates": [
      106.391,
      30.4059
    ],
    "type": "Point"
  }
}