{
  "type": "Feature",
  "properties": {
    "gn:admin1_code": "04",
    "gn:asciiname": "Taowu",
    "gn:country_code": "CN",
    "gn:dem": 16,
    "gn:feature_class": "P",
    "gn:feature_code": "PPLA4",
    "gn:name": "Taowu",
    "gn:population": 0,
    "gn:timezone": "Asia/Shanghai",
    "iso:country": "CN",
    "name:und_x_variant": [
      "T’ao-wu-chen",
      "Taowu Zhen",
      "陶吴镇",
      "Taowu"
    ],
    "name:zho_x_preferred": [
      "陶吴"
    ],
    "wof:name": "Taowu",
    "wof:placetype": "locality"
  },
  "geometry": {
    "coordinates": [
      118.77125,
      31.77725
    ],
    "type": "Point"
  }
}