{
  "type": "Feature",
  "properties": {
    "gn:admin1_code": "25",
    "gn:asciiname": "Luzhuang",
    "gn:country_code": "CN",
    "gn:dem": 183,
    "gn:feature_class": "P",
    "gn:feature_code": "PPL",
    "gn:name": "Lüzhuang",
    "gn:population": 0,
    "gn:timezone": "Asia/Shanghai",
    "iso:country": "CN",
    "name:und_x_variant": [
      "Lüzhuang"
    ],
    "name:zho_x_preferred": [
      "吕庄"
    ],
    "wof:name": "Luzhuang",
    "wof:placetype": "locality"
  },
  "geometry": {
    "coordinates": [
      118.705,
      36.2809
    ],
    "type": "Point"
  }
}