{
  "type": "Feature",
  "properties": {
    "gn:admin1_code": "10",
    "gn:asciiname": "Yuanquanchang",
    "gn:country_code": "CN",
    "gn:dem": 1416,
    "gn:feature_class": "P",
    "gn:feature_code": "PPL",
    "gn:name": "Yuanquanchang",
    "gn:population": 0,
    "gn:timezone": "Asia/Shanghai",
    "iso:country": "CN",
    "name:zho_x_preferred": [
      "元泉厂"
    ],
    "wof:name": "Yuanquanchang",
    "wof:placetype": "locality"
  },
  "geometry": {
    "coordinates": [
      114.6257,
      41.14447
    ],
    "type": "Point"
  }
}