{
  "type": "Feature",
  "properties": {
    "gn:admin1_code": "14.0",
    "gn:asciiname": "Lari",
    "gn:country_code": "CN",
    "gn:dem": 3609,
    "gn:feature_class": "P",
    "gn:feature_code": "PPL",
    "gn:name": "Lari",
    "gn:population": 0,
    "gn:timezone": "Asia/Urumqi",
    "iso:country": "CN",
    "name:ara_x_preferred": [
      "نورساويات"
    ],
    "name:cat_x_preferred": [
      "Lari"
    ],
    "name:ces_x_preferred": [
      "Racci"
    ],
    "name:fas_x_preferred": [
      "مرغان نوروزی"
    ],
    "name:fin_x_preferred": [
      "Lari"
    ],
    "name:heb_x_preferred": [
      "שחפאיים"
    ],
    "name:isl_x_preferred": [
      "Máfuglar"
    ],
    "name:ita_x_preferred": [
      "Lari"
    ],
    "name:kat_x_preferred": [
      "თოლიასნაირნი"
    ],
    "name:kor_x_preferred": [
      "갈매기아목"
    ],
    "name:lav_x_preferred": [
      "Kaijveidīgie"
    ],
    "name:nor_x_preferred": [
      "Måkefugler"
    ],
    "name:pol_x_preferred": [
      "Mewowce"
    ],
    "name:por_x_preferred": [
      "Lari"
    ],
    "name:rus_x_preferred": [
      "Lari"
    ],
    "name:scn_x_preferred": [
      "Lari"
    ],
    "name:spa_x_preferred": [
      "Lari"
    ],
    "name:swe_x_preferred": [
      "Lari"
    ],
    "name:tam_x_preferred": [
      "லேரி"
    ],
    "name:zho_x_preferred": [
      "拉日"
    ],
    "wof:name": "Lari",
    "wof:placetype": "locality"
  },
  "geometry": {
    "coordinates": [
      96.93299,
      30.0395
    ],
    "type": "Point"
  }
}