{
  "type": "Feature",
  "properties": {
    "gn:admin1_code": "21",
    "gn:asciiname": "Qianjin",
    "gn:country_code": "CN",
    "gn:dem": 1101,
    "gn:feature_class": "P",
    "gn:feature_code": "PPL",
    "gn:name": "Qianjin",
    "gn:population": 0,
    "gn:timezone": "Asia/Shanghai",
    "iso:country": "CN",
    "name:ceb_x_preferred": [
      "Qianjin"
    ],
    "name:deu_x_preferred": [
      "Qianjin"
    ],
    "name:eus_x_preferred": [
      "Qianjin"
    ],
    "name:kor_x_preferred": [
      "첸진구"
    ],
    "name:rus_x_preferred": [
      "Цяньцзинь"
    ],
    "wof:name": "Qianjin",
    "wof:placetype": "locality"
  },
  "geometry": {
    "coordinates": [
      106.51667,
      38.81667
    ],
    "type": "Point"
  }
}