{
  "type": "Feature",
  "properties": {
    "gn:admin1_code": "7.0",
    "gn:asciiname": "Xiongjia",
    "gn:country_code": "CN",
    "gn:dem": 869,
    "gn:feature_class": "P",
    "gn:feature_code": "PPL",
    "gn:name": "Xiongjia",
    "gn:population": 0,
    "gn:timezone": "Asia/Shanghai",
    "iso:country": "CN",
    "name:zho_x_preferred": [
      "熊家"
    ],
    "wof:name": "Xiongjia",
    "wof:placetype": "locality"
  },
  "geometry": {
    "coordinates": [
      117.44455,
      27.13534000000001
    ],
    "type": "Point"
  }
}