{
  "type": "Feature",
  "properties": {
    "gn:admin1_code": "16.0",
    "gn:asciiname": "Longjiang",
    "gn:country_code": "CN",
    "gn:dem": 1074,
    "gn:feature_class": "P",
    "gn:feature_code": "PPL",
    "gn:name": "Longjiang",
    "gn:population": 0,
    "gn:timezone": "Asia/Shanghai",
    "iso:country": "CN",
    "name:ara_x_preferred": [
      "لونتشونغ"
    ],
    "name:ben_x_preferred": [
      "লংজিয়াং"
    ],
    "name:ceb_x_preferred": [
      "Longjiang"
    ],
    "name:deu_x_preferred": [
      "Longjiang"
    ],
    "name:ell_x_preferred": [
      "Λονγκτζιάνγκ"
    ],
    "name:eng_x_preferred": [
      "Longjiang"
    ],
    "name:fas_x_preferred": [
      "لانگ جیانگ"
    ],
    "name:fra_x_preferred": [
      "Longjiang"
    ],
    "name:heb_x_preferred": [
      "לונגג'יאנג"
    ],
    "name:hin_x_preferred": [
      "लांगजियांग"
    ],
    "name:hun_x_preferred": [
      "Longjiang"
    ],
    "name:ind_x_preferred": [
      "Longjiang"
    ],
    "name:ita_x_preferred": [
      "Longjiang"
    ],
    "name:kor_x_preferred": [
      "룽장"
    ],
    "name:mlg_x_preferred": [
      "Longjiang"
    ],
    "name:nld_x_preferred": [
      "Longjiang"
    ],
    "name:pol_x_preferred": [
      "Longjiang"
    ],
    "name:por_x_preferred": [
      "Longjiang"
    ],
    "name:rus_x_preferred": [
      "Лунцзян"
    ],
    "name:spa_x_preferred": [
      "Longjiang"
    ],
    "name:swe_x_preferred": [
      "Longjiang"
    ],
    "name:tur_x_preferred": [
      "Longjiang"
    ],
    "name:ukr_x_preferred": [
      "Лунцзян"
    ],
    "name:urd_x_preferred": [
      "لانگجیان"
    ],
    "name:vie_x_preferred": [
      "Long Giang"
    ],
    "name:zho_x_preferred": [
      "龙江"
    ],
    "wof:name": "Longjiang",
    "wof:placetype": "locality"
  },
  "geometry": {
    "coordinates": [
      106.471,
      24.5634
    ],
    "type": "Point"
  }
}