{
  "type": "Feature",
  "properties": {
    "gn:admin1_code": "26",
    "gn:asciiname": "Shunning",
    "gn:country_code": "CN",
    "gn:dem": 1412,
    "gn:feature_class": "P",
    "gn:feature_code": "PPL",
    "gn:name": "Shunning",
    "gn:population": 0,
    "gn:timezone": "Asia/Shanghai",
    "iso:country": "CN",
    "name:heb_x_preferred": [
      "חרם חברתי"
    ],
    "name:jpn_x_preferred": [
      "共同絶交"
    ],
    "name:swe_x_preferred": [
      "Utfrysning"
    ],
    "wof:name": "Shunning",
    "wof:placetype": "locality"
  },
  "geometry": {
    "coordinates": [
      108.63333,
      36.95
    ],
    "type": "Point"
  }
}