{
  "type": "Feature",
  "properties": {
    "gn:admin1_code": "19.0",
    "gn:asciiname": "Songjia Buzi",
    "gn:country_code": "CN",
    "gn:dem": 279,
    "gn:feature_class": "P",
    "gn:feature_code": "PPL",
    "gn:name": "Songjia Buzi",
    "gn:population": 0,
    "gn:timezone": "Asia/Shanghai",
    "iso:country": "CN",
    "name:zho_x_preferred": [
      "宋家堡子"
    ],
    "wof:name": "Songjia Buzi",
    "wof:placetype": "locality"
  },
  "geometry": {
    "coordinates": [
      124.113,
      40.9202
    ],
    "type": "Point"
  }
}