{
  "type": "Feature",
  "properties": {
    "gn:admin1_code": "18.0",
    "gn:asciiname": "Ren'ao",
    "gn:country_code": "CN",
    "gn:dem": 1034,
    "gn:feature_class": "P",
    "gn:feature_code": "PPL",
    "gn:name": "Ren’ao",
    "gn:population": 0,
    "gn:timezone": "Asia/Shanghai",
    "iso:country": "CN",
    "name:und_x_variant": [
      "Ren’ao"
    ],
    "name:zho_x_preferred": [
      "仁坳"
    ],
    "wof:name": "Ren'ao",
    "wof:placetype": "locality"
  },
  "geometry": {
    "coordinates": [
      107.989,
      26.8473
    ],
    "type": "Point"
  }
}