{
  "type": "Feature",
  "properties": {
    "gn:admin1_code": "30",
    "gn:asciiname": "Jiaoyuan",
    "gn:country_code": "CN",
    "gn:dem": 44,
    "gn:feature_class": "P",
    "gn:feature_code": "PPL",
    "gn:name": "Jiaoyuan",
    "gn:population": 0,
    "gn:timezone": "Asia/Shanghai",
    "iso:country": "CN",
    "name:zho_x_preferred": [
      "蕉园"
    ],
    "wof:name": "Jiaoyuan",
    "wof:placetype": "locality"
  },
  "geometry": {
    "coordinates": [
      115.92889,
      23.11688
    ],
    "type": "Point"
  }
}