{
  "type": "Feature",
  "properties": {
    "gn:admin1_code": "9.0",
    "gn:asciiname": "Xuzhuangcun",
    "gn:country_code": "CN",
    "gn:dem": 66,
    "gn:feature_class": "P",
    "gn:feature_code": "PPL",
    "gn:name": "Xuzhuangcun",
    "gn:population": 0,
    "gn:timezone": "Asia/Shanghai",
    "iso:country": "CN",
    "name:zho_x_preferred": [
      "许庄村"
    ],
    "wof:name": "Xuzhuangcun",
    "wof:placetype": "locality"
  },
  "geometry": {
    "coordinates": [
      113.98045,
      33.97313
    ],
    "type": "Point"
  }
}