{
  "type": "Feature",
  "properties": {
    "gn:admin1_code": "4.0",
    "gn:asciiname": "Gangjiabian",
    "gn:country_code": "CN",
    "gn:dem": 27,
    "gn:feature_class": "P",
    "gn:feature_code": "PPL",
    "gn:name": "Gangjiabian",
    "gn:population": 0,
    "gn:timezone": "Asia/Shanghai",
    "iso:country": "CN",
    "name:zho_x_preferred": [
      "岗家边"
    ],
    "wof:name": "Gangjiabian",
    "wof:placetype": "locality"
  },
  "geometry": {
    "coordinates": [
      118.99361,
      31.94146
    ],
    "type": "Point"
  }
}