{
  "type": "Feature",
  "properties": {
    "iso:country": "CN",
    "name:ara_x_preferred": [
      "محافظة دانبا"
    ],
    "name:bod_x_preferred": [
      "རོང་བྲག།"
    ],
    "name:deu_x_preferred": [
      "Rongzhag"
    ],
    "name:eng_x_preferred": [
      "Danba County"
    ],
    "name:fas_x_preferred": [
      "شهرستان دانبا"
    ],
    "name:gan_x_preferred": [
      "丹巴县"
    ],
    "name:jpn_x_preferred": [
      "丹巴県"
    ],
    "name:kor_x_preferred": [
      "단바현"
    ],
    "name:nan_x_preferred": [
      "Rongzhag-koān"
    ],
    "name:nld_x_preferred": [
      "Rongzhag"
    ],
    "name:nob_x_preferred": [
      "Danba"
    ],
    "name:rus_x_preferred": [
      "Ронгджаг"
    ],
    "name:spa_x_preferred": [
      "Rongzhag"
    ],
    "name:swe_x_preferred": [
      "Danba"
    ],
    "name:vie_x_preferred": [
      "Đan Ba"
    ],
    "name:wuu_x_preferred": [
      "丹巴县"
    ],
    "name:zho_x_preferred": [
      "丹巴县"
    ],
    "qs:name": "丹巴",
    "qs:name_adm0": "中國",
    "qs:name_adm1": "四川省",
    "qs:photos": 550,
    "qs:photos_1k": 111,
    "qs:photos_9k": 2,
    "qs:photos_9r": 5,
    "qs:photos_all": 550,
    "qs:photos_sr": 7,
    "qs:placetype": "Town",
    "qs:pop_sr": "0",
    "wd:wordcount": 40,
    "wof:name": "丹巴",
    "wof:placetype": "locality"
  },
  "geometry": {
    "coordinates": [
      101.877079,
      30.892
    ],
    "type": "Point"
  }
}