{
  "type": "Feature",
  "properties": {
    "gn:admin1_code": "33.0",
    "gn:asciiname": "Guanyin",
    "gn:country_code": "CN",
    "gn:dem": 497,
    "gn:feature_class": "P",
    "gn:feature_code": "PPL",
    "gn:name": "Guanyin",
    "gn:population": 0,
    "gn:timezone": "Asia/Shanghai",
    "iso:country": "CN",
    "name:cat_x_preferred": [
      "Guanyin"
    ],
    "name:ces_x_preferred": [
      "Kuan-jin"
    ],
    "name:deu_x_preferred": [
      "Guanyin"
    ],
    "name:epo_x_preferred": [
      "Guanjin"
    ],
    "name:fra_x_preferred": [
      "Guanyin"
    ],
    "name:hak_x_preferred": [
      "Kôn-yîm"
    ],
    "name:hun_x_preferred": [
      "Kannon"
    ],
    "name:ind_x_preferred": [
      "Kwan Im"
    ],
    "name:ita_x_preferred": [
      "Guanshiyin"
    ],
    "name:jpn_x_preferred": [
      "観音菩薩"
    ],
    "name:kor_x_preferred": [
      "관세음보살"
    ],
    "name:lat_x_preferred": [
      "Guanyin"
    ],
    "name:lit_x_preferred": [
      "Guanjin"
    ],
    "name:mya_x_preferred": [
      "ကွမ်ယင်မယ်တော်"
    ],
    "name:nld_x_preferred": [
      "Guanyin"
    ],
    "name:nno_x_preferred": [
      "Guanyin"
    ],
    "name:nor_x_preferred": [
      "Guanyin"
    ],
    "name:pol_x_preferred": [
      "Guanyin"
    ],
    "name:por_x_preferred": [
      "Kuan Yin"
    ],
    "name:rus_x_preferred": [
      "Гуаньинь"
    ],
    "name:slv_x_preferred": [
      "Kvamon"
    ],
    "name:spa_x_preferred": [
      "Guan Yin"
    ],
    "name:swe_x_preferred": [
      "Guanyin"
    ],
    "name:tha_x_preferred": [
      "กวนอิม"
    ],
    "name:tur_x_preferred": [
      "Guan Yin"
    ],
    "name:ukr_x_preferred": [
      "Ґуаньїнь"
    ],
    "name:vie_x_preferred": [
      "Quan Âm"
    ],
    "name:wuu_x_preferred": [
      "觀世音菩薩"
    ],
    "name:zho_x_preferred": [
      "观音"
    ],
    "name:zho_x_variant": [
      "觀世音菩薩"
    ],
    "wof:name": "Guanyin",
    "wof:placetype": "locality"
  },
  "geometry": {
    "coordinates": [
      106.31638,
      29.90829
    ],
    "type": "Point"
  }
}