{
  "type": "Feature",
  "properties": {
    "gn:admin1_code": "25",
    "gn:asciiname": "Songlizhuang",
    "gn:country_code": "CN",
    "gn:dem": 49,
    "gn:feature_class": "P",
    "gn:feature_code": "PPL",
    "gn:name": "Songlizhuang",
    "gn:population": 0,
    "gn:timezone": "Asia/Shanghai",
    "iso:country": "CN",
    "name:zho_x_preferred": [
      "宋李庄"
    ],
    "wof:name": "Songlizhuang",
    "wof:placetype": "locality"
  },
  "geometry": {
    "coordinates": [
      115.71,
      34.9164
    ],
    "type": "Point"
  }
}