{
  "type": "Feature",
  "properties": {
    "gn:admin1_code": "11.0",
    "gn:asciiname": "Shanchong'ao",
    "gn:country_code": "CN",
    "gn:dem": 205,
    "gn:feature_class": "P",
    "gn:feature_code": "PPL",
    "gn:name": "Shanchong’ao",
    "gn:population": 0,
    "gn:timezone": "Asia/Shanghai",
    "iso:country": "CN",
    "name:und_x_variant": [
      "Shanchong’ao"
    ],
    "name:zho_x_preferred": [
      "山冲坳"
    ],
    "wof:name": "Shanchong'ao",
    "wof:placetype": "locality"
  },
  "geometry": {
    "coordinates": [
      113.27795,
      25.94916
    ],
    "type": "Point"
  }
}