{
  "type": "Feature",
  "properties": {
    "gn:admin1_code": "9",
    "gn:asciiname": "Luli",
    "gn:country_code": "CN",
    "gn:dem": 56,
    "gn:feature_class": "P",
    "gn:feature_code": "PPL",
    "gn:name": "Luli",
    "gn:population": 0,
    "gn:timezone": "Asia/Shanghai",
    "iso:country": "CN",
    "name:deu_x_preferred": [
      "Elulaios"
    ],
    "name:fra_x_preferred": [
      "Louli"
    ],
    "name:nld_x_preferred": [
      "Elulaios"
    ],
    "name:por_x_preferred": [
      "Luli"
    ],
    "name:rus_x_preferred": [
      "Элулай"
    ],
    "name:spa_x_preferred": [
      "Elulayo"
    ],
    "name:zho_x_preferred": [
      "芦里"
    ],
    "wof:name": "Luli",
    "wof:placetype": "locality"
  },
  "geometry": {
    "coordinates": [
      115.079,
      35.5606
    ],
    "type": "Point"
  }
}