{
  "type": "Feature",
  "properties": {
    "gn:admin1_code": "19.0",
    "gn:asciiname": "Changweizicun",
    "gn:country_code": "CN",
    "gn:dem": 155,
    "gn:feature_class": "P",
    "gn:feature_code": "PPL",
    "gn:name": "Changweizicun",
    "gn:population": 0,
    "gn:timezone": "Asia/Shanghai",
    "iso:country": "CN",
    "name:zho_x_preferred": [
      "长尾子村"
    ],
    "wof:name": "Changweizicun",
    "wof:placetype": "locality"
  },
  "geometry": {
    "coordinates": [
      124.162,
      42.9561
    ],
    "type": "Point"
  }
}