{
  "type": "Feature",
  "properties": {
    "gn:admin1_code": "01",
    "gn:asciiname": "Tangqiaocun",
    "gn:country_code": "CN",
    "gn:dem": 21,
    "gn:feature_class": "P",
    "gn:feature_code": "PPL",
    "gn:name": "Tangqiaocun",
    "gn:population": 0,
    "gn:timezone": "Asia/Shanghai",
    "iso:country": "CN",
    "name:und_x_variant": [
      "T’ang-ch’iao",
      "Tangqiao",
      "Tangqiaocun"
    ],
    "name:zho_x_preferred": [
      "汤桥村"
    ],
    "wof:name": "Tangqiaocun",
    "wof:placetype": "locality"
  },
  "geometry": {
    "coordinates": [
      119.25293,
      31.2019
    ],
    "type": "Point"
  }
}