{
  "type": "Feature",
  "properties": {
    "gn:admin1_code": "12.0",
    "gn:asciiname": "Ancangping",
    "gn:country_code": "CN",
    "gn:dem": 958,
    "gn:feature_class": "P",
    "gn:feature_code": "PPL",
    "gn:name": "Ancangping",
    "gn:population": 0,
    "gn:timezone": "Asia/Shanghai",
    "iso:country": "CN",
    "name:zho_x_preferred": [
      "安仓坪"
    ],
    "wof:name": "Ancangping",
    "wof:placetype": "locality"
  },
  "geometry": {
    "coordinates": [
      110.88044,
      30.92931
    ],
    "type": "Point"
  }
}