{
  "type": "Feature",
  "properties": {
    "gn:admin1_code": "14.0",
    "gn:asciiname": "Naga",
    "gn:country_code": "CN",
    "gn:dem": 4199,
    "gn:feature_class": "P",
    "gn:feature_code": "PPL",
    "gn:name": "Naga",
    "gn:population": 0,
    "gn:timezone": "Asia/Urumqi",
    "iso:country": "CN",
    "name:ara_x_preferred": [
      "نجا"
    ],
    "name:bcl_x_preferred": [
      "Naga"
    ],
    "name:ben_x_preferred": [
      "নাগা"
    ],
    "name:cat_x_preferred": [
      "Naga"
    ],
    "name:ceb_x_preferred": [
      "Naga"
    ],
    "name:dan_x_preferred": [
      "Naga"
    ],
    "name:deu_x_preferred": [
      "Naga City"
    ],
    "name:deu_x_variant": [
      "Naga"
    ],
    "name:ell_x_preferred": [
      "Νάγκα"
    ],
    "name:eng_x_preferred": [
      "Naga"
    ],
    "name:fas_x_preferred": [
      "ناگا"
    ],
    "name:fin_x_preferred": [
      "Naga"
    ],
    "name:fra_x_preferred": [
      "Naga"
    ],
    "name:heb_x_preferred": [
      "גבעות נאגה"
    ],
    "name:hin_x_preferred": [
      "नाग"
    ],
    "name:hrv_x_preferred": [
      "Naga"
    ],
    "name:hun_x_preferred": [
      "Naga"
    ],
    "name:ind_x_preferred": [
      "Naga"
    ],
    "name:ita_x_preferred": [
      "Naga"
    ],
    "name:jav_x_preferred": [
      "Naga"
    ],
    "name:jpn_x_preferred": [
      "ナが"
    ],
    "name:kor_x_preferred": [
      "나가"
    ],
    "name:lit_x_preferred": [
      "Naga"
    ],
    "name:msa_x_preferred": [
      "Naga"
    ],
    "name:nld_x_preferred": [
      "Naga"
    ],
    "name:pol_x_preferred": [
      "Naga"
    ],
    "name:por_x_preferred": [
      "Naga"
    ],
    "name:rus_x_preferred": [
      "Нага"
    ],
    "name:spa_x_preferred": [
      "Naga"
    ],
    "name:swe_x_preferred": [
      "Naga"
    ],
    "name:tgl_x_preferred": [
      "Naga"
    ],
    "name:tur_x_preferred": [
      "Naga"
    ],
    "name:ukr_x_preferred": [
      "Нага"
    ],
    "name:urd_x_preferred": [
      "ناگا"
    ],
    "name:vie_x_preferred": [
      "Naga"
    ],
    "name:war_x_preferred": [
      "Naga"
    ],
    "name:zho_cn_x_preferred": [
      "那牙"
    ],
    "name:zho_tw_x_preferred": [
      "那牙"
    ],
    "name:zho_x_preferred": [
      "那嘎"
    ],
    "wof:name": "Naga",
    "wof:placetype": "locality"
  },
  "geometry": {
    "coordinates": [
      95.84386,
      31.04513
    ],
    "type": "Point"
  }
}