{
  "type": "Feature",
  "properties": {
    "gn:admin1_code": "22",
    "gn:asciiname": "Xiaotangshan",
    "gn:country_code": "CN",
    "gn:dem": 39,
    "gn:feature_class": "P",
    "gn:feature_code": "PPLA4",
    "gn:name": "Xiaotangshan",
    "gn:population": 0,
    "gn:timezone": "Asia/Shanghai",
    "iso:country": "CN",
    "name:und_x_variant": [
      "Hsiao-t’ang-shan",
      "Ta-t’ang-shan",
      "T’ang-shan",
      "Xiaotangshan",
      "Xiaotangshan Zhen"
    ],
    "name:zho_x_preferred": [
      "小汤山"
    ],
    "name:zho_x_variant": [
      "小汤山镇"
    ],
    "wof:name": "Xiaotangshan",
    "wof:placetype": "locality"
  },
  "geometry": {
    "coordinates": [
      116.38456,
      40.17663
    ],
    "type": "Point"
  }
}