{
  "type": "Feature",
  "properties": {
    "gn:admin1_code": "5.0",
    "gn:asciiname": "Houwu Minggou",
    "gn:country_code": "CN",
    "gn:dem": 407,
    "gn:feature_class": "P",
    "gn:feature_code": "PPL",
    "gn:name": "Houwu Minggou",
    "gn:population": 0,
    "gn:timezone": "Asia/Shanghai",
    "iso:country": "CN",
    "name:zho_x_preferred": [
      "后乌鸣沟"
    ],
    "wof:name": "Houwu Minggou",
    "wof:placetype": "locality"
  },
  "geometry": {
    "coordinates": [
      125.05769,
      42.6754
    ],
    "type": "Point"
  }
}