{
  "type": "Feature",
  "properties": {
    "gn:admin1_code": "26.0",
    "gn:asciiname": "Houjumingou",
    "gn:country_code": "CN",
    "gn:dem": 1349,
    "gn:feature_class": "P",
    "gn:feature_code": "PPL",
    "gn:name": "Houjumingou",
    "gn:population": 0,
    "gn:timezone": "Asia/Shanghai",
    "iso:country": "CN",
    "name:zho_x_preferred": [
      "后居民沟"
    ],
    "wof:name": "Houjumingou",
    "wof:placetype": "locality"
  },
  "geometry": {
    "coordinates": [
      109.69278,
      35.90535
    ],
    "type": "Point"
  }
}