{
  "type": "Feature",
  "properties": {
    "gn:admin1_code": "08",
    "gn:asciiname": "Yanjiang",
    "gn:country_code": "CN",
    "gn:dem": 120,
    "gn:feature_class": "P",
    "gn:feature_code": "PPLA4",
    "gn:name": "Yanjiang",
    "gn:population": 0,
    "gn:timezone": "Asia/Shanghai",
    "iso:country": "CN",
    "name:und_x_variant": [
      "Huo-erh-mo-chin",
      "Huormojin",
      "Yanjiang",
      "Yanjiang Manzu Dawo’erzu",
      "Yanjiang Manzu Dawo’erzu Xiang"
    ],
    "name:zho_x_preferred": [
      "沿江"
    ],
    "name:zho_x_variant": [
      "沿江满族达斡尔族",
      "沿江满族达斡尔族乡"
    ],
    "wof:name": "Yanjiang",
    "wof:placetype": "locality"
  },
  "geometry": {
    "coordinates": [
      127.78266,
      49.57308
    ],
    "type": "Point"
  }
}