{
  "type": "Feature",
  "properties": {
    "gn:admin1_code": "16.0",
    "gn:asciiname": "Zhen'an",
    "gn:country_code": "CN",
    "gn:dem": 48,
    "gn:feature_class": "P",
    "gn:feature_code": "PPL",
    "gn:name": "Zhen’an",
    "gn:population": 0,
    "gn:timezone": "Asia/Shanghai",
    "iso:country": "CN",
    "name:und_x_variant": [
      "Zhen’an"
    ],
    "name:zho_x_preferred": [
      "镇安"
    ],
    "wof:name": "Zhen'an",
    "wof:placetype": "locality"
  },
  "geometry": {
    "coordinates": [
      109.873,
      23.1553
    ],
    "type": "Point"
  }
}