{
  "type": "Feature",
  "properties": {
    "gn:admin1_code": "32.0",
    "gn:asciiname": "Tongling",
    "gn:country_code": "CN",
    "gn:dem": 388,
    "gn:feature_class": "P",
    "gn:feature_code": "PPL",
    "gn:name": "Tongling",
    "gn:population": 0,
    "gn:timezone": "Asia/Shanghai",
    "iso:country": "CN",
    "name:ara_x_preferred": [
      "تونغلينغ"
    ],
    "name:bul_x_preferred": [
      "Тунлин"
    ],
    "name:cdo_x_preferred": [
      "Dè̤ng-lìng"
    ],
    "name:ces_x_preferred": [
      "Tchung-ling"
    ],
    "name:cym_x_preferred": [
      "Tongling"
    ],
    "name:dan_x_preferred": [
      "Tongling"
    ],
    "name:deu_x_preferred": [
      "Tongling"
    ],
    "name:epo_x_preferred": [
      "Tonglingo"
    ],
    "name:eus_x_preferred": [
      "Tongling"
    ],
    "name:fas_x_preferred": [
      "تانگلینگ"
    ],
    "name:fin_x_preferred": [
      "Tongling"
    ],
    "name:fra_x_preferred": [
      "Tongling"
    ],
    "name:heb_x_preferred": [
      "טונגלינג"
    ],
    "name:hye_x_preferred": [
      "Տունլին"
    ],
    "name:ita_x_preferred": [
      "Tongling"
    ],
    "name:jpn_x_preferred": [
      "銅陵市"
    ],
    "name:kik_x_preferred": [
      "Tongling"
    ],
    "name:kor_x_preferred": [
      "퉁링시"
    ],
    "name:mlg_x_preferred": [
      "Tongling"
    ],
    "name:nld_x_preferred": [
      "Tongling"
    ],
    "name:nno_x_preferred": [
      "Tongling"
    ],
    "name:nor_x_preferred": [
      "Tongling"
    ],
    "name:pam_x_preferred": [
      "Tongling"
    ],
    "name:pnb_x_preferred": [
      "تونگ لینگ"
    ],
    "name:pol_x_preferred": [
      "Tongling"
    ],
    "name:por_x_preferred": [
      "Tongling"
    ],
    "name:rus_x_preferred": [
      "Тунлин"
    ],
    "name:spa_x_preferred": [
      "Tongling"
    ],
    "name:srp_x_preferred": [
      "Тунглинг"
    ],
    "name:swe_x_preferred": [
      "Tongling"
    ],
    "name:tgl_x_preferred": [
      "Tongling"
    ],
    "name:tur_x_preferred": [
      "Tongling"
    ],
    "name:urd_x_preferred": [
      "تونگلنگ"
    ],
    "name:vie_x_preferred": [
      "Đồng Lăng"
    ],
    "name:war_x_preferred": [
      "Tongling"
    ],
    "name:wuu_x_preferred": [
      "铜陵市"
    ],
    "name:zho_x_preferred": [
      "铜铃"
    ],
    "name:zho_x_variant": [
      "铜陵市"
    ],
    "wof:name": "Tongling",
    "wof:placetype": "locality"
  },
  "geometry": {
    "coordinates": [
      104.283,
      30.0964
    ],
    "type": "Point"
  }
}