{
  "type": "Feature",
  "properties": {
    "gn:admin1_code": "32.0",
    "gn:asciiname": "Qiaoting",
    "gn:country_code": "CN",
    "gn:dem": 770,
    "gn:feature_class": "P",
    "gn:feature_code": "PPLA4",
    "gn:name": "Qiaoting",
    "gn:population": 0,
    "gn:timezone": "Asia/Shanghai",
    "iso:country": "CN",
    "name:und_x_variant": [
      "Qiaoting Xiang",
      "桥亭乡"
    ],
    "name:zho_x_preferred": [
      "桥亭"
    ],
    "wof:name": "Qiaoting",
    "wof:placetype": "locality"
  },
  "geometry": {
    "coordinates": [
      106.89823,
      32.46492
    ],
    "type": "Point"
  }
}