{
  "type": "Feature",
  "properties": {
    "gn:admin1_code": "4.0",
    "gn:asciiname": "Dongfeng",
    "gn:country_code": "CN",
    "gn:dem": 5,
    "gn:feature_class": "P",
    "gn:feature_code": "PPL",
    "gn:name": "Dongfeng",
    "gn:population": 0,
    "gn:timezone": "Asia/Shanghai",
    "iso:country": "CN",
    "name:ceb_x_preferred": [
      "Dongfeng"
    ],
    "name:dan_x_preferred": [
      "Dong Feng"
    ],
    "name:deu_x_preferred": [
      "Dongfeng"
    ],
    "name:fra_x_preferred": [
      "Dongfeng"
    ],
    "name:mlg_x_preferred": [
      "Dongfeng"
    ],
    "name:nld_x_preferred": [
      "Dongfeng"
    ],
    "name:nor_x_preferred": [
      "Dongfeng"
    ],
    "name:pol_x_preferred": [
      "Dongfeng"
    ],
    "name:rus_x_preferred": [
      "Дунфэн"
    ],
    "name:swe_x_preferred": [
      "Dongfeng"
    ],
    "name:vie_x_preferred": [
      "Đông Phong"
    ],
    "name:zho_x_preferred": [
      "东冯"
    ],
    "wof:name": "Dongfeng",
    "wof:placetype": "locality"
  },
  "geometry": {
    "coordinates": [
      119.98135,
      32.73939
    ],
    "type": "Point"
  }
}