{
  "type": "Feature",
  "properties": {
    "gn:country": "CN",
    "gn:fcode": "PPL",
    "gn:population": 41484,
    "iso:country": "CN",
    "name:ceb_x_preferred": [
      "Guye"
    ],
    "name:deu_x_preferred": [
      "Guye"
    ],
    "name:fra_x_preferred": [
      "Guye"
    ],
    "name:mlg_x_preferred": [
      "Guye"
    ],
    "name:rus_x_preferred": [
      "Гюи"
    ],
    "name:und_x_variant": [
      "Ku-yeh"
    ],
    "name:zho_x_preferred": [
      "古冶"
    ],
    "qs:name": "Guye",
    "qs:photos_9r": 0,
    "qs:photos_sr": 0,
    "qs:pop_sr": "7",
    "wd:wordcount": 47,
    "wof:name": "Guye",
    "wof:placetype": "locality",
    "wof:population": 41484
  },
  "geometry": {
    "coordinates": [
      118.41667,
      39.73333
    ],
    "type": "Point"
  }
}