{
  "type": "Feature",
  "properties": {
    "gn:admin1_code": "33.0",
    "gn:asciiname": "Wuhu",
    "gn:country_code": "CN",
    "gn:dem": 687,
    "gn:feature_class": "P",
    "gn:feature_code": "PPL",
    "gn:name": "Wuhu",
    "gn:population": 0,
    "gn:timezone": "Asia/Shanghai",
    "iso:country": "CN",
    "name:afr_x_preferred": [
      "Wuhu"
    ],
    "name:ara_x_preferred": [
      "ووهو"
    ],
    "name:bul_x_preferred": [
      "Уху"
    ],
    "name:cdo_x_preferred": [
      "Ù-hù"
    ],
    "name:ceb_x_preferred": [
      "Wuhu Shi"
    ],
    "name:ces_x_preferred": [
      "Wu-chu"
    ],
    "name:cym_x_preferred": [
      "Wuhu"
    ],
    "name:dan_x_preferred": [
      "Wuhu"
    ],
    "name:deu_x_preferred": [
      "Wuhu"
    ],
    "name:epo_x_preferred": [
      "Vuĥu"
    ],
    "name:eus_x_preferred": [
      "Wuhu"
    ],
    "name:fas_x_preferred": [
      "واها"
    ],
    "name:fin_x_preferred": [
      "Wuhu"
    ],
    "name:fra_x_preferred": [
      "Wuhu"
    ],
    "name:heb_x_preferred": [
      "ווהו"
    ],
    "name:hye_x_preferred": [
      "Վուհու"
    ],
    "name:ita_x_preferred": [
      "Wuhu"
    ],
    "name:jpn_x_preferred": [
      "蕪湖市"
    ],
    "name:kik_x_preferred": [
      "Wuhu"
    ],
    "name:kor_x_preferred": [
      "우후시"
    ],
    "name:lit_x_preferred": [
      "Uhu"
    ],
    "name:mal_x_preferred": [
      "വുഹു"
    ],
    "name:mlg_x_preferred": [
      "Wuhu"
    ],
    "name:mwl_x_preferred": [
      "Wuhu"
    ],
    "name:nld_x_preferred": [
      "Wuhu"
    ],
    "name:nno_x_preferred": [
      "Wuhu"
    ],
    "name:nor_x_preferred": [
      "Wuhu"
    ],
    "name:pam_x_preferred": [
      "Wuhu"
    ],
    "name:pnb_x_preferred": [
      "ووہو"
    ],
    "name:pol_x_preferred": [
      "Wuhu"
    ],
    "name:por_x_preferred": [
      "Wuhu"
    ],
    "name:rus_x_preferred": [
      "Уху"
    ],
    "name:spa_x_preferred": [
      "Wuhu"
    ],
    "name:srp_x_preferred": [
      "Вуху"
    ],
    "name:swe_x_preferred": [
      "Wuhu"
    ],
    "name:tam_x_preferred": [
      "உகு"
    ],
    "name:tgl_x_preferred": [
      "Wuhu"
    ],
    "name:tur_x_preferred": [
      "Wuhu"
    ],
    "name:urd_x_preferred": [
      "ووہو"
    ],
    "name:vie_x_preferred": [
      "Vu Hồ"
    ],
    "name:war_x_preferred": [
      "Wuhu"
    ],
    "name:wuu_x_preferred": [
      "芜湖市"
    ],
    "name:zho_x_preferred": [
      "五湖"
    ],
    "name:zho_x_variant": [
      "芜湖市"
    ],
    "wof:name": "Wuhu",
    "wof:placetype": "locality"
  },
  "geometry": {
    "coordinates": [
      108.47227,
      31.01224
    ],
    "type": "Point"
  }
}