{
  "type": "Feature",
  "properties": {
    "gn:admin1_code": "7.0",
    "gn:asciiname": "Pukou",
    "gn:country_code": "CN",
    "gn:dem": 11,
    "gn:feature_class": "P",
    "gn:feature_code": "PPL",
    "gn:name": "Pukou",
    "gn:population": 0,
    "gn:timezone": "Asia/Shanghai",
    "iso:country": "CN",
    "name:zho_x_preferred": [
      "浦口"
    ],
    "wof:name": "Pukou",
    "wof:placetype": "locality"
  },
  "geometry": {
    "coordinates": [
      119.20526,
      26.06516
    ],
    "type": "Point"
  }
}