{
  "type": "Feature",
  "properties": {
    "gn:admin1_code": "19.0",
    "gn:asciiname": "Changlingcun",
    "gn:country_code": "CN",
    "gn:dem": 176,
    "gn:feature_class": "P",
    "gn:feature_code": "PPL",
    "gn:name": "Changlingcun",
    "gn:population": 0,
    "gn:timezone": "Asia/Shanghai",
    "iso:country": "CN",
    "name:zho_x_preferred": [
      "长岭村"
    ],
    "wof:name": "Changlingcun",
    "wof:placetype": "locality"
  },
  "geometry": {
    "coordinates": [
      125.30777,
      40.94055
    ],
    "type": "Point"
  }
}