{
  "type": "Feature",
  "properties": {
    "gn:admin1_code": "7.0",
    "gn:asciiname": "Yuegang",
    "gn:country_code": "CN",
    "gn:dem": 43,
    "gn:feature_class": "P",
    "gn:feature_code": "PPL",
    "gn:name": "Yuegang",
    "gn:population": 0,
    "gn:timezone": "Asia/Shanghai",
    "iso:country": "CN",
    "name:zho_x_preferred": [
      "月港"
    ],
    "wof:name": "Yuegang",
    "wof:placetype": "locality"
  },
  "geometry": {
    "coordinates": [
      117.1141,
      23.80864
    ],
    "type": "Point"
  }
}