{
  "type": "Feature",
  "properties": {
    "gn:admin1_code": "16.0",
    "gn:asciiname": "Fada",
    "gn:country_code": "CN",
    "gn:dem": 258,
    "gn:feature_class": "P",
    "gn:feature_code": "PPL",
    "gn:name": "Fada",
    "gn:population": 0,
    "gn:timezone": "Asia/Shanghai",
    "iso:country": "CN",
    "name:ben_x_preferred": [
      "ফাদা"
    ],
    "name:ceb_x_preferred": [
      "Fada"
    ],
    "name:deu_x_preferred": [
      "Fada"
    ],
    "name:fas_x_preferred": [
      "فادا"
    ],
    "name:fra_x_preferred": [
      "Fada"
    ],
    "name:hun_x_preferred": [
      "Fada"
    ],
    "name:jpn_x_preferred": [
      "ファダ"
    ],
    "name:por_x_preferred": [
      "Fada"
    ],
    "name:spa_x_preferred": [
      "Fada"
    ],
    "name:vie_x_preferred": [
      "Fada"
    ],
    "name:zho_x_preferred": [
      "发达"
    ],
    "wof:name": "Fada",
    "wof:placetype": "locality"
  },
  "geometry": {
    "coordinates": [
      107.445,
      23.0923
    ],
    "type": "Point"
  }
}