{
  "type": "Feature",
  "properties": {
    "gn:admin1_code": "30",
    "gn:asciiname": "Shitan",
    "gn:country_code": "CN",
    "gn:dem": 69,
    "gn:feature_class": "P",
    "gn:feature_code": "PPLA4",
    "gn:name": "Shitan",
    "gn:population": 0,
    "gn:timezone": "Asia/Shanghai",
    "iso:country": "CN",
    "name:und_x_variant": [
      "Shih-t’an",
      "Shitan",
      "石潭",
      "Shitan Zhen"
    ],
    "name:zho_x_preferred": [
      "石潭镇"
    ],
    "wof:name": "Shitan",
    "wof:placetype": "locality"
  },
  "geometry": {
    "coordinates": [
      112.76377,
      24.12861
    ],
    "type": "Point"
  }
}