{
  "type": "Feature",
  "properties": {
    "gn:admin1_code": "32.0",
    "gn:asciiname": "Baiyun",
    "gn:country_code": "CN",
    "gn:dem": 717,
    "gn:feature_class": "P",
    "gn:feature_code": "PPL",
    "gn:name": "Baiyun",
    "gn:population": 0,
    "gn:timezone": "Asia/Shanghai",
    "iso:country": "CN",
    "name:ceb_x_preferred": [
      "Baiyun"
    ],
    "name:deu_x_preferred": [
      "Baiyun"
    ],
    "name:eus_x_preferred": [
      "Baiyun barrutia"
    ],
    "name:fra_x_preferred": [
      "Baiyun"
    ],
    "name:jpn_x_preferred": [
      "白雲区"
    ],
    "name:kor_x_preferred": [
      "바이윈구"
    ],
    "name:nor_x_preferred": [
      "Baiyun"
    ],
    "name:swe_x_preferred": [
      "Baiyun"
    ],
    "name:zho_x_preferred": [
      "白云"
    ],
    "name:zho_x_variant": [
      "白云区"
    ],
    "wof:name": "Baiyun",
    "wof:placetype": "locality"
  },
  "geometry": {
    "coordinates": [
      104.632,
      28.3666
    ],
    "type": "Point"
  }
}