{
  "type": "Feature",
  "properties": {
    "gn:admin1_code": "3.0",
    "gn:asciiname": "Hushan",
    "gn:country_code": "CN",
    "gn:dem": 54,
    "gn:feature_class": "P",
    "gn:feature_code": "PPL",
    "gn:name": "Hushan",
    "gn:population": 0,
    "gn:timezone": "Asia/Shanghai",
    "iso:country": "CN",
    "name:und_x_variant": [
      "虎山"
    ],
    "wof:name": "Hushan",
    "wof:placetype": "locality"
  },
  "geometry": {
    "coordinates": [
      115.1355,
      27.92106
    ],
    "type": "Point"
  }
}