{
  "type": "Feature",
  "properties": {
    "gn:admin1_code": "16.0",
    "gn:asciiname": "Caixian",
    "gn:country_code": "CN",
    "gn:dem": 253,
    "gn:feature_class": "P",
    "gn:feature_code": "PPL",
    "gn:name": "Caixian",
    "gn:population": 0,
    "gn:timezone": "Asia/Shanghai",
    "iso:country": "CN",
    "name:zho_x_preferred": [
      "才现"
    ],
    "wof:name": "Caixian",
    "wof:placetype": "locality"
  },
  "geometry": {
    "coordinates": [
      108.192,
      24.9592
    ],
    "type": "Point"
  }
}