{
  "type": "Feature",
  "properties": {
    "gn:admin1_code": "4.0",
    "gn:asciiname": "Taiping",
    "gn:country_code": "CN",
    "gn:dem": 8,
    "gn:feature_class": "P",
    "gn:feature_code": "PPL",
    "gn:name": "Taiping",
    "gn:population": 0,
    "gn:timezone": "Asia/Shanghai",
    "iso:country": "CN",
    "name:ceb_x_preferred": [
      "Taiping"
    ],
    "name:deu_x_preferred": [
      "Taiping"
    ],
    "name:fra_x_preferred": [
      "Taiping"
    ],
    "name:hun_x_preferred": [
      "Taiping"
    ],
    "name:ind_x_preferred": [
      "Taiping"
    ],
    "name:msa_x_preferred": [
      "Taiping"
    ],
    "name:nld_x_preferred": [
      "Taiping"
    ],
    "name:rus_x_preferred": [
      "Тайпин"
    ],
    "name:swe_x_preferred": [
      "Taiping"
    ],
    "name:zho_x_preferred": [
      "太平"
    ],
    "wof:name": "Taiping",
    "wof:placetype": "locality"
  },
  "geometry": {
    "coordinates": [
      118.83938,
      31.3295
    ],
    "type": "Point"
  }
}