{
  "type": "Feature",
  "properties": {
    "gn:admin1_code": "16.0",
    "gn:asciiname": "Zhongganlan",
    "gn:country_code": "CN",
    "gn:dem": 501,
    "gn:feature_class": "P",
    "gn:feature_code": "PPL",
    "gn:name": "Zhongganlan",
    "gn:population": 0,
    "gn:timezone": "Asia/Shanghai",
    "iso:country": "CN",
    "name:zho_x_preferred": [
      "中干榄"
    ],
    "wof:name": "Zhongganlan",
    "wof:placetype": "locality"
  },
  "geometry": {
    "coordinates": [
      108.815,
      25.2944
    ],
    "type": "Point"
  }
}