{
  "type": "Feature",
  "properties": {
    "gn:admin1_code": "4.0",
    "gn:asciiname": "Xihu",
    "gn:country_code": "CN",
    "gn:dem": 8,
    "gn:feature_class": "P",
    "gn:feature_code": "PPL",
    "gn:name": "Xihu",
    "gn:population": 0,
    "gn:timezone": "Asia/Shanghai",
    "iso:country": "CN",
    "name:ceb_x_preferred": [
      "Xihu"
    ],
    "name:dan_x_preferred": [
      "Xihu"
    ],
    "name:deu_x_preferred": [
      "Xihu"
    ],
    "name:eus_x_preferred": [
      "Xihu"
    ],
    "name:fra_x_preferred": [
      "Xihu"
    ],
    "name:jpn_x_preferred": [
      "西湖区"
    ],
    "name:kor_x_preferred": [
      "시후구"
    ],
    "name:nor_x_preferred": [
      "Xihu"
    ],
    "name:pol_x_preferred": [
      "Xihu"
    ],
    "name:spa_x_preferred": [
      "Xihu"
    ],
    "name:zho_x_preferred": [
      "Xihu"
    ],
    "name:zho_x_variant": [
      "西胡",
      "西湖区"
    ],
    "wof:name": "Xihu",
    "wof:placetype": "locality"
  },
  "geometry": {
    "coordinates": [
      119.15129,
      34.98402
    ],
    "type": "Point"
  }
}