{
  "type": "Feature",
  "properties": {
    "gn:admin1_code": "26.0",
    "gn:asciiname": "Zoumaliang",
    "gn:country_code": "CN",
    "gn:dem": 1589,
    "gn:feature_class": "P",
    "gn:feature_code": "PPL",
    "gn:name": "Zoumaliang",
    "gn:population": 0,
    "gn:timezone": "Asia/Shanghai",
    "iso:country": "CN",
    "name:zho_x_preferred": [
      "走马梁"
    ],
    "wof:name": "Zoumaliang",
    "wof:placetype": "locality"
  },
  "geometry": {
    "coordinates": [
      108.03535,
      37.20119
    ],
    "type": "Point"
  }
}