{
  "type": "Feature",
  "properties": {
    "gn:admin1_code": "26.0",
    "gn:asciiname": "Nanzhuang",
    "gn:country_code": "CN",
    "gn:dem": 784,
    "gn:feature_class": "P",
    "gn:feature_code": "PPL",
    "gn:name": "Nanzhuang",
    "gn:population": 0,
    "gn:timezone": "Asia/Shanghai",
    "iso:country": "CN",
    "name:fra_x_preferred": [
      "Nanzhuang"
    ],
    "name:hak_x_preferred": [
      "Nàm-chông-hiông"
    ],
    "name:jpn_x_preferred": [
      "南庄郷"
    ],
    "name:kor_x_preferred": [
      "난좡향"
    ],
    "name:und_x_variant": [
      "南庄"
    ],
    "name:vie_x_preferred": [
      "Nam Trang"
    ],
    "name:zho_x_preferred": [
      "南庄鄉"
    ],
    "wof:name": "Nanzhuang",
    "wof:placetype": "locality"
  },
  "geometry": {
    "coordinates": [
      107.72355,
      34.4757
    ],
    "type": "Point"
  }
}