{
  "type": "Feature",
  "properties": {
    "gn:admin1_code": "24.0",
    "gn:asciiname": "Liangjiapo",
    "gn:country_code": "CN",
    "gn:dem": 944,
    "gn:feature_class": "P",
    "gn:feature_code": "PPL",
    "gn:name": "Liangjiapo",
    "gn:population": 0,
    "gn:timezone": "Asia/Shanghai",
    "iso:country": "CN",
    "name:zho_x_preferred": [
      "梁家坡"
    ],
    "wof:name": "Liangjiapo",
    "wof:placetype": "locality"
  },
  "geometry": {
    "coordinates": [
      110.80368,
      35.81903
    ],
    "type": "Point"
  }
}