{
  "type": "Feature",
  "properties": {
    "gn:admin1_code": "12",
    "gn:asciiname": "Guanting",
    "gn:country_code": "CN",
    "gn:dem": 338,
    "gn:feature_class": "P",
    "gn:feature_code": "PPL",
    "gn:name": "Guanting",
    "gn:population": 0,
    "gn:timezone": "Asia/Shanghai",
    "iso:country": "CN",
    "name:deu_x_preferred": [
      "Guanting"
    ],
    "name:zho_x_preferred": [
      "官亭"
    ],
    "wof:name": "Guanting",
    "wof:placetype": "locality"
  },
  "geometry": {
    "coordinates": [
      110.91303,
      32.43302
    ],
    "type": "Point"
  }
}