{
  "type": "Feature",
  "properties": {
    "gn:admin1_code": "2.0",
    "gn:asciiname": "Kengxi",
    "gn:country_code": "CN",
    "gn:dem": 117,
    "gn:feature_class": "P",
    "gn:feature_code": "PPL",
    "gn:name": "Kengxi",
    "gn:population": 0,
    "gn:timezone": "Asia/Shanghai",
    "iso:country": "CN",
    "name:zho_x_preferred": [
      "坑西"
    ],
    "wof:name": "Kengxi",
    "wof:placetype": "locality"
  },
  "geometry": {
    "coordinates": [
      120.96604,
      29.61138
    ],
    "type": "Point"
  }
}