{
  "type": "Feature",
  "properties": {
    "gn:admin1_code": "24.0",
    "gn:asciiname": "Muling",
    "gn:country_code": "CN",
    "gn:dem": 767,
    "gn:feature_class": "P",
    "gn:feature_code": "PPL",
    "gn:name": "Muling",
    "gn:population": 0,
    "gn:timezone": "Asia/Shanghai",
    "iso:country": "CN",
    "name:ara_x_preferred": [
      "مولنج"
    ],
    "name:dan_x_preferred": [
      "Muling"
    ],
    "name:deu_x_preferred": [
      "Muling"
    ],
    "name:fra_x_preferred": [
      "Muling"
    ],
    "name:ita_x_preferred": [
      "Muling"
    ],
    "name:jpn_x_preferred": [
      "穆リョウ市"
    ],
    "name:kik_x_preferred": [
      "Muling"
    ],
    "name:kor_x_preferred": [
      "무링시"
    ],
    "name:mlg_x_preferred": [
      "Muling"
    ],
    "name:nor_x_preferred": [
      "Muling"
    ],
    "name:pam_x_preferred": [
      "Muling"
    ],
    "name:rus_x_preferred": [
      "Мулин"
    ],
    "name:swe_x_preferred": [
      "Muling"
    ],
    "name:urd_x_preferred": [
      "مولنگ"
    ],
    "name:vie_x_preferred": [
      "Sông Mục Lăng"
    ],
    "name:vie_x_variant": [
      "Mục Lăng"
    ],
    "name:zho_x_preferred": [
      "牧岭"
    ],
    "name:zho_x_variant": [
      "穆棱市"
    ],
    "wof:name": "Muling",
    "wof:placetype": "locality"
  },
  "geometry": {
    "coordinates": [
      110.79536,
      36.47992
    ],
    "type": "Point"
  }
}