{
  "type": "Feature",
  "properties": {
    "gn:admin1_code": "25.0",
    "gn:asciiname": "Jingangkoucun",
    "gn:country_code": "CN",
    "gn:dem": 62,
    "gn:feature_class": "P",
    "gn:feature_code": "PPL",
    "gn:name": "Jingangkoucun",
    "gn:population": 0,
    "gn:timezone": "Asia/Shanghai",
    "iso:country": "CN",
    "name:zho_x_preferred": [
      "金岗口村"
    ],
    "wof:name": "Jingangkoucun",
    "wof:placetype": "locality"
  },
  "geometry": {
    "coordinates": [
      120.65589,
      36.88079000000001
    ],
    "type": "Point"
  }
}