{
  "type": "Feature",
  "properties": {
    "gn:admin1_code": "11",
    "gn:asciiname": "Furongqiao",
    "gn:country_code": "CN",
    "gn:dem": 416,
    "gn:feature_class": "P",
    "gn:feature_code": "PPLA4",
    "gn:name": "Furongqiao",
    "gn:population": 0,
    "gn:timezone": "Asia/Shanghai",
    "iso:country": "CN",
    "name:und_x_variant": [
      "Furongqiao Baizuxiang",
      "Furongqiao"
    ],
    "name:zho_x_preferred": [
      "芙容桥"
    ],
    "name:zho_x_variant": [
      "芙容桥白族乡"
    ],
    "wof:name": "Furongqiao",
    "wof:placetype": "locality"
  },
  "geometry": {
    "coordinates": [
      110.30001,
      29.51435
    ],
    "type": "Point"
  }
}