{
  "type": "Feature",
  "properties": {
    "gn:admin1_code": "3.0",
    "gn:asciiname": "Dongshan",
    "gn:country_code": "CN",
    "gn:dem": 489,
    "gn:feature_class": "P",
    "gn:feature_code": "PPL",
    "gn:name": "Dongshan",
    "gn:population": 0,
    "gn:timezone": "Asia/Shanghai",
    "iso:country": "CN",
    "name:ceb_x_preferred": [
      "Dongshan"
    ],
    "name:deu_x_preferred": [
      "Dongshan"
    ],
    "name:eus_x_preferred": [
      "Dongshan"
    ],
    "name:fra_x_preferred": [
      "Dongshan"
    ],
    "name:nor_x_preferred": [
      "Dongshan"
    ],
    "name:rus_x_preferred": [
      "Дуншань"
    ],
    "name:spa_x_preferred": [
      "Dongshan"
    ],
    "name:swe_x_preferred": [
      "Dongshan"
    ],
    "name:zho_x_preferred": [
      "东山"
    ],
    "wof:name": "Dongshan",
    "wof:placetype": "locality"
  },
  "geometry": {
    "coordinates": [
      117.638,
      27.9102
    ],
    "type": "Point"
  }
}