{
  "type": "Feature",
  "properties": {
    "gn:admin1_code": "3.0",
    "gn:asciiname": "Xiangkou",
    "gn:country_code": "CN",
    "gn:dem": 79,
    "gn:feature_class": "P",
    "gn:feature_code": "PPL",
    "gn:name": "Xiangkou",
    "gn:population": 0,
    "gn:timezone": "Asia/Shanghai",
    "iso:country": "CN",
    "name:und_x_variant": [
      "巷口"
    ],
    "name:zho_x_preferred": [
      "巷口镇"
    ],
    "wof:name": "Xiangkou",
    "wof:placetype": "locality"
  },
  "geometry": {
    "coordinates": [
      114.763,
      27.0259
    ],
    "type": "Point"
  }
}