{
  "type": "Feature",
  "properties": {
    "gn:admin1_code": "15.0",
    "gn:asciiname": "Moba",
    "gn:country_code": "CN",
    "gn:dem": 1336,
    "gn:feature_class": "P",
    "gn:feature_code": "PPL",
    "gn:name": "Moba",
    "gn:population": 0,
    "gn:timezone": "Asia/Shanghai",
    "iso:country": "CN",
    "name:ben_x_preferred": [
      "মোবা"
    ],
    "name:ceb_x_preferred": [
      "Moba"
    ],
    "name:deu_x_preferred": [
      "Moba"
    ],
    "name:fas_x_preferred": [
      "موبا"
    ],
    "name:fra_x_preferred": [
      "Moba"
    ],
    "name:heb_x_preferred": [
      "מובה"
    ],
    "name:hin_x_preferred": [
      "मोबा"
    ],
    "name:hun_x_preferred": [
      "Moba"
    ],
    "name:ind_x_preferred": [
      "Moba"
    ],
    "name:ita_x_preferred": [
      "Moba"
    ],
    "name:kor_x_preferred": [
      "모바"
    ],
    "name:nld_x_preferred": [
      "Moba"
    ],
    "name:ron_x_preferred": [
      "Moba"
    ],
    "name:rus_x_preferred": [
      "MOBA"
    ],
    "name:spa_x_preferred": [
      "Moba"
    ],
    "name:swe_x_preferred": [
      "Moba"
    ],
    "name:tur_x_preferred": [
      "Moba"
    ],
    "name:urd_x_preferred": [
      "موبا"
    ],
    "name:vie_x_preferred": [
      "Moba"
    ],
    "name:zho_x_preferred": [
      "磨坝"
    ],
    "wof:name": "Moba",
    "wof:placetype": "locality"
  },
  "geometry": {
    "coordinates": [
      106.064,
      34.212
    ],
    "type": "Point"
  }
}