{
  "type": "Feature",
  "properties": {
    "gn:admin1_code": "18.0",
    "gn:asciiname": "Luma",
    "gn:country_code": "CN",
    "gn:dem": 310,
    "gn:feature_class": "P",
    "gn:feature_code": "PPL",
    "gn:name": "Lüma",
    "gn:population": 0,
    "gn:timezone": "Asia/Shanghai",
    "iso:country": "CN",
    "name:ceb_x_preferred": [
      "Luma"
    ],
    "name:deu_x_preferred": [
      "Luma"
    ],
    "name:fin_x_preferred": [
      "Luma"
    ],
    "name:fra_x_preferred": [
      "Luma"
    ],
    "name:mar_x_preferred": [
      "आर्मेनियन लुमा"
    ],
    "name:por_x_preferred": [
      "Luma"
    ],
    "name:rus_x_preferred": [
      "Лума"
    ],
    "name:spa_x_preferred": [
      "Luma"
    ],
    "name:swe_x_preferred": [
      "Luma"
    ],
    "name:und_x_variant": [
      "Lüma"
    ],
    "name:zho_x_preferred": [
      "吕孖"
    ],
    "wof:name": "Luma",
    "wof:placetype": "locality"
  },
  "geometry": {
    "coordinates": [
      108.863,
      25.9891
    ],
    "type": "Point"
  }
}