{
  "type": "Feature",
  "properties": {
    "gn:admin1_code": "30",
    "gn:asciiname": "Lutian",
    "gn:country_code": "CN",
    "gn:dem": 219,
    "gn:feature_class": "P",
    "gn:feature_code": "PPLA4",
    "gn:name": "Lütian",
    "gn:population": 0,
    "gn:timezone": "Asia/Shanghai",
    "iso:country": "CN",
    "name:und_x_variant": [
      "Lü-t’ien",
      "Lütian Zhen",
      "Lvtian Zhen",
      "吕田镇"
    ],
    "name:zho_x_preferred": [
      "吕田"
    ],
    "name:zho_x_variant": [
      "Lütian"
    ],
    "wof:name": "Lutian",
    "wof:placetype": "locality"
  },
  "geometry": {
    "coordinates": [
      113.94413,
      23.81111
    ],
    "type": "Point"
  }
}