{
  "type": "Feature",
  "properties": {
    "gn:admin1_code": "19.0",
    "gn:asciiname": "Toudaogou",
    "gn:country_code": "CN",
    "gn:dem": 144,
    "gn:feature_class": "P",
    "gn:feature_code": "PPL",
    "gn:name": "Toudaogou",
    "gn:population": 0,
    "gn:timezone": "Asia/Shanghai",
    "iso:country": "CN",
    "name:und_x_variant": [
      "Toudaohemanzuxiang"
    ],
    "name:zho_x_preferred": [
      "头道沟"
    ],
    "wof:name": "Toudaogou",
    "wof:placetype": "locality"
  },
  "geometry": {
    "coordinates": [
      120.894,
      41.3418
    ],
    "type": "Point"
  }
}