{
  "type": "Feature",
  "properties": {
    "gn:admin1_code": "10",
    "gn:asciiname": "Shuangsongting",
    "gn:country_code": "CN",
    "gn:dem": 271,
    "gn:feature_class": "P",
    "gn:feature_code": "PPL",
    "gn:name": "Shuangsongting",
    "gn:population": 0,
    "gn:timezone": "Asia/Shanghai",
    "iso:country": "CN",
    "name:zho_x_preferred": [
      "双松汀"
    ],
    "wof:name": "Shuangsongting",
    "wof:placetype": "locality"
  },
  "geometry": {
    "coordinates": [
      119.09992,
      40.62138
    ],
    "type": "Point"
  }
}