{
  "type": "Feature",
  "properties": {
    "gn:admin1_code": "15.0",
    "gn:asciiname": "Mami",
    "gn:country_code": "CN",
    "gn:dem": 2542,
    "gn:feature_class": "P",
    "gn:feature_code": "PPL",
    "gn:name": "Mami",
    "gn:population": 0,
    "gn:timezone": "Asia/Shanghai",
    "iso:country": "CN",
    "name:ceb_x_preferred": [
      "Mami"
    ],
    "name:deu_x_preferred": [
      "Mami"
    ],
    "name:eus_x_preferred": [
      "Mami"
    ],
    "name:fas_x_preferred": [
      "ممی"
    ],
    "name:fra_x_preferred": [
      "Mami"
    ],
    "name:hun_x_preferred": [
      "Mami"
    ],
    "name:por_x_preferred": [
      "Mami"
    ],
    "name:swe_x_preferred": [
      "Mami"
    ],
    "name:tur_x_preferred": [
      "Mami"
    ],
    "name:und_x_variant": [
      "嘛咪"
    ],
    "wof:name": "Mami",
    "wof:placetype": "locality"
  },
  "geometry": {
    "coordinates": [
      104.40762,
      34.65916
    ],
    "type": "Point"
  }
}