{
  "type": "Feature",
  "properties": {
    "gn:admin1_code": "9.0",
    "gn:asciiname": "Zhongwei",
    "gn:country_code": "CN",
    "gn:dem": 804,
    "gn:feature_class": "P",
    "gn:feature_code": "PPL",
    "gn:name": "Zhongwei",
    "gn:population": 0,
    "gn:timezone": "Asia/Shanghai",
    "iso:country": "CN",
    "name:ara_x_preferred": [
      "تشونغ وى"
    ],
    "name:cdo_x_preferred": [
      "Dṳ̆ng-ôi"
    ],
    "name:ces_x_preferred": [
      "Čung-wej"
    ],
    "name:dan_x_preferred": [
      "Zhongwei"
    ],
    "name:deu_x_preferred": [
      "Zhongwei"
    ],
    "name:eus_x_preferred": [
      "Zhongwei"
    ],
    "name:fas_x_preferred": [
      "ژانگوی"
    ],
    "name:fin_x_preferred": [
      "Zhongwei"
    ],
    "name:fra_x_preferred": [
      "Zhongwei"
    ],
    "name:ita_x_preferred": [
      "Zhongwei"
    ],
    "name:jpn_x_preferred": [
      "中衛市"
    ],
    "name:kik_x_preferred": [
      "Zhongwei"
    ],
    "name:kor_x_preferred": [
      "중웨이시"
    ],
    "name:nld_x_preferred": [
      "Zhongwei"
    ],
    "name:nor_x_preferred": [
      "Zhongwei"
    ],
    "name:pol_x_preferred": [
      "Zhongwei"
    ],
    "name:por_x_preferred": [
      "Zhongwei"
    ],
    "name:rus_x_preferred": [
      "Чжунвэй"
    ],
    "name:spa_x_preferred": [
      "Zhongwei"
    ],
    "name:swe_x_preferred": [
      "Zhongwei"
    ],
    "name:tur_x_preferred": [
      "Zhongwei"
    ],
    "name:urd_x_preferred": [
      "ژونگوئی"
    ],
    "name:vie_x_preferred": [
      "Trung Vệ"
    ],
    "name:zho_x_preferred": [
      "中围"
    ],
    "name:zho_x_variant": [
      "中卫市"
    ],
    "wof:name": "Zhongwei",
    "wof:placetype": "locality"
  },
  "geometry": {
    "coordinates": [
      113.16947,
      35.32449000000001
    ],
    "type": "Point"
  }
}