{
  "type": "Feature",
  "properties": {
    "gn:admin1_code": "3.0",
    "gn:asciiname": "Puqian",
    "gn:country_code": "CN",
    "gn:dem": 110,
    "gn:feature_class": "P",
    "gn:feature_code": "PPL",
    "gn:name": "Puqian",
    "gn:population": 0,
    "gn:timezone": "Asia/Shanghai",
    "iso:country": "CN",
    "name:fas_x_preferred": [
      "پوکیان"
    ],
    "name:und_x_variant": [
      "铺前"
    ],
    "name:zho_x_preferred": [
      "铺前镇"
    ],
    "wof:name": "Puqian",
    "wof:placetype": "locality"
  },
  "geometry": {
    "coordinates": [
      116.42195,
      27.02944
    ],
    "type": "Point"
  }
}