{
  "type": "Feature",
  "properties": {
    "gn:admin1_code": "26.0",
    "gn:asciiname": "Zhangjiacun",
    "gn:country_code": "CN",
    "gn:dem": 687,
    "gn:feature_class": "P",
    "gn:feature_code": "PPL",
    "gn:name": "Zhangjiacun",
    "gn:population": 0,
    "gn:timezone": "Asia/Shanghai",
    "iso:country": "CN",
    "name:und_x_variant": [
      "张家村"
    ],
    "wof:name": "Zhangjiacun",
    "wof:placetype": "locality"
  },
  "geometry": {
    "coordinates": [
      107.67982,
      33.28529
    ],
    "type": "Point"
  }
}