{
  "type": "Feature",
  "properties": {
    "gn:admin1_code": "7.0",
    "gn:asciiname": "Zhongcun",
    "gn:country_code": "CN",
    "gn:dem": 586,
    "gn:feature_class": "P",
    "gn:feature_code": "PPL",
    "gn:name": "Zhongcun",
    "gn:population": 0,
    "gn:timezone": "Asia/Shanghai",
    "iso:country": "CN",
    "name:zho_x_preferred": [
      "中村"
    ],
    "wof:name": "Zhongcun",
    "wof:placetype": "locality"
  },
  "geometry": {
    "coordinates": [
      118.04589,
      26.97423
    ],
    "type": "Point"
  }
}