{
  "type": "Feature",
  "properties": {
    "gn:admin1_code": "12.0",
    "gn:asciiname": "Chiba",
    "gn:country_code": "CN",
    "gn:dem": 31,
    "gn:feature_class": "P",
    "gn:feature_code": "PPLA4",
    "gn:name": "Chiba",
    "gn:population": 0,
    "gn:timezone": "Asia/Shanghai",
    "iso:country": "CN",
    "name:ast_x_preferred": [
      "Chiba"
    ],
    "name:cat_x_preferred": [
      "Chiba"
    ],
    "name:ceb_x_preferred": [
      "Chiba"
    ],
    "name:deu_x_preferred": [
      "Chiba"
    ],
    "name:epo_x_preferred": [
      "Ĉiba"
    ],
    "name:fas_x_preferred": [
      "چیبا"
    ],
    "name:fra_x_preferred": [
      "Chiba"
    ],
    "name:ita_x_preferred": [
      "Chiba"
    ],
    "name:mlg_x_preferred": [
      "Chiba"
    ],
    "name:nld_x_preferred": [
      "Chiba"
    ],
    "name:nor_x_preferred": [
      "Chiba"
    ],
    "name:pol_x_preferred": [
      "Chiba"
    ],
    "name:rus_x_preferred": [
      "Тиба"
    ],
    "name:sco_x_preferred": [
      "Chiba"
    ],
    "name:slk_x_preferred": [
      "Čiba"
    ],
    "name:spa_x_preferred": [
      "Chiba"
    ],
    "name:srp_x_preferred": [
      "Чиба"
    ],
    "name:swa_x_preferred": [
      "Chiba"
    ],
    "name:swe_x_preferred": [
      "Chiba"
    ],
    "name:tha_x_preferred": [
      "ชิบะ"
    ],
    "name:tur_x_preferred": [
      "Chiba"
    ],
    "name:ukr_x_preferred": [
      "Тіба"
    ],
    "name:und_x_variant": [
      "Chiba Zhen"
    ],
    "name:zho_x_preferred": [
      "尺八"
    ],
    "name:zho_x_variant": [
      "尺八镇"
    ],
    "wof:name": "Chiba",
    "wof:placetype": "locality"
  },
  "geometry": {
    "coordinates": [
      113.01197,
      29.59004
    ],
    "type": "Point"
  }
}