{
  "type": "Feature",
  "properties": {
    "gn:admin1_code": "12.0",
    "gn:asciiname": "Xiajiayuan",
    "gn:country_code": "CN",
    "gn:dem": 557,
    "gn:feature_class": "P",
    "gn:feature_code": "PPL",
    "gn:name": "Xiajiayuan",
    "gn:population": 0,
    "gn:timezone": "Asia/Shanghai",
    "iso:country": "CN",
    "name:zho_x_preferred": [
      "夏家院"
    ],
    "wof:name": "Xiajiayuan",
    "wof:placetype": "locality"
  },
  "geometry": {
    "coordinates": [
      110.57835,
      32.41808
    ],
    "type": "Point"
  }
}