{
  "type": "Feature",
  "properties": {
    "gn:admin1_code": "26.0",
    "gn:asciiname": "An'erpocun",
    "gn:country_code": "CN",
    "gn:dem": 1098,
    "gn:feature_class": "P",
    "gn:feature_code": "PPL",
    "gn:name": "An’erpocun",
    "gn:population": 0,
    "gn:timezone": "Asia/Shanghai",
    "iso:country": "CN",
    "name:und_x_variant": [
      "An’erpocun"
    ],
    "name:zho_x_preferred": [
      "安儿坡村"
    ],
    "wof:name": "An'erpocun",
    "wof:placetype": "locality"
  },
  "geometry": {
    "coordinates": [
      106.91421,
      34.93261
    ],
    "type": "Point"
  }
}