{
  "type": "Feature",
  "properties": {
    "gn:admin1_code": "15.0",
    "gn:asciiname": "Dalu",
    "gn:country_code": "CN",
    "gn:dem": 1658,
    "gn:feature_class": "P",
    "gn:feature_code": "PPL",
    "gn:name": "Dalü",
    "gn:population": 0,
    "gn:timezone": "Asia/Shanghai",
    "iso:country": "CN",
    "name:ceb_x_preferred": [
      "Dalu"
    ],
    "name:deu_x_preferred": [
      "Dalu"
    ],
    "name:und_x_variant": [
      "Dalü"
    ],
    "name:zho_x_preferred": [
      "大吕"
    ],
    "wof:name": "Dalu",
    "wof:placetype": "locality"
  },
  "geometry": {
    "coordinates": [
      105.57,
      34.1827
    ],
    "type": "Point"
  }
}