{
  "type": "Feature",
  "properties": {
    "gn:admin1_code": "3.0",
    "gn:asciiname": "Tangbashang",
    "gn:country_code": "CN",
    "gn:dem": 35,
    "gn:feature_class": "P",
    "gn:feature_code": "PPL",
    "gn:name": "Tangbashang",
    "gn:population": 0,
    "gn:timezone": "Asia/Shanghai",
    "iso:country": "CN",
    "name:und_x_variant": [
      "塘坝上"
    ],
    "wof:name": "Tangbashang",
    "wof:placetype": "locality"
  },
  "geometry": {
    "coordinates": [
      117.0683,
      29.17283
    ],
    "type": "Point"
  }
}