{
  "type": "Feature",
  "properties": {
    "gn:admin1_code": "18.0",
    "gn:asciiname": "Gaoyi",
    "gn:country_code": "CN",
    "gn:dem": 1167,
    "gn:feature_class": "P",
    "gn:feature_code": "PPL",
    "gn:name": "Gaoyi",
    "gn:population": 0,
    "gn:timezone": "Asia/Shanghai",
    "iso:country": "CN",
    "name:zho_x_preferred": [
      "高倚"
    ],
    "wof:name": "Gaoyi",
    "wof:placetype": "locality"
  },
  "geometry": {
    "coordinates": [
      108.778,
      26.4463
    ],
    "type": "Point"
  }
}