{
  "type": "Feature",
  "properties": {
    "gn:admin1_code": "11.0",
    "gn:asciiname": "Lingtang",
    "gn:country_code": "CN",
    "gn:dem": 636,
    "gn:feature_class": "P",
    "gn:feature_code": "PPL",
    "gn:name": "Lingtang",
    "gn:population": 0,
    "gn:timezone": "Asia/Shanghai",
    "iso:country": "CN",
    "name:zho_x_preferred": [
      "岭塘"
    ],
    "wof:name": "Lingtang",
    "wof:placetype": "locality"
  },
  "geometry": {
    "coordinates": [
      113.63432,
      25.42801
    ],
    "type": "Point"
  }
}