{
  "type": "Feature",
  "properties": {
    "gn:admin1_code": "16.0",
    "gn:asciiname": "Dashi",
    "gn:country_code": "CN",
    "gn:dem": 425,
    "gn:feature_class": "P",
    "gn:feature_code": "PPL",
    "gn:name": "Dashi",
    "gn:population": 0,
    "gn:timezone": "Asia/Shanghai",
    "iso:country": "CN",
    "name:ara_x_preferred": [
      "داشي"
    ],
    "name:cat_x_preferred": [
      "Dashi"
    ],
    "name:ceb_x_preferred": [
      "Dashi"
    ],
    "name:dan_x_preferred": [
      "Dashi"
    ],
    "name:deu_x_preferred": [
      "Dashi"
    ],
    "name:epo_x_preferred": [
      "Daŝio"
    ],
    "name:fas_x_preferred": [
      "داشی"
    ],
    "name:fin_x_preferred": [
      "Dashi"
    ],
    "name:fra_x_preferred": [
      "Dashi"
    ],
    "name:heb_x_preferred": [
      "דאשי"
    ],
    "name:hun_x_preferred": [
      "Dasi"
    ],
    "name:hye_x_preferred": [
      "Դասի"
    ],
    "name:ind_x_preferred": [
      "Dashi"
    ],
    "name:ita_x_preferred": [
      "Dashi"
    ],
    "name:jav_x_preferred": [
      "Dashi"
    ],
    "name:msa_x_preferred": [
      "Dashi"
    ],
    "name:nld_x_preferred": [
      "Dashi"
    ],
    "name:nor_x_preferred": [
      "Dashi"
    ],
    "name:pol_x_preferred": [
      "Dashi"
    ],
    "name:por_x_preferred": [
      "Dashi"
    ],
    "name:rus_x_preferred": [
      "Даси"
    ],
    "name:spa_x_preferred": [
      "Dashi"
    ],
    "name:swe_x_preferred": [
      "Dashi"
    ],
    "name:tha_x_preferred": [
      "ดาชิ"
    ],
    "name:tur_x_preferred": [
      "Dashi"
    ],
    "name:ukr_x_preferred": [
      "Дасі"
    ],
    "name:zho_x_preferred": [
      "大市"
    ],
    "name:zho_x_variant": [
      "日式上湯"
    ],
    "wof:name": "Dashi",
    "wof:placetype": "locality"
  },
  "geometry": {
    "coordinates": [
      108.874,
      25.2702
    ],
    "type": "Point"
  }
}