{
  "type": "Feature",
  "properties": {
    "gn:admin1_code": "19.0",
    "gn:asciiname": "Dongdazhangzi",
    "gn:country_code": "CN",
    "gn:dem": 456,
    "gn:feature_class": "P",
    "gn:feature_code": "PPL",
    "gn:name": "Dongdazhangzi",
    "gn:population": 0,
    "gn:timezone": "Asia/Shanghai",
    "iso:country": "CN",
    "name:zho_x_preferred": [
      "东大杖子"
    ],
    "wof:name": "Dongdazhangzi",
    "wof:placetype": "locality"
  },
  "geometry": {
    "coordinates": [
      119.59221,
      40.63304
    ],
    "type": "Point"
  }
}