{
  "type": "Feature",
  "properties": {
    "iso:country": "CN",
    "name:eng_x_preferred": [
      "Qianshan"
    ],
    "name:zho_x_preferred": [
      "前山镇"
    ],
    "qs:name": "前山镇",
    "qs:name_adm0": "中國",
    "qs:name_adm1": "广东省",
    "qs:photos": 63,
    "qs:photos_1k": 13,
    "qs:photos_9k": 1,
    "qs:photos_9r": 2,
    "qs:photos_all": 63,
    "qs:photos_sr": 2,
    "qs:placetype": "Town",
    "qs:pop_sr": "0",
    "wof:name": "Qianshan",
    "wof:placetype": "locality"
  },
  "geometry": {
    "coordinates": [
      113.523101,
      22.240166
    ],
    "type": "Point"
  }
}