{
  "type": "Feature",
  "properties": {
    "gn:admin1_code": "7.0",
    "gn:asciiname": "Yunju",
    "gn:country_code": "CN",
    "gn:dem": 236,
    "gn:feature_class": "P",
    "gn:feature_code": "PPL",
    "gn:name": "Yunju",
    "gn:population": 0,
    "gn:timezone": "Asia/Shanghai",
    "iso:country": "CN",
    "name:zho_x_preferred": [
      "云居"
    ],
    "wof:name": "Yunju",
    "wof:placetype": "locality"
  },
  "geometry": {
    "coordinates": [
      118.50802,
      25.45007
    ],
    "type": "Point"
  }
}