{
  "type": "Feature",
  "properties": {
    "gn:admin1_code": "01",
    "gn:asciiname": "Lutingyi",
    "gn:cc2": "CN",
    "gn:country_code": "CN",
    "gn:dem": 41,
    "gn:feature_class": "P",
    "gn:feature_code": "PPL",
    "gn:name": "Lütingyi",
    "gn:population": 0,
    "gn:timezone": "Asia/Shanghai",
    "iso:country": "CN",
    "name:und_x_variant": [
      "Lü-t’ing",
      "Lü-t’ing-i",
      "Lütingyi"
    ],
    "wof:name": "Lutingyi",
    "wof:placetype": "locality"
  },
  "geometry": {
    "coordinates": [
      117.00972,
      31.11333
    ],
    "type": "Point"
  }
}