{
  "type": "Feature",
  "properties": {
    "gn:admin1_code": "29.0",
    "gn:asciiname": "Huilongzhai",
    "gn:country_code": "CN",
    "gn:dem": 1081,
    "gn:feature_class": "P",
    "gn:feature_code": "PPL",
    "gn:name": "Huilongzhai",
    "gn:population": 0,
    "gn:timezone": "Asia/Shanghai",
    "iso:country": "CN",
    "name:zho_x_preferred": [
      "回龙寨"
    ],
    "wof:name": "Huilongzhai",
    "wof:placetype": "locality"
  },
  "geometry": {
    "coordinates": [
      100.928,
      22.9552
    ],
    "type": "Point"
  }
}