{
  "type": "Feature",
  "properties": {
    "gn:admin1_code": "11",
    "gn:asciiname": "Xinwu Yangjia",
    "gn:country_code": "CN",
    "gn:dem": 82,
    "gn:feature_class": "P",
    "gn:feature_code": "PPL",
    "gn:name": "Xinwu Yangjia",
    "gn:population": 0,
    "gn:timezone": "Asia/Shanghai",
    "iso:country": "CN",
    "name:zho_x_preferred": [
      "新屋阳家"
    ],
    "wof:name": "Xinwu Yangjia",
    "wof:placetype": "locality"
  },
  "geometry": {
    "coordinates": [
      112.37013,
      26.3804
    ],
    "type": "Point"
  }
}