{
  "type": "Feature",
  "properties": {
    "gn:admin1_code": "13.0",
    "gn:asciiname": "Rokiya",
    "gn:country_code": "CN",
    "gn:dem": 1410,
    "gn:feature_class": "P",
    "gn:feature_code": "PPLA4",
    "gn:name": "Rokiya",
    "gn:population": 0,
    "gn:timezone": "Asia/Urumqi",
    "iso:country": "CN",
    "name:uig_x_preferred": [
      "Rok̩iyə"
    ],
    "name:uig_x_variant": [
      "Roqiye",
      "روقىيە",
      "Роқыя"
    ],
    "name:und_x_variant": [
      "Rokiya Xiang",
      "Rokiya",
      "Ruokeya",
      "Ruokeya Xiang"
    ],
    "name:zho_x_preferred": [
      "若克雅"
    ],
    "name:zho_x_variant": [
      "若克雅乡"
    ],
    "wof:name": "Rokiya",
    "wof:placetype": "locality"
  },
  "geometry": {
    "coordinates": [
      82.81528,
      37.07861
    ],
    "type": "Point"
  }
}