{
  "type": "Feature",
  "properties": {
    "gn:admin1_code": "4.0",
    "gn:asciiname": "Panlaozhuangcun",
    "gn:country_code": "CN",
    "gn:dem": 5,
    "gn:feature_class": "P",
    "gn:feature_code": "PPL",
    "gn:name": "Panlaozhuangcun",
    "gn:population": 0,
    "gn:timezone": "Asia/Shanghai",
    "iso:country": "CN",
    "name:zho_x_preferred": [
      "潘老庄村"
    ],
    "wof:name": "Panlaozhuangcun",
    "wof:placetype": "locality"
  },
  "geometry": {
    "coordinates": [
      119.51111000000002,
      34.23108
    ],
    "type": "Point"
  }
}