{
  "type": "Feature",
  "properties": {
    "gn:admin1_code": "29.0",
    "gn:asciiname": "Wenling",
    "gn:country_code": "CN",
    "gn:dem": 1179,
    "gn:feature_class": "P",
    "gn:feature_code": "PPL",
    "gn:name": "Wenling",
    "gn:population": 0,
    "gn:timezone": "Asia/Shanghai",
    "iso:country": "CN",
    "name:ara_x_preferred": [
      "نلينغ"
    ],
    "name:ceb_x_preferred": [
      "Wenling"
    ],
    "name:deu_x_preferred": [
      "Wenling"
    ],
    "name:fra_x_preferred": [
      "Wenling"
    ],
    "name:ita_x_preferred": [
      "Wenling"
    ],
    "name:jpn_x_preferred": [
      "温嶺市"
    ],
    "name:kik_x_preferred": [
      "Wenling"
    ],
    "name:kor_x_preferred": [
      "원링시"
    ],
    "name:mlg_x_preferred": [
      "Wenling"
    ],
    "name:nld_x_preferred": [
      "Wenling"
    ],
    "name:nor_x_preferred": [
      "Wenling"
    ],
    "name:swe_x_preferred": [
      "Wenling"
    ],
    "name:tgl_x_preferred": [
      "Wenling"
    ],
    "name:urd_x_preferred": [
      "وینلینگ"
    ],
    "name:vie_x_preferred": [
      "Ôn Lĩnh"
    ],
    "name:war_x_preferred": [
      "Wenling"
    ],
    "name:wuu_x_preferred": [
      "温岭市"
    ],
    "name:zho_x_preferred": [
      "文令"
    ],
    "name:zho_x_variant": [
      "温岭市"
    ],
    "wof:name": "Wenling",
    "wof:placetype": "locality"
  },
  "geometry": {
    "coordinates": [
      101.172,
      23.495
    ],
    "type": "Point"
  }
}