{
  "type": "Feature",
  "properties": {
    "gn:admin1_code": "4.0",
    "gn:asciiname": "Xiaolizhuang",
    "gn:country_code": "CN",
    "gn:dem": 5,
    "gn:feature_class": "P",
    "gn:feature_code": "PPL",
    "gn:name": "Xiaolizhuang",
    "gn:population": 0,
    "gn:timezone": "Asia/Shanghai",
    "iso:country": "CN",
    "name:zho_x_preferred": [
      "Xiaolizhuang"
    ],
    "name:zho_x_variant": [
      "小李庄"
    ],
    "wof:name": "Xiaolizhuang",
    "wof:placetype": "locality"
  },
  "geometry": {
    "coordinates": [
      119.32523,
      34.19754
    ],
    "type": "Point"
  }
}