{
  "type": "Feature",
  "properties": {
    "gn:admin1_code": "14.0",
    "gn:asciiname": "Sajia",
    "gn:country_code": "CN",
    "gn:dem": 4643,
    "gn:feature_class": "P",
    "gn:feature_code": "PPLA3",
    "gn:name": "Sajia",
    "gn:population": 0,
    "gn:timezone": "Asia/Urumqi",
    "iso:country": "CN",
    "name:ara_x_preferred": [
      "دير ساكيا"
    ],
    "name:bod_x_preferred": [
      "Sa’gya"
    ],
    "name:bod_x_variant": [
      "ས་སྐྱ་དགོན།"
    ],
    "name:ces_x_preferred": [
      "Klášter Sakja"
    ],
    "name:deu_x_preferred": [
      "Sakya-Kloster"
    ],
    "name:hun_x_preferred": [
      "Szakja kolostor"
    ],
    "name:jpn_x_preferred": [
      "サキャ寺"
    ],
    "name:nld_x_preferred": [
      "Sakya"
    ],
    "name:pol_x_preferred": [
      "Sakja"
    ],
    "name:por_x_preferred": [
      "Mosteiro Sakya"
    ],
    "name:rus_x_preferred": [
      "Сакья"
    ],
    "name:und_x_variant": [
      "Sakya Gömpa",
      "Sakya Gomba",
      "Sayka Gompa",
      "Sa-chia",
      "Sa-chia-tsung",
      "Sa’gyaxoi"
    ],
    "name:zho_x_preferred": [
      "Sajia"
    ],
    "name:zho_x_variant": [
      "萨迦",
      "萨迦寺"
    ],
    "wof:name": "Sajia",
    "wof:placetype": "locality"
  },
  "geometry": {
    "coordinates": [
      88.05,
      28.91667
    ],
    "type": "Point"
  }
}