{
  "type": "Feature",
  "properties": {
    "gn:admin1_code": "30",
    "gn:asciiname": "Zijing",
    "gn:country_code": "CN",
    "gn:dem": 101,
    "gn:feature_class": "P",
    "gn:feature_code": "PPL",
    "gn:name": "Zijing",
    "gn:population": 0,
    "gn:timezone": "Asia/Shanghai",
    "iso:country": "CN",
    "name:zho_x_preferred": [
      "紫迳"
    ],
    "wof:name": "Zijing",
    "wof:placetype": "locality"
  },
  "geometry": {
    "coordinates": [
      112.06231,
      23.33753
    ],
    "type": "Point"
  }
}