{
  "type": "Feature",
  "properties": {
    "gn:admin1_code": "10.0",
    "gn:asciiname": "Guang'entun",
    "gn:country_code": "CN",
    "gn:dem": 505,
    "gn:feature_class": "P",
    "gn:feature_code": "PPL",
    "gn:name": "Guang’entun",
    "gn:population": 0,
    "gn:timezone": "Asia/Shanghai",
    "iso:country": "CN",
    "name:und_x_variant": [
      "Guang’entun"
    ],
    "name:zho_x_preferred": [
      "广恩屯"
    ],
    "wof:name": "Guang'entun",
    "wof:placetype": "locality"
  },
  "geometry": {
    "coordinates": [
      115.32534,
      40.3456
    ],
    "type": "Point"
  }
}