{
  "type": "Feature",
  "properties": {
    "gn:admin1_code": "3.0",
    "gn:asciiname": "Xintian",
    "gn:country_code": "CN",
    "gn:dem": 234,
    "gn:feature_class": "P",
    "gn:feature_code": "PPL",
    "gn:name": "Xintian",
    "gn:population": 0,
    "gn:timezone": "Asia/Shanghai",
    "iso:country": "CN",
    "name:ceb_x_preferred": [
      "Xintian"
    ],
    "name:deu_x_preferred": [
      "Xintian"
    ],
    "name:und_x_variant": [
      "新田"
    ],
    "name:zho_x_preferred": [
      "新田鄉"
    ],
    "wof:name": "Xintian",
    "wof:placetype": "locality"
  },
  "geometry": {
    "coordinates": [
      116.30134,
      27.05199
    ],
    "type": "Point"
  }
}