{
  "type": "Feature",
  "properties": {
    "gn:admin1_code": "18",
    "gn:asciiname": "Yujiawan",
    "gn:country_code": "CN",
    "gn:dem": 1269,
    "gn:feature_class": "P",
    "gn:feature_code": "PPL",
    "gn:name": "Yujiawan",
    "gn:population": 0,
    "gn:timezone": "Asia/Shanghai",
    "iso:country": "CN",
    "name:zho_x_preferred": [
      "余家弯"
    ],
    "wof:name": "Yujiawan",
    "wof:placetype": "locality"
  },
  "geometry": {
    "coordinates": [
      104.993,
      25.1458
    ],
    "type": "Point"
  }
}