{
  "type": "Feature",
  "properties": {
    "gn:admin1_code": "8.0",
    "gn:asciiname": "Langwo",
    "gn:country_code": "CN",
    "gn:dem": 50,
    "gn:feature_class": "P",
    "gn:feature_code": "PPL",
    "gn:name": "Langwo",
    "gn:population": 0,
    "gn:timezone": "Asia/Shanghai",
    "iso:country": "CN",
    "name:zho_x_preferred": [
      "浪窝"
    ],
    "wof:name": "Langwo",
    "wof:placetype": "locality"
  },
  "geometry": {
    "coordinates": [
      133.20612,
      46.97185
    ],
    "type": "Point"
  }
}