{
  "type": "Feature",
  "properties": {
    "gn:admin1_code": "16.0",
    "gn:asciiname": "Gaolao",
    "gn:country_code": "CN",
    "gn:dem": 601,
    "gn:feature_class": "P",
    "gn:feature_code": "PPL",
    "gn:name": "Gaolao",
    "gn:population": 0,
    "gn:timezone": "Asia/Shanghai",
    "iso:country": "CN",
    "name:fra_x_preferred": [
      "Gaolao"
    ],
    "name:kan_x_preferred": [
      "ಗೌಳವ್"
    ],
    "name:tam_x_preferred": [
      "கௌலவ் மாடு"
    ],
    "name:zho_x_preferred": [
      "告劳"
    ],
    "wof:name": "Gaolao",
    "wof:placetype": "locality"
  },
  "geometry": {
    "coordinates": [
      106.874,
      23.6145
    ],
    "type": "Point"
  }
}