{
  "type": "Feature",
  "properties": {
    "gn:admin1_code": "9.0",
    "gn:asciiname": "Huadian",
    "gn:country_code": "CN",
    "gn:dem": 43,
    "gn:feature_class": "P",
    "gn:feature_code": "PPL",
    "gn:name": "Huadian",
    "gn:population": 0,
    "gn:timezone": "Asia/Shanghai",
    "iso:country": "CN",
    "name:ceb_x_preferred": [
      "Huadian"
    ],
    "name:mlg_x_preferred": [
      "Huadian"
    ],
    "name:rus_x_preferred": [
      "Хуадянь"
    ],
    "name:zho_x_preferred": [
      "华店"
    ],
    "wof:name": "Huadian",
    "wof:placetype": "locality"
  },
  "geometry": {
    "coordinates": [
      115.02709,
      32.3076
    ],
    "type": "Point"
  }
}