{
  "type": "Feature",
  "properties": {
    "gn:admin1_code": "11.0",
    "gn:asciiname": "Beidi",
    "gn:country_code": "CN",
    "gn:dem": 420,
    "gn:feature_class": "P",
    "gn:feature_code": "PPL",
    "gn:name": "Beidi",
    "gn:population": 0,
    "gn:timezone": "Asia/Shanghai",
    "iso:country": "CN",
    "name:bul_x_preferred": [
      "Бейди"
    ],
    "name:ind_x_preferred": [
      "Beidi"
    ],
    "name:nld_x_preferred": [
      "Noordelijke Di"
    ],
    "name:rus_x_preferred": [
      "Северные варвары"
    ],
    "name:spa_x_preferred": [
      "Beidi"
    ],
    "name:swe_x_preferred": [
      "Beidi"
    ],
    "name:ukr_x_preferred": [
      "Північні варвари"
    ],
    "name:vie_x_preferred": [
      "Bắc Địch"
    ],
    "name:zho_x_preferred": [
      "背地"
    ],
    "wof:name": "Beidi",
    "wof:placetype": "locality"
  },
  "geometry": {
    "coordinates": [
      109.5708,
      26.29649
    ],
    "type": "Point"
  }
}