{
  "type": "Feature",
  "properties": {
    "gn:admin1_code": "15.0",
    "gn:asciiname": "Yanghe",
    "gn:country_code": "CN",
    "gn:dem": 1757,
    "gn:feature_class": "P",
    "gn:feature_code": "PPL",
    "gn:name": "Yanghe",
    "gn:population": 0,
    "gn:timezone": "Asia/Shanghai",
    "iso:country": "CN",
    "name:ceb_x_preferred": [
      "Yanghe"
    ],
    "name:deu_x_preferred": [
      "Yanghe"
    ],
    "name:swe_x_preferred": [
      "Yanghe"
    ],
    "name:und_x_variant": [
      "杨河"
    ],
    "wof:name": "Yanghe",
    "wof:placetype": "locality"
  },
  "geometry": {
    "coordinates": [
      105.20839,
      34.04274
    ],
    "type": "Point"
  }
}