{
  "type": "Feature",
  "properties": {
    "gn:admin1_code": "16.0",
    "gn:asciiname": "Bai'ai",
    "gn:country_code": "CN",
    "gn:dem": 598,
    "gn:feature_class": "P",
    "gn:feature_code": "PPL",
    "gn:name": "Bai’ai",
    "gn:population": 0,
    "gn:timezone": "Asia/Shanghai",
    "iso:country": "CN",
    "name:und_x_variant": [
      "Bai’ai"
    ],
    "name:zho_x_preferred": [
      "百艾"
    ],
    "wof:name": "Bai'ai",
    "wof:placetype": "locality"
  },
  "geometry": {
    "coordinates": [
      106.557,
      24.1795
    ],
    "type": "Point"
  }
}