{
  "type": "Feature",
  "properties": {
    "gn:admin1_code": "13.0",
    "gn:asciiname": "Sidaohezi",
    "gn:country_code": "CN",
    "gn:dem": 357,
    "gn:feature_class": "P",
    "gn:feature_code": "PPLA4",
    "gn:name": "Sidaohezi",
    "gn:population": 0,
    "gn:timezone": "Asia/Urumqi",
    "iso:country": "CN",
    "name:und_x_variant": [
      "Sidaohezi Zhen"
    ],
    "name:zho_x_preferred": [
      "四道河子"
    ],
    "name:zho_x_variant": [
      "四道河子镇"
    ],
    "wof:name": "Sidaohezi",
    "wof:placetype": "locality"
  },
  "geometry": {
    "coordinates": [
      85.70456,
      44.68907
    ],
    "type": "Point"
  }
}