{
  "type": "Feature",
  "properties": {
    "gn:admin1_code": "4.0",
    "gn:asciiname": "Yediancun",
    "gn:country_code": "CN",
    "gn:dem": 1,
    "gn:feature_class": "P",
    "gn:feature_code": "PPL",
    "gn:name": "Yediancun",
    "gn:population": 0,
    "gn:timezone": "Asia/Shanghai",
    "iso:country": "CN",
    "name:und_x_variant": [
      "Yedian",
      "叶甸",
      "Yediancun"
    ],
    "name:zho_x_preferred": [
      "叶甸村"
    ],
    "wof:name": "Yediancun",
    "wof:placetype": "locality"
  },
  "geometry": {
    "coordinates": [
      119.97553,
      32.64288
    ],
    "type": "Point"
  }
}