{
  "type": "Feature",
  "properties": {
    "gn:admin1_code": "18.0",
    "gn:asciiname": "Baishui",
    "gn:country_code": "CN",
    "gn:dem": 801,
    "gn:feature_class": "P",
    "gn:feature_code": "PPL",
    "gn:name": "Baishui",
    "gn:population": 0,
    "gn:timezone": "Asia/Shanghai",
    "iso:country": "CN",
    "name:deu_x_preferred": [
      "Baishui"
    ],
    "name:kor_x_preferred": [
      "바이수이"
    ],
    "name:zho_x_preferred": [
      "摆水"
    ],
    "wof:name": "Baishui",
    "wof:placetype": "locality"
  },
  "geometry": {
    "coordinates": [
      108.333,
      25.921
    ],
    "type": "Point"
  }
}