{
  "type": "Feature",
  "properties": {
    "gn:admin1_code": "16.0",
    "gn:asciiname": "Hudong",
    "gn:country_code": "CN",
    "gn:dem": 257,
    "gn:feature_class": "P",
    "gn:feature_code": "PPL",
    "gn:name": "Hudong",
    "gn:population": 0,
    "gn:timezone": "Asia/Shanghai",
    "iso:country": "CN",
    "name:zho_x_preferred": [
      "湖洞"
    ],
    "wof:name": "Hudong",
    "wof:placetype": "locality"
  },
  "geometry": {
    "coordinates": [
      109.345,
      24.9178
    ],
    "type": "Point"
  }
}