{
  "type": "Feature",
  "properties": {
    "gn:admin1_code": "22.0",
    "gn:asciiname": "Sanzuo'ancun",
    "gn:country_code": "CN",
    "gn:dem": 159,
    "gn:feature_class": "P",
    "gn:feature_code": "PPL",
    "gn:name": "Sanzuo’ancun",
    "gn:population": 0,
    "gn:timezone": "Asia/Shanghai",
    "iso:country": "CN",
    "name:und_x_variant": [
      "Sanzuo’ancun"
    ],
    "name:zho_x_preferred": [
      "三座庵村"
    ],
    "wof:name": "Sanzuo'ancun",
    "wof:placetype": "locality"
  },
  "geometry": {
    "coordinates": [
      115.8214,
      39.60846
    ],
    "type": "Point"
  }
}