{
  "type": "Feature",
  "properties": {
    "gn:admin1_code": "2",
    "gn:asciiname": "Houlong",
    "gn:country_code": "CN",
    "gn:dem": 945,
    "gn:feature_class": "P",
    "gn:feature_code": "PPL",
    "gn:name": "Houlong",
    "gn:population": 0,
    "gn:timezone": "Asia/Shanghai",
    "iso:country": "CN",
    "name:fra_x_preferred": [
      "Houlong"
    ],
    "name:hak_x_preferred": [
      "Heu-liùng-chṳ́n"
    ],
    "name:ita_x_preferred": [
      "Houlong"
    ],
    "name:jpn_x_preferred": [
      "後龍鎮"
    ],
    "name:kor_x_preferred": [
      "허우룽진"
    ],
    "name:vie_x_preferred": [
      "Hậu Long"
    ],
    "name:zho_x_preferred": [
      "后垄"
    ],
    "name:zho_x_variant": [
      "後龍鎮"
    ],
    "wof:name": "Houlong",
    "wof:placetype": "locality"
  },
  "geometry": {
    "coordinates": [
      119.64278,
      27.86028
    ],
    "type": "Point"
  }
}