{
  "type": "Feature",
  "properties": {
    "gn:admin1_code": "19.0",
    "gn:asciiname": "Linjiagou",
    "gn:country_code": "CN",
    "gn:dem": 517,
    "gn:feature_class": "P",
    "gn:feature_code": "PPL",
    "gn:name": "Linjiagou",
    "gn:population": 0,
    "gn:timezone": "Asia/Shanghai",
    "iso:country": "CN",
    "name:zho_x_preferred": [
      "林家沟"
    ],
    "wof:name": "Linjiagou",
    "wof:placetype": "locality"
  },
  "geometry": {
    "coordinates": [
      119.344,
      41.2127
    ],
    "type": "Point"
  }
}