{
  "type": "Feature",
  "properties": {
    "gn:admin1_code": "25",
    "gn:asciiname": "Luchangxi",
    "gn:country_code": "CN",
    "gn:dem": 18,
    "gn:feature_class": "P",
    "gn:feature_code": "PPL",
    "gn:name": "Lüchangxi",
    "gn:population": 0,
    "gn:timezone": "Asia/Shanghai",
    "iso:country": "CN",
    "name:und_x_variant": [
      "Lüchangxi"
    ],
    "name:zho_x_preferred": [
      "吕常西"
    ],
    "wof:name": "Luchangxi",
    "wof:placetype": "locality"
  },
  "geometry": {
    "coordinates": [
      117.144,
      37.1881
    ],
    "type": "Point"
  }
}