{
  "type": "Feature",
  "properties": {
    "gn:admin1_code": "24.0",
    "gn:asciiname": "Zirun",
    "gn:country_code": "CN",
    "gn:dem": 1041,
    "gn:feature_class": "P",
    "gn:feature_code": "PPLA4",
    "gn:name": "Zirun",
    "gn:population": 0,
    "gn:timezone": "Asia/Shanghai",
    "iso:country": "CN",
    "name:und_x_variant": [
      "Tzu-jun",
      "Tzu-jun-ts’un",
      "Zirun",
      "滋润",
      "Zirun Xiang",
      "滋润乡"
    ],
    "wof:name": "Zirun",
    "wof:placetype": "locality"
  },
  "geometry": {
    "coordinates": [
      112.68358,
      39.30346
    ],
    "type": "Point"
  }
}