{
  "type": "Feature",
  "properties": {
    "gn:admin1_code": "24.0",
    "gn:asciiname": "Mingxing",
    "gn:country_code": "CN",
    "gn:dem": 1732,
    "gn:feature_class": "P",
    "gn:feature_code": "PPL",
    "gn:name": "Mingxing",
    "gn:population": 0,
    "gn:timezone": "Asia/Shanghai",
    "iso:country": "CN",
    "name:deu_x_preferred": [
      "Mingxing-Filmgesellschaft"
    ],
    "name:kaz_x_preferred": [
      "Минсин кинокомпаниясы"
    ],
    "name:nor_x_preferred": [
      "Mingxing"
    ],
    "name:rus_x_preferred": [
      "Минсин"
    ],
    "name:swe_x_preferred": [
      "Mingxing"
    ],
    "name:zho_x_preferred": [
      "明星"
    ],
    "name:zho_x_variant": [
      "明星电影公司"
    ],
    "wof:name": "Mingxing",
    "wof:placetype": "locality"
  },
  "geometry": {
    "coordinates": [
      113.76474,
      39.20483
    ],
    "type": "Point"
  }
}