{
  "type": "Feature",
  "properties": {
    "gn:admin1_code": "26.0",
    "gn:asciiname": "Yujiagou",
    "gn:country_code": "CN",
    "gn:dem": 1270,
    "gn:feature_class": "P",
    "gn:feature_code": "PPL",
    "gn:name": "Yujiagou",
    "gn:population": 0,
    "gn:timezone": "Asia/Shanghai",
    "iso:country": "CN",
    "name:zho_x_preferred": [
      "余家沟"
    ],
    "wof:name": "Yujiagou",
    "wof:placetype": "locality"
  },
  "geometry": {
    "coordinates": [
      110.69714,
      33.81165
    ],
    "type": "Point"
  }
}