{
  "type": "Feature",
  "properties": {
    "gn:admin1_code": "11",
    "gn:asciiname": "Yuantou",
    "gn:country_code": "CN",
    "gn:dem": 972,
    "gn:feature_class": "P",
    "gn:feature_code": "PPL",
    "gn:name": "Yuantou",
    "gn:population": 0,
    "gn:timezone": "Asia/Shanghai",
    "iso:country": "CN",
    "name:zho_x_preferred": [
      "源头"
    ],
    "wof:name": "Yuantou",
    "wof:placetype": "locality"
  },
  "geometry": {
    "coordinates": [
      112.06517,
      25.20174
    ],
    "type": "Point"
  }
}