{
  "type": "Feature",
  "properties": {
    "gn:admin1_code": "9.0",
    "gn:asciiname": "Zhangping",
    "gn:country_code": "CN",
    "gn:dem": 255,
    "gn:feature_class": "P",
    "gn:feature_code": "PPL",
    "gn:name": "Zhangping",
    "gn:population": 0,
    "gn:timezone": "Asia/Shanghai",
    "iso:country": "CN",
    "name:ara_x_preferred": [
      "زهانغبينغ"
    ],
    "name:cdo_x_preferred": [
      "Ciŏng-bìng"
    ],
    "name:deu_x_preferred": [
      "Zhangping"
    ],
    "name:fas_x_preferred": [
      "جانگپینگ"
    ],
    "name:fra_x_preferred": [
      "Zhangping"
    ],
    "name:hak_x_preferred": [
      "Chông-phìn-sṳ"
    ],
    "name:ita_x_preferred": [
      "Zhangping"
    ],
    "name:jpn_x_preferred": [
      "ショウ平市"
    ],
    "name:kik_x_preferred": [
      "Zhangping"
    ],
    "name:kor_x_preferred": [
      "장핑시"
    ],
    "name:mlg_x_preferred": [
      "Zhangping"
    ],
    "name:mwl_x_preferred": [
      "Zhangping"
    ],
    "name:nor_x_preferred": [
      "Zhangping"
    ],
    "name:pam_x_preferred": [
      "Zhangping"
    ],
    "name:pnb_x_preferred": [
      "ژانگ پینگ"
    ],
    "name:spa_x_preferred": [
      "Zhāngpíng Shì"
    ],
    "name:swe_x_preferred": [
      "Zhangping"
    ],
    "name:urd_x_preferred": [
      "ژانگپنگ"
    ],
    "name:vie_x_preferred": [
      "Chương Bình"
    ],
    "name:zho_x_preferred": [
      "张坪"
    ],
    "name:zho_x_variant": [
      "漳平市"
    ],
    "wof:name": "Zhangping",
    "wof:placetype": "locality"
  },
  "geometry": {
    "coordinates": [
      111.19402,
      33.14235
    ],
    "type": "Point"
  }
}