{
  "type": "Feature",
  "properties": {
    "gn:admin1_code": "25.0",
    "gn:asciiname": "Yujiadiancun",
    "gn:country_code": "CN",
    "gn:dem": 50,
    "gn:feature_class": "P",
    "gn:feature_code": "PPL",
    "gn:name": "Yujiadiancun",
    "gn:population": 0,
    "gn:timezone": "Asia/Shanghai",
    "iso:country": "CN",
    "name:zho_x_preferred": [
      "于家店村"
    ],
    "wof:name": "Yujiadiancun",
    "wof:placetype": "locality"
  },
  "geometry": {
    "coordinates": [
      120.66325,
      36.97821
    ],
    "type": "Point"
  }
}