{
  "type": "Feature",
  "properties": {
    "gn:admin1_code": "3.0",
    "gn:asciiname": "Guangyangcun",
    "gn:country_code": "CN",
    "gn:dem": 24,
    "gn:feature_class": "P",
    "gn:feature_code": "PPL",
    "gn:name": "Guangyangcun",
    "gn:population": 0,
    "gn:timezone": "Asia/Shanghai",
    "iso:country": "CN",
    "name:und_x_variant": [
      "广阳村"
    ],
    "wof:name": "Guangyangcun",
    "wof:placetype": "locality"
  },
  "geometry": {
    "coordinates": [
      115.98063,
      28.66861
    ],
    "type": "Point"
  }
}