{
  "type": "Feature",
  "properties": {
    "gn:admin1_code": "26.0",
    "gn:asciiname": "Liangjia",
    "gn:country_code": "CN",
    "gn:dem": 744,
    "gn:feature_class": "P",
    "gn:feature_code": "PPL",
    "gn:name": "Liangjia",
    "gn:population": 0,
    "gn:timezone": "Asia/Shanghai",
    "iso:country": "CN",
    "name:zho_x_preferred": [
      "梁家"
    ],
    "name:zho_x_variant": [
      "梁家镇"
    ],
    "wof:name": "Liangjia",
    "wof:placetype": "locality"
  },
  "geometry": {
    "coordinates": [
      108.0065,
      34.51750999999999
    ],
    "type": "Point"
  }
}