{
  "type": "Feature",
  "properties": {
    "gn:admin1_code": "2.0",
    "gn:asciiname": "Zhuyeping",
    "gn:country_code": "CN",
    "gn:dem": 652,
    "gn:feature_class": "P",
    "gn:feature_code": "PPL",
    "gn:name": "Zhuyeping",
    "gn:population": 0,
    "gn:timezone": "Asia/Shanghai",
    "iso:country": "CN",
    "name:zho_x_preferred": [
      "竹叶坪"
    ],
    "wof:name": "Zhuyeping",
    "wof:placetype": "locality"
  },
  "geometry": {
    "coordinates": [
      119.52437,
      28.77303
    ],
    "type": "Point"
  }
}