{
  "type": "Feature",
  "properties": {
    "gn:admin1_code": "7.0",
    "gn:asciiname": "Longquan",
    "gn:country_code": "CN",
    "gn:dem": 9,
    "gn:feature_class": "P",
    "gn:feature_code": "PPL",
    "gn:name": "Longquan",
    "gn:population": 0,
    "gn:timezone": "Asia/Shanghai",
    "iso:country": "CN",
    "name:deu_x_preferred": [
      "Longquan"
    ],
    "name:fra_x_preferred": [
      "Longquan"
    ],
    "name:ita_x_preferred": [
      "Longquan"
    ],
    "name:jpn_x_preferred": [
      "竜泉市"
    ],
    "name:kik_x_preferred": [
      "Longquan"
    ],
    "name:kor_x_preferred": [
      "룽취안시"
    ],
    "name:mlg_x_preferred": [
      "Longquan"
    ],
    "name:nld_x_preferred": [
      "Longquan"
    ],
    "name:nor_x_preferred": [
      "Longquan"
    ],
    "name:rus_x_preferred": [
      "Лунцюань"
    ],
    "name:swe_x_preferred": [
      "Longquan"
    ],
    "name:tgl_x_preferred": [
      "Longquan"
    ],
    "name:urd_x_preferred": [
      "لونگشوان"
    ],
    "name:vie_x_preferred": [
      "Long Tuyền"
    ],
    "name:war_x_preferred": [
      "Longquan"
    ],
    "name:wuu_x_preferred": [
      "龙泉市"
    ],
    "name:zho_x_preferred": [
      "龙泉"
    ],
    "name:zho_x_variant": [
      "龙泉市"
    ],
    "wof:name": "Longquan",
    "wof:placetype": "locality"
  },
  "geometry": {
    "coordinates": [
      119.1724,
      25.90525
    ],
    "type": "Point"
  }
}