{
  "type": "Feature",
  "properties": {
    "gn:admin1_code": "13.0",
    "gn:asciiname": "Karayulgun",
    "gn:cc2": "CN",
    "gn:country_code": "CN",
    "gn:dem": 908,
    "gn:feature_class": "P",
    "gn:feature_code": "PPL",
    "gn:name": "Karayulgun",
    "gn:population": 0,
    "gn:timezone": "Asia/Urumqi",
    "iso:country": "CN",
    "name:uig_x_preferred": [
      "K̩arayulƣun"
    ],
    "name:uig_x_variant": [
      "Qarayulghun",
      "قارايۇلغۇن",
      "Қараюлғун"
    ],
    "name:und_x_variant": [
      "Karayulgun Xiang",
      "Karayulgun"
    ],
    "wof:name": "Karayulgun",
    "wof:placetype": "locality"
  },
  "geometry": {
    "coordinates": [
      86.05444,
      41.59806
    ],
    "type": "Point"
  }
}