{
  "type": "Feature",
  "properties": {
    "gn:admin1_code": "03",
    "gn:asciiname": "Pengze",
    "gn:cc2": "CN",
    "gn:country_code": "CN",
    "gn:dem": 51,
    "gn:feature_class": "P",
    "gn:feature_code": "PPL",
    "gn:name": "Pengze",
    "gn:population": 0,
    "gn:timezone": "Asia/Shanghai",
    "iso:country": "CN",
    "name:deu_x_preferred": [
      "Pengze"
    ],
    "name:fas_x_preferred": [
      "شهرستان پنگزه"
    ],
    "name:jpn_x_preferred": [
      "彭沢県"
    ],
    "name:kor_x_preferred": [
      "펑쩌현"
    ],
    "name:nor_x_preferred": [
      "Pengze"
    ],
    "name:swe_x_preferred": [
      "Pengze"
    ],
    "name:und_x_variant": [
      "P’eng-tse",
      "P’eng-tse-hsien",
      "Pengtseh-hsien",
      "Pengtsch",
      "P’eng-tse-hsien-ch’eng",
      "Pengtseh",
      "Pang-tsis Hien"
    ],
    "name:vie_x_preferred": [
      "Bành Trạch"
    ],
    "name:zho_x_preferred": [
      "彭泽县"
    ],
    "wof:name": "Pengze",
    "wof:placetype": "locality"
  },
  "geometry": {
    "coordinates": [
      116.54572,
      29.89885
    ],
    "type": "Point"
  }
}