{
  "type": "Feature",
  "properties": {
    "gn:admin1_code": "0.0",
    "gn:asciiname": "Jing'an",
    "gn:country_code": "CN",
    "gn:dem": 497,
    "gn:feature_class": "P",
    "gn:feature_code": "PPL",
    "gn:name": "Jing’an",
    "gn:population": 0,
    "gn:timezone": "Asia/Shanghai",
    "iso:country": "CN",
    "name:zho_x_preferred": [
      "靖安"
    ],
    "name:zho_x_variant": [
      "Jing’an"
    ],
    "wof:name": "Jing'an",
    "wof:placetype": "locality"
  },
  "geometry": {
    "coordinates": [
      107.80579,
      30.94622
    ],
    "type": "Point"
  }
}