{
  "type": "Feature",
  "properties": {
    "gn:admin1_code": "30.0",
    "gn:asciiname": "Lingbei",
    "gn:country_code": "CN",
    "gn:dem": 5,
    "gn:feature_class": "P",
    "gn:feature_code": "PPL",
    "gn:name": "Lingbei",
    "gn:population": 0,
    "gn:timezone": "Asia/Shanghai",
    "iso:country": "CN",
    "name:deu_x_preferred": [
      "Lingbei"
    ],
    "name:zho_x_preferred": [
      "嶺背"
    ],
    "wof:name": "Lingbei",
    "wof:placetype": "locality"
  },
  "geometry": {
    "coordinates": [
      112.73073,
      22.25889
    ],
    "type": "Point"
  }
}