{
  "type": "Feature",
  "properties": {
    "gn:admin1_code": "21",
    "gn:asciiname": "Heshangpu",
    "gn:country_code": "CN",
    "gn:dem": 2067,
    "gn:feature_class": "P",
    "gn:feature_code": "PPL",
    "gn:name": "Heshangpu",
    "gn:population": 0,
    "gn:timezone": "Asia/Shanghai",
    "iso:country": "CN",
    "name:und_x_variant": [
      "Ho-shang-p’u",
      "Heshangpu"
    ],
    "name:zho_x_preferred": [
      "和尚铺"
    ],
    "wof:name": "Heshangpu",
    "wof:placetype": "locality"
  },
  "geometry": {
    "coordinates": [
      106.241,
      35.6761
    ],
    "type": "Point"
  }
}