{
  "type": "Feature",
  "properties": {
    "gn:admin1_code": "3",
    "gn:asciiname": "Zhudong",
    "gn:country_code": "CN",
    "gn:dem": 468,
    "gn:feature_class": "P",
    "gn:feature_code": "PPL",
    "gn:name": "Zhudong",
    "gn:population": 0,
    "gn:timezone": "Asia/Shanghai",
    "iso:country": "CN",
    "name:hak_x_preferred": [
      "Chuk-tûng-chṳ́n"
    ],
    "name:jpn_x_preferred": [
      "竹東鎮"
    ],
    "name:kor_x_preferred": [
      "주둥진"
    ],
    "name:vie_x_preferred": [
      "Trúc Đông"
    ],
    "name:zho_x_preferred": [
      "珠洞"
    ],
    "name:zho_x_variant": [
      "竹東鎮"
    ],
    "wof:name": "Zhudong",
    "wof:placetype": "locality"
  },
  "geometry": {
    "coordinates": [
      114.252,
      25.5066
    ],
    "type": "Point"
  }
}