{
  "type": "Feature",
  "properties": {
    "gn:admin1_code": "10",
    "gn:asciiname": "Xiniezhuang",
    "gn:country_code": "CN",
    "gn:dem": 55,
    "gn:feature_class": "P",
    "gn:feature_code": "PPL",
    "gn:name": "Xiniezhuang",
    "gn:population": 0,
    "gn:timezone": "Asia/Shanghai",
    "iso:country": "CN",
    "name:zho_x_preferred": [
      "西聂庄"
    ],
    "wof:name": "Xiniezhuang",
    "wof:placetype": "locality"
  },
  "geometry": {
    "coordinates": [
      114.612,
      36.5462
    ],
    "type": "Point"
  }
}