{
  "type": "Feature",
  "properties": {
    "gn:admin1_code": "16",
    "gn:asciiname": "Tongren",
    "gn:country_code": "CN",
    "gn:dem": 429,
    "gn:feature_class": "P",
    "gn:feature_code": "PPL",
    "gn:name": "Tongren",
    "gn:population": 0,
    "gn:timezone": "Asia/Shanghai",
    "iso:country": "CN",
    "name:ara_x_preferred": [
      "تونغران"
    ],
    "name:cdo_x_preferred": [
      "Dè̤ng-ìng"
    ],
    "name:ceb_x_preferred": [
      "Tongren Diqu"
    ],
    "name:cym_x_preferred": [
      "Tongren"
    ],
    "name:dan_x_preferred": [
      "Tongren"
    ],
    "name:deu_x_preferred": [
      "Tongren"
    ],
    "name:eus_x_preferred": [
      "Tongren"
    ],
    "name:fas_x_preferred": [
      "تانگرن"
    ],
    "name:fin_x_preferred": [
      "Tongren"
    ],
    "name:heb_x_preferred": [
      "טונגרן"
    ],
    "name:hun_x_preferred": [
      "Tongren"
    ],
    "name:ita_x_preferred": [
      "Tongren"
    ],
    "name:jpn_x_preferred": [
      "銅仁市"
    ],
    "name:kik_x_preferred": [
      "Tongren"
    ],
    "name:kor_x_preferred": [
      "퉁런시"
    ],
    "name:mlg_x_preferred": [
      "Tongren"
    ],
    "name:nld_x_preferred": [
      "Tongren"
    ],
    "name:nno_x_preferred": [
      "Tongren"
    ],
    "name:nor_x_preferred": [
      "Tongren"
    ],
    "name:pol_x_preferred": [
      "Tongren"
    ],
    "name:rus_x_preferred": [
      "Тунжэнь"
    ],
    "name:spa_x_preferred": [
      "Tong'rén"
    ],
    "name:swe_x_preferred": [
      "Tongren"
    ],
    "name:tur_x_preferred": [
      "Tongren"
    ],
    "name:urd_x_preferred": [
      "تونگرن"
    ],
    "name:vie_x_preferred": [
      "Đồng Nhân"
    ],
    "name:zho_x_preferred": [
      "同仁"
    ],
    "name:zho_x_variant": [
      "铜仁市"
    ],
    "wof:name": "Tongren",
    "wof:placetype": "locality"
  },
  "geometry": {
    "coordinates": [
      111.243,
      25.7227
    ],
    "type": "Point"
  }
}