{
  "type": "Feature",
  "properties": {
    "gn:admin1_code": "11.0",
    "gn:asciiname": "Lijiatuan",
    "gn:country_code": "CN",
    "gn:dem": 365,
    "gn:feature_class": "P",
    "gn:feature_code": "PPL",
    "gn:name": "Lijiatuan",
    "gn:population": 0,
    "gn:timezone": "Asia/Shanghai",
    "iso:country": "CN",
    "name:zho_x_preferred": [
      "李家团"
    ],
    "wof:name": "Lijiatuan",
    "wof:placetype": "locality"
  },
  "geometry": {
    "coordinates": [
      109.59315,
      26.57216
    ],
    "type": "Point"
  }
}