{
  "type": "Feature",
  "properties": {
    "gn:admin1_code": "10",
    "gn:asciiname": "Jiucaigou Shangyingzi",
    "gn:country_code": "CN",
    "gn:dem": 1585,
    "gn:feature_class": "P",
    "gn:feature_code": "PPL",
    "gn:name": "Jiucaigou Shangyingzi",
    "gn:population": 0,
    "gn:timezone": "Asia/Shanghai",
    "iso:country": "CN",
    "name:zho_x_preferred": [
      "韭菜沟上营子"
    ],
    "wof:name": "Jiucaigou Shangyingzi",
    "wof:placetype": "locality"
  },
  "geometry": {
    "coordinates": [
      116.16132,
      41.85329
    ],
    "type": "Point"
  }
}