{
  "type": "Feature",
  "properties": {
    "gn:admin1_code": "02",
    "gn:asciiname": "Man'aocun",
    "gn:country_code": "CN",
    "gn:dem": 22,
    "gn:feature_class": "P",
    "gn:feature_code": "PPL",
    "gn:name": "Man’aocun",
    "gn:population": 0,
    "gn:timezone": "Asia/Shanghai",
    "iso:country": "CN",
    "name:und_x_variant": [
      "Man-tou",
      "Man’aocun"
    ],
    "name:zho_x_preferred": [
      "Man’ao"
    ],
    "name:zho_x_variant": [
      "曼岙",
      "曼岙村"
    ],
    "wof:name": "Man'aocun",
    "wof:placetype": "locality"
  },
  "geometry": {
    "coordinates": [
      121.43622,
      29.13975
    ],
    "type": "Point"
  }
}