{
  "type": "Feature",
  "properties": {
    "gn:admin1_code": "26.0",
    "gn:asciiname": "Liangjiachacun",
    "gn:country_code": "CN",
    "gn:dem": 962,
    "gn:feature_class": "P",
    "gn:feature_code": "PPL",
    "gn:name": "Liangjiachacun",
    "gn:population": 0,
    "gn:timezone": "Asia/Shanghai",
    "iso:country": "CN",
    "name:zho_x_preferred": [
      "梁家岔村"
    ],
    "wof:name": "Liangjiachacun",
    "wof:placetype": "locality"
  },
  "geometry": {
    "coordinates": [
      110.19209,
      36.99319000000001
    ],
    "type": "Point"
  }
}