{
  "type": "Feature",
  "properties": {
    "gn:admin1_code": "3.0",
    "gn:asciiname": "Zuolong",
    "gn:country_code": "CN",
    "gn:dem": 70,
    "gn:feature_class": "P",
    "gn:feature_code": "PPLA4",
    "gn:name": "Zuolong",
    "gn:population": 0,
    "gn:timezone": "Asia/Shanghai",
    "iso:country": "CN",
    "name:ces_x_preferred": [
      "Zuolong"
    ],
    "name:fin_x_preferred": [
      "Zuolong"
    ],
    "name:fra_x_preferred": [
      "Zuolong"
    ],
    "name:mal_x_preferred": [
      "സൂഓലോങ്"
    ],
    "name:nld_x_preferred": [
      "Zuolong"
    ],
    "name:ori_x_preferred": [
      "Zuolong"
    ],
    "name:pol_x_preferred": [
      "Zuolong"
    ],
    "name:rus_x_preferred": [
      "Zuolong salleei"
    ],
    "name:slk_x_preferred": [
      "Zuolong"
    ],
    "name:spa_x_preferred": [
      "Zuolong"
    ],
    "name:ukr_x_preferred": [
      "Zuolong"
    ],
    "name:und_x_variant": [
      "佐龙",
      "Zuolong Xiang",
      "佐龙乡"
    ],
    "name:vie_x_preferred": [
      "Zuolong"
    ],
    "name:zho_x_preferred": [
      "左龍屬"
    ],
    "wof:name": "Zuolong",
    "wof:placetype": "locality"
  },
  "geometry": {
    "coordinates": [
      115.40903,
      27.31388
    ],
    "type": "Point"
  }
}