{
  "type": "Feature",
  "properties": {
    "gn:admin1_code": "26",
    "gn:asciiname": "Beidu",
    "gn:country_code": "CN",
    "gn:dem": 496,
    "gn:feature_class": "P",
    "gn:feature_code": "PPLA4",
    "gn:name": "Beidu",
    "gn:population": 0,
    "gn:timezone": "Asia/Shanghai",
    "iso:country": "CN",
    "name:und_x_variant": [
      "Pei-tu-ts’un",
      "Pei-tu-chen",
      "Pei-tu",
      "Beidu Zhen",
      "Beidu"
    ],
    "name:zho_x_preferred": [
      "北杜"
    ],
    "name:zho_x_variant": [
      "北杜镇"
    ],
    "wof:name": "Beidu",
    "wof:placetype": "locality"
  },
  "geometry": {
    "coordinates": [
      108.73444,
      34.4625
    ],
    "type": "Point"
  }
}