{
  "type": "Feature",
  "properties": {
    "gn:admin1_code": "2.0",
    "gn:asciiname": "Baishe",
    "gn:country_code": "CN",
    "gn:dem": 53,
    "gn:feature_class": "P",
    "gn:feature_code": "PPLA4",
    "gn:name": "Baishe",
    "gn:population": 0,
    "gn:timezone": "Asia/Shanghai",
    "iso:country": "CN",
    "name:und_x_variant": [
      "柏社",
      "Baishe",
      "Baishe Xiang"
    ],
    "name:zho_x_preferred": [
      "柏社乡"
    ],
    "wof:name": "Baishe",
    "wof:placetype": "locality"
  },
  "geometry": {
    "coordinates": [
      119.65011,
      29.33976
    ],
    "type": "Point"
  }
}