{
  "type": "Feature",
  "properties": {
    "gn:admin1_code": "07",
    "gn:asciiname": "Reshuikou",
    "gn:country_code": "CN",
    "gn:dem": 218,
    "gn:feature_class": "P",
    "gn:feature_code": "PPL",
    "gn:name": "Reshuikou",
    "gn:population": 0,
    "gn:timezone": "Asia/Shanghai",
    "iso:country": "CN",
    "name:zho_x_preferred": [
      "热水口"
    ],
    "wof:name": "Reshuikou",
    "wof:placetype": "locality"
  },
  "geometry": {
    "coordinates": [
      117.27192,
      25.89728
    ],
    "type": "Point"
  }
}