{
  "type": "Feature",
  "properties": {
    "gn:admin1_code": "10.0",
    "gn:asciiname": "Songjiashan",
    "gn:country_code": "CN",
    "gn:dem": 1018,
    "gn:feature_class": "P",
    "gn:feature_code": "PPL",
    "gn:name": "Songjiashan",
    "gn:population": 0,
    "gn:timezone": "Asia/Shanghai",
    "iso:country": "CN",
    "name:zho_x_preferred": [
      "宋家山"
    ],
    "wof:name": "Songjiashan",
    "wof:placetype": "locality"
  },
  "geometry": {
    "coordinates": [
      115.15899,
      40.6819
    ],
    "type": "Point"
  }
}