{
  "type": "Feature",
  "properties": {
    "gn:admin1_code": "3",
    "gn:asciiname": "Luodong",
    "gn:country_code": "CN",
    "gn:dem": 269,
    "gn:feature_class": "P",
    "gn:feature_code": "PPL",
    "gn:name": "Luodong",
    "gn:population": 0,
    "gn:timezone": "Asia/Shanghai",
    "iso:country": "CN",
    "name:ceb_x_preferred": [
      "Luodong Zhen"
    ],
    "name:deu_x_preferred": [
      "Luodong"
    ],
    "name:hak_x_preferred": [
      "Lò-tûng-tsṳ́n"
    ],
    "name:ita_x_preferred": [
      "Luodong"
    ],
    "name:jpn_x_preferred": [
      "羅東鎮"
    ],
    "name:kor_x_preferred": [
      "뤄둥진"
    ],
    "name:spa_x_preferred": [
      "Luodong"
    ],
    "name:vie_x_preferred": [
      "La Đông"
    ],
    "name:zho_x_preferred": [
      "罗洞"
    ],
    "name:zho_x_variant": [
      "羅東鎮"
    ],
    "wof:name": "Luodong",
    "wof:placetype": "locality"
  },
  "geometry": {
    "coordinates": [
      114.5948,
      26.13808
    ],
    "type": "Point"
  }
}