{
  "type": "Feature",
  "properties": {
    "gn:admin1_code": "9.0",
    "gn:asciiname": "Diaolou",
    "gn:country_code": "CN",
    "gn:dem": 40,
    "gn:feature_class": "P",
    "gn:feature_code": "PPL",
    "gn:name": "Diaolou",
    "gn:population": 0,
    "gn:timezone": "Asia/Shanghai",
    "iso:country": "CN",
    "name:ast_x_preferred": [
      "Diaolou"
    ],
    "name:cat_x_preferred": [
      "Diaolou"
    ],
    "name:ces_x_preferred": [
      "Tiao-lou"
    ],
    "name:deu_x_preferred": [
      "Diaolou"
    ],
    "name:fin_x_preferred": [
      "Kaipingin diaolout"
    ],
    "name:fra_x_preferred": [
      "Diaolou"
    ],
    "name:ita_x_preferred": [
      "Diaolou"
    ],
    "name:jpn_x_preferred": [
      "開平楼閣と村落"
    ],
    "name:kat_x_preferred": [
      "დიაოლოუ"
    ],
    "name:mal_x_preferred": [
      "കൈപിങ് ഡിയാവ്ലു"
    ],
    "name:nld_x_preferred": [
      "Diaolou"
    ],
    "name:nor_x_preferred": [
      "Diaolou"
    ],
    "name:pol_x_preferred": [
      "Diaolou"
    ],
    "name:rus_x_preferred": [
      "Дяолоу"
    ],
    "name:slk_x_preferred": [
      "Tiao-lou"
    ],
    "name:spa_x_preferred": [
      "Diaolou"
    ],
    "name:swe_x_preferred": [
      "Diaolou"
    ],
    "name:tha_x_preferred": [
      "หอตรวจการณ์และหมู่บ้านแห่งไคผิง"
    ],
    "name:tur_x_preferred": [
      "Diaolou"
    ],
    "name:ukr_x_preferred": [
      "Дяолоу"
    ],
    "name:zho_x_preferred": [
      "刁楼"
    ],
    "name:zho_x_variant": [
      "开平碉楼"
    ],
    "wof:name": "Diaolou",
    "wof:placetype": "locality"
  },
  "geometry": {
    "coordinates": [
      115.60331,
      33.62649
    ],
    "type": "Point"
  }
}