{
  "type": "Feature",
  "properties": {
    "gn:admin1_code": "18",
    "gn:asciiname": "Sami",
    "gn:country_code": "CN",
    "gn:dem": 1270,
    "gn:feature_class": "P",
    "gn:feature_code": "PPL",
    "gn:name": "Sami",
    "gn:population": 0,
    "gn:timezone": "Asia/Shanghai",
    "iso:country": "CN",
    "name:ara_x_preferred": [
      "سامي"
    ],
    "name:cat_x_preferred": [
      "Sami"
    ],
    "name:ceb_x_preferred": [
      "Sami"
    ],
    "name:deu_x_preferred": [
      "Sami"
    ],
    "name:diq_x_preferred": [
      "Sami"
    ],
    "name:eus_x_preferred": [
      "Sami"
    ],
    "name:fas_x_preferred": [
      "سامی"
    ],
    "name:fra_x_preferred": [
      "Sami"
    ],
    "name:hrv_x_preferred": [
      "Sami"
    ],
    "name:ind_x_preferred": [
      "Sami"
    ],
    "name:ita_x_preferred": [
      "Sami"
    ],
    "name:kor_x_preferred": [
      "사미"
    ],
    "name:nld_x_preferred": [
      "Sami"
    ],
    "name:nor_x_preferred": [
      "Samisk"
    ],
    "name:pol_x_preferred": [
      "Sami"
    ],
    "name:por_x_preferred": [
      "Sami"
    ],
    "name:ron_x_preferred": [
      "Sami"
    ],
    "name:rus_x_preferred": [
      "Сами"
    ],
    "name:slv_x_preferred": [
      "Sami"
    ],
    "name:spa_x_preferred": [
      "Sami"
    ],
    "name:srp_x_preferred": [
      "Сами"
    ],
    "name:swe_x_preferred": [
      "Sami"
    ],
    "name:tam_x_preferred": [
      "சாமி"
    ],
    "name:tur_x_preferred": [
      "Sami"
    ],
    "name:zho_x_preferred": [
      "撒米"
    ],
    "wof:name": "Sami",
    "wof:placetype": "locality"
  },
  "geometry": {
    "coordinates": [
      106.653,
      25.9095
    ],
    "type": "Point"
  }
}