{
  "type": "Feature",
  "properties": {
    "gn:admin1_code": "7.0",
    "gn:asciiname": "Xichang",
    "gn:country_code": "CN",
    "gn:dem": 299,
    "gn:feature_class": "P",
    "gn:feature_code": "PPL",
    "gn:name": "Xichang",
    "gn:population": 0,
    "gn:timezone": "Asia/Shanghai",
    "iso:country": "CN",
    "name:ara_x_preferred": [
      "شيتشانغ"
    ],
    "name:ceb_x_preferred": [
      "Xichang"
    ],
    "name:ces_x_preferred": [
      "Si-čchang"
    ],
    "name:dan_x_preferred": [
      "Xichang"
    ],
    "name:deu_x_preferred": [
      "Xichang"
    ],
    "name:fas_x_preferred": [
      "شیچانگ"
    ],
    "name:fin_x_preferred": [
      "Xichang"
    ],
    "name:fra_x_preferred": [
      "Xichang"
    ],
    "name:hak_x_preferred": [
      "Sî-chhông-sṳ"
    ],
    "name:heb_x_preferred": [
      "קסיצ'אנג"
    ],
    "name:hun_x_preferred": [
      "Hszicsang"
    ],
    "name:ind_x_preferred": [
      "Xichang"
    ],
    "name:ita_x_preferred": [
      "Xichang"
    ],
    "name:jpn_x_preferred": [
      "西昌市"
    ],
    "name:kik_x_preferred": [
      "Xichang"
    ],
    "name:kor_x_preferred": [
      "시창시"
    ],
    "name:mlg_x_preferred": [
      "Xichang"
    ],
    "name:nld_x_preferred": [
      "Xichang"
    ],
    "name:nor_x_preferred": [
      "Xichang"
    ],
    "name:pol_x_preferred": [
      "Xichang"
    ],
    "name:por_x_preferred": [
      "Xichang"
    ],
    "name:ron_x_preferred": [
      "Xichang"
    ],
    "name:rus_x_preferred": [
      "Сичан"
    ],
    "name:spa_x_preferred": [
      "Xichang"
    ],
    "name:swe_x_preferred": [
      "Xichang"
    ],
    "name:urd_x_preferred": [
      "شیکچانگ"
    ],
    "name:vie_x_preferred": [
      "Tây Xương"
    ],
    "name:war_x_preferred": [
      "Xichang"
    ],
    "name:zho_x_preferred": [
      "西昌"
    ],
    "name:zho_x_variant": [
      "西昌市"
    ],
    "wof:name": "Xichang",
    "wof:placetype": "locality"
  },
  "geometry": {
    "coordinates": [
      118.13477,
      25.38289
    ],
    "type": "Point"
  }
}