{
  "type": "Feature",
  "properties": {
    "gn:admin1_code": "14.0",
    "gn:asciiname": "Xueponong",
    "gn:country_code": "CN",
    "gn:dem": 4319,
    "gn:feature_class": "P",
    "gn:feature_code": "PPL",
    "gn:name": "Xueponong",
    "gn:population": 0,
    "gn:timezone": "Asia/Urumqi",
    "iso:country": "CN",
    "name:zho_x_preferred": [
      "学坡弄"
    ],
    "wof:name": "Xueponong",
    "wof:placetype": "locality"
  },
  "geometry": {
    "coordinates": [
      96.13827,
      30.74266
    ],
    "type": "Point"
  }
}