{
  "type": "Feature",
  "properties": {
    "gn:admin1_code": "12.0",
    "gn:asciiname": "Houbai'erzhao",
    "gn:country_code": "CN",
    "gn:dem": 28,
    "gn:feature_class": "P",
    "gn:feature_code": "PPL",
    "gn:name": "Houbai’erzhao",
    "gn:population": 0,
    "gn:timezone": "Asia/Shanghai",
    "iso:country": "CN",
    "name:und_x_variant": [
      "Houbai’erzhao"
    ],
    "name:zho_x_preferred": [
      "后百二沼"
    ],
    "wof:name": "Houbai'erzhao",
    "wof:placetype": "locality"
  },
  "geometry": {
    "coordinates": [
      113.488,
      30.43245
    ],
    "type": "Point"
  }
}