{
  "type": "Feature",
  "properties": {
    "gn:admin1_code": "24",
    "gn:asciiname": "Hongya",
    "gn:country_code": "CN",
    "gn:dem": 1524,
    "gn:feature_class": "P",
    "gn:feature_code": "PPL",
    "gn:name": "Hongya",
    "gn:population": 0,
    "gn:timezone": "Asia/Shanghai",
    "iso:country": "CN",
    "name:deu_x_preferred": [
      "Hongya"
    ],
    "name:rus_x_preferred": [
      "Хунъя"
    ],
    "name:und_x_variant": [
      "Hung-ya",
      "Hung-yai",
      "Hung-yai-ts’un"
    ],
    "name:zho_x_preferred": [
      "红崖"
    ],
    "wof:name": "Hongya",
    "wof:placetype": "locality"
  },
  "geometry": {
    "coordinates": [
      113.31435,
      37.53132
    ],
    "type": "Point"
  }
}