{
  "type": "Feature",
  "properties": {
    "gn:admin1_code": "10",
    "gn:asciiname": "Diliutun",
    "gn:country_code": "CN",
    "gn:dem": 757,
    "gn:feature_class": "P",
    "gn:feature_code": "PPL",
    "gn:name": "Diliutun",
    "gn:population": 0,
    "gn:timezone": "Asia/Shanghai",
    "iso:country": "CN",
    "wof:name": "Diliutun",
    "wof:placetype": "locality"
  },
  "geometry": {
    "coordinates": [
      114.56528,
      40.6575
    ],
    "type": "Point"
  }
}