{
  "type": "Feature",
  "properties": {
    "gn:admin1_code": "10",
    "gn:asciiname": "Shanhaiguan",
    "gn:country_code": "CN",
    "gn:dem": 13,
    "gn:feature_class": "P",
    "gn:feature_code": "PPLA3",
    "gn:name": "Shanhaiguan",
    "gn:population": 140000,
    "gn:timezone": "Asia/Shanghai",
    "iso:country": "CN",
    "name:deu_x_preferred": [
      "Shanhaiguan"
    ],
    "name:eng_x_preferred": [
      "Shanhaiguan"
    ],
    "name:jpn_x_preferred": [
      "山海関区"
    ],
    "name:kor_x_preferred": [
      "산하이관구"
    ],
    "name:rus_x_preferred": [
      "Шаньхайгуань"
    ],
    "name:swe_x_preferred": [
      "Shanhaiguan"
    ],
    "name:ukr_x_preferred": [
      "Шаньхайгуань"
    ],
    "name:und_x_variant": [
      "Lin-yü",
      "Shan-hai-kuan",
      "Shanhaikwan"
    ],
    "name:urd_x_preferred": [
      "شانہایگوان ضلع"
    ],
    "name:zho_x_preferred": [
      "山海关"
    ],
    "name:zho_x_variant": [
      "山海关区"
    ],
    "wof:name": "Shanhaiguan",
    "wof:placetype": "locality",
    "wof:population": 140000
  },
  "geometry": {
    "coordinates": [
      119.74889,
      40.0025
    ],
    "type": "Point"
  }
}