{
  "type": "Feature",
  "properties": {
    "gn:admin1_code": "19.0",
    "gn:asciiname": "Luzhangzi",
    "gn:country_code": "CN",
    "gn:dem": 285,
    "gn:feature_class": "P",
    "gn:feature_code": "PPL",
    "gn:name": "Lüzhangzi",
    "gn:population": 0,
    "gn:timezone": "Asia/Shanghai",
    "iso:country": "CN",
    "name:zho_x_preferred": [
      "吕杖子"
    ],
    "name:zho_x_variant": [
      "Lüzhangzi"
    ],
    "wof:name": "Luzhangzi",
    "wof:placetype": "locality"
  },
  "geometry": {
    "coordinates": [
      119.65,
      40.3912
    ],
    "type": "Point"
  }
}