{
  "type": "Feature",
  "properties": {
    "gn:admin1_code": "29",
    "gn:asciiname": "Zhedeqing",
    "gn:country_code": "CN",
    "gn:dem": 1954,
    "gn:feature_class": "P",
    "gn:feature_code": "PPL",
    "gn:name": "Zhedeqing",
    "gn:population": 0,
    "gn:timezone": "Asia/Shanghai",
    "iso:country": "CN",
    "name:zho_x_preferred": [
      "者德箐"
    ],
    "wof:name": "Zhedeqing",
    "wof:placetype": "locality"
  },
  "geometry": {
    "coordinates": [
      102.05666,
      24.75165
    ],
    "type": "Point"
  }
}