{
  "type": "Feature",
  "properties": {
    "gn:admin1_code": "11.0",
    "gn:asciiname": "Wenjiadong",
    "gn:country_code": "CN",
    "gn:dem": 100,
    "gn:feature_class": "P",
    "gn:feature_code": "PPL",
    "gn:name": "Wenjiadong",
    "gn:population": 0,
    "gn:timezone": "Asia/Shanghai",
    "iso:country": "CN",
    "name:zho_x_preferred": [
      "文家洞"
    ],
    "wof:name": "Wenjiadong",
    "wof:placetype": "locality"
  },
  "geometry": {
    "coordinates": [
      112.69023,
      26.47766
    ],
    "type": "Point"
  }
}