{
  "type": "Feature",
  "properties": {
    "gn:admin1_code": "30",
    "gn:asciiname": "Duzhoushan",
    "gn:country_code": "CN",
    "gn:dem": 20,
    "gn:feature_class": "P",
    "gn:feature_code": "PPL",
    "gn:name": "Duzhoushan",
    "gn:population": 0,
    "gn:timezone": "Asia/Shanghai",
    "iso:country": "CN",
    "name:zho_x_preferred": [
      "笃洲山"
    ],
    "wof:name": "Duzhoushan",
    "wof:placetype": "locality"
  },
  "geometry": {
    "coordinates": [
      111.67356,
      21.60353
    ],
    "type": "Point"
  }
}