{
  "type": "Feature",
  "properties": {
    "gn:admin1_code": "5.0",
    "gn:asciiname": "Sanjiazi",
    "gn:country_code": "CN",
    "gn:dem": 136,
    "gn:feature_class": "P",
    "gn:feature_code": "PPL",
    "gn:name": "Sanjiazi",
    "gn:population": 0,
    "gn:timezone": "Asia/Shanghai",
    "iso:country": "CN",
    "name:zho_x_preferred": [
      "三家子"
    ],
    "name:zho_x_variant": [
      "三家子村"
    ],
    "wof:name": "Sanjiazi",
    "wof:placetype": "locality"
  },
  "geometry": {
    "coordinates": [
      123.29366,
      45.81126
    ],
    "type": "Point"
  }
}