{
  "type": "Feature",
  "properties": {
    "gn:admin1_code": "26.0",
    "gn:asciiname": "Dangjiatuncun",
    "gn:country_code": "CN",
    "gn:dem": 938,
    "gn:feature_class": "P",
    "gn:feature_code": "PPL",
    "gn:name": "Dangjiatuncun",
    "gn:population": 0,
    "gn:timezone": "Asia/Shanghai",
    "iso:country": "CN",
    "name:zho_x_preferred": [
      "党家屯村"
    ],
    "wof:name": "Dangjiatuncun",
    "wof:placetype": "locality"
  },
  "geometry": {
    "coordinates": [
      109.87037,
      36.57525
    ],
    "type": "Point"
  }
}