{
  "type": "Feature",
  "properties": {
    "gn:admin1_code": "19.0",
    "gn:asciiname": "Shangwangtun",
    "gn:country_code": "CN",
    "gn:dem": 186,
    "gn:feature_class": "P",
    "gn:feature_code": "PPL",
    "gn:name": "Shangwangtun",
    "gn:population": 0,
    "gn:timezone": "Asia/Shanghai",
    "iso:country": "CN",
    "name:zho_x_preferred": [
      "上王屯"
    ],
    "wof:name": "Shangwangtun",
    "wof:placetype": "locality"
  },
  "geometry": {
    "coordinates": [
      120.329,
      40.6857
    ],
    "type": "Point"
  }
}