{
  "type": "Feature",
  "properties": {
    "gn:admin1_code": "3.0",
    "gn:asciiname": "Tangbei",
    "gn:country_code": "CN",
    "gn:dem": 167,
    "gn:feature_class": "P",
    "gn:feature_code": "PPL",
    "gn:name": "Tangbei",
    "gn:population": 0,
    "gn:timezone": "Asia/Shanghai",
    "iso:country": "CN",
    "name:und_x_variant": [
      "塘背"
    ],
    "wof:name": "Tangbei",
    "wof:placetype": "locality"
  },
  "geometry": {
    "coordinates": [
      115.01416,
      25.43685
    ],
    "type": "Point"
  }
}