{
  "type": "Feature",
  "properties": {
    "gn:admin1_code": "16.0",
    "gn:asciiname": "Dunu",
    "gn:country_code": "CN",
    "gn:dem": 136,
    "gn:feature_class": "P",
    "gn:feature_code": "PPL",
    "gn:name": "Dunü",
    "gn:population": 0,
    "gn:timezone": "Asia/Shanghai",
    "iso:country": "CN",
    "name:und_x_variant": [
      "Dunü"
    ],
    "name:zho_x_preferred": [
      "独女"
    ],
    "wof:name": "Dunu",
    "wof:placetype": "locality"
  },
  "geometry": {
    "coordinates": [
      108.377,
      23.1605
    ],
    "type": "Point"
  }
}