{
  "type": "Feature",
  "properties": {
    "gn:admin1_code": "13.0",
    "gn:asciiname": "Qiman",
    "gn:country_code": "CN",
    "gn:dem": 1005,
    "gn:feature_class": "P",
    "gn:feature_code": "PPLA4",
    "gn:name": "Qiman",
    "gn:population": 0,
    "gn:timezone": "Asia/Urumqi",
    "iso:country": "CN",
    "name:uig_x_preferred": [
      "Qimən"
    ],
    "name:uig_x_variant": [
      "Chimen",
      "چىمەن",
      "Чимән"
    ],
    "name:und_x_variant": [
      "Qiman Zhen"
    ],
    "name:zho_x_preferred": [
      "齐满"
    ],
    "name:zho_x_variant": [
      "齐满镇"
    ],
    "wof:name": "Qiman",
    "wof:placetype": "locality"
  },
  "geometry": {
    "coordinates": [
      82.91139,
      41.53778
    ],
    "type": "Point"
  }
}