{
  "type": "Feature",
  "properties": {
    "gn:admin1_code": "18.0",
    "gn:asciiname": "Yintan Shangzhai",
    "gn:country_code": "CN",
    "gn:dem": 658,
    "gn:feature_class": "P",
    "gn:feature_code": "PPL",
    "gn:name": "Yintan Shangzhai",
    "gn:population": 0,
    "gn:timezone": "Asia/Shanghai",
    "iso:country": "CN",
    "name:zho_x_preferred": [
      "银潭上寨"
    ],
    "wof:name": "Yintan Shangzhai",
    "wof:placetype": "locality"
  },
  "geometry": {
    "coordinates": [
      108.844,
      25.8353
    ],
    "type": "Point"
  }
}