{
  "type": "Feature",
  "properties": {
    "gn:admin1_code": "24",
    "gn:asciiname": "Beidong",
    "gn:country_code": "CN",
    "gn:dem": 511,
    "gn:feature_class": "P",
    "gn:feature_code": "PPLA4",
    "gn:name": "Beidong",
    "gn:population": 0,
    "gn:timezone": "Asia/Shanghai",
    "iso:country": "CN",
    "name:und_x_variant": [
      "Pei-tung-ts’un",
      "Pei-tung",
      "Beidong",
      "北董",
      "Beidong Xiang",
      "北董乡"
    ],
    "wof:name": "Beidong",
    "wof:placetype": "locality"
  },
  "geometry": {
    "coordinates": [
      111.54265,
      35.616
    ],
    "type": "Point"
  }
}