{
  "type": "Feature",
  "properties": {
    "gn:admin1_code": "13",
    "gn:asciiname": "Yalegu Zibage",
    "gn:country_code": "CN",
    "gn:dem": 1330,
    "gn:feature_class": "P",
    "gn:feature_code": "PPL",
    "gn:name": "Yalegu Zibage",
    "gn:population": 0,
    "gn:timezone": "Asia/Shanghai",
    "iso:country": "CN",
    "name:und_x_variant": [
      "亚勒古孜巴格"
    ],
    "wof:name": "Yalegu Zibage",
    "wof:placetype": "locality"
  },
  "geometry": {
    "coordinates": [
      77.14359,
      38.10225
    ],
    "type": "Point"
  }
}