{
  "type": "Feature",
  "properties": {
    "gn:admin1_code": "32.0",
    "gn:asciiname": "Dadiwan",
    "gn:country_code": "CN",
    "gn:dem": 448,
    "gn:feature_class": "P",
    "gn:feature_code": "PPL",
    "gn:name": "Dadiwan",
    "gn:population": 0,
    "gn:timezone": "Asia/Shanghai",
    "iso:country": "CN",
    "name:deu_x_preferred": [
      "Dadiwan"
    ],
    "name:fas_x_preferred": [
      "فرهنگ دادی‌وان"
    ],
    "name:jpn_x_preferred": [
      "老官台文化"
    ],
    "name:kor_x_preferred": [
      "라오관타이 문화"
    ],
    "name:nor_x_preferred": [
      "Dadiwankulturen"
    ],
    "name:zho_x_preferred": [
      "大地湾"
    ],
    "name:zho_x_variant": [
      "老官台文化"
    ],
    "wof:name": "Dadiwan",
    "wof:placetype": "locality"
  },
  "geometry": {
    "coordinates": [
      105.04498,
      31.23706
    ],
    "type": "Point"
  }
}