{
  "type": "Feature",
  "properties": {
    "gn:admin1_code": "29.0",
    "gn:asciiname": "Xingyang",
    "gn:country_code": "CN",
    "gn:dem": 1724,
    "gn:feature_class": "P",
    "gn:feature_code": "PPL",
    "gn:name": "Xingyang",
    "gn:population": 0,
    "gn:timezone": "Asia/Shanghai",
    "iso:country": "CN",
    "name:deu_x_preferred": [
      "Xingyang"
    ],
    "name:eus_x_preferred": [
      "Xingyang"
    ],
    "name:fra_x_preferred": [
      "Xingyang"
    ],
    "name:ita_x_preferred": [
      "Xingyang"
    ],
    "name:jpn_x_preferred": [
      "ケイ陽市"
    ],
    "name:kik_x_preferred": [
      "Xingyang"
    ],
    "name:kor_x_preferred": [
      "싱양시"
    ],
    "name:nor_x_preferred": [
      "Xingyang"
    ],
    "name:pam_x_preferred": [
      "Xingyang"
    ],
    "name:rus_x_preferred": [
      "Синъян"
    ],
    "name:spa_x_preferred": [
      "Xingyang"
    ],
    "name:swe_x_preferred": [
      "Xingyang"
    ],
    "name:urd_x_preferred": [
      "شنگیانگ"
    ],
    "name:vie_x_preferred": [
      "Huỳnh Dương"
    ],
    "name:zho_x_preferred": [
      "荥阳"
    ],
    "name:zho_x_variant": [
      "荥阳市"
    ],
    "wof:name": "Xingyang",
    "wof:placetype": "locality"
  },
  "geometry": {
    "coordinates": [
      98.5031,
      25.2942
    ],
    "type": "Point"
  }
}