{
  "type": "Feature",
  "properties": {
    "gn:admin1_code": "02",
    "gn:asciiname": "Wayaotoucun",
    "gn:country_code": "CN",
    "gn:dem": 148,
    "gn:feature_class": "P",
    "gn:feature_code": "PPL",
    "gn:name": "Wayaotoucun",
    "gn:population": 0,
    "gn:timezone": "Asia/Shanghai",
    "iso:country": "CN",
    "name:und_x_variant": [
      "Wayaotou",
      "Wayaotoucun"
    ],
    "name:zho_x_preferred": [
      "瓦窑头"
    ],
    "name:zho_x_variant": [
      "瓦窑头村"
    ],
    "wof:name": "Wayaotoucun",
    "wof:placetype": "locality"
  },
  "geometry": {
    "coordinates": [
      121.51397,
      29.31821
    ],
    "type": "Point"
  }
}