{
  "type": "Feature",
  "properties": {
    "gn:admin1_code": "21.0",
    "gn:asciiname": "Xia'anlongzhuang",
    "gn:country_code": "CN",
    "gn:dem": 1760,
    "gn:feature_class": "P",
    "gn:feature_code": "PPL",
    "gn:name": "Xia’anlongzhuang",
    "gn:population": 0,
    "gn:timezone": "Asia/Shanghai",
    "iso:country": "CN",
    "name:zho_x_preferred": [
      "Xia’anlongzhuang"
    ],
    "name:zho_x_variant": [
      "下安隆庄"
    ],
    "wof:name": "Xia'anlongzhuang",
    "wof:placetype": "locality"
  },
  "geometry": {
    "coordinates": [
      106.14927,
      36.04437
    ],
    "type": "Point"
  }
}