{
  "type": "Feature",
  "properties": {
    "gn:admin1_code": "29.0",
    "gn:asciiname": "Huashiban",
    "gn:country_code": "CN",
    "gn:dem": 1702,
    "gn:feature_class": "P",
    "gn:feature_code": "PPL",
    "gn:name": "Huashiban",
    "gn:population": 0,
    "gn:timezone": "Asia/Shanghai",
    "iso:country": "CN",
    "name:zho_x_preferred": [
      "滑石板"
    ],
    "wof:name": "Huashiban",
    "wof:placetype": "locality"
  },
  "geometry": {
    "coordinates": [
      103.407,
      22.8261
    ],
    "type": "Point"
  }
}