{
  "type": "Feature",
  "properties": {
    "gn:admin1_code": "19",
    "gn:asciiname": "Tianjiacun",
    "gn:country_code": "CN",
    "gn:dem": 46,
    "gn:feature_class": "P",
    "gn:feature_code": "PPL",
    "gn:name": "Tianjiacun",
    "gn:population": 0,
    "gn:timezone": "Asia/Shanghai",
    "iso:country": "CN",
    "name:und_x_variant": [
      "T’ien-chia-tien",
      "T’ien-chia",
      "T’ien-chia-t’un",
      "Tianjia",
      "Tianjiacun"
    ],
    "name:zho_x_preferred": [
      "田家村"
    ],
    "wof:name": "Tianjiacun",
    "wof:placetype": "locality"
  },
  "geometry": {
    "coordinates": [
      122.00327,
      39.53511
    ],
    "type": "Point"
  }
}