{
  "type": "Feature",
  "properties": {
    "gn:admin1_code": "09",
    "gn:asciiname": "Panlong",
    "gn:country_code": "CN",
    "gn:dem": 99,
    "gn:feature_class": "P",
    "gn:feature_code": "PPLA3",
    "gn:name": "Panlong",
    "gn:population": 0,
    "gn:timezone": "Asia/Shanghai",
    "iso:country": "CN",
    "name:deu_x_preferred": [
      "Queshan"
    ],
    "name:fas_x_preferred": [
      "شهرستان چوشان"
    ],
    "name:jpn_x_preferred": [
      "確山県"
    ],
    "name:kor_x_preferred": [
      "췌산현"
    ],
    "name:nor_x_preferred": [
      "Queshan"
    ],
    "name:rus_x_preferred": [
      "Цюэшань"
    ],
    "name:swe_x_preferred": [
      "Queshan"
    ],
    "name:und_x_variant": [
      "Kioshan-hsien",
      "Ch’üeh-shan-hsien",
      "Kioshan",
      "Ch’üeh-shan",
      "Chiu-shan",
      "Panlong"
    ],
    "name:vie_x_preferred": [
      "Xác Sơn"
    ],
    "name:zho_x_preferred": [
      "盘龙"
    ],
    "name:zho_x_variant": [
      "确山县"
    ],
    "wof:name": "Panlong",
    "wof:placetype": "locality"
  },
  "geometry": {
    "coordinates": [
      114.01917,
      32.80222
    ],
    "type": "Point"
  }
}