{
  "type": "Feature",
  "properties": {
    "gn:admin1_code": "16.0",
    "gn:asciiname": "Banba",
    "gn:country_code": "CN",
    "gn:dem": 518,
    "gn:feature_class": "P",
    "gn:feature_code": "PPL",
    "gn:name": "Banba",
    "gn:population": 0,
    "gn:timezone": "Asia/Shanghai",
    "iso:country": "CN",
    "name:deu_x_preferred": [
      "Banba"
    ],
    "name:fin_x_preferred": [
      "Banbha"
    ],
    "name:fra_x_preferred": [
      "Banba"
    ],
    "name:gle_x_preferred": [
      "Banbha"
    ],
    "name:ita_x_preferred": [
      "Banba"
    ],
    "name:jpn_x_preferred": [
      "バンバ"
    ],
    "name:nld_x_preferred": [
      "Banba"
    ],
    "name:pol_x_preferred": [
      "Banba"
    ],
    "name:por_x_preferred": [
      "Banba"
    ],
    "name:zho_x_preferred": [
      "板岜"
    ],
    "wof:name": "Banba",
    "wof:placetype": "locality"
  },
  "geometry": {
    "coordinates": [
      107.283,
      24.5023
    ],
    "type": "Point"
  }
}