{
  "type": "Feature",
  "properties": {
    "gn:admin1_code": "16.0",
    "gn:asciiname": "Chongyan",
    "gn:country_code": "CN",
    "gn:dem": 181,
    "gn:feature_class": "P",
    "gn:feature_code": "PPL",
    "gn:name": "Chongyan",
    "gn:population": 0,
    "gn:timezone": "Asia/Shanghai",
    "iso:country": "CN",
    "name:zho_x_preferred": [
      "崇岩"
    ],
    "wof:name": "Chongyan",
    "wof:placetype": "locality"
  },
  "geometry": {
    "coordinates": [
      108.348,
      24.3245
    ],
    "type": "Point"
  }
}