{
  "type": "Feature",
  "properties": {
    "gn:admin1_code": "13.0",
    "gn:asciiname": "Aykol",
    "gn:country_code": "CN",
    "gn:dem": 1075,
    "gn:feature_class": "P",
    "gn:feature_code": "PPL",
    "gn:name": "Aykol",
    "gn:population": 11260,
    "gn:timezone": "Asia/Shanghai",
    "iso:country": "CN",
    "name:ceb_x_preferred": [
      "Aykol"
    ],
    "name:fas_x_preferred": [
      "ایکول"
    ],
    "name:mlg_x_preferred": [
      "Aykol"
    ],
    "name:swe_x_preferred": [
      "Aykol"
    ],
    "name:uig_x_preferred": [
      "Aykɵl"
    ],
    "name:uig_x_variant": [
      "Ayköl",
      "ئايكۆل",
      "Айкөл",
      "ئايكۆل يېزىسى"
    ],
    "name:und_x_variant": [
      "A-yin-k’o"
    ],
    "name:zho_x_preferred": [
      "阿依库勒乡"
    ],
    "wof:name": "Aykol",
    "wof:placetype": "locality",
    "wof:population": 11260
  },
  "geometry": {
    "coordinates": [
      80.13574,
      40.95759
    ],
    "type": "Point"
  }
}