{
  "type": "Feature",
  "properties": {
    "gn:admin1_code": "30",
    "gn:asciiname": "Fenshui'ao",
    "gn:country_code": "CN",
    "gn:dem": 50,
    "gn:feature_class": "P",
    "gn:feature_code": "PPL",
    "gn:name": "Fenshui’ao",
    "gn:population": 0,
    "gn:timezone": "Asia/Shanghai",
    "iso:country": "CN",
    "name:zho_x_preferred": [
      "分水坳"
    ],
    "name:zho_x_variant": [
      "Fenshui’ao"
    ],
    "wof:name": "Fenshui'ao",
    "wof:placetype": "locality"
  },
  "geometry": {
    "coordinates": [
      111.52263,
      21.77595
    ],
    "type": "Point"
  }
}