{
  "type": "Feature",
  "properties": {
    "gn:admin1_code": "31.0",
    "gn:asciiname": "Sanjian",
    "gn:country_code": "CN",
    "gn:dem": 57,
    "gn:feature_class": "P",
    "gn:feature_code": "PPL",
    "gn:name": "Sanjian",
    "gn:population": 0,
    "gn:timezone": "Asia/Shanghai",
    "iso:country": "CN",
    "name:zho_x_preferred": [
      "三间"
    ],
    "wof:name": "Sanjian",
    "wof:placetype": "locality"
  },
  "geometry": {
    "coordinates": [
      108.76417,
      18.82513
    ],
    "type": "Point"
  }
}