{
  "type": "Feature",
  "properties": {
    "gn:admin1_code": "21.0",
    "gn:asciiname": "Liangjianao",
    "gn:country_code": "CN",
    "gn:dem": 1991,
    "gn:feature_class": "P",
    "gn:feature_code": "PPL",
    "gn:name": "Liangjianao",
    "gn:population": 0,
    "gn:timezone": "Asia/Shanghai",
    "iso:country": "CN",
    "name:zho_x_preferred": [
      "梁家垴"
    ],
    "wof:name": "Liangjianao",
    "wof:placetype": "locality"
  },
  "geometry": {
    "coordinates": [
      105.4254,
      35.88136
    ],
    "type": "Point"
  }
}