{
  "type": "Feature",
  "properties": {
    "gn:admin1_code": "3",
    "gn:asciiname": "Huangqiutang",
    "gn:country_code": "CN",
    "gn:dem": 1055,
    "gn:feature_class": "P",
    "gn:feature_code": "PPL",
    "gn:name": "Huangqiutang",
    "gn:population": 0,
    "gn:timezone": "Asia/Shanghai",
    "iso:country": "CN",
    "name:zho_x_preferred": [
      "黄鳅塘"
    ],
    "wof:name": "Huangqiutang",
    "wof:placetype": "locality"
  },
  "geometry": {
    "coordinates": [
      114.141,
      26.1137
    ],
    "type": "Point"
  }
}