{
  "type": "Feature",
  "properties": {
    "gn:admin1_code": "2.0",
    "gn:asciiname": "Long'ertou",
    "gn:country_code": "CN",
    "gn:dem": 559,
    "gn:feature_class": "P",
    "gn:feature_code": "PPL",
    "gn:name": "Long’ertou",
    "gn:population": 0,
    "gn:timezone": "Asia/Shanghai",
    "iso:country": "CN",
    "name:und_x_variant": [
      "Long’ertou"
    ],
    "name:zho_x_preferred": [
      "龙儿头"
    ],
    "wof:name": "Long'ertou",
    "wof:placetype": "locality"
  },
  "geometry": {
    "coordinates": [
      120.08514,
      27.81411
    ],
    "type": "Point"
  }
}