{
  "type": "Feature",
  "properties": {
    "gn:admin1_code": "5.0",
    "gn:asciiname": "Ma'anshan",
    "gn:country_code": "CN",
    "gn:dem": 780,
    "gn:feature_class": "P",
    "gn:feature_code": "PPL",
    "gn:name": "Ma’anshan",
    "gn:population": 0,
    "gn:timezone": "Asia/Shanghai",
    "iso:country": "CN",
    "name:afr_x_preferred": [
      "Ma'anshan"
    ],
    "name:ara_x_preferred": [
      "مانشان"
    ],
    "name:bul_x_preferred": [
      "Мааншан"
    ],
    "name:cdo_x_preferred": [
      "Mā-ăng-săng"
    ],
    "name:ces_x_preferred": [
      "Ma-an-šan"
    ],
    "name:cym_x_preferred": [
      "Ma'anshan"
    ],
    "name:dan_x_preferred": [
      "Ma'anshan"
    ],
    "name:deu_x_preferred": [
      "Ma’anshan"
    ],
    "name:epo_x_preferred": [
      "Maanŝan"
    ],
    "name:eus_x_preferred": [
      "Ma'anshan"
    ],
    "name:fas_x_preferred": [
      "مانشان"
    ],
    "name:fin_x_preferred": [
      "Ma’anshan"
    ],
    "name:fra_x_preferred": [
      "Ma'anshan"
    ],
    "name:hye_x_preferred": [
      "Մաանշան"
    ],
    "name:ind_x_preferred": [
      "Ma'anshan"
    ],
    "name:ita_x_preferred": [
      "Ma'anshan"
    ],
    "name:jpn_x_preferred": [
      "馬鞍山市"
    ],
    "name:kik_x_preferred": [
      "Ma'anshan"
    ],
    "name:kor_x_preferred": [
      "마안산시"
    ],
    "name:mlg_x_preferred": [
      "Ma'anshan"
    ],
    "name:nld_x_preferred": [
      "Ma'anshan"
    ],
    "name:nno_x_preferred": [
      "Ma'anshan"
    ],
    "name:nor_x_preferred": [
      "Ma'anshan"
    ],
    "name:pam_x_preferred": [
      "Ma'anshan"
    ],
    "name:pnb_x_preferred": [
      "مآنشان"
    ],
    "name:pol_x_preferred": [
      "Ma’anshan"
    ],
    "name:por_x_preferred": [
      "Maanshan"
    ],
    "name:rus_x_preferred": [
      "Мааньшань"
    ],
    "name:sco_x_preferred": [
      "Ma'anshan"
    ],
    "name:spa_x_preferred": [
      "Maanshan"
    ],
    "name:srp_x_preferred": [
      "Ма'аншан"
    ],
    "name:swe_x_preferred": [
      "Ma'anshan"
    ],
    "name:tgl_x_preferred": [
      "Ma'anshan"
    ],
    "name:tur_x_preferred": [
      "Ma'anshan"
    ],
    "name:uig_x_preferred": [
      "مائەنشەن شەھىرى"
    ],
    "name:ukr_x_preferred": [
      "Мааньшань"
    ],
    "name:und_x_variant": [
      "马鞍山"
    ],
    "name:urd_x_preferred": [
      "مآنشان"
    ],
    "name:war_x_preferred": [
      "Maanshan"
    ],
    "name:wuu_x_preferred": [
      "马鞍山市"
    ],
    "name:zho_x_preferred": [
      "马鞍山市"
    ],
    "wof:name": "Ma'anshan",
    "wof:placetype": "locality"
  },
  "geometry": {
    "coordinates": [
      127.28,
      41.55784
    ],
    "type": "Point"
  }
}