{
  "type": "Feature",
  "properties": {
    "gn:admin1_code": "10",
    "gn:asciiname": "Jiashizhuang",
    "gn:cc2": "CN",
    "gn:country_code": "CN",
    "gn:dem": 45,
    "gn:feature_class": "P",
    "gn:feature_code": "PPL",
    "gn:name": "Jiashizhuang",
    "gn:population": 0,
    "gn:timezone": "Asia/Shanghai",
    "iso:country": "CN",
    "name:und_x_variant": [
      "Chia-shih-chuang-chen",
      "Ku-shih-chuang-chen",
      "Chia-shih-chuang",
      "Jiashizhuang"
    ],
    "name:zho_x_preferred": [
      "贾市庄镇"
    ],
    "wof:name": "Jiashizhuang",
    "wof:placetype": "locality"
  },
  "geometry": {
    "coordinates": [
      114.94583,
      37.86556
    ],
    "type": "Point"
  }
}