{
  "type": "Feature",
  "properties": {
    "gn:admin1_code": "6.0",
    "gn:asciiname": "Kuarilong",
    "gn:country_code": "CN",
    "gn:dem": 3791,
    "gn:feature_class": "P",
    "gn:feature_code": "PPL",
    "gn:name": "Kuarilong",
    "gn:population": 0,
    "gn:timezone": "Asia/Shanghai",
    "iso:country": "CN",
    "name:zho_x_preferred": [
      "夸日龙"
    ],
    "wof:name": "Kuarilong",
    "wof:placetype": "locality"
  },
  "geometry": {
    "coordinates": [
      101.419,
      35.16406
    ],
    "type": "Point"
  }
}