{
  "type": "Feature",
  "properties": {
    "gn:admin1_code": "10",
    "gn:asciiname": "Tiejianggou",
    "gn:country_code": "CN",
    "gn:dem": 727,
    "gn:feature_class": "P",
    "gn:feature_code": "PPL",
    "gn:name": "Tiejianggou",
    "gn:population": 0,
    "gn:timezone": "Asia/Shanghai",
    "iso:country": "CN",
    "name:zho_x_preferred": [
      "铁匠沟"
    ],
    "wof:name": "Tiejianggou",
    "wof:placetype": "locality"
  },
  "geometry": {
    "coordinates": [
      118.71183,
      41.22317
    ],
    "type": "Point"
  }
}