{
  "type": "Feature",
  "properties": {
    "gn:admin1_code": "16",
    "gn:asciiname": "Limu",
    "gn:country_code": "CN",
    "gn:dem": 191,
    "gn:feature_class": "P",
    "gn:feature_code": "PPL",
    "gn:name": "Limu",
    "gn:population": 0,
    "gn:timezone": "Asia/Shanghai",
    "iso:country": "CN",
    "name:deu_x_preferred": [
      "Limu"
    ],
    "name:fra_x_preferred": [
      "Limu"
    ],
    "name:hye_x_preferred": [
      "Լիմու"
    ],
    "name:ton_x_preferred": [
      "Limu"
    ],
    "name:zho_x_preferred": [
      "栗木"
    ],
    "wof:name": "Limu",
    "wof:placetype": "locality"
  },
  "geometry": {
    "coordinates": [
      110.55,
      24.6799
    ],
    "type": "Point"
  }
}