{
  "type": "Feature",
  "properties": {
    "gn:admin1_code": "25",
    "gn:asciiname": "Nanmajia Zhuangzi",
    "gn:country_code": "CN",
    "gn:dem": 58,
    "gn:feature_class": "P",
    "gn:feature_code": "PPL",
    "gn:name": "Nanmajia Zhuangzi",
    "gn:population": 0,
    "gn:timezone": "Asia/Shanghai",
    "iso:country": "CN",
    "name:zho_x_preferred": [
      "南马家庄子"
    ],
    "wof:name": "Nanmajia Zhuangzi",
    "wof:placetype": "locality"
  },
  "geometry": {
    "coordinates": [
      119.547,
      35.7701
    ],
    "type": "Point"
  }
}