{
  "type": "Feature",
  "properties": {
    "gn:admin1_code": "22.0",
    "gn:asciiname": "Tianpuchigou",
    "gn:country_code": "CN",
    "gn:dem": 344,
    "gn:feature_class": "P",
    "gn:feature_code": "PPL",
    "gn:name": "Tianpuchigou",
    "gn:population": 0,
    "gn:timezone": "Asia/Shanghai",
    "iso:country": "CN",
    "name:zho_x_preferred": [
      "天蒲池沟"
    ],
    "wof:name": "Tianpuchigou",
    "wof:placetype": "locality"
  },
  "geometry": {
    "coordinates": [
      116.68294,
      40.74402
    ],
    "type": "Point"
  }
}