{
  "type": "Feature",
  "properties": {
    "gn:admin1_code": "21.0",
    "gn:asciiname": "Tong'erzhuang",
    "gn:country_code": "CN",
    "gn:dem": 1540,
    "gn:feature_class": "P",
    "gn:feature_code": "PPL",
    "gn:name": "Tong’erzhuang",
    "gn:population": 0,
    "gn:timezone": "Asia/Shanghai",
    "iso:country": "CN",
    "name:und_x_variant": [
      "Tong’erzhuang"
    ],
    "name:zho_x_preferred": [
      "童儿庄"
    ],
    "wof:name": "Tong'erzhuang",
    "wof:placetype": "locality"
  },
  "geometry": {
    "coordinates": [
      106.54,
      37.1337
    ],
    "type": "Point"
  }
}