{
  "type": "Feature",
  "properties": {
    "gn:admin1_code": "4.0",
    "gn:asciiname": "Jinqiao",
    "gn:country_code": "CN",
    "gn:dem": 24,
    "gn:feature_class": "P",
    "gn:feature_code": "PPL",
    "gn:name": "Jinqiao",
    "gn:population": 0,
    "gn:timezone": "Asia/Shanghai",
    "iso:country": "CN",
    "name:zho_x_preferred": [
      "金桥"
    ],
    "name:zho_x_variant": [
      "金桥镇"
    ],
    "wof:name": "Jinqiao",
    "wof:placetype": "locality"
  },
  "geometry": {
    "coordinates": [
      117.86871,
      33.8833
    ],
    "type": "Point"
  }
}