{
  "type": "Feature",
  "properties": {
    "gn:admin1_code": "10.0",
    "gn:asciiname": "Dongzhuang",
    "gn:country_code": "CN",
    "gn:dem": 19,
    "gn:feature_class": "P",
    "gn:feature_code": "PPL",
    "gn:name": "Dongzhuang",
    "gn:population": 0,
    "gn:timezone": "Asia/Shanghai",
    "iso:country": "CN",
    "name:zho_x_preferred": [
      "东壮"
    ],
    "wof:name": "Dongzhuang",
    "wof:placetype": "locality"
  },
  "geometry": {
    "coordinates": [
      116.53794,
      39.34924
    ],
    "type": "Point"
  }
}