{
  "type": "Feature",
  "properties": {
    "gn:admin1_code": "1.0",
    "gn:asciiname": "Chakou",
    "gn:country_code": "CN",
    "gn:dem": 201,
    "gn:feature_class": "P",
    "gn:feature_code": "PPL",
    "gn:name": "Chakou",
    "gn:population": 0,
    "gn:timezone": "Asia/Shanghai",
    "iso:country": "CN",
    "name:zho_x_preferred": [
      "汊口"
    ],
    "wof:name": "Chakou",
    "wof:placetype": "locality"
  },
  "geometry": {
    "coordinates": [
      118.4049,
      29.64247
    ],
    "type": "Point"
  }
}