{
  "type": "Feature",
  "properties": {
    "gn:admin1_code": "31.0",
    "gn:asciiname": "Shitong",
    "gn:country_code": "CN",
    "gn:dem": 59,
    "gn:feature_class": "P",
    "gn:feature_code": "PPL",
    "gn:name": "Shitong",
    "gn:population": 0,
    "gn:timezone": "Asia/Shanghai",
    "iso:country": "CN",
    "name:und_x_variant": [
      "石峝"
    ],
    "name:vie_x_preferred": [
      "Sử thông"
    ],
    "wof:name": "Shitong",
    "wof:placetype": "locality"
  },
  "geometry": {
    "coordinates": [
      109.7623,
      18.62774
    ],
    "type": "Point"
  }
}