{
  "type": "Feature",
  "properties": {
    "gn:admin1_code": "20.0",
    "gn:asciiname": "Xigaowan",
    "gn:country_code": "CN",
    "gn:dem": 1823,
    "gn:feature_class": "P",
    "gn:feature_code": "PPL",
    "gn:name": "Xigaowan",
    "gn:population": 0,
    "gn:timezone": "Asia/Shanghai",
    "iso:country": "CN",
    "name:und_x_variant": [
      "西高湾"
    ],
    "wof:name": "Xigaowan",
    "wof:placetype": "locality"
  },
  "geometry": {
    "coordinates": [
      110.6883,
      41.2291
    ],
    "type": "Point"
  }
}