{
  "type": "Feature",
  "properties": {
    "gn:admin1_code": "02",
    "gn:asciiname": "Fanzhoucun",
    "gn:country_code": "CN",
    "gn:dem": 6,
    "gn:feature_class": "P",
    "gn:feature_code": "PPL",
    "gn:name": "Fanzhoucun",
    "gn:population": 0,
    "gn:timezone": "Asia/Shanghai",
    "iso:country": "CN",
    "name:und_x_variant": [
      "Fanzhou",
      "畈周",
      "Fan-chou-ts’un",
      "Fanzhoucun"
    ],
    "name:zho_x_preferred": [
      "畈周村"
    ],
    "wof:name": "Fanzhoucun",
    "wof:placetype": "locality"
  },
  "geometry": {
    "coordinates": [
      121.12189,
      30.07428
    ],
    "type": "Point"
  }
}