{
  "type": "Feature",
  "properties": {
    "gn:admin1_code": "18.0",
    "gn:asciiname": "Hua'ao",
    "gn:country_code": "CN",
    "gn:dem": 789,
    "gn:feature_class": "P",
    "gn:feature_code": "PPL",
    "gn:name": "Hua’ao",
    "gn:population": 0,
    "gn:timezone": "Asia/Shanghai",
    "iso:country": "CN",
    "name:und_x_variant": [
      "Hua’ao"
    ],
    "name:zho_x_preferred": [
      "化敖"
    ],
    "wof:name": "Hua'ao",
    "wof:placetype": "locality"
  },
  "geometry": {
    "coordinates": [
      108.877,
      26.6897
    ],
    "type": "Point"
  }
}