{
  "type": "Feature",
  "properties": {
    "gn:admin1_code": "30",
    "gn:asciiname": "Shijing",
    "gn:country_code": "CN",
    "gn:dem": 36,
    "gn:feature_class": "P",
    "gn:feature_code": "PPLA4",
    "gn:name": "Shijing",
    "gn:population": 0,
    "gn:timezone": "Asia/Urumqi",
    "iso:country": "CN",
    "name:und_x_variant": [
      "Shijing Zhen",
      "石颈镇"
    ],
    "name:zho_x_preferred": [
      "石颈"
    ],
    "wof:name": "Shijing",
    "wof:placetype": "locality"
  },
  "geometry": {
    "coordinates": [
      110.0233,
      21.69851
    ],
    "type": "Point"
  }
}