{
  "type": "Feature",
  "properties": {
    "gn:admin1_code": "06",
    "gn:asciiname": "Zhenqin",
    "gn:country_code": "CN",
    "gn:dem": 4271,
    "gn:feature_class": "P",
    "gn:feature_code": "PPL",
    "gn:name": "Zhenqin",
    "gn:population": 0,
    "gn:timezone": "Asia/Urumqi",
    "iso:country": "CN",
    "name:bod_x_preferred": [
      "སྒྲུབ་བརྒྱུད་དགོན"
    ],
    "name:und_x_variant": [
      "Zhubgyügoin"
    ],
    "name:zho_x_preferred": [
      "珍秦"
    ],
    "wof:name": "Zhenqin",
    "wof:placetype": "locality"
  },
  "geometry": {
    "coordinates": [
      97.29784,
      33.41504
    ],
    "type": "Point"
  }
}