{
  "type": "Feature",
  "properties": {
    "gn:admin1_code": "30.0",
    "gn:asciiname": "Hudi",
    "gn:country_code": "CN",
    "gn:dem": 5,
    "gn:feature_class": "P",
    "gn:feature_code": "PPL",
    "gn:name": "Hudi",
    "gn:population": 0,
    "gn:timezone": "Asia/Shanghai",
    "iso:country": "CN",
    "name:fas_x_preferred": [
      "هودی"
    ],
    "name:msa_x_preferred": [
      "Hudi"
    ],
    "name:ukr_x_preferred": [
      "Худі"
    ],
    "name:ukr_x_variant": [
      "Гуді"
    ],
    "name:urd_x_preferred": [
      "ہودی"
    ],
    "name:vie_x_preferred": [
      "Sông Hudi"
    ],
    "name:zho_cn_x_preferred": [
      "胡迪河"
    ],
    "name:zho_tw_x_preferred": [
      "胡第河"
    ],
    "name:zho_x_preferred": [
      "笏底"
    ],
    "wof:name": "Hudi",
    "wof:placetype": "locality"
  },
  "geometry": {
    "coordinates": [
      115.59816,
      22.92671
    ],
    "type": "Point"
  }
}