{
  "type": "Feature",
  "properties": {
    "gn:admin1_code": "15.0",
    "gn:asciiname": "Xiaofang",
    "gn:country_code": "CN",
    "gn:dem": 1489,
    "gn:feature_class": "P",
    "gn:feature_code": "PPL",
    "gn:name": "Xiaofang",
    "gn:population": 0,
    "gn:timezone": "Asia/Shanghai",
    "iso:country": "CN",
    "name:zho_x_preferred": [
      "小方"
    ],
    "wof:name": "Xiaofang",
    "wof:placetype": "locality"
  },
  "geometry": {
    "coordinates": [
      107.29398,
      35.9991
    ],
    "type": "Point"
  }
}