{
  "type": "Feature",
  "properties": {
    "gn:admin1_code": "25",
    "gn:asciiname": "Baishan",
    "gn:country_code": "CN",
    "gn:dem": 44,
    "gn:feature_class": "P",
    "gn:feature_code": "PPL",
    "gn:name": "Baishan",
    "gn:population": 0,
    "gn:timezone": "Asia/Shanghai",
    "iso:country": "CN",
    "name:ara_x_preferred": [
      "بايشان"
    ],
    "name:ast_x_preferred": [
      "Baishan"
    ],
    "name:cdo_x_preferred": [
      "Băh-săng"
    ],
    "name:ceb_x_preferred": [
      "Baishan"
    ],
    "name:ces_x_preferred": [
      "Paj-šan"
    ],
    "name:dan_x_preferred": [
      "Baishan"
    ],
    "name:deu_x_preferred": [
      "Baishan"
    ],
    "name:eus_x_preferred": [
      "Baishan"
    ],
    "name:fas_x_preferred": [
      "بایشان"
    ],
    "name:fin_x_preferred": [
      "Baishan"
    ],
    "name:fra_x_preferred": [
      "Baishan"
    ],
    "name:heb_x_preferred": [
      "באיישאן"
    ],
    "name:hun_x_preferred": [
      "Baishan"
    ],
    "name:ind_x_preferred": [
      "Baishan"
    ],
    "name:ita_x_preferred": [
      "Baishan"
    ],
    "name:jpn_x_preferred": [
      "白山市"
    ],
    "name:kik_x_preferred": [
      "Baishan"
    ],
    "name:kor_x_preferred": [
      "바이산시"
    ],
    "name:mlg_x_preferred": [
      "Baishan"
    ],
    "name:nld_x_preferred": [
      "Baishan"
    ],
    "name:nno_x_preferred": [
      "Baishan"
    ],
    "name:nor_x_preferred": [
      "Baishan"
    ],
    "name:pol_x_preferred": [
      "Baishan"
    ],
    "name:por_x_preferred": [
      "Baishan"
    ],
    "name:rus_x_preferred": [
      "Байшань"
    ],
    "name:spa_x_preferred": [
      "Baishán"
    ],
    "name:swe_x_preferred": [
      "Baishan"
    ],
    "name:tur_x_preferred": [
      "Baishan"
    ],
    "name:urd_x_preferred": [
      "بائشان"
    ],
    "name:vie_x_preferred": [
      "Bạch Sơn"
    ],
    "name:war_x_preferred": [
      "Baishan"
    ],
    "name:wuu_x_preferred": [
      "白山市"
    ],
    "name:zho_x_preferred": [
      "白山市"
    ],
    "wof:name": "Baishan",
    "wof:placetype": "locality"
  },
  "geometry": {
    "coordinates": [
      116.71917,
      35.11194
    ],
    "type": "Point"
  }
}