{
  "type": "Feature",
  "properties": {
    "gn:admin1_code": "3",
    "gn:asciiname": "Changxi",
    "gn:country_code": "CN",
    "gn:dem": 220,
    "gn:feature_class": "P",
    "gn:feature_code": "PPL",
    "gn:name": "Changxi",
    "gn:population": 0,
    "gn:timezone": "Asia/Shanghai",
    "iso:country": "CN",
    "name:dan_x_preferred": [
      "Changxi"
    ],
    "name:fas_x_preferred": [
      "چانگ‌شی"
    ],
    "name:hun_x_preferred": [
      "Csang-hszi"
    ],
    "name:swe_x_preferred": [
      "Chang Xi"
    ],
    "name:zho_x_preferred": [
      "长溪"
    ],
    "wof:name": "Changxi",
    "wof:placetype": "locality"
  },
  "geometry": {
    "coordinates": [
      114.028,
      26.7473
    ],
    "type": "Point"
  }
}