{
  "type": "Feature",
  "properties": {
    "gn:admin1_code": "8.0",
    "gn:asciiname": "Qinglongshan Shiyidui",
    "gn:country_code": "CN",
    "gn:dem": 58,
    "gn:feature_class": "P",
    "gn:feature_code": "PPLF",
    "gn:name": "Qinglongshan Shiyidui",
    "gn:population": 0,
    "gn:timezone": "Asia/Shanghai",
    "iso:country": "CN",
    "name:zho_x_preferred": [
      "青龙山十一队"
    ],
    "wof:name": "Qinglongshan Shiyidui",
    "wof:placetype": "locality"
  },
  "geometry": {
    "coordinates": [
      132.97066999999998,
      47.75401
    ],
    "type": "Point"
  }
}