{
  "type": "Feature",
  "properties": {
    "gn:admin1_code": "25.0",
    "gn:asciiname": "Menjiabu",
    "gn:country_code": "CN",
    "gn:dem": 30,
    "gn:feature_class": "P",
    "gn:feature_code": "PPL",
    "gn:name": "Menjiabu",
    "gn:population": 0,
    "gn:timezone": "Asia/Shanghai",
    "iso:country": "CN",
    "name:zho_x_preferred": [
      "门家埠"
    ],
    "wof:name": "Menjiabu",
    "wof:placetype": "locality"
  },
  "geometry": {
    "coordinates": [
      119.812,
      36.29751
    ],
    "type": "Point"
  }
}