{
  "type": "Feature",
  "properties": {
    "gn:admin1_code": "7.0",
    "gn:asciiname": "Longxing",
    "gn:country_code": "CN",
    "gn:dem": 81,
    "gn:feature_class": "P",
    "gn:feature_code": "PPL",
    "gn:name": "Longxing",
    "gn:population": 0,
    "gn:timezone": "Asia/Shanghai",
    "iso:country": "CN",
    "name:deu_x_preferred": [
      "Longxing"
    ],
    "name:zho_x_preferred": [
      "龙兴"
    ],
    "wof:name": "Longxing",
    "wof:placetype": "locality"
  },
  "geometry": {
    "coordinates": [
      118.7269,
      25.32479
    ],
    "type": "Point"
  }
}