{
  "type": "Feature",
  "properties": {
    "gn:admin1_code": "32.0",
    "gn:asciiname": "Hongyanding",
    "gn:country_code": "CN",
    "gn:dem": 652,
    "gn:feature_class": "P",
    "gn:feature_code": "PPL",
    "gn:name": "Hongyanding",
    "gn:population": 0,
    "gn:timezone": "Asia/Shanghai",
    "iso:country": "CN",
    "name:zho_x_preferred": [
      "红岩顶"
    ],
    "wof:name": "Hongyanding",
    "wof:placetype": "locality"
  },
  "geometry": {
    "coordinates": [
      104.32215,
      28.72638
    ],
    "type": "Point"
  }
}