{
  "type": "Feature",
  "properties": {
    "gn:admin1_code": "10.0",
    "gn:asciiname": "Xiaozhu Hugou",
    "gn:country_code": "CN",
    "gn:dem": 649,
    "gn:feature_class": "P",
    "gn:feature_code": "PPL",
    "gn:name": "Xiaozhu Hugou",
    "gn:population": 0,
    "gn:timezone": "Asia/Shanghai",
    "iso:country": "CN",
    "name:zho_x_preferred": [
      "小朱湖沟"
    ],
    "wof:name": "Xiaozhu Hugou",
    "wof:placetype": "locality"
  },
  "geometry": {
    "coordinates": [
      117.60266,
      40.43733
    ],
    "type": "Point"
  }
}