{
  "type": "Feature",
  "properties": {
    "gn:admin1_code": "12.0",
    "gn:asciiname": "Gujiagou",
    "gn:country_code": "CN",
    "gn:dem": 21,
    "gn:feature_class": "P",
    "gn:feature_code": "PPL",
    "gn:name": "Gujiagou",
    "gn:population": 0,
    "gn:timezone": "Asia/Shanghai",
    "iso:country": "CN",
    "name:und_x_variant": [
      "股家沟"
    ],
    "wof:name": "Gujiagou",
    "wof:placetype": "locality"
  },
  "geometry": {
    "coordinates": [
      114.6971,
      30.38529
    ],
    "type": "Point"
  }
}