{
  "type": "Feature",
  "properties": {
    "gn:admin1_code": "16",
    "gn:asciiname": "Leidaping",
    "gn:country_code": "CN",
    "gn:dem": 664,
    "gn:feature_class": "P",
    "gn:feature_code": "PPL",
    "gn:name": "Leidaping",
    "gn:population": 0,
    "gn:timezone": "Asia/Shanghai",
    "iso:country": "CN",
    "name:zho_x_preferred": [
      "雷打坪"
    ],
    "wof:name": "Leidaping",
    "wof:placetype": "locality"
  },
  "geometry": {
    "coordinates": [
      110.913,
      25.6183
    ],
    "type": "Point"
  }
}