{
  "type": "Feature",
  "properties": {
    "gn:admin1_code": "16.0",
    "gn:asciiname": "Liuqin",
    "gn:country_code": "CN",
    "gn:dem": 678,
    "gn:feature_class": "P",
    "gn:feature_code": "PPL",
    "gn:name": "Liuqin",
    "gn:population": 0,
    "gn:timezone": "Asia/Shanghai",
    "iso:country": "CN",
    "name:ara_x_preferred": [
      "ليو تشين"
    ],
    "name:deu_x_preferred": [
      "Liuqin"
    ],
    "name:epo_x_preferred": [
      "Liuĉino"
    ],
    "name:fra_x_preferred": [
      "Liuqin"
    ],
    "name:spa_x_preferred": [
      "Liuqin"
    ],
    "name:tam_x_preferred": [
      "லியுசின்"
    ],
    "name:zho_x_preferred": [
      "六勤"
    ],
    "wof:name": "Liuqin",
    "wof:placetype": "locality"
  },
  "geometry": {
    "coordinates": [
      106.877,
      24.1589
    ],
    "type": "Point"
  }
}