{
  "type": "Feature",
  "properties": {
    "gn:admin1_code": "19.0",
    "gn:asciiname": "Zhanggangzi",
    "gn:country_code": "CN",
    "gn:dem": 24,
    "gn:feature_class": "P",
    "gn:feature_code": "PPL",
    "gn:name": "Zhanggangzi",
    "gn:population": 0,
    "gn:timezone": "Asia/Shanghai",
    "iso:country": "CN",
    "name:zho_x_preferred": [
      "张岗子"
    ],
    "wof:name": "Zhanggangzi",
    "wof:placetype": "locality"
  },
  "geometry": {
    "coordinates": [
      122.29932,
      41.78649
    ],
    "type": "Point"
  }
}