{
  "type": "Feature",
  "properties": {
    "gn:admin1_code": "16.0",
    "gn:asciiname": "Zhengdu",
    "gn:country_code": "CN",
    "gn:dem": 480,
    "gn:feature_class": "P",
    "gn:feature_code": "PPL",
    "gn:name": "Zhengdu",
    "gn:population": 0,
    "gn:timezone": "Asia/Shanghai",
    "iso:country": "CN",
    "name:zho_x_preferred": [
      "整堵"
    ],
    "wof:name": "Zhengdu",
    "wof:placetype": "locality"
  },
  "geometry": {
    "coordinates": [
      109.106,
      25.3894
    ],
    "type": "Point"
  }
}