{
  "type": "Feature",
  "properties": {
    "gn:admin1_code": "13.0",
    "gn:asciiname": "Baozileke",
    "gn:country_code": "CN",
    "gn:dem": 2172,
    "gn:feature_class": "P",
    "gn:feature_code": "PPL",
    "gn:name": "Baozileke",
    "gn:population": 0,
    "gn:timezone": "Asia/Shanghai",
    "iso:country": "CN",
    "name:und_x_variant": [
      "Baozi Leke"
    ],
    "name:zho_x_preferred": [
      "保孜勒克"
    ],
    "wof:name": "Baozileke",
    "wof:placetype": "locality"
  },
  "geometry": {
    "coordinates": [
      81.73056,
      36.37691
    ],
    "type": "Point"
  }
}