{
  "type": "Feature",
  "properties": {
    "gn:admin1_code": "24.0",
    "gn:asciiname": "Yangquan",
    "gn:country_code": "CN",
    "gn:dem": 1497,
    "gn:feature_class": "P",
    "gn:feature_code": "PPL",
    "gn:name": "Yangquan",
    "gn:population": 0,
    "gn:timezone": "Asia/Shanghai",
    "iso:country": "CN",
    "name:ara_x_preferred": [
      "يانغتشوان"
    ],
    "name:cdo_x_preferred": [
      "Iòng-ciòng"
    ],
    "name:ceb_x_preferred": [
      "Yangquan"
    ],
    "name:ces_x_preferred": [
      "Jang-čchüan"
    ],
    "name:dan_x_preferred": [
      "Yangquan"
    ],
    "name:deu_x_preferred": [
      "Yangquan"
    ],
    "name:epo_x_preferred": [
      "Jancjuan"
    ],
    "name:eus_x_preferred": [
      "Yangquan"
    ],
    "name:fas_x_preferred": [
      "یانگکوان"
    ],
    "name:fin_x_preferred": [
      "Yangquan"
    ],
    "name:fra_x_preferred": [
      "Yangquan"
    ],
    "name:ita_x_preferred": [
      "Yangquan"
    ],
    "name:jpn_x_preferred": [
      "陽泉"
    ],
    "name:jpn_x_variant": [
      "陽泉市"
    ],
    "name:kik_x_preferred": [
      "Yangquan"
    ],
    "name:kor_x_preferred": [
      "양취안시"
    ],
    "name:mlg_x_preferred": [
      "Yangquan"
    ],
    "name:nld_x_preferred": [
      "Yangquan"
    ],
    "name:nno_x_preferred": [
      "Yangquan"
    ],
    "name:nor_x_preferred": [
      "Yangquan"
    ],
    "name:pol_x_preferred": [
      "Yangquan"
    ],
    "name:por_x_preferred": [
      "Yangquan"
    ],
    "name:rus_x_preferred": [
      "Янцюань"
    ],
    "name:spa_x_preferred": [
      "Yangquan"
    ],
    "name:srp_x_preferred": [
      "Јангћуен"
    ],
    "name:swe_x_preferred": [
      "Yangquan"
    ],
    "name:tur_x_preferred": [
      "Yangquan"
    ],
    "name:urd_x_preferred": [
      "یانگچوان"
    ],
    "name:vie_x_preferred": [
      "Dương Tuyền"
    ],
    "name:war_x_preferred": [
      "Yangquan"
    ],
    "name:wuu_x_preferred": [
      "阳泉市"
    ],
    "name:zho_x_preferred": [
      "羊圈"
    ],
    "name:zho_x_variant": [
      "阳泉市"
    ],
    "wof:name": "Yangquan",
    "wof:placetype": "locality"
  },
  "geometry": {
    "coordinates": [
      113.70346,
      39.39271
    ],
    "type": "Point"
  }
}