{
  "type": "Feature",
  "properties": {
    "gn:admin1_code": "15.0",
    "gn:asciiname": "Heiniuyinwo",
    "gn:country_code": "CN",
    "gn:dem": 1207,
    "gn:feature_class": "P",
    "gn:feature_code": "PPL",
    "gn:name": "Heiniuyinwo",
    "gn:population": 0,
    "gn:timezone": "Asia/Shanghai",
    "iso:country": "CN",
    "name:und_x_variant": [
      "黑牛阴窝"
    ],
    "wof:name": "Heiniuyinwo",
    "wof:placetype": "locality"
  },
  "geometry": {
    "coordinates": [
      105.54807,
      33.44746
    ],
    "type": "Point"
  }
}