{
  "type": "Feature",
  "properties": {
    "gn:admin1_code": "13.0",
    "gn:asciiname": "Yengimahalla",
    "gn:country_code": "CN",
    "gn:dem": 923,
    "gn:feature_class": "P",
    "gn:feature_code": "PPL",
    "gn:name": "Yengimahalla",
    "gn:population": 0,
    "gn:timezone": "Asia/Urumqi",
    "iso:country": "CN",
    "name:uig_x_preferred": [
      "Yengiməh̨əllə"
    ],
    "name:uig_x_variant": [
      "Yéngimehelle",
      "يېڭىمەھەللە",
      "Еңимәһәллә"
    ],
    "wof:name": "Yengimahalla",
    "wof:placetype": "locality"
  },
  "geometry": {
    "coordinates": [
      84.68333,
      41.21667
    ],
    "type": "Point"
  }
}