{
  "type": "Feature",
  "properties": {
    "gn:admin1_code": "31.0",
    "gn:asciiname": "Xinxing Liuqu Wudui",
    "gn:country_code": "CN",
    "gn:dem": 108,
    "gn:feature_class": "P",
    "gn:feature_code": "PPLF",
    "gn:name": "Xinxing Liuqu Wudui",
    "gn:population": 0,
    "gn:timezone": "Asia/Shanghai",
    "iso:country": "CN",
    "name:und_x_variant": [
      "新星六区五队"
    ],
    "wof:name": "Xinxing Liuqu Wudui",
    "wof:placetype": "locality"
  },
  "geometry": {
    "coordinates": [
      109.66509,
      18.6958
    ],
    "type": "Point"
  }
}