{
  "type": "Feature",
  "properties": {
    "gn:admin1_code": "30",
    "gn:asciiname": "Cangcheng",
    "gn:country_code": "CN",
    "gn:dem": 11,
    "gn:feature_class": "P",
    "gn:feature_code": "PPLA4",
    "gn:name": "Cangcheng",
    "gn:population": 0,
    "gn:timezone": "Asia/Shanghai",
    "iso:country": "CN",
    "name:und_x_variant": [
      "K’ai-p’ing-hsien",
      "Chiu-k’ai-p’ing",
      "Ts’ang-ch’eng",
      "Hoiping",
      "K’ai-p’ing",
      "Hoiping-hsien",
      "Cangcheng",
      "Cangcheng Zhen",
      "苍城镇"
    ],
    "name:zho_x_preferred": [
      "苍城"
    ],
    "wof:name": "Cangcheng",
    "wof:placetype": "locality"
  },
  "geometry": {
    "coordinates": [
      112.5481,
      22.47805
    ],
    "type": "Point"
  }
}