{
  "type": "Feature",
  "properties": {
    "gn:admin1_code": "14.0",
    "gn:asciiname": "Zaxoi",
    "gn:country_code": "CN",
    "gn:dem": 3926,
    "gn:feature_class": "P",
    "gn:feature_code": "PPL",
    "gn:name": "Zaxoi",
    "gn:population": 0,
    "gn:timezone": "Asia/Urumqi",
    "iso:country": "CN",
    "name:bod_x_preferred": [
      "རྩ་ཞོལ"
    ],
    "name:msa_x_preferred": [
      "Zaxoi"
    ],
    "name:und_x_variant": [
      "Zhaxue"
    ],
    "name:zho_x_preferred": [
      "扎雪"
    ],
    "name:zho_x_variant": [
      "扎雪乡"
    ],
    "wof:name": "Zaxoi",
    "wof:placetype": "locality"
  },
  "geometry": {
    "coordinates": [
      91.81804,
      30.04755
    ],
    "type": "Point"
  }
}