{
  "type": "Feature",
  "properties": {
    "gn:admin1_code": "11",
    "gn:asciiname": "Reshi",
    "gn:country_code": "CN",
    "gn:dem": 94,
    "gn:feature_class": "P",
    "gn:feature_code": "PPLA4",
    "gn:name": "Reshi",
    "gn:population": 0,
    "gn:timezone": "Asia/Shanghai",
    "iso:country": "CN",
    "name:und_x_variant": [
      "Je-Shih",
      "Reshi",
      "热市",
      "Reshuikeng",
      "Reshi Zhen",
      "热市镇",
      "热水坑"
    ],
    "wof:name": "Reshi",
    "wof:placetype": "locality"
  },
  "geometry": {
    "coordinates": [
      111.32248,
      29.32137
    ],
    "type": "Point"
  }
}