{
  "type": "Feature",
  "properties": {
    "gn:admin1_code": "29.0",
    "gn:asciiname": "Shuangxiang",
    "gn:country_code": "CN",
    "gn:dem": 931,
    "gn:feature_class": "P",
    "gn:feature_code": "PPL",
    "gn:name": "Shuangxiang",
    "gn:population": 0,
    "gn:timezone": "Asia/Shanghai",
    "iso:country": "CN",
    "name:zho_x_preferred": [
      "双相"
    ],
    "wof:name": "Shuangxiang",
    "wof:placetype": "locality"
  },
  "geometry": {
    "coordinates": [
      99.2162,
      22.1526
    ],
    "type": "Point"
  }
}