{
  "type": "Feature",
  "properties": {
    "gn:admin1_code": "11.0",
    "gn:asciiname": "Huangjia",
    "gn:country_code": "CN",
    "gn:dem": 80,
    "gn:feature_class": "P",
    "gn:feature_code": "PPL",
    "gn:name": "Huangjia",
    "gn:population": 0,
    "gn:timezone": "Asia/Shanghai",
    "iso:country": "CN",
    "name:zho_x_preferred": [
      "黄家"
    ],
    "wof:name": "Huangjia",
    "wof:placetype": "locality"
  },
  "geometry": {
    "coordinates": [
      112.57602,
      26.3857
    ],
    "type": "Point"
  }
}