{
  "type": "Feature",
  "properties": {
    "gn:admin1_code": "3",
    "gn:asciiname": "Tushi",
    "gn:country_code": "CN",
    "gn:dem": 134,
    "gn:feature_class": "P",
    "gn:feature_code": "PPL",
    "gn:name": "Tushi",
    "gn:population": 0,
    "gn:timezone": "Asia/Shanghai",
    "iso:country": "CN",
    "name:ceb_x_preferred": [
      "Tūshī"
    ],
    "name:fas_x_preferred": [
      "توشی"
    ],
    "name:msa_x_preferred": [
      "Tushi"
    ],
    "name:swe_x_preferred": [
      "Tūshī"
    ],
    "name:ukr_x_preferred": [
      "Туші"
    ],
    "name:zho_x_preferred": [
      "土石"
    ],
    "wof:name": "Tushi",
    "wof:placetype": "locality"
  },
  "geometry": {
    "coordinates": [
      114.64205,
      25.78014
    ],
    "type": "Point"
  }
}