{
  "type": "Feature",
  "properties": {
    "gn:admin1_code": "16.0",
    "gn:asciiname": "Naning",
    "gn:country_code": "CN",
    "gn:dem": 199,
    "gn:feature_class": "P",
    "gn:feature_code": "PPL",
    "gn:name": "Naning",
    "gn:population": 0,
    "gn:timezone": "Asia/Shanghai",
    "iso:country": "CN",
    "name:cat_x_preferred": [
      "Naning"
    ],
    "name:msa_x_preferred": [
      "Naning"
    ],
    "name:zho_x_preferred": [
      "那宁"
    ],
    "wof:name": "Naning",
    "wof:placetype": "locality"
  },
  "geometry": {
    "coordinates": [
      106.334,
      24.0658
    ],
    "type": "Point"
  }
}