{
  "type": "Feature",
  "properties": {
    "gn:admin1_code": "18.0",
    "gn:asciiname": "Shuangyan",
    "gn:country_code": "CN",
    "gn:dem": 1249,
    "gn:feature_class": "P",
    "gn:feature_code": "PPL",
    "gn:name": "Shuangyan",
    "gn:population": 0,
    "gn:timezone": "Asia/Shanghai",
    "iso:country": "CN",
    "name:zho_x_preferred": [
      "双岩"
    ],
    "wof:name": "Shuangyan",
    "wof:placetype": "locality"
  },
  "geometry": {
    "coordinates": [
      107.272,
      26.6096
    ],
    "type": "Point"
  }
}