{
  "type": "Feature",
  "properties": {
    "gn:admin1_code": "9.0",
    "gn:asciiname": "Shanding",
    "gn:country_code": "CN",
    "gn:dem": 487,
    "gn:feature_class": "P",
    "gn:feature_code": "PPL",
    "gn:name": "Shanding",
    "gn:population": 0,
    "gn:timezone": "Asia/Shanghai",
    "iso:country": "CN",
    "name:zho_x_preferred": [
      "山顶"
    ],
    "wof:name": "Shanding",
    "wof:placetype": "locality"
  },
  "geometry": {
    "coordinates": [
      113.41156,
      34.58828
    ],
    "type": "Point"
  }
}