{
  "type": "Feature",
  "properties": {
    "gn:admin1_code": "11.0",
    "gn:asciiname": "Nanyue",
    "gn:country_code": "CN",
    "gn:dem": 68,
    "gn:feature_class": "P",
    "gn:feature_code": "PPL",
    "gn:name": "Nanyue",
    "gn:population": 0,
    "gn:timezone": "Asia/Shanghai",
    "iso:country": "CN",
    "name:als_x_preferred": [
      "Nan-Yue"
    ],
    "name:ara_x_preferred": [
      "نانياو"
    ],
    "name:ast_x_preferred": [
      "Nanyue"
    ],
    "name:cat_x_preferred": [
      "Nanyue"
    ],
    "name:cdo_x_preferred": [
      "Nàng-uŏk-guók"
    ],
    "name:ces_x_preferred": [
      "Nan-jüe"
    ],
    "name:dan_x_preferred": [
      "Nanyue"
    ],
    "name:deu_x_preferred": [
      "Nan-Yue"
    ],
    "name:epo_x_preferred": [
      "Nanjueo"
    ],
    "name:eus_x_preferred": [
      "Nanyue"
    ],
    "name:fin_x_preferred": [
      "Nam Việt"
    ],
    "name:fra_x_preferred": [
      "Nanyue"
    ],
    "name:hak_x_preferred": [
      "Nàm-ye̍t-koet"
    ],
    "name:ind_x_preferred": [
      "Nanyue"
    ],
    "name:ita_x_preferred": [
      "Nanyue"
    ],
    "name:jpn_x_preferred": [
      "南越国"
    ],
    "name:nor_x_preferred": [
      "Nanyue"
    ],
    "name:pol_x_preferred": [
      "Nanyue"
    ],
    "name:por_x_preferred": [
      "Nanyue"
    ],
    "name:rus_x_preferred": [
      "Намвьет"
    ],
    "name:sco_x_preferred": [
      "Nanyue"
    ],
    "name:spa_x_preferred": [
      "Nanyue"
    ],
    "name:swe_x_preferred": [
      "Nanyue"
    ],
    "name:tha_x_preferred": [
      "หนานเยฺว่"
    ],
    "name:ukr_x_preferred": [
      "Намв'єт"
    ],
    "name:vie_x_preferred": [
      "Nam Việt"
    ],
    "name:wuu_x_preferred": [
      "南越国"
    ],
    "name:zha_x_preferred": [
      "Namzyied"
    ],
    "name:zho_x_preferred": [
      "南岳"
    ],
    "name:zho_x_variant": [
      "南越国"
    ],
    "wof:name": "Nanyue",
    "wof:placetype": "locality"
  },
  "geometry": {
    "coordinates": [
      112.88259,
      26.70741
    ],
    "type": "Point"
  }
}