{
  "type": "Feature",
  "properties": {
    "gn:admin1_code": "2.0",
    "gn:asciiname": "Waimaoyang",
    "gn:country_code": "CN",
    "gn:dem": 172,
    "gn:feature_class": "P",
    "gn:feature_code": "PPL",
    "gn:name": "Waimaoyang",
    "gn:population": 0,
    "gn:timezone": "Asia/Shanghai",
    "iso:country": "CN",
    "name:zho_x_preferred": [
      "外毛洋"
    ],
    "wof:name": "Waimaoyang",
    "wof:placetype": "locality"
  },
  "geometry": {
    "coordinates": [
      120.79276000000002,
      29.46535
    ],
    "type": "Point"
  }
}