{
  "type": "Feature",
  "properties": {
    "gn:country": "CN",
    "gn:fcode": "PPL",
    "gn:population": 89107,
    "iso:country": "CN",
    "name:ceb_x_preferred": [
      "Hede"
    ],
    "name:deu_x_preferred": [
      "Hede"
    ],
    "name:fin_x_preferred": [
      "Hede"
    ],
    "name:nds_x_preferred": [
      "Hede"
    ],
    "name:nld_x_preferred": [
      "Hede"
    ],
    "name:rus_x_preferred": [
      "Хеде"
    ],
    "name:srp_x_preferred": [
      "Хеде"
    ],
    "name:swe_x_preferred": [
      "Hede"
    ],
    "name:und_x_variant": [
      "Sheyang"
    ],
    "name:zho_x_preferred": [
      "合德"
    ],
    "name:zho_x_variant": [
      "射阳"
    ],
    "qs:name": "Hede",
    "qs:name_adm0": "中國",
    "qs:name_adm1": "江苏省",
    "qs:photos_9k": 1,
    "qs:photos_9r": 1,
    "qs:photos_all": 9,
    "qs:photos_sr": 0,
    "qs:placetype": "Town",
    "qs:pop_sr": "8",
    "wd:wordcount": 35,
    "wof:name": "Hede",
    "wof:placetype": "locality",
    "wof:population": 89107
  },
  "geometry": {
    "coordinates": [
      120.25167,
      33.76806
    ],
    "type": "Point"
  }
}