{
  "type": "Feature",
  "properties": {
    "gn:admin1_code": "24",
    "gn:asciiname": "Wangdu",
    "gn:country_code": "CN",
    "gn:dem": 787,
    "gn:feature_class": "P",
    "gn:feature_code": "PPL",
    "gn:name": "Wangdu",
    "gn:population": 0,
    "gn:timezone": "Asia/Shanghai",
    "iso:country": "CN",
    "name:und_x_variant": [
      "Wang-tu",
      "Wangdu"
    ],
    "name:zho_x_preferred": [
      "王都"
    ],
    "wof:name": "Wangdu",
    "wof:placetype": "locality"
  },
  "geometry": {
    "coordinates": [
      112.64884,
      37.58105
    ],
    "type": "Point"
  }
}