{
  "type": "Feature",
  "properties": {
    "gn:admin1_code": "19.0",
    "gn:asciiname": "Guanjia",
    "gn:country_code": "CN",
    "gn:dem": 23,
    "gn:feature_class": "P",
    "gn:feature_code": "PPL",
    "gn:name": "Guanjia",
    "gn:population": 0,
    "gn:timezone": "Asia/Shanghai",
    "iso:country": "CN",
    "name:zho_x_preferred": [
      "贯家"
    ],
    "wof:name": "Guanjia",
    "wof:placetype": "locality"
  },
  "geometry": {
    "coordinates": [
      122.39723,
      41.77867
    ],
    "type": "Point"
  }
}