{
  "type": "Feature",
  "properties": {
    "gn:admin1_code": "24",
    "gn:asciiname": "Nancha",
    "gn:country_code": "CN",
    "gn:dem": 1517,
    "gn:feature_class": "P",
    "gn:feature_code": "PPL",
    "gn:name": "Nancha",
    "gn:population": 0,
    "gn:timezone": "Asia/Shanghai",
    "iso:country": "CN",
    "name:ara_x_preferred": [
      "نانشا"
    ],
    "name:ben_x_preferred": [
      "নানচা"
    ],
    "name:ell_x_preferred": [
      "Νάντσα"
    ],
    "name:fas_x_preferred": [
      "نانچا"
    ],
    "name:fra_x_preferred": [
      "Nancha"
    ],
    "name:heb_x_preferred": [
      "ננצ'ה"
    ],
    "name:hin_x_preferred": [
      "नांचा"
    ],
    "name:hun_x_preferred": [
      "Nancha"
    ],
    "name:ind_x_preferred": [
      "Nancha"
    ],
    "name:ita_x_preferred": [
      "Nancha"
    ],
    "name:jpn_x_preferred": [
      "南岔"
    ],
    "name:kor_x_preferred": [
      "난차"
    ],
    "name:nld_x_preferred": [
      "Nancha"
    ],
    "name:pol_x_preferred": [
      "Nancha"
    ],
    "name:por_x_preferred": [
      "Nancha"
    ],
    "name:rus_x_preferred": [
      "Наньча"
    ],
    "name:spa_x_preferred": [
      "Nancha"
    ],
    "name:tur_x_preferred": [
      "Nancha"
    ],
    "name:ukr_x_preferred": [
      "Наньча"
    ],
    "name:urd_x_preferred": [
      "نانچا"
    ],
    "name:vie_x_preferred": [
      "Nam Xóa"
    ],
    "name:zho_x_preferred": [
      "南岔"
    ],
    "wof:name": "Nancha",
    "wof:placetype": "locality"
  },
  "geometry": {
    "coordinates": [
      111.81663,
      37.92187
    ],
    "type": "Point"
  }
}