{
  "type": "Feature",
  "properties": {
    "gn:admin1_code": "02",
    "gn:asciiname": "Shangtian",
    "gn:country_code": "CN",
    "gn:dem": 23,
    "gn:feature_class": "P",
    "gn:feature_code": "PPLA4",
    "gn:name": "Shangtian",
    "gn:population": 0,
    "gn:timezone": "Asia/Shanghai",
    "iso:country": "CN",
    "name:und_x_variant": [
      "Shang-t’ien-fan",
      "Shang-t’ien-fan-shih",
      "Shangtianfang",
      "Shangtian",
      "Shangtian Zhen"
    ],
    "name:zho_x_preferred": [
      "尚田"
    ],
    "name:zho_x_variant": [
      "尚田镇"
    ],
    "wof:name": "Shangtian",
    "wof:placetype": "locality"
  },
  "geometry": {
    "coordinates": [
      121.405,
      29.6175
    ],
    "type": "Point"
  }
}