{
  "type": "Feature",
  "properties": {
    "gn:admin1_code": "24.0",
    "gn:asciiname": "Qiancun",
    "gn:country_code": "CN",
    "gn:dem": 1013,
    "gn:feature_class": "P",
    "gn:feature_code": "PPL",
    "gn:name": "Qiancun",
    "gn:population": 0,
    "gn:timezone": "Asia/Shanghai",
    "iso:country": "CN",
    "name:und_x_variant": [
      "前村"
    ],
    "wof:name": "Qiancun",
    "wof:placetype": "locality"
  },
  "geometry": {
    "coordinates": [
      113.2228,
      39.91678
    ],
    "type": "Point"
  }
}