{
  "type": "Feature",
  "properties": {
    "gn:admin1_code": "10",
    "gn:asciiname": "Xigoumen",
    "gn:country_code": "CN",
    "gn:dem": 1157,
    "gn:feature_class": "P",
    "gn:feature_code": "PPL",
    "gn:name": "Xigoumen",
    "gn:population": 0,
    "gn:timezone": "Asia/Shanghai",
    "iso:country": "CN",
    "name:zho_x_preferred": [
      "西沟门"
    ],
    "wof:name": "Xigoumen",
    "wof:placetype": "locality"
  },
  "geometry": {
    "coordinates": [
      116.3988,
      41.49882
    ],
    "type": "Point"
  }
}