{
  "type": "Feature",
  "properties": {
    "gn:admin1_code": "11.0",
    "gn:asciiname": "Mituosi",
    "gn:country_code": "CN",
    "gn:dem": 485,
    "gn:feature_class": "P",
    "gn:feature_code": "PPL",
    "gn:name": "Mituosi",
    "gn:population": 0,
    "gn:timezone": "Asia/Shanghai",
    "iso:country": "CN",
    "name:zho_x_preferred": [
      "弥陀寺"
    ],
    "wof:name": "Mituosi",
    "wof:placetype": "locality"
  },
  "geometry": {
    "coordinates": [
      112.72628,
      27.28741
    ],
    "type": "Point"
  }
}