{
  "type": "Feature",
  "properties": {
    "gn:admin1_code": "10",
    "gn:asciiname": "Gaozhuang",
    "gn:country_code": "CN",
    "gn:dem": 412,
    "gn:feature_class": "P",
    "gn:feature_code": "PPL",
    "gn:name": "Gaozhuang",
    "gn:population": 0,
    "gn:timezone": "Asia/Shanghai",
    "iso:country": "CN",
    "name:zho_x_preferred": [
      "高庄"
    ],
    "wof:name": "Gaozhuang",
    "wof:placetype": "locality"
  },
  "geometry": {
    "coordinates": [
      114.12,
      36.9054
    ],
    "type": "Point"
  }
}