{
  "type": "Feature",
  "properties": {
    "gn:admin1_code": "1.0",
    "gn:asciiname": "Dougang",
    "gn:country_code": "CN",
    "gn:dem": 43,
    "gn:feature_class": "P",
    "gn:feature_code": "PPL",
    "gn:name": "Dougang",
    "gn:population": 0,
    "gn:timezone": "Asia/Shanghai",
    "iso:country": "CN",
    "name:zho_x_preferred": [
      "陡岗"
    ],
    "wof:name": "Dougang",
    "wof:placetype": "locality"
  },
  "geometry": {
    "coordinates": [
      116.08821,
      32.08069
    ],
    "type": "Point"
  }
}