{
  "type": "Feature",
  "properties": {
    "gn:admin1_code": "30",
    "gn:asciiname": "Erli",
    "gn:country_code": "CN",
    "gn:dem": 71,
    "gn:feature_class": "P",
    "gn:feature_code": "PPL",
    "gn:name": "Erli",
    "gn:population": 0,
    "gn:timezone": "Asia/Shanghai",
    "iso:country": "CN",
    "name:azb_x_preferred": [
      "ارلی"
    ],
    "name:bel_x_preferred": [
      "Эрлі"
    ],
    "name:bul_x_preferred": [
      "Ерли"
    ],
    "name:cat_x_preferred": [
      "Erli"
    ],
    "name:ceb_x_preferred": [
      "Erli"
    ],
    "name:deu_x_preferred": [
      "Erli"
    ],
    "name:epo_x_preferred": [
      "Erli"
    ],
    "name:eus_x_preferred": [
      "Erli"
    ],
    "name:fas_x_preferred": [
      "ارلی"
    ],
    "name:fra_x_preferred": [
      "Erli"
    ],
    "name:hun_x_preferred": [
      "Erli"
    ],
    "name:hye_x_preferred": [
      "Էրլի"
    ],
    "name:ina_x_preferred": [
      "Erli"
    ],
    "name:ita_x_preferred": [
      "Erli"
    ],
    "name:jpn_x_preferred": [
      "エルリ"
    ],
    "name:lat_x_preferred": [
      "Erlis"
    ],
    "name:lij_x_preferred": [
      "Erli"
    ],
    "name:lmo_x_preferred": [
      "Erli"
    ],
    "name:msa_x_preferred": [
      "Erli"
    ],
    "name:nap_x_preferred": [
      "Erli"
    ],
    "name:nld_x_preferred": [
      "Erli"
    ],
    "name:pms_x_preferred": [
      "Erli"
    ],
    "name:pol_x_preferred": [
      "Erli"
    ],
    "name:por_x_preferred": [
      "Erli"
    ],
    "name:ron_x_preferred": [
      "Erli"
    ],
    "name:rus_x_preferred": [
      "Эрли"
    ],
    "name:scn_x_preferred": [
      "Erli"
    ],
    "name:spa_x_preferred": [
      "Erli"
    ],
    "name:srp_x_preferred": [
      "Ерли"
    ],
    "name:ukr_x_preferred": [
      "Ерлі"
    ],
    "name:uzb_x_preferred": [
      "Erli"
    ],
    "name:vie_x_preferred": [
      "Erli"
    ],
    "name:vol_x_preferred": [
      "Erli"
    ],
    "name:war_x_preferred": [
      "Erli"
    ],
    "wof:name": "Erli",
    "wof:placetype": "locality"
  },
  "geometry": {
    "coordinates": [
      116.16889,
      23.68361
    ],
    "type": "Point"
  }
}