{
  "type": "Feature",
  "properties": {
    "gn:admin1_code": "09",
    "gn:asciiname": "Hancheng",
    "gn:country_code": "CN",
    "gn:dem": 251,
    "gn:feature_class": "P",
    "gn:feature_code": "PPL",
    "gn:name": "Hancheng",
    "gn:population": 0,
    "gn:timezone": "Asia/Shanghai",
    "iso:country": "CN",
    "name:ara_x_preferred": [
      "هانتشنغ"
    ],
    "name:ceb_x_preferred": [
      "Hancheng"
    ],
    "name:ces_x_preferred": [
      "Chan-čcheng"
    ],
    "name:deu_x_preferred": [
      "Hancheng"
    ],
    "name:fra_x_preferred": [
      "Hancheng"
    ],
    "name:ind_x_preferred": [
      "Hancheng"
    ],
    "name:ita_x_preferred": [
      "Hancheng"
    ],
    "name:jpn_x_preferred": [
      "韓城"
    ],
    "name:jpn_x_variant": [
      "韓城市"
    ],
    "name:kik_x_preferred": [
      "Hancheng"
    ],
    "name:kor_x_preferred": [
      "한청시"
    ],
    "name:lat_x_preferred": [
      "Hancheng"
    ],
    "name:mlg_x_preferred": [
      "Hancheng"
    ],
    "name:nor_x_preferred": [
      "Hancheng"
    ],
    "name:rus_x_preferred": [
      "Ханьчэн"
    ],
    "name:swe_x_preferred": [
      "Hancheng"
    ],
    "name:urd_x_preferred": [
      "ہانچینگ"
    ],
    "name:vie_x_preferred": [
      "Hàn Thành"
    ],
    "name:war_x_preferred": [
      "Hancheng"
    ],
    "name:zho_x_preferred": [
      "韩城市"
    ],
    "wof:name": "Hancheng",
    "wof:placetype": "locality"
  },
  "geometry": {
    "coordinates": [
      111.92,
      34.49111
    ],
    "type": "Point"
  }
}