{
  "type": "Feature",
  "properties": {
    "gn:admin1_code": "10.0",
    "gn:asciiname": "Zhaojiagang",
    "gn:country_code": "CN",
    "gn:dem": 10,
    "gn:feature_class": "P",
    "gn:feature_code": "PPL",
    "gn:name": "Zhaojiagang",
    "gn:population": 0,
    "gn:timezone": "Asia/Shanghai",
    "iso:country": "CN",
    "name:zho_x_preferred": [
      "赵家港"
    ],
    "name:zho_x_variant": [
      "赵家岗土家族乡"
    ],
    "wof:name": "Zhaojiagang",
    "wof:placetype": "locality"
  },
  "geometry": {
    "coordinates": [
      119.14142,
      39.64323
    ],
    "type": "Point"
  }
}