{
  "type": "Feature",
  "properties": {
    "gn:admin1_code": "15.0",
    "gn:asciiname": "Changping",
    "gn:country_code": "CN",
    "gn:dem": 1895,
    "gn:feature_class": "P",
    "gn:feature_code": "PPL",
    "gn:name": "Changping",
    "gn:population": 0,
    "gn:timezone": "Asia/Shanghai",
    "iso:country": "CN",
    "name:ara_x_preferred": [
      "تشانغبينغ"
    ],
    "name:ben_x_preferred": [
      "চ্যাংপিং"
    ],
    "name:ceb_x_preferred": [
      "Changping"
    ],
    "name:ces_x_preferred": [
      "Čchang-pching"
    ],
    "name:deu_x_preferred": [
      "Changping"
    ],
    "name:ell_x_preferred": [
      "Τσανγκπίνγκ"
    ],
    "name:fas_x_preferred": [
      "چانگ پینگ"
    ],
    "name:fra_x_preferred": [
      "Changping"
    ],
    "name:heb_x_preferred": [
      "צ'נגפינג"
    ],
    "name:hin_x_preferred": [
      "चैंगपिंग"
    ],
    "name:hun_x_preferred": [
      "Changping"
    ],
    "name:ind_x_preferred": [
      "Changping"
    ],
    "name:ita_x_preferred": [
      "Changping"
    ],
    "name:jpn_x_preferred": [
      "常平镇"
    ],
    "name:kor_x_preferred": [
      "창핑"
    ],
    "name:mlg_x_preferred": [
      "Changping"
    ],
    "name:nld_x_preferred": [
      "Changping"
    ],
    "name:pol_x_preferred": [
      "Changping"
    ],
    "name:por_x_preferred": [
      "Changping"
    ],
    "name:rus_x_preferred": [
      "Чанпин"
    ],
    "name:spa_x_preferred": [
      "Changping"
    ],
    "name:swe_x_preferred": [
      "Changping"
    ],
    "name:tur_x_preferred": [
      "Changping"
    ],
    "name:ukr_x_preferred": [
      "Чанпін"
    ],
    "name:und_x_variant": [
      "常坪"
    ],
    "name:urd_x_preferred": [
      "چینگپنگ"
    ],
    "name:vie_x_preferred": [
      "Xương Bình"
    ],
    "name:zho_cn_x_preferred": [
      "常平镇"
    ],
    "name:zho_tw_x_preferred": [
      "常平"
    ],
    "wof:name": "Changping",
    "wof:placetype": "locality"
  },
  "geometry": {
    "coordinates": [
      105.1174,
      35.11559
    ],
    "type": "Point"
  }
}