{
  "type": "Feature",
  "properties": {
    "gn:admin1_code": "32.0",
    "gn:asciiname": "Luojia'an",
    "gn:country_code": "CN",
    "gn:dem": 698,
    "gn:feature_class": "P",
    "gn:feature_code": "PPL",
    "gn:name": "Luojia’an",
    "gn:population": 0,
    "gn:timezone": "Asia/Shanghai",
    "iso:country": "CN",
    "name:zho_x_preferred": [
      "罗家庵"
    ],
    "name:zho_x_variant": [
      "Luojia’an"
    ],
    "wof:name": "Luojia'an",
    "wof:placetype": "locality"
  },
  "geometry": {
    "coordinates": [
      107.61914,
      31.84115
    ],
    "type": "Point"
  }
}