{
  "type": "Feature",
  "properties": {
    "gn:admin1_code": "26",
    "gn:asciiname": "Sanguanmiao",
    "gn:country_code": "CN",
    "gn:dem": 823,
    "gn:feature_class": "P",
    "gn:feature_code": "PPL",
    "gn:name": "Sanguanmiao",
    "gn:population": 0,
    "gn:timezone": "Asia/Shanghai",
    "iso:country": "CN",
    "name:zho_x_preferred": [
      "三官庙"
    ],
    "wof:name": "Sanguanmiao",
    "wof:placetype": "locality"
  },
  "geometry": {
    "coordinates": [
      109.51099,
      34.29038
    ],
    "type": "Point"
  }
}