{
  "type": "Feature",
  "properties": {
    "gn:admin1_code": "16.0",
    "gn:asciiname": "Longgang",
    "gn:country_code": "CN",
    "gn:dem": 87,
    "gn:feature_class": "P",
    "gn:feature_code": "PPL",
    "gn:name": "Longgang",
    "gn:population": 0,
    "gn:timezone": "Asia/Shanghai",
    "iso:country": "CN",
    "name:ceb_x_preferred": [
      "Longgang"
    ],
    "name:deu_x_preferred": [
      "Longgang"
    ],
    "name:fra_x_preferred": [
      "Longgang"
    ],
    "name:kor_x_preferred": [
      "룽강구"
    ],
    "name:mlg_x_preferred": [
      "Longgang"
    ],
    "name:nor_x_preferred": [
      "Longgang"
    ],
    "name:pol_x_preferred": [
      "Longgang"
    ],
    "name:zho_x_preferred": [
      "龙岗"
    ],
    "wof:name": "Longgang",
    "wof:placetype": "locality"
  },
  "geometry": {
    "coordinates": [
      108.451,
      22.7646
    ],
    "type": "Point"
  }
}