{
  "type": "Feature",
  "properties": {
    "gn:admin1_code": "2.0",
    "gn:asciiname": "Huangbanyang",
    "gn:country_code": "CN",
    "gn:dem": 552,
    "gn:feature_class": "P",
    "gn:feature_code": "PPL",
    "gn:name": "Huangbanyang",
    "gn:population": 0,
    "gn:timezone": "Asia/Shanghai",
    "iso:country": "CN",
    "name:zho_x_preferred": [
      "黄坂阳"
    ],
    "wof:name": "Huangbanyang",
    "wof:placetype": "locality"
  },
  "geometry": {
    "coordinates": [
      120.51222,
      28.93158
    ],
    "type": "Point"
  }
}