{
  "type": "Feature",
  "properties": {
    "gn:admin1_code": "07",
    "gn:asciiname": "Shangluo",
    "gn:country_code": "CN",
    "gn:dem": 396,
    "gn:feature_class": "P",
    "gn:feature_code": "PPL",
    "gn:name": "Shangluo",
    "gn:population": 0,
    "gn:timezone": "Asia/Shanghai",
    "iso:country": "CN",
    "name:ara_x_preferred": [
      "شانغلو"
    ],
    "name:cdo_x_preferred": [
      "Siŏng-lŏk"
    ],
    "name:ces_x_preferred": [
      "Šang-luo"
    ],
    "name:dan_x_preferred": [
      "Shangluo"
    ],
    "name:deu_x_preferred": [
      "Shangluo"
    ],
    "name:eus_x_preferred": [
      "Shangluo"
    ],
    "name:fas_x_preferred": [
      "شانگلو"
    ],
    "name:fin_x_preferred": [
      "Shangluo"
    ],
    "name:fra_x_preferred": [
      "Shangluo"
    ],
    "name:ita_x_preferred": [
      "Shangluo"
    ],
    "name:jpn_x_preferred": [
      "商洛市"
    ],
    "name:kik_x_preferred": [
      "Shangluo"
    ],
    "name:kor_x_preferred": [
      "상뤄시"
    ],
    "name:mlg_x_preferred": [
      "Shangluo"
    ],
    "name:nld_x_preferred": [
      "Shangluo"
    ],
    "name:nno_x_preferred": [
      "Shangluo"
    ],
    "name:nor_x_preferred": [
      "Shangluo"
    ],
    "name:pol_x_preferred": [
      "Shangluo"
    ],
    "name:rus_x_preferred": [
      "Шанло"
    ],
    "name:spa_x_preferred": [
      "Shangluo"
    ],
    "name:swe_x_preferred": [
      "Shangluo"
    ],
    "name:tur_x_preferred": [
      "Shangluo"
    ],
    "name:ukr_x_preferred": [
      "Шанло"
    ],
    "name:urd_x_preferred": [
      "شانگلیو"
    ],
    "name:vie_x_preferred": [
      "Thương Lạc"
    ],
    "name:war_x_preferred": [
      "Shangluo"
    ],
    "name:zho_x_preferred": [
      "上螺"
    ],
    "name:zho_x_variant": [
      "商洛市"
    ],
    "wof:name": "Shangluo",
    "wof:placetype": "locality"
  },
  "geometry": {
    "coordinates": [
      117.39972,
      25.7925
    ],
    "type": "Point"
  }
}