{
  "type": "Feature",
  "properties": {
    "gn:admin1_code": "15.0",
    "gn:asciiname": "Zuitou Zhaojia",
    "gn:country_code": "CN",
    "gn:dem": 1102,
    "gn:feature_class": "P",
    "gn:feature_code": "PPL",
    "gn:name": "Zuitou Zhaojia",
    "gn:population": 0,
    "gn:timezone": "Asia/Shanghai",
    "iso:country": "CN",
    "name:zho_x_preferred": [
      "咀头赵家"
    ],
    "wof:name": "Zuitou Zhaojia",
    "wof:placetype": "locality"
  },
  "geometry": {
    "coordinates": [
      107.832,
      35.2948
    ],
    "type": "Point"
  }
}