{
  "type": "Feature",
  "properties": {
    "gn:admin1_code": "29.0",
    "gn:asciiname": "Yinchang",
    "gn:country_code": "CN",
    "gn:dem": 1110,
    "gn:feature_class": "P",
    "gn:feature_code": "PPL",
    "gn:name": "Yinchang",
    "gn:population": 0,
    "gn:timezone": "Asia/Shanghai",
    "iso:country": "CN",
    "name:deu_x_preferred": [
      "Yin-Chang"
    ],
    "name:jpn_x_preferred": [
      "イン昌"
    ],
    "name:zho_x_preferred": [
      "银厂"
    ],
    "wof:name": "Yinchang",
    "wof:placetype": "locality"
  },
  "geometry": {
    "coordinates": [
      101.238,
      21.9795
    ],
    "type": "Point"
  }
}