{
  "type": "Feature",
  "properties": {
    "gn:admin1_code": "11.0",
    "gn:asciiname": "Bujiachong",
    "gn:country_code": "CN",
    "gn:dem": 227,
    "gn:feature_class": "P",
    "gn:feature_code": "PPL",
    "gn:name": "Bujiachong",
    "gn:population": 0,
    "gn:timezone": "Asia/Shanghai",
    "iso:country": "CN",
    "name:zho_x_preferred": [
      "Bujiachong"
    ],
    "name:zho_x_variant": [
      "卜家冲"
    ],
    "wof:name": "Bujiachong",
    "wof:placetype": "locality"
  },
  "geometry": {
    "coordinates": [
      114.06753,
      28.23812
    ],
    "type": "Point"
  }
}