{
  "type": "Feature",
  "properties": {
    "gn:admin1_code": "26",
    "gn:asciiname": "Baishipu",
    "gn:country_code": "CN",
    "gn:dem": 1224,
    "gn:feature_class": "P",
    "gn:feature_code": "PPL",
    "gn:name": "Baishipu",
    "gn:population": 0,
    "gn:timezone": "Asia/Shanghai",
    "iso:country": "CN",
    "name:und_x_variant": [
      "Pai-shih-p’u",
      "Baishipu",
      "白石铺"
    ],
    "wof:name": "Baishipu",
    "wof:placetype": "locality"
  },
  "geometry": {
    "coordinates": [
      106.66412,
      33.98988
    ],
    "type": "Point"
  }
}