{
  "type": "Feature",
  "properties": {
    "gn:admin1_code": "32.0",
    "gn:asciiname": "Sanjia Buzi",
    "gn:country_code": "CN",
    "gn:dem": 2333,
    "gn:feature_class": "P",
    "gn:feature_code": "PPL",
    "gn:name": "Sanjia Buzi",
    "gn:population": 0,
    "gn:timezone": "Asia/Shanghai",
    "iso:country": "CN",
    "name:zho_x_preferred": [
      "三家堡子"
    ],
    "wof:name": "Sanjia Buzi",
    "wof:placetype": "locality"
  },
  "geometry": {
    "coordinates": [
      101.73,
      28.4721
    ],
    "type": "Point"
  }
}