{
  "type": "Feature",
  "properties": {
    "gn:admin1_code": "19.0",
    "gn:asciiname": "Tangchi",
    "gn:country_code": "CN",
    "gn:dem": 64,
    "gn:feature_class": "P",
    "gn:feature_code": "PPL",
    "gn:name": "Tangchi",
    "gn:population": 0,
    "gn:timezone": "Asia/Shanghai",
    "iso:country": "CN",
    "name:und_x_variant": [
      "汤池"
    ],
    "name:zho_x_preferred": [
      "汤池镇"
    ],
    "wof:name": "Tangchi",
    "wof:placetype": "locality"
  },
  "geometry": {
    "coordinates": [
      123.74129,
      40.29837
    ],
    "type": "Point"
  }
}