{
  "type": "Feature",
  "properties": {
    "gn:admin1_code": "23.0",
    "gn:asciiname": "Zhenjiang",
    "gn:country_code": "CN",
    "gn:dem": 6,
    "gn:feature_class": "P",
    "gn:feature_code": "PPL",
    "gn:name": "Zhenjiang",
    "gn:population": 0,
    "gn:timezone": "Asia/Shanghai",
    "iso:country": "CN",
    "name:afr_x_preferred": [
      "Zhenjiang"
    ],
    "name:ara_x_preferred": [
      "تشنجيانغ"
    ],
    "name:ast_x_preferred": [
      "Zhenjiang"
    ],
    "name:aze_x_preferred": [
      "Çjentszyan"
    ],
    "name:bod_x_preferred": [
      "ཀྲེན་ཅང་།"
    ],
    "name:bul_x_preferred": [
      "Джъндзян"
    ],
    "name:cdo_x_preferred": [
      "Déng-gŏng"
    ],
    "name:ceb_x_preferred": [
      "Zhenjiang"
    ],
    "name:ces_x_preferred": [
      "Čen-ťiang"
    ],
    "name:dan_x_preferred": [
      "Zhenjiang"
    ],
    "name:deu_x_preferred": [
      "Zhenjiang"
    ],
    "name:epo_x_preferred": [
      "Ĉĵencjan"
    ],
    "name:eus_x_preferred": [
      "Zhenjiang"
    ],
    "name:fas_x_preferred": [
      "جنجیانگ"
    ],
    "name:fin_x_preferred": [
      "Zhenjiang"
    ],
    "name:fra_x_preferred": [
      "Zhenjiang"
    ],
    "name:heb_x_preferred": [
      "ז'נג'יאנג"
    ],
    "name:ind_x_preferred": [
      "Zhenjiang"
    ],
    "name:ita_x_preferred": [
      "Zhenjiang"
    ],
    "name:jpn_x_preferred": [
      "鎮江市"
    ],
    "name:kik_x_preferred": [
      "Zhenjiang"
    ],
    "name:kor_x_preferred": [
      "전장시"
    ],
    "name:mlg_x_preferred": [
      "Zhenjiang"
    ],
    "name:nld_x_preferred": [
      "Zhenjiang"
    ],
    "name:nno_x_preferred": [
      "Zhenjiang"
    ],
    "name:nor_x_preferred": [
      "Zhenjiang"
    ],
    "name:pol_x_preferred": [
      "Zhenjiang"
    ],
    "name:por_x_preferred": [
      "Zhenjiang"
    ],
    "name:rus_x_preferred": [
      "Чжэньцзян"
    ],
    "name:sco_x_preferred": [
      "Zhenjiang"
    ],
    "name:spa_x_preferred": [
      "Zhenjiang"
    ],
    "name:srp_x_preferred": [
      "Џенђанг"
    ],
    "name:swe_x_preferred": [
      "Zhenjiang"
    ],
    "name:tgl_x_preferred": [
      "Zhenjiang"
    ],
    "name:uig_x_preferred": [
      "جاڭجياڭ شەھىرى"
    ],
    "name:ukr_x_preferred": [
      "Чженьцзян"
    ],
    "name:und_x_variant": [
      "真江"
    ],
    "name:urd_x_preferred": [
      "ژینجیانگ"
    ],
    "name:vie_x_preferred": [
      "Trấn Giang"
    ],
    "name:war_x_preferred": [
      "Zhenjiang"
    ],
    "name:wuu_x_preferred": [
      "镇江市"
    ],
    "name:zho_x_preferred": [
      "镇江市"
    ],
    "wof:name": "Zhenjiang",
    "wof:placetype": "locality"
  },
  "geometry": {
    "coordinates": [
      121.36465,
      31.25978
    ],
    "type": "Point"
  }
}