{
  "type": "Feature",
  "properties": {
    "gn:admin1_code": "13.0",
    "gn:asciiname": "Burjay",
    "gn:country_code": "CN",
    "gn:dem": 870,
    "gn:feature_class": "P",
    "gn:feature_code": "PPL",
    "gn:name": "Burjay",
    "gn:population": 0,
    "gn:timezone": "Asia/Urumqi",
    "iso:country": "CN",
    "name:uig_x_preferred": [
      "بۇرجاي"
    ],
    "name:uig_x_variant": [
      "Бурҗай"
    ],
    "name:und_x_variant": [
      "Bu’erjian"
    ],
    "name:zho_x_preferred": [
      "布尔碱"
    ],
    "wof:name": "Burjay",
    "wof:placetype": "locality"
  },
  "geometry": {
    "coordinates": [
      87.98472,
      42.88778
    ],
    "type": "Point"
  }
}