{
  "type": "Feature",
  "properties": {
    "gn:admin1_code": "16.0",
    "gn:asciiname": "Gaowu",
    "gn:country_code": "CN",
    "gn:dem": 656,
    "gn:feature_class": "P",
    "gn:feature_code": "PPL",
    "gn:name": "Gaowu",
    "gn:population": 0,
    "gn:timezone": "Asia/Shanghai",
    "iso:country": "CN",
    "name:zho_x_preferred": [
      "高武"
    ],
    "wof:name": "Gaowu",
    "wof:placetype": "locality"
  },
  "geometry": {
    "coordinates": [
      109.194,
      25.6054
    ],
    "type": "Point"
  }
}