{
  "type": "Feature",
  "properties": {
    "gn:admin1_code": "15.0",
    "gn:asciiname": "Jiangjiagou",
    "gn:country_code": "CN",
    "gn:dem": 1552,
    "gn:feature_class": "P",
    "gn:feature_code": "PPL",
    "gn:name": "Jiangjiagou",
    "gn:population": 0,
    "gn:timezone": "Asia/Shanghai",
    "iso:country": "CN",
    "name:zho_x_preferred": [
      "蒋家沟"
    ],
    "wof:name": "Jiangjiagou",
    "wof:placetype": "locality"
  },
  "geometry": {
    "coordinates": [
      106.571,
      35.5355
    ],
    "type": "Point"
  }
}