{
  "type": "Feature",
  "properties": {
    "gn:admin1_code": "2.0",
    "gn:asciiname": "Guanlu'ao",
    "gn:country_code": "CN",
    "gn:dem": 116,
    "gn:feature_class": "P",
    "gn:feature_code": "PPL",
    "gn:name": "Guanlu’ao",
    "gn:population": 0,
    "gn:timezone": "Asia/Shanghai",
    "iso:country": "CN",
    "name:und_x_variant": [
      "Guanlu’ao"
    ],
    "name:zho_x_preferred": [
      "官路岙"
    ],
    "wof:name": "Guanlu'ao",
    "wof:placetype": "locality"
  },
  "geometry": {
    "coordinates": [
      121.00081000000002,
      28.26275
    ],
    "type": "Point"
  }
}