{
  "type": "Feature",
  "properties": {
    "gn:admin1_code": "14.0",
    "gn:asciiname": "Gongmai",
    "gn:country_code": "CN",
    "gn:dem": 4050,
    "gn:feature_class": "P",
    "gn:feature_code": "PPL",
    "gn:name": "Gongmai",
    "gn:population": 0,
    "gn:timezone": "Asia/Urumqi",
    "iso:country": "CN",
    "name:zho_x_preferred": [
      "公麦"
    ],
    "wof:name": "Gongmai",
    "wof:placetype": "locality"
  },
  "geometry": {
    "coordinates": [
      92.22377,
      29.34833
    ],
    "type": "Point"
  }
}