{
  "type": "Feature",
  "properties": {
    "gn:admin1_code": "13",
    "gn:asciiname": "Narede Muchang",
    "gn:country_code": "CN",
    "gn:dem": 2481,
    "gn:feature_class": "P",
    "gn:feature_code": "PPLF",
    "gn:name": "Narede Muchang",
    "gn:population": 0,
    "gn:timezone": "Asia/Urumqi",
    "iso:country": "CN",
    "name:und_x_variant": [
      "那热德牧场"
    ],
    "wof:name": "Narede Muchang",
    "wof:placetype": "locality"
  },
  "geometry": {
    "coordinates": [
      84.19272,
      43.05002
    ],
    "type": "Point"
  }
}