{
  "type": "Feature",
  "properties": {
    "gn:admin1_code": "3.0",
    "gn:asciiname": "Jingyuan",
    "gn:country_code": "CN",
    "gn:dem": 141,
    "gn:feature_class": "P",
    "gn:feature_code": "PPL",
    "gn:name": "Jingyuan",
    "gn:population": 0,
    "gn:timezone": "Asia/Shanghai",
    "iso:country": "CN",
    "name:deu_x_preferred": [
      "Jingyuan"
    ],
    "name:fra_x_preferred": [
      "Jingyuan"
    ],
    "name:kor_x_preferred": [
      "징위안현"
    ],
    "name:nor_x_preferred": [
      "Jingyuan"
    ],
    "name:pol_x_preferred": [
      "Jingyuan"
    ],
    "name:rus_x_preferred": [
      "Цзинъюань"
    ],
    "name:swe_x_preferred": [
      "Jingyuan"
    ],
    "name:und_x_variant": [
      "荆沅"
    ],
    "wof:name": "Jingyuan",
    "wof:placetype": "locality"
  },
  "geometry": {
    "coordinates": [
      116.93487,
      27.31341
    ],
    "type": "Point"
  }
}