{
  "type": "Feature",
  "properties": {
    "gn:admin1_code": "32.0",
    "gn:asciiname": "Tutang",
    "gn:country_code": "CN",
    "gn:dem": 380,
    "gn:feature_class": "P",
    "gn:feature_code": "PPL",
    "gn:name": "Tutang",
    "gn:population": 0,
    "gn:timezone": "Asia/Shanghai",
    "iso:country": "CN",
    "name:ara_x_preferred": [
      "تو تنغ"
    ],
    "name:ceb_x_preferred": [
      "Tūtang"
    ],
    "name:fas_x_preferred": [
      "توتنگ"
    ],
    "name:msa_x_preferred": [
      "Tutang"
    ],
    "name:swe_x_preferred": [
      "Tūtang"
    ],
    "name:urd_x_preferred": [
      "توتنگ"
    ],
    "name:zho_x_preferred": [
      "土塘"
    ],
    "wof:name": "Tutang",
    "wof:placetype": "locality"
  },
  "geometry": {
    "coordinates": [
      106.56,
      31.2014
    ],
    "type": "Point"
  }
}