{
  "type": "Feature",
  "properties": {
    "gn:admin1_code": "16",
    "gn:asciiname": "Bao'an",
    "gn:country_code": "CN",
    "gn:dem": 252,
    "gn:feature_class": "P",
    "gn:feature_code": "PPL",
    "gn:name": "Bao’an",
    "gn:population": 0,
    "gn:timezone": "Asia/Shanghai",
    "iso:country": "CN",
    "name:ceb_x_preferred": [
      "Bao'an"
    ],
    "name:deu_x_preferred": [
      "Bao’an"
    ],
    "name:nor_x_preferred": [
      "Bao'an"
    ],
    "name:pol_x_preferred": [
      "Bao’an"
    ],
    "name:und_x_variant": [
      "Pao-an",
      "Pao-an-hsü"
    ],
    "name:zho_x_preferred": [
      "保安"
    ],
    "wof:name": "Bao'an",
    "wof:placetype": "locality"
  },
  "geometry": {
    "coordinates": [
      109.799,
      25.3398
    ],
    "type": "Point"
  }
}