{
  "type": "Feature",
  "properties": {
    "gn:admin1_code": "26",
    "gn:asciiname": "Baozi",
    "gn:country_code": "CN",
    "gn:dem": 912,
    "gn:feature_class": "P",
    "gn:feature_code": "PPL",
    "gn:name": "Baozi",
    "gn:population": 0,
    "gn:timezone": "Asia/Shanghai",
    "iso:country": "CN",
    "name:ara_x_preferred": [
      "باوزي"
    ],
    "name:bjn_x_preferred": [
      "Bakpao"
    ],
    "name:bul_x_preferred": [
      "Паучи"
    ],
    "name:cat_x_preferred": [
      "Baozi"
    ],
    "name:deu_x_preferred": [
      "Baozi"
    ],
    "name:fin_x_preferred": [
      "Baozi"
    ],
    "name:fra_x_preferred": [
      "Baozi"
    ],
    "name:ind_x_preferred": [
      "Bakpao"
    ],
    "name:ita_x_preferred": [
      "Baozi"
    ],
    "name:jav_x_preferred": [
      "Bakpao"
    ],
    "name:kor_x_preferred": [
      "바오쯔"
    ],
    "name:msa_x_preferred": [
      "Pau"
    ],
    "name:mya_x_preferred": [
      "ပေါက်စီ"
    ],
    "name:nor_x_preferred": [
      "Baozi"
    ],
    "name:pol_x_preferred": [
      "Baozi"
    ],
    "name:por_x_preferred": [
      "Baozi"
    ],
    "name:rus_x_preferred": [
      "Баоцзы"
    ],
    "name:spa_x_preferred": [
      "Baozi"
    ],
    "name:swe_x_preferred": [
      "Baozi"
    ],
    "name:tur_x_preferred": [
      "Baozi"
    ],
    "name:ukr_x_preferred": [
      "Баоцзи"
    ],
    "name:vie_x_preferred": [
      "Bánh bao"
    ],
    "name:zho_x_preferred": [
      "堡子"
    ],
    "wof:name": "Baozi",
    "wof:placetype": "locality"
  },
  "geometry": {
    "coordinates": [
      108.45778,
      34.81444
    ],
    "type": "Point"
  }
}