{
  "type": "Feature",
  "properties": {
    "gn:admin1_code": "3.0",
    "gn:asciiname": "Qiaotou",
    "gn:country_code": "CN",
    "gn:dem": 193,
    "gn:feature_class": "P",
    "gn:feature_code": "PPL",
    "gn:name": "Qiaotou",
    "gn:population": 0,
    "gn:timezone": "Asia/Shanghai",
    "iso:country": "CN",
    "name:ceb_x_preferred": [
      "Qiaotou"
    ],
    "name:deu_x_preferred": [
      "Qiaotou"
    ],
    "name:swe_x_preferred": [
      "Qiaotou"
    ],
    "name:und_x_variant": [
      "桥头"
    ],
    "name:zho_x_preferred": [
      "桥头镇"
    ],
    "wof:name": "Qiaotou",
    "wof:placetype": "locality"
  },
  "geometry": {
    "coordinates": [
      116.07422,
      27.29358
    ],
    "type": "Point"
  }
}