{
  "type": "Feature",
  "properties": {
    "gn:admin1_code": "25",
    "gn:asciiname": "Caotun",
    "gn:country_code": "CN",
    "gn:dem": 28,
    "gn:feature_class": "P",
    "gn:feature_code": "PPL",
    "gn:name": "Caotun",
    "gn:population": 0,
    "gn:timezone": "Asia/Shanghai",
    "iso:country": "CN",
    "name:deu_x_preferred": [
      "Caotun"
    ],
    "name:hak_x_preferred": [
      "Chhó-thùn-tsṳ́n"
    ],
    "name:ita_x_preferred": [
      "Caotun"
    ],
    "name:jpn_x_preferred": [
      "草屯鎮"
    ],
    "name:kor_x_preferred": [
      "차오툰진"
    ],
    "name:pol_x_preferred": [
      "Caotun"
    ],
    "name:vie_x_preferred": [
      "Thảo Đồn"
    ],
    "name:zho_x_preferred": [
      "草屯"
    ],
    "name:zho_x_variant": [
      "草屯鎮"
    ],
    "wof:name": "Caotun",
    "wof:placetype": "locality"
  },
  "geometry": {
    "coordinates": [
      116.215,
      37.2593
    ],
    "type": "Point"
  }
}