{
  "type": "Feature",
  "properties": {
    "gn:country": "CN",
    "gn:fcode": "PPL",
    "gn:population": 56637,
    "iso:country": "CN",
    "name:ces_x_preferred": [
      "Chua"
    ],
    "name:deu_x_preferred": [
      "Hua"
    ],
    "name:eng_x_preferred": [
      "Hua County"
    ],
    "name:fas_x_preferred": [
      "شهرستان هوا"
    ],
    "name:gan_x_preferred": [
      "滑县"
    ],
    "name:jpn_x_preferred": [
      "滑県"
    ],
    "name:kor_x_preferred": [
      "화현"
    ],
    "name:nan_x_preferred": [
      "Ku̍t-koān"
    ],
    "name:nld_x_preferred": [
      "Hua"
    ],
    "name:nob_x_preferred": [
      "Hua"
    ],
    "name:rus_x_preferred": [
      "Хуасянь"
    ],
    "name:swe_x_preferred": [
      "Hua"
    ],
    "name:ukr_x_preferred": [
      "Хуасянь"
    ],
    "name:und_x_variant": [
      "Taokow"
    ],
    "name:vie_x_preferred": [
      "Hoạt"
    ],
    "name:wuu_x_preferred": [
      "滑县"
    ],
    "name:yue_x_preferred": [
      "滑縣"
    ],
    "name:zho_x_preferred": [
      "道口"
    ],
    "name:zho_x_variant": [
      "滑县"
    ],
    "qs:name": "Huaxian",
    "qs:photos_9r": 0,
    "qs:photos_sr": 0,
    "qs:pop_sr": "8",
    "wd:wordcount": 262,
    "wof:name": "Huaxian",
    "wof:placetype": "locality",
    "wof:population": 56637
  },
  "geometry": {
    "coordinates": [
      114.50583,
      35.56389
    ],
    "type": "Point"
  }
}