{
  "type": "Feature",
  "properties": {
    "gn:admin1_code": "32.0",
    "gn:asciiname": "Jiankang",
    "gn:country_code": "CN",
    "gn:dem": 506,
    "gn:feature_class": "P",
    "gn:feature_code": "PPL",
    "gn:name": "Jiankang",
    "gn:population": 0,
    "gn:timezone": "Asia/Shanghai",
    "iso:country": "CN",
    "name:ceb_x_preferred": [
      "Jianye Qu"
    ],
    "name:fra_x_preferred": [
      "Jianye"
    ],
    "name:ind_x_preferred": [
      "Jiankang"
    ],
    "name:jpn_x_preferred": [
      "建康"
    ],
    "name:kor_x_preferred": [
      "건강"
    ],
    "name:nld_x_preferred": [
      "Jiankang"
    ],
    "name:rus_x_preferred": [
      "Цзянькан"
    ],
    "name:spa_x_preferred": [
      "Jiankang"
    ],
    "name:urd_x_preferred": [
      "جیانکانگ"
    ],
    "name:vie_x_preferred": [
      "Kiến Khang"
    ],
    "name:zho_x_preferred": [
      "健康"
    ],
    "name:zho_x_variant": [
      "六朝建康都城遗址"
    ],
    "wof:name": "Jiankang",
    "wof:placetype": "locality"
  },
  "geometry": {
    "coordinates": [
      104.216,
      30.5421
    ],
    "type": "Point"
  }
}