{
  "type": "Feature",
  "properties": {
    "gn:admin1_code": "20",
    "gn:asciiname": "Baochang",
    "gn:country_code": "CN",
    "gn:dem": 1456,
    "gn:feature_class": "P",
    "gn:feature_code": "PPLA3",
    "gn:name": "Baochang",
    "gn:population": 0,
    "gn:timezone": "Asia/Shanghai",
    "iso:country": "CN",
    "name:und_x_variant": [
      "Koting",
      "T’ai-p’u-ssu-ch’i",
      "Pao-ch’ang",
      "Taibusi Qi",
      "Pao-ch’ang-chen",
      "Pao-ch’ang-hsien",
      "Baochang",
      "宝昌",
      "Taipusi Qi",
      "Baochang Zhen",
      "太仆寺旗"
    ],
    "name:zho_x_preferred": [
      "宝昌镇"
    ],
    "wof:name": "Baochang",
    "wof:placetype": "locality"
  },
  "geometry": {
    "coordinates": [
      115.27889,
      41.88444000000001
    ],
    "type": "Point"
  }
}