{
  "type": "Feature",
  "properties": {
    "gn:admin1_code": "12.0",
    "gn:asciiname": "Nanmuping",
    "gn:country_code": "CN",
    "gn:dem": 1261,
    "gn:feature_class": "P",
    "gn:feature_code": "PPL",
    "gn:name": "Nanmuping",
    "gn:population": 0,
    "gn:timezone": "Asia/Shanghai",
    "iso:country": "CN",
    "name:zho_x_preferred": [
      "楠木坪"
    ],
    "wof:name": "Nanmuping",
    "wof:placetype": "locality"
  },
  "geometry": {
    "coordinates": [
      109.23499,
      30.15261
    ],
    "type": "Point"
  }
}