{
  "type": "Feature",
  "properties": {
    "gn:admin1_code": "3.0",
    "gn:asciiname": "Wangjia",
    "gn:country_code": "CN",
    "gn:dem": 178,
    "gn:feature_class": "P",
    "gn:feature_code": "PPL",
    "gn:name": "Wangjia",
    "gn:population": 0,
    "gn:timezone": "Asia/Shanghai",
    "iso:country": "CN",
    "name:zho_x_preferred": [
      "汪家"
    ],
    "wof:name": "Wangjia",
    "wof:placetype": "locality"
  },
  "geometry": {
    "coordinates": [
      117.131,
      29.7085
    ],
    "type": "Point"
  }
}