{
  "type": "Feature",
  "properties": {
    "gn:admin1_code": "25",
    "gn:asciiname": "Hanjiaqiao",
    "gn:country_code": "CN",
    "gn:dem": 10,
    "gn:feature_class": "P",
    "gn:feature_code": "PPL",
    "gn:name": "Hanjiaqiao",
    "gn:population": 0,
    "gn:timezone": "Asia/Shanghai",
    "iso:country": "CN",
    "name:zho_x_preferred": [
      "韩家桥"
    ],
    "wof:name": "Hanjiaqiao",
    "wof:placetype": "locality"
  },
  "geometry": {
    "coordinates": [
      119.424,
      36.9317
    ],
    "type": "Point"
  }
}