{
  "type": "Feature",
  "properties": {
    "gn:admin1_code": "10",
    "gn:asciiname": "Dazhuang",
    "gn:country_code": "CN",
    "gn:dem": 51,
    "gn:feature_class": "P",
    "gn:feature_code": "PPL",
    "gn:name": "Dazhuang",
    "gn:population": 0,
    "gn:timezone": "Asia/Shanghai",
    "iso:country": "CN",
    "name:ceb_x_preferred": [
      "Dazhuang"
    ],
    "name:deu_x_preferred": [
      "Dazhuang"
    ],
    "name:swe_x_preferred": [
      "Dazhuang"
    ],
    "name:zho_x_preferred": [
      "大庄"
    ],
    "wof:name": "Dazhuang",
    "wof:placetype": "locality"
  },
  "geometry": {
    "coordinates": [
      115.0185,
      36.33753
    ],
    "type": "Point"
  }
}