{
  "type": "Feature",
  "properties": {
    "gn:admin1_code": "04",
    "gn:asciiname": "Houyu",
    "gn:country_code": "CN",
    "gn:dem": 7,
    "gn:feature_class": "P",
    "gn:feature_code": "PPL",
    "gn:name": "Houyu",
    "gn:population": 0,
    "gn:timezone": "Asia/Shanghai",
    "iso:country": "CN",
    "name:und_x_variant": [
      "Hou-yü-chen",
      "Houyu"
    ],
    "name:zho_x_preferred": [
      "厚余"
    ],
    "wof:name": "Houyu",
    "wof:placetype": "locality"
  },
  "geometry": {
    "coordinates": [
      119.80627,
      31.72632
    ],
    "type": "Point"
  }
}