{
  "type": "Feature",
  "properties": {
    "gn:admin1_code": "4.0",
    "gn:asciiname": "Huiyuan",
    "gn:country_code": "CN",
    "gn:dem": 5,
    "gn:feature_class": "P",
    "gn:feature_code": "PPL",
    "gn:name": "Huiyuan",
    "gn:population": 0,
    "gn:timezone": "Asia/Shanghai",
    "iso:country": "CN",
    "name:ara_x_preferred": [
      "هويوان"
    ],
    "name:deu_x_preferred": [
      "Huiyuan"
    ],
    "name:nld_x_preferred": [
      "Huiyuan"
    ],
    "name:rus_x_preferred": [
      "Хуэйюань"
    ],
    "name:und_x_variant": [
      "汇源"
    ],
    "name:zho_x_preferred": [
      "Huiyuanzhen"
    ],
    "name:zho_x_variant": [
      "汇源镇"
    ],
    "wof:name": "Huiyuan",
    "wof:placetype": "locality"
  },
  "geometry": {
    "coordinates": [
      121.21578999999998,
      31.99441
    ],
    "type": "Point"
  }
}