{
  "type": "Feature",
  "properties": {
    "gn:admin1_code": "30.0",
    "gn:asciiname": "Masi",
    "gn:country_code": "CN",
    "gn:dem": 8,
    "gn:feature_class": "P",
    "gn:feature_code": "PPL",
    "gn:name": "Masi",
    "gn:population": 0,
    "gn:timezone": "Asia/Shanghai",
    "iso:country": "CN",
    "name:ara_x_preferred": [
      "ماسي"
    ],
    "name:ben_x_preferred": [
      "মাসি"
    ],
    "name:ceb_x_preferred": [
      "Masi"
    ],
    "name:deu_x_preferred": [
      "Masi"
    ],
    "name:ell_x_preferred": [
      "Μάσι"
    ],
    "name:fas_x_preferred": [
      "ماسی"
    ],
    "name:fra_x_preferred": [
      "Masi"
    ],
    "name:heb_x_preferred": [
      "מאסיף דה בונגוס"
    ],
    "name:hin_x_preferred": [
      "मासी"
    ],
    "name:hun_x_preferred": [
      "Masi"
    ],
    "name:ind_x_preferred": [
      "Masi"
    ],
    "name:ita_x_preferred": [
      "Masi"
    ],
    "name:jpn_x_preferred": [
      "マシ川"
    ],
    "name:kor_x_preferred": [
      "마시"
    ],
    "name:nld_x_preferred": [
      "Masi"
    ],
    "name:pol_x_preferred": [
      "Masi"
    ],
    "name:por_x_preferred": [
      "Masi"
    ],
    "name:rus_x_preferred": [
      "река Муси"
    ],
    "name:spa_x_preferred": [
      "Masi"
    ],
    "name:srp_x_preferred": [
      "Mazi"
    ],
    "name:swe_x_preferred": [
      "Masi"
    ],
    "name:tur_x_preferred": [
      "Masi"
    ],
    "name:ukr_x_preferred": [
      "Масі"
    ],
    "name:und_x_variant": [
      "Ma-ssu",
      "马嘶"
    ],
    "name:urd_x_preferred": [
      "ماسی"
    ],
    "name:vie_x_preferred": [
      "Sông Masi"
    ],
    "name:zho_cn_x_preferred": [
      "马西河"
    ],
    "name:zho_tw_x_preferred": [
      "馬西河"
    ],
    "name:zho_x_preferred": [
      "马嘶"
    ],
    "wof:name": "Masi",
    "wof:placetype": "locality"
  },
  "geometry": {
    "coordinates": [
      114.03675,
      23.1081
    ],
    "type": "Point"
  }
}