{
  "type": "Feature",
  "properties": {
    "gn:admin1_code": "31.0",
    "gn:asciiname": "Tougan",
    "gn:country_code": "CN",
    "gn:dem": 107,
    "gn:feature_class": "P",
    "gn:feature_code": "PPL",
    "gn:name": "Tougan",
    "gn:population": 0,
    "gn:timezone": "Asia/Shanghai",
    "iso:country": "CN",
    "name:ben_x_preferred": [
      "টোউগান"
    ],
    "name:ceb_x_preferred": [
      "Tougan"
    ],
    "name:deu_x_preferred": [
      "Tougan"
    ],
    "name:ell_x_preferred": [
      "Τουγκάν"
    ],
    "name:fas_x_preferred": [
      "توگان"
    ],
    "name:fra_x_preferred": [
      "Tougan"
    ],
    "name:frr_x_preferred": [
      "Tougan"
    ],
    "name:heb_x_preferred": [
      "טוגן"
    ],
    "name:hin_x_preferred": [
      "तोउगन"
    ],
    "name:hun_x_preferred": [
      "Tougan"
    ],
    "name:ind_x_preferred": [
      "Tougan"
    ],
    "name:ita_x_preferred": [
      "Tougan"
    ],
    "name:kor_x_preferred": [
      "투간"
    ],
    "name:nld_x_preferred": [
      "Tougan"
    ],
    "name:pol_x_preferred": [
      "Tougan"
    ],
    "name:por_x_preferred": [
      "Tougan"
    ],
    "name:ron_x_preferred": [
      "Tougan"
    ],
    "name:rus_x_preferred": [
      "Туган"
    ],
    "name:spa_x_preferred": [
      "Tougan"
    ],
    "name:swe_x_preferred": [
      "Tougan"
    ],
    "name:tur_x_preferred": [
      "Tougan"
    ],
    "name:ukr_x_preferred": [
      "Туган"
    ],
    "name:urd_x_preferred": [
      "تؤگان"
    ],
    "name:vie_x_preferred": [
      "Tougan"
    ],
    "name:war_x_preferred": [
      "Tougan"
    ],
    "name:zho_cn_x_preferred": [
      "图冈"
    ],
    "name:zho_tw_x_preferred": [
      "圖岡"
    ],
    "name:zho_x_preferred": [
      "头干"
    ],
    "wof:name": "Tougan",
    "wof:placetype": "locality"
  },
  "geometry": {
    "coordinates": [
      109.76435,
      19.63949
    ],
    "type": "Point"
  }
}