{
  "type": "Feature",
  "properties": {
    "gn:admin1_code": "13.0",
    "gn:asciiname": "Karjaw",
    "gn:country_code": "CN",
    "gn:dem": 1292,
    "gn:feature_class": "P",
    "gn:feature_code": "PPLA4",
    "gn:name": "Karjaw",
    "gn:population": 0,
    "gn:timezone": "Asia/Urumqi",
    "iso:country": "CN",
    "name:uig_x_preferred": [
      "K̩arjaw"
    ],
    "name:uig_x_variant": [
      "Qarjaw",
      "قارجاۋ",
      "Қарҗав"
    ],
    "name:und_x_variant": [
      "Ka’erjiao",
      "Ka’erjiao Xiang"
    ],
    "name:zho_x_preferred": [
      "喀尔交"
    ],
    "name:zho_x_variant": [
      "喀尔交乡"
    ],
    "wof:name": "Karjaw",
    "wof:placetype": "locality"
  },
  "geometry": {
    "coordinates": [
      86.39848,
      47.19094000000001
    ],
    "type": "Point"
  }
}