{
  "type": "Feature",
  "properties": {
    "gn:admin1_code": "26",
    "gn:asciiname": "Tiangecun",
    "gn:country_code": "CN",
    "gn:dem": 494,
    "gn:feature_class": "P",
    "gn:feature_code": "PPL",
    "gn:name": "Tiangecun",
    "gn:population": 0,
    "gn:timezone": "Asia/Shanghai",
    "iso:country": "CN",
    "name:und_x_variant": [
      "Tiange"
    ],
    "name:zho_x_preferred": [
      "天阁"
    ],
    "name:zho_x_variant": [
      "天阁村"
    ],
    "wof:name": "Tiangecun",
    "wof:placetype": "locality"
  },
  "geometry": {
    "coordinates": [
      108.63537,
      34.45221
    ],
    "type": "Point"
  }
}