{
  "type": "Feature",
  "properties": {
    "gn:admin1_code": "4.0",
    "gn:asciiname": "Heyuan",
    "gn:country_code": "CN",
    "gn:dem": 2,
    "gn:feature_class": "P",
    "gn:feature_code": "PPL",
    "gn:name": "Heyuan",
    "gn:population": 0,
    "gn:timezone": "Asia/Shanghai",
    "iso:country": "CN",
    "name:ara_x_preferred": [
      "هيوان"
    ],
    "name:cdo_x_preferred": [
      "Ò̤-nguòng"
    ],
    "name:ceb_x_preferred": [
      "Heyuan"
    ],
    "name:ces_x_preferred": [
      "Che-jüan"
    ],
    "name:cym_x_preferred": [
      "Heyuan"
    ],
    "name:dan_x_preferred": [
      "Heyuan"
    ],
    "name:deu_x_preferred": [
      "Heyuan"
    ],
    "name:eus_x_preferred": [
      "Heyuan"
    ],
    "name:fas_x_preferred": [
      "هیوان"
    ],
    "name:fin_x_preferred": [
      "Heyuan"
    ],
    "name:fra_x_preferred": [
      "Heyuan"
    ],
    "name:hak_x_preferred": [
      "Hò-ngièn-sṳ"
    ],
    "name:hun_x_preferred": [
      "Heyuan"
    ],
    "name:ind_x_preferred": [
      "Heyuan"
    ],
    "name:ita_x_preferred": [
      "Heyuan"
    ],
    "name:jpn_x_preferred": [
      "河源市"
    ],
    "name:kik_x_preferred": [
      "Heyuan"
    ],
    "name:kor_x_preferred": [
      "허위안시"
    ],
    "name:mlg_x_preferred": [
      "Heyuan"
    ],
    "name:msa_x_preferred": [
      "Heyuan"
    ],
    "name:nld_x_preferred": [
      "Heyuan"
    ],
    "name:nno_x_preferred": [
      "Heyuan"
    ],
    "name:nor_x_preferred": [
      "Heyuan"
    ],
    "name:pam_x_preferred": [
      "Heyuan"
    ],
    "name:pnb_x_preferred": [
      "ہی یوآن"
    ],
    "name:pol_x_preferred": [
      "Heyuan"
    ],
    "name:rus_x_preferred": [
      "Хэюань"
    ],
    "name:spa_x_preferred": [
      "Heyuan"
    ],
    "name:swa_x_preferred": [
      "Heyuan"
    ],
    "name:swe_x_preferred": [
      "Heyuan"
    ],
    "name:tur_x_preferred": [
      "Heyuan"
    ],
    "name:urd_x_preferred": [
      "ہیئوان"
    ],
    "name:vie_x_preferred": [
      "Hà Nguyên"
    ],
    "name:war_x_preferred": [
      "Heyuan"
    ],
    "name:wuu_x_preferred": [
      "河源市"
    ],
    "name:zho_x_preferred": [
      "荷园"
    ],
    "name:zho_x_variant": [
      "河源市"
    ],
    "wof:name": "Heyuan",
    "wof:placetype": "locality"
  },
  "geometry": {
    "coordinates": [
      120.896,
      32.4449
    ],
    "type": "Point"
  }
}