{
  "type": "Feature",
  "properties": {
    "gn:admin1_code": "3.0",
    "gn:asciiname": "Changfu",
    "gn:country_code": "CN",
    "gn:dem": 112,
    "gn:feature_class": "P",
    "gn:feature_code": "PPL",
    "gn:name": "Changfu",
    "gn:population": 0,
    "gn:timezone": "Asia/Shanghai",
    "iso:country": "CN",
    "name:zho_x_preferred": [
      "长富"
    ],
    "wof:name": "Changfu",
    "wof:placetype": "locality"
  },
  "geometry": {
    "coordinates": [
      115.293,
      27.0383
    ],
    "type": "Point"
  }
}