{
  "type": "Feature",
  "properties": {
    "gn:admin1_code": "15.0",
    "gn:asciiname": "Shangdu",
    "gn:country_code": "CN",
    "gn:dem": 1635,
    "gn:feature_class": "P",
    "gn:feature_code": "PPL",
    "gn:name": "Shangdu",
    "gn:population": 0,
    "gn:timezone": "Asia/Shanghai",
    "iso:country": "CN",
    "name:afr_x_preferred": [
      "Shangdu"
    ],
    "name:als_x_preferred": [
      "Shangdu"
    ],
    "name:ast_x_preferred": [
      "Xanadú"
    ],
    "name:bul_x_preferred": [
      "Шанду"
    ],
    "name:cat_x_preferred": [
      "Xanadú"
    ],
    "name:ces_x_preferred": [
      "Šang-tu"
    ],
    "name:deu_x_preferred": [
      "Shangdu"
    ],
    "name:est_x_preferred": [
      "Shangdu"
    ],
    "name:eus_x_preferred": [
      "Xanadu"
    ],
    "name:fas_x_preferred": [
      "شانگدو"
    ],
    "name:fin_x_preferred": [
      "Xanadu"
    ],
    "name:fra_x_preferred": [
      "Shangdu"
    ],
    "name:heb_x_preferred": [
      "זאנאדו"
    ],
    "name:hrv_x_preferred": [
      "Xanadu"
    ],
    "name:hun_x_preferred": [
      "Xanadu"
    ],
    "name:ind_x_preferred": [
      "Shangdu"
    ],
    "name:ind_x_variant": [
      "Xanadu"
    ],
    "name:ita_x_preferred": [
      "Xanadu"
    ],
    "name:kat_x_preferred": [
      "შანდუ"
    ],
    "name:kor_x_preferred": [
      "상도"
    ],
    "name:lit_x_preferred": [
      "Šandu"
    ],
    "name:mon_x_preferred": [
      "Шанду"
    ],
    "name:nld_x_preferred": [
      "Xanadu"
    ],
    "name:nor_x_preferred": [
      "Xanadu"
    ],
    "name:pol_x_preferred": [
      "Xanadu"
    ],
    "name:por_x_preferred": [
      "Xanadu"
    ],
    "name:por_x_variant": [
      "Shangdu"
    ],
    "name:rus_x_preferred": [
      "Шанду"
    ],
    "name:spa_x_preferred": [
      "Xanadú"
    ],
    "name:srp_x_preferred": [
      "Ксанаду"
    ],
    "name:swe_x_preferred": [
      "Xanadu"
    ],
    "name:tha_x_preferred": [
      "แหล่งแซนาดู"
    ],
    "name:tur_x_preferred": [
      "Shangdu"
    ],
    "name:ukr_x_preferred": [
      "Шанду"
    ],
    "name:und_x_variant": [
      "上杜"
    ],
    "name:urd_x_preferred": [
      "سنادو"
    ],
    "name:vie_x_preferred": [
      "Thượng Đô"
    ],
    "name:zho_x_preferred": [
      "元上都"
    ],
    "wof:name": "Shangdu",
    "wof:placetype": "locality"
  },
  "geometry": {
    "coordinates": [
      105.68362,
      35.17965
    ],
    "type": "Point"
  }
}