{
  "type": "Feature",
  "properties": {
    "gn:admin1_code": "24.0",
    "gn:asciiname": "Baotou",
    "gn:country_code": "CN",
    "gn:dem": 740,
    "gn:feature_class": "P",
    "gn:feature_code": "PPL",
    "gn:name": "Baotou",
    "gn:population": 0,
    "gn:timezone": "Asia/Shanghai",
    "iso:country": "CN",
    "name:afr_x_preferred": [
      "Baotou"
    ],
    "name:ara_x_preferred": [
      "باوتو"
    ],
    "name:bul_x_preferred": [
      "Баотоу"
    ],
    "name:cat_x_preferred": [
      "Baotou"
    ],
    "name:cdo_x_preferred": [
      "Bău-tàu"
    ],
    "name:ceb_x_preferred": [
      "Baotou"
    ],
    "name:ces_x_preferred": [
      "Pao-tchou"
    ],
    "name:che_x_preferred": [
      "Баотоу"
    ],
    "name:dan_x_preferred": [
      "Baotou"
    ],
    "name:deu_x_preferred": [
      "Baotou"
    ],
    "name:epo_x_preferred": [
      "Baŭtoŭo"
    ],
    "name:est_x_preferred": [
      "Baotou"
    ],
    "name:eus_x_preferred": [
      "Baotou"
    ],
    "name:fas_x_preferred": [
      "بائوتو"
    ],
    "name:fin_x_preferred": [
      "Baotou"
    ],
    "name:fra_x_preferred": [
      "Baotou"
    ],
    "name:hak_x_preferred": [
      "Pâu-thèu-sṳ"
    ],
    "name:heb_x_preferred": [
      "באוטואו"
    ],
    "name:hun_x_preferred": [
      "Paotou"
    ],
    "name:hye_x_preferred": [
      "Բաոտոու"
    ],
    "name:ind_x_preferred": [
      "Baotou"
    ],
    "name:ita_x_preferred": [
      "Baotou"
    ],
    "name:jpn_x_preferred": [
      "包頭市"
    ],
    "name:kik_x_preferred": [
      "Baotou"
    ],
    "name:kir_x_preferred": [
      "Баотоу шаары"
    ],
    "name:kor_x_preferred": [
      "바오터우시"
    ],
    "name:lit_x_preferred": [
      "Baotou"
    ],
    "name:mlg_x_preferred": [
      "Baotou"
    ],
    "name:mon_x_preferred": [
      "Бугат хот"
    ],
    "name:nld_x_preferred": [
      "Baotou"
    ],
    "name:nor_x_preferred": [
      "Baotou"
    ],
    "name:pan_x_preferred": [
      "ਬਾਓਟਾਓ"
    ],
    "name:pol_x_preferred": [
      "Baotou"
    ],
    "name:por_x_preferred": [
      "Baotou"
    ],
    "name:rus_x_preferred": [
      "Баотоу"
    ],
    "name:sco_x_preferred": [
      "Baotou"
    ],
    "name:spa_x_preferred": [
      "Baotou"
    ],
    "name:srp_x_preferred": [
      "Баотоу"
    ],
    "name:swe_x_preferred": [
      "Baotou"
    ],
    "name:tgl_x_preferred": [
      "Baotou"
    ],
    "name:tur_x_preferred": [
      "Baotou"
    ],
    "name:uig_x_preferred": [
      "باۋتۇ شەھىر"
    ],
    "name:ukr_x_preferred": [
      "Баотоу"
    ],
    "name:und_x_variant": [
      "堡头"
    ],
    "name:urd_x_preferred": [
      "بائوتو"
    ],
    "name:uzb_x_preferred": [
      "Baotou"
    ],
    "name:vep_x_preferred": [
      "Baotou"
    ],
    "name:vie_x_preferred": [
      "Bao Đầu"
    ],
    "name:war_x_preferred": [
      "Baotou"
    ],
    "name:zho_x_preferred": [
      "包头市"
    ],
    "wof:name": "Baotou",
    "wof:placetype": "locality"
  },
  "geometry": {
    "coordinates": [
      111.20246,
      35.43184
    ],
    "type": "Point"
  }
}