{
  "type": "Feature",
  "properties": {
    "gn:admin1_code": "33.0",
    "gn:asciiname": "Huyan",
    "gn:country_code": "CN",
    "gn:dem": 310,
    "gn:feature_class": "P",
    "gn:feature_code": "PPL",
    "gn:name": "Huyan",
    "gn:population": 0,
    "gn:timezone": "Asia/Shanghai",
    "iso:country": "CN",
    "name:aze_x_preferred": [
      "Qiyan qəbiləsi"
    ],
    "name:cat_x_preferred": [
      "Huyan"
    ],
    "name:kor_x_preferred": [
      "호연씨"
    ],
    "name:rus_x_preferred": [
      "Хуянь"
    ],
    "name:zho_x_preferred": [
      "虎岩"
    ],
    "name:zho_x_variant": [
      "呼延姓"
    ],
    "wof:name": "Huyan",
    "wof:placetype": "locality"
  },
  "geometry": {
    "coordinates": [
      106.315,
      29.5402
    ],
    "type": "Point"
  }
}