{
  "type": "Feature",
  "properties": {
    "gn:admin1_code": "10.0",
    "gn:asciiname": "Yeqiaoying",
    "gn:country_code": "CN",
    "gn:dem": 21,
    "gn:feature_class": "P",
    "gn:feature_code": "PPL",
    "gn:name": "Yeqiaoying",
    "gn:population": 0,
    "gn:timezone": "Asia/Shanghai",
    "iso:country": "CN",
    "name:zho_x_preferred": [
      "野桥营"
    ],
    "wof:name": "Yeqiaoying",
    "wof:placetype": "locality"
  },
  "geometry": {
    "coordinates": [
      115.79148,
      39.10381
    ],
    "type": "Point"
  }
}