{
  "type": "Feature",
  "properties": {
    "gn:admin1_code": "07",
    "gn:asciiname": "Anren",
    "gn:country_code": "CN",
    "gn:dem": 43,
    "gn:feature_class": "P",
    "gn:feature_code": "PPL",
    "gn:name": "Anren",
    "gn:population": 0,
    "gn:timezone": "Asia/Shanghai",
    "iso:country": "CN",
    "name:zho_x_preferred": [
      "安仁"
    ],
    "wof:name": "Anren",
    "wof:placetype": "locality"
  },
  "geometry": {
    "coordinates": [
      120.30523,
      27.23922
    ],
    "type": "Point"
  }
}