{
  "type": "Feature",
  "properties": {
    "gn:country": "CN",
    "gn:fcode": "PPL",
    "gn:population": 104277,
    "iso:country": "CN",
    "name:ast_x_preferred": [
      "Pulandian"
    ],
    "name:ceb_x_preferred": [
      "Pulandian"
    ],
    "name:cym_x_preferred": [
      "Ardal Pulandian"
    ],
    "name:deu_x_preferred": [
      "Pulandian"
    ],
    "name:eng_x_preferred": [
      "Pulandian District"
    ],
    "name:fra_x_preferred": [
      "Pulandian"
    ],
    "name:gan_x_preferred": [
      "普兰店区"
    ],
    "name:jpn_x_preferred": [
      "普蘭店区"
    ],
    "name:kor_x_preferred": [
      "푸란뎬 시"
    ],
    "name:nan_x_preferred": [
      "Phó͘-lân-tiàm-khu"
    ],
    "name:nld_x_preferred": [
      "Pulandian"
    ],
    "name:nob_x_preferred": [
      "Pulandian"
    ],
    "name:rus_x_preferred": [
      "Пуланьдянь"
    ],
    "name:spa_x_preferred": [
      "Pulandian"
    ],
    "name:swe_x_preferred": [
      "Pulandian"
    ],
    "name:und_x_variant": [
      "Xinjin"
    ],
    "name:urd_x_preferred": [
      "پولاندیان"
    ],
    "name:wuu_x_preferred": [
      "普兰店区"
    ],
    "name:zho_x_preferred": [
      "普兰店区"
    ],
    "qs:name": "普兰店",
    "qs:name_adm0": "中國",
    "qs:name_adm1": "辽宁省",
    "qs:photos_9k": 1,
    "qs:photos_9r": 3,
    "qs:photos_all": 92,
    "qs:photos_sr": 0,
    "qs:placetype": "Town",
    "qs:pop_sr": "9",
    "wd:wordcount": 358,
    "wof:name": "普兰店",
    "wof:placetype": "locality",
    "wof:population": 104277
  },
  "geometry": {
    "coordinates": [
      121.96694,
      39.39528
    ],
    "type": "Point"
  }
}