{
  "type": "Feature",
  "properties": {
    "gn:admin1_code": "7.0",
    "gn:asciiname": "Jiangshi",
    "gn:country_code": "CN",
    "gn:dem": 350,
    "gn:feature_class": "P",
    "gn:feature_code": "PPL",
    "gn:name": "Jiangshi",
    "gn:population": 0,
    "gn:timezone": "Asia/Shanghai",
    "iso:country": "CN",
    "name:deu_x_preferred": [
      "Jiang Shi"
    ],
    "name:epo_x_preferred": [
      "Ĝjangŝio"
    ],
    "name:fra_x_preferred": [
      "Jiangshi"
    ],
    "name:ind_x_preferred": [
      "Jiangshi"
    ],
    "name:jpn_x_preferred": [
      "キョンシー"
    ],
    "name:msa_x_preferred": [
      "Jiang Shi"
    ],
    "name:por_x_preferred": [
      "Jiangshi"
    ],
    "name:rus_x_preferred": [
      "Цзянши"
    ],
    "name:spa_x_preferred": [
      "Jiang Shi"
    ],
    "name:swe_x_preferred": [
      "Kiang-Tsi"
    ],
    "name:tha_x_preferred": [
      "เจียงซือ"
    ],
    "name:vie_x_preferred": [
      "Cương thi"
    ],
    "name:zho_x_preferred": [
      "将石"
    ],
    "wof:name": "Jiangshi",
    "wof:placetype": "locality"
  },
  "geometry": {
    "coordinates": [
      117.26659,
      27.09244
    ],
    "type": "Point"
  }
}