{
  "type": "Feature",
  "properties": {
    "gn:admin1_code": "4.0",
    "gn:asciiname": "Xiangxiang",
    "gn:country_code": "CN",
    "gn:dem": 31,
    "gn:feature_class": "P",
    "gn:feature_code": "PPL",
    "gn:name": "Xiangxiang",
    "gn:population": 0,
    "gn:timezone": "Asia/Shanghai",
    "iso:country": "CN",
    "name:ceb_x_preferred": [
      "Xiangxiang"
    ],
    "name:deu_x_preferred": [
      "Xiangxiang"
    ],
    "name:fra_x_preferred": [
      "Xiangxiang"
    ],
    "name:hak_x_preferred": [
      "Siong-hiông-sṳ"
    ],
    "name:ita_x_preferred": [
      "Xiangxiang"
    ],
    "name:jpn_x_preferred": [
      "湘郷市"
    ],
    "name:kik_x_preferred": [
      "Xiangxiang"
    ],
    "name:kor_x_preferred": [
      "샹샹시"
    ],
    "name:mlg_x_preferred": [
      "Xiangxiang"
    ],
    "name:nor_x_preferred": [
      "Xiangxiang"
    ],
    "name:pam_x_preferred": [
      "Xiangxiang"
    ],
    "name:pol_x_preferred": [
      "Xiangxiang"
    ],
    "name:swe_x_preferred": [
      "Xiangxiang"
    ],
    "name:vie_x_preferred": [
      "Tương Hương"
    ],
    "name:war_x_preferred": [
      "Xiangxiang"
    ],
    "name:wuu_x_preferred": [
      "湘乡市"
    ],
    "name:zho_x_preferred": [
      "香巷"
    ],
    "name:zho_x_variant": [
      "湘乡市"
    ],
    "wof:name": "Xiangxiang",
    "wof:placetype": "locality"
  },
  "geometry": {
    "coordinates": [
      119.34658,
      32.45745
    ],
    "type": "Point"
  }
}