{
  "type": "Feature",
  "properties": {
    "gn:admin1_code": "13",
    "gn:asciiname": "Arele Caochang",
    "gn:country_code": "CN",
    "gn:dem": 1273,
    "gn:feature_class": "P",
    "gn:feature_code": "PPLF",
    "gn:name": "Arele Caochang",
    "gn:population": 0,
    "gn:timezone": "Asia/Shanghai",
    "iso:country": "CN",
    "name:zho_x_preferred": [
      "阿热勒草场"
    ],
    "wof:name": "Arele Caochang",
    "wof:placetype": "locality"
  },
  "geometry": {
    "coordinates": [
      76.18908,
      39.17179
    ],
    "type": "Point"
  }
}