{
  "type": "Feature",
  "properties": {
    "gn:admin1_code": "10.0",
    "gn:asciiname": "Diaoyutai",
    "gn:country_code": "CN",
    "gn:dem": 93,
    "gn:feature_class": "P",
    "gn:feature_code": "PPL",
    "gn:name": "Diaoyutai",
    "gn:population": 0,
    "gn:timezone": "Asia/Shanghai",
    "iso:country": "CN",
    "name:und_x_variant": [
      "钓鱼台"
    ],
    "wof:name": "Diaoyutai",
    "wof:placetype": "locality"
  },
  "geometry": {
    "coordinates": [
      114.84028,
      38.66019
    ],
    "type": "Point"
  }
}