{
  "type": "Feature",
  "properties": {
    "gn:admin1_code": "10.0",
    "gn:asciiname": "Zhongyukou",
    "gn:country_code": "CN",
    "gn:dem": 151,
    "gn:feature_class": "P",
    "gn:feature_code": "PPL",
    "gn:name": "Zhongyukou",
    "gn:population": 0,
    "gn:timezone": "Asia/Shanghai",
    "iso:country": "CN",
    "name:zho_x_preferred": [
      "重峪口"
    ],
    "name:zho_x_variant": [
      "中鱼口乡"
    ],
    "wof:name": "Zhongyukou",
    "wof:placetype": "locality"
  },
  "geometry": {
    "coordinates": [
      119.07447,
      40.07537
    ],
    "type": "Point"
  }
}