{
  "type": "Feature",
  "properties": {
    "gn:admin1_code": "30.0",
    "gn:asciiname": "Jiu'ao",
    "gn:country_code": "CN",
    "gn:dem": 9,
    "gn:feature_class": "P",
    "gn:feature_code": "PPL",
    "gn:name": "Jiu’ao",
    "gn:population": 0,
    "gn:timezone": "Asia/Shanghai",
    "iso:country": "CN",
    "name:und_x_variant": [
      "Jiu’ao"
    ],
    "name:zho_x_preferred": [
      "旧澳"
    ],
    "wof:name": "Jiu'ao",
    "wof:placetype": "locality"
  },
  "geometry": {
    "coordinates": [
      112.5836,
      21.87537
    ],
    "type": "Point"
  }
}