{
  "type": "Feature",
  "properties": {
    "gn:admin1_code": "28",
    "gn:asciiname": "Liqizhuang",
    "gn:country_code": "CN",
    "gn:dem": 6,
    "gn:feature_class": "P",
    "gn:feature_code": "PPLA4",
    "gn:name": "Liqizhuang",
    "gn:population": 0,
    "gn:timezone": "Asia/Shanghai",
    "iso:country": "CN",
    "name:und_x_variant": [
      "Li-ch’i-chuang",
      "Liqizhuang",
      "Liqizhuang Jiedao"
    ],
    "name:zho_x_preferred": [
      "李七庄"
    ],
    "name:zho_x_variant": [
      "李七庄街道"
    ],
    "wof:name": "Liqizhuang",
    "wof:placetype": "locality"
  },
  "geometry": {
    "coordinates": [
      117.16198,
      39.06982
    ],
    "type": "Point"
  }
}