{
  "type": "Feature",
  "properties": {
    "gn:admin1_code": "30.0",
    "gn:asciiname": "Siwan",
    "gn:country_code": "CN",
    "gn:dem": 24,
    "gn:feature_class": "P",
    "gn:feature_code": "PPL",
    "gn:name": "Siwan",
    "gn:population": 0,
    "gn:timezone": "Asia/Shanghai",
    "iso:country": "CN",
    "name:ara_x_preferred": [
      "سيوان"
    ],
    "name:bih_x_preferred": [
      "सिवान"
    ],
    "name:bpy_x_preferred": [
      "সিৱান"
    ],
    "name:bre_x_preferred": [
      "Siwan"
    ],
    "name:cym_x_preferred": [
      "Siwan"
    ],
    "name:deu_x_preferred": [
      "Siwan"
    ],
    "name:ind_x_preferred": [
      "Siwan"
    ],
    "name:msa_x_preferred": [
      "Siwan"
    ],
    "name:zho_x_preferred": [
      "寺湾"
    ],
    "wof:name": "Siwan",
    "wof:placetype": "locality"
  },
  "geometry": {
    "coordinates": [
      112.43611,
      23.4852
    ],
    "type": "Point"
  }
}