{
  "type": "Feature",
  "properties": {
    "gn:admin1_code": "32.0",
    "gn:asciiname": "Tongba",
    "gn:country_code": "CN",
    "gn:dem": 739,
    "gn:feature_class": "P",
    "gn:feature_code": "PPL",
    "gn:name": "Tongba",
    "gn:population": 0,
    "gn:timezone": "Asia/Shanghai",
    "iso:country": "CN",
    "name:deu_x_preferred": [
      "Tongba"
    ],
    "name:fra_x_preferred": [
      "Tongba"
    ],
    "name:nep_x_preferred": [
      "तोङवा"
    ],
    "name:nld_x_preferred": [
      "Tongba"
    ],
    "name:pol_x_preferred": [
      "Tongba"
    ],
    "name:por_x_preferred": [
      "Tongba"
    ],
    "name:ukr_x_preferred": [
      "Тонгба"
    ],
    "name:zho_x_preferred": [
      "通坝"
    ],
    "wof:name": "Tongba",
    "wof:placetype": "locality"
  },
  "geometry": {
    "coordinates": [
      105.082,
      32.4898
    ],
    "type": "Point"
  }
}