{
  "type": "Feature",
  "properties": {
    "gn:admin1_code": "10.0",
    "gn:asciiname": "Donggezhuang",
    "gn:country_code": "CN",
    "gn:dem": 107,
    "gn:feature_class": "P",
    "gn:feature_code": "PPL",
    "gn:name": "Donggezhuang",
    "gn:population": 0,
    "gn:timezone": "Asia/Shanghai",
    "iso:country": "CN",
    "name:zho_x_preferred": [
      "董各庄"
    ],
    "wof:name": "Donggezhuang",
    "wof:placetype": "locality"
  },
  "geometry": {
    "coordinates": [
      119.30526,
      40.07009
    ],
    "type": "Point"
  }
}