{
  "type": "Feature",
  "properties": {
    "gn:admin1_code": "15.0",
    "gn:asciiname": "Wu'ercun",
    "gn:country_code": "CN",
    "gn:dem": 1356,
    "gn:feature_class": "P",
    "gn:feature_code": "PPL",
    "gn:name": "Wu’ercun",
    "gn:population": 0,
    "gn:timezone": "Asia/Shanghai",
    "iso:country": "CN",
    "name:und_x_variant": [
      "Wu’ercun"
    ],
    "name:zho_x_preferred": [
      "五二村"
    ],
    "wof:name": "Wu'ercun",
    "wof:placetype": "locality"
  },
  "geometry": {
    "coordinates": [
      99.9054,
      39.3743
    ],
    "type": "Point"
  }
}