{
  "type": "Feature",
  "properties": {
    "gn:admin1_code": "16.0",
    "gn:asciiname": "Liuguang",
    "gn:country_code": "CN",
    "gn:dem": 146,
    "gn:feature_class": "P",
    "gn:feature_code": "PPL",
    "gn:name": "Liuguang",
    "gn:population": 0,
    "gn:timezone": "Asia/Shanghai",
    "iso:country": "CN",
    "name:zho_x_preferred": [
      "六广"
    ],
    "wof:name": "Liuguang",
    "wof:placetype": "locality"
  },
  "geometry": {
    "coordinates": [
      109.385,
      24.6163
    ],
    "type": "Point"
  }
}