{
  "type": "Feature",
  "properties": {
    "gn:admin1_code": "26.0",
    "gn:asciiname": "Xiecun",
    "gn:cc2": "CN",
    "gn:country_code": "CN",
    "gn:dem": 477,
    "gn:feature_class": "P",
    "gn:feature_code": "PPL",
    "gn:name": "Xiecun",
    "gn:population": 0,
    "gn:timezone": "Asia/Shanghai",
    "iso:country": "CN",
    "name:und_x_variant": [
      "Hsieh-ts’un-chen",
      "Hsih-ts’un-chen",
      "Hsieh-ts’un",
      "Xiecun"
    ],
    "wof:name": "Xiecun",
    "wof:placetype": "locality"
  },
  "geometry": {
    "coordinates": [
      107.4025,
      33.18083
    ],
    "type": "Point"
  }
}