{
  "type": "Feature",
  "properties": {
    "gn:admin1_code": "4.0",
    "gn:asciiname": "Lianhecun",
    "gn:country_code": "CN",
    "gn:dem": -1,
    "gn:feature_class": "P",
    "gn:feature_code": "PPL",
    "gn:name": "Lianhecun",
    "gn:population": 0,
    "gn:timezone": "Asia/Shanghai",
    "iso:country": "CN",
    "name:zho_x_preferred": [
      "联合村"
    ],
    "wof:name": "Lianhecun",
    "wof:placetype": "locality"
  },
  "geometry": {
    "coordinates": [
      120.22729,
      34.21991
    ],
    "type": "Point"
  }
}