{
  "type": "Feature",
  "properties": {
    "gn:admin1_code": "7.0",
    "gn:asciiname": "Chishuiyang",
    "gn:country_code": "CN",
    "gn:dem": 594,
    "gn:feature_class": "P",
    "gn:feature_code": "PPL",
    "gn:name": "Chishuiyang",
    "gn:population": 0,
    "gn:timezone": "Asia/Shanghai",
    "iso:country": "CN",
    "name:zho_x_preferred": [
      "赤水洋"
    ],
    "wof:name": "Chishuiyang",
    "wof:placetype": "locality"
  },
  "geometry": {
    "coordinates": [
      116.5404,
      25.24167000000001
    ],
    "type": "Point"
  }
}