{
  "type": "Feature",
  "properties": {
    "gn:admin1_code": "2.0",
    "gn:asciiname": "Xiashanmen",
    "gn:country_code": "CN",
    "gn:dem": 123,
    "gn:feature_class": "P",
    "gn:feature_code": "PPL",
    "gn:name": "Xiashanmen",
    "gn:population": 0,
    "gn:timezone": "Asia/Shanghai",
    "iso:country": "CN",
    "name:zho_x_preferred": [
      "下山门"
    ],
    "wof:name": "Xiashanmen",
    "wof:placetype": "locality"
  },
  "geometry": {
    "coordinates": [
      120.0054,
      28.8346
    ],
    "type": "Point"
  }
}