{
  "type": "Feature",
  "properties": {
    "gn:admin1_code": "24.0",
    "gn:asciiname": "Shanding",
    "gn:country_code": "CN",
    "gn:dem": 1024,
    "gn:feature_class": "P",
    "gn:feature_code": "PPL",
    "gn:name": "Shanding",
    "gn:population": 0,
    "gn:timezone": "Asia/Shanghai",
    "iso:country": "CN",
    "name:und_x_variant": [
      "山顶"
    ],
    "wof:name": "Shanding",
    "wof:placetype": "locality"
  },
  "geometry": {
    "coordinates": [
      111.64646,
      35.87461
    ],
    "type": "Point"
  }
}