{
  "type": "Feature",
  "properties": {
    "gn:admin1_code": "3",
    "gn:asciiname": "Qingnian Zonghe Kenzhichang",
    "gn:country_code": "CN",
    "gn:dem": 80,
    "gn:feature_class": "P",
    "gn:feature_code": "PPLF",
    "gn:name": "Qingnian Zonghe Kenzhichang",
    "gn:population": 0,
    "gn:timezone": "Asia/Shanghai",
    "iso:country": "CN",
    "name:und_x_variant": [
      "青年综合垦殖场",
      "Qingnianzonghekenzhichang"
    ],
    "name:zho_x_preferred": [
      "Qingnian Zonghe Kenzhichang"
    ],
    "wof:name": "Qingnian Zonghe Kenzhichang",
    "wof:placetype": "locality"
  },
  "geometry": {
    "coordinates": [
      116.27079,
      27.67436
    ],
    "type": "Point"
  }
}