{
  "type": "Feature",
  "properties": {
    "gn:admin1_code": "20.0",
    "gn:asciiname": "Zaoqingshan",
    "gn:country_code": "CN",
    "gn:dem": 1431,
    "gn:feature_class": "P",
    "gn:feature_code": "PPL",
    "gn:name": "Zaoqingshan",
    "gn:population": 0,
    "gn:timezone": "Asia/Shanghai",
    "iso:country": "CN",
    "name:und_x_variant": [
      "赵青山"
    ],
    "wof:name": "Zaoqingshan",
    "wof:placetype": "locality"
  },
  "geometry": {
    "coordinates": [
      111.6431,
      39.7772
    ],
    "type": "Point"
  }
}