{
  "type": "Feature",
  "properties": {
    "gn:admin1_code": "29",
    "gn:asciiname": "Luojiasongyuan",
    "gn:country_code": "CN",
    "gn:dem": 1898,
    "gn:feature_class": "P",
    "gn:feature_code": "PPL",
    "gn:name": "Luojiasongyuan",
    "gn:population": 0,
    "gn:timezone": "Asia/Shanghai",
    "iso:country": "CN",
    "name:zho_x_preferred": [
      "罗家松园"
    ],
    "wof:name": "Luojiasongyuan",
    "wof:placetype": "locality"
  },
  "geometry": {
    "coordinates": [
      102.98555,
      24.64434
    ],
    "type": "Point"
  }
}