{
  "type": "Feature",
  "properties": {
    "gn:admin1_code": "16.0",
    "gn:asciiname": "Zhai'ao",
    "gn:country_code": "CN",
    "gn:dem": 293,
    "gn:feature_class": "P",
    "gn:feature_code": "PPL",
    "gn:name": "Zhai’ao",
    "gn:population": 0,
    "gn:timezone": "Asia/Shanghai",
    "iso:country": "CN",
    "name:und_x_variant": [
      "Zhai’ao"
    ],
    "name:zho_x_preferred": [
      "寨熬"
    ],
    "wof:name": "Zhai'ao",
    "wof:placetype": "locality"
  },
  "geometry": {
    "coordinates": [
      107.798,
      24.7608
    ],
    "type": "Point"
  }
}