{
  "type": "Feature",
  "properties": {
    "gn:admin1_code": "4.0",
    "gn:asciiname": "Hongxing",
    "gn:country_code": "CN",
    "gn:dem": 6,
    "gn:feature_class": "P",
    "gn:feature_code": "PPL",
    "gn:name": "Hongxing",
    "gn:population": 0,
    "gn:timezone": "Asia/Shanghai",
    "iso:country": "CN",
    "name:ceb_x_preferred": [
      "Hongxing"
    ],
    "name:deu_x_preferred": [
      "Hongxing"
    ],
    "name:zho_x_preferred": [
      "红星"
    ],
    "wof:name": "Hongxing",
    "wof:placetype": "locality"
  },
  "geometry": {
    "coordinates": [
      120.05657,
      32.16094
    ],
    "type": "Point"
  }
}