{
  "type": "Feature",
  "properties": {
    "gn:admin1_code": "20",
    "gn:asciiname": "Dongtucheng",
    "gn:country_code": "CN",
    "gn:dem": 1567,
    "gn:feature_class": "P",
    "gn:feature_code": "PPLA4",
    "gn:name": "Dongtucheng",
    "gn:population": 0,
    "gn:timezone": "Asia/Shanghai",
    "iso:country": "CN",
    "name:und_x_variant": [
      "Tung-t’u-ch’eng-tzu",
      "Dongtucheng Xiang",
      "Dongtucheng",
      "东土城",
      "东土城乡"
    ],
    "wof:name": "Dongtucheng",
    "wof:placetype": "locality"
  },
  "geometry": {
    "coordinates": [
      111.26077,
      41.11859000000001
    ],
    "type": "Point"
  }
}