{
  "type": "Feature",
  "properties": {
    "gn:admin1_code": "2",
    "gn:asciiname": "Aokeng",
    "gn:country_code": "CN",
    "gn:dem": 345,
    "gn:feature_class": "P",
    "gn:feature_code": "PPL",
    "gn:name": "Aokeng",
    "gn:population": 0,
    "gn:timezone": "Asia/Shanghai",
    "iso:country": "CN",
    "name:zho_x_preferred": [
      "鳌坑"
    ],
    "wof:name": "Aokeng",
    "wof:placetype": "locality"
  },
  "geometry": {
    "coordinates": [
      121.03875,
      29.32686
    ],
    "type": "Point"
  }
}