{
  "type": "Feature",
  "properties": {
    "gn:admin1_code": "11.0",
    "gn:asciiname": "Lijiawan",
    "gn:country_code": "CN",
    "gn:dem": 162,
    "gn:feature_class": "P",
    "gn:feature_code": "PPL",
    "gn:name": "Lijiawan",
    "gn:population": 0,
    "gn:timezone": "Asia/Shanghai",
    "iso:country": "CN",
    "name:zho_x_preferred": [
      "李家湾"
    ],
    "wof:name": "Lijiawan",
    "wof:placetype": "locality"
  },
  "geometry": {
    "coordinates": [
      110.09281,
      27.92269000000001
    ],
    "type": "Point"
  }
}