{
  "type": "Feature",
  "properties": {
    "gn:admin1_code": "8.0",
    "gn:asciiname": "Xingwangcun",
    "gn:country_code": "CN",
    "gn:dem": 174,
    "gn:feature_class": "P",
    "gn:feature_code": "PPL",
    "gn:name": "Xingwangcun",
    "gn:population": 0,
    "gn:timezone": "Asia/Shanghai",
    "iso:country": "CN",
    "name:zho_x_preferred": [
      "兴旺村"
    ],
    "wof:name": "Xingwangcun",
    "wof:placetype": "locality"
  },
  "geometry": {
    "coordinates": [
      126.49138,
      45.38025
    ],
    "type": "Point"
  }
}