{
  "type": "Feature",
  "properties": {
    "gn:admin1_code": "11",
    "gn:asciiname": "Huangjialing",
    "gn:country_code": "CN",
    "gn:dem": 411,
    "gn:feature_class": "P",
    "gn:feature_code": "PPL",
    "gn:name": "Huangjialing",
    "gn:population": 0,
    "gn:timezone": "Asia/Shanghai",
    "iso:country": "CN",
    "name:zho_x_preferred": [
      "黄家岭"
    ],
    "wof:name": "Huangjialing",
    "wof:placetype": "locality"
  },
  "geometry": {
    "coordinates": [
      112.0152,
      26.55562
    ],
    "type": "Point"
  }
}