{
  "type": "Feature",
  "properties": {
    "gn:admin1_code": "10.0",
    "gn:asciiname": "Nanyuanxilou",
    "gn:country_code": "CN",
    "gn:dem": 12,
    "gn:feature_class": "P",
    "gn:feature_code": "PPL",
    "gn:name": "Nanyuanxilou",
    "gn:population": 0,
    "gn:timezone": "Asia/Shanghai",
    "iso:country": "CN",
    "name:zho_x_preferred": [
      "南园西楼"
    ],
    "wof:name": "Nanyuanxilou",
    "wof:placetype": "locality"
  },
  "geometry": {
    "coordinates": [
      119.73722,
      39.99751
    ],
    "type": "Point"
  }
}