{
  "type": "Feature",
  "properties": {
    "gn:admin1_code": "31",
    "gn:asciiname": "Xiqing Nongchang Ershisidui",
    "gn:country_code": "CN",
    "gn:dem": 56,
    "gn:feature_class": "P",
    "gn:feature_code": "PPLF",
    "gn:name": "Xiqing Nongchang Ershisidui",
    "gn:population": 0,
    "gn:timezone": "Asia/Shanghai",
    "iso:country": "CN",
    "name:und_x_variant": [
      "西庆农场二十四队",
      "Xiqingershiliulian"
    ],
    "wof:name": "Xiqing Nongchang Ershisidui",
    "wof:placetype": "locality"
  },
  "geometry": {
    "coordinates": [
      109.46389,
      19.61583
    ],
    "type": "Point"
  }
}