{
  "type": "Feature",
  "properties": {
    "gn:admin1_code": "24",
    "gn:asciiname": "Shangxin'an",
    "gn:country_code": "CN",
    "gn:dem": 1266,
    "gn:feature_class": "P",
    "gn:feature_code": "PPL",
    "gn:name": "Shangxin’an",
    "gn:population": 0,
    "gn:timezone": "Asia/Shanghai",
    "iso:country": "CN",
    "name:und_x_variant": [
      "Shang-hsin-an",
      "Shangxin’an",
      "上辛安"
    ],
    "wof:name": "Shangxin'an",
    "wof:placetype": "locality"
  },
  "geometry": {
    "coordinates": [
      113.66127,
      39.83104
    ],
    "type": "Point"
  }
}