{
  "type": "Feature",
  "properties": {
    "gn:admin1_code": "7.0",
    "gn:asciiname": "Gaolin",
    "gn:country_code": "CN",
    "gn:dem": 357,
    "gn:feature_class": "P",
    "gn:feature_code": "PPL",
    "gn:name": "Gaolin",
    "gn:population": 0,
    "gn:timezone": "Asia/Shanghai",
    "iso:country": "CN",
    "name:zho_x_preferred": [
      "高林"
    ],
    "wof:name": "Gaolin",
    "wof:placetype": "locality"
  },
  "geometry": {
    "coordinates": [
      117.0888,
      25.4291
    ],
    "type": "Point"
  }
}