{
  "type": "Feature",
  "properties": {
    "gn:admin1_code": "32.0",
    "gn:asciiname": "Huangyan",
    "gn:country_code": "CN",
    "gn:dem": 333,
    "gn:feature_class": "P",
    "gn:feature_code": "PPL",
    "gn:name": "Huangyan",
    "gn:population": 0,
    "gn:timezone": "Asia/Shanghai",
    "iso:country": "CN",
    "name:ara_x_preferred": [
      "هوانغيان"
    ],
    "name:ben_x_preferred": [
      "হুয়াংইয়ান"
    ],
    "name:ell_x_preferred": [
      "Χουανγκγουάν"
    ],
    "name:fas_x_preferred": [
      "هوانگیان"
    ],
    "name:heb_x_preferred": [
      "הואנגיאן"
    ],
    "name:hin_x_preferred": [
      "हुआंग्यान"
    ],
    "name:hun_x_preferred": [
      "Huangyan"
    ],
    "name:ind_x_preferred": [
      "Huangyan"
    ],
    "name:jpn_x_preferred": [
      "黄岩"
    ],
    "name:pol_x_preferred": [
      "Huangyan"
    ],
    "name:por_x_preferred": [
      "Huangyan"
    ],
    "name:spa_x_preferred": [
      "Huangyan"
    ],
    "name:tur_x_preferred": [
      "Huangyan"
    ],
    "name:ukr_x_preferred": [
      "Хуан’янь"
    ],
    "name:zho_x_preferred": [
      "黄岩"
    ],
    "wof:name": "Huangyan",
    "wof:placetype": "locality"
  },
  "geometry": {
    "coordinates": [
      105.174,
      28.9424
    ],
    "type": "Point"
  }
}