{
  "type": "Feature",
  "properties": {
    "iso:country": "CN",
    "name:eng_x_preferred": [
      "Huanggang"
    ],
    "name:zho_x_preferred": [
      "黄冈"
    ],
    "qs:name": "黄冈",
    "qs:name_adm0": "中國",
    "qs:name_adm1": "湖北省",
    "qs:photos": 144,
    "qs:photos_1k": 29,
    "qs:photos_9k": 1,
    "qs:photos_9r": 3,
    "qs:photos_all": 144,
    "qs:photos_sr": 3,
    "qs:placetype": "Town",
    "qs:pop_sr": "0",
    "wof:name": "Huanggang",
    "wof:placetype": "locality"
  },
  "geometry": {
    "coordinates": [
      114.865493,
      30.448895
    ],
    "type": "Point"
  }
}