{
  "type": "Feature",
  "properties": {
    "gn:admin1_code": "25",
    "gn:asciiname": "Gushan",
    "gn:country_code": "CN",
    "gn:dem": 22,
    "gn:feature_class": "P",
    "gn:feature_code": "PPLA4",
    "gn:name": "Gushan",
    "gn:population": 0,
    "gn:timezone": "Asia/Shanghai",
    "iso:country": "CN",
    "name:ceb_x_preferred": [
      "Gushan"
    ],
    "name:deu_x_preferred": [
      "Gushan"
    ],
    "name:swe_x_preferred": [
      "Gushan"
    ],
    "name:und_x_variant": [
      "Gushan Zhen"
    ],
    "name:zho_x_preferred": [
      "崮山"
    ],
    "name:zho_x_variant": [
      "崮山镇"
    ],
    "wof:name": "Gushan",
    "wof:placetype": "locality"
  },
  "geometry": {
    "coordinates": [
      122.23913,
      37.40821
    ],
    "type": "Point"
  }
}