{
  "type": "Feature",
  "properties": {
    "gn:admin1_code": "6.0",
    "gn:asciiname": "Wutumeiren",
    "gn:country_code": "CN",
    "gn:dem": 2873,
    "gn:feature_class": "P",
    "gn:feature_code": "PPLA4",
    "gn:name": "Wutumeiren",
    "gn:population": 0,
    "gn:timezone": "Asia/Urumqi",
    "iso:country": "CN",
    "name:und_x_variant": [
      "Wutumeiren Xiang"
    ],
    "name:zho_x_preferred": [
      "乌图美仁"
    ],
    "name:zho_x_variant": [
      "乌图美仁乡"
    ],
    "wof:name": "Wutumeiren",
    "wof:placetype": "locality"
  },
  "geometry": {
    "coordinates": [
      93.16113,
      36.90934
    ],
    "type": "Point"
  }
}