{
  "type": "Feature",
  "properties": {
    "gn:admin1_code": "13.0",
    "gn:asciiname": "Bole",
    "gn:country_code": "CN",
    "gn:dem": 509,
    "gn:feature_class": "P",
    "gn:feature_code": "PPL",
    "gn:name": "Bole",
    "gn:population": 0,
    "gn:timezone": "Asia/Shanghai",
    "iso:country": "CN",
    "name:ara_x_preferred": [
      "بولي"
    ],
    "name:deu_x_preferred": [
      "Bortala"
    ],
    "name:eng_x_preferred": [
      "Bole"
    ],
    "name:fin_x_preferred": [
      "Bole"
    ],
    "name:fra_x_preferred": [
      "Bole"
    ],
    "name:ita_x_preferred": [
      "Bole"
    ],
    "name:jpn_x_preferred": [
      "ボルタラ市"
    ],
    "name:kik_x_preferred": [
      "Bole"
    ],
    "name:kor_x_preferred": [
      "보러시"
    ],
    "name:lit_x_preferred": [
      "Boro Tala"
    ],
    "name:mon_x_preferred": [
      "Бортал хот"
    ],
    "name:nor_x_preferred": [
      "Bortala"
    ],
    "name:pol_x_preferred": [
      "Bole"
    ],
    "name:rus_x_preferred": [
      "Боро-Тала"
    ],
    "name:swe_x_preferred": [
      "Börtala"
    ],
    "name:tur_x_preferred": [
      "Bortala"
    ],
    "name:uig_x_preferred": [
      "بۆرتالا"
    ],
    "name:uig_x_variant": [
      "بورتالا شەھىرى"
    ],
    "name:urd_x_preferred": [
      "بولے"
    ],
    "name:vie_x_preferred": [
      "Bác Lạc"
    ],
    "name:war_x_preferred": [
      "Bole"
    ],
    "name:zho_x_preferred": [
      "博乐"
    ],
    "name:zho_x_variant": [
      "博樂",
      "Bólè",
      "博乐市"
    ],
    "wof:name": "Bole",
    "wof:placetype": "locality"
  },
  "geometry": {
    "coordinates": [
      82.06993,
      44.89334
    ],
    "type": "Point"
  }
}