{
  "type": "Feature",
  "properties": {
    "gn:admin1_code": "3.0",
    "gn:asciiname": "Fengtian",
    "gn:country_code": "CN",
    "gn:dem": 99,
    "gn:feature_class": "P",
    "gn:feature_code": "PPL",
    "gn:name": "Fengtian",
    "gn:population": 0,
    "gn:timezone": "Asia/Shanghai",
    "iso:country": "CN",
    "name:ceb_x_preferred": [
      "Fengtian"
    ],
    "name:deu_x_preferred": [
      "Fengtian"
    ],
    "name:pol_x_preferred": [
      "Fengtian"
    ],
    "name:rus_x_preferred": [
      "Фэнтянь"
    ],
    "name:vie_x_preferred": [
      "Phụng Thiên"
    ],
    "name:zho_x_preferred": [
      "丰田"
    ],
    "wof:name": "Fengtian",
    "wof:placetype": "locality"
  },
  "geometry": {
    "coordinates": [
      117.735,
      29.2126
    ],
    "type": "Point"
  }
}