{
  "type": "Feature",
  "properties": {
    "gn:admin1_code": "19.0",
    "gn:asciiname": "Qiandazitun",
    "gn:country_code": "CN",
    "gn:dem": 117,
    "gn:feature_class": "P",
    "gn:feature_code": "PPL",
    "gn:name": "Qiandazitun",
    "gn:population": 0,
    "gn:timezone": "Asia/Shanghai",
    "iso:country": "CN",
    "name:zho_x_preferred": [
      "钱搭子屯"
    ],
    "wof:name": "Qiandazitun",
    "wof:placetype": "locality"
  },
  "geometry": {
    "coordinates": [
      120.75212,
      40.98182
    ],
    "type": "Point"
  }
}