{
  "type": "Feature",
  "properties": {
    "gn:admin1_code": "32.0",
    "gn:asciiname": "Xianglong",
    "gn:country_code": "CN",
    "gn:dem": 357,
    "gn:feature_class": "P",
    "gn:feature_code": "PPL",
    "gn:name": "Xianglong",
    "gn:population": 0,
    "gn:timezone": "Asia/Shanghai",
    "iso:country": "CN",
    "name:cat_x_preferred": [
      "Xianglong zhaoi"
    ],
    "name:deu_x_preferred": [
      "Xianglong"
    ],
    "name:heb_x_preferred": [
      "שיאנגלונג"
    ],
    "name:ita_x_preferred": [
      "Xianglong zhaoi"
    ],
    "name:nor_x_preferred": [
      "Xianglong zhaoi"
    ],
    "name:rus_x_preferred": [
      "Xianglong zhaoi"
    ],
    "name:spa_x_preferred": [
      "Xianglong"
    ],
    "name:vie_x_preferred": [
      "Xianglong"
    ],
    "name:zho_x_preferred": [
      "祥龙"
    ],
    "wof:name": "Xianglong",
    "wof:placetype": "locality"
  },
  "geometry": {
    "coordinates": [
      105.70141,
      30.93361
    ],
    "type": "Point"
  }
}