{
  "type": "Feature",
  "properties": {
    "gn:admin1_code": "7.0",
    "gn:asciiname": "Luanzhou",
    "gn:country_code": "CN",
    "gn:dem": 760,
    "gn:feature_class": "P",
    "gn:feature_code": "PPL",
    "gn:name": "Luanzhou",
    "gn:population": 0,
    "gn:timezone": "Asia/Shanghai",
    "iso:country": "CN",
    "name:deu_x_preferred": [
      "Luanzhou"
    ],
    "name:fas_x_preferred": [
      "شهرستان لوانژوو"
    ],
    "name:ita_x_preferred": [
      "Luanzhou"
    ],
    "name:jpn_x_preferred": [
      "ラン州市"
    ],
    "name:kor_x_preferred": [
      "롼저우시"
    ],
    "name:nor_x_preferred": [
      "Luan"
    ],
    "name:rus_x_preferred": [
      "Луаньчжоу"
    ],
    "name:swe_x_preferred": [
      "Luan"
    ],
    "name:urd_x_preferred": [
      "لوانژؤ"
    ],
    "name:vie_x_preferred": [
      "Loan Châu"
    ],
    "name:zho_x_preferred": [
      "銮洲"
    ],
    "name:zho_x_variant": [
      "滦州市"
    ],
    "wof:name": "Luanzhou",
    "wof:placetype": "locality"
  },
  "geometry": {
    "coordinates": [
      117.55326,
      26.72972
    ],
    "type": "Point"
  }
}