{
  "type": "Feature",
  "properties": {
    "gn:admin1_code": "10",
    "gn:asciiname": "Shedigou",
    "gn:country_code": "CN",
    "gn:dem": 1142,
    "gn:feature_class": "P",
    "gn:feature_code": "PPL",
    "gn:name": "Shedigou",
    "gn:population": 0,
    "gn:timezone": "Asia/Shanghai",
    "iso:country": "CN",
    "name:zho_x_preferred": [
      "蛇地沟"
    ],
    "wof:name": "Shedigou",
    "wof:placetype": "locality"
  },
  "geometry": {
    "coordinates": [
      115.67691,
      40.98528
    ],
    "type": "Point"
  }
}