{
  "type": "Feature",
  "properties": {
    "gn:admin1_code": "32.0",
    "gn:asciiname": "Gaoping",
    "gn:country_code": "CN",
    "gn:dem": 1260,
    "gn:feature_class": "P",
    "gn:feature_code": "PPL",
    "gn:name": "Gaoping",
    "gn:population": 0,
    "gn:timezone": "Asia/Shanghai",
    "iso:country": "CN",
    "name:ara_x_preferred": [
      "قاوبينغ"
    ],
    "name:ceb_x_preferred": [
      "Gaoping Shi"
    ],
    "name:deu_x_preferred": [
      "Gaoping"
    ],
    "name:fra_x_preferred": [
      "Gaoping"
    ],
    "name:ita_x_preferred": [
      "Gaoping"
    ],
    "name:jpn_x_preferred": [
      "高平市"
    ],
    "name:kik_x_preferred": [
      "Gaoping"
    ],
    "name:kor_x_preferred": [
      "가오핑시"
    ],
    "name:mlg_x_preferred": [
      "Gaoping"
    ],
    "name:nld_x_preferred": [
      "Gaoping"
    ],
    "name:nor_x_preferred": [
      "Gaoping"
    ],
    "name:rus_x_preferred": [
      "Гаопин"
    ],
    "name:swe_x_preferred": [
      "Gaoping"
    ],
    "name:urd_x_preferred": [
      "گاوپنگ"
    ],
    "name:vie_x_preferred": [
      "Cao Bình"
    ],
    "name:zho_x_preferred": [
      "高坪"
    ],
    "name:zho_x_variant": [
      "高平市"
    ],
    "wof:name": "Gaoping",
    "wof:placetype": "locality"
  },
  "geometry": {
    "coordinates": [
      104.471,
      32.2008
    ],
    "type": "Point"
  }
}