{
  "type": "Feature",
  "properties": {
    "gn:admin1_code": "19.0",
    "gn:asciiname": "Sanchakou",
    "gn:country_code": "CN",
    "gn:dem": 137,
    "gn:feature_class": "P",
    "gn:feature_code": "PPL",
    "gn:name": "Sanchakou",
    "gn:population": 0,
    "gn:timezone": "Asia/Shanghai",
    "iso:country": "CN",
    "name:ceb_x_preferred": [
      "Sanchakou"
    ],
    "name:swe_x_preferred": [
      "Sanchakou"
    ],
    "name:zho_x_preferred": [
      "三叉口"
    ],
    "name:zho_x_variant": [
      "三岔口"
    ],
    "wof:name": "Sanchakou",
    "wof:placetype": "locality"
  },
  "geometry": {
    "coordinates": [
      122.04135,
      42.36071
    ],
    "type": "Point"
  }
}