{
  "type": "Feature",
  "properties": {
    "gn:admin1_code": "3.0",
    "gn:asciiname": "Zhenyuan",
    "gn:country_code": "CN",
    "gn:dem": 123,
    "gn:feature_class": "P",
    "gn:feature_code": "PPL",
    "gn:name": "Zhenyuan",
    "gn:population": 0,
    "gn:timezone": "Asia/Shanghai",
    "iso:country": "CN",
    "name:deu_x_preferred": [
      "Zhenyuan"
    ],
    "name:fra_x_preferred": [
      "Zhenyuan"
    ],
    "name:kor_x_preferred": [
      "전위안현"
    ],
    "name:rus_x_preferred": [
      "Чжэньюань"
    ],
    "name:swe_x_preferred": [
      "Zhenyuan"
    ],
    "name:und_x_variant": [
      "真源"
    ],
    "wof:name": "Zhenyuan",
    "wof:placetype": "locality"
  },
  "geometry": {
    "coordinates": [
      115.24481000000002,
      27.37355
    ],
    "type": "Point"
  }
}