{
  "type": "Feature",
  "properties": {
    "gn:admin1_code": "5.0",
    "gn:asciiname": "Zixing",
    "gn:country_code": "CN",
    "gn:dem": 52,
    "gn:feature_class": "P",
    "gn:feature_code": "PPL",
    "gn:name": "Zixing",
    "gn:population": 0,
    "gn:timezone": "Asia/Shanghai",
    "iso:country": "CN",
    "name:ara_x_preferred": [
      "زيكسينج"
    ],
    "name:ben_x_preferred": [
      "জিশিং"
    ],
    "name:ceb_x_preferred": [
      "Zixing Shi"
    ],
    "name:deu_x_preferred": [
      "Zixing"
    ],
    "name:ell_x_preferred": [
      "Ζιξίνγκ"
    ],
    "name:fas_x_preferred": [
      "زیکسینگ"
    ],
    "name:fra_x_preferred": [
      "Zixing"
    ],
    "name:hak_x_preferred": [
      "Chṳ̂-hîn-sṳ"
    ],
    "name:heb_x_preferred": [
      "זיקסינג"
    ],
    "name:hin_x_preferred": [
      "ज़िक्सिंग"
    ],
    "name:hun_x_preferred": [
      "Zixing"
    ],
    "name:ind_x_preferred": [
      "Zixing"
    ],
    "name:ita_x_preferred": [
      "Zixing"
    ],
    "name:jpn_x_preferred": [
      "資興市"
    ],
    "name:kik_x_preferred": [
      "Zixing"
    ],
    "name:kor_x_preferred": [
      "쯔싱시"
    ],
    "name:mlg_x_preferred": [
      "Zixing"
    ],
    "name:nld_x_preferred": [
      "Zixing"
    ],
    "name:nor_x_preferred": [
      "Zixing"
    ],
    "name:pam_x_preferred": [
      "Zixing"
    ],
    "name:pol_x_preferred": [
      "Zixing"
    ],
    "name:por_x_preferred": [
      "Zixing"
    ],
    "name:spa_x_preferred": [
      "Zixing"
    ],
    "name:swe_x_preferred": [
      "Zixing"
    ],
    "name:tur_x_preferred": [
      "Zixing"
    ],
    "name:ukr_x_preferred": [
      "Цзисінь"
    ],
    "name:und_x_variant": [
      "自兴"
    ],
    "name:urd_x_preferred": [
      "ززنگ"
    ],
    "name:vie_x_preferred": [
      "Tư Hưng"
    ],
    "name:war_x_preferred": [
      "Zixing"
    ],
    "name:zho_x_preferred": [
      "资兴市"
    ],
    "wof:name": "Zixing",
    "wof:placetype": "locality"
  },
  "geometry": {
    "coordinates": [
      130.42317,
      42.90194
    ],
    "type": "Point"
  }
}