{
  "type": "Feature",
  "properties": {
    "gn:admin1_code": "30.0",
    "gn:asciiname": "Neihu",
    "gn:country_code": "CN",
    "gn:dem": 11,
    "gn:feature_class": "P",
    "gn:feature_code": "PPLA4",
    "gn:name": "Neihu",
    "gn:population": 0,
    "gn:timezone": "Asia/Shanghai",
    "iso:country": "CN",
    "name:fas_x_preferred": [
      "نیهو"
    ],
    "name:und_x_variant": [
      "Neihu Zhen"
    ],
    "name:zho_x_preferred": [
      "内湖"
    ],
    "name:zho_x_variant": [
      "内湖镇"
    ],
    "wof:name": "Neihu",
    "wof:placetype": "locality"
  },
  "geometry": {
    "coordinates": [
      115.82403,
      22.97882
    ],
    "type": "Point"
  }
}