{
  "type": "Feature",
  "properties": {
    "gn:admin1_code": "04",
    "gn:asciiname": "Caixiangcun",
    "gn:country_code": "CN",
    "gn:dem": 30,
    "gn:feature_class": "P",
    "gn:feature_code": "PPL",
    "gn:name": "Caixiangcun",
    "gn:population": 0,
    "gn:timezone": "Asia/Shanghai",
    "iso:country": "CN",
    "name:und_x_variant": [
      "Ts’ai-hsiang-chen",
      "Ts’ai-hsiang",
      "Ts’ai-chia-chen",
      "Caixiang",
      "Caixiangcun"
    ],
    "name:zho_x_preferred": [
      "蔡巷"
    ],
    "name:zho_x_variant": [
      "蔡巷村"
    ],
    "wof:name": "Caixiangcun",
    "wof:placetype": "locality"
  },
  "geometry": {
    "coordinates": [
      119.22729,
      31.71613
    ],
    "type": "Point"
  }
}