{
  "type": "Feature",
  "properties": {
    "gn:country": "CN",
    "gn:fcode": "PPL",
    "gn:population": 198423,
    "iso:country": "CN",
    "name:ceb_x_preferred": [
      "Kaiyuan"
    ],
    "name:deu_x_preferred": [
      "Kaiyuan"
    ],
    "name:fra_x_preferred": [
      "Kaiyuan"
    ],
    "name:kor_x_preferred": [
      "카이위안시"
    ],
    "name:mlg_x_preferred": [
      "Kaiyuan"
    ],
    "name:nld_x_preferred": [
      "Kaiyuan"
    ],
    "name:nor_x_preferred": [
      "Kaiyuan"
    ],
    "name:pol_x_preferred": [
      "Kaiyuan"
    ],
    "name:rus_x_preferred": [
      "Кайюань"
    ],
    "name:swe_x_preferred": [
      "Kaiyuan"
    ],
    "name:und_x_variant": [
      "Ami-hsien"
    ],
    "qs:name": "Kaiyuan",
    "qs:photos_9r": 0,
    "qs:photos_sr": 0,
    "qs:pop_sr": "9",
    "wd:wordcount": 147,
    "wof:name": "Kaiyuan",
    "wof:placetype": "locality",
    "wof:population": 198423
  },
  "geometry": {
    "coordinates": [
      103.30372,
      23.69767
    ],
    "type": "Point"
  }
}