{
  "type": "Feature",
  "properties": {
    "gn:admin1_code": "20.0",
    "gn:asciiname": "Gala Bu'er",
    "gn:country_code": "CN",
    "gn:dem": 553,
    "gn:feature_class": "P",
    "gn:feature_code": "PPL",
    "gn:name": "Gala Bu’er",
    "gn:population": 0,
    "gn:timezone": "Asia/Shanghai",
    "iso:country": "CN",
    "name:und_x_variant": [
      "Gala Bu’er"
    ],
    "name:zho_x_preferred": [
      "嘎拉布尔"
    ],
    "wof:name": "Gala Bu'er",
    "wof:placetype": "locality"
  },
  "geometry": {
    "coordinates": [
      118.09105,
      49.26108
    ],
    "type": "Point"
  }
}