{
  "type": "Feature",
  "properties": {
    "gn:admin1_code": "29.0",
    "gn:asciiname": "Shengping",
    "gn:country_code": "CN",
    "gn:dem": 3362,
    "gn:feature_class": "P",
    "gn:feature_code": "PPLA3",
    "gn:name": "Shengping",
    "gn:population": 0,
    "gn:timezone": "Asia/Shanghai",
    "iso:country": "CN",
    "name:und_x_variant": [
      "A-tun",
      "Atun-hsien",
      "Tehtsin",
      "A-tun-tzu",
      "Tehching",
      "Atun-tse",
      "Atung",
      "Dong",
      "Atuntze",
      "Shengping",
      "Deqin"
    ],
    "name:zho_x_preferred": [
      "Te-ch’in"
    ],
    "name:zho_x_variant": [
      "Te-ch’in-she-chih-chü",
      "Te-ch’in-hsien-tsang-tsu-tzu-chih-ch’ü",
      "升平",
      "德钦"
    ],
    "wof:name": "Shengping",
    "wof:placetype": "locality"
  },
  "geometry": {
    "coordinates": [
      98.91139,
      28.48563
    ],
    "type": "Point"
  }
}