{
  "type": "Feature",
  "properties": {
    "gn:admin1_code": "7.0",
    "gn:asciiname": "Nanshan",
    "gn:country_code": "CN",
    "gn:dem": 487,
    "gn:feature_class": "P",
    "gn:feature_code": "PPL",
    "gn:name": "Nanshan",
    "gn:population": 0,
    "gn:timezone": "Asia/Shanghai",
    "iso:country": "CN",
    "name:cat_x_preferred": [
      "Nanshan"
    ],
    "name:ceb_x_preferred": [
      "Nanshan"
    ],
    "name:deu_x_preferred": [
      "Nanshan"
    ],
    "name:eus_x_preferred": [
      "Nanshan"
    ],
    "name:fra_x_preferred": [
      "Nanshan"
    ],
    "name:jpn_x_preferred": [
      "南山区"
    ],
    "name:kor_x_preferred": [
      "난산구"
    ],
    "name:nld_x_preferred": [
      "Nanshan"
    ],
    "name:nor_x_preferred": [
      "Nanshan"
    ],
    "name:rus_x_preferred": [
      "Наньшань"
    ],
    "name:swe_x_preferred": [
      "Nanshan"
    ],
    "name:zho_x_preferred": [
      "南山"
    ],
    "name:zho_x_variant": [
      "南山区"
    ],
    "wof:name": "Nanshan",
    "wof:placetype": "locality"
  },
  "geometry": {
    "coordinates": [
      116.78662,
      25.12418
    ],
    "type": "Point"
  }
}