{
  "type": "Feature",
  "properties": {
    "gn:admin1_code": "30",
    "gn:asciiname": "Jiadong",
    "gn:country_code": "CN",
    "gn:dem": 667,
    "gn:feature_class": "P",
    "gn:feature_code": "PPL",
    "gn:name": "Jiadong",
    "gn:population": 0,
    "gn:timezone": "Asia/Urumqi",
    "iso:country": "CN",
    "name:deu_x_preferred": [
      "Jiadong"
    ],
    "name:hak_x_preferred": [
      "Kâ-tûng-hiông"
    ],
    "name:jpn_x_preferred": [
      "佳冬郷"
    ],
    "name:kor_x_preferred": [
      "자둥향"
    ],
    "name:vie_x_preferred": [
      "Giai Đông"
    ],
    "name:zho_x_preferred": [
      "家垌"
    ],
    "name:zho_x_variant": [
      "佳冬鄉"
    ],
    "wof:name": "Jiadong",
    "wof:placetype": "locality"
  },
  "geometry": {
    "coordinates": [
      111.29719,
      22.28298
    ],
    "type": "Point"
  }
}