{
  "type": "Feature",
  "properties": {
    "gn:admin1_code": "18.0",
    "gn:asciiname": "Maobiling Shangzhai",
    "gn:country_code": "CN",
    "gn:dem": 793,
    "gn:feature_class": "P",
    "gn:feature_code": "PPL",
    "gn:name": "Maobiling Shangzhai",
    "gn:population": 0,
    "gn:timezone": "Asia/Shanghai",
    "iso:country": "CN",
    "name:zho_x_preferred": [
      "猫鼻岭上寨"
    ],
    "wof:name": "Maobiling Shangzhai",
    "wof:placetype": "locality"
  },
  "geometry": {
    "coordinates": [
      108.381,
      26.7871
    ],
    "type": "Point"
  }
}