{
  "type": "Feature",
  "properties": {
    "gn:admin1_code": "18.0",
    "gn:asciiname": "Fengxing",
    "gn:country_code": "CN",
    "gn:dem": 420,
    "gn:feature_class": "P",
    "gn:feature_code": "PPL",
    "gn:name": "Fengxing",
    "gn:population": 0,
    "gn:timezone": "Asia/Shanghai",
    "iso:country": "CN",
    "name:zho_x_preferred": [
      "风形"
    ],
    "wof:name": "Fengxing",
    "wof:placetype": "locality"
  },
  "geometry": {
    "coordinates": [
      109.053,
      26.5398
    ],
    "type": "Point"
  }
}