{
  "type": "Feature",
  "properties": {
    "gn:admin1_code": "30",
    "gn:asciiname": "Shabeicun",
    "gn:country_code": "CN",
    "gn:dem": 239,
    "gn:feature_class": "P",
    "gn:feature_code": "PPL",
    "gn:name": "Shabeicun",
    "gn:population": 0,
    "gn:timezone": "Asia/Shanghai",
    "iso:country": "CN",
    "name:zho_x_preferred": [
      "沙陂村"
    ],
    "wof:name": "Shabeicun",
    "wof:placetype": "locality"
  },
  "geometry": {
    "coordinates": [
      116.41766,
      23.11647
    ],
    "type": "Point"
  }
}