{
  "type": "Feature",
  "properties": {
    "gn:admin1_code": "18",
    "gn:asciiname": "Tiziyan",
    "gn:country_code": "CN",
    "gn:dem": 796,
    "gn:feature_class": "P",
    "gn:feature_code": "PPL",
    "gn:name": "Tiziyan",
    "gn:population": 0,
    "gn:timezone": "Asia/Shanghai",
    "iso:country": "CN",
    "name:zho_x_preferred": [
      "梯子堰"
    ],
    "wof:name": "Tiziyan",
    "wof:placetype": "locality"
  },
  "geometry": {
    "coordinates": [
      107.219,
      27.7394
    ],
    "type": "Point"
  }
}