{
  "type": "Feature",
  "properties": {
    "gn:admin1_code": "3.0",
    "gn:asciiname": "Shiyan",
    "gn:country_code": "CN",
    "gn:dem": 165,
    "gn:feature_class": "P",
    "gn:feature_code": "PPL",
    "gn:name": "Shiyan",
    "gn:population": 0,
    "gn:timezone": "Asia/Shanghai",
    "iso:country": "CN",
    "name:ara_x_preferred": [
      "شيان"
    ],
    "name:bul_x_preferred": [
      "Шъйен"
    ],
    "name:cdo_x_preferred": [
      "Sĕk-iēng"
    ],
    "name:ceb_x_preferred": [
      "Shiyan"
    ],
    "name:ces_x_preferred": [
      "Š’-jen"
    ],
    "name:dan_x_preferred": [
      "Shiyan"
    ],
    "name:deu_x_preferred": [
      "Shiyan"
    ],
    "name:eus_x_preferred": [
      "Shiyan"
    ],
    "name:fas_x_preferred": [
      "شییان"
    ],
    "name:fin_x_preferred": [
      "Shiyan"
    ],
    "name:fra_x_preferred": [
      "Shiyan"
    ],
    "name:heb_x_preferred": [
      "שיאן"
    ],
    "name:hun_x_preferred": [
      "Shiyan"
    ],
    "name:ita_x_preferred": [
      "Shiyan"
    ],
    "name:jpn_x_preferred": [
      "十堰市"
    ],
    "name:kik_x_preferred": [
      "Shiyan"
    ],
    "name:kor_x_preferred": [
      "스옌시"
    ],
    "name:mlg_x_preferred": [
      "Shiyan"
    ],
    "name:nld_x_preferred": [
      "Shiyan"
    ],
    "name:nno_x_preferred": [
      "Shiyan"
    ],
    "name:nor_x_preferred": [
      "Shiyan"
    ],
    "name:pam_x_preferred": [
      "Shiyan"
    ],
    "name:pol_x_preferred": [
      "Shiyan"
    ],
    "name:rus_x_preferred": [
      "Шиянь"
    ],
    "name:spa_x_preferred": [
      "Shiyan"
    ],
    "name:srp_x_preferred": [
      "Шијен"
    ],
    "name:swe_x_preferred": [
      "Shiyan"
    ],
    "name:tgl_x_preferred": [
      "Shiyan"
    ],
    "name:tur_x_preferred": [
      "Shiyan"
    ],
    "name:und_x_variant": [
      "石燕"
    ],
    "name:urd_x_preferred": [
      "شییان"
    ],
    "name:vie_x_preferred": [
      "Thập Yển"
    ],
    "name:war_x_preferred": [
      "Shiyan"
    ],
    "name:zho_x_preferred": [
      "十堰市"
    ],
    "wof:name": "Shiyan",
    "wof:placetype": "locality"
  },
  "geometry": {
    "coordinates": [
      115.41548,
      26.31854
    ],
    "type": "Point"
  }
}