{
  "type": "Feature",
  "properties": {
    "gn:admin1_code": "4.0",
    "gn:asciiname": "Sharen",
    "gn:country_code": "CN",
    "gn:dem": 60,
    "gn:feature_class": "P",
    "gn:feature_code": "PPL",
    "gn:name": "Sharen",
    "gn:population": 0,
    "gn:timezone": "Asia/Shanghai",
    "iso:country": "CN",
    "name:zho_x_preferred": [
      "沙仁"
    ],
    "wof:name": "Sharen",
    "wof:placetype": "locality"
  },
  "geometry": {
    "coordinates": [
      119.29079,
      31.69879
    ],
    "type": "Point"
  }
}