{
  "type": "Feature",
  "properties": {
    "gn:admin1_code": "14",
    "gn:asciiname": "Baga",
    "gn:country_code": "CN",
    "gn:dem": 4713,
    "gn:feature_class": "P",
    "gn:feature_code": "PPL",
    "gn:name": "Baga",
    "gn:population": 0,
    "gn:timezone": "Asia/Urumqi",
    "iso:country": "CN",
    "name:ceb_x_preferred": [
      "Baga"
    ],
    "name:deu_x_preferred": [
      "Baga"
    ],
    "name:eus_x_preferred": [
      "Baga"
    ],
    "name:fao_x_preferred": [
      "Baga"
    ],
    "name:fra_x_preferred": [
      "Baga"
    ],
    "name:hye_x_preferred": [
      "Բագա"
    ],
    "name:ita_x_preferred": [
      "Baga"
    ],
    "name:kat_x_preferred": [
      "ბაგა"
    ],
    "name:nld_x_preferred": [
      "Baga"
    ],
    "name:por_x_preferred": [
      "Baga"
    ],
    "name:rus_x_preferred": [
      "Бага"
    ],
    "name:swe_x_preferred": [
      "Baga"
    ],
    "name:tgl_x_preferred": [
      "Baga"
    ],
    "name:ukr_x_preferred": [
      "Бага"
    ],
    "name:zho_x_preferred": [
      "巴嘎"
    ],
    "wof:name": "Baga",
    "wof:placetype": "locality"
  },
  "geometry": {
    "coordinates": [
      88.1187,
      29.8785
    ],
    "type": "Point"
  }
}