{
  "type": "Feature",
  "properties": {
    "gn:admin1_code": "16.0",
    "gn:asciiname": "Chang'an",
    "gn:country_code": "CN",
    "gn:dem": 41,
    "gn:feature_class": "P",
    "gn:feature_code": "PPL",
    "gn:name": "Chang’an",
    "gn:population": 0,
    "gn:timezone": "Asia/Shanghai",
    "iso:country": "CN",
    "name:als_x_preferred": [
      "Chang'an"
    ],
    "name:ara_x_preferred": [
      "تشانغآن"
    ],
    "name:aze_x_preferred": [
      "Çanqan"
    ],
    "name:bod_x_preferred": [
      "ཧྲང་ཨན།"
    ],
    "name:cat_x_preferred": [
      "Chang'an"
    ],
    "name:deu_x_preferred": [
      "Chang’an"
    ],
    "name:epo_x_preferred": [
      "Ĉangano"
    ],
    "name:est_x_preferred": [
      "Chang'an"
    ],
    "name:fas_x_preferred": [
      "چانگ‌آن"
    ],
    "name:hin_x_preferred": [
      "चांगआन"
    ],
    "name:ind_x_preferred": [
      "Chang'an"
    ],
    "name:ita_x_preferred": [
      "Chang'an"
    ],
    "name:kat_x_preferred": [
      "ჩანანი"
    ],
    "name:msa_x_preferred": [
      "Chang'an"
    ],
    "name:nld_x_preferred": [
      "Chang'an"
    ],
    "name:nor_x_preferred": [
      "Chang'an"
    ],
    "name:por_x_preferred": [
      "Changan"
    ],
    "name:rus_x_preferred": [
      "Чанъань"
    ],
    "name:sco_x_preferred": [
      "Chang'an"
    ],
    "name:spa_x_preferred": [
      "Chang'an"
    ],
    "name:swe_x_preferred": [
      "Chang’an"
    ],
    "name:tha_x_preferred": [
      "ฉางอาน"
    ],
    "name:tur_x_preferred": [
      "Çangan"
    ],
    "name:ukr_x_preferred": [
      "Чанань"
    ],
    "name:urd_x_preferred": [
      "چانگ آن"
    ],
    "name:vie_x_preferred": [
      "Trường An"
    ],
    "name:zho_x_preferred": [
      "长安"
    ],
    "wof:name": "Chang'an",
    "wof:placetype": "locality"
  },
  "geometry": {
    "coordinates": [
      110.087,
      23.3199
    ],
    "type": "Point"
  }
}