{
  "type": "Feature",
  "properties": {
    "gn:admin1_code": "3.0",
    "gn:asciiname": "Lujia",
    "gn:country_code": "CN",
    "gn:dem": 85,
    "gn:feature_class": "P",
    "gn:feature_code": "PPL",
    "gn:name": "Lüjia",
    "gn:population": 0,
    "gn:timezone": "Asia/Shanghai",
    "iso:country": "CN",
    "name:und_x_variant": [
      "Lüjia",
      "吕家"
    ],
    "wof:name": "Lujia",
    "wof:placetype": "locality"
  },
  "geometry": {
    "coordinates": [
      115.72076,
      29.59925
    ],
    "type": "Point"
  }
}