{
  "type": "Feature",
  "properties": {
    "gn:admin1_code": "3",
    "gn:asciiname": "Liuwugang",
    "gn:country_code": "CN",
    "gn:dem": 158,
    "gn:feature_class": "P",
    "gn:feature_code": "PPL",
    "gn:name": "Liuwugang",
    "gn:population": 0,
    "gn:timezone": "Asia/Shanghai",
    "iso:country": "CN",
    "name:zho_x_preferred": [
      "留屋岗"
    ],
    "wof:name": "Liuwugang",
    "wof:placetype": "locality"
  },
  "geometry": {
    "coordinates": [
      114.564,
      25.7122
    ],
    "type": "Point"
  }
}