{
  "type": "Feature",
  "properties": {
    "gn:admin1_code": "10.0",
    "gn:asciiname": "Yaozhanbu",
    "gn:country_code": "CN",
    "gn:dem": 666,
    "gn:feature_class": "P",
    "gn:feature_code": "PPL",
    "gn:name": "Yaozhanbu",
    "gn:population": 0,
    "gn:timezone": "Asia/Shanghai",
    "iso:country": "CN",
    "name:zho_x_preferred": [
      "腰站堡"
    ],
    "wof:name": "Yaozhanbu",
    "wof:placetype": "locality"
  },
  "geometry": {
    "coordinates": [
      114.80366,
      40.70657
    ],
    "type": "Point"
  }
}