{
  "type": "Feature",
  "properties": {
    "gn:admin1_code": "19",
    "gn:asciiname": "Xindian",
    "gn:country_code": "CN",
    "gn:dem": 116,
    "gn:feature_class": "P",
    "gn:feature_code": "PPLA4",
    "gn:name": "Xindian",
    "gn:population": 0,
    "gn:timezone": "Asia/Shanghai",
    "iso:country": "CN",
    "name:ceb_x_preferred": [
      "Xindian"
    ],
    "name:deu_x_preferred": [
      "Xindian"
    ],
    "name:swe_x_preferred": [
      "Xindian"
    ],
    "name:und_x_variant": [
      "Xindian Zhen",
      "新甸镇",
      "Dashan",
      "新甸",
      "Xindian Manzu Zhen",
      "新甸满族镇"
    ],
    "name:zho_x_preferred": [
      "大山"
    ],
    "wof:name": "Xindian",
    "wof:placetype": "locality"
  },
  "geometry": {
    "coordinates": [
      123.11266,
      40.10735
    ],
    "type": "Point"
  }
}