{
  "type": "Feature",
  "properties": {
    "gn:admin1_code": "2.0",
    "gn:asciiname": "Bankeng",
    "gn:country_code": "CN",
    "gn:dem": 558,
    "gn:feature_class": "P",
    "gn:feature_code": "PPL",
    "gn:name": "Bankeng",
    "gn:population": 0,
    "gn:timezone": "Asia/Shanghai",
    "iso:country": "CN",
    "name:zho_x_preferred": [
      "半坑"
    ],
    "wof:name": "Bankeng",
    "wof:placetype": "locality"
  },
  "geometry": {
    "coordinates": [
      120.44152,
      28.88561
    ],
    "type": "Point"
  }
}