{
  "type": "Feature",
  "properties": {
    "gn:admin1_code": "19.0",
    "gn:asciiname": "Zhoujia Wopengcun",
    "gn:country_code": "CN",
    "gn:dem": 172,
    "gn:feature_class": "P",
    "gn:feature_code": "PPL",
    "gn:name": "Zhoujia Wopengcun",
    "gn:population": 0,
    "gn:timezone": "Asia/Shanghai",
    "iso:country": "CN",
    "name:zho_x_preferred": [
      "周家窝棚村"
    ],
    "wof:name": "Zhoujia Wopengcun",
    "wof:placetype": "locality"
  },
  "geometry": {
    "coordinates": [
      124.30938,
      42.6212
    ],
    "type": "Point"
  }
}