{
  "type": "Feature",
  "properties": {
    "gn:admin1_code": "12.0",
    "gn:asciiname": "Sanlibian",
    "gn:country_code": "CN",
    "gn:dem": 1206,
    "gn:feature_class": "P",
    "gn:feature_code": "PPL",
    "gn:name": "Sanlibian",
    "gn:population": 0,
    "gn:timezone": "Asia/Shanghai",
    "iso:country": "CN",
    "name:zho_x_preferred": [
      "三里扁"
    ],
    "wof:name": "Sanlibian",
    "wof:placetype": "locality"
  },
  "geometry": {
    "coordinates": [
      110.47632,
      31.91731
    ],
    "type": "Point"
  }
}