{
  "type": "Feature",
  "properties": {
    "gn:admin1_code": "7.0",
    "gn:asciiname": "Xinhong",
    "gn:country_code": "CN",
    "gn:dem": 165,
    "gn:feature_class": "P",
    "gn:feature_code": "PPL",
    "gn:name": "Xinhong",
    "gn:population": 0,
    "gn:timezone": "Asia/Shanghai",
    "iso:country": "CN",
    "name:zho_x_preferred": [
      "新红"
    ],
    "wof:name": "Xinhong",
    "wof:placetype": "locality"
  },
  "geometry": {
    "coordinates": [
      117.10832,
      24.10924
    ],
    "type": "Point"
  }
}