{
  "type": "Feature",
  "properties": {
    "gn:admin1_code": "26.0",
    "gn:asciiname": "Yaoqucun",
    "gn:country_code": "CN",
    "gn:dem": 1175,
    "gn:feature_class": "P",
    "gn:feature_code": "PPL",
    "gn:name": "Yaoqucun",
    "gn:population": 0,
    "gn:timezone": "Asia/Shanghai",
    "iso:country": "CN",
    "name:zho_x_preferred": [
      "瑶渠村"
    ],
    "wof:name": "Yaoqucun",
    "wof:placetype": "locality"
  },
  "geometry": {
    "coordinates": [
      110.21711,
      38.74686
    ],
    "type": "Point"
  }
}