{
  "type": "Feature",
  "properties": {
    "gn:admin1_code": "02",
    "gn:asciiname": "Xincheng",
    "gn:country_code": "CN",
    "gn:dem": 7,
    "gn:feature_class": "P",
    "gn:feature_code": "PPL",
    "gn:name": "Xincheng",
    "gn:population": 0,
    "gn:timezone": "Asia/Shanghai",
    "iso:country": "CN",
    "name:ceb_x_preferred": [
      "Xincheng"
    ],
    "name:deu_x_preferred": [
      "Xincheng"
    ],
    "name:fra_x_preferred": [
      "Xincheng"
    ],
    "name:jpn_x_preferred": [
      "新城区"
    ],
    "name:kor_x_preferred": [
      "신청구"
    ],
    "name:mlg_x_preferred": [
      "Xincheng"
    ],
    "name:nor_x_preferred": [
      "Xincheng"
    ],
    "name:rus_x_preferred": [
      "Синьчэн"
    ],
    "name:swe_x_preferred": [
      "Xincheng"
    ],
    "name:zho_x_preferred": [
      "Hsin-ch’eng"
    ],
    "name:zho_x_variant": [
      "新城",
      "新城区"
    ],
    "wof:name": "Xincheng",
    "wof:placetype": "locality"
  },
  "geometry": {
    "coordinates": [
      120.84051,
      28.00145
    ],
    "type": "Point"
  }
}