{
  "type": "Feature",
  "properties": {
    "gn:admin1_code": "19",
    "gn:asciiname": "Huangtuling",
    "gn:country_code": "CN",
    "gn:dem": 164,
    "gn:feature_class": "P",
    "gn:feature_code": "PPLA4",
    "gn:name": "Huangtuling",
    "gn:population": 0,
    "gn:timezone": "Asia/Shanghai",
    "iso:country": "CN",
    "name:und_x_variant": [
      "Huang-t’u-ling-tzu",
      "Huangtuling",
      "黄土岭",
      "Huangtuling Zhen",
      "黄土岭镇"
    ],
    "wof:name": "Huangtuling",
    "wof:placetype": "locality"
  },
  "geometry": {
    "coordinates": [
      122.79144,
      40.41322
    ],
    "type": "Point"
  }
}