{
  "type": "Feature",
  "properties": {
    "gn:admin1_code": "26.0",
    "gn:asciiname": "Sanxiaocun",
    "gn:country_code": "CN",
    "gn:dem": 684,
    "gn:feature_class": "P",
    "gn:feature_code": "PPL",
    "gn:name": "Sanxiaocun",
    "gn:population": 0,
    "gn:timezone": "Asia/Shanghai",
    "iso:country": "CN",
    "name:und_x_variant": [
      "三孝村"
    ],
    "wof:name": "Sanxiaocun",
    "wof:placetype": "locality"
  },
  "geometry": {
    "coordinates": [
      109.60067,
      34.42998
    ],
    "type": "Point"
  }
}