{
  "type": "Feature",
  "properties": {
    "gn:admin1_code": "7.0",
    "gn:asciiname": "Xikeng",
    "gn:country_code": "CN",
    "gn:dem": 193,
    "gn:feature_class": "P",
    "gn:feature_code": "PPL",
    "gn:name": "Xikeng",
    "gn:population": 0,
    "gn:timezone": "Asia/Shanghai",
    "iso:country": "CN",
    "name:zho_x_preferred": [
      "西坑"
    ],
    "wof:name": "Xikeng",
    "wof:placetype": "locality"
  },
  "geometry": {
    "coordinates": [
      117.25523,
      24.32738
    ],
    "type": "Point"
  }
}