{
  "type": "Feature",
  "properties": {
    "gn:admin1_code": "8.0",
    "gn:asciiname": "Fuxin",
    "gn:country_code": "CN",
    "gn:dem": 245,
    "gn:feature_class": "P",
    "gn:feature_code": "PPL",
    "gn:name": "Fuxin",
    "gn:population": 0,
    "gn:timezone": "Asia/Shanghai",
    "iso:country": "CN",
    "name:afr_x_preferred": [
      "Fuxin"
    ],
    "name:ara_x_preferred": [
      "فوشين"
    ],
    "name:bul_x_preferred": [
      "Фусин"
    ],
    "name:cat_x_preferred": [
      "Fuxin"
    ],
    "name:cdo_x_preferred": [
      "Pâiu-sĭng"
    ],
    "name:ces_x_preferred": [
      "Fu-sin"
    ],
    "name:dan_x_preferred": [
      "Fuxin"
    ],
    "name:deu_x_preferred": [
      "Fuxin"
    ],
    "name:epo_x_preferred": [
      "Fusin"
    ],
    "name:eus_x_preferred": [
      "Fuxin"
    ],
    "name:fas_x_preferred": [
      "فاکسین"
    ],
    "name:fin_x_preferred": [
      "Fuxin"
    ],
    "name:fra_x_preferred": [
      "Fuxin"
    ],
    "name:heb_x_preferred": [
      "פוקסין"
    ],
    "name:hun_x_preferred": [
      "Fuxin"
    ],
    "name:ita_x_preferred": [
      "Fuxin"
    ],
    "name:jpn_x_preferred": [
      "阜新市"
    ],
    "name:kik_x_preferred": [
      "Fuxin"
    ],
    "name:kor_x_preferred": [
      "푸신시"
    ],
    "name:lit_x_preferred": [
      "Fusinas"
    ],
    "name:mlg_x_preferred": [
      "Fuxin"
    ],
    "name:mon_x_preferred": [
      "Фүшинь хот"
    ],
    "name:mwl_x_preferred": [
      "Fuxin"
    ],
    "name:nld_x_preferred": [
      "Fuxin"
    ],
    "name:nno_x_preferred": [
      "Fuxin"
    ],
    "name:nor_x_preferred": [
      "Fuxin"
    ],
    "name:pol_x_preferred": [
      "Fuxin"
    ],
    "name:por_x_preferred": [
      "Fuxin"
    ],
    "name:rus_x_preferred": [
      "Фусинь"
    ],
    "name:sco_x_preferred": [
      "Fuxin"
    ],
    "name:spa_x_preferred": [
      "Fuxin"
    ],
    "name:srp_x_preferred": [
      "Фусин"
    ],
    "name:swe_x_preferred": [
      "Fuxin"
    ],
    "name:tur_x_preferred": [
      "Fuxin"
    ],
    "name:urd_x_preferred": [
      "فوشن"
    ],
    "name:vie_x_preferred": [
      "Phụ Tân"
    ],
    "name:war_x_preferred": [
      "Fuxin"
    ],
    "name:wuu_x_preferred": [
      "阜新市"
    ],
    "name:zho_x_preferred": [
      "富新"
    ],
    "name:zho_x_variant": [
      "阜新市"
    ],
    "wof:name": "Fuxin",
    "wof:placetype": "locality"
  },
  "geometry": {
    "coordinates": [
      123.30415,
      47.89676
    ],
    "type": "Point"
  }
}