{
  "type": "Feature",
  "properties": {
    "gn:admin1_code": "5.0",
    "gn:asciiname": "Shi'erdaowancun",
    "gn:country_code": "CN",
    "gn:dem": 520,
    "gn:feature_class": "P",
    "gn:feature_code": "PPL",
    "gn:name": "Shi’erdaowancun",
    "gn:population": 0,
    "gn:timezone": "Asia/Shanghai",
    "iso:country": "CN",
    "name:und_x_variant": [
      "Shi’erdaowancun",
      "十二道湾村",
      "Shih-erh-tao-kou-wai",
      "Shi’erdaogouwai"
    ],
    "wof:name": "Shi'erdaowancun",
    "wof:placetype": "locality"
  },
  "geometry": {
    "coordinates": [
      127.61945,
      41.42813
    ],
    "type": "Point"
  }
}