{
  "type": "Feature",
  "properties": {
    "gn:admin1_code": "11.0",
    "gn:asciiname": "Yanmenchong",
    "gn:country_code": "CN",
    "gn:dem": 224,
    "gn:feature_class": "P",
    "gn:feature_code": "PPL",
    "gn:name": "Yanmenchong",
    "gn:population": 0,
    "gn:timezone": "Asia/Shanghai",
    "iso:country": "CN",
    "name:zho_x_preferred": [
      "岩门冲"
    ],
    "wof:name": "Yanmenchong",
    "wof:placetype": "locality"
  },
  "geometry": {
    "coordinates": [
      111.5345,
      28.59816
    ],
    "type": "Point"
  }
}