{
  "type": "Feature",
  "properties": {
    "gn:admin1_code": "1.0",
    "gn:asciiname": "Shandongcun",
    "gn:country_code": "CN",
    "gn:dem": 29,
    "gn:feature_class": "P",
    "gn:feature_code": "PPL",
    "gn:name": "Shandongcun",
    "gn:population": 0,
    "gn:timezone": "Asia/Shanghai",
    "iso:country": "CN",
    "name:zho_x_preferred": [
      "山东村"
    ],
    "wof:name": "Shandongcun",
    "wof:placetype": "locality"
  },
  "geometry": {
    "coordinates": [
      118.1502,
      33.00867
    ],
    "type": "Point"
  }
}