{
  "type": "Feature",
  "properties": {
    "gn:admin1_code": "29.0",
    "gn:asciiname": "Machang'ao",
    "gn:country_code": "CN",
    "gn:dem": 1174,
    "gn:feature_class": "P",
    "gn:feature_code": "PPL",
    "gn:name": "Machang’ao",
    "gn:population": 0,
    "gn:timezone": "Asia/Shanghai",
    "iso:country": "CN",
    "name:und_x_variant": [
      "Machang’ao"
    ],
    "name:zho_x_preferred": [
      "马厂凹"
    ],
    "wof:name": "Machang'ao",
    "wof:placetype": "locality"
  },
  "geometry": {
    "coordinates": [
      99.0048,
      24.5002
    ],
    "type": "Point"
  }
}