{
  "type": "Feature",
  "properties": {
    "gn:admin1_code": "30.0",
    "gn:asciiname": "Lilong",
    "gn:country_code": "CN",
    "gn:dem": 396,
    "gn:feature_class": "P",
    "gn:feature_code": "PPL",
    "gn:name": "Lilong",
    "gn:population": 0,
    "gn:timezone": "Asia/Shanghai",
    "iso:country": "CN",
    "name:zho_x_preferred": [
      "里龙"
    ],
    "wof:name": "Lilong",
    "wof:placetype": "locality"
  },
  "geometry": {
    "coordinates": [
      111.5405,
      23.00422
    ],
    "type": "Point"
  }
}