{
  "type": "Feature",
  "properties": {
    "gn:admin1_code": "6.0",
    "gn:asciiname": "Nani",
    "gn:country_code": "CN",
    "gn:dem": 4040,
    "gn:feature_class": "P",
    "gn:feature_code": "PPL",
    "gn:name": "Nani",
    "gn:population": 0,
    "gn:timezone": "Asia/Shanghai",
    "iso:country": "CN",
    "name:ara_x_preferred": [
      "ناني"
    ],
    "name:azb_x_preferred": [
      "نانی"
    ],
    "name:aze_x_preferred": [
      "Nani"
    ],
    "name:bel_x_preferred": [
      "Нані"
    ],
    "name:ben_x_preferred": [
      "ন্যানি"
    ],
    "name:bul_x_preferred": [
      "Нани"
    ],
    "name:ces_x_preferred": [
      "Nani"
    ],
    "name:dan_x_preferred": [
      "Nani"
    ],
    "name:deu_x_preferred": [
      "Nani"
    ],
    "name:ell_x_preferred": [
      "Νανί"
    ],
    "name:est_x_preferred": [
      "Nani"
    ],
    "name:fas_x_preferred": [
      "نانی"
    ],
    "name:fin_x_preferred": [
      "Nani"
    ],
    "name:fra_x_preferred": [
      "Nani"
    ],
    "name:gle_x_preferred": [
      "Nani"
    ],
    "name:glg_x_preferred": [
      "Nani"
    ],
    "name:heb_x_preferred": [
      "נאני"
    ],
    "name:hun_x_preferred": [
      "Nani"
    ],
    "name:hye_x_preferred": [
      "Նանի"
    ],
    "name:isl_x_preferred": [
      "Nani"
    ],
    "name:ita_x_preferred": [
      "Nani"
    ],
    "name:jav_x_preferred": [
      "Nani"
    ],
    "name:jpn_x_preferred": [
      "ルイス・カルロス・アルメイダ・ダ・クーニャ"
    ],
    "name:kat_x_preferred": [
      "ნანი"
    ],
    "name:kaz_x_preferred": [
      "Нани"
    ],
    "name:lav_x_preferred": [
      "Nani"
    ],
    "name:mai_x_preferred": [
      "नानी"
    ],
    "name:mar_x_preferred": [
      "नानी"
    ],
    "name:mkd_x_preferred": [
      "Нани"
    ],
    "name:mlt_x_preferred": [
      "Nani"
    ],
    "name:mon_x_preferred": [
      "Нани"
    ],
    "name:msa_x_preferred": [
      "Nani"
    ],
    "name:nep_x_preferred": [
      "नानी"
    ],
    "name:nld_x_preferred": [
      "Nani"
    ],
    "name:nno_x_preferred": [
      "Nani"
    ],
    "name:nor_x_preferred": [
      "Nani"
    ],
    "name:pan_x_preferred": [
      "ਨਾਨੀ"
    ],
    "name:pnb_x_preferred": [
      "نانی"
    ],
    "name:pol_x_preferred": [
      "Nani"
    ],
    "name:por_x_preferred": [
      "Nani"
    ],
    "name:ron_x_preferred": [
      "Nani"
    ],
    "name:rus_x_preferred": [
      "Нани"
    ],
    "name:san_x_preferred": [
      "लुईस नानी"
    ],
    "name:sco_x_preferred": [
      "Nani"
    ],
    "name:slk_x_preferred": [
      "Nani"
    ],
    "name:slv_x_preferred": [
      "Nani"
    ],
    "name:spa_x_preferred": [
      "Nani"
    ],
    "name:srp_x_preferred": [
      "Нани"
    ],
    "name:swa_x_preferred": [
      "Nani"
    ],
    "name:swe_x_preferred": [
      "Nani"
    ],
    "name:tha_x_preferred": [
      "นานี"
    ],
    "name:tuk_x_preferred": [
      "Nani"
    ],
    "name:tur_x_preferred": [
      "Nani"
    ],
    "name:ukr_x_preferred": [
      "Нані"
    ],
    "name:uzb_x_preferred": [
      "Nani"
    ],
    "name:vie_x_preferred": [
      "Nani"
    ],
    "name:xmf_x_preferred": [
      "ნანი"
    ],
    "name:zho_x_preferred": [
      "那尼"
    ],
    "wof:name": "Nani",
    "wof:placetype": "locality"
  },
  "geometry": {
    "coordinates": [
      99.68344,
      32.7779
    ],
    "type": "Point"
  }
}