{
  "type": "Feature",
  "properties": {
    "gn:admin1_code": "3.0",
    "gn:asciiname": "Gongqingcheng",
    "gn:country_code": "CN",
    "gn:dem": 30,
    "gn:feature_class": "P",
    "gn:feature_code": "PPL",
    "gn:name": "Gongqingcheng",
    "gn:population": 0,
    "gn:timezone": "Asia/Shanghai",
    "iso:country": "CN",
    "name:ara_x_preferred": [
      "غونكينغتشانغ"
    ],
    "name:deu_x_preferred": [
      "Gongqingcheng"
    ],
    "name:ita_x_preferred": [
      "Gongqingcheng"
    ],
    "name:jpn_x_preferred": [
      "共青城市"
    ],
    "name:kik_x_preferred": [
      "Gongqingcheng"
    ],
    "name:kor_x_preferred": [
      "궁칭청시"
    ],
    "name:mlg_x_preferred": [
      "Gongqing"
    ],
    "name:pol_x_preferred": [
      "Gongqingcheng"
    ],
    "name:urd_x_preferred": [
      "گونگچینگچینگ"
    ],
    "name:zho_x_preferred": [
      "共青城市"
    ],
    "wof:name": "Gongqingcheng",
    "wof:placetype": "locality"
  },
  "geometry": {
    "coordinates": [
      115.80953,
      29.24915
    ],
    "type": "Point"
  }
}