{
  "type": "Feature",
  "properties": {
    "gn:admin1_code": "19.0",
    "gn:asciiname": "Xi'ercha",
    "gn:country_code": "CN",
    "gn:dem": 292,
    "gn:feature_class": "P",
    "gn:feature_code": "PPL",
    "gn:name": "Xi’ercha",
    "gn:population": 0,
    "gn:timezone": "Asia/Shanghai",
    "iso:country": "CN",
    "name:zho_x_preferred": [
      "Xi’ercha"
    ],
    "name:zho_x_variant": [
      "西二岔"
    ],
    "wof:name": "Xi'ercha",
    "wof:placetype": "locality"
  },
  "geometry": {
    "coordinates": [
      124.44938,
      40.8515
    ],
    "type": "Point"
  }
}