{
  "type": "Feature",
  "properties": {
    "gn:admin1_code": "16.0",
    "gn:asciiname": "Zhangshu",
    "gn:country_code": "CN",
    "gn:dem": 105,
    "gn:feature_class": "P",
    "gn:feature_code": "PPL",
    "gn:name": "Zhangshu",
    "gn:population": 0,
    "gn:timezone": "Asia/Shanghai",
    "iso:country": "CN",
    "name:ces_x_preferred": [
      "Čang-šu"
    ],
    "name:deu_x_preferred": [
      "Zhangshu"
    ],
    "name:fra_x_preferred": [
      "Zhangshu"
    ],
    "name:ita_x_preferred": [
      "Zhangshu"
    ],
    "name:jpn_x_preferred": [
      "樟樹市"
    ],
    "name:kik_x_preferred": [
      "Zhangshu"
    ],
    "name:kor_x_preferred": [
      "장수시"
    ],
    "name:nor_x_preferred": [
      "Zhangshu"
    ],
    "name:swe_x_preferred": [
      "Zhangshu"
    ],
    "name:urd_x_preferred": [
      "ژانگشو"
    ],
    "name:vie_x_preferred": [
      "Chương Thụ"
    ],
    "name:war_x_preferred": [
      "Zhangshu"
    ],
    "name:zho_x_preferred": [
      "樟树"
    ],
    "name:zho_x_variant": [
      "樟树市"
    ],
    "wof:name": "Zhangshu",
    "wof:placetype": "locality"
  },
  "geometry": {
    "coordinates": [
      109.255,
      24.6535
    ],
    "type": "Point"
  }
}