{
  "type": "Feature",
  "properties": {
    "gn:admin1_code": "25.0",
    "gn:asciiname": "Dongpenqucun",
    "gn:country_code": "CN",
    "gn:dem": 80,
    "gn:feature_class": "P",
    "gn:feature_code": "PPL",
    "gn:name": "Dongpenqucun",
    "gn:population": 0,
    "gn:timezone": "Asia/Shanghai",
    "iso:country": "CN",
    "name:zho_x_preferred": [
      "东盆渠村"
    ],
    "wof:name": "Dongpenqucun",
    "wof:placetype": "locality"
  },
  "geometry": {
    "coordinates": [
      119.60385,
      36.137
    ],
    "type": "Point"
  }
}