{
  "type": "Feature",
  "properties": {
    "gn:admin1_code": "16.0",
    "gn:asciiname": "Hemei",
    "gn:country_code": "CN",
    "gn:dem": 135,
    "gn:feature_class": "P",
    "gn:feature_code": "PPL",
    "gn:name": "Hemei",
    "gn:population": 0,
    "gn:timezone": "Asia/Shanghai",
    "iso:country": "CN",
    "name:hak_x_preferred": [
      "Fò-mî-chṳ́n"
    ],
    "name:ita_x_preferred": [
      "Hemei"
    ],
    "name:jpn_x_preferred": [
      "和美鎮"
    ],
    "name:kor_x_preferred": [
      "허메이진"
    ],
    "name:pol_x_preferred": [
      "Hemei"
    ],
    "name:vie_x_preferred": [
      "Hòa Mỹ"
    ],
    "name:zho_x_preferred": [
      "合美"
    ],
    "name:zho_x_variant": [
      "和美鎮"
    ],
    "wof:name": "Hemei",
    "wof:placetype": "locality"
  },
  "geometry": {
    "coordinates": [
      108.356,
      23.0932
    ],
    "type": "Point"
  }
}