{
  "type": "Feature",
  "properties": {
    "gn:admin1_code": "7",
    "gn:asciiname": "Yuanqian",
    "gn:country_code": "CN",
    "gn:dem": 10,
    "gn:feature_class": "P",
    "gn:feature_code": "PPL",
    "gn:name": "Yuanqian",
    "gn:population": 0,
    "gn:timezone": "Asia/Shanghai",
    "iso:country": "CN",
    "name:zho_x_preferred": [
      "院前"
    ],
    "wof:name": "Yuanqian",
    "wof:placetype": "locality"
  },
  "geometry": {
    "coordinates": [
      118.61588,
      24.89026
    ],
    "type": "Point"
  }
}