{
  "type": "Feature",
  "properties": {
    "gn:admin1_code": "19.0",
    "gn:asciiname": "Zhangjiajie",
    "gn:country_code": "CN",
    "gn:dem": 282,
    "gn:feature_class": "P",
    "gn:feature_code": "PPL",
    "gn:name": "Zhangjiajie",
    "gn:population": 0,
    "gn:timezone": "Asia/Shanghai",
    "iso:country": "CN",
    "name:ara_x_preferred": [
      "زانغجياجي"
    ],
    "name:cdo_x_preferred": [
      "Diŏng-gă-gái"
    ],
    "name:ceb_x_preferred": [
      "Zhangjiajie"
    ],
    "name:ces_x_preferred": [
      "Čang-ťia-ťie"
    ],
    "name:dan_x_preferred": [
      "Zhangjiajie"
    ],
    "name:deu_x_preferred": [
      "Zhangjiajie"
    ],
    "name:eus_x_preferred": [
      "Zhangjiajie"
    ],
    "name:fas_x_preferred": [
      "ژانگجیاجی"
    ],
    "name:fin_x_preferred": [
      "Zhangjiajie"
    ],
    "name:fra_x_preferred": [
      "Zhangjiajie"
    ],
    "name:hak_x_preferred": [
      "Chông-kâ-kie-sṳ"
    ],
    "name:heb_x_preferred": [
      "ז'אנגג'יאג'יה"
    ],
    "name:ind_x_preferred": [
      "Zhangjiajie"
    ],
    "name:ita_x_preferred": [
      "Zhangjiajie"
    ],
    "name:jpn_x_preferred": [
      "張家界市"
    ],
    "name:kik_x_preferred": [
      "Zhangjiajie"
    ],
    "name:kor_x_preferred": [
      "장자제시"
    ],
    "name:mlg_x_preferred": [
      "Zhangjiajie"
    ],
    "name:mya_x_preferred": [
      "ကျန်းကျားကျဲသဘာဝဥယျာဉ်"
    ],
    "name:nld_x_preferred": [
      "Zhangjiajie"
    ],
    "name:nno_x_preferred": [
      "Zhangjiajie"
    ],
    "name:nor_x_preferred": [
      "Zhangjiajie"
    ],
    "name:pam_x_preferred": [
      "Zhangjiajie"
    ],
    "name:pol_x_preferred": [
      "Zhangjiajie"
    ],
    "name:por_x_preferred": [
      "Zhangjiajie"
    ],
    "name:rus_x_preferred": [
      "Чжанцзяцзе"
    ],
    "name:sco_x_preferred": [
      "Zhangjiajie"
    ],
    "name:slv_x_preferred": [
      "Zhangjiajie"
    ],
    "name:spa_x_preferred": [
      "Zhangjiajie"
    ],
    "name:swe_x_preferred": [
      "Zhangjiajie"
    ],
    "name:tha_x_preferred": [
      "จางเจียเจีย"
    ],
    "name:tur_x_preferred": [
      "Zhangjiajie"
    ],
    "name:urd_x_preferred": [
      "ژانگجیانیے"
    ],
    "name:war_x_preferred": [
      "Zhangjiajie"
    ],
    "name:zho_x_preferred": [
      "张家街"
    ],
    "name:zho_x_variant": [
      "张家界市"
    ],
    "wof:name": "Zhangjiajie",
    "wof:placetype": "locality"
  },
  "geometry": {
    "coordinates": [
      123.09172,
      40.53537
    ],
    "type": "Point"
  }
}