{
  "type": "Feature",
  "properties": {
    "gn:admin1_code": "16.0",
    "gn:asciiname": "Fuxi",
    "gn:country_code": "CN",
    "gn:dem": 307,
    "gn:feature_class": "P",
    "gn:feature_code": "PPL",
    "gn:name": "Fuxi",
    "gn:population": 0,
    "gn:timezone": "Asia/Shanghai",
    "iso:country": "CN",
    "name:bul_x_preferred": [
      "Фу Си"
    ],
    "name:cat_x_preferred": [
      "Fu Xi"
    ],
    "name:ces_x_preferred": [
      "Fu-si"
    ],
    "name:deu_x_preferred": [
      "Fu Xi"
    ],
    "name:epo_x_preferred": [
      "Fu Xi"
    ],
    "name:est_x_preferred": [
      "Fu Xi"
    ],
    "name:fas_x_preferred": [
      "فو هسی"
    ],
    "name:fra_x_preferred": [
      "Fuxi"
    ],
    "name:hak_x_preferred": [
      "Phu̍k-hî"
    ],
    "name:heb_x_preferred": [
      "פו שי"
    ],
    "name:hrv_x_preferred": [
      "Fu Xi"
    ],
    "name:hun_x_preferred": [
      "Fu-hszi"
    ],
    "name:ind_x_preferred": [
      "Fúxī"
    ],
    "name:ita_x_preferred": [
      "Fu Xi"
    ],
    "name:kat_x_preferred": [
      "ფუსი"
    ],
    "name:lit_x_preferred": [
      "Fuši"
    ],
    "name:msa_x_preferred": [
      "Fu Xi"
    ],
    "name:nld_x_preferred": [
      "Fuxi"
    ],
    "name:nor_x_preferred": [
      "Fuxi"
    ],
    "name:pol_x_preferred": [
      "Fuxi"
    ],
    "name:por_x_preferred": [
      "Fu Xi"
    ],
    "name:rus_x_preferred": [
      "Фу Си"
    ],
    "name:slk_x_preferred": [
      "Fu si"
    ],
    "name:spa_x_preferred": [
      "Fuxi"
    ],
    "name:swe_x_preferred": [
      "Fuxi"
    ],
    "name:tha_x_preferred": [
      "ฝูซี"
    ],
    "name:tur_x_preferred": [
      "Fu Xi"
    ],
    "name:ukr_x_preferred": [
      "Фу-сі"
    ],
    "name:vie_x_preferred": [
      "Phục Hy"
    ],
    "name:zho_x_preferred": [
      "福溪"
    ],
    "wof:name": "Fuxi",
    "wof:placetype": "locality"
  },
  "geometry": {
    "coordinates": [
      111.218,
      25.0731
    ],
    "type": "Point"
  }
}