{
  "type": "Feature",
  "properties": {
    "gn:admin1_code": "10.0",
    "gn:asciiname": "Xugezhai",
    "gn:country_code": "CN",
    "gn:dem": 15,
    "gn:feature_class": "P",
    "gn:feature_code": "PPL",
    "gn:name": "Xugezhai",
    "gn:population": 0,
    "gn:timezone": "Asia/Shanghai",
    "iso:country": "CN",
    "name:zho_x_preferred": [
      "许各寨"
    ],
    "wof:name": "Xugezhai",
    "wof:placetype": "locality"
  },
  "geometry": {
    "coordinates": [
      118.08891,
      39.59905
    ],
    "type": "Point"
  }
}