{
  "type": "Feature",
  "properties": {
    "gn:admin1_code": "19.0",
    "gn:asciiname": "Sanzuodian",
    "gn:country_code": "CN",
    "gn:dem": 334,
    "gn:feature_class": "P",
    "gn:feature_code": "PPL",
    "gn:name": "Sanzuodian",
    "gn:population": 0,
    "gn:timezone": "Asia/Shanghai",
    "iso:country": "CN",
    "name:zho_x_preferred": [
      "三座店"
    ],
    "wof:name": "Sanzuodian",
    "wof:placetype": "locality"
  },
  "geometry": {
    "coordinates": [
      119.87654,
      41.00766
    ],
    "type": "Point"
  }
}