{
  "type": "Feature",
  "properties": {
    "gn:admin1_code": "5.0",
    "gn:asciiname": "Wangzicun",
    "gn:country_code": "CN",
    "gn:dem": 136,
    "gn:feature_class": "P",
    "gn:feature_code": "PPL",
    "gn:name": "Wangzicun",
    "gn:population": 0,
    "gn:timezone": "Asia/Shanghai",
    "iso:country": "CN",
    "name:zho_x_preferred": [
      "往字村"
    ],
    "wof:name": "Wangzicun",
    "wof:placetype": "locality"
  },
  "geometry": {
    "coordinates": [
      123.87148,
      45.15905
    ],
    "type": "Point"
  }
}