{
  "type": "Feature",
  "properties": {
    "gn:admin1_code": "11",
    "gn:asciiname": "Hechi",
    "gn:country_code": "CN",
    "gn:dem": 170,
    "gn:feature_class": "P",
    "gn:feature_code": "PPL",
    "gn:name": "Hechi",
    "gn:population": 0,
    "gn:timezone": "Asia/Shanghai",
    "iso:country": "CN",
    "name:ara_x_preferred": [
      "هيشي"
    ],
    "name:aze_x_preferred": [
      "Heçi"
    ],
    "name:cdo_x_preferred": [
      "Ò̤-diè"
    ],
    "name:ceb_x_preferred": [
      "Hechi Shi"
    ],
    "name:ces_x_preferred": [
      "Che-čch’"
    ],
    "name:dan_x_preferred": [
      "Hechi"
    ],
    "name:deu_x_preferred": [
      "Hechi"
    ],
    "name:eus_x_preferred": [
      "Hechi"
    ],
    "name:fas_x_preferred": [
      "هیچی"
    ],
    "name:fin_x_preferred": [
      "Hechi"
    ],
    "name:fra_x_preferred": [
      "Hechi"
    ],
    "name:hak_x_preferred": [
      "Hò-chhṳ̀-sṳ"
    ],
    "name:heb_x_preferred": [
      "חייצ'י"
    ],
    "name:hun_x_preferred": [
      "Hechi"
    ],
    "name:ita_x_preferred": [
      "Hechi"
    ],
    "name:jpn_x_preferred": [
      "河池市"
    ],
    "name:kik_x_preferred": [
      "Hechi"
    ],
    "name:kor_x_preferred": [
      "허츠시"
    ],
    "name:nld_x_preferred": [
      "Hechi"
    ],
    "name:nno_x_preferred": [
      "Hechi"
    ],
    "name:nor_x_preferred": [
      "Hechi"
    ],
    "name:pnb_x_preferred": [
      "ہیچی"
    ],
    "name:pol_x_preferred": [
      "Hechi"
    ],
    "name:por_x_preferred": [
      "Hechi"
    ],
    "name:rus_x_preferred": [
      "Хэчи"
    ],
    "name:spa_x_preferred": [
      "Hechi"
    ],
    "name:swe_x_preferred": [
      "Hechi"
    ],
    "name:tur_x_preferred": [
      "Hechi"
    ],
    "name:ukr_x_preferred": [
      "Гечі"
    ],
    "name:urd_x_preferred": [
      "ہیچی"
    ],
    "name:vie_x_preferred": [
      "Hà Trì"
    ],
    "name:war_x_preferred": [
      "Hechi"
    ],
    "name:zha_x_preferred": [
      "Hozciz"
    ],
    "name:zho_x_preferred": [
      "河池市"
    ],
    "wof:name": "Hechi",
    "wof:placetype": "locality"
  },
  "geometry": {
    "coordinates": [
      111.32833,
      26.34056
    ],
    "type": "Point"
  }
}