{
  "type": "Feature",
  "properties": {
    "gn:admin1_code": "26.0",
    "gn:asciiname": "Qianmiaoshancun",
    "gn:country_code": "CN",
    "gn:dem": 784,
    "gn:feature_class": "P",
    "gn:feature_code": "PPL",
    "gn:name": "Qianmiaoshancun",
    "gn:population": 0,
    "gn:timezone": "Asia/Shanghai",
    "iso:country": "CN",
    "name:zho_x_preferred": [
      "前庙山村"
    ],
    "wof:name": "Qianmiaoshancun",
    "wof:placetype": "locality"
  },
  "geometry": {
    "coordinates": [
      110.69003,
      37.45795
    ],
    "type": "Point"
  }
}