{
  "type": "Feature",
  "properties": {
    "gn:admin1_code": "14",
    "gn:asciiname": "Jiana",
    "gn:country_code": "CN",
    "gn:dem": 3945,
    "gn:feature_class": "P",
    "gn:feature_code": "PPL",
    "gn:name": "Jiana",
    "gn:population": 0,
    "gn:timezone": "Asia/Urumqi",
    "iso:country": "CN",
    "name:ceb_x_preferred": [
      "Comuna Jiana"
    ],
    "name:fra_x_preferred": [
      "Jiana"
    ],
    "name:ita_x_preferred": [
      "Jiana"
    ],
    "name:msa_x_preferred": [
      "Jiana"
    ],
    "name:nld_x_preferred": [
      "Jiana"
    ],
    "name:por_x_preferred": [
      "Jiana"
    ],
    "name:ron_x_preferred": [
      "Comuna Jiana"
    ],
    "name:srp_x_preferred": [
      "Општина Жиана"
    ],
    "name:ukr_x_preferred": [
      "Жіана"
    ],
    "name:vie_x_preferred": [
      "Jiana"
    ],
    "name:vol_x_preferred": [
      "Jiana"
    ],
    "name:zho_x_preferred": [
      "加那"
    ],
    "name:zho_x_variant": [
      "日亞納鄉"
    ],
    "wof:name": "Jiana",
    "wof:placetype": "locality"
  },
  "geometry": {
    "coordinates": [
      89.4662,
      29.0506
    ],
    "type": "Point"
  }
}