{
  "type": "Feature",
  "properties": {
    "gn:admin1_code": "2.0",
    "gn:asciiname": "Jintangbang",
    "gn:country_code": "CN",
    "gn:dem": 6,
    "gn:feature_class": "P",
    "gn:feature_code": "PPL",
    "gn:name": "Jintangbang",
    "gn:population": 0,
    "gn:timezone": "Asia/Shanghai",
    "iso:country": "CN",
    "name:und_x_variant": [
      "金堂浜"
    ],
    "wof:name": "Jintangbang",
    "wof:placetype": "locality"
  },
  "geometry": {
    "coordinates": [
      120.65975,
      30.69431
    ],
    "type": "Point"
  }
}