{
  "type": "Feature",
  "properties": {
    "gn:admin1_code": "10",
    "gn:asciiname": "Xiaohaojiasicun",
    "gn:country_code": "CN",
    "gn:dem": 16,
    "gn:feature_class": "P",
    "gn:feature_code": "PPL",
    "gn:name": "Xiaohaojiasicun",
    "gn:population": 0,
    "gn:timezone": "Asia/Shanghai",
    "iso:country": "CN",
    "name:und_x_variant": [
      "Xiaohao"
    ],
    "name:zho_x_preferred": [
      "小郝家寺村"
    ],
    "name:zho_x_variant": [
      "小郝"
    ],
    "wof:name": "Xiaohaojiasicun",
    "wof:placetype": "locality"
  },
  "geometry": {
    "coordinates": [
      116.66594,
      37.86622
    ],
    "type": "Point"
  }
}