{
  "type": "Feature",
  "properties": {
    "gn:admin1_code": "33.0",
    "gn:asciiname": "Basan",
    "gn:country_code": "CN",
    "gn:dem": 335,
    "gn:feature_class": "P",
    "gn:feature_code": "PPL",
    "gn:name": "Basan",
    "gn:population": 0,
    "gn:timezone": "Asia/Shanghai",
    "iso:country": "CN",
    "name:fra_x_preferred": [
      "Basan"
    ],
    "name:por_x_preferred": [
      "Basan"
    ],
    "name:rus_x_preferred": [
      "Басан"
    ],
    "name:spa_x_preferred": [
      "Basan"
    ],
    "name:zho_x_preferred": [
      "把伞"
    ],
    "wof:name": "Basan",
    "wof:placetype": "locality"
  },
  "geometry": {
    "coordinates": [
      106.02764,
      30.13259
    ],
    "type": "Point"
  }
}