{
  "type": "Feature",
  "properties": {
    "gn:admin1_code": "16.0",
    "gn:asciiname": "Chaodong",
    "gn:country_code": "CN",
    "gn:dem": 392,
    "gn:feature_class": "P",
    "gn:feature_code": "PPL",
    "gn:name": "Chaodong",
    "gn:population": 0,
    "gn:timezone": "Asia/Shanghai",
    "iso:country": "CN",
    "name:zho_x_preferred": [
      "朝峒"
    ],
    "wof:name": "Chaodong",
    "wof:placetype": "locality"
  },
  "geometry": {
    "coordinates": [
      108.165,
      24.355
    ],
    "type": "Point"
  }
}