{
  "type": "Feature",
  "properties": {
    "gn:admin1_code": "29.0",
    "gn:asciiname": "Wusu",
    "gn:country_code": "CN",
    "gn:dem": 1398,
    "gn:feature_class": "P",
    "gn:feature_code": "PPL",
    "gn:name": "Wusu",
    "gn:population": 0,
    "gn:timezone": "Asia/Shanghai",
    "iso:country": "CN",
    "name:deu_x_preferred": [
      "Usu"
    ],
    "name:est_x_preferred": [
      "Usu"
    ],
    "name:fra_x_preferred": [
      "Wusu"
    ],
    "name:hun_x_preferred": [
      "Vusu"
    ],
    "name:ita_x_preferred": [
      "Wusu"
    ],
    "name:jpn_x_preferred": [
      "ウス市"
    ],
    "name:kik_x_preferred": [
      "Wusu"
    ],
    "name:kor_x_preferred": [
      "우쑤시"
    ],
    "name:mon_x_preferred": [
      "Ус хот"
    ],
    "name:nor_x_preferred": [
      "Wusu"
    ],
    "name:pol_x_preferred": [
      "Wusu"
    ],
    "name:por_x_preferred": [
      "Wusu"
    ],
    "name:rus_x_preferred": [
      "Усу"
    ],
    "name:swe_x_preferred": [
      "Usu"
    ],
    "name:tur_x_preferred": [
      "Usu"
    ],
    "name:uig_x_preferred": [
      "شىخۇ شەھىرى"
    ],
    "name:urd_x_preferred": [
      "ووسو"
    ],
    "name:vie_x_preferred": [
      "Ô Tô"
    ],
    "name:zho_x_preferred": [
      "五素"
    ],
    "name:zho_x_variant": [
      "乌苏市"
    ],
    "wof:name": "Wusu",
    "wof:placetype": "locality"
  },
  "geometry": {
    "coordinates": [
      101.662,
      23.3661
    ],
    "type": "Point"
  }
}