{
  "type": "Feature",
  "properties": {
    "gn:admin1_code": "30.0",
    "gn:asciiname": "Minggangcun",
    "gn:country_code": "CN",
    "gn:dem": 10,
    "gn:feature_class": "P",
    "gn:feature_code": "PPL",
    "gn:name": "Minggangcun",
    "gn:population": 0,
    "gn:timezone": "Asia/Shanghai",
    "iso:country": "CN",
    "name:zho_x_preferred": [
      "鸣岗村"
    ],
    "wof:name": "Minggangcun",
    "wof:placetype": "locality"
  },
  "geometry": {
    "coordinates": [
      116.20355,
      23.42546
    ],
    "type": "Point"
  }
}