{
  "type": "Feature",
  "properties": {
    "gn:admin1_code": "15.0",
    "gn:asciiname": "Qigong",
    "gn:country_code": "CN",
    "gn:dem": 1148,
    "gn:feature_class": "P",
    "gn:feature_code": "PPL",
    "gn:name": "Qigong",
    "gn:population": 0,
    "gn:timezone": "Asia/Urumqi",
    "iso:country": "CN",
    "name:ara_x_preferred": [
      "تشي كونغ"
    ],
    "name:ast_x_preferred": [
      "Qigong"
    ],
    "name:bul_x_preferred": [
      "Ци гун"
    ],
    "name:cat_x_preferred": [
      "Txikung"
    ],
    "name:ces_x_preferred": [
      "Čchi-kung"
    ],
    "name:dan_x_preferred": [
      "Qigong"
    ],
    "name:deu_x_preferred": [
      "Qigong"
    ],
    "name:ell_x_preferred": [
      "Τσι κουνγκ"
    ],
    "name:epo_x_preferred": [
      "Ĉigongo"
    ],
    "name:est_x_preferred": [
      "Qigong"
    ],
    "name:eus_x_preferred": [
      "Qigong"
    ],
    "name:fas_x_preferred": [
      "چی کونگ"
    ],
    "name:fin_x_preferred": [
      "Qigong"
    ],
    "name:fra_x_preferred": [
      "Qi gong"
    ],
    "name:heb_x_preferred": [
      "צ'י קונג"
    ],
    "name:hrv_x_preferred": [
      "Chi Kung"
    ],
    "name:hun_x_preferred": [
      "Csikung"
    ],
    "name:ind_x_preferred": [
      "Qigong"
    ],
    "name:ita_x_preferred": [
      "Qi Gong"
    ],
    "name:jav_x_preferred": [
      "Qigong"
    ],
    "name:kor_x_preferred": [
      "기공"
    ],
    "name:lav_x_preferred": [
      "Ciguns"
    ],
    "name:lit_x_preferred": [
      "Čigongas"
    ],
    "name:msa_x_preferred": [
      "Qigong"
    ],
    "name:mya_x_preferred": [
      "ချိကုန်း"
    ],
    "name:nld_x_preferred": [
      "Qi gong"
    ],
    "name:nno_x_preferred": [
      "Qigong"
    ],
    "name:nor_x_preferred": [
      "Qi gong"
    ],
    "name:oci_x_preferred": [
      "Qìgōng"
    ],
    "name:pol_x_preferred": [
      "Qigong"
    ],
    "name:por_x_preferred": [
      "Qigong"
    ],
    "name:ron_x_preferred": [
      "Qigong"
    ],
    "name:rus_x_preferred": [
      "Цигун"
    ],
    "name:sco_x_preferred": [
      "Qigong"
    ],
    "name:slv_x_preferred": [
      "Qigong"
    ],
    "name:spa_x_preferred": [
      "Chi kung"
    ],
    "name:srp_x_preferred": [
      "Чи кунг"
    ],
    "name:swe_x_preferred": [
      "Qigong"
    ],
    "name:tha_x_preferred": [
      "ชี่กง"
    ],
    "name:tur_x_preferred": [
      "Çigong"
    ],
    "name:ukr_x_preferred": [
      "Ціґун"
    ],
    "name:vie_x_preferred": [
      "Khí công"
    ],
    "name:zho_x_preferred": [
      "七工"
    ],
    "wof:name": "Qigong",
    "wof:placetype": "locality"
  },
  "geometry": {
    "coordinates": [
      95.6373,
      40.4009
    ],
    "type": "Point"
  }
}