{
  "type": "Feature",
  "properties": {
    "gn:admin1_code": "26.0",
    "gn:asciiname": "Zhoujia Taizi",
    "gn:country_code": "CN",
    "gn:dem": 1672,
    "gn:feature_class": "P",
    "gn:feature_code": "PPL",
    "gn:name": "Zhoujia Taizi",
    "gn:population": 0,
    "gn:timezone": "Asia/Shanghai",
    "iso:country": "CN",
    "name:und_x_variant": [
      "周家台子"
    ],
    "wof:name": "Zhoujia Taizi",
    "wof:placetype": "locality"
  },
  "geometry": {
    "coordinates": [
      109.72074,
      34.22045
    ],
    "type": "Point"
  }
}