{
  "type": "Feature",
  "properties": {
    "gn:admin1_code": "25",
    "gn:asciiname": "Jiaonan",
    "gn:country_code": "CN",
    "gn:dem": 189,
    "gn:feature_class": "P",
    "gn:feature_code": "PPL",
    "gn:name": "Jiaonan",
    "gn:population": 0,
    "gn:timezone": "Asia/Shanghai",
    "iso:country": "CN",
    "name:ceb_x_preferred": [
      "Jiaonan Shi"
    ],
    "name:deu_x_preferred": [
      "Jiaonan"
    ],
    "name:fas_x_preferred": [
      "جیاونان"
    ],
    "name:fra_x_preferred": [
      "Jiaonan"
    ],
    "name:jpn_x_preferred": [
      "膠南市"
    ],
    "name:kor_x_preferred": [
      "자오난시"
    ],
    "name:nor_x_preferred": [
      "Jiaonan"
    ],
    "name:swe_x_preferred": [
      "Jiaonan"
    ],
    "name:vie_x_preferred": [
      "Giao Nam"
    ],
    "name:zho_x_preferred": [
      "焦南"
    ],
    "name:zho_x_variant": [
      "胶南市"
    ],
    "wof:name": "Jiaonan",
    "wof:placetype": "locality"
  },
  "geometry": {
    "coordinates": [
      117.331,
      36.3052
    ],
    "type": "Point"
  }
}