{
  "type": "Feature",
  "properties": {
    "gn:admin1_code": "12.0",
    "gn:asciiname": "Ermuping",
    "gn:country_code": "CN",
    "gn:dem": 1170,
    "gn:feature_class": "P",
    "gn:feature_code": "PPL",
    "gn:name": "Ermuping",
    "gn:population": 0,
    "gn:timezone": "Asia/Shanghai",
    "iso:country": "CN",
    "name:zho_x_preferred": [
      "二木坪"
    ],
    "wof:name": "Ermuping",
    "wof:placetype": "locality"
  },
  "geometry": {
    "coordinates": [
      110.17841,
      30.32943
    ],
    "type": "Point"
  }
}