{
  "type": "Feature",
  "properties": {
    "gn:admin1_code": "21.0",
    "gn:asciiname": "Liuzhuang",
    "gn:country_code": "CN",
    "gn:dem": 1185,
    "gn:feature_class": "P",
    "gn:feature_code": "PPL",
    "gn:name": "Liuzhuang",
    "gn:population": 0,
    "gn:timezone": "Asia/Shanghai",
    "iso:country": "CN",
    "name:zho_x_preferred": [
      "刘庄"
    ],
    "wof:name": "Liuzhuang",
    "wof:placetype": "locality"
  },
  "geometry": {
    "coordinates": [
      105.737,
      37.4808
    ],
    "type": "Point"
  }
}