{
  "type": "Feature",
  "properties": {
    "gn:admin1_code": "4.0",
    "gn:asciiname": "Nanpan",
    "gn:country_code": "CN",
    "gn:dem": 12,
    "gn:feature_class": "P",
    "gn:feature_code": "PPL",
    "gn:name": "Nanpan",
    "gn:population": 0,
    "gn:timezone": "Asia/Shanghai",
    "iso:country": "CN",
    "name:ara_x_preferred": [
      "نانبان"
    ],
    "name:ben_x_preferred": [
      "নানপান"
    ],
    "name:ell_x_preferred": [
      "Νανπάν"
    ],
    "name:fas_x_preferred": [
      "نانپان"
    ],
    "name:heb_x_preferred": [
      "נאנפאן"
    ],
    "name:hin_x_preferred": [
      "नानपन"
    ],
    "name:hun_x_preferred": [
      "Nanpan"
    ],
    "name:ind_x_preferred": [
      "Nanpan"
    ],
    "name:ita_x_preferred": [
      "Nanpan"
    ],
    "name:kor_x_preferred": [
      "난판"
    ],
    "name:nld_x_preferred": [
      "Nanpan"
    ],
    "name:pol_x_preferred": [
      "Nanpan"
    ],
    "name:por_x_preferred": [
      "Nanpan"
    ],
    "name:spa_x_preferred": [
      "Nanpan"
    ],
    "name:tur_x_preferred": [
      "Nanpan"
    ],
    "name:ukr_x_preferred": [
      "Нанпан"
    ],
    "name:urd_x_preferred": [
      "نانپان"
    ],
    "name:zho_x_preferred": [
      "南盘"
    ],
    "wof:name": "Nanpan",
    "wof:placetype": "locality"
  },
  "geometry": {
    "coordinates": [
      118.50553,
      31.97159
    ],
    "type": "Point"
  }
}