{
  "type": "Feature",
  "properties": {
    "gn:admin1_code": "12.0",
    "gn:asciiname": "Jiefangling",
    "gn:country_code": "CN",
    "gn:dem": 49,
    "gn:feature_class": "P",
    "gn:feature_code": "PPL",
    "gn:name": "Jiefangling",
    "gn:population": 0,
    "gn:timezone": "Asia/Shanghai",
    "iso:country": "CN",
    "name:zho_x_preferred": [
      "Jiefangling"
    ],
    "name:zho_x_variant": [
      "解放岭"
    ],
    "wof:name": "Jiefangling",
    "wof:placetype": "locality"
  },
  "geometry": {
    "coordinates": [
      112.39409,
      30.58077
    ],
    "type": "Point"
  }
}