{
  "type": "Feature",
  "properties": {
    "gn:admin1_code": "14.0",
    "gn:asciiname": "Xitang",
    "gn:country_code": "CN",
    "gn:dem": 3417,
    "gn:feature_class": "P",
    "gn:feature_code": "PPL",
    "gn:name": "Xitang",
    "gn:population": 0,
    "gn:timezone": "Asia/Urumqi",
    "iso:country": "CN",
    "name:ara_x_preferred": [
      "شيتانغ"
    ],
    "name:deu_x_preferred": [
      "Xitang"
    ],
    "name:fra_x_preferred": [
      "Xitang"
    ],
    "name:jpn_x_preferred": [
      "西塘鎮"
    ],
    "name:vie_x_preferred": [
      "Tây Đường"
    ],
    "name:wuu_x_preferred": [
      "西塘镇"
    ],
    "name:zho_x_preferred": [
      "希塘"
    ],
    "name:zho_x_variant": [
      "西塘镇"
    ],
    "wof:name": "Xitang",
    "wof:placetype": "locality"
  },
  "geometry": {
    "coordinates": [
      96.3381,
      30.41053
    ],
    "type": "Point"
  }
}