{
  "type": "Feature",
  "properties": {
    "gn:admin1_code": "29.0",
    "gn:asciiname": "Linyi",
    "gn:country_code": "CN",
    "gn:dem": 1764,
    "gn:feature_class": "P",
    "gn:feature_code": "PPL",
    "gn:name": "Linyi",
    "gn:population": 0,
    "gn:timezone": "Asia/Shanghai",
    "iso:country": "CN",
    "name:afr_x_preferred": [
      "Linyi"
    ],
    "name:ara_x_preferred": [
      "ليني"
    ],
    "name:cat_x_preferred": [
      "Linyi"
    ],
    "name:cdo_x_preferred": [
      "Lìng-gì"
    ],
    "name:ceb_x_preferred": [
      "Linyi"
    ],
    "name:ces_x_preferred": [
      "Lin-i"
    ],
    "name:dan_x_preferred": [
      "Linyi"
    ],
    "name:deu_x_preferred": [
      "Linyi"
    ],
    "name:eus_x_preferred": [
      "Linyi"
    ],
    "name:fas_x_preferred": [
      "لینیای"
    ],
    "name:fin_x_preferred": [
      "Linyi"
    ],
    "name:fra_x_preferred": [
      "Linyi"
    ],
    "name:heb_x_preferred": [
      "ליניי"
    ],
    "name:hun_x_preferred": [
      "Linji"
    ],
    "name:ita_x_preferred": [
      "Linyi"
    ],
    "name:jpn_x_preferred": [
      "臨沂市"
    ],
    "name:kik_x_preferred": [
      "Linyi"
    ],
    "name:kor_x_preferred": [
      "린이시"
    ],
    "name:mlg_x_preferred": [
      "Linyi"
    ],
    "name:mon_x_preferred": [
      "Линьи"
    ],
    "name:nld_x_preferred": [
      "Linyi"
    ],
    "name:nno_x_preferred": [
      "Linyi"
    ],
    "name:nor_x_preferred": [
      "Linyi"
    ],
    "name:pol_x_preferred": [
      "Linyi"
    ],
    "name:por_x_preferred": [
      "Linyi"
    ],
    "name:rus_x_preferred": [
      "Линьи"
    ],
    "name:spa_x_preferred": [
      "Linyi"
    ],
    "name:srp_x_preferred": [
      "Линји"
    ],
    "name:swe_x_preferred": [
      "Linyi"
    ],
    "name:tgl_x_preferred": [
      "Linyi"
    ],
    "name:tur_x_preferred": [
      "Linyi"
    ],
    "name:urd_x_preferred": [
      "لنیی"
    ],
    "name:vie_x_preferred": [
      "Lâm Nghi"
    ],
    "name:war_x_preferred": [
      "Linyi"
    ],
    "name:wuu_x_preferred": [
      "临沂市"
    ],
    "name:zho_x_preferred": [
      "林益"
    ],
    "name:zho_x_variant": [
      "临沂市"
    ],
    "wof:name": "Linyi",
    "wof:placetype": "locality"
  },
  "geometry": {
    "coordinates": [
      103.674,
      24.4253
    ],
    "type": "Point"
  }
}