{
  "type": "Feature",
  "properties": {
    "gn:admin1_code": "16.0",
    "gn:asciiname": "Liugan",
    "gn:country_code": "CN",
    "gn:dem": 44,
    "gn:feature_class": "P",
    "gn:feature_code": "PPL",
    "gn:name": "Liugan",
    "gn:population": 0,
    "gn:timezone": "Asia/Shanghai",
    "iso:country": "CN",
    "name:zho_x_preferred": [
      "六甘"
    ],
    "wof:name": "Liugan",
    "wof:placetype": "locality"
  },
  "geometry": {
    "coordinates": [
      109.632,
      21.8643
    ],
    "type": "Point"
  }
}