{
  "type": "Feature",
  "properties": {
    "gn:admin1_code": "10.0",
    "gn:asciiname": "Jueluntun",
    "gn:country_code": "CN",
    "gn:dem": 963,
    "gn:feature_class": "P",
    "gn:feature_code": "PPL",
    "gn:name": "Jueluntun",
    "gn:population": 0,
    "gn:timezone": "Asia/Shanghai",
    "iso:country": "CN",
    "name:zho_x_preferred": [
      "崛仑屯"
    ],
    "wof:name": "Jueluntun",
    "wof:placetype": "locality"
  },
  "geometry": {
    "coordinates": [
      114.35518,
      40.64295
    ],
    "type": "Point"
  }
}