{
  "type": "Feature",
  "properties": {
    "gn:admin1_code": "11",
    "gn:asciiname": "Shazitian",
    "gn:country_code": "CN",
    "gn:dem": 384,
    "gn:feature_class": "P",
    "gn:feature_code": "PPL",
    "gn:name": "Shazitian",
    "gn:population": 0,
    "gn:timezone": "Asia/Shanghai",
    "iso:country": "CN",
    "name:zho_x_preferred": [
      "沙子田"
    ],
    "wof:name": "Shazitian",
    "wof:placetype": "locality"
  },
  "geometry": {
    "coordinates": [
      111.945,
      25.72444
    ],
    "type": "Point"
  }
}