{
  "type": "Feature",
  "properties": {
    "gn:admin1_code": "25",
    "gn:asciiname": "Shiquan",
    "gn:country_code": "CN",
    "gn:dem": 146,
    "gn:feature_class": "P",
    "gn:feature_code": "PPL",
    "gn:name": "Shiquan",
    "gn:population": 0,
    "gn:timezone": "Asia/Shanghai",
    "iso:country": "CN",
    "name:ara_x_preferred": [
      "شيكوان"
    ],
    "name:ben_x_preferred": [
      "শিকান"
    ],
    "name:deu_x_preferred": [
      "Sênggê Zangbo"
    ],
    "name:ell_x_preferred": [
      "Σικουάν"
    ],
    "name:fas_x_preferred": [
      "شیکوان"
    ],
    "name:fra_x_preferred": [
      "Shiquan"
    ],
    "name:heb_x_preferred": [
      "שיקאן"
    ],
    "name:hun_x_preferred": [
      "Shiquan"
    ],
    "name:ind_x_preferred": [
      "Shiquan"
    ],
    "name:ita_x_preferred": [
      "Shiquan"
    ],
    "name:kor_x_preferred": [
      "스촨"
    ],
    "name:pol_x_preferred": [
      "Shiquan"
    ],
    "name:por_x_preferred": [
      "Shiquan"
    ],
    "name:rus_x_preferred": [
      "река Шицюань"
    ],
    "name:spa_x_preferred": [
      "Shiquan"
    ],
    "name:tur_x_preferred": [
      "Shiquan"
    ],
    "name:ukr_x_preferred": [
      "Шікван"
    ],
    "name:urd_x_preferred": [
      "شیقوان"
    ],
    "name:vie_x_preferred": [
      "Sông Shiquan"
    ],
    "name:zho_x_preferred": [
      "石泉"
    ],
    "wof:name": "Shiquan",
    "wof:placetype": "locality"
  },
  "geometry": {
    "coordinates": [
      117.453,
      35.909
    ],
    "type": "Point"
  }
}