{
  "type": "Feature",
  "properties": {
    "gn:admin1_code": "30",
    "gn:asciiname": "Dashan",
    "gn:country_code": "CN",
    "gn:dem": 8,
    "gn:feature_class": "P",
    "gn:feature_code": "PPL",
    "gn:name": "Dashan",
    "gn:population": 0,
    "gn:timezone": "Asia/Urumqi",
    "iso:country": "CN",
    "name:fra_x_preferred": [
      "Dashan"
    ],
    "name:ita_x_preferred": [
      "Dashan"
    ],
    "name:jpn_x_preferred": [
      "大山"
    ],
    "name:kor_x_preferred": [
      "다산"
    ],
    "name:nor_x_preferred": [
      "Dashan"
    ],
    "name:swe_x_preferred": [
      "Dashan"
    ],
    "name:ukr_x_preferred": [
      "Дашан"
    ],
    "name:zho_x_preferred": [
      "大山"
    ],
    "wof:name": "Dashan",
    "wof:placetype": "locality"
  },
  "geometry": {
    "coordinates": [
      109.98296,
      21.4844
    ],
    "type": "Point"
  }
}