{
  "type": "Feature",
  "properties": {
    "gn:admin1_code": "7",
    "gn:asciiname": "Nanyang",
    "gn:country_code": "CN",
    "gn:dem": 390,
    "gn:feature_class": "P",
    "gn:feature_code": "PPLA4",
    "gn:name": "Nanyang",
    "gn:population": 0,
    "gn:timezone": "Asia/Shanghai",
    "iso:country": "CN",
    "name:ceb_x_preferred": [
      "Nanyang"
    ],
    "name:deu_x_preferred": [
      "Nanyang"
    ],
    "name:heb_x_preferred": [
      "נניאנג"
    ],
    "name:hun_x_preferred": [
      "Nanjang"
    ],
    "name:mlg_x_preferred": [
      "Nanyang"
    ],
    "name:nor_x_preferred": [
      "Nanyang"
    ],
    "name:swe_x_preferred": [
      "Nanyang"
    ],
    "name:und_x_variant": [
      "Hongfang",
      "南阳",
      "Hongfang Zhen",
      "红坊"
    ],
    "name:vie_x_preferred": [
      "Nam Dương"
    ],
    "name:zho_x_preferred": [
      "红坊镇"
    ],
    "wof:name": "Nanyang",
    "wof:placetype": "locality"
  },
  "geometry": {
    "coordinates": [
      116.95252,
      25.02654
    ],
    "type": "Point"
  }
}