{
  "type": "Feature",
  "properties": {
    "gn:admin1_code": "10",
    "gn:asciiname": "Xi'erdaowa",
    "gn:country_code": "CN",
    "gn:dem": 1080,
    "gn:feature_class": "P",
    "gn:feature_code": "PPL",
    "gn:name": "Xi’erdaowa",
    "gn:population": 0,
    "gn:timezone": "Asia/Shanghai",
    "iso:country": "CN",
    "name:und_x_variant": [
      "Xi’erdaowa"
    ],
    "name:zho_x_preferred": [
      "西二道洼"
    ],
    "wof:name": "Xi'erdaowa",
    "wof:placetype": "locality"
  },
  "geometry": {
    "coordinates": [
      115.55605,
      40.69721
    ],
    "type": "Point"
  }
}