{
  "type": "Feature",
  "properties": {
    "gn:admin1_code": "11.0",
    "gn:asciiname": "Xiawu Liping",
    "gn:country_code": "CN",
    "gn:dem": 632,
    "gn:feature_class": "P",
    "gn:feature_code": "PPL",
    "gn:name": "Xiawu Liping",
    "gn:population": 0,
    "gn:timezone": "Asia/Shanghai",
    "iso:country": "CN",
    "name:zho_x_preferred": [
      "下五里坪"
    ],
    "wof:name": "Xiawu Liping",
    "wof:placetype": "locality"
  },
  "geometry": {
    "coordinates": [
      110.98096,
      29.99042
    ],
    "type": "Point"
  }
}