{
  "type": "Feature",
  "properties": {
    "gn:admin1_code": "15.0",
    "gn:asciiname": "Dashitouhe",
    "gn:country_code": "CN",
    "gn:dem": 2626,
    "gn:feature_class": "P",
    "gn:feature_code": "PPL",
    "gn:name": "Dashitouhe",
    "gn:population": 0,
    "gn:timezone": "Asia/Shanghai",
    "iso:country": "CN",
    "name:und_x_variant": [
      "大石头河"
    ],
    "wof:name": "Dashitouhe",
    "wof:placetype": "locality"
  },
  "geometry": {
    "coordinates": [
      103.9525,
      35.02034
    ],
    "type": "Point"
  }
}