{
  "type": "Feature",
  "properties": {
    "gn:admin1_code": "13.0",
    "gn:asciiname": "Kalatongke",
    "gn:country_code": "CN",
    "gn:dem": 919,
    "gn:feature_class": "P",
    "gn:feature_code": "PPLA4",
    "gn:name": "Kalatongke",
    "gn:population": 0,
    "gn:timezone": "Asia/Urumqi",
    "iso:country": "CN",
    "name:und_x_variant": [
      "Ha-la-t’ung-ku",
      "Ha-la-t’ung-kou",
      "Karatünggü",
      "Kalatongke",
      "Kalatongke Xiang"
    ],
    "name:zho_x_preferred": [
      "喀拉通克"
    ],
    "name:zho_x_variant": [
      "喀拉通克乡"
    ],
    "wof:name": "Kalatongke",
    "wof:placetype": "locality"
  },
  "geometry": {
    "coordinates": [
      89.69761,
      46.85591
    ],
    "type": "Point"
  }
}