{
  "type": "Feature",
  "properties": {
    "gn:admin1_code": "4.0",
    "gn:asciiname": "Zhangjiazhuang",
    "gn:country_code": "CN",
    "gn:dem": 5,
    "gn:feature_class": "P",
    "gn:feature_code": "PPL",
    "gn:name": "Zhangjiazhuang",
    "gn:population": 0,
    "gn:timezone": "Asia/Shanghai",
    "iso:country": "CN",
    "name:zho_x_preferred": [
      "张家庄"
    ],
    "name:zho_x_variant": [
      "张家庄镇"
    ],
    "wof:name": "Zhangjiazhuang",
    "wof:placetype": "locality"
  },
  "geometry": {
    "coordinates": [
      119.6421,
      32.53751
    ],
    "type": "Point"
  }
}