{
  "type": "Feature",
  "properties": {
    "gn:admin1_code": "5.0",
    "gn:asciiname": "Dongtaipingcun",
    "gn:country_code": "CN",
    "gn:dem": 184,
    "gn:feature_class": "P",
    "gn:feature_code": "PPL",
    "gn:name": "Dongtaipingcun",
    "gn:population": 0,
    "gn:timezone": "Asia/Shanghai",
    "iso:country": "CN",
    "name:zho_x_preferred": [
      "东太平村"
    ],
    "wof:name": "Dongtaipingcun",
    "wof:placetype": "locality"
  },
  "geometry": {
    "coordinates": [
      126.02145,
      44.87376
    ],
    "type": "Point"
  }
}