{
  "type": "Feature",
  "properties": {
    "gn:admin1_code": "11",
    "gn:asciiname": "Wulipai",
    "gn:country_code": "CN",
    "gn:dem": 85,
    "gn:feature_class": "P",
    "gn:feature_code": "PPL",
    "gn:name": "Wulipai",
    "gn:population": 0,
    "gn:timezone": "Asia/Shanghai",
    "iso:country": "CN",
    "name:zho_x_preferred": [
      "五里排"
    ],
    "name:zho_x_variant": [
      "五里牌街道"
    ],
    "wof:name": "Wulipai",
    "wof:placetype": "locality"
  },
  "geometry": {
    "coordinates": [
      112.42427,
      26.863
    ],
    "type": "Point"
  }
}