{
  "type": "Feature",
  "properties": {
    "gn:admin1_code": "30",
    "gn:asciiname": "Lintou",
    "gn:country_code": "CN",
    "gn:dem": 23,
    "gn:feature_class": "P",
    "gn:feature_code": "PPLA4",
    "gn:name": "Lintou",
    "gn:population": 0,
    "gn:timezone": "Asia/Urumqi",
    "iso:country": "CN",
    "name:und_x_variant": [
      "Lin-t’ou",
      "Lin-t’ou-hsü",
      "Lintouxu",
      "Lintou",
      "Lintou Zhen",
      "林头镇"
    ],
    "name:zho_x_preferred": [
      "林头"
    ],
    "wof:name": "Lintou",
    "wof:placetype": "locality"
  },
  "geometry": {
    "coordinates": [
      111.04865,
      21.66572
    ],
    "type": "Point"
  }
}