{
  "type": "Feature",
  "properties": {
    "gn:admin1_code": "32.0",
    "gn:asciiname": "Qianjin",
    "gn:country_code": "CN",
    "gn:dem": 489,
    "gn:feature_class": "P",
    "gn:feature_code": "PPL",
    "gn:name": "Qianjin",
    "gn:population": 0,
    "gn:timezone": "Asia/Shanghai",
    "iso:country": "CN",
    "name:ceb_x_preferred": [
      "Qianjin"
    ],
    "name:deu_x_preferred": [
      "Qianjin"
    ],
    "name:eus_x_preferred": [
      "Qianjin"
    ],
    "name:kor_x_preferred": [
      "첸진구"
    ],
    "name:rus_x_preferred": [
      "Цяньцзинь"
    ],
    "name:zho_x_preferred": [
      "前进"
    ],
    "wof:name": "Qianjin",
    "wof:placetype": "locality"
  },
  "geometry": {
    "coordinates": [
      103.54046,
      30.40906
    ],
    "type": "Point"
  }
}