{
  "type": "Feature",
  "properties": {
    "gn:admin1_code": "3.0",
    "gn:asciiname": "Shaping",
    "gn:country_code": "CN",
    "gn:dem": 291,
    "gn:feature_class": "P",
    "gn:feature_code": "PPL",
    "gn:name": "Shaping",
    "gn:population": 0,
    "gn:timezone": "Asia/Shanghai",
    "iso:country": "CN",
    "name:ceb_x_preferred": [
      "Shaping"
    ],
    "name:deu_x_preferred": [
      "Shaping"
    ],
    "name:mlg_x_preferred": [
      "Shaping"
    ],
    "name:rus_x_preferred": [
      "Шейпинг"
    ],
    "name:und_x_variant": [
      "沙坪"
    ],
    "wof:name": "Shaping",
    "wof:placetype": "locality"
  },
  "geometry": {
    "coordinates": [
      115.83978,
      25.52134
    ],
    "type": "Point"
  }
}