{
  "type": "Feature",
  "properties": {
    "gn:admin1_code": "19.0",
    "gn:asciiname": "Xinglongtaicun",
    "gn:country_code": "CN",
    "gn:dem": 54,
    "gn:feature_class": "P",
    "gn:feature_code": "PPL",
    "gn:name": "Xinglongtaicun",
    "gn:population": 0,
    "gn:timezone": "Asia/Shanghai",
    "iso:country": "CN",
    "name:zho_x_preferred": [
      "兴隆台村"
    ],
    "wof:name": "Xinglongtaicun",
    "wof:placetype": "locality"
  },
  "geometry": {
    "coordinates": [
      122.155,
      41.9935
    ],
    "type": "Point"
  }
}