{
  "type": "Feature",
  "properties": {
    "gn:admin1_code": "10",
    "gn:asciiname": "Habaqi",
    "gn:country_code": "CN",
    "gn:dem": 1400,
    "gn:feature_class": "P",
    "gn:feature_code": "PPL",
    "gn:name": "Habaqi",
    "gn:population": 0,
    "gn:timezone": "Asia/Shanghai",
    "iso:country": "CN",
    "name:zho_x_preferred": [
      "哈叭气"
    ],
    "wof:name": "Habaqi",
    "wof:placetype": "locality"
  },
  "geometry": {
    "coordinates": [
      114.52947,
      41.00606
    ],
    "type": "Point"
  }
}