{
  "type": "Feature",
  "properties": {
    "gn:admin1_code": "16.0",
    "gn:asciiname": "Tongluo",
    "gn:country_code": "CN",
    "gn:dem": 290,
    "gn:feature_class": "P",
    "gn:feature_code": "PPL",
    "gn:name": "Tongluo",
    "gn:population": 0,
    "gn:timezone": "Asia/Shanghai",
    "iso:country": "CN",
    "name:fra_x_preferred": [
      "Tongluo"
    ],
    "name:hak_x_preferred": [
      "Thùng-lò-hiông"
    ],
    "name:jpn_x_preferred": [
      "銅鑼郷"
    ],
    "name:kor_x_preferred": [
      "퉁뤄향"
    ],
    "name:vie_x_preferred": [
      "Đồng La"
    ],
    "name:zho_x_preferred": [
      "铜锣"
    ],
    "name:zho_x_variant": [
      "銅鑼鄉"
    ],
    "wof:name": "Tongluo",
    "wof:placetype": "locality"
  },
  "geometry": {
    "coordinates": [
      111.243,
      24.066
    ],
    "type": "Point"
  }
}