{
  "type": "Feature",
  "properties": {
    "gn:admin1_code": "30",
    "gn:asciiname": "Mashan",
    "gn:country_code": "CN",
    "gn:dem": 25,
    "gn:feature_class": "P",
    "gn:feature_code": "PPL",
    "gn:name": "Mashan",
    "gn:population": 0,
    "gn:timezone": "Asia/Shanghai",
    "iso:country": "CN",
    "name:ceb_x_preferred": [
      "Mashan"
    ],
    "name:deu_x_preferred": [
      "Mashan"
    ],
    "name:fra_x_preferred": [
      "Mashan"
    ],
    "name:nor_x_preferred": [
      "Mashan"
    ],
    "name:rus_x_preferred": [
      "Машань"
    ],
    "name:swe_x_preferred": [
      "Mashan"
    ],
    "name:zho_x_preferred": [
      "马山"
    ],
    "wof:name": "Mashan",
    "wof:placetype": "locality"
  },
  "geometry": {
    "coordinates": [
      111.61815,
      21.87942
    ],
    "type": "Point"
  }
}