{
  "type": "Feature",
  "properties": {
    "gn:admin1_code": "07",
    "gn:asciiname": "Yangzhong",
    "gn:country_code": "CN",
    "gn:dem": 839,
    "gn:feature_class": "P",
    "gn:feature_code": "PPL",
    "gn:name": "Yangzhong",
    "gn:population": 0,
    "gn:timezone": "Asia/Shanghai",
    "iso:country": "CN",
    "name:deu_x_preferred": [
      "Yangzhong"
    ],
    "name:fas_x_preferred": [
      "یانگژانگ"
    ],
    "name:fra_x_preferred": [
      "Yangzhong"
    ],
    "name:ita_x_preferred": [
      "Yangzhong"
    ],
    "name:jpn_x_preferred": [
      "揚中市"
    ],
    "name:kik_x_preferred": [
      "Yangzhong"
    ],
    "name:kor_x_preferred": [
      "양중시"
    ],
    "name:nor_x_preferred": [
      "Yangzhong"
    ],
    "name:rus_x_preferred": [
      "Янчжун"
    ],
    "name:swe_x_preferred": [
      "Yangzhong"
    ],
    "name:tgl_x_preferred": [
      "Yangzhong"
    ],
    "name:urd_x_preferred": [
      "یانگژونگ"
    ],
    "name:vie_x_preferred": [
      "Dương Trung"
    ],
    "name:wuu_x_preferred": [
      "扬中市"
    ],
    "name:zho_x_preferred": [
      "洋中"
    ],
    "name:zho_x_variant": [
      "扬中市"
    ],
    "wof:name": "Yangzhong",
    "wof:placetype": "locality"
  },
  "geometry": {
    "coordinates": [
      117.8097,
      25.31742
    ],
    "type": "Point"
  }
}