{
  "type": "Feature",
  "properties": {
    "gn:admin1_code": "11",
    "gn:asciiname": "Songshu'ao",
    "gn:country_code": "CN",
    "gn:dem": 100,
    "gn:feature_class": "P",
    "gn:feature_code": "PPL",
    "gn:name": "Songshu’ao",
    "gn:population": 0,
    "gn:timezone": "Asia/Shanghai",
    "iso:country": "CN",
    "name:und_x_variant": [
      "Songshu’ao"
    ],
    "name:zho_x_preferred": [
      "松树坳"
    ],
    "wof:name": "Songshu'ao",
    "wof:placetype": "locality"
  },
  "geometry": {
    "coordinates": [
      112.16473,
      27.44677
    ],
    "type": "Point"
  }
}