{
  "type": "Feature",
  "properties": {
    "gn:admin1_code": "19.0",
    "gn:asciiname": "Dahenancun",
    "gn:country_code": "CN",
    "gn:dem": 77,
    "gn:feature_class": "P",
    "gn:feature_code": "PPL",
    "gn:name": "Dahenancun",
    "gn:population": 0,
    "gn:timezone": "Asia/Shanghai",
    "iso:country": "CN",
    "name:zho_x_preferred": [
      "大河南村"
    ],
    "wof:name": "Dahenancun",
    "wof:placetype": "locality"
  },
  "geometry": {
    "coordinates": [
      123.509,
      40.4176
    ],
    "type": "Point"
  }
}