{
  "type": "Feature",
  "properties": {
    "gn:admin1_code": "9.0",
    "gn:asciiname": "Qicun",
    "gn:country_code": "CN",
    "gn:dem": 159,
    "gn:feature_class": "P",
    "gn:feature_code": "PPLA4",
    "gn:name": "Qicun",
    "gn:population": 0,
    "gn:timezone": "Asia/Shanghai",
    "iso:country": "CN",
    "name:und_x_variant": [
      "齐村",
      "Qicun Xiang",
      "齐村乡"
    ],
    "wof:name": "Qicun",
    "wof:placetype": "locality"
  },
  "geometry": {
    "coordinates": [
      114.50254,
      38.69456
    ],
    "type": "Point"
  }
}