{
  "type": "Feature",
  "properties": {
    "gn:admin1_code": "7.0",
    "gn:asciiname": "Shangwa",
    "gn:country_code": "CN",
    "gn:dem": 183,
    "gn:feature_class": "P",
    "gn:feature_code": "PPL",
    "gn:name": "Shangwa",
    "gn:population": 0,
    "gn:timezone": "Asia/Shanghai",
    "iso:country": "CN",
    "name:zho_x_preferred": [
      "上瓦"
    ],
    "wof:name": "Shangwa",
    "wof:placetype": "locality"
  },
  "geometry": {
    "coordinates": [
      118.00258999999998,
      26.81014
    ],
    "type": "Point"
  }
}