{
  "type": "Feature",
  "properties": {
    "gn:admin1_code": "20.0",
    "gn:asciiname": "Xuetai'ao",
    "gn:country_code": "CN",
    "gn:dem": 1902,
    "gn:feature_class": "P",
    "gn:feature_code": "PPL",
    "gn:name": "Xuetai’ao",
    "gn:population": 0,
    "gn:timezone": "Asia/Shanghai",
    "iso:country": "CN",
    "name:und_x_variant": [
      "Xuetai’ao",
      "薛台凹"
    ],
    "wof:name": "Xuetai'ao",
    "wof:placetype": "locality"
  },
  "geometry": {
    "coordinates": [
      111.46294,
      40.94409
    ],
    "type": "Point"
  }
}