{
  "type": "Feature",
  "properties": {
    "gn:admin1_code": "32.0",
    "gn:asciiname": "Wujia",
    "gn:country_code": "CN",
    "gn:dem": 482,
    "gn:feature_class": "P",
    "gn:feature_code": "PPL",
    "gn:name": "Wujia",
    "gn:population": 0,
    "gn:timezone": "Asia/Shanghai",
    "iso:country": "CN",
    "name:ara_x_preferred": [
      "ووجيا"
    ],
    "name:ben_x_preferred": [
      "উজিয়া"
    ],
    "name:deu_x_preferred": [
      "Wujia"
    ],
    "name:ell_x_preferred": [
      "Ουιτζία"
    ],
    "name:fas_x_preferred": [
      "ووجیا"
    ],
    "name:fra_x_preferred": [
      "Wujia"
    ],
    "name:heb_x_preferred": [
      "ווג'יה"
    ],
    "name:hin_x_preferred": [
      "वुजिया"
    ],
    "name:hun_x_preferred": [
      "Wujia"
    ],
    "name:ind_x_preferred": [
      "Wujia"
    ],
    "name:ita_x_preferred": [
      "Wujia"
    ],
    "name:jpn_x_preferred": [
      "ウージャ川"
    ],
    "name:kor_x_preferred": [
      "우자"
    ],
    "name:nld_x_preferred": [
      "Wujia"
    ],
    "name:pol_x_preferred": [
      "Wujia"
    ],
    "name:por_x_preferred": [
      "Wujia"
    ],
    "name:rus_x_preferred": [
      "озеро Уцзя"
    ],
    "name:spa_x_preferred": [
      "Wujia"
    ],
    "name:swe_x_preferred": [
      "Wujia"
    ],
    "name:tur_x_preferred": [
      "Wujia"
    ],
    "name:ukr_x_preferred": [
      "Вуджа"
    ],
    "name:urd_x_preferred": [
      "ووجیا"
    ],
    "name:vie_x_preferred": [
      "Sông Ô Gia"
    ],
    "name:zho_cn_x_preferred": [
      "乌加河"
    ],
    "name:zho_tw_x_preferred": [
      "吳家河"
    ],
    "name:zho_x_preferred": [
      "吴家"
    ],
    "wof:name": "Wujia",
    "wof:placetype": "locality"
  },
  "geometry": {
    "coordinates": [
      104.788,
      31.5211
    ],
    "type": "Point"
  }
}