{
  "type": "Feature",
  "properties": {
    "gn:admin1_code": "12.0",
    "gn:asciiname": "Zhangjiagang",
    "gn:country_code": "CN",
    "gn:dem": 35,
    "gn:feature_class": "P",
    "gn:feature_code": "PPL",
    "gn:name": "Zhangjiagang",
    "gn:population": 0,
    "gn:timezone": "Asia/Shanghai",
    "iso:country": "CN",
    "name:ara_x_preferred": [
      "تشانغ جياغانغ"
    ],
    "name:ceb_x_preferred": [
      "Zhangjiagang"
    ],
    "name:deu_x_preferred": [
      "Zhangjiagang"
    ],
    "name:fas_x_preferred": [
      "ژانگژیانگانگ"
    ],
    "name:fra_x_preferred": [
      "Zhangjiagang"
    ],
    "name:ita_x_preferred": [
      "Zhangjiagang"
    ],
    "name:jpn_x_preferred": [
      "張家港市"
    ],
    "name:kik_x_preferred": [
      "Zhangjiagang"
    ],
    "name:kor_x_preferred": [
      "장자강시"
    ],
    "name:mlg_x_preferred": [
      "Zhangjiagang"
    ],
    "name:nor_x_preferred": [
      "Zhangjiagang"
    ],
    "name:rus_x_preferred": [
      "Чжанцзяган"
    ],
    "name:spa_x_preferred": [
      "Zhangjiagang"
    ],
    "name:swe_x_preferred": [
      "Zhangjiagang"
    ],
    "name:tgl_x_preferred": [
      "Zhangjiagang"
    ],
    "name:urd_x_preferred": [
      "ژانگجیاگانگ"
    ],
    "name:war_x_preferred": [
      "Zhangjiagang"
    ],
    "name:wuu_x_preferred": [
      "张家港市"
    ],
    "name:zho_x_preferred": [
      "Zhangjiagang"
    ],
    "name:zho_x_variant": [
      "张家岗",
      "张家港市"
    ],
    "wof:name": "Zhangjiagang",
    "wof:placetype": "locality"
  },
  "geometry": {
    "coordinates": [
      111.93608,
      30.01221
    ],
    "type": "Point"
  }
}