{
  "type": "Feature",
  "properties": {
    "gn:admin1_code": "26.0",
    "gn:asciiname": "Bei'aocun",
    "gn:country_code": "CN",
    "gn:dem": 809,
    "gn:feature_class": "P",
    "gn:feature_code": "PPL",
    "gn:name": "Bei’aocun",
    "gn:population": 0,
    "gn:timezone": "Asia/Shanghai",
    "iso:country": "CN",
    "name:und_x_variant": [
      "Bei’aocun"
    ],
    "name:zho_x_preferred": [
      "背凹村"
    ],
    "wof:name": "Bei'aocun",
    "wof:placetype": "locality"
  },
  "geometry": {
    "coordinates": [
      110.36498,
      35.54797999999999
    ],
    "type": "Point"
  }
}