{
  "type": "Feature",
  "properties": {
    "gn:admin1_code": "7.0",
    "gn:asciiname": "Huli",
    "gn:country_code": "CN",
    "gn:dem": 1173,
    "gn:feature_class": "P",
    "gn:feature_code": "PPL",
    "gn:name": "Huli",
    "gn:population": 0,
    "gn:timezone": "Asia/Shanghai",
    "iso:country": "CN",
    "name:ceb_x_preferred": [
      "Huli"
    ],
    "name:deu_x_preferred": [
      "Huli"
    ],
    "name:fra_x_preferred": [
      "Huli"
    ],
    "name:rus_x_preferred": [
      "Хули"
    ],
    "name:swe_x_preferred": [
      "Huli"
    ],
    "name:tur_x_preferred": [
      "Huli"
    ],
    "name:zho_x_preferred": [
      "Huli"
    ],
    "name:zho_x_variant": [
      "湖里"
    ],
    "wof:name": "Huli",
    "wof:placetype": "locality"
  },
  "geometry": {
    "coordinates": [
      119.22306,
      26.73722
    ],
    "type": "Point"
  }
}