{
  "type": "Feature",
  "properties": {
    "gn:admin1_code": "4.0",
    "gn:asciiname": "Shangyingcun",
    "gn:country_code": "CN",
    "gn:dem": 33,
    "gn:feature_class": "P",
    "gn:feature_code": "PPL",
    "gn:name": "Shangyingcun",
    "gn:population": 0,
    "gn:timezone": "Asia/Shanghai",
    "iso:country": "CN",
    "name:zho_x_preferred": [
      "尚营村"
    ],
    "wof:name": "Shangyingcun",
    "wof:placetype": "locality"
  },
  "geometry": {
    "coordinates": [
      118.39807,
      34.29907
    ],
    "type": "Point"
  }
}