{
  "type": "Feature",
  "properties": {
    "gn:admin1_code": "25.0",
    "gn:asciiname": "Dalianchi",
    "gn:country_code": "CN",
    "gn:dem": 55,
    "gn:feature_class": "P",
    "gn:feature_code": "PPL",
    "gn:name": "Dalianchi",
    "gn:population": 0,
    "gn:timezone": "Asia/Shanghai",
    "iso:country": "CN",
    "name:zho_x_preferred": [
      "大莲池"
    ],
    "wof:name": "Dalianchi",
    "wof:placetype": "locality"
  },
  "geometry": {
    "coordinates": [
      119.36406,
      36.38228
    ],
    "type": "Point"
  }
}