{
  "type": "Feature",
  "properties": {
    "gn:admin1_code": "29.0",
    "gn:asciiname": "Shandao",
    "gn:country_code": "CN",
    "gn:dem": 1785,
    "gn:feature_class": "P",
    "gn:feature_code": "PPL",
    "gn:name": "Shandao",
    "gn:population": 0,
    "gn:timezone": "Asia/Shanghai",
    "iso:country": "CN",
    "name:fra_x_preferred": [
      "Shandao"
    ],
    "name:pol_x_preferred": [
      "Shandao"
    ],
    "name:rus_x_preferred": [
      "Шаньдао"
    ],
    "name:swe_x_preferred": [
      "Shan-tao"
    ],
    "name:zho_x_preferred": [
      "善导"
    ],
    "wof:name": "Shandao",
    "wof:placetype": "locality"
  },
  "geometry": {
    "coordinates": [
      103.778,
      24.5984
    ],
    "type": "Point"
  }
}