{
  "type": "Feature",
  "properties": {
    "gn:admin1_code": "9.0",
    "gn:asciiname": "Malin",
    "gn:country_code": "CN",
    "gn:dem": 87,
    "gn:feature_class": "P",
    "gn:feature_code": "PPL",
    "gn:name": "Malin",
    "gn:population": 0,
    "gn:timezone": "Asia/Shanghai",
    "iso:country": "CN",
    "name:bel_x_preferred": [
      "Малін"
    ],
    "name:ceb_x_preferred": [
      "Malin"
    ],
    "name:ces_x_preferred": [
      "Malín"
    ],
    "name:deu_x_preferred": [
      "Malin"
    ],
    "name:fas_x_preferred": [
      "مالین"
    ],
    "name:heb_x_preferred": [
      "מאלין"
    ],
    "name:hun_x_preferred": [
      "Malin"
    ],
    "name:ita_x_preferred": [
      "Malin"
    ],
    "name:nld_x_preferred": [
      "Malin"
    ],
    "name:pol_x_preferred": [
      "Malin"
    ],
    "name:rus_x_preferred": [
      "Малин"
    ],
    "name:swe_x_preferred": [
      "Malin"
    ],
    "name:ukr_x_preferred": [
      "Малин"
    ],
    "name:zho_x_preferred": [
      "马林"
    ],
    "wof:name": "Malin",
    "wof:placetype": "locality"
  },
  "geometry": {
    "coordinates": [
      113.74811,
      34.8394
    ],
    "type": "Point"
  }
}