{
  "type": "Feature",
  "properties": {
    "gn:admin1_code": "07",
    "gn:asciiname": "Hetian",
    "gn:country_code": "CN",
    "gn:dem": 280,
    "gn:feature_class": "P",
    "gn:feature_code": "PPLA4",
    "gn:name": "Hetian",
    "gn:population": 0,
    "gn:timezone": "Asia/Shanghai",
    "iso:country": "CN",
    "name:und_x_variant": [
      "Ho-t’ien-hsün",
      "Hotein",
      "Ho-t’ien",
      "Hetian",
      "河田",
      "Hetian Zhen",
      "河田镇"
    ],
    "wof:name": "Hetian",
    "wof:placetype": "locality"
  },
  "geometry": {
    "coordinates": [
      116.41543,
      25.667
    ],
    "type": "Point"
  }
}