{
  "type": "Feature",
  "properties": {
    "gn:admin1_code": "13",
    "gn:asciiname": "Yilingertuan Erlinglian",
    "gn:country_code": "CN",
    "gn:dem": 449,
    "gn:feature_class": "P",
    "gn:feature_code": "PPL",
    "gn:name": "Yilingertuan Erlinglian",
    "gn:population": 0,
    "gn:timezone": "Asia/Urumqi",
    "iso:country": "CN",
    "name:zho_x_preferred": [
      "一零二团二零连"
    ],
    "wof:name": "Yilingertuan Erlinglian",
    "wof:placetype": "locality"
  },
  "geometry": {
    "coordinates": [
      87.75333,
      44.34226
    ],
    "type": "Point"
  }
}