{
  "type": "Feature",
  "properties": {
    "gn:admin1_code": "30.0",
    "gn:asciiname": "Ma'nan",
    "gn:country_code": "CN",
    "gn:dem": 8,
    "gn:feature_class": "P",
    "gn:feature_code": "PPL",
    "gn:name": "Ma’nan",
    "gn:population": 0,
    "gn:timezone": "Asia/Shanghai",
    "iso:country": "CN",
    "name:und_x_variant": [
      "Ma’nan"
    ],
    "name:zho_x_preferred": [
      "马南"
    ],
    "wof:name": "Ma'nan",
    "wof:placetype": "locality"
  },
  "geometry": {
    "coordinates": [
      113.24166,
      22.78481
    ],
    "type": "Point"
  }
}