{
  "type": "Feature",
  "properties": {
    "gn:admin1_code": "3.0",
    "gn:asciiname": "Dacun",
    "gn:country_code": "CN",
    "gn:dem": 145,
    "gn:feature_class": "P",
    "gn:feature_code": "PPL",
    "gn:name": "Dacun",
    "gn:population": 0,
    "gn:timezone": "Asia/Shanghai",
    "iso:country": "CN",
    "name:ceb_x_preferred": [
      "Dacun Xiang"
    ],
    "name:hak_x_preferred": [
      "Thai-tshûn-hiông"
    ],
    "name:ita_x_preferred": [
      "Dacun"
    ],
    "name:jpn_x_preferred": [
      "大村郷"
    ],
    "name:kor_x_preferred": [
      "다춘향"
    ],
    "name:pol_x_preferred": [
      "Dacun"
    ],
    "name:und_x_variant": [
      "大村"
    ],
    "name:vie_x_preferred": [
      "Đại Thôn"
    ],
    "name:zho_x_preferred": [
      "大村鄉"
    ],
    "wof:name": "Dacun",
    "wof:placetype": "locality"
  },
  "geometry": {
    "coordinates": [
      114.18917,
      27.11333
    ],
    "type": "Point"
  }
}