{
  "type": "Feature",
  "properties": {
    "gn:admin1_code": "4.0",
    "gn:asciiname": "Liujia Guanyintang",
    "gn:country_code": "CN",
    "gn:dem": 2,
    "gn:feature_class": "P",
    "gn:feature_code": "PPL",
    "gn:name": "Liujia Guanyintang",
    "gn:population": 0,
    "gn:timezone": "Asia/Shanghai",
    "iso:country": "CN",
    "name:zho_x_preferred": [
      "Liujia Guanyintang"
    ],
    "name:zho_x_variant": [
      "刘家观音堂"
    ],
    "wof:name": "Liujia Guanyintang",
    "wof:placetype": "locality"
  },
  "geometry": {
    "coordinates": [
      119.42529,
      34.07631
    ],
    "type": "Point"
  }
}