{
  "type": "Feature",
  "properties": {
    "gn:admin1_code": "33.0",
    "gn:asciiname": "Guan'erkan",
    "gn:country_code": "CN",
    "gn:dem": 201,
    "gn:feature_class": "P",
    "gn:feature_code": "PPL",
    "gn:name": "Guan’erkan",
    "gn:population": 0,
    "gn:timezone": "Asia/Shanghai",
    "iso:country": "CN",
    "name:und_x_variant": [
      "Guan’erkan"
    ],
    "name:zho_x_preferred": [
      "官耳坎"
    ],
    "wof:name": "Guan'erkan",
    "wof:placetype": "locality"
  },
  "geometry": {
    "coordinates": [
      107.61911,
      30.07707000000001
    ],
    "type": "Point"
  }
}