{
  "type": "Feature",
  "properties": {
    "gn:admin1_code": "16.0",
    "gn:asciiname": "Liangyou Xiazhai",
    "gn:country_code": "CN",
    "gn:dem": 327,
    "gn:feature_class": "P",
    "gn:feature_code": "PPL",
    "gn:name": "Liangyou Xiazhai",
    "gn:population": 0,
    "gn:timezone": "Asia/Shanghai",
    "iso:country": "CN",
    "name:zho_x_preferred": [
      "良友下寨"
    ],
    "wof:name": "Liangyou Xiazhai",
    "wof:placetype": "locality"
  },
  "geometry": {
    "coordinates": [
      109.166,
      25.5521
    ],
    "type": "Point"
  }
}