{
  "type": "Feature",
  "properties": {
    "gn:admin1_code": "1.0",
    "gn:asciiname": "Nangang",
    "gn:country_code": "CN",
    "gn:dem": 51,
    "gn:feature_class": "P",
    "gn:feature_code": "PPL",
    "gn:name": "Nangang",
    "gn:population": 0,
    "gn:timezone": "Asia/Shanghai",
    "iso:country": "CN",
    "name:ceb_x_preferred": [
      "Nangang"
    ],
    "name:deu_x_preferred": [
      "Nangang"
    ],
    "name:eus_x_preferred": [
      "Nangang"
    ],
    "name:fra_x_preferred": [
      "Nangang"
    ],
    "name:kor_x_preferred": [
      "난강구"
    ],
    "name:nor_x_preferred": [
      "Nangang"
    ],
    "name:sco_x_preferred": [
      "Nangang"
    ],
    "name:swe_x_preferred": [
      "Nangang"
    ],
    "name:zho_x_preferred": [
      "南岗"
    ],
    "wof:name": "Nangang",
    "wof:placetype": "locality"
  },
  "geometry": {
    "coordinates": [
      118.67082,
      32.64157
    ],
    "type": "Point"
  }
}