{
  "type": "Feature",
  "properties": {
    "gn:admin1_code": "15.0",
    "gn:asciiname": "Bana",
    "gn:country_code": "CN",
    "gn:dem": 2547,
    "gn:feature_class": "P",
    "gn:feature_code": "PPL",
    "gn:name": "Bana",
    "gn:population": 0,
    "gn:timezone": "Asia/Shanghai",
    "iso:country": "CN",
    "name:cat_x_preferred": [
      "Bana"
    ],
    "name:ceb_x_preferred": [
      "Bana"
    ],
    "name:deu_x_preferred": [
      "Bana"
    ],
    "name:fas_x_preferred": [
      "بانا"
    ],
    "name:fra_x_preferred": [
      "Bana"
    ],
    "name:ind_x_preferred": [
      "Bana"
    ],
    "name:ita_x_preferred": [
      "Bana"
    ],
    "name:jpn_x_preferred": [
      "バーナ"
    ],
    "name:new_x_preferred": [
      "बना"
    ],
    "name:nld_x_preferred": [
      "Bana"
    ],
    "name:oci_x_preferred": [
      "Bana"
    ],
    "name:por_x_preferred": [
      "Bana"
    ],
    "name:rus_x_preferred": [
      "Бана"
    ],
    "name:spa_x_preferred": [
      "Bana"
    ],
    "name:swe_x_preferred": [
      "Bana"
    ],
    "name:und_x_variant": [
      "拔那"
    ],
    "wof:name": "Bana",
    "wof:placetype": "locality"
  },
  "geometry": {
    "coordinates": [
      104.70393,
      34.39934
    ],
    "type": "Point"
  }
}