{
  "type": "Feature",
  "properties": {
    "gn:admin1_code": "3.0",
    "gn:asciiname": "Huoliqiao Yangjia",
    "gn:country_code": "CN",
    "gn:dem": 33,
    "gn:feature_class": "P",
    "gn:feature_code": "PPL",
    "gn:name": "Huoliqiao Yangjia",
    "gn:population": 0,
    "gn:timezone": "Asia/Shanghai",
    "iso:country": "CN",
    "name:zho_x_preferred": [
      "火里桥杨家"
    ],
    "wof:name": "Huoliqiao Yangjia",
    "wof:placetype": "locality"
  },
  "geometry": {
    "coordinates": [
      117.03152,
      28.38877
    ],
    "type": "Point"
  }
}