{
  "type": "Feature",
  "properties": {
    "gn:admin1_code": "32.0",
    "gn:asciiname": "Wayaoping",
    "gn:country_code": "CN",
    "gn:dem": 889,
    "gn:feature_class": "P",
    "gn:feature_code": "PPL",
    "gn:name": "Wayaoping",
    "gn:population": 0,
    "gn:timezone": "Asia/Shanghai",
    "iso:country": "CN",
    "name:zho_x_preferred": [
      "瓦窑坪"
    ],
    "wof:name": "Wayaoping",
    "wof:placetype": "locality"
  },
  "geometry": {
    "coordinates": [
      103.487,
      29.4685
    ],
    "type": "Point"
  }
}