{
  "type": "Feature",
  "properties": {
    "gn:admin1_code": "18",
    "gn:asciiname": "Longchang",
    "gn:cc2": "CN",
    "gn:country_code": "CN",
    "gn:dem": 1284,
    "gn:feature_class": "P",
    "gn:feature_code": "PPL",
    "gn:name": "Longchang",
    "gn:population": 0,
    "gn:timezone": "Asia/Shanghai",
    "iso:country": "CN",
    "name:ceb_x_preferred": [
      "Longchang Xian"
    ],
    "name:deu_x_preferred": [
      "Longchang"
    ],
    "name:ita_x_preferred": [
      "Longchang"
    ],
    "name:jpn_x_preferred": [
      "隆昌市"
    ],
    "name:kor_x_preferred": [
      "룽창시"
    ],
    "name:nor_x_preferred": [
      "Longchang"
    ],
    "name:rus_x_preferred": [
      "Лунчан"
    ],
    "name:swe_x_preferred": [
      "Longchang"
    ],
    "name:und_x_variant": [
      "Lung-ch’ang"
    ],
    "name:vie_x_preferred": [
      "Long Xương"
    ],
    "name:zho_x_preferred": [
      "隆昌市"
    ],
    "wof:name": "Longchang",
    "wof:placetype": "locality"
  },
  "geometry": {
    "coordinates": [
      105.51667,
      25.46667
    ],
    "type": "Point"
  }
}