{
  "type": "Feature",
  "properties": {
    "gn:admin1_code": "11.0",
    "gn:asciiname": "Liaojiaduan",
    "gn:country_code": "CN",
    "gn:dem": 175,
    "gn:feature_class": "P",
    "gn:feature_code": "PPL",
    "gn:name": "Liaojiaduan",
    "gn:population": 0,
    "gn:timezone": "Asia/Shanghai",
    "iso:country": "CN",
    "name:zho_x_preferred": [
      "Liaojiaduan"
    ],
    "name:zho_x_variant": [
      "廖家塅"
    ],
    "wof:name": "Liaojiaduan",
    "wof:placetype": "locality"
  },
  "geometry": {
    "coordinates": [
      114.06172,
      28.46768
    ],
    "type": "Point"
  }
}