{
  "type": "Feature",
  "properties": {
    "gn:admin1_code": "14.0",
    "gn:asciiname": "Gaiba",
    "gn:country_code": "CN",
    "gn:dem": 3262,
    "gn:feature_class": "P",
    "gn:feature_code": "PPL",
    "gn:name": "Gaiba",
    "gn:population": 0,
    "gn:timezone": "Asia/Urumqi",
    "iso:country": "CN",
    "name:azb_x_preferred": [
      "جایبا"
    ],
    "name:bel_x_preferred": [
      "Гайба"
    ],
    "name:bod_x_preferred": [
      "Gaiba"
    ],
    "name:bul_x_preferred": [
      "Гайба"
    ],
    "name:cat_x_preferred": [
      "Gaiba"
    ],
    "name:ceb_x_preferred": [
      "Gaiba"
    ],
    "name:deu_x_preferred": [
      "Gaiba"
    ],
    "name:eml_x_preferred": [
      "Gàiba"
    ],
    "name:epo_x_preferred": [
      "Gaiba"
    ],
    "name:eus_x_preferred": [
      "Gaiba"
    ],
    "name:fas_x_preferred": [
      "جایبا"
    ],
    "name:fra_x_preferred": [
      "Gaiba"
    ],
    "name:hun_x_preferred": [
      "Gaiba"
    ],
    "name:hye_x_preferred": [
      "Գայբա"
    ],
    "name:ita_x_preferred": [
      "Gaiba"
    ],
    "name:jpn_x_preferred": [
      "ガイバ"
    ],
    "name:kaz_x_preferred": [
      "Гайба"
    ],
    "name:kor_x_preferred": [
      "가이바"
    ],
    "name:lat_x_preferred": [
      "Gaiba"
    ],
    "name:lmo_x_preferred": [
      "Gaiba"
    ],
    "name:msa_x_preferred": [
      "Gaiba"
    ],
    "name:nap_x_preferred": [
      "Gaiba"
    ],
    "name:nld_x_preferred": [
      "Gaiba"
    ],
    "name:pms_x_preferred": [
      "Gaiba"
    ],
    "name:pol_x_preferred": [
      "Gaiba"
    ],
    "name:por_x_preferred": [
      "Gaiba"
    ],
    "name:ron_x_preferred": [
      "Gaiba"
    ],
    "name:rus_x_preferred": [
      "Гайба"
    ],
    "name:scn_x_preferred": [
      "Gaiba"
    ],
    "name:spa_x_preferred": [
      "Gaiba"
    ],
    "name:srp_x_preferred": [
      "Гаиба"
    ],
    "name:tgl_x_preferred": [
      "Gaiba"
    ],
    "name:ukr_x_preferred": [
      "Гаїба"
    ],
    "name:uzb_x_preferred": [
      "Gaiba"
    ],
    "name:vec_x_preferred": [
      "Gaiba"
    ],
    "name:vie_x_preferred": [
      "Gaiba"
    ],
    "name:vol_x_preferred": [
      "Gaiba"
    ],
    "name:war_x_preferred": [
      "Gaiba"
    ],
    "name:zho_x_preferred": [
      "Geba"
    ],
    "name:zho_x_variant": [
      "格巴",
      "加伊巴"
    ],
    "wof:name": "Gaiba",
    "wof:placetype": "locality"
  },
  "geometry": {
    "coordinates": [
      98.06257,
      28.96273
    ],
    "type": "Point"
  }
}